{
  "type": "Feature",
  "properties": {
    "gn:admin1_code":"40.0",
    "gn:asciiname":"Mazra`eh-ye `Aliabad",
    "gn:country_code":"IR",
    "gn:dem":1463,
    "gn:feature_class":"P",
    "gn:feature_code":"PPL",
    "gn:name":"Mazra\u2018eh-ye \u2018Al\u012b\u0101b\u0101d",
    "gn:population":0,
    "gn:timezone":"Asia/Tehran",
    "iso:country":"IR",
    "name:fas_x_preferred":[
        "\u2018Al\u012b\u0101b\u0101d"
    ],
    "name:fas_x_variant":[
        "\u0639\u0644\u06cc \u0622\u0628\u0627\u062f",
        "\u0645\u0632\u0631\u0639\u0647 \u0639\u0644\u06cc \u0622\u0628\u0627\u062f",
        "\u0639\u0644\u06cc \u0622\u0628\u0627\u062f \u06af\u0631\u062f\u0647 \u06a9\u0648\u0647"
    ],
    "name:und_x_variant":[
        "Mazra\u2018eh-ye \u2018Al\u012b\u0101b\u0101d",
        "\u2018Al\u012b\u0101b\u0101d Gerdeh K\u016bh"
    ],
    "wof:name":"Mazra`eh-ye `Aliabad",
    "wof:placetype":"locality"
},
  "geometry": {"coordinates":[54.88264,31.45396],"type":"Point"}
}