{
  "type": "Feature",
  "properties": {
    "gn:admin1_code":"10.0",
    "gn:asciiname":"Vargar",
    "gn:country_code":"IR",
    "gn:dem":1130,
    "gn:feature_class":"P",
    "gn:feature_code":"PPL",
    "gn:name":"Vargar",
    "gn:population":0,
    "gn:timezone":"Asia/Tehran",
    "iso:country":"IR",
    "name:fas_x_preferred":[
        "\u0648\u0631\u06af\u0631"
    ],
    "wof:name":"Vargar",
    "wof:placetype":"locality"
},
  "geometry": {"coordinates":[47.33389,32.98706],"type":"Point"}
}