{
  "type": "Feature",
  "properties": {
    "gn:admin1_code":"42",
    "gn:asciiname":"Kariz-e Sabah",
    "gn:country_code":"IR",
    "gn:dem":1189,
    "gn:feature_class":"P",
    "gn:feature_code":"PPL",
    "gn:name":"K\u0101r\u012bz-e \u015eab\u0101\u1e29",
    "gn:population":0,
    "gn:timezone":"Asia/Tehran",
    "iso:country":"IR",
    "name:fas_x_preferred":[
        "\u06a9\u0627\u0631\u06cc\u0632 \u0635\u0628\u0627\u062d"
    ],
    "name:fas_x_variant":[
        "K\u0101r\u012bz-e \u015eab\u0101\u1e29"
    ],
    "wof:name":"Kariz-e Sabah",
    "wof:placetype":"locality"
},
  "geometry": {"coordinates":[58.93356,36.07863],"type":"Point"}
}