{
  "type": "Feature",
  "properties": {
    "gn:admin1_code":"23",
    "gn:asciiname":"Barzan",
    "gn:country_code":"IR",
    "gn:dem":1519,
    "gn:feature_class":"P",
    "gn:feature_code":"PPL",
    "gn:name":"Barz\u0101n",
    "gn:population":0,
    "gn:timezone":"Asia/Tehran",
    "iso:country":"IR",
    "name:ara_x_preferred":[
        "\u0628\u0631\u0632\u0627\u0646"
    ],
    "name:fas_x_preferred":[
        "\u0628\u0631\u0632\u0627\u0646"
    ],
    "name:fas_x_variant":[
        "Barz\u0101n"
    ],
    "name:pol_x_preferred":[
        "Barzan"
    ],
    "name:und_x_variant":[
        "Berz\u0101n"
    ],
    "wof:name":"Barzan",
    "wof:placetype":"locality"
},
  "geometry": {"coordinates":[49.13503,33.49609],"type":"Point"}
}