{
  "type": "Feature",
  "properties": {
    "gn:admin1_code":"4.0",
    "gn:asciiname":"Purteh'i",
    "gn:country_code":"IR",
    "gn:dem":204,
    "gn:feature_class":"P",
    "gn:feature_code":"PPL",
    "gn:name":"P\u016brteh\u2019\u012b",
    "gn:population":0,
    "gn:timezone":"Asia/Tehran",
    "iso:country":"IR",
    "name:fas_x_preferred":[
        "\u067e\u0648\u0631\u062a\u0647 \u0627\u06cc"
    ],
    "name:und_x_variant":[
        "P\u016brteh\u2019\u012b"
    ],
    "wof:name":"Purteh'i",
    "wof:placetype":"locality"
},
  "geometry": {"coordinates":[59.06125,26.07646],"type":"Point"}
}