{
  "type": "Feature",
  "properties": {
    "gn:admin1_code":"33",
    "gn:asciiname":"Nazar Kahriz",
    "gn:country_code":"IR",
    "gn:dem":1685,
    "gn:feature_class":"P",
    "gn:feature_code":"PPL",
    "gn:name":"Naz\u0327ar Kahr\u012bz",
    "gn:population":0,
    "gn:timezone":"Asia/Tehran",
    "iso:country":"IR",
    "name:fas_x_preferred":[
        "\u0646\u0638\u0631 \u06a9\u0647\u0631\u06cc\u0632"
    ],
    "name:fas_x_variant":[
        "Nazar Kahr\u012bz\u012b",
        "Naz\u0327ar Kahr\u012bz",
        "\u0646\u0638\u0631 \u06a9\u0647\u0631\u06cc\u0632\u06cc"
    ],
    "name:und_x_variant":[
        "Naz\u0327ar Kahr\u012bz\u012b"
    ],
    "wof:name":"Nazar Kahriz",
    "wof:placetype":"locality"
},
  "geometry": {"coordinates":[46.7627,37.3467],"type":"Point"}
}