{
  "type": "Feature",
  "properties": {
    "gn:admin1_code":"3",
    "gn:asciiname":"Bar Aftab-e Milas",
    "gn:country_code":"IR",
    "gn:dem":1613,
    "gn:feature_class":"P",
    "gn:feature_code":"PPL",
    "gn:name":"Bar \u0100ft\u0101b-e M\u012bl\u0101s",
    "gn:population":0,
    "gn:timezone":"Asia/Tehran",
    "iso:country":"IR",
    "name:ceb_x_preferred":[
        "Bar \u0100ft\u0101b-e M\u012bl\u0101s"
    ],
    "name:fas_x_preferred":[
        "Bar Aft\u0101b-e M\u012bl\u0101s"
    ],
    "name:fas_x_variant":[
        "Bar \u0100ft\u0101b-e M\u012bl\u0101s",
        "\u0628\u0631 \u0622\u0641\u062a\u0627\u0628 \u0645\u064a\u0644\u0627\u0633",
        "\u0628\u0631\u0622\u0641\u062a\u0627\u0628 \u0645\u06cc\u0644\u0627\u0633"
    ],
    "name:msa_x_preferred":[
        "Bar Aftab-e Milas"
    ],
    "name:swe_x_preferred":[
        "Bar \u0100ft\u0101b-e M\u012bl\u0101s"
    ],
    "name:und_x_variant":[
        "Bar Aft\u0101b M\u012bl\u0101s"
    ],
    "wof:name":"Bar Aftab-e Milas",
    "wof:placetype":"locality"
},
  "geometry": {"coordinates":[50.78565,31.49718],"type":"Point"}
}