{
  "type": "Feature",
  "properties": {
    "gn:admin1_code":"29",
    "gn:asciiname":"Rahmatabad",
    "gn:country_code":"IR",
    "gn:dem":1372,
    "gn:feature_class":"P",
    "gn:feature_code":"PPL",
    "gn:name":"Ra\u1e29mat\u0101b\u0101d",
    "gn:population":0,
    "gn:timezone":"Asia/Tehran",
    "iso:country":"IR",
    "name:ceb_x_preferred":[
        "Rahmatabad"
    ],
    "name:fas_x_preferred":[
        "\u0631\u064e\u062d\u0645\u064e\u062a \u0622\u0628\u0627\u062f"
    ],
    "name:fas_x_variant":[
        "Ra\u1e29mat\u0101b\u0101d",
        "\u0631\u062d\u0645\u062a \u0622\u0628\u0627\u062f",
        "\u0631\u062d\u0645\u062a\u200c\u0622\u0628\u0627\u062f"
    ],
    "name:swe_x_preferred":[
        "Rahmatabad"
    ],
    "wof:name":"Rahmatabad",
    "wof:placetype":"locality"
},
  "geometry": {"coordinates":[55.94461,31.03435],"type":"Point"}
}