{
  "type": "Feature",
  "properties": {
    "gn:admin1_code":"0",
    "gn:asciiname":"Kankhak-e Janub",
    "gn:cc2":"IR",
    "gn:country_code":"IR",
    "gn:dem":308,
    "gn:feature_class":"P",
    "gn:feature_code":"PPL",
    "gn:name":"Kankhak-e Jan\u016bb",
    "gn:population":0,
    "gn:timezone":"Asia/Tehran",
    "iso:country":"IR",
    "name:fas_x_preferred":[
        "\u0643\u064e\u0646\u062e\u064e\u0643\u0650 \u062c\u064e\u0646\u0648\u0628"
    ],
    "name:fas_x_variant":[
        "\u0643\u064e\u0646\u062f\u062e\u0627\u0643",
        "Kankhak-e Jan\u016bb"
    ],
    "name:und_x_variant":[
        "Gandkh\u0101k Shim\u0101ll",
        "Kandkh\u0101k"
    ],
    "wof:name":"Kankhak-e Janub",
    "wof:placetype":"locality"
},
  "geometry": {"coordinates":[51.63333,28.26667],"type":"Point"}
}