{
  "type": "Feature",
  "properties": {
    "gn:admin1_code":"25",
    "gn:asciiname":"Bakhshabad",
    "gn:country_code":"IR",
    "gn:dem":1143,
    "gn:feature_class":"P",
    "gn:feature_code":"PPL",
    "gn:name":"Bakhsh\u0101b\u0101d",
    "gn:population":0,
    "gn:timezone":"Asia/Tehran",
    "iso:country":"IR",
    "name:fas_x_preferred":[
        "\u0628\u062e\u0634 \u0622\u0628\u0627\u062f"
    ],
    "name:fas_x_variant":[
        "\u0628\u0650\u0643\u064e\u0647\u064e\u0634 \u0622\u0628\u0627\u062f",
        "Bakhsh\u0101b\u0101d",
        "\u0628\u062e\u0634\u200c\u0622\u0628\u0627\u062f"
    ],
    "name:und_x_variant":[
        "Bekahash\u0101b\u0101d"
    ],
    "wof:name":"Bakhshabad",
    "wof:placetype":"locality"
},
  "geometry": {"coordinates":[54.1816,36.08581],"type":"Point"}
}