{
  "type": "Feature",
  "properties": {
    "gn:admin1_code":"43",
    "gn:asciiname":"Rashvanlu",
    "gn:country_code":"IR",
    "gn:dem":1168,
    "gn:feature_class":"P",
    "gn:feature_code":"PPL",
    "gn:name":"Rashv\u0101nl\u016b",
    "gn:population":0,
    "gn:timezone":"Asia/Tehran",
    "iso:country":"IR",
    "name:fas_x_preferred":[
        "Rashv\u0101nl\u016b"
    ],
    "name:fas_x_variant":[
        "\u0631\u0634\u0648\u0627\u0646\u0644\u0648"
    ],
    "wof:name":"Rashvanlu",
    "wof:placetype":"locality"
},
  "geometry": {"coordinates":[57.34526999999999,37.41969],"type":"Point"}
}