{
  "type": "Feature",
  "properties": {
    "gn:admin1_code":"32",
    "gn:asciiname":"Khorramabad",
    "gn:country_code":"IR",
    "gn:dem":1256,
    "gn:feature_class":"P",
    "gn:feature_code":"PPL",
    "gn:name":"Khorram\u0101b\u0101d",
    "gn:population":0,
    "gn:timezone":"Asia/Tehran",
    "iso:country":"IR",
    "name:fas_x_preferred":[
        "\u062e\u0631\u0645 \u0622\u0628\u0627\u062f"
    ],
    "name:fas_x_variant":[
        "Khorram\u0101b\u0101d"
    ],
    "wof:name":"Khorramabad",
    "wof:placetype":"locality"
},
  "geometry": {"coordinates":[47.6182,38.4122],"type":"Point"}
}