{
  "type": "Feature",
  "properties": {
    "gn:admin1_code":"13",
    "gn:asciiname":"Hesar",
    "gn:country_code":"IR",
    "gn:dem":1699,
    "gn:feature_class":"P",
    "gn:feature_code":"PPL",
    "gn:name":"\u1e28e\u015f\u0101r",
    "gn:population":0,
    "gn:timezone":"Asia/Tehran",
    "iso:country":"IR",
    "name:fas_x_preferred":[
        "\u062d\u0635\u0627\u0631"
    ],
    "name:fas_x_variant":[
        "\u1e28e\u015f\u0101r"
    ],
    "name:und_x_variant":[
        "\u1e28a\u015f\u0101r"
    ],
    "wof:name":"Hesar",
    "wof:placetype":"locality"
},
  "geometry": {"coordinates":[47.84296,34.61059],"type":"Point"}
}