{
  "type": "Feature",
  "properties": {
    "gn:admin1_code":"37.0",
    "gn:asciiname":"Qarah Qach",
    "gn:country_code":"IR",
    "gn:dem":382,
    "gn:feature_class":"P",
    "gn:feature_code":"PPL",
    "gn:name":"Qarah Q\u0101ch",
    "gn:population":0,
    "gn:timezone":"Asia/Tehran",
    "iso:country":"IR",
    "name:fas_x_preferred":[
        "Qarah Q\u0101ch"
    ],
    "name:fas_x_variant":[
        "Qareh Q\u0101ch",
        "\u0642\u0631\u0647 \u0642\u0627\u0686",
        "\u0642\u0631\u0647\u200c\u0642\u0627\u0686"
    ],
    "wof:name":"Qarah Qach",
    "wof:placetype":"locality"
},
  "geometry": {"coordinates":[55.57743000000001,37.72799000000001],"type":"Point"}
}