{
  "type": "Feature",
  "properties": {
    "gn:admin1_code":"4",
    "gn:asciiname":"Bon Kuh",
    "gn:country_code":"IR",
    "gn:dem":739,
    "gn:feature_class":"P",
    "gn:feature_code":"PPL",
    "gn:name":"Bon K\u016bh",
    "gn:population":0,
    "gn:timezone":"Asia/Tehran",
    "iso:country":"IR",
    "name:ceb_x_preferred":[
        "Bon Kuh"
    ],
    "name:fas_x_preferred":[
        "Beng\u016br"
    ],
    "name:fas_x_variant":[
        "\u0628\u0646 \u06a9\u0648\u0647",
        "\u0628\u0646\u06af\u0648\u0647"
    ],
    "name:swe_x_preferred":[
        "Bon Kuh"
    ],
    "name:und_x_variant":[
        "Bonk\u016br",
        "Bon K\u016bh",
        "Beng\u016bh"
    ],
    "wof:name":"Bon Kuh",
    "wof:placetype":"locality"
},
  "geometry": {"coordinates":[59.32293000000001,27.90647],"type":"Point"}
}