{
  "type": "Feature",
  "properties": {
    "gn:admin1_code":"32",
    "gn:asciiname":"Tak Bolaghi",
    "gn:country_code":"IR",
    "gn:dem":1849,
    "gn:feature_class":"P",
    "gn:feature_code":"PPL",
    "gn:name":"Tak Bol\u0101gh\u012b",
    "gn:population":0,
    "gn:timezone":"Asia/Tehran",
    "iso:country":"IR",
    "name:fas_x_preferred":[
        "\u062a\u06a9 \u0628\u0644\u0627\u063a\u06cc"
    ],
    "name:fas_x_variant":[
        "Tak Bol\u0101gh\u012b"
    ],
    "wof:name":"Tak Bolaghi",
    "wof:placetype":"locality"
},
  "geometry": {"coordinates":[48.0807,38.0263],"type":"Point"}
}