{
  "type": "Feature",
  "properties": {
    "gn:admin1_code":"10",
    "gn:asciiname":"Cham Push",
    "gn:country_code":"IR",
    "gn:dem":794,
    "gn:feature_class":"P",
    "gn:feature_code":"PPL",
    "gn:name":"Cham P\u016bsh",
    "gn:population":0,
    "gn:timezone":"Asia/Tehran",
    "iso:country":"IR",
    "name:ara_x_preferred":[
        "\u062a\u0634\u0645 \u0628\u0648\u0634"
    ],
    "name:fas_x_preferred":[
        "\u0686\u0645 \u067e\u0648\u0634"
    ],
    "name:fas_x_variant":[
        "Champ\u016bsh",
        "Cham P\u016bsh"
    ],
    "name:msa_x_preferred":[
        "Cham Push"
    ],
    "wof:name":"Cham Push",
    "wof:placetype":"locality"
},
  "geometry": {"coordinates":[46.812,33.6245],"type":"Point"}
}