{
  "type": "Feature",
  "properties": {
    "gn:admin1_code":"26.0",
    "gn:asciiname":"Mahalleh-ye Aminabad",
    "gn:country_code":"IR",
    "gn:dem":1039,
    "gn:feature_class":"P",
    "gn:feature_code":"PPL",
    "gn:name":"Ma\u1e29alleh-ye Am\u012bn\u0101b\u0101d",
    "gn:population":0,
    "gn:timezone":"Asia/Tehran",
    "iso:country":"IR",
    "name:fas_x_preferred":[
        "\u0627\u0645\u06cc\u0646 \u0622\u0628\u0627\u062f"
    ],
    "name:fas_x_variant":[
        "Am\u012bn\u0101b\u0101d",
        "Ma\u1e29alleh-ye Am\u012bn\u0101b\u0101d",
        "\u0645\u062d\u0644\u0647 \u0627\u0645\u064a\u0646 \u0622\u0628\u0627\u062f",
        "\u0627\u0645\u06cc\u0646\u200c\u0622\u0628\u0627\u062f"
    ],
    "wof:name":"Mahalleh-ye Aminabad",
    "wof:placetype":"locality"
},
  "geometry": {"coordinates":[51.48404,35.58008],"type":"Point"}
}