{
  "type": "Feature",
  "properties": {
    "gn:admin1_code":"23",
    "gn:asciiname":"Zahedshir",
    "gn:country_code":"IR",
    "gn:dem":1326,
    "gn:feature_class":"P",
    "gn:feature_code":"PPL",
    "gn:name":"Z\u0101hedsh\u012br",
    "gn:population":0,
    "gn:timezone":"Asia/Tehran",
    "iso:country":"IR",
    "name:ceb_x_preferred":[
        "Z\u0101hedsh\u012br"
    ],
    "name:fas_x_preferred":[
        "Z\u0101hedsh\u012bn"
    ],
    "name:fas_x_variant":[
        "Z\u0101hed Sh\u012br",
        "Z\u0101hedsh\u012br",
        "\u0632\u0627\u0647\u062f\u0634\u064a\u0631",
        "\u0632\u0627\u0647\u062f\u0634\u06cc\u0646",
        "\u0632\u0627\u0647\u062f\u0634\u06cc\u0631"
    ],
    "name:pol_x_preferred":[
        "Zahedszir"
    ],
    "name:swe_x_preferred":[
        "Z\u0101hedsh\u012br"
    ],
    "name:und_x_variant":[
        "Deh Z\u0101hid",
        "Deh-e Z\u0101hed"
    ],
    "name:urd_x_preferred":[
        "\u0632\u06c1\u06d2\u062f\u0634\u0631"
    ],
    "wof:name":"Zahedshir",
    "wof:placetype":"locality"
},
  "geometry": {"coordinates":[48.4508,33.4721],"type":"Point"}
}