{
  "type": "Feature",
  "properties": {
    "gn:admin1_code":"35.0",
    "gn:asciiname":"Jazireh-ye Ashuradeh",
    "gn:country_code":"IR",
    "gn:dem":-27,
    "gn:feature_class":"P",
    "gn:feature_code":"PPL",
    "gn:name":"Jaz\u012breh-ye \u0100sh\u016br\u0101deh",
    "gn:population":0,
    "gn:timezone":"Asia/Tehran",
    "iso:country":"IR",
    "name:fas_x_preferred":[
        "\u062c\u0632\u06cc\u0631\u0647 \u0622\u0634\u0648\u0631\u0627\u062f\u0647"
    ],
    "name:und_x_variant":[
        "Jaz\u012breh-ye \u0100sh\u016br\u0101deh"
    ],
    "wof:name":"Jazireh-ye Ashuradeh",
    "wof:placetype":"locality"
},
  "geometry": {"coordinates":[54.01308,36.90493],"type":"Point"}
}