{
  "type": "Feature",
  "properties": {
    "gn:admin1_code":"3.0",
    "gn:asciiname":"Khavarabad",
    "gn:country_code":"IR",
    "gn:dem":2588,
    "gn:feature_class":"P",
    "gn:feature_code":"PPL",
    "gn:name":"Kh\u0101var\u0101b\u0101d",
    "gn:population":0,
    "gn:timezone":"Asia/Tehran",
    "iso:country":"IR",
    "name:fas_x_preferred":[
        "Kh\u0101var\u0101b\u0101d"
    ],
    "name:fas_x_variant":[
        "\u062e\u0627\u0648\u0631 \u0622\u0628\u0627\u062f"
    ],
    "name:und_x_variant":[
        "\u062e\u0627\u0648\u0631 \u0622\u0628\u0627\u062f"
    ],
    "wof:name":"Khavarabad",
    "wof:placetype":"locality"
},
  "geometry": {"coordinates":[50.43092,32.36718],"type":"Point"}
}