{
  "type": "Feature",
  "properties": {
    "gn:admin1_code":"37",
    "gn:asciiname":"Tarajiq",
    "gn:country_code":"IR",
    "gn:dem":179,
    "gn:feature_class":"P",
    "gn:feature_code":"PPL",
    "gn:name":"Tar\u0101j\u012bq",
    "gn:population":0,
    "gn:timezone":"Asia/Tehran",
    "iso:country":"IR",
    "name:ceb_x_preferred":[
        "\u0162\u0101r\u0101j\u012bq"
    ],
    "name:fas_x_preferred":[
        "\u0162\u0101r\u0101j\u012bq"
    ],
    "name:fas_x_variant":[
        "Tar\u0101j\u012bq",
        "\u0637\u0627\u0631\u0627\u062c\u06cc\u0642",
        "\u062a\u0631\u0627\u062c\u064a\u0642",
        "\u062a\u0631\u0627\u062c\u06cc\u0642"
    ],
    "name:msa_x_preferred":[
        "Tarajiq"
    ],
    "name:swe_x_preferred":[
        "\u0162\u0101r\u0101j\u012bq"
    ],
    "wof:name":"Tarajiq",
    "wof:placetype":"locality"
},
  "geometry": {"coordinates":[55.48096,37.30904],"type":"Point"}
}