{
  "type": "Feature",
  "properties": {
    "gn:admin1_code":"35.0",
    "gn:asciiname":"Gangsar",
    "gn:country_code":"IR",
    "gn:dem":108,
    "gn:feature_class":"P",
    "gn:feature_code":"PPL",
    "gn:name":"G\u0101ngsar",
    "gn:population":0,
    "gn:timezone":"Asia/Tehran",
    "iso:country":"IR",
    "name:fas_x_preferred":[
        "\u06af\u0646\u06af \u0633\u0631"
    ],
    "name:fas_x_variant":[
        "\u06af\u0627\u0646\u06af\u0633\u0631"
    ],
    "name:und_x_variant":[
        "Gong Sar",
        "G\u0101ngsar"
    ],
    "wof:name":"Gangsar",
    "wof:placetype":"locality"
},
  "geometry": {"coordinates":[50.72628,36.82494000000001],"type":"Point"}
}