{
  "type": "Feature",
  "properties": {
    "gn:admin1_code":"29",
    "gn:asciiname":"Rigabad",
    "gn:country_code":"IR",
    "gn:dem":2137,
    "gn:feature_class":"P",
    "gn:feature_code":"PPL",
    "gn:name":"R\u012bg\u0101b\u0101d",
    "gn:population":0,
    "gn:timezone":"Asia/Tehran",
    "iso:country":"IR",
    "name:fas_x_preferred":[
        "R\u012bg\u0101b\u0101d"
    ],
    "name:fas_x_variant":[
        "\u0631\u06cc\u06af \u0622\u0628\u0627\u062f"
    ],
    "wof:name":"Rigabad",
    "wof:placetype":"locality"
},
  "geometry": {"coordinates":[56.94665,30.81876],"type":"Point"}
}