{
  "type": "Feature",
  "properties": {
    "gn:admin1_code":"33",
    "gn:asciiname":"Tazeh Kand-e Tahmaseb",
    "gn:country_code":"IR",
    "gn:dem":1672,
    "gn:feature_class":"P",
    "gn:feature_code":"PPL",
    "gn:name":"T\u0101zeh Kand-e \u0162ahm\u0101seb",
    "gn:population":0,
    "gn:timezone":"Asia/Tehran",
    "iso:country":"IR",
    "name:fas_x_preferred":[
        "T\u0101zeh Kand-e \u0162ahm\u0101seb"
    ],
    "wof:name":"Tazeh Kand-e Tahmaseb",
    "wof:placetype":"locality"
},
  "geometry": {"coordinates":[47.15,38.78333],"type":"Point"}
}