{
  "type": "Feature",
  "properties": {
    "gn:admin1_code":"15",
    "gn:asciiname":"Yekaviyeh-ye Seh",
    "gn:country_code":"IR",
    "gn:dem":27,
    "gn:feature_class":"P",
    "gn:feature_code":"PPL",
    "gn:name":"Yek\u0101v\u012byeh-ye Seh",
    "gn:population":0,
    "gn:timezone":"Asia/Tehran",
    "iso:country":"IR",
    "name:fas_x_preferred":[
        "\u06cc\u06a9\u0627\u0648\u06cc\u0647 \u0633\u0647"
    ],
    "name:fas_x_variant":[
        "Yek\u0101v\u012byeh-ye Seh"
    ],
    "name:und_x_variant":[
        "Lek\u0101v\u012bgeh-e Seh",
        "Lek\u0101v\u012bgeh-ye Seh"
    ],
    "wof:name":"Yekaviyeh-ye Seh",
    "wof:placetype":"locality"
},
  "geometry": {"coordinates":[48.81718,31.59193],"type":"Point"}
}