{
  "type": "Feature",
  "properties": {
    "gn:admin1_code":"43.0",
    "gn:asciiname":"Tappeh Sorkh",
    "gn:country_code":"IR",
    "gn:dem":1005,
    "gn:feature_class":"P",
    "gn:feature_code":"PPLL",
    "gn:name":"Tappeh Sorkh",
    "gn:population":0,
    "gn:timezone":"Asia/Tehran",
    "iso:country":"IR",
    "name:fas_x_preferred":[
        "\u062a\u067e\u0647 \u0633\u0631\u062e"
    ],
    "wof:name":"Tappeh Sorkh",
    "wof:placetype":"locality"
},
  "geometry": {"coordinates":[57.14999,36.92781],"type":"Point"}
}