{
  "type": "Feature",
  "properties": {
    "gn:admin1_code":"41",
    "gn:asciiname":"Cheshmeh Musa",
    "gn:country_code":"IR",
    "gn:dem":1510,
    "gn:feature_class":"P",
    "gn:feature_code":"PPL",
    "gn:name":"Cheshmeh M\u016bs\u00e1",
    "gn:population":0,
    "gn:timezone":"Asia/Tehran",
    "iso:country":"IR",
    "name:fas_x_preferred":[
        "Cheshmeh M\u016bs\u00e1"
    ],
    "name:fas_x_variant":[
        "\u0686\u0634\u0645\u0647 \u0645\u0648\u0633\u06cc"
    ],
    "name:und_x_variant":[
        "Chashmeh-i-M\u016bsa",
        "Chashmeh-ye M\u016bs\u00e1"
    ],
    "wof:name":"Cheshmeh Musa",
    "wof:placetype":"locality"
},
  "geometry": {"coordinates":[58.4935,33.10968],"type":"Point"}
}