{
  "type": "Feature",
  "properties": {
    "gn:admin1_code":"4.0",
    "gn:asciiname":"Akhundzadeh",
    "gn:country_code":"IR",
    "gn:dem":485,
    "gn:feature_class":"P",
    "gn:feature_code":"PPL",
    "gn:name":"\u0100kh\u016bndz\u0101deh",
    "gn:population":0,
    "gn:timezone":"Asia/Tehran",
    "iso:country":"IR",
    "name:fas_x_preferred":[
        "\u0622\u062e\u0648\u0646\u062f\u0632\u0627\u062f\u0647"
    ],
    "name:fas_x_variant":[
        "\u0100kh\u016bndz\u0101deh"
    ],
    "wof:name":"Akhundzadeh",
    "wof:placetype":"locality"
},
  "geometry": {"coordinates":[61.719,31.071],"type":"Point"}
}