{
  "type": "Feature",
  "properties": {
    "gn:admin1_code":"8",
    "gn:asciiname":"Mazandaran Mahalleh",
    "gn:country_code":"IR",
    "gn:dem":-3,
    "gn:feature_class":"P",
    "gn:feature_code":"PPL",
    "gn:name":"M\u0101zandar\u0101n Ma\u1e29alleh",
    "gn:population":0,
    "gn:timezone":"Asia/Tehran",
    "iso:country":"IR",
    "name:fas_x_preferred":[
        "M\u0101zandar\u0101n Ma\u1e29alleh"
    ],
    "name:fas_x_variant":[
        "\u0645\u0627\u0632\u0646\u062f\u0631\u0627\u0646 \u0645\u062d\u0644\u0647",
        "\u0645\u0627\u0632\u0646\u062f\u0631\u0627\u0646\u200c\u0645\u062d\u0644\u0647"
    ],
    "name:msa_x_preferred":[
        "Mazandaran Mahalleh"
    ],
    "name:ukr_x_preferred":[
        "\u041c\u0430\u0437\u0430\u043d\u0434\u0435\u0440\u0430\u043d-\u041c\u0430\u0445\u0430\u043b\u0435"
    ],
    "wof:name":"Mazandaran Mahalleh",
    "wof:placetype":"locality"
},
  "geometry": {"coordinates":[50.25802,37.13832],"type":"Point"}
}