{
  "type": "Feature",
  "properties": {
    "gn:admin1_code":"33.0",
    "gn:asciiname":"Dizaj-e Aqa Hoseyn",
    "gn:country_code":"IR",
    "gn:dem":1341,
    "gn:feature_class":"P",
    "gn:feature_code":"PPL",
    "gn:name":"D\u012bzaj-e \u0100q\u0101 \u1e28oseyn",
    "gn:population":0,
    "gn:timezone":"Asia/Tehran",
    "iso:country":"IR",
    "name:fas_x_preferred":[
        "\u062f\u06cc\u0632\u062c \u0622\u0642\u0627 \u062d\u0633\u06cc\u0646"
    ],
    "name:fas_x_variant":[
        "D\u012bzaj-e \u0100q\u0101 \u1e28oseyn"
    ],
    "name:und_x_variant":[
        "D\u012bzaj-e \u0100q\u0101 \u1e28oseyn"
    ],
    "wof:name":"Dizaj-e Aqa Hoseyn",
    "wof:placetype":"locality"
},
  "geometry": {"coordinates":[45.9517,37.7715],"type":"Point"}
}