{
  "type": "Feature",
  "properties": {
    "gn:admin1_code":"25",
    "gn:asciiname":"Zarrin",
    "gn:cc2":"IR",
    "gn:country_code":"IR",
    "gn:dem":1392,
    "gn:feature_class":"P",
    "gn:feature_code":"PPL",
    "gn:name":"Zarr\u012bn",
    "gn:population":0,
    "gn:timezone":"Asia/Tehran",
    "iso:country":"IR",
    "name:fas_x_preferred":[
        "Zarr\u012bn"
    ],
    "name:und_x_variant":[
        "Zar\u012bn"
    ],
    "wof:name":"Zarrin",
    "wof:placetype":"locality"
},
  "geometry": {"coordinates":[54.15,35.76667],"type":"Point"}
}