{
  "type": "Feature",
  "properties": {
    "gn:admin1_code":"34",
    "gn:asciiname":"Yevlaq",
    "gn:country_code":"IR",
    "gn:dem":1710,
    "gn:feature_class":"P",
    "gn:feature_code":"PPL",
    "gn:name":"Yevl\u0101q",
    "gn:population":0,
    "gn:timezone":"Asia/Tehran",
    "iso:country":"IR",
    "name:fas_x_preferred":[
        "\u064a\u0648\u0644\u0627\u0642"
    ],
    "name:fas_x_variant":[
        "Yevl\u0101q",
        "\u06cc\u0648\u0644\u0627\u0642"
    ],
    "name:ukr_x_preferred":[
        "\u0404\u0432\u043b\u0430\u043a"
    ],
    "name:urd_x_preferred":[
        "\u06cc\u0648\u0644\u0642"
    ],
    "wof:name":"Yevlaq",
    "wof:placetype":"locality"
},
  "geometry": {"coordinates":[50.2191,35.1337],"type":"Point"}
}