{
  "type": "Feature",
  "properties": {
    "gn:admin1_code":"15",
    "gn:asciiname":"Muran",
    "gn:country_code":"IR",
    "gn:dem":14,
    "gn:feature_class":"P",
    "gn:feature_code":"PPL",
    "gn:name":"M\u016br\u0101n",
    "gn:population":0,
    "gn:timezone":"Asia/Tehran",
    "iso:country":"IR",
    "name:ceb_x_preferred":[
        "Muran"
    ],
    "name:fas_x_preferred":[
        "M\u016br\u0101n"
    ],
    "name:fas_x_variant":[
        "\u0645\u0648\u0631\u0627\u0646"
    ],
    "name:swe_x_preferred":[
        "Muran"
    ],
    "name:und_x_variant":[
        "M\u016bz\u0101n",
        "\u0645\u0648\u0631\u0627\u0646"
    ],
    "wof:name":"Muran",
    "wof:placetype":"locality"
},
  "geometry": {"coordinates":[48.51527,31.1664],"type":"Point"}
}