{
  "type": "Feature",
  "properties": {
    "gn:admin1_code":"33",
    "gn:asciiname":"Nasir Kandi",
    "gn:country_code":"IR",
    "gn:dem":2208,
    "gn:feature_class":"P",
    "gn:feature_code":"PPL",
    "gn:name":"Na\u015f\u012br Kand\u012b",
    "gn:population":0,
    "gn:timezone":"Asia/Tehran",
    "iso:country":"IR",
    "name:fas_x_preferred":[
        "Na\u015f\u012br\u0101b\u0101d"
    ],
    "name:fas_x_variant":[
        "Na\u015f\u012br Kand\u012b",
        "\u0646\u0635\u06cc\u0631 \u06a9\u0646\u062f\u06cc",
        "\u0646\u0635\u06cc\u0631 \u0622\u0628\u0627\u062f"
    ],
    "name:und_x_variant":[
        "\u0646\u0635\u06cc\u0631 \u06a9\u0646\u062f\u06cc"
    ],
    "wof:name":"Nasir Kandi",
    "wof:placetype":"locality"
},
  "geometry": {"coordinates":[46.7918,37.0933],"type":"Point"}
}