{
  "type": "Feature",
  "properties": {
    "gn:admin1_code":"15",
    "gn:asciiname":"Omm ot Tuleh",
    "gn:country_code":"IR",
    "gn:dem":11,
    "gn:feature_class":"P",
    "gn:feature_code":"PPL",
    "gn:name":"Omm o\u0163 \u0162\u016bleh",
    "gn:population":0,
    "gn:timezone":"Asia/Tehran",
    "iso:country":"IR",
    "name:fas_x_preferred":[
        "\u0627\u0645 \u0627\u0644\u0637\u0648\u0644\u0647"
    ],
    "name:fas_x_variant":[
        "Omm ot T\u016bley",
        "Omm o\u0163 \u0162\u016bleh"
    ],
    "name:und_x_variant":[
        "Om\u012bd Dowleh"
    ],
    "wof:name":"Omm ot Tuleh",
    "wof:placetype":"locality"
},
  "geometry": {"coordinates":[49.41591,30.63847],"type":"Point"}
}