{
  "type": "Feature",
  "properties": {
    "gn:admin1_code":"29.0",
    "gn:asciiname":"Anarestan",
    "gn:country_code":"IR",
    "gn:dem":1996,
    "gn:feature_class":"P",
    "gn:feature_code":"PPL",
    "gn:name":"An\u0101rest\u0101n",
    "gn:population":0,
    "gn:timezone":"Asia/Tehran",
    "iso:country":"IR",
    "name:fas_x_preferred":[
        "\u0627\u0646\u0627\u0631\u0633\u062a\u0627\u0646"
    ],
    "name:fas_x_variant":[
        "An\u0101rest\u0101n",
        "Darb An\u0101rest\u0101n",
        "An\u0101rist\u0101n"
    ],
    "wof:name":"Anarestan",
    "wof:placetype":"locality"
},
  "geometry": {"coordinates":[57.27654,30.50615],"type":"Point"}
}