{
  "type": "Feature",
  "properties": {
    "gn:admin1_code":"28.0",
    "gn:asciiname":"Mahalleh-ye Chehel Dastgah",
    "gn:country_code":"IR",
    "gn:dem":1673,
    "gn:feature_class":"P",
    "gn:feature_code":"PPL",
    "gn:name":"Ma\u1e29alleh-ye Chehel Dastg\u0101h",
    "gn:population":0,
    "gn:timezone":"Asia/Tehran",
    "iso:country":"IR",
    "name:fas_x_preferred":[
        "\u0645\u062d\u0644\u0647 \u0686\u0647\u0644 \u062f\u0633\u062a\u06af\u0627\u0647"
    ],
    "name:und_x_variant":[
        "Ma\u1e29alleh-ye Chehel Dastg\u0101h"
    ],
    "wof:name":"Mahalleh-ye Chehel Dastgah",
    "wof:placetype":"locality"
},
  "geometry": {"coordinates":[51.91296,33.50312],"type":"Point"}
}