{
  "type": "Feature",
  "properties": {
    "gn:admin1_code":"4",
    "gn:asciiname":"Lashgariabad",
    "gn:country_code":"IR",
    "gn:dem":753,
    "gn:feature_class":"P",
    "gn:feature_code":"PPL",
    "gn:name":"Lashgar\u012b\u0101b\u0101d",
    "gn:population":0,
    "gn:timezone":"Asia/Tehran",
    "iso:country":"IR",
    "name:fas_x_preferred":[
        "Lashgar\u012b\u0101b\u0101d"
    ],
    "wof:name":"Lashgariabad",
    "wof:placetype":"locality"
},
  "geometry": {"coordinates":[59.86666999999999,28.61667000000001],"type":"Point"}
}