{
  "type": "Feature",
  "properties": {
    "gn:admin1_code":"0",
    "gn:asciiname":"Patak-e Shokuh",
    "gn:country_code":"IR",
    "gn:dem":480,
    "gn:feature_class":"P",
    "gn:feature_code":"PPL",
    "gn:name":"P\u0101tak-e Shok\u016bh",
    "gn:population":0,
    "gn:timezone":"Asia/Tehran",
    "iso:country":"IR",
    "name:fas_x_preferred":[
        "\u067e\u0627\u062a\u06a9 \u0634\u06a9\u0648\u0647"
    ],
    "name:fas_x_variant":[
        "P\u0101tak-e Shok\u016bh"
    ],
    "wof:name":"Patak-e Shokuh",
    "wof:placetype":"locality"
},
  "geometry": {"coordinates":[57.482,27.5593],"type":"Point"}
}