{
  "type": "Feature",
  "properties": {
    "gn:admin1_code":"22",
    "gn:asciiname":"Mangeli",
    "gn:country_code":"IR",
    "gn:dem":38,
    "gn:feature_class":"P",
    "gn:feature_code":"PPL",
    "gn:name":"Mangel\u012b",
    "gn:population":0,
    "gn:timezone":"Asia/Tehran",
    "iso:country":"IR",
    "name:fas_x_preferred":[
        "\u0645\u0646\u06af\u0644\u06cc"
    ],
    "name:fas_x_variant":[
        "Mangel\u012b"
    ],
    "wof:name":"Mangeli",
    "wof:placetype":"locality"
},
  "geometry": {"coordinates":[51.1666,28.8856],"type":"Point"}
}