{
  "type": "Feature",
  "properties": {
    "gn:admin1_code":"23",
    "gn:asciiname":"Sarab-e Hashem-e Yek",
    "gn:country_code":"IR",
    "gn:dem":1309,
    "gn:feature_class":"P",
    "gn:feature_code":"PPL",
    "gn:name":"Sar\u0101b-e H\u0101shem-e Yek",
    "gn:population":0,
    "gn:timezone":"Asia/Tehran",
    "iso:country":"IR",
    "name:fas_x_preferred":[
        "\u0647\u0627\u0634\u0645 \u0628\u06af"
    ],
    "name:fas_x_variant":[
        "H\u0101shem Bak",
        "H\u0101shem Beg",
        "\u0633\u0631\u0627\u0628 \u0647\u0627\u0634\u0645 \u06cc\u06a9",
        "\u06a9\u0645\u0631\u0647 \u0647\u0627\u0634\u0645 \u0628\u06af"
    ],
    "name:und_x_variant":[
        "Hashem Beyg\u012b",
        "Sar\u0101b-e H\u0101shem-e Yek",
        "Kamareh H\u0101shem Beg"
    ],
    "wof:name":"Sarab-e Hashem-e Yek",
    "wof:placetype":"locality"
},
  "geometry": {"coordinates":[47.48533,33.43553],"type":"Point"}
}