{
  "type": "Feature",
  "properties": {
    "gn:admin1_code":"1.0",
    "gn:asciiname":"Uch Tappeh",
    "gn:country_code":"IR",
    "gn:dem":1331,
    "gn:feature_class":"P",
    "gn:feature_code":"PPL",
    "gn:name":"\u016ach Tappeh",
    "gn:population":0,
    "gn:timezone":"Asia/Tehran",
    "iso:country":"IR",
    "name:fas_x_preferred":[
        "\u0648\u0686 \u062a\u064e\u067e\u0650\u0651\u0647"
    ],
    "name:fas_x_variant":[
        "\u0627\u0648\u0686 \u062a\u067e\u0651\u0647",
        "\u016ach Tappeh"
    ],
    "wof:name":"Uch Tappeh",
    "wof:placetype":"locality"
},
  "geometry": {"coordinates":[46.2129,36.6008],"type":"Point"}
}