{
  "type": "Feature",
  "properties": {
    "gn:admin1_code":"25.0",
    "gn:asciiname":"Ahmadabad",
    "gn:country_code":"IR",
    "gn:dem":1377,
    "gn:feature_class":"P",
    "gn:feature_code":"PPL",
    "gn:name":"A\u1e29mad\u0101b\u0101d",
    "gn:population":0,
    "gn:timezone":"Asia/Tehran",
    "iso:country":"IR",
    "name:fas_x_preferred":[
        "\u0627\u062d\u0645\u062f \u0622\u0628\u0627\u062f \u062e\u0627\u0643 \u062a\u067e\u0647"
    ],
    "name:fas_x_variant":[
        "\u0627\u064e\u062d\u0645\u064e\u062f\u0627\u0628\u0627\u062f\u0650 \u06af\u064f\u0644 \u062a\u064e\u067e\u0650\u0651\u0647",
        "\u0627\u064e\u0647\u0645\u064e\u062f \u0622\u0628\u0627\u062f",
        "A\u1e29mad\u0101b\u0101d-e Kh\u0101k Tappeh",
        "\u0627\u062d\u0645\u062f \u0622\u0628\u0627\u062f"
    ],
    "name:und_x_variant":[
        "A\u1e29mad\u0101b\u0101d-e Gol Tappeh",
        "Ahmad \u0100b\u0101d",
        "A\u1e29mad\u0101b\u0101d"
    ],
    "wof:name":"Ahmadabad",
    "wof:placetype":"locality"
},
  "geometry": {"coordinates":[52.1635,35.44002000000001],"type":"Point"}
}