{
  "type": "Feature",
  "properties": {
    "gn:admin1_code":"29",
    "gn:asciiname":"Deykhu'iyeh-ye Pa'in",
    "gn:country_code":"IR",
    "gn:dem":1821,
    "gn:feature_class":"P",
    "gn:feature_code":"PPL",
    "gn:name":"Deykh\u016b\u2019\u012byeh-ye P\u0101\u2019\u012bn",
    "gn:population":0,
    "gn:timezone":"Asia/Tehran",
    "iso:country":"IR",
    "name:fas_x_preferred":[
        "\u062f\u06cc\u062e\u0648\u0626\u06cc\u0647"
    ],
    "name:fas_x_variant":[
        "\u062f\u06cc\u062e\u0648\u0626\u06cc\u0647 \u067e\u0627\u06cc\u06cc\u0646"
    ],
    "name:und_x_variant":[
        "Deykh\u016b\u2019\u012byeh",
        "Deykh\u016b\u2019\u012byeh-ye P\u0101\u2019\u012bn"
    ],
    "wof:name":"Deykhu'iyeh-ye Pa'in",
    "wof:placetype":"locality"
},
  "geometry": {"coordinates":[56.2451,28.8131],"type":"Point"}
}