{
  "type": "Feature",
  "properties": {
    "gn:admin1_code":"29",
    "gn:asciiname":"Dahaneh-ye Zardar",
    "gn:cc2":"IR",
    "gn:country_code":"IR",
    "gn:dem":2862,
    "gn:feature_class":"P",
    "gn:feature_code":"PPL",
    "gn:name":"Dahaneh-ye Z\u0101rd\u0101r",
    "gn:population":0,
    "gn:timezone":"Asia/Tehran",
    "iso:country":"IR",
    "name:fas_x_preferred":[
        "Dahaneh-ye Z\u0101rd\u0101r"
    ],
    "name:und_x_variant":[
        "Dahaneh-ye Zahrd\u0101r"
    ],
    "wof:name":"Dahaneh-ye Zardar",
    "wof:placetype":"locality"
},
  "geometry": {"coordinates":[56.71083,29.48083],"type":"Point"}
}