{
  "type": "Feature",
  "properties": {
    "gn:admin1_code":"22.0",
    "gn:asciiname":"Kamali",
    "gn:country_code":"IR",
    "gn:dem":6,
    "gn:feature_class":"P",
    "gn:feature_code":"PPL",
    "gn:name":"Kam\u0101l\u012b",
    "gn:population":0,
    "gn:timezone":"Asia/Tehran",
    "iso:country":"IR",
    "name:ceb_x_preferred":[
        "Kamali"
    ],
    "name:deu_x_preferred":[
        "Kamali"
    ],
    "name:fas_x_preferred":[
        "\u06a9\u0645\u0627\u0644\u06cc"
    ],
    "name:fas_x_variant":[
        "Kam\u0101l\u012b"
    ],
    "wof:name":"Kamali",
    "wof:placetype":"locality"
},
  "geometry": {"coordinates":[50.5246,29.5934],"type":"Point"}
}