{
  "type": "Feature",
  "properties": {
    "gn:admin1_code":"32",
    "gn:asciiname":"Kordlu",
    "gn:country_code":"IR",
    "gn:dem":1503,
    "gn:feature_class":"P",
    "gn:feature_code":"PPL",
    "gn:name":"Kordl\u016b",
    "gn:population":0,
    "gn:timezone":"Asia/Tehran",
    "iso:country":"IR",
    "name:fas_x_preferred":[
        "\u06a9\u0631\u062f\u0644\u0648"
    ],
    "name:fas_x_variant":[
        "Kordl\u016b"
    ],
    "wof:name":"Kordlu",
    "wof:placetype":"locality"
},
  "geometry": {"coordinates":[48.5579,38.1733],"type":"Point"}
}