{
  "type": "Feature",
  "properties": {
    "gn:admin1_code":"43",
    "gn:asciiname":"Shahrak-e Mamalkheh",
    "gn:country_code":"IR",
    "gn:dem":1226,
    "gn:feature_class":"P",
    "gn:feature_code":"PPL",
    "gn:name":"Shahrak-e Mamalkheh",
    "gn:population":0,
    "gn:timezone":"Asia/Tehran",
    "iso:country":"IR",
    "name:fas_x_preferred":[
        "\u0634\u0647\u0631\u06a9 \u0645\u0645\u0644\u062e\u0647"
    ],
    "name:und_x_variant":[
        "\u0634\u0647\u0631\u06a9 \u0645\u0645\u0644\u062e\u0647"
    ],
    "wof:name":"Shahrak-e Mamalkheh",
    "wof:placetype":"locality"
},
  "geometry": {"coordinates":[57.17252,37.5023],"type":"Point"}
}