{
  "type": "Feature",
  "properties": {
    "gn:admin1_code":"38",
    "gn:asciiname":"Molla `Ali",
    "gn:country_code":"IR",
    "gn:dem":650,
    "gn:feature_class":"P",
    "gn:feature_code":"PPL",
    "gn:name":"Moll\u0101 \u2018Al\u012b",
    "gn:population":0,
    "gn:timezone":"Asia/Tehran",
    "iso:country":"IR",
    "name:fas_x_preferred":[
        "\u0645\u0644\u0627 \u0639\u0644\u06cc"
    ],
    "name:fas_x_variant":[
        "Moll\u0101 \u2018Al\u012b",
        "\u0645\u0644\u0627\u0639\u0644\u06cc"
    ],
    "name:und_x_variant":[
        "Mulla-Ali"
    ],
    "wof:name":"Molla `Ali",
    "wof:placetype":"locality"
},
  "geometry": {"coordinates":[49.5164,36.51089],"type":"Point"}
}