{
  "type": "Feature",
  "properties": {
    "gn:admin1_code":"25",
    "gn:asciiname":"`Abdia",
    "gn:country_code":"IR",
    "gn:dem":1070,
    "gn:feature_class":"P",
    "gn:feature_code":"PPLF",
    "gn:name":"\u2018Abd\u012b\u0101",
    "gn:population":0,
    "gn:timezone":"Asia/Tehran",
    "iso:country":"IR",
    "name:fas_x_preferred":[
        "\u0639\u0628\u062f\u064a\u0627"
    ],
    "name:fas_x_variant":[
        "\u2018Abd\u012b\u0101"
    ],
    "wof:name":"`Abdia",
    "wof:placetype":"locality"
},
  "geometry": {"coordinates":[54.3873,36.06495],"type":"Point"}
}