{
  "type": "Feature",
  "properties": {
    "gn:admin1_code":"0",
    "gn:asciiname":"Do Dahaneh'i",
    "gn:country_code":"IR",
    "gn:dem":495,
    "gn:feature_class":"P",
    "gn:feature_code":"PPL",
    "gn:name":"Do Dahaneh\u2019\u012b",
    "gn:population":0,
    "gn:timezone":"Asia/Tehran",
    "iso:country":"IR",
    "name:fas_x_preferred":[
        "\u062f\u0648\u062f\u0647\u0646\u0647 \u0627\u06cc"
    ],
    "name:fas_x_variant":[
        "Do Dahaneh\u2019\u012b"
    ],
    "wof:name":"Do Dahaneh'i",
    "wof:placetype":"locality"
},
  "geometry": {"coordinates":[57.4119,27.7134],"type":"Point"}
}