{
  "type": "Feature",
  "properties": {
    "gn:admin1_code":"1",
    "gn:asciiname":"Hesar-e Aq Bolagh",
    "gn:country_code":"IR",
    "gn:dem":1672,
    "gn:feature_class":"P",
    "gn:feature_code":"PPL",
    "gn:name":"\u1e28e\u015f\u0101r-e \u0100q Bol\u0101gh",
    "gn:population":0,
    "gn:timezone":"Asia/Tehran",
    "iso:country":"IR",
    "name:fas_x_preferred":[
        "\u062d\u0650\u0635\u0627\u0631\u0650 \u0622\u0642\u0628\u064f\u0644\u0627\u063a"
    ],
    "name:fas_x_variant":[
        "\u062d\u0635\u0627\u0631 \u0622\u0642 \u0628\u0644\u0627\u063a",
        "\u1e28e\u015f\u0101r-e \u0100qbol\u0101gh",
        "\u1e28e\u015f\u0101r-e \u0100q Bol\u0101gh"
    ],
    "wof:name":"Hesar-e Aq Bolagh",
    "wof:placetype":"locality"
},
  "geometry": {"coordinates":[45.0592,37.3597],"type":"Point"}
}