{
  "type": "Feature",
  "properties": {
    "gn:admin1_code":"40",
    "gn:asciiname":"Talaqabad",
    "gn:cc2":"IR",
    "gn:country_code":"IR",
    "gn:dem":1859,
    "gn:feature_class":"P",
    "gn:feature_code":"PPL",
    "gn:name":"\u0162al\u0101q\u0101b\u0101d",
    "gn:population":0,
    "gn:timezone":"Asia/Tehran",
    "iso:country":"IR",
    "name:fas_x_preferred":[
        "\u0637\u064e\u0644\u0627\u0642 \u0622\u0628\u0627\u062f"
    ],
    "name:fas_x_variant":[
        "\u062a\u064e\u0644\u0627\u06af \u0622\u0628\u0627\u062f",
        "\u0162al\u0101q\u0101b\u0101d"
    ],
    "name:und_x_variant":[
        "Tal\u0101g\u0101b\u0101d"
    ],
    "wof:name":"Talaqabad",
    "wof:placetype":"locality"
},
  "geometry": {"coordinates":[53.49166999999999,32.28306],"type":"Point"}
}