{
  "type": "Feature",
  "properties": {
    "gn:admin1_code":"15",
    "gn:asciiname":"Sheykh Mohammad",
    "gn:country_code":"IR",
    "gn:dem":13,
    "gn:feature_class":"P",
    "gn:feature_code":"PPL",
    "gn:name":"Sheykh Mo\u1e29ammad",
    "gn:population":0,
    "gn:timezone":"Asia/Tehran",
    "iso:country":"IR",
    "name:fas_x_preferred":[
        "\u0634\u06cc\u062e \u0645\u062d\u0645\u0651\u062f \u062f\u0648"
    ],
    "name:fas_x_variant":[
        "\u015eovayyed",
        "Sheykh Mo\u1e29ammad-e Do",
        "\u0634\u06cc\u062e \u0645\u062d\u0645\u062f",
        "\u0633\u0639\u062f\u0648\u0646 \u0634\u06cc\u062e \u0645\u062d\u0645\u062f"
    ],
    "name:und_x_variant":[
        "Shaikh Mohammad\u00e9 Dow\u00e9 Hachem",
        "Sheykh Mo\u1e29ammad",
        "Sa\u2018d\u016bn Sheykh Mo\u1e29ammad"
    ],
    "wof:name":"Sheykh Mohammad",
    "wof:placetype":"locality"
},
  "geometry": {"coordinates":[48.29628,31.24675],"type":"Point"}
}