{
  "type": "Feature",
  "properties": {
    "gn:admin1_code":"40.0",
    "gn:asciiname":"Mazra`eh-ye Kalantar",
    "gn:country_code":"IR",
    "gn:dem":1099,
    "gn:feature_class":"P",
    "gn:feature_code":"PPLF",
    "gn:name":"Mazra\u2018eh-ye Kal\u0101ntar",
    "gn:population":0,
    "gn:timezone":"Asia/Tehran",
    "iso:country":"IR",
    "name:fas_x_preferred":[
        "Mazra\u2018eh-ye Kal\u0101ntar"
    ],
    "name:fas_x_variant":[
        "\u0645\u0632\u0631\u0639\u0647 \u06a9\u0644\u0627\u0646\u062a\u0631"
    ],
    "name:und_x_variant":[
        "\u0645\u0632\u0631\u0639\u0647 \u06a9\u0644\u0627\u0646\u062a\u0631"
    ],
    "wof:name":"Mazra`eh-ye Kalantar",
    "wof:placetype":"locality"
},
  "geometry": {"coordinates":[54.10335,32.19947],"type":"Point"}
}