{
  "type": "Feature",
  "properties": {
    "gn:admin1_code":"11",
    "gn:asciiname":"Mazra`eh-ye Chah Savab",
    "gn:country_code":"IR",
    "gn:dem":838,
    "gn:feature_class":"P",
    "gn:feature_code":"PPLF",
    "gn:name":"Mazra\u2018eh-ye Ch\u0101h \u015eav\u0101b",
    "gn:population":0,
    "gn:timezone":"Asia/Tehran",
    "iso:country":"IR",
    "name:fas_x_preferred":[
        "\u0645\u0632\u0631\u0639\u0647 \u0686\u0627\u0647 \u0635\u0648\u0627\u0628"
    ],
    "name:fas_x_variant":[
        "\u0645\u0632\u0631\u0639\u0647 \u0686\u0627\u0647 \u062b\u0648\u0627\u0628"
    ],
    "name:und_x_variant":[
        "Mazra\u2018eh-ye Ch\u0101h \u015eav\u0101b",
        "Mazra\u2018eh-ye Ch\u0101h S\u0304av\u0101b"
    ],
    "wof:name":"Mazra`eh-ye Chah Savab",
    "wof:placetype":"locality"
},
  "geometry": {"coordinates":[56.00684,28.23326],"type":"Point"}
}