{
  "type": "Feature",
  "properties": {
    "gn:admin1_code":"7.0",
    "gn:asciiname":"Deh Man",
    "gn:country_code":"IR",
    "gn:dem":1759,
    "gn:feature_class":"P",
    "gn:feature_code":"PPL",
    "gn:name":"Deh Man",
    "gn:population":0,
    "gn:timezone":"Asia/Tehran",
    "iso:country":"IR",
    "wof:name":"Deh Man",
    "wof:placetype":"locality"
},
  "geometry": {"coordinates":[54.01556,29.75306],"type":"Point"}
}