{
  "type": "Feature",
  "properties": {
    "gn:admin1_code":"28",
    "gn:asciiname":"Nivan Nar",
    "gn:country_code":"IR",
    "gn:dem":1800,
    "gn:feature_class":"P",
    "gn:feature_code":"PPL",
    "gn:name":"N\u012bv\u0101n N\u0101r",
    "gn:population":0,
    "gn:timezone":"Asia/Tehran",
    "iso:country":"IR",
    "name:ara_x_preferred":[
        "\u0646\u064a\u0648\u0627\u0646 \u0646\u0627\u0631"
    ],
    "name:fas_x_preferred":[
        "N\u012bv\u0101n N\u0101r"
    ],
    "name:fas_x_variant":[
        "\u0646\u06cc\u0648\u0627\u0646 \u0646\u0627\u0631",
        "\u0646\u06cc\u0648\u0627\u0646 \u0628\u0632\u0631\u06af"
    ],
    "name:und_x_variant":[
        "N\u012bv\u0101n T\u0101r",
        "N\u012bv\u0101n-e N\u0101r",
        "N\u012bv\u0101n-e Bozorg"
    ],
    "wof:name":"Nivan Nar",
    "wof:placetype":"locality"
},
  "geometry": {"coordinates":[50.38005,33.45846],"type":"Point"}
}