{
  "type": "Feature",
  "properties": {
    "gn:admin1_code":"15.0",
    "gn:asciiname":"Mehrabad",
    "gn:cc2":"IR",
    "gn:country_code":"IR",
    "gn:dem":12,
    "gn:feature_class":"P",
    "gn:feature_code":"PPL",
    "gn:name":"Mehr\u0101b\u0101d",
    "gn:population":0,
    "gn:timezone":"Asia/Tehran",
    "iso:country":"IR",
    "name:fas_x_preferred":[
        "Mehr\u0101b\u0101d"
    ],
    "name:und_x_variant":[
        "M\u012bhan \u0100b\u0101d"
    ],
    "wof:name":"Mehrabad",
    "wof:placetype":"locality"
},
  "geometry": {"coordinates":[48.03917,31.68306],"type":"Point"}
}