{
  "type": "Feature",
  "properties": {
    "iso:country":"IR",
    "name:ara_x_preferred":[
        "\u0641\u0634\u0645"
    ],
    "name:aze_x_preferred":[
        "\u0641\u0634\u0645"
    ],
    "name:bul_x_preferred":[
        "\u0424\u0430\u0448\u0430\u043c"
    ],
    "name:ceb_x_preferred":[
        "Fasham"
    ],
    "name:eng_x_preferred":[
        "Fasham"
    ],
    "name:fas_x_preferred":[
        "\u0641\u0634\u0645"
    ],
    "name:fas_x_variant":[
        "\u0641\u064e\u0634\u064e\u0646\u062f",
        "\u0641\u064e\u0686\u064e\u0645",
        "\u067e\u064e\u0634\u064e\u0645"
    ],
    "name:fra_x_preferred":[
        "Fasham"
    ],
    "name:ita_x_preferred":[
        "Fasham"
    ],
    "name:mlg_x_preferred":[
        "Fasham"
    ],
    "name:mzn_x_preferred":[
        "\u0641\u0634\u0645"
    ],
    "name:nld_x_preferred":[
        "Fasham"
    ],
    "name:swe_x_preferred":[
        "Fasham"
    ],
    "name:tur_x_preferred":[
        "Fe\u015fem"
    ],
    "name:und_x_variant":[
        "Pasham"
    ],
    "qs:gn_country":"IR",
    "qs:gn_fcode":"PPL",
    "qs:gn_pop":0,
    "qs:name":"Fasham",
    "qs:name_adm0":"Iran",
    "qs:name_adm1":"Tehran",
    "qs:photos":52,
    "qs:photos_1k":11,
    "qs:photos_9k":1,
    "qs:photos_9r":2,
    "qs:photos_all":52,
    "qs:photos_sr":2,
    "qs:placetype":"Town",
    "qs:pop_sr":"0",
    "qs:woe_adm0":23424851,
    "wd:wordcount":100,
    "wof:name":"Fasham",
    "wof:placetype":"locality"
},
  "geometry": {"coordinates":[51.5266,35.9306],"type":"Point"}
}