{
  "type": "Feature",
  "properties": {
    "gn:admin1_code":"36",
    "gn:asciiname":"Hajji Bachcheh",
    "gn:country_code":"IR",
    "gn:dem":1896,
    "gn:feature_class":"P",
    "gn:feature_code":"PPL",
    "gn:name":"\u1e28\u0101jj\u012b Bachcheh",
    "gn:population":0,
    "gn:timezone":"Asia/Tehran",
    "iso:country":"IR",
    "name:fas_x_preferred":[
        "\u062d\u0627\u062c\u06cc \u0628\u0686\u0647"
    ],
    "name:fas_x_variant":[
        "\u1e28\u0101jj\u012b Bachcheh"
    ],
    "name:und_x_variant":[
        "\u1e28\u0101j\u012b Bachcheh",
        "H\u0101jibacheh"
    ],
    "wof:name":"Hajji Bachcheh",
    "wof:placetype":"locality"
},
  "geometry": {"coordinates":[47.97189,36.58392],"type":"Point"}
}