{
  "type": "Feature",
  "properties": {
    "gn:admin1_code":"41",
    "gn:asciiname":"Vazaq",
    "gn:country_code":"IR",
    "gn:dem":1818,
    "gn:feature_class":"P",
    "gn:feature_code":"PPL",
    "gn:name":"Vazaq",
    "gn:population":0,
    "gn:timezone":"Asia/Tehran",
    "iso:country":"IR",
    "name:fas_x_preferred":[
        "\u0648\u0632\u0642"
    ],
    "name:und_x_variant":[
        "Wazak",
        "Wezk",
        "Vezq"
    ],
    "wof:name":"Vazaq",
    "wof:placetype":"locality"
},
  "geometry": {"coordinates":[59.26447,33.37827],"type":"Point"}
}