{
  "type": "Feature",
  "properties": {
    "gn:admin1_code":"42.0",
    "gn:asciiname":"Hey'at",
    "gn:country_code":"IR",
    "gn:dem":1217,
    "gn:feature_class":"P",
    "gn:feature_code":"PPL",
    "gn:name":"Hey\u2019at",
    "gn:population":0,
    "gn:timezone":"Asia/Tehran",
    "iso:country":"IR",
    "name:fas_x_preferred":[
        "\u0647\u06cc\u0626\u062a"
    ],
    "name:und_x_variant":[
        "Hey\u2019at"
    ],
    "wof:name":"Hey'at",
    "wof:placetype":"locality"
},
  "geometry": {"coordinates":[58.87001,35.93177],"type":"Point"}
}