{
  "type": "Feature",
  "properties": {
    "gn:admin1_code":"8.0",
    "gn:asciiname":"Sorush Mahalleh",
    "gn:country_code":"IR",
    "gn:dem":71,
    "gn:feature_class":"P",
    "gn:feature_code":"PPL",
    "gn:name":"Sor\u016bsh Ma\u1e29alleh",
    "gn:population":0,
    "gn:timezone":"Asia/Tehran",
    "iso:country":"IR",
    "name:fas_x_preferred":[
        "\u0633\u0631\u0648\u0634 \u0645\u062d\u0644\u0647"
    ],
    "name:und_x_variant":[
        "Sor\u016bsh Ma\u1e29alleh"
    ],
    "wof:name":"Sorush Mahalleh",
    "wof:placetype":"locality"
},
  "geometry": {"coordinates":[49.07351,37.55026],"type":"Point"}
}