{
  "type": "Feature",
  "properties": {
    "gn:admin1_code":"13",
    "gn:asciiname":"Kahriz-e Kalan",
    "gn:country_code":"IR",
    "gn:dem":1376,
    "gn:feature_class":"P",
    "gn:feature_code":"PPL",
    "gn:name":"Kahr\u012bz-e Kal\u0101n",
    "gn:population":0,
    "gn:timezone":"Asia/Tehran",
    "iso:country":"IR",
    "name:fas_x_preferred":[
        "\u06a9\u0647\u0631\u06cc\u0632 \u06a9\u0644\u0627\u0646"
    ],
    "name:fas_x_variant":[
        "Kahr\u012bz-e Kal\u0101n",
        "\u06a9\u0647\u0631\u06cc\u0632\u06a9\u0644\u0627\u0646"
    ],
    "wof:name":"Kahriz-e Kalan",
    "wof:placetype":"locality"
},
  "geometry": {"coordinates":[47.7916,34.3714],"type":"Point"}
}