{
  "type": "Feature",
  "properties": {
    "gn:admin1_code":"11",
    "gn:asciiname":"Gorbah Dan",
    "gn:country_code":"IR",
    "gn:dem":20,
    "gn:feature_class":"P",
    "gn:feature_code":"PPL",
    "gn:name":"Gorbah D\u0101n",
    "gn:population":0,
    "gn:timezone":"Asia/Tehran",
    "iso:country":"IR",
    "name:ceb_x_preferred":[
        "Gorbah D\u0101n"
    ],
    "name:fas_x_preferred":[
        "\u06af\u0631\u0628\u0647\u0650\u062f\u0627\u0646"
    ],
    "name:fas_x_variant":[
        "\u06af\u064f\u0631\u0628\u0650\u0647\u062f\u0627\u0646",
        "\u06af\u0631\u0628\u0647 \u062f\u0627\u0646",
        "Gorbahed\u0101n",
        "Gorbah D\u0101n"
    ],
    "name:msa_x_preferred":[
        "Gorbah Dan"
    ],
    "name:swe_x_preferred":[
        "Gorbah D\u0101n"
    ],
    "name:und_x_variant":[
        "Gorbehd\u0101n"
    ],
    "wof:name":"Gorbah Dan",
    "wof:placetype":"locality"
},
  "geometry": {"coordinates":[55.9823,26.8619],"type":"Point"}
}