{
  "type": "Feature",
  "properties": {
    "gn:admin1_code":"5.0",
    "gn:asciiname":"Dasht-e Daraveh",
    "gn:country_code":"IR",
    "gn:dem":1580,
    "gn:feature_class":"P",
    "gn:feature_code":"PPL",
    "gn:name":"Dasht-e D\u0101r\u0101veh",
    "gn:population":0,
    "gn:timezone":"Asia/Tehran",
    "iso:country":"IR",
    "name:fas_x_preferred":[
        "\u062f\u0634\u062a \u062f\u0627\u0631\u0627\u0648\u0647"
    ],
    "name:und_x_variant":[
        "Dasht-e D\u0101r\u0101veh"
    ],
    "wof:name":"Dasht-e Daraveh",
    "wof:placetype":"locality"
},
  "geometry": {"coordinates":[50.51541,31.07671],"type":"Point"}
}