{
  "type": "Feature",
  "properties": {
    "gn:admin1_code":"32.0",
    "gn:asciiname":"Al Hashem-e Sofla",
    "gn:country_code":"IR",
    "gn:dem":1984,
    "gn:feature_class":"P",
    "gn:feature_code":"PPL",
    "gn:name":"\u0100l H\u0101shem-e Sofl\u00e1",
    "gn:population":0,
    "gn:timezone":"Asia/Tehran",
    "iso:country":"IR",
    "name:fas_x_preferred":[
        "\u0622\u0644 \u0647\u0627\u0634\u0645 \u067e\u0627\u0626\u06cc\u0646"
    ],
    "name:fas_x_variant":[
        "\u0100lh\u0101shem-e Sofl\u00e1",
        "\u0622\u0644 \u0647\u0627\u0634\u0645 \u0633\u0641\u0644\u06cc",
        "\u0622\u0644\u200c\u0647\u0627\u0634\u0645 \u0633\u0641\u0644\u06cc"
    ],
    "name:msa_x_preferred":[
        "Alhashem-e Sofla"
    ],
    "name:mzn_x_preferred":[
        "\u0622\u0644\u200c\u0647\u0627\u0634\u0645 \u0633\u0641\u0644\u06cc"
    ],
    "name:und_x_variant":[
        "Marghz\u0101r",
        "\u0100l H\u0101shem-e Sofl\u00e1",
        "\u0100l H\u0101shem-e P\u0101\u2019\u012bn"
    ],
    "wof:name":"Al Hashem-e Sofla",
    "wof:placetype":"locality"
},
  "geometry": {"coordinates":[48.51091,37.54642],"type":"Point"}
}