{
  "type": "Feature",
  "properties": {
    "gn:admin1_code":"1",
    "gn:asciiname":"Fishal-e Qarah Qowyun",
    "gn:country_code":"IR",
    "gn:dem":1846,
    "gn:feature_class":"P",
    "gn:feature_code":"PPL",
    "gn:name":"F\u012bshal-e Qarah Qowy\u016bn",
    "gn:population":0,
    "gn:timezone":"Asia/Tehran",
    "iso:country":"IR",
    "name:fas_x_preferred":[
        "\u0641\u064a\u0634\u064e\u0644"
    ],
    "name:fas_x_variant":[
        "\u0641\u06cc\u0634\u0644 \u0642\u0631\u0647 \u0642\u0648\u06cc\u0648\u0646",
        "F\u012bshal",
        "F\u012bshal-e Qarah Qowy\u016bn"
    ],
    "wof:name":"Fishal-e Qarah Qowyun",
    "wof:placetype":"locality"
},
  "geometry": {"coordinates":[44.8016,39.0524],"type":"Point"}
}