{
  "type": "Feature",
  "properties": {
    "gn:admin1_code":"36",
    "gn:asciiname":"Qarah Bolagh",
    "gn:country_code":"IR",
    "gn:dem":2103,
    "gn:feature_class":"P",
    "gn:feature_code":"PPL",
    "gn:name":"Qarah Bol\u0101gh",
    "gn:population":0,
    "gn:timezone":"Asia/Tehran",
    "iso:country":"IR",
    "name:ara_x_preferred":[
        "\u0642\u0631\u0629 \u0628\u0644\u0627\u063a"
    ],
    "name:azb_x_preferred":[
        "\u0642\u0631\u0647 \u0628\u0644\u0627\u063a"
    ],
    "name:fas_x_preferred":[
        "\u0642\u064e\u0631\u0650\u0647 \u0628\u064f\u0644\u0627\u063a"
    ],
    "name:fas_x_variant":[
        "\u0643\u064e\u0631\u0628\u064e\u0644\u064e",
        "\u0642\u0631\u0647 \u0628\u0644\u0627\u063a",
        "Qareh Bol\u0101gh",
        "Qarah Bol\u0101gh",
        "\u0642\u0631\u0647\u200c\u0628\u0644\u0627\u063a"
    ],
    "name:und_x_variant":[
        "Karbala"
    ],
    "wof:name":"Qarah Bolagh",
    "wof:placetype":"locality"
},
  "geometry": {"coordinates":[48.01273,36.4176],"type":"Point"}
}