{
  "type": "Feature",
  "properties": {
    "gn:admin1_code":"29",
    "gn:asciiname":"Godar-e Moghak",
    "gn:cc2":"IR",
    "gn:country_code":"IR",
    "gn:dem":1194,
    "gn:feature_class":"P",
    "gn:feature_code":"PPL",
    "gn:name":"God\u0101r-e Moghak",
    "gn:population":0,
    "gn:timezone":"Asia/Tehran",
    "iso:country":"IR",
    "name:fas_x_preferred":[
        "God\u0101r-e Moghak"
    ],
    "name:und_x_variant":[
        "Gowd Maghak",
        "Gowd Moghak"
    ],
    "wof:name":"Godar-e Moghak",
    "wof:placetype":"locality"
},
  "geometry": {"coordinates":[57.79389000000001,28.81722],"type":"Point"}
}