{
  "type": "Feature",
  "properties": {
    "gn:admin1_code":"23",
    "gn:asciiname":"Kazemabad",
    "gn:country_code":"IR",
    "gn:dem":1714,
    "gn:feature_class":"P",
    "gn:feature_code":"PPL",
    "gn:name":"K\u0101z\u0327em\u0101b\u0101d",
    "gn:population":0,
    "gn:timezone":"Asia/Tehran",
    "iso:country":"IR",
    "name:fas_x_preferred":[
        "\u062a\u064a\u0632\u0627\u0628\u0650 \u0643\u0627\u0638\u0650\u0645\u06cc"
    ],
    "name:fas_x_variant":[
        "\u0643\u0627\u0638\u0645\u06cc",
        "T\u012bz\u0101b-e K\u0101z\u0327em\u012b",
        "\u06a9\u0627\u0638\u0645 \u0622\u0628\u0627\u062f",
        "\u06a9\u0627\u0638\u0645 \u0622\u0628\u0627\u062f \u0633\u0648\u0631\u062c\u0645"
    ],
    "name:und_x_variant":[
        "K\u0101z\u0327em\u012b",
        "K\u0101z\u0327em\u0101b\u0101d",
        "K\u0101z\u0327em\u0101b\u0101d S\u016brjam"
    ],
    "wof:name":"Kazemabad",
    "wof:placetype":"locality"
},
  "geometry": {"coordinates":[47.83445,33.95527],"type":"Point"}
}