{
  "type": "Feature",
  "properties": {
    "gn:admin1_code":"11",
    "gn:asciiname":"Tomban Rahi",
    "gn:country_code":"IR",
    "gn:dem":12,
    "gn:feature_class":"P",
    "gn:feature_code":"PPL",
    "gn:name":"Tomb\u0101n R\u0101h\u012b",
    "gn:population":0,
    "gn:timezone":"Asia/Tehran",
    "iso:country":"IR",
    "name:fas_x_preferred":[
        "\u062a\u0645\u0628\u0627\u0646 \u0631\u0627\u0647\u06cc"
    ],
    "name:fas_x_variant":[
        "T\u016bm\u0101nz\u0101h\u012b",
        "Tomb\u0101n R\u0101h\u012b",
        "\u062a\u0648\u0645\u0627\u0646 \u0631\u0627\u0647\u06cc"
    ],
    "name:und_x_variant":[
        "Towm\u0101n R\u0101h\u012b"
    ],
    "wof:name":"Tomban Rahi",
    "wof:placetype":"locality"
},
  "geometry": {"coordinates":[57.15818,26.47298],"type":"Point"}
}