{
  "type": "Feature",
  "properties": {
    "gn:admin1_code":"35.0",
    "gn:asciiname":"Ramadan Kheyl",
    "gn:country_code":"IR",
    "gn:dem":757,
    "gn:feature_class":"P",
    "gn:feature_code":"PPL",
    "gn:name":"Ramad\u0101n Kheyl",
    "gn:population":0,
    "gn:timezone":"Asia/Tehran",
    "iso:country":"IR",
    "name:ceb_x_preferred":[
        "Ramad\u0101n Kheyl"
    ],
    "name:fas_x_preferred":[
        "Ramad\u0101n Kheyl"
    ],
    "name:fas_x_variant":[
        "\u0631\u0645\u062f\u0627\u0646 \u062e\u064a\u0644",
        "\u0631\u0645\u062f\u0627\u0646\u200c\u062e\u06cc\u0644"
    ],
    "name:swe_x_preferred":[
        "Ramad\u0101n Kheyl"
    ],
    "name:und_x_variant":[
        "\u0631\u0645\u062f\u0627\u0646 \u062e\u064a\u0644"
    ],
    "wof:name":"Ramadan Kheyl",
    "wof:placetype":"locality"
},
  "geometry": {"coordinates":[53.59072,36.53822],"type":"Point"}
}