{
  "type": "Feature",
  "properties": {
    "gn:admin1_code":"33",
    "gn:asciiname":"Goljeh",
    "gn:country_code":"IR",
    "gn:dem":1738,
    "gn:feature_class":"P",
    "gn:feature_code":"PPL",
    "gn:name":"Goljeh",
    "gn:population":0,
    "gn:timezone":"Asia/Tehran",
    "iso:country":"IR",
    "name:fas_x_preferred":[
        "\u06af\u0644\u062c\u0647"
    ],
    "name:fas_x_variant":[
        "Goll\u016bjeh"
    ],
    "name:und_x_variant":[
        "Gyulyudzha",
        "Golujeh",
        "Goljeh"
    ],
    "wof:name":"Goljeh",
    "wof:placetype":"locality"
},
  "geometry": {"coordinates":[46.8966,38.5867],"type":"Point"}
}