{
  "type": "Feature",
  "properties": {
    "gn:admin1_code":"4.0",
    "gn:asciiname":"Surmich",
    "gn:country_code":"IR",
    "gn:dem":958,
    "gn:feature_class":"P",
    "gn:feature_code":"PPL",
    "gn:name":"S\u016brm\u012bch",
    "gn:population":0,
    "gn:timezone":"Asia/Tehran",
    "iso:country":"IR",
    "name:fas_x_preferred":[
        "\u0633\u0648\u0631\u0645\u06cc\u0686"
    ],
    "name:fas_x_variant":[
        "Sorm\u012bch",
        "S\u016brm\u012bch",
        "Sarm\u012bj",
        "Sarm\u012bch",
        "J\u0101hali",
        "Surm\u012bch",
        "S\u016brm\u012bsh"
    ],
    "name:und_x_variant":[
        "J\u0101hali",
        "Surm\u012bch",
        "S\u016brm\u012bsh",
        "Sarm\u012bj",
        "Sarm\u012bch"
    ],
    "wof:name":"Surmich",
    "wof:placetype":"locality"
},
  "geometry": {"coordinates":[60.3588,26.78724],"type":"Point"}
}