{
  "type": "Feature",
  "properties": {
    "gn:admin1_code":"33",
    "gn:asciiname":"Yaleh Qarshu",
    "gn:country_code":"IR",
    "gn:dem":1651,
    "gn:feature_class":"P",
    "gn:feature_code":"PPL",
    "gn:name":"Yaleh Q\u0101rsh\u016b",
    "gn:population":0,
    "gn:timezone":"Asia/Tehran",
    "iso:country":"IR",
    "name:fas_x_preferred":[
        "\u06cc\u0644\u0647 \u0642\u0627\u0631\u0634\u0648"
    ],
    "name:und_x_variant":[
        "Yaleh Q\u0101rsh\u016b"
    ],
    "wof:name":"Yaleh Qarshu",
    "wof:placetype":"locality"
},
  "geometry": {"coordinates":[46.8369,37.34],"type":"Point"}
}