{
  "type": "Feature",
  "properties": {
    "iso:country":"IR",
    "name:ara_x_preferred":[
        "\u0627\u0644\u0641\u0644\u0627\u062d\u064a\u0629"
    ],
    "name:aze_x_preferred":[
        "\u015eadgan"
    ],
    "name:cat_x_preferred":[
        "Xadegan"
    ],
    "name:deu_x_preferred":[
        "Schadegan"
    ],
    "name:eng_x_preferred":[
        "Shadegan"
    ],
    "name:epo_x_preferred":[
        "\u015cadegano"
    ],
    "name:fas_x_preferred":[
        "\u0634\u0627\u062f\u06af\u0627\u0646"
    ],
    "name:fas_x_variant":[
        "Sh\u0101deg\u0101n"
    ],
    "name:fra_x_preferred":[
        "Shadegan"
    ],
    "name:ita_x_preferred":[
        "Shadegan"
    ],
    "name:mlg_x_preferred":[
        "Shadegan"
    ],
    "name:nld_x_preferred":[
        "Shadegan"
    ],
    "name:pnb_x_preferred":[
        "\u0634\u0627\u062f\u06af\u0627\u0646"
    ],
    "name:pol_x_preferred":[
        "Szadegan"
    ],
    "name:rus_x_preferred":[
        "\u0428\u0430\u0434\u0435\u0433\u0430\u043d"
    ],
    "name:rus_x_variant":[
        "\u0428\u0430\u0434\u0435\u0433\u0430\u043d\u0441\u043a\u0438\u0435"
    ],
    "name:swe_x_preferred":[
        "Sh\u0101deg\u0101n"
    ],
    "name:tgk_x_preferred":[
        "\u0428\u043e\u0434\u0430\u0433\u043e\u043d"
    ],
    "name:tur_x_preferred":[
        "\u015eadgan"
    ],
    "name:unk_x_variant":[
        "Fall\u0101b\u012byeh"
    ],
    "name:zho_x_preferred":[
        "\u6c99\u4ee3\u7518"
    ],
    "qs:gn_country":"IR",
    "qs:gn_fcode":"PPL",
    "qs:gn_pop":37220,
    "qs:name":"Shadgan",
    "qs:name_adm0":"Iran",
    "qs:name_adm1":"Khuzestan",
    "qs:photos":0,
    "qs:photos_1k":0,
    "qs:photos_9k":0,
    "qs:photos_9r":0,
    "qs:photos_all":0,
    "qs:photos_sr":0,
    "qs:placetype":"Town",
    "qs:pop_sr":"7",
    "qs:woe_adm0":23424851,
    "wd:wordcount":129,
    "wof:name":"Shadgan",
    "wof:placetype":"locality",
    "wof:population":37220
},
  "geometry": {"coordinates":[48.66472,30.64972],"type":"Point"}
}