{
  "type": "Feature",
  "properties": {
    "gn:admin1_code":"28.0",
    "gn:asciiname":"Chaqa Gerd",
    "gn:country_code":"IR",
    "gn:dem":2520,
    "gn:feature_class":"P",
    "gn:feature_code":"PPL",
    "gn:name":"Ch\u0101q\u0101 Gerd",
    "gn:population":0,
    "gn:timezone":"Asia/Tehran",
    "iso:country":"IR",
    "name:fas_x_preferred":[
        "Ch\u0101q\u0101 Gerd"
    ],
    "name:fas_x_variant":[
        "\u0686\u0627\u0642\u0627 \u06af\u0631\u062f"
    ],
    "wof:name":"Chaqa Gerd",
    "wof:placetype":"locality"
},
  "geometry": {"coordinates":[50.13511,32.99427],"type":"Point"}
}