{
  "type": "Feature",
  "properties": {
    "gn:admin1_code":"42.0",
    "gn:asciiname":"Chah-e Nowruz",
    "gn:country_code":"IR",
    "gn:dem":886,
    "gn:feature_class":"P",
    "gn:feature_code":"PPLL",
    "gn:name":"Ch\u0101h-e Nowr\u016bz",
    "gn:population":0,
    "gn:timezone":"Asia/Tehran",
    "iso:country":"IR",
    "name:fas_x_preferred":[
        "\u0686\u0627\u0647 \u0646\u0648\u0631\u0648\u0632"
    ],
    "name:fas_x_variant":[
        "\u0686\u0627\u0647 \u0639\u0645\u064a\u0642 \u062e\u0627\u0646\u0647 \u0646\u0648\u0631\u0648\u0632"
    ],
    "name:und_x_variant":[
        "Ch\u0101h-e Nowr\u016bz",
        "Ch\u0101h-e \u2018Am\u012bq Kh\u0101neh-ye Nowr\u016bz"
    ],
    "wof:name":"Chah-e Nowruz",
    "wof:placetype":"locality"
},
  "geometry": {"coordinates":[58.68858,34.9973],"type":"Point"}
}