{
  "type": "Feature",
  "properties": {
    "gn:admin1_code":"32",
    "gn:asciiname":"Chalgar",
    "gn:country_code":"IR",
    "gn:dem":1710,
    "gn:feature_class":"P",
    "gn:feature_code":"PPL",
    "gn:name":"Ch\u0101lgar",
    "gn:population":0,
    "gn:timezone":"Asia/Tehran",
    "iso:country":"IR",
    "name:fas_x_preferred":[
        "\u0686\u0627\u0644\u06af\u0631"
    ],
    "name:fas_x_variant":[
        "Ch\u0101lgar\u016bd",
        "Ch\u0101lgar",
        "\u0686\u0627\u0644\u06af\u0631\u0648\u062f"
    ],
    "wof:name":"Chalgar",
    "wof:placetype":"locality"
},
  "geometry": {"coordinates":[48.39688,37.67533],"type":"Point"}
}