{
  "type": "Feature",
  "properties": {
    "gn:admin1_code":"8",
    "gn:asciiname":"Reza Borna",
    "gn:country_code":"IR",
    "gn:dem":1884,
    "gn:feature_class":"P",
    "gn:feature_code":"PPL",
    "gn:name":"Re\u1e95\u0101 Born\u0101",
    "gn:population":0,
    "gn:timezone":"Asia/Tehran",
    "iso:country":"IR",
    "name:fas_x_preferred":[
        "\u0631\u0636\u0627 \u0628\u0631\u0646\u0627"
    ],
    "name:fas_x_variant":[
        "Re\u1e95\u0101 Born\u0101"
    ],
    "wof:name":"Reza Borna",
    "wof:placetype":"locality"
},
  "geometry": {"coordinates":[49.03437,37.09061],"type":"Point"}
}