{
  "type": "Feature",
  "properties": {
    "gn:admin1_code":"7",
    "gn:asciiname":"Mohit Ab",
    "gn:country_code":"IR",
    "gn:dem":1061,
    "gn:feature_class":"P",
    "gn:feature_code":"PPL",
    "gn:name":"Mo\u1e29\u012b\u0163 \u0100b",
    "gn:population":0,
    "gn:timezone":"Asia/Tehran",
    "iso:country":"IR",
    "name:fas_x_preferred":[
        "\u0645\u062d\u06cc\u0637 \u0622\u0628"
    ],
    "name:fas_x_variant":[
        "Mo\u1e29\u012b\u0163 \u0100b",
        "\u0645\u062d\u06cc\u0637\u0627\u0628"
    ],
    "name:msa_x_preferred":[
        "Mohit Ab"
    ],
    "name:und_x_variant":[
        "Mo\u1e29\u012b\u0163\u0101"
    ],
    "wof:name":"Mohit Ab",
    "wof:placetype":"locality"
},
  "geometry": {"coordinates":[53.0124,28.663],"type":"Point"}
}