{
  "type": "Feature",
  "properties": {
    "gn:admin1_code":"15",
    "gn:asciiname":"Ab Anari",
    "gn:country_code":"IR",
    "gn:dem":572,
    "gn:feature_class":"P",
    "gn:feature_code":"PPL",
    "gn:name":"\u0100b An\u0101r\u012b",
    "gn:population":0,
    "gn:timezone":"Asia/Tehran",
    "iso:country":"IR",
    "name:azb_x_preferred":[
        "\u0622\u0628\u0627\u0646\u0627\u0631\u06cc"
    ],
    "name:fas_x_preferred":[
        "\u06a9\u0644\u0628\u0644\u06cc \u0639\u0631\u0628"
    ],
    "name:fas_x_variant":[
        "Kalb\u2018al\u012b \u2018Arab",
        "Kalbal\u012b \u2018Arab",
        "\u0622\u0628 \u0627\u0646\u0627\u0631\u06cc",
        "\u06a9\u0644\u0628\u0639\u0644\u06cc \u0639\u0631\u0628",
        "\u0622\u0628\u0627\u0646\u0627\u0631\u06cc"
    ],
    "name:und_x_variant":[
        "\u0100b An\u0101r\u012b"
    ],
    "name:urd_x_preferred":[
        "\u0622\u0628\u0627\u0646\u0627\u0631\u06cc"
    ],
    "wof:name":"Ab Anari",
    "wof:placetype":"locality"
},
  "geometry": {"coordinates":[49.4496,32.1055],"type":"Point"}
}