{
  "type": "Feature",
  "properties": {
    "gn:admin1_code":"7",
    "gn:asciiname":"Hoseynabad Kamin",
    "gn:country_code":"IR",
    "gn:dem":1613,
    "gn:feature_class":"P",
    "gn:feature_code":"PPL",
    "gn:name":"\u1e28oseyn\u0101b\u0101d Kam\u012bn",
    "gn:population":0,
    "gn:timezone":"Asia/Tehran",
    "iso:country":"IR",
    "name:fas_x_preferred":[
        "\u062d\u0633\u0646 \u0622\u0628\u0627\u062f \u062a\u0644 \u06a9\u0645\u06cc\u0646"
    ],
    "name:fas_x_variant":[
        "\u1e28asan\u0101b\u0101d-e Tall Kam\u012bn",
        "\u062d\u0633\u064a\u0646 \u0622\u0628\u0627\u062f \u06a9\u0645\u06cc\u0646",
        "\u062d\u0633\u0646\u200c\u0622\u0628\u0627\u062f \u062a\u0644 \u06a9\u0645\u06cc\u0646"
    ],
    "name:msa_x_preferred":[
        "Hasanabad-e Tall Kamin"
    ],
    "name:und_x_variant":[
        "\u1e28asan\u0101b\u0101d-e Tol Kam\u012bn",
        "\u1e28asan\u0101b\u0101d Tol Kam\u012bn",
        "\u1e28oseyn\u0101b\u0101d Kam\u012bn"
    ],
    "wof:name":"Hoseynabad Kamin",
    "wof:placetype":"locality"
},
  "geometry": {"coordinates":[52.8302,30.0175],"type":"Point"}
}