{
  "type": "Feature",
  "properties": {
    "gn:admin1_code":"35",
    "gn:asciiname":"Nowabad",
    "gn:country_code":"IR",
    "gn:dem":358,
    "gn:feature_class":"P",
    "gn:feature_code":"PPL",
    "gn:name":"Now\u0101b\u0101d",
    "gn:population":0,
    "gn:timezone":"Asia/Tehran",
    "iso:country":"IR",
    "name:fas_x_preferred":[
        "\u0646\u0648 \u0622\u0628\u0627\u062f"
    ],
    "name:fas_x_variant":[
        "Now\u0101b\u0101d"
    ],
    "wof:name":"Nowabad",
    "wof:placetype":"locality"
},
  "geometry": {"coordinates":[52.92036,36.21179],"type":"Point"}
}