{
  "type": "Feature",
  "properties": {
    "gn:admin1_code":"16.0",
    "gn:asciiname":"Shilan",
    "gn:country_code":"IR",
    "gn:dem":1513,
    "gn:elevation":"0.0",
    "gn:feature_class":"P",
    "gn:feature_code":"PPL",
    "gn:name":"Sh\u012bl\u0101n",
    "gn:population":0,
    "gn:timezone":"Asia/Tehran",
    "iso:country":"IR",
    "name:fas_x_preferred":[
        "\u0643\u0627\u0646\u06cc \u0634\u064a\u0644\u0627\u0646"
    ],
    "name:fas_x_variant":[
        "\u0634\u06cc\u0644\u0627\u0646",
        "K\u0101n\u012b Sh\u012bl\u0101n",
        "Sh\u012bl\u0101n"
    ],
    "wof:name":"Shilan",
    "wof:placetype":"locality"
},
  "geometry": {"coordinates":[45.9192,35.8621],"type":"Point"}
}