{
  "type": "Feature",
  "properties": {
    "gn:admin1_code":"3.0",
    "gn:asciiname":"Kalmeh Tin",
    "gn:country_code":"IR",
    "gn:dem":1625,
    "gn:feature_class":"P",
    "gn:feature_code":"PPL",
    "gn:name":"Kalmeh T\u012bn",
    "gn:population":0,
    "gn:timezone":"Asia/Tehran",
    "iso:country":"IR",
    "name:fas_x_preferred":[
        "Kalmeh T\u012bn"
    ],
    "name:fas_x_variant":[
        "\u06a9\u0644\u0645\u0647 \u062a\u06cc\u0646",
        "\u06af\u0644\u0645\u062a\u06cc\u0646"
    ],
    "name:und_x_variant":[
        "\u06a9\u0644\u0645\u0647 \u062a\u06cc\u0646",
        "Galmet\u012bn"
    ],
    "wof:name":"Kalmeh Tin",
    "wof:placetype":"locality"
},
  "geometry": {"coordinates":[50.7589,31.35485],"type":"Point"}
}