{
  "type": "Feature",
  "properties": {
    "gn:admin1_code":"8.0",
    "gn:asciiname":"Kolisarak",
    "gn:country_code":"IR",
    "gn:dem":228,
    "gn:feature_class":"P",
    "gn:feature_code":"PPL",
    "gn:name":"Kol\u012bsarak",
    "gn:population":0,
    "gn:timezone":"Asia/Tehran",
    "iso:country":"IR",
    "name:fas_x_preferred":[
        "Gel\u012bsarak"
    ],
    "name:fas_x_variant":[
        "\u06a9\u0644\u06cc\u0633\u0631\u06a9"
    ],
    "name:und_x_variant":[
        "\u06a9\u0644\u06cc\u0633\u0631\u06a9",
        "Kol\u012bsarak"
    ],
    "wof:name":"Kolisarak",
    "wof:placetype":"locality"
},
  "geometry": {"coordinates":[49.6325,37.07056],"type":"Point"}
}