{
  "type": "Feature",
  "properties": {
    "gn:admin1_code":"23",
    "gn:asciiname":"Miran Mard",
    "gn:country_code":"IR",
    "gn:dem":1404,
    "gn:feature_class":"P",
    "gn:feature_code":"PPL",
    "gn:name":"M\u012br\u0101n Mard",
    "gn:population":0,
    "gn:timezone":"Asia/Tehran",
    "iso:country":"IR",
    "name:fas_x_preferred":[
        "\u06af\u064e\u0686 \u0643\u0650\u064a\u062e\u0648\u0627\u0647"
    ],
    "name:fas_x_variant":[
        "Gach Keykhv\u0101h",
        "\u0645\u06cc\u0631\u0627\u0646 \u0645\u0631\u062f",
        "\u0686\u0645 \u06af\u0632",
        "\u06af\u0686 \u06a9\u064a\u062e\u0648\u0627\u0647"
    ],
    "name:und_x_variant":[
        "M\u012br\u0101n Mard",
        "Cham Gaz"
    ],
    "wof:name":"Miran Mard",
    "wof:placetype":"locality"
},
  "geometry": {"coordinates":[48.21813,33.12159],"type":"Point"}
}