{
  "type": "Feature",
  "properties": {
    "gn:admin1_code":"8",
    "gn:asciiname":"Poshteh Sara",
    "gn:country_code":"IR",
    "gn:dem":203,
    "gn:feature_class":"P",
    "gn:feature_code":"PPL",
    "gn:name":"Poshteh Sar\u0101",
    "gn:population":0,
    "gn:timezone":"Asia/Tehran",
    "iso:country":"IR",
    "name:fas_x_preferred":[
        "Poshteh Sar\u0101"
    ],
    "name:fas_x_variant":[
        "\u067e\u0634\u062a\u0647 \u0633\u0631\u0627"
    ],
    "name:msa_x_preferred":[
        "Poshteh Sara"
    ],
    "name:ukr_x_preferred":[
        "\u041f\u043e\u0448\u0442\u0435-\u0421\u0430\u0440\u0430"
    ],
    "wof:name":"Poshteh Sara",
    "wof:placetype":"locality"
},
  "geometry": {"coordinates":[49.68722,37.03111],"type":"Point"}
}