{
  "type": "Feature",
  "properties": {
    "gn:admin1_code":"41",
    "gn:asciiname":"Salmangun",
    "gn:country_code":"IR",
    "gn:dem":2004,
    "gn:feature_class":"P",
    "gn:feature_code":"PPL",
    "gn:name":"Salmang\u016bn",
    "gn:population":0,
    "gn:timezone":"Asia/Tehran",
    "iso:country":"IR",
    "name:fas_x_preferred":[
        "\u0633\u0644\u0645\u0646\u06af\u0648\u0646"
    ],
    "name:fas_x_variant":[
        "Salmang\u016bn",
        "\u0633\u0644\u0645\u0646\u06af\u0627\u0646"
    ],
    "name:und_x_variant":[
        "Salmang\u0101n"
    ],
    "wof:name":"Salmangun",
    "wof:placetype":"locality"
},
  "geometry": {"coordinates":[59.63486,32.44097],"type":"Point"}
}