{
  "type": "Feature",
  "properties": {
    "gn:admin1_code":"23",
    "gn:asciiname":"Vareh Deh",
    "gn:country_code":"IR",
    "gn:dem":1132,
    "gn:feature_class":"P",
    "gn:feature_code":"PPL",
    "gn:name":"Vareh Deh",
    "gn:population":0,
    "gn:timezone":"Asia/Tehran",
    "iso:country":"IR",
    "name:fas_x_preferred":[
        "\u0648\u0631\u062f\u0647"
    ],
    "name:fas_x_variant":[
        "\u0648\u0631\u0647 \u062f\u0647"
    ],
    "name:und_x_variant":[
        "Varedeh",
        "\u0648\u0631\u062f\u0647",
        "Vareh Deh"
    ],
    "wof:name":"Vareh Deh",
    "wof:placetype":"locality"
},
  "geometry": {"coordinates":[48.2578,33.4484],"type":"Point"}
}