{
  "type": "Feature",
  "properties": {
    "gn:admin1_code":"8",
    "gn:asciiname":"`Aziz Kian",
    "gn:country_code":"IR",
    "gn:dem":76,
    "gn:feature_class":"P",
    "gn:feature_code":"PPL",
    "gn:name":"\u2018Az\u012bz K\u012b\u0101n",
    "gn:population":0,
    "gn:timezone":"Asia/Tehran",
    "iso:country":"IR",
    "name:fas_x_preferred":[
        "\u2018Az\u012bz K\u012b\u0101n"
    ],
    "name:fas_x_variant":[
        "\u2018Az\u012bz K\u012b\u0101n Varzal",
        "\u0639\u0632\u06cc\u0632 \u06a9\u06cc\u0627\u0646",
        "\u0639\u0632\u06cc\u0632\u06a9\u06cc\u0627\u0646"
    ],
    "name:msa_x_preferred":[
        "Aziz Kian"
    ],
    "name:ukr_x_preferred":[
        "\u0410\u0437\u0456\u0437-\u041a\u0456\u044f\u043d"
    ],
    "wof:name":"`Aziz Kian",
    "wof:placetype":"locality"
},
  "geometry": {"coordinates":[49.56467,37.13717000000001],"type":"Point"}
}