{
  "type": "Feature",
  "properties": {
    "gn:admin1_code":"28.0",
    "gn:asciiname":"`Abbasabad",
    "gn:country_code":"IR",
    "gn:dem":1403,
    "gn:feature_class":"P",
    "gn:feature_code":"PPL",
    "gn:name":"\u2018Abb\u0101s\u0101b\u0101d",
    "gn:population":0,
    "gn:timezone":"Asia/Tehran",
    "iso:country":"IR",
    "name:fas_x_preferred":[
        "\u2018Abb\u0101s\u0101b\u0101d"
    ],
    "name:fas_x_variant":[
        "\u0639\u0628\u0627\u0633 \u0622\u0628\u0627\u062f"
    ],
    "wof:name":"`Abbasabad",
    "wof:placetype":"locality"
},
  "geometry": {"coordinates":[53.19308,32.98445],"type":"Point"}
}