{
  "type": "Feature",
  "properties": {
    "gn:admin1_code":"8.0",
    "gn:asciiname":"Tul",
    "gn:country_code":"IR",
    "gn:dem":1695,
    "gn:feature_class":"P",
    "gn:feature_code":"PPL",
    "gn:name":"T\u016bl",
    "gn:population":0,
    "gn:timezone":"Asia/Tehran",
    "iso:country":"IR",
    "name:fas_x_preferred":[
        "\u0162\u016bl"
    ],
    "name:fas_x_variant":[
        "\u062a\u0648\u0644",
        "\u0633\u0644 \u06cc\u0648\u0631\u062f\u06cc"
    ],
    "name:und_x_variant":[
        "T\u016bl",
        "Sel Y\u016brd\u012b"
    ],
    "wof:name":"Tul",
    "wof:placetype":"locality"
},
  "geometry": {"coordinates":[48.6057,37.83302],"type":"Point"}
}