{
  "type": "Feature",
  "properties": {
    "gn:admin1_code":"35.0",
    "gn:asciiname":"Dozbon",
    "gn:country_code":"IR",
    "gn:dem":896,
    "gn:feature_class":"P",
    "gn:feature_code":"PPL",
    "gn:name":"Dozbon",
    "gn:population":0,
    "gn:timezone":"Asia/Tehran",
    "iso:country":"IR",
    "name:fas_x_preferred":[
        "\u062f\u0632\u0628\u0646"
    ],
    "name:fas_x_variant":[
        "\u062f\u0632\u062f\u0628\u0646"
    ],
    "name:und_x_variant":[
        "Dozdbon"
    ],
    "wof:name":"Dozbon",
    "wof:placetype":"locality"
},
  "geometry": {"coordinates":[51.24814,36.31409],"type":"Point"}
}