{
  "type": "Feature",
  "properties": {
    "gn:admin1_code":"42.0",
    "gn:asciiname":"Dargahabad",
    "gn:country_code":"IR",
    "gn:dem":1684,
    "gn:feature_class":"P",
    "gn:feature_code":"PPL",
    "gn:name":"Darg\u0101h\u0101b\u0101d",
    "gn:population":0,
    "gn:timezone":"Asia/Tehran",
    "iso:country":"IR",
    "name:ceb_x_preferred":[
        "Darg\u0101h\u0101b\u0101d"
    ],
    "name:fas_x_preferred":[
        "Darg\u0101h\u0101b\u0101d"
    ],
    "name:fas_x_variant":[
        "\u062f\u0631\u06af\u0627\u0647 \u0622\u0628\u0627\u062f",
        "\u062f\u0631\u06af\u0627\u0647\u200c\u0622\u0628\u0627\u062f"
    ],
    "name:swe_x_preferred":[
        "Darg\u0101h\u0101b\u0101d"
    ],
    "name:und_x_variant":[
        "\u062f\u0631\u06af\u0627\u0647 \u0622\u0628\u0627\u062f"
    ],
    "wof:name":"Dargahabad",
    "wof:placetype":"locality"
},
  "geometry": {"coordinates":[58.111,36.82273],"type":"Point"}
}