{
  "type": "Feature",
  "properties": {
    "gn:admin1_code":"38",
    "gn:asciiname":"Eqbaliyeh",
    "gn:country_code":"IR",
    "gn:dem":1267,
    "gn:feature_class":"P",
    "gn:feature_code":"PPL",
    "gn:name":"Eqb\u0101l\u012byeh",
    "gn:population":0,
    "gn:timezone":"Asia/Tehran",
    "iso:country":"IR",
    "name:ara_x_preferred":[
        "\u0627\u0642\u0628\u0627\u0644\u064a\u0629"
    ],
    "name:azb_x_preferred":[
        "\u0627\u0642\u0628\u0627\u0644\u06cc\u0647"
    ],
    "name:aze_x_preferred":[
        "\u0130qbaliy\u0259"
    ],
    "name:fas_x_preferred":[
        "\u0633\u0644\u0637\u0627\u0646 \u0622\u0628\u0627\u062f \u0627\u0642\u0628\u0627\u0644\u06cc\u0647"
    ],
    "name:fas_x_variant":[
        "Sol\u0163\u0101n\u0101b\u0101d",
        "Sol\u0163\u0101n\u0101b\u0101d-e Eqb\u0101l\u012byeh",
        "\u0627\u0642\u0628\u0627\u0644\u06cc\u0647"
    ],
    "name:hin_x_preferred":[
        "\u0907\u0915\u092c\u093e\u0932\u093f\u092f\u093e\u0939"
    ],
    "name:ita_x_preferred":[
        "Eqbaliyeh"
    ],
    "name:mlg_x_preferred":[
        "Eqbaliyeh"
    ],
    "name:pol_x_preferred":[
        "Eghbalije"
    ],
    "name:rus_x_preferred":[
        "\u0421\u043e\u043b\u044c\u0442\u0430\u043d\u0430\u0431\u0430\u0434"
    ],
    "name:tur_x_preferred":[
        "\u0130kbaliye"
    ],
    "name:und_x_variant":[
        "Sultanabad",
        "Eqb\u0101l\u012byeh"
    ],
    "name:urd_x_preferred":[
        "\u0627\u0642\u0628\u0627\u0644\u06cc\u06c1"
    ],
    "wof:name":"Eqbaliyeh",
    "wof:placetype":"locality"
},
  "geometry": {"coordinates":[49.92499,36.23081],"type":"Point"}
}