{
  "type": "Feature",
  "properties": {
    "gn:admin1_code":"38",
    "gn:asciiname":"Eqbaliyeh",
    "gn:country_code":"IR",
    "gn:dem":1267,
    "gn:feature_class":"P",
    "gn:feature_code":"PPL",
    "gn:name":"Eqb\u0101l\u012byeh",
    "gn:population":0,
    "gn:timezone":"Asia/Tehran",
    "iso:country":"IR",
    "name:fas_x_preferred":[
        "\u0633\u0644\u0637\u0627\u0646 \u0622\u0628\u0627\u062f \u0627\u0642\u0628\u0627\u0644\u06cc\u0647"
    ],
    "name:fas_x_variant":[
        "Sol\u0163\u0101n\u0101b\u0101d",
        "Sol\u0163\u0101n\u0101b\u0101d-e Eqb\u0101l\u012byeh",
        "\u0627\u0642\u0628\u0627\u0644\u06cc\u0647"
    ],
    "name:und_x_variant":[
        "Sultanabad",
        "Eqb\u0101l\u012byeh"
    ],
    "wof:name":"Eqbaliyeh",
    "wof:placetype":"locality"
},
  "geometry": {"coordinates":[49.92499,36.23081],"type":"Point"}
}