{
  "type": "Feature",
  "properties": {
    "gn:admin1_code":"29.0",
    "gn:asciiname":"Khorramshahi",
    "gn:country_code":"IR",
    "gn:dem":1657,
    "gn:feature_class":"P",
    "gn:feature_code":"PPL",
    "gn:name":"Khorramsh\u0101h\u012b",
    "gn:population":0,
    "gn:timezone":"Asia/Tehran",
    "iso:country":"IR",
    "name:fas_x_preferred":[
        "\u062e\u0631\u0645\u0634\u0627\u0647\u06cc"
    ],
    "name:fas_x_variant":[
        "Khorramsh\u0101h\u012b"
    ],
    "name:pol_x_preferred":[
        "Chorramszahi"
    ],
    "wof:name":"Khorramshahi",
    "wof:placetype":"locality"
},
  "geometry": {"coordinates":[57.6438,28.9665],"type":"Point"}
}