{
  "type": "Feature",
  "properties": {
    "gn:admin1_code":"32",
    "gn:asciiname":"Paruq",
    "gn:country_code":"IR",
    "gn:dem":1441,
    "gn:feature_class":"P",
    "gn:feature_code":"PPL",
    "gn:name":"P\u0101r\u016bq",
    "gn:population":0,
    "gn:timezone":"Asia/Tehran",
    "iso:country":"IR",
    "name:fas_x_preferred":[
        "P\u0101r\u016bq"
    ],
    "wof:name":"Paruq",
    "wof:placetype":"locality"
},
  "geometry": {"coordinates":[48.16667,38.28333],"type":"Point"}
}