{
  "type": "Feature",
  "properties": {
    "gn:admin1_code":"4.0",
    "gn:asciiname":"Chah Hoseyni",
    "gn:country_code":"IR",
    "gn:dem":468,
    "gn:feature_class":"P",
    "gn:feature_code":"PPL",
    "gn:name":"Ch\u0101h \u1e28oseyn\u012b",
    "gn:population":0,
    "gn:timezone":"Asia/Tehran",
    "iso:country":"IR",
    "name:fas_x_preferred":[
        "\u0634\u0627\u0647 \u062d\u064f\u0633\u0650\u064a\u0646"
    ],
    "name:fas_x_variant":[
        "\u0686\u0627\u0647 \u062d\u064f\u0633\u0650\u064a\u0646",
        "Sh\u0101h \u1e28oseyn",
        "Ch\u0101h \u1e28oseyn\u012b",
        "\u0686\u0627\u0647 \u062d\u0633\u06cc\u0646\u06cc",
        "Ch\u0101h Husaini",
        "Ch\u0101h \u1e28oseyn"
    ],
    "wof:name":"Chah Hoseyni",
    "wof:placetype":"locality"
},
  "geometry": {"coordinates":[60.16866,27.19845],"type":"Point"}
}