{
  "type": "Feature",
  "properties": {
    "gn:admin1_code":"8.0",
    "gn:asciiname":"Talabown",
    "gn:country_code":"IR",
    "gn:dem":1310,
    "gn:feature_class":"P",
    "gn:feature_code":"PPL",
    "gn:name":"T\u0101l\u0101bown",
    "gn:population":0,
    "gn:timezone":"Asia/Tehran",
    "iso:country":"IR",
    "name:fas_x_preferred":[
        "Tal\u0101bon"
    ],
    "name:fas_x_variant":[
        "\u062a\u0644\u0627\u0628\u0646",
        "\u062a\u0627\u0644\u0627\u0628\u0648\u0646"
    ],
    "name:und_x_variant":[
        "\u062a\u0644\u0627\u0628\u0646",
        "T\u0101l\u0101bown"
    ],
    "wof:name":"Talabown",
    "wof:placetype":"locality"
},
  "geometry": {"coordinates":[50.30442,36.75471],"type":"Point"}
}