{
  "type": "Feature",
  "properties": {
    "gn:admin1_code":"42",
    "gn:asciiname":"Haqurudi",
    "gn:country_code":"IR",
    "gn:dem":629,
    "gn:feature_class":"P",
    "gn:feature_code":"PPL",
    "gn:name":"\u1e28aq\u016br\u016bd\u012b",
    "gn:population":0,
    "gn:timezone":"Asia/Tehran",
    "iso:country":"IR",
    "name:ara_x_preferred":[
        "\u062d\u0642 \u0648\u0631\u062f\u064a"
    ],
    "name:ceb_x_preferred":[
        "\u1e28aq\u016br\u016bd\u012b"
    ],
    "name:fas_x_preferred":[
        "\u062d\u0642\u0648\u0631\u0648\u062f\u06cc"
    ],
    "name:fas_x_variant":[
        "\u1e28aqverd\u012b",
        "\u1e28aq\u016br\u016bd\u012b",
        "\u062d\u0642 \u0648\u0631\u062f\u06cc"
    ],
    "name:kur_x_preferred":[
        "Heqv\u00eard\u00ee"
    ],
    "name:swe_x_preferred":[
        "\u1e28aq\u016br\u016bd\u012b"
    ],
    "wof:name":"Haqurudi",
    "wof:placetype":"locality"
},
  "geometry": {"coordinates":[59.05623000000001,37.38443],"type":"Point"}
}