{
  "type": "Feature",
  "properties": {
    "gn:admin1_code":"42",
    "gn:asciiname":"Ma`danabad",
    "gn:country_code":"IR",
    "gn:dem":1121,
    "gn:feature_class":"P",
    "gn:feature_code":"PPL",
    "gn:name":"Ma\u2018dan\u0101b\u0101d",
    "gn:population":0,
    "gn:timezone":"Asia/Tehran",
    "iso:country":"IR",
    "name:fas_x_preferred":[
        "\u0645\u0639\u06cc\u0646 \u0622\u0628\u0627\u062f"
    ],
    "name:fas_x_variant":[
        "Mo\u2018\u012bn\u0101b\u0101d",
        "\u0645\u0639\u062f\u0646 \u0622\u0628\u0627\u062f"
    ],
    "name:und_x_variant":[
        "Ma\u2018dan\u0101b\u0101d"
    ],
    "wof:name":"Ma`danabad",
    "wof:placetype":"locality"
},
  "geometry": {"coordinates":[58.72407,36.13047],"type":"Point"}
}