{
  "type": "Feature",
  "properties": {
    "gn:admin1_code":"10",
    "gn:asciiname":"Nasrian",
    "gn:cc2":"IR",
    "gn:country_code":"IR",
    "gn:dem":358,
    "gn:feature_class":"P",
    "gn:feature_code":"PPL",
    "gn:name":"Na\u015fr\u012b\u0101n",
    "gn:population":0,
    "gn:timezone":"Asia/Tehran",
    "iso:country":"IR",
    "name:fas_x_preferred":[
        "\u0646\u064e\u0635\u064a\u0631\u064a\u0627\u0646"
    ],
    "name:fas_x_variant":[
        "\u0646\u064e\u0633\u064a\u0631\u064a\u064e\u0651\u0646",
        "\u067e\u0627\u0633\u06af\u0627\u0647\u0650 \u0646\u064e\u0635\u0631\u0650\u064a\u0627\u0646",
        "Na\u015fr\u012b\u0101n",
        "\u0646\u0635\u0631\u064a\u0627\u0646"
    ],
    "name:und_x_variant":[
        "P\u0101sg\u0101h-e Na\u015frey\u0101n",
        "Na\u015f\u012br\u012b\u0101n",
        "Nas\u012br\u012byan"
    ],
    "wof:name":"Nasrian",
    "wof:placetype":"locality"
},
  "geometry": {"coordinates":[46.88167,32.84389],"type":"Point"}
}