{
  "type": "Feature",
  "properties": {
    "gn:admin1_code":"38",
    "gn:asciiname":"Kamalabad",
    "gn:country_code":"IR",
    "gn:dem":1214,
    "gn:feature_class":"P",
    "gn:feature_code":"PPL",
    "gn:name":"Kam\u0101l\u0101b\u0101d",
    "gn:population":0,
    "gn:timezone":"Asia/Tehran",
    "iso:country":"IR",
    "name:ara_x_preferred":[
        "\u0643\u0645\u0627\u0644 \u0623\u0628\u0627\u062f"
    ],
    "name:fas_x_preferred":[
        "\u0643\u0645\u0627\u0644 \u0622\u0628\u0627\u062f"
    ],
    "name:fas_x_variant":[
        "Kam\u0101l\u0101b\u0101d",
        "\u06a9\u0645\u0627\u0644\u200c\u0622\u0628\u0627\u062f"
    ],
    "wof:name":"Kamalabad",
    "wof:placetype":"locality"
},
  "geometry": {"coordinates":[50.0572,36.1407],"type":"Point"}
}