{
  "type": "Feature",
  "properties": {
    "gn:admin1_code":"16",
    "gn:asciiname":"Darvishan",
    "gn:country_code":"IR",
    "gn:dem":1450,
    "gn:feature_class":"P",
    "gn:feature_code":"PPL",
    "gn:name":"Darv\u012bsh\u0101n",
    "gn:population":0,
    "gn:timezone":"Asia/Tehran",
    "iso:country":"IR",
    "name:fas_x_preferred":[
        "\u062f\u064e\u0631\u0650\u0651\u0647 \u0634\u0627\u0646"
    ],
    "name:fas_x_variant":[
        "\u062f\u0631\u0648\u06cc\u0634\u0627\u0646",
        "Darv\u012bsh\u0101n"
    ],
    "name:und_x_variant":[
        "Darreh Sh\u0101n"
    ],
    "wof:name":"Darvishan",
    "wof:placetype":"locality"
},
  "geometry": {"coordinates":[46.8537,35.1541],"type":"Point"}
}