{
  "type": "Feature",
  "properties": {
    "gn:admin1_code":"42",
    "gn:asciiname":"Chah-e Musa",
    "gn:country_code":"IR",
    "gn:dem":1226,
    "gn:feature_class":"P",
    "gn:feature_code":"PPL",
    "gn:name":"Ch\u0101h-e M\u016bs\u00e1",
    "gn:population":0,
    "gn:timezone":"Asia/Tehran",
    "iso:country":"IR",
    "name:fas_x_preferred":[
        "Ch\u0101h-e M\u016bs\u00e1"
    ],
    "name:fas_x_variant":[
        "\u0686\u0627\u0647 \u0645\u0648\u0633\u06cc"
    ],
    "name:und_x_variant":[
        "\u0686\u0627\u0647 \u0645\u0648\u0633\u06cc"
    ],
    "wof:name":"Chah-e Musa",
    "wof:placetype":"locality"
},
  "geometry": {"coordinates":[58.31981,35.91388],"type":"Point"}
}