{
  "type": "Feature",
  "properties": {
    "gn:admin1_code":"33.0",
    "gn:asciiname":"Bashab",
    "gn:country_code":"IR",
    "gn:dem":1009,
    "gn:feature_class":"P",
    "gn:feature_code":"PPL",
    "gn:name":"Bash\u0101b",
    "gn:population":0,
    "gn:timezone":"Asia/Tehran",
    "iso:country":"IR",
    "name:fas_x_preferred":[
        "\u0628\u0634\u0627\u0628"
    ],
    "name:fas_x_variant":[
        "Bash\u0101b"
    ],
    "wof:name":"Bashab",
    "wof:placetype":"locality"
},
  "geometry": {"coordinates":[47.1295,39.0763],"type":"Point"}
}