{
  "type": "Feature",
  "properties": {
    "gn:admin1_code":"15",
    "gn:asciiname":"Fe`liyeh",
    "gn:country_code":"IR",
    "gn:dem":-2,
    "gn:feature_class":"P",
    "gn:feature_code":"PPL",
    "gn:name":"Fe\u2018l\u012byeh",
    "gn:population":0,
    "gn:timezone":"Asia/Tehran",
    "iso:country":"IR",
    "name:fas_x_preferred":[
        "\u0641\u0639\u0644\u06cc\u0651\u0647"
    ],
    "name:fas_x_variant":[
        "Feyl\u012byeh",
        "Fe\u2018l\u012byeh"
    ],
    "name:und_x_variant":[
        "Fail\u012bya",
        "F\u012bl\u012byeh"
    ],
    "wof:name":"Fe`liyeh",
    "wof:placetype":"locality"
},
  "geometry": {"coordinates":[48.1289,30.4514],"type":"Point"}
}