{
  "type": "Feature",
  "properties": {
    "gn:admin1_code":"34",
    "gn:asciiname":"Jamalak",
    "gn:country_code":"IR",
    "gn:dem":1582,
    "gn:feature_class":"P",
    "gn:feature_code":"PPL",
    "gn:name":"Jam\u0101lak",
    "gn:population":0,
    "gn:timezone":"Asia/Tehran",
    "iso:country":"IR",
    "name:fas_x_preferred":[
        "\u062c\u0645\u0627\u0644\u0643"
    ],
    "name:fas_x_variant":[
        "Jam\u0101lak"
    ],
    "wof:name":"Jamalak",
    "wof:placetype":"locality"
},
  "geometry": {"coordinates":[49.76596,35.10464],"type":"Point"}
}