{
  "type": "Feature",
  "properties": {
    "gn:admin1_code":"33",
    "gn:asciiname":"Yengiabad-e Cha'i",
    "gn:country_code":"IR",
    "gn:dem":1077,
    "gn:feature_class":"P",
    "gn:feature_code":"PPL",
    "gn:name":"Yeng\u012b\u0101b\u0101d-e Ch\u0101\u2019\u012b",
    "gn:population":0,
    "gn:timezone":"Asia/Tehran",
    "iso:country":"IR",
    "name:azb_x_preferred":[
        "\u06cc\u0646\u06af\u200c\u0622\u0628\u0627\u062f\u0686\u0627\u06cc"
    ],
    "name:ceb_x_preferred":[
        "Yeng\u012b\u0101b\u0101d-e Ch\u0101'\u012b"
    ],
    "name:fas_x_preferred":[
        "\u06cc\u0646\u06af\u06cc \u0622\u0628\u0627\u062f \u0686\u0627\u0626\u06cc"
    ],
    "name:fas_x_variant":[
        "Yeng\u0101b\u0101d-e Ch\u0101y",
        "\u06cc\u0646\u06af\u200c\u0622\u0628\u0627\u062f \u0686\u0627\u06cc"
    ],
    "name:msa_x_preferred":[
        "Yengabad-e Chay"
    ],
    "name:swe_x_preferred":[
        "Yeng\u012b\u0101b\u0101d-e Ch\u0101'\u012b"
    ],
    "name:und_x_variant":[
        "Yeng\u012b\u0101b\u0101d-e Ch\u0101\u2019\u012b"
    ],
    "name:urd_x_preferred":[
        "\u06cc\u0646\u06af \u0622\u0628\u0627\u062f-\u0686\u06d2"
    ],
    "wof:name":"Yengiabad-e Cha'i",
    "wof:placetype":"locality"
},
  "geometry": {"coordinates":[47.6909,37.3911],"type":"Point"}
}