{
  "type": "Feature",
  "properties": {
    "gn:admin1_code":"35.0",
    "gn:asciiname":"Teli Andun",
    "gn:country_code":"IR",
    "gn:dem":-17,
    "gn:feature_class":"P",
    "gn:feature_code":"PPL",
    "gn:name":"Tel\u012b And\u016bn",
    "gn:population":0,
    "gn:timezone":"Asia/Tehran",
    "iso:country":"IR",
    "name:fas_x_preferred":[
        "Tel\u012b And\u016bn"
    ],
    "name:fas_x_variant":[
        "\u062a\u0644\u06cc \u0627\u0646\u062f\u0648\u0646"
    ],
    "wof:name":"Teli Andun",
    "wof:placetype":"locality"
},
  "geometry": {"coordinates":[52.75,36.681],"type":"Point"}
}