{
  "type": "Feature",
  "properties": {
    "gn:admin1_code":"8.0",
    "gn:asciiname":"Bowdagh Mahalleh",
    "gn:country_code":"IR",
    "gn:dem":-15,
    "gn:feature_class":"P",
    "gn:feature_code":"PPL",
    "gn:name":"Bowd\u0101gh Ma\u1e29alleh",
    "gn:population":0,
    "gn:timezone":"Asia/Tehran",
    "iso:country":"IR",
    "name:fas_x_preferred":[
        "\u0628\u062f\u0627\u063a \u0645\u062d\u0644\u0647"
    ],
    "name:fas_x_variant":[
        "Bod\u0101gh Ma\u1e29alleh",
        "\u0628\u0648\u062f\u0627\u063a \u0645\u062d\u0644\u0647",
        "\u0622\u0644\u0627\u0644\u0627\u0646"
    ],
    "name:und_x_variant":[
        "Bowd\u0101gh Ma\u1e29alleh",
        "\u0100l\u0101l\u0101n"
    ],
    "wof:name":"Bowdagh Mahalleh",
    "wof:placetype":"locality"
},
  "geometry": {"coordinates":[48.99781,37.73024],"type":"Point"}
}