{
  "type": "Feature",
  "properties": {
    "gn:admin1_code":"28.0",
    "gn:asciiname":"Chalian",
    "gn:country_code":"IR",
    "gn:dem":2525,
    "gn:feature_class":"P",
    "gn:feature_code":"PPL",
    "gn:name":"Ch\u0101l\u012b\u0101n",
    "gn:population":0,
    "gn:timezone":"Asia/Tehran",
    "iso:country":"IR",
    "name:fas_x_preferred":[
        "Ch\u0101l\u012b\u0101n"
    ],
    "name:fas_x_variant":[
        "\u0686\u0627\u0644\u06cc\u0627\u0646"
    ],
    "wof:name":"Chalian",
    "wof:placetype":"locality"
},
  "geometry": {"coordinates":[50.00664,32.92294],"type":"Point"}
}