{
  "type": "Feature",
  "properties": {
    "gn:admin1_code":"22",
    "gn:asciiname":"Maqatel",
    "gn:country_code":"IR",
    "gn:dem":35,
    "gn:feature_class":"P",
    "gn:feature_code":"PPL",
    "gn:name":"Maq\u0101\u0163el",
    "gn:population":0,
    "gn:timezone":"Asia/Tehran",
    "iso:country":"IR",
    "name:ara_x_preferred":[
        "\u0645\u0642\u0627\u062a\u0644"
    ],
    "name:fas_x_preferred":[
        "\u0645\u0642\u0627\u062a\u0644"
    ],
    "name:fas_x_variant":[
        "Maq\u0101tel",
        "\u0645\u0642\u0627\u0637\u0644"
    ],
    "name:msa_x_preferred":[
        "Maqatel"
    ],
    "name:und_x_variant":[
        "Moq\u0101tel",
        "Maq\u0101\u0163el"
    ],
    "wof:name":"Maqatel",
    "wof:placetype":"locality"
},
  "geometry": {"coordinates":[51.3303,28.4219],"type":"Point"}
}