{
  "type": "Feature",
  "properties": {
    "gn:admin1_code":"38",
    "gn:asciiname":"Zia'abad",
    "gn:country_code":"IR",
    "gn:dem":1400,
    "gn:feature_class":"P",
    "gn:feature_code":"PPL",
    "gn:name":"\u1e94\u012b\u0101\u2019\u0101b\u0101d",
    "gn:population":0,
    "gn:timezone":"Asia/Tehran",
    "iso:country":"IR",
    "name:ara_x_preferred":[
        "\u0636\u064a\u0627\u0621\u0623\u0628\u0627\u062f"
    ],
    "name:aze_x_preferred":[
        "Ziyaabad"
    ],
    "name:ceb_x_preferred":[
        "\u1e94\u012b\u0101'\u0101b\u0101d"
    ],
    "name:fas_x_preferred":[
        "\u0636\u06cc\u0627\u0621 \u0622\u0628\u0627\u062f"
    ],
    "name:fas_x_variant":[
        "\u1e94\u012b\u0101\u2019\u0101b\u0101d",
        "\u0636\u06cc\u0627 \u0622\u0628\u0627\u062f",
        "\u0636\u06cc\u0627\u0621\u0622\u0628\u0627\u062f"
    ],
    "name:ita_x_preferred":[
        "Zeya'Abad"
    ],
    "name:mlg_x_preferred":[
        "Ziaabad"
    ],
    "name:rus_x_preferred":[
        "\u0417\u0438\u0430\u0430\u0431\u0430\u0434"
    ],
    "name:swe_x_preferred":[
        "\u1e94\u012b\u0101'\u0101b\u0101d"
    ],
    "name:tur_x_preferred":[
        "Ziyaabad"
    ],
    "name:und_x_variant":[
        "Shahr-e Shaq\u0101yeq",
        "\u1e94ey\u0101\u2019\u0101b\u0101d",
        "Z\u012bya Abad",
        "\u1e94\u012b\u0101\u0101b\u0101d"
    ],
    "wof:name":"Zia'abad",
    "wof:placetype":"locality"
},
  "geometry": {"coordinates":[49.44638,35.99325],"type":"Point"}
}