{
  "type": "Feature",
  "properties": {
    "gn:admin1_code":"8.0",
    "gn:asciiname":"Tu Sar Bandan",
    "gn:country_code":"IR",
    "gn:dem":2,
    "gn:feature_class":"P",
    "gn:feature_code":"PPL",
    "gn:name":"T\u016b Sar Band\u0101n",
    "gn:population":0,
    "gn:timezone":"Asia/Tehran",
    "iso:country":"IR",
    "name:fas_x_preferred":[
        "T\u016b Sar Band\u0101n"
    ],
    "name:fas_x_variant":[
        "\u062a\u0648 \u0633\u0631 \u0628\u0646\u062f\u0627\u0646"
    ],
    "name:und_x_variant":[
        "\u062a\u0648 \u0633\u0631 \u0628\u0646\u062f\u0627\u0646"
    ],
    "wof:name":"Tu Sar Bandan",
    "wof:placetype":"locality"
},
  "geometry": {"coordinates":[49.66208,37.25771],"type":"Point"}
}