{
  "type": "Feature",
  "properties": {
    "gn:admin1_code":"13",
    "gn:asciiname":"Jelugireh-ye Sofla",
    "gn:country_code":"IR",
    "gn:dem":1315,
    "gn:feature_class":"P",
    "gn:feature_code":"PPL",
    "gn:name":"Jel\u016bg\u012breh-ye Sofl\u00e1",
    "gn:population":0,
    "gn:timezone":"Asia/Tehran",
    "iso:country":"IR",
    "name:fas_x_preferred":[
        "\u062c\u0644\u0648\u06af\u06cc\u0631\u0647 \u0633\u0641\u0644\u0649"
    ],
    "name:fas_x_variant":[
        "Jelog\u012breh-ye Sofl\u00e1",
        "Jel\u016bg\u012breh-ye Sofl\u00e1"
    ],
    "wof:name":"Jelugireh-ye Sofla",
    "wof:placetype":"locality"
},
  "geometry": {"coordinates":[46.8559,34.5903],"type":"Point"}
}