{
  "type": "Feature",
  "properties": {
    "gn:admin1_code":"4.0",
    "gn:asciiname":"Naserabad",
    "gn:country_code":"IR",
    "gn:dem":1,
    "gn:feature_class":"P",
    "gn:feature_code":"PPL",
    "gn:name":"N\u0101\u015fer\u0101b\u0101d",
    "gn:population":0,
    "gn:timezone":"Asia/Tehran",
    "iso:country":"IR",
    "name:fas_x_preferred":[
        "N\u0101\u015fer\u0101b\u0101d"
    ],
    "wof:name":"Naserabad",
    "wof:placetype":"locality"
},
  "geometry": {"coordinates":[60.45,25.43333],"type":"Point"}
}