{
  "type": "Feature",
  "properties": {
    "gn:admin1_code":"15",
    "gn:asciiname":"Sabz Ab",
    "gn:country_code":"IR",
    "gn:dem":134,
    "gn:feature_class":"P",
    "gn:feature_code":"PPL",
    "gn:name":"Sabz \u0100b",
    "gn:population":0,
    "gn:timezone":"Asia/Tehran",
    "iso:country":"IR",
    "name:ceb_x_preferred":[
        "Sabz \u0100b"
    ],
    "name:fas_x_preferred":[
        "\u0633\u0628\u0632 \u0622\u0628"
    ],
    "name:fas_x_variant":[
        "Sabz \u0100b",
        "\u0633\u0628\u0632\u0622\u0628"
    ],
    "name:swe_x_preferred":[
        "Sabz \u0100b"
    ],
    "name:urd_x_preferred":[
        "\u0633\u0628\u0632 \u0627\u0628"
    ],
    "wof:name":"Sabz Ab",
    "wof:placetype":"locality"
},
  "geometry": {"coordinates":[48.66387,32.29476],"type":"Point"}
}