{
  "type": "Feature",
  "properties": {
    "gn:admin1_code":"29",
    "gn:asciiname":"Gas Peni Gun",
    "gn:country_code":"IR",
    "gn:dem":2470,
    "gn:feature_class":"P",
    "gn:feature_code":"PPL",
    "gn:name":"Gas Pen\u012b G\u016bn",
    "gn:population":0,
    "gn:timezone":"Asia/Tehran",
    "iso:country":"IR",
    "name:fas_x_preferred":[
        "\u06af\u0633 \u067e\u0646\u06cc \u06af\u0648\u0646"
    ],
    "name:fas_x_variant":[
        "Gas Pen\u012b G\u016bn"
    ],
    "wof:name":"Gas Peni Gun",
    "wof:placetype":"locality"
},
  "geometry": {"coordinates":[57.6172,29.0348],"type":"Point"}
}