{
  "type": "Feature",
  "properties": {
    "gn:admin1_code":"7",
    "gn:asciiname":"Bayegan",
    "gn:country_code":"IR",
    "gn:dem":1350,
    "gn:feature_class":"P",
    "gn:feature_code":"PPL",
    "gn:name":"B\u0101yeg\u0101n",
    "gn:population":0,
    "gn:timezone":"Asia/Tehran",
    "iso:country":"IR",
    "name:fas_x_preferred":[
        "\u0628\u0627\u06cc\u06af\u0627\u0646"
    ],
    "name:fas_x_variant":[
        "B\u0101yeg\u0101n"
    ],
    "name:und_x_variant":[
        "B\u0101yg\u0101n"
    ],
    "wof:name":"Bayegan",
    "wof:placetype":"locality"
},
  "geometry": {"coordinates":[52.4249,28.8646],"type":"Point"}
}