{
  "type": "Feature",
  "properties": {
    "gn:admin1_code":"26",
    "gn:asciiname":"Sowhanak",
    "gn:country_code":"IR",
    "gn:dem":1814,
    "gn:feature_class":"P",
    "gn:feature_code":"PPL",
    "gn:name":"Sowh\u0101nak",
    "gn:population":0,
    "gn:timezone":"Asia/Tehran",
    "iso:country":"IR",
    "name:fas_x_preferred":[
        "\u0633\u0648\u0647\u0627\u0646\u06a9"
    ],
    "name:fas_x_variant":[
        "\u0634\u0648\u0647\u0627\u0646\u064e\u0643",
        "Sowh\u0101nak"
    ],
    "name:und_x_variant":[
        "Sh\u016bh\u0101nak",
        "S\u016bh\u0101nak"
    ],
    "wof:name":"Sowhanak",
    "wof:placetype":"locality"
},
  "geometry": {"coordinates":[51.5334,35.8035],"type":"Point"}
}