{
  "type": "Feature",
  "properties": {
    "gn:admin1_code":"28",
    "gn:asciiname":"Qal`eh-ye Baba Mohammad",
    "gn:country_code":"IR",
    "gn:dem":2728,
    "gn:feature_class":"P",
    "gn:feature_code":"PPL",
    "gn:name":"Qal\u2018eh-ye B\u0101b\u0101 Mo\u1e29ammad",
    "gn:population":0,
    "gn:timezone":"Asia/Tehran",
    "iso:country":"IR",
    "name:fas_x_preferred":[
        "Qal\u2018eh-ye B\u0101b\u0101 Mo\u1e29ammad"
    ],
    "name:fas_x_variant":[
        "\u0642\u0644\u0639\u0647 \u0628\u0627\u0628\u0627 \u0645\u062d\u0645\u0651\u062f"
    ],
    "name:und_x_variant":[
        "Qal\u2018eh B\u0101b\u0101 Mohammad",
        "Ghal\u2018eh Baba Mo\u1e29ammad"
    ],
    "wof:name":"Qal`eh-ye Baba Mohammad",
    "wof:placetype":"locality"
},
  "geometry": {"coordinates":[50.41511,33.16764000000001],"type":"Point"}
}