{
  "type": "Feature",
  "properties": {
    "gn:admin1_code":"32",
    "gn:asciiname":"Ayaz",
    "gn:country_code":"IR",
    "gn:dem":896,
    "gn:feature_class":"P",
    "gn:feature_code":"PPL",
    "gn:name":"Ay\u0101z",
    "gn:population":0,
    "gn:timezone":"Asia/Tehran",
    "iso:country":"IR",
    "name:fas_x_preferred":[
        "\u0627\u06cc\u0627\u0632"
    ],
    "name:fas_x_variant":[
        "Ay\u0101z"
    ],
    "wof:name":"Ayaz",
    "wof:placetype":"locality"
},
  "geometry": {"coordinates":[47.9969,39.037],"type":"Point"}
}