{
  "type": "Feature",
  "properties": {
    "gn:admin1_code":"41.0",
    "gn:asciiname":"Badamestan",
    "gn:country_code":"IR",
    "gn:dem":1721,
    "gn:feature_class":"P",
    "gn:feature_code":"PPL",
    "gn:name":"B\u0101d\u0101mest\u0101n",
    "gn:population":0,
    "gn:timezone":"Asia/Tehran",
    "iso:country":"IR",
    "name:fas_x_preferred":[
        "B\u0101d\u0101mest\u0101n"
    ],
    "name:fas_x_variant":[
        "\u0628\u0627\u062f\u0627\u0645\u0633\u062a\u0627\u0646"
    ],
    "wof:name":"Badamestan",
    "wof:placetype":"locality"
},
  "geometry": {"coordinates":[60.02454,33.16583],"type":"Point"}
}