{
  "type": "Feature",
  "properties": {
    "gn:admin1_code":"38.0",
    "gn:asciiname":"Zamgeh-ye Mir Asneh",
    "gn:country_code":"IR",
    "gn:dem":687,
    "gn:feature_class":"P",
    "gn:feature_code":"PPL",
    "gn:name":"Zamgeh-ye M\u012br \u0100s\u0304neh",
    "gn:population":0,
    "gn:timezone":"Asia/Tehran",
    "iso:country":"IR",
    "name:fas_x_preferred":[
        "Zamgeh-ye M\u012br \u0100s\u0304neh"
    ],
    "name:fas_x_variant":[
        "\u0632\u0645\u06af\u0647 \u0645\u06cc\u0631 \u0622\u062b\u0646\u0647"
    ],
    "wof:name":"Zamgeh-ye Mir Asneh",
    "wof:placetype":"locality"
},
  "geometry": {"coordinates":[49.65206,36.57227],"type":"Point"}
}