{
  "type": "Feature",
  "properties": {
    "gn:admin1_code":"42.0",
    "gn:asciiname":"Mir Hoseyn",
    "gn:country_code":"IR",
    "gn:dem":1342,
    "gn:feature_class":"P",
    "gn:feature_code":"PPL",
    "gn:name":"M\u012br \u1e28oseyn",
    "gn:population":0,
    "gn:timezone":"Asia/Tehran",
    "iso:country":"IR",
    "name:fas_x_preferred":[
        "M\u012br \u1e28oseyn"
    ],
    "name:fas_x_variant":[
        "\u0645\u064a\u0631 \u062d\u0633\u064a\u0646"
    ],
    "name:und_x_variant":[
        "\u0645\u064a\u0631 \u062d\u0633\u064a\u0646"
    ],
    "wof:name":"Mir Hoseyn",
    "wof:placetype":"locality"
},
  "geometry": {"coordinates":[57.66438,36.3291],"type":"Point"}
}