{
  "type": "Feature",
  "properties": {
    "gn:admin1_code":"22",
    "gn:asciiname":"Shoveh",
    "gn:cc2":"IR",
    "gn:country_code":"IR",
    "gn:dem":85,
    "gn:feature_class":"P",
    "gn:feature_code":"PPL",
    "gn:name":"Shoveh",
    "gn:population":0,
    "gn:timezone":"Asia/Tehran",
    "iso:country":"IR",
    "name:fas_x_preferred":[
        "\u0634\u064f\u0648\u0650\u0647"
    ],
    "name:fas_x_variant":[
        "\u0634\u0648\u0650\u0646",
        "\u0634\u0648\u0648\u0650\u0647"
    ],
    "name:und_x_variant":[
        "Sh\u016bveh",
        "Sh\u016ben",
        "Shoveh"
    ],
    "wof:name":"Shoveh",
    "wof:placetype":"locality"
},
  "geometry": {"coordinates":[51.22361,29.09944],"type":"Point"}
}