{
  "type": "Feature",
  "properties": {
    "gn:admin1_code":"15",
    "gn:asciiname":"Hayavi",
    "gn:cc2":"IR",
    "gn:country_code":"IR",
    "gn:dem":145,
    "gn:feature_class":"P",
    "gn:feature_code":"PPL",
    "gn:name":"\u1e28ay\u0101v\u012b",
    "gn:population":0,
    "gn:timezone":"Asia/Tehran",
    "iso:country":"IR",
    "name:fas_x_preferred":[
        "\u1e28ay\u0101v\u012b"
    ],
    "name:und_x_variant":[
        "\u1e28ay\u0101y\u012b"
    ],
    "wof:name":"Hayavi",
    "wof:placetype":"locality"
},
  "geometry": {"coordinates":[47.95111,32.12167],"type":"Point"}
}