{
  "type": "Feature",
  "properties": {
    "gn:admin1_code":"7",
    "gn:asciiname":"Ab Bid-e Bajgah",
    "gn:country_code":"IR",
    "gn:dem":1269,
    "gn:feature_class":"P",
    "gn:feature_code":"PPL",
    "gn:name":"\u0100b B\u012bd-e B\u0101jg\u0101h",
    "gn:population":0,
    "gn:timezone":"Asia/Tehran",
    "iso:country":"IR",
    "name:fas_x_preferred":[
        "\u0100b B\u012bd-e B\u0101jg\u0101h"
    ],
    "wof:name":"Ab Bid-e Bajgah",
    "wof:placetype":"locality"
},
  "geometry": {"coordinates":[51.55,30.15],"type":"Point"}
}