{
  "type": "Feature",
  "properties": {
    "gn:admin1_code":"1.0",
    "gn:asciiname":"Hendvar",
    "gn:country_code":"IR",
    "gn:dem":1059,
    "gn:feature_class":"P",
    "gn:feature_code":"PPL",
    "gn:name":"Hendvar",
    "gn:population":0,
    "gn:timezone":"Asia/Tehran",
    "iso:country":"IR",
    "name:azb_x_preferred":[
        "\u0647\u06cc\u0646\u062f\u0648\u0631"
    ],
    "name:aze_x_preferred":[
        "H\u0259ndvar"
    ],
    "name:ceb_x_preferred":[
        "Hendvar"
    ],
    "name:fas_x_preferred":[
        "\u0647\u0650\u0646\u062f\u0648\u064e\u0631"
    ],
    "name:fas_x_variant":[
        "\u0647\u0646\u062f\u0648\u0631"
    ],
    "name:msa_x_preferred":[
        "Hendvar"
    ],
    "name:swe_x_preferred":[
        "Hendvar"
    ],
    "wof:name":"Hendvar",
    "wof:placetype":"locality"
},
  "geometry": {"coordinates":[44.6142,39.2696],"type":"Point"}
}