{
  "type": "Feature",
  "properties": {
    "gn:admin1_code":"15",
    "gn:asciiname":"Mo`ayyed Samer",
    "gn:country_code":"IR",
    "gn:dem":34,
    "gn:feature_class":"P",
    "gn:feature_code":"PPL",
    "gn:name":"Mo\u2018ayyed \u015e\u0101mer",
    "gn:population":0,
    "gn:timezone":"Asia/Tehran",
    "iso:country":"IR",
    "name:fas_x_preferred":[
        "Mo\u2018ayyed \u015e\u0101mer"
    ],
    "wof:name":"Mo`ayyed Samer",
    "wof:placetype":"locality"
},
  "geometry": {"coordinates":[48.445,31.7975],"type":"Point"}
}