{
  "type": "Feature",
  "properties": {
    "gn:admin1_code":"34",
    "gn:asciiname":"Dehpul",
    "gn:country_code":"IR",
    "gn:dem":1874,
    "gn:feature_class":"P",
    "gn:feature_code":"PPL",
    "gn:name":"Dehp\u016bl",
    "gn:population":0,
    "gn:timezone":"Asia/Tehran",
    "iso:country":"IR",
    "name:fas_x_preferred":[
        "Dehb\u016bl"
    ],
    "name:fas_x_variant":[
        "\u062f\u0647\u067e\u0648\u0644",
        "\u062f\u0647 \u067e\u0648\u0644"
    ],
    "name:ukr_x_preferred":[
        "\u0414\u0435\u0433\u043f\u0443\u043b\u044c"
    ],
    "name:und_x_variant":[
        "Deh F\u016bl",
        "Dehpol",
        "Deh P\u012bl",
        "Dehp\u016bl"
    ],
    "wof:name":"Dehpul",
    "wof:placetype":"locality"
},
  "geometry": {"coordinates":[49.44572,33.95242],"type":"Point"}
}