{
  "type": "Feature",
  "properties": {
    "gn:admin1_code":"7",
    "gn:asciiname":"Mahmudabad",
    "gn:country_code":"IR",
    "gn:dem":1636,
    "gn:feature_class":"P",
    "gn:feature_code":"PPL",
    "gn:name":"Ma\u1e29m\u016bd\u0101b\u0101d",
    "gn:population":0,
    "gn:timezone":"Asia/Tehran",
    "iso:country":"IR",
    "name:fas_x_preferred":[
        "\u0645\u062d\u0645\u0648\u062f \u0622\u0628\u0627\u062f"
    ],
    "name:fas_x_variant":[
        "Ma\u1e29m\u016bd\u0101b\u0101d",
        "\u0645\u062d\u0645\u0648\u062f \u0622\u0628\u0627\u062f \u0639\u0644\u064a\u0627"
    ],
    "name:und_x_variant":[
        "Mahmud Abad Khafrak",
        "Ma\u1e29m\u016bd\u0101b\u0101d-e Khafrak",
        "Ma\u1e29m\u016bd\u0101b\u0101d-e \u2018Oly\u0101"
    ],
    "wof:name":"Mahmudabad",
    "wof:placetype":"locality"
},
  "geometry": {"coordinates":[53.1279,29.8635],"type":"Point"}
}