{
  "type": "Feature",
  "properties": {
    "gn:admin1_code":"3",
    "gn:asciiname":"Kinak",
    "gn:country_code":"IR",
    "gn:dem":1792,
    "gn:feature_class":"P",
    "gn:feature_code":"PPL",
    "gn:name":"K\u012bnak",
    "gn:population":0,
    "gn:timezone":"Asia/Tehran",
    "iso:country":"IR",
    "name:fas_x_preferred":[
        "K\u012bnak"
    ],
    "name:fas_x_variant":[
        "\u06a9\u06cc\u0646\u06a9"
    ],
    "name:msa_x_preferred":[
        "Kinak"
    ],
    "name:und_x_variant":[
        "Kink"
    ],
    "wof:name":"Kinak",
    "wof:placetype":"locality"
},
  "geometry": {"coordinates":[50.78603,31.61608],"type":"Point"}
}