{
  "type": "Feature",
  "properties": {
    "gn:admin1_code":"42",
    "gn:asciiname":"Lush Ab",
    "gn:country_code":"IR",
    "gn:dem":1443,
    "gn:feature_class":"P",
    "gn:feature_code":"PPL",
    "gn:name":"L\u016bsh \u0100b",
    "gn:population":0,
    "gn:timezone":"Asia/Tehran",
    "iso:country":"IR",
    "name:fas_x_preferred":[
        "\u0644\u0648\u0634 \u0622\u0628"
    ],
    "name:fas_x_variant":[
        "L\u016bsh \u0100b-e Qalandar\u0101b\u0101d",
        "L\u016bsh \u0100b"
    ],
    "name:und_x_variant":[
        "L\u016bsh-e Qalandar\u0101b\u0101d"
    ],
    "wof:name":"Lush Ab",
    "wof:placetype":"locality"
},
  "geometry": {"coordinates":[59.96402,35.55323],"type":"Point"}
}