{
  "type": "Feature",
  "properties": {
    "gn:admin1_code":"5.0",
    "gn:asciiname":"Chafkanam",
    "gn:country_code":"IR",
    "gn:dem":1555,
    "gn:feature_class":"P",
    "gn:feature_code":"PPL",
    "gn:name":"Chafkan\u0101m",
    "gn:population":0,
    "gn:timezone":"Asia/Tehran",
    "iso:country":"IR",
    "name:fas_x_preferred":[
        "Chafkan\u0101m"
    ],
    "name:fas_x_variant":[
        "\u0686\u0641\u06a9\u0646\u0627\u0645"
    ],
    "wof:name":"Chafkanam",
    "wof:placetype":"locality"
},
  "geometry": {"coordinates":[50.97747,30.64563],"type":"Point"}
}