{
  "type": "Feature",
  "properties": {
    "gn:admin1_code":"5.0",
    "gn:asciiname":"Narj-e Musa",
    "gn:country_code":"IR",
    "gn:dem":1373,
    "gn:feature_class":"P",
    "gn:feature_code":"PPL",
    "gn:name":"N\u0101rj-e M\u016bs\u00e1",
    "gn:population":0,
    "gn:timezone":"Asia/Tehran",
    "iso:country":"IR",
    "name:fas_x_preferred":[
        "N\u0101rj-e M\u016bs\u00e1"
    ],
    "name:fas_x_variant":[
        "\u0646\u0627\u0631\u062c \u0645\u0648\u0633\u0649"
    ],
    "wof:name":"Narj-e Musa",
    "wof:placetype":"locality"
},
  "geometry": {"coordinates":[51.02319,30.49758],"type":"Point"}
}