{
  "type": "Feature",
  "properties": {
    "gn:admin1_code":"23",
    "gn:asciiname":"Vanab",
    "gn:country_code":"IR",
    "gn:dem":1745,
    "gn:feature_class":"P",
    "gn:feature_code":"PPL",
    "gn:name":"Van\u0101b",
    "gn:population":0,
    "gn:timezone":"Asia/Tehran",
    "iso:country":"IR",
    "name:ara_x_preferred":[
        "\u0641\u0627\u0646\u0627\u0628"
    ],
    "name:ceb_x_preferred":[
        "Van\u0101b"
    ],
    "name:fas_x_preferred":[
        "\u0648\u064e\u0646\u0627\u0628"
    ],
    "name:fas_x_variant":[
        "\u0648\u0646\u0627\u0628",
        "Van\u0101b"
    ],
    "name:swe_x_preferred":[
        "Van\u0101b"
    ],
    "wof:name":"Vanab",
    "wof:placetype":"locality"
},
  "geometry": {"coordinates":[47.801,34.1204],"type":"Point"}
}