{
  "type": "Feature",
  "properties": {
    "gn:admin1_code":"42",
    "gn:asciiname":"Sowme`eh-ye Kuchak",
    "gn:country_code":"IR",
    "gn:dem":1678,
    "gn:feature_class":"P",
    "gn:feature_code":"PPL",
    "gn:name":"\u015eowme\u2018eh-ye K\u016bchak",
    "gn:population":0,
    "gn:timezone":"Asia/Tehran",
    "iso:country":"IR",
    "name:fas_x_preferred":[
        "\u0635\u0648\u0645\u0639\u0647 \u06a9\u0648\u0686\u06a9"
    ],
    "name:fas_x_variant":[
        "\u015eowma\u2018eh-ye P\u0101\u2019\u012bn",
        "\u015eowme\u2018eh-ye K\u016bchak"
    ],
    "wof:name":"Sowme`eh-ye Kuchak",
    "wof:placetype":"locality"
},
  "geometry": {"coordinates":[59.80897,35.55976],"type":"Point"}
}