{
  "type": "Feature",
  "properties": {
    "gn:admin1_code":"28",
    "gn:asciiname":"Hasanabad-e Pa'in",
    "gn:country_code":"IR",
    "gn:dem":2039,
    "gn:feature_class":"P",
    "gn:feature_code":"PPL",
    "gn:name":"\u1e28asan\u0101b\u0101d-e P\u0101\u2019\u012bn",
    "gn:population":0,
    "gn:timezone":"Asia/Tehran",
    "iso:country":"IR",
    "name:fas_x_preferred":[
        "\u1e28asan\u0101b\u0101d-e Vos\u0163\u00e1"
    ],
    "name:fas_x_variant":[
        "\u1e28asan\u0101b\u0101d-e P\u0101\u2019\u012bn",
        "\u062d\u0633\u0646 \u0622\u0628\u0627\u062f \u067e\u0627\u0626\u06cc\u0646",
        "\u062d\u0633\u0646\u200c\u0622\u0628\u0627\u062f \u0648\u0633\u0637\u06cc"
    ],
    "wof:name":"Hasanabad-e Pa'in",
    "wof:placetype":"locality"
},
  "geometry": {"coordinates":[50.95438,32.78968],"type":"Point"}
}