{
  "type": "Feature",
  "properties": {
    "gn:admin1_code":"28.0",
    "gn:asciiname":"Hasanabad",
    "gn:country_code":"IR",
    "gn:dem":1605,
    "gn:feature_class":"P",
    "gn:feature_code":"PPL",
    "gn:name":"\u1e28asan\u0101b\u0101d",
    "gn:population":0,
    "gn:timezone":"Asia/Tehran",
    "iso:country":"IR",
    "name:fas_x_preferred":[
        "\u1e28asan\u0101b\u0101d-e Khalaf Darreh"
    ],
    "name:fas_x_variant":[
        "\u062d\u0633\u0646 \u0622\u0628\u0627\u062f"
    ],
    "name:und_x_variant":[
        "\u1e28asan\u0101b\u0101d"
    ],
    "wof:name":"Hasanabad",
    "wof:placetype":"locality"
},
  "geometry": {"coordinates":[51.57505,32.5772],"type":"Point"}
}