{
  "type": "Feature",
  "properties": {
    "gn:admin1_code":"5",
    "gn:asciiname":"Chenar Bon-e Bala",
    "gn:country_code":"IR",
    "gn:dem":1616,
    "gn:feature_class":"P",
    "gn:feature_code":"PPL",
    "gn:name":"Chen\u0101r Bon-e B\u0101l\u0101",
    "gn:population":0,
    "gn:timezone":"Asia/Tehran",
    "iso:country":"IR",
    "name:fas_x_preferred":[
        "\u0686\u0650\u0646\u0627\u0631 \u0628\u064f\u0646\u0650 \u0628\u0627\u0644\u0627"
    ],
    "wof:name":"Chenar Bon-e Bala",
    "wof:placetype":"locality"
},
  "geometry": {"coordinates":[51.26361,30.98694],"type":"Point"}
}