{
  "type": "Feature",
  "properties": {
    "gn:admin1_code":"15",
    "gn:asciiname":"Ab Amiri",
    "gn:country_code":"IR",
    "gn:dem":415,
    "gn:feature_class":"P",
    "gn:feature_code":"PPL",
    "gn:name":"\u0100b Am\u012br\u012b",
    "gn:population":0,
    "gn:timezone":"Asia/Tehran",
    "iso:country":"IR",
    "name:azb_x_preferred":[
        "\u0627\u0628 \u0627\u0645\u06cc\u0631\u06cc(\u0628\u0647\u0628\u0647\u0627\u0646)"
    ],
    "name:ceb_x_preferred":[
        "\u0100b Am\u012br\u012b"
    ],
    "name:fas_x_preferred":[
        "\u0622\u0628 \u0627\u0645\u06cc\u0631\u06cc"
    ],
    "name:fas_x_variant":[
        "\u0100b Am\u012br\u012b",
        "\u0622\u0628\u200c\u0627\u0645\u06cc\u0631\u06cc"
    ],
    "name:swe_x_preferred":[
        "\u0100b Am\u012br\u012b"
    ],
    "name:urd_x_preferred":[
        "\u0622\u0628\u200c\u0627\u0645\u06cc\u0631\u06cc"
    ],
    "wof:name":"Ab Amiri",
    "wof:placetype":"locality"
},
  "geometry": {"coordinates":[50.0628,30.7349],"type":"Point"}
}