{
  "type": "Feature",
  "properties": {
    "gn:admin1_code":"29",
    "gn:asciiname":"Gal-e Bozorg",
    "gn:country_code":"IR",
    "gn:dem":406,
    "gn:feature_class":"P",
    "gn:feature_code":"PPL",
    "gn:name":"Gal-e Bozorg",
    "gn:population":0,
    "gn:timezone":"Asia/Tehran",
    "iso:country":"IR",
    "name:fas_x_preferred":[
        "\u06af\u0644 \u0628\u0632\u0631\u06af"
    ],
    "wof:name":"Gal-e Bozorg",
    "wof:placetype":"locality"
},
  "geometry": {"coordinates":[57.8814,27.4621],"type":"Point"}
}