{
  "type": "Feature",
  "properties": {
    "gn:admin1_code":"35",
    "gn:asciiname":"Salar Darreh",
    "gn:country_code":"IR",
    "gn:dem":119,
    "gn:feature_class":"P",
    "gn:feature_code":"PPL",
    "gn:name":"S\u0101l\u0101r Darreh",
    "gn:population":0,
    "gn:timezone":"Asia/Tehran",
    "iso:country":"IR",
    "name:fas_x_preferred":[
        "\u0633\u0627\u0644\u0627\u0631 \u062f\u064e\u0631\u0650\u0651\u0647"
    ],
    "name:fas_x_variant":[
        "S\u0101l\u0101r Darreh",
        "\u0633\u0627\u0644\u0627\u0631 \u062f\u0631\u0647"
    ],
    "wof:name":"Salar Darreh",
    "wof:placetype":"locality"
},
  "geometry": {"coordinates":[53.08834,36.47041],"type":"Point"}
}