{
  "type": "Feature",
  "properties": {
    "gn:admin1_code":"29.0",
    "gn:asciiname":"Sartangu'iyeh",
    "gn:country_code":"IR",
    "gn:dem":2119,
    "gn:feature_class":"P",
    "gn:feature_code":"PPL",
    "gn:name":"Sartang\u016b\u2019\u012byeh",
    "gn:population":0,
    "gn:timezone":"Asia/Tehran",
    "iso:country":"IR",
    "name:fas_x_preferred":[
        "Sartang\u016b\u2019\u012byeh"
    ],
    "name:und_x_variant":[
        "Sar Tang\u016b"
    ],
    "wof:name":"Sartangu'iyeh",
    "wof:placetype":"locality"
},
  "geometry": {"coordinates":[57.88806,28.96972],"type":"Point"}
}