{
  "type": "Feature",
  "properties": {
    "gn:admin1_code":"8",
    "gn:asciiname":"Uri",
    "gn:country_code":"IR",
    "gn:dem":302,
    "gn:feature_class":"P",
    "gn:feature_code":"PPL",
    "gn:name":"\u016ar\u012b",
    "gn:population":0,
    "gn:timezone":"Asia/Tehran",
    "iso:country":"IR",
    "name:fas_x_preferred":[
        "\u016ar\u012b"
    ],
    "wof:name":"Uri",
    "wof:placetype":"locality"
},
  "geometry": {"coordinates":[49.00972,37.38083],"type":"Point"}
}