{
  "type": "Feature",
  "properties": {
    "gn:admin1_code":"25.0",
    "gn:asciiname":"Kalateh-ye Mir A`lam",
    "gn:country_code":"IR",
    "gn:dem":1050,
    "gn:feature_class":"P",
    "gn:feature_code":"PPL",
    "gn:name":"Kal\u0101teh-ye M\u012br A\u2018lam",
    "gn:population":0,
    "gn:timezone":"Asia/Tehran",
    "iso:country":"IR",
    "name:fas_x_preferred":[
        "\u0643\u0644\u0627\u062a\u0647 \u0645\u064a\u0631 \u0639\u0644\u0645"
    ],
    "name:fas_x_variant":[
        "Kal\u0101teh-ye M\u012br \u2018Alam",
        "\u0643\u0644\u0627\u062a\u0647 \u0645\u064a\u0631 \u0627\u0639\u0644\u0645",
        "\u0645\u064a\u0631 \u0627\u0639\u0644\u0645"
    ],
    "name:und_x_variant":[
        "Kal\u0101teh-ye M\u012br A\u2018lam",
        "M\u012br A\u2018lam"
    ],
    "wof:name":"Kalateh-ye Mir A`lam",
    "wof:placetype":"locality"
},
  "geometry": {"coordinates":[56.64156,36.50364],"type":"Point"}
}