{
  "type": "Feature",
  "properties": {
    "gn:admin1_code":"41",
    "gn:asciiname":"Kalateh-ye Zard",
    "gn:country_code":"IR",
    "gn:dem":942,
    "gn:feature_class":"P",
    "gn:feature_code":"PPL",
    "gn:name":"Kal\u0101teh-ye Zard",
    "gn:population":0,
    "gn:timezone":"Asia/Tehran",
    "iso:country":"IR",
    "name:fas_x_preferred":[
        "Kal\u0101teh-ye Zard"
    ],
    "wof:name":"Kalateh-ye Zard",
    "wof:placetype":"locality"
},
  "geometry": {"coordinates":[59.88166999999999,33.85667],"type":"Point"}
}