{
  "type": "Feature",
  "properties": {
    "gn:admin1_code":"29",
    "gn:asciiname":"Zanaqi",
    "gn:country_code":"IR",
    "gn:dem":1380,
    "gn:feature_class":"P",
    "gn:feature_code":"PPLL",
    "gn:name":"Zan\u0101q\u012b",
    "gn:population":0,
    "gn:timezone":"Asia/Tehran",
    "iso:country":"IR",
    "name:fas_x_preferred":[
        "\u0639\u0644\u06cc \u0622\u0628\u0627\u062f"
    ],
    "name:fas_x_variant":[
        "\u2018Al\u012b\u0101b\u0101d",
        "\u0632\u0646\u0627\u0642\u06cc"
    ],
    "name:und_x_variant":[
        "Zan\u0101q\u012b"
    ],
    "wof:name":"Zanaqi",
    "wof:placetype":"locality"
},
  "geometry": {"coordinates":[58.68337,28.32584],"type":"Point"}
}