{
  "type": "Feature",
  "properties": {
    "gn:admin1_code":"16",
    "gn:asciiname":"Kazhikaran",
    "gn:country_code":"IR",
    "gn:dem":1920,
    "gn:feature_class":"P",
    "gn:feature_code":"PPL",
    "gn:name":"Kazh\u012bkar\u0101n",
    "gn:population":0,
    "gn:timezone":"Asia/Tehran",
    "iso:country":"IR",
    "name:fas_x_preferred":[
        "\u06a9\u0698\u06cc\u06a9\u0631\u0627\u0646"
    ],
    "name:und_x_variant":[
        "Q\u0101z\u012b Kar\u0101n",
        "Kazhi Garan",
        "Kazh\u012bkar\u0101n"
    ],
    "wof:name":"Kazhikaran",
    "wof:placetype":"locality"
},
  "geometry": {"coordinates":[47.23676,35.62344],"type":"Point"}
}