{
  "type": "Feature",
  "properties": {
    "gn:admin1_code":"43",
    "gn:asciiname":"Tuy-e Bala",
    "gn:country_code":"IR",
    "gn:dem":1186,
    "gn:feature_class":"P",
    "gn:feature_code":"PPL",
    "gn:name":"T\u016by-e B\u0101l\u0101",
    "gn:population":0,
    "gn:timezone":"Asia/Tehran",
    "iso:country":"IR",
    "name:fas_x_preferred":[
        "T\u016by-e B\u0101l\u0101"
    ],
    "name:fas_x_variant":[
        "\u062a\u0648\u06cc \u0628\u0627\u0644\u0627"
    ],
    "name:und_x_variant":[
        "\u062a\u0648\u06cc \u0628\u0627\u0644\u0627"
    ],
    "wof:name":"Tuy-e Bala",
    "wof:placetype":"locality"
},
  "geometry": {"coordinates":[57.09789,37.16051],"type":"Point"}
}