{
  "type": "Feature",
  "properties": {
    "gn:admin1_code":"37.0",
    "gn:asciiname":"Abparan",
    "gn:country_code":"IR",
    "gn:dem":404,
    "gn:feature_class":"P",
    "gn:feature_code":"PPL",
    "gn:name":"\u0100bpar\u0101n",
    "gn:population":0,
    "gn:timezone":"Asia/Tehran",
    "iso:country":"IR",
    "name:fas_x_preferred":[
        "\u0622\u0628\u067e\u0631\u0627\u0646"
    ],
    "name:fas_x_variant":[
        "\u0622\u0628 \u067e\u0631\u0627\u0646",
        "\u0622\u0628\u200c\u067e\u0631\u0627\u0646"
    ],
    "name:msa_x_preferred":[
        "Ab Paran"
    ],
    "name:und_x_variant":[
        "\u0100bpar\u0101n",
        "\u0100b Par\u0101n"
    ],
    "wof:name":"Abparan",
    "wof:placetype":"locality"
},
  "geometry": {"coordinates":[55.48881,37.25087],"type":"Point"}
}