{
  "type": "Feature",
  "properties": {
    "gn:admin1_code":"16",
    "gn:asciiname":"Dalan",
    "gn:country_code":"IR",
    "gn:dem":1711,
    "gn:feature_class":"P",
    "gn:feature_code":"PPL",
    "gn:name":"D\u0101l\u0101n",
    "gn:population":0,
    "gn:timezone":"Asia/Tehran",
    "iso:country":"IR",
    "name:ceb_x_preferred":[
        "Dalan"
    ],
    "name:fas_x_preferred":[
        "\u062f\u0627\u0644\u0627\u0646"
    ],
    "name:fas_x_variant":[
        "D\u0101l\u0101n"
    ],
    "name:swe_x_preferred":[
        "Dalan"
    ],
    "wof:name":"Dalan",
    "wof:placetype":"locality"
},
  "geometry": {"coordinates":[47.20404,35.88878],"type":"Point"}
}