{
  "type": "Feature",
  "properties": {
    "gn:admin1_code":"8",
    "gn:asciiname":"Varvarandis",
    "gn:country_code":"IR",
    "gn:dem":1758,
    "gn:feature_class":"P",
    "gn:feature_code":"PPL",
    "gn:name":"Varvar\u0101nd\u012bs",
    "gn:population":0,
    "gn:timezone":"Asia/Tehran",
    "iso:country":"IR",
    "name:fas_x_preferred":[
        "\u0648\u0631\u0648\u0631\u0627\u0646\u062f\u06cc\u0633"
    ],
    "name:fas_x_variant":[
        "Ver\u016br\u0101nd\u012bs"
    ],
    "name:und_x_variant":[
        "Varvar\u0101nd\u012bs"
    ],
    "wof:name":"Varvarandis",
    "wof:placetype":"locality"
},
  "geometry": {"coordinates":[48.82053,37.44463],"type":"Point"}
}