{
  "type": "Feature",
  "properties": {
    "gn:admin1_code":"3",
    "gn:asciiname":"Markadeh",
    "gn:country_code":"IR",
    "gn:dem":1960,
    "gn:feature_class":"P",
    "gn:feature_code":"PPL",
    "gn:name":"M\u0101rkadeh",
    "gn:population":0,
    "gn:timezone":"Asia/Tehran",
    "iso:country":"IR",
    "name:fas_x_preferred":[
        "\u0645\u064e\u0632\u0631\u064e\u0639\u0650\u06c0 \u0645\u0627\u0631 \u0643\u064e\u062f\u0650\u0647"
    ],
    "name:fas_x_variant":[
        "M\u0101rkadeh",
        "\u0645\u064e\u0631\u0643\u064e\u062f\u0650\u0647 \u067e\u0627\u0626\u064a\u0646",
        "\u0645\u0627\u0631\u06a9\u062f\u0647"
    ],
    "name:und_x_variant":[
        "Markadeh P\u0101\u2019\u012bn",
        "Mazra\u2018eh-ye M\u0101r Kadeh",
        "\u0645\u0627\u0631\u06a9\u062f\u0647"
    ],
    "wof:name":"Markadeh",
    "wof:placetype":"locality"
},
  "geometry": {"coordinates":[50.83382,32.65496],"type":"Point"}
}