{
  "type": "Feature",
  "properties": {
    "gn:admin1_code":"1.0",
    "gn:asciiname":"Nezh Darreh",
    "gn:country_code":"IR",
    "gn:dem":1878,
    "gn:feature_class":"P",
    "gn:feature_code":"PPL",
    "gn:name":"Nezh Darreh",
    "gn:population":0,
    "gn:timezone":"Asia/Tehran",
    "iso:country":"IR",
    "name:fas_x_preferred":[
        "\u0646\u0698 \u062f\u0631\u0651\u0647"
    ],
    "wof:name":"Nezh Darreh",
    "wof:placetype":"locality"
},
  "geometry": {"coordinates":[45.1698,37.2647],"type":"Point"}
}