{
  "type": "Feature",
  "properties": {
    "gn:admin1_code":"13",
    "gn:asciiname":"Sefidu",
    "gn:country_code":"IR",
    "gn:dem":1461,
    "gn:feature_class":"P",
    "gn:feature_code":"PPL",
    "gn:name":"Sef\u012bd\u016b",
    "gn:population":0,
    "gn:timezone":"Asia/Tehran",
    "iso:country":"IR",
    "name:fas_x_preferred":[
        "Sef\u012bd\u016b"
    ],
    "wof:name":"Sefidu",
    "wof:placetype":"locality"
},
  "geometry": {"coordinates":[47.07722,34.12],"type":"Point"}
}