{
  "type": "Feature",
  "properties": {
    "gn:admin1_code":"41",
    "gn:asciiname":"Kalateh-ye Now",
    "gn:country_code":"IR",
    "gn:dem":1748,
    "gn:feature_class":"P",
    "gn:feature_code":"PPL",
    "gn:name":"Kal\u0101teh-ye Now",
    "gn:population":0,
    "gn:timezone":"Asia/Tehran",
    "iso:country":"IR",
    "name:fas_x_preferred":[
        "\u06a9\u0644\u0627\u062a \u0646\u0648"
    ],
    "name:fas_x_variant":[
        "Kal\u0101teh-ye Now",
        "Kal\u0101t-e Now",
        "\u06a9\u0644\u0627\u062a\u0647 \u0646\u0648"
    ],
    "name:und_x_variant":[
        "M\u012b\u0101n R\u016bd",
        "Kal\u0101teh Now",
        "Miyan Rood",
        "Kal\u0101teh-ye M\u012b\u0101n R\u016bd",
        "Kal\u0101teh Miy\u0101nr\u016bd"
    ],
    "wof:name":"Kalateh-ye Now",
    "wof:placetype":"locality"
},
  "geometry": {"coordinates":[59.68131999999999,32.10023],"type":"Point"}
}