{
  "type": "Feature",
  "properties": {
    "gn:admin1_code":"4.0",
    "gn:asciiname":"Molla Ebrahim",
    "gn:country_code":"IR",
    "gn:dem":481,
    "gn:feature_class":"P",
    "gn:feature_code":"PPL",
    "gn:name":"Moll\u0101 Ebr\u0101h\u012bm",
    "gn:population":0,
    "gn:timezone":"Asia/Tehran",
    "iso:country":"IR",
    "name:fas_x_preferred":[
        "\u0645\u0644\u0627\u0651 \u0627\u0628\u0631\u0627\u0647\u06cc\u0645"
    ],
    "name:fas_x_variant":[
        "Moll\u0101 Ebr\u0101h\u012bm"
    ],
    "name:und_x_variant":[
        "Moll\u0101 Ebr\u0101h\u012bm"
    ],
    "wof:name":"Molla Ebrahim",
    "wof:placetype":"locality"
},
  "geometry": {"coordinates":[61.4374,30.8168],"type":"Point"}
}