{
  "type": "Feature",
  "properties": {
    "gn:admin1_code":"1.0",
    "gn:asciiname":"Galvan",
    "gn:country_code":"IR",
    "gn:dem":1376,
    "gn:elevation":"0.0",
    "gn:feature_class":"P",
    "gn:feature_code":"PPL",
    "gn:name":"Galv\u0101n",
    "gn:population":0,
    "gn:timezone":"Asia/Tehran",
    "iso:country":"IR",
    "name:fas_x_preferred":[
        "\u06af\u0644\u0648\u0627\u0646"
    ],
    "name:fas_x_variant":[
        "Galv\u0101n"
    ],
    "name:und_x_variant":[
        "Gelv\u0101n"
    ],
    "wof:name":"Galvan",
    "wof:placetype":"locality"
},
  "geometry": {"coordinates":[45.3235,36.9106],"type":"Point"}
}