{
  "type": "Feature",
  "properties": {
    "gn:admin1_code":"8",
    "gn:asciiname":"Beg Mahalleh",
    "gn:country_code":"IR",
    "gn:dem":994,
    "gn:feature_class":"P",
    "gn:feature_code":"PPL",
    "gn:name":"Beg Ma\u1e29alleh",
    "gn:population":0,
    "gn:timezone":"Asia/Tehran",
    "iso:country":"IR",
    "name:fas_x_preferred":[
        "\u0628\u06af \u0645\u062d\u0644\u0647"
    ],
    "name:fas_x_variant":[
        "Beg Ma\u1e29alleh"
    ],
    "wof:name":"Beg Mahalleh",
    "wof:placetype":"locality"
},
  "geometry": {"coordinates":[48.8336,37.4937],"type":"Point"}
}