{
  "type": "Feature",
  "properties": {
    "gn:admin1_code":"13",
    "gn:asciiname":"Asiab-e Musa",
    "gn:country_code":"IR",
    "gn:dem":1721,
    "gn:feature_class":"P",
    "gn:feature_code":"PPL",
    "gn:name":"\u0100s\u012b\u0101b-e M\u016bs\u00e1",
    "gn:population":0,
    "gn:timezone":"Asia/Tehran",
    "iso:country":"IR",
    "name:fas_x_preferred":[
        "\u0622\u0633\u06cc\u0627\u0628 \u0645\u0648\u0633\u06cc"
    ],
    "name:fas_x_variant":[
        "\u0100s\u012b\u0101b-e M\u016bs\u00e1"
    ],
    "wof:name":"Asiab-e Musa",
    "wof:placetype":"locality"
},
  "geometry": {"coordinates":[46.1677,34.4586],"type":"Point"}
}