{
  "type": "Feature",
  "properties": {
    "gn:admin1_code":"8",
    "gn:asciiname":"Jowr-e Kulakabar",
    "gn:country_code":"IR",
    "gn:dem":304,
    "gn:feature_class":"P",
    "gn:feature_code":"PPL",
    "gn:name":"Jowr-e K\u016bl\u0101kabar",
    "gn:population":0,
    "gn:timezone":"Asia/Tehran",
    "iso:country":"IR",
    "name:fas_x_preferred":[
        "Kal\u0101k\u0101var-e B\u0101l\u0101"
    ],
    "name:fas_x_variant":[
        "\u062c\u0648\u0631 \u06a9\u0648\u0644\u0627\u06a9\u0628\u0631",
        "\u0628\u0627\u0644\u0627 \u06a9\u0644\u0627 \u06af\u0648\u0627\u0628\u0631"
    ],
    "name:und_x_variant":[
        "Jowr-e K\u016bl\u0101kabar",
        "B\u0101l\u0101 Kal\u0101 Gav\u0101bar"
    ],
    "wof:name":"Jowr-e Kulakabar",
    "wof:placetype":"locality"
},
  "geometry": {"coordinates":[49.89928,37.10212],"type":"Point"}
}