{
  "type": "Feature",
  "properties": {
    "gn:admin1_code":"8",
    "gn:asciiname":"Chenar Chal",
    "gn:country_code":"IR",
    "gn:dem":1659,
    "gn:feature_class":"P",
    "gn:feature_code":"PPL",
    "gn:name":"Chen\u0101r Ch\u0101l",
    "gn:population":0,
    "gn:timezone":"Asia/Tehran",
    "iso:country":"IR",
    "name:fas_x_preferred":[
        "Chen\u0101r Ch\u0101l"
    ],
    "name:fas_x_variant":[
        "\u0686\u0646\u0627\u0631 \u0686\u0627\u0644"
    ],
    "wof:name":"Chenar Chal",
    "wof:placetype":"locality"
},
  "geometry": {"coordinates":[50.3436,36.89125],"type":"Point"}
}