{
  "type": "Feature",
  "properties": {
    "gn:admin1_code":"23",
    "gn:asciiname":"Morshedabad",
    "gn:country_code":"IR",
    "gn:dem":1569,
    "gn:feature_class":"P",
    "gn:feature_code":"PPL",
    "gn:name":"Morshed\u0101b\u0101d",
    "gn:population":0,
    "gn:timezone":"Asia/Tehran",
    "iso:country":"IR",
    "name:fas_x_preferred":[
        "\u0645\u064f\u0631\u0634\u0650\u062f\u0627\u0628\u0627\u062f\u0650 \u0645\u064f\u0639\u0645\u0650\u0646"
    ],
    "name:fas_x_variant":[
        "Morshed\u0101b\u0101d-e Mo\u2018men",
        "\u0645\u0631\u0634\u062f \u0622\u0628\u0627\u062f"
    ],
    "name:und_x_variant":[
        "Morshed\u0101b\u0101d"
    ],
    "wof:name":"Morshedabad",
    "wof:placetype":"locality"
},
  "geometry": {"coordinates":[48.22489,33.8371],"type":"Point"}
}