{
  "type": "Feature",
  "properties": {
    "iso:country":"IR",
    "name:ara_x_preferred":[
        "\u0628\u0631\u0627\u0632\u062c\u0627\u0646"
    ],
    "name:aze_x_preferred":[
        "B\u00fcrazcan"
    ],
    "name:aze_x_variant":[
        "Borazcan"
    ],
    "name:ceb_x_preferred":[
        "Bor\u0101zj\u0101n"
    ],
    "name:ckb_x_preferred":[
        "\u0628\u06c6\u0631\u0627\u0632\u062c\u0627\u0646"
    ],
    "name:deu_x_preferred":[
        "Borazdschan"
    ],
    "name:eng_x_preferred":[
        "Borazjan"
    ],
    "name:epo_x_preferred":[
        "Boraz\u011dan"
    ],
    "name:fas_x_preferred":[
        "\u0628\u0631\u0627\u0632\u062c\u0627\u0646"
    ],
    "name:fas_x_variant":[
        "\u0628\u064f\u0631\u064e\u0632\u062f\u062c\u064e\u0646",
        "Bor\u0101zj\u0101n"
    ],
    "name:fra_x_preferred":[
        "Borazjan"
    ],
    "name:fra_x_variant":[
        "Borazdjan"
    ],
    "name:gle_x_preferred":[
        "Borazjan"
    ],
    "name:heb_x_preferred":[
        "\u05d1\u05d5\u05e8\u05d0\u05d6\u05d2'\u05d0\u05df"
    ],
    "name:hin_x_preferred":[
        "\u092c\u094b\u0930\u093e\u091c\u093c\u091c\u093e\u0928"
    ],
    "name:ind_x_preferred":[
        "Borazjan"
    ],
    "name:ita_x_preferred":[
        "Borazjan"
    ],
    "name:jpn_x_preferred":[
        "\u30dc\u30e9\u30b8\u30e3\u30f3"
    ],
    "name:mlg_x_preferred":[
        "Borazjan"
    ],
    "name:msa_x_preferred":[
        "Borazjan"
    ],
    "name:nan_x_preferred":[
        "Borazjan"
    ],
    "name:nld_x_preferred":[
        "Borazjan"
    ],
    "name:pnb_x_preferred":[
        "\u0628\u0631\u0627\u0632\u062c\u0627\u0646"
    ],
    "name:pol_x_preferred":[
        "Borazd\u017can"
    ],
    "name:por_x_preferred":[
        "Borazjan"
    ],
    "name:ron_x_preferred":[
        "Borazjan"
    ],
    "name:rus_x_preferred":[
        "\u0411\u043e\u0440\u0430\u0437\u0434\u0436\u0430\u043d"
    ],
    "name:swe_x_preferred":[
        "Borazjan"
    ],
    "name:tat_x_preferred":[
        "\u0411\u04e9\u0440\u0430\u0437\u0497\u0430\u043d"
    ],
    "name:tgk_x_preferred":[
        "\u0411\u0435\u0440\u043e\u0437\u04b7\u043e\u043d"
    ],
    "name:tur_x_preferred":[
        "Borazcan"
    ],
    "name:und_x_variant":[
        "Bor\u0101zj\u016bn"
    ],
    "name:urd_x_preferred":[
        "\u0628\u0631\u0627\u0632\u062c\u0627\u0646"
    ],
    "name:zho_x_preferred":[
        "\u535a\u62c9\u8332\u8a79"
    ],
    "qs:gn_country":"IR",
    "qs:gn_fcode":"PPL",
    "qs:gn_pop":86059,
    "qs:name":"Borazdjan",
    "qs:name_adm0":"Iran",
    "qs:name_adm1":"Bushehr",
    "qs:photos":0,
    "qs:photos_1k":0,
    "qs:photos_9k":0,
    "qs:photos_9r":0,
    "qs:photos_all":0,
    "qs:photos_sr":0,
    "qs:placetype":"Town",
    "qs:pop_sr":"8",
    "qs:woe_adm0":23424851,
    "wd:wordcount":822,
    "wof:name":"Borazdjan",
    "wof:placetype":"locality",
    "wof:population":86059
},
  "geometry": {"coordinates":[51.2159,29.2666],"type":"Point"}
}