{
  "type": "Feature",
  "properties": {
    "gn:admin1_code":"33",
    "gn:asciiname":"Aznavi-ye Bala",
    "gn:country_code":"IR",
    "gn:dem":563,
    "gn:feature_class":"P",
    "gn:feature_code":"PPL",
    "gn:name":"Aznav\u012b-ye B\u0101l\u0101",
    "gn:population":0,
    "gn:timezone":"Asia/Tehran",
    "iso:country":"IR",
    "name:ara_x_preferred":[
        "\u0623\u0632\u0646\u0627\u0628 \u0627\u0644\u0639\u0644\u064a\u0627"
    ],
    "name:azb_x_preferred":[
        "\u0627\u0632\u0646\u0627\u0628 \u0639\u0644\u06cc\u0627"
    ],
    "name:fas_x_preferred":[
        "\u0627\u0632\u0646\u0648\u06cc \u0628\u0627\u0644\u0627"
    ],
    "name:fas_x_variant":[
        "Azn\u0101b-e \u2018Oly\u0101",
        "Aznav\u012b-ye B\u0101l\u0101",
        "\u0627\u0632\u0646\u0627\u0628 \u0639\u0644\u06cc\u0627"
    ],
    "name:msa_x_preferred":[
        "Aznab-e Olya"
    ],
    "wof:name":"Aznavi-ye Bala",
    "wof:placetype":"locality"
},
  "geometry": {"coordinates":[47.4348,39.0491],"type":"Point"}
}