{
  "type": "Feature",
  "properties": {
    "gn:admin1_code":"42",
    "gn:asciiname":"Chalpu",
    "gn:country_code":"IR",
    "gn:dem":1935,
    "gn:feature_class":"P",
    "gn:feature_code":"PPL",
    "gn:name":"Chalp\u016b",
    "gn:population":0,
    "gn:timezone":"Asia/Tehran",
    "iso:country":"IR",
    "name:fas_x_preferred":[
        "Chalp\u016b"
    ],
    "wof:name":"Chalpu",
    "wof:placetype":"locality"
},
  "geometry": {"coordinates":[58.48806,35.62860999999999],"type":"Point"}
}