{
  "type": "Feature",
  "properties": {
    "gn:admin1_code":"1",
    "gn:asciiname":"Gazanehkesh",
    "gn:country_code":"IR",
    "gn:dem":1471,
    "gn:feature_class":"P",
    "gn:feature_code":"PPL",
    "gn:name":"Gazanehkesh",
    "gn:population":0,
    "gn:timezone":"Asia/Tehran",
    "iso:country":"IR",
    "name:azb_x_preferred":[
        "\u06af\u0632\u0646\u0647 \u06a9\u0634"
    ],
    "name:aze_x_preferred":[
        "Qazan\u0259ke\u015f"
    ],
    "name:ceb_x_preferred":[
        "Gazanehkesh"
    ],
    "name:fas_x_preferred":[
        "\u06af\u0632\u0646\u0647 \u06a9\u0634"
    ],
    "name:fas_x_variant":[
        "\u06af\u064e\u0632\u064e\u0646\u0650\u0647\u0643\u0650\u0634",
        "\u06af\u0632\u0646\u0647\u200c\u06a9\u0634"
    ],
    "name:msa_x_preferred":[
        "Gazanehkesh"
    ],
    "name:pol_x_preferred":[
        "Gazanekesz"
    ],
    "name:swe_x_preferred":[
        "Gazanehkesh"
    ],
    "name:ukr_x_preferred":[
        "\u0413\u0430\u0437\u0430\u043d\u0435\u043a\u0435\u0448"
    ],
    "wof:name":"Gazanehkesh",
    "wof:placetype":"locality"
},
  "geometry": {"coordinates":[44.9943,37.384],"type":"Point"}
}