{
  "type": "Feature",
  "properties": {
    "gn:admin1_code":"1",
    "gn:asciiname":"Gazanehkesh",
    "gn:country_code":"IR",
    "gn:dem":1471,
    "gn:feature_class":"P",
    "gn:feature_code":"PPL",
    "gn:name":"Gazanehkesh",
    "gn:population":0,
    "gn:timezone":"Asia/Tehran",
    "iso:country":"IR",
    "name:fas_x_preferred":[
        "\u06af\u0632\u0646\u0647 \u06a9\u0634"
    ],
    "name:fas_x_variant":[
        "\u06af\u064e\u0632\u064e\u0646\u0650\u0647\u0643\u0650\u0634"
    ],
    "wof:name":"Gazanehkesh",
    "wof:placetype":"locality"
},
  "geometry": {"coordinates":[44.9943,37.384],"type":"Point"}
}