{
  "type": "Feature",
  "properties": {
    "gn:admin1_code":"16.0",
    "gn:asciiname":"Qom Dureh",
    "gn:country_code":"IR",
    "gn:dem":1650,
    "gn:feature_class":"P",
    "gn:feature_code":"PPL",
    "gn:name":"Qom D\u016breh",
    "gn:population":0,
    "gn:timezone":"Asia/Tehran",
    "iso:country":"IR",
    "name:ara_x_preferred":[
        "\u0642\u0645\u062f\u0631\u0629"
    ],
    "name:fas_x_preferred":[
        "\u0642\u0645\u062f\u0631\u0651\u0647"
    ],
    "name:fas_x_variant":[
        "\u0642\u0645 \u062f\u0648\u0631\u0647",
        "\u0642\u0645\u062f\u0631\u0647"
    ],
    "name:und_x_variant":[
        "Gomdarreh",
        "Qomdarreh",
        "Qom Dowreh",
        "Qom D\u016breh"
    ],
    "wof:name":"Qom Dureh",
    "wof:placetype":"locality"
},
  "geometry": {"coordinates":[47.39376,35.94036],"type":"Point"}
}