{
  "type": "Feature",
  "properties": {
    "gn:admin1_code":"8",
    "gn:asciiname":"Lisar",
    "gn:country_code":"IR",
    "gn:dem":16,
    "gn:feature_class":"P",
    "gn:feature_code":"PPL",
    "gn:name":"L\u012bs\u0101r",
    "gn:population":0,
    "gn:timezone":"Asia/Tehran",
    "iso:country":"IR",
    "name:ara_x_preferred":[
        "\u0644\u064a\u0633\u0627\u0631"
    ],
    "name:azb_x_preferred":[
        "\u0644\u06cc\u0633\u0627\u0631"
    ],
    "name:aze_x_preferred":[
        "Lisar"
    ],
    "name:fas_x_preferred":[
        "\u0645\u062d\u0645\u0648\u062f \u0622\u0628\u0627\u062f"
    ],
    "name:fas_x_variant":[
        "Ma\u1e29m\u016bd\u0101b\u0101d",
        "\u0644\u06cc\u0633\u0627\u0631"
    ],
    "name:mlg_x_preferred":[
        "Lisar"
    ],
    "name:msa_x_preferred":[
        "Lisar"
    ],
    "name:und_x_variant":[
        "L\u012bs\u0101r"
    ],
    "wof:name":"Lisar",
    "wof:placetype":"locality"
},
  "geometry": {"coordinates":[48.90793,37.96488],"type":"Point"}
}