{
  "type": "Feature",
  "properties": {
    "gn:admin1_code":"3",
    "gn:asciiname":"Geysaran",
    "gn:country_code":"IR",
    "gn:dem":1528,
    "gn:feature_class":"P",
    "gn:feature_code":"PPL",
    "gn:name":"Geys\u0101r\u0101n",
    "gn:population":0,
    "gn:timezone":"Asia/Tehran",
    "iso:country":"IR",
    "name:ceb_x_preferred":[
        "Geys\u0101r\u0101n"
    ],
    "name:fas_x_preferred":[
        "Geys\u0101r\u0101n"
    ],
    "name:fas_x_variant":[
        "\u06af\u06cc\u0633\u0627\u0631\u0627\u0646"
    ],
    "name:msa_x_preferred":[
        "Geysaran"
    ],
    "name:swe_x_preferred":[
        "Geys\u0101r\u0101n"
    ],
    "name:und_x_variant":[
        "\u06af\u06cc\u0633\u0627\u0631\u0627\u0646"
    ],
    "wof:name":"Geysaran",
    "wof:placetype":"locality"
},
  "geometry": {"coordinates":[51.16188,31.21231],"type":"Point"}
}