{
  "type": "Feature",
  "properties": {
    "gn:admin1_code":"8",
    "gn:asciiname":"Kureh Darreh",
    "gn:country_code":"IR",
    "gn:dem":1468,
    "gn:feature_class":"P",
    "gn:feature_code":"PPL",
    "gn:name":"K\u016breh Darreh",
    "gn:population":0,
    "gn:timezone":"Asia/Tehran",
    "iso:country":"IR",
    "name:ceb_x_preferred":[
        "K\u016brdarreh"
    ],
    "name:ckb_x_preferred":[
        "\u06a9\u06c6\u0631\u06cc\u06d5\u0631\u06d5"
    ],
    "name:fas_x_preferred":[
        "\u06a9\u0648\u0631\u0647 \u062f\u0631\u0647"
    ],
    "name:fas_x_variant":[
        "K\u016breh Darreh",
        "\u06a9\u0648\u0631\u0647\u200c\u062f\u0631\u0647"
    ],
    "name:swe_x_preferred":[
        "K\u016brdarreh"
    ],
    "wof:name":"Kureh Darreh",
    "wof:placetype":"locality"
},
  "geometry": {"coordinates":[48.7381,37.9404],"type":"Point"}
}