{
  "type": "Feature",
  "properties": {
    "gn:admin1_code":"1",
    "gn:asciiname":"Lajani",
    "gn:country_code":"IR",
    "gn:dem":1774,
    "gn:feature_class":"P",
    "gn:feature_code":"PPL",
    "gn:name":"L\u0101j\u0101n\u012b",
    "gn:population":0,
    "gn:timezone":"Asia/Tehran",
    "iso:country":"IR",
    "name:ara_x_preferred":[
        "\u0644\u0627\u062c\u0627\u0646\u064a"
    ],
    "name:azb_x_preferred":[
        "\u0644\u0627\u062c\u0627\u0646\u06cc"
    ],
    "name:aze_x_preferred":[
        "Lacani"
    ],
    "name:ceb_x_preferred":[
        "L\u0101j\u0101n\u012b"
    ],
    "name:ckb_x_preferred":[
        "\u0644\u0627\u062c\u0627\u0646\u06cc"
    ],
    "name:fas_x_preferred":[
        "\u0644\u0627\u062c\u0627\u0646\u06cc"
    ],
    "name:fas_x_variant":[
        "L\u0101j\u0101n\u012b"
    ],
    "name:kur_x_preferred":[
        "Lacan\u00ee"
    ],
    "name:msa_x_preferred":[
        "Lajani"
    ],
    "name:swe_x_preferred":[
        "L\u0101j\u0101n\u012b"
    ],
    "name:urd_x_preferred":[
        "\u0644\u0627\u062e\u0627\u0646\u06cc"
    ],
    "wof:name":"Lajani",
    "wof:placetype":"locality"
},
  "geometry": {"coordinates":[44.9794,37.277],"type":"Point"}
}