{
  "type": "Feature",
  "properties": {
    "gn:admin1_code":"4.0",
    "gn:asciiname":"Kud",
    "gn:country_code":"IR",
    "gn:dem":491,
    "gn:feature_class":"P",
    "gn:feature_code":"PPL",
    "gn:name":"K\u016bd",
    "gn:population":0,
    "gn:timezone":"Asia/Tehran",
    "iso:country":"IR",
    "name:bpy_x_preferred":[
        "\u0995\u09c1\u09a6"
    ],
    "name:ceb_x_preferred":[
        "K\u016bd"
    ],
    "name:fas_x_preferred":[
        "\u06a9\u0648\u062f"
    ],
    "name:fas_x_variant":[
        "K\u016bd",
        "\u06a9\u0648\u062f \u0646\u0648"
    ],
    "name:hin_x_preferred":[
        "\u0915\u0941\u0926"
    ],
    "name:ita_x_preferred":[
        "Kud"
    ],
    "name:msa_x_preferred":[
        "Kud"
    ],
    "name:new_x_preferred":[
        "\u0915\u0941\u0926"
    ],
    "name:nld_x_preferred":[
        "Kud"
    ],
    "name:por_x_preferred":[
        "Kud"
    ],
    "name:swe_x_preferred":[
        "Kud"
    ],
    "name:und_x_variant":[
        "K\u016bd-e Now"
    ],
    "name:vie_x_preferred":[
        "Kud"
    ],
    "name:zho_x_preferred":[
        "\u5e93\u5fb7"
    ],
    "wof:name":"Kud",
    "wof:placetype":"locality"
},
  "geometry": {"coordinates":[61.698,30.9379],"type":"Point"}
}