{
  "type": "Feature",
  "properties": {
    "gn:admin1_code":"41.0",
    "gn:asciiname":"Mazra`eh-ye Chah-e Panj Tan",
    "gn:country_code":"IR",
    "gn:dem":1356,
    "gn:feature_class":"P",
    "gn:feature_code":"PPL",
    "gn:name":"Mazra\u2018eh-ye Ch\u0101h-e Panj Tan",
    "gn:population":0,
    "gn:timezone":"Asia/Tehran",
    "iso:country":"IR",
    "name:fas_x_preferred":[
        "\u0645\u0632\u0631\u0639\u0647 \u0686\u0627\u0647 \u067e\u0646\u062c \u062a\u0646"
    ],
    "name:und_x_variant":[
        "Mazra\u2018eh-ye Ch\u0101h-e Panj Tan"
    ],
    "wof:name":"Mazra`eh-ye Chah-e Panj Tan",
    "wof:placetype":"locality"
},
  "geometry": {"coordinates":[58.75574,33.60499],"type":"Point"}
}