{
  "type": "Feature",
  "properties": {
    "gn:admin1_code":"41",
    "gn:asciiname":"Na'emeh",
    "gn:country_code":"IR",
    "gn:dem":1659,
    "gn:feature_class":"P",
    "gn:feature_code":"PPL",
    "gn:name":"N\u0101\u2019emeh",
    "gn:population":0,
    "gn:timezone":"Asia/Tehran",
    "iso:country":"IR",
    "name:fas_x_preferred":[
        "\u0646\u0627\u0626\u0645\u0647"
    ],
    "name:fas_x_variant":[
        "N\u0101\u2019emeh",
        "\u0646\u0627\u06cc\u0645\u0647"
    ],
    "name:und_x_variant":[
        "N\u0101\u2019em\u012b",
        "N\u0101\u2019eh",
        "N\u0101\u012bmeh"
    ],
    "wof:name":"Na'emeh",
    "wof:placetype":"locality"
},
  "geometry": {"coordinates":[59.70696,32.14318],"type":"Point"}
}