{
  "type": "Feature",
  "properties": {
    "gn:admin1_code":"7",
    "gn:asciiname":"Par Eshkaft",
    "gn:country_code":"IR",
    "gn:dem":2327,
    "gn:feature_class":"P",
    "gn:feature_code":"PPL",
    "gn:name":"Par Eshkaft",
    "gn:population":0,
    "gn:timezone":"Asia/Tehran",
    "iso:country":"IR",
    "name:fas_x_preferred":[
        "\u067e\u0631 \u0627\u0634\u06a9\u0641\u062a"
    ],
    "name:und_x_variant":[
        "Per Eshkaf\u012b",
        "Per\u0101shkaft",
        "Per Eshkaft",
        "Par Eshkaft"
    ],
    "wof:name":"Par Eshkaft",
    "wof:placetype":"locality"
},
  "geometry": {"coordinates":[52.0753,29.6313],"type":"Point"}
}