{
  "type": "Feature",
  "properties": {
    "gn:admin1_code":"7.0",
    "gn:asciiname":"Tall Saman",
    "gn:country_code":"IR",
    "gn:dem":810,
    "gn:feature_class":"P",
    "gn:feature_code":"PPL",
    "gn:name":"Tall S\u0101m\u0101n",
    "gn:population":0,
    "gn:timezone":"Asia/Tehran",
    "iso:country":"IR",
    "name:fas_x_preferred":[
        "Tall S\u0101m\u0101n"
    ],
    "name:fas_x_variant":[
        "\u062a\u0644 \u0633\u0627\u0645\u0627\u0646"
    ],
    "name:msa_x_preferred":[
        "Tall Saman"
    ],
    "wof:name":"Tall Saman",
    "wof:placetype":"locality"
},
  "geometry": {"coordinates":[51.72955,29.26667],"type":"Point"}
}