{
  "type": "Feature",
  "properties": {
    "gn:admin1_code":"29",
    "gn:asciiname":"Hemmatabad",
    "gn:country_code":"IR",
    "gn:dem":720,
    "gn:feature_class":"P",
    "gn:feature_code":"PPL",
    "gn:name":"Hemmat\u0101b\u0101d",
    "gn:population":0,
    "gn:timezone":"Asia/Tehran",
    "iso:country":"IR",
    "name:ara_x_preferred":[
        "\u0647\u0645\u062a \u0623\u0628\u0627\u062f"
    ],
    "name:aze_x_preferred":[
        "H\u00fcmm\u0259tabad"
    ],
    "name:fas_x_preferred":[
        "\u0647\u0645\u062a \u0622\u0628\u0627\u062f"
    ],
    "name:fas_x_variant":[
        "Hemmat\u0101b\u0101d",
        "\u0647\u0645\u062a \u0622\u0628\u0627\u062f \u0648\u0627\u0647\u0628",
        "\u0647\u0645\u062a\u200c\u0622\u0628\u0627\u062f"
    ],
    "name:ita_x_preferred":[
        "Hemmatabad"
    ],
    "name:mlg_x_preferred":[
        "Hemmatabad"
    ],
    "name:tur_x_preferred":[
        "Himmetabad"
    ],
    "name:und_x_variant":[
        "Hemmat\u0101b\u0101d-e V\u0101heb"
    ],
    "wof:name":"Hemmatabad",
    "wof:placetype":"locality"
},
  "geometry": {"coordinates":[58.8528,28.7674],"type":"Point"}
}