{
  "type": "Feature",
  "properties": {
    "gn:admin1_code":"42.0",
    "gn:asciiname":"Mazra`eh-ye Shahid Qasem-e Pur",
    "gn:country_code":"IR",
    "gn:dem":922,
    "gn:feature_class":"P",
    "gn:feature_code":"PPLF",
    "gn:name":"Mazra\u2018eh-ye Shah\u012bd Q\u0101sem-e P\u016br",
    "gn:population":0,
    "gn:timezone":"Asia/Tehran",
    "iso:country":"IR",
    "name:fas_x_preferred":[
        "\u0645\u0632\u0631\u0639\u0647 \u0634\u0647\u064a\u062f \u0642\u0627\u0633\u0645 \u067e\u0648\u0631"
    ],
    "name:und_x_variant":[
        "Mazra\u2018eh-ye Shah\u012bd Q\u0101sem-e P\u016br"
    ],
    "wof:name":"Mazra`eh-ye Shahid Qasem-e Pur",
    "wof:placetype":"locality"
},
  "geometry": {"coordinates":[57.46959,33.76418],"type":"Point"}
}