{
  "type": "Feature",
  "properties": {
    "gn:admin1_code":"8",
    "gn:asciiname":"Shakuh",
    "gn:country_code":"IR",
    "gn:dem":-19,
    "gn:feature_class":"P",
    "gn:feature_code":"PPL",
    "gn:name":"Sh\u0101k\u016bh",
    "gn:population":0,
    "gn:timezone":"Asia/Tehran",
    "iso:country":"IR",
    "name:fas_x_preferred":[
        "\u0634\u0627\u06a9\u0648\u0647"
    ],
    "name:fas_x_variant":[
        "Sh\u0101k\u016bh"
    ],
    "wof:name":"Shakuh",
    "wof:placetype":"locality"
},
  "geometry": {"coordinates":[49.1456,37.5965],"type":"Point"}
}