{
  "type": "Feature",
  "properties": {
    "gn:admin1_code":"29",
    "gn:asciiname":"Bozar-e Bala",
    "gn:cc2":"IR",
    "gn:country_code":"IR",
    "gn:dem":2125,
    "gn:feature_class":"P",
    "gn:feature_code":"PPL",
    "gn:name":"Boz\u0101r-e B\u0101l\u0101",
    "gn:population":0,
    "gn:timezone":"Asia/Tehran",
    "iso:country":"IR",
    "name:fas_x_preferred":[
        "Boz\u0101r-e B\u0101l\u0101"
    ],
    "name:und_x_variant":[
        "Bez\u0101r B\u0101l\u0101",
        "Bez\u0101r-e B\u0101l\u0101"
    ],
    "wof:name":"Bozar-e Bala",
    "wof:placetype":"locality"
},
  "geometry": {"coordinates":[56.54083000000001,28.74722],"type":"Point"}
}