{
  "type": "Feature",
  "properties": {
    "gn:admin1_code":"35.0",
    "gn:asciiname":"Pa'in Basra",
    "gn:country_code":"IR",
    "gn:dem":-4,
    "gn:feature_class":"P",
    "gn:feature_code":"PPL",
    "gn:name":"P\u0101\u2019\u012bn Ba\u015fr\u0101",
    "gn:population":0,
    "gn:timezone":"Asia/Tehran",
    "iso:country":"IR",
    "name:fas_x_preferred":[
        "\u067e\u0627\u0626\u064a\u0646 \u0628\u0635\u0631\u0627"
    ],
    "name:fas_x_variant":[
        "\u067e\u0627\u0626\u064a\u0646 \u0628\u064e\u0635\u0631\u0650\u0647",
        "P\u0101\u2019\u012bn Ba\u015fr\u0101"
    ],
    "name:und_x_variant":[
        "P\u0101\u2019\u012bn Ba\u015freh"
    ],
    "wof:name":"Pa'in Basra",
    "wof:placetype":"locality"
},
  "geometry": {"coordinates":[52.58689,36.56327],"type":"Point"}
}