{
  "type": "Feature",
  "properties": {
    "gn:admin1_code":"13",
    "gn:asciiname":"Sheykheh",
    "gn:country_code":"IR",
    "gn:dem":1320,
    "gn:feature_class":"P",
    "gn:feature_code":"PPL",
    "gn:name":"Sheykheh",
    "gn:population":0,
    "gn:timezone":"Asia/Tehran",
    "iso:country":"IR",
    "name:fas_x_preferred":[
        "\u0634\u06cc\u062e\u0647"
    ],
    "name:fas_x_variant":[
        "S\u012b\u0101h S\u012b\u0101h-ye Sheykheh"
    ],
    "name:und_x_variant":[
        "S\u012b\u0101 S\u012b\u0101",
        "Siahsia",
        "S\u012b\u0101 S\u012b\u0101-ye Sheykheh",
        "Sheykheh"
    ],
    "wof:name":"Sheykheh",
    "wof:placetype":"locality"
},
  "geometry": {"coordinates":[46.6123,34.0082],"type":"Point"}
}