{
  "type": "Feature",
  "properties": {
    "gn:admin1_code":"9.0",
    "gn:asciiname":"Baba Nazar",
    "gn:country_code":"IR",
    "gn:dem":1876,
    "gn:feature_class":"P",
    "gn:feature_code":"PPL",
    "gn:name":"B\u0101b\u0101 Naz\u0327ar",
    "gn:population":0,
    "gn:timezone":"Asia/Tehran",
    "iso:country":"IR",
    "name:fas_x_preferred":[
        "\u0628\u0627\u0628\u0627 \u0646\u0638\u0631"
    ],
    "name:fas_x_variant":[
        "B\u0101b\u0101 Naz\u0327ar",
        "\u0628\u0627\u0628\u0627\u0646\u0638\u0631"
    ],
    "name:msa_x_preferred":[
        "Baba Nazar"
    ],
    "wof:name":"Baba Nazar",
    "wof:placetype":"locality"
},
  "geometry": {"coordinates":[48.699,35.46149000000001],"type":"Point"}
}