{
  "type": "Feature",
  "properties": {
    "gn:admin1_code":"3",
    "gn:asciiname":"Gusheh",
    "gn:country_code":"IR",
    "gn:dem":1521,
    "gn:feature_class":"P",
    "gn:feature_code":"PPL",
    "gn:name":"G\u016bsheh",
    "gn:population":0,
    "gn:timezone":"Asia/Tehran",
    "iso:country":"IR",
    "name:ceb_x_preferred":[
        "Gusheh"
    ],
    "name:fas_x_preferred":[
        "G\u016bsheh"
    ],
    "name:fas_x_variant":[
        "\u06af\u0648\u0634\u0647"
    ],
    "name:swe_x_preferred":[
        "Gusheh"
    ],
    "wof:name":"Gusheh",
    "wof:placetype":"locality"
},
  "geometry": {"coordinates":[50.73407,31.51245],"type":"Point"}
}