{
  "type": "Feature",
  "properties": {
    "gn:admin1_code":"33",
    "gn:asciiname":"Bashkand",
    "gn:country_code":"IR",
    "gn:dem":2372,
    "gn:feature_class":"P",
    "gn:feature_code":"PPL",
    "gn:name":"B\u0101shkand",
    "gn:population":0,
    "gn:timezone":"Asia/Tehran",
    "iso:country":"IR",
    "name:ara_x_preferred":[
        "\u0628\u0627\u0634\u06a9\u0646\u062f"
    ],
    "name:azb_x_preferred":[
        "\u0628\u0627\u0634\u06a9\u0646\u062f"
    ],
    "name:fas_x_preferred":[
        "\u0628\u0627\u0634\u06a9\u0646\u062f"
    ],
    "name:fas_x_variant":[
        "B\u0101sh Kand",
        "B\u0101shkand"
    ],
    "name:msa_x_preferred":[
        "Bashkand"
    ],
    "name:tur_x_preferred":[
        "Ba\u015fkent"
    ],
    "wof:name":"Bashkand",
    "wof:placetype":"locality"
},
  "geometry": {"coordinates":[47.1049,37.789],"type":"Point"}
}