{
  "type": "Feature",
  "properties": {
    "gn:admin1_code":"32",
    "gn:asciiname":"Tajaraq",
    "gn:country_code":"IR",
    "gn:dem":1597,
    "gn:feature_class":"P",
    "gn:feature_code":"PPL",
    "gn:name":"Tajaraq",
    "gn:population":0,
    "gn:timezone":"Asia/Tehran",
    "iso:country":"IR",
    "name:fas_x_preferred":[
        "\u062a\u062c\u0631\u0642"
    ],
    "name:msa_x_preferred":[
        "Tajaraq"
    ],
    "name:mzn_x_preferred":[
        "\u062a\u062c\u0631\u0642"
    ],
    "wof:name":"Tajaraq",
    "wof:placetype":"locality"
},
  "geometry": {"coordinates":[48.0496,38.0826],"type":"Point"}
}