{
  "type": "Feature",
  "properties": {
    "gn:admin1_code":"35",
    "gn:asciiname":"Herteh Kola",
    "gn:country_code":"IR",
    "gn:dem":-4,
    "gn:feature_class":"P",
    "gn:feature_code":"PPL",
    "gn:name":"Her\u0163eh Kol\u0101",
    "gn:population":0,
    "gn:timezone":"Asia/Tehran",
    "iso:country":"IR",
    "name:ara_x_preferred":[
        "\u0647\u0631\u0637\u0647\u0643\u0644\u0627"
    ],
    "name:fas_x_preferred":[
        "Her\u0163eh Kol\u0101"
    ],
    "name:fas_x_variant":[
        "Hart Kol\u0101",
        "\u0647\u0631\u062a \u0643\u0644\u0627",
        "\u0647\u0631\u0637\u0647 \u06a9\u0644\u0627",
        "\u0647\u0631\u062f\u0647 \u06a9\u0644\u0627",
        "\u0647\u0631\u0637\u0647\u200c\u06a9\u0644\u0627"
    ],
    "name:und_x_variant":[
        "Hart Kol\u0101",
        "Hert Kal\u0101",
        "\u0647\u0631\u062a \u0643\u0644\u0627",
        "Hardeh Kol\u0101"
    ],
    "wof:name":"Herteh Kola",
    "wof:placetype":"locality"
},
  "geometry": {"coordinates":[51.35129000000001,36.67028],"type":"Point"}
}