{
  "type": "Feature",
  "properties": {
    "gn:admin1_code":"29",
    "gn:asciiname":"Gazgun",
    "gn:country_code":"IR",
    "gn:dem":646,
    "gn:feature_class":"P",
    "gn:feature_code":"PPLL",
    "gn:name":"Gazg\u016bn",
    "gn:population":0,
    "gn:timezone":"Asia/Tehran",
    "iso:country":"IR",
    "name:fas_x_preferred":[
        "\u06af\u0632\u06af\u0648\u0646"
    ],
    "name:fas_x_variant":[
        "Gazg\u016bn"
    ],
    "wof:name":"Gazgun",
    "wof:placetype":"locality"
},
  "geometry": {"coordinates":[58.28988,27.06929],"type":"Point"}
}