{
  "type": "Feature",
  "properties": {
    "gn:admin1_code":"32",
    "gn:asciiname":"Jabbarlu",
    "gn:country_code":"IR",
    "gn:dem":1230,
    "gn:feature_class":"P",
    "gn:feature_code":"PPL",
    "gn:name":"Jabb\u0101rl\u016b",
    "gn:population":0,
    "gn:timezone":"Asia/Tehran",
    "iso:country":"IR",
    "name:fas_x_preferred":[
        "\u062c\u0628\u0627\u0631\u0644\u0648"
    ],
    "name:fas_x_variant":[
        "Jabb\u0101rl\u016b"
    ],
    "wof:name":"Jabbarlu",
    "wof:placetype":"locality"
},
  "geometry": {"coordinates":[47.98,38.6022],"type":"Point"}
}