{
  "type": "Feature",
  "properties": {
    "gn:admin1_code":"33",
    "gn:asciiname":"Qarah Bolagh",
    "gn:country_code":"IR",
    "gn:dem":2090,
    "gn:elevation":"0.0",
    "gn:feature_class":"P",
    "gn:feature_code":"PPL",
    "gn:name":"Qarah Bol\u0101gh",
    "gn:population":0,
    "gn:timezone":"Asia/Tehran",
    "iso:country":"IR",
    "name:ceb_x_preferred":[
        "Qarah Bolagh"
    ],
    "name:fas_x_preferred":[
        "\u0642\u0631\u0647 \u0628\u0644\u0627\u063a"
    ],
    "name:fas_x_variant":[
        "Qareh Bol\u0101gh",
        "Qarah Bol\u0101gh",
        "\u0642\u0631\u0647\u200c\u0628\u0644\u0627\u063a"
    ],
    "name:swe_x_preferred":[
        "Qarah Bolagh"
    ],
    "wof:name":"Qarah Bolagh",
    "wof:placetype":"locality"
},
  "geometry": {"coordinates":[47.3478,38.1354],"type":"Point"}
}