{
  "type": "Feature",
  "properties": {
    "gn:admin1_code":"22",
    "gn:asciiname":"Ravani",
    "gn:country_code":"IR",
    "gn:dem":36,
    "gn:feature_class":"P",
    "gn:feature_code":"PPL",
    "gn:name":"Ravan\u012b",
    "gn:population":0,
    "gn:timezone":"Asia/Tehran",
    "iso:country":"IR",
    "name:fas_x_preferred":[
        "\u0631\u0648\u0627\u0646\u06cc"
    ],
    "name:fas_x_variant":[
        "Rav\u0101n\u012b",
        "\u0631\u0648\u0646\u06cc"
    ],
    "name:und_x_variant":[
        "Bavuni",
        "Ravuni",
        "Rayani",
        "Ravan\u012b"
    ],
    "wof:name":"Ravani",
    "wof:placetype":"locality"
},
  "geometry": {"coordinates":[50.8466,28.8959],"type":"Point"}
}