{
  "type": "Feature",
  "properties": {
    "gn:admin1_code":"28.0",
    "gn:asciiname":"Talkhvoncheh",
    "gn:country_code":"IR",
    "gn:dem":1727,
    "gn:feature_class":"P",
    "gn:feature_code":"PPL",
    "gn:name":"\u0162\u0101lkhvoncheh",
    "gn:population":0,
    "gn:timezone":"Asia/Tehran",
    "iso:country":"IR",
    "name:fas_x_preferred":[
        "\u0637\u0627\u0644\u062e\u0648\u0646\u0686\u0647"
    ],
    "name:fas_x_variant":[
        "\u0162\u0101lkhvoncheh",
        "\u0162\u0101lkh\u016bncheh"
    ],
    "name:und_x_variant":[
        "\u0637\u0627\u0644\u062e\u0648\u0646\u0686\u0647"
    ],
    "wof:name":"Talkhvoncheh",
    "wof:placetype":"locality"
},
  "geometry": {"coordinates":[51.56231,32.26303],"type":"Point"}
}