{
  "type": "Feature",
  "properties": {
    "gn:admin1_code":"35.0",
    "gn:asciiname":"Asb Tajnan",
    "gn:country_code":"IR",
    "gn:dem":1875,
    "gn:feature_class":"P",
    "gn:feature_code":"PPL",
    "gn:name":"Asb T\u0101jn\u0101n",
    "gn:population":0,
    "gn:timezone":"Asia/Tehran",
    "iso:country":"IR",
    "name:fas_x_preferred":[
        "\u0627\u064e\u0633\u0628 \u062a\u0627\u062c\u0646\u0627\u0646"
    ],
    "name:und_x_variant":[
        "Asb T\u0101jn\u0101n"
    ],
    "wof:name":"Asb Tajnan",
    "wof:placetype":"locality"
},
  "geometry": {"coordinates":[53.91667,36.46667],"type":"Point"}
}