{
  "type": "Feature",
  "properties": {
    "gn:admin1_code":"1",
    "gn:asciiname":"Shur Bolagh",
    "gn:country_code":"IR",
    "gn:dem":1845,
    "gn:feature_class":"P",
    "gn:feature_code":"PPL",
    "gn:name":"Sh\u016br Bol\u0101gh",
    "gn:population":0,
    "gn:timezone":"Asia/Tehran",
    "iso:country":"IR",
    "name:fas_x_preferred":[
        "\u0634\u0648\u0631\u0628\u064f\u0644\u0627\u063a"
    ],
    "name:fas_x_variant":[
        "\u0634\u0648\u0631 \u0628\u0644\u0627\u063a",
        "Sh\u016brbol\u0101gh",
        "Sh\u016br Bol\u0101gh"
    ],
    "wof:name":"Shur Bolagh",
    "wof:placetype":"locality"
},
  "geometry": {"coordinates":[44.6093,39.0748],"type":"Point"}
}