{
  "type": "Feature",
  "properties": {
    "gn:admin1_code":"29",
    "gn:asciiname":"Tolombeh-ye Deh Panah",
    "gn:country_code":"IR",
    "gn:dem":1663,
    "gn:feature_class":"P",
    "gn:feature_code":"PPL",
    "gn:name":"Tolombeh-ye Deh Pan\u0101h",
    "gn:population":0,
    "gn:timezone":"Asia/Tehran",
    "iso:country":"IR",
    "name:ceb_x_preferred":[
        "Tolombeh-ye Deh Pan\u0101h"
    ],
    "name:fas_x_preferred":[
        "\u062a\u0644\u0645\u0628\u0647 \u062f\u0647 \u067e\u0646\u0627\u0647"
    ],
    "name:fas_x_variant":[
        "Deh Pan\u0101h",
        "Tolombeh-ye Deh Pan\u0101h"
    ],
    "name:swe_x_preferred":[
        "Tolombeh-ye Deh Pan\u0101h"
    ],
    "name:und_x_variant":[
        "Q\u0101sem\u0101b\u0101d-e Deh Pan\u0101h"
    ],
    "wof:name":"Tolombeh-ye Deh Panah",
    "wof:placetype":"locality"
},
  "geometry": {"coordinates":[56.4374,30.3354],"type":"Point"}
}