{
  "type": "Feature",
  "properties": {
    "gn:admin1_code":"33",
    "gn:asciiname":"Qal`eh Cheh",
    "gn:country_code":"IR",
    "gn:dem":1377,
    "gn:feature_class":"P",
    "gn:feature_code":"PPL",
    "gn:name":"Qal\u2018eh Cheh",
    "gn:population":0,
    "gn:timezone":"Asia/Tehran",
    "iso:country":"IR",
    "name:fas_x_preferred":[
        "\u0642\u0644\u0639\u0647 \u0686\u0647"
    ],
    "name:und_x_variant":[
        "Kalacha",
        "Ghal\u2019eh Cheh",
        "Qal\u2018eh Cheh"
    ],
    "wof:name":"Qal`eh Cheh",
    "wof:placetype":"locality"
},
  "geometry": {"coordinates":[46.12595,38.01608],"type":"Point"}
}