{
  "type": "Feature",
  "properties": {
    "gn:admin1_code":"29",
    "gn:asciiname":"Shahid Soleymani",
    "gn:country_code":"IR",
    "gn:dem":2100,
    "gn:feature_class":"P",
    "gn:feature_code":"PPL",
    "gn:name":"Shah\u012bd Soleym\u0101n\u012b",
    "gn:population":0,
    "gn:timezone":"Asia/Tehran",
    "iso:country":"IR",
    "name:fas_x_preferred":[
        "\u0634\u0647\u06cc\u062f \u0633\u0644\u06cc\u0645\u0627\u0646\u06cc"
    ],
    "name:fas_x_variant":[
        "Shah\u012bd Soleym\u0101n\u012b"
    ],
    "wof:name":"Shahid Soleymani",
    "wof:placetype":"locality"
},
  "geometry": {"coordinates":[56.7025,29.8028],"type":"Point"}
}