{
  "type": "Feature",
  "properties": {
    "gn:admin1_code":"15",
    "gn:asciiname":"Sij",
    "gn:country_code":"IR",
    "gn:dem":387,
    "gn:feature_class":"P",
    "gn:feature_code":"PPL",
    "gn:name":"S\u012bj",
    "gn:population":0,
    "gn:timezone":"Asia/Tehran",
    "iso:country":"IR",
    "name:fas_x_preferred":[
        "S\u012bch"
    ],
    "name:fas_x_variant":[
        "\u0633\u06cc\u0686",
        "\u0633\u06cc\u062c"
    ],
    "name:und_x_variant":[
        "S\u012bj"
    ],
    "wof:name":"Sij",
    "wof:placetype":"locality"
},
  "geometry": {"coordinates":[48.2894,32.69697],"type":"Point"}
}