{
  "type": "Feature",
  "properties": {
    "gn:admin1_code":"26.0",
    "gn:asciiname":"`Asgarabad",
    "gn:country_code":"IR",
    "gn:dem":811,
    "gn:feature_class":"P",
    "gn:feature_code":"PPL",
    "gn:name":"\u2018Asgar\u0101b\u0101d",
    "gn:population":0,
    "gn:timezone":"Asia/Tehran",
    "iso:country":"IR",
    "name:fas_x_preferred":[
        "\u0639\u0633\u06af\u0631 \u0622\u0628\u0627\u062f"
    ],
    "name:fas_x_variant":[
        "\u0639\u0633\u0643\u0631 \u0622\u0628\u0627\u062f",
        "\u2018Asgar\u0101b\u0101d",
        "\u2018Askar\u0101b\u0101d"
    ],
    "wof:name":"`Asgarabad",
    "wof:placetype":"locality"
},
  "geometry": {"coordinates":[51.7768,35.1645],"type":"Point"}
}