{
  "type": "Feature",
  "properties": {
    "gn:admin1_code":"7",
    "gn:asciiname":"Qal`eh Sohrab",
    "gn:country_code":"IR",
    "gn:dem":474,
    "gn:feature_class":"P",
    "gn:feature_code":"PPL",
    "gn:name":"Qal\u2018eh Sohr\u0101b",
    "gn:population":0,
    "gn:timezone":"Asia/Tehran",
    "iso:country":"IR",
    "name:fas_x_preferred":[
        "\u0642\u0644\u0639\u0647 \u0633\u0647\u0631\u0627\u0628"
    ],
    "name:fas_x_variant":[
        "Sohr\u0101b",
        "Qal\u2018eh Sohr\u0101b"
    ],
    "wof:name":"Qal`eh Sohrab",
    "wof:placetype":"locality"
},
  "geometry": {"coordinates":[53.26031,27.51085],"type":"Point"}
}