{
  "type": "Feature",
  "properties": {
    "gn:admin1_code":"29",
    "gn:asciiname":"Chah-e Reza",
    "gn:country_code":"IR",
    "gn:dem":401,
    "gn:feature_class":"P",
    "gn:feature_code":"PPL",
    "gn:name":"Ch\u0101h-e Re\u1e95\u0101",
    "gn:population":0,
    "gn:timezone":"Asia/Tehran",
    "iso:country":"IR",
    "name:fas_x_preferred":[
        "\u0686\u0627\u0647 \u0631\u0636\u0627"
    ],
    "name:fas_x_variant":[
        "Ch\u0101h-e Re\u1e95\u0101"
    ],
    "wof:name":"Chah-e Reza",
    "wof:placetype":"locality"
},
  "geometry": {"coordinates":[58.1374,27.33882],"type":"Point"}
}