{
  "type": "Feature",
  "properties": {
    "gn:admin1_code":"28",
    "gn:asciiname":"Barzabad",
    "gn:country_code":"IR",
    "gn:dem":1605,
    "gn:feature_class":"P",
    "gn:feature_code":"PPL",
    "gn:name":"Barz\u0101b\u0101d",
    "gn:population":0,
    "gn:timezone":"Asia/Tehran",
    "iso:country":"IR",
    "name:fas_x_preferred":[
        "\u0628\u0631\u0632 \u0622\u0628\u0627\u062f"
    ],
    "name:fas_x_variant":[
        "Barz\u0101b\u0101d",
        "\u0628\u0631\u0632\u0622\u0628\u0627\u062f"
    ],
    "wof:name":"Barzabad",
    "wof:placetype":"locality"
},
  "geometry": {"coordinates":[53.1609,32.6904],"type":"Point"}
}