{
  "type": "Feature",
  "properties": {
    "gn:admin1_code":"15.0",
    "gn:asciiname":"Tarfian",
    "gn:country_code":"IR",
    "gn:dem":92,
    "gn:feature_class":"P",
    "gn:feature_code":"PPL",
    "gn:name":"Tarf\u012b\u0101n",
    "gn:population":0,
    "gn:timezone":"Asia/Tehran",
    "iso:country":"IR",
    "name:fas_x_preferred":[
        "\u062a\u0631\u0641\u06cc\u0627\u0646"
    ],
    "name:und_x_variant":[
        "Tarf\u012b\u0101n"
    ],
    "wof:name":"Tarfian",
    "wof:placetype":"locality"
},
  "geometry": {"coordinates":[48.28617,32.26705],"type":"Point"}
}