{
  "type": "Feature",
  "properties": {
    "gn:admin1_code":"1",
    "gn:asciiname":"Sadr",
    "gn:country_code":"IR",
    "gn:dem":2121,
    "gn:feature_class":"P",
    "gn:feature_code":"PPL",
    "gn:name":"\u015eadr",
    "gn:population":0,
    "gn:timezone":"Asia/Tehran",
    "iso:country":"IR",
    "name:ara_x_preferred":[
        "\u0635\u062f\u0631"
    ],
    "name:ceb_x_preferred":[
        "Sadr"
    ],
    "name:deu_x_preferred":[
        "Sadr"
    ],
    "name:fas_x_preferred":[
        "\u015eadr"
    ],
    "name:fas_x_variant":[
        "\u0635\u062f\u0631"
    ],
    "name:fra_x_preferred":[
        "Sadr"
    ],
    "name:heb_x_preferred":[
        "\u05e1\u05d0\u05d3\u05e8"
    ],
    "name:jav_x_preferred":[
        "Dhadha"
    ],
    "name:pag_x_preferred":[
        "Pageo"
    ],
    "name:rus_x_preferred":[
        "\u0421\u0430\u0434\u0440"
    ],
    "name:swe_x_preferred":[
        "Sadr"
    ],
    "name:urd_x_preferred":[
        "\u0635\u062f\u0631"
    ],
    "wof:name":"Sadr",
    "wof:placetype":"locality"
},
  "geometry": {"coordinates":[44.324,38.8862],"type":"Point"}
}