{
  "type": "Feature",
  "properties": {
    "gn:admin1_code":"1",
    "gn:asciiname":"Sadr",
    "gn:country_code":"IR",
    "gn:dem":2121,
    "gn:feature_class":"P",
    "gn:feature_code":"PPL",
    "gn:name":"\u015eadr",
    "gn:population":0,
    "gn:timezone":"Asia/Tehran",
    "iso:country":"IR",
    "name:fas_x_preferred":[
        "\u015eadr"
    ],
    "name:fas_x_variant":[
        "\u0635\u062f\u0631"
    ],
    "name:und_x_variant":[
        "\u0635\u062f\u0631"
    ],
    "wof:name":"Sadr",
    "wof:placetype":"locality"
},
  "geometry": {"coordinates":[44.324,38.8862],"type":"Point"}
}