{
  "type": "Feature",
  "properties": {
    "gn:admin1_code":"4",
    "gn:asciiname":"Sul",
    "gn:country_code":"IR",
    "gn:dem":13,
    "gn:feature_class":"P",
    "gn:feature_code":"PPL",
    "gn:name":"S\u016bl",
    "gn:population":0,
    "gn:timezone":"Asia/Tehran",
    "iso:country":"IR",
    "name:fas_x_preferred":[
        "S\u016bl"
    ],
    "name:fas_x_variant":[
        "\u0633\u0648\u0644"
    ],
    "name:und_x_variant":[
        "S\u0101vol",
        "Sool"
    ],
    "wof:name":"Sul",
    "wof:placetype":"locality"
},
  "geometry": {"coordinates":[59.28025,25.60986],"type":"Point"}
}