{
  "type": "Feature",
  "properties": {
    "gn:admin1_code":"4.0",
    "gn:asciiname":"Michi Govash",
    "gn:country_code":"IR",
    "gn:dem":223,
    "gn:feature_class":"P",
    "gn:feature_code":"PPL",
    "gn:name":"M\u012bch\u012b Gov\u0101sh",
    "gn:population":0,
    "gn:timezone":"Asia/Tehran",
    "iso:country":"IR",
    "name:fas_x_preferred":[
        "\u0645\u064a\u0686\u06cc \u06af\u0648\u0627\u0634"
    ],
    "name:und_x_variant":[
        "M\u012bch\u012b Gov\u0101sh",
        "Machg\u016b\u0101sh"
    ],
    "wof:name":"Michi Govash",
    "wof:placetype":"locality"
},
  "geometry": {"coordinates":[60.51971,25.99259],"type":"Point"}
}