{
  "type": "Feature",
  "properties": {
    "gn:admin1_code":"4.0",
    "gn:asciiname":"Qaderabad",
    "gn:country_code":"IR",
    "gn:dem":1957,
    "gn:feature_class":"P",
    "gn:feature_code":"PPL",
    "gn:name":"Q\u0101der\u0101b\u0101d",
    "gn:population":0,
    "gn:timezone":"Asia/Tehran",
    "iso:country":"IR",
    "name:fas_x_preferred":[
        "Q\u0101der\u0101b\u0101d"
    ],
    "wof:name":"Qaderabad",
    "wof:placetype":"locality"
},
  "geometry": {"coordinates":[60.72889,28.83917000000001],"type":"Point"}
}