{
  "type": "Feature",
  "properties": {
    "gn:admin1_code":"1",
    "gn:asciiname":"Sheykhlar-e Mazari",
    "gn:country_code":"IR",
    "gn:dem":1663,
    "gn:feature_class":"P",
    "gn:feature_code":"PPL",
    "gn:name":"Sheykhlar-e Maz\u0101r\u012b",
    "gn:population":0,
    "gn:timezone":"Asia/Tehran",
    "iso:country":"IR",
    "name:fas_x_preferred":[
        "\u0634\u06cc\u062e \u0644\u0631 \u0645\u0632\u0627\u0631\u06cc"
    ],
    "name:fas_x_variant":[
        "\u0634\u0650\u064a\u062e\u0644\u064e\u0631\u0650 \u0645\u064e\u0632\u0627\u0631\u06cc",
        "Sheykhlar-e Maz\u0101r\u012b"
    ],
    "wof:name":"Sheykhlar-e Mazari",
    "wof:placetype":"locality"
},
  "geometry": {"coordinates":[45.0455,37.4375],"type":"Point"}
}