{
  "type": "Feature",
  "properties": {
    "gn:admin1_code":"5",
    "gn:asciiname":"`Azizi-ye Sofla",
    "gn:country_code":"IR",
    "gn:dem":1103,
    "gn:feature_class":"P",
    "gn:feature_code":"PPL",
    "gn:name":"\u2018Az\u012bz\u012b-ye Sofl\u00e1",
    "gn:population":0,
    "gn:timezone":"Asia/Tehran",
    "iso:country":"IR",
    "name:fas_x_preferred":[
        "\u0639\u064e\u0632\u064a\u0632\u0626 \u067e\u0627\u0626\u064a\u0646"
    ],
    "name:fas_x_variant":[
        "\u2018Az\u012bz\u012b-ye Sofl\u00e1",
        "\u2018Az\u012bz\u012b-ye P\u0101\u2019\u012bn",
        "\u0639\u0632\u06cc\u0632\u06cc \u0633\u0641\u0644\u06cc"
    ],
    "wof:name":"`Azizi-ye Sofla",
    "wof:placetype":"locality"
},
  "geometry": {"coordinates":[50.82567,30.79946],"type":"Point"}
}