{
  "type": "Feature",
  "properties": {
    "gn:admin1_code":"42",
    "gn:asciiname":"Mohammad Taqi Beyg",
    "gn:country_code":"IR",
    "gn:dem":990,
    "gn:feature_class":"P",
    "gn:feature_code":"PPL",
    "gn:name":"Mo\u1e29ammad Taq\u012b Beyg",
    "gn:population":0,
    "gn:timezone":"Asia/Tehran",
    "iso:country":"IR",
    "name:ara_x_preferred":[
        "\u0645\u062d\u0645\u062f \u062a\u0642\u064a \u0628\u064a\u063a"
    ],
    "name:ceb_x_preferred":[
        "Mo\u1e29ammad Taq\u012b Beyg"
    ],
    "name:fas_x_preferred":[
        "Mo\u1e29ammad Taq\u012b Beyg"
    ],
    "name:fas_x_variant":[
        "\u0645\u062d\u0645\u062f\u062a\u0642\u06cc \u0628\u06cc\u06af"
    ],
    "name:swe_x_preferred":[
        "Mo\u1e29ammad Taq\u012b Beyg"
    ],
    "name:und_x_variant":[
        "During\u0101r",
        "Mo\u1e29ammad Taq\u012b Bag",
        "Dor\u016bngar"
    ],
    "wof:name":"Mohammad Taqi Beyg",
    "wof:placetype":"locality"
},
  "geometry": {"coordinates":[58.63944,37.61861],"type":"Point"}
}