{
  "type": "Feature",
  "properties": {
    "gn:admin1_code":"15",
    "gn:asciiname":"Sa'ad",
    "gn:country_code":"IR",
    "gn:dem":29,
    "gn:feature_class":"P",
    "gn:feature_code":"PPL",
    "gn:name":"Sa\u2019ad",
    "gn:population":0,
    "gn:timezone":"Asia/Tehran",
    "iso:country":"IR",
    "name:ces_x_preferred":[
        "Sa'ad"
    ],
    "name:fas_x_preferred":[
        "Sa\u2019ad"
    ],
    "name:fra_x_preferred":[
        "Sa'ad"
    ],
    "name:heb_x_preferred":[
        "\u05e1\u05e2\u05d3"
    ],
    "name:nno_x_preferred":[
        "Sa'ad kibbutz"
    ],
    "name:nor_x_preferred":[
        "Sa'ad kibbutz"
    ],
    "name:pol_x_preferred":[
        "Sa\u2019ad"
    ],
    "name:urd_x_preferred":[
        "\u0633\u0627\u062f"
    ],
    "wof:name":"Sa'ad",
    "wof:placetype":"locality"
},
  "geometry": {"coordinates":[48.61667,31.75],"type":"Point"}
}