{
  "type": "Feature",
  "properties": {
    "gn:admin1_code":"1.0",
    "gn:asciiname":"Toppozabad",
    "gn:country_code":"IR",
    "gn:dem":1300,
    "gn:feature_class":"P",
    "gn:feature_code":"PPL",
    "gn:name":"Toppoz\u0101b\u0101d",
    "gn:population":0,
    "gn:timezone":"Asia/Tehran",
    "iso:country":"IR",
    "name:fas_x_preferred":[
        "\u062a\u0648\u067e\u0632 \u0622\u0628\u0627\u062f"
    ],
    "name:fas_x_variant":[
        "Toppoz\u0101b\u0101d"
    ],
    "wof:name":"Toppozabad",
    "wof:placetype":"locality"
},
  "geometry": {"coordinates":[45.4298,36.9639],"type":"Point"}
}