{
  "type": "Feature",
  "properties": {
    "gn:admin1_code":"42.0",
    "gn:asciiname":"Delqand",
    "gn:country_code":"IR",
    "gn:dem":946,
    "gn:feature_class":"P",
    "gn:feature_code":"PPL",
    "gn:name":"Delqand",
    "gn:population":0,
    "gn:timezone":"Asia/Tehran",
    "iso:country":"IR",
    "name:fas_x_preferred":[
        "\u062f\u0644\u0642\u0646\u062f"
    ],
    "name:und_x_variant":[
        "\u062f\u0644\u0642\u0646\u062f"
    ],
    "wof:name":"Delqand",
    "wof:placetype":"locality"
},
  "geometry": {"coordinates":[57.74714,36.19306],"type":"Point"}
}