{
  "type": "Feature",
  "properties": {
    "gn:admin1_code":"8",
    "gn:asciiname":"Pa'in Angulbak",
    "gn:country_code":"IR",
    "gn:dem":338,
    "gn:feature_class":"P",
    "gn:feature_code":"PPL",
    "gn:name":"P\u0101\u2019\u012bn Ang\u016blbak",
    "gn:population":0,
    "gn:timezone":"Asia/Tehran",
    "iso:country":"IR",
    "name:ceb_x_preferred":[
        "Ang\u016blvar"
    ],
    "name:fas_x_preferred":[
        "Ang\u016blvar"
    ],
    "name:fas_x_variant":[
        "\u0627\u0646\u06af\u0648\u0644\u0648\u0631",
        "\u067e\u0627\u0626\u06cc\u0646 \u0627\u0646\u06af\u0648\u0644\u0628\u06a9"
    ],
    "name:msa_x_preferred":[
        "Angulvar"
    ],
    "name:swe_x_preferred":[
        "Ang\u016blvar"
    ],
    "name:ukr_x_preferred":[
        "\u0410\u043d\u0491\u0443\u043b\u044c\u0432\u0430\u0440"
    ],
    "name:und_x_variant":[
        "Angolbar",
        "P\u0101\u2019\u012bn Ang\u016blbak"
    ],
    "wof:name":"Pa'in Angulbak",
    "wof:placetype":"locality"
},
  "geometry": {"coordinates":[49.86357,37.0607],"type":"Point"}
}