{
  "type": "Feature",
  "properties": {
    "gn:admin1_code":"32",
    "gn:asciiname":"Hasan Khan Darrehsi",
    "gn:country_code":"IR",
    "gn:dem":394,
    "gn:feature_class":"P",
    "gn:feature_code":"PPL",
    "gn:name":"\u1e28asan Khan Darrehs\u012b",
    "gn:population":0,
    "gn:timezone":"Asia/Tehran",
    "iso:country":"IR",
    "name:ara_x_preferred":[
        "\u062d\u0633\u0646 \u06a9\u0646\u062f\u064a \u062f\u0631\u0629 \u0633\u064a"
    ],
    "name:ceb_x_preferred":[
        "\u1e28asan Khan Darrehs\u012b"
    ],
    "name:fas_x_preferred":[
        "\u1e28asan Khan Darrehs\u012b"
    ],
    "name:fas_x_variant":[
        "\u062d\u064e\u0633\u064e\u0646 \u062e\u064e\u0646 \u062f\u064e\u0631\u0650\u0651\u0647\u0633\u06cc",
        "\u062d\u0633\u0646 \u062e\u0627\u0646 \u062f\u0631\u0647 \u0633\u06cc"
    ],
    "name:msa_x_preferred":[
        "Hasan Khan Darrehsi"
    ],
    "name:swe_x_preferred":[
        "\u1e28asan Khan Darrehs\u012b"
    ],
    "wof:name":"Hasan Khan Darrehsi",
    "wof:placetype":"locality"
},
  "geometry": {"coordinates":[47.83222,39.32972],"type":"Point"}
}