{
  "type": "Feature",
  "properties": {
    "gn:admin1_code":"7",
    "gn:asciiname":"Khik Andeh",
    "gn:country_code":"IR",
    "gn:dem":1406,
    "gn:feature_class":"P",
    "gn:feature_code":"PPL",
    "gn:name":"Kh\u012bk Andeh",
    "gn:population":0,
    "gn:timezone":"Asia/Tehran",
    "iso:country":"IR",
    "name:fas_x_preferred":[
        "Kh\u012bk Andeh"
    ],
    "name:fas_x_variant":[
        "\u062e\u06cc\u06a9 \u0627\u0646\u062f\u0647",
        "\u062e\u06cc\u06a9\u0646\u062f\u0647"
    ],
    "name:msa_x_preferred":[
        "Khik Andeh"
    ],
    "wof:name":"Khik Andeh",
    "wof:placetype":"locality"
},
  "geometry": {"coordinates":[51.27941,30.50641],"type":"Point"}
}