{
  "type": "Feature",
  "properties": {
    "gn:admin1_code":"23",
    "gn:asciiname":"Hoseynabad Shahivand",
    "gn:country_code":"IR",
    "gn:dem":1131,
    "gn:feature_class":"P",
    "gn:feature_code":"PPL",
    "gn:name":"\u1e28oseyn\u0101b\u0101d Sh\u0101h\u012bvand",
    "gn:population":0,
    "gn:timezone":"Asia/Tehran",
    "iso:country":"IR",
    "name:fas_x_preferred":[
        "\u0686\u0634\u0645\u0647 \u062c\u0627\u0645\u06cc\u0644\u0647"
    ],
    "name:fas_x_variant":[
        "Cheshmeh J\u0101m\u012bleh",
        "\u062d\u0633\u06cc\u0646 \u0622\u0628\u0627\u062f \u0634\u0627\u0647\u06cc\u0648\u0646\u062f"
    ],
    "name:und_x_variant":[
        "\u1e28oseyn\u0101b\u0101d Sh\u0101h\u012bvand"
    ],
    "wof:name":"Hoseynabad Shahivand",
    "wof:placetype":"locality"
},
  "geometry": {"coordinates":[47.83085,33.57545],"type":"Point"}
}