{
  "type": "Feature",
  "properties": {
    "gn:admin1_code":"16",
    "gn:asciiname":"Do Sineh",
    "gn:country_code":"IR",
    "gn:dem":1741,
    "gn:feature_class":"P",
    "gn:feature_code":"PPL",
    "gn:name":"Do S\u012bneh",
    "gn:population":0,
    "gn:timezone":"Asia/Tehran",
    "iso:country":"IR",
    "name:ara_x_preferred":[
        "\u062f\u0648\u0633\u064a\u0646\u0629"
    ],
    "name:ceb_x_preferred":[
        "Do S\u012bneh"
    ],
    "name:ckb_x_preferred":[
        "\u062f\u06d5\u0648\u0633\u06ce\u0646\u06d5"
    ],
    "name:fas_x_preferred":[
        "\u062f\u0648\u0633\u064a\u0646\u0650\u0647"
    ],
    "name:fas_x_variant":[
        "\u062f\u064f\u0648 \u0633\u064a\u0646\u0650\u0647",
        "\u062f\u0648 \u0633\u06cc\u0646\u0647",
        "D\u016bs\u012bneh",
        "Do S\u012bneh",
        "\u062f\u0648\u0633\u06cc\u0646\u0647"
    ],
    "name:swe_x_preferred":[
        "Do S\u012bneh"
    ],
    "wof:name":"Do Sineh",
    "wof:placetype":"locality"
},
  "geometry": {"coordinates":[46.0317,35.9833],"type":"Point"}
}