{
  "type": "Feature",
  "properties": {
    "gn:admin1_code":"4",
    "gn:asciiname":"Lulakdan",
    "gn:country_code":"IR",
    "gn:dem":698,
    "gn:feature_class":"P",
    "gn:feature_code":"PPL",
    "gn:name":"L\u016blakd\u0101n",
    "gn:population":0,
    "gn:timezone":"Asia/Tehran",
    "iso:country":"IR",
    "name:fas_x_preferred":[
        "\u0644\u0648\u0644\u06a9\u062f\u0627\u0646"
    ],
    "name:fas_x_variant":[
        "L\u016blakd\u0101n"
    ],
    "wof:name":"Lulakdan",
    "wof:placetype":"locality"
},
  "geometry": {"coordinates":[61.9721,28.4978],"type":"Point"}
}