{
  "type": "Feature",
  "properties": {
    "gn:admin1_code":"1",
    "gn:asciiname":"Yalquz Aghaj",
    "gn:country_code":"IR",
    "gn:dem":1291,
    "gn:feature_class":"P",
    "gn:feature_code":"PPL",
    "gn:name":"Y\u0101lq\u016bz \u0100gh\u0101j",
    "gn:population":0,
    "gn:timezone":"Asia/Tehran",
    "iso:country":"IR",
    "name:fas_x_preferred":[
        "\u06cc\u0627\u0644\u0642\u0648\u0632 \u0622\u063a\u0627\u062c"
    ],
    "name:fas_x_variant":[
        "Y\u0101lq\u016bz \u0100gh\u0101j",
        "\u06cc\u0627\u0644\u0642\u0648\u0632\u0622\u063a\u0627\u062c"
    ],
    "wof:name":"Yalquz Aghaj",
    "wof:placetype":"locality"
},
  "geometry": {"coordinates":[44.9393,38.2296],"type":"Point"}
}