{
  "type": "Feature",
  "properties": {
    "gn:admin1_code":"16.0",
    "gn:asciiname":"Bardeh Rash",
    "gn:country_code":"IR",
    "gn:dem":1365,
    "gn:feature_class":"P",
    "gn:feature_code":"PPL",
    "gn:name":"Bardeh Rash",
    "gn:population":0,
    "gn:timezone":"Asia/Tehran",
    "iso:country":"IR",
    "name:ckb_x_preferred":[
        "\u0628\u06d5\u0631\u062f\u06d5\u0695\u06d5\u0634"
    ],
    "name:fas_x_preferred":[
        "\u0628\u0631\u062f\u0647 \u0631\u0634"
    ],
    "name:fas_x_variant":[
        "\u0628\u0631\u062f\u0647\u200c\u0631\u0634"
    ],
    "wof:name":"Bardeh Rash",
    "wof:placetype":"locality"
},
  "geometry": {"coordinates":[45.5895,35.9893],"type":"Point"}
}