{
  "type": "Feature",
  "properties": {
    "gn:admin1_code":"4.0",
    "gn:asciiname":"Basut-e Pa'in",
    "gn:country_code":"IR",
    "gn:dem":25,
    "gn:feature_class":"P",
    "gn:feature_code":"PPL",
    "gn:name":"Bas\u016bt-e P\u0101\u2019\u012bn",
    "gn:population":0,
    "gn:timezone":"Asia/Tehran",
    "iso:country":"IR",
    "name:fas_x_preferred":[
        "Bas\u016bt"
    ],
    "name:fas_x_variant":[
        "Bas\u016bt-e P\u0101\u2019\u012bn",
        "\u0628\u0633\u0648\u062a \u067e\u0627\u0626\u06cc\u0646"
    ],
    "name:und_x_variant":[
        "\u0628\u0633\u0648\u062a \u067e\u0627\u0626\u06cc\u0646"
    ],
    "wof:name":"Basut-e Pa'in",
    "wof:placetype":"locality"
},
  "geometry": {"coordinates":[61.41831,25.53985],"type":"Point"}
}