{
  "type": "Feature",
  "properties": {
    "gn:admin1_code":"11",
    "gn:asciiname":"Jask",
    "gn:country_code":"IR",
    "gn:dem":5,
    "gn:feature_class":"P",
    "gn:feature_code":"PPLA2",
    "gn:name":"Jask",
    "gn:population":0,
    "gn:timezone":"Asia/Tehran",
    "iso:country":"IR",
    "name:eng_x_preferred":[
        "Jask"
    ],
    "name:fas_x_preferred":[
        "\u062c\u0627\u0633\u06a9"
    ],
    "name:fas_x_variant":[
        "\u0628\u0646\u062f\u0631\u0650 \u062c\u0627\u0633\u06a9",
        "J\u0101sk"
    ],
    "wof:name":"Jask",
    "wof:placetype":"locality"
},
  "geometry": {"coordinates":[57.77551999999999,25.64533],"type":"Point"}
}