{
  "type": "Feature",
  "properties": {
    "gn:admin1_code":"11",
    "gn:asciiname":"Jask",
    "gn:country_code":"IR",
    "gn:dem":5,
    "gn:feature_class":"P",
    "gn:feature_code":"PPLA2",
    "gn:name":"Jask",
    "gn:population":0,
    "gn:timezone":"Asia/Tehran",
    "iso:country":"IR",
    "name:ara_x_preferred":[
        "\u0628\u0646\u062f\u0631 \u062c\u0627\u0633\u0643"
    ],
    "name:azb_x_preferred":[
        "\u062c\u0627\u0633\u06a9"
    ],
    "name:aze_x_preferred":[
        "Cask"
    ],
    "name:cat_x_preferred":[
        "Jesaq"
    ],
    "name:ceb_x_preferred":[
        "J\u0101sk"
    ],
    "name:deu_x_preferred":[
        "Bandar-e Dschask"
    ],
    "name:eng_x_preferred":[
        "Jask"
    ],
    "name:epo_x_preferred":[
        "\u0134asko"
    ],
    "name:fas_x_preferred":[
        "\u062c\u0627\u0633\u06a9"
    ],
    "name:fas_x_variant":[
        "\u0628\u0646\u062f\u0631\u0650 \u062c\u0627\u0633\u06a9",
        "J\u0101sk",
        "\u0628\u0646\u062f\u0631 \u062c\u0627\u0633\u06a9"
    ],
    "name:ita_x_preferred":[
        "Bandar-e Jask"
    ],
    "name:kor_x_preferred":[
        "\uc790\uc2a4\ud06c"
    ],
    "name:mlg_x_preferred":[
        "Jask"
    ],
    "name:msa_x_preferred":[
        "Jask"
    ],
    "name:pnb_x_preferred":[
        "\u062c\u0627\u0633\u06a9"
    ],
    "name:pol_x_preferred":[
        "D\u017cask"
    ],
    "name:ron_x_preferred":[
        "Jask"
    ],
    "name:rus_x_preferred":[
        "\u0414\u0436\u0430\u0441\u043a"
    ],
    "name:swe_x_preferred":[
        "Bandar-e J\u0101sk"
    ],
    "name:tur_x_preferred":[
        "Cask"
    ],
    "name:urd_x_preferred":[
        "\u062c\u0627\u0633\u06a9"
    ],
    "name:zho_x_preferred":[
        "\u8cc8\u65af\u514b"
    ],
    "wof:name":"Jask",
    "wof:placetype":"locality"
},
  "geometry": {"coordinates":[57.77551999999999,25.64533],"type":"Point"}
}