{
  "type": "Feature",
  "properties": {
    "gn:admin1_code":"8.0",
    "gn:asciiname":"Pa'in Mahalleh-ye Marz Dasht",
    "gn:country_code":"IR",
    "gn:dem":-15,
    "gn:feature_class":"P",
    "gn:feature_code":"PPL",
    "gn:name":"P\u0101\u2019\u012bn Ma\u1e29alleh-ye Marz Dasht",
    "gn:population":0,
    "gn:timezone":"Asia/Tehran",
    "iso:country":"IR",
    "name:fas_x_preferred":[
        "\u067e\u0627\u0626\u06cc\u0646 \u0645\u062d\u0644\u0647 \u0645\u0631\u0632\u062f\u0634\u062a"
    ],
    "name:und_x_variant":[
        "P\u0101\u2019\u012bn Ma\u1e29alleh-ye Marz Dasht"
    ],
    "wof:name":"Pa'in Mahalleh-ye Marz Dasht",
    "wof:placetype":"locality"
},
  "geometry": {"coordinates":[49.68744,37.38291],"type":"Point"}
}