{
  "type": "Feature",
  "properties": {
    "gn:admin1_code":"29",
    "gn:asciiname":"Hoseynabad-e `Ali Akbarkhan",
    "gn:country_code":"IR",
    "gn:dem":1508,
    "gn:feature_class":"P",
    "gn:feature_code":"PPL",
    "gn:name":"\u1e28oseyn\u0101b\u0101d-e \u2018Al\u012b Akbarkh\u0101n",
    "gn:population":0,
    "gn:timezone":"Asia/Tehran",
    "iso:country":"IR",
    "name:fas_x_preferred":[
        "\u1e28oseyn\u0101b\u0101d-e \u2018Al\u012b Akbarkh\u0101n"
    ],
    "name:und_x_variant":[
        "Husain\u0101b\u0101d",
        "\u1e28oseyn\u0101b\u0101d-e P\u0101\u2019\u012bn",
        "\u1e28oseyn\u0101b\u0101d",
        "\u1e28oseyn\u0101b\u0101d-e Sofl\u00e1"
    ],
    "wof:name":"Hoseynabad-e `Ali Akbarkhan",
    "wof:placetype":"locality"
},
  "geometry": {"coordinates":[56.0225,30.44972000000001],"type":"Point"}
}