{
  "type": "Feature",
  "properties": {
    "gn:admin1_code":"4.0",
    "gn:asciiname":"Moradabad",
    "gn:country_code":"IR",
    "gn:dem":1167,
    "gn:feature_class":"P",
    "gn:feature_code":"PPL",
    "gn:name":"Mor\u0101d\u0101b\u0101d",
    "gn:population":0,
    "gn:timezone":"Asia/Tehran",
    "iso:country":"IR",
    "name:fas_x_preferred":[
        "\u0645\u062d\u0645\u0648\u062f \u0622\u0628\u0627\u062f"
    ],
    "name:fas_x_variant":[
        "Ch\u0101h-e Ma\u1e29m\u016bd\u0101b\u0101d",
        "Ma\u1e29m\u016bd\u0101b\u0101d",
        "\u0645\u0631\u0627\u062f \u0622\u0628\u0627\u062f",
        "\u0686\u0627\u0647 \u0645\u062d\u0645\u0651\u062f \u0622\u0628\u0627\u062f"
    ],
    "name:und_x_variant":[
        "Mor\u0101d\u0101b\u0101d",
        "Ch\u0101h-e Mo\u1e29ammad\u0101b\u0101d"
    ],
    "wof:name":"Moradabad",
    "wof:placetype":"locality"
},
  "geometry": {"coordinates":[61.8797,27.35805],"type":"Point"}
}