{
  "type": "Feature",
  "properties": {
    "gn:admin1_code":"8",
    "gn:asciiname":"Kharmali",
    "gn:country_code":"IR",
    "gn:dem":919,
    "gn:feature_class":"P",
    "gn:feature_code":"PPL",
    "gn:name":"Kharm\u0101l\u012b",
    "gn:population":0,
    "gn:timezone":"Asia/Tehran",
    "iso:country":"IR",
    "name:fas_x_preferred":[
        "\u062e\u0631\u0645\u0644\u06cc"
    ],
    "name:fas_x_variant":[
        "Kharaml\u012b",
        "\u062e\u0631\u0645\u0627\u0644\u06cc"
    ],
    "name:und_x_variant":[
        "Kharm\u0101l\u012b"
    ],
    "wof:name":"Kharmali",
    "wof:placetype":"locality"
},
  "geometry": {"coordinates":[48.98915,37.32492],"type":"Point"}
}