{
  "type": "Feature",
  "properties": {
    "gn:admin1_code":"4.0",
    "gn:asciiname":"Sorkh Gazi",
    "gn:country_code":"IR",
    "gn:dem":1285,
    "gn:feature_class":"P",
    "gn:feature_code":"PPL",
    "gn:name":"Sorkh Gaz\u012b",
    "gn:population":0,
    "gn:timezone":"Asia/Tehran",
    "iso:country":"IR",
    "name:fas_x_preferred":[
        "Sorkh Gaz\u012b"
    ],
    "wof:name":"Sorkh Gazi",
    "wof:placetype":"locality"
},
  "geometry": {"coordinates":[61.13333000000001,27.55],"type":"Point"}
}