{
  "type": "Feature",
  "properties": {
    "gn:admin1_code":"16.0",
    "gn:asciiname":"Chichuran",
    "gn:country_code":"IR",
    "gn:dem":1633,
    "gn:elevation":"0.0",
    "gn:feature_class":"P",
    "gn:feature_code":"PPL",
    "gn:name":"Ch\u012bch\u016br\u0101n",
    "gn:population":0,
    "gn:timezone":"Asia/Tehran",
    "iso:country":"IR",
    "name:ara_x_preferred":[
        "\u062a\u0634\u064a \u062a\u0634\u0648\u0631\u0627\u0646"
    ],
    "name:ceb_x_preferred":[
        "Ch\u012bch\u016br\u0101n"
    ],
    "name:ckb_x_preferred":[
        "\u0686\u06cc\u0686\u06c6\u0631\u0627\u0646"
    ],
    "name:fas_x_preferred":[
        "\u0686\u064a\u0686\u0648\u0631\u0627\u0646"
    ],
    "name:fas_x_variant":[
        "\u0686\u06cc \u0686\u0648\u0631\u0627\u0646",
        "Ch\u012bch\u016br\u0101n"
    ],
    "name:swe_x_preferred":[
        "Ch\u012bch\u016br\u0101n"
    ],
    "wof:name":"Chichuran",
    "wof:placetype":"locality"
},
  "geometry": {"coordinates":[45.9482,35.9657],"type":"Point"}
}