{
  "type": "Feature",
  "properties": {
    "gn:admin1_code":"13",
    "gn:asciiname":"Gand Ab",
    "gn:country_code":"IR",
    "gn:dem":1392,
    "gn:feature_class":"P",
    "gn:feature_code":"PPL",
    "gn:name":"Gand \u0100b",
    "gn:population":0,
    "gn:timezone":"Asia/Tehran",
    "iso:country":"IR",
    "name:fas_x_preferred":[
        "\u06af\u0646\u062f \u0622\u0628"
    ],
    "name:fas_x_variant":[
        "Gand\u0101b",
        "Gand \u0100b"
    ],
    "wof:name":"Gand Ab",
    "wof:placetype":"locality"
},
  "geometry": {"coordinates":[46.9447,34.7316],"type":"Point"}
}