{
  "type": "Feature",
  "properties": {
    "gn:admin1_code":"42",
    "gn:asciiname":"Bayg",
    "gn:country_code":"IR",
    "gn:dem":1521,
    "gn:feature_class":"P",
    "gn:feature_code":"PPL",
    "gn:name":"B\u0101yg",
    "gn:population":0,
    "gn:timezone":"Asia/Tehran",
    "iso:country":"IR",
    "name:ara_x_preferred":[
        "\u0628\u0627\u064a\u063a"
    ],
    "name:aze_x_preferred":[
        "Bayg"
    ],
    "name:ceb_x_preferred":[
        "B\u0101yg"
    ],
    "name:fas_x_preferred":[
        "\u0628\u0627\u06cc\u06af"
    ],
    "name:fas_x_variant":[
        "B\u0101yk",
        "B\u0101yg"
    ],
    "name:ita_x_preferred":[
        "Bayag"
    ],
    "name:mlg_x_preferred":[
        "Bayg"
    ],
    "name:swe_x_preferred":[
        "B\u0101yg"
    ],
    "name:tur_x_preferred":[
        "Bayk"
    ],
    "wof:name":"Bayg",
    "wof:placetype":"locality"
},
  "geometry": {"coordinates":[59.03785,35.37571],"type":"Point"}
}