{
  "type": "Feature",
  "properties": {
    "gn:admin1_code":"33",
    "gn:asciiname":"Zandabad",
    "gn:country_code":"IR",
    "gn:dem":1874,
    "gn:feature_class":"P",
    "gn:feature_code":"PPL",
    "gn:name":"Zand\u0101b\u0101d",
    "gn:population":0,
    "gn:timezone":"Asia/Tehran",
    "iso:country":"IR",
    "name:fas_x_preferred":[
        "\u0632\u064e\u0646\u062f\u064e\u0648\u064e"
    ],
    "name:fas_x_variant":[
        "\u0632\u0646\u062f \u0622\u0628\u0627\u062f",
        "Zand\u0101b\u0101d",
        "\u0632\u064e\u0646\u062f \u0622\u0628\u0627\u062f"
    ],
    "name:und_x_variant":[
        "Zand\u0101wa",
        "Zandava"
    ],
    "wof:name":"Zandabad",
    "wof:placetype":"locality"
},
  "geometry": {"coordinates":[46.9316,38.601],"type":"Point"}
}