{
  "type": "Feature",
  "properties": {
    "gn:admin1_code":"36",
    "gn:asciiname":"Paskuhan",
    "gn:country_code":"IR",
    "gn:dem":2068,
    "gn:feature_class":"P",
    "gn:feature_code":"PPL",
    "gn:name":"Pask\u016bh\u0101n",
    "gn:population":0,
    "gn:timezone":"Asia/Tehran",
    "iso:country":"IR",
    "name:azb_x_preferred":[
        "\u067e\u0633\u06a9\u0648\u0647\u0627\u0646"
    ],
    "name:fas_x_preferred":[
        "\u067e\u0633\u06a9\u0648\u0647\u0627\u0646"
    ],
    "name:fas_x_variant":[
        "Pask\u016bh\u0101n"
    ],
    "name:und_x_variant":[
        "Pushtw\u0101n",
        "Pushtvan",
        "Poshtv\u0101n"
    ],
    "wof:name":"Paskuhan",
    "wof:placetype":"locality"
},
  "geometry": {"coordinates":[48.53537,36.07814000000001],"type":"Point"}
}