{
  "type": "Feature",
  "properties": {
    "gn:admin1_code":"41",
    "gn:asciiname":"Zamani",
    "gn:country_code":"IR",
    "gn:dem":1877,
    "gn:feature_class":"P",
    "gn:feature_code":"PPL",
    "gn:name":"Zam\u0101n\u012b",
    "gn:population":0,
    "gn:timezone":"Asia/Tehran",
    "iso:country":"IR",
    "name:deu_x_preferred":[
        "Zamani"
    ],
    "name:fas_x_preferred":[
        "\u0632\u0645\u0627\u0646\u06cc"
    ],
    "name:fas_x_variant":[
        "Zam\u0101n\u012b"
    ],
    "name:und_x_variant":[
        "Zam\u012bni"
    ],
    "wof:name":"Zamani",
    "wof:placetype":"locality"
},
  "geometry": {"coordinates":[59.24983,33.41905],"type":"Point"}
}