{
  "type": "Feature",
  "properties": {
    "gn:admin1_code":"1",
    "gn:asciiname":"Qarquluq-e Pa'in",
    "gn:country_code":"IR",
    "gn:dem":788,
    "gn:feature_class":"P",
    "gn:feature_code":"PPL",
    "gn:name":"Q\u0101rq\u016bl\u016bq-e P\u0101\u2019\u012bn",
    "gn:population":0,
    "gn:timezone":"Asia/Tehran",
    "iso:country":"IR",
    "name:azb_x_preferred":[
        "\u0622\u0634\u0627\u063a\u0627 \u0642\u0627\u0631\u0642\u06cc\u0644\u06cc\u0642"
    ],
    "name:aze_x_preferred":[
        "A\u015fa\u011f\u0131 Qarquluq"
    ],
    "name:ceb_x_preferred":[
        "Q\u0101rq\u016bl\u016bq-e P\u0101'\u012bn"
    ],
    "name:fas_x_preferred":[
        "\u0642\u0627\u0631\u0642\u0648\u0644\u0648\u0642\u0650 \u0633\u064f\u0641\u0644\u064e\u0649"
    ],
    "name:fas_x_variant":[
        "\u063a\u064e\u0631 \u063a\u064f\u0644\u064f\u0651\u0646 \u0633\u064f\u0641\u0644\u064e",
        "\u0642\u0627\u0631\u0642\u0627\u0644\u0648\u0642\u0650 \u067e\u0627\u0626\u064a\u0646",
        "Q\u0101rq\u016bl\u016bq-e Sofl\u00e1",
        "\u0642\u0627\u0631\u0642\u0648\u0644\u0648\u0642 \u067e\u0627\u0626\u06cc\u0646",
        "\u0642\u0627\u0631\u0642\u0627\u0644\u0648\u0642\u0650 \u0633\u064f\u0641\u0644\u064e\u0649",
        "Q\u0101rq\u016bl\u016bq-e P\u0101\u2019\u012bn",
        "\u0642\u0627\u0631\u0642\u0648\u0644\u0648\u0642 \u0633\u0641\u0644\u06cc"
    ],
    "name:mlg_x_preferred":[
        "Qarquluq-e Sofla"
    ],
    "name:msa_x_preferred":[
        "Qarquluq-e Sofla"
    ],
    "name:swe_x_preferred":[
        "Q\u0101rq\u016bl\u016bq-e P\u0101'\u012bn"
    ],
    "name:und_x_variant":[
        "Ghar Gholoon Sofla",
        "Q\u0101rq\u0101l\u016bq-e P\u0101\u2019\u012bn",
        "Q\u0101rq\u0101l\u016bq-e Sofl\u00e1"
    ],
    "wof:name":"Qarquluq-e Pa'in",
    "wof:placetype":"locality"
},
  "geometry": {"coordinates":[45.1415,39.2552],"type":"Point"}
}