{
  "type": "Feature",
  "properties": {
    "gn:admin1_code":"40",
    "gn:asciiname":"Mehrabad",
    "gn:country_code":"IR",
    "gn:dem":1118,
    "gn:feature_class":"P",
    "gn:feature_code":"PPL",
    "gn:name":"Mehr\u0101b\u0101d",
    "gn:population":0,
    "gn:timezone":"Asia/Tehran",
    "iso:country":"IR",
    "name:fas_x_preferred":[
        "\u0645\u0647\u0631 \u0622\u0628\u0627\u062f"
    ],
    "name:fas_x_variant":[
        "Mehr\u0101b\u0101d-e B\u0101l\u0101",
        "Mehr\u0101b\u0101d",
        "\u0645\u0647\u0631\u0622\u0628\u0627\u062f \u0628\u0627\u0644\u0627"
    ],
    "name:und_x_variant":[
        "Mehr Abad Meibod",
        "\u0645\u0647\u0631\u0622\u0628\u0627\u062f \u0628\u0627\u0644\u0627"
    ],
    "wof:name":"Mehrabad",
    "wof:placetype":"locality"
},
  "geometry": {"coordinates":[54.04857,32.2052],"type":"Point"}
}