{
  "type": "Feature",
  "properties": {
    "gn:admin1_code":"4.0",
    "gn:asciiname":"Rahmatabad-e Ziaratgah",
    "gn:country_code":"IR",
    "gn:dem":1976,
    "gn:feature_class":"P",
    "gn:feature_code":"PPL",
    "gn:name":"Ra\u1e29mat\u0101b\u0101d-e Z\u012b\u0101ratg\u0101h",
    "gn:population":0,
    "gn:timezone":"Asia/Tehran",
    "iso:country":"IR",
    "name:fas_x_preferred":[
        "Ra\u1e29mat\u0101b\u0101d-e Z\u012b\u0101ratg\u0101h"
    ],
    "wof:name":"Rahmatabad-e Ziaratgah",
    "wof:placetype":"locality"
},
  "geometry": {"coordinates":[60.56667,29.38333],"type":"Point"}
}