{
  "type": "Feature",
  "properties": {
    "gn:admin1_code":"33",
    "gn:asciiname":"Tatar-e `Olya",
    "gn:country_code":"IR",
    "gn:dem":379,
    "gn:feature_class":"P",
    "gn:feature_code":"PPL",
    "gn:name":"T\u0101t\u0101r-e \u2018Oly\u0101",
    "gn:population":0,
    "gn:timezone":"Asia/Tehran",
    "iso:country":"IR",
    "name:azb_x_preferred":[
        "\u06cc\u0648\u062e\u0627\u0631\u06cc \u062a\u0627\u062a\u0627\u0631"
    ],
    "name:fas_x_preferred":[
        "\u062a\u0627\u062a\u0627\u0631\u0650 \u0639\u064f\u0644\u064a\u0627"
    ],
    "name:fas_x_variant":[
        "\u062a\u0627\u062a\u0627\u0631",
        "\u062a\u0627\u062a\u0627\u0631 \u0639\u0644\u06cc\u0627",
        "\u062a\u0627\u062a\u0627\u0631\u0650 \u0628\u0627\u0644\u0627",
        "T\u0101t\u0101r-e B\u0101l\u0101",
        "\u062a\u064e\u0647\u062a\u064e\u0631\u06cc \u0643\u064e\u0646\u062f\u064e\u0631\u0650\u0647",
        "T\u0101t\u0101r-e \u2018Oly\u0101"
    ],
    "name:msa_x_preferred":[
        "Tatar-e Olya"
    ],
    "name:und_x_variant":[
        "Chaindara",
        "Tahtar\u012b Kandareh",
        "Chalandara-Tatar",
        "Tatari",
        "T\u0101t\u0101r",
        "Chalandere-Tatar"
    ],
    "wof:name":"Tatar-e `Olya",
    "wof:placetype":"locality"
},
  "geometry": {"coordinates":[46.7743,39.0394],"type":"Point"}
}