{
  "type": "Feature",
  "properties": {
    "gn:admin1_code":"42",
    "gn:asciiname":"Jarrahi",
    "gn:country_code":"IR",
    "gn:dem":1373,
    "gn:feature_class":"P",
    "gn:feature_code":"PPL",
    "gn:name":"Jarr\u0101\u1e29\u012b",
    "gn:population":0,
    "gn:timezone":"Asia/Tehran",
    "iso:country":"IR",
    "name:fas_x_preferred":[
        "\u062c\u0631\u0627\u062d\u06cc"
    ],
    "name:fas_x_variant":[
        "Jarr\u0101\u1e29\u012b-ye B\u0101l\u0101",
        "Jarr\u0101\u1e29\u012b"
    ],
    "wof:name":"Jarrahi",
    "wof:placetype":"locality"
},
  "geometry": {"coordinates":[57.22046,35.76772000000001],"type":"Point"}
}