{
  "type": "Feature",
  "properties": {
    "gn:admin1_code":"1",
    "gn:asciiname":"Kachu-ye Bala",
    "gn:country_code":"IR",
    "gn:dem":1411,
    "gn:feature_class":"P",
    "gn:feature_code":"PPL",
    "gn:name":"Kach\u016b-ye B\u0101l\u0101",
    "gn:population":0,
    "gn:timezone":"Asia/Tehran",
    "iso:country":"IR",
    "name:fas_x_preferred":[
        "\u0643\u064e\u0686\u0648\u06cc \u0639\u064f\u0644\u064a\u0627"
    ],
    "name:fas_x_variant":[
        "\u06a9\u0686\u0648\u06cc \u0628\u0627\u0644\u0627",
        "Kach\u016b-ye \u2018Oly\u0101",
        "Kach\u016b-ye B\u0101l\u0101"
    ],
    "wof:name":"Kachu-ye Bala",
    "wof:placetype":"locality"
},
  "geometry": {"coordinates":[44.9043,39.0362],"type":"Point"}
}