{
  "type": "Feature",
  "properties": {
    "gn:admin1_code":"41",
    "gn:asciiname":"Khushin-e `Olya",
    "gn:country_code":"IR",
    "gn:dem":1925,
    "gn:feature_class":"P",
    "gn:feature_code":"PPL",
    "gn:name":"Kh\u016bsh\u012bn-e \u2018Oly\u0101",
    "gn:population":0,
    "gn:timezone":"Asia/Tehran",
    "iso:country":"IR",
    "name:fas_x_preferred":[
        "\u062e\u0648\u0634\u06cc\u0646\u0647 \u0628\u0627\u0644\u0627"
    ],
    "name:fas_x_variant":[
        "Kh\u016bsh\u012bneh-ye B\u0101l\u0101",
        "\u062e\u0648\u0634\u06cc\u0646 \u0639\u0644\u06cc\u0627",
        "\u062e\u0648\u0634\u06cc\u0646\u0647 \u0639\u0644\u06cc\u0627"
    ],
    "name:und_x_variant":[
        "Khosinad Olya",
        "Kh\u016bsh\u012bneh B\u0101l\u0101",
        "Kh\u016bsh\u012bneh \u2018Oly\u0101",
        "Kh\u016bsh\u012bn-e \u2018Oly\u0101",
        "Kh\u016bsh\u012bneh-ye \u2018Oly\u0101"
    ],
    "wof:name":"Khushin-e `Olya",
    "wof:placetype":"locality"
},
  "geometry": {"coordinates":[59.51834,32.94542],"type":"Point"}
}