{
  "type": "Feature",
  "properties": {
    "gn:admin1_code":"5",
    "gn:asciiname":"Garab-e Bala",
    "gn:country_code":"IR",
    "gn:dem":1520,
    "gn:feature_class":"P",
    "gn:feature_code":"PPL",
    "gn:name":"Gar\u0101b-e B\u0101l\u0101",
    "gn:population":0,
    "gn:timezone":"Asia/Tehran",
    "iso:country":"IR",
    "name:fas_x_preferred":[
        "Gar\u0101b-e B\u0101l\u0101"
    ],
    "name:fas_x_variant":[
        "\u06af\u0631\u0627\u0628 \u0628\u0627\u0644\u0627"
    ],
    "name:und_x_variant":[
        "\u06af\u0631\u0627\u0628 \u0628\u0627\u0644\u0627"
    ],
    "wof:name":"Garab-e Bala",
    "wof:placetype":"locality"
},
  "geometry": {"coordinates":[50.89768,30.94172],"type":"Point"}
}