{
  "type": "Feature",
  "properties": {
    "gn:admin1_code":"35.0",
    "gn:asciiname":"Ahangar Kola",
    "gn:country_code":"IR",
    "gn:dem":81,
    "gn:feature_class":"P",
    "gn:feature_code":"PPL",
    "gn:name":"\u0100hangar Kol\u0101",
    "gn:population":0,
    "gn:timezone":"Asia/Tehran",
    "iso:country":"IR",
    "name:fas_x_preferred":[
        "\u0622\u0647\u0646\u06af\u0631 \u0643\u0644\u0627"
    ],
    "name:fas_x_variant":[
        "\u0100hangar Kol\u0101"
    ],
    "wof:name":"Ahangar Kola",
    "wof:placetype":"locality"
},
  "geometry": {"coordinates":[52.48988000000001,36.38915],"type":"Point"}
}