{
  "type": "Feature",
  "properties": {
    "gn:admin1_code":"42.0",
    "gn:asciiname":"Seyyedabad",
    "gn:country_code":"IR",
    "gn:dem":1068,
    "gn:feature_class":"P",
    "gn:feature_code":"PPL",
    "gn:name":"Seyyed\u0101b\u0101d",
    "gn:population":0,
    "gn:timezone":"Asia/Tehran",
    "iso:country":"IR",
    "name:fas_x_preferred":[
        "Seyyed\u0101b\u0101d"
    ],
    "name:fas_x_variant":[
        "\u0633\u06cc\u062f \u0622\u0628\u0627\u062f",
        "\u0633\u06cc\u062f \u0622\u0628\u0627\u062f \u06a9\u0644\u0648\u062a",
        "\u0633\u06cc\u062f\u0622\u0628\u0627\u062f \u06a9\u0644\u0648\u062a"
    ],
    "name:und_x_variant":[
        "Seyyed\u0101b\u0101d-e Kal\u016bt"
    ],
    "wof:name":"Seyyedabad",
    "wof:placetype":"locality"
},
  "geometry": {"coordinates":[57.59802,36.25914],"type":"Point"}
}