{
  "type": "Feature",
  "properties": {
    "gn:admin1_code":"3",
    "gn:asciiname":"Mazra`eh-ye Zuradgan-e `Olya",
    "gn:country_code":"IR",
    "gn:dem":2331,
    "gn:feature_class":"P",
    "gn:feature_code":"PPL",
    "gn:name":"Mazra\u2018eh-ye Z\u016bradgan-e \u2018Oly\u0101",
    "gn:population":0,
    "gn:timezone":"Asia/Tehran",
    "iso:country":"IR",
    "name:fas_x_preferred":[
        "\u0632\u0648\u0631\u064e\u062f\u0643\u064e\u0646 \u0639\u064f\u0644\u064a\u0627"
    ],
    "name:fas_x_variant":[
        "\u0632\u0650\u0648\u0650\u0631\u062f\u0643\u064e\u0646\u0650 \u0628\u0627\u0644\u0627",
        "Zeverdekan-e B\u0101l\u0101",
        "\u0632\u0650\u0648\u0650\u0631\u062f\u0650\u0643\u064e\u0646\u0650 \u0628\u0627\u0644\u0627",
        "\u0632\u0650\u0648\u0650\u0631\u062f\u0643\u0627\u0646 \u0628\u0627\u0644\u0627",
        "\u0632\u064f\u0651\u0631\u064e\u062f\u06af\u064e\u0646 \u0627\u064f\u0644\u064a\u064e",
        "\u0645\u0632\u0631\u0639\u0647 \u0632\u0648\u0631\u062f\u06af\u0627\u0646 \u0639\u0644\u06cc\u0627"
    ],
    "name:und_x_variant":[
        "Z\u016bradkan \u2018Oly\u0101",
        "Zeverdk\u0101n B\u0101l\u0101",
        "Zooradgan Olya",
        "Zeverdkan-e B\u0101l\u0101",
        "Mazra\u2018eh-ye Z\u016bradgan-e \u2018Oly\u0101"
    ],
    "wof:name":"Mazra`eh-ye Zuradgan-e `Olya",
    "wof:placetype":"locality"
},
  "geometry": {"coordinates":[50.85744,31.95625],"type":"Point"}
}