{
  "type": "Feature",
  "properties": {
    "gn:admin1_code":"7",
    "gn:asciiname":"Paqal`eh",
    "gn:country_code":"IR",
    "gn:dem":1890,
    "gn:feature_class":"P",
    "gn:feature_code":"PPL",
    "gn:name":"P\u0101qal\u2018eh",
    "gn:population":0,
    "gn:timezone":"Asia/Tehran",
    "iso:country":"IR",
    "name:fas_x_preferred":[
        "\u067e\u0627\u0642\u0644\u0639\u0647"
    ],
    "name:und_x_variant":[
        "Qal\u2018eh-ye \u0100q\u0101kh\u0101n",
        "P\u0101qal\u2018eh"
    ],
    "wof:name":"Paqal`eh",
    "wof:placetype":"locality"
},
  "geometry": {"coordinates":[52.02538,30.00139],"type":"Point"}
}