{
  "type": "Feature",
  "properties": {
    "gn:admin1_code":"23",
    "gn:asciiname":"Kivarku",
    "gn:country_code":"IR",
    "gn:dem":1106,
    "gn:feature_class":"P",
    "gn:feature_code":"PPL",
    "gn:name":"K\u012bvark\u016b",
    "gn:population":0,
    "gn:timezone":"Asia/Tehran",
    "iso:country":"IR",
    "name:fas_x_preferred":[
        "\u0643\u064a\u0648\u064e\u0631\u0643\u0648"
    ],
    "name:fas_x_variant":[
        "K\u012bvark\u016b"
    ],
    "wof:name":"Kivarku",
    "wof:placetype":"locality"
},
  "geometry": {"coordinates":[47.96667,33.23333],"type":"Point"}
}