{
  "type": "Feature",
  "properties": {
    "gn:admin1_code":"33",
    "gn:asciiname":"Senziq",
    "gn:country_code":"IR",
    "gn:dem":1688,
    "gn:feature_class":"P",
    "gn:feature_code":"PPL",
    "gn:name":"Senz\u012bq",
    "gn:population":0,
    "gn:timezone":"Asia/Tehran",
    "iso:country":"IR",
    "name:ceb_x_preferred":[
        "Senz\u012bq"
    ],
    "name:fas_x_preferred":[
        "\u0633\u0646\u0632\u06cc\u0642"
    ],
    "name:fas_x_variant":[
        "Senz\u012bq"
    ],
    "name:msa_x_preferred":[
        "Senziq"
    ],
    "name:swe_x_preferred":[
        "Senz\u012bq"
    ],
    "name:und_x_variant":[
        "Sinzik",
        "Sanaz\u012bq",
        "Sanzigh",
        "Sanz\u012bq"
    ],
    "wof:name":"Senziq",
    "wof:placetype":"locality"
},
  "geometry": {"coordinates":[47.6496,37.9153],"type":"Point"}
}