{
  "type": "Feature",
  "properties": {
    "gn:admin1_code":"23",
    "gn:asciiname":"Shiravand-e `Olya",
    "gn:country_code":"IR",
    "gn:dem":928,
    "gn:feature_class":"P",
    "gn:feature_code":"PPL",
    "gn:name":"Sh\u012br\u0101vand-e \u2018Oly\u0101",
    "gn:population":0,
    "gn:timezone":"Asia/Tehran",
    "iso:country":"IR",
    "name:fas_x_preferred":[
        "\u0634\u064a\u0631\u0648\u064e\u0646\u062f\u0650 \u0639\u064f\u0644\u064a\u0627"
    ],
    "name:fas_x_variant":[
        "\u0634\u064a\u0631\u0648\u064e\u0646\u062f",
        "\u0634\u06cc\u0631\u0622\u0648\u0646\u062f \u0639\u0644\u06cc\u0627",
        "Sh\u012brvand-e \u2018Oly\u0101",
        "Sh\u012br\u0101vand-e \u2018Oly\u0101"
    ],
    "name:und_x_variant":[
        "Sh\u012brvand"
    ],
    "wof:name":"Shiravand-e `Olya",
    "wof:placetype":"locality"
},
  "geometry": {"coordinates":[47.1898,33.718],"type":"Point"}
}