{
  "type": "Feature",
  "properties": {
    "gn:admin1_code":"4.0",
    "gn:asciiname":"Deh-e Khodabakhsh",
    "gn:country_code":"IR",
    "gn:dem":481,
    "gn:feature_class":"P",
    "gn:feature_code":"PPL",
    "gn:name":"Deh-e Khod\u0101bakhsh",
    "gn:population":0,
    "gn:timezone":"Asia/Tehran",
    "iso:country":"IR",
    "name:fas_x_preferred":[
        "\u062f\u0647 \u062e\u062f\u0627\u0628\u062e\u0634"
    ],
    "name:fas_x_variant":[
        "Deh-e Khod\u0101bakhsh"
    ],
    "wof:name":"Deh-e Khodabakhsh",
    "wof:placetype":"locality"
},
  "geometry": {"coordinates":[61.4224,30.7843],"type":"Point"}
}