{
  "type": "Feature",
  "properties": {
    "gn:admin1_code":"32",
    "gn:asciiname":"Alardeh",
    "gn:country_code":"IR",
    "gn:dem":1817,
    "gn:feature_class":"P",
    "gn:feature_code":"PPLL",
    "gn:name":"Alardeh",
    "gn:population":0,
    "gn:timezone":"Asia/Tehran",
    "iso:country":"IR",
    "name:fas_x_preferred":[
        "\u0627\u0644\u0631\u062f\u0647"
    ],
    "name:fas_x_variant":[
        "\u0628\u0627\u0628\u064a\u0627\u0646"
    ],
    "name:und_x_variant":[
        "B\u0101b\u012b\u0101n"
    ],
    "wof:name":"Alardeh",
    "wof:placetype":"locality"
},
  "geometry": {"coordinates":[47.9046,38.4336],"type":"Point"}
}