{
  "type": "Feature",
  "properties": {
    "gn:admin1_code":"8.0",
    "gn:asciiname":"Lapa Alam",
    "gn:country_code":"IR",
    "gn:dem":169,
    "gn:feature_class":"P",
    "gn:feature_code":"PPL",
    "gn:name":"L\u0101p\u0101 Alam",
    "gn:population":0,
    "gn:timezone":"Asia/Tehran",
    "iso:country":"IR",
    "name:fas_x_preferred":[
        "L\u0101p-e A\u2018lam"
    ],
    "name:fas_x_variant":[
        "\u0644\u0627\u067e\u0627 \u0627\u0644\u0645",
        "\u0644\u0627\u067e\u0627\u0644\u0627\u0646"
    ],
    "name:und_x_variant":[
        "L\u0101p\u0101 Alam",
        "L\u0101p\u0101l\u0101n"
    ],
    "wof:name":"Lapa Alam",
    "wof:placetype":"locality"
},
  "geometry": {"coordinates":[50.43578,36.98576],"type":"Point"}
}