{
  "type": "Feature",
  "properties": {
    "gn:admin1_code":"15",
    "gn:asciiname":"Parneveshteh",
    "gn:country_code":"IR",
    "gn:dem":230,
    "gn:feature_class":"P",
    "gn:feature_code":"PPL",
    "gn:name":"Parneveshteh",
    "gn:population":0,
    "gn:timezone":"Asia/Tehran",
    "iso:country":"IR",
    "name:fas_x_preferred":[
        "\u067e\u0631 \u0646\u0648\u0634\u062a\u0647"
    ],
    "name:fas_x_variant":[
        "\u067e\u0631 \u0646\u0648\u0634\u062a\u0647 \u062f\u0648",
        "\u067e\u0631\u0646\u0648\u0634\u062a\u0647 \u062f\u0648"
    ],
    "name:und_x_variant":[
        "Par Neveshteh-ye Do"
    ],
    "wof:name":"Parneveshteh",
    "wof:placetype":"locality"
},
  "geometry": {"coordinates":[49.10558,32.18340999999999],"type":"Point"}
}