{
  "type": "Feature",
  "properties": {
    "gn:admin1_code":"7",
    "gn:asciiname":"Pa Qalat",
    "gn:country_code":"IR",
    "gn:dem":399,
    "gn:feature_class":"P",
    "gn:feature_code":"PPL",
    "gn:name":"P\u0101 Qal\u0101t",
    "gn:population":0,
    "gn:timezone":"Asia/Tehran",
    "iso:country":"IR",
    "name:fas_x_preferred":[
        "\u067e\u0627\u063a\u0644\u0627\u062a"
    ],
    "name:fas_x_variant":[
        "P\u0101 Qal\u0101t",
        "P\u0101 Ghal\u0101t",
        "P\u0101qal\u0101t",
        "\u067e\u0627\u0642\u0644\u0627\u062a"
    ],
    "name:und_x_variant":[
        "P\u0101qal\u0101t",
        "B\u0101 Qal\u0101t",
        "Paghelat",
        "B\u0101ql\u0101t",
        "P\u0101 Oal\u0101t",
        "Pa Kal\u0101t",
        "Pa yi Kal\u0101t"
    ],
    "wof:name":"Pa Qalat",
    "wof:placetype":"locality"
},
  "geometry": {"coordinates":[53.721,27.27604],"type":"Point"}
}