{
  "type": "Feature",
  "properties": {
    "gn:admin1_code":"32",
    "gn:asciiname":"Kachalabad",
    "gn:country_code":"IR",
    "gn:dem":1649,
    "gn:feature_class":"P",
    "gn:feature_code":"PPL",
    "gn:name":"Kachal\u0101b\u0101d",
    "gn:population":0,
    "gn:timezone":"Asia/Tehran",
    "iso:country":"IR",
    "name:fas_x_preferred":[
        "\u06a9\u0686\u0644 \u0622\u0628\u0627\u062f"
    ],
    "name:fas_x_variant":[
        "Kachal\u0101b\u0101d"
    ],
    "name:und_x_variant":[
        "Kachalobad"
    ],
    "wof:name":"Kachalabad",
    "wof:placetype":"locality"
},
  "geometry": {"coordinates":[48.17312,37.92002],"type":"Point"}
}