{
  "type": "Feature",
  "properties": {
    "gn:admin1_code":"29",
    "gn:asciiname":"Hezargaz",
    "gn:country_code":"IR",
    "gn:dem":1968,
    "gn:feature_class":"P",
    "gn:feature_code":"PPLF",
    "gn:name":"Hez\u0101rgaz",
    "gn:population":0,
    "gn:timezone":"Asia/Tehran",
    "iso:country":"IR",
    "name:fas_x_preferred":[
        "Hez\u0101rgaz"
    ],
    "name:fas_x_variant":[
        "\u0647\u0632\u0627\u0631\u06af\u0632",
        "\u0647\u0632\u0627\u0631 \u06af\u0632"
    ],
    "wof:name":"Hezargaz",
    "wof:placetype":"locality"
},
  "geometry": {"coordinates":[56.42325,31.08563],"type":"Point"}
}