{
  "type": "Feature",
  "properties": {
    "gn:admin1_code":"33",
    "gn:asciiname":"Homu",
    "gn:country_code":"IR",
    "gn:dem":954,
    "gn:feature_class":"P",
    "gn:feature_code":"PPL",
    "gn:name":"Hom\u016b",
    "gn:population":0,
    "gn:timezone":"Asia/Tehran",
    "iso:country":"IR",
    "name:ceb_x_preferred":[
        "Hom\u016b"
    ],
    "name:fas_x_preferred":[
        "\u0647\u0645\u0648"
    ],
    "name:fas_x_variant":[
        "Hom\u016b"
    ],
    "name:msa_x_preferred":[
        "Homu"
    ],
    "name:swe_x_preferred":[
        "Hom\u016b"
    ],
    "wof:name":"Homu",
    "wof:placetype":"locality"
},
  "geometry": {"coordinates":[47.3343,39.0211],"type":"Point"}
}