{
  "type": "Feature",
  "properties": {
    "gn:admin1_code":"15",
    "gn:asciiname":"`Ati",
    "gn:country_code":"IR",
    "gn:dem":45,
    "gn:feature_class":"P",
    "gn:feature_code":"PPL",
    "gn:name":"\u2018\u0100\u0163\u012b",
    "gn:population":0,
    "gn:timezone":"Asia/Tehran",
    "iso:country":"IR",
    "name:fas_x_preferred":[
        "\u0639\u0627\u0637\u06cc"
    ],
    "name:fas_x_variant":[
        "Boneh-ye \u2018\u0100\u0163\u012b",
        "\u2018\u0100\u0163\u012b",
        "\u0628\u0646\u0647 \u0639\u0627\u0637\u06cc"
    ],
    "wof:name":"`Ati",
    "wof:placetype":"locality"
},
  "geometry": {"coordinates":[48.54735,32.0583],"type":"Point"}
}