{
  "type": "Feature",
  "properties": {
    "gn:admin1_code":"16",
    "gn:asciiname":"Kas Nazan",
    "gn:country_code":"IR",
    "gn:dem":1771,
    "gn:feature_class":"P",
    "gn:feature_code":"PPL",
    "gn:name":"Kas Naz\u0101n",
    "gn:population":0,
    "gn:timezone":"Asia/Tehran",
    "iso:country":"IR",
    "name:fas_x_preferred":[
        "\u0643\u064e\u0633 \u0646\u064e\u0632\u0627\u0646"
    ],
    "name:fas_x_variant":[
        "\u06a9\u0633 \u0646\u0632\u0627\u0646",
        "Kasan Naz\u0101n",
        "Kas Naz\u0101n"
    ],
    "wof:name":"Kas Nazan",
    "wof:placetype":"locality"
},
  "geometry": {"coordinates":[46.2139,36.1073],"type":"Point"}
}