{
  "type": "Feature",
  "properties": {
    "gn:admin1_code":"8.0",
    "gn:asciiname":"Tularud",
    "gn:country_code":"IR",
    "gn:dem":21,
    "gn:feature_class":"P",
    "gn:feature_code":"PPL",
    "gn:name":"\u0162\u016bl\u0101r\u016bd",
    "gn:population":0,
    "gn:timezone":"Asia/Tehran",
    "iso:country":"IR",
    "name:fas_x_preferred":[
        "Dahaneh-ye \u0162\u016bl\u0101r\u016bd-e B\u0101l\u0101"
    ],
    "name:fas_x_variant":[
        "\u0637\u0648\u0644\u0627\u0631\u0648\u062f",
        "\u06a9\u06cc\u0634\u0647 \u0648\u06cc\u0634\u0647",
        "\u06a9\u06cc\u0634\u0627 \u0648\u06cc\u0634\u0647 \u0633\u0641\u0644\u06cc"
    ],
    "name:und_x_variant":[
        "K\u012bsheh Kh\u0101leh",
        "\u0162\u016bl\u0101r\u016bd",
        "K\u012bsheh V\u012bsheh",
        "K\u012bsh\u0101 V\u012bsheh-ye Sofl\u00e1"
    ],
    "wof:name":"Tularud",
    "wof:placetype":"locality"
},
  "geometry": {"coordinates":[48.92706,37.77253],"type":"Point"}
}