{
  "type": "Feature",
  "properties": {
    "gn:admin1_code":"22.0",
    "gn:asciiname":"Baghcheh-ye Jonubi",
    "gn:country_code":"IR",
    "gn:dem":51,
    "gn:feature_class":"P",
    "gn:feature_code":"PPL",
    "gn:name":"B\u0101ghcheh-ye Jon\u016bb\u012b",
    "gn:population":0,
    "gn:timezone":"Asia/Tehran",
    "iso:country":"IR",
    "name:fas_x_preferred":[
        "\u0628\u0627\u063a\u0686\u0647 \u062c\u0646\u0648\u0628\u06cc"
    ],
    "name:fas_x_variant":[
        "B\u0101ghcheh-ye Jon\u016bb\u012b"
    ],
    "name:msa_x_preferred":[
        "Baghcheh-ye Jonubi"
    ],
    "wof:name":"Baghcheh-ye Jonubi",
    "wof:placetype":"locality"
},
  "geometry": {"coordinates":[51.2162,28.7973],"type":"Point"}
}