{
  "type": "Feature",
  "properties": {
    "gn:admin1_code":"35.0",
    "gn:asciiname":"Shah Najer",
    "gn:country_code":"IR",
    "gn:dem":1751,
    "gn:feature_class":"P",
    "gn:feature_code":"PPL",
    "gn:name":"Sh\u0101h N\u0101jer",
    "gn:population":0,
    "gn:timezone":"Asia/Tehran",
    "iso:country":"IR",
    "name:ceb_x_preferred":[
        "Sh\u0101h N\u0101jer"
    ],
    "name:fas_x_preferred":[
        "\u0634\u0627\u0647 \u0646\u0627\u062c\u0631"
    ],
    "name:fas_x_variant":[
        "Sh\u0101h N\u0101jer",
        "\u0646\u0627\u062c\u0650\u0631\u0650 \u062f\u064e\u0634\u062a\u0650 \u0631\u0648\u064a\u0627\u0646",
        "\u0634\u0627\u0647\u200c\u0646\u0627\u062c\u0631"
    ],
    "name:swe_x_preferred":[
        "Sh\u0101h N\u0101jer"
    ],
    "name:und_x_variant":[
        "\u0634\u0627\u0647 \u0646\u0627\u062c\u0650\u0631",
        "N\u0101jer-e Dasht-e R\u016by\u0101n"
    ],
    "wof:name":"Shah Najer",
    "wof:placetype":"locality"
},
  "geometry": {"coordinates":[51.77025,36.30385],"type":"Point"}
}