{
  "type": "Feature",
  "properties": {
    "gn:admin1_code":"23",
    "gn:asciiname":"Khaled Ben `Ali",
    "gn:country_code":"IR",
    "gn:dem":1482,
    "gn:feature_class":"P",
    "gn:feature_code":"PPL",
    "gn:name":"Kh\u0101led Ben \u2018Al\u012b",
    "gn:population":0,
    "gn:timezone":"Asia/Tehran",
    "iso:country":"IR",
    "name:fas_x_preferred":[
        "\u062f\u0631\u0628 \u0622\u0633\u062a\u0627\u0646\u0647"
    ],
    "name:fas_x_variant":[
        "Darb-e \u0100st\u0101neh",
        "\u062e\u0627\u0644\u062f \u0628\u0646 \u0639\u0644\u06cc"
    ],
    "name:und_x_variant":[
        "Darreh Suna",
        "Darb \u0100st\u0101neh",
        "Darreh-ye S\u016bneh",
        "Kh\u0101led Ben \u2018Al\u012b"
    ],
    "wof:name":"Khaled Ben `Ali",
    "wof:placetype":"locality"
},
  "geometry": {"coordinates":[48.819,33.7034],"type":"Point"}
}