{
  "type": "Feature",
  "properties": {
    "gn:admin1_code":"23",
    "gn:asciiname":"Kicheh",
    "gn:country_code":"IR",
    "gn:dem":2243,
    "gn:feature_class":"P",
    "gn:feature_code":"PPL",
    "gn:name":"K\u012bcheh",
    "gn:population":0,
    "gn:timezone":"Asia/Tehran",
    "iso:country":"IR",
    "name:ara_x_preferred":[
        "\u0643\u064a\u062a\u0634\u0629"
    ],
    "name:fas_x_preferred":[
        "\u0643\u0650\u0647\u0686\u0650\u0647"
    ],
    "name:fas_x_variant":[
        "\u06a9\u06cc\u0686\u0647"
    ],
    "name:und_x_variant":[
        "Kehcheh",
        "K\u012bcheh"
    ],
    "wof:name":"Kicheh",
    "wof:placetype":"locality"
},
  "geometry": {"coordinates":[49.73205,33.13645],"type":"Point"}
}