{
  "type": "Feature",
  "properties": {
    "gn:admin1_code":"33",
    "gn:asciiname":"Dashbolagh-e Moghar",
    "gn:country_code":"IR",
    "gn:dem":1199,
    "gn:feature_class":"P",
    "gn:feature_code":"PPL",
    "gn:name":"D\u0101shbol\u0101gh-e Mogh\u0101r",
    "gn:population":0,
    "gn:timezone":"Asia/Tehran",
    "iso:country":"IR",
    "name:ara_x_preferred":[
        "\u062f\u0627\u0634 \u0628\u0644\u0627\u063a \u0645\u063a\u0627\u0631"
    ],
    "name:fas_x_preferred":[
        "\u062a\u064e\u0644\u06cc \u0628\u064f\u0644\u0627\u063a"
    ],
    "name:fas_x_variant":[
        "Tal\u012b Bol\u0101gh",
        "\u062f\u0627\u0634\u0628\u0644\u0627\u063a \u0645\u063a\u0627\u0631",
        "\u062f\u0627\u0634\u0628\u0644\u0627\u063a",
        "\u062f\u0627\u0634\u200c\u0628\u0644\u0627\u063a \u0645\u063a\u0627\u0631"
    ],
    "name:msa_x_preferred":[
        "Dashbolagh-e Moghar"
    ],
    "name:und_x_variant":[
        "D\u0101shbol\u0101gh-e Mogh\u0101r",
        "D\u0101shbol\u0101gh"
    ],
    "wof:name":"Dashbolagh-e Moghar",
    "wof:placetype":"locality"
},
  "geometry": {"coordinates":[47.41031,38.61342],"type":"Point"}
}