{
  "type": "Feature",
  "properties": {
    "gn:admin1_code":"29.0",
    "gn:asciiname":"Qanat Marvan",
    "gn:country_code":"IR",
    "gn:dem":3026,
    "gn:feature_class":"P",
    "gn:feature_code":"PPL",
    "gn:name":"Qan\u0101t Marv\u0101n",
    "gn:population":0,
    "gn:timezone":"Asia/Tehran",
    "iso:country":"IR",
    "name:ara_x_preferred":[
        "\u0642\u0646\u0627\u062a \u0645\u0631\u0648\u0627\u0646"
    ],
    "name:fas_x_preferred":[
        "\u0642\u0646\u0627\u062a \u0645\u0631\u0648\u0627\u0646"
    ],
    "name:fas_x_variant":[
        "Ma\u2018dan-e Qan\u0101t Marv\u0101n",
        "Qan\u0101t-e Marv\u0101n",
        "Qan\u0101t Marv\u0101n"
    ],
    "name:und_x_variant":[
        "Qan\u0101t-e Merv\u0101n"
    ],
    "wof:name":"Qanat Marvan",
    "wof:placetype":"locality"
},
  "geometry": {"coordinates":[56.7699,29.3387],"type":"Point"}
}