{
  "type": "Feature",
  "properties": {
    "gn:admin1_code":"42",
    "gn:asciiname":"Mahvid",
    "gn:country_code":"IR",
    "gn:dem":1905,
    "gn:feature_class":"P",
    "gn:feature_code":"PPL",
    "gn:name":"Mahv\u012bd",
    "gn:population":0,
    "gn:timezone":"Asia/Tehran",
    "iso:country":"IR",
    "name:ara_x_preferred":[
        "\u0645\u0647\u0648\u064a\u062f"
    ],
    "name:ceb_x_preferred":[
        "Mahv\u012bd"
    ],
    "name:fas_x_preferred":[
        "Mahv\u012bd"
    ],
    "name:fas_x_variant":[
        "\u0645\u0647\u0648\u06cc\u062f"
    ],
    "name:swe_x_preferred":[
        "Mahv\u012bd"
    ],
    "name:und_x_variant":[
        "\u0645\u0647\u0648\u06cc\u062f"
    ],
    "wof:name":"Mahvid",
    "wof:placetype":"locality"
},
  "geometry": {"coordinates":[58.38482,34.184],"type":"Point"}
}