{
  "type": "Feature",
  "properties": {
    "gn:admin1_code":"29",
    "gn:asciiname":"Now Dezh",
    "gn:country_code":"IR",
    "gn:dem":461,
    "gn:feature_class":"P",
    "gn:feature_code":"PPL",
    "gn:name":"Now Dezh",
    "gn:population":0,
    "gn:timezone":"Asia/Tehran",
    "iso:country":"IR",
    "name:fas_x_preferred":[
        "\u0646\u0648 \u062f\u0698"
    ],
    "name:und_x_variant":[
        "Now Dez",
        "Now Dezh"
    ],
    "wof:name":"Now Dezh",
    "wof:placetype":"locality"
},
  "geometry": {"coordinates":[57.4449,27.5463],"type":"Point"}
}