{
  "type": "Feature",
  "properties": {
    "gn:admin1_code":"29",
    "gn:asciiname":"Sorkh Kalat",
    "gn:country_code":"IR",
    "gn:dem":440,
    "gn:feature_class":"P",
    "gn:feature_code":"PPL",
    "gn:name":"Sorkh Kal\u0101t",
    "gn:population":0,
    "gn:timezone":"Asia/Tehran",
    "iso:country":"IR",
    "name:fas_x_preferred":[
        "\u0633\u0631\u062e \u06a9\u0644\u0627\u062a"
    ],
    "name:fas_x_variant":[
        "Sorkh Kal\u0101t"
    ],
    "wof:name":"Sorkh Kalat",
    "wof:placetype":"locality"
},
  "geometry": {"coordinates":[57.9657,27.7653],"type":"Point"}
}