{
  "type": "Feature",
  "properties": {
    "gn:admin1_code":"8",
    "gn:asciiname":"Kaljar",
    "gn:country_code":"IR",
    "gn:dem":366,
    "gn:feature_class":"P",
    "gn:feature_code":"PPL",
    "gn:name":"Kalj\u0101r",
    "gn:population":0,
    "gn:timezone":"Asia/Tehran",
    "iso:country":"IR",
    "name:fas_x_preferred":[
        "Kal\u012bj\u0101r"
    ],
    "name:fas_x_variant":[
        "\u06a9\u0644\u062c\u0627\u0631"
    ],
    "name:und_x_variant":[
        "Kalj\u0101r"
    ],
    "wof:name":"Kaljar",
    "wof:placetype":"locality"
},
  "geometry": {"coordinates":[50.28699,37.01649000000001],"type":"Point"}
}