{
  "type": "Feature",
  "properties": {
    "gn:admin1_code":"7",
    "gn:asciiname":"Ardeshiri-ye Sofla",
    "gn:country_code":"IR",
    "gn:dem":1765,
    "gn:feature_class":"P",
    "gn:feature_code":"PPL",
    "gn:name":"Ardesh\u012br\u012b-ye Sofl\u00e1",
    "gn:population":0,
    "gn:timezone":"Asia/Tehran",
    "iso:country":"IR",
    "name:fas_x_preferred":[
        "\u0627\u0631\u062f\u0634\u06cc\u0631\u06cc \u062d\u0633\u06cc\u0646 \u0622\u0628\u0627\u062f"
    ],
    "name:fas_x_variant":[
        "Ardesh\u012br\u012b-ye P\u0101\u2019\u012bn",
        "Ardesh\u012br\u012b-ye \u1e28oseyn\u0101b\u0101d",
        "\u0627\u0631\u062f\u0634\u06cc\u0631\u06cc \u0633\u0641\u0644\u06cc"
    ],
    "name:msa_x_preferred":[
        "Ardeshiri-ye Sofla"
    ],
    "name:und_x_variant":[
        "Ardesh\u012br\u012b-ye Sofl\u00e1"
    ],
    "wof:name":"Ardeshiri-ye Sofla",
    "wof:placetype":"locality"
},
  "geometry": {"coordinates":[52.0291,30.0616],"type":"Point"}
}