{
  "type": "Feature",
  "properties": {
    "gn:admin1_code":"4.0",
    "gn:asciiname":"Keykha",
    "gn:country_code":"IR",
    "gn:dem":481,
    "gn:feature_class":"P",
    "gn:feature_code":"PPL",
    "gn:name":"Keykh\u0101",
    "gn:population":0,
    "gn:timezone":"Asia/Tehran",
    "iso:country":"IR",
    "name:fas_x_preferred":[
        "\u06a9\u06cc\u062e\u0627"
    ],
    "name:fas_x_variant":[
        "Keykh\u0101"
    ],
    "wof:name":"Keykha",
    "wof:placetype":"locality"
},
  "geometry": {"coordinates":[61.4634,30.9501],"type":"Point"}
}