{
  "type": "Feature",
  "properties": {
    "gn:admin1_code":"11",
    "gn:asciiname":"Poshtom",
    "gn:country_code":"IR",
    "gn:dem":1016,
    "gn:feature_class":"P",
    "gn:feature_code":"PPL",
    "gn:name":"Poshtom",
    "gn:population":0,
    "gn:timezone":"Asia/Tehran",
    "iso:country":"IR",
    "name:fas_x_preferred":[
        "\u067e\u064f\u0634\u062a\u064f\u0645"
    ],
    "wof:name":"Poshtom",
    "wof:placetype":"locality"
},
  "geometry": {"coordinates":[56.66167,27.92361],"type":"Point"}
}