{
  "type": "Feature",
  "properties": {
    "gn:admin1_code":"28.0",
    "gn:asciiname":"Kuy-e Modarres",
    "gn:country_code":"IR",
    "gn:dem":1816,
    "gn:feature_class":"P",
    "gn:feature_code":"PPL",
    "gn:name":"K\u016by-e Modarres",
    "gn:population":0,
    "gn:timezone":"Asia/Tehran",
    "iso:country":"IR",
    "name:fas_x_preferred":[
        "K\u016by-e Modarres"
    ],
    "name:fas_x_variant":[
        "\u06a9\u0648\u06cc \u0645\u062f\u0631\u0651\u0633"
    ],
    "wof:name":"Kuy-e Modarres",
    "wof:placetype":"locality"
},
  "geometry": {"coordinates":[50.30825,33.43955],"type":"Point"}
}