{
  "type": "Feature",
  "properties": {
    "gn:admin1_code":"10",
    "gn:asciiname":"Posht Qal`eh",
    "gn:country_code":"IR",
    "gn:dem":832,
    "gn:feature_class":"P",
    "gn:feature_code":"PPL",
    "gn:name":"Posht Qal\u2018eh",
    "gn:population":0,
    "gn:timezone":"Asia/Tehran",
    "iso:country":"IR",
    "name:fas_x_preferred":[
        "\u067e\u0634\u062a \u0642\u0644\u0639\u0647"
    ],
    "name:fas_x_variant":[
        "Posht Qal\u2018eh"
    ],
    "wof:name":"Posht Qal`eh",
    "wof:placetype":"locality"
},
  "geometry": {"coordinates":[47.4352,32.9666],"type":"Point"}
}