{
  "type": "Feature",
  "properties": {
    "gn:admin1_code":"23",
    "gn:asciiname":"Choqa",
    "gn:country_code":"IR",
    "gn:dem":1584,
    "gn:feature_class":"P",
    "gn:feature_code":"PPL",
    "gn:name":"Choq\u0101",
    "gn:population":0,
    "gn:timezone":"Asia/Tehran",
    "iso:country":"IR",
    "name:fas_x_preferred":[
        "\u0686\u064f\u0642\u0627"
    ],
    "wof:name":"Choqa",
    "wof:placetype":"locality"
},
  "geometry": {"coordinates":[47.61667,34.26667],"type":"Point"}
}