{
  "type": "Feature",
  "properties": {
    "gn:admin1_code":"4.0",
    "gn:asciiname":"Allah Dad",
    "gn:country_code":"IR",
    "gn:dem":493,
    "gn:feature_class":"P",
    "gn:feature_code":"PPL",
    "gn:name":"All\u0101h D\u0101d",
    "gn:population":0,
    "gn:timezone":"Asia/Tehran",
    "iso:country":"IR",
    "name:fas_x_preferred":[
        "\u0627\u0644\u0644\u0647 \u062f\u0627\u062f"
    ],
    "name:fas_x_variant":[
        "All\u0101h Dow",
        "All\u0101h D\u0101d",
        "\u0627\u0644\u0644\u0647 \u062f\u0648"
    ],
    "wof:name":"Allah Dad",
    "wof:placetype":"locality"
},
  "geometry": {"coordinates":[61.7431,30.866],"type":"Point"}
}