{
  "type": "Feature",
  "properties": {
    "gn:admin1_code":"40.0",
    "gn:asciiname":"Chah-e Farizi",
    "gn:country_code":"IR",
    "gn:dem":1240,
    "gn:feature_class":"P",
    "gn:feature_code":"PPLL",
    "gn:name":"Ch\u0101h-e Far\u012bz\u012b",
    "gn:population":0,
    "gn:timezone":"Asia/Tehran",
    "iso:country":"IR",
    "name:fas_x_preferred":[
        "\u0686\u0627\u0647 \u0641\u0631\u064a\u0632\u06cc"
    ],
    "name:und_x_variant":[
        "Ch\u0101h-e Far\u012bz\u012b"
    ],
    "wof:name":"Chah-e Farizi",
    "wof:placetype":"locality"
},
  "geometry": {"coordinates":[57.15826,34.88346],"type":"Point"}
}