{
  "type": "Feature",
  "properties": {
    "gn:admin1_code":"13",
    "gn:asciiname":"Babaha",
    "gn:country_code":"IR",
    "gn:dem":1403,
    "gn:feature_class":"P",
    "gn:feature_code":"PPL",
    "gn:name":"B\u0101b\u0101h\u0101",
    "gn:population":0,
    "gn:timezone":"Asia/Tehran",
    "iso:country":"IR",
    "name:fas_x_preferred":[
        "\u0628\u0627\u0628\u0627\u0647\u0627"
    ],
    "name:fas_x_variant":[
        "B\u0101b\u0101h\u0101"
    ],
    "wof:name":"Babaha",
    "wof:placetype":"locality"
},
  "geometry": {"coordinates":[46.5929,34.4175],"type":"Point"}
}