{
  "type": "Feature",
  "properties": {
    "gn:admin1_code":"22",
    "gn:asciiname":"Tokhmari",
    "gn:country_code":"IR",
    "gn:dem":32,
    "gn:feature_class":"P",
    "gn:feature_code":"PPL",
    "gn:name":"Tokhm\u0101r\u012b",
    "gn:population":0,
    "gn:timezone":"Asia/Tehran",
    "iso:country":"IR",
    "name:fas_x_preferred":[
        "\u062a\u062e\u0645\u0627\u0631\u06cc"
    ],
    "name:fas_x_variant":[
        "\u062a\u064f\u062e\u0645\u0650 \u0645\u0627\u0631\u06cc",
        "Tokhm\u0101r\u012b",
        "\u062d\u064e\u0645\u0627\u0631\u06cc"
    ],
    "name:und_x_variant":[
        "Tokhm\u0101ri",
        "Tukhm M\u0101ri",
        "Tokhm-e M\u0101r\u012b",
        "\u1e28am\u0101r\u012b"
    ],
    "wof:name":"Tokhmari",
    "wof:placetype":"locality"
},
  "geometry": {"coordinates":[51.1321,28.9263],"type":"Point"}
}