{
  "type": "Feature",
  "properties": {
    "gn:admin1_code":"7",
    "gn:asciiname":"Hasanabad-e Ramjerd",
    "gn:country_code":"IR",
    "gn:dem":1597,
    "gn:feature_class":"P",
    "gn:feature_code":"PPL",
    "gn:name":"\u1e28asan\u0101b\u0101d-e R\u0101mjerd",
    "gn:population":0,
    "gn:timezone":"Asia/Tehran",
    "iso:country":"IR",
    "name:fas_x_preferred":[
        "\u062d\u0633\u0646 \u0622\u0628\u0627\u062f \u0631\u0627\u0645\u062c\u0631\u062f"
    ],
    "name:fas_x_variant":[
        "\u1e28asan\u0101b\u0101d",
        "\u1e28asan\u0101b\u0101d-e R\u0101mjerd",
        "\u062d\u0633\u0646 \u0622\u0628\u0627\u062f"
    ],
    "name:msa_x_preferred":[
        "Hasanabad"
    ],
    "name:und_x_variant":[
        "Hasan Abad Ramjerd"
    ],
    "wof:name":"Hasanabad-e Ramjerd",
    "wof:placetype":"locality"
},
  "geometry": {"coordinates":[52.5689,29.9385],"type":"Point"}
}