{
  "type": "Feature",
  "properties": {
    "gn:admin1_code":"22",
    "gn:asciiname":"Konari",
    "gn:country_code":"IR",
    "gn:dem":43,
    "gn:feature_class":"P",
    "gn:feature_code":"PPL",
    "gn:name":"Kon\u0101r\u012b",
    "gn:population":0,
    "gn:timezone":"Asia/Tehran",
    "iso:country":"IR",
    "name:fas_x_preferred":[
        "\u0643\u0646\u0627\u0631\u06cc"
    ],
    "name:fas_x_variant":[
        "Kon\u0101r\u012b",
        "\u0643\u064f\u0646\u0627\u0631\u0650 \u0628\u0627\u0628\u0627\u0626\u06cc",
        "\u06a9\u0646\u0627\u0631\u06cc"
    ],
    "name:msa_x_preferred":[
        "Konari"
    ],
    "name:und_x_variant":[
        "Kenari",
        "Kon\u0101r-e B\u0101b\u0101\u2019\u012b"
    ],
    "wof:name":"Konari",
    "wof:placetype":"locality"
},
  "geometry": {"coordinates":[51.27184000000001,28.96431],"type":"Point"}
}