{
  "type": "Feature",
  "properties": {
    "gn:admin1_code":"35",
    "gn:asciiname":"Til Khani",
    "gn:country_code":"IR",
    "gn:dem":78,
    "gn:feature_class":"P",
    "gn:feature_code":"PPL",
    "gn:name":"T\u012bl Kh\u0101n\u012b",
    "gn:population":0,
    "gn:timezone":"Asia/Tehran",
    "iso:country":"IR",
    "name:fas_x_preferred":[
        "\u062a\u064a\u0644 \u062e\u0627\u0646\u06cc"
    ],
    "name:fas_x_variant":[
        "T\u012bl Kh\u0101n\u012b"
    ],
    "wof:name":"Til Khani",
    "wof:placetype":"locality"
},
  "geometry": {"coordinates":[52.78333000000001,36.41667],"type":"Point"}
}