{
  "type": "Feature",
  "properties": {
    "gn:admin1_code":"13",
    "gn:asciiname":"Kal Tarin",
    "gn:country_code":"IR",
    "gn:dem":1464,
    "gn:feature_class":"P",
    "gn:feature_code":"PPL",
    "gn:name":"Kal Tar\u012bn",
    "gn:population":0,
    "gn:timezone":"Asia/Tehran",
    "iso:country":"IR",
    "name:fas_x_preferred":[
        "Kal Tar\u012bn"
    ],
    "wof:name":"Kal Tarin",
    "wof:placetype":"locality"
},
  "geometry": {"coordinates":[47.14472,34.45139],"type":"Point"}
}