{
  "type": "Feature",
  "properties": {
    "gn:admin1_code":"5.0",
    "gn:asciiname":"Shahravi",
    "gn:country_code":"IR",
    "gn:dem":952,
    "gn:feature_class":"P",
    "gn:feature_code":"PPL",
    "gn:name":"Shahrav\u012b",
    "gn:population":0,
    "gn:timezone":"Asia/Tehran",
    "iso:country":"IR",
    "name:fas_x_preferred":[
        "Shahrav\u012b"
    ],
    "name:fas_x_variant":[
        "\u0634\u0647\u0631\u0648\u06cc",
        "\u0634\u0627\u0647 \u0648\u064e\u0644\u06cc"
    ],
    "name:und_x_variant":[
        "Sh\u0101h Val\u012b"
    ],
    "wof:name":"Shahravi",
    "wof:placetype":"locality"
},
  "geometry": {"coordinates":[50.24998,31.02641],"type":"Point"}
}