{
  "type": "Feature",
  "properties": {
    "gn:admin1_code":"8",
    "gn:asciiname":"Chaharman",
    "gn:country_code":"IR",
    "gn:dem":328,
    "gn:feature_class":"P",
    "gn:feature_code":"PPL",
    "gn:name":"Chah\u0101rm\u0101n",
    "gn:population":0,
    "gn:timezone":"Asia/Tehran",
    "iso:country":"IR",
    "name:fas_x_preferred":[
        "Chah\u0101rm\u0101n"
    ],
    "name:fas_x_variant":[
        "Ch\u0101rem\u0101n",
        "\u0686\u0647\u0627\u0631\u0645\u0627\u0646"
    ],
    "name:und_x_variant":[
        "\u0686\u0647\u0627\u0631\u0645\u0627\u0646"
    ],
    "wof:name":"Chaharman",
    "wof:placetype":"locality"
},
  "geometry": {"coordinates":[49.53861,36.96878],"type":"Point"}
}