{
  "type": "Feature",
  "properties": {
    "gn:admin1_code":"15.0",
    "gn:asciiname":"Gowreh",
    "gn:country_code":"IR",
    "gn:dem":588,
    "gn:feature_class":"P",
    "gn:feature_code":"PPL",
    "gn:name":"Gowreh",
    "gn:population":0,
    "gn:timezone":"Asia/Tehran",
    "iso:country":"IR",
    "name:fas_x_preferred":[
        "\u062e\u0648\u0631\u0647"
    ],
    "name:fas_x_variant":[
        "\u06af\u0648\u0631\u0647"
    ],
    "name:und_x_variant":[
        "Khowreh",
        "Gowreh"
    ],
    "wof:name":"Gowreh",
    "wof:placetype":"locality"
},
  "geometry": {"coordinates":[49.74705,31.52765],"type":"Point"}
}