{
  "type": "Feature",
  "properties": {
    "gn:admin1_code":"7",
    "gn:asciiname":"Hararkunzard",
    "gn:cc2":"IR",
    "gn:country_code":"IR",
    "gn:dem":1851,
    "gn:feature_class":"P",
    "gn:feature_code":"PPL",
    "gn:name":"\u1e24ar\u0101rk\u016bnzard",
    "gn:population":0,
    "gn:timezone":"Asia/Tehran",
    "iso:country":"IR",
    "name:fas_x_preferred":[
        "\u1e24ar\u0101rk\u016bnzard"
    ],
    "name:und_x_variant":[
        "B\u016byer A\u1e29mad"
    ],
    "wof:name":"Hararkunzard",
    "wof:placetype":"locality"
},
  "geometry": {"coordinates":[51.78333,30.03333],"type":"Point"}
}