{
  "type": "Feature",
  "properties": {
    "gn:admin1_code":"11",
    "gn:asciiname":"Pegu",
    "gn:country_code":"IR",
    "gn:dem":47,
    "gn:feature_class":"P",
    "gn:feature_code":"PPL",
    "gn:name":"Peg\u016b",
    "gn:population":0,
    "gn:timezone":"Asia/Tehran",
    "iso:country":"IR",
    "name:fas_x_preferred":[
        "\u067e\u06af\u0648"
    ],
    "name:fas_x_variant":[
        "Peg\u016b"
    ],
    "name:und_x_variant":[
        "Pog\u016b"
    ],
    "wof:name":"Pegu",
    "wof:placetype":"locality"
},
  "geometry": {"coordinates":[57.3405,26.3453],"type":"Point"}
}