{
  "type": "Feature",
  "properties": {
    "gn:admin1_code":"29",
    "gn:asciiname":"Kaliyan",
    "gn:country_code":"IR",
    "gn:dem":1916,
    "gn:feature_class":"P",
    "gn:feature_code":"PPL",
    "gn:name":"Kal\u012by\u0101n",
    "gn:population":0,
    "gn:timezone":"Asia/Tehran",
    "iso:country":"IR",
    "name:ara_x_preferred":[
        "\u0643\u0644\u064a\u0627\u0646"
    ],
    "name:fas_x_preferred":[
        "\u06a9\u0644\u06cc\u0651\u0627\u0646"
    ],
    "name:fas_x_variant":[
        "Kal\u012b\u0101n",
        "Kal\u012by\u0101n",
        "\u06a9\u0644\u06cc\u0627\u0646"
    ],
    "name:und_x_variant":[
        "G\u012blan",
        "Kaly\u016bn",
        "Kaliy\u016bn",
        "Kaly\u0101n",
        "Kaliyan"
    ],
    "wof:name":"Kaliyan",
    "wof:placetype":"locality"
},
  "geometry": {"coordinates":[56.6823,28.7055],"type":"Point"}
}