{
  "type": "Feature",
  "properties": {
    "gn:admin1_code":"8",
    "gn:asciiname":"Khuki",
    "gn:country_code":"IR",
    "gn:dem":405,
    "gn:feature_class":"P",
    "gn:feature_code":"PPL",
    "gn:name":"Kh\u016bk\u012b",
    "gn:population":0,
    "gn:timezone":"Asia/Tehran",
    "iso:country":"IR",
    "name:fas_x_preferred":[
        "Kh\u016bk\u012b"
    ],
    "name:fas_x_variant":[
        "\u062e\u0648\u06a9\u06cc"
    ],
    "wof:name":"Khuki",
    "wof:placetype":"locality"
},
  "geometry": {"coordinates":[49.53489,37.02026],"type":"Point"}
}