{
  "type": "Feature",
  "properties": {
    "gn:admin1_code":"23",
    "gn:asciiname":"Bagh-e Taleqani",
    "gn:country_code":"IR",
    "gn:dem":2448,
    "gn:feature_class":"P",
    "gn:feature_code":"PPL",
    "gn:name":"B\u0101gh-e \u0162\u0101leq\u0101n\u012b",
    "gn:population":0,
    "gn:timezone":"Asia/Tehran",
    "iso:country":"IR",
    "name:fas_x_preferred":[
        "B\u0101gh-e Sh\u0101h"
    ],
    "name:fas_x_variant":[
        "\u0628\u0627\u063a\u0634\u0627\u0647",
        "\u0628\u0627\u063a \u0637\u0627\u0644\u0642\u0627\u0646\u06cc"
    ],
    "name:und_x_variant":[
        "B\u0101gh-e \u0162\u0101leq\u0101n\u012b"
    ],
    "wof:name":"Bagh-e Taleqani",
    "wof:placetype":"locality"
},
  "geometry": {"coordinates":[49.8622,33.09458],"type":"Point"}
}