{
  "type": "Feature",
  "properties": {
    "gn:admin1_code":"4.0",
    "gn:asciiname":"Shamsabad-e Sarhang",
    "gn:country_code":"IR",
    "gn:dem":550,
    "gn:feature_class":"P",
    "gn:feature_code":"PPL",
    "gn:name":"Shams\u0101b\u0101d-e Sarhang",
    "gn:population":0,
    "gn:timezone":"Asia/Tehran",
    "iso:country":"IR",
    "name:fas_x_preferred":[
        "\u0634\u0645\u0633 \u0622\u0628\u0627\u062f \u0633\u0631\u0647\u0646\u06af"
    ],
    "name:fas_x_variant":[
        "N\u016bk\u0101b\u0101d",
        "\u0646\u0648\u06a9 \u0622\u0628\u0627\u062f",
        "Shams\u0101b\u0101d-e Sarhang"
    ],
    "wof:name":"Shamsabad-e Sarhang",
    "wof:placetype":"locality"
},
  "geometry": {"coordinates":[60.61084,27.19421],"type":"Point"}
}