{
  "type": "Feature",
  "properties": {
    "gn:admin1_code":"1",
    "gn:asciiname":"Daylaq",
    "gn:country_code":"IR",
    "gn:dem":1305,
    "gn:feature_class":"P",
    "gn:feature_code":"PPL",
    "gn:name":"D\u0101yl\u0101q",
    "gn:population":0,
    "gn:timezone":"Asia/Tehran",
    "iso:country":"IR",
    "name:azb_x_preferred":[
        "\u062f\u0627\u06cc\u0644\u0627\u0642"
    ],
    "name:aze_x_preferred":[
        "Daylaq"
    ],
    "name:fas_x_preferred":[
        "\u062f\u0627\u06cc\u0644\u0627\u0642"
    ],
    "name:fas_x_variant":[
        "D\u0101yl\u0101q"
    ],
    "name:msa_x_preferred":[
        "Daylaq"
    ],
    "name:ukr_x_preferred":[
        "\u0414\u0430\u0439\u043b\u0430\u043a"
    ],
    "wof:name":"Daylaq",
    "wof:placetype":"locality"
},
  "geometry": {"coordinates":[45.0897,37.6328],"type":"Point"}
}