{
  "type": "Feature",
  "properties": {
    "gn:admin1_code":"8",
    "gn:asciiname":"Chomaqestan-e Sofla",
    "gn:country_code":"IR",
    "gn:dem":2,
    "gn:feature_class":"P",
    "gn:feature_code":"PPL",
    "gn:name":"Chom\u0101qest\u0101n-e Sofl\u00e1",
    "gn:population":0,
    "gn:timezone":"Asia/Tehran",
    "iso:country":"IR",
    "name:fas_x_preferred":[
        "Chom\u0101qest\u0101n"
    ],
    "name:fas_x_variant":[
        "\u0686\u0645\u0627\u0642\u0633\u062a\u0627\u0646 \u0633\u0641\u0644\u06cc",
        "\u0686\u0645\u0627\u0642\u0633\u062a\u0627\u0646"
    ],
    "name:und_x_variant":[
        "Chom\u0101qest\u0101n-e Sofl\u00e1"
    ],
    "wof:name":"Chomaqestan-e Sofla",
    "wof:placetype":"locality"
},
  "geometry": {"coordinates":[50.20239,37.13427],"type":"Point"}
}