{
  "type": "Feature",
  "properties": {
    "gn:admin1_code":"41",
    "gn:asciiname":"Hesar",
    "gn:country_code":"IR",
    "gn:dem":1964,
    "gn:feature_class":"P",
    "gn:feature_code":"PPL",
    "gn:name":"\u1e28e\u015f\u0101r",
    "gn:population":0,
    "gn:timezone":"Asia/Tehran",
    "iso:country":"IR",
    "name:fas_x_preferred":[
        "\u1e28e\u015f\u0101r"
    ],
    "name:fas_x_variant":[
        "\u062d\u0635\u0627\u0631",
        "His\u0101r",
        "\u0627\u0633\u067e\u064a\u06af\u06cc"
    ],
    "name:und_x_variant":[
        "His\u0101r",
        "\u062d\u0635\u0627\u0631",
        "Esp\u012bg\u012b"
    ],
    "wof:name":"Hesar",
    "wof:placetype":"locality"
},
  "geometry": {"coordinates":[59.28742,32.6748],"type":"Point"}
}