{
  "type": "Feature",
  "properties": {
    "gn:admin1_code":"11",
    "gn:asciiname":"Dalalan",
    "gn:country_code":"IR",
    "gn:dem":13,
    "gn:feature_class":"P",
    "gn:feature_code":"PPL",
    "gn:name":"Dal\u0101lan",
    "gn:population":0,
    "gn:timezone":"Asia/Tehran",
    "iso:country":"IR",
    "name:fas_x_preferred":[
        "\u062f\u0644\u0627\u0644\u0646"
    ],
    "name:fas_x_variant":[
        "Dal\u0101lan",
        "\u062f\u0644\u0627\u0644\u0648\u0646"
    ],
    "name:msa_x_preferred":[
        "Dalalun"
    ],
    "name:und_x_variant":[
        "Del\u0101l\u0101n",
        "Del\u0101lon",
        "Dal\u0101l\u016bn"
    ],
    "wof:name":"Dalalan",
    "wof:placetype":"locality"
},
  "geometry": {"coordinates":[56.9478,27.1603],"type":"Point"}
}