{
  "type": "Feature",
  "properties": {
    "gn:admin1_code":"35.0",
    "gn:asciiname":"Karsank",
    "gn:country_code":"IR",
    "gn:dem":362,
    "gn:feature_class":"P",
    "gn:feature_code":"PPL",
    "gn:name":"Karsank",
    "gn:population":0,
    "gn:timezone":"Asia/Tehran",
    "iso:country":"IR",
    "name:fas_x_preferred":[
        "\u0643\u0631\u0633\u0646\u06a9"
    ],
    "wof:name":"Karsank",
    "wof:placetype":"locality"
},
  "geometry": {"coordinates":[52.3653,36.29543],"type":"Point"}
}