{
  "type": "Feature",
  "properties": {
    "gn:admin1_code":"23",
    "gn:asciiname":"Alus",
    "gn:country_code":"IR",
    "gn:dem":2056,
    "gn:feature_class":"P",
    "gn:feature_code":"PPL",
    "gn:name":"Al\u016bs",
    "gn:population":0,
    "gn:timezone":"Asia/Tehran",
    "iso:country":"IR",
    "name:fas_x_preferred":[
        "\u0645\u0644\u06a9 \u0627\u0644\u0648\u0633"
    ],
    "name:fas_x_variant":[
        "\u0627\u064e\u0644\u0648\u0633",
        "\u0627\u0644\u0648\u0633"
    ],
    "name:und_x_variant":[
        "Malek Al\u016bs",
        "Al\u016bs",
        "\u0627\u0644\u0648\u0633",
        "Alows"
    ],
    "wof:name":"Alus",
    "wof:placetype":"locality"
},
  "geometry": {"coordinates":[49.60588,33.03766],"type":"Point"}
}