{
  "type": "Feature",
  "properties": {
    "gn:admin1_code":"29",
    "gn:asciiname":"Garik",
    "gn:country_code":"IR",
    "gn:dem":2471,
    "gn:feature_class":"P",
    "gn:feature_code":"PPL",
    "gn:name":"G\u0101r\u012bk",
    "gn:population":0,
    "gn:timezone":"Asia/Tehran",
    "iso:country":"IR",
    "name:fas_x_preferred":[
        "\u06af\u0627\u0631\u06cc\u06a9"
    ],
    "name:fas_x_variant":[
        "K\u0101r\u012bg",
        "G\u0101r\u012bk"
    ],
    "wof:name":"Garik",
    "wof:placetype":"locality"
},
  "geometry": {"coordinates":[55.1947,30.4013],"type":"Point"}
}