{
  "type": "Feature",
  "properties": {
    "gn:admin1_code":"11",
    "gn:asciiname":"Bar Ahang",
    "gn:country_code":"IR",
    "gn:dem":526,
    "gn:feature_class":"P",
    "gn:feature_code":"PPL",
    "gn:name":"Bar \u0100hang",
    "gn:population":0,
    "gn:timezone":"Asia/Tehran",
    "iso:country":"IR",
    "name:fas_x_preferred":[
        "\u0628\u0631 \u0622\u0647\u0646\u06af"
    ],
    "name:fas_x_variant":[
        "Bar \u0100hang"
    ],
    "wof:name":"Bar Ahang",
    "wof:placetype":"locality"
},
  "geometry": {"coordinates":[57.5191,26.4406],"type":"Point"}
}