{
  "type": "Feature",
  "properties": {
    "gn:admin1_code":"8.0",
    "gn:asciiname":"Yekavark",
    "gn:country_code":"IR",
    "gn:dem":451,
    "gn:feature_class":"P",
    "gn:feature_code":"PPL",
    "gn:name":"Yek\u0101vark",
    "gn:population":0,
    "gn:timezone":"Asia/Tehran",
    "iso:country":"IR",
    "name:fas_x_preferred":[
        "\u06cc\u06a9\u0627\u0648\u0631\u06a9"
    ],
    "name:und_x_variant":[
        "Yek\u0101vark"
    ],
    "wof:name":"Yekavark",
    "wof:placetype":"locality"
},
  "geometry": {"coordinates":[49.90063,37.03413],"type":"Point"}
}