{
  "type": "Feature",
  "properties": {
    "gn:admin1_code":"3",
    "gn:asciiname":"Bagh-e Mohammad `Ali",
    "gn:country_code":"IR",
    "gn:dem":1960,
    "gn:feature_class":"P",
    "gn:feature_code":"PPL",
    "gn:name":"B\u0101gh-e Mo\u1e29ammad \u2018Al\u012b",
    "gn:population":0,
    "gn:timezone":"Asia/Tehran",
    "iso:country":"IR",
    "name:fas_x_preferred":[
        "\u0628\u0627\u063a \u0645\u062d\u0645\u062f \u0639\u0644\u06cc"
    ],
    "name:fas_x_variant":[
        "B\u0101gh-e Mo\u1e29ammad \u2018Al\u012b"
    ],
    "wof:name":"Bagh-e Mohammad `Ali",
    "wof:placetype":"locality"
},
  "geometry": {"coordinates":[51.11836,31.2841],"type":"Point"}
}