{
  "type": "Feature",
  "properties": {
    "gn:admin1_code":"23",
    "gn:asciiname":"Dul Gaz",
    "gn:country_code":"IR",
    "gn:dem":1254,
    "gn:feature_class":"P",
    "gn:feature_code":"PPL",
    "gn:name":"D\u016bl Gaz",
    "gn:population":0,
    "gn:timezone":"Asia/Tehran",
    "iso:country":"IR",
    "name:fas_x_preferred":[
        "\u062f\u0648\u0644 \u06af\u064e\u0632\u0650 \u0631\u064e\u062c\u064e\u0628\u0639\u064e\u0644\u06cc"
    ],
    "name:fas_x_variant":[
        "D\u016bl Gaz-e Rajab\u2018al\u012b",
        "\u062f\u0648\u0644 \u06af\u0632",
        "\u0634\u0647\u06cc\u062f \u062c\u0645\u0631\u0627\u0646 \u062f\u0648",
        "\u062f\u0648\u0644\u06af\u0632\u0631\u062c\u0628\u0639\u0644\u06cc"
    ],
    "name:und_x_variant":[
        "D\u016bl Gaz",
        "Shah\u012bd Chamr\u0101n-e Do"
    ],
    "wof:name":"Dul Gaz",
    "wof:placetype":"locality"
},
  "geometry": {"coordinates":[48.0765,33.2107],"type":"Point"}
}