{
  "type": "Feature",
  "properties": {
    "gn:admin1_code":"15",
    "gn:asciiname":"Qeysariyeh-ye `Olya",
    "gn:country_code":"IR",
    "gn:dem":14,
    "gn:feature_class":"P",
    "gn:feature_code":"PPL",
    "gn:name":"Qey\u015far\u012byeh-ye \u2018Oly\u0101",
    "gn:population":0,
    "gn:timezone":"Asia/Tehran",
    "iso:country":"IR",
    "name:fas_x_preferred":[
        "\u0642\u06cc\u0635\u0631\u06cc\u0647 \u0639\u0644\u06cc\u0627"
    ],
    "name:fas_x_variant":[
        "Qey\u015far\u012byeh-ye B\u0101l\u0101",
        "Qey\u015far\u012byeh-ye \u2018Oly\u0101"
    ],
    "wof:name":"Qeysariyeh-ye `Olya",
    "wof:placetype":"locality"
},
  "geometry": {"coordinates":[48.15414000000001,31.42095],"type":"Point"}
}