{
  "type": "Feature",
  "properties": {
    "gn:admin1_code":"35",
    "gn:asciiname":"`Ali Kola",
    "gn:country_code":"IR",
    "gn:dem":731,
    "gn:feature_class":"P",
    "gn:feature_code":"PPL",
    "gn:name":"\u2018\u0100l\u012b Kol\u0101",
    "gn:population":0,
    "gn:timezone":"Asia/Tehran",
    "iso:country":"IR",
    "name:fas_x_preferred":[
        "\u0639\u0627\u0644\u064a\u0650\u0651\u0647 \u0643\u064f\u0644\u0627"
    ],
    "name:fas_x_variant":[
        "\u2018\u0100l\u012byeh Kol\u0101",
        "\u2018\u0100l\u012b Kol\u0101",
        "\u0639\u0627\u0644\u06cc \u0643\u0644\u0627"
    ],
    "wof:name":"`Ali Kola",
    "wof:placetype":"locality"
},
  "geometry": {"coordinates":[52.99473,36.17571],"type":"Point"}
}