{
  "type": "Feature",
  "properties": {
    "gn:admin1_code":"4",
    "gn:asciiname":"Khaleqabad",
    "gn:country_code":"IR",
    "gn:dem":377,
    "gn:feature_class":"P",
    "gn:feature_code":"PPL",
    "gn:name":"Kh\u0101leq\u0101b\u0101d",
    "gn:population":0,
    "gn:timezone":"Asia/Tehran",
    "iso:country":"IR",
    "name:fas_x_preferred":[
        "\u1e28\u0101lek\u0101b\u0101d"
    ],
    "name:fas_x_variant":[
        "\u062e\u0627\u0644\u0642 \u0622\u0628\u0627\u062f"
    ],
    "name:und_x_variant":[
        "Kh\u0101leq\u0101b\u0101d",
        "Kh\u0101leg\u0101b\u0101d"
    ],
    "wof:name":"Khaleqabad",
    "wof:placetype":"locality"
},
  "geometry": {"coordinates":[59.2085,27.1301],"type":"Point"}
}