{
  "type": "Feature",
  "properties": {
    "gn:admin1_code":"15",
    "gn:asciiname":"Pameleh",
    "gn:country_code":"IR",
    "gn:dem":1636,
    "gn:feature_class":"P",
    "gn:feature_code":"PPL",
    "gn:name":"P\u0101meleh",
    "gn:population":0,
    "gn:timezone":"Asia/Tehran",
    "iso:country":"IR",
    "name:azb_x_preferred":[
        "\u067e\u0627\u0645\u0644\u0647(\u0627\u06cc\u0630\u0647)"
    ],
    "name:fas_x_preferred":[
        "P\u0101meleh"
    ],
    "name:fas_x_variant":[
        "\u067e\u0627\u0645\u0644\u0647"
    ],
    "wof:name":"Pameleh",
    "wof:placetype":"locality"
},
  "geometry": {"coordinates":[50.11194,31.84889],"type":"Point"}
}