{
  "type": "Feature",
  "properties": {
    "gn:admin1_code":"28.0",
    "gn:asciiname":"Sohr",
    "gn:country_code":"IR",
    "gn:dem":1645,
    "gn:feature_class":"P",
    "gn:feature_code":"PPL",
    "gn:name":"Sohr",
    "gn:population":0,
    "gn:timezone":"Asia/Tehran",
    "iso:country":"IR",
    "name:fas_x_preferred":[
        "\u0633\u0647\u0631"
    ],
    "wof:name":"Sohr",
    "wof:placetype":"locality"
},
  "geometry": {"coordinates":[51.53322,32.45423],"type":"Point"}
}