{
  "type": "Feature",
  "properties": {
    "gn:admin1_code":"34",
    "gn:asciiname":"Shur Qu'i",
    "gn:country_code":"IR",
    "gn:dem":1274,
    "gn:feature_class":"P",
    "gn:feature_code":"PPL",
    "gn:name":"Sh\u016br Q\u016b\u2019\u012b",
    "gn:population":0,
    "gn:timezone":"Asia/Tehran",
    "iso:country":"IR",
    "name:fas_x_preferred":[
        "\u0642\u064a\u0651\u0648\u062c\u064a\u0643"
    ],
    "name:fas_x_variant":[
        "\u0642\u0650\u0634\u0644\u0627\u0642\u0650 \u0642\u0648\u064a\u0648\u062c\u0627\u0642",
        "Sh\u016br Q\u016b\u2019\u012b",
        "Q\u012by\u016bj\u012bk",
        "\u0634\u0648\u0631 \u0642\u0648\u0626\u06cc"
    ],
    "name:und_x_variant":[
        "Qeshl\u0101q-e Q\u016by\u016bj\u0101q"
    ],
    "wof:name":"Shur Qu'i",
    "wof:placetype":"locality"
},
  "geometry": {"coordinates":[50.09233,34.94694],"type":"Point"}
}