{
  "type": "Feature",
  "properties": {
    "gn:admin1_code":"11",
    "gn:asciiname":"Kordap",
    "gn:cc2":"IR",
    "gn:country_code":"IR",
    "gn:dem":5,
    "gn:feature_class":"P",
    "gn:feature_code":"PPL",
    "gn:name":"Kord\u0101p",
    "gn:population":0,
    "gn:timezone":"Asia/Tehran",
    "iso:country":"IR",
    "name:fas_x_preferred":[
        "\u0643\u064f\u0631\u062f\u0627\u067e"
    ],
    "name:fas_x_variant":[
        "\u0643\u064f\u0631\u062f\u064e\u0641",
        "\u0643\u064e\u0631\u064e\u067e",
        "Kord\u0101p"
    ],
    "name:und_x_variant":[
        "Karap",
        "Kordaf"
    ],
    "wof:name":"Kordap",
    "wof:placetype":"locality"
},
  "geometry": {"coordinates":[58.16667,25.61667000000001],"type":"Point"}
}