{
  "type": "Feature",
  "properties": {
    "gn:admin1_code":"32",
    "gn:asciiname":"Mollalar",
    "gn:country_code":"IR",
    "gn:dem":743,
    "gn:feature_class":"P",
    "gn:feature_code":"PPL",
    "gn:name":"Moll\u0101lar",
    "gn:population":0,
    "gn:timezone":"Asia/Tehran",
    "iso:country":"IR",
    "name:fas_x_preferred":[
        "\u0645\u064f\u0644\u0651\u0627\u0644\u064f\u0631"
    ],
    "name:fas_x_variant":[
        "\u0645\u064f\u0644\u0651\u0627\u0644\u0648",
        "\u0645\u0644\u0627\u0644\u0631",
        "Moll\u0101lor",
        "Moll\u0101lar"
    ],
    "name:und_x_variant":[
        "Moll\u0101l\u016b"
    ],
    "wof:name":"Mollalar",
    "wof:placetype":"locality"
},
  "geometry": {"coordinates":[47.7322,39.0534],"type":"Point"}
}