{
  "type": "Feature",
  "properties": {
    "gn:admin1_code":"16",
    "gn:asciiname":"Dahlek",
    "gn:country_code":"IR",
    "gn:dem":1740,
    "gn:feature_class":"P",
    "gn:feature_code":"PPL",
    "gn:name":"Dahlek",
    "gn:population":0,
    "gn:timezone":"Asia/Tehran",
    "iso:country":"IR",
    "name:fas_x_preferred":[
        "\u062f\u0644\u06a9"
    ],
    "name:fas_x_variant":[
        "\u062f\u0647\u0644\u06a9"
    ],
    "name:und_x_variant":[
        "Deh-e L\u016b",
        "Dahlek",
        "Deh-i-Lu",
        "Delak",
        "Dalak"
    ],
    "wof:name":"Dahlek",
    "wof:placetype":"locality"
},
  "geometry": {"coordinates":[47.53174,35.37555],"type":"Point"}
}