{
  "type": "Feature",
  "properties": {
    "gn:admin1_code":"44.0",
    "gn:asciiname":"Lahran",
    "gn:country_code":"IR",
    "gn:dem":1808,
    "gn:feature_class":"P",
    "gn:feature_code":"PPL",
    "gn:name":"Lahr\u0101n",
    "gn:population":0,
    "gn:timezone":"Asia/Tehran",
    "iso:country":"IR",
    "name:fas_x_preferred":[
        "Lahr\u0101n"
    ],
    "name:fas_x_variant":[
        "\u0644\u0647\u0631\u0627\u0646"
    ],
    "name:und_x_variant":[
        "\u0644\u0647\u0631\u0627\u0646"
    ],
    "wof:name":"Lahran",
    "wof:placetype":"locality"
},
  "geometry": {"coordinates":[50.6077,36.21884],"type":"Point"}
}