{
  "type": "Feature",
  "properties": {
    "gn:admin1_code":"36",
    "gn:asciiname":"Tazeh Kand",
    "gn:country_code":"IR",
    "gn:dem":1540,
    "gn:feature_class":"P",
    "gn:feature_code":"PPL",
    "gn:name":"T\u0101zeh Kand",
    "gn:population":0,
    "gn:timezone":"Asia/Tehran",
    "iso:country":"IR",
    "name:fas_x_preferred":[
        "\u0646\u0638\u0627\u0645 \u0622\u0628\u0627\u062f"
    ],
    "name:fas_x_variant":[
        "\u0646\u064e\u0632\u064a\u0645 \u0622\u0628\u0627\u062f",
        "Nez\u0327\u0101m\u0101b\u0101d",
        "\u062a\u0627\u0632\u0647 \u06a9\u0646\u062f"
    ],
    "name:und_x_variant":[
        "Naz\u012bm\u0101b\u0101d",
        "Nizvimabad",
        "T\u0101zeh Kand"
    ],
    "wof:name":"Tazeh Kand",
    "wof:placetype":"locality"
},
  "geometry": {"coordinates":[48.3653,36.7184],"type":"Point"}
}