{
  "type": "Feature",
  "properties": {
    "gn:admin1_code":"4.0",
    "gn:asciiname":"Zangian",
    "gn:country_code":"IR",
    "gn:dem":1164,
    "gn:feature_class":"P",
    "gn:feature_code":"PPL",
    "gn:name":"Zang\u012b\u0101n",
    "gn:population":0,
    "gn:timezone":"Asia/Tehran",
    "iso:country":"IR",
    "name:fas_x_preferred":[
        "\u0632\u0646\u06af\u06cc\u0627\u0646"
    ],
    "name:fas_x_variant":[
        "Zang\u012b\u0101n"
    ],
    "name:und_x_variant":[
        "Sang\u012b\u0101n"
    ],
    "wof:name":"Zangian",
    "wof:placetype":"locality"
},
  "geometry": {"coordinates":[62.37838000000001,27.33462],"type":"Point"}
}