{
  "type": "Feature",
  "properties": {
    "gn:admin1_code":"3.0",
    "gn:asciiname":"Shuran",
    "gn:country_code":"IR",
    "gn:dem":1808,
    "gn:feature_class":"P",
    "gn:feature_code":"PPL",
    "gn:name":"Sh\u016br\u0101n",
    "gn:population":0,
    "gn:timezone":"Asia/Tehran",
    "iso:country":"IR",
    "name:fas_x_preferred":[
        "Sh\u016br\u0101n"
    ],
    "name:fas_x_variant":[
        "\u0634\u0648\u0631\u0627\u0646"
    ],
    "name:und_x_variant":[
        "\u0634\u0648\u0631\u0627\u0646"
    ],
    "wof:name":"Shuran",
    "wof:placetype":"locality"
},
  "geometry": {"coordinates":[50.46629,31.94069],"type":"Point"}
}