{
  "type": "Feature",
  "properties": {
    "gn:admin1_code":"0",
    "gn:asciiname":"Murtestan",
    "gn:country_code":"IR",
    "gn:dem":1534,
    "gn:feature_class":"P",
    "gn:feature_code":"PPL",
    "gn:name":"M\u016brtest\u0101n",
    "gn:population":0,
    "gn:timezone":"Asia/Tehran",
    "iso:country":"IR",
    "name:fas_x_preferred":[
        "\u0645\u0648\u0631\u062a\u0633\u062a\u0627\u0646"
    ],
    "name:fas_x_variant":[
        "M\u016brtest\u0101n"
    ],
    "wof:name":"Murtestan",
    "wof:placetype":"locality"
},
  "geometry": {"coordinates":[55.3664,28.4982],"type":"Point"}
}