{
  "type": "Feature",
  "properties": {
    "gn:admin1_code":"22",
    "gn:asciiname":"Shahr-e Viran",
    "gn:cc2":"IR",
    "gn:country_code":"IR",
    "gn:dem":56,
    "gn:feature_class":"P",
    "gn:feature_code":"PPL",
    "gn:name":"Shahr-e V\u012br\u0101n",
    "gn:population":0,
    "gn:timezone":"Asia/Tehran",
    "iso:country":"IR",
    "name:fas_x_preferred":[
        "\u0634\u064e\u0647\u0631\u0650 \u0648\u064a\u0631\u0627\u0646"
    ],
    "name:fas_x_variant":[
        "\u0634\u064e\u0647\u0631\u0650 \u0648\u0650\u064a\u0631\u0648\u0646",
        "\u0634\u064e\u0647\u0631\u0650 \u0648\u0650\u064a\u0631\u0627\u0646",
        "Shahr-e V\u012br\u0101n"
    ],
    "name:und_x_variant":[
        "Sharviran",
        "Shahr-e Veyr\u0101n",
        "Shahr-e Veyr\u016bn"
    ],
    "wof:name":"Shahr-e Viran",
    "wof:placetype":"locality"
},
  "geometry": {"coordinates":[50.49444,29.90444],"type":"Point"}
}