{
  "type": "Feature",
  "properties": {
    "gn:admin1_code":"38",
    "gn:asciiname":"Danesfahan",
    "gn:country_code":"IR",
    "gn:dem":1325,
    "gn:feature_class":"P",
    "gn:feature_code":"PPL",
    "gn:name":"D\u0101nesfah\u0101n",
    "gn:population":0,
    "gn:timezone":"Asia/Tehran",
    "iso:country":"IR",
    "name:ara_x_preferred":[
        "\u062f\u0627\u0646\u0633\u0641\u0647\u0627\u0646"
    ],
    "name:aze_x_preferred":[
        "Danisfahan"
    ],
    "name:ceb_x_preferred":[
        "D\u0101nesfah\u0101n"
    ],
    "name:deu_x_preferred":[
        "Danesfahan"
    ],
    "name:fas_x_preferred":[
        "\u062f\u0627\u0646\u0633\u0641\u0647\u0627\u0646"
    ],
    "name:fas_x_variant":[
        "D\u0101nesfah\u0101n"
    ],
    "name:ita_x_preferred":[
        "Danesfahan"
    ],
    "name:mlg_x_preferred":[
        "Danesfahan"
    ],
    "name:pol_x_preferred":[
        "Danesfahan"
    ],
    "name:rus_x_preferred":[
        "\u0414\u0430\u043d\u0435\u0441\u0444\u0435\u0445\u0430\u043d"
    ],
    "name:swe_x_preferred":[
        "D\u0101nesfah\u0101n"
    ],
    "name:tur_x_preferred":[
        "Danisfahan"
    ],
    "name:und_x_variant":[
        "D\u0101nesf\u0101n",
        "Dan\u012bsfah\u0101n"
    ],
    "wof:name":"Danesfahan",
    "wof:placetype":"locality"
},
  "geometry": {"coordinates":[49.74315,35.81151],"type":"Point"}
}