{
  "type": "Feature",
  "properties": {
    "gn:admin1_code":"32.0",
    "gn:asciiname":"Sari Darreh Qeshlaq",
    "gn:country_code":"IR",
    "gn:dem":1340,
    "gn:feature_class":"P",
    "gn:feature_code":"PPLL",
    "gn:name":"S\u0101r\u012b Darreh Qeshl\u0101q",
    "gn:population":0,
    "gn:timezone":"Asia/Tehran",
    "iso:country":"IR",
    "name:fas_x_preferred":[
        "\u0633\u0627\u0631\u06cc \u062f\u0631\u0647 \u0642\u0634\u0644\u0627\u0642"
    ],
    "name:und_x_variant":[
        "S\u0101r\u012b Darreh Qeshl\u0101q"
    ],
    "wof:name":"Sari Darreh Qeshlaq",
    "wof:placetype":"locality"
},
  "geometry": {"coordinates":[47.67767,38.71016],"type":"Point"}
}