{
  "type": "Feature",
  "properties": {
    "gn:admin1_code":"3",
    "gn:asciiname":"Kaj",
    "gn:country_code":"IR",
    "gn:dem":1695,
    "gn:feature_class":"P",
    "gn:feature_code":"PPL",
    "gn:name":"K\u0101j",
    "gn:population":0,
    "gn:timezone":"Asia/Tehran",
    "iso:country":"IR",
    "name:ceb_x_preferred":[
        "Kaj"
    ],
    "name:dan_x_preferred":[
        "Kaj"
    ],
    "name:fas_x_preferred":[
        "\u0643\u0627\u062c"
    ],
    "name:fas_x_variant":[
        "\u0642\u0627\u0686 \u0643\u064e\u062c",
        "K\u0101j",
        "\u06af\u0627\u0686 \u0643\u064e\u062c"
    ],
    "name:pol_x_preferred":[
        "Kaj"
    ],
    "name:swe_x_preferred":[
        "Kaj"
    ],
    "name:und_x_variant":[
        "Q\u0101ch Kaj",
        "G\u0101ch Kaj"
    ],
    "wof:name":"Kaj",
    "wof:placetype":"locality"
},
  "geometry": {"coordinates":[50.58286,32.05819],"type":"Point"}
}