{
  "type": "Feature",
  "properties": {
    "gn:admin1_code":"34",
    "gn:asciiname":"Qelich Tappeh",
    "gn:country_code":"IR",
    "gn:dem":1791,
    "gn:feature_class":"P",
    "gn:feature_code":"PPL",
    "gn:name":"Qel\u012bch Tappeh",
    "gn:population":0,
    "gn:timezone":"Asia/Tehran",
    "iso:country":"IR",
    "name:fas_x_preferred":[
        "\u0642\u0644\u064a\u0686 \u062a\u067e\u0647"
    ],
    "name:fas_x_variant":[
        "Qel\u012bch Tappeh"
    ],
    "wof:name":"Qelich Tappeh",
    "wof:placetype":"locality"
},
  "geometry": {"coordinates":[49.2525,34.4776],"type":"Point"}
}