{
  "type": "Feature",
  "properties": {
    "gn:admin1_code":"34",
    "gn:asciiname":"Qelich Tappeh",
    "gn:country_code":"IR",
    "gn:dem":1791,
    "gn:feature_class":"P",
    "gn:feature_code":"PPL",
    "gn:name":"Qel\u012bch Tappeh",
    "gn:population":0,
    "gn:timezone":"Asia/Tehran",
    "iso:country":"IR",
    "name:ceb_x_preferred":[
        "Qel\u012bch Tappeh"
    ],
    "name:fas_x_preferred":[
        "\u0642\u0644\u064a\u0686 \u062a\u067e\u0647"
    ],
    "name:fas_x_variant":[
        "Qel\u012bch Tappeh",
        "\u0642\u0644\u06cc\u0686\u200c\u062a\u067e\u0647"
    ],
    "name:swe_x_preferred":[
        "Qel\u012bch Tappeh"
    ],
    "name:ukr_x_preferred":[
        "\u041a\u0435\u043b\u0456\u0447-\u0422\u0430\u043f\u043f\u0435"
    ],
    "wof:name":"Qelich Tappeh",
    "wof:placetype":"locality"
},
  "geometry": {"coordinates":[49.2525,34.4776],"type":"Point"}
}