{
  "type": "Feature",
  "properties": {
    "gn:admin1_code":"34",
    "gn:asciiname":"Farajabad",
    "gn:country_code":"IR",
    "gn:dem":1303,
    "gn:feature_class":"P",
    "gn:feature_code":"PPL",
    "gn:name":"Faraj\u0101b\u0101d",
    "gn:population":0,
    "gn:timezone":"Asia/Tehran",
    "iso:country":"IR",
    "name:fas_x_preferred":[
        "\u0641\u0631\u062c \u0622\u0628\u0627\u062f"
    ],
    "name:fas_x_variant":[
        "Faraj\u0101b\u0101d"
    ],
    "name:und_x_variant":[
        "Faraj\u0101b\u0101d-e A\u1e29madl\u016b"
    ],
    "wof:name":"Farajabad",
    "wof:placetype":"locality"
},
  "geometry": {"coordinates":[50.60336,35.21445],"type":"Point"}
}