{
  "type": "Feature",
  "properties": {
    "gn:admin1_code":"28",
    "gn:asciiname":"Shah Qandab",
    "gn:country_code":"IR",
    "gn:dem":1978,
    "gn:feature_class":"P",
    "gn:feature_code":"PPL",
    "gn:name":"Sh\u0101h Qand\u0101b",
    "gn:population":0,
    "gn:timezone":"Asia/Tehran",
    "iso:country":"IR",
    "name:fas_x_preferred":[
        "\u0634\u0627\u0647 \u0642\u0646\u062f\u0627\u0628"
    ],
    "name:fas_x_variant":[
        "Kam\u0101l\u0101b\u0101d-e Sh\u0101h Qand\u0101b",
        "Sh\u0101h Qand\u0101b"
    ],
    "wof:name":"Shah Qandab",
    "wof:placetype":"locality"
},
  "geometry": {"coordinates":[52.2272,31.7459],"type":"Point"}
}