{
  "type": "Feature",
  "properties": {
    "gn:admin1_code":"7",
    "gn:asciiname":"Fotuhabad",
    "gn:cc2":"IR",
    "gn:country_code":"IR",
    "gn:dem":2148,
    "gn:feature_class":"P",
    "gn:feature_code":"PPL",
    "gn:name":"Fot\u016b\u1e29\u0101b\u0101d",
    "gn:population":0,
    "gn:timezone":"Asia/Tehran",
    "iso:country":"IR",
    "name:fas_x_preferred":[
        "Fot\u016b\u1e29\u0101b\u0101d"
    ],
    "name:fas_x_variant":[
        "\u0641\u062a\u0648\u062d\u200c\u0622\u0628\u0627\u062f"
    ],
    "name:msa_x_preferred":[
        "Fotuhabad"
    ],
    "name:und_x_variant":[
        "Fot\u016b\u1e29\u0101b\u0101d",
        "F\u012bt\u0101b\u0101d"
    ],
    "wof:name":"Fotuhabad",
    "wof:placetype":"locality"
},
  "geometry": {"coordinates":[53.35,30.38333],"type":"Point"}
}