{
  "type": "Feature",
  "properties": {
    "gn:admin1_code":"8",
    "gn:asciiname":"Gilandeh",
    "gn:country_code":"IR",
    "gn:dem":1122,
    "gn:feature_class":"P",
    "gn:feature_code":"PPL",
    "gn:name":"G\u012bl\u0101ndeh",
    "gn:population":0,
    "gn:timezone":"Asia/Tehran",
    "iso:country":"IR",
    "name:fas_x_preferred":[
        "\u06af\u06cc\u0644\u0627\u0646\u062f\u0647"
    ],
    "name:fas_x_variant":[
        "G\u012bl\u0101ndeh-e Yeyl\u0101q",
        "G\u012bl\u0101n Deh",
        "G\u012bl\u0101ndeh"
    ],
    "name:msa_x_preferred":[
        "Gilandeh"
    ],
    "name:ukr_x_preferred":[
        "\u0490\u0456\u043b\u044f\u043d\u0434\u0435"
    ],
    "name:und_x_variant":[
        "Kalandeh",
        "Kalandekh"
    ],
    "wof:name":"Gilandeh",
    "wof:placetype":"locality"
},
  "geometry": {"coordinates":[48.7997,37.6014],"type":"Point"}
}