{
  "type": "Feature",
  "properties": {
    "gn:admin1_code":"4.0",
    "gn:asciiname":"Kahnu",
    "gn:country_code":"IR",
    "gn:dem":825,
    "gn:feature_class":"P",
    "gn:feature_code":"PPL",
    "gn:name":"Kahn\u016b",
    "gn:population":0,
    "gn:timezone":"Asia/Tehran",
    "iso:country":"IR",
    "name:fas_x_preferred":[
        "\u06a9\u0647\u0646\u0648"
    ],
    "name:fas_x_variant":[
        "Kahn\u016b"
    ],
    "name:und_x_variant":[
        "Kahnow",
        "Kahanow",
        "Kahnoo"
    ],
    "wof:name":"Kahnu",
    "wof:placetype":"locality"
},
  "geometry": {"coordinates":[60.82487,27.48773],"type":"Point"}
}