{
  "type": "Feature",
  "properties": {
    "gn:admin1_code":"4.0",
    "gn:asciiname":"Rigu",
    "gn:country_code":"IR",
    "gn:dem":1317,
    "gn:feature_class":"P",
    "gn:feature_code":"PPL",
    "gn:name":"R\u012bg\u016b",
    "gn:population":0,
    "gn:timezone":"Asia/Tehran",
    "iso:country":"IR",
    "name:fas_x_preferred":[
        "R\u012bko"
    ],
    "name:fas_x_variant":[
        "\u0631\u064a\u06af\u0648"
    ],
    "name:und_x_variant":[
        "R\u012bg\u016b"
    ],
    "wof:name":"Rigu",
    "wof:placetype":"locality"
},
  "geometry": {"coordinates":[61.41432,28.53417],"type":"Point"}
}