{
  "type": "Feature",
  "properties": {
    "gn:admin1_code":"5",
    "gn:asciiname":"Bar Aftab-e Cheshmeh Liru",
    "gn:country_code":"IR",
    "gn:dem":1944,
    "gn:feature_class":"P",
    "gn:feature_code":"PPL",
    "gn:name":"Bar \u0100ft\u0101b-e Cheshmeh L\u012br\u016b",
    "gn:population":0,
    "gn:timezone":"Asia/Tehran",
    "iso:country":"IR",
    "name:fas_x_preferred":[
        "Bar \u0100ft\u0101b-e Cheshmeh L\u012br\u016b"
    ],
    "wof:name":"Bar Aftab-e Cheshmeh Liru",
    "wof:placetype":"locality"
},
  "geometry": {"coordinates":[50.86694,31.03083],"type":"Point"}
}