{
  "type": "Feature",
  "properties": {
    "gn:admin1_code":"15.0",
    "gn:asciiname":"Taleb-e As`ur",
    "gn:country_code":"IR",
    "gn:dem":4,
    "gn:feature_class":"P",
    "gn:feature_code":"PPL",
    "gn:name":"\u0162\u0101leb-e A\u015f\u2018\u016br",
    "gn:population":0,
    "gn:timezone":"Asia/Tehran",
    "iso:country":"IR",
    "name:fas_x_preferred":[
        "\u0637\u0627\u0644\u0628 \u0627\u0635\u0639\u0648\u0631"
    ],
    "name:fas_x_variant":[
        "\u0162\u0101leb-e A\u015f\u2018\u016br"
    ],
    "wof:name":"Taleb-e As`ur",
    "wof:placetype":"locality"
},
  "geometry": {"coordinates":[48.21925,30.32298],"type":"Point"}
}