{
  "type": "Feature",
  "properties": {
    "gn:admin1_code":"13",
    "gn:asciiname":"Chehr",
    "gn:country_code":"IR",
    "gn:dem":1299,
    "gn:feature_class":"P",
    "gn:feature_code":"PPL",
    "gn:name":"Chehr",
    "gn:population":0,
    "gn:timezone":"Asia/Tehran",
    "iso:country":"IR",
    "name:fas_x_preferred":[
        "\u0686\u0647\u0631"
    ],
    "wof:name":"Chehr",
    "wof:placetype":"locality"
},
  "geometry": {"coordinates":[47.4335,34.3216],"type":"Point"}
}