{
  "type": "Feature",
  "properties": {
    "gn:admin1_code":"4.0",
    "gn:asciiname":"Patannag",
    "gn:country_code":"IR",
    "gn:dem":1213,
    "gn:feature_class":"P",
    "gn:feature_code":"PPL",
    "gn:name":"Patann\u0101g",
    "gn:population":0,
    "gn:timezone":"Asia/Tehran",
    "iso:country":"IR",
    "name:fas_x_preferred":[
        "\u067e\u062a\u0646\u0651\u0627\u06af"
    ],
    "name:fas_x_variant":[
        "Patant\u0101k",
        "Patann\u0101g"
    ],
    "wof:name":"Patannag",
    "wof:placetype":"locality"
},
  "geometry": {"coordinates":[61.5861,26.5421],"type":"Point"}
}