{
  "type": "Feature",
  "properties": {
    "gn:admin1_code":"16",
    "gn:asciiname":"Bileh",
    "gn:country_code":"IR",
    "gn:dem":1433,
    "gn:feature_class":"P",
    "gn:feature_code":"PPL",
    "gn:name":"B\u012bleh",
    "gn:population":0,
    "gn:timezone":"Asia/Tehran",
    "iso:country":"IR",
    "name:fas_x_preferred":[
        "\u0628\u064a\u0644\u0650\u0647"
    ],
    "name:fas_x_variant":[
        "\u0628\u064a\u0627\u0644\u0650\u0647",
        "\u0628\u0650\u064a\u0644\u0650\u0647",
        "\u0628\u0650\u064a\u0644\u064e\u0647",
        "\u0628\u064e\u064a\u064e\u0644\u0650\u0647",
        "\u0628\u06cc\u0644\u0647",
        "B\u012bleh"
    ],
    "name:und_x_variant":[
        "Bayaleh",
        "Beylah",
        "Beyleh",
        "B\u012b\u0101leh"
    ],
    "wof:name":"Bileh",
    "wof:placetype":"locality"
},
  "geometry": {"coordinates":[46.18600000000001,35.5034],"type":"Point"}
}