{
  "type": "Feature",
  "properties": {
    "gn:admin1_code":"15",
    "gn:asciiname":"Bonivar-e `Olya",
    "gn:country_code":"IR",
    "gn:dem":18,
    "gn:feature_class":"P",
    "gn:feature_code":"PPL",
    "gn:name":"Bon\u012bv\u0101r-e \u2018Oly\u0101",
    "gn:population":0,
    "gn:timezone":"Asia/Tehran",
    "iso:country":"IR",
    "name:fas_x_preferred":[
        "\u0628\u0646\u0648\u0627\u0631 \u0639\u0644\u06cc\u0627"
    ],
    "name:fas_x_variant":[
        "Bonv\u0101r-e B\u0101l\u0101",
        "Bonv\u0101r-e \u2018Oly\u0101",
        "Benv\u0101r-e \u2018Oly\u0101",
        "\u0628\u0646\u06cc\u0648\u0627\u0631 \u0639\u0644\u06cc\u0627"
    ],
    "name:und_x_variant":[
        "Benv\u0101r-e B\u0101l\u0101",
        "Bonvar-e \u2018Oly\u0101",
        "Benv\u0101r",
        "Buniwar",
        "Bon\u012bv\u0101r-e \u2018Oly\u0101"
    ],
    "wof:name":"Bonivar-e `Olya",
    "wof:placetype":"locality"
},
  "geometry": {"coordinates":[49.26269,30.77357],"type":"Point"}
}