{
  "type": "Feature",
  "properties": {
    "gn:admin1_code":"1",
    "gn:asciiname":"Jagan-e Kord",
    "gn:country_code":"IR",
    "gn:dem":991,
    "gn:feature_class":"P",
    "gn:feature_code":"PPL",
    "gn:name":"Jagan-e Kord",
    "gn:population":0,
    "gn:timezone":"Asia/Tehran",
    "iso:country":"IR",
    "name:fas_x_preferred":[
        "\u062c\u064e\u06af\u064e\u0646\u0644\u0648\u06cc \u0643\u064f\u0631\u062f"
    ],
    "name:fas_x_variant":[
        "\u062c\u06af\u0646 \u06a9\u0631\u062f",
        "Jaganl\u016b-ye Kord"
    ],
    "wof:name":"Jagan-e Kord",
    "wof:placetype":"locality"
},
  "geometry": {"coordinates":[44.7273,39.3054],"type":"Point"}
}