{
  "type": "Feature",
  "properties": {
    "gn:admin1_code":"32",
    "gn:asciiname":"Agh Bolagh Gaduk-e Pa'in",
    "gn:country_code":"IR",
    "gn:dem":1576,
    "gn:feature_class":"P",
    "gn:feature_code":"PPL",
    "gn:name":"\u0100gh Bol\u0101gh Gad\u016bk-e P\u0101\u2019\u012bn",
    "gn:population":0,
    "gn:timezone":"Asia/Tehran",
    "iso:country":"IR",
    "name:fas_x_preferred":[
        "\u0622\u063a \u0628\u064f\u0644\u0627\u063a \u06af\u064e\u062f\u0648\u0643\u0650 \u067e\u0627\u0626\u064a\u0646"
    ],
    "name:fas_x_variant":[
        "\u0100gh Bol\u0101gh Gad\u016bk-e P\u0101\u2019\u012bn"
    ],
    "wof:name":"Agh Bolagh Gaduk-e Pa'in",
    "wof:placetype":"locality"
},
  "geometry": {"coordinates":[47.95,38.83333],"type":"Point"}
}