{
  "type": "Feature",
  "properties": {
    "gn:admin1_code":"34.0",
    "gn:asciiname":"Argun-e Zadeqabad",
    "gn:country_code":"IR",
    "gn:dem":1746,
    "gn:feature_class":"P",
    "gn:feature_code":"PPL",
    "gn:name":"Arg\u016bn-e Z\u0304\u0101deq\u0101b\u0101d",
    "gn:population":0,
    "gn:timezone":"Asia/Tehran",
    "iso:country":"IR",
    "name:fas_x_preferred":[
        "\u0627\u0631\u06af\u0648\u0646 \u0630\u0627\u062f\u0642 \u0622\u0628\u0627\u062f"
    ],
    "name:und_x_variant":[
        "Arg\u016bn-e Z\u0304\u0101deq\u0101b\u0101d"
    ],
    "wof:name":"Argun-e Zadeqabad",
    "wof:placetype":"locality"
},
  "geometry": {"coordinates":[49.32081,34.6997],"type":"Point"}
}