{
  "type": "Feature",
  "properties": {
    "gn:admin1_code":"9.0",
    "gn:asciiname":"Basishaneh",
    "gn:country_code":"IR",
    "gn:dem":1657,
    "gn:feature_class":"P",
    "gn:feature_code":"PPL",
    "gn:name":"Bas\u012bsh\u0101neh",
    "gn:population":0,
    "gn:timezone":"Asia/Tehran",
    "iso:country":"IR",
    "name:fas_x_preferred":[
        "\u0628\u064e\u0633\u064a\u0634\u0627\u0646\u0650\u0647"
    ],
    "name:fas_x_variant":[
        "Bas\u012bsh\u0101neh"
    ],
    "wof:name":"Basishaneh",
    "wof:placetype":"locality"
},
  "geometry": {"coordinates":[49.31667,35.16667],"type":"Point"}
}