{
  "type": "Feature",
  "properties": {
    "gn:admin1_code":"41",
    "gn:asciiname":"Kalateh-ye Mir Jan",
    "gn:country_code":"IR",
    "gn:dem":2278,
    "gn:feature_class":"P",
    "gn:feature_code":"PPL",
    "gn:name":"Kal\u0101teh-ye M\u012br J\u0101n",
    "gn:population":0,
    "gn:timezone":"Asia/Tehran",
    "iso:country":"IR",
    "name:fas_x_preferred":[
        "\u0643\u064e\u0644\u0627\u062a\u0650\u06c0 \u0645\u064a\u0631 \u062c\u0627\u0646"
    ],
    "name:fas_x_variant":[
        "Kal\u0101teh-ye M\u012br J\u0101n"
    ],
    "name:und_x_variant":[
        "Kal\u0101teh-i-M\u012br J\u0101n"
    ],
    "wof:name":"Kalateh-ye Mir Jan",
    "wof:placetype":"locality"
},
  "geometry": {"coordinates":[59.78333000000001,32.91667],"type":"Point"}
}