{
  "type": "Feature",
  "properties": {
    "gn:admin1_code":"15",
    "gn:asciiname":"Maqate`",
    "gn:country_code":"IR",
    "gn:dem":3,
    "gn:feature_class":"P",
    "gn:feature_code":"PPL",
    "gn:name":"Maq\u0101\u0163e\u2018",
    "gn:population":0,
    "gn:timezone":"Asia/Tehran",
    "iso:country":"IR",
    "name:fas_x_preferred":[
        "\u0645\u0642\u0627\u0637\u0639"
    ],
    "name:fas_x_variant":[
        "Maq\u0101\u0163\u012b\u2018",
        "Maq\u0101\u0163e\u2018"
    ],
    "wof:name":"Maqate`",
    "wof:placetype":"locality"
},
  "geometry": {"coordinates":[48.20796,30.35151],"type":"Point"}
}