{
  "type": "Feature",
  "properties": {
    "gn:admin1_code":"41.0",
    "gn:asciiname":"Nasr od Din",
    "gn:country_code":"IR",
    "gn:dem":1294,
    "gn:feature_class":"P",
    "gn:feature_code":"PPL",
    "gn:name":"Na\u015fr od D\u012bn",
    "gn:population":0,
    "gn:timezone":"Asia/Tehran",
    "iso:country":"IR",
    "name:fas_x_preferred":[
        "\u0646\u0635\u0631 \u0627\u0644\u062f\u06cc\u0646"
    ],
    "name:fas_x_variant":[
        "Na\u015fr od D\u012bn",
        "Nasred\u012b"
    ],
    "name:und_x_variant":[
        "Nasreddin",
        "Nasradi"
    ],
    "wof:name":"Nasr od Din",
    "wof:placetype":"locality"
},
  "geometry": {"coordinates":[60.2552,32.9152],"type":"Point"}
}