{
  "type": "Feature",
  "properties": {
    "gn:admin1_code":"32",
    "gn:asciiname":"Siah Push",
    "gn:country_code":"IR",
    "gn:dem":1633,
    "gn:feature_class":"P",
    "gn:feature_code":"PPL",
    "gn:name":"S\u012b\u0101h P\u016bsh",
    "gn:population":0,
    "gn:timezone":"Asia/Tehran",
    "iso:country":"IR",
    "name:fas_x_preferred":[
        "\u0633\u06cc\u0627\u0647 \u067e\u0648\u0634"
    ],
    "name:fas_x_variant":[
        "S\u012b\u0101hp\u016bsh",
        "S\u012b\u0101h P\u016bsh"
    ],
    "name:und_x_variant":[
        "Push"
    ],
    "wof:name":"Siah Push",
    "wof:placetype":"locality"
},
  "geometry": {"coordinates":[48.22087,37.8782],"type":"Point"}
}