{
  "type": "Feature",
  "properties": {
    "gn:admin1_code":"1",
    "gn:asciiname":"Kani Shamdin",
    "gn:country_code":"IR",
    "gn:dem":1795,
    "gn:feature_class":"P",
    "gn:feature_code":"PPL",
    "gn:name":"K\u0101n\u012b Shamd\u012bn",
    "gn:population":0,
    "gn:timezone":"Asia/Tehran",
    "iso:country":"IR",
    "name:fas_x_preferred":[
        "K\u0101n\u012b Shamd\u012bn"
    ],
    "name:fas_x_variant":[
        "\u0643\u0627\u0646\u06cc \u0634\u064e\u0645\u062f\u064a\u0646"
    ],
    "wof:name":"Kani Shamdin",
    "wof:placetype":"locality"
},
  "geometry": {"coordinates":[44.71667,37.88333],"type":"Point"}
}