{
  "type": "Feature",
  "properties": {
    "gn:admin1_code":"23.0",
    "gn:asciiname":"Halad",
    "gn:country_code":"IR",
    "gn:dem":1088,
    "gn:feature_class":"P",
    "gn:feature_code":"PPL",
    "gn:name":"\u1e28alad",
    "gn:population":0,
    "gn:timezone":"Asia/Tehran",
    "iso:country":"IR",
    "name:fas_x_preferred":[
        "\u1e28alad"
    ],
    "name:fas_x_variant":[
        "\u062d\u0644\u062f"
    ],
    "wof:name":"Halad",
    "wof:placetype":"locality"
},
  "geometry": {"coordinates":[48.21729000000001,33.0378],"type":"Point"}
}