{
  "type": "Feature",
  "properties": {
    "gn:admin1_code":"37",
    "gn:asciiname":"Jafa Kandeh",
    "gn:country_code":"IR",
    "gn:dem":21,
    "gn:feature_class":"P",
    "gn:feature_code":"PPL",
    "gn:name":"Jaf\u0101 Kandeh",
    "gn:population":0,
    "gn:timezone":"Asia/Tehran",
    "iso:country":"IR",
    "name:ara_x_preferred":[
        "\u062c\u0641\u0627\u06a9\u0646\u062f\u0629"
    ],
    "name:fas_x_preferred":[
        "Jaf\u0101 Kandeh"
    ],
    "name:fas_x_variant":[
        "\u062c\u0641\u0627 \u0643\u0646\u062f\u0647",
        "\u062c\u0641\u0627\u06a9\u0646\u062f\u0647"
    ],
    "name:msa_x_preferred":[
        "Jafa Kandeh"
    ],
    "name:und_x_variant":[
        "\u062c\u0641\u0627 \u0643\u0646\u062f\u0647"
    ],
    "name:urd_x_preferred":[
        "\u062c\u0641\u0627\u06a9\u0646\u062f\u06c1"
    ],
    "wof:name":"Jafa Kandeh",
    "wof:placetype":"locality"
},
  "geometry": {"coordinates":[53.93561,36.73619],"type":"Point"}
}