{
  "type": "Feature",
  "properties": {
    "gn:admin1_code":"43",
    "gn:asciiname":"Zeyvanlu",
    "gn:country_code":"IR",
    "gn:dem":1662,
    "gn:feature_class":"P",
    "gn:feature_code":"PPL",
    "gn:name":"Zeyv\u0101nl\u016b",
    "gn:population":0,
    "gn:timezone":"Asia/Tehran",
    "iso:country":"IR",
    "name:fas_x_preferred":[
        "Zen\u012bd\u0101nl\u016b"
    ],
    "name:fas_x_variant":[
        "Zeyv\u0101nl\u016b",
        "\u0632\u06cc\u0648\u0627\u0646\u0644\u0648"
    ],
    "wof:name":"Zeyvanlu",
    "wof:placetype":"locality"
},
  "geometry": {"coordinates":[58.04999,37.68751],"type":"Point"}
}