{
  "type": "Feature",
  "properties": {
    "gn:admin1_code":"5.0",
    "gn:asciiname":"Dulab Shirin",
    "gn:country_code":"IR",
    "gn:dem":1461,
    "gn:feature_class":"P",
    "gn:feature_code":"PPL",
    "gn:name":"D\u016bl\u0101b Sh\u012br\u012bn",
    "gn:population":0,
    "gn:timezone":"Asia/Tehran",
    "iso:country":"IR",
    "name:fas_x_preferred":[
        "D\u016bl\u0101b"
    ],
    "name:fas_x_variant":[
        "\u062f\u0648\u0644\u0627\u0628",
        "\u062f\u0648\u0644\u0627\u0628 \u0634\u064a\u0631\u064a\u0646"
    ],
    "name:und_x_variant":[
        "D\u016bl\u0101b Sh\u012br\u012bn"
    ],
    "wof:name":"Dulab Shirin",
    "wof:placetype":"locality"
},
  "geometry": {"coordinates":[50.4862,31.21928],"type":"Point"}
}