{
  "type": "Feature",
  "properties": {
    "gn:admin1_code":"29.0",
    "gn:asciiname":"Hasharabad",
    "gn:country_code":"IR",
    "gn:dem":488,
    "gn:feature_class":"P",
    "gn:feature_code":"PPL",
    "gn:name":"\u1e28ashar\u0101b\u0101d",
    "gn:population":0,
    "gn:timezone":"Asia/Tehran",
    "iso:country":"IR",
    "name:fas_x_preferred":[
        "\u062d\u0634\u0631 \u0622\u0628\u0627\u062f"
    ],
    "name:fas_x_variant":[
        "\u062d\u0634\u0631\u0622\u0628\u0627\u062f"
    ],
    "name:und_x_variant":[
        "\u1e28ashar\u0101b\u0101d"
    ],
    "wof:name":"Hasharabad",
    "wof:placetype":"locality"
},
  "geometry": {"coordinates":[58.17077,27.99996],"type":"Point"}
}