{
  "type": "Feature",
  "properties": {
    "gn:admin1_code":"15",
    "gn:asciiname":"Sardasht",
    "gn:country_code":"IR",
    "gn:dem":493,
    "gn:feature_class":"P",
    "gn:feature_code":"PPL",
    "gn:name":"Sardasht",
    "gn:population":0,
    "gn:timezone":"Asia/Tehran",
    "iso:country":"IR",
    "name:ceb_x_preferred":[
        "Sardasht"
    ],
    "name:fas_x_preferred":[
        "\u0633\u0631 \u062f\u0634\u062a"
    ],
    "name:fas_x_variant":[
        "\u0633\u0631\u062f\u0634\u062a"
    ],
    "name:rus_x_preferred":[
        "\u0421\u0435\u0440\u0434\u0435\u0448\u0442"
    ],
    "name:swe_x_preferred":[
        "Sardasht"
    ],
    "name:und_x_variant":[
        "Sar-\u012b-Dasht",
        "Sar Dasht"
    ],
    "wof:name":"Sardasht",
    "wof:placetype":"locality"
},
  "geometry": {"coordinates":[48.83505,32.49871],"type":"Point"}
}