{
  "type": "Feature",
  "properties": {
    "gn:admin1_code":"29.0",
    "gn:asciiname":"Howr-e Esfandi",
    "gn:country_code":"IR",
    "gn:dem":650,
    "gn:feature_class":"P",
    "gn:feature_code":"PPLF",
    "gn:name":"\u1e28owr-e Esfand\u012b",
    "gn:population":0,
    "gn:timezone":"Asia/Tehran",
    "iso:country":"IR",
    "name:fas_x_preferred":[
        "\u062d\u0648\u0631 \u0627\u0633\u0641\u0646\u062f\u06cc"
    ],
    "name:und_x_variant":[
        "\u1e28owr-e Esfand\u012b"
    ],
    "wof:name":"Howr-e Esfandi",
    "wof:placetype":"locality"
},
  "geometry": {"coordinates":[57.2733,28.14399],"type":"Point"}
}