{
  "type": "Feature",
  "properties": {
    "gn:admin1_code":"41",
    "gn:asciiname":"Qodsian",
    "gn:country_code":"IR",
    "gn:dem":1945,
    "gn:feature_class":"P",
    "gn:feature_code":"PPL",
    "gn:name":"Qods\u012b\u0101n",
    "gn:population":0,
    "gn:timezone":"Asia/Tehran",
    "iso:country":"IR",
    "name:fas_x_preferred":[
        "Qods\u012b\u0101n"
    ],
    "name:fas_x_variant":[
        "\u0642\u062f\u0633\u06cc\u0627\u0646"
    ],
    "name:und_x_variant":[
        "G\u016bsy\u0101n",
        "G\u016bs\u012ban"
    ],
    "wof:name":"Qodsian",
    "wof:placetype":"locality"
},
  "geometry": {"coordinates":[59.62776,32.45251],"type":"Point"}
}