{
  "type": "Feature",
  "properties": {
    "gn:admin1_code":"11",
    "gn:asciiname":"Mir Hasani",
    "gn:country_code":"IR",
    "gn:dem":983,
    "gn:feature_class":"P",
    "gn:feature_code":"PPL",
    "gn:name":"M\u012br \u1e28asan\u012b",
    "gn:population":0,
    "gn:timezone":"Asia/Tehran",
    "iso:country":"IR",
    "name:fas_x_preferred":[
        "\u0645\u06cc\u0631 \u062d\u0633\u0646\u06cc"
    ],
    "name:fas_x_variant":[
        "M\u012br \u1e28asan\u012b"
    ],
    "wof:name":"Mir Hasani",
    "wof:placetype":"locality"
},
  "geometry": {"coordinates":[56.6712,27.9592],"type":"Point"}
}