{
  "type": "Feature",
  "properties": {
    "gn:admin1_code":"5",
    "gn:asciiname":"Pas Qal`eh-ye Mah Shah Hoseyni",
    "gn:country_code":"IR",
    "gn:dem":1122,
    "gn:feature_class":"P",
    "gn:feature_code":"PPL",
    "gn:name":"Pas Qal\u2018eh-ye Mah Sh\u0101h \u1e28oseyn\u012b",
    "gn:population":0,
    "gn:timezone":"Asia/Tehran",
    "iso:country":"IR",
    "name:fas_x_preferred":[
        "Sh\u0101h \u1e28oseyn\u012b"
    ],
    "name:fas_x_variant":[
        "\u0634\u0627\u0647 \u062d\u0633\u064a\u0646\u06cc",
        "\u067e\u0633 \u0642\u0644\u0639\u0647 \u0645\u0647 \u0634\u0627\u0647 \u062d\u0633\u06cc\u0646\u06cc"
    ],
    "name:und_x_variant":[
        "Pas Qal\u2018eh-ye Mah Sh\u0101h \u1e28oseyn\u012b"
    ],
    "wof:name":"Pas Qal`eh-ye Mah Shah Hoseyni",
    "wof:placetype":"locality"
},
  "geometry": {"coordinates":[50.67977,31.41942],"type":"Point"}
}