{
  "type": "Feature",
  "properties": {
    "gn:admin1_code":"13",
    "gn:asciiname":"Maleh Dazgeh",
    "gn:country_code":"IR",
    "gn:dem":602,
    "gn:feature_class":"P",
    "gn:feature_code":"PPL",
    "gn:name":"Maleh Dazgeh",
    "gn:population":0,
    "gn:timezone":"Asia/Tehran",
    "iso:country":"IR",
    "name:fas_x_preferred":[
        "\u0645\u0644\u0647 \u062f\u0632\u06af\u0647"
    ],
    "name:und_x_variant":[
        "Maleh Dezgeh",
        "Maleh Dazgeh"
    ],
    "wof:name":"Maleh Dazgeh",
    "wof:placetype":"locality"
},
  "geometry": {"coordinates":[45.83462,34.65943],"type":"Point"}
}