{
  "type": "Feature",
  "properties": {
    "gn:admin1_code":"15",
    "gn:asciiname":"Chesti",
    "gn:country_code":"IR",
    "gn:dem":1228,
    "gn:feature_class":"P",
    "gn:feature_code":"PPL",
    "gn:name":"Chest\u012b",
    "gn:population":0,
    "gn:timezone":"Asia/Tehran",
    "iso:country":"IR",
    "name:fas_x_preferred":[
        "Chest\u012b"
    ],
    "name:fas_x_variant":[
        "\u0686\u0633\u062a\u06cc"
    ],
    "wof:name":"Chesti",
    "wof:placetype":"locality"
},
  "geometry": {"coordinates":[50.13296,31.34534],"type":"Point"}
}