{
  "type": "Feature",
  "properties": {
    "gn:admin1_code":"5",
    "gn:asciiname":"Jahrab-e Sartang",
    "gn:country_code":"IR",
    "gn:dem":1328,
    "gn:feature_class":"P",
    "gn:feature_code":"PPL",
    "gn:name":"Jahr\u0101b-e Sartang",
    "gn:population":0,
    "gn:timezone":"Asia/Tehran",
    "iso:country":"IR",
    "name:fas_x_preferred":[
        "Sar Tang-e Gahr\u0101b"
    ],
    "name:fas_x_variant":[
        "Tang Gahr\u0101b",
        "\u062a\u0646\u06af \u06af\u0647\u0631\u0627\u0628",
        "\u062c\u0647\u0631\u0627\u0628 \u0633\u0631\u062a\u0646\u06af",
        "\u0633\u0631 \u062a\u0646\u06af \u06af\u0647\u0631\u0627\u0628"
    ],
    "name:und_x_variant":[
        "Jehr\u0101b-e Sar Lang",
        "Jahr\u0101b-e Sartang"
    ],
    "wof:name":"Jahrab-e Sartang",
    "wof:placetype":"locality"
},
  "geometry": {"coordinates":[50.81741,31.32205],"type":"Point"}
}