{
  "type": "Feature",
  "properties": {
    "gn:admin1_code":"5",
    "gn:asciiname":"Kamak-e Vosta",
    "gn:country_code":"IR",
    "gn:dem":1721,
    "gn:feature_class":"P",
    "gn:feature_code":"PPL",
    "gn:name":"Kamak-e Vos\u0163\u00e1",
    "gn:population":0,
    "gn:timezone":"Asia/Tehran",
    "iso:country":"IR",
    "name:fas_x_preferred":[
        "\u0643\u064e\u0645\u064e\u0643\u0650 \u0648\u064f\u0633\u0637\u064e\u0649"
    ],
    "name:fas_x_variant":[
        "Kamak-e Vos\u0163\u00e1"
    ],
    "wof:name":"Kamak-e Vosta",
    "wof:placetype":"locality"
},
  "geometry": {"coordinates":[50.80083,31.01306],"type":"Point"}
}