{
  "type": "Feature",
  "properties": {
    "gn:admin1_code":"8",
    "gn:asciiname":"Gurab Varzal",
    "gn:country_code":"IR",
    "gn:dem":35,
    "gn:feature_class":"P",
    "gn:feature_code":"PPL",
    "gn:name":"G\u016br\u0101b Varzal",
    "gn:population":0,
    "gn:timezone":"Asia/Tehran",
    "iso:country":"IR",
    "name:ceb_x_preferred":[
        "G\u016br\u0101b Varzal"
    ],
    "name:fas_x_preferred":[
        "G\u016br\u0101b Varzal"
    ],
    "name:fas_x_variant":[
        "\u06af\u0648\u0631\u0627\u0628 \u0648\u0631\u0632\u0644",
        "\u06af\u0648\u0631\u0627\u0628\u200c\u0648\u0631\u0632\u0644"
    ],
    "name:msa_x_preferred":[
        "Gurab Varzal"
    ],
    "name:swe_x_preferred":[
        "G\u016br\u0101b Varzal"
    ],
    "name:ukr_x_preferred":[
        "\u0490\u0443\u0440\u0430\u0431-\u0412\u0430\u0440\u0437\u0430\u043b\u044c"
    ],
    "wof:name":"Gurab Varzal",
    "wof:placetype":"locality"
},
  "geometry": {"coordinates":[49.55339,37.1915],"type":"Point"}
}