{
  "type": "Feature",
  "properties": {
    "gn:admin1_code":"26",
    "gn:asciiname":"Mehranabad",
    "gn:country_code":"IR",
    "gn:dem":1070,
    "gn:feature_class":"P",
    "gn:feature_code":"PPL",
    "gn:name":"Mehr\u0101n\u0101b\u0101d",
    "gn:population":0,
    "gn:timezone":"Asia/Tehran",
    "iso:country":"IR",
    "name:ara_x_preferred":[
        "\u0645\u0647\u0631\u0627\u0646\u200c\u0622\u0628\u0627\u062f"
    ],
    "name:ceb_x_preferred":[
        "Mehr\u0101n\u0101b\u0101d"
    ],
    "name:fas_x_preferred":[
        "\u0645\u0647\u0631\u0627\u0646 \u0622\u0628\u0627\u062f"
    ],
    "name:fas_x_variant":[
        "\u0645\u0650\u0647\u0631\u0627\u0646\u0627\u0628\u0627\u062f\u0650 \u0641\u0650\u064a\u0632 \u0622\u0628\u0627\u062f",
        "\u0645\u0650\u0647\u0631\u0627\u0646 \u0622\u0628\u0627\u062f \u0648\u064e \u0641\u0650\u064a\u0632 \u0622\u0628\u0627\u062f",
        "Mehr\u0101n\u0101b\u0101d",
        "\u0645\u0647\u0631\u0627\u0646\u200c\u0622\u0628\u0627\u062f"
    ],
    "name:und_x_variant":[
        "Mihr\u0101n\u0101b\u0101d",
        "Mehr\u0101n\u0101b\u0101d-e Feyz\u0101b\u0101d",
        "Mehr\u0101n\u0101b\u0101d va Feyz\u0101b\u0101d"
    ],
    "name:urd_x_preferred":[
        "\u0645\u06c1\u0631\u0627\u0646\u200c\u0622\u0628\u0627\u062f"
    ],
    "wof:name":"Mehranabad",
    "wof:placetype":"locality"
},
  "geometry": {"coordinates":[51.2915,35.569],"type":"Point"}
}