{
  "type": "Feature",
  "properties": {
    "gn:admin1_code":"32.0",
    "gn:asciiname":"`Ata'i Qeshlaqi",
    "gn:country_code":"IR",
    "gn:dem":897,
    "gn:feature_class":"P",
    "gn:feature_code":"PPLL",
    "gn:name":"\u2018A\u0163\u0101\u2019\u012b Qeshl\u0101q\u012b",
    "gn:population":0,
    "gn:timezone":"Asia/Tehran",
    "iso:country":"IR",
    "name:fas_x_preferred":[
        "\u0639\u0637\u0627\u06cc\u06cc \u0642\u0634\u0644\u0627\u0642\u06cc"
    ],
    "name:und_x_variant":[
        "\u2018A\u0163\u0101\u2019\u012b Qeshl\u0101q\u012b"
    ],
    "wof:name":"`Ata'i Qeshlaqi",
    "wof:placetype":"locality"
},
  "geometry": {"coordinates":[47.61349000000001,38.52917],"type":"Point"}
}