{
  "type": "Feature",
  "properties": {
    "gn:admin1_code":"23",
    "gn:asciiname":"Rud Ab",
    "gn:country_code":"IR",
    "gn:dem":2067,
    "gn:feature_class":"P",
    "gn:feature_code":"PPL",
    "gn:name":"R\u016bd \u0100b",
    "gn:population":0,
    "gn:timezone":"Asia/Tehran",
    "iso:country":"IR",
    "name:ara_x_preferred":[
        "\u0631\u0648\u062f\u0623\u0628"
    ],
    "name:aze_x_preferred":[
        "Rudab"
    ],
    "name:fas_x_preferred":[
        "\u0631\u0648\u062f \u0622\u0628"
    ],
    "name:fas_x_variant":[
        "R\u016bd \u0100b",
        "\u0631\u0648\u062f\u0622\u0628"
    ],
    "name:ita_x_preferred":[
        "Rud Ab"
    ],
    "name:mlg_x_preferred":[
        "Rud Ab"
    ],
    "name:sco_x_preferred":[
        "Rud Ab"
    ],
    "name:tur_x_preferred":[
        "Rudab"
    ],
    "wof:name":"Rud Ab",
    "wof:placetype":"locality"
},
  "geometry": {"coordinates":[49.58722,32.87806],"type":"Point"}
}