{
  "type": "Feature",
  "properties": {
    "gn:admin1_code":"11",
    "gn:asciiname":"Kal Taniru",
    "gn:country_code":"IR",
    "gn:dem":366,
    "gn:feature_class":"P",
    "gn:feature_code":"PPL",
    "gn:name":"Kal Tan\u012br\u016b",
    "gn:population":0,
    "gn:timezone":"Asia/Tehran",
    "iso:country":"IR",
    "name:fas_x_preferred":[
        "\u0643\u064e\u0644 \u062a\u064e\u0646\u064a\u0631\u0648"
    ],
    "name:fas_x_variant":[
        "Kal Tan\u012br\u016b"
    ],
    "wof:name":"Kal Taniru",
    "wof:placetype":"locality"
},
  "geometry": {"coordinates":[56.11111,27.59167],"type":"Point"}
}