{
  "type": "Feature",
  "properties": {
    "gn:admin1_code":"33.0",
    "gn:asciiname":"Afshar Jeq",
    "gn:country_code":"IR",
    "gn:dem":1707,
    "gn:feature_class":"P",
    "gn:feature_code":"PPL",
    "gn:name":"Afsh\u0101r Jeq",
    "gn:population":0,
    "gn:timezone":"Asia/Tehran",
    "iso:country":"IR",
    "name:azb_x_preferred":[
        "\u0627\u0641\u0634\u0627\u0631\u062c\u06cc\u0642"
    ],
    "name:ceb_x_preferred":[
        "Afsh\u0101r Jeq"
    ],
    "name:fas_x_preferred":[
        "\u0627\u0641\u0634\u0627\u0631\u062c\u0642"
    ],
    "name:fas_x_variant":[
        "Afsh\u0101r J\u012bq",
        "Afsh\u0101r Jeq",
        "\u0627\u0641\u0634\u0627\u0631\u062c\u06cc\u0642"
    ],
    "name:msa_x_preferred":[
        "Afshar Jiq"
    ],
    "name:swe_x_preferred":[
        "Afsh\u0101r Jeq"
    ],
    "name:und_x_variant":[
        "Ushadik",
        "Afsh\u0101r \u1e28aq"
    ],
    "wof:name":"Afshar Jeq",
    "wof:placetype":"locality"
},
  "geometry": {"coordinates":[47.2295,37.4101],"type":"Point"}
}