{
  "type": "Feature",
  "properties": {
    "gn:admin1_code":"35",
    "gn:asciiname":"Siah Dasht-e Bala",
    "gn:country_code":"IR",
    "gn:dem":736,
    "gn:feature_class":"P",
    "gn:feature_code":"PPL",
    "gn:name":"S\u012b\u0101h Dasht-e B\u0101l\u0101",
    "gn:population":0,
    "gn:timezone":"Asia/Tehran",
    "iso:country":"IR",
    "name:fas_x_preferred":[
        "\u0633\u064a\u0627\u0647 \u062f\u064e\u0634\u062a\u0650 \u0639\u064f\u0644\u064a\u0627"
    ],
    "name:fas_x_variant":[
        "\u0633\u064a\u0627\u0647 \u062f\u0634\u062a \u0628\u0627\u0644\u0627",
        "S\u012b\u0101h Dasht-e \u2018Oly\u0101",
        "S\u012b\u0101h Dasht-e B\u0101l\u0101"
    ],
    "wof:name":"Siah Dasht-e Bala",
    "wof:placetype":"locality"
},
  "geometry": {"coordinates":[53.29208000000001,36.14722],"type":"Point"}
}