{
  "type": "Feature",
  "properties": {
    "gn:admin1_code":"33",
    "gn:asciiname":"Sheykh Boran",
    "gn:country_code":"IR",
    "gn:dem":1115,
    "gn:elevation":"0.0",
    "gn:feature_class":"P",
    "gn:feature_code":"PPL",
    "gn:name":"Sheykh Bor\u0101n",
    "gn:population":0,
    "gn:timezone":"Asia/Tehran",
    "iso:country":"IR",
    "name:ara_x_preferred":[
        "\u0634\u064a\u062e \u0628\u0648\u0631\u0627\u0646"
    ],
    "name:fas_x_preferred":[
        "\u0634\u06cc\u062e \u0628\u0631\u0627\u0646"
    ],
    "name:fas_x_variant":[
        "Sheykh Bor\u0101n",
        "\u0634\u06cc\u062e\u200c\u0628\u0631\u0627\u0646"
    ],
    "name:msa_x_preferred":[
        "Sheykh Boran"
    ],
    "wof:name":"Sheykh Boran",
    "wof:placetype":"locality"
},
  "geometry": {"coordinates":[47.3519,38.9809],"type":"Point"}
}