{
  "type": "Feature",
  "properties": {
    "gn:admin1_code":"35",
    "gn:asciiname":"Pepin",
    "gn:country_code":"IR",
    "gn:dem":-4,
    "gn:feature_class":"P",
    "gn:feature_code":"PPL",
    "gn:name":"Pep\u012bn",
    "gn:population":0,
    "gn:timezone":"Asia/Tehran",
    "iso:country":"IR",
    "name:fas_x_preferred":[
        "\u067e\u067e\u064a\u0646"
    ],
    "name:fas_x_variant":[
        "Pep\u012bn"
    ],
    "wof:name":"Pepin",
    "wof:placetype":"locality"
},
  "geometry": {"coordinates":[52.50032,36.56774],"type":"Point"}
}