{
  "type": "Feature",
  "properties": {
    "gn:admin1_code":"44.0",
    "gn:asciiname":"Ruy-e Zamin",
    "gn:country_code":"IR",
    "gn:dem":1838,
    "gn:feature_class":"P",
    "gn:feature_code":"PPL",
    "gn:name":"R\u016by-e Zam\u012bn",
    "gn:population":0,
    "gn:timezone":"Asia/Tehran",
    "iso:country":"IR",
    "name:fas_x_preferred":[
        "\u0631\u0650\u06cc \u0632\u064e\u0645\u064a\u0646"
    ],
    "name:fas_x_variant":[
        "Rey Zam\u012bn",
        "\u0631\u0648\u06cc \u0632\u0645\u06cc\u0646",
        "\u0631\u06cc \u0632\u0645\u06cc\u0646"
    ],
    "name:und_x_variant":[
        "R\u016by-e Zam\u012bn"
    ],
    "wof:name":"Ruy-e Zamin",
    "wof:placetype":"locality"
},
  "geometry": {"coordinates":[51.17979,36.03396],"type":"Point"}
}