{
  "type": "Feature",
  "properties": {
    "gn:admin1_code":"29.0",
    "gn:asciiname":"Posht Kam",
    "gn:country_code":"IR",
    "gn:dem":1148,
    "gn:feature_class":"P",
    "gn:feature_code":"PPLL",
    "gn:name":"Posht Kam",
    "gn:population":0,
    "gn:timezone":"Asia/Tehran",
    "iso:country":"IR",
    "name:fas_x_preferred":[
        "\u067e\u0634\u062a \u06a9\u0645"
    ],
    "wof:name":"Posht Kam",
    "wof:placetype":"locality"
},
  "geometry": {"coordinates":[58.93029,28.07397000000001],"type":"Point"}
}