{
  "type": "Feature",
  "properties": {
    "gn:admin1_code":"13",
    "gn:asciiname":"Zangi Choqa",
    "gn:country_code":"IR",
    "gn:dem":1275,
    "gn:feature_class":"P",
    "gn:feature_code":"PPL",
    "gn:name":"Zang\u012b Choq\u0101",
    "gn:population":0,
    "gn:timezone":"Asia/Tehran",
    "iso:country":"IR",
    "name:fas_x_preferred":[
        "\u0632\u0646\u06af\u06cc \u0686\u0642\u0627"
    ],
    "name:fas_x_variant":[
        "Zang\u012b Choq\u0101"
    ],
    "wof:name":"Zangi Choqa",
    "wof:placetype":"locality"
},
  "geometry": {"coordinates":[47.4128,34.2867],"type":"Point"}
}