{
  "type": "Feature",
  "properties": {
    "gn:admin1_code":"29",
    "gn:asciiname":"Bagh-e Hanti",
    "gn:country_code":"IR",
    "gn:dem":2880,
    "gn:feature_class":"P",
    "gn:feature_code":"PPL",
    "gn:name":"B\u0101gh-e Hanti",
    "gn:population":0,
    "gn:timezone":"Asia/Tehran",
    "iso:country":"IR",
    "name:fas_x_preferred":[
        "B\u0101gh-e Hanti"
    ],
    "name:und_x_variant":[
        "B\u0101gh-i-Hanti"
    ],
    "wof:name":"Bagh-e Hanti",
    "wof:placetype":"locality"
},
  "geometry": {"coordinates":[57.23333,29.21667],"type":"Point"}
}