{
  "type": "Feature",
  "properties": {
    "gn:admin1_code":"43",
    "gn:asciiname":"Qaracheh",
    "gn:country_code":"IR",
    "gn:dem":1042,
    "gn:feature_class":"P",
    "gn:feature_code":"PPL",
    "gn:name":"Qar\u0101cheh",
    "gn:population":0,
    "gn:timezone":"Asia/Tehran",
    "iso:country":"IR",
    "name:ceb_x_preferred":[
        "Qar\u0101cheh"
    ],
    "name:fas_x_preferred":[
        "Qar\u0101cheh"
    ],
    "name:fas_x_variant":[
        "\u0642\u0631\u0627\u0686\u0647"
    ],
    "name:swe_x_preferred":[
        "Qar\u0101cheh"
    ],
    "name:und_x_variant":[
        "\u0642\u0631\u0627\u0686\u0647"
    ],
    "wof:name":"Qaracheh",
    "wof:placetype":"locality"
},
  "geometry": {"coordinates":[57.0997,37.55719000000001],"type":"Point"}
}