{
  "type": "Feature",
  "properties": {
    "gn:admin1_code":"3.0",
    "gn:asciiname":"Qal`eh-ye `Ali Hoseyn",
    "gn:country_code":"IR",
    "gn:dem":2247,
    "gn:feature_class":"P",
    "gn:feature_code":"PPL",
    "gn:name":"Qal\u2018eh-ye \u2018Al\u012b \u1e28oseyn",
    "gn:population":0,
    "gn:timezone":"Asia/Tehran",
    "iso:country":"IR",
    "name:fas_x_preferred":[
        "Qal\u2018eh-ye \u2018Al\u012b \u1e28oseyn"
    ],
    "name:fas_x_variant":[
        "\u0642\u0644\u0639\u0647 \u0639\u0644\u06cc \u062d\u0633\u06cc\u0646"
    ],
    "wof:name":"Qal`eh-ye `Ali Hoseyn",
    "wof:placetype":"locality"
},
  "geometry": {"coordinates":[50.28817,32.46049],"type":"Point"}
}