{
  "type": "Feature",
  "properties": {
    "gn:admin1_code":"34.0",
    "gn:asciiname":"Rahimabad-e Parandak",
    "gn:country_code":"IR",
    "gn:dem":1189,
    "gn:feature_class":"P",
    "gn:feature_code":"PPL",
    "gn:name":"Ra\u1e29\u012bm\u0101b\u0101d-e Parandak",
    "gn:population":0,
    "gn:timezone":"Asia/Tehran",
    "iso:country":"IR",
    "name:ara_x_preferred":[
        "\u0628\u0631\u0646\u062f\u0643"
    ],
    "name:aze_x_preferred":[
        "P\u0259r\u0259nd\u0259k"
    ],
    "name:ceb_x_preferred":[
        "Parandak"
    ],
    "name:fas_x_preferred":[
        "\u067e\u0631\u0646\u062f\u06a9"
    ],
    "name:fas_x_variant":[
        "Ra\u1e29\u012bm\u0101b\u0101d",
        "\u0631\u062d\u06cc\u0645 \u0622\u0628\u0627\u062f \u067e\u0631\u0646\u062f\u06a9",
        "\u0631\u062d\u06cc\u0645 \u0622\u0628\u0627\u062f"
    ],
    "name:fra_x_preferred":[
        "Parandak"
    ],
    "name:ita_x_preferred":[
        "Parandak"
    ],
    "name:mlg_x_preferred":[
        "Parandak"
    ],
    "name:por_x_preferred":[
        "Parandak"
    ],
    "name:rus_x_preferred":[
        "\u041f\u0430\u0440\u0430\u043d\u0434\u0430\u043a"
    ],
    "name:swe_x_preferred":[
        "Parandak"
    ],
    "name:tur_x_preferred":[
        "Perendek"
    ],
    "name:und_x_variant":[
        "Parandak",
        "Ra\u1e29\u012bm\u0101b\u0101d-e Parandak"
    ],
    "name:zho_x_preferred":[
        "\u5e15\u862d\u9054\u514b"
    ],
    "wof:name":"Rahimabad-e Parandak",
    "wof:placetype":"locality"
},
  "geometry": {"coordinates":[50.68209,35.36183],"type":"Point"}
}