{
  "type": "Feature",
  "properties": {
    "gn:admin1_code":"1.0",
    "gn:asciiname":"Khowr Khowreh",
    "gn:country_code":"IR",
    "gn:dem":1556,
    "gn:elevation":"0.0",
    "gn:feature_class":"P",
    "gn:feature_code":"PPL",
    "gn:name":"Khowr Khowreh",
    "gn:population":0,
    "gn:timezone":"Asia/Tehran",
    "iso:country":"IR",
    "name:fas_x_preferred":[
        "\u062e\u0648\u0631\u062e\u0648\u0631\u0647"
    ],
    "name:fas_x_variant":[
        "\u062e\u064f\u0648\u0631 \u062e\u064f\u0648\u0631\u0650\u0647"
    ],
    "wof:name":"Khowr Khowreh",
    "wof:placetype":"locality"
},
  "geometry": {"coordinates":[45.8008,36.295],"type":"Point"}
}