{
  "type": "Feature",
  "properties": {
    "gn:admin1_code":"36",
    "gn:asciiname":"Merash",
    "gn:country_code":"IR",
    "gn:dem":1621,
    "gn:feature_class":"P",
    "gn:feature_code":"PPL",
    "gn:name":"Mer\u0101sh",
    "gn:population":0,
    "gn:timezone":"Asia/Tehran",
    "iso:country":"IR",
    "name:fas_x_preferred":[
        "\u0645\u0631\u0627\u0634"
    ],
    "name:fas_x_variant":[
        "Mer\u0101sh"
    ],
    "name:und_x_variant":[
        "Mar\u0101sh"
    ],
    "wof:name":"Merash",
    "wof:placetype":"locality"
},
  "geometry": {"coordinates":[47.56602,36.54998],"type":"Point"}
}