{
  "type": "Feature",
  "properties": {
    "gn:admin1_code":"4.0",
    "gn:asciiname":"Nambit",
    "gn:country_code":"IR",
    "gn:dem":63,
    "gn:feature_class":"P",
    "gn:feature_code":"PPL",
    "gn:name":"N\u0101mb\u012bt",
    "gn:population":0,
    "gn:timezone":"Asia/Tehran",
    "iso:country":"IR",
    "name:fas_x_preferred":[
        "N\u0101mb\u012bt"
    ],
    "name:fas_x_variant":[
        "\u0646\u0627\u0645\u0628\u064a\u062a"
    ],
    "wof:name":"Nambit",
    "wof:placetype":"locality"
},
  "geometry": {"coordinates":[60.81089,25.75945],"type":"Point"}
}