{
  "type": "Feature",
  "properties": {
    "gn:admin1_code":"35",
    "gn:asciiname":"Hachirud",
    "gn:country_code":"IR",
    "gn:dem":-19,
    "gn:feature_class":"P",
    "gn:feature_code":"PPL",
    "gn:name":"Hach\u012br\u016bd",
    "gn:population":0,
    "gn:timezone":"Asia/Tehran",
    "iso:country":"IR",
    "name:ara_x_preferred":[
        "\u0647\u062a\u0634\u064a\u0631\u0648\u062f"
    ],
    "name:fas_x_preferred":[
        "H\u012bch R\u016bd"
    ],
    "name:fas_x_variant":[
        "Hach\u012br\u016bd",
        "\u0647\u06cc\u0686 \u0631\u0648\u062f",
        "\u0647\u0686\u06cc\u0631\u0648\u062f",
        "\u0647\u0686\u06cc\u200c\u0631\u0648\u062f"
    ],
    "name:und_x_variant":[
        "Hecher\u016bd",
        "Hachr\u016bd",
        "Hechr\u016bd",
        "Hijrood"
    ],
    "name:urd_x_preferred":[
        "\u06c1\u0686\u06cc\u0631\u0648\u062f"
    ],
    "wof:name":"Hachirud",
    "wof:placetype":"locality"
},
  "geometry": {"coordinates":[51.34433,36.68483],"type":"Point"}
}