{
  "type": "Feature",
  "properties": {
    "gn:admin1_code":"16.0",
    "gn:asciiname":"Sar Takaltu",
    "gn:country_code":"IR",
    "gn:dem":1778,
    "gn:feature_class":"P",
    "gn:feature_code":"PPL",
    "gn:name":"Sar Takalt\u016b",
    "gn:population":0,
    "gn:timezone":"Asia/Tehran",
    "iso:country":"IR",
    "name:ara_x_preferred":[
        "\u0633\u0644\u062a\u0647 \u0643\u0644\u062a\u0648"
    ],
    "name:ceb_x_preferred":[
        "Sar Takalt\u016b"
    ],
    "name:ckb_x_preferred":[
        "\u0633\u06d5\u06b5\u062a\u06d5\u06a9\u06d5\u06b5\u062a\u0648\u0648"
    ],
    "name:fas_x_preferred":[
        "\u0633\u064e\u0631 \u062a\u064e\u0643\u062a\u064e\u0644\u0648"
    ],
    "name:fas_x_variant":[
        "\u0633\u0631 \u062a\u06a9\u0644\u062a\u0648",
        "Sar Taktal\u016b",
        "Sar Takalt\u016b",
        "\u0633\u0631\u062a\u06a9\u0644\u062a\u0648"
    ],
    "name:kur_x_preferred":[
        "Seltekelto"
    ],
    "name:swe_x_preferred":[
        "Sar Takalt\u016b"
    ],
    "wof:name":"Sar Takaltu",
    "wof:placetype":"locality"
},
  "geometry": {"coordinates":[46.2747,36.1444],"type":"Point"}
}