{
  "type": "Feature",
  "properties": {
    "gn:admin1_code":"42.0",
    "gn:asciiname":"Sang-e Atash",
    "gn:country_code":"IR",
    "gn:dem":1241,
    "gn:feature_class":"P",
    "gn:feature_code":"PPL",
    "gn:name":"Sang-e \u0100tash",
    "gn:population":0,
    "gn:timezone":"Asia/Tehran",
    "iso:country":"IR",
    "name:fas_x_preferred":[
        "\u0633\u0646\u06af \u0622\u062a\u0634"
    ],
    "name:fas_x_variant":[
        "Sang-e \u0100tash",
        "\u0633\u0646\u06af\u0627\u062a\u0634"
    ],
    "name:und_x_variant":[
        "Sang \u0100tash",
        "Sang \u0100tesh"
    ],
    "wof:name":"Sang-e Atash",
    "wof:placetype":"locality"
},
  "geometry": {"coordinates":[60.84922,35.39087],"type":"Point"}
}