{
  "type": "Feature",
  "properties": {
    "gn:admin1_code":"1.0",
    "gn:asciiname":"Almaran",
    "gn:country_code":"IR",
    "gn:dem":2111,
    "gn:feature_class":"P",
    "gn:feature_code":"PPL",
    "gn:name":"\u0100lmar\u0101n",
    "gn:population":0,
    "gn:timezone":"Asia/Tehran",
    "iso:country":"IR",
    "name:fas_x_preferred":[
        "\u0622\u0644\u0645\u064e\u0631\u0627\u0646"
    ],
    "name:fas_x_variant":[
        "\u0100lmar\u0101n"
    ],
    "wof:name":"Almaran",
    "wof:placetype":"locality"
},
  "geometry": {"coordinates":[45.21667,36.45],"type":"Point"}
}