{
  "type": "Feature",
  "properties": {
    "gn:admin1_code":"15",
    "gn:asciiname":"Chaga Parviz",
    "gn:country_code":"IR",
    "gn:dem":653,
    "gn:feature_class":"P",
    "gn:feature_code":"PPL",
    "gn:name":"Chag\u0101 Parv\u012bz",
    "gn:population":0,
    "gn:timezone":"Asia/Tehran",
    "iso:country":"IR",
    "name:fas_x_preferred":[
        "Chag\u0101 Parv\u012bz"
    ],
    "name:fas_x_variant":[
        "\u0686\u06af\u0627 \u067e\u0631\u0648\u06cc\u0632",
        "\u0686\u06af\u0627\u067e\u0631\u0648\u06cc\u0632"
    ],
    "wof:name":"Chaga Parviz",
    "wof:placetype":"locality"
},
  "geometry": {"coordinates":[49.74256,31.54586],"type":"Point"}
}