{
  "type": "Feature",
  "properties": {
    "gn:admin1_code":"5.0",
    "gn:asciiname":"Deh Chal",
    "gn:country_code":"IR",
    "gn:dem":906,
    "gn:feature_class":"P",
    "gn:feature_code":"PPL",
    "gn:name":"Deh Ch\u0101l",
    "gn:population":0,
    "gn:timezone":"Asia/Tehran",
    "iso:country":"IR",
    "name:fas_x_preferred":[
        "Deh Ch\u0101l"
    ],
    "name:fas_x_variant":[
        "\u062f\u0647 \u0686\u0627\u0644"
    ],
    "name:ukr_x_preferred":[
        "\u0414\u0435\u0433\u0447\u0430\u043b\u044c"
    ],
    "wof:name":"Deh Chal",
    "wof:placetype":"locality"
},
  "geometry": {"coordinates":[50.52322,30.99554],"type":"Point"}
}