{
  "type": "Feature",
  "properties": {
    "gn:admin1_code":"4.0",
    "gn:asciiname":"Kur Gaz",
    "gn:cc2":"IR",
    "gn:country_code":"IR",
    "gn:dem":1380,
    "gn:feature_class":"P",
    "gn:feature_code":"PPL",
    "gn:name":"K\u016br Gaz",
    "gn:population":0,
    "gn:timezone":"Asia/Tehran",
    "iso:country":"IR",
    "name:fas_x_preferred":[
        "K\u016br Gaz"
    ],
    "name:und_x_variant":[
        "Kargaz\u012b",
        "Korgaz\u012b"
    ],
    "wof:name":"Kur Gaz",
    "wof:placetype":"locality"
},
  "geometry": {"coordinates":[61.22667,29.30222],"type":"Point"}
}