{
  "type": "Feature",
  "properties": {
    "gn:admin1_code":"44",
    "gn:asciiname":"Khowranak",
    "gn:country_code":"IR",
    "gn:dem":1910,
    "gn:feature_class":"P",
    "gn:feature_code":"PPL",
    "gn:name":"Khowr\u0101nak",
    "gn:population":0,
    "gn:timezone":"Asia/Tehran",
    "iso:country":"IR",
    "name:fas_x_preferred":[
        "\u062e\u0648\u0631\u0627\u0646\u064e\u0643"
    ],
    "name:fas_x_variant":[
        "Kh\u016br\u0101nak",
        "\u062e\u0648\u0631\u0627\u0646\u06a9"
    ],
    "name:msa_x_preferred":[
        "Khvoranak"
    ],
    "name:und_x_variant":[
        "Khowr\u0101nak",
        "\u062e\u0648\u0631\u0627\u0646\u06a9"
    ],
    "wof:name":"Khowranak",
    "wof:placetype":"locality"
},
  "geometry": {"coordinates":[50.57085,36.20109],"type":"Point"}
}