{
  "type": "Feature",
  "properties": {
    "gn:admin1_code":"4",
    "gn:asciiname":"Barzanidan",
    "gn:country_code":"IR",
    "gn:dem":1318,
    "gn:feature_class":"P",
    "gn:feature_code":"PPL",
    "gn:name":"Barzan\u012bdan",
    "gn:population":0,
    "gn:timezone":"Asia/Tehran",
    "iso:country":"IR",
    "name:fas_x_preferred":[
        "\u06a9\u0631\u06cc\u0645 \u0622\u0628\u0627\u062f"
    ],
    "name:fas_x_variant":[
        "Kar\u012bm\u0101b\u0101d",
        "\u0628\u0631\u0632\u0646\u064a\u062f\u0646",
        "\u0628\u0647\u0631 \u0622\u0628\u0627\u062f \u06a9\u0631\u06cc\u0645 \u0622\u0628\u0627\u062f"
    ],
    "name:und_x_variant":[
        "Barzan\u012bdan",
        "Behr\u0101b\u0101d-e Kar\u012bm\u0101b\u0101d"
    ],
    "wof:name":"Barzanidan",
    "wof:placetype":"locality"
},
  "geometry": {"coordinates":[61.5292,27.1375],"type":"Point"}
}