{
  "type": "Feature",
  "properties": {
    "gn:admin1_code":"11",
    "gn:asciiname":"Borhanabad",
    "gn:country_code":"IR",
    "gn:dem":52,
    "gn:feature_class":"P",
    "gn:feature_code":"PPL",
    "gn:name":"Borh\u0101n\u0101b\u0101d",
    "gn:population":0,
    "gn:timezone":"Asia/Tehran",
    "iso:country":"IR",
    "name:fas_x_preferred":[
        "\u0628\u064f\u0631\u0647\u0627\u0646 \u0622\u0628\u0627\u062f"
    ],
    "name:fas_x_variant":[
        "Borh\u0101n\u0101b\u0101d"
    ],
    "wof:name":"Borhanabad",
    "wof:placetype":"locality"
},
  "geometry": {"coordinates":[57.79389000000001,25.79306],"type":"Point"}
}