{
  "type": "Feature",
  "properties": {
    "gn:admin1_code":"15.0",
    "gn:asciiname":"Hajji Hoseyn",
    "gn:country_code":"IR",
    "gn:dem":3,
    "gn:feature_class":"P",
    "gn:feature_code":"PPL",
    "gn:name":"\u1e28\u0101jj\u012b \u1e28oseyn",
    "gn:population":0,
    "gn:timezone":"Asia/Tehran",
    "iso:country":"IR",
    "name:fas_x_preferred":[
        "\u062d\u0627\u062c\u0651\u06cc \u062d\u0633\u064a\u0646"
    ],
    "name:fas_x_variant":[
        "Shalheh-ye \u1e28\u0101jj \u1e28oseyn",
        "\u1e28\u0101jj\u012b \u1e28oseyn",
        "\u062d\u0627\u062c\u06cc \u062d\u0633\u06cc\u0646"
    ],
    "name:und_x_variant":[
        "H\u0101j\u012b Hoseyn",
        "Shalheh H\u0101j\u012b Hoseyn"
    ],
    "wof:name":"Hajji Hoseyn",
    "wof:placetype":"locality"
},
  "geometry": {"coordinates":[48.3484,30.2764],"type":"Point"}
}