{
  "type": "Feature",
  "properties": {
    "gn:admin1_code":"32",
    "gn:asciiname":"Qeshlaq-e Qirlu",
    "gn:country_code":"IR",
    "gn:dem":354,
    "gn:feature_class":"P",
    "gn:feature_code":"PPL",
    "gn:name":"Qeshl\u0101q-e Q\u012brl\u016b",
    "gn:population":0,
    "gn:timezone":"Asia/Tehran",
    "iso:country":"IR",
    "name:fas_x_preferred":[
        "Qeshl\u0101q-e Q\u012brl\u016b"
    ],
    "name:fas_x_variant":[
        "\u0642\u0650\u0634\u0644\u0627\u0642\u0650 \u0642\u064a\u0631\u0644\u0648"
    ],
    "wof:name":"Qeshlaq-e Qirlu",
    "wof:placetype":"locality"
},
  "geometry": {"coordinates":[48.08333,39.26667],"type":"Point"}
}