{
  "type": "Feature",
  "properties": {
    "gn:admin1_code":"11.0",
    "gn:asciiname":"Ala'i",
    "gn:country_code":"IR",
    "gn:dem":123,
    "gn:feature_class":"P",
    "gn:feature_code":"PPL",
    "gn:name":"\u0100l\u0101\u2019\u012b",
    "gn:population":0,
    "gn:timezone":"Asia/Tehran",
    "iso:country":"IR",
    "name:fas_x_preferred":[
        "\u0622\u0644\u0627\u0626\u06cc"
    ],
    "name:fas_x_variant":[
        "\u0100l\u0101\u2019\u012b"
    ],
    "name:msa_x_preferred":[
        "Alai"
    ],
    "wof:name":"Ala'i",
    "wof:placetype":"locality"
},
  "geometry": {"coordinates":[58.77908000000001,25.86057000000001],"type":"Point"}
}