{
  "type": "Feature",
  "properties": {
    "gn:admin1_code":"15",
    "gn:asciiname":"Kungerdeh",
    "gn:country_code":"IR",
    "gn:dem":521,
    "gn:feature_class":"P",
    "gn:feature_code":"PPL",
    "gn:name":"K\u016bngerdeh",
    "gn:population":0,
    "gn:timezone":"Asia/Tehran",
    "iso:country":"IR",
    "name:ara_x_preferred":[
        "\u0643\u0648\u0646\u063a\u0631\u062f\u0629"
    ],
    "name:ceb_x_preferred":[
        "K\u016bngerdeh"
    ],
    "name:fas_x_preferred":[
        "K\u016bngerdeh"
    ],
    "name:fas_x_variant":[
        "\u06a9\u0648\u0646\u06af\u0631\u062f\u0647"
    ],
    "name:swe_x_preferred":[
        "K\u016bngerdeh"
    ],
    "wof:name":"Kungerdeh",
    "wof:placetype":"locality"
},
  "geometry": {"coordinates":[49.86667,31.13333],"type":"Point"}
}