{
  "type": "Feature",
  "properties": {
    "gn:admin1_code":"15",
    "gn:asciiname":"Kungerdeh",
    "gn:country_code":"IR",
    "gn:dem":521,
    "gn:feature_class":"P",
    "gn:feature_code":"PPL",
    "gn:name":"K\u016bngerdeh",
    "gn:population":0,
    "gn:timezone":"Asia/Tehran",
    "iso:country":"IR",
    "name:fas_x_preferred":[
        "K\u016bngerdeh"
    ],
    "wof:name":"Kungerdeh",
    "wof:placetype":"locality"
},
  "geometry": {"coordinates":[49.86667,31.13333],"type":"Point"}
}