{
  "type": "Feature",
  "properties": {
    "gn:admin1_code":"40.0",
    "gn:asciiname":"Fathabad-e Golshan",
    "gn:country_code":"IR",
    "gn:dem":2045,
    "gn:feature_class":"P",
    "gn:feature_code":"PPL",
    "gn:name":"Fat\u1e29\u0101b\u0101d-e Golshan",
    "gn:population":0,
    "gn:timezone":"Asia/Tehran",
    "iso:country":"IR",
    "name:fas_x_preferred":[
        "\u0641\u062a\u062d \u0622\u0628\u0627\u062f \u06af\u0644\u0634\u0646"
    ],
    "name:fas_x_variant":[
        "\u0641\u064e\u062a\u0647\u0627\u0628\u0627\u062f\u0650 \u06af\u064f\u0644\u0634\u064e\u0646",
        "Fat\u1e29\u0101b\u0101d-e Golshan"
    ],
    "name:und_x_variant":[
        "Fath\u0101b\u0101d-e Golshan"
    ],
    "wof:name":"Fathabad-e Golshan",
    "wof:placetype":"locality"
},
  "geometry": {"coordinates":[53.9257,31.4007],"type":"Point"}
}