{
  "type": "Feature",
  "properties": {
    "gn:admin1_code":"22",
    "gn:asciiname":"Khar Guneh",
    "gn:country_code":"IR",
    "gn:dem":46,
    "gn:feature_class":"P",
    "gn:feature_code":"PPL",
    "gn:name":"Khar G\u016bneh",
    "gn:population":0,
    "gn:timezone":"Asia/Tehran",
    "iso:country":"IR",
    "name:fas_x_preferred":[
        "\u062e\u0631 \u06af\u0648\u0646\u0647"
    ],
    "name:fas_x_variant":[
        "\u062e\u0631 \u06af\u0627\u0646\u0647",
        "\u062e\u064e\u0631 \u06af\u064f\u0651\u0646\u0650\u0647",
        "Khar G\u016bneh"
    ],
    "name:und_x_variant":[
        "Khar G\u0101neh",
        "Khar Gooneh"
    ],
    "wof:name":"Khar Guneh",
    "wof:placetype":"locality"
},
  "geometry": {"coordinates":[51.73411,28.00235],"type":"Point"}
}