{
  "type": "Feature",
  "properties": {
    "gn:admin1_code":"9",
    "gn:asciiname":"Jahanabad",
    "gn:country_code":"IR",
    "gn:dem":1623,
    "gn:feature_class":"P",
    "gn:feature_code":"PPL",
    "gn:name":"Jah\u0101n\u0101b\u0101d",
    "gn:population":0,
    "gn:timezone":"Asia/Tehran",
    "iso:country":"IR",
    "name:ara_x_preferred":[
        "\u062c\u0647\u0627\u0646\u200c\u0622\u0628\u0627\u062f"
    ],
    "name:fas_x_preferred":[
        "\u062c\u0647\u0627\u0646 \u0622\u0628\u0627\u062f"
    ],
    "name:fas_x_variant":[
        "Jah\u0101n\u0101b\u0101d",
        "\u062c\u0647\u0627\u0646\u200c\u0622\u0628\u0627\u062f"
    ],
    "name:msa_x_preferred":[
        "Jahanabad"
    ],
    "name:urd_x_preferred":[
        "\u062c\u06c1\u0627\u0646 \u0622\u0628\u0627\u062f"
    ],
    "wof:name":"Jahanabad",
    "wof:placetype":"locality"
},
  "geometry": {"coordinates":[48.96206,35.07313],"type":"Point"}
}