{
  "type": "Feature",
  "properties": {
    "gn:admin1_code":"3.0",
    "gn:asciiname":"Qasemabad",
    "gn:country_code":"IR",
    "gn:dem":2353,
    "gn:feature_class":"P",
    "gn:feature_code":"PPL",
    "gn:name":"Q\u0101sem\u0101b\u0101d",
    "gn:population":0,
    "gn:timezone":"Asia/Tehran",
    "iso:country":"IR",
    "name:fas_x_preferred":[
        "Q\u0101sem\u0101b\u0101d"
    ],
    "name:fas_x_variant":[
        "\u0642\u0627\u0633\u0645 \u0622\u0628\u0627\u062f"
    ],
    "name:und_x_variant":[
        "\u0642\u0627\u0633\u0645 \u0622\u0628\u0627\u062f"
    ],
    "wof:name":"Qasemabad",
    "wof:placetype":"locality"
},
  "geometry": {"coordinates":[50.13886,32.43964],"type":"Point"}
}