{
  "type": "Feature",
  "properties": {
    "gn:admin1_code":"5.0",
    "gn:asciiname":"Dameh",
    "gn:country_code":"IR",
    "gn:dem":2570,
    "gn:feature_class":"P",
    "gn:feature_code":"PPL",
    "gn:name":"Dameh",
    "gn:population":0,
    "gn:timezone":"Asia/Tehran",
    "iso:country":"IR",
    "name:ara_x_preferred":[
        "\u062f\u0627\u0645\u0629"
    ],
    "name:fas_x_preferred":[
        "\u062f\u0645\u0647"
    ],
    "wof:name":"Dameh",
    "wof:placetype":"locality"
},
  "geometry": {"coordinates":[51.00302,30.86945],"type":"Point"}
}