{
  "type": "Feature",
  "properties": {
    "gn:admin1_code":"32",
    "gn:asciiname":"Dalikli Dash",
    "gn:country_code":"IR",
    "gn:dem":1576,
    "gn:feature_class":"P",
    "gn:feature_code":"PPL",
    "gn:name":"Dal\u012bkl\u012b D\u0101sh",
    "gn:population":0,
    "gn:timezone":"Asia/Tehran",
    "iso:country":"IR",
    "name:fas_x_preferred":[
        "\u062f\u064e\u0644\u064a\u0644\u064e\u0643\u0644\u064a\u062f\u0627\u0634"
    ],
    "name:fas_x_variant":[
        "\u062f\u0644\u064a\u0643\u0644\u06cc \u062f\u0627\u0634",
        "Dal\u012blakl\u012bd\u0101sh",
        "Dal\u012bkl\u012b D\u0101sh"
    ],
    "wof:name":"Dalikli Dash",
    "wof:placetype":"locality"
},
  "geometry": {"coordinates":[48.3022,38.5873],"type":"Point"}
}