{
  "type": "Feature",
  "properties": {
    "gn:admin1_code":"13",
    "gn:asciiname":"Kamarab",
    "gn:country_code":"IR",
    "gn:dem":1282,
    "gn:feature_class":"P",
    "gn:feature_code":"PPL",
    "gn:name":"Kamar\u0101b",
    "gn:population":0,
    "gn:timezone":"Asia/Tehran",
    "iso:country":"IR",
    "name:fas_x_preferred":[
        "\u06a9\u0645\u0631\u0627\u0628"
    ],
    "name:fas_x_variant":[
        "Kamar \u0100b",
        "Kamar\u0101b"
    ],
    "wof:name":"Kamarab",
    "wof:placetype":"locality"
},
  "geometry": {"coordinates":[47.309,34.1866],"type":"Point"}
}