{
  "type": "Feature",
  "properties": {
    "gn:admin1_code":"8",
    "gn:asciiname":"Garsak",
    "gn:country_code":"IR",
    "gn:dem":132,
    "gn:feature_class":"P",
    "gn:feature_code":"PPL",
    "gn:name":"Garsak",
    "gn:population":0,
    "gn:timezone":"Asia/Tehran",
    "iso:country":"IR",
    "name:fas_x_preferred":[
        "\u06af\u0631\u0633\u06af"
    ],
    "name:fas_x_variant":[
        "\u06af\u0631\u0633\u06a9",
        "\u06af\u0631\u0633\u06a9 \u067e\u0627\u0626\u06cc\u0646",
        "\u06af\u0631\u0633\u06a9 \u067e\u0627\u06cc\u06cc\u0646"
    ],
    "name:msa_x_preferred":[
        "Garsak-e Pain"
    ],
    "name:ukr_x_preferred":[
        "\u0490\u0430\u0440\u0441\u0430\u043a-\u0435 \u041f\u0430\u0457\u043d"
    ],
    "name:und_x_variant":[
        "P\u0101\u2019\u012bn Gerasg",
        "Gerasg",
        "Garsag",
        "Garsak",
        "\u06af\u0631\u0633\u06af",
        "Garsak-e P\u0101\u2019\u012bn"
    ],
    "wof:name":"Garsak",
    "wof:placetype":"locality"
},
  "geometry": {"coordinates":[50.1131,37.06635],"type":"Point"}
}