{
  "type": "Feature",
  "properties": {
    "gn:admin1_code":"13",
    "gn:asciiname":"A'inalah",
    "gn:country_code":"IR",
    "gn:dem":1683,
    "gn:feature_class":"P",
    "gn:feature_code":"PPL",
    "gn:name":"\u0100\u2019\u012bnalah",
    "gn:population":0,
    "gn:timezone":"Asia/Tehran",
    "iso:country":"IR",
    "name:fas_x_preferred":[
        "\u0622\u0626\u06cc\u0646\u0644\u0647"
    ],
    "name:und_x_variant":[
        "\u0100\u2019\u012bnalah"
    ],
    "wof:name":"A'inalah",
    "wof:placetype":"locality"
},
  "geometry": {"coordinates":[47.4345,34.7459],"type":"Point"}
}