{
  "type": "Feature",
  "properties": {
    "gn:admin1_code":"16.0",
    "gn:asciiname":"Siuch",
    "gn:country_code":"IR",
    "gn:dem":1584,
    "gn:feature_class":"P",
    "gn:feature_code":"PPL",
    "gn:name":"Siuch",
    "gn:population":0,
    "gn:timezone":"Asia/Tehran",
    "iso:country":"IR",
    "name:fas_x_preferred":[
        "\u0633\u0650\u064a\u0648\u0686"
    ],
    "name:fas_x_variant":[
        "S\u012bvech",
        "\u0633\u06cc\u0648\u0686",
        "\u0633\u064a\u0648\u0650\u0686"
    ],
    "name:und_x_variant":[
        "Sey\u016bch",
        "Siuch"
    ],
    "wof:name":"Siuch",
    "wof:placetype":"locality"
},
  "geometry": {"coordinates":[45.8036,36.0793],"type":"Point"}
}