{
  "type": "Feature",
  "properties": {
    "gn:admin1_code":"8",
    "gn:asciiname":"Ganaz Darreh",
    "gn:country_code":"IR",
    "gn:dem":1612,
    "gn:feature_class":"P",
    "gn:feature_code":"PPL",
    "gn:name":"Ganaz Darreh",
    "gn:population":0,
    "gn:timezone":"Asia/Tehran",
    "iso:country":"IR",
    "name:fas_x_preferred":[
        "\u06af\u0646\u0632 \u062f\u0631\u0647"
    ],
    "wof:name":"Ganaz Darreh",
    "wof:placetype":"locality"
},
  "geometry": {"coordinates":[48.6814,37.6951],"type":"Point"}
}