{
  "type": "Feature",
  "properties": {
    "gn:admin1_code":"29",
    "gn:asciiname":"Dehu Henek",
    "gn:country_code":"IR",
    "gn:dem":2049,
    "gn:feature_class":"P",
    "gn:feature_code":"PPL",
    "gn:name":"Deh\u016b Henek",
    "gn:population":0,
    "gn:timezone":"Asia/Tehran",
    "iso:country":"IR",
    "name:fas_x_preferred":[
        "\u062f\u0647\u0648\u0626\u06cc\u0647 \u062d\u0646\u06a9"
    ],
    "name:fas_x_variant":[
        "Deh\u016b Henek",
        "Dohr\u012b Henek"
    ],
    "name:und_x_variant":[
        "Dohr\u012b Henek"
    ],
    "wof:name":"Dehu Henek",
    "wof:placetype":"locality"
},
  "geometry": {"coordinates":[57.14809,30.74425],"type":"Point"}
}