{
  "type": "Feature",
  "properties": {
    "gn:admin1_code":"36",
    "gn:asciiname":"Murestaneh",
    "gn:country_code":"IR",
    "gn:dem":528,
    "gn:feature_class":"P",
    "gn:feature_code":"PPL",
    "gn:name":"M\u016brest\u0101neh",
    "gn:population":0,
    "gn:timezone":"Asia/Tehran",
    "iso:country":"IR",
    "name:azb_x_preferred":[
        "\u0645\u0648\u0631\u0633\u062a\u0627\u0646\u0647"
    ],
    "name:ceb_x_preferred":[
        "M\u016brest\u0101neh"
    ],
    "name:fas_x_preferred":[
        "\u0645\u0648\u0631\u0633\u062a\u0627\u0646\u0647"
    ],
    "name:fas_x_variant":[
        "M\u016brest\u0101neh"
    ],
    "name:swe_x_preferred":[
        "M\u016brest\u0101neh"
    ],
    "name:und_x_variant":[
        "Muristanekh",
        "M\u016brest\u0101neh-ye-Q\u0101z\u012b Bol\u0101gh\u012b",
        "Murist\u0101neh"
    ],
    "wof:name":"Murestaneh",
    "wof:placetype":"locality"
},
  "geometry": {"coordinates":[48.92534000000001,36.84662],"type":"Point"}
}