{
  "type": "Feature",
  "properties": {
    "gn:admin1_code":"9.0",
    "gn:asciiname":"Shahrak-e Qandi",
    "gn:country_code":"IR",
    "gn:dem":1635,
    "gn:feature_class":"P",
    "gn:feature_code":"PPL",
    "gn:name":"Shahrak-e Qand\u012b",
    "gn:population":0,
    "gn:timezone":"Asia/Tehran",
    "iso:country":"IR",
    "name:fas_x_preferred":[
        "\u0634\u0647\u0631\u06a9 \u0642\u0646\u062f\u06cc"
    ],
    "name:und_x_variant":[
        "Shahrak-e Qand\u012b"
    ],
    "wof:name":"Shahrak-e Qandi",
    "wof:placetype":"locality"
},
  "geometry": {"coordinates":[48.13445,34.77884],"type":"Point"}
}