{
  "type": "Feature",
  "properties": {
    "gn:admin1_code":"8",
    "gn:asciiname":"Eshkalan-e Bala",
    "gn:country_code":"IR",
    "gn:dem":43,
    "gn:feature_class":"P",
    "gn:feature_code":"PPL",
    "gn:name":"Eshkal\u0101n-e B\u0101l\u0101",
    "gn:population":0,
    "gn:timezone":"Asia/Tehran",
    "iso:country":"IR",
    "name:fas_x_preferred":[
        "\u0627\u0634\u06a9\u0627\u0644\u0627\u0646"
    ],
    "name:fas_x_variant":[
        "Eshkal\u0101n",
        "\u0627\u0634\u06a9\u0627\u0644\u0627\u0646 \u0628\u0627\u0644\u0627"
    ],
    "name:und_x_variant":[
        "Eshkal\u0101n-e B\u0101l\u0101"
    ],
    "wof:name":"Eshkalan-e Bala",
    "wof:placetype":"locality"
},
  "geometry": {"coordinates":[49.25666,37.25963],"type":"Point"}
}