{
  "type": "Feature",
  "properties": {
    "gn:admin1_code":"33",
    "gn:asciiname":"Deshab",
    "gn:country_code":"IR",
    "gn:dem":1683,
    "gn:feature_class":"P",
    "gn:feature_code":"PPL",
    "gn:name":"Desh\u0101b",
    "gn:population":0,
    "gn:timezone":"Asia/Tehran",
    "iso:country":"IR",
    "name:ceb_x_preferred":[
        "Desh\u0101b"
    ],
    "name:fas_x_preferred":[
        "\u062f\u0634\u0627\u0628"
    ],
    "name:fas_x_variant":[
        "D\u012bsh\u0101b",
        "Desh\u0101b",
        "\u062f\u06cc\u0634\u0627\u0628"
    ],
    "name:msa_x_preferred":[
        "Dishab"
    ],
    "name:swe_x_preferred":[
        "Desh\u0101b"
    ],
    "wof:name":"Deshab",
    "wof:placetype":"locality"
},
  "geometry": {"coordinates":[47.6131,37.6288],"type":"Point"}
}