{
  "type": "Feature",
  "properties": {
    "gn:admin1_code":"41",
    "gn:asciiname":"Seyyed Morad",
    "gn:country_code":"IR",
    "gn:dem":1645,
    "gn:feature_class":"P",
    "gn:feature_code":"PPLF",
    "gn:name":"Seyyed Mor\u0101d",
    "gn:population":0,
    "gn:timezone":"Asia/Tehran",
    "iso:country":"IR",
    "name:fas_x_preferred":[
        "Seyyed Mor\u0101d"
    ],
    "name:fas_x_variant":[
        "\u0633\u06cc\u062f \u0645\u0631\u0627\u062f",
        "\u0632\u0646\u0648\u06af"
    ],
    "name:und_x_variant":[
        "Zon\u016bk",
        "Seyyed \u2018Emr\u0101n",
        "Saiyid \u2018Umr\u0101n",
        "Zan\u016bg",
        "Zon\u016bg"
    ],
    "wof:name":"Seyyed Morad",
    "wof:placetype":"locality"
},
  "geometry": {"coordinates":[59.76834,32.30317],"type":"Point"}
}