{
  "type": "Feature",
  "properties": {
    "gn:admin1_code":"32",
    "gn:asciiname":"Dust Beyglu",
    "gn:country_code":"IR",
    "gn:dem":816,
    "gn:feature_class":"P",
    "gn:feature_code":"PPL",
    "gn:name":"D\u016bst Beygl\u016b",
    "gn:population":0,
    "gn:timezone":"Asia/Tehran",
    "iso:country":"IR",
    "name:fas_x_preferred":[
        "\u062f\u0648\u0633\u062a \u0628\u06cc\u06af\u0644\u0648"
    ],
    "name:fas_x_variant":[
        "D\u016bst Beygl\u016b"
    ],
    "name:und_x_variant":[
        "Dust\u2018ali Beygl\u016b"
    ],
    "wof:name":"Dust Beyglu",
    "wof:placetype":"locality"
},
  "geometry": {"coordinates":[47.53614,38.54754000000001],"type":"Point"}
}