{
  "type": "Feature",
  "properties": {
    "gn:admin1_code":"37",
    "gn:asciiname":"Kashadeleh",
    "gn:country_code":"IR",
    "gn:dem":298,
    "gn:feature_class":"P",
    "gn:feature_code":"PPL",
    "gn:name":"Kashadeleh",
    "gn:population":0,
    "gn:timezone":"Asia/Tehran",
    "iso:country":"IR",
    "name:fas_x_preferred":[
        "\u0643\u064e\u0634\u064e\u062f\u0650\u0644\u0650\u0647"
    ],
    "wof:name":"Kashadeleh",
    "wof:placetype":"locality"
},
  "geometry": {"coordinates":[56.25,37.91667],"type":"Point"}
}