{
  "type": "Feature",
  "properties": {
    "gn:admin1_code":"11",
    "gn:asciiname":"Deh Bandan",
    "gn:cc2":"IR",
    "gn:country_code":"IR",
    "gn:dem":702,
    "gn:feature_class":"P",
    "gn:feature_code":"PPL",
    "gn:name":"Deh Band\u0101n",
    "gn:population":0,
    "gn:timezone":"Asia/Tehran",
    "iso:country":"IR",
    "name:fas_x_preferred":[
        "\u062f\u0650\u0647 \u0628\u064e\u0646\u062f\u0627\u0646"
    ],
    "name:fas_x_variant":[
        "\u062f\u0650\u0647\u0650 \u0628\u064e\u0646\u062f\u0627\u0646",
        "Deh Band\u0101n"
    ],
    "name:und_x_variant":[
        "Deh-e Band\u0101n"
    ],
    "wof:name":"Deh Bandan",
    "wof:placetype":"locality"
},
  "geometry": {"coordinates":[57.56667,26.38333],"type":"Point"}
}