{
  "type": "Feature",
  "properties": {
    "gn:admin1_code":"35",
    "gn:asciiname":"Kafak",
    "gn:country_code":"IR",
    "gn:dem":314,
    "gn:feature_class":"P",
    "gn:feature_code":"PPL",
    "gn:name":"Kaf\u0101k",
    "gn:population":0,
    "gn:timezone":"Asia/Tehran",
    "iso:country":"IR",
    "name:fas_x_preferred":[
        "\u0643\u0641\u0627\u0643"
    ],
    "name:fas_x_variant":[
        "Kaf\u0101k",
        "\u06a9\u0641\u0627\u06a9"
    ],
    "wof:name":"Kafak",
    "wof:placetype":"locality"
},
  "geometry": {"coordinates":[52.8487,36.19876],"type":"Point"}
}