{
  "type": "Feature",
  "properties": {
    "gn:admin1_code":"42",
    "gn:asciiname":"Mazra`eh-ye Sheykh",
    "gn:country_code":"IR",
    "gn:dem":1207,
    "gn:feature_class":"P",
    "gn:feature_code":"PPL",
    "gn:name":"Mazra\u2018eh-ye Sheykh",
    "gn:population":0,
    "gn:timezone":"Asia/Tehran",
    "iso:country":"IR",
    "name:fas_x_preferred":[
        "\u0634\u06cc\u062e\u0627\u0646"
    ],
    "name:fas_x_variant":[
        "Sheykh\u0101n",
        "\u0645\u0632\u0631\u0639\u0647 \u0634\u06cc\u062e"
    ],
    "name:und_x_variant":[
        "Mazra\u2018eh-ye Sheykh"
    ],
    "wof:name":"Mazra`eh-ye Sheykh",
    "wof:placetype":"locality"
},
  "geometry": {"coordinates":[59.9121,34.874],"type":"Point"}
}