{
  "type": "Feature",
  "properties": {
    "gn:admin1_code":"37",
    "gn:asciiname":"Yalu",
    "gn:country_code":"IR",
    "gn:dem":260,
    "gn:feature_class":"P",
    "gn:feature_code":"PPL",
    "gn:name":"Y\u0101l\u016b",
    "gn:population":0,
    "gn:timezone":"Asia/Tehran",
    "iso:country":"IR",
    "name:fas_x_preferred":[
        "\u064a\u0627\u0644\u0648"
    ],
    "name:fas_x_variant":[
        "Y\u0101l\u016b",
        "\u0628\u0627\u0644\u0648"
    ],
    "name:und_x_variant":[
        "B\u0101l\u016b"
    ],
    "wof:name":"Yalu",
    "wof:placetype":"locality"
},
  "geometry": {"coordinates":[54.36342,36.78376],"type":"Point"}
}