{
  "type": "Feature",
  "properties": {
    "gn:admin1_code":"33",
    "gn:asciiname":"Qarab-e Sofla",
    "gn:country_code":"IR",
    "gn:dem":1353,
    "gn:feature_class":"P",
    "gn:feature_code":"PPL",
    "gn:name":"Q\u0101r\u0101b-e Sofl\u00e1",
    "gn:population":0,
    "gn:timezone":"Asia/Tehran",
    "iso:country":"IR",
    "name:fas_x_preferred":[
        "Q\u0101r\u0101b-e Sofl\u00e1"
    ],
    "name:fas_x_variant":[
        "\u0642\u0627\u0631\u0627\u0628 \u0633\u0641\u0644\u06cc"
    ],
    "name:und_x_variant":[
        "Nizhnyaya Kerov",
        "Q\u0101r\u0101b P\u0101\u2019\u012bn",
        "Kerov Ashagi",
        "F\u0101r\u0101b-e Sofl\u00e1"
    ],
    "wof:name":"Qarab-e Sofla",
    "wof:placetype":"locality"
},
  "geometry": {"coordinates":[48.15379,37.4355],"type":"Point"}
}