{
  "type": "Feature",
  "properties": {
    "gn:admin1_code":"41",
    "gn:asciiname":"Sangabad",
    "gn:country_code":"IR",
    "gn:dem":1979,
    "gn:feature_class":"P",
    "gn:feature_code":"PPL",
    "gn:name":"Sang\u0101b\u0101d",
    "gn:population":0,
    "gn:timezone":"Asia/Tehran",
    "iso:country":"IR",
    "name:fas_x_preferred":[
        "Sang\u0101b\u0101d"
    ],
    "name:fas_x_variant":[
        "\u0633\u0646\u06af \u0622\u0628\u0627\u062f",
        "Sang\u0101b\u0101d-e B\u0101l\u0101"
    ],
    "name:und_x_variant":[
        "Sang\u0101b\u0101d-e B\u0101l\u0101",
        "\u0633\u0646\u06af \u0622\u0628\u0627\u062f"
    ],
    "wof:name":"Sangabad",
    "wof:placetype":"locality"
},
  "geometry": {"coordinates":[59.37119000000001,33.06634],"type":"Point"}
}