{
  "type": "Feature",
  "properties": {
    "gn:admin1_code":"15",
    "gn:asciiname":"Ab Kharzma",
    "gn:country_code":"IR",
    "gn:dem":408,
    "gn:feature_class":"P",
    "gn:feature_code":"PPL",
    "gn:name":"\u0100b Kharzm\u0101",
    "gn:population":0,
    "gn:timezone":"Asia/Tehran",
    "iso:country":"IR",
    "name:fas_x_preferred":[
        "\u0622\u0628 \u062e\u0631\u0632\u0645\u0627"
    ],
    "name:fas_x_variant":[
        "\u0100b Kharzahreh",
        "\u0100b Kharzm\u0101",
        "\u062c\u0645\u0627\u0644 \u062c\u0647\u0627\u0646"
    ],
    "name:und_x_variant":[
        "Jam\u0101l Jah\u0101n"
    ],
    "wof:name":"Ab Kharzma",
    "wof:placetype":"locality"
},
  "geometry": {"coordinates":[50.0579,30.768],"type":"Point"}
}