{
  "type": "Feature",
  "properties": {
    "gn:admin1_code":"33",
    "gn:asciiname":"Sari Qayeh",
    "gn:country_code":"IR",
    "gn:dem":1581,
    "gn:feature_class":"P",
    "gn:feature_code":"PPL",
    "gn:name":"S\u0101r\u012b Qayeh",
    "gn:population":0,
    "gn:timezone":"Asia/Tehran",
    "iso:country":"IR",
    "name:fas_x_preferred":[
        "\u0633\u0627\u0631\u06cc \u0642\u06cc\u0647"
    ],
    "name:fas_x_variant":[
        "S\u0101r\u012b Qayeh"
    ],
    "wof:name":"Sari Qayeh",
    "wof:placetype":"locality"
},
  "geometry": {"coordinates":[46.4789,37.2142],"type":"Point"}
}