{
  "type": "Feature",
  "properties": {
    "gn:admin1_code":"35",
    "gn:asciiname":"Eram",
    "gn:country_code":"IR",
    "gn:dem":1318,
    "gn:feature_class":"P",
    "gn:feature_code":"PPL",
    "gn:name":"Eram",
    "gn:population":0,
    "gn:timezone":"Asia/Tehran",
    "iso:country":"IR",
    "name:fas_x_preferred":[
        "\u0627\u0631\u0645"
    ],
    "name:und_x_variant":[
        "Eram"
    ],
    "wof:name":"Eram",
    "wof:placetype":"locality"
},
  "geometry": {"coordinates":[53.7032,36.40596],"type":"Point"}
}