{
  "type": "Feature",
  "properties": {
    "gn:admin1_code":"1.0",
    "gn:asciiname":"Kulseh-ye Sofla",
    "gn:country_code":"IR",
    "gn:dem":1282,
    "gn:elevation":"0.0",
    "gn:feature_class":"P",
    "gn:feature_code":"PPL",
    "gn:name":"K\u016blseh-ye Sofl\u00e1",
    "gn:population":0,
    "gn:timezone":"Asia/Tehran",
    "iso:country":"IR",
    "name:azb_x_preferred":[
        "\u0622\u0634\u0627\u063a\u06cc \u06a9\u0648\u0644\u0633\u0647"
    ],
    "name:ceb_x_preferred":[
        "K\u016blseh-ye Sofl\u00e1"
    ],
    "name:ckb_x_preferred":[
        "\u06a9\u06c6\u06b5\u06d5\u0633\u06d5\u06cc \u062e\u0648\u0627\u0631\u06ce"
    ],
    "name:fas_x_preferred":[
        "\u0643\u0648\u0644\u0633\u0650\u06c0 \u067e\u0627\u0626\u064a\u0646"
    ],
    "name:fas_x_variant":[
        "\u06a9\u0648\u0644\u0633\u0647 \u0633\u0641\u0644\u06cc",
        "K\u016blseh-ye Sofl\u00e1"
    ],
    "name:kur_x_preferred":[
        "Kollesey xwar\u00ea"
    ],
    "name:msa_x_preferred":[
        "Kulseh-ye Sofla"
    ],
    "name:swe_x_preferred":[
        "K\u016blseh-ye Sofl\u00e1"
    ],
    "name:und_x_variant":[
        "K\u016blseh-ye P\u0101\u2019\u012bn"
    ],
    "wof:name":"Kulseh-ye Sofla",
    "wof:placetype":"locality"
},
  "geometry": {"coordinates":[45.5817,36.0985],"type":"Point"}
}