{
  "type": "Feature",
  "properties": {
    "gn:admin1_code":"29",
    "gn:asciiname":"Kabu",
    "gn:country_code":"IR",
    "gn:dem":432,
    "gn:feature_class":"P",
    "gn:feature_code":"PPL",
    "gn:name":"Kab\u016b",
    "gn:population":0,
    "gn:timezone":"Asia/Tehran",
    "iso:country":"IR",
    "name:ceb_x_preferred":[
        "Kabu"
    ],
    "name:fas_x_preferred":[
        "\u06a9\u0628\u0648"
    ],
    "name:fas_x_variant":[
        "Kab\u016b"
    ],
    "name:nld_x_preferred":[
        "Kabu"
    ],
    "name:swe_x_preferred":[
        "Kabu"
    ],
    "wof:name":"Kabu",
    "wof:placetype":"locality"
},
  "geometry": {"coordinates":[57.951,27.7502],"type":"Point"}
}