{
  "type": "Feature",
  "properties": {
    "gn:admin1_code":"29",
    "gn:asciiname":"Salmanabad",
    "gn:country_code":"IR",
    "gn:dem":550,
    "gn:feature_class":"P",
    "gn:feature_code":"PPL",
    "gn:name":"Salm\u0101n\u0101b\u0101d",
    "gn:population":0,
    "gn:timezone":"Asia/Tehran",
    "iso:country":"IR",
    "name:ara_x_preferred":[
        "\u0633\u0644\u0645\u0627\u0646 \u0623\u0628\u0627\u062f"
    ],
    "name:fas_x_preferred":[
        "\u0633\u0644\u0645\u0627\u0646 \u0622\u0628\u0627\u062f"
    ],
    "name:fas_x_variant":[
        "Salm\u0101n\u0101b\u0101d-e P\u0101\u2019\u012bn",
        "Salm\u0101n\u0101b\u0101d",
        "\u0633\u0644\u0645\u0627\u0646\u200c\u0622\u0628\u0627\u062f"
    ],
    "wof:name":"Salmanabad",
    "wof:placetype":"locality"
},
  "geometry": {"coordinates":[57.7893,28.3432],"type":"Point"}
}