{
  "type": "Feature",
  "properties": {
    "gn:admin1_code":"40",
    "gn:asciiname":"Baghshah",
    "gn:country_code":"IR",
    "gn:dem":2424,
    "gn:feature_class":"P",
    "gn:feature_code":"PPL",
    "gn:name":"B\u0101ghsh\u0101h",
    "gn:population":0,
    "gn:timezone":"Asia/Tehran",
    "iso:country":"IR",
    "name:fas_x_preferred":[
        "\u0628\u0627\u063a \u0634\u0627\u0647"
    ],
    "name:fas_x_variant":[
        "\u0628\u0627\u063a\u0634\u0627\u0647",
        "B\u0101gh-e Sh\u0101h",
        "B\u0101ghsh\u0101h"
    ],
    "name:und_x_variant":[
        "B\u0101gh-i-Sh\u0101h"
    ],
    "wof:name":"Baghshah",
    "wof:placetype":"locality"
},
  "geometry": {"coordinates":[53.9921,31.6015],"type":"Point"}
}