{
  "type": "Feature",
  "properties": {
    "gn:admin1_code":"9",
    "gn:asciiname":"Heyran",
    "gn:country_code":"IR",
    "gn:dem":2019,
    "gn:feature_class":"P",
    "gn:feature_code":"PPL",
    "gn:name":"\u1e28eyr\u0101n",
    "gn:population":0,
    "gn:timezone":"Asia/Tehran",
    "iso:country":"IR",
    "name:aze_x_preferred":[
        "Heyran"
    ],
    "name:fas_x_preferred":[
        "\u1e28eyr\u0101n"
    ],
    "name:fas_x_variant":[
        "\u062d\u06cc\u0631\u0627\u0646"
    ],
    "name:und_x_variant":[
        "Hair\u0101n",
        "\u062d\u06cc\u0631\u0627\u0646"
    ],
    "wof:name":"Heyran",
    "wof:placetype":"locality"
},
  "geometry": {"coordinates":[48.85273,34.80675],"type":"Point"}
}