{
  "type": "Feature",
  "properties": {
    "gn:admin1_code":"35.0",
    "gn:asciiname":"Najjar Kola",
    "gn:country_code":"IR",
    "gn:dem":1023,
    "gn:feature_class":"P",
    "gn:feature_code":"PPL",
    "gn:name":"Najj\u0101r Kol\u0101",
    "gn:population":0,
    "gn:timezone":"Asia/Tehran",
    "iso:country":"IR",
    "name:fas_x_preferred":[
        "\u0646\u062c\u0627\u0631 \u0643\u0644\u0627"
    ],
    "name:fas_x_variant":[
        "Najj\u0101r Kol\u0101"
    ],
    "wof:name":"Najjar Kola",
    "wof:placetype":"locality"
},
  "geometry": {"coordinates":[52.4262,36.19856],"type":"Point"}
}