{
  "type": "Feature",
  "properties": {
    "gn:admin1_code":"4",
    "gn:asciiname":"Mohammadabad-e Pulki",
    "gn:country_code":"IR",
    "gn:dem":1679,
    "gn:feature_class":"P",
    "gn:feature_code":"PPL",
    "gn:name":"Mo\u1e29ammad\u0101b\u0101d-e P\u016blk\u012b",
    "gn:population":0,
    "gn:timezone":"Asia/Tehran",
    "iso:country":"IR",
    "name:fas_x_preferred":[
        "\u0645\u062d\u0645\u0651\u062f \u0622\u0628\u0627\u062f \u067e\u0648\u0644\u06a9\u06cc"
    ],
    "name:fas_x_variant":[
        "Mo\u1e29ammad\u0101b\u0101d-e P\u016blk\u012b"
    ],
    "wof:name":"Mohammadabad-e Pulki",
    "wof:placetype":"locality"
},
  "geometry": {"coordinates":[60.4459,29.52636],"type":"Point"}
}