{
  "type": "Feature",
  "properties": {
    "gn:admin1_code":"16.0",
    "gn:asciiname":"Kamar Siah",
    "gn:country_code":"IR",
    "gn:dem":1587,
    "gn:feature_class":"P",
    "gn:feature_code":"PPL",
    "gn:name":"Kamar S\u012b\u0101h",
    "gn:population":0,
    "gn:timezone":"Asia/Tehran",
    "iso:country":"IR",
    "name:ceb_x_preferred":[
        "S\u012b\u0101h Kamareh-ye Sofl\u00e1"
    ],
    "name:fas_x_preferred":[
        "\u06a9\u0645\u0631 \u0633\u06cc\u0627\u0647"
    ],
    "name:fas_x_variant":[
        "Kamar S\u012b\u0101h",
        "\u06a9\u0645\u0631\u0633\u06cc\u0627\u0647"
    ],
    "name:swe_x_preferred":[
        "S\u012b\u0101h Kamareh-ye Sofl\u00e1"
    ],
    "wof:name":"Kamar Siah",
    "wof:placetype":"locality"
},
  "geometry": {"coordinates":[46.3924,36.1007],"type":"Point"}
}