{
  "type": "Feature",
  "properties": {
    "gn:admin1_code":"9",
    "gn:asciiname":"Tappeh `Ali",
    "gn:country_code":"IR",
    "gn:dem":1893,
    "gn:feature_class":"P",
    "gn:feature_code":"PPL",
    "gn:name":"Tappeh \u2018Al\u012b",
    "gn:population":0,
    "gn:timezone":"Asia/Tehran",
    "iso:country":"IR",
    "name:fas_x_preferred":[
        "Tappeh \u2018Al\u012b"
    ],
    "name:fas_x_variant":[
        "\u062a\u067e\u0647 \u0639\u0644\u06cc"
    ],
    "name:und_x_variant":[
        "Tappeh-ye \u2018Al\u012b"
    ],
    "wof:name":"Tappeh `Ali",
    "wof:placetype":"locality"
},
  "geometry": {"coordinates":[48.02407,34.25117],"type":"Point"}
}