{
  "type": "Feature",
  "properties": {
    "gn:admin1_code":"15",
    "gn:asciiname":"Pir Mahmud",
    "gn:country_code":"IR",
    "gn:dem":715,
    "gn:feature_class":"P",
    "gn:feature_code":"PPL",
    "gn:name":"P\u012br Ma\u1e29m\u016bd",
    "gn:population":0,
    "gn:timezone":"Asia/Tehran",
    "iso:country":"IR",
    "name:ara_x_preferred":[
        "\u0628\u064a\u0631 \u0645\u062d\u0645\u062f"
    ],
    "name:fas_x_preferred":[
        "P\u012br Ma\u1e29m\u016bd"
    ],
    "name:fas_x_variant":[
        "\u067e\u06cc\u0631\u0645\u062d\u0645\u0648\u062f"
    ],
    "wof:name":"Pir Mahmud",
    "wof:placetype":"locality"
},
  "geometry": {"coordinates":[49.6025,32.23139],"type":"Point"}
}