{
  "type": "Feature",
  "properties": {
    "gn:admin1_code":"4.0",
    "gn:asciiname":"Govash",
    "gn:country_code":"IR",
    "gn:dem":860,
    "gn:feature_class":"P",
    "gn:feature_code":"PPL",
    "gn:name":"Gov\u0101sh",
    "gn:population":0,
    "gn:timezone":"Asia/Tehran",
    "iso:country":"IR",
    "name:fas_x_preferred":[
        "\u06af\u0648\u0627\u0634"
    ],
    "name:fas_x_variant":[
        "G\u016b\u0101sh",
        "Gov\u0101sh",
        "G\u016b \u0100sn"
    ],
    "name:und_x_variant":[
        "G\u016b \u0100sn"
    ],
    "wof:name":"Govash",
    "wof:placetype":"locality"
},
  "geometry": {"coordinates":[59.73526,26.69893],"type":"Point"}
}