{
  "type": "Feature",
  "properties": {
    "gn:admin1_code":"34",
    "gn:asciiname":"Khar Afkaleh",
    "gn:country_code":"IR",
    "gn:dem":1901,
    "gn:feature_class":"P",
    "gn:feature_code":"PPL",
    "gn:name":"Khar Afkaleh",
    "gn:population":0,
    "gn:timezone":"Asia/Tehran",
    "iso:country":"IR",
    "name:fas_x_preferred":[
        "\u062e\u064e\u0631 \u0627\u064e\u0641\u0643\u064e\u0644\u0650\u0647"
    ],
    "wof:name":"Khar Afkaleh",
    "wof:placetype":"locality"
},
  "geometry": {"coordinates":[49.94667000000001,33.64611],"type":"Point"}
}