{
  "type": "Feature",
  "properties": {
    "gn:admin1_code":"33",
    "gn:asciiname":"Shalqun",
    "gn:country_code":"IR",
    "gn:dem":1751,
    "gn:feature_class":"P",
    "gn:feature_code":"PPL",
    "gn:name":"Sh\u0101lq\u016bn",
    "gn:population":0,
    "gn:timezone":"Asia/Tehran",
    "iso:country":"IR",
    "name:azb_x_preferred":[
        "\u0634\u0627\u0644\u0642\u06cc\u0646"
    ],
    "name:ceb_x_preferred":[
        "Sh\u0101lq\u016bn"
    ],
    "name:fas_x_preferred":[
        "\u0634\u0627\u0644\u0642\u0648\u0646"
    ],
    "name:fas_x_variant":[
        "Sh\u0101lq\u016bn"
    ],
    "name:msa_x_preferred":[
        "Shalqun"
    ],
    "name:swe_x_preferred":[
        "Sh\u0101lq\u016bn"
    ],
    "name:und_x_variant":[
        "Shelgun"
    ],
    "wof:name":"Shalqun",
    "wof:placetype":"locality"
},
  "geometry": {"coordinates":[47.6158,37.8155],"type":"Point"}
}