{
  "type": "Feature",
  "properties": {
    "gn:admin1_code":"41",
    "gn:asciiname":"Naduk",
    "gn:country_code":"IR",
    "gn:dem":2240,
    "gn:feature_class":"P",
    "gn:feature_code":"PPL",
    "gn:name":"N\u0101d\u016bk",
    "gn:population":0,
    "gn:timezone":"Asia/Tehran",
    "iso:country":"IR",
    "name:fas_x_preferred":[
        "Nabard\u016bk"
    ],
    "name:fas_x_variant":[
        "N\u0101d\u016bk",
        "\u0646\u0628\u0631\u062f\u0648\u06a9",
        "\u0646\u0627\u062f\u0648\u06a9",
        "\u0646\u0648\u062f\u0648\u06a9"
    ],
    "name:und_x_variant":[
        "\u0646\u0628\u0631\u062f\u0648\u06a9",
        "Nowd\u016bk"
    ],
    "wof:name":"Naduk",
    "wof:placetype":"locality"
},
  "geometry": {"coordinates":[59.24188,32.7514],"type":"Point"}
}