{
  "type": "Feature",
  "properties": {
    "gn:admin1_code":"8.0",
    "gn:asciiname":"Bala Mahalleh-ye Zakelbar",
    "gn:country_code":"IR",
    "gn:dem":114,
    "gn:feature_class":"P",
    "gn:feature_code":"PPL",
    "gn:name":"B\u0101l\u0101 Ma\u1e29alleh-ye Z\u0304\u0101kelbar",
    "gn:population":0,
    "gn:timezone":"Asia/Tehran",
    "iso:country":"IR",
    "name:fas_x_preferred":[
        "\u0628\u0627\u0644\u0627 \u0645\u062d\u0644\u0647 \u0630\u0627\u06a9\u0644\u0628\u0631"
    ],
    "name:fas_x_variant":[
        "\u0632\u0627\u06a9\u0644\u0628\u0631"
    ],
    "name:und_x_variant":[
        "B\u0101l\u0101 Ma\u1e29alleh-ye Z\u0304\u0101kelbar",
        "Z\u0101klebar"
    ],
    "wof:name":"Bala Mahalleh-ye Zakelbar",
    "wof:placetype":"locality"
},
  "geometry": {"coordinates":[49.99703,37.13223],"type":"Point"}
}