{
  "type": "Feature",
  "properties": {
    "gn:admin1_code":"25.0",
    "gn:asciiname":"Armian",
    "gn:country_code":"IR",
    "gn:dem":1431,
    "gn:feature_class":"P",
    "gn:feature_code":"PPL",
    "gn:name":"Arm\u012b\u0101n",
    "gn:population":0,
    "gn:timezone":"Asia/Tehran",
    "iso:country":"IR",
    "name:fas_x_preferred":[
        "Arm\u012b\u0101n"
    ],
    "name:fas_x_variant":[
        "\u0627\u0631\u0645\u064a\u0627\u0646"
    ],
    "name:und_x_variant":[
        "\u0100rm\u012by\u0101n",
        "\u0100rmey\u0101n"
    ],
    "wof:name":"Armian",
    "wof:placetype":"locality"
},
  "geometry": {"coordinates":[55.40269,36.35978],"type":"Point"}
}