{
  "type": "Feature",
  "properties": {
    "gn:admin1_code":"13",
    "gn:asciiname":"Vara",
    "gn:country_code":"IR",
    "gn:dem":968,
    "gn:feature_class":"P",
    "gn:feature_code":"PPL",
    "gn:name":"Var\u0101",
    "gn:population":0,
    "gn:timezone":"Asia/Tehran",
    "iso:country":"IR",
    "name:cat_x_preferred":[
        "Vara"
    ],
    "name:ceb_x_preferred":[
        "Vara"
    ],
    "name:deu_x_preferred":[
        "Vara"
    ],
    "name:epo_x_preferred":[
        "Vara"
    ],
    "name:est_x_preferred":[
        "Vara"
    ],
    "name:fas_x_preferred":[
        "\u0648\u0631\u0627"
    ],
    "name:fas_x_variant":[
        "Var\u0101"
    ],
    "name:fin_x_preferred":[
        "Vara"
    ],
    "name:fra_x_preferred":[
        "Vara"
    ],
    "name:ita_x_preferred":[
        "Vara"
    ],
    "name:lim_x_preferred":[
        "Vara"
    ],
    "name:nld_x_preferred":[
        "Vara"
    ],
    "name:nno_x_preferred":[
        "Vara"
    ],
    "name:por_x_preferred":[
        "Vara"
    ],
    "name:ron_x_preferred":[
        "Vara"
    ],
    "name:rus_x_preferred":[
        "\u0412\u0430\u0440\u0430"
    ],
    "name:sco_x_preferred":[
        "Vara"
    ],
    "name:spa_x_preferred":[
        "Vara"
    ],
    "name:swe_x_preferred":[
        "Vara"
    ],
    "name:ukr_x_preferred":[
        "\u0412\u0430\u0440\u0430"
    ],
    "name:und_x_variant":[
        "Garra",
        "Vorr\u0101\u2019",
        "G\u0101r\u0101",
        "Vara"
    ],
    "wof:name":"Vara",
    "wof:placetype":"locality"
},
  "geometry": {"coordinates":[46.3006,35.1369],"type":"Point"}
}