{
  "type": "Feature",
  "properties": {
    "gn:admin1_code":"13",
    "gn:asciiname":"Vara",
    "gn:country_code":"IR",
    "gn:dem":968,
    "gn:feature_class":"P",
    "gn:feature_code":"PPL",
    "gn:name":"Var\u0101",
    "gn:population":0,
    "gn:timezone":"Asia/Tehran",
    "iso:country":"IR",
    "name:fas_x_preferred":[
        "\u0648\u0631\u0627"
    ],
    "name:fas_x_variant":[
        "Var\u0101"
    ],
    "name:und_x_variant":[
        "Garra",
        "Vorr\u0101\u2019",
        "G\u0101r\u0101",
        "Vara"
    ],
    "wof:name":"Vara",
    "wof:placetype":"locality"
},
  "geometry": {"coordinates":[46.3006,35.1369],"type":"Point"}
}