{
  "type": "Feature",
  "properties": {
    "gn:admin1_code":"33",
    "gn:asciiname":"Qulan",
    "gn:country_code":"IR",
    "gn:dem":496,
    "gn:feature_class":"P",
    "gn:feature_code":"PPL",
    "gn:name":"Q\u016bl\u0101n",
    "gn:population":0,
    "gn:timezone":"Asia/Tehran",
    "iso:country":"IR",
    "name:fas_x_preferred":[
        "\u0642\u0648\u0644\u0627\u0646"
    ],
    "name:fas_x_variant":[
        "Q\u016bl\u0101n",
        "\u063a\u064f\u0651\u0644\u064e\u0646",
        "\u0642\u064f\u0644\u0627\u0646"
    ],
    "name:und_x_variant":[
        "Kulan",
        "Ghoolan",
        "Qol\u0101n"
    ],
    "wof:name":"Qulan",
    "wof:placetype":"locality"
},
  "geometry": {"coordinates":[46.3981,38.894],"type":"Point"}
}