{
  "type": "Feature",
  "properties": {
    "gn:admin1_code":"5",
    "gn:asciiname":"Chat Barik",
    "gn:country_code":"IR",
    "gn:dem":2155,
    "gn:feature_class":"P",
    "gn:feature_code":"PPL",
    "gn:name":"Ch\u0101t B\u0101r\u012bk",
    "gn:population":0,
    "gn:timezone":"Asia/Tehran",
    "iso:country":"IR",
    "name:fas_x_preferred":[
        "Ch\u0101t B\u0101r\u012bk"
    ],
    "name:fas_x_variant":[
        "\u0686\u0627\u062a \u0628\u0627\u0631\u06cc\u06a9"
    ],
    "wof:name":"Chat Barik",
    "wof:placetype":"locality"
},
  "geometry": {"coordinates":[51.56618,30.53383],"type":"Point"}
}