{
  "type": "Feature",
  "properties": {
    "gn:admin1_code":"42",
    "gn:asciiname":"Dowgha'i",
    "gn:country_code":"IR",
    "gn:dem":1439,
    "gn:feature_class":"P",
    "gn:feature_code":"PPL",
    "gn:name":"Dowgh\u0101\u2019\u012b",
    "gn:population":0,
    "gn:timezone":"Asia/Tehran",
    "iso:country":"IR",
    "name:fas_x_preferred":[
        "\u062f\u0648\u063a\u0627\u0626\u06cc"
    ],
    "name:fas_x_variant":[
        "Dowgh\u0101\u2019\u012b"
    ],
    "name:und_x_variant":[
        "Dughai",
        "Doq\u0101\u2019\u012b",
        "D\u016bgh\u0101n\u012b",
        "Dowq\u0101\u2019\u012b"
    ],
    "wof:name":"Dowgha'i",
    "wof:placetype":"locality"
},
  "geometry": {"coordinates":[58.58188000000001,36.91257],"type":"Point"}
}