{
  "type": "Feature",
  "properties": {
    "gn:admin1_code":"42",
    "gn:asciiname":"Barqi",
    "gn:country_code":"IR",
    "gn:dem":975,
    "gn:feature_class":"P",
    "gn:feature_code":"PPL",
    "gn:name":"Barq\u012b",
    "gn:population":0,
    "gn:timezone":"Asia/Tehran",
    "iso:country":"IR",
    "name:fas_x_preferred":[
        "\u0628\u0631\u0642\u06cc"
    ],
    "name:fas_x_variant":[
        "Barq\u012b"
    ],
    "name:und_x_variant":[
        "Qarq\u012b"
    ],
    "wof:name":"Barqi",
    "wof:placetype":"locality"
},
  "geometry": {"coordinates":[59.6912,36.3952],"type":"Point"}
}