{
  "type": "Feature",
  "properties": {
    "gn:admin1_code":"9",
    "gn:asciiname":"Jereya",
    "gn:country_code":"IR",
    "gn:dem":1645,
    "gn:feature_class":"P",
    "gn:feature_code":"PPL",
    "gn:name":"Jerey\u0101",
    "gn:population":0,
    "gn:timezone":"Asia/Tehran",
    "iso:country":"IR",
    "name:ceb_x_preferred":[
        "Jar\u012b\u0101"
    ],
    "name:fas_x_preferred":[
        "Jar\u012b\u0101"
    ],
    "name:fas_x_variant":[
        "\u062c\u0631\u06cc\u0627",
        "\u062d\u062f\u06cc\u0651\u0627"
    ],
    "name:msa_x_preferred":[
        "Jaria"
    ],
    "name:swe_x_preferred":[
        "Jar\u012b\u0101"
    ],
    "name:und_x_variant":[
        "Girya",
        "Jerey\u0101",
        "Girieh",
        "Jery\u0101",
        "G\u012bryeh",
        "\u1e28odyy\u0101"
    ],
    "name:urd_x_preferred":[
        "\u062c\u0631\u06cc\u0627"
    ],
    "wof:name":"Jereya",
    "wof:placetype":"locality"
},
  "geometry": {"coordinates":[48.47304000000001,34.35207],"type":"Point"}
}