{
  "type": "Feature",
  "properties": {
    "gn:admin1_code":"1.0",
    "gn:asciiname":"Valiv",
    "gn:country_code":"IR",
    "gn:dem":1247,
    "gn:feature_class":"P",
    "gn:feature_code":"PPL",
    "gn:name":"V\u0101l\u012bv",
    "gn:population":0,
    "gn:timezone":"Asia/Tehran",
    "iso:country":"IR",
    "name:fas_x_preferred":[
        "\u0648\u0627\u0644\u06cc\u0648"
    ],
    "name:fas_x_variant":[
        "V\u0101l\u012bv"
    ],
    "wof:name":"Valiv",
    "wof:placetype":"locality"
},
  "geometry": {"coordinates":[45.5217,36.2889],"type":"Point"}
}