{
  "type": "Feature",
  "properties": {
    "gn:admin1_code":"7",
    "gn:asciiname":"Reza",
    "gn:country_code":"IR",
    "gn:dem":1750,
    "gn:feature_class":"P",
    "gn:feature_code":"PPL",
    "gn:name":"Re\u1e95\u0101",
    "gn:population":0,
    "gn:timezone":"Asia/Tehran",
    "iso:country":"IR",
    "name:fas_x_preferred":[
        "Re\u1e95\u0101"
    ],
    "wof:name":"Reza",
    "wof:placetype":"locality"
},
  "geometry": {"coordinates":[51.44139000000001,30.37917],"type":"Point"}
}