{
  "type": "Feature",
  "properties": {
    "gn:admin1_code":"4",
    "gn:asciiname":"Chahuk",
    "gn:country_code":"IR",
    "gn:dem":941,
    "gn:feature_class":"P",
    "gn:feature_code":"PPL",
    "gn:name":"Ch\u0101h\u016bk",
    "gn:population":0,
    "gn:timezone":"Asia/Tehran",
    "iso:country":"IR",
    "name:fas_x_preferred":[
        "\u0686\u0627\u0647\u0648\u06a9"
    ],
    "name:fas_x_variant":[
        "Ch\u0101h\u016bk"
    ],
    "wof:name":"Chahuk",
    "wof:placetype":"locality"
},
  "geometry": {"coordinates":[59.87992,27.79891],"type":"Point"}
}