{
  "type": "Feature",
  "properties": {
    "gn:admin1_code":"29",
    "gn:asciiname":"Donbeh-ye Bala",
    "gn:country_code":"IR",
    "gn:dem":2110,
    "gn:feature_class":"P",
    "gn:feature_code":"PPL",
    "gn:name":"Donbeh-ye B\u0101l\u0101",
    "gn:population":0,
    "gn:timezone":"Asia/Tehran",
    "iso:country":"IR",
    "name:fas_x_preferred":[
        "\u062f\u0646\u0628\u0647 \u0628\u0627\u0644\u0627"
    ],
    "name:fas_x_variant":[
        "Donbeh-ye B\u0101l\u0101",
        "\u062f\u0646\u0628\u0647 \u0639\u0644\u064a\u0627"
    ],
    "name:und_x_variant":[
        "Donbeh-ye \u2018Oly\u0101"
    ],
    "wof:name":"Donbeh-ye Bala",
    "wof:placetype":"locality"
},
  "geometry": {"coordinates":[55.499,30.1938],"type":"Point"}
}