{
  "type": "Feature",
  "properties": {
    "gn:admin1_code":"32",
    "gn:asciiname":"Berni Balanga",
    "gn:country_code":"IR",
    "gn:dem":1838,
    "gn:feature_class":"P",
    "gn:feature_code":"PPL",
    "gn:name":"Bern\u012b Balang\u0101",
    "gn:population":0,
    "gn:timezone":"Asia/Tehran",
    "iso:country":"IR",
    "name:fas_x_preferred":[
        "\u0628\u0631\u06cc\u0645 \u0628\u0644\u0646\u06af\u0627"
    ],
    "name:fas_x_variant":[
        "Ber\u012bm Balang\u0101",
        "\u0628\u0631\u0646\u06cc \u0628\u0644\u0646\u06af\u0627"
    ],
    "name:und_x_variant":[
        "Bern\u012b Balang\u0101"
    ],
    "wof:name":"Berni Balanga",
    "wof:placetype":"locality"
},
  "geometry": {"coordinates":[48.89364000000001,37.31747],"type":"Point"}
}