{
  "type": "Feature",
  "properties": {
    "gn:admin1_code":"16",
    "gn:asciiname":"Dadaneh Kamangir",
    "gn:country_code":"IR",
    "gn:dem":1554,
    "gn:feature_class":"P",
    "gn:feature_code":"PPL",
    "gn:name":"D\u0101d\u0101neh Kam\u0101ng\u012br",
    "gn:population":0,
    "gn:timezone":"Asia/Tehran",
    "iso:country":"IR",
    "name:ceb_x_preferred":[
        "D\u0101d\u0101neh Kam\u0101ng\u012br"
    ],
    "name:ckb_x_preferred":[
        "\u062f\u0627\u062f\u0627\u0646\u06d5\u06cc \u06a9\u06d5\u0645\u0627\u0646\u06af\u06d5\u0631"
    ],
    "name:fas_x_preferred":[
        "\u062f\u064f\u0648\u062f\u0627\u0646\u0650\u06c0 \u062f\u064e\u0631\u0650\u0651\u0644\u064e\u0647"
    ],
    "name:fas_x_variant":[
        "\u062f\u064e\u062f\u064e\u0646\u0650\u0647",
        "D\u0101d\u0101neh-ye Kam\u0101ngar",
        "\u062f\u0627\u062f\u0627\u0646\u0647 \u06a9\u0645\u0627\u0646\u06af\u0631",
        "D\u0101d\u0101neh Kam\u0101ngar",
        "\u062f\u0627\u062f\u0627\u0646\u0647 \u06a9\u0645\u0627\u0646\u06af\u064a\u0631"
    ],
    "name:kur_x_preferred":[
        "Dadaney Kemanger"
    ],
    "name:swe_x_preferred":[
        "D\u0101d\u0101neh Kam\u0101ng\u012br"
    ],
    "name:und_x_variant":[
        "Dowd\u0101neh-ye Darrelah",
        "Dadaneh"
    ],
    "wof:name":"Dadaneh Kamangir",
    "wof:placetype":"locality"
},
  "geometry": {"coordinates":[46.6324,35.3109],"type":"Point"}
}