{
  "type": "Feature",
  "properties": {
    "gn:admin1_code":"44",
    "gn:asciiname":"Qeshlaq-e Inalu-ye Yaghmarlu",
    "gn:country_code":"IR",
    "gn:dem":1179,
    "gn:feature_class":"P",
    "gn:feature_code":"PPL",
    "gn:name":"Qeshl\u0101q-e \u012an\u0101l\u016b-ye Yaghmarl\u016b",
    "gn:population":0,
    "gn:timezone":"Asia/Tehran",
    "iso:country":"IR",
    "name:fas_x_preferred":[
        "Qeshl\u0101q-e \u012an\u0101l\u016b-ye Yaghmarl\u016b"
    ],
    "wof:name":"Qeshlaq-e Inalu-ye Yaghmarlu",
    "wof:placetype":"locality"
},
  "geometry": {"coordinates":[50.25,35.75],"type":"Point"}
}