{
  "type": "Feature",
  "properties": {
    "gn:admin1_code":"36",
    "gn:asciiname":"Chahar Taq",
    "gn:country_code":"IR",
    "gn:dem":1942,
    "gn:feature_class":"P",
    "gn:feature_code":"PPL",
    "gn:name":"Chah\u0101r \u0162\u0101q",
    "gn:population":0,
    "gn:timezone":"Asia/Tehran",
    "iso:country":"IR",
    "name:fas_x_preferred":[
        "\u0686\u0647\u0627\u0631 \u0637\u0627\u0642"
    ],
    "name:fas_x_variant":[
        "Chah\u0101r \u0162\u0101q"
    ],
    "wof:name":"Chahar Taq",
    "wof:placetype":"locality"
},
  "geometry": {"coordinates":[47.75899999999999,36.42788],"type":"Point"}
}