{
  "type": "Feature",
  "properties": {
    "gn:admin1_code":"15",
    "gn:asciiname":"Masiri",
    "gn:country_code":"IR",
    "gn:dem":474,
    "gn:feature_class":"P",
    "gn:feature_code":"PPL",
    "gn:name":"Mas\u012br\u012b",
    "gn:population":0,
    "gn:timezone":"Asia/Tehran",
    "iso:country":"IR",
    "name:ara_x_preferred":[
        "\u0645\u0635\u064a\u0631\u064a"
    ],
    "name:aze_x_preferred":[
        "M\u0259siri"
    ],
    "name:ceb_x_preferred":[
        "Ma\u015f\u012br\u012b"
    ],
    "name:fas_x_preferred":[
        "\u0645\u0633\u06cc\u0631\u06cc"
    ],
    "name:fas_x_variant":[
        "Mas\u012br\u012b",
        "\u1e28ow\u1e95-e M\u0101h\u012b",
        "\u0645\u0635\u06cc\u0631\u06cc"
    ],
    "name:ita_x_preferred":[
        "Mosiri"
    ],
    "name:mlg_x_preferred":[
        "Masiri"
    ],
    "name:msa_x_preferred":[
        "Masiri"
    ],
    "name:rus_x_preferred":[
        "\u041c\u0430\u0441\u0438\u0440\u0438"
    ],
    "name:swe_x_preferred":[
        "Ma\u015f\u012br\u012b"
    ],
    "name:tur_x_preferred":[
        "Mesiri"
    ],
    "name:urd_x_preferred":[
        "\u0645\u0635\u06cc\u0631\u06cc"
    ],
    "name:zho_x_preferred":[
        "\u99ac\u897f\u91cc"
    ],
    "wof:name":"Masiri",
    "wof:placetype":"locality"
},
  "geometry": {"coordinates":[50.1831,30.8387],"type":"Point"}
}