{
  "type": "Feature",
  "properties": {
    "gn:admin1_code":"28",
    "gn:asciiname":"Sokkan",
    "gn:country_code":"IR",
    "gn:dem":2415,
    "gn:feature_class":"P",
    "gn:feature_code":"PPL",
    "gn:name":"Sokk\u0101n",
    "gn:population":0,
    "gn:timezone":"Asia/Tehran",
    "iso:country":"IR",
    "name:ara_x_preferred":[
        "\u0633\u0643\u0627\u0646"
    ],
    "name:fas_x_preferred":[
        "Sokk\u0101n"
    ],
    "name:fas_x_variant":[
        "\u0633\u06a9\u0627\u0646"
    ],
    "name:und_x_variant":[
        "Sak\u0101n",
        "Sok\u016bn",
        "Seh G\u0101neh",
        "Sok\u0101neh",
        "Sakun",
        "\u0633\u06a9\u0627\u0646"
    ],
    "wof:name":"Sokkan",
    "wof:placetype":"locality"
},
  "geometry": {"coordinates":[49.84993,33.00876],"type":"Point"}
}