{
  "type": "Feature",
  "properties": {
    "gn:admin1_code":"35",
    "gn:asciiname":"Bala Helal Kola",
    "gn:country_code":"IR",
    "gn:dem":3,
    "gn:feature_class":"P",
    "gn:feature_code":"PPL",
    "gn:name":"B\u0101l\u0101 Hel\u0101l Kol\u0101",
    "gn:population":0,
    "gn:timezone":"Asia/Tehran",
    "iso:country":"IR",
    "name:fas_x_preferred":[
        "\u0628\u0627\u0644\u0627 \u0647\u0650\u0644\u0627\u0644 \u0643\u064f\u0644\u0627"
    ],
    "name:fas_x_variant":[
        "B\u0101l\u0101 Hel\u0101l Kol\u0101"
    ],
    "wof:name":"Bala Helal Kola",
    "wof:placetype":"locality"
},
  "geometry": {"coordinates":[52.53333000000001,36.51667],"type":"Point"}
}