{
  "type": "Feature",
  "properties": {
    "gn:admin1_code":"38.0",
    "gn:asciiname":"Altin Kosh",
    "gn:country_code":"IR",
    "gn:dem":559,
    "gn:feature_class":"P",
    "gn:feature_code":"PPL",
    "gn:name":"\u0100lt\u012bn Kosh",
    "gn:population":0,
    "gn:timezone":"Asia/Tehran",
    "iso:country":"IR",
    "name:fas_x_preferred":[
        "\u0622\u0644\u062a\u064a\u0646 \u0643\u0634"
    ],
    "name:fas_x_variant":[
        "\u0100lt\u012bn Kosh"
    ],
    "name:und_x_variant":[
        "Altunkush",
        "Alt\u016bnkosh"
    ],
    "wof:name":"Altin Kosh",
    "wof:placetype":"locality"
},
  "geometry": {"coordinates":[49.13625,36.72473],"type":"Point"}
}