{
  "type": "Feature",
  "properties": {
    "gn:admin1_code":"15",
    "gn:asciiname":"Julagi",
    "gn:country_code":"IR",
    "gn:dem":183,
    "gn:feature_class":"P",
    "gn:feature_code":"PPL",
    "gn:name":"J\u016blag\u012b",
    "gn:population":0,
    "gn:timezone":"Asia/Tehran",
    "iso:country":"IR",
    "name:fas_x_preferred":[
        "\u062c\u0648\u0644\u06a9\u06cc"
    ],
    "name:fas_x_variant":[
        "J\u016blak\u012b",
        "\u062c\u0648\u0644\u06af\u06cc"
    ],
    "name:und_x_variant":[
        "J\u016blek\u012b",
        "J\u016blag\u012b"
    ],
    "wof:name":"Julagi",
    "wof:placetype":"locality"
},
  "geometry": {"coordinates":[49.88616,30.82065],"type":"Point"}
}