{
  "type": "Feature",
  "properties": {
    "gn:admin1_code":"15.0",
    "gn:asciiname":"Fiyeh Shavardi",
    "gn:country_code":"IR",
    "gn:dem":6,
    "gn:feature_class":"P",
    "gn:feature_code":"PPL",
    "gn:name":"F\u012byeh Sh\u0101vard\u012b",
    "gn:population":0,
    "gn:timezone":"Asia/Tehran",
    "iso:country":"IR",
    "name:fas_x_preferred":[
        "\u0641\u06cc\u0647 \u0634\u0627\u0648\u0631\u062f\u06cc"
    ],
    "name:und_x_variant":[
        "F\u012byeh Sh\u0101vard\u012b"
    ],
    "wof:name":"Fiyeh Shavardi",
    "wof:placetype":"locality"
},
  "geometry": {"coordinates":[48.6089,30.61717],"type":"Point"}
}