{
  "type": "Feature",
  "properties": {
    "gn:admin1_code":"7",
    "gn:asciiname":"Gaz-e Kheng",
    "gn:country_code":"IR",
    "gn:dem":2127,
    "gn:feature_class":"P",
    "gn:feature_code":"PPL",
    "gn:name":"Gaz-e Kheng",
    "gn:population":0,
    "gn:timezone":"Asia/Tehran",
    "iso:country":"IR",
    "name:ara_x_preferred":[
        "\u063a\u0632 \u062e\u0646\u063a"
    ],
    "name:fas_x_preferred":[
        "\u06af\u0632 \u062e\u0646\u06af"
    ],
    "name:fas_x_variant":[
        "\u06af\u0632\u062e\u0646\u06af"
    ],
    "name:msa_x_preferred":[
        "Gaz-e Kheng"
    ],
    "name:und_x_variant":[
        "Gaz-e Khong",
        "B\u012bd-e S\u016bkhteh"
    ],
    "wof:name":"Gaz-e Kheng",
    "wof:placetype":"locality"
},
  "geometry": {"coordinates":[53.51404,30.20063],"type":"Point"}
}