{
  "type": "Feature",
  "properties": {
    "gn:admin1_code":"11",
    "gn:asciiname":"Posht Pari",
    "gn:country_code":"IR",
    "gn:dem":865,
    "gn:feature_class":"P",
    "gn:feature_code":"PPL",
    "gn:name":"Posht Par\u012b",
    "gn:population":0,
    "gn:timezone":"Asia/Tehran",
    "iso:country":"IR",
    "name:fas_x_preferred":[
        "\u067e\u0634\u062a \u067e\u0631\u06cc"
    ],
    "name:fas_x_variant":[
        "Posht Par\u012b"
    ],
    "name:msa_x_preferred":[
        "Posht Pari"
    ],
    "wof:name":"Posht Pari",
    "wof:placetype":"locality"
},
  "geometry": {"coordinates":[56.6133,27.7797],"type":"Point"}
}