{
  "type": "Feature",
  "properties": {
    "gn:admin1_code":"15",
    "gn:asciiname":"Sa`idiyeh",
    "gn:country_code":"IR",
    "gn:dem":16,
    "gn:feature_class":"P",
    "gn:feature_code":"PPL",
    "gn:name":"Sa\u2018\u012bd\u012byeh",
    "gn:population":0,
    "gn:timezone":"Asia/Tehran",
    "iso:country":"IR",
    "name:fas_x_preferred":[
        "\u0633\u0639\u06cc\u062f\u06cc\u0651\u0647"
    ],
    "name:und_x_variant":[
        "Seyyedeh",
        "Sa\u2018\u012bd\u012byeh"
    ],
    "wof:name":"Sa`idiyeh",
    "wof:placetype":"locality"
},
  "geometry": {"coordinates":[48.2558,31.3799],"type":"Point"}
}