{
  "type": "Feature",
  "properties": {
    "gn:admin1_code":"25.0",
    "gn:asciiname":"Ebrahimabad-e `Olya",
    "gn:country_code":"IR",
    "gn:dem":1072,
    "gn:feature_class":"P",
    "gn:feature_code":"PPL",
    "gn:name":"Ebr\u0101h\u012bm\u0101b\u0101d-e \u2018Oly\u0101",
    "gn:population":0,
    "gn:timezone":"Asia/Tehran",
    "iso:country":"IR",
    "name:fas_x_preferred":[
        "\u0627\u0650\u0628\u0631\u0627\u0647\u064a\u0645\u0627\u0628\u0627\u062f\u0650 \u067e\u0627\u0626\u064a\u0646"
    ],
    "name:fas_x_variant":[
        "Ebr\u0101h\u012bm\u0101b\u0101d-e P\u0101\u2019\u012bn",
        "Ebr\u0101h\u012bm\u0101b\u0101d",
        "\u0627\u0628\u0631\u0627\u0647\u06cc\u0645 \u0622\u0628\u0627\u062f",
        "\u0627\u0628\u0631\u0627\u0647\u06cc\u0645 \u0622\u0628\u0627\u062f \u0639\u0644\u06cc\u0627"
    ],
    "name:und_x_variant":[
        "Ebr\u0101h\u012bm\u0101b\u0101d-e \u2018Oly\u0101"
    ],
    "wof:name":"Ebrahimabad-e `Olya",
    "wof:placetype":"locality"
},
  "geometry": {"coordinates":[55.72389,36.41542000000001],"type":"Point"}
}