{
  "type": "Feature",
  "properties": {
    "gn:admin1_code":"29",
    "gn:asciiname":"Rigak",
    "gn:country_code":"IR",
    "gn:dem":381,
    "gn:feature_class":"P",
    "gn:feature_code":"PPL",
    "gn:name":"R\u012bgak",
    "gn:population":0,
    "gn:timezone":"Asia/Tehran",
    "iso:country":"IR",
    "name:fas_x_preferred":[
        "\u0631\u06cc\u06af\u06a9"
    ],
    "name:fas_x_variant":[
        "R\u012bgak"
    ],
    "wof:name":"Rigak",
    "wof:placetype":"locality"
},
  "geometry": {"coordinates":[58.68576,27.76954000000001],"type":"Point"}
}