{
  "type": "Feature",
  "properties": {
    "gn:admin1_code":"32",
    "gn:asciiname":"Melli Kandi",
    "gn:country_code":"IR",
    "gn:dem":874,
    "gn:feature_class":"P",
    "gn:feature_code":"PPL",
    "gn:name":"Mell\u012b Kand\u012b",
    "gn:population":0,
    "gn:timezone":"Asia/Tehran",
    "iso:country":"IR",
    "name:ara_x_preferred":[
        "\u0645\u0644\u064a \u06a9\u0646\u062f\u064a"
    ],
    "name:fas_x_preferred":[
        "\u0645\u0644\u06cc \u0643\u0646\u062f\u06cc"
    ],
    "name:fas_x_variant":[
        "Mell\u012b Kand\u012b",
        "\u0645\u0644\u06cc \u06a9\u0646\u062f\u06cc"
    ],
    "name:msa_x_preferred":[
        "Melli Kandi"
    ],
    "wof:name":"Melli Kandi",
    "wof:placetype":"locality"
},
  "geometry": {"coordinates":[47.7369,39.1938],"type":"Point"}
}