{
  "type": "Feature",
  "properties": {
    "gn:admin1_code":"9",
    "gn:asciiname":"Morghabad",
    "gn:country_code":"IR",
    "gn:dem":1726,
    "gn:feature_class":"P",
    "gn:feature_code":"PPL",
    "gn:name":"Morgh\u0101b\u0101d",
    "gn:population":0,
    "gn:timezone":"Asia/Tehran",
    "iso:country":"IR",
    "name:ara_x_preferred":[
        "\u0645\u0631\u063a\u200c\u0622\u0628\u0627\u062f"
    ],
    "name:ceb_x_preferred":[
        "Morgh\u0101b\u0101d"
    ],
    "name:fas_x_preferred":[
        "\u0645\u0631\u063a \u0622\u0628\u0627\u062f"
    ],
    "name:fas_x_variant":[
        "Morgh\u0101b\u0101d",
        "\u0645\u0631\u063a\u200c\u0622\u0628\u0627\u062f"
    ],
    "name:msa_x_preferred":[
        "Morghabad"
    ],
    "name:swe_x_preferred":[
        "Morgh\u0101b\u0101d"
    ],
    "name:und_x_variant":[
        "Murgh\u0101b\u0101d"
    ],
    "wof:name":"Morghabad",
    "wof:placetype":"locality"
},
  "geometry": {"coordinates":[49.2827,35.18897],"type":"Point"}
}