{
  "type": "Feature",
  "properties": {
    "gn:admin1_code":"33",
    "gn:asciiname":"Jarayeh",
    "gn:country_code":"IR",
    "gn:dem":1200,
    "gn:feature_class":"P",
    "gn:feature_code":"PPL",
    "gn:name":"Jar\u0101yeh",
    "gn:population":0,
    "gn:timezone":"Asia/Tehran",
    "iso:country":"IR",
    "name:fas_x_preferred":[
        "Jar\u0101yeh"
    ],
    "wof:name":"Jarayeh",
    "wof:placetype":"locality"
},
  "geometry": {"coordinates":[47.86667,37.53333],"type":"Point"}
}