{
  "type": "Feature",
  "properties": {
    "gn:admin1_code":"33",
    "gn:asciiname":"Yengi Kand",
    "gn:country_code":"IR",
    "gn:dem":1441,
    "gn:feature_class":"P",
    "gn:feature_code":"PPL",
    "gn:name":"Yeng\u012b Kand",
    "gn:population":0,
    "gn:timezone":"Asia/Tehran",
    "iso:country":"IR",
    "name:fas_x_preferred":[
        "\u06cc\u0646\u06af\u0647 \u06a9\u0646\u062f"
    ],
    "name:fas_x_variant":[
        "Yeng\u012b Kand\u012b",
        "\u06cc\u0646\u06af\u06cc \u06a9\u0646\u062f"
    ],
    "name:und_x_variant":[
        "Yeng\u012b",
        "Yengeh Kand",
        "Yeng\u012b Kand"
    ],
    "wof:name":"Yengi Kand",
    "wof:placetype":"locality"
},
  "geometry": {"coordinates":[48.0211,37.17792],"type":"Point"}
}