{
  "type": "Feature",
  "properties": {
    "gn:admin1_code":"7.0",
    "gn:asciiname":"Esma`ilabad-e Darengun",
    "gn:country_code":"IR",
    "gn:dem":1792,
    "gn:feature_class":"P",
    "gn:feature_code":"PPL",
    "gn:name":"Esm\u0101\u2018\u012bl\u0101b\u0101d-e D\u0101reng\u016bn",
    "gn:population":0,
    "gn:timezone":"Asia/Tehran",
    "iso:country":"IR",
    "name:fas_x_preferred":[
        "\u0627\u0633\u0645\u0627\u0639\u06cc\u0644 \u0622\u0628\u0627\u062f \u062f\u0627\u0631\u0646\u06af\u0648\u0646"
    ],
    "name:fas_x_variant":[
        "Esm\u0101\u2018\u012bl\u0101b\u0101d-e D\u0101reng\u016bn"
    ],
    "wof:name":"Esma`ilabad-e Darengun",
    "wof:placetype":"locality"
},
  "geometry": {"coordinates":[52.343,29.4186],"type":"Point"}
}