{
  "type": "Feature",
  "properties": {
    "gn:admin1_code":"5",
    "gn:asciiname":"Jan Khani",
    "gn:country_code":"IR",
    "gn:dem":665,
    "gn:feature_class":"P",
    "gn:feature_code":"PPL",
    "gn:name":"J\u0101n Kh\u0101n\u012b",
    "gn:population":0,
    "gn:timezone":"Asia/Tehran",
    "iso:country":"IR",
    "name:ceb_x_preferred":[
        "Q\u012b\u0101m"
    ],
    "name:fas_x_preferred":[
        "\u0642\u064a\u0627\u0645"
    ],
    "name:fas_x_variant":[
        "Q\u012b\u0101m",
        "\u062c\u0627\u0646 \u062e\u0627\u0646\u06cc"
    ],
    "name:swe_x_preferred":[
        "Q\u012b\u0101m"
    ],
    "name:und_x_variant":[
        "J\u0101n Kh\u0101n\u012b",
        "Qey\u0101m",
        "Jah\u0101n Kh\u0101n\u012b"
    ],
    "name:urd_x_preferred":[
        "\u062c\u0627\u0646 \u062e\u0627\u0646\u06cc"
    ],
    "wof:name":"Jan Khani",
    "wof:placetype":"locality"
},
  "geometry": {"coordinates":[50.2731,30.9271],"type":"Point"}
}