{
  "type": "Feature",
  "properties": {
    "gn:admin1_code":"40",
    "gn:asciiname":"Mahalleh-ye Amohsen",
    "gn:country_code":"IR",
    "gn:dem":2545,
    "gn:feature_class":"P",
    "gn:feature_code":"PPLF",
    "gn:name":"Ma\u1e29alleh-ye \u0100mo\u1e29sen",
    "gn:population":0,
    "gn:timezone":"Asia/Tehran",
    "iso:country":"IR",
    "name:fas_x_preferred":[
        "\u0622\u0645\u064f\u062d\u0633\u0650\u0646"
    ],
    "name:fas_x_variant":[
        "\u0100mo\u1e29sen",
        "Mazra\u2018eh-ye \u2018Am\u016b \u1e28oseyn",
        "\u0645\u0632\u0631\u0639\u0647 \u0639\u0645\u0648 \u062d\u0633\u064a\u0646",
        "\u0645\u062d\u0644\u0647 \u0622\u0645\u062d\u0633\u0646",
        "\u0645\u0632\u0631\u0639\u0647 \u0627\u0645\u062d\u0633\u0646"
    ],
    "name:und_x_variant":[
        "Ma\u1e29alleh-ye \u0100mo\u1e29sen",
        "Mazra\u2018eh-ye Amo\u1e29sen"
    ],
    "wof:name":"Mahalleh-ye Amohsen",
    "wof:placetype":"locality"
},
  "geometry": {"coordinates":[54.10968,31.59937],"type":"Point"}
}