{
  "type": "Feature",
  "properties": {
    "gn:admin1_code":"15",
    "gn:asciiname":"Na`miyeh-ye Naser",
    "gn:country_code":"IR",
    "gn:dem":2,
    "gn:feature_class":"P",
    "gn:feature_code":"PPL",
    "gn:name":"Na\u2018m\u012byeh-ye N\u0101\u015fer",
    "gn:population":0,
    "gn:timezone":"Asia/Tehran",
    "iso:country":"IR",
    "name:fas_x_preferred":[
        "\u0646\u0639\u0645\u06cc\u0647 \u0646\u0627\u0635\u0631"
    ],
    "name:fas_x_variant":[
        "Na\u2018\u012bm\u012byeh-ye Seyyed N\u0101\u015fer",
        "Na\u2018m\u012byeh-ye N\u0101\u015fer"
    ],
    "wof:name":"Na`miyeh-ye Naser",
    "wof:placetype":"locality"
},
  "geometry": {"coordinates":[48.1963,30.3509],"type":"Point"}
}