{
  "type": "Feature",
  "properties": {
    "gn:admin1_code":"23",
    "gn:asciiname":"Koleh Jub-e `Olya",
    "gn:country_code":"IR",
    "gn:dem":1742,
    "gn:feature_class":"P",
    "gn:feature_code":"PPL",
    "gn:name":"Koleh J\u016bb-e \u2018Oly\u0101",
    "gn:population":0,
    "gn:timezone":"Asia/Tehran",
    "iso:country":"IR",
    "name:fas_x_preferred":[
        "\u0643\u0644\u0647 \u062c\u0648\u0628 \u0639\u0644\u064a\u0627"
    ],
    "name:fas_x_variant":[
        "\u06a9\u0644\u0647 \u062c\u0648\u0628",
        "Koleh J\u016bb-e B\u0101l\u0101",
        "Kalleh J\u016bb"
    ],
    "name:und_x_variant":[
        "Kaleh Ch\u016bb",
        "Khaluju",
        "Koleh J\u016bb-e \u2018Oly\u0101"
    ],
    "wof:name":"Koleh Jub-e `Olya",
    "wof:placetype":"locality"
},
  "geometry": {"coordinates":[48.7611,33.5332],"type":"Point"}
}