{
  "type": "Feature",
  "properties": {
    "gn:admin1_code":"32",
    "gn:asciiname":"Golestan-e Sofla",
    "gn:country_code":"IR",
    "gn:dem":1878,
    "gn:feature_class":"P",
    "gn:feature_code":"PPL",
    "gn:name":"Golest\u0101n-e Sofl\u00e1",
    "gn:population":0,
    "gn:timezone":"Asia/Tehran",
    "iso:country":"IR",
    "name:fas_x_preferred":[
        "\u06af\u0644\u0633\u062a\u0627\u0646 \u067e\u0627\u0626\u064a\u0646"
    ],
    "name:fas_x_variant":[
        "Kalest\u0101n-e Sofl\u00e1",
        "Golest\u0101n-e P\u0101\u2019\u012bn",
        "\u06af\u0644\u0633\u062a\u0627\u0646 \u0633\u0641\u0644\u06cc"
    ],
    "name:und_x_variant":[
        "Kyal\u2019ston",
        "Golest\u0101n-e Sofl\u00e1"
    ],
    "wof:name":"Golestan-e Sofla",
    "wof:placetype":"locality"
},
  "geometry": {"coordinates":[48.54426,37.73973],"type":"Point"}
}