{
  "type": "Feature",
  "properties": {
    "iso:country":"IR",
    "name:ara_x_preferred":[
        "\u062e\u0627\u0634"
    ],
    "name:azb_x_preferred":[
        "\u062e\u0627\u0634"
    ],
    "name:aze_x_preferred":[
        "Xa\u015f"
    ],
    "name:ben_x_preferred":[
        "\u0996\u09be\u09b8"
    ],
    "name:chi_x_preferred":[
        "\u54c8\u4ec0"
    ],
    "name:dan_x_preferred":[
        "Khash"
    ],
    "name:dut_x_preferred":[
        "Khash"
    ],
    "name:eng_x_preferred":[
        "Khash"
    ],
    "name:fas_x_preferred":[
        "\u062e\u0627\u0634"
    ],
    "name:fas_x_variant":[
        "Kh\u0101sh",
        "V\u0101sht",
        "Kw\u0101sh"
    ],
    "name:fin_x_preferred":[
        "Khash"
    ],
    "name:fra_x_preferred":[
        "Khash"
    ],
    "name:fre_x_preferred":[
        "Khash"
    ],
    "name:gre_x_preferred":[
        "\u039a\u03b1\u03c2"
    ],
    "name:guj_x_preferred":[
        "\u0a96\u0abe\u0ab6"
    ],
    "name:hin_x_preferred":[
        "\u0916\u093e\u0936"
    ],
    "name:ind_x_preferred":[
        "Khash"
    ],
    "name:ita_x_preferred":[
        "Khash"
    ],
    "name:jpn_x_preferred":[
        "\u30cf\u30fc\u30b7\u30e5"
    ],
    "name:kan_x_preferred":[
        "\u0c96\u0cb6\u0ccd"
    ],
    "name:kor_x_preferred":[
        "\uce74\uc0ac\ud558"
    ],
    "name:lav_x_preferred":[
        "Ha\u0161a"
    ],
    "name:lit_x_preferred":[
        "Ka\u0161as"
    ],
    "name:mar_x_preferred":[
        "\u0916\u093e\u0936"
    ],
    "name:may_x_preferred":[
        "Khash"
    ],
    "name:mlg_x_preferred":[
        "Khash"
    ],
    "name:nob_x_preferred":[
        "Khash"
    ],
    "name:per_x_preferred":[
        "\u062e\u0627\u0634"
    ],
    "name:pol_x_preferred":[
        "Chasz"
    ],
    "name:por_x_preferred":[
        "Khash"
    ],
    "name:rus_x_preferred":[
        "\u0425\u0430\u0448"
    ],
    "name:sin_x_preferred":[
        "\u0d9b\u0dcf\u0dc1\u0dca"
    ],
    "name:spa_x_preferred":[
        "Khash"
    ],
    "name:swe_x_preferred":[
        "Kh\u0101sh"
    ],
    "name:tam_x_preferred":[
        "\u0b95\u0bbe\u0bb8\u0bcd"
    ],
    "name:tel_x_preferred":[
        "\u0c16\u0c3e\u0c38\u0c4d"
    ],
    "name:tha_x_preferred":[
        "\u0e04\u0e32\u0e0a\u0e39\u0e23\u0e34"
    ],
    "name:tur_x_preferred":[
        "Ha\u015f"
    ],
    "name:ukr_x_preferred":[
        "\u0425\u0430\u0448"
    ],
    "name:unk_x_variant":[
        "V\u0101sht"
    ],
    "name:urd_x_preferred":[
        "\u062e\u0627\u0634\u060c \u0627\u06cc\u0631\u0627\u0646"
    ],
    "name:vie_x_preferred":[
        "Khash"
    ],
    "name:zho_x_preferred":[
        "\u54c8\u4ec0"
    ],
    "qs:gn_country":"IR",
    "qs:gn_fcode":"PPL",
    "qs:gn_pop":69603,
    "qs:name":"Kavash",
    "qs:name_adm0":"Iran",
    "qs:name_adm1":"Sistan va Baluchestan",
    "qs:photos":0,
    "qs:photos_1k":0,
    "qs:photos_9k":1,
    "qs:photos_9r":1,
    "qs:photos_all":1,
    "qs:photos_sr":0,
    "qs:placetype":"Town",
    "qs:pop_sr":"8",
    "qs:woe_adm0":23424851,
    "wd:wordcount":260,
    "wof:name":"Kavash",
    "wof:placetype":"locality",
    "wof:population":69603
},
  "geometry": {"coordinates":[61.21582,28.22107],"type":"Point"}
}