{
  "type": "Feature",
  "properties": {
    "gn:admin1_code":"1.0",
    "gn:asciiname":"Petaklu",
    "gn:country_code":"IR",
    "gn:dem":1864,
    "gn:feature_class":"P",
    "gn:feature_code":"PPL",
    "gn:name":"Petakl\u016b",
    "gn:population":0,
    "gn:timezone":"Asia/Tehran",
    "iso:country":"IR",
    "name:aze_x_preferred":[
        "P\u0259t\u0259kli"
    ],
    "name:fas_x_preferred":[
        "\u067e\u062a\u06a9 \u0644\u0648"
    ],
    "name:fas_x_variant":[
        "Petakl\u016b",
        "\u067e\u062a\u06a9\u200c\u0644\u0648"
    ],
    "name:msa_x_preferred":[
        "Petaklu"
    ],
    "wof:name":"Petaklu",
    "wof:placetype":"locality"
},
  "geometry": {"coordinates":[46.72389,36.97044],"type":"Point"}
}