{
  "type": "Feature",
  "properties": {
    "gn:admin1_code":"10",
    "gn:asciiname":"Bi Shi",
    "gn:country_code":"IR",
    "gn:dem":1115,
    "gn:feature_class":"P",
    "gn:feature_code":"PPL",
    "gn:name":"B\u012b Sh\u012b",
    "gn:population":0,
    "gn:timezone":"Asia/Tehran",
    "iso:country":"IR",
    "name:fas_x_preferred":[
        "\u0628\u06cc \u0634\u06cc"
    ],
    "name:und_x_variant":[
        "B\u012b Sh\u012b"
    ],
    "wof:name":"Bi Shi",
    "wof:placetype":"locality"
},
  "geometry": {"coordinates":[47.4035,33.7891],"type":"Point"}
}