{
  "type": "Feature",
  "properties": {
    "gn:admin1_code":"23",
    "gn:asciiname":"Qapundar",
    "gn:country_code":"IR",
    "gn:dem":674,
    "gn:feature_class":"P",
    "gn:feature_code":"PPL",
    "gn:name":"Qap\u016bndar",
    "gn:population":0,
    "gn:timezone":"Asia/Tehran",
    "iso:country":"IR",
    "name:fas_x_preferred":[
        "\u0642\u064e\u067e\u0648\u0646\u062f\u064e\u0631"
    ],
    "name:fas_x_variant":[
        "Qap\u016bndar"
    ],
    "wof:name":"Qapundar",
    "wof:placetype":"locality"
},
  "geometry": {"coordinates":[47.69389,33.13444],"type":"Point"}
}