{
  "type": "Feature",
  "properties": {
    "gn:admin1_code":"0",
    "gn:asciiname":"Kahurabad",
    "gn:country_code":"IR",
    "gn:dem":533,
    "gn:feature_class":"P",
    "gn:feature_code":"PPL",
    "gn:name":"Kah\u016br\u0101b\u0101d",
    "gn:population":0,
    "gn:timezone":"Asia/Tehran",
    "iso:country":"IR",
    "name:fas_x_preferred":[
        "\u06a9\u0647\u0648\u0631 \u0622\u0628\u0627\u062f"
    ],
    "name:fas_x_variant":[
        "Kah\u016br\u0101b\u0101d",
        "\u06a9\u0647\u0648\u0631\u0622\u0628\u0627\u062f"
    ],
    "wof:name":"Kahurabad",
    "wof:placetype":"locality"
},
  "geometry": {"coordinates":[57.4674,27.9051],"type":"Point"}
}