{
  "type": "Feature",
  "properties": {
    "gn:admin1_code":"38",
    "gn:asciiname":"Khatayan",
    "gn:country_code":"IR",
    "gn:dem":1188,
    "gn:feature_class":"P",
    "gn:feature_code":"PPL",
    "gn:name":"Kha\u0163\u0101y\u0101n",
    "gn:population":0,
    "gn:timezone":"Asia/Tehran",
    "iso:country":"IR",
    "name:fas_x_preferred":[
        "\u062e\u0637\u0627\u064a\u0627\u0646"
    ],
    "name:fas_x_variant":[
        "Kha\u0163\u0101y\u0101n"
    ],
    "wof:name":"Khatayan",
    "wof:placetype":"locality"
},
  "geometry": {"coordinates":[50.2641,36.0898],"type":"Point"}
}