{
  "type": "Feature",
  "properties": {
    "gn:admin1_code":"5",
    "gn:asciiname":"Kamar Zard",
    "gn:country_code":"IR",
    "gn:dem":2046,
    "gn:feature_class":"P",
    "gn:feature_code":"PPL",
    "gn:name":"Kamar Zard",
    "gn:population":0,
    "gn:timezone":"Asia/Tehran",
    "iso:country":"IR",
    "name:ceb_x_preferred":[
        "Kamar Zard"
    ],
    "name:fas_x_preferred":[
        "\u0643\u064e\u0645\u064e\u0631 \u0632\u064e\u0631\u062f"
    ],
    "name:swe_x_preferred":[
        "Kamar Zard"
    ],
    "wof:name":"Kamar Zard",
    "wof:placetype":"locality"
},
  "geometry": {"coordinates":[50.86667,30.66667],"type":"Point"}
}