{
  "type": "Feature",
  "properties": {
    "gn:admin1_code":"4.0",
    "gn:asciiname":"Hesaru",
    "gn:country_code":"IR",
    "gn:dem":1561,
    "gn:feature_class":"P",
    "gn:feature_code":"PPL",
    "gn:name":"\u1e28e\u015f\u0101r\u016b",
    "gn:population":0,
    "gn:timezone":"Asia/Tehran",
    "iso:country":"IR",
    "name:fas_x_preferred":[
        "\u062d\u0635\u0627\u0631\u0648"
    ],
    "name:fas_x_variant":[
        "\u1e28e\u015f\u0101r\u016b\u2019\u012byeh",
        "\u1e28e\u015f\u0101r\u016b",
        "His\u0101r",
        "\u1e28as\u0101r\u016b"
    ],
    "wof:name":"Hesaru",
    "wof:placetype":"locality"
},
  "geometry": {"coordinates":[60.14166,29.42302],"type":"Point"}
}