{
  "type": "Feature",
  "properties": {
    "gn:admin1_code":"29",
    "gn:asciiname":"Pari Kuh",
    "gn:cc2":"IR",
    "gn:country_code":"IR",
    "gn:dem":2526,
    "gn:feature_class":"P",
    "gn:feature_code":"PPL",
    "gn:name":"P\u0101r\u012b K\u016bh",
    "gn:population":0,
    "gn:timezone":"Asia/Tehran",
    "iso:country":"IR",
    "name:fas_x_preferred":[
        "P\u0101r\u012b K\u016bh"
    ],
    "name:und_x_variant":[
        "B\u0101r\u012bk\u016bh"
    ],
    "wof:name":"Pari Kuh",
    "wof:placetype":"locality"
},
  "geometry": {"coordinates":[55.37083000000001,30.36611],"type":"Point"}
}