{
  "type": "Feature",
  "properties": {
    "gn:admin1_code":"8",
    "gn:asciiname":"Mudegan",
    "gn:country_code":"IR",
    "gn:dem":82,
    "gn:feature_class":"P",
    "gn:feature_code":"PPL",
    "gn:name":"M\u016bdeg\u0101n",
    "gn:population":0,
    "gn:timezone":"Asia/Tehran",
    "iso:country":"IR",
    "name:ara_x_preferred":[
        "\u0645\u0648\u062f\u063a\u0627\u0646"
    ],
    "name:fas_x_preferred":[
        "\u0645\u0648\u062f\u06af\u0627\u0646"
    ],
    "name:fas_x_variant":[
        "M\u016bdeg\u0101n"
    ],
    "name:msa_x_preferred":[
        "Mudegan"
    ],
    "name:ukr_x_preferred":[
        "\u041c\u0443\u0434\u0435\u0491\u0430\u043d"
    ],
    "name:und_x_variant":[
        "M\u016bdk\u0101n"
    ],
    "wof:name":"Mudegan",
    "wof:placetype":"locality"
},
  "geometry": {"coordinates":[49.25936,37.18158],"type":"Point"}
}