{
  "type": "Feature",
  "properties": {
    "gn:admin1_code":"15",
    "gn:asciiname":"Rusta-ye Hamid",
    "gn:country_code":"IR",
    "gn:dem":1,
    "gn:feature_class":"P",
    "gn:feature_code":"PPL",
    "gn:name":"R\u016bst\u0101-ye \u1e28am\u012bd",
    "gn:population":0,
    "gn:timezone":"Asia/Tehran",
    "iso:country":"IR",
    "name:fas_x_preferred":[
        "\u0631\u0648\u0633\u062a\u0627\u06cc \u062d\u0645\u06cc\u062f"
    ],
    "name:fas_x_variant":[
        "\u1e28amayyed",
        "R\u016bst\u0101-ye \u1e28am\u012bd"
    ],
    "wof:name":"Rusta-ye Hamid",
    "wof:placetype":"locality"
},
  "geometry": {"coordinates":[48.4831,30.0279],"type":"Point"}
}