{
  "type": "Feature",
  "properties": {
    "gn:admin1_code":"28.0",
    "gn:asciiname":"Mir Gun",
    "gn:country_code":"IR",
    "gn:dem":1632,
    "gn:feature_class":"P",
    "gn:feature_code":"PPL",
    "gn:name":"M\u012br G\u016bn",
    "gn:population":0,
    "gn:timezone":"Asia/Tehran",
    "iso:country":"IR",
    "name:fas_x_preferred":[
        "M\u012br G\u016bn"
    ],
    "wof:name":"Mir Gun",
    "wof:placetype":"locality"
},
  "geometry": {"coordinates":[51.60389,32.47361],"type":"Point"}
}