{
  "type": "Feature",
  "properties": {
    "gn:admin1_code":"33",
    "gn:asciiname":"Ashrafabad",
    "gn:country_code":"IR",
    "gn:dem":1762,
    "gn:feature_class":"P",
    "gn:feature_code":"PPL",
    "gn:name":"Ashraf\u0101b\u0101d",
    "gn:population":0,
    "gn:timezone":"Asia/Tehran",
    "iso:country":"IR",
    "name:fas_x_preferred":[
        "\u0627\u0634\u0631\u0641 \u0622\u0628\u0627\u062f"
    ],
    "name:fas_x_variant":[
        "Ashraf\u0101b\u0101d"
    ],
    "wof:name":"Ashrafabad",
    "wof:placetype":"locality"
},
  "geometry": {"coordinates":[46.826,37.8081],"type":"Point"}
}