{
  "type": "Feature",
  "properties": {
    "gn:admin1_code":"7",
    "gn:asciiname":"Varak",
    "gn:country_code":"IR",
    "gn:dem":1624,
    "gn:feature_class":"P",
    "gn:feature_code":"PPL",
    "gn:name":"V\u0101rak",
    "gn:population":0,
    "gn:timezone":"Asia/Tehran",
    "iso:country":"IR",
    "name:fas_x_preferred":[
        "V\u0101rak"
    ],
    "name:fas_x_variant":[
        "\u0648\u0627\u0631\u0643",
        "\u0648\u0627\u0631\u06a9"
    ],
    "name:msa_x_preferred":[
        "Varak"
    ],
    "name:und_x_variant":[
        "\u0648\u0627\u0631\u0643"
    ],
    "wof:name":"Varak",
    "wof:placetype":"locality"
},
  "geometry": {"coordinates":[51.95772,29.51031],"type":"Point"}
}