{
  "type": "Feature",
  "properties": {
    "gn:admin1_code":"26",
    "gn:asciiname":"Taskan",
    "gn:country_code":"IR",
    "gn:dem":1934,
    "gn:feature_class":"P",
    "gn:feature_code":"PPL",
    "gn:name":"T\u0101skan",
    "gn:population":0,
    "gn:timezone":"Asia/Tehran",
    "iso:country":"IR",
    "name:fas_x_preferred":[
        "\u062a\u0627\u0633\u0643\u064e\u0646"
    ],
    "name:fas_x_variant":[
        "T\u0101skan"
    ],
    "wof:name":"Taskan",
    "wof:placetype":"locality"
},
  "geometry": {"coordinates":[52.13333,35.61667],"type":"Point"}
}