{
  "type": "Feature",
  "properties": {
    "gn:admin1_code":"29",
    "gn:asciiname":"Nah'i",
    "gn:country_code":"IR",
    "gn:dem":1176,
    "gn:feature_class":"P",
    "gn:feature_code":"PPLL",
    "gn:name":"Nah\u2019\u012b",
    "gn:population":0,
    "gn:timezone":"Asia/Tehran",
    "iso:country":"IR",
    "name:fas_x_preferred":[
        "\u0646\u0639\u06cc \u06af\u0632 \u0628\u0647\u0645\u0646"
    ],
    "name:fas_x_variant":[
        "Na\u2018\u012b-ye Gaz Bahman",
        "\u0646\u0647 \u0627\u06cc"
    ],
    "name:und_x_variant":[
        "Nah\u2019\u012b"
    ],
    "wof:name":"Nah'i",
    "wof:placetype":"locality"
},
  "geometry": {"coordinates":[58.63214,28.54612],"type":"Point"}
}