{
  "type": "Feature",
  "properties": {
    "gn:admin1_code":"8",
    "gn:asciiname":"Jirsar-e Baqer Khaleh",
    "gn:country_code":"IR",
    "gn:dem":-24,
    "gn:feature_class":"P",
    "gn:feature_code":"PPL",
    "gn:name":"J\u012brsar-e B\u0101qer Kh\u0101leh",
    "gn:population":0,
    "gn:timezone":"Asia/Tehran",
    "iso:country":"IR",
    "name:ceb_x_preferred":[
        "J\u012brsar-e B\u0101qer Kh\u0101leh"
    ],
    "name:fas_x_preferred":[
        "J\u012brsar-e B\u0101qer Kh\u0101leh"
    ],
    "name:fas_x_variant":[
        "\u062c\u06cc\u0631 \u0633\u0631 \u0628\u0627\u0642\u0631 \u062e\u0627\u0644\u0647",
        "\u062c\u06cc\u0631\u0633\u0631\u0628\u0627\u0642\u0631\u062e\u0627\u0644\u0647"
    ],
    "name:msa_x_preferred":[
        "Jirsar-e Baqer Khaleh"
    ],
    "name:swe_x_preferred":[
        "J\u012brsar-e B\u0101qer Kh\u0101leh"
    ],
    "name:ukr_x_preferred":[
        "\u0414\u0436\u0456\u0440\u0441\u0430\u0440-\u0435-\u0411\u0430\u043a\u0435\u0440-\u0425\u0430\u043b\u0435"
    ],
    "name:und_x_variant":[
        "J\u012brsar-e B\u0101qer"
    ],
    "wof:name":"Jirsar-e Baqer Khaleh",
    "wof:placetype":"locality"
},
  "geometry": {"coordinates":[49.55861,37.38969],"type":"Point"}
}