{
  "type": "Feature",
  "properties": {
    "gn:admin1_code":"40",
    "gn:asciiname":"Kordabad",
    "gn:country_code":"IR",
    "gn:dem":663,
    "gn:feature_class":"P",
    "gn:feature_code":"PPL",
    "gn:name":"Kord\u0101b\u0101d",
    "gn:population":0,
    "gn:timezone":"Asia/Tehran",
    "iso:country":"IR",
    "name:fas_x_preferred":[
        "\u06a9\u0631\u062f \u0622\u0628\u0627\u062f"
    ],
    "name:fas_x_variant":[
        "Kerd\u0101b\u0101d",
        "Kord\u0101b\u0101d",
        "\u06a9\u0631\u062f\u0622\u0628\u0627\u062f"
    ],
    "name:und_x_variant":[
        "Kord\u0101b\u0101d"
    ],
    "wof:name":"Kordabad",
    "wof:placetype":"locality"
},
  "geometry": {"coordinates":[56.83799000000001,33.68995],"type":"Point"}
}