{
  "type": "Feature",
  "properties": {
    "gn:admin1_code":"34",
    "gn:asciiname":"Lakan",
    "gn:country_code":"IR",
    "gn:dem":2099,
    "gn:feature_class":"P",
    "gn:feature_code":"PPL",
    "gn:name":"Lak\u0101n",
    "gn:population":0,
    "gn:timezone":"Asia/Tehran",
    "iso:country":"IR",
    "name:fas_x_preferred":[
        "\u0644\u064e\u06af\u0627\u0646"
    ],
    "name:fas_x_variant":[
        "\u0644\u06a9\u0627\u0646",
        "\u0644\u0627\u062e\u064e\u0648\u0646",
        "\u0644\u0627\u062e\u0648\u0646",
        "Lag\u0101n",
        "Lak\u0101n"
    ],
    "name:und_x_variant":[
        "Lak\u0101n",
        "L\u0101kha\u016bn",
        "L\u0101kh\u016bn"
    ],
    "wof:name":"Lakan",
    "wof:placetype":"locality"
},
  "geometry": {"coordinates":[49.73638,33.7045],"type":"Point"}
}