{
  "type": "Feature",
  "properties": {
    "gn:admin1_code":"33.0",
    "gn:asciiname":"Beyg Dali",
    "gn:country_code":"IR",
    "gn:dem":1073,
    "gn:feature_class":"P",
    "gn:feature_code":"PPL",
    "gn:name":"Beyg Dal\u012b",
    "gn:population":0,
    "gn:timezone":"Asia/Tehran",
    "iso:country":"IR",
    "name:fas_x_preferred":[
        "\u0628\u06cc\u06af \u062f\u0644\u06cc"
    ],
    "name:und_x_variant":[
        "Beyg Dal\u012b"
    ],
    "wof:name":"Beyg Dali",
    "wof:placetype":"locality"
},
  "geometry": {"coordinates":[47.60358,38.59033],"type":"Point"}
}