{
  "type": "Feature",
  "properties": {
    "gn:admin1_code":"5.0",
    "gn:asciiname":"Murga",
    "gn:country_code":"IR",
    "gn:dem":2368,
    "gn:feature_class":"P",
    "gn:feature_code":"PPL",
    "gn:name":"M\u016brg\u0101",
    "gn:population":0,
    "gn:timezone":"Asia/Tehran",
    "iso:country":"IR",
    "name:deu_x_preferred":[
        "Murga"
    ],
    "name:eus_x_preferred":[
        "Murga"
    ],
    "name:fas_x_preferred":[
        "Y\u0101ser\u0101b\u0101d"
    ],
    "name:fas_x_variant":[
        "\u06cc\u0627\u0633\u0631 \u0622\u0628\u0627\u062f",
        "\u0645\u0648\u0631\u06af\u0627"
    ],
    "name:fra_x_preferred":[
        "Murga"
    ],
    "name:ita_x_preferred":[
        "Murga"
    ],
    "name:jpn_x_preferred":[
        "\u30e0\u30eb\u30ac"
    ],
    "name:nld_x_preferred":[
        "Murga"
    ],
    "name:por_x_preferred":[
        "Murga"
    ],
    "name:spa_x_preferred":[
        "Murga"
    ],
    "name:und_x_variant":[
        "M\u016brg\u0101"
    ],
    "wof:name":"Murga",
    "wof:placetype":"locality"
},
  "geometry": {"coordinates":[51.78675,30.63393],"type":"Point"}
}