{
  "type": "Feature",
  "properties": {
    "gn:admin1_code":"8",
    "gn:asciiname":"Dareh Sar",
    "gn:country_code":"IR",
    "gn:dem":1794,
    "gn:feature_class":"P",
    "gn:feature_code":"PPL",
    "gn:name":"D\u0101reh Sar",
    "gn:population":0,
    "gn:timezone":"Asia/Tehran",
    "iso:country":"IR",
    "name:fas_x_preferred":[
        "\u062f\u0627\u0631\u0650\u0647 \u0633\u064e\u0631"
    ],
    "name:fas_x_variant":[
        "D\u0101reh Sar"
    ],
    "wof:name":"Dareh Sar",
    "wof:placetype":"locality"
},
  "geometry": {"coordinates":[48.96556,37.16917],"type":"Point"}
}