{
  "type": "Feature",
  "properties": {
    "gn:admin1_code":"41",
    "gn:asciiname":"Mianki",
    "gn:country_code":"IR",
    "gn:dem":2196,
    "gn:feature_class":"P",
    "gn:feature_code":"PPL",
    "gn:name":"M\u012b\u0101nk\u012b",
    "gn:population":0,
    "gn:timezone":"Asia/Tehran",
    "iso:country":"IR",
    "name:ara_x_preferred":[
        "\u0645\u064a\u0627\u0646\u0643\u064a"
    ],
    "name:ceb_x_preferred":[
        "M\u012b\u0101nk\u012b"
    ],
    "name:fas_x_preferred":[
        "\u0645\u06cc\u0627\u0646\u06a9\u06cc"
    ],
    "name:fas_x_variant":[
        "M\u012b\u0101nk\u012b",
        "\u0645\u06cc\u0627\u0646 \u06a9\u0648\u0647"
    ],
    "name:swe_x_preferred":[
        "M\u012b\u0101nk\u012b"
    ],
    "name:und_x_variant":[
        "Mey\u0101nk\u012b",
        "M\u012b\u0101n K\u016bh"
    ],
    "wof:name":"Mianki",
    "wof:placetype":"locality"
},
  "geometry": {"coordinates":[59.72617,32.79144],"type":"Point"}
}