{
  "type": "Feature",
  "properties": {
    "gn:admin1_code":"7",
    "gn:asciiname":"Jahadabad",
    "gn:country_code":"IR",
    "gn:dem":856,
    "gn:feature_class":"P",
    "gn:feature_code":"PPL",
    "gn:name":"Jah\u0101d\u0101b\u0101d",
    "gn:population":0,
    "gn:timezone":"Asia/Tehran",
    "iso:country":"IR",
    "name:fas_x_preferred":[
        "B\u0101lang\u016b-ye Sofl\u00e1"
    ],
    "name:fas_x_variant":[
        "B\u0101lang\u016b-ye P\u0101\u2019\u012bn",
        "\u0628\u0627\u0644\u0646\u06af\u0648\u06cc \u0633\u0641\u0644\u06cc",
        "\u062c\u0647\u0627\u062f \u0622\u0628\u0627\u062f",
        "\u062c\u0647\u0627\u062f\u0622\u0628\u0627\u062f"
    ],
    "name:msa_x_preferred":[
        "Jahadabad"
    ],
    "name:und_x_variant":[
        "Jah\u0101d\u0101b\u0101d"
    ],
    "name:urd_x_preferred":[
        "\u062c\u06c1\u0627\u062f \u0622\u0628\u0627\u062f"
    ],
    "wof:name":"Jahadabad",
    "wof:placetype":"locality"
},
  "geometry": {"coordinates":[51.37737,30.35322],"type":"Point"}
}