{
  "type": "Feature",
  "properties": {
    "gn:admin1_code":"39",
    "gn:asciiname":"Dudkesh",
    "gn:country_code":"IR",
    "gn:dem":911,
    "gn:feature_class":"P",
    "gn:feature_code":"PPL",
    "gn:name":"D\u016bdkesh",
    "gn:population":0,
    "gn:timezone":"Asia/Tehran",
    "iso:country":"IR",
    "name:fas_x_preferred":[
        "\u062f\u0648\u062f\u0643\u0650\u0634"
    ],
    "name:fas_x_variant":[
        "D\u016bdkesh"
    ],
    "wof:name":"Dudkesh",
    "wof:placetype":"locality"
},
  "geometry": {"coordinates":[50.93333,34.63333],"type":"Point"}
}