{
  "type": "Feature",
  "properties": {
    "gn:admin1_code":"43",
    "gn:asciiname":"Tuy",
    "gn:country_code":"IR",
    "gn:dem":1066,
    "gn:feature_class":"P",
    "gn:feature_code":"PPL",
    "gn:name":"T\u016by",
    "gn:population":0,
    "gn:timezone":"Asia/Tehran",
    "iso:country":"IR",
    "name:bre_x_preferred":[
        "Tuy"
    ],
    "name:cat_x_preferred":[
        "Tuy"
    ],
    "name:ceb_x_preferred":[
        "Tuy"
    ],
    "name:deu_x_preferred":[
        "Tuy"
    ],
    "name:fas_x_preferred":[
        "T\u016by"
    ],
    "name:fas_x_variant":[
        "\u062a\u0648\u06cc"
    ],
    "name:fra_x_preferred":[
        "Tuy"
    ],
    "name:jpn_x_preferred":[
        "\u30c8\u30a5\u30a4"
    ],
    "name:nld_x_preferred":[
        "Tuy"
    ],
    "name:rus_x_preferred":[
        "\u0422\u0443\u0439"
    ],
    "name:spa_x_preferred":[
        "Tuy"
    ],
    "name:swe_x_preferred":[
        "Tuy"
    ],
    "name:ukr_x_preferred":[
        "\u0422\u0443\u0439"
    ],
    "name:und_x_variant":[
        "Tavi",
        "T\u016bi",
        "Toy",
        "\u062a\u0648\u06cc"
    ],
    "name:war_x_preferred":[
        "Tuy"
    ],
    "wof:name":"Tuy",
    "wof:placetype":"locality"
},
  "geometry": {"coordinates":[57.10654,37.13313],"type":"Point"}
}