{
  "type": "Feature",
  "properties": {
    "gn:admin1_code":"8.0",
    "gn:asciiname":"Arbastan",
    "gn:country_code":"IR",
    "gn:dem":-3,
    "gn:feature_class":"P",
    "gn:feature_code":"PPL",
    "gn:name":"Arb\u0101st\u0101n",
    "gn:population":0,
    "gn:timezone":"Asia/Tehran",
    "iso:country":"IR",
    "name:ceb_x_preferred":[
        "Arb\u0101st\u0101n"
    ],
    "name:fas_x_preferred":[
        "Arb\u0101st\u0101n-e B\u0101l\u0101"
    ],
    "name:fas_x_variant":[
        "Arb\u0101st\u0101n",
        "\u0627\u0631\u0628\u0627\u0633\u062a\u0627\u0646"
    ],
    "name:msa_x_preferred":[
        "Arbastan"
    ],
    "name:swe_x_preferred":[
        "Arb\u0101st\u0101n"
    ],
    "name:ukr_x_preferred":[
        "\u0410\u0440\u0431\u0430\u0441\u0442\u0430\u043d"
    ],
    "name:und_x_variant":[
        "Arb\u0101set\u0101n"
    ],
    "wof:name":"Arbastan",
    "wof:placetype":"locality"
},
  "geometry": {"coordinates":[50.11591,37.24503],"type":"Point"}
}