{
  "type": "Feature",
  "properties": {
    "gn:admin1_code":"32",
    "gn:asciiname":"Molla Kandi",
    "gn:country_code":"IR",
    "gn:dem":52,
    "gn:feature_class":"P",
    "gn:feature_code":"PPL",
    "gn:name":"Moll\u0101 Kand\u012b",
    "gn:population":0,
    "gn:timezone":"Asia/Tehran",
    "iso:country":"IR",
    "name:fas_x_preferred":[
        "\u0645\u0644\u0627 \u0643\u0646\u062f\u06cc"
    ],
    "name:fas_x_variant":[
        "Moll\u0101 Kand\u012b"
    ],
    "wof:name":"Molla Kandi",
    "wof:placetype":"locality"
},
  "geometry": {"coordinates":[47.9742,39.6077],"type":"Point"}
}