{
  "type": "Feature",
  "properties": {
    "gn:admin1_code":"13",
    "gn:asciiname":"Cheshmeh Qanbar",
    "gn:country_code":"IR",
    "gn:dem":1387,
    "gn:feature_class":"P",
    "gn:feature_code":"PPL",
    "gn:name":"Cheshmeh Qanbar",
    "gn:population":0,
    "gn:timezone":"Asia/Tehran",
    "iso:country":"IR",
    "name:fas_x_preferred":[
        "\u0686\u0634\u0645\u0647 \u0642\u0646\u0628\u0631"
    ],
    "wof:name":"Cheshmeh Qanbar",
    "wof:placetype":"locality"
},
  "geometry": {"coordinates":[47.3284,34.6123],"type":"Point"}
}