{
  "type": "Feature",
  "properties": {
    "gn:admin1_code":"40.0",
    "gn:asciiname":"Mazra`eh-ye Mirza Mohammad `Ali",
    "gn:country_code":"IR",
    "gn:dem":1973,
    "gn:feature_class":"P",
    "gn:feature_code":"PPL",
    "gn:name":"Mazra\u2018eh-ye M\u012brz\u0101 Mo\u1e29ammad \u2018Al\u012b",
    "gn:population":0,
    "gn:timezone":"Asia/Tehran",
    "iso:country":"IR",
    "name:fas_x_preferred":[
        "\u0645\u0632\u0631\u0639\u06c0 \u0645\u064a\u0631\u0632\u0627 \u0645\u062d\u0645\u062f \u0639\u0644\u06cc"
    ],
    "name:fas_x_variant":[
        "\u0645\u064e\u0632\u0631\u064e\u0639\u0650\u06c0 \u0645\u064a\u0631\u0632\u0627 \u0645\u064f\u0647\u064e\u0645\u064e\u0651\u062f",
        "Mazra\u2018eh-ye M\u012brz\u0101 Mo\u1e29ammad \u2018Al\u012b"
    ],
    "name:und_x_variant":[
        "Mazra\u2018eh-ye M\u012brz\u0101 Mohammad"
    ],
    "wof:name":"Mazra`eh-ye Mirza Mohammad `Ali",
    "wof:placetype":"locality"
},
  "geometry": {"coordinates":[53.8551,31.4138],"type":"Point"}
}