{
  "type": "Feature",
  "properties": {
    "gn:admin1_code":"16.0",
    "gn:asciiname":"Garmidar",
    "gn:country_code":"IR",
    "gn:dem":2174,
    "gn:feature_class":"P",
    "gn:feature_code":"PPL",
    "gn:name":"Garm\u012bdar",
    "gn:population":0,
    "gn:timezone":"Asia/Tehran",
    "iso:country":"IR",
    "name:fas_x_preferred":[
        "\u06af\u064e\u0631\u0645\u064a\u062f\u064e\u0631"
    ],
    "name:fas_x_variant":[
        "Garm\u012bdar"
    ],
    "wof:name":"Garmidar",
    "wof:placetype":"locality"
},
  "geometry": {"coordinates":[47.11667,35.41667],"type":"Point"}
}