{
  "type": "Feature",
  "properties": {
    "gn:admin1_code":"13.0",
    "gn:asciiname":"Duleh Khoshk-e Salehi",
    "gn:country_code":"IR",
    "gn:dem":524,
    "gn:feature_class":"P",
    "gn:feature_code":"PPL",
    "gn:name":"D\u016bleh Khoshk-e \u015e\u0101le\u1e29\u012b",
    "gn:population":0,
    "gn:timezone":"Asia/Tehran",
    "iso:country":"IR",
    "name:fas_x_preferred":[
        "\u062f\u0648\u0644\u0647 \u062e\u0634\u06a9 \u0635\u0627\u0644\u062d\u06cc"
    ],
    "name:fas_x_variant":[
        "D\u016bleh Khoshk-e \u015e\u0101le\u1e29\u012b"
    ],
    "wof:name":"Duleh Khoshk-e Salehi",
    "wof:placetype":"locality"
},
  "geometry": {"coordinates":[45.8291,34.7838],"type":"Point"}
}