{
  "type": "Feature",
  "properties": {
    "gn:admin1_code":"33",
    "gn:asciiname":"Miardan",
    "gn:country_code":"IR",
    "gn:dem":1984,
    "gn:feature_class":"P",
    "gn:feature_code":"PPL",
    "gn:name":"M\u012b\u0101rd\u0101n",
    "gn:population":0,
    "gn:timezone":"Asia/Tehran",
    "iso:country":"IR",
    "name:fas_x_preferred":[
        "\u0645\u06cc\u0627\u0631\u062f\u0627\u0646"
    ],
    "name:fas_x_variant":[
        "M\u012b\u0101rd\u0101n"
    ],
    "wof:name":"Miardan",
    "wof:placetype":"locality"
},
  "geometry": {"coordinates":[46.6746,37.8148],"type":"Point"}
}