{
  "type": "Feature",
  "properties": {
    "gn:admin1_code":"4",
    "gn:asciiname":"Mohammadan",
    "gn:country_code":"IR",
    "gn:dem":697,
    "gn:feature_class":"P",
    "gn:feature_code":"PPL",
    "gn:name":"Mo\u1e29ammad\u0101n",
    "gn:population":0,
    "gn:timezone":"Asia/Tehran",
    "iso:country":"IR",
    "name:fas_x_preferred":[
        "Mo\u1e29ammad\u0101n"
    ],
    "wof:name":"Mohammadan",
    "wof:placetype":"locality"
},
  "geometry": {"coordinates":[59.70306,26.83028],"type":"Point"}
}