{
  "type": "Feature",
  "properties": {
    "gn:admin1_code":"0",
    "gn:asciiname":"Ahmadabad-e Now Kahan",
    "gn:country_code":"IR",
    "gn:dem":1724,
    "gn:feature_class":"P",
    "gn:feature_code":"PPL",
    "gn:name":"A\u1e29mad\u0101b\u0101d-e Now Kahan",
    "gn:population":0,
    "gn:timezone":"Asia/Tehran",
    "iso:country":"IR",
    "name:fas_x_preferred":[
        "\u0627\u062d\u0645\u062f \u0622\u0628\u0627\u062f \u0646\u0648 \u06a9\u0647\u0646"
    ],
    "name:fas_x_variant":[
        "A\u1e29mad\u0101b\u0101d-e Now Kahan"
    ],
    "wof:name":"Ahmadabad-e Now Kahan",
    "wof:placetype":"locality"
},
  "geometry": {"coordinates":[55.966,28.9955],"type":"Point"}
}