{
  "type": "Feature",
  "properties": {
    "gn:admin1_code":"1",
    "gn:asciiname":"Sunias",
    "gn:country_code":"IR",
    "gn:dem":1584,
    "gn:feature_class":"P",
    "gn:feature_code":"PPL",
    "gn:name":"S\u016bn\u012b\u0101s",
    "gn:population":0,
    "gn:timezone":"Asia/Tehran",
    "iso:country":"IR",
    "name:azb_x_preferred":[
        "\u0633\u0648\u06cc\u0646\u0627\u0633(\u0633\u0648\u06cc\u0648\u0642\u200c\u0628\u0648\u0644\u0627\u0642)"
    ],
    "name:aze_x_preferred":[
        "S\u0259vinas"
    ],
    "name:ceb_x_preferred":[
        "S\u016bn\u012b\u0101s"
    ],
    "name:ckb_x_preferred":[
        "\u0633\u0648\u06ce\u0646\u0627\u0633"
    ],
    "name:fas_x_preferred":[
        "\u0633\u064e\u0648\u064a\u0646\u0627\u0633"
    ],
    "name:fas_x_variant":[
        "\u0633\u0648\u0646\u06cc\u0627\u0633",
        "Sav\u012bn\u0101s",
        "\u0633\u0648\u064a\u0646\u0627\u0633",
        "S\u016bn\u012b\u0101s",
        "\u0633\u0648\u0646\u064a\u0651\u0627\u0633",
        "\u0633\u0648\u06cc\u0646\u0627\u0633"
    ],
    "name:msa_x_preferred":[
        "Savinas"
    ],
    "name:swe_x_preferred":[
        "S\u016bn\u012b\u0101s"
    ],
    "name:und_x_variant":[
        "S\u016byn\u0101s",
        "S\u016bn\u012by\u0101s"
    ],
    "wof:name":"Sunias",
    "wof:placetype":"locality"
},
  "geometry": {"coordinates":[45.7103,36.3608],"type":"Point"}
}