{
  "type": "Feature",
  "properties": {
    "gn:admin1_code":"32",
    "gn:asciiname":"Samarin",
    "gn:country_code":"IR",
    "gn:dem":1505,
    "gn:feature_class":"P",
    "gn:feature_code":"PPL",
    "gn:name":"S\u0304amar\u012bn",
    "gn:population":0,
    "gn:timezone":"Asia/Tehran",
    "iso:country":"IR",
    "name:fas_x_preferred":[
        "\u062b\u064f\u0645\u064e\u0631\u064a\u0646"
    ],
    "name:fas_x_variant":[
        "\u062b\u0645\u0631\u064a\u0646",
        "S\u0304omar\u012bn",
        "S\u0304amar\u012bn"
    ],
    "wof:name":"Samarin",
    "wof:placetype":"locality"
},
  "geometry": {"coordinates":[48.135,38.3558],"type":"Point"}
}