{
  "type": "Feature",
  "properties": {
    "gn:admin1_code":"16",
    "gn:asciiname":"Darreh Qebleh",
    "gn:country_code":"IR",
    "gn:dem":1645,
    "gn:feature_class":"P",
    "gn:feature_code":"PPL",
    "gn:name":"Darreh Qebleh",
    "gn:population":0,
    "gn:timezone":"Asia/Tehran",
    "iso:country":"IR",
    "name:ara_x_preferred":[
        "\u062f\u0631\u06d5 \u0642\u0648\u0644\u0647"
    ],
    "name:ceb_x_preferred":[
        "Darreh Qebleh"
    ],
    "name:ckb_x_preferred":[
        "\u062f\u06d5\u0631\u06d5\u0642\u0648\u0648\u06b5\u06d5"
    ],
    "name:fas_x_preferred":[
        "\u062f\u0631\u0647 \u0642\u0628\u0644\u0647"
    ],
    "name:fas_x_variant":[
        "\u062f\u0631\u0647\u200c\u0642\u0628\u0644\u0647"
    ],
    "name:kur_x_preferred":[
        "Dereq\u00fble"
    ],
    "name:swe_x_preferred":[
        "Darreh Qebleh"
    ],
    "wof:name":"Darreh Qebleh",
    "wof:placetype":"locality"
},
  "geometry": {"coordinates":[46.53113,36.09104],"type":"Point"}
}