{
  "type": "Feature",
  "properties": {
    "gn:admin1_code":"16",
    "gn:asciiname":"Darreh Qebleh",
    "gn:country_code":"IR",
    "gn:dem":1645,
    "gn:feature_class":"P",
    "gn:feature_code":"PPL",
    "gn:name":"Darreh Qebleh",
    "gn:population":0,
    "gn:timezone":"Asia/Tehran",
    "iso:country":"IR",
    "name:fas_x_preferred":[
        "\u062f\u0631\u0647 \u0642\u0628\u0644\u0647"
    ],
    "wof:name":"Darreh Qebleh",
    "wof:placetype":"locality"
},
  "geometry": {"coordinates":[46.53113,36.09104],"type":"Point"}
}