{
  "type": "Feature",
  "properties": {
    "gn:admin1_code":"15",
    "gn:asciiname":"Kelasmadin-e Do",
    "gn:country_code":"IR",
    "gn:dem":500,
    "gn:feature_class":"P",
    "gn:feature_code":"PPL",
    "gn:name":"Kel\u0101smad\u012bn-e Do",
    "gn:population":0,
    "gn:timezone":"Asia/Tehran",
    "iso:country":"IR",
    "name:fas_x_preferred":[
        "Kel\u0101smad\u012bn-e Do"
    ],
    "name:fas_x_variant":[
        "\u06a9\u0644\u0627\u0633\u0645\u062f\u06cc\u0646 \u062f\u0648"
    ],
    "name:und_x_variant":[
        "Kol\u0101m od D\u012bn"
    ],
    "wof:name":"Kelasmadin-e Do",
    "wof:placetype":"locality"
},
  "geometry": {"coordinates":[49.7614,31.49292],"type":"Point"}
}