{
  "type": "Feature",
  "properties": {
    "gn:admin1_code":"8",
    "gn:asciiname":"Makhzan Ab",
    "gn:country_code":"IR",
    "gn:dem":-2,
    "gn:feature_class":"P",
    "gn:feature_code":"PPL",
    "gn:name":"Makhzan \u0100b",
    "gn:population":0,
    "gn:timezone":"Asia/Tehran",
    "iso:country":"IR",
    "name:fas_x_preferred":[
        "Mojr\u0101n \u0100b"
    ],
    "name:fas_x_variant":[
        "\u0645\u062e\u0632\u0646 \u0622\u0628"
    ],
    "name:und_x_variant":[
        "Makhzan \u0100b"
    ],
    "wof:name":"Makhzan Ab",
    "wof:placetype":"locality"
},
  "geometry": {"coordinates":[49.30166,37.32805],"type":"Point"}
}