{
  "type": "Feature",
  "properties": {
    "gn:admin1_code":"37",
    "gn:asciiname":"Eslamabad",
    "gn:country_code":"IR",
    "gn:dem":99,
    "gn:feature_class":"P",
    "gn:feature_code":"PPL",
    "gn:name":"Esl\u0101m\u0101b\u0101d",
    "gn:population":0,
    "gn:timezone":"Asia/Tehran",
    "iso:country":"IR",
    "name:fas_x_preferred":[
        "Esl\u0101m\u0101b\u0101d"
    ],
    "name:fas_x_variant":[
        "\u0627\u0633\u0644\u0627\u0645 \u0622\u0628\u0627\u062f",
        "\u0627\u0633\u0644\u0627\u0645 \u0622\u0628\u0627\u062f \u0645\u0632\u0631\u0639\u0647 \u0634\u0645\u0627\u0631\u0647 \u064a\u06a9"
    ],
    "name:und_x_variant":[
        "\u0627\u0633\u0644\u0627\u0645 \u0622\u0628\u0627\u062f",
        "Esl\u0101m\u0101b\u0101d Mazra\u2018eh-ye Shom\u0101reh-ye Yek"
    ],
    "wof:name":"Eslamabad",
    "wof:placetype":"locality"
},
  "geometry": {"coordinates":[54.85589,36.94463],"type":"Point"}
}