{
  "type": "Feature",
  "properties": {
    "gn:admin1_code":"34.0",
    "gn:asciiname":"Shahrak-e Sar Dasht",
    "gn:country_code":"IR",
    "gn:dem":1831,
    "gn:feature_class":"P",
    "gn:feature_code":"PPL",
    "gn:name":"Shahrak-e Sar Dasht",
    "gn:population":0,
    "gn:timezone":"Asia/Tehran",
    "iso:country":"IR",
    "name:fas_x_preferred":[
        "\u0634\u0647\u0631\u06a9 \u0633\u0631 \u062f\u0634\u062a"
    ],
    "wof:name":"Shahrak-e Sar Dasht",
    "wof:placetype":"locality"
},
  "geometry": {"coordinates":[49.65294,34.07566],"type":"Point"}
}