{
  "type": "Feature",
  "properties": {
    "gn:admin1_code":"23",
    "gn:asciiname":"Sar Chol",
    "gn:country_code":"IR",
    "gn:dem":1575,
    "gn:feature_class":"P",
    "gn:feature_code":"PPL",
    "gn:name":"Sar Chol",
    "gn:population":0,
    "gn:timezone":"Asia/Tehran",
    "iso:country":"IR",
    "name:fas_x_preferred":[
        "\u0633\u0631 \u0686\u0644"
    ],
    "name:fas_x_variant":[
        "\u0633\u0631 \u0686\u0648\u0644 \u0646\u0648\u0634 \u0622\u0628\u0627\u062f",
        "Sar Ch\u016bl-e N\u016bsh\u0101b\u0101d",
        "\u0646\u0648\u0634 \u0622\u0628\u0627\u062f"
    ],
    "name:und_x_variant":[
        "N\u016bsh\u0101b\u0101d"
    ],
    "wof:name":"Sar Chol",
    "wof:placetype":"locality"
},
  "geometry": {"coordinates":[48.5836,33.3262],"type":"Point"}
}