{
  "type": "Feature",
  "properties": {
    "gn:admin1_code":"11",
    "gn:asciiname":"Mashangi",
    "gn:country_code":"IR",
    "gn:dem":481,
    "gn:feature_class":"P",
    "gn:feature_code":"PPL",
    "gn:name":"M\u0101shang\u012b",
    "gn:population":0,
    "gn:timezone":"Asia/Tehran",
    "iso:country":"IR",
    "name:fas_x_preferred":[
        "\u0645\u0627\u0634\u0646\u06af\u06cc"
    ],
    "name:fas_x_variant":[
        "\u0645\u0627\u0634\u0650\u0646\u06af\u06cc",
        "M\u0101shang\u012b"
    ],
    "name:und_x_variant":[
        "M\u0101sheng\u012b"
    ],
    "wof:name":"Mashangi",
    "wof:placetype":"locality"
},
  "geometry": {"coordinates":[57.1631,27.7682],"type":"Point"}
}