{
  "type": "Feature",
  "properties": {
    "gn:admin1_code":"7",
    "gn:asciiname":"Shahrak-e Ghadir",
    "gn:country_code":"IR",
    "gn:dem":1367,
    "gn:feature_class":"P",
    "gn:feature_code":"PPL",
    "gn:name":"Shahrak-e Ghad\u012br",
    "gn:population":0,
    "gn:timezone":"Asia/Tehran",
    "iso:country":"IR",
    "name:fas_x_preferred":[
        "\u0634\u0647\u0631\u0643 \u063a\u062f\u06cc\u0631"
    ],
    "name:fas_x_variant":[
        "Shahrak-e Ghad\u012br",
        "\u0634\u0647\u0631\u06a9 \u063a\u062f\u06cc\u0631"
    ],
    "name:msa_x_preferred":[
        "Shahrak-e Ghadir"
    ],
    "wof:name":"Shahrak-e Ghadir",
    "wof:placetype":"locality"
},
  "geometry": {"coordinates":[54.8592,28.577],"type":"Point"}
}