{
  "type": "Feature",
  "properties": {
    "gn:admin1_code":"33",
    "gn:asciiname":"Aqbolagh-e Fotuhi",
    "gn:country_code":"IR",
    "gn:dem":1776,
    "gn:feature_class":"P",
    "gn:feature_code":"PPL",
    "gn:name":"\u0100qbol\u0101gh-e Fot\u016b\u1e29\u012b",
    "gn:population":0,
    "gn:timezone":"Asia/Tehran",
    "iso:country":"IR",
    "name:fas_x_preferred":[
        "\u0622\u063a\u0628\u0644\u0627\u063a \u0641\u062a\u0648\u062d\u06cc"
    ],
    "name:fas_x_variant":[
        "\u0100qbol\u0101gh-e Fot\u016b\u1e29\u012b"
    ],
    "name:und_x_variant":[
        "\u0100q Bol\u0101gh"
    ],
    "wof:name":"Aqbolagh-e Fotuhi",
    "wof:placetype":"locality"
},
  "geometry": {"coordinates":[46.38072,37.22869],"type":"Point"}
}