{
  "type": "Feature",
  "properties": {
    "gn:admin1_code":"29",
    "gn:asciiname":"Mahallati",
    "gn:country_code":"IR",
    "gn:dem":613,
    "gn:feature_class":"P",
    "gn:feature_code":"PPLL",
    "gn:name":"Ma\u1e29all\u0101t\u012b",
    "gn:population":0,
    "gn:timezone":"Asia/Tehran",
    "iso:country":"IR",
    "name:fas_x_preferred":[
        "\u0645\u062d\u0644\u0627\u062a\u06cc"
    ],
    "name:fas_x_variant":[
        "Ma\u1e29all\u0101t\u012b"
    ],
    "wof:name":"Mahallati",
    "wof:placetype":"locality"
},
  "geometry": {"coordinates":[58.12324,27.15998],"type":"Point"}
}