{
  "type": "Feature",
  "properties": {
    "gn:admin1_code":"32",
    "gn:asciiname":"Qeshlaq-e Qushdash Mirza Khan",
    "gn:country_code":"IR",
    "gn:dem":252,
    "gn:feature_class":"P",
    "gn:feature_code":"PPL",
    "gn:name":"Qeshl\u0101q-e Q\u016bshd\u0101sh M\u012brz\u0101 Kh\u0101n",
    "gn:population":0,
    "gn:timezone":"Asia/Tehran",
    "iso:country":"IR",
    "name:fas_x_preferred":[
        "\u0642\u0650\u0634\u0644\u0627\u0642\u0650 \u0642\u0648\u0634\u062f\u0627\u0634 \u0645\u064a\u0631\u0632\u0627 \u062e\u0627\u0646"
    ],
    "name:fas_x_variant":[
        "Qeshl\u0101q-e Q\u016bshd\u0101sh M\u012brz\u0101 Kh\u0101n"
    ],
    "wof:name":"Qeshlaq-e Qushdash Mirza Khan",
    "wof:placetype":"locality"
},
  "geometry": {"coordinates":[48.18333,39.35],"type":"Point"}
}