{
  "type": "Feature",
  "properties": {
    "gn:admin1_code":"11.0",
    "gn:asciiname":"Dow Teflan",
    "gn:country_code":"IR",
    "gn:dem":13,
    "gn:feature_class":"P",
    "gn:feature_code":"PPL",
    "gn:name":"Dow \u0162efl\u0101n",
    "gn:population":0,
    "gn:timezone":"Asia/Tehran",
    "iso:country":"IR",
    "name:fas_x_preferred":[
        "\u062f\u0648 \u0637\u0641\u0644\u0627\u0646"
    ],
    "name:fas_x_variant":[
        "Dow \u0162efl\u0101n"
    ],
    "wof:name":"Dow Teflan",
    "wof:placetype":"locality"
},
  "geometry": {"coordinates":[56.9575,27.1938],"type":"Point"}
}