{
  "type": "Feature",
  "properties": {
    "gn:admin1_code":"3.0",
    "gn:asciiname":"Aqbolagh",
    "gn:country_code":"IR",
    "gn:dem":2280,
    "gn:feature_class":"P",
    "gn:feature_code":"PPL",
    "gn:name":"\u0100qbol\u0101gh",
    "gn:population":0,
    "gn:timezone":"Asia/Tehran",
    "iso:country":"IR",
    "name:fas_x_preferred":[
        "\u0100qbol\u0101gh"
    ],
    "name:fas_x_variant":[
        "\u0622\u06af \u0628\u064f\u0644\u0627\u0642",
        "\u0627\u064e\u063a\u0628\u064e\u0644\u064e\u063a \u0644\u064e\u0631",
        "\u0622\u0642\u0628\u0644\u0627\u063a"
    ],
    "name:und_x_variant":[
        "\u0100g Bol\u0101q",
        "Aghbalagh Lar",
        "\u0622\u0642\u0628\u0644\u0627\u063a"
    ],
    "wof:name":"Aqbolagh",
    "wof:placetype":"locality"
},
  "geometry": {"coordinates":[50.66468,32.38054],"type":"Point"}
}