{
  "type": "Feature",
  "properties": {
    "gn:admin1_code":"4.0",
    "gn:asciiname":"Siahdak",
    "gn:country_code":"IR",
    "gn:dem":1292,
    "gn:feature_class":"P",
    "gn:feature_code":"PPL",
    "gn:name":"S\u012b\u0101hdak",
    "gn:population":0,
    "gn:timezone":"Asia/Tehran",
    "iso:country":"IR",
    "name:fas_x_preferred":[
        "\u0633\u06cc\u0627\u062f\u0643"
    ],
    "name:fas_x_variant":[
        "S\u012b\u0101dek",
        "\u0633\u064a\u0627\u0647\u062f\u06a9"
    ],
    "name:und_x_variant":[
        "Seyah Dak",
        "S\u012b\u0101hdak"
    ],
    "wof:name":"Siahdak",
    "wof:placetype":"locality"
},
  "geometry": {"coordinates":[61.5773,27.6076],"type":"Point"}
}