{
  "type": "Feature",
  "properties": {
    "gn:admin1_code":"4.0",
    "gn:asciiname":"Godan",
    "gn:country_code":"IR",
    "gn:dem":40,
    "gn:feature_class":"P",
    "gn:feature_code":"PPL",
    "gn:name":"Godan",
    "gn:population":0,
    "gn:timezone":"Asia/Tehran",
    "iso:country":"IR",
    "name:fas_x_preferred":[
        "\u06af\u062f\u0646"
    ],
    "name:fas_x_variant":[
        "\u06af\u0648\u062f\u0646"
    ],
    "name:und_x_variant":[
        "Gowdan",
        "Godan"
    ],
    "wof:name":"Godan",
    "wof:placetype":"locality"
},
  "geometry": {"coordinates":[60.1514,25.6452],"type":"Point"}
}