{
  "type": "Feature",
  "properties": {
    "gn:admin1_code":"26.0",
    "gn:asciiname":"Valiabad",
    "gn:country_code":"IR",
    "gn:dem":1565,
    "gn:feature_class":"P",
    "gn:feature_code":"PPL",
    "gn:name":"Val\u012b\u0101b\u0101d",
    "gn:population":0,
    "gn:timezone":"Asia/Tehran",
    "iso:country":"IR",
    "name:fas_x_preferred":[
        "\u0627\u064e\u0628\u0651\u0627\u0633 \u0622\u0628\u0627\u062f"
    ],
    "name:fas_x_variant":[
        "\u0639\u0628\u0651\u0627\u0633 \u0622\u0628\u0627\u062f",
        "Abb\u0101s\u0101b\u0101d",
        "\u2018Abb\u0101s\u0101b\u0101d",
        "\u0648\u0644\u06cc \u0622\u0628\u0627\u062f",
        "\u0648\u0644\u06cc\u200c\u0622\u0628\u0627\u062f"
    ],
    "name:und_x_variant":[
        "Val\u012b\u0101b\u0101d"
    ],
    "wof:name":"Valiabad",
    "wof:placetype":"locality"
},
  "geometry": {"coordinates":[51.8867,35.662],"type":"Point"}
}