{
  "type": "Feature",
  "properties": {
    "gn:admin1_code":"42",
    "gn:asciiname":"Sang-e Sefid",
    "gn:country_code":"IR",
    "gn:dem":1354,
    "gn:feature_class":"P",
    "gn:feature_code":"PPL",
    "gn:name":"Sang-e Sef\u012bd",
    "gn:population":0,
    "gn:timezone":"Asia/Tehran",
    "iso:country":"IR",
    "name:fas_x_preferred":[
        "Sang-e Sef\u012bd"
    ],
    "name:fas_x_variant":[
        "\u0633\u0646\u06af \u0633\u0641\u064a\u062f"
    ],
    "name:und_x_variant":[
        "Sang-i-Sef\u012bd",
        "\u0633\u0646\u06af \u0633\u0641\u064a\u062f",
        "Sang Sefid"
    ],
    "wof:name":"Sang-e Sefid",
    "wof:placetype":"locality"
},
  "geometry": {"coordinates":[57.6966,36.3194],"type":"Point"}
}