{
  "type": "Feature",
  "properties": {
    "gn:admin1_code":"42",
    "gn:asciiname":"Golak",
    "gn:country_code":"IR",
    "gn:dem":1147,
    "gn:feature_class":"P",
    "gn:feature_code":"PPL",
    "gn:name":"Golak",
    "gn:population":0,
    "gn:timezone":"Asia/Tehran",
    "iso:country":"IR",
    "name:ara_x_preferred":[
        "\u063a\u0644\u0643"
    ],
    "name:ceb_x_preferred":[
        "Galk"
    ],
    "name:fas_x_preferred":[
        "\u06af\u0644\u06a9"
    ],
    "name:swe_x_preferred":[
        "Galk"
    ],
    "wof:name":"Golak",
    "wof:placetype":"locality"
},
  "geometry": {"coordinates":[59.14001999999999,36.66418],"type":"Point"}
}