{
  "type": "Feature",
  "properties": {
    "gn:admin1_code":"16",
    "gn:asciiname":"Sivar",
    "gn:country_code":"IR",
    "gn:dem":1622,
    "gn:feature_class":"P",
    "gn:feature_code":"PPL",
    "gn:name":"S\u012bvar",
    "gn:population":0,
    "gn:timezone":"Asia/Tehran",
    "iso:country":"IR",
    "name:fas_x_preferred":[
        "\u0633\u0650\u0648\u064e\u0631"
    ],
    "name:fas_x_variant":[
        "\u0633\u06cc\u0648\u0631",
        "S\u012bvar"
    ],
    "name:und_x_variant":[
        "Sevar",
        "S\u012bwar",
        "Seyvar"
    ],
    "wof:name":"Sivar",
    "wof:placetype":"locality"
},
  "geometry": {"coordinates":[46.5323,35.4912],"type":"Point"}
}