{
  "type": "Feature",
  "properties": {
    "gn:admin1_code":"13",
    "gn:asciiname":"Meykhowran-e Mohammad Aqa",
    "gn:country_code":"IR",
    "gn:dem":1986,
    "gn:feature_class":"P",
    "gn:feature_code":"PPL",
    "gn:name":"Meykhowr\u0101n-e Mo\u1e29ammad \u0100q\u0101",
    "gn:population":0,
    "gn:timezone":"Asia/Tehran",
    "iso:country":"IR",
    "name:fas_x_preferred":[
        "\u0645\u06cc\u062e\u0648\u0627\u0631\u0627\u0646 \u0645\u062d\u0645\u062f \u0622\u0642\u0627"
    ],
    "name:fas_x_variant":[
        "Meykhvor\u0101n-e Mo\u1e29ammad \u0100q\u0101",
        "Meykhv\u0101r\u0101n-e Mo\u1e29ammad \u0100q\u0101",
        "\u0645\u06cc\u062e\u0648\u0631\u0627\u0646 \u0645\u062d\u0645\u062f \u0622\u0642\u0627"
    ],
    "name:und_x_variant":[
        "Maikhoran\u00e9 Mohammad Agh\u0101",
        "Meykhvor\u0101n",
        "Mey Kh\u0101r\u0101n",
        "Meykhowr\u0101n-e Mo\u1e29ammad \u0100q\u0101",
        "Meykhowr\u0101n-e P\u0101\u2019\u012bn"
    ],
    "wof:name":"Meykhowran-e Mohammad Aqa",
    "wof:placetype":"locality"
},
  "geometry": {"coordinates":[47.68596,34.98935],"type":"Point"}
}