{
  "type": "Feature",
  "properties": {
    "gn:admin1_code":"13",
    "gn:asciiname":"Mahaki Pol Mahiyat",
    "gn:country_code":"IR",
    "gn:dem":660,
    "gn:feature_class":"P",
    "gn:feature_code":"PPL",
    "gn:name":"Mahak\u012b Pol M\u0101h\u012byat",
    "gn:population":0,
    "gn:timezone":"Asia/Tehran",
    "iso:country":"IR",
    "name:ceb_x_preferred":[
        "Mahak\u012b Pol M\u0101h\u012byat"
    ],
    "name:fas_x_preferred":[
        "\u0645\u0647\u06a9\u06cc \u067e\u0644 \u0645\u0627\u0647\u06cc\u062a"
    ],
    "name:fas_x_variant":[
        "Pol M\u0101h\u012bt",
        "Mahak\u012b Pol M\u0101h\u012byat",
        "\u067e\u0644\u200c\u0645\u0627\u0647\u06cc\u062a"
    ],
    "name:swe_x_preferred":[
        "Mahak\u012b Pol M\u0101h\u012byat"
    ],
    "name:und_x_variant":[
        "Mahak\u012b P\u016bl M\u0101h\u012b",
        "P\u016bl Mahib",
        "Mahk\u012b Pol M\u0101h\u012b"
    ],
    "wof:name":"Mahaki Pol Mahiyat",
    "wof:placetype":"locality"
},
  "geometry": {"coordinates":[45.92915,34.43499],"type":"Point"}
}