{
  "type": "Feature",
  "properties": {
    "gn:admin1_code":"25",
    "gn:asciiname":"Qal`eh-ye Aqa `Abdollah",
    "gn:country_code":"IR",
    "gn:dem":1422,
    "gn:feature_class":"P",
    "gn:feature_code":"PPL",
    "gn:name":"Qal\u2018eh-ye \u0100q\u0101 \u2018Abdoll\u0101h",
    "gn:population":0,
    "gn:timezone":"Asia/Tehran",
    "iso:country":"IR",
    "name:fas_x_preferred":[
        "\u0642\u0644\u0639\u0647 \u0622\u0642\u0627 \u0639\u0628\u062f \ufdf2"
    ],
    "name:fas_x_variant":[
        "Qal\u2018eh-ye \u0100q\u0101 \u2018Abdoll\u0101h",
        "\u0642\u0644\u0639\u0647 \u0622\u0642\u0627"
    ],
    "name:und_x_variant":[
        "Qal\u2018eh-ye \u0100q\u0101"
    ],
    "wof:name":"Qal`eh-ye Aqa `Abdollah",
    "wof:placetype":"locality"
},
  "geometry": {"coordinates":[55.05737,36.59622],"type":"Point"}
}