{
  "type": "Feature",
  "properties": {
    "gn:admin1_code":"40",
    "gn:asciiname":"Zardeyn",
    "gn:country_code":"IR",
    "gn:dem":2397,
    "gn:feature_class":"P",
    "gn:feature_code":"PPL",
    "gn:name":"Zardeyn",
    "gn:population":0,
    "gn:timezone":"Asia/Tehran",
    "iso:country":"IR",
    "name:fas_x_preferred":[
        "\u0632\u0631\u062f\u064a\u0646"
    ],
    "name:und_x_variant":[
        "Zard Deh",
        "Zardan",
        "Zard\u012bn",
        "Zardeyn"
    ],
    "wof:name":"Zardeyn",
    "wof:placetype":"locality"
},
  "geometry": {"coordinates":[54.23514,31.44392],"type":"Point"}
}