{
  "type": "Feature",
  "properties": {
    "gn:admin1_code":"13",
    "gn:asciiname":"Tazehabad Bati",
    "gn:country_code":"IR",
    "gn:dem":1142,
    "gn:feature_class":"P",
    "gn:feature_code":"PPL",
    "gn:name":"T\u0101zeh\u0101b\u0101d Ba\u0163\u012b",
    "gn:population":0,
    "gn:timezone":"Asia/Tehran",
    "iso:country":"IR",
    "name:fas_x_preferred":[
        "\u062a\u0627\u0632\u0647 \u0622\u0628\u0627\u062f \u0628\u0637\u06cc"
    ],
    "name:fas_x_variant":[
        "T\u0101zeh\u0101b\u0101d Ba\u0163\u012b"
    ],
    "wof:name":"Tazehabad Bati",
    "wof:placetype":"locality"
},
  "geometry": {"coordinates":[46.1207,34.042],"type":"Point"}
}