{
  "type": "Feature",
  "properties": {
    "gn:admin1_code":"28.0",
    "gn:asciiname":"Mazra`eh-ye `Abdollah",
    "gn:country_code":"IR",
    "gn:dem":2295,
    "gn:feature_class":"P",
    "gn:feature_code":"PPL",
    "gn:name":"Mazra\u2018eh-ye \u2018Abdoll\u0101h",
    "gn:population":0,
    "gn:timezone":"Asia/Tehran",
    "iso:country":"IR",
    "name:fas_x_preferred":[
        "\u0645\u0632\u0631\u0639\u0647 \u0639\u0628\u062f \u0627\u0644\u0644\u0651\u0647"
    ],
    "name:fas_x_variant":[
        "Mazra\u2018eh-ye \u2018Abdoll\u0101h"
    ],
    "wof:name":"Mazra`eh-ye `Abdollah",
    "wof:placetype":"locality"
},
  "geometry": {"coordinates":[52.2673,33.0012],"type":"Point"}
}