{
  "type": "Feature",
  "properties": {
    "gn:admin1_code":"5.0",
    "gn:asciiname":"Mowrna",
    "gn:country_code":"IR",
    "gn:dem":1985,
    "gn:feature_class":"P",
    "gn:feature_code":"PPL",
    "gn:name":"Mowrn\u0101",
    "gn:population":0,
    "gn:timezone":"Asia/Tehran",
    "iso:country":"IR",
    "name:fas_x_preferred":[
        "\u0645\u0648\u0631\u062f"
    ],
    "name:fas_x_variant":[
        "\u0645\u0648\u0631\u0646\u0627"
    ],
    "name:und_x_variant":[
        "Mowrd",
        "Mowrn\u0101"
    ],
    "wof:name":"Mowrna",
    "wof:placetype":"locality"
},
  "geometry": {"coordinates":[50.77429,31.03948],"type":"Point"}
}