{
  "type": "Feature",
  "properties": {
    "gn:admin1_code":"23.0",
    "gn:asciiname":"`Abbas-e Galpat",
    "gn:country_code":"IR",
    "gn:dem":1095,
    "gn:feature_class":"P",
    "gn:feature_code":"PPL",
    "gn:name":"\u2018Abb\u0101s-e Galpat",
    "gn:population":0,
    "gn:timezone":"Asia/Tehran",
    "iso:country":"IR",
    "name:fas_x_preferred":[
        "\u2018Abb\u0101s-e Galpat"
    ],
    "name:fas_x_variant":[
        "\u0639\u0628\u0651\u0627\u0633 \u06af\u0644\u067e\u062a",
        "\u2018Abb\u0101s-e Kalpat",
        "\u0639\u0628\u0651\u0627\u0633 \u06a9\u0644\u067e\u062a"
    ],
    "name:und_x_variant":[
        "\u2018Abb\u0101s Kolpat"
    ],
    "wof:name":"`Abbas-e Galpat",
    "wof:placetype":"locality"
},
  "geometry": {"coordinates":[48.0436,33.472],"type":"Point"}
}