{
  "type": "Feature",
  "properties": {
    "gn:admin1_code":"29",
    "gn:asciiname":"Kuh-e Do Rud",
    "gn:country_code":"IR",
    "gn:dem":793,
    "gn:feature_class":"P",
    "gn:feature_code":"PPL",
    "gn:name":"K\u016bh-e Do R\u016bd",
    "gn:population":0,
    "gn:timezone":"Asia/Tehran",
    "iso:country":"IR",
    "name:fas_x_preferred":[
        "\u06a9\u0648\u0647 \u062f\u0648\u0631\u0648\u062f"
    ],
    "name:fas_x_variant":[
        "Kodr\u016bt",
        "K\u016bh-e Do R\u016bd",
        "Kod R\u016bd"
    ],
    "name:und_x_variant":[
        "Kod R\u016bd"
    ],
    "wof:name":"Kuh-e Do Rud",
    "wof:placetype":"locality"
},
  "geometry": {"coordinates":[57.78851,30.20872],"type":"Point"}
}