{
  "type": "Feature",
  "properties": {
    "gn:admin1_code":"15",
    "gn:asciiname":"Darreh Estel",
    "gn:country_code":"IR",
    "gn:dem":835,
    "gn:feature_class":"P",
    "gn:feature_code":"PPL",
    "gn:name":"Darreh Estel",
    "gn:population":0,
    "gn:timezone":"Asia/Tehran",
    "iso:country":"IR",
    "name:ceb_x_preferred":[
        "Darreh Est\u012bl"
    ],
    "name:fas_x_preferred":[
        "Est\u012bl"
    ],
    "name:fas_x_variant":[
        "\u062f\u0631\u0651\u0647 \u0627\u0633\u062a\u06cc\u0644",
        "Darreh Est\u012bl",
        "\u062f\u0631\u0647 \u0627\u0633\u062a\u0644",
        "\u0627\u0633\u0637\u0644"
    ],
    "name:swe_x_preferred":[
        "Darreh Est\u012bl"
    ],
    "name:und_x_variant":[
        "Darreh-ye Est\u012bl",
        "Darreh Est\u012bl",
        "Darreh Estel",
        "Es\u0163el"
    ],
    "wof:name":"Darreh Estel",
    "wof:placetype":"locality"
},
  "geometry": {"coordinates":[49.82381,31.61938],"type":"Point"}
}