{
  "type": "Feature",
  "properties": {
    "gn:admin1_code":"42.0",
    "gn:asciiname":"Badamuk",
    "gn:country_code":"IR",
    "gn:dem":1867,
    "gn:feature_class":"P",
    "gn:feature_code":"PPL",
    "gn:name":"B\u0101d\u0101m\u016bk",
    "gn:population":0,
    "gn:timezone":"Asia/Tehran",
    "iso:country":"IR",
    "name:ara_x_preferred":[
        "\u0628\u0627\u062f\u0627\u0645\u0648\u0643"
    ],
    "name:ceb_x_preferred":[
        "B\u0101d\u0101m\u016bk"
    ],
    "name:fas_x_preferred":[
        "B\u0101d\u016bmak"
    ],
    "name:fas_x_variant":[
        "B\u0101d\u0101m\u016bk",
        "\u0628\u0627\u062f\u0648\u0645\u06a9",
        "B\u0101d\u0101m\u016bn",
        "B\u0101d\u0101mak",
        "\u0628\u0627\u062f\u0627\u0645\u0648\u06a9"
    ],
    "name:swe_x_preferred":[
        "B\u0101d\u0101m\u016bk"
    ],
    "wof:name":"Badamuk",
    "wof:placetype":"locality"
},
  "geometry": {"coordinates":[58.40657,34.13178],"type":"Point"}
}