{
  "type": "Feature",
  "properties": {
    "gn:admin1_code":"15",
    "gn:asciiname":"`Asalu",
    "gn:country_code":"IR",
    "gn:dem":172,
    "gn:feature_class":"P",
    "gn:feature_code":"PPL",
    "gn:name":"\u2018Asal\u016b",
    "gn:population":0,
    "gn:timezone":"Asia/Tehran",
    "iso:country":"IR",
    "name:fas_x_preferred":[
        "\u2018Asal\u016b"
    ],
    "name:fas_x_variant":[
        "\u0639\u0633\u0644\u0648"
    ],
    "wof:name":"`Asalu",
    "wof:placetype":"locality"
},
  "geometry": {"coordinates":[49.62894,31.28864],"type":"Point"}
}