{
  "type": "Feature",
  "properties": {
    "gn:admin1_code":"15",
    "gn:asciiname":"Saleh Kur",
    "gn:country_code":"IR",
    "gn:dem":1145,
    "gn:feature_class":"P",
    "gn:feature_code":"PPL",
    "gn:name":"\u015e\u0101le\u1e29 K\u016br",
    "gn:population":0,
    "gn:timezone":"Asia/Tehran",
    "iso:country":"IR",
    "name:fas_x_preferred":[
        "\u015e\u0101le\u1e29 K\u016br"
    ],
    "wof:name":"Saleh Kur",
    "wof:placetype":"locality"
},
  "geometry": {"coordinates":[49.6925,32.055],"type":"Point"}
}