{
  "type": "Feature",
  "properties": {
    "gn:admin1_code":"40.0",
    "gn:asciiname":"Shahrak-e Emam Hasan",
    "gn:country_code":"IR",
    "gn:dem":1568,
    "gn:feature_class":"P",
    "gn:feature_code":"PPL",
    "gn:name":"Shahrak-e Em\u0101m \u1e28asan",
    "gn:population":0,
    "gn:timezone":"Asia/Tehran",
    "iso:country":"IR",
    "name:fas_x_preferred":[
        "Mazra\u2018eh-ye Moll\u0101"
    ],
    "name:fas_x_variant":[
        "\u0645\u0632\u0631\u0639\u0647 \u0645\u0644\u0627",
        "\u0634\u0647\u0631\u06a9 \u0627\u0645\u0627\u0645 \u062d\u0633\u0646"
    ],
    "name:und_x_variant":[
        "Shahrak-e Em\u0101m \u1e28asan"
    ],
    "wof:name":"Shahrak-e Emam Hasan",
    "wof:placetype":"locality"
},
  "geometry": {"coordinates":[54.41091,31.52967],"type":"Point"}
}