{
  "type": "Feature",
  "properties": {
    "gn:admin1_code":"5",
    "gn:asciiname":"Nazmakan",
    "gn:country_code":"IR",
    "gn:dem":675,
    "gn:feature_class":"P",
    "gn:feature_code":"PPL",
    "gn:name":"N\u0101zmak\u0101n",
    "gn:population":0,
    "gn:timezone":"Asia/Tehran",
    "iso:country":"IR",
    "name:fas_x_preferred":[
        "\u0646\u0627\u0632\u0645\u064e\u0643\u0627\u0646\u0650 \u067e\u0627\u0626\u064a\u0646"
    ],
    "name:fas_x_variant":[
        "N\u0101zmak\u0101n",
        "N\u0101zmak\u0101n-e P\u0101\u2019\u012bn",
        "\u0646\u0627\u0632\u0645\u0643\u0627\u0646"
    ],
    "name:und_x_variant":[
        "\u0646\u0627\u0632\u0645\u0643\u0627\u0646"
    ],
    "wof:name":"Nazmakan",
    "wof:placetype":"locality"
},
  "geometry": {"coordinates":[50.74517,30.63917],"type":"Point"}
}