{
  "type": "Feature",
  "properties": {
    "gn:admin1_code":"16",
    "gn:asciiname":"Hezar Khani",
    "gn:country_code":"IR",
    "gn:dem":1698,
    "gn:feature_class":"P",
    "gn:feature_code":"PPL",
    "gn:name":"Hez\u0101r Kh\u0101n\u012b",
    "gn:population":0,
    "gn:timezone":"Asia/Tehran",
    "iso:country":"IR",
    "name:fas_x_preferred":[
        "\u0647\u0632\u0627\u0631 \u062e\u0627\u0646\u06cc"
    ],
    "name:fas_x_variant":[
        "Haz\u0101r Kh\u0101n\u012b",
        "Hez\u0101r Kh\u0101n\u012b"
    ],
    "name:und_x_variant":[
        "Haz\u0101r Kh\u0101neh"
    ],
    "wof:name":"Hezar Khani",
    "wof:placetype":"locality"
},
  "geometry": {"coordinates":[46.3667,35.3549],"type":"Point"}
}