{
  "type": "Feature",
  "properties": {
    "gn:admin1_code":"1.0",
    "gn:asciiname":"Mirza Hasan",
    "gn:country_code":"IR",
    "gn:dem":1240,
    "gn:feature_class":"P",
    "gn:feature_code":"PPL",
    "gn:name":"M\u012brz\u0101 \u1e28asan",
    "gn:population":0,
    "gn:timezone":"Asia/Tehran",
    "iso:country":"IR",
    "name:fas_x_preferred":[
        "\u0645\u06cc\u0631\u0632\u0627 \u062d\u0633\u0646"
    ],
    "name:fas_x_variant":[
        "M\u012brz\u0101 \u1e28es\u0101m",
        "M\u012brz\u0101 \u1e28asan"
    ],
    "wof:name":"Mirza Hasan",
    "wof:placetype":"locality"
},
  "geometry": {"coordinates":[45.0226,38.9679],"type":"Point"}
}