{
  "type": "Feature",
  "properties": {
    "gn:admin1_code":"9",
    "gn:asciiname":"Chenar-e Sofla",
    "gn:country_code":"IR",
    "gn:dem":1629,
    "gn:feature_class":"P",
    "gn:feature_code":"PPL",
    "gn:name":"Chen\u0101r-e Sofl\u00e1",
    "gn:population":0,
    "gn:timezone":"Asia/Tehran",
    "iso:country":"IR",
    "name:fas_x_preferred":[
        "\u0686\u0646\u0627\u0631 \u0633\u0641\u0644\u06cc"
    ],
    "name:fas_x_variant":[
        "Chen\u0101r-e Sofl\u00e1",
        "\u0634\u06cc\u062e"
    ],
    "name:und_x_variant":[
        "Ch\u012bn\u0101r",
        "Chen\u0101r Sheykh-e Sofl\u00e1",
        "Chen\u0101r Sheykh",
        "Chen\u0101r-e Sheykh",
        "Chen\u0101r",
        "Sheykh"
    ],
    "wof:name":"Chenar-e Sofla",
    "wof:placetype":"locality"
},
  "geometry": {"coordinates":[47.97638,34.77104],"type":"Point"}
}