{
  "type": "Feature",
  "properties": {
    "gn:admin1_code":"4",
    "gn:asciiname":"Kahnuk-e Bala'i",
    "gn:country_code":"IR",
    "gn:dem":928,
    "gn:feature_class":"P",
    "gn:feature_code":"PPL",
    "gn:name":"Kahn\u016bk-e B\u0101l\u0101\u2019\u012b",
    "gn:population":0,
    "gn:timezone":"Asia/Tehran",
    "iso:country":"IR",
    "name:fas_x_preferred":[
        "\u0645\u06af\u06cc \u06a9\u0686\u0648\u06a9"
    ],
    "name:fas_x_variant":[
        "Meg\u012b Kech\u016bk",
        "\u06a9\u0647\u0646\u0648\u06a9 \u0628\u0627\u0644\u0627\u0626\u06cc"
    ],
    "name:und_x_variant":[
        "Kahn\u016bk-e B\u0101l\u0101\u2019\u012b"
    ],
    "wof:name":"Kahnuk-e Bala'i",
    "wof:placetype":"locality"
},
  "geometry": {"coordinates":[59.32986,27.99303],"type":"Point"}
}