{
  "type": "Feature",
  "properties": {
    "gn:admin1_code":"8",
    "gn:asciiname":"Miandeh",
    "gn:country_code":"IR",
    "gn:dem":19,
    "gn:feature_class":"P",
    "gn:feature_code":"PPL",
    "gn:name":"M\u012b\u0101ndeh",
    "gn:population":0,
    "gn:timezone":"Asia/Tehran",
    "iso:country":"IR",
    "name:fas_x_preferred":[
        "M\u012b\u0101ndeh"
    ],
    "name:fas_x_variant":[
        "\u0645\u06cc\u0627\u0646\u062f\u0647"
    ],
    "name:und_x_variant":[
        "\u0645\u06cc\u0627\u0646\u062f\u0647"
    ],
    "wof:name":"Miandeh",
    "wof:placetype":"locality"
},
  "geometry": {"coordinates":[49.71973,37.20758],"type":"Point"}
}