{
  "type": "Feature",
  "properties": {
    "gn:admin1_code":"35",
    "gn:asciiname":"Salah Dar Kola",
    "gn:country_code":"IR",
    "gn:dem":1,
    "gn:feature_class":"P",
    "gn:feature_code":"PPL",
    "gn:name":"\u015eala\u1e29 D\u0101r Kol\u0101",
    "gn:population":0,
    "gn:timezone":"Asia/Tehran",
    "iso:country":"IR",
    "name:fas_x_preferred":[
        "\u0635\u064e\u0644\u0627\u062d \u062f\u0627\u0631 \u0643\u064f\u0644\u0627"
    ],
    "name:fas_x_variant":[
        "\u015eal\u0101\u1e29 D\u0101r Kol\u0101",
        "\u015eala\u1e29 D\u0101r Kol\u0101",
        "\u0635\u0644\u062d \u062f\u0627\u0631 \u0643\u0644\u0627"
    ],
    "wof:name":"Salah Dar Kola",
    "wof:placetype":"locality"
},
  "geometry": {"coordinates":[52.88036999999999,36.54856],"type":"Point"}
}