{
  "type": "Feature",
  "properties": {
    "gn:admin1_code":"35",
    "gn:asciiname":"Bikh Dasht",
    "gn:country_code":"IR",
    "gn:dem":640,
    "gn:feature_class":"P",
    "gn:feature_code":"PPL",
    "gn:name":"B\u012bkh Dasht",
    "gn:population":0,
    "gn:timezone":"Asia/Tehran",
    "iso:country":"IR",
    "name:fas_x_preferred":[
        "\u0628\u06cc\u062e \u062f\u0634\u062a"
    ],
    "name:fas_x_variant":[
        "B\u012bkh Dasht"
    ],
    "wof:name":"Bikh Dasht",
    "wof:placetype":"locality"
},
  "geometry": {"coordinates":[53.04358000000001,36.1416],"type":"Point"}
}