{
  "type": "Feature",
  "properties": {
    "gn:admin1_code":"29",
    "gn:asciiname":"Chah-e Ja`far",
    "gn:country_code":"IR",
    "gn:dem":1452,
    "gn:feature_class":"P",
    "gn:feature_code":"PPL",
    "gn:name":"Ch\u0101h-e Ja\u2018far",
    "gn:population":0,
    "gn:timezone":"Asia/Tehran",
    "iso:country":"IR",
    "name:fas_x_preferred":[
        "Ch\u0101h Ja\u2018far"
    ],
    "name:fas_x_variant":[
        "Ch\u0101h-e Ja\u2018far",
        "\u0686\u0627\u0647 \u062c\u0639\u0641\u0631"
    ],
    "wof:name":"Chah-e Ja`far",
    "wof:placetype":"locality"
},
  "geometry": {"coordinates":[55.93099,30.59447],"type":"Point"}
}