{
  "type": "Feature",
  "properties": {
    "gn:admin1_code":"4.0",
    "gn:asciiname":"Tall-e Siah",
    "gn:cc2":"IR",
    "gn:country_code":"IR",
    "gn:dem":1287,
    "gn:feature_class":"P",
    "gn:feature_code":"PPL",
    "gn:name":"Tall-e S\u012b\u0101h",
    "gn:population":0,
    "gn:timezone":"Asia/Tehran",
    "iso:country":"IR",
    "name:fas_x_preferred":[
        "Tall-e S\u012b\u0101h"
    ],
    "name:und_x_variant":[
        "Tall-e Sey\u0101h"
    ],
    "wof:name":"Tall-e Siah",
    "wof:placetype":"locality"
},
  "geometry": {"coordinates":[60.46666999999999,29.83333],"type":"Point"}
}