{
  "type": "Feature",
  "properties": {
    "gn:admin1_code":"7",
    "gn:asciiname":"Kushk-e Sofla",
    "gn:country_code":"IR",
    "gn:dem":1301,
    "gn:feature_class":"P",
    "gn:feature_code":"PPL",
    "gn:name":"K\u016bshk-e Sofl\u00e1",
    "gn:population":0,
    "gn:timezone":"Asia/Tehran",
    "iso:country":"IR",
    "name:fas_x_preferred":[
        "Keveshk-e P\u0101\u2019\u012bn"
    ],
    "name:fas_x_variant":[
        "K\u016bshk-e Sofl\u00e1",
        "\u06a9\u0648\u0634\u06a9 \u0633\u0641\u0644\u06cc"
    ],
    "name:und_x_variant":[
        "K\u016bshk-e P\u0101\u2019\u012bn",
        "Keveshk P\u0101\u2019\u012bn",
        "K\u016bshk",
        "K\u016bshk-e Sofl\u00e1",
        "\u06a9\u0648\u0634\u06a9 \u0633\u0641\u0644\u06cc"
    ],
    "wof:name":"Kushk-e Sofla",
    "wof:placetype":"locality"
},
  "geometry": {"coordinates":[51.46805,30.42884],"type":"Point"}
}