{
  "type": "Feature",
  "properties": {
    "gn:admin1_code":"29.0",
    "gn:asciiname":"Meshkan",
    "gn:country_code":"IR",
    "gn:dem":2596,
    "gn:feature_class":"P",
    "gn:feature_code":"PPL",
    "gn:name":"Meshk\u0101n",
    "gn:population":0,
    "gn:timezone":"Asia/Tehran",
    "iso:country":"IR",
    "name:ara_x_preferred":[
        "\u0645\u0634\u0643\u0627\u0646"
    ],
    "name:fas_x_preferred":[
        "\u0645\u0634\u06a9\u0627\u0646"
    ],
    "name:fas_x_variant":[
        "Moshg\u0101n",
        "Meshk\u0101n"
    ],
    "wof:name":"Meshkan",
    "wof:placetype":"locality"
},
  "geometry": {"coordinates":[56.6278,29.3722],"type":"Point"}
}