{
  "type": "Feature",
  "properties": {
    "gn:admin1_code":"29",
    "gn:asciiname":"Sarban",
    "gn:country_code":"IR",
    "gn:dem":1505,
    "gn:feature_class":"P",
    "gn:feature_code":"PPL",
    "gn:name":"Sarb\u0101n",
    "gn:population":0,
    "gn:timezone":"Asia/Tehran",
    "iso:country":"IR",
    "name:deu_x_preferred":[
        "Sarban"
    ],
    "name:fas_x_preferred":[
        "\u0633\u0631\u0628\u0627\u0646"
    ],
    "name:fas_x_variant":[
        "Sarb\u0101n"
    ],
    "name:und_x_variant":[
        "Sarbon"
    ],
    "wof:name":"Sarban",
    "wof:placetype":"locality"
},
  "geometry": {"coordinates":[57.78100000000001,27.021],"type":"Point"}
}