{
  "type": "Feature",
  "properties": {
    "gn:admin1_code":"1.0",
    "gn:asciiname":"Gerd Morad Beyg",
    "gn:country_code":"IR",
    "gn:dem":1968,
    "gn:feature_class":"P",
    "gn:feature_code":"PPL",
    "gn:name":"Gerd Morad Beyg",
    "gn:population":0,
    "gn:timezone":"Asia/Tehran",
    "iso:country":"IR",
    "name:fas_x_preferred":[
        "\u06af\u0631\u062f \u0645\u0631\u0627\u062f \u0628\u06cc\u06af"
    ],
    "wof:name":"Gerd Morad Beyg",
    "wof:placetype":"locality"
},
  "geometry": {"coordinates":[45.4102,36.5624],"type":"Point"}
}