{
  "type": "Feature",
  "properties": {
    "gn:admin1_code":"35.0",
    "gn:asciiname":"Hajji Kola",
    "gn:cc2":"IR",
    "gn:country_code":"IR",
    "gn:dem":-15,
    "gn:feature_class":"P",
    "gn:feature_code":"PPL",
    "gn:name":"\u1e28\u0101jj\u012b Kol\u0101",
    "gn:population":0,
    "gn:timezone":"Asia/Tehran",
    "iso:country":"IR",
    "name:fas_x_preferred":[
        "\u062d\u0627\u062c\u0651\u06cc \u0643\u064f\u0644\u0627"
    ],
    "name:fas_x_variant":[
        "\u062d\u0627\u062c\u0651\u06cc \u0643\u064e\u0644\u0627",
        "\u062d\u0627\u062c\u06cc \u0643\u064f\u0644\u0627",
        "\u1e28\u0101jj\u012b Kol\u0101"
    ],
    "name:und_x_variant":[
        "\u1e28\u0101jj\u012b Kal\u0101",
        "\u1e28\u0101j\u012b Kol\u0101"
    ],
    "wof:name":"Hajji Kola",
    "wof:placetype":"locality"
},
  "geometry": {"coordinates":[52.76056,36.6675],"type":"Point"}
}