{
  "type": "Feature",
  "properties": {
    "gn:admin1_code":"40",
    "gn:asciiname":"Vizhdaneh",
    "gn:country_code":"IR",
    "gn:dem":1503,
    "gn:feature_class":"P",
    "gn:feature_code":"PPL",
    "gn:name":"V\u012bzhd\u0101neh",
    "gn:population":0,
    "gn:timezone":"Asia/Tehran",
    "iso:country":"IR",
    "name:fas_x_preferred":[
        "V\u012bzhd\u0101neh"
    ],
    "name:und_x_variant":[
        "V\u012bzd\u0101neh"
    ],
    "wof:name":"Vizhdaneh",
    "wof:placetype":"locality"
},
  "geometry": {"coordinates":[53.60444,30.79861],"type":"Point"}
}