{
  "type": "Feature",
  "properties": {
    "gn:admin1_code":"29",
    "gn:asciiname":"Mazra`eh-ye Shahid Beheshti",
    "gn:country_code":"IR",
    "gn:dem":395,
    "gn:feature_class":"P",
    "gn:feature_code":"PPLL",
    "gn:name":"Mazra\u2018eh-ye Shah\u012bd Behesht\u012b",
    "gn:population":0,
    "gn:timezone":"Asia/Tehran",
    "iso:country":"IR",
    "name:fas_x_preferred":[
        "\u0645\u0632\u0631\u0639\u0647 \u0634\u0647\u06cc\u062f \u0628\u0647\u0634\u062a\u06cc"
    ],
    "name:fas_x_variant":[
        "Mazra\u2018eh-ye Shah\u012bd Behesht\u012b"
    ],
    "wof:name":"Mazra`eh-ye Shahid Beheshti",
    "wof:placetype":"locality"
},
  "geometry": {"coordinates":[58.32454,27.23641],"type":"Point"}
}