{
  "type": "Feature",
  "properties": {
    "gn:admin1_code":"4",
    "gn:asciiname":"Moradabad",
    "gn:country_code":"IR",
    "gn:dem":732,
    "gn:feature_class":"P",
    "gn:feature_code":"PPL",
    "gn:name":"Mor\u0101d\u0101b\u0101d",
    "gn:population":0,
    "gn:timezone":"Asia/Tehran",
    "iso:country":"IR",
    "name:fas_x_preferred":[
        "\u062c\u0648\u0646\u062f\u0631"
    ],
    "name:fas_x_variant":[
        "J\u016bndar",
        "\u0645\u0631\u0627\u062f \u0622\u0628\u0627\u062f",
        "\u0634\u064a\u0632\u0648\u0627\u0631"
    ],
    "name:und_x_variant":[
        "Mor\u0101d\u0101b\u0101d",
        "Sh\u012bzv\u0101r"
    ],
    "wof:name":"Moradabad",
    "wof:placetype":"locality"
},
  "geometry": {"coordinates":[59.93716,26.87161],"type":"Point"}
}