{
  "type": "Feature",
  "properties": {
    "gn:admin1_code":"13",
    "gn:asciiname":"Marzyani",
    "gn:country_code":"IR",
    "gn:dem":1597,
    "gn:feature_class":"P",
    "gn:feature_code":"PPL",
    "gn:name":"Marzy\u0101n\u012b",
    "gn:population":0,
    "gn:timezone":"Asia/Tehran",
    "iso:country":"IR",
    "name:ceb_x_preferred":[
        "Marzy\u0101n\u012b"
    ],
    "name:fas_x_preferred":[
        "\u0645\u0631\u0632\u06cc\u0627\u0646\u06cc"
    ],
    "name:fas_x_variant":[
        "Marzb\u0101n\u012b",
        "Marzy\u0101n\u012b",
        "\u0645\u0631\u0632\u0628\u0627\u0646\u06cc"
    ],
    "name:fra_x_preferred":[
        "Marzbani"
    ],
    "name:swe_x_preferred":[
        "Marzy\u0101n\u012b"
    ],
    "name:und_x_variant":[
        "Marzeb\u0101n\u012b",
        "Marzab\u0101n\u012b"
    ],
    "wof:name":"Marzyani",
    "wof:placetype":"locality"
},
  "geometry": {"coordinates":[47.0771,34.7124],"type":"Point"}
}