{
  "type": "Feature",
  "properties": {
    "gn:admin1_code":"28",
    "gn:asciiname":"Sa`adatabad",
    "gn:country_code":"IR",
    "gn:dem":2397,
    "gn:feature_class":"P",
    "gn:feature_code":"PPL",
    "gn:name":"Sa\u2018\u0101dat\u0101b\u0101d",
    "gn:population":0,
    "gn:timezone":"Asia/Tehran",
    "iso:country":"IR",
    "name:fas_x_preferred":[
        "Sa\u2018\u0101dat\u0101b\u0101d"
    ],
    "name:fas_x_variant":[
        "\u0633\u0639\u0627\u062f\u062a \u0622\u0628\u0627\u062f"
    ],
    "name:und_x_variant":[
        "S\u0101kht-e Seyd\u0101"
    ],
    "wof:name":"Sa`adatabad",
    "wof:placetype":"locality"
},
  "geometry": {"coordinates":[51.61101,31.6308],"type":"Point"}
}