{
  "type": "Feature",
  "properties": {
    "gn:admin1_code":"4.0",
    "gn:asciiname":"Torond",
    "gn:country_code":"IR",
    "gn:dem":1140,
    "gn:feature_class":"P",
    "gn:feature_code":"PPL",
    "gn:name":"Torond",
    "gn:population":0,
    "gn:timezone":"Asia/Tehran",
    "iso:country":"IR",
    "name:fas_x_preferred":[
        "\u062a\u0631\u0646\u062f"
    ],
    "name:und_x_variant":[
        "Terand",
        "Tarond",
        "Torond"
    ],
    "wof:name":"Torond",
    "wof:placetype":"locality"
},
  "geometry": {"coordinates":[61.5472,26.6107],"type":"Point"}
}