{
  "type": "Feature",
  "properties": {
    "gn:admin1_code":"11",
    "gn:asciiname":"Heydari",
    "gn:country_code":"IR",
    "gn:dem":592,
    "gn:feature_class":"P",
    "gn:feature_code":"PPL",
    "gn:name":"\u1e28eydar\u012b",
    "gn:population":0,
    "gn:timezone":"Asia/Tehran",
    "iso:country":"IR",
    "name:fas_x_preferred":[
        "\u062d\u064a\u062f\u0631\u06cc"
    ],
    "name:fas_x_variant":[
        "\u1e28eydar\u012b",
        "\u062d\u06cc\u062f\u0631\u06cc"
    ],
    "name:msa_x_preferred":[
        "Heydari"
    ],
    "wof:name":"Heydari",
    "wof:placetype":"locality"
},
  "geometry": {"coordinates":[57.0885,27.6154],"type":"Point"}
}