{
  "type": "Feature",
  "properties": {
    "gn:admin1_code":"8.0",
    "gn:asciiname":"Pareh",
    "gn:country_code":"IR",
    "gn:dem":475,
    "gn:feature_class":"P",
    "gn:feature_code":"PPL",
    "gn:name":"Pareh",
    "gn:population":0,
    "gn:timezone":"Asia/Tehran",
    "iso:country":"IR",
    "name:fas_x_preferred":[
        "\u067e\u0631\u0647"
    ],
    "name:und_x_variant":[
        "\u067e\u0631\u0647"
    ],
    "wof:name":"Pareh",
    "wof:placetype":"locality"
},
  "geometry": {"coordinates":[49.54355,36.84662],"type":"Point"}
}