{
  "type": "Feature",
  "properties": {
    "gn:admin1_code":"11",
    "gn:asciiname":"Gazi",
    "gn:country_code":"IR",
    "gn:dem":7,
    "gn:feature_class":"P",
    "gn:feature_code":"PPL",
    "gn:name":"Gaz\u012b",
    "gn:population":0,
    "gn:timezone":"Asia/Tehran",
    "iso:country":"IR",
    "name:fas_x_preferred":[
        "\u06af\u0632\u06cc"
    ],
    "name:fas_x_variant":[
        "Gaz\u012b"
    ],
    "name:msa_x_preferred":[
        "Gazi"
    ],
    "wof:name":"Gazi",
    "wof:placetype":"locality"
},
  "geometry": {"coordinates":[57.23119000000001,26.07189],"type":"Point"}
}