{
  "type": "Feature",
  "properties": {
    "gn:admin1_code":"11",
    "gn:asciiname":"Tonbeh",
    "gn:country_code":"IR",
    "gn:dem":17,
    "gn:feature_class":"P",
    "gn:feature_code":"PPL",
    "gn:name":"Tonbeh",
    "gn:population":0,
    "gn:timezone":"Asia/Tehran",
    "iso:country":"IR",
    "name:ceb_x_preferred":[
        "Tonbeh"
    ],
    "name:fas_x_preferred":[
        "Tonb T\u016bch"
    ],
    "name:fas_x_variant":[
        "\u062a\u0646\u0628\u0647",
        "\u062a\u0645 \u06af\u0648\u0647\u0631",
        "\u062a\u0645\u0628 \u06af\u0648\u0647\u0631",
        "\u062a\u0648\u0645 \u06af\u0648\u0647\u0631"
    ],
    "name:msa_x_preferred":[
        "Tomb-e Gowhar"
    ],
    "name:swe_x_preferred":[
        "Tonbeh"
    ],
    "name:und_x_variant":[
        "Tomb T\u016bch",
        "Tam-e Gowhar",
        "Towm-e Gowhar"
    ],
    "wof:name":"Tonbeh",
    "wof:placetype":"locality"
},
  "geometry": {"coordinates":[57.00109000000001,27.11553],"type":"Point"}
}