{
  "type": "Feature",
  "properties": {
    "gn:admin1_code":"13",
    "gn:asciiname":"Jujar",
    "gn:country_code":"IR",
    "gn:dem":1548,
    "gn:feature_class":"P",
    "gn:feature_code":"PPL",
    "gn:name":"J\u016bj\u0101r",
    "gn:population":0,
    "gn:timezone":"Asia/Tehran",
    "iso:country":"IR",
    "name:fas_x_preferred":[
        "J\u016bj\u0101r"
    ],
    "name:fas_x_variant":[
        "\u062c\u0648\u062c\u0627\u0631"
    ],
    "wof:name":"Jujar",
    "wof:placetype":"locality"
},
  "geometry": {"coordinates":[47.4201,34.1259],"type":"Point"}
}