{
  "type": "Feature",
  "properties": {
    "gn:admin1_code":"15",
    "gn:asciiname":"Seh Boneh-ye `Olya",
    "gn:country_code":"IR",
    "gn:dem":37,
    "gn:feature_class":"P",
    "gn:feature_code":"PPL",
    "gn:name":"Seh Boneh-ye \u2018Oly\u0101",
    "gn:population":0,
    "gn:timezone":"Asia/Tehran",
    "iso:country":"IR",
    "name:ceb_x_preferred":[
        "Seh Boneh-ye \u2018Oly\u0101"
    ],
    "name:fas_x_preferred":[
        "\u0633\u0647 \u0628\u0646\u0647 \u0639\u0644\u06cc\u0627"
    ],
    "name:fas_x_variant":[
        "Seh Boneh-ye B\u0101l\u0101",
        "Seh Boneh-ye \u2018Oly\u0101",
        "\u0633\u0647 \u0628\u0646\u0647"
    ],
    "name:swe_x_preferred":[
        "Seh Boneh-ye \u2018Oly\u0101"
    ],
    "name:und_x_variant":[
        "Seh Boneh"
    ],
    "wof:name":"Seh Boneh-ye `Olya",
    "wof:placetype":"locality"
},
  "geometry": {"coordinates":[48.88662,31.92728],"type":"Point"}
}