{
  "type": "Feature",
  "properties": {
    "gn:admin1_code":"9",
    "gn:asciiname":"Tazeh Kand",
    "gn:country_code":"IR",
    "gn:dem":1732,
    "gn:feature_class":"P",
    "gn:feature_code":"PPL",
    "gn:name":"T\u0101zeh Kand",
    "gn:population":0,
    "gn:timezone":"Asia/Tehran",
    "iso:country":"IR",
    "name:fas_x_preferred":[
        "\u062a\u0627\u0632\u0650\u0647 \u0643\u064e\u0646\u062f"
    ],
    "name:fas_x_variant":[
        "T\u0101zeh Kand"
    ],
    "wof:name":"Tazeh Kand",
    "wof:placetype":"locality"
},
  "geometry": {"coordinates":[48.43333,34.96667],"type":"Point"}
}