{
  "type": "Feature",
  "properties": {
    "gn:admin1_code":"33",
    "gn:asciiname":"Abriq",
    "gn:country_code":"IR",
    "gn:dem":1601,
    "gn:feature_class":"P",
    "gn:feature_code":"PPL",
    "gn:name":"Abr\u012bq",
    "gn:population":0,
    "gn:timezone":"Asia/Tehran",
    "iso:country":"IR",
    "name:ara_x_preferred":[
        "\u0623\u0628\u0631\u064a\u0642"
    ],
    "name:azb_x_preferred":[
        "\u0627\u0628\u0631\u06cc\u0642"
    ],
    "name:ceb_x_preferred":[
        "Abr\u012bq"
    ],
    "name:fas_x_preferred":[
        "\u0627\u0628\u0631\u06cc\u0642"
    ],
    "name:fas_x_variant":[
        "Abr\u012bq"
    ],
    "name:msa_x_preferred":[
        "Abriq"
    ],
    "name:swe_x_preferred":[
        "Abr\u012bq"
    ],
    "wof:name":"Abriq",
    "wof:placetype":"locality"
},
  "geometry": {"coordinates":[46.9243,38.565],"type":"Point"}
}