{
  "type": "Feature",
  "properties": {
    "gn:admin1_code":"41.0",
    "gn:asciiname":"Kalat-e Baba",
    "gn:country_code":"IR",
    "gn:dem":1600,
    "gn:feature_class":"P",
    "gn:feature_code":"PPL",
    "gn:name":"Kal\u0101t-e B\u0101b\u0101",
    "gn:population":0,
    "gn:timezone":"Asia/Tehran",
    "iso:country":"IR",
    "name:fas_x_preferred":[
        "\u06a9\u0644\u0627\u062a \u0628\u0627\u0644\u0627"
    ],
    "name:fas_x_variant":[
        "\u06a9\u0644\u0627\u062a \u0628\u0627\u0628\u0627"
    ],
    "name:und_x_variant":[
        "Kal\u0101t-e B\u0101l\u0101",
        "Kal\u0101t-e B\u0101b\u0101",
        "Kal\u0101teh-ye B\u0101l\u0101",
        "Kalateh Bala Nahar Khan",
        "Kal\u0101teh B\u0101la"
    ],
    "wof:name":"Kalat-e Baba",
    "wof:placetype":"locality"
},
  "geometry": {"coordinates":[59.25884,32.82467],"type":"Point"}
}