{
  "type": "Feature",
  "properties": {
    "gn:admin1_code":"29",
    "gn:asciiname":"Deh Musa",
    "gn:country_code":"IR",
    "gn:dem":1848,
    "gn:feature_class":"P",
    "gn:feature_code":"PPL",
    "gn:name":"Deh M\u016bs\u00e1",
    "gn:population":0,
    "gn:timezone":"Asia/Tehran",
    "iso:country":"IR",
    "name:fas_x_preferred":[
        "Deh M\u016bs\u00e1"
    ],
    "wof:name":"Deh Musa",
    "wof:placetype":"locality"
},
  "geometry": {"coordinates":[55.09166999999999,30.11222],"type":"Point"}
}