{
  "type": "Feature",
  "properties": {
    "gn:admin1_code":"8.0",
    "gn:asciiname":"Dafsar",
    "gn:country_code":"IR",
    "gn:dem":3,
    "gn:feature_class":"P",
    "gn:feature_code":"PPLF",
    "gn:name":"D\u0101fs\u0101r",
    "gn:population":0,
    "gn:timezone":"Asia/Tehran",
    "iso:country":"IR",
    "name:fas_x_preferred":[
        "\u062f\u0627\u0641\u0633\u0627\u0631"
    ],
    "name:und_x_variant":[
        "D\u0101fs\u0101r"
    ],
    "wof:name":"Dafsar",
    "wof:placetype":"locality"
},
  "geometry": {"coordinates":[49.46703,37.24859],"type":"Point"}
}