{
  "type": "Feature",
  "properties": {
    "gn:admin1_code":"35",
    "gn:asciiname":"Pa'in Gardan Bori",
    "gn:country_code":"IR",
    "gn:dem":-4,
    "gn:feature_class":"P",
    "gn:feature_code":"PPL",
    "gn:name":"P\u0101\u2019\u012bn Gardan Bor\u012b",
    "gn:population":0,
    "gn:timezone":"Asia/Tehran",
    "iso:country":"IR",
    "name:fas_x_preferred":[
        "\u067e\u0627\u0626\u064a\u0646 \u06af\u0631\u062f\u0646 \u0628\u0631\u06cc"
    ],
    "name:fas_x_variant":[
        "P\u0101\u2019\u012bn Gardan Bor\u012b"
    ],
    "wof:name":"Pa'in Gardan Bori",
    "wof:placetype":"locality"
},
  "geometry": {"coordinates":[52.56098000000001,36.552],"type":"Point"}
}