{
  "type": "Feature",
  "properties": {
    "gn:admin1_code":"15",
    "gn:asciiname":"Lakam",
    "gn:country_code":"IR",
    "gn:dem":1785,
    "gn:feature_class":"P",
    "gn:feature_code":"PPL",
    "gn:name":"L\u0101kam",
    "gn:population":0,
    "gn:timezone":"Asia/Tehran",
    "iso:country":"IR",
    "name:fas_x_preferred":[
        "L\u0101kam"
    ],
    "wof:name":"Lakam",
    "wof:placetype":"locality"
},
  "geometry": {"coordinates":[50.11583,31.84889],"type":"Point"}
}