{
  "type": "Feature",
  "properties": {
    "gn:admin1_code":"33",
    "gn:asciiname":"Choghanlu",
    "gn:country_code":"IR",
    "gn:dem":1418,
    "gn:feature_class":"P",
    "gn:feature_code":"PPL",
    "gn:name":"Chogh\u0101nl\u016b",
    "gn:population":0,
    "gn:timezone":"Asia/Tehran",
    "iso:country":"IR",
    "name:fas_x_preferred":[
        "Chogh\u0101nl\u016b"
    ],
    "wof:name":"Choghanlu",
    "wof:placetype":"locality"
},
  "geometry": {"coordinates":[46.26667,37.05],"type":"Point"}
}