{
  "type": "Feature",
  "properties": {
    "gn:admin1_code":"7",
    "gn:asciiname":"Bast Kutku",
    "gn:country_code":"IR",
    "gn:dem":1458,
    "gn:feature_class":"P",
    "gn:feature_code":"PPL",
    "gn:name":"Bast K\u016btk\u016b",
    "gn:population":0,
    "gn:timezone":"Asia/Tehran",
    "iso:country":"IR",
    "name:fas_x_preferred":[
        "\u0628\u0633\u062a \u06a9\u0648\u062a\u06a9"
    ],
    "name:fas_x_variant":[
        "Bast K\u016btak",
        "\u0628\u0633\u062a \u06a9\u0648\u062a\u06a9\u0648",
        "\u0628\u0633 \u06a9\u0648\u062a\u06a9\u0648"
    ],
    "name:und_x_variant":[
        "Bast K\u016btk\u016b",
        "Bas K\u016btk\u016b"
    ],
    "wof:name":"Bast Kutku",
    "wof:placetype":"locality"
},
  "geometry": {"coordinates":[53.74016999999999,28.45583],"type":"Point"}
}