{
  "type": "Feature",
  "properties": {
    "gn:admin1_code":"13",
    "gn:asciiname":"Kakavand",
    "gn:country_code":"IR",
    "gn:dem":1397,
    "gn:feature_class":"P",
    "gn:feature_code":"PPL",
    "gn:name":"K\u0101k\u0101vand",
    "gn:population":0,
    "gn:timezone":"Asia/Tehran",
    "iso:country":"IR",
    "name:ckb_x_preferred":[
        "\u06a9\u0627\u06a9\u06d5\u0648\u06d5\u0646"
    ],
    "name:fas_x_preferred":[
        "\u06a9\u0627\u06a9\u0627\u0648\u0646\u062f"
    ],
    "name:fas_x_variant":[
        "K\u0101k\u0101vand",
        "\u0627\u06cc\u0644 \u06a9\u0627\u06a9\u0627\u0648\u0646\u062f"
    ],
    "name:kur_x_preferred":[
        "Kakewen"
    ],
    "wof:name":"Kakavand",
    "wof:placetype":"locality"
},
  "geometry": {"coordinates":[47.5298,34.55588],"type":"Point"}
}