{
  "type": "Feature",
  "properties": {
    "gn:admin1_code":"35.0",
    "gn:asciiname":"Kalas",
    "gn:country_code":"IR",
    "gn:dem":561,
    "gn:feature_class":"P",
    "gn:feature_code":"PPL",
    "gn:name":"Kalas",
    "gn:population":0,
    "gn:timezone":"Asia/Tehran",
    "iso:country":"IR",
    "name:ceb_x_preferred":[
        "Kalas"
    ],
    "name:ces_x_preferred":[
        "Kala\u0161"
    ],
    "name:deu_x_preferred":[
        "Kalas"
    ],
    "name:fas_x_preferred":[
        "\u06a9\u0644\u0633"
    ],
    "name:fin_x_preferred":[
        "Kalas"
    ],
    "name:pol_x_preferred":[
        "Kalas"
    ],
    "name:srp_x_preferred":[
        "\u041a\u0430\u043b\u0430\u0441"
    ],
    "name:swe_x_preferred":[
        "Kalas"
    ],
    "wof:name":"Kalas",
    "wof:placetype":"locality"
},
  "geometry": {"coordinates":[52.7039,36.19075],"type":"Point"}
}