{
  "type": "Feature",
  "properties": {
    "gn:admin1_code":"43",
    "gn:asciiname":"Firuzabad",
    "gn:country_code":"IR",
    "gn:dem":1044,
    "gn:feature_class":"P",
    "gn:feature_code":"PPL",
    "gn:name":"F\u012br\u016bz\u0101b\u0101d",
    "gn:population":0,
    "gn:timezone":"Asia/Tehran",
    "iso:country":"IR",
    "name:aze_x_preferred":[
        "Firuzabad"
    ],
    "name:ceb_x_preferred":[
        "Firuzabad"
    ],
    "name:fas_x_preferred":[
        "F\u012br\u016bz\u0101b\u0101d"
    ],
    "name:fas_x_variant":[
        "\u0641\u06cc\u0631\u0648\u0632 \u0622\u0628\u0627\u062f",
        "\u0641\u06cc\u0631\u0648\u0632\u0622\u0628\u0627\u062f"
    ],
    "name:mzn_x_preferred":[
        "\u0641\u06cc\u0631\u0648\u0632\u0622\u0628\u0627\u062f"
    ],
    "name:pnb_x_preferred":[
        "\u0641\u06cc\u0631\u0648\u0632\u0622\u0628\u0627\u062f"
    ],
    "name:pol_x_preferred":[
        "Firuzabad"
    ],
    "name:swe_x_preferred":[
        "Firuzabad"
    ],
    "wof:name":"Firuzabad",
    "wof:placetype":"locality"
},
  "geometry": {"coordinates":[57.79663000000001,37.40992],"type":"Point"}
}