{
  "type": "Feature",
  "properties": {
    "gn:admin1_code":"8",
    "gn:asciiname":"Giga Sar",
    "gn:country_code":"IR",
    "gn:dem":2,
    "gn:feature_class":"P",
    "gn:feature_code":"PPL",
    "gn:name":"G\u012bg\u0101 Sar",
    "gn:population":0,
    "gn:timezone":"Asia/Tehran",
    "iso:country":"IR",
    "name:ara_x_preferred":[
        "\u063a\u064a\u063a\u0627\u0633\u0631"
    ],
    "name:ceb_x_preferred":[
        "G\u012bg\u0101 Sar"
    ],
    "name:fas_x_preferred":[
        "\u06af\u06cc\u06af\u0627 \u0633\u0631"
    ],
    "name:fas_x_variant":[
        "G\u012bg\u0101 Sar",
        "\u06af\u06cc\u06af\u0627\u0633\u0631"
    ],
    "name:msa_x_preferred":[
        "Giga Sar"
    ],
    "name:swe_x_preferred":[
        "G\u012bg\u0101 Sar"
    ],
    "name:ukr_x_preferred":[
        "\u0490\u0456\u0491\u0430-\u0421\u0430\u0440"
    ],
    "wof:name":"Giga Sar",
    "wof:placetype":"locality"
},
  "geometry": {"coordinates":[49.37774,37.26487],"type":"Point"}
}