{
  "type": "Feature",
  "properties": {
    "gn:admin1_code":"32",
    "gn:asciiname":"Hashem",
    "gn:country_code":"IR",
    "gn:dem":324,
    "gn:feature_class":"P",
    "gn:feature_code":"PPL",
    "gn:name":"H\u0101shem",
    "gn:population":0,
    "gn:timezone":"Asia/Tehran",
    "iso:country":"IR",
    "name:fas_x_preferred":[
        "\u0647\u0627\u0634\u0645"
    ],
    "name:fas_x_variant":[
        "H\u0101shem"
    ],
    "wof:name":"Hashem",
    "wof:placetype":"locality"
},
  "geometry": {"coordinates":[47.5458,39.1996],"type":"Point"}
}