{
  "type": "Feature",
  "properties": {
    "gn:admin1_code":"15",
    "gn:asciiname":"Rudkhaneh-ye Fasli-ye Ab Shur",
    "gn:country_code":"IR",
    "gn:dem":436,
    "gn:feature_class":"P",
    "gn:feature_code":"PPL",
    "gn:name":"R\u016bdkh\u0101neh-ye Fa\u015fl\u012b-ye \u0100b Sh\u016br",
    "gn:population":0,
    "gn:timezone":"Asia/Tehran",
    "iso:country":"IR",
    "name:fas_x_preferred":[
        "Lev\u012bs"
    ],
    "name:fas_x_variant":[
        "\u0631\u0648\u062f\u062e\u0627\u0646\u0647 \u0641\u0635\u0644\u06cc \u0622\u0628 \u0634\u0648\u0631",
        "\u0631\u0648\u062f\u062e\u0627\u0646\u0647 \u0644\u064a\u0648\u0633"
    ],
    "name:und_x_variant":[
        "L\u012bvas",
        "R\u016bdkh\u0101neh-ye Fa\u015fl\u012b-ye \u0100b Sh\u016br",
        "R\u016bdkh\u0101neh-ye L\u012bvas"
    ],
    "wof:name":"Rudkhaneh-ye Fasli-ye Ab Shur",
    "wof:placetype":"locality"
},
  "geometry": {"coordinates":[48.6948,32.73461],"type":"Point"}
}