{
  "type": "Feature",
  "properties": {
    "gn:admin1_code":"22.0",
    "gn:asciiname":"Bon-e Sena",
    "gn:country_code":"IR",
    "gn:dem":876,
    "gn:feature_class":"P",
    "gn:feature_code":"PPL",
    "gn:name":"Bon-e Sen\u0101",
    "gn:population":0,
    "gn:timezone":"Asia/Tehran",
    "iso:country":"IR",
    "name:fas_x_preferred":[
        "Bon-e Sen\u0101"
    ],
    "name:fas_x_variant":[
        "\u0628\u0646 \u0633\u0646\u0627"
    ],
    "wof:name":"Bon-e Sena",
    "wof:placetype":"locality"
},
  "geometry": {"coordinates":[51.57213,29.20327],"type":"Point"}
}