{
  "type": "Feature",
  "properties": {
    "gn:admin1_code":"15.0",
    "gn:asciiname":"Abshar",
    "gn:country_code":"IR",
    "gn:dem":9,
    "gn:feature_class":"P",
    "gn:feature_code":"PPL",
    "gn:name":"\u0100bsh\u0101r",
    "gn:population":0,
    "gn:timezone":"Asia/Tehran",
    "iso:country":"IR",
    "name:fas_x_preferred":[
        "\u0100bsh\u0101r"
    ],
    "name:fas_x_variant":[
        "\u0622\u0628\u0634\u0627\u0631"
    ],
    "name:und_x_variant":[
        "\u0622\u0628\u0634\u0627\u0631"
    ],
    "wof:name":"Abshar",
    "wof:placetype":"locality"
},
  "geometry": {"coordinates":[48.7027,30.6369],"type":"Point"}
}