{
  "type": "Feature",
  "properties": {
    "gn:admin1_code":"32",
    "gn:asciiname":"Mir Ja`farlu",
    "gn:country_code":"IR",
    "gn:dem":1279,
    "gn:feature_class":"P",
    "gn:feature_code":"PPL",
    "gn:name":"M\u012br Ja\u2018farl\u016b",
    "gn:population":0,
    "gn:timezone":"Asia/Tehran",
    "iso:country":"IR",
    "name:fas_x_preferred":[
        "\u0645\u064a\u0631 \u062c\u0639\u0641\u0631\u0644\u0648"
    ],
    "name:fas_x_variant":[
        "Mashhad\u012b Ja\u2018far",
        "\u0645\u064e\u0634\u0647\u064e\u062f\u06cc \u062c\u064e\u0639\u0641\u064e\u0631",
        "M\u012br Ja\u2018farl\u016b"
    ],
    "wof:name":"Mir Ja`farlu",
    "wof:placetype":"locality"
},
  "geometry": {"coordinates":[47.7254,38.8693],"type":"Point"}
}