{
  "type": "Feature",
  "properties": {
    "gn:admin1_code":"26.0",
    "gn:asciiname":"Shahrak-e Mahdiyeh",
    "gn:country_code":"IR",
    "gn:dem":1183,
    "gn:feature_class":"P",
    "gn:feature_code":"PPL",
    "gn:name":"Shahrak-e Mahd\u012byeh",
    "gn:population":0,
    "gn:timezone":"Asia/Tehran",
    "iso:country":"IR",
    "name:fas_x_preferred":[
        "\u0634\u0647\u0631\u06a9 \u0645\u0647\u062f\u06cc\u0647"
    ],
    "name:fas_x_variant":[
        "Shahrak-e Mahd\u012byeh"
    ],
    "name:msa_x_preferred":[
        "Shahrak-e Mahdiyeh"
    ],
    "wof:name":"Shahrak-e Mahdiyeh",
    "wof:placetype":"locality"
},
  "geometry": {"coordinates":[50.8575,35.7201],"type":"Point"}
}