{
  "type": "Feature",
  "properties": {
    "gn:admin1_code":"4",
    "gn:asciiname":"Hasht Yek-e Bala",
    "gn:country_code":"IR",
    "gn:dem":674,
    "gn:feature_class":"P",
    "gn:feature_code":"PPL",
    "gn:name":"Hasht Yek-e B\u0101l\u0101",
    "gn:population":0,
    "gn:timezone":"Asia/Tehran",
    "iso:country":"IR",
    "name:fas_x_preferred":[
        "\u0647\u0634\u062a \u06cc\u0643 \u0628\u0627\u0644\u0627"
    ],
    "name:fas_x_variant":[
        "Hasht Yek-e B\u0101l\u0101"
    ],
    "wof:name":"Hasht Yek-e Bala",
    "wof:placetype":"locality"
},
  "geometry": {"coordinates":[60.0716,26.3596],"type":"Point"}
}