{
  "type": "Feature",
  "properties": {
    "gn:admin1_code":"29",
    "gn:asciiname":"Ziarat Mir Meghdad",
    "gn:country_code":"IR",
    "gn:dem":408,
    "gn:feature_class":"P",
    "gn:feature_code":"PPL",
    "gn:name":"Z\u012b\u0101rat M\u012br Meghd\u0101d",
    "gn:population":0,
    "gn:timezone":"Asia/Tehran",
    "iso:country":"IR",
    "name:fas_x_preferred":[
        "\u0632\u064a\u0627\u0631\u062a \u0645\u064a\u0631 \u0645\u063a\u062f\u0627\u062f"
    ],
    "name:fas_x_variant":[
        "\u0632\u06cc\u0627\u0631\u062a"
    ],
    "name:und_x_variant":[
        "Z\u012b\u0101rat M\u012br Meghd\u0101d",
        "Z\u012b\u0101rat"
    ],
    "wof:name":"Ziarat Mir Meghdad",
    "wof:placetype":"locality"
},
  "geometry": {"coordinates":[58.33815,27.82408],"type":"Point"}
}