{
  "type": "Feature",
  "properties": {
    "gn:admin1_code":"33",
    "gn:asciiname":"Aq Beraz",
    "gn:country_code":"IR",
    "gn:dem":975,
    "gn:feature_class":"P",
    "gn:feature_code":"PPL",
    "gn:name":"\u0100q Ber\u0101z",
    "gn:population":0,
    "gn:timezone":"Asia/Tehran",
    "iso:country":"IR",
    "name:ara_x_preferred":[
        "\u0623\u0642 \u0628\u0631\u0627\u0632"
    ],
    "name:azb_x_preferred":[
        "\u0622\u0642\u200c\u0628\u0631\u0627\u0632"
    ],
    "name:ceb_x_preferred":[
        "\u0100q Ber\u0101z"
    ],
    "name:fas_x_preferred":[
        "\u0622\u0642 \u0628\u0631\u0627\u0632"
    ],
    "name:fas_x_variant":[
        "\u0100q Ber\u0101z",
        "\u0622\u0642\u200c\u0628\u0631\u0627\u0632"
    ],
    "name:msa_x_preferred":[
        "Aq Beraz"
    ],
    "name:swe_x_preferred":[
        "\u0100q Ber\u0101z"
    ],
    "name:und_x_variant":[
        "\u0100q Bar\u0101r"
    ],
    "wof:name":"Aq Beraz",
    "wof:placetype":"locality"
},
  "geometry": {"coordinates":[47.3927,39.0108],"type":"Point"}
}