{
  "type": "Feature",
  "properties": {
    "gn:admin1_code":"10",
    "gn:asciiname":"`Arab Rudbar",
    "gn:country_code":"IR",
    "gn:dem":744,
    "gn:feature_class":"P",
    "gn:feature_code":"PPL",
    "gn:name":"\u2018Arab R\u016bdb\u0101r",
    "gn:population":0,
    "gn:timezone":"Asia/Tehran",
    "iso:country":"IR",
    "name:fas_x_preferred":[
        "\u0639\u0631\u0628 \u0631\u0648\u062f\u0628\u0627\u0631"
    ],
    "name:fas_x_variant":[
        "\u2018Arab R\u016bdb\u0101r"
    ],
    "wof:name":"`Arab Rudbar",
    "wof:placetype":"locality"
},
  "geometry": {"coordinates":[46.9563,33.4563],"type":"Point"}
}