{
  "type": "Feature",
  "properties": {
    "gn:admin1_code":"23",
    "gn:asciiname":"Shineh",
    "gn:country_code":"IR",
    "gn:dem":1579,
    "gn:feature_class":"P",
    "gn:feature_code":"PPL",
    "gn:name":"Sh\u012bneh",
    "gn:population":0,
    "gn:timezone":"Asia/Tehran",
    "iso:country":"IR",
    "name:fas_x_preferred":[
        "\u0634\u06cc\u0646\u0647 \u0628\u0627\u062c\u06a9"
    ],
    "name:fas_x_variant":[
        "Sh\u012bneh-ye B\u0101joq",
        "Sh\u012bneh-ye B\u0101jek",
        "\u0634\u06cc\u0646\u0647"
    ],
    "name:und_x_variant":[
        "Sh\u012bneh"
    ],
    "wof:name":"Shineh",
    "wof:placetype":"locality"
},
  "geometry": {"coordinates":[47.7811,33.8598],"type":"Point"}
}