{
  "type": "Feature",
  "properties": {
    "gn:admin1_code":"25",
    "gn:asciiname":"Chongi",
    "gn:country_code":"IR",
    "gn:dem":2443,
    "gn:feature_class":"P",
    "gn:feature_code":"PPL",
    "gn:name":"Chong\u012b",
    "gn:population":0,
    "gn:timezone":"Asia/Tehran",
    "iso:country":"IR",
    "name:fas_x_preferred":[
        "\u0686\u064f\u0646\u06af\u06cc"
    ],
    "name:fas_x_variant":[
        "Chong\u012b"
    ],
    "wof:name":"Chongi",
    "wof:placetype":"locality"
},
  "geometry": {"coordinates":[54.04639,36.43111],"type":"Point"}
}