{
  "type": "Feature",
  "properties": {
    "gn:admin1_code":"8",
    "gn:asciiname":"Gushlavandan",
    "gn:country_code":"IR",
    "gn:dem":22,
    "gn:feature_class":"P",
    "gn:feature_code":"PPL",
    "gn:name":"G\u016bshlavand\u0101n",
    "gn:population":0,
    "gn:timezone":"Asia/Tehran",
    "iso:country":"IR",
    "name:ara_x_preferred":[
        "\u063a\u0648\u0634\u0644\u0648\u0646\u062f\u0627\u0646"
    ],
    "name:ceb_x_preferred":[
        "G\u016bsh\u012b Lavand\u0101n"
    ],
    "name:fas_x_preferred":[
        "\u06af\u0648\u0634\u06cc \u0644\u0648\u0646\u062f\u0627\u0646"
    ],
    "name:fas_x_variant":[
        "G\u016bshlavand\u0101n",
        "G\u016bsh\u012b Lavand\u0101n",
        "\u06af\u0648\u0634\u0644\u0648\u0646\u062f\u0627\u0646"
    ],
    "name:msa_x_preferred":[
        "Gushlavandan"
    ],
    "name:swe_x_preferred":[
        "G\u016bsh\u012b Lavand\u0101n"
    ],
    "name:ukr_x_preferred":[
        "\u0490\u0443\u0448\u043b\u0430\u0432\u0430\u043d\u0434\u0430\u043d"
    ],
    "name:und_x_variant":[
        "K\u016bshalvand\u0101n",
        "Koshlyavandan"
    ],
    "wof:name":"Gushlavandan",
    "wof:placetype":"locality"
},
  "geometry": {"coordinates":[49.35927,37.22112],"type":"Point"}
}