{
  "type": "Feature",
  "properties": {
    "gn:admin1_code":"0",
    "gn:asciiname":"Koreh Muchi",
    "gn:country_code":"IR",
    "gn:dem":408,
    "gn:feature_class":"P",
    "gn:feature_code":"PPL",
    "gn:name":"Koreh M\u016bch\u012b",
    "gn:population":0,
    "gn:timezone":"Asia/Tehran",
    "iso:country":"IR",
    "name:fas_x_preferred":[
        "\u06a9\u0631\u0647 \u0645\u0648\u0686\u06cc"
    ],
    "name:fas_x_variant":[
        "Koreh M\u016bch\u012b"
    ],
    "name:msa_x_preferred":[
        "Koreh Muchi"
    ],
    "wof:name":"Koreh Muchi",
    "wof:placetype":"locality"
},
  "geometry": {"coordinates":[53.2774,27.3064],"type":"Point"}
}