{
  "type": "Feature",
  "properties": {
    "gn:admin1_code":"8",
    "gn:asciiname":"Miska",
    "gn:country_code":"IR",
    "gn:dem":1717,
    "gn:feature_class":"P",
    "gn:feature_code":"PPL",
    "gn:name":"M\u012bsk\u0101",
    "gn:population":0,
    "gn:timezone":"Asia/Tehran",
    "iso:country":"IR",
    "name:deu_x_preferred":[
        "Miska"
    ],
    "name:fas_x_preferred":[
        "\u0645\u064a\u0633\u0643\u0627"
    ],
    "name:fas_x_variant":[
        "M\u012bsk\u0101"
    ],
    "name:fin_x_preferred":[
        "Miska"
    ],
    "wof:name":"Miska",
    "wof:placetype":"locality"
},
  "geometry": {"coordinates":[49.03389,37.22],"type":"Point"}
}