{
  "type": "Feature",
  "properties": {
    "gn:admin1_code":"1.0",
    "gn:asciiname":"Qahhar Kandi",
    "gn:country_code":"IR",
    "gn:dem":1286,
    "gn:feature_class":"P",
    "gn:feature_code":"PPL",
    "gn:name":"Qahh\u0101r Kand\u012b",
    "gn:population":0,
    "gn:timezone":"Asia/Tehran",
    "iso:country":"IR",
    "name:fas_x_preferred":[
        "Qahh\u0101r Kand\u012b"
    ],
    "name:fas_x_variant":[
        "\u0642\u064e\u0647\u0651\u0627\u0631 \u0643\u064e\u0646\u062f\u06cc"
    ],
    "wof:name":"Qahhar Kandi",
    "wof:placetype":"locality"
},
  "geometry": {"coordinates":[46.06667,36.91667],"type":"Point"}
}