{
  "type": "Feature",
  "properties": {
    "gn:admin1_code":"8.0",
    "gn:asciiname":"Patardabl",
    "gn:country_code":"IR",
    "gn:dem":1022,
    "gn:feature_class":"P",
    "gn:feature_code":"PPL",
    "gn:name":"Patardabl",
    "gn:population":0,
    "gn:timezone":"Asia/Tehran",
    "iso:country":"IR",
    "name:fas_x_preferred":[
        "\u067e\u062a\u0631\u062f\u0628\u0644"
    ],
    "name:und_x_variant":[
        "P\u012btert\u016bl"
    ],
    "wof:name":"Patardabl",
    "wof:placetype":"locality"
},
  "geometry": {"coordinates":[49.664,36.866],"type":"Point"}
}