{
  "type": "Feature",
  "properties": {
    "gn:admin1_code":"32.0",
    "gn:asciiname":"Sar Band",
    "gn:country_code":"IR",
    "gn:dem":94,
    "gn:feature_class":"P",
    "gn:feature_code":"PPL",
    "gn:name":"Sar Band",
    "gn:population":0,
    "gn:timezone":"Asia/Tehran",
    "iso:country":"IR",
    "name:fas_x_preferred":[
        "\u0633\u064e\u0631 \u0628\u064e\u0646\u062f"
    ],
    "wof:name":"Sar Band",
    "wof:placetype":"locality"
},
  "geometry": {"coordinates":[47.68167,39.53528],"type":"Point"}
}