{
  "type": "Feature",
  "properties": {
    "gn:admin1_code":"43.0",
    "gn:asciiname":"Ruy-e Tangeh-ye Raz",
    "gn:country_code":"IR",
    "gn:dem":997,
    "gn:feature_class":"P",
    "gn:feature_code":"PPL",
    "gn:name":"R\u016by-e Tangeh-ye R\u0101z",
    "gn:population":0,
    "gn:timezone":"Asia/Tehran",
    "iso:country":"IR",
    "name:fas_x_preferred":[
        "\u0631\u0648\u06cc \u062a\u0646\u06af\u0647 \u0631\u0627\u0632"
    ],
    "name:und_x_variant":[
        "R\u016by-e Tangeh-ye R\u0101z"
    ],
    "wof:name":"Ruy-e Tangeh-ye Raz",
    "wof:placetype":"locality"
},
  "geometry": {"coordinates":[56.91819,37.94116],"type":"Point"}
}