{
  "type": "Feature",
  "properties": {
    "gn:admin1_code":"11",
    "gn:asciiname":"Kharaji",
    "gn:country_code":"IR",
    "gn:dem":185,
    "gn:feature_class":"P",
    "gn:feature_code":"PPL",
    "gn:name":"Khar\u0101j\u012b",
    "gn:population":0,
    "gn:timezone":"Asia/Tehran",
    "iso:country":"IR",
    "name:fas_x_preferred":[
        "\u062e\u0631\u0627\u062c\u06cc"
    ],
    "name:fas_x_variant":[
        "Khar\u0101j\u012b"
    ],
    "name:und_x_variant":[
        "Kher\u0101j\u012b"
    ],
    "wof:name":"Kharaji",
    "wof:placetype":"locality"
},
  "geometry": {"coordinates":[57.23705,27.40267],"type":"Point"}
}