{
  "type": "Feature",
  "properties": {
    "gn:admin1_code":"28",
    "gn:asciiname":"Do Rahan",
    "gn:country_code":"IR",
    "gn:dem":2118,
    "gn:feature_class":"P",
    "gn:feature_code":"PPL",
    "gn:name":"Do R\u0101h\u0101n",
    "gn:population":0,
    "gn:timezone":"Asia/Tehran",
    "iso:country":"IR",
    "name:fas_x_preferred":[
        "Do R\u0101h\u0101n"
    ],
    "name:fas_x_variant":[
        "Dowr\u0101h\u0101n",
        "\u062f\u0648 \u0631\u0627\u0647\u0627\u0646",
        "\u062f\u0648\u0631\u0627\u0647\u0627\u0646"
    ],
    "wof:name":"Do Rahan",
    "wof:placetype":"locality"
},
  "geometry": {"coordinates":[51.64589,30.92261],"type":"Point"}
}