{
  "type": "Feature",
  "properties": {
    "gn:admin1_code":"7",
    "gn:asciiname":"Rirgadiki",
    "gn:country_code":"IR",
    "gn:dem":2427,
    "gn:feature_class":"P",
    "gn:feature_code":"PPL",
    "gn:name":"R\u012brgad\u012bk\u012b",
    "gn:population":0,
    "gn:timezone":"Asia/Tehran",
    "iso:country":"IR",
    "name:fas_x_preferred":[
        "R\u012brgad\u012bk\u012b"
    ],
    "wof:name":"Rirgadiki",
    "wof:placetype":"locality"
},
  "geometry": {"coordinates":[51.96194000000001,31.06944],"type":"Point"}
}