{
  "type": "Feature",
  "properties": {
    "gn:admin1_code":"8",
    "gn:asciiname":"Khaneh Meydan",
    "gn:country_code":"IR",
    "gn:dem":2274,
    "gn:feature_class":"P",
    "gn:feature_code":"PPL",
    "gn:name":"Kh\u0101neh Meyd\u0101n",
    "gn:population":0,
    "gn:timezone":"Asia/Tehran",
    "iso:country":"IR",
    "name:fas_x_preferred":[
        "\u062e\u0627\u0646\u0647 \u0645\u06cc\u062f\u0627\u0646"
    ],
    "name:fas_x_variant":[
        "Kh\u0101neh Meyd\u0101n"
    ],
    "wof:name":"Khaneh Meydan",
    "wof:placetype":"locality"
},
  "geometry": {"coordinates":[48.7758,37.44648],"type":"Point"}
}