{
  "type": "Feature",
  "properties": {
    "gn:admin1_code":"29",
    "gn:asciiname":"Heydarabad",
    "gn:country_code":"IR",
    "gn:dem":655,
    "gn:feature_class":"P",
    "gn:feature_code":"PPL",
    "gn:name":"\u1e28eydar\u0101b\u0101d",
    "gn:population":0,
    "gn:timezone":"Asia/Tehran",
    "iso:country":"IR",
    "name:fas_x_preferred":[
        "\u062d\u06cc\u062f\u0631 \u0622\u0628\u0627\u062f"
    ],
    "name:fas_x_variant":[
        "\u1e28eydar\u0101b\u0101d",
        "\u062d\u06cc\u062f\u0631 \u0622\u0628\u0627\u062f \u0686\u0627\u0647 \u0646\u0627\u0631\u0646\u062c"
    ],
    "name:und_x_variant":[
        "Heidar Abad Kahnooj",
        "\u1e28eydar\u0101b\u0101d-e Ch\u0101h N\u0101renj"
    ],
    "wof:name":"Heydarabad",
    "wof:placetype":"locality"
},
  "geometry": {"coordinates":[57.38763,28.17388],"type":"Point"}
}