{
  "type": "Feature",
  "properties": {
    "gn:admin1_code":"35",
    "gn:asciiname":"Vasat Kola",
    "gn:country_code":"IR",
    "gn:dem":88,
    "gn:feature_class":"P",
    "gn:feature_code":"PPL",
    "gn:name":"Vasa\u0163 Kol\u0101",
    "gn:population":0,
    "gn:timezone":"Asia/Tehran",
    "iso:country":"IR",
    "name:fas_x_preferred":[
        "\u0648\u064f\u0633\u0637\u064e\u0649 \u0643\u064f\u0644\u0627"
    ],
    "name:fas_x_variant":[
        "Vos\u0163\u00e1 Kol\u0101",
        "Vasa\u0163 Kol\u0101",
        "\u0648\u0633\u0637 \u0643\u0644\u0627"
    ],
    "wof:name":"Vasat Kola",
    "wof:placetype":"locality"
},
  "geometry": {"coordinates":[52.883,36.41901],"type":"Point"}
}