{
  "type": "Feature",
  "properties": {
    "gn:admin1_code":"8",
    "gn:asciiname":"`Ali Gavabar",
    "gn:country_code":"IR",
    "gn:dem":241,
    "gn:feature_class":"P",
    "gn:feature_code":"PPL",
    "gn:name":"\u2018Al\u012b Gav\u0101bar",
    "gn:population":0,
    "gn:timezone":"Asia/Tehran",
    "iso:country":"IR",
    "name:fas_x_preferred":[
        "Tam\u0101s Gav\u0101bar"
    ],
    "name:fas_x_variant":[
        "\u062a\u0645\u0627\u0633 \u06af\u0648\u0627\u0628\u0631",
        "\u0639\u0644\u06cc \u06af\u0648\u0627\u0628\u0631"
    ],
    "name:und_x_variant":[
        "\u2018Al\u012b Gav\u0101bar"
    ],
    "wof:name":"`Ali Gavabar",
    "wof:placetype":"locality"
},
  "geometry": {"coordinates":[50.16177,37.06398],"type":"Point"}
}