{
  "type": "Feature",
  "properties": {
    "gn:admin1_code":"28.0",
    "gn:asciiname":"Harpazeh Jabal",
    "gn:country_code":"IR",
    "gn:dem":2137,
    "gn:feature_class":"P",
    "gn:feature_code":"PPL",
    "gn:name":"Harpazeh Jabal",
    "gn:population":0,
    "gn:timezone":"Asia/Tehran",
    "iso:country":"IR",
    "name:eng_x_preferred":[
        "Harpazeh Jabal"
    ],
    "name:eng_x_variant":[
        "Har\u012bzeh"
    ],
    "name:fas_x_preferred":[
        "\u0647\u0631\u067e\u0632\u0647 \u062c\u0628\u0644"
    ],
    "name:fas_x_variant":[
        "Her\u012bzeh",
        "\u0647\u0631\u06cc\u0632\u0647"
    ],
    "name:und_x_variant":[
        "K\u016bk\u012b"
    ],
    "wof:name":"Harpazeh Jabal",
    "wof:placetype":"locality"
},
  "geometry": {"coordinates":[52.4287,32.8202],"type":"Point"}
}