{
  "type": "Feature",
  "properties": {
    "gn:admin1_code":"42",
    "gn:asciiname":"Farsheh",
    "gn:country_code":"IR",
    "gn:dem":1269,
    "gn:feature_class":"P",
    "gn:feature_code":"PPL",
    "gn:name":"Farsheh",
    "gn:population":0,
    "gn:timezone":"Asia/Tehran",
    "iso:country":"IR",
    "name:fas_x_preferred":[
        "\u0641\u0631\u0634\u0647"
    ],
    "name:und_x_variant":[
        "Forshah",
        "Forsheh",
        "Farsheh"
    ],
    "wof:name":"Farsheh",
    "wof:placetype":"locality"
},
  "geometry": {"coordinates":[58.75102,35.27211],"type":"Point"}
}