{
  "type": "Feature",
  "properties": {
    "gn:admin1_code":"29",
    "gn:asciiname":"Malekabad",
    "gn:country_code":"IR",
    "gn:dem":803,
    "gn:feature_class":"P",
    "gn:feature_code":"PPL",
    "gn:name":"Malek\u0101b\u0101d",
    "gn:population":0,
    "gn:timezone":"Asia/Tehran",
    "iso:country":"IR",
    "name:ara_x_preferred":[
        "\u0645\u0644\u0643 \u0623\u0628\u0627\u062f"
    ],
    "name:fas_x_preferred":[
        "\u0645\u0644\u06a9 \u0622\u0628\u0627\u062f"
    ],
    "name:fas_x_variant":[
        "Malek\u0101b\u0101d",
        "\u0645\u0644\u06a9\u200c\u0622\u0628\u0627\u062f"
    ],
    "name:und_x_variant":[
        "Malik\u0101b\u0101d"
    ],
    "wof:name":"Malekabad",
    "wof:placetype":"locality"
},
  "geometry": {"coordinates":[58.105,28.3355],"type":"Point"}
}