{
  "type": "Feature",
  "properties": {
    "gn:admin1_code":"42",
    "gn:asciiname":"Kalateh-ye Somba",
    "gn:country_code":"IR",
    "gn:dem":1918,
    "gn:feature_class":"P",
    "gn:feature_code":"PPL",
    "gn:name":"Kal\u0101teh-ye Somb\u0101",
    "gn:population":0,
    "gn:timezone":"Asia/Tehran",
    "iso:country":"IR",
    "name:fas_x_preferred":[
        "\u06a9\u0644\u0627\u062a\u0647 \u0633\u0645\u0628\u0627"
    ],
    "name:fas_x_variant":[
        "Somb\u0101",
        "Kal\u0101teh-ye Somb\u0101"
    ],
    "wof:name":"Kalateh-ye Somba",
    "wof:placetype":"locality"
},
  "geometry": {"coordinates":[59.64426,35.55053],"type":"Point"}
}