{
  "type": "Feature",
  "properties": {
    "gn:admin1_code":"29",
    "gn:asciiname":"Toghr ol Jerd",
    "gn:country_code":"IR",
    "gn:dem":2129,
    "gn:feature_class":"P",
    "gn:feature_code":"PPL",
    "gn:name":"\u0162oghr ol Jerd",
    "gn:population":0,
    "gn:timezone":"Asia/Tehran",
    "iso:country":"IR",
    "name:fas_x_preferred":[
        "\u0162oghr ol Jerd"
    ],
    "name:fas_x_variant":[
        "\u0162oghrol Jerd",
        "\u0637\u063a\u0631\u0644 \u062c\u0631\u062f",
        "\u0637\u063a\u0631 \u0627\u0644\u062c\u0631\u062f"
    ],
    "wof:name":"Toghr ol Jerd",
    "wof:placetype":"locality"
},
  "geometry": {"coordinates":[56.39015,31.15028],"type":"Point"}
}