{
  "type": "Feature",
  "properties": {
    "gn:admin1_code":"28",
    "gn:asciiname":"Garmeh",
    "gn:country_code":"IR",
    "gn:dem":897,
    "gn:feature_class":"P",
    "gn:feature_code":"PPL",
    "gn:name":"Garmeh",
    "gn:population":0,
    "gn:timezone":"Asia/Tehran",
    "iso:country":"IR",
    "name:fas_x_preferred":[
        "\u06af\u0631\u0645\u0647"
    ],
    "name:fas_x_variant":[
        "Garm\u0101b"
    ],
    "name:und_x_variant":[
        "Garmeh"
    ],
    "wof:name":"Garmeh",
    "wof:placetype":"locality"
},
  "geometry": {"coordinates":[55.03971,33.52589],"type":"Point"}
}