{
  "type": "Feature",
  "properties": {
    "gn:admin1_code":"29",
    "gn:asciiname":"Tolombeh-ye Arjomand",
    "gn:country_code":"IR",
    "gn:dem":1660,
    "gn:feature_class":"P",
    "gn:feature_code":"PPL",
    "gn:name":"Tolombeh-ye Arjomand",
    "gn:population":0,
    "gn:timezone":"Asia/Tehran",
    "iso:country":"IR",
    "wof:name":"Tolombeh-ye Arjomand",
    "wof:placetype":"locality"
},
  "geometry": {"coordinates":[56.53333000000001,30.28333],"type":"Point"}
}