{
  "type": "Feature",
  "properties": {
    "gn:admin1_code":"35.0",
    "gn:asciiname":"Churet",
    "gn:country_code":"IR",
    "gn:dem":1082,
    "gn:feature_class":"P",
    "gn:feature_code":"PPL",
    "gn:name":"Ch\u016bret",
    "gn:population":0,
    "gn:timezone":"Asia/Tehran",
    "iso:country":"IR",
    "name:fas_x_preferred":[
        "\u0686\u0648\u0631\u064e\u062a"
    ],
    "name:fas_x_variant":[
        "Ch\u016bret",
        "\u0686\u0648\u0631\u062a"
    ],
    "name:mzn_x_preferred":[
        "\u0686\u0648\u0631\u062a"
    ],
    "name:und_x_variant":[
        "Ch\u016brat"
    ],
    "wof:name":"Churet",
    "wof:placetype":"locality"
},
  "geometry": {"coordinates":[53.46821,36.37229],"type":"Point"}
}