{
  "type": "Feature",
  "properties": {
    "gn:admin1_code":"36",
    "gn:asciiname":"Do Sangan",
    "gn:country_code":"IR",
    "gn:dem":2048,
    "gn:feature_class":"P",
    "gn:feature_code":"PPL",
    "gn:name":"Do Sang\u0101n",
    "gn:population":0,
    "gn:timezone":"Asia/Tehran",
    "iso:country":"IR",
    "name:ara_x_preferred":[
        "\u062f\u0648 \u0633\u0646\u063a\u0627\u0646"
    ],
    "name:azb_x_preferred":[
        "\u062f\u0648\u0633\u0646\u06af\u0627\u0646"
    ],
    "name:ceb_x_preferred":[
        "Do Sang\u0101n"
    ],
    "name:fas_x_preferred":[
        "\u062f\u0648 \u0633\u0646\u06af\u0627\u0646"
    ],
    "name:fas_x_variant":[
        "Do Sang\u0101n",
        "\u062f\u0648\u0633\u0646\u06af\u0627\u0646"
    ],
    "name:swe_x_preferred":[
        "Do Sang\u0101n"
    ],
    "name:und_x_variant":[
        "T\u016bsang\u0101n",
        "Dowsang\u0101n",
        "Dowsank\u0101l"
    ],
    "wof:name":"Do Sangan",
    "wof:placetype":"locality"
},
  "geometry": {"coordinates":[48.93934,36.49458],"type":"Point"}
}