{
  "type": "Feature",
  "properties": {
    "gn:admin1_code":"33",
    "gn:asciiname":"`Alikhanlu",
    "gn:country_code":"IR",
    "gn:dem":380,
    "gn:feature_class":"P",
    "gn:feature_code":"PPL",
    "gn:name":"\u2018Al\u012bkh\u0101nl\u016b",
    "gn:population":0,
    "gn:timezone":"Asia/Tehran",
    "iso:country":"IR",
    "name:fas_x_preferred":[
        "\u0639\u0644\u06cc\u062e\u0627\u0646\u0644\u0648"
    ],
    "name:fas_x_variant":[
        "\u2018Al\u012bkh\u0101nl\u016b",
        "\u0639\u0644\u06cc\u200c\u062e\u0627\u0646\u0644\u0648"
    ],
    "name:fra_x_preferred":[
        "Alikhanlu"
    ],
    "name:msa_x_preferred":[
        "Alikhanlu"
    ],
    "name:pol_x_preferred":[
        "Alichanlu"
    ],
    "wof:name":"`Alikhanlu",
    "wof:placetype":"locality"
},
  "geometry": {"coordinates":[47.1861,39.1996],"type":"Point"}
}