{
  "type": "Feature",
  "properties": {
    "gn:admin1_code":"29.0",
    "gn:asciiname":"Tezerj",
    "gn:country_code":"IR",
    "gn:dem":2526,
    "gn:feature_class":"P",
    "gn:feature_code":"PPL",
    "gn:name":"Tez\u0304erj",
    "gn:population":0,
    "gn:timezone":"Asia/Tehran",
    "iso:country":"IR",
    "name:fas_x_preferred":[
        "\u062a\u0630\u0631\u062c"
    ],
    "name:fas_x_variant":[
        "Tez\u0304erj"
    ],
    "name:und_x_variant":[
        "Tezerch",
        "Tezerj"
    ],
    "wof:name":"Tezerj",
    "wof:placetype":"locality"
},
  "geometry": {"coordinates":[56.8645,29.3231],"type":"Point"}
}