{
  "type": "Feature",
  "properties": {
    "gn:admin1_code":"35.0",
    "gn:asciiname":"Yaras",
    "gn:country_code":"IR",
    "gn:dem":1089,
    "gn:feature_class":"P",
    "gn:feature_code":"PPL",
    "gn:name":"Y\u0101ras",
    "gn:population":0,
    "gn:timezone":"Asia/Tehran",
    "iso:country":"IR",
    "name:fas_x_preferred":[
        "\u0648\u0627\u0631\u064e\u0633"
    ],
    "name:fas_x_variant":[
        "Y\u0101rasm",
        "Y\u0101ras",
        "\u064a\u0627\u0631\u0633",
        "\u064a\u0627\u0631\u0633\u0645"
    ],
    "name:und_x_variant":[
        "V\u0101ras",
        "Y\u0101ras",
        "\u064a\u0627\u0631\u0633\u0645",
        "\u064a\u0627\u0631\u0633"
    ],
    "wof:name":"Yaras",
    "wof:placetype":"locality"
},
  "geometry": {"coordinates":[53.74536,36.52036],"type":"Point"}
}