{
  "type": "Feature",
  "properties": {
    "gn:admin1_code":"42.0",
    "gn:asciiname":"Shurak-e Maleki",
    "gn:country_code":"IR",
    "gn:dem":829,
    "gn:feature_class":"P",
    "gn:feature_code":"PPL",
    "gn:name":"Sh\u016brak-e Malek\u012b",
    "gn:population":0,
    "gn:timezone":"Asia/Tehran",
    "iso:country":"IR",
    "name:ceb_x_preferred":[
        "Sh\u016brak-e Malek\u012b"
    ],
    "name:fas_x_preferred":[
        "\u0634\u0648\u0631\u06a9 \u0645\u0644\u06a9\u06cc"
    ],
    "name:fas_x_variant":[
        "Sh\u016brak-e Malek\u012b",
        "Sh\u016brak Malek\u012b"
    ],
    "name:swe_x_preferred":[
        "Sh\u016brak-e Malek\u012b"
    ],
    "name:und_x_variant":[
        "Shorak"
    ],
    "wof:name":"Shurak-e Maleki",
    "wof:placetype":"locality"
},
  "geometry": {"coordinates":[60.2242,36.07],"type":"Point"}
}