{
  "type": "Feature",
  "properties": {
    "gn:admin1_code":"34.0",
    "gn:asciiname":"Qashqa Bolagh",
    "gn:country_code":"IR",
    "gn:dem":1009,
    "gn:feature_class":"P",
    "gn:feature_code":"PPL",
    "gn:name":"Q\u0101shq\u0101 Bol\u0101gh",
    "gn:population":0,
    "gn:timezone":"Asia/Tehran",
    "iso:country":"IR",
    "name:fas_x_preferred":[
        "\u0642\u0627\u0634\u0642\u0627 \u0628\u0644\u0627\u063a"
    ],
    "name:fas_x_variant":[
        "Q\u0101shq\u0101 Bol\u0101gh"
    ],
    "wof:name":"Qashqa Bolagh",
    "wof:placetype":"locality"
},
  "geometry": {"coordinates":[50.7849,34.9478],"type":"Point"}
}