{
  "type": "Feature",
  "properties": {
    "gn:admin1_code":"16.0",
    "gn:asciiname":"Kani Salam",
    "gn:country_code":"IR",
    "gn:dem":1419,
    "gn:feature_class":"P",
    "gn:feature_code":"PPL",
    "gn:name":"K\u0101n\u012b Sal\u0101m",
    "gn:population":0,
    "gn:timezone":"Asia/Tehran",
    "iso:country":"IR",
    "name:fas_x_preferred":[
        "\u06a9\u0627\u0646\u06cc \u0633\u0644\u0627\u0645"
    ],
    "name:fas_x_variant":[
        "K\u0101n\u012b Sal\u0101m"
    ],
    "wof:name":"Kani Salam",
    "wof:placetype":"locality"
},
  "geometry": {"coordinates":[46.8802,35.1187],"type":"Point"}
}