{
  "type": "Feature",
  "properties": {
    "gn:admin1_code":"42.0",
    "gn:asciiname":"Turaneh",
    "gn:country_code":"IR",
    "gn:dem":1612,
    "gn:feature_class":"P",
    "gn:feature_code":"PPL",
    "gn:name":"T\u016br\u0101neh",
    "gn:population":0,
    "gn:timezone":"Asia/Tehran",
    "iso:country":"IR",
    "name:ara_x_preferred":[
        "\u062a\u0648\u0631\u0627\u0646\u0629"
    ],
    "name:fas_x_preferred":[
        "\u062a\u0648\u0631\u0627\u0646\u0647"
    ],
    "name:fas_x_variant":[
        "T\u016br\u0101neh",
        "Towr\u0101neh"
    ],
    "wof:name":"Turaneh",
    "wof:placetype":"locality"
},
  "geometry": {"coordinates":[60.10561,35.02186],"type":"Point"}
}