{
  "type": "Feature",
  "properties": {
    "gn:admin1_code":"5",
    "gn:asciiname":"Senugan",
    "gn:country_code":"IR",
    "gn:dem":851,
    "gn:feature_class":"P",
    "gn:feature_code":"PPL",
    "gn:name":"\u015een\u016bg\u0101n",
    "gn:population":0,
    "gn:timezone":"Asia/Tehran",
    "iso:country":"IR",
    "name:fas_x_preferred":[
        "\u0635\u0646\u0648\u06af\u0627\u0646"
    ],
    "name:fas_x_variant":[
        "Sen\u0101g\u016bn",
        "\u015een\u016bg\u0101n",
        "\u0633\u0646\u06af\u0648\u0646"
    ],
    "name:und_x_variant":[
        "Sang\u016bn"
    ],
    "wof:name":"Senugan",
    "wof:placetype":"locality"
},
  "geometry": {"coordinates":[50.47242,30.67486],"type":"Point"}
}