{
  "type": "Feature",
  "properties": {
    "gn:admin1_code":"7",
    "gn:asciiname":"Dehnow-ye Moqimi",
    "gn:country_code":"IR",
    "gn:dem":805,
    "gn:feature_class":"P",
    "gn:feature_code":"PPL",
    "gn:name":"Dehnow-ye Moq\u012bm\u012b",
    "gn:population":0,
    "gn:timezone":"Asia/Tehran",
    "iso:country":"IR",
    "name:fas_x_preferred":[
        "\u062f\u0647\u0646\u0648 \u0645\u0642\u06cc\u0645\u06cc"
    ],
    "name:msa_x_preferred":[
        "Dehnow-e Moqimi"
    ],
    "name:und_x_variant":[
        "Deh-i-Nau",
        "Dehnow",
        "Deh Now-e P\u0101\u2019\u012bn",
        "Dehnow-ye Moq\u012bm\u012b",
        "\u062f\u0647\u0646\u0648 \u0645\u0642\u06cc\u0645\u06cc"
    ],
    "wof:name":"Dehnow-ye Moqimi",
    "wof:placetype":"locality"
},
  "geometry": {"coordinates":[51.38929,30.31983],"type":"Point"}
}