{
  "type": "Feature",
  "properties": {
    "gn:admin1_code":"8",
    "gn:asciiname":"Ne`mat Sara",
    "gn:country_code":"IR",
    "gn:dem":28,
    "gn:feature_class":"P",
    "gn:feature_code":"PPL",
    "gn:name":"Ne\u2018mat Sar\u0101",
    "gn:population":0,
    "gn:timezone":"Asia/Tehran",
    "iso:country":"IR",
    "name:fas_x_preferred":[
        "Ne\u2018mat Sar\u0101"
    ],
    "name:fas_x_variant":[
        "\u0646\u0639\u0645\u062a \u0633\u0631\u0627"
    ],
    "name:und_x_variant":[
        "\u0646\u0639\u0645\u062a \u0633\u0631\u0627"
    ],
    "wof:name":"Ne`mat Sara",
    "wof:placetype":"locality"
},
  "geometry": {"coordinates":[50.36151,37.03161],"type":"Point"}
}