{
  "type": "Feature",
  "properties": {
    "gn:admin1_code":"23",
    "gn:asciiname":"Da'ichi",
    "gn:country_code":"IR",
    "gn:dem":1509,
    "gn:feature_class":"P",
    "gn:feature_code":"PPL",
    "gn:name":"D\u0101\u2019\u012bch\u012b",
    "gn:population":0,
    "gn:timezone":"Asia/Tehran",
    "iso:country":"IR",
    "name:fas_x_preferred":[
        "\u062f\u0627\u0626\u06cc \u0686\u06cc"
    ],
    "name:fas_x_variant":[
        "D\u0101\u2019\u012bch\u012b"
    ],
    "name:und_x_variant":[
        "D\u0101ych\u012b"
    ],
    "wof:name":"Da'ichi",
    "wof:placetype":"locality"
},
  "geometry": {"coordinates":[48.99237,33.64467],"type":"Point"}
}