{
  "type": "Feature",
  "properties": {
    "gn:admin1_code":"13",
    "gn:asciiname":"Dar Badam-e Sofla",
    "gn:country_code":"IR",
    "gn:dem":1727,
    "gn:feature_class":"P",
    "gn:feature_code":"PPLF",
    "gn:name":"D\u0101r B\u0101d\u0101m-e Sofl\u00e1",
    "gn:population":0,
    "gn:timezone":"Asia/Tehran",
    "iso:country":"IR",
    "name:ara_x_preferred":[
        "\u0627\u062d\u0645\u062f\u0643\u0634\u062a\u0647\u200c\u062f\u0627\u0631\u0628\u0627\u062f\u0627\u0645"
    ],
    "name:fas_x_preferred":[
        "\u062f\u0627\u0631 \u0628\u0627\u062f\u0627\u0645 \u0633\u0641\u0644\u06cc"
    ],
    "name:fas_x_variant":[
        "A\u1e29mad Koshteh-ye D\u0101rb\u0101d\u0101m",
        "D\u0101r B\u0101d\u0101m-e Sofl\u00e1",
        "\u0627\u062d\u0645\u062f\u06a9\u0634\u062a\u0647\u200c\u062f\u0627\u0631\u0628\u0627\u062f\u0627\u0645"
    ],
    "wof:name":"Dar Badam-e Sofla",
    "wof:placetype":"locality"
},
  "geometry": {"coordinates":[46.4203,34.019],"type":"Point"}
}