{
  "type": "Feature",
  "properties": {
    "gn:admin1_code":"35.0",
    "gn:asciiname":"Siah San",
    "gn:country_code":"IR",
    "gn:dem":104,
    "gn:feature_class":"P",
    "gn:feature_code":"PPL",
    "gn:name":"S\u012b\u0101h S\u0101n",
    "gn:population":0,
    "gn:timezone":"Asia/Tehran",
    "iso:country":"IR",
    "name:fas_x_preferred":[
        "Der\u0101z Poshteh"
    ],
    "name:fas_x_variant":[
        "\u062f\u0631\u0627\u0632 \u067e\u0634\u062a\u0647",
        "\u0633\u064a\u0627\u0647 \u0633\u0627\u0646",
        "\u0633\u064a\u0627\u0633\u0627\u0646"
    ],
    "name:und_x_variant":[
        "\u062f\u0631\u0627\u0632 \u067e\u0634\u062a\u0647",
        "S\u012b\u0101h S\u0101n",
        "S\u012b\u0101s\u0101n"
    ],
    "wof:name":"Siah San",
    "wof:placetype":"locality"
},
  "geometry": {"coordinates":[50.66314000000001,36.8898],"type":"Point"}
}