{
  "type": "Feature",
  "properties": {
    "gn:admin1_code":"36",
    "gn:asciiname":"Tudar",
    "gn:country_code":"IR",
    "gn:dem":1883,
    "gn:feature_class":"P",
    "gn:feature_code":"PPL",
    "gn:name":"T\u016bd\u0101r",
    "gn:population":0,
    "gn:timezone":"Asia/Tehran",
    "iso:country":"IR",
    "name:fas_x_preferred":[
        "\u062a\u0648\u062f\u0627\u0631"
    ],
    "name:fas_x_variant":[
        "T\u016bd\u0101r"
    ],
    "wof:name":"Tudar",
    "wof:placetype":"locality"
},
  "geometry": {"coordinates":[47.83748,36.38041],"type":"Point"}
}