{
  "type": "Feature",
  "properties": {
    "gn:admin1_code":"38",
    "gn:asciiname":"Mansur",
    "gn:country_code":"IR",
    "gn:dem":1853,
    "gn:feature_class":"P",
    "gn:feature_code":"PPL",
    "gn:name":"Man\u015f\u016br",
    "gn:population":0,
    "gn:timezone":"Asia/Tehran",
    "iso:country":"IR",
    "name:fas_x_preferred":[
        "\u0645\u0646\u0635\u0648\u0631"
    ],
    "name:fas_x_variant":[
        "Man\u015f\u016br"
    ],
    "name:und_x_variant":[
        "Mansoor"
    ],
    "wof:name":"Mansur",
    "wof:placetype":"locality"
},
  "geometry": {"coordinates":[49.05834,35.69539],"type":"Point"}
}