{
  "type": "Feature",
  "properties": {
    "gn:admin1_code":"15.0",
    "gn:asciiname":"Lop Sefid-e Sofla",
    "gn:country_code":"IR",
    "gn:dem":842,
    "gn:elevation":"0.0",
    "gn:feature_class":"P",
    "gn:feature_code":"PPL",
    "gn:name":"Lop Sef\u012bd-e Sofl\u00e1",
    "gn:population":0,
    "gn:timezone":"Asia/Tehran",
    "iso:country":"IR",
    "name:azb_x_preferred":[
        "\u0644\u0628 \u0633\u0641\u06cc\u062f\u0633\u0641\u0644\u06cc"
    ],
    "name:fas_x_preferred":[
        "\u0644\u067e \u0633\u0641\u06cc\u062f \u0633\u0641\u0644\u06cc"
    ],
    "name:fas_x_variant":[
        "Lab Sef\u012bd-e Sofl\u00e1",
        "Lop Sef\u012bd-e Sofl\u00e1",
        "\u0644\u0628\u200c\u0633\u0641\u06cc\u062f \u0633\u0641\u0644\u06cc"
    ],
    "name:urd_x_preferred":[
        "\u0644\u0628 \u0633\u0641\u06cc\u062f \u0633\u0641\u0644\u06cc"
    ],
    "wof:name":"Lop Sefid-e Sofla",
    "wof:placetype":"locality"
},
  "geometry": {"coordinates":[48.8105,32.5621],"type":"Point"}
}