{
  "type": "Feature",
  "properties": {
    "gn:admin1_code":"29",
    "gn:asciiname":"Lotfabad",
    "gn:country_code":"IR",
    "gn:dem":1413,
    "gn:feature_class":"P",
    "gn:feature_code":"PPL",
    "gn:name":"Lo\u0163f\u0101b\u0101d",
    "gn:population":0,
    "gn:timezone":"Asia/Tehran",
    "iso:country":"IR",
    "name:fas_x_preferred":[
        "Lo\u0163f\u0101b\u0101d"
    ],
    "name:fas_x_variant":[
        "\u0644\u0637\u0641 \u0622\u0628\u0627\u062f"
    ],
    "name:und_x_variant":[
        "\u0644\u0637\u0641 \u0622\u0628\u0627\u062f"
    ],
    "wof:name":"Lotfabad",
    "wof:placetype":"locality"
},
  "geometry": {"coordinates":[55.53971,30.66016],"type":"Point"}
}