{
  "type": "Feature",
  "properties": {
    "gn:admin1_code":"29",
    "gn:asciiname":"Kan-e `Abdollah",
    "gn:country_code":"IR",
    "gn:dem":2234,
    "gn:feature_class":"P",
    "gn:feature_code":"PPL",
    "gn:name":"Kan-e \u2018Abdoll\u0101h",
    "gn:population":0,
    "gn:timezone":"Asia/Tehran",
    "iso:country":"IR",
    "name:fas_x_preferred":[
        "\u06a9\u0646 \u0639\u0628\u062f \u0627\u0644\u0644\u0647"
    ],
    "name:fas_x_variant":[
        "Kan-e \u2018Abdoll\u0101h"
    ],
    "wof:name":"Kan-e `Abdollah",
    "wof:placetype":"locality"
},
  "geometry": {"coordinates":[55.1603,30.3254],"type":"Point"}
}