{
  "type": "Feature",
  "properties": {
    "gn:admin1_code":"7",
    "gn:asciiname":"Pishvar",
    "gn:country_code":"IR",
    "gn:dem":533,
    "gn:feature_class":"P",
    "gn:feature_code":"PPL",
    "gn:name":"P\u012bshvar",
    "gn:population":0,
    "gn:timezone":"Asia/Tehran",
    "iso:country":"IR",
    "name:fas_x_preferred":[
        "\u067e\u064a\u0634\u0648\u064e\u0631"
    ],
    "name:fas_x_variant":[
        "P\u012bshvar"
    ],
    "name:und_x_variant":[
        "Pishavar"
    ],
    "wof:name":"Pishvar",
    "wof:placetype":"locality"
},
  "geometry": {"coordinates":[53.06667,27.88333],"type":"Point"}
}