{
  "type": "Feature",
  "properties": {
    "gn:admin1_code":"33",
    "gn:asciiname":"Seyd Beyg",
    "gn:country_code":"IR",
    "gn:dem":1782,
    "gn:feature_class":"P",
    "gn:feature_code":"PPL",
    "gn:name":"\u015eeyd Beyg",
    "gn:population":0,
    "gn:timezone":"Asia/Tehran",
    "iso:country":"IR",
    "name:ceb_x_preferred":[
        "\u015eeyd Beyg"
    ],
    "name:fas_x_preferred":[
        "\u0633\u06cc\u062f\u06cc \u0628\u06cc\u06af"
    ],
    "name:fas_x_variant":[
        "\u015eeyd Beyg",
        "Seyyed\u012b Beyg",
        "\u0635\u06cc\u062f \u0628\u06cc\u06af",
        "\u0635\u06cc\u062f\u0628\u06cc\u06af"
    ],
    "name:msa_x_preferred":[
        "Seyd Beyg"
    ],
    "name:swe_x_preferred":[
        "\u015eeyd Beyg"
    ],
    "wof:name":"Seyd Beyg",
    "wof:placetype":"locality"
},
  "geometry": {"coordinates":[46.80924,37.61141],"type":"Point"}
}