{
  "type": "Feature",
  "properties": {
    "gn:admin1_code":"8",
    "gn:asciiname":"Molla Sara",
    "gn:country_code":"IR",
    "gn:dem":-10,
    "gn:feature_class":"P",
    "gn:feature_code":"PPL",
    "gn:name":"Moll\u0101 Sar\u0101",
    "gn:population":0,
    "gn:timezone":"Asia/Tehran",
    "iso:country":"IR",
    "name:fas_x_preferred":[
        "\u0645\u0644\u0627 \u0633\u0631\u0627"
    ],
    "name:fas_x_variant":[
        "Moll\u0101 Sar\u0101"
    ],
    "wof:name":"Molla Sara",
    "wof:placetype":"locality"
},
  "geometry": {"coordinates":[49.26102,37.38222],"type":"Point"}
}