{
  "type": "Feature",
  "properties": {
    "gn:admin1_code":"8.0",
    "gn:asciiname":"Pir Kari",
    "gn:country_code":"IR",
    "gn:dem":1674,
    "gn:feature_class":"P",
    "gn:feature_code":"PPL",
    "gn:name":"P\u012br Kar\u012b",
    "gn:population":0,
    "gn:timezone":"Asia/Tehran",
    "iso:country":"IR",
    "name:fas_x_preferred":[
        "\u067e\u06cc\u0631 \u06a9\u0631\u06cc"
    ],
    "name:fas_x_variant":[
        "P\u012br\u0101 Kar\u012b",
        "P\u012br Kar\u012b",
        "\u067e\u06cc\u0631\u0627 \u06a9\u0631\u06cc"
    ],
    "wof:name":"Pir Kari",
    "wof:placetype":"locality"
},
  "geometry": {"coordinates":[48.71100000000001,37.8741],"type":"Point"}
}