{
  "type": "Feature",
  "properties": {
    "gn:admin1_code":"4.0",
    "gn:asciiname":"Galindar",
    "gn:country_code":"IR",
    "gn:dem":900,
    "gn:feature_class":"P",
    "gn:feature_code":"PPL",
    "gn:name":"Gal\u012bndar",
    "gn:population":0,
    "gn:timezone":"Asia/Tehran",
    "iso:country":"IR",
    "name:fas_x_preferred":[
        "\u06af\u0644\u064a\u0646\u062f\u0631"
    ],
    "name:fas_x_variant":[
        "Gal\u012bndar"
    ],
    "wof:name":"Galindar",
    "wof:placetype":"locality"
},
  "geometry": {"coordinates":[60.71189,26.55373],"type":"Point"}
}