{
  "type": "Feature",
  "properties": {
    "gn:admin1_code":"23",
    "gn:asciiname":"Konarvand",
    "gn:country_code":"IR",
    "gn:dem":1815,
    "gn:feature_class":"P",
    "gn:feature_code":"PPL",
    "gn:name":"Kon\u0101rvand",
    "gn:population":0,
    "gn:timezone":"Asia/Tehran",
    "iso:country":"IR",
    "name:fas_x_preferred":[
        "\u0643\u0646\u0627\u0631\u0648\u0646\u062f"
    ],
    "name:fas_x_variant":[
        "Kon\u0101rvand-e Varkow",
        "Kon\u0101rvand",
        "\u06af\u0646\u0627\u0631\u0648\u0646\u062f"
    ],
    "name:und_x_variant":[
        "Kanarw\u0101n",
        "Kenar Vand",
        "Kon\u0101rvan-e \u2018Oly\u0101",
        "Gon\u0101rvand"
    ],
    "wof:name":"Konarvand",
    "wof:placetype":"locality"
},
  "geometry": {"coordinates":[48.7295,33.6839],"type":"Point"}
}