{
  "type": "Feature",
  "properties": {
    "gn:admin1_code":"11",
    "gn:asciiname":"Gerdu'i",
    "gn:country_code":"IR",
    "gn:dem":853,
    "gn:feature_class":"P",
    "gn:feature_code":"PPL",
    "gn:name":"Gerd\u016b\u2019\u012b",
    "gn:population":0,
    "gn:timezone":"Asia/Tehran",
    "iso:country":"IR",
    "name:fas_x_preferred":[
        "\u06af\u0631\u062f\u0648\u0626\u06cc"
    ],
    "name:fas_x_variant":[
        "Gerd\u016b\u2019\u012b"
    ],
    "wof:name":"Gerdu'i",
    "wof:placetype":"locality"
},
  "geometry": {"coordinates":[56.4827,27.8212],"type":"Point"}
}