{
  "type": "Feature",
  "properties": {
    "gn:admin1_code":"15",
    "gn:asciiname":"Hoseyn Mashlush",
    "gn:country_code":"IR",
    "gn:dem":38,
    "gn:feature_class":"P",
    "gn:feature_code":"PPL",
    "gn:name":"\u1e28oseyn Mashl\u016bsh",
    "gn:population":0,
    "gn:timezone":"Asia/Tehran",
    "iso:country":"IR",
    "name:ceb_x_preferred":[
        "\u1e28oseyn Mashk\u016bsh"
    ],
    "name:fas_x_preferred":[
        "\u062d\u0633\u06cc\u0646 \u0645\u0634\u06a9\u0648\u0634"
    ],
    "name:fas_x_variant":[
        "\u1e28oseyn Mashl\u016bsh",
        "\u1e28oseyn Mashk\u016bsh",
        "\u062d\u0633\u06cc\u0646 \u0645\u0634\u0644\u0648\u0634"
    ],
    "name:swe_x_preferred":[
        "\u1e28oseyn Mashk\u016bsh"
    ],
    "wof:name":"Hoseyn Mashlush",
    "wof:placetype":"locality"
},
  "geometry": {"coordinates":[48.37748,31.89062],"type":"Point"}
}