{
  "type": "Feature",
  "properties": {
    "gn:admin1_code":"37",
    "gn:asciiname":"Shirleh",
    "gn:country_code":"IR",
    "gn:dem":284,
    "gn:feature_class":"P",
    "gn:feature_code":"PPL",
    "gn:name":"Sh\u012brleh",
    "gn:population":0,
    "gn:timezone":"Asia/Tehran",
    "iso:country":"IR",
    "name:fas_x_preferred":[
        "\u0634\u064a\u0631\u0644\u0650\u0647"
    ],
    "name:fas_x_variant":[
        "Sh\u012brleh"
    ],
    "wof:name":"Shirleh",
    "wof:placetype":"locality"
},
  "geometry": {"coordinates":[55.65,37.81667],"type":"Point"}
}