{
  "type": "Feature",
  "properties": {
    "gn:admin1_code":"13",
    "gn:asciiname":"Gorgeh Bisheh-ye Sofla",
    "gn:country_code":"IR",
    "gn:dem":1852,
    "gn:feature_class":"P",
    "gn:feature_code":"PPL",
    "gn:name":"Gorgeh B\u012bsheh-ye Sofl\u00e1",
    "gn:population":0,
    "gn:timezone":"Asia/Tehran",
    "iso:country":"IR",
    "name:fas_x_preferred":[
        "\u06af\u0631\u06af\u0647 \u0628\u06cc\u0634\u0647 \u0633\u0641\u0644\u06cc"
    ],
    "name:fas_x_variant":[
        "Gorg-e B\u012bsheh-ye Sofl\u00e1",
        "Gorgeh B\u012bsheh-ye Sofl\u00e1"
    ],
    "wof:name":"Gorgeh Bisheh-ye Sofla",
    "wof:placetype":"locality"
},
  "geometry": {"coordinates":[47.65747,34.55756],"type":"Point"}
}