{
  "type": "Feature",
  "properties": {
    "gn:admin1_code":"23",
    "gn:asciiname":"Eylar",
    "gn:country_code":"IR",
    "gn:dem":652,
    "gn:feature_class":"P",
    "gn:feature_code":"PPL",
    "gn:name":"Eylar",
    "gn:population":0,
    "gn:timezone":"Asia/Tehran",
    "iso:country":"IR",
    "name:fas_x_preferred":[
        "\u0627\u06cc\u0644\u0631"
    ],
    "wof:name":"Eylar",
    "wof:placetype":"locality"
},
  "geometry": {"coordinates":[48.6526,33.05272],"type":"Point"}
}