{
  "type": "Feature",
  "properties": {
    "gn:admin1_code":"23",
    "gn:asciiname":"Cheraghabad-e Bala",
    "gn:country_code":"IR",
    "gn:dem":1596,
    "gn:feature_class":"P",
    "gn:feature_code":"PPL",
    "gn:name":"Cher\u0101gh\u0101b\u0101d-e B\u0101l\u0101",
    "gn:population":0,
    "gn:timezone":"Asia/Tehran",
    "iso:country":"IR",
    "name:fas_x_preferred":[
        "\u0686\u0631\u0627\u063a \u0622\u0628\u0627\u062f \u0639\u0644\u06cc\u0627"
    ],
    "name:fas_x_variant":[
        "Cher\u0101gh\u0101b\u0101d-e \u2018Oly\u0101",
        "\u0686\u0631\u0627\u063a \u0622\u0628\u0627\u062f \u0628\u0627\u0644\u0627"
    ],
    "name:und_x_variant":[
        "Cher\u0101gh\u0101b\u0101d-e B\u0101l\u0101"
    ],
    "wof:name":"Cheraghabad-e Bala",
    "wof:placetype":"locality"
},
  "geometry": {"coordinates":[48.2267,33.8771],"type":"Point"}
}