{
  "type": "Feature",
  "properties": {
    "gn:admin1_code":"29",
    "gn:asciiname":"Dashtkhak",
    "gn:country_code":"IR",
    "gn:dem":2269,
    "gn:feature_class":"P",
    "gn:feature_code":"PPL",
    "gn:name":"Dashtkh\u0101k",
    "gn:population":0,
    "gn:timezone":"Asia/Tehran",
    "iso:country":"IR",
    "name:fas_x_preferred":[
        "Dasht-e Kh\u0101k"
    ],
    "name:fas_x_variant":[
        "\u062f\u0634\u062a\u062e\u0627\u06a9",
        "Dasht-i-Kh\u0101k",
        "\u062f\u0634\u062a \u062e\u0627\u06a9"
    ],
    "name:und_x_variant":[
        "Dashtkh\u0101k"
    ],
    "wof:name":"Dashtkhak",
    "wof:placetype":"locality"
},
  "geometry": {"coordinates":[56.55416999999999,31.06675],"type":"Point"}
}