{
  "type": "Feature",
  "properties": {
    "gn:admin1_code":"3.0",
    "gn:asciiname":"Chaylar",
    "gn:country_code":"IR",
    "gn:dem":1836,
    "gn:feature_class":"P",
    "gn:feature_code":"PPL",
    "gn:name":"Ch\u0101ylar",
    "gn:population":0,
    "gn:timezone":"Asia/Tehran",
    "iso:country":"IR",
    "name:fas_x_preferred":[
        "Ch\u0101ylar"
    ],
    "name:fas_x_variant":[
        "\u0686\u0627\u06cc\u0644\u0631"
    ],
    "name:und_x_variant":[
        "\u0686\u0627\u06cc\u0644\u0631"
    ],
    "wof:name":"Chaylar",
    "wof:placetype":"locality"
},
  "geometry": {"coordinates":[51.15138,31.186],"type":"Point"}
}