{
  "type": "Feature",
  "properties": {
    "gn:admin1_code":"43.0",
    "gn:asciiname":"Kalateh-ye Anneh Goli",
    "gn:country_code":"IR",
    "gn:dem":875,
    "gn:feature_class":"P",
    "gn:feature_code":"PPL",
    "gn:name":"Kal\u0101teh-ye Anneh Gol\u012b",
    "gn:population":0,
    "gn:timezone":"Asia/Tehran",
    "iso:country":"IR",
    "name:fas_x_preferred":[
        "Kal\u0101teh-ye Anneh Gol\u012b"
    ],
    "name:fas_x_variant":[
        "\u06a9\u0644\u0627\u062a\u0647 \u0627\u0646\u0651\u0647 \u06af\u0644\u06cc"
    ],
    "wof:name":"Kalateh-ye Anneh Goli",
    "wof:placetype":"locality"
},
  "geometry": {"coordinates":[56.67643,37.86752],"type":"Point"}
}