{
  "type": "Feature",
  "properties": {
    "gn:admin1_code":"23",
    "gn:asciiname":"Qasem`ali",
    "gn:country_code":"IR",
    "gn:dem":1337,
    "gn:feature_class":"P",
    "gn:feature_code":"PPL",
    "gn:name":"Q\u0101sem\u2018al\u012b",
    "gn:population":0,
    "gn:timezone":"Asia/Tehran",
    "iso:country":"IR",
    "name:fas_x_preferred":[
        "\u0642\u0627\u0633\u0650\u0645\u0639\u064e\u0644\u06cc"
    ],
    "name:fas_x_variant":[
        "Q\u0101sem\u2018al\u012b"
    ],
    "wof:name":"Qasem`ali",
    "wof:placetype":"locality"
},
  "geometry": {"coordinates":[47.51667,33.76667],"type":"Point"}
}