{
  "type": "Feature",
  "properties": {
    "gn:admin1_code":"15.0",
    "gn:asciiname":"Chogha Shir",
    "gn:country_code":"IR",
    "gn:dem":87,
    "gn:feature_class":"P",
    "gn:feature_code":"PPL",
    "gn:name":"Chogh\u0101 Sh\u012br",
    "gn:population":0,
    "gn:timezone":"Asia/Tehran",
    "iso:country":"IR",
    "name:fas_x_preferred":[
        "Chogh\u0101 Sh\u012br"
    ],
    "wof:name":"Chogha Shir",
    "wof:placetype":"locality"
},
  "geometry": {"coordinates":[48.46667,32.26667],"type":"Point"}
}