{
  "type": "Feature",
  "properties": {
    "gn:admin1_code":"40",
    "gn:asciiname":"Mahakabad",
    "gn:country_code":"IR",
    "gn:dem":1572,
    "gn:feature_class":"P",
    "gn:feature_code":"PPL",
    "gn:name":"Mahak\u0101b\u0101d",
    "gn:population":0,
    "gn:timezone":"Asia/Tehran",
    "iso:country":"IR",
    "name:fas_x_preferred":[
        "\u0645\u064e\u0647\u064e\u0643 \u0622\u0628\u0627\u062f"
    ],
    "name:fas_x_variant":[
        "\u0645\u064e\u0647\u0642 \u0622\u0628\u0627\u062f",
        "Mahak\u0101b\u0101d"
    ],
    "name:und_x_variant":[
        "Mahq\u0101b\u0101d"
    ],
    "wof:name":"Mahakabad",
    "wof:placetype":"locality"
},
  "geometry": {"coordinates":[54.38333000000001,31.63333],"type":"Point"}
}