{
  "type": "Feature",
  "properties": {
    "gn:admin1_code":"36",
    "gn:asciiname":"Churuk-e `Olya",
    "gn:country_code":"IR",
    "gn:dem":1235,
    "gn:feature_class":"P",
    "gn:feature_code":"PPL",
    "gn:name":"Ch\u016br\u016bk-e \u2018Oly\u0101",
    "gn:population":0,
    "gn:timezone":"Asia/Tehran",
    "iso:country":"IR",
    "name:azb_x_preferred":[
        "\u0686\u0648\u0631\u0648\u06a9 \u0639\u0644\u06cc\u0627"
    ],
    "name:fas_x_preferred":[
        "\u0686\u0648\u0631\u0648\u0643\u0650 \u0628\u0627\u0644\u0627"
    ],
    "name:fas_x_variant":[
        "\u0686\u0648\u0632\u064e\u0643\u0650 \u0639\u064f\u0644\u064a\u0627",
        "\u0686\u064f\u0631\u064e\u0643",
        "\u0686\u0648\u0631\u0648\u0643 \u0639\u0644\u064a\u0627",
        "Ch\u016br\u016bk-e B\u0101l\u0101",
        "Ch\u016br\u016bk-e \u2018Oly\u0101",
        "\u0686\u0648\u0631\u0648\u06a9 \u0639\u0644\u06cc\u0627"
    ],
    "name:und_x_variant":[
        "Churak",
        "Ch\u016bzak-e \u2018Oly\u0101",
        "Chorak"
    ],
    "wof:name":"Churuk-e `Olya",
    "wof:placetype":"locality"
},
  "geometry": {"coordinates":[47.8849,37.0797],"type":"Point"}
}