{
  "type": "Feature",
  "properties": {
    "gn:admin1_code":"10.0",
    "gn:asciiname":"Qarjalgan",
    "gn:country_code":"IR",
    "gn:dem":867,
    "gn:elevation":"0.0",
    "gn:feature_class":"P",
    "gn:feature_code":"PPL",
    "gn:name":"Qarjalg\u0101n",
    "gn:population":0,
    "gn:timezone":"Asia/Tehran",
    "iso:country":"IR",
    "name:fas_x_preferred":[
        "\u0642\u064e\u0631\u062c\u064e\u0644\u06af\u0627\u0646"
    ],
    "name:fas_x_variant":[
        "\u0642\u0631\u062c\u0644\u06af\u0627\u0646",
        "Qarjalg\u0101n"
    ],
    "wof:name":"Qarjalgan",
    "wof:placetype":"locality"
},
  "geometry": {"coordinates":[46.4603,33.2536],"type":"Point"}
}