{
  "type": "Feature",
  "properties": {
    "gn:admin1_code":"7",
    "gn:asciiname":"Ab Barik",
    "gn:country_code":"IR",
    "gn:dem":689,
    "gn:feature_class":"P",
    "gn:feature_code":"PPL",
    "gn:name":"\u0100b B\u0101r\u012bk",
    "gn:population":0,
    "gn:timezone":"Asia/Tehran",
    "iso:country":"IR",
    "name:fas_x_preferred":[
        "\u0100b B\u0101r\u012bk"
    ],
    "name:fas_x_variant":[
        "\u0627\u0628\u0628\u0627\u0631\u06cc\u06a9"
    ],
    "wof:name":"Ab Barik",
    "wof:placetype":"locality"
},
  "geometry": {"coordinates":[53.21417,28.39194],"type":"Point"}
}