{
  "type": "Feature",
  "properties": {
    "gn:admin1_code":"4",
    "gn:asciiname":"Nurabad",
    "gn:country_code":"IR",
    "gn:dem":1427,
    "gn:feature_class":"P",
    "gn:feature_code":"PPL",
    "gn:name":"N\u016br\u0101b\u0101d",
    "gn:population":0,
    "gn:timezone":"Asia/Tehran",
    "iso:country":"IR",
    "name:aze_x_preferred":[
        "Nurabad"
    ],
    "name:deu_x_preferred":[
        "Nurabad"
    ],
    "name:fas_x_preferred":[
        "\u0646\u0648\u0631 \u0622\u0628\u0627\u062f"
    ],
    "name:fas_x_variant":[
        "N\u016br\u0101b\u0101d",
        "\u0646\u0648\u0631\u0622\u0628\u0627\u062f"
    ],
    "name:fra_x_preferred":[
        "Nourabad"
    ],
    "name:hin_x_preferred":[
        "\u0928\u0942\u0930\u093e\u092c\u093e\u0926"
    ],
    "name:pol_x_preferred":[
        "Nurabad"
    ],
    "name:rus_x_preferred":[
        "\u041d\u0443\u0440\u0430\u0431\u0430\u0434"
    ],
    "name:ukr_x_preferred":[
        "\u041d\u0443\u0440\u0430\u0431\u0430\u0434"
    ],
    "wof:name":"Nurabad",
    "wof:placetype":"locality"
},
  "geometry": {"coordinates":[60.40711999999999,28.54874],"type":"Point"}
}