{
  "type": "Feature",
  "properties": {
    "gn:admin1_code":"4.0",
    "gn:asciiname":"Ya`qub Zehi",
    "gn:country_code":"IR",
    "gn:dem":29,
    "gn:feature_class":"P",
    "gn:feature_code":"PPL",
    "gn:name":"Ya\u2018q\u016bb Zeh\u012b",
    "gn:population":0,
    "gn:timezone":"Asia/Tehran",
    "iso:country":"IR",
    "name:fas_x_preferred":[
        "Ya\u2018q\u016bb Zeh\u012b"
    ],
    "name:fas_x_variant":[
        "\u06cc\u0639\u0642\u0648\u0628 \u0632\u0647\u06cc"
    ],
    "name:und_x_variant":[
        "\u06cc\u0639\u0642\u0648\u0628 \u0632\u0647\u06cc"
    ],
    "wof:name":"Ya`qub Zehi",
    "wof:placetype":"locality"
},
  "geometry": {"coordinates":[61.12421,25.59399],"type":"Point"}
}