{
  "type": "Feature",
  "properties": {
    "gn:admin1_code":"42",
    "gn:asciiname":"Sar Dasht",
    "gn:country_code":"IR",
    "gn:dem":1961,
    "gn:feature_class":"P",
    "gn:feature_code":"PPL",
    "gn:name":"Sar Dasht",
    "gn:population":0,
    "gn:timezone":"Asia/Tehran",
    "iso:country":"IR",
    "name:fas_x_preferred":[
        "\u0633\u0631 \u062f\u0634\u062a"
    ],
    "name:und_x_variant":[
        "Sar-i-Dasht",
        "Sar Dasht"
    ],
    "wof:name":"Sar Dasht",
    "wof:placetype":"locality"
},
  "geometry": {"coordinates":[59.58666,35.62766],"type":"Point"}
}