{
  "type": "Feature",
  "properties": {
    "gn:admin1_code":"15.0",
    "gn:asciiname":"Qeshlaq-e Cham-e Reza",
    "gn:country_code":"IR",
    "gn:dem":84,
    "gn:feature_class":"P",
    "gn:feature_code":"PPLL",
    "gn:name":"Qeshl\u0101q-e Cham-e Re\u1e95\u0101",
    "gn:population":0,
    "gn:timezone":"Asia/Tehran",
    "iso:country":"IR",
    "name:fas_x_preferred":[
        "\u0642\u0634\u0644\u0627\u0642 \u0686\u0645 \u0631\u0636\u0627"
    ],
    "name:und_x_variant":[
        "Qeshl\u0101q-e Cham-e Re\u1e95\u0101"
    ],
    "wof:name":"Qeshlaq-e Cham-e Reza",
    "wof:placetype":"locality"
},
  "geometry": {"coordinates":[48.88844,32.26993],"type":"Point"}
}