{
  "type": "Feature",
  "properties": {
    "gn:admin1_code":"9",
    "gn:asciiname":"Gav Savar",
    "gn:country_code":"IR",
    "gn:dem":1913,
    "gn:feature_class":"P",
    "gn:feature_code":"PPL",
    "gn:name":"G\u0101v Sav\u0101r",
    "gn:population":0,
    "gn:timezone":"Asia/Tehran",
    "iso:country":"IR",
    "name:fas_x_preferred":[
        "\u06af\u0627\u0648 \u0633\u0648\u0627\u0631"
    ],
    "name:fas_x_variant":[
        "G\u0101v Sav\u0101r"
    ],
    "name:und_x_variant":[
        "Gosw\u0101r"
    ],
    "wof:name":"Gav Savar",
    "wof:placetype":"locality"
},
  "geometry": {"coordinates":[48.81216,35.48781],"type":"Point"}
}