{
  "type": "Feature",
  "properties": {
    "gn:admin1_code":"23",
    "gn:asciiname":"Feyal",
    "gn:country_code":"IR",
    "gn:dem":1609,
    "gn:feature_class":"P",
    "gn:feature_code":"PPL",
    "gn:name":"Fey\u0101l",
    "gn:population":0,
    "gn:timezone":"Asia/Tehran",
    "iso:country":"IR",
    "name:ara_x_preferred":[
        "\u0641\u064a\u0627\u0644"
    ],
    "name:fas_x_preferred":[
        "\u0641\u06cc\u0627\u0644"
    ],
    "name:fas_x_variant":[
        "Fey\u0101l"
    ],
    "name:und_x_variant":[
        "Sheykh M\u012br\u012b S\u0101d\u0101t",
        "F\u012b\u0101l",
        "Fiy\u0101l"
    ],
    "wof:name":"Feyal",
    "wof:placetype":"locality"
},
  "geometry": {"coordinates":[48.7103,33.8966],"type":"Point"}
}