{
  "type": "Feature",
  "properties": {
    "gn:admin1_code":"28",
    "gn:asciiname":"Qaderabad",
    "gn:country_code":"IR",
    "gn:dem":871,
    "gn:feature_class":"P",
    "gn:feature_code":"PPL",
    "gn:name":"Q\u0101der\u0101b\u0101d",
    "gn:population":0,
    "gn:timezone":"Asia/Tehran",
    "iso:country":"IR",
    "name:fas_x_preferred":[
        "Q\u0101der\u0101b\u0101d"
    ],
    "name:fas_x_variant":[
        "\u0642\u0627\u062f\u0631 \u0622\u0628\u0627\u062f",
        "\u0642\u0627\u062f\u0631\u0622\u0628\u0627\u062f"
    ],
    "wof:name":"Qaderabad",
    "wof:placetype":"locality"
},
  "geometry": {"coordinates":[54.67693000000001,33.74972],"type":"Point"}
}