{
  "type": "Feature",
  "properties": {
    "gn:admin1_code":"4",
    "gn:asciiname":"Chah-e Bist-o Do-ye Bahman",
    "gn:country_code":"IR",
    "gn:dem":1177,
    "gn:feature_class":"P",
    "gn:feature_code":"PPL",
    "gn:name":"Ch\u0101h-e B\u012bst-o Do-ye Bahman",
    "gn:population":0,
    "gn:timezone":"Asia/Tehran",
    "iso:country":"IR",
    "name:fas_x_preferred":[
        "\u0686\u0627\u0647 \u0628\u06cc\u0633\u062a \u0648 \u062f\u0648 \u0628\u0647\u0645\u0646"
    ],
    "name:und_x_variant":[
        "Ch\u0101h-e B\u012bst-o Do-ye Bahman"
    ],
    "wof:name":"Chah-e Bist-o Do-ye Bahman",
    "wof:placetype":"locality"
},
  "geometry": {"coordinates":[61.865,27.4021],"type":"Point"}
}