{
  "type": "Feature",
  "properties": {
    "gn:admin1_code":"13",
    "gn:asciiname":"Kur Bolagh-e Mohammad Naqi",
    "gn:country_code":"IR",
    "gn:dem":1314,
    "gn:feature_class":"P",
    "gn:feature_code":"PPL",
    "gn:name":"K\u016br Bol\u0101gh-e Mo\u1e29ammad Naq\u012b",
    "gn:population":0,
    "gn:timezone":"Asia/Tehran",
    "iso:country":"IR",
    "name:ceb_x_preferred":[
        "K\u016br Bol\u0101gh-e Mo\u1e29ammad Naq\u012b"
    ],
    "name:fas_x_preferred":[
        "\u06a9\u0648\u0631 \u0628\u0644\u0627\u063a \u0645\u062d\u0645\u0651\u062f \u0646\u0642\u06cc"
    ],
    "name:fas_x_variant":[
        "K\u016br Bol\u0101gh-e Do",
        "K\u016br Bol\u0101gh-e Mo\u1e29ammad Naq\u012b",
        "\u06a9\u0648\u0631\u0628\u0644\u0627\u063a \u062f\u0648"
    ],
    "name:swe_x_preferred":[
        "K\u016br Bol\u0101gh-e Mo\u1e29ammad Naq\u012b"
    ],
    "name:und_x_variant":[
        "K\u016br Bol\u0101gh-e Mo\u1e29ammad Taq\u012b"
    ],
    "wof:name":"Kur Bolagh-e Mohammad Naqi",
    "wof:placetype":"locality"
},
  "geometry": {"coordinates":[46.8251,34.47],"type":"Point"}
}