{
  "type": "Feature",
  "properties": {
    "gn:admin1_code":"4.0",
    "gn:asciiname":"Kalateh-ye Razzaqzadeh",
    "gn:country_code":"IR",
    "gn:dem":1501,
    "gn:feature_class":"P",
    "gn:feature_code":"PPL",
    "gn:name":"Kal\u0101teh-ye Razz\u0101qz\u0101deh",
    "gn:population":0,
    "gn:timezone":"Asia/Tehran",
    "iso:country":"IR",
    "name:fas_x_preferred":[
        "\u06a9\u0644\u0627\u062a\u0647 \u0631\u0632\u0627\u0642 \u0632\u0627\u062f\u0647"
    ],
    "name:fas_x_variant":[
        "Kal\u0101teh-ye Razz\u0101qz\u0101deh"
    ],
    "wof:name":"Kalateh-ye Razzaqzadeh",
    "wof:placetype":"locality"
},
  "geometry": {"coordinates":[60.8141,29.3876],"type":"Point"}
}