{
  "type": "Feature",
  "properties": {
    "gn:admin1_code":"15",
    "gn:asciiname":"Tall Gavineh",
    "gn:country_code":"IR",
    "gn:dem":142,
    "gn:feature_class":"P",
    "gn:feature_code":"PPL",
    "gn:name":"Tall Gav\u012bneh",
    "gn:population":0,
    "gn:timezone":"Asia/Tehran",
    "iso:country":"IR",
    "name:azb_x_preferred":[
        "\u062a\u0644 \u06af\u0648\u06cc\u0646\u0647(\u0628\u0647\u0628\u0647\u0627\u0646)"
    ],
    "name:ceb_x_preferred":[
        "Tall Gav\u012bneh"
    ],
    "name:fas_x_preferred":[
        "\u062a\u0644 \u06af\u0648\u06cc\u0646\u0647"
    ],
    "name:fas_x_variant":[
        "Tol Gav\u012bneh",
        "Tall Gav\u012bneh",
        "\u062a\u0644\u200c\u06af\u0648\u06cc\u0646\u0647"
    ],
    "name:swe_x_preferred":[
        "Tall Gav\u012bneh"
    ],
    "wof:name":"Tall Gavineh",
    "wof:placetype":"locality"
},
  "geometry": {"coordinates":[50.1006,30.3367],"type":"Point"}
}