{
  "type": "Feature",
  "properties": {
    "gn:admin1_code":"22",
    "gn:asciiname":"Mordeva",
    "gn:country_code":"IR",
    "gn:dem":49,
    "gn:feature_class":"P",
    "gn:feature_code":"PPLF",
    "gn:name":"Mordev\u0101",
    "gn:population":0,
    "gn:timezone":"Asia/Tehran",
    "iso:country":"IR",
    "name:fas_x_preferred":[
        "\u0645\u0631\u062f\u0648\u0627"
    ],
    "name:fas_x_variant":[
        "\u0645\u064f\u0631\u0648\u0627\u0628\u0650\u0647",
        "Mordev\u0101"
    ],
    "name:und_x_variant":[
        "Maroo\u2019i",
        "Mordov\u0101",
        "Morv\u0101beh"
    ],
    "wof:name":"Mordeva",
    "wof:placetype":"locality"
},
  "geometry": {"coordinates":[51.73236,27.99016],"type":"Point"}
}