{
  "type": "Feature",
  "properties": {
    "gn:admin1_code":"37.0",
    "gn:asciiname":"Hoseynabad-e Akhundi",
    "gn:country_code":"IR",
    "gn:dem":195,
    "gn:feature_class":"P",
    "gn:feature_code":"PPL",
    "gn:name":"\u1e28oseyn\u0101b\u0101d-e \u0100kh\u016bnd\u012b",
    "gn:population":0,
    "gn:timezone":"Asia/Tehran",
    "iso:country":"IR",
    "name:fas_x_preferred":[
        "\u062d\u0633\u06cc\u0646 \u0622\u0628\u0627\u062f \u0622\u062e\u0648\u0646\u062f\u06cc"
    ],
    "name:fas_x_variant":[
        "\u062d\u0633\u06cc\u0646 \u0622\u0628\u0627\u062f"
    ],
    "name:und_x_variant":[
        "\u1e28oseyn\u0101b\u0101d-e \u0100kh\u016bnd\u012b",
        "\u1e28oseyn\u0101b\u0101d"
    ],
    "wof:name":"Hoseynabad-e Akhundi",
    "wof:placetype":"locality"
},
  "geometry": {"coordinates":[55.45631,37.29181],"type":"Point"}
}