{
  "type": "Feature",
  "properties": {
    "gn:admin1_code":"29",
    "gn:asciiname":"Tajabad-e Now",
    "gn:country_code":"IR",
    "gn:dem":1501,
    "gn:feature_class":"P",
    "gn:feature_code":"PPL",
    "gn:name":"T\u0101j\u0101b\u0101d-e Now",
    "gn:population":0,
    "gn:timezone":"Asia/Tehran",
    "iso:country":"IR",
    "name:fas_x_preferred":[
        "\u062a\u0627\u062c \u0622\u0628\u0627\u062f \u0646\u0648"
    ],
    "name:fas_x_variant":[
        "T\u0101j\u0101b\u0101d-e Now"
    ],
    "name:und_x_variant":[
        "Kaf\u0101\u2019\u012byeh",
        "T\u0101j\u0101b\u0101d"
    ],
    "wof:name":"Tajabad-e Now",
    "wof:placetype":"locality"
},
  "geometry": {"coordinates":[56.0132,30.4734],"type":"Point"}
}