{
  "type": "Feature",
  "properties": {
    "gn:admin1_code":"35.0",
    "gn:asciiname":"Shahrak-e Shali",
    "gn:country_code":"IR",
    "gn:dem":-9,
    "gn:feature_class":"P",
    "gn:feature_code":"PPL",
    "gn:name":"Shahrak-e Sh\u0101l\u012b",
    "gn:population":0,
    "gn:timezone":"Asia/Tehran",
    "iso:country":"IR",
    "name:fas_x_preferred":[
        "\u0634\u0647\u0631\u06a9 \u0634\u0627\u0644\u06cc"
    ],
    "name:und_x_variant":[
        "Shahrak-e Sh\u0101l\u012b"
    ],
    "wof:name":"Shahrak-e Shali",
    "wof:placetype":"locality"
},
  "geometry": {"coordinates":[51.65448,36.58878],"type":"Point"}
}