{
  "type": "Feature",
  "properties": {
    "gn:admin1_code":"8",
    "gn:asciiname":"Kureh Asneh",
    "gn:country_code":"IR",
    "gn:dem":892,
    "gn:feature_class":"P",
    "gn:feature_code":"PPL",
    "gn:name":"K\u016breh Asneh",
    "gn:population":0,
    "gn:timezone":"Asia/Tehran",
    "iso:country":"IR",
    "name:fas_x_preferred":[
        "\u06a9\u0648\u0631\u0647 \u0627\u0633\u0646\u0647"
    ],
    "name:fas_x_variant":[
        "K\u016breh Asneh"
    ],
    "name:und_x_variant":[
        "K\u016breh Asneh"
    ],
    "wof:name":"Kureh Asneh",
    "wof:placetype":"locality"
},
  "geometry": {"coordinates":[49.0496,37.239],"type":"Point"}
}