{
  "type": "Feature",
  "properties": {
    "gn:admin1_code":"36.0",
    "gn:asciiname":"Kalgeh Bin",
    "gn:country_code":"IR",
    "gn:dem":1912,
    "gn:feature_class":"P",
    "gn:feature_code":"PPL",
    "gn:name":"Kalgeh B\u012bn",
    "gn:population":0,
    "gn:timezone":"Asia/Tehran",
    "iso:country":"IR",
    "name:fas_x_preferred":[
        "\u06a9\u0644\u06af\u0647 \u0628\u06cc\u0646"
    ],
    "name:und_x_variant":[
        "Kalgeh B\u012bn"
    ],
    "wof:name":"Kalgeh Bin",
    "wof:placetype":"locality"
},
  "geometry": {"coordinates":[48.58094000000001,36.70098],"type":"Point"}
}