{
  "type": "Feature",
  "properties": {
    "gn:admin1_code":"33",
    "gn:asciiname":"Kapirabad",
    "gn:country_code":"IR",
    "gn:dem":1271,
    "gn:feature_class":"P",
    "gn:feature_code":"PPL",
    "gn:name":"Kap\u012br\u0101b\u0101d",
    "gn:population":0,
    "gn:timezone":"Asia/Tehran",
    "iso:country":"IR",
    "name:fas_x_preferred":[
        "Kab\u012br\u0101b\u0101d"
    ],
    "name:fas_x_variant":[
        "\u06a9\u067e\u06cc\u0631 \u0622\u0628\u0627\u062f"
    ],
    "name:und_x_variant":[
        "Kap\u012br\u0101b\u0101d"
    ],
    "wof:name":"Kapirabad",
    "wof:placetype":"locality"
},
  "geometry": {"coordinates":[47.08585,38.95551],"type":"Point"}
}