{
  "type": "Feature",
  "properties": {
    "gn:admin1_code":"11",
    "gn:asciiname":"Jagin-e Zir",
    "gn:country_code":"IR",
    "gn:dem":88,
    "gn:feature_class":"P",
    "gn:feature_code":"PPL",
    "gn:name":"Jag\u012bn-e Z\u012br",
    "gn:population":0,
    "gn:timezone":"Asia/Tehran",
    "iso:country":"IR",
    "name:fas_x_preferred":[
        "\u062c\u064e\u06af\u064a\u0646\u0650 \u0632\u064a\u0631"
    ],
    "name:fas_x_variant":[
        "Jag\u012bn-e Z\u012br"
    ],
    "name:und_x_variant":[
        "Jagin"
    ],
    "wof:name":"Jagin-e Zir",
    "wof:placetype":"locality"
},
  "geometry": {"coordinates":[58.03333000000001,25.95],"type":"Point"}
}