{
  "type": "Feature",
  "properties": {
    "gn:admin1_code":"35.0",
    "gn:asciiname":"Mojtame`-ye Vila'i-ye Golbaran",
    "gn:country_code":"IR",
    "gn:dem":-18,
    "gn:feature_class":"P",
    "gn:feature_code":"PPL",
    "gn:name":"Mojtame\u2018-ye V\u012bl\u0101\u2019\u012b-ye Golbar\u0101n",
    "gn:population":0,
    "gn:timezone":"Asia/Tehran",
    "iso:country":"IR",
    "name:fas_x_preferred":[
        "\u06a9\u062a \u06a9\u0644\u0647"
    ],
    "name:fas_x_variant":[
        "\u0645\u062c\u062a\u0645\u0639 \u0648\u064a\u0644\u0627\u064a\u06cc \u06af\u0644\u0628\u0631\u0627\u0646"
    ],
    "name:und_x_variant":[
        "Kot Kalleh",
        "Mojtame\u2018-ye V\u012bl\u0101\u2019\u012b-ye Golbar\u0101n"
    ],
    "wof:name":"Mojtame`-ye Vila'i-ye Golbaran",
    "wof:placetype":"locality"
},
  "geometry": {"coordinates":[50.99352,36.75943],"type":"Point"}
}