{
  "type": "Feature",
  "properties": {
    "gn:admin1_code":"34",
    "gn:asciiname":"Savarabad",
    "gn:country_code":"IR",
    "gn:dem":1842,
    "gn:feature_class":"P",
    "gn:feature_code":"PPL",
    "gn:name":"Sav\u0101r\u0101b\u0101d",
    "gn:population":0,
    "gn:timezone":"Asia/Tehran",
    "iso:country":"IR",
    "name:fas_x_preferred":[
        "Sav\u0101r\u0101b\u0101d"
    ],
    "name:fas_x_variant":[
        "\u0633\u0648\u0627\u0631 \u0622\u0628\u0627\u062f",
        "\u0633\u0648\u0627\u0631\u0622\u0628\u0627\u062f"
    ],
    "name:und_x_variant":[
        "\u0633\u0648\u0627\u0631 \u0622\u0628\u0627\u062f"
    ],
    "wof:name":"Savarabad",
    "wof:placetype":"locality"
},
  "geometry": {"coordinates":[49.82212,33.98821],"type":"Point"}
}