{
  "type": "Feature",
  "properties": {
    "gn:admin1_code":"7",
    "gn:asciiname":"Chahar Rah",
    "gn:country_code":"IR",
    "gn:dem":1061,
    "gn:feature_class":"P",
    "gn:feature_code":"PPL",
    "gn:name":"Chah\u0101r R\u0101h",
    "gn:population":0,
    "gn:timezone":"Asia/Tehran",
    "iso:country":"IR",
    "name:fas_x_preferred":[
        "Chah\u0101r R\u0101h"
    ],
    "wof:name":"Chahar Rah",
    "wof:placetype":"locality"
},
  "geometry": {"coordinates":[51.15056,30.08583],"type":"Point"}
}