{
  "type": "Feature",
  "properties": {
    "gn:admin1_code":"7",
    "gn:asciiname":"Kaman Keshi",
    "gn:country_code":"IR",
    "gn:dem":506,
    "gn:feature_class":"P",
    "gn:feature_code":"PPL",
    "gn:name":"Kam\u0101n Kesh\u012b",
    "gn:population":0,
    "gn:timezone":"Asia/Tehran",
    "iso:country":"IR",
    "name:fas_x_preferred":[
        "\u06a9\u0645\u0627\u0646 \u06a9\u0634\u06cc"
    ],
    "name:fas_x_variant":[
        "Kam\u0101n Kesh\u012b",
        "\u06a9\u0645\u0627\u0646\u06a9\u0634\u06cc"
    ],
    "name:msa_x_preferred":[
        "Kaman Keshi"
    ],
    "wof:name":"Kaman Keshi",
    "wof:placetype":"locality"
},
  "geometry": {"coordinates":[51.3999,29.5449],"type":"Point"}
}