{
  "type": "Feature",
  "properties": {
    "gn:admin1_code":"15",
    "gn:asciiname":"Dezh Musa",
    "gn:country_code":"IR",
    "gn:dem":94,
    "gn:feature_class":"P",
    "gn:feature_code":"PPL",
    "gn:name":"Dezh M\u016bs\u00e1",
    "gn:population":0,
    "gn:timezone":"Asia/Tehran",
    "iso:country":"IR",
    "name:fas_x_preferred":[
        "Dezh M\u016bs\u00e1"
    ],
    "name:fas_x_variant":[
        "\u062f\u0698 \u0645\u0648\u0633\u06cc"
    ],
    "wof:name":"Dezh Musa",
    "wof:placetype":"locality"
},
  "geometry": {"coordinates":[48.22747,32.32324000000001],"type":"Point"}
}