{
  "type": "Feature",
  "properties": {
    "gn:admin1_code":"36",
    "gn:asciiname":"Gollijeh",
    "gn:country_code":"IR",
    "gn:dem":2153,
    "gn:feature_class":"P",
    "gn:feature_code":"PPL",
    "gn:name":"Goll\u012bjeh",
    "gn:population":0,
    "gn:timezone":"Asia/Tehran",
    "iso:country":"IR",
    "name:fas_x_preferred":[
        "\u06af\u0644\u06cc\u062c\u0647"
    ],
    "name:fas_x_variant":[
        "Goll\u012bjeh",
        "\u06af\u0644\u06cc\u062c\u0647 \u0633\u0641\u0644\u06cc"
    ],
    "name:und_x_variant":[
        "Gul\u016bjab",
        "Kol\u016bcheh",
        "Gyul\u2019dzya",
        "Goljeh",
        "Goll\u012bjeh-ye Sofl\u00e1"
    ],
    "wof:name":"Gollijeh",
    "wof:placetype":"locality"
},
  "geometry": {"coordinates":[48.67892,36.76525],"type":"Point"}
}