{
  "type": "Feature",
  "properties": {
    "gn:admin1_code":"42",
    "gn:asciiname":"Shah Galdi",
    "gn:country_code":"IR",
    "gn:dem":1103,
    "gn:feature_class":"P",
    "gn:feature_code":"PPL",
    "gn:name":"Sh\u0101h Gald\u012b",
    "gn:population":0,
    "gn:timezone":"Asia/Tehran",
    "iso:country":"IR",
    "name:ara_x_preferred":[
        "\u0634\u0627\u0647 \u063a\u0644\u062f\u064a"
    ],
    "name:fas_x_preferred":[
        "\u0634\u0627\u0647 \u06af\u0644\u062f\u06cc"
    ],
    "name:fas_x_variant":[
        "Sh\u0101h Gald\u012b"
    ],
    "wof:name":"Shah Galdi",
    "wof:placetype":"locality"
},
  "geometry": {"coordinates":[59.29434000000001,36.59078],"type":"Point"}
}