{
  "type": "Feature",
  "properties": {
    "gn:admin1_code":"26",
    "gn:asciiname":"Salehabad",
    "gn:country_code":"IR",
    "gn:dem":973,
    "gn:feature_class":"P",
    "gn:feature_code":"PPL",
    "gn:name":"\u015e\u0101le\u1e29\u0101b\u0101d",
    "gn:population":0,
    "gn:timezone":"Asia/Tehran",
    "iso:country":"IR",
    "name:fas_x_preferred":[
        "\u015e\u0101le\u1e29\u0101b\u0101d"
    ],
    "name:fas_x_variant":[
        "\u0635\u0627\u0644\u062d \u0622\u0628\u0627\u062f"
    ],
    "wof:name":"Salehabad",
    "wof:placetype":"locality"
},
  "geometry": {"coordinates":[51.7584,35.3579],"type":"Point"}
}