{
  "type": "Feature",
  "properties": {
    "gn:admin1_code":"3.0",
    "gn:asciiname":"Cheshmeh Shen",
    "gn:country_code":"IR",
    "gn:dem":2083,
    "gn:feature_class":"P",
    "gn:feature_code":"PPL",
    "gn:name":"Cheshmeh Shen",
    "gn:population":0,
    "gn:timezone":"Asia/Tehran",
    "iso:country":"IR",
    "name:fas_x_preferred":[
        "\u0686\u0634\u0645\u0647 \u0634\u0646"
    ],
    "wof:name":"Cheshmeh Shen",
    "wof:placetype":"locality"
},
  "geometry": {"coordinates":[50.50379,31.76555],"type":"Point"}
}