{
  "type": "Feature",
  "properties": {
    "gn:admin1_code":"4",
    "gn:asciiname":"Kaliri",
    "gn:country_code":"IR",
    "gn:dem":37,
    "gn:feature_class":"P",
    "gn:feature_code":"PPL",
    "gn:name":"Kal\u012br\u012b",
    "gn:population":0,
    "gn:timezone":"Asia/Tehran",
    "iso:country":"IR",
    "name:fas_x_preferred":[
        "Kal\u012br\u012b"
    ],
    "name:fas_x_variant":[
        "\u06a9\u0644\u06cc\u0631\u06cc"
    ],
    "name:und_x_variant":[
        "\u06a9\u0644\u06cc\u0631\u06cc"
    ],
    "wof:name":"Kaliri",
    "wof:placetype":"locality"
},
  "geometry": {"coordinates":[59.28376,25.76544],"type":"Point"}
}