{
  "type": "Feature",
  "properties": {
    "gn:admin1_code":"1",
    "gn:asciiname":"Qadu Kandi",
    "gn:country_code":"IR",
    "gn:dem":1918,
    "gn:feature_class":"P",
    "gn:feature_code":"PPL",
    "gn:name":"Q\u0101d\u016b Kand\u012b",
    "gn:population":0,
    "gn:timezone":"Asia/Tehran",
    "iso:country":"IR",
    "name:ara_x_preferred":[
        "\u0642\u0627\u062f\u0648\u0643\u0646\u062f\u064a"
    ],
    "name:aze_x_preferred":[
        "Qad\u0131k\u0259ndi"
    ],
    "name:ceb_x_preferred":[
        "Q\u0101d\u016b Kand\u012b"
    ],
    "name:fas_x_preferred":[
        "\u0642\u0627\u062f\u0648 \u06a9\u0646\u062f\u06cc"
    ],
    "name:fas_x_variant":[
        "\u0642\u0627\u062f\u0648 \u0643\u064e\u0646\u062f\u06cc",
        "Q\u0101d\u016b Kand\u012b",
        "\u0642\u0627\u062f\u0648\u06a9\u0646\u062f\u06cc"
    ],
    "name:msa_x_preferred":[
        "Qadu Kandi"
    ],
    "name:swe_x_preferred":[
        "Q\u0101d\u016b Kand\u012b"
    ],
    "wof:name":"Qadu Kandi",
    "wof:placetype":"locality"
},
  "geometry": {"coordinates":[44.5039,39.0634],"type":"Point"}
}