{
  "type": "Feature",
  "properties": {
    "gn:admin1_code":"13",
    "gn:asciiname":"Elyasi-ye Mahmud",
    "gn:country_code":"IR",
    "gn:dem":605,
    "gn:feature_class":"P",
    "gn:feature_code":"PPL",
    "gn:name":"Ely\u0101s\u012b-ye Ma\u1e29m\u016bd",
    "gn:population":0,
    "gn:timezone":"Asia/Tehran",
    "iso:country":"IR",
    "name:ceb_x_preferred":[
        "Ely\u0101s\u012b-ye Ma\u1e29m\u016bd"
    ],
    "name:fas_x_preferred":[
        "\u0627\u0644\u064a\u0627\u0633\u06cc \u0645\u062d\u0645\u0648\u062f"
    ],
    "name:fas_x_variant":[
        "Ely\u0101s-e Ma\u1e29m\u016bd",
        "Ely\u0101s\u012b-ye Ma\u1e29m\u016bd",
        "\u0627\u0644\u06cc\u0627\u0633\u200c\u0645\u062d\u0645\u0648\u062f"
    ],
    "name:swe_x_preferred":[
        "Ely\u0101s\u012b-ye Ma\u1e29m\u016bd"
    ],
    "wof:name":"Elyasi-ye Mahmud",
    "wof:placetype":"locality"
},
  "geometry": {"coordinates":[45.867,34.607],"type":"Point"}
}