{
  "type": "Feature",
  "properties": {
    "gn:admin1_code":"16",
    "gn:asciiname":"Kalati",
    "gn:country_code":"IR",
    "gn:dem":1694,
    "gn:feature_class":"P",
    "gn:feature_code":"PPL",
    "gn:name":"Kal\u0101t\u012b",
    "gn:population":0,
    "gn:timezone":"Asia/Tehran",
    "iso:country":"IR",
    "name:ara_x_preferred":[
        "\u0643\u0627\u0644\u0627\u062a\u064a"
    ],
    "name:bos_x_preferred":[
        "Kalati"
    ],
    "name:ell_x_preferred":[
        "\u039a\u03ac\u03bb\u03b1\u03c4\u03b9"
    ],
    "name:fas_x_preferred":[
        "\u0643\u064e\u0644\u0627\u062a\u0650\u0647"
    ],
    "name:fas_x_variant":[
        "\u06a9\u0644\u0627\u062a\u06cc",
        "Kal\u0101teh",
        "Kal\u0101t\u012b"
    ],
    "name:fra_x_preferred":[
        "Kalati"
    ],
    "name:hrv_x_preferred":[
        "Kalati"
    ],
    "name:slv_x_preferred":[
        "Kalati"
    ],
    "name:srp_x_preferred":[
        "\u041a\u0430\u043b\u0430\u0442\u0438"
    ],
    "wof:name":"Kalati",
    "wof:placetype":"locality"
},
  "geometry": {"coordinates":[46.7434,34.8755],"type":"Point"}
}