{
  "type": "Feature",
  "properties": {
    "gn:admin1_code":"16",
    "gn:asciiname":"Kalati",
    "gn:country_code":"IR",
    "gn:dem":1694,
    "gn:feature_class":"P",
    "gn:feature_code":"PPL",
    "gn:name":"Kal\u0101t\u012b",
    "gn:population":0,
    "gn:timezone":"Asia/Tehran",
    "iso:country":"IR",
    "name:fas_x_preferred":[
        "\u0643\u064e\u0644\u0627\u062a\u0650\u0647"
    ],
    "name:fas_x_variant":[
        "\u06a9\u0644\u0627\u062a\u06cc",
        "Kal\u0101teh",
        "Kal\u0101t\u012b"
    ],
    "wof:name":"Kalati",
    "wof:placetype":"locality"
},
  "geometry": {"coordinates":[46.7434,34.8755],"type":"Point"}
}