{
  "type": "Feature",
  "properties": {
    "gn:admin1_code":"15",
    "gn:asciiname":"Zahrab-e Bala",
    "gn:country_code":"IR",
    "gn:dem":840,
    "gn:feature_class":"P",
    "gn:feature_code":"PPL",
    "gn:name":"Z\u0327ahr\u0101b-e B\u0101l\u0101",
    "gn:population":0,
    "gn:timezone":"Asia/Tehran",
    "iso:country":"IR",
    "name:fas_x_preferred":[
        "Z\u0327ahr\u0101b-e B\u0101l\u0101"
    ],
    "wof:name":"Zahrab-e Bala",
    "wof:placetype":"locality"
},
  "geometry": {"coordinates":[49.52861,32.125],"type":"Point"}
}