{
  "type": "Feature",
  "properties": {
    "gn:admin1_code":"16",
    "gn:asciiname":"Getmah Gatir",
    "gn:country_code":"IR",
    "gn:dem":1753,
    "gn:feature_class":"P",
    "gn:feature_code":"PPL",
    "gn:name":"Getmah Gat\u012br",
    "gn:population":0,
    "gn:timezone":"Asia/Tehran",
    "iso:country":"IR",
    "name:fas_x_preferred":[
        "\u06af\u0627\u062f\u0645\u0647 \u06af\u062a\u0631"
    ],
    "name:fas_x_variant":[
        "G\u0101dmeh Gater",
        "\u06af\u062a\u0645\u0647 \u06af\u062a\u06cc\u0631"
    ],
    "name:und_x_variant":[
        "Getmah Gat\u012br"
    ],
    "wof:name":"Getmah Gatir",
    "wof:placetype":"locality"
},
  "geometry": {"coordinates":[47.30995,36.08034],"type":"Point"}
}