{
  "type": "Feature",
  "properties": {
    "gn:admin1_code":"8",
    "gn:asciiname":"Taleghan",
    "gn:country_code":"IR",
    "gn:dem":411,
    "gn:feature_class":"P",
    "gn:feature_code":"PPL",
    "gn:name":"Taleghan",
    "gn:population":0,
    "gn:timezone":"Asia/Tehran",
    "iso:country":"IR",
    "name:fas_x_preferred":[
        "\u0162\u0101leq\u0101n"
    ],
    "name:fas_x_variant":[
        "\u0637\u0627\u0644\u0642\u0627\u0646"
    ],
    "name:msa_x_preferred":[
        "Taleqan"
    ],
    "name:ukr_x_preferred":[
        "\u0422\u0430\u043b\u0435\u043a\u0430\u043d"
    ],
    "wof:name":"Taleghan",
    "wof:placetype":"locality"
},
  "geometry": {"coordinates":[49.32835,36.99855],"type":"Point"}
}