{
  "type": "Feature",
  "properties": {
    "gn:admin1_code":"42",
    "gn:asciiname":"Deh Now-e Shur",
    "gn:country_code":"IR",
    "gn:dem":1128,
    "gn:feature_class":"P",
    "gn:feature_code":"PPL",
    "gn:name":"Deh Now-e Sh\u016br",
    "gn:population":0,
    "gn:timezone":"Asia/Tehran",
    "iso:country":"IR",
    "name:ceb_x_preferred":[
        "Deh Now-e Sh\u016br"
    ],
    "name:fas_x_preferred":[
        "\u062f\u0647 \u0646\u0648 \u0634\u0648\u0631"
    ],
    "name:fas_x_variant":[
        "Deh Now-e Sh\u016br",
        "\u062f\u0647\u200c\u0646\u0648 \u0634\u0648\u0631"
    ],
    "name:swe_x_preferred":[
        "Deh Now-e Sh\u016br"
    ],
    "name:und_x_variant":[
        "Dehnow-e Sarbor"
    ],
    "wof:name":"Deh Now-e Shur",
    "wof:placetype":"locality"
},
  "geometry": {"coordinates":[58.71271,36.04657],"type":"Point"}
}