{
  "type": "Feature",
  "properties": {
    "gn:admin1_code":"38.0",
    "gn:asciiname":"Qanbar Shah",
    "gn:country_code":"IR",
    "gn:dem":1334,
    "gn:elevation":"0.0",
    "gn:feature_class":"P",
    "gn:feature_code":"PPL",
    "gn:name":"Qanbar Sh\u0101h",
    "gn:population":0,
    "gn:timezone":"Asia/Tehran",
    "iso:country":"IR",
    "name:fas_x_preferred":[
        "\u0642\u0646\u0628\u0631 \u0634\u0627\u0647"
    ],
    "name:fas_x_variant":[
        "Qanbar\u0101b\u0101d",
        "Qanbar Sh\u0101h"
    ],
    "wof:name":"Qanbar Shah",
    "wof:placetype":"locality"
},
  "geometry": {"coordinates":[49.63703,35.90101],"type":"Point"}
}