{
  "type": "Feature",
  "properties": {
    "gn:admin1_code":"11.0",
    "gn:asciiname":"Mehmani",
    "gn:country_code":"IR",
    "gn:dem":51,
    "gn:feature_class":"P",
    "gn:feature_code":"PPL",
    "gn:name":"Mehm\u0101n\u012b",
    "gn:population":0,
    "gn:timezone":"Asia/Tehran",
    "iso:country":"IR",
    "name:ceb_x_preferred":[
        "Mehm\u0101n\u012b"
    ],
    "name:fas_x_preferred":[
        "\u0645\u0647\u0645\u0627\u0646\u06cc"
    ],
    "name:fas_x_variant":[
        "Mehm\u0101n\u012b"
    ],
    "name:msa_x_preferred":[
        "Mehmani"
    ],
    "name:swe_x_preferred":[
        "Mehm\u0101n\u012b"
    ],
    "wof:name":"Mehmani",
    "wof:placetype":"locality"
},
  "geometry": {"coordinates":[57.2476,26.5201],"type":"Point"}
}