{
  "type": "Feature",
  "properties": {
    "gn:admin1_code":"7",
    "gn:asciiname":"Sahlabad",
    "gn:country_code":"IR",
    "gn:dem":1315,
    "gn:feature_class":"P",
    "gn:feature_code":"PPL",
    "gn:name":"Sahl\u0101b\u0101d",
    "gn:population":0,
    "gn:timezone":"Asia/Tehran",
    "iso:country":"IR",
    "name:fas_x_preferred":[
        "\u0633\u0647\u0644 \u0622\u0628\u0627\u062f"
    ],
    "name:fas_x_variant":[
        "Sahl\u0101b\u0101d"
    ],
    "wof:name":"Sahlabad",
    "wof:placetype":"locality"
},
  "geometry": {"coordinates":[52.4978,28.8345],"type":"Point"}
}