{
  "type": "Feature",
  "properties": {
    "gn:admin1_code":"29",
    "gn:asciiname":"Khvajeh Nezam",
    "gn:country_code":"IR",
    "gn:dem":1183,
    "gn:feature_class":"P",
    "gn:feature_code":"PPL",
    "gn:name":"Khv\u0101jeh Nez\u0327\u0101m",
    "gn:population":0,
    "gn:timezone":"Asia/Tehran",
    "iso:country":"IR",
    "name:fas_x_preferred":[
        "\u062e\u0648\u0627\u062c\u0650\u0647 \u0646\u0650\u0638\u0627\u0645"
    ],
    "name:fas_x_variant":[
        "\u062e\u0627\u0643 \u0646\u0650\u0632\u0627\u0645",
        "Khv\u0101jeh Nez\u0327\u0101m",
        "\u062e\u0648\u0627\u062c\u0647 \u0646\u0638\u0627\u0645",
        "\u0646\u0638\u0627\u0645 \u0648\u0641\u0627"
    ],
    "name:und_x_variant":[
        "Khakenesun",
        "Kh\u0101k Nez\u0101m",
        "Nez\u0327\u0101m Vaf\u0101"
    ],
    "wof:name":"Khvajeh Nezam",
    "wof:placetype":"locality"
},
  "geometry": {"coordinates":[58.24469000000001,29.13357],"type":"Point"}
}