{
  "type": "Feature",
  "properties": {
    "gn:admin1_code":"40",
    "gn:asciiname":"Bisheh",
    "gn:country_code":"IR",
    "gn:dem":980,
    "gn:feature_class":"P",
    "gn:feature_code":"PPL",
    "gn:name":"B\u012bsheh",
    "gn:population":0,
    "gn:timezone":"Asia/Tehran",
    "iso:country":"IR",
    "name:fas_x_preferred":[
        "B\u012bsheh-ye B\u0101l\u0101"
    ],
    "name:fas_x_variant":[
        "\u0628\u064a\u0634\u0647 \u0628\u0627\u0644\u0627",
        "B\u012bsheh",
        "\u0628\u064a\u0634\u0647",
        "\u0628\u064a\u0634\u0647 \u0639\u0644\u064a\u0627"
    ],
    "name:und_x_variant":[
        "B\u012bsheh-ye \u2018Oly\u0101"
    ],
    "wof:name":"Bisheh",
    "wof:placetype":"locality"
},
  "geometry": {"coordinates":[56.52479,33.80988],"type":"Point"}
}