{
  "type": "Feature",
  "properties": {
    "gn:admin1_code":"1",
    "gn:asciiname":"Akhyan-e Bozorg",
    "gn:country_code":"IR",
    "gn:dem":1616,
    "gn:feature_class":"P",
    "gn:feature_code":"PPL",
    "gn:name":"Akhy\u0101n-e Bozorg",
    "gn:population":0,
    "gn:timezone":"Asia/Tehran",
    "iso:country":"IR",
    "name:fas_x_preferred":[
        "\u0627\u064e\u062e\u064a\u0627\u0646\u0650 \u0628\u064f\u0632\u064f\u0631\u06af"
    ],
    "name:fas_x_variant":[
        "\u0627\u062e\u06cc\u0627\u0646 \u0628\u0632\u0631\u06af",
        "Akhy\u0101n-e Bozorg"
    ],
    "wof:name":"Akhyan-e Bozorg",
    "wof:placetype":"locality"
},
  "geometry": {"coordinates":[44.6723,37.7074],"type":"Point"}
}