{
  "type": "Feature",
  "properties": {
    "gn:admin1_code":"15.0",
    "gn:asciiname":"Hezar Mani-ye Sofla",
    "gn:country_code":"IR",
    "gn:dem":125,
    "gn:feature_class":"P",
    "gn:feature_code":"PPL",
    "gn:name":"Hez\u0101r Man\u012b-ye Sofl\u00e1",
    "gn:population":0,
    "gn:timezone":"Asia/Tehran",
    "iso:country":"IR",
    "name:ara_x_preferred":[
        "\u0647\u0632\u0627\u0631 \u0645\u0646\u064a \u0627\u0644\u0633\u0641\u0644\u0649"
    ],
    "name:fas_x_preferred":[
        "Hez\u0101r Man\u012b"
    ],
    "name:fas_x_variant":[
        "\u0647\u0632\u0627\u0631 \u0645\u0646\u06cc",
        "\u0647\u0632\u0627\u0631 \u0645\u0646\u06cc \u0633\u0641\u0644\u06cc",
        "\u06a9\u0645\u0627\u0626\u06cc",
        "\u0647\u0632\u0627\u0631\u0645\u0646\u06cc \u0633\u0641\u0644\u06cc"
    ],
    "name:und_x_variant":[
        "Hez\u0101r Man\u012b-ye Sofl\u00e1",
        "Kam\u0101\u2019\u012b"
    ],
    "wof:name":"Hezar Mani-ye Sofla",
    "wof:placetype":"locality"
},
  "geometry": {"coordinates":[49.58238,31.18823],"type":"Point"}
}