{
  "type": "Feature",
  "properties": {
    "gn:admin1_code":"29",
    "gn:asciiname":"Hojdak",
    "gn:country_code":"IR",
    "gn:dem":2073,
    "gn:feature_class":"P",
    "gn:feature_code":"PPL",
    "gn:name":"Hojdak",
    "gn:population":0,
    "gn:timezone":"Asia/Tehran",
    "iso:country":"IR",
    "name:fas_x_preferred":[
        "\u0647\u062c\u062f\u06a9"
    ],
    "wof:name":"Hojdak",
    "wof:placetype":"locality"
},
  "geometry": {"coordinates":[57.00313000000001,30.75897],"type":"Point"}
}