{
  "type": "Feature",
  "properties": {
    "gn:admin1_code":"44",
    "gn:asciiname":"Eshtehard",
    "gn:country_code":"IR",
    "gn:dem":1161,
    "gn:feature_class":"P",
    "gn:feature_code":"PPLA2",
    "gn:name":"Eshteh\u0101rd",
    "gn:population":0,
    "gn:timezone":"Asia/Tehran",
    "iso:country":"IR",
    "name:ara_x_preferred":[
        "\u0625\u0634\u062a\u0647\u0627\u0631\u062f"
    ],
    "name:aze_x_preferred":[
        "\u0130\u015ftihard"
    ],
    "name:ceb_x_preferred":[
        "Eshteh\u0101rd"
    ],
    "name:fas_x_preferred":[
        "\u0627\u0634\u062a\u0647\u0627\u0631\u062f"
    ],
    "name:fas_x_variant":[
        "Eshteh\u0101rd"
    ],
    "name:fra_x_preferred":[
        "Echtehard"
    ],
    "name:ita_x_preferred":[
        "Eshtehard"
    ],
    "name:mlg_x_preferred":[
        "Eshtehard"
    ],
    "name:tur_x_preferred":[
        "\u0130\u015ftihard"
    ],
    "name:und_x_variant":[
        "\u012ashtahard",
        "\u012ashtah\u0101b\u0101d"
    ],
    "name:urd_x_preferred":[
        "\u0627\u0634\u062a\u06c1\u0627\u0631\u062f"
    ],
    "wof:name":"Eshtehard",
    "wof:placetype":"locality"
},
  "geometry": {"coordinates":[50.3662,35.7255],"type":"Point"}
}