{
  "type": "Feature",
  "properties": {
    "gn:admin1_code":"4.0",
    "gn:asciiname":"`Ali Sarani",
    "gn:country_code":"IR",
    "gn:dem":483,
    "gn:feature_class":"P",
    "gn:feature_code":"PPL",
    "gn:name":"\u2018Al\u012b S\u0101r\u0101n\u012b",
    "gn:population":0,
    "gn:timezone":"Asia/Tehran",
    "iso:country":"IR",
    "name:fas_x_preferred":[
        "\u0639\u0644\u06cc \u0633\u0627\u0631\u0627\u0646\u06cc"
    ],
    "name:fas_x_variant":[
        "\u2018Al\u012b S\u0101r\u0101n\u012b",
        "\u0639\u0644\u06cc\u062c\u0627\u0646"
    ],
    "name:und_x_variant":[
        "\u2018Al\u012bkh\u0101n"
    ],
    "wof:name":"`Ali Sarani",
    "wof:placetype":"locality"
},
  "geometry": {"coordinates":[61.6964,31.1076],"type":"Point"}
}