{
  "type": "Feature",
  "properties": {
    "gn:admin1_code":"23",
    "gn:asciiname":"Golsorkh-e Sofla",
    "gn:country_code":"IR",
    "gn:dem":1121,
    "gn:feature_class":"P",
    "gn:feature_code":"PPL",
    "gn:name":"Golsorkh-e Sofl\u00e1",
    "gn:population":0,
    "gn:timezone":"Asia/Tehran",
    "iso:country":"IR",
    "name:fas_x_preferred":[
        "\u06af\u0644\u0633\u0631\u062e \u0633\u0641\u0644\u06cc"
    ],
    "name:fas_x_variant":[
        "Kal Sorkh-e Sofl\u00e1",
        "\u06af\u0644 \u0633\u0631\u062e \u0639\u064a\u062f\u06cc",
        "\u06af\u0644 \u0633\u0631\u062e \u0633\u0641\u0644\u06cc"
    ],
    "name:und_x_variant":[
        "Golsorkh-e Sofl\u00e1",
        "Gol Sorkh-e \u2018Eyd\u012b",
        "Gol Sorkh-e Sofl\u00e1"
    ],
    "wof:name":"Golsorkh-e Sofla",
    "wof:placetype":"locality"
},
  "geometry": {"coordinates":[47.3124,33.46009],"type":"Point"}
}