{
  "type": "Feature",
  "properties": {
    "gn:admin1_code":"29",
    "gn:asciiname":"Madim",
    "gn:cc2":"IR",
    "gn:country_code":"IR",
    "gn:dem":2814,
    "gn:feature_class":"P",
    "gn:feature_code":"PPL",
    "gn:name":"Mad\u012bm",
    "gn:population":0,
    "gn:timezone":"Asia/Tehran",
    "iso:country":"IR",
    "name:fas_x_preferred":[
        "Mad\u012bm"
    ],
    "name:und_x_variant":[
        "Mod\u012bm"
    ],
    "wof:name":"Madim",
    "wof:placetype":"locality"
},
  "geometry": {"coordinates":[56.59639,29.48389],"type":"Point"}
}