{
  "type": "Feature",
  "properties": {
    "gn:admin1_code":"35.0",
    "gn:asciiname":"Taru",
    "gn:country_code":"IR",
    "gn:dem":363,
    "gn:feature_class":"P",
    "gn:feature_code":"PPL",
    "gn:name":"Tar\u016b",
    "gn:population":0,
    "gn:timezone":"Asia/Tehran",
    "iso:country":"IR",
    "name:ceb_x_preferred":[
        "Taru"
    ],
    "name:fas_x_preferred":[
        "\u062a\u064e\u0631\u0648"
    ],
    "name:fas_x_variant":[
        "Tar\u016b"
    ],
    "name:fin_x_preferred":[
        "Taru"
    ],
    "name:swe_x_preferred":[
        "Taru"
    ],
    "wof:name":"Taru",
    "wof:placetype":"locality"
},
  "geometry": {"coordinates":[52.81667,36.23333],"type":"Point"}
}