{
  "type": "Feature",
  "properties": {
    "gn:admin1_code":"41.0",
    "gn:asciiname":"Gavi",
    "gn:country_code":"IR",
    "gn:dem":1471,
    "gn:feature_class":"P",
    "gn:feature_code":"PPL",
    "gn:name":"Gav\u012b",
    "gn:population":0,
    "gn:timezone":"Asia/Tehran",
    "iso:country":"IR",
    "name:fas_x_preferred":[
        "\u06af\u0648\u06cc"
    ],
    "name:fas_x_variant":[
        "Gav\u012b"
    ],
    "wof:name":"Gavi",
    "wof:placetype":"locality"
},
  "geometry": {"coordinates":[60.5239,32.4042],"type":"Point"}
}