{
  "type": "Feature",
  "properties": {
    "gn:admin1_code":"16.0",
    "gn:asciiname":"Hashli",
    "gn:country_code":"IR",
    "gn:dem":1524,
    "gn:feature_class":"P",
    "gn:feature_code":"PPL",
    "gn:name":"Hashl\u012b",
    "gn:population":0,
    "gn:timezone":"Asia/Tehran",
    "iso:country":"IR",
    "name:fas_x_preferred":[
        "\u0647\u064e\u0634\u0644\u06cc"
    ],
    "name:fas_x_variant":[
        "Hashl\u012b"
    ],
    "wof:name":"Hashli",
    "wof:placetype":"locality"
},
  "geometry": {"coordinates":[46.83333,35.16667],"type":"Point"}
}