{
  "type": "Feature",
  "properties": {
    "gn:admin1_code":"7",
    "gn:asciiname":"Tol-e Khuk",
    "gn:country_code":"IR",
    "gn:dem":436,
    "gn:feature_class":"P",
    "gn:feature_code":"PPL",
    "gn:name":"Tol-e Kh\u016bk",
    "gn:population":0,
    "gn:timezone":"Asia/Tehran",
    "iso:country":"IR",
    "name:fas_x_preferred":[
        "Tol-e Kh\u016bk"
    ],
    "wof:name":"Tol-e Khuk",
    "wof:placetype":"locality"
},
  "geometry": {"coordinates":[52.86083000000001,27.71806],"type":"Point"}
}