{
  "type": "Feature",
  "properties": {
    "gn:admin1_code":"38.0",
    "gn:asciiname":"Kushkak",
    "gn:country_code":"IR",
    "gn:dem":1436,
    "gn:feature_class":"P",
    "gn:feature_code":"PPL",
    "gn:name":"K\u016bshkak",
    "gn:population":0,
    "gn:timezone":"Asia/Tehran",
    "iso:country":"IR",
    "name:fas_x_preferred":[
        "\u06a9\u0648\u0634\u06a9\u06a9"
    ],
    "name:fas_x_variant":[
        "K\u016bshkak"
    ],
    "wof:name":"Kushkak",
    "wof:placetype":"locality"
},
  "geometry": {"coordinates":[49.74619000000001,36.34297],"type":"Point"}
}