{
  "type": "Feature",
  "properties": {
    "gn:admin1_code":"29",
    "gn:asciiname":"Bagh Guk",
    "gn:country_code":"IR",
    "gn:dem":1844,
    "gn:feature_class":"P",
    "gn:feature_code":"PPL",
    "gn:name":"B\u0101gh G\u016bk",
    "gn:population":0,
    "gn:timezone":"Asia/Tehran",
    "iso:country":"IR",
    "name:fas_x_preferred":[
        "\u0628\u0627\u063a \u06af\u0648\u0643"
    ],
    "name:fas_x_variant":[
        "B\u0101gh G\u016bk"
    ],
    "wof:name":"Bagh Guk",
    "wof:placetype":"locality"
},
  "geometry": {"coordinates":[57.7641,29.0802],"type":"Point"}
}