{
  "type": "Feature",
  "properties": {
    "gn:admin1_code":"33.0",
    "gn:asciiname":"Qezeljeh Zarrin",
    "gn:country_code":"IR",
    "gn:dem":1798,
    "gn:feature_class":"P",
    "gn:feature_code":"PPL",
    "gn:name":"Qezeljeh Zarr\u012bn",
    "gn:population":0,
    "gn:timezone":"Asia/Tehran",
    "iso:country":"IR",
    "name:fas_x_preferred":[
        "\u0642\u0632\u0644\u062c\u0647 \u062e\u0631\u0627\u0628\u0647"
    ],
    "name:fas_x_variant":[
        "\u0642\u0650\u0632\u0650\u0644\u062c\u0650\u0647 \u062e\u064e\u0631\u0627\u0628\u0650\u0647",
        "\u0642\u0650\u0632\u0650\u0644\u062c\u0650\u0647",
        "Qezeljeh-ye Khar\u0101beh",
        "\u0642\u0632\u0644\u062c\u0647 \u0632\u0631\u06cc\u0646"
    ],
    "name:und_x_variant":[
        "Qezeljeh Khar\u0101beh",
        "Qezeljeh",
        "Qezeljeh Zarr\u012bn"
    ],
    "wof:name":"Qezeljeh Zarrin",
    "wof:placetype":"locality"
},
  "geometry": {"coordinates":[47.1045,38.18],"type":"Point"}
}