{
  "type": "Feature",
  "properties": {
    "gn:admin1_code":"44.0",
    "gn:asciiname":"Leylestan",
    "gn:country_code":"IR",
    "gn:dem":2114,
    "gn:feature_class":"P",
    "gn:feature_code":"PPL",
    "gn:name":"Leylest\u0101n",
    "gn:population":0,
    "gn:timezone":"Asia/Tehran",
    "iso:country":"IR",
    "name:ceb_x_preferred":[
        "Leylest\u0101n"
    ],
    "name:fas_x_preferred":[
        "Leylest\u0101n"
    ],
    "name:fas_x_variant":[
        "\u0644\u064a\u0644\u0633\u062a\u0627\u0646",
        "\u0644\u06cc\u0644\u0633\u062a\u0627\u0646"
    ],
    "name:msa_x_preferred":[
        "Leylestan"
    ],
    "name:rus_x_preferred":[
        "\u041b\u0435\u0439\u043b\u0435\u0441\u0442\u0430\u043d"
    ],
    "name:swe_x_preferred":[
        "Leylest\u0101n"
    ],
    "name:und_x_variant":[
        "\u0644\u064a\u0644\u0633\u062a\u0627\u0646"
    ],
    "wof:name":"Leylestan",
    "wof:placetype":"locality"
},
  "geometry": {"coordinates":[51.12605,36.06718],"type":"Point"}
}