{
  "type": "Feature",
  "properties": {
    "gn:admin1_code":"22",
    "gn:asciiname":"Chahar Borj",
    "gn:country_code":"IR",
    "gn:dem":33,
    "gn:feature_class":"P",
    "gn:feature_code":"PPL",
    "gn:name":"Chah\u0101r Borj",
    "gn:population":0,
    "gn:timezone":"Asia/Tehran",
    "iso:country":"IR",
    "name:ara_x_preferred":[
        "\u062a\u0634\u0647\u0627\u0631 \u0628\u0631\u062c"
    ],
    "name:fas_x_preferred":[
        "\u0686\u0647\u0627\u0631 \u0628\u0631\u062c"
    ],
    "name:fas_x_variant":[
        "\u0686\u064e\u0647\u0627\u0631 \u0628\u0648\u0631\u062c",
        "Chah\u0101r Borj",
        "\u0686\u0647\u0627\u0631\u0628\u0631\u062c"
    ],
    "name:msa_x_preferred":[
        "Chahar Borj"
    ],
    "name:und_x_variant":[
        "Cheh\u0101r Burj",
        "Chah\u0101r B\u016brj"
    ],
    "wof:name":"Chahar Borj",
    "wof:placetype":"locality"
},
  "geometry": {"coordinates":[50.7198,29.6065],"type":"Point"}
}