{
  "type": "Feature",
  "properties": {
    "gn:admin1_code":"13",
    "gn:asciiname":"Kaseh-ye Geran",
    "gn:country_code":"IR",
    "gn:dem":1019,
    "gn:feature_class":"P",
    "gn:feature_code":"PPL",
    "gn:name":"K\u0101seh-ye Ger\u0101n",
    "gn:population":0,
    "gn:timezone":"Asia/Tehran",
    "iso:country":"IR",
    "name:fas_x_preferred":[
        "\u06a9\u0627\u0633\u0647 \u06af\u0631\u0627\u0646"
    ],
    "name:fas_x_variant":[
        "K\u0101seh Gar\u0101n",
        "K\u0101seh-ye Ger\u0101n"
    ],
    "name:und_x_variant":[
        "K\u0101s\u0101kran",
        "K\u0101seh Kar\u0101n"
    ],
    "wof:name":"Kaseh-ye Geran",
    "wof:placetype":"locality"
},
  "geometry": {"coordinates":[46.0296,34.0906],"type":"Point"}
}