{
  "type": "Feature",
  "properties": {
    "gn:admin1_code":"28",
    "gn:asciiname":"Mobarakeh",
    "gn:country_code":"IR",
    "gn:dem":1538,
    "gn:feature_class":"P",
    "gn:feature_code":"PPL",
    "gn:name":"Mob\u0101rakeh",
    "gn:population":0,
    "gn:timezone":"Asia/Tehran",
    "iso:country":"IR",
    "name:ara_x_preferred":[
        "\u0645\u0628\u0627\u0631\u0643\u0629"
    ],
    "name:azb_x_preferred":[
        "\u0645\u0648\u0628\u0627\u0631\u06a9\u0647"
    ],
    "name:aze_x_preferred":[
        "M\u00fcbar\u0259k\u0259"
    ],
    "name:fas_x_preferred":[
        "\u0645\u0628\u0627\u0631\u06a9\u0647"
    ],
    "name:fas_x_variant":[
        "Mob\u0101rakeh"
    ],
    "name:hin_x_preferred":[
        "\u092e\u0941\u092c\u093e\u0930\u0915\u0947"
    ],
    "name:ita_x_preferred":[
        "Mobarakeh"
    ],
    "name:mlg_x_preferred":[
        "Mobarakeh"
    ],
    "name:mzn_x_preferred":[
        "\u0645\u0628\u0627\u0631\u06a9\u0647"
    ],
    "name:pnb_x_preferred":[
        "\u0645\u0628\u0627\u0631\u06a9\u06c1"
    ],
    "name:pol_x_preferred":[
        "Mobarake"
    ],
    "name:rus_x_preferred":[
        "\u041c\u043e\u0431\u0430\u0440\u0435\u043a\u0435"
    ],
    "name:tgk_x_preferred":[
        "\u041c\u0443\u0431\u043e\u0440\u0430\u043a\u0430"
    ],
    "name:tur_x_preferred":[
        "M\u00fcbareke"
    ],
    "name:und_x_variant":[
        "Mobarakeh Pishkooh"
    ],
    "wof:name":"Mobarakeh",
    "wof:placetype":"locality"
},
  "geometry": {"coordinates":[52.5134,31.8418],"type":"Point"}
}