{
  "type": "Feature",
  "properties": {
    "gn:admin1_code":"28",
    "gn:asciiname":"Mobarakeh",
    "gn:country_code":"IR",
    "gn:dem":1538,
    "gn:feature_class":"P",
    "gn:feature_code":"PPL",
    "gn:name":"Mob\u0101rakeh",
    "gn:population":0,
    "gn:timezone":"Asia/Tehran",
    "iso:country":"IR",
    "name:fas_x_preferred":[
        "\u0645\u0628\u0627\u0631\u06a9\u0647"
    ],
    "name:fas_x_variant":[
        "Mob\u0101rakeh"
    ],
    "name:und_x_variant":[
        "Mobarakeh Pishkooh"
    ],
    "wof:name":"Mobarakeh",
    "wof:placetype":"locality"
},
  "geometry": {"coordinates":[52.5134,31.8418],"type":"Point"}
}