{
  "type": "Feature",
  "properties": {
    "gn:admin1_code":"4.0",
    "gn:asciiname":"`Ata Mohammad",
    "gn:country_code":"IR",
    "gn:dem":490,
    "gn:feature_class":"P",
    "gn:feature_code":"PPL",
    "gn:name":"\u2018A\u0163\u0101 Mo\u1e29ammad",
    "gn:population":0,
    "gn:timezone":"Asia/Tehran",
    "iso:country":"IR",
    "name:fas_x_preferred":[
        "\u0639\u0637\u0627 \u0645\u062d\u0645\u062f"
    ],
    "name:fas_x_variant":[
        "\u2018A\u0163\u0101 Mo\u1e29ammad"
    ],
    "wof:name":"`Ata Mohammad",
    "wof:placetype":"locality"
},
  "geometry": {"coordinates":[61.6705,30.9139],"type":"Point"}
}