{
  "type": "Feature",
  "properties": {
    "gn:admin1_code":"13",
    "gn:asciiname":"Yangijeh",
    "gn:country_code":"IR",
    "gn:dem":1286,
    "gn:feature_class":"P",
    "gn:feature_code":"PPL",
    "gn:name":"Yang\u012bjeh",
    "gn:population":0,
    "gn:timezone":"Asia/Tehran",
    "iso:country":"IR",
    "name:fas_x_preferred":[
        "Yang\u012bjeh"
    ],
    "wof:name":"Yangijeh",
    "wof:placetype":"locality"
},
  "geometry": {"coordinates":[47.45556,34.40333],"type":"Point"}
}