{
  "type": "Feature",
  "properties": {
    "gn:admin1_code":"40",
    "gn:asciiname":"Feyzabad-e Now",
    "gn:country_code":"IR",
    "gn:dem":1489,
    "gn:feature_class":"P",
    "gn:feature_code":"PPL",
    "gn:name":"Fey\u1e95\u0101b\u0101d-e Now",
    "gn:population":0,
    "gn:timezone":"Asia/Tehran",
    "iso:country":"IR",
    "name:ara_x_preferred":[
        "\u0641\u064a\u0636 \u0623\u0628\u0627\u062f \u0627\u0644\u062c\u062f\u064a\u062f\u0629"
    ],
    "name:fas_x_preferred":[
        "\u0641\u06cc\u0636 \u0622\u0628\u0627\u062f \u0639\u0644\u06cc\u0627"
    ],
    "name:fas_x_variant":[
        "Fey\u1e95\u0101b\u0101d-e \u2018Oly\u0101",
        "Fey\u1e95\u0101b\u0101d-e Now",
        "\u0641\u064a\u0636 \u0622\u0628\u0627\u062f \u0646\u0648",
        "\u0641\u06cc\u0636\u200c\u0622\u0628\u0627\u062f \u0646\u0648"
    ],
    "name:por_x_preferred":[
        "Feyzabad-e Now"
    ],
    "name:urd_x_preferred":[
        "\u0641\u06cc\u0636\u200c\u0622\u0628\u0627\u062f \u0646\u0648"
    ],
    "wof:name":"Feyzabad-e Now",
    "wof:placetype":"locality"
},
  "geometry": {"coordinates":[53.3509,31.1567],"type":"Point"}
}