{
  "type": "Feature",
  "properties": {
    "gn:admin1_code":"32",
    "gn:asciiname":"Qabakh",
    "gn:country_code":"IR",
    "gn:dem":1160,
    "gn:feature_class":"P",
    "gn:feature_code":"PPL",
    "gn:name":"Qab\u0101kh",
    "gn:population":0,
    "gn:timezone":"Asia/Tehran",
    "iso:country":"IR",
    "name:ceb_x_preferred":[
        "Q\u0101b\u0101kh"
    ],
    "name:fas_x_preferred":[
        "Qab\u0101kh"
    ],
    "name:fas_x_variant":[
        "\u0642\u0627\u0628\u0627\u062e"
    ],
    "name:swe_x_preferred":[
        "Q\u0101b\u0101kh"
    ],
    "name:und_x_variant":[
        "Krepost\u2019 Kabakh",
        "Q\u0101b\u0101gh",
        "K\u016bb\u0101j"
    ],
    "wof:name":"Qabakh",
    "wof:placetype":"locality"
},
  "geometry": {"coordinates":[48.23788,37.58264000000001],"type":"Point"}
}