{
  "type": "Feature",
  "properties": {
    "gn:admin1_code":"1.0",
    "gn:asciiname":"Kalik",
    "gn:country_code":"IR",
    "gn:dem":2348,
    "gn:feature_class":"P",
    "gn:feature_code":"PPL",
    "gn:name":"K\u0101l\u012bk",
    "gn:population":0,
    "gn:timezone":"Asia/Tehran",
    "iso:country":"IR",
    "name:ara_x_preferred":[
        "\u0643\u0627\u0644\u064a\u0643"
    ],
    "name:deu_x_preferred":[
        "Kalik"
    ],
    "name:fas_x_preferred":[
        "K\u0101l\u012bk"
    ],
    "name:fas_x_variant":[
        "\u06a9\u0627\u0644\u06cc\u06a9"
    ],
    "name:nld_x_preferred":[
        "Kalik"
    ],
    "name:ukr_x_preferred":[
        "Kalik"
    ],
    "name:und_x_variant":[
        "\u06a9\u0627\u0644\u06cc\u06a9"
    ],
    "wof:name":"Kalik",
    "wof:placetype":"locality"
},
  "geometry": {"coordinates":[44.343,38.0077],"type":"Point"}
}