{
  "type": "Feature",
  "properties": {
    "gn:admin1_code":"1.0",
    "gn:asciiname":"Gavmishan",
    "gn:country_code":"IR",
    "gn:dem":1626,
    "gn:elevation":"0.0",
    "gn:feature_class":"P",
    "gn:feature_code":"PPL",
    "gn:name":"G\u0101vm\u012bsh\u0101n",
    "gn:population":0,
    "gn:timezone":"Asia/Tehran",
    "iso:country":"IR",
    "name:fas_x_preferred":[
        "\u06af\u0627\u0648\u0645\u06cc\u0634\u0627\u0646"
    ],
    "name:fas_x_variant":[
        "G\u0101vm\u012bsh\u0101n"
    ],
    "wof:name":"Gavmishan",
    "wof:placetype":"locality"
},
  "geometry": {"coordinates":[45.7446,36.3928],"type":"Point"}
}