{
  "type": "Feature",
  "properties": {
    "gn:admin1_code":"38",
    "gn:asciiname":"Kakuhestan",
    "gn:country_code":"IR",
    "gn:dem":1443,
    "gn:feature_class":"P",
    "gn:feature_code":"PPL",
    "gn:name":"K\u0101k\u016bhest\u0101n",
    "gn:population":0,
    "gn:timezone":"Asia/Tehran",
    "iso:country":"IR",
    "name:fas_x_preferred":[
        "\u0643\u064e\u0643\u064f\u0633\u062a\u064e\u0646"
    ],
    "name:fas_x_variant":[
        "K\u0101k\u016bhest\u0101n",
        "\u0643\u0627\u0643\u0648\u0647\u0633\u062a\u0627\u0646"
    ],
    "name:und_x_variant":[
        "Kakostan",
        "\u0643\u0627\u0643\u0648\u0647\u0633\u062a\u0627\u0646"
    ],
    "wof:name":"Kakuhestan",
    "wof:placetype":"locality"
},
  "geometry": {"coordinates":[49.97685,36.55898],"type":"Point"}
}