{
  "type": "Feature",
  "properties": {
    "gn:admin1_code":"29.0",
    "gn:asciiname":"Bab Kahkin",
    "gn:country_code":"IR",
    "gn:dem":2248,
    "gn:feature_class":"P",
    "gn:feature_code":"PPLF",
    "gn:name":"B\u0101b Kahk\u012bn",
    "gn:population":0,
    "gn:timezone":"Asia/Tehran",
    "iso:country":"IR",
    "name:fas_x_preferred":[
        "B\u0101b Kahk\u012bn"
    ],
    "name:fas_x_variant":[
        "\u0628\u0627\u0628 \u06a9\u0647\u06a9\u06cc\u0646"
    ],
    "wof:name":"Bab Kahkin",
    "wof:placetype":"locality"
},
  "geometry": {"coordinates":[56.44123,30.53235],"type":"Point"}
}