{
  "type": "Feature",
  "properties": {
    "gn:admin1_code":"8.0",
    "gn:asciiname":"Nasur Mahalleh",
    "gn:country_code":"IR",
    "gn:dem":-7,
    "gn:feature_class":"P",
    "gn:feature_code":"PPL",
    "gn:name":"Nas\u016br Ma\u1e29alleh",
    "gn:population":0,
    "gn:timezone":"Asia/Tehran",
    "iso:country":"IR",
    "name:fas_x_preferred":[
        "Man\u015f\u016br Ma\u1e29alleh"
    ],
    "name:fas_x_variant":[
        "\u0646\u0633\u0648\u0631 \u0645\u062d\u0644\u0647",
        "\u0646\u0635\u0648\u0631 \u0645\u062d\u0644\u0647",
        "\u0646\u0635\u0648\u0631\u0645\u062d\u0644\u0647"
    ],
    "name:msa_x_preferred":[
        "Nasur Mahalleh"
    ],
    "name:ukr_x_preferred":[
        "\u041d\u0430\u0441\u0443\u0440-\u041c\u0430\u0445\u0430\u043b\u0435"
    ],
    "name:und_x_variant":[
        "Nas\u016br Ma\u1e29alleh",
        "Na\u015f\u016br Ma\u1e29alleh"
    ],
    "wof:name":"Nasur Mahalleh",
    "wof:placetype":"locality"
},
  "geometry": {"coordinates":[48.90721,37.86514],"type":"Point"}
}