{
  "type": "Feature",
  "properties": {
    "gn:admin1_code":"41",
    "gn:asciiname":"Chah-e Azu",
    "gn:country_code":"IR",
    "gn:dem":1861,
    "gn:feature_class":"P",
    "gn:feature_code":"PPL",
    "gn:name":"Ch\u0101h-e Az\u016b",
    "gn:population":0,
    "gn:timezone":"Asia/Tehran",
    "iso:country":"IR",
    "name:fas_x_preferred":[
        "Yek Ch\u0101h"
    ],
    "name:fas_x_variant":[
        "\u0686\u0627\u0647 \u0627\u0632\u0648",
        "\u06cc\u06a9 \u0686\u0627\u0647"
    ],
    "name:und_x_variant":[
        "Yak Ch\u0101h",
        "Ch\u0101h-e Az\u016b"
    ],
    "wof:name":"Chah-e Azu",
    "wof:placetype":"locality"
},
  "geometry": {"coordinates":[59.74841,31.83103],"type":"Point"}
}