{
  "type": "Feature",
  "properties": {
    "gn:admin1_code":"7",
    "gn:asciiname":"Qalat-e Kord Shir",
    "gn:country_code":"IR",
    "gn:dem":626,
    "gn:feature_class":"P",
    "gn:feature_code":"PPL",
    "gn:name":"Qal\u0101t-e Kord Sh\u012br",
    "gn:population":0,
    "gn:timezone":"Asia/Tehran",
    "iso:country":"IR",
    "name:fas_x_preferred":[
        "\u06a9\u0631\u062f\u0647 \u0634\u06cc\u062e"
    ],
    "name:fas_x_variant":[
        "\u0642\u0644\u0627\u062a \u06a9\u0631\u062f \u0634\u06cc\u0631"
    ],
    "name:msa_x_preferred":[
        "Kordeh Sheykh"
    ],
    "name:und_x_variant":[
        "Kordeh Sheykh",
        "Qal\u0101t-e Kord Sh\u012br"
    ],
    "wof:name":"Qalat-e Kord Shir",
    "wof:placetype":"locality"
},
  "geometry": {"coordinates":[53.817,27.5182],"type":"Point"}
}