{
  "type": "Feature",
  "properties": {
    "gn:admin1_code":"5",
    "gn:asciiname":"Ab Chendar",
    "gn:country_code":"IR",
    "gn:dem":1952,
    "gn:feature_class":"P",
    "gn:feature_code":"PPL",
    "gn:name":"\u0100b Chend\u0101r",
    "gn:population":0,
    "gn:timezone":"Asia/Tehran",
    "iso:country":"IR",
    "name:fas_x_preferred":[
        "\u0100b Chend\u0101r"
    ],
    "name:fas_x_variant":[
        "\u0622\u0628 \u0686\u0646\u062f\u0627\u0631",
        "\u0622\u0628 \u0686\u0646\u062f\u0627\u0631\u0627\u0646 \u0633\u0641\u0644\u06cc \u06af\u0644\u0627\u0644",
        "\u0622\u0628\u200c\u0686\u0646\u062f\u0627\u0631"
    ],
    "name:und_x_variant":[
        "\u0100b Chend\u0101r\u0101n",
        "\u0100b Chend\u0101r-e Gel\u0101l",
        "\u0100b Chend\u0101r\u0101n-e Sofl\u00e1 Gel\u0101l"
    ],
    "wof:name":"Ab Chendar",
    "wof:placetype":"locality"
},
  "geometry": {"coordinates":[50.7927,31.06982],"type":"Point"}
}