{
  "type": "Feature",
  "properties": {
    "gn:admin1_code":"42.0",
    "gn:asciiname":"Aqar-e `Olya",
    "gn:country_code":"IR",
    "gn:dem":1464,
    "gn:feature_class":"P",
    "gn:feature_code":"PPL",
    "gn:name":"Aqar-e \u2018Oly\u0101",
    "gn:population":0,
    "gn:timezone":"Asia/Tehran",
    "iso:country":"IR",
    "name:ara_x_preferred":[
        "\u0627\u0642\u0631 \u0639\u0644\u064a\u0627"
    ],
    "name:fas_x_preferred":[
        "\u0639\u0642\u0631 \u0628\u0627\u0644\u0627"
    ],
    "name:fas_x_variant":[
        "Aqar-e B\u0101l\u0101",
        "\u2018Aqar-e B\u0101l\u0101",
        "\u0627\u0642\u0631 \u0639\u0644\u06cc\u0627"
    ],
    "name:und_x_variant":[
        "Aqar \u2018Oly\u0101",
        "Aqar",
        "Aqar-e \u2018Oly\u0101",
        "\u0627\u0642\u0631 \u0639\u0644\u064a\u0627"
    ],
    "wof:name":"Aqar-e `Olya",
    "wof:placetype":"locality"
},
  "geometry": {"coordinates":[59.93374,35.78716],"type":"Point"}
}