{
  "type": "Feature",
  "properties": {
    "gn:admin1_code":"28",
    "gn:asciiname":"Hemmatabad",
    "gn:country_code":"IR",
    "gn:dem":1770,
    "gn:feature_class":"P",
    "gn:feature_code":"PPL",
    "gn:name":"Hemmat\u0101b\u0101d",
    "gn:population":0,
    "gn:timezone":"Asia/Tehran",
    "iso:country":"IR",
    "name:ara_x_preferred":[
        "\u0647\u0645\u062a \u0623\u0628\u0627\u062f"
    ],
    "name:fas_x_preferred":[
        "\u0647\u0645\u062a \u0622\u0628\u0627\u062f"
    ],
    "name:fas_x_variant":[
        "Hemmat\u0101b\u0101d",
        "\u0647\u0645\u062a\u200c\u0622\u0628\u0627\u062f"
    ],
    "wof:name":"Hemmatabad",
    "wof:placetype":"locality"
},
  "geometry": {"coordinates":[52.7822,33.2099],"type":"Point"}
}