{
  "type": "Feature",
  "properties": {
    "gn:admin1_code":"26",
    "gn:asciiname":"Shahrak-e Azad Shahr",
    "gn:country_code":"IR",
    "gn:dem":1248,
    "gn:feature_class":"P",
    "gn:feature_code":"PPL",
    "gn:name":"Shahrak-e \u0100z\u0101d Shahr",
    "gn:population":0,
    "gn:timezone":"Asia/Tehran",
    "iso:country":"IR",
    "name:fas_x_preferred":[
        "\u0634\u0647\u0631\u06a9 \u0622\u0632\u0627\u062f \u0634\u0647\u0631"
    ],
    "name:und_x_variant":[
        "Shahrak-e \u0100z\u0101d Shahr"
    ],
    "wof:name":"Shahrak-e Azad Shahr",
    "wof:placetype":"locality"
},
  "geometry": {"coordinates":[51.1889,35.7312],"type":"Point"}
}