{
  "type": "Feature",
  "properties": {
    "gn:admin1_code":"38.0",
    "gn:asciiname":"Shaluq Zamin",
    "gn:country_code":"IR",
    "gn:dem":595,
    "gn:feature_class":"P",
    "gn:feature_code":"PPL",
    "gn:name":"Sh\u0101l\u016bq Zam\u012bn",
    "gn:population":0,
    "gn:timezone":"Asia/Tehran",
    "iso:country":"IR",
    "name:fas_x_preferred":[
        "\u1e28asan Kh\u0101n\u012b"
    ],
    "name:fas_x_variant":[
        "\u062d\u0633\u0646 \u062e\u0627\u0646\u06cc",
        "\u0634\u0627\u0644\u0648\u0642 \u0632\u0645\u06cc\u0646",
        "\u0634\u0627\u0644\u0642 \u0632\u0645\u06cc\u0646"
    ],
    "name:und_x_variant":[
        "\u062d\u0633\u0646 \u062e\u0627\u0646\u06cc",
        "Sh\u0101l\u016bq Zam\u012bn",
        "Sh\u0101loq Zam\u012bn"
    ],
    "wof:name":"Shaluq Zamin",
    "wof:placetype":"locality"
},
  "geometry": {"coordinates":[49.51654,36.52259],"type":"Point"}
}