{
  "type": "Feature",
  "properties": {
    "gn:admin1_code":"23",
    "gn:asciiname":"Hendi",
    "gn:country_code":"IR",
    "gn:dem":1592,
    "gn:feature_class":"P",
    "gn:feature_code":"PPL",
    "gn:name":"Hend\u012b",
    "gn:population":0,
    "gn:timezone":"Asia/Tehran",
    "iso:country":"IR",
    "name:fas_x_preferred":[
        "\u0647\u0646\u062f\u06cc"
    ],
    "name:fas_x_variant":[
        "Hend\u012b"
    ],
    "name:und_x_variant":[
        "\u1e28oseyn\u0101b\u0101d-e Hend\u012b",
        "\u062d\u064f\u0633\u0650\u064a\u0646\u0627\u0628\u0627\u062f\u0650 \u0647\u0650\u0646\u062f\u06cc"
    ],
    "wof:name":"Hendi",
    "wof:placetype":"locality"
},
  "geometry": {"coordinates":[48.2382,33.8613],"type":"Point"}
}