{
  "type": "Feature",
  "properties": {
    "gn:admin1_code":"32",
    "gn:asciiname":"Aq Tappeh",
    "gn:country_code":"IR",
    "gn:dem":1177,
    "gn:feature_class":"P",
    "gn:feature_code":"PPL",
    "gn:name":"\u0100q Tappeh",
    "gn:population":0,
    "gn:timezone":"Asia/Tehran",
    "iso:country":"IR",
    "name:ceb_x_preferred":[
        "Aq Tappeh"
    ],
    "name:fas_x_preferred":[
        "\u0622\u0642 \u062a\u067e\u0647"
    ],
    "name:fas_x_variant":[
        "\u0100q Tappeh"
    ],
    "name:swe_x_preferred":[
        "Aq Tappeh"
    ],
    "wof:name":"Aq Tappeh",
    "wof:placetype":"locality"
},
  "geometry": {"coordinates":[47.7371,38.9113],"type":"Point"}
}