{
  "type": "Feature",
  "properties": {
    "gn:admin1_code":"15",
    "gn:asciiname":"Alazangi",
    "gn:country_code":"IR",
    "gn:dem":597,
    "gn:feature_class":"P",
    "gn:feature_code":"PPL",
    "gn:name":"Al\u0101zang\u012b",
    "gn:population":0,
    "gn:timezone":"Asia/Tehran",
    "iso:country":"IR",
    "name:fas_x_preferred":[
        "Al\u0101zang\u012b"
    ],
    "wof:name":"Alazangi",
    "wof:placetype":"locality"
},
  "geometry": {"coordinates":[49.51861,32.1025],"type":"Point"}
}