{
  "type": "Feature",
  "properties": {
    "gn:admin1_code":"15",
    "gn:asciiname":"Bonvar-e Hoseyn",
    "gn:country_code":"IR",
    "gn:dem":104,
    "gn:feature_class":"P",
    "gn:feature_code":"PPL",
    "gn:name":"Bonv\u0101r-e \u1e28oseyn",
    "gn:population":0,
    "gn:timezone":"Asia/Tehran",
    "iso:country":"IR",
    "name:ceb_x_preferred":[
        "Bonv\u0101r \u1e28oseyn"
    ],
    "name:fas_x_preferred":[
        "\u0628\u0646\u0648\u0627\u0631 \u062d\u0633\u06cc\u0646"
    ],
    "name:fas_x_variant":[
        "Benv\u0101r-e \u1e28oseyn",
        "Bonv\u0101r \u1e28oseyn",
        "\u0628\u0646\u0648\u0627\u0631\u062d\u0633\u06cc\u0646"
    ],
    "name:pol_x_preferred":[
        "Bonwar Hosejn"
    ],
    "name:swe_x_preferred":[
        "Bonv\u0101r \u1e28oseyn"
    ],
    "name:und_x_variant":[
        "Bunwar Buzurg",
        "Hoseyn Bozorg",
        "Bownvar-e Bozorg",
        "Bonv\u0101r-e \u1e28oseyn"
    ],
    "wof:name":"Bonvar-e Hoseyn",
    "wof:placetype":"locality"
},
  "geometry": {"coordinates":[48.31254000000001,32.35949],"type":"Point"}
}