{
  "type": "Feature",
  "properties": {
    "gn:admin1_code":"43",
    "gn:asciiname":"Sisab",
    "gn:country_code":"IR",
    "gn:dem":981,
    "gn:feature_class":"P",
    "gn:feature_code":"PPL",
    "gn:name":"S\u012bs\u0101b",
    "gn:population":0,
    "gn:timezone":"Asia/Tehran",
    "iso:country":"IR",
    "name:ara_x_preferred":[
        "\u0633\u064a\u0633\u0627\u0628"
    ],
    "name:ceb_x_preferred":[
        "S\u012bs\u0101b"
    ],
    "name:fas_x_preferred":[
        "S\u012bs\u0101b"
    ],
    "name:fas_x_variant":[
        "\u0633\u06cc\u0633\u0627\u0628"
    ],
    "name:swe_x_preferred":[
        "S\u012bs\u0101b"
    ],
    "wof:name":"Sisab",
    "wof:placetype":"locality"
},
  "geometry": {"coordinates":[57.6567,37.45572],"type":"Point"}
}