{
  "type": "Feature",
  "properties": {
    "gn:admin1_code":"8.0",
    "gn:asciiname":"Randeh",
    "gn:country_code":"IR",
    "gn:dem":2012,
    "gn:feature_class":"P",
    "gn:feature_code":"PPL",
    "gn:name":"Randeh",
    "gn:population":0,
    "gn:timezone":"Asia/Tehran",
    "iso:country":"IR",
    "name:fas_x_preferred":[
        "\u0631\u0646\u062f\u0647"
    ],
    "wof:name":"Randeh",
    "wof:placetype":"locality"
},
  "geometry": {"coordinates":[48.69861,37.57745],"type":"Point"}
}