{
  "type": "Feature",
  "properties": {
    "gn:admin1_code":"40",
    "gn:asciiname":"Feyzabad",
    "gn:country_code":"IR",
    "gn:dem":1488,
    "gn:feature_class":"P",
    "gn:feature_code":"PPL",
    "gn:name":"Fey\u1e95\u0101b\u0101d",
    "gn:population":0,
    "gn:timezone":"Asia/Tehran",
    "iso:country":"IR",
    "name:ceb_x_preferred":[
        "Fey\u1e95\u0101b\u0101d"
    ],
    "name:fas_x_preferred":[
        "\u0641\u064a\u0636\u0627\u0628\u0627\u062f \u0643\u0647\u0646\u0647"
    ],
    "name:fas_x_variant":[
        "\u0641\u0650\u064a\u0632\u0627\u0628\u0627\u062f\u0650 \u0643\u064f\u0647\u0646\u0650\u0647",
        "\u0641\u0650\u064a\u0632 \u0622\u0628\u0627\u062f",
        "\u0641\u06cc\u0636 \u0622\u0628\u0627\u062f \u0633\u0641\u0644\u06cc",
        "Fey\u1e95\u0101b\u0101d-e Kohneh",
        "Fey\u1e95\u0101b\u0101d-e Sofl\u00e1",
        "Fey\u1e95\u0101b\u0101d",
        "\u0641\u06cc\u0636 \u0622\u0628\u0627\u062f",
        "\u0641\u06cc\u0636\u200c\u0622\u0628\u0627\u062f \u06a9\u0647\u0646\u0647"
    ],
    "name:por_x_preferred":[
        "Feyzabad-e Kohneh"
    ],
    "name:swe_x_preferred":[
        "Fey\u1e95\u0101b\u0101d"
    ],
    "name:und_x_variant":[
        "Feyz\u0101b\u0101d",
        "Feyz\u0101b\u0101d-e Kohneh",
        "Faiz\u0101b\u0101d"
    ],
    "name:urd_x_preferred":[
        "\u0641\u06cc\u0636\u200c\u0622\u0628\u0627\u062f \u06a9\u06c1\u0646\u06c1"
    ],
    "wof:name":"Feyzabad",
    "wof:placetype":"locality"
},
  "geometry": {"coordinates":[53.3627,31.1746],"type":"Point"}
}