{
  "type": "Feature",
  "properties": {
    "gn:admin1_code":"4",
    "gn:asciiname":"Kashilgi",
    "gn:country_code":"IR",
    "gn:dem":1437,
    "gn:feature_class":"P",
    "gn:feature_code":"PPL",
    "gn:name":"K\u0101sh\u012blg\u012b",
    "gn:population":0,
    "gn:timezone":"Asia/Tehran",
    "iso:country":"IR",
    "name:fas_x_preferred":[
        "\u06a9\u0627\u0634\u06cc\u0644\u06af\u06cc"
    ],
    "name:fas_x_variant":[
        "K\u0101sh\u012blg\u012b"
    ],
    "wof:name":"Kashilgi",
    "wof:placetype":"locality"
},
  "geometry": {"coordinates":[60.39546,29.04228],"type":"Point"}
}