{
  "type": "Feature",
  "properties": {
    "gn:admin1_code":"32",
    "gn:asciiname":"Seyyed Kandi",
    "gn:country_code":"IR",
    "gn:dem":539,
    "gn:feature_class":"P",
    "gn:feature_code":"PPL",
    "gn:name":"Seyyed Kand\u012b",
    "gn:population":0,
    "gn:timezone":"Asia/Tehran",
    "iso:country":"IR",
    "name:fas_x_preferred":[
        "\u0633\u064a\u062f \u0643\u0646\u062f\u06cc"
    ],
    "name:fas_x_variant":[
        "Seyyed Kand\u012b"
    ],
    "wof:name":"Seyyed Kandi",
    "wof:placetype":"locality"
},
  "geometry": {"coordinates":[48.1404,39.1034],"type":"Point"}
}