{
  "type": "Feature",
  "properties": {
    "gn:admin1_code":"5.0",
    "gn:asciiname":"Deh-e Espid",
    "gn:country_code":"IR",
    "gn:dem":1471,
    "gn:feature_class":"P",
    "gn:feature_code":"PPL",
    "gn:name":"Deh-e Esp\u012bd",
    "gn:population":0,
    "gn:timezone":"Asia/Tehran",
    "iso:country":"IR",
    "name:fas_x_preferred":[
        "Deh-e Esp\u012bd"
    ],
    "name:fas_x_variant":[
        "\u062f\u0647 \u0627\u0633\u067e\u06cc\u062f",
        "Tal Sep\u012bd",
        "\u062a\u0644 \u0633\u067e\u06cc\u062f"
    ],
    "wof:name":"Deh-e Espid",
    "wof:placetype":"locality"
},
  "geometry": {"coordinates":[50.41777,31.2201],"type":"Point"}
}