{
  "type": "Feature",
  "properties": {
    "gn:admin1_code":"1",
    "gn:asciiname":"Karikan",
    "gn:country_code":"IR",
    "gn:dem":2300,
    "gn:feature_class":"P",
    "gn:feature_code":"PPL",
    "gn:name":"Kar\u012bk\u0101n",
    "gn:population":0,
    "gn:timezone":"Asia/Tehran",
    "iso:country":"IR",
    "name:aze_x_preferred":[
        "Karikan"
    ],
    "name:ceb_x_preferred":[
        "Kar\u012bk\u0101n"
    ],
    "name:fas_x_preferred":[
        "\u06a9\u0631\u06cc \u06a9\u0627\u0646"
    ],
    "name:fas_x_variant":[
        "\u06af\u064e\u0631\u064a\u0643\u0627\u0646",
        "Gar\u012bk\u0101n",
        "Kar\u012bk\u0101n",
        "\u06a9\u0631\u06cc\u06a9\u0627\u0646"
    ],
    "name:msa_x_preferred":[
        "Karikan"
    ],
    "name:swe_x_preferred":[
        "Kar\u012bk\u0101n"
    ],
    "wof:name":"Karikan",
    "wof:placetype":"locality"
},
  "geometry": {"coordinates":[44.2898,37.9634],"type":"Point"}
}