{
  "type": "Feature",
  "properties": {
    "gn:admin1_code":"29",
    "gn:asciiname":"Chah-e Ziarat",
    "gn:country_code":"IR",
    "gn:dem":666,
    "gn:feature_class":"P",
    "gn:feature_code":"PPLF",
    "gn:name":"Ch\u0101h-e Z\u012b\u0101rat",
    "gn:population":0,
    "gn:timezone":"Asia/Tehran",
    "iso:country":"IR",
    "name:ara_x_preferred":[
        "\u062a\u0634\u0627\u0629 \u0632\u064a\u0627\u0631\u062a"
    ],
    "name:ceb_x_preferred":[
        "Ch\u0101h-e Z\u012b\u0101rat"
    ],
    "name:fas_x_preferred":[
        "\u0686\u0627\u0647 \u0632\u06cc\u0627\u0631\u062a"
    ],
    "name:fas_x_variant":[
        "Ch\u0101h-e Z\u012b\u0101rat"
    ],
    "name:swe_x_preferred":[
        "Ch\u0101h-e Z\u012b\u0101rat"
    ],
    "name:und_x_variant":[
        "Ch\u0101h-e Del\u016bng\u0101h",
        "Ch\u0101h N\u0101renj P\u0101\u2019\u012bn",
        "Ch\u0101h N\u0101renj-e P\u0101\u2019\u012bn"
    ],
    "wof:name":"Chah-e Ziarat",
    "wof:placetype":"locality"
},
  "geometry": {"coordinates":[57.33552,28.20239],"type":"Point"}
}