{
  "type": "Feature",
  "properties": {
    "gn:admin1_code":"16.0",
    "gn:asciiname":"Kupich-e `Olya",
    "gn:country_code":"IR",
    "gn:dem":1521,
    "gn:feature_class":"P",
    "gn:feature_code":"PPL",
    "gn:name":"K\u016bp\u012bch-e \u2018Oly\u0101",
    "gn:population":0,
    "gn:timezone":"Asia/Tehran",
    "iso:country":"IR",
    "name:fas_x_preferred":[
        "\u06a9\u0648\u067e\u06cc\u0686 \u0639\u0644\u06cc\u0627"
    ],
    "name:fas_x_variant":[
        "K\u016bp\u012bch-e \u2018Oly\u0101"
    ],
    "wof:name":"Kupich-e `Olya",
    "wof:placetype":"locality"
},
  "geometry": {"coordinates":[45.8596,36.0125],"type":"Point"}
}