{
  "type": "Feature",
  "properties": {
    "gn:admin1_code":"33.0",
    "gn:asciiname":"Shah Bodaghlu",
    "gn:country_code":"IR",
    "gn:dem":442,
    "gn:feature_class":"P",
    "gn:feature_code":"PPL",
    "gn:name":"Sh\u0101h Bod\u0101ghl\u016b",
    "gn:population":0,
    "gn:timezone":"Asia/Tehran",
    "iso:country":"IR",
    "name:fas_x_preferred":[
        "\u0634\u0627\u0647 \u0628\u062f\u0627\u063a\u0644\u0648"
    ],
    "name:fas_x_variant":[
        "Sh\u0101h Bod\u0101ghl\u016b",
        "\u0634\u0627\u0647\u200c\u0628\u062f\u0627\u063a\u0644\u0648"
    ],
    "name:msa_x_preferred":[
        "Shah Bodaghlu"
    ],
    "wof:name":"Shah Bodaghlu",
    "wof:placetype":"locality"
},
  "geometry": {"coordinates":[47.1569,39.1736],"type":"Point"}
}