{
  "type": "Feature",
  "properties": {
    "gn:admin1_code":"29.0",
    "gn:asciiname":"`Arababad",
    "gn:country_code":"IR",
    "gn:dem":2498,
    "gn:feature_class":"P",
    "gn:feature_code":"PPL",
    "gn:name":"\u2018Arab\u0101b\u0101d",
    "gn:population":0,
    "gn:timezone":"Asia/Tehran",
    "iso:country":"IR",
    "name:fas_x_preferred":[
        "\u0639\u0631\u0628 \u0622\u0628\u0627\u062f"
    ],
    "name:fas_x_variant":[
        "\u2018Arab\u0101b\u0101d"
    ],
    "wof:name":"`Arababad",
    "wof:placetype":"locality"
},
  "geometry": {"coordinates":[57.5049,29.9213],"type":"Point"}
}