{
  "type": "Feature",
  "properties": {
    "gn:admin1_code":"28.0",
    "gn:asciiname":"Heydarabad",
    "gn:country_code":"IR",
    "gn:dem":2360,
    "gn:feature_class":"P",
    "gn:feature_code":"PPL",
    "gn:name":"\u1e28eydar\u0101b\u0101d",
    "gn:population":0,
    "gn:timezone":"Asia/Tehran",
    "iso:country":"IR",
    "name:fas_x_preferred":[
        "\u1e28eydar\u0101b\u0101d"
    ],
    "name:fas_x_variant":[
        "\u062d\u06cc\u062f\u0631 \u0622\u0628\u0627\u062f",
        "\u062d\u06cc\u062f\u0631\u0622\u0628\u0627\u062f"
    ],
    "name:und_x_variant":[
        "\u062d\u06cc\u062f\u0631 \u0622\u0628\u0627\u062f"
    ],
    "wof:name":"Heydarabad",
    "wof:placetype":"locality"
},
  "geometry": {"coordinates":[51.57146,31.64153],"type":"Point"}
}