{
  "type": "Feature",
  "properties": {
    "gn:admin1_code":"5",
    "gn:asciiname":"Pa Gachi",
    "gn:country_code":"IR",
    "gn:dem":537,
    "gn:feature_class":"P",
    "gn:feature_code":"PPL",
    "gn:name":"P\u0101 Gach\u012b",
    "gn:population":0,
    "gn:timezone":"Asia/Tehran",
    "iso:country":"IR",
    "name:fas_x_preferred":[
        "\u067e\u0627 \u06af\u0686\u06cc"
    ],
    "name:fas_x_variant":[
        "P\u0101 Gach",
        "\u2018Asgar\u012b",
        "\u0639\u0633\u06af\u0631\u06cc",
        "P\u0101 Gach\u012b",
        "\u067e\u0627 \u06af\u0686 \u06af\u0644 \u062c\u0645\u0634\u06cc\u062f"
    ],
    "name:und_x_variant":[
        "P\u0101 Gach-e Gol Jamsh\u012bd"
    ],
    "wof:name":"Pa Gachi",
    "wof:placetype":"locality"
},
  "geometry": {"coordinates":[50.1495,30.8708],"type":"Point"}
}