{
  "type": "Feature",
  "properties": {
    "gn:admin1_code":"16",
    "gn:asciiname":"Tudar-e Ruteh",
    "gn:country_code":"IR",
    "gn:dem":1911,
    "gn:feature_class":"P",
    "gn:feature_code":"PPL",
    "gn:name":"T\u016bd\u0101r-e R\u016bteh",
    "gn:population":0,
    "gn:timezone":"Asia/Tehran",
    "iso:country":"IR",
    "name:ceb_x_preferred":[
        "T\u016bd\u0101r-e R\u016bteh"
    ],
    "name:ckb_x_preferred":[
        "\u062a\u0648\u0627\u0631\u06d5 \u0695\u0648\u0648\u062a\u06d5"
    ],
    "name:fas_x_preferred":[
        "\u062a\u0648\u062f\u0627\u0631\u0650 \u0631\u0648\u0646\u0650\u0647"
    ],
    "name:fas_x_variant":[
        "\u062a\u0648\u0626\u06cc \u062f\u064e\u0631\u062a\u0627\u0646",
        "\u062a\u0648\u062f\u0627\u0631 \u0631\u0648\u062a\u0647",
        "T\u016bd\u0101r-e R\u016bteh",
        "\u062a\u0648\u062f\u0627\u0631\u0631\u0648\u062a\u0647"
    ],
    "name:kur_x_preferred":[
        "Tiware R\u00fbte"
    ],
    "name:swe_x_preferred":[
        "T\u016bd\u0101r-e R\u016bteh"
    ],
    "name:und_x_variant":[
        "T\u016bd\u0101r-e R\u016bneh",
        "T\u016btd\u0101r-e R\u016bteh",
        "T\u016b\u2019\u012b Dart\u0101n",
        "Tu yi Dar Ruten"
    ],
    "wof:name":"Tudar-e Ruteh",
    "wof:placetype":"locality"
},
  "geometry": {"coordinates":[46.7939,35.4157],"type":"Point"}
}