{
  "type": "Feature",
  "properties": {
    "gn:admin1_code":"15.0",
    "gn:asciiname":"Chinibeh-ye Do",
    "gn:country_code":"IR",
    "gn:dem":26,
    "gn:feature_class":"P",
    "gn:feature_code":"PPL",
    "gn:name":"Ch\u012bn\u012bbeh-ye Do",
    "gn:population":0,
    "gn:timezone":"Asia/Tehran",
    "iso:country":"IR",
    "name:ceb_x_preferred":[
        "Chan\u012bbeh-ye Yek"
    ],
    "name:fas_x_preferred":[
        "\u0686\u0646\u06cc\u0628\u0647 \u06cc\u06a9"
    ],
    "name:fas_x_variant":[
        "Chan\u012bbeh-ye Yek",
        "\u0686\u06cc\u0646\u06cc\u0628\u0647 \u062f\u0648",
        "\u0686\u0646\u06cc\u0628\u0647 \u062f\u0648"
    ],
    "name:swe_x_preferred":[
        "Chan\u012bbeh-ye Yek"
    ],
    "name:und_x_variant":[
        "Ch\u012bn\u012bbeh-ye Do",
        "Chan\u012bbeh-ye Do"
    ],
    "wof:name":"Chinibeh-ye Do",
    "wof:placetype":"locality"
},
  "geometry": {"coordinates":[48.8323,31.6613],"type":"Point"}
}