{
  "type": "Feature",
  "properties": {
    "gn:admin1_code":"5.0",
    "gn:asciiname":"Darreh Baki",
    "gn:country_code":"IR",
    "gn:dem":753,
    "gn:feature_class":"P",
    "gn:feature_code":"PPL",
    "gn:name":"Darreh Bak\u012b",
    "gn:population":0,
    "gn:timezone":"Asia/Tehran",
    "iso:country":"IR",
    "name:fas_x_preferred":[
        "Darreh Bak\u012b"
    ],
    "name:fas_x_variant":[
        "\u062f\u0631\u0651\u0647 \u0628\u06a9\u06cc"
    ],
    "wof:name":"Darreh Baki",
    "wof:placetype":"locality"
},
  "geometry": {"coordinates":[50.51933,30.741],"type":"Point"}
}