{
  "type": "Feature",
  "properties": {
    "gn:admin1_code":"13",
    "gn:asciiname":"Mian Rah-e Vizhnan",
    "gn:country_code":"IR",
    "gn:dem":913,
    "gn:feature_class":"P",
    "gn:feature_code":"PPL",
    "gn:name":"M\u012b\u0101n R\u0101h-e V\u012bzhn\u0101n",
    "gn:population":0,
    "gn:timezone":"Asia/Tehran",
    "iso:country":"IR",
    "name:fas_x_preferred":[
        "\u0645\u06cc\u0627\u0646 \u0631\u0627\u0647 \u0648\u06cc\u0698\u0646\u0627\u0646"
    ],
    "name:fas_x_variant":[
        "M\u012b\u0101n R\u0101h-e V\u012bzhn\u0101n",
        "M\u012b\u0101n R\u0101h-e V\u012bzhehn\u0101n"
    ],
    "wof:name":"Mian Rah-e Vizhnan",
    "wof:placetype":"locality"
},
  "geometry": {"coordinates":[45.8819,34.0975],"type":"Point"}
}