{
  "type": "Feature",
  "properties": {
    "gn:admin1_code":"33",
    "gn:asciiname":"Khordeh Bolagh",
    "gn:country_code":"IR",
    "gn:dem":1804,
    "gn:feature_class":"P",
    "gn:feature_code":"PPL",
    "gn:name":"Khordeh Bol\u0101gh",
    "gn:population":0,
    "gn:timezone":"Asia/Tehran",
    "iso:country":"IR",
    "name:ceb_x_preferred":[
        "Khordeh Bol\u0101gh"
    ],
    "name:fas_x_preferred":[
        "\u062e\u0631\u062f\u0647 \u0628\u0644\u0627\u063a"
    ],
    "name:fas_x_variant":[
        "Khvordeh Bol\u0101gh",
        "Khordeh Bol\u0101gh",
        "\u062e\u0648\u0631\u062f\u0647\u200c\u0628\u0644\u0627\u063a"
    ],
    "name:msa_x_preferred":[
        "Khvordeh Bolagh"
    ],
    "name:swe_x_preferred":[
        "Khordeh Bol\u0101gh"
    ],
    "name:und_x_variant":[
        "Hardabul\u0101q",
        "Khordeh B\u0101l\u0101",
        "Kharda-Bulakh"
    ],
    "wof:name":"Khordeh Bolagh",
    "wof:placetype":"locality"
},
  "geometry": {"coordinates":[48.0538,37.42745],"type":"Point"}
}