{
  "type": "Feature",
  "properties": {
    "gn:admin1_code":"15",
    "gn:asciiname":"Abu Shakar",
    "gn:country_code":"IR",
    "gn:dem":1,
    "gn:feature_class":"P",
    "gn:feature_code":"PPL",
    "gn:name":"Ab\u016b Shakar",
    "gn:population":0,
    "gn:timezone":"Asia/Tehran",
    "iso:country":"IR",
    "name:fas_x_preferred":[
        "Ab\u016b Shakar"
    ],
    "wof:name":"Abu Shakar",
    "wof:placetype":"locality"
},
  "geometry": {"coordinates":[48.41667,30.13333],"type":"Point"}
}