{
  "type": "Feature",
  "properties": {
    "gn:admin1_code":"15",
    "gn:asciiname":"Abu Shakar",
    "gn:country_code":"IR",
    "gn:dem":1,
    "gn:feature_class":"P",
    "gn:feature_code":"PPL",
    "gn:name":"Ab\u016b Shakar",
    "gn:population":0,
    "gn:timezone":"Asia/Tehran",
    "iso:country":"IR",
    "name:ara_x_preferred":[
        "\u0623\u0628\u0648 \u0634\u0643\u0631"
    ],
    "name:azb_x_preferred":[
        "\u0627\u0628\u0648\u0634\u06a9\u0631"
    ],
    "name:ceb_x_preferred":[
        "Ab\u016b Shakar"
    ],
    "name:fas_x_preferred":[
        "Ab\u016b Shakar"
    ],
    "name:fas_x_variant":[
        "\u0627\u0628\u0648\u0634\u06a9\u0631"
    ],
    "name:por_x_preferred":[
        "Abu Shakar"
    ],
    "name:swe_x_preferred":[
        "Ab\u016b Shakar"
    ],
    "wof:name":"Abu Shakar",
    "wof:placetype":"locality"
},
  "geometry": {"coordinates":[48.41667,30.13333],"type":"Point"}
}