{
  "type": "Feature",
  "properties": {
    "gn:admin1_code":"7",
    "gn:asciiname":"Dastjerd",
    "gn:country_code":"IR",
    "gn:dem":1572,
    "gn:feature_class":"P",
    "gn:feature_code":"PPL",
    "gn:name":"Dastjerd",
    "gn:population":0,
    "gn:timezone":"Asia/Tehran",
    "iso:country":"IR",
    "name:fas_x_preferred":[
        "\u062f\u0633\u062a\u062c\u0631\u062f"
    ],
    "wof:name":"Dastjerd",
    "wof:placetype":"locality"
},
  "geometry": {"coordinates":[53.923,29.2723],"type":"Point"}
}