{
  "type": "Feature",
  "properties": {
    "gn:admin1_code":"23",
    "gn:asciiname":"Deh-e Sheykhan",
    "gn:country_code":"IR",
    "gn:dem":1669,
    "gn:feature_class":"P",
    "gn:feature_code":"PPL",
    "gn:name":"Deh-e Sheykh\u0101n",
    "gn:population":0,
    "gn:timezone":"Asia/Tehran",
    "iso:country":"IR",
    "name:ara_x_preferred":[
        "\u062f\u0647 \u0634\u064a\u062e\u0627\u0646"
    ],
    "name:ceb_x_preferred":[
        "Deh-e Sheykh\u0101n"
    ],
    "name:fas_x_preferred":[
        "\u062f\u0647 \u0634\u06cc\u062e\u0627\u0646"
    ],
    "name:fas_x_variant":[
        "Deh-e Sheykh\u0101n"
    ],
    "name:swe_x_preferred":[
        "Deh-e Sheykh\u0101n"
    ],
    "name:und_x_variant":[
        "Deh Shikan",
        "Deh-e Shekh\u0101t"
    ],
    "wof:name":"Deh-e Sheykhan",
    "wof:placetype":"locality"
},
  "geometry": {"coordinates":[48.8582,33.8448],"type":"Point"}
}