{
  "type": "Feature",
  "properties": {
    "gn:admin1_code":"33",
    "gn:asciiname":"Kalu",
    "gn:country_code":"IR",
    "gn:dem":1275,
    "gn:feature_class":"P",
    "gn:feature_code":"PPL",
    "gn:name":"Kal\u016b",
    "gn:population":0,
    "gn:timezone":"Asia/Tehran",
    "iso:country":"IR",
    "name:fas_x_preferred":[
        "\u06a9\u0644\u0648"
    ],
    "name:fas_x_variant":[
        "Kal\u016b"
    ],
    "name:msa_x_preferred":[
        "Kalu"
    ],
    "name:und_x_variant":[
        "Chalow",
        "Kaloo",
        "Chel\u016b",
        "Kalow",
        "Chelou",
        "Chelow",
        "Chilov",
        "Ch\u012blowv"
    ],
    "wof:name":"Kalu",
    "wof:placetype":"locality"
},
  "geometry": {"coordinates":[46.309,38.7011],"type":"Point"}
}