{
  "type": "Feature",
  "properties": {
    "gn:admin1_code":"11",
    "gn:asciiname":"Gerusia",
    "gn:country_code":"IR",
    "gn:dem":645,
    "gn:feature_class":"P",
    "gn:feature_code":"PPL",
    "gn:name":"Ger\u016bs\u012b\u0101",
    "gn:population":0,
    "gn:timezone":"Asia/Tehran",
    "iso:country":"IR",
    "name:fas_x_preferred":[
        "\u06af\u0631\u0648 \u0633\u064a\u0627\u0647"
    ],
    "name:fas_x_variant":[
        "\u06af\u0631\u0648\u0633\u064a\u0627",
        "Ger\u016b S\u012b\u0101h",
        "Ger\u016bs\u012b\u0101",
        "\u06af\u0631\u0648\u0633\u06cc\u0627\u0647"
    ],
    "name:msa_x_preferred":[
        "Geru Siah"
    ],
    "wof:name":"Gerusia",
    "wof:placetype":"locality"
},
  "geometry": {"coordinates":[57.2249,27.6298],"type":"Point"}
}