{
  "type": "Feature",
  "properties": {
    "gn:admin1_code":"15",
    "gn:asciiname":"Khamzeh-ye Sofla",
    "gn:country_code":"IR",
    "gn:dem":15,
    "gn:feature_class":"P",
    "gn:feature_code":"PPL",
    "gn:name":"Khamzeh-ye Sofl\u00e1",
    "gn:population":0,
    "gn:timezone":"Asia/Tehran",
    "iso:country":"IR",
    "name:azb_x_preferred":[
        "\u062e\u0645\u0632\u0647 \u0633\u0641\u0644\u06cc(\u0628\u0646\u062f\u0631\u0645\u0627\u0647\u0634\u0647\u0631)"
    ],
    "name:ceb_x_preferred":[
        "\u1e28amzeh-ye Sofl\u00e1"
    ],
    "name:fas_x_preferred":[
        "\u062d\u0645\u0632\u0647 \u0633\u0641\u0644\u06cc"
    ],
    "name:fas_x_variant":[
        "Khamzeh-ye P\u0101\u2019\u012bn",
        "\u1e28amzeh-ye Sofl\u00e1",
        "\u062e\u0645\u0632\u0647 \u0633\u0641\u0644\u06cc"
    ],
    "name:swe_x_preferred":[
        "\u1e28amzeh-ye Sofl\u00e1"
    ],
    "name:und_x_variant":[
        "Khamzeh-ye Sofl\u00e1"
    ],
    "wof:name":"Khamzeh-ye Sofla",
    "wof:placetype":"locality"
},
  "geometry": {"coordinates":[49.05662,30.71787],"type":"Point"}
}