{
  "type": "Feature",
  "properties": {
    "gn:admin1_code":"22",
    "gn:asciiname":"Bu ol Fath",
    "gn:country_code":"IR",
    "gn:dem":40,
    "gn:feature_class":"P",
    "gn:feature_code":"PPL",
    "gn:name":"B\u016b ol Fat\u1e29",
    "gn:population":0,
    "gn:timezone":"Asia/Tehran",
    "iso:country":"IR",
    "name:fas_x_preferred":[
        "\u0627\u064e\u0628\u0648 \u0627\u0644\u0641\u064e\u062a\u062d"
    ],
    "name:fas_x_variant":[
        "\u0628\u0648\u0644 \u0641\u064e\u062a\u0647",
        "\u0627\u064e\u0628\u064f\u0644\u0641\u064e\u062a\u062d",
        "\u0628\u0648\u0627\u0644\u0641\u062a\u062d",
        "Ab\u016b ol Fat\u1e29",
        "B\u016b ol Fat\u1e29"
    ],
    "name:und_x_variant":[
        "Boolfat-h",
        "Abolfat\u1e29",
        "B\u016bl Fath"
    ],
    "wof:name":"Bu ol Fath",
    "wof:placetype":"locality"
},
  "geometry": {"coordinates":[50.4197,29.8474],"type":"Point"}
}