{
  "type": "Feature",
  "properties": {
    "gn:admin1_code":"7",
    "gn:asciiname":"Qanat",
    "gn:country_code":"IR",
    "gn:dem":2264,
    "gn:feature_class":"P",
    "gn:feature_code":"PPL",
    "gn:name":"Qan\u0101t",
    "gn:population":0,
    "gn:timezone":"Asia/Tehran",
    "iso:country":"IR",
    "name:fas_x_preferred":[
        "Qan\u0101t"
    ],
    "name:fas_x_variant":[
        "\u0642\u0646\u0627\u062a"
    ],
    "name:und_x_variant":[
        "Qan\u0101",
        "\u0642\u0646\u0627\u062a"
    ],
    "wof:name":"Qanat",
    "wof:placetype":"locality"
},
  "geometry": {"coordinates":[51.91988,30.25323],"type":"Point"}
}