{
  "type": "Feature",
  "properties": {
    "gn:admin1_code":"7",
    "gn:asciiname":"Qanat",
    "gn:country_code":"IR",
    "gn:dem":2264,
    "gn:feature_class":"P",
    "gn:feature_code":"PPL",
    "gn:name":"Qan\u0101t",
    "gn:population":0,
    "gn:timezone":"Asia/Tehran",
    "iso:country":"IR",
    "name:als_x_preferred":[
        "Qanat"
    ],
    "name:ara_x_preferred":[
        "\u0642\u0646\u0627\u0629"
    ],
    "name:arg_x_preferred":[
        "Canyo"
    ],
    "name:aze_x_preferred":[
        "K\u0259hriz"
    ],
    "name:bul_x_preferred":[
        "\u0413\u0430\u043d\u0430\u0442"
    ],
    "name:cat_x_preferred":[
        "Qanat"
    ],
    "name:ces_x_preferred":[
        "Kan\u00e1t"
    ],
    "name:dan_x_preferred":[
        "Kareze"
    ],
    "name:deu_x_preferred":[
        "Qanat"
    ],
    "name:ell_x_preferred":[
        "\u039a\u03b1\u03bd\u03ac\u03c4"
    ],
    "name:epo_x_preferred":[
        "Kanato"
    ],
    "name:eus_x_preferred":[
        "Qanat"
    ],
    "name:fas_x_preferred":[
        "Qan\u0101t"
    ],
    "name:fas_x_variant":[
        "\u0642\u0646\u0627\u062a"
    ],
    "name:fra_x_preferred":[
        "Qanat"
    ],
    "name:heb_x_preferred":[
        "\u05e4\u05d5\u05d2\u05d0\u05e8\u05d4"
    ],
    "name:hin_x_preferred":[
        "\u0915\u093e\u0930\u0947\u091c\u093c"
    ],
    "name:hrv_x_preferred":[
        "Kanat"
    ],
    "name:hun_x_preferred":[
        "Qanat"
    ],
    "name:ita_x_preferred":[
        "Qanat"
    ],
    "name:jpn_x_preferred":[
        "\u30ab\u30ca\u30fc\u30c8"
    ],
    "name:kaz_x_preferred":[
        "\u041a\u04d9\u0440\u0456\u0437"
    ],
    "name:kir_x_preferred":[
        "\u041a\u044f\u0440\u0438\u0437"
    ],
    "name:kor_x_preferred":[
        "\uce74\ub098\ud2b8"
    ],
    "name:lit_x_preferred":[
        "Kiarizas"
    ],
    "name:msa_x_preferred":[
        "Qanat"
    ],
    "name:nld_x_preferred":[
        "Qanat"
    ],
    "name:nno_x_preferred":[
        "Qanat"
    ],
    "name:nor_x_preferred":[
        "Qanat"
    ],
    "name:pol_x_preferred":[
        "Kanat"
    ],
    "name:por_x_preferred":[
        "Qanat"
    ],
    "name:rus_x_preferred":[
        "\u041a\u044f\u0440\u0438\u0437"
    ],
    "name:slv_x_preferred":[
        "Kanat"
    ],
    "name:spa_x_preferred":[
        "Qanat"
    ],
    "name:srp_x_preferred":[
        "\u041a\u0430\u043d\u0430\u0442"
    ],
    "name:swe_x_preferred":[
        "Qanat"
    ],
    "name:tat_x_preferred":[
        "\u041a\u04d9\u04bb\u0440\u0438\u0437"
    ],
    "name:tur_x_preferred":[
        "Kehriz"
    ],
    "name:ukr_x_preferred":[
        "\u041a\u044f\u0440\u0438\u0437"
    ],
    "name:und_x_variant":[
        "Qan\u0101",
        "\u0642\u0646\u0627\u062a"
    ],
    "name:urd_x_preferred":[
        "\u06a9\u0627\u0631\u06cc\u0632"
    ],
    "name:zho_x_preferred":[
        "\u574e\u5152\u4e95"
    ],
    "wof:name":"Qanat",
    "wof:placetype":"locality"
},
  "geometry": {"coordinates":[51.91988,30.25323],"type":"Point"}
}