{
  "type": "Feature",
  "properties": {
    "gn:admin1_code":"15",
    "gn:asciiname":"Palam-e Zivar",
    "gn:country_code":"IR",
    "gn:dem":768,
    "gn:feature_class":"P",
    "gn:feature_code":"PPL",
    "gn:name":"Palam-e Z\u012bv\u0101r",
    "gn:population":0,
    "gn:timezone":"Asia/Tehran",
    "iso:country":"IR",
    "name:fas_x_preferred":[
        "Darv\u012bsh Sa\u2018\u012bd\u012b"
    ],
    "name:fas_x_variant":[
        "\u067e\u0644\u0645 \u0632\u06cc\u0648\u0627\u0631",
        "\u067e\u0644\u0627\u0645 \u0632\u06cc\u0648\u0627\u0631",
        "\u062f\u0631\u0648\u06cc\u0634 \u0633\u0639\u06cc\u062f\u06cc"
    ],
    "name:und_x_variant":[
        "Palam-e Z\u012bv\u0101r",
        "Pal\u0101m-e Z\u012bv\u0101r"
    ],
    "wof:name":"Palam-e Zivar",
    "wof:placetype":"locality"
},
  "geometry": {"coordinates":[49.90432,31.97829],"type":"Point"}
}