{
  "type": "Feature",
  "properties": {
    "gn:admin1_code":"4",
    "gn:asciiname":"Shatiab-e Jurashtar",
    "gn:country_code":"IR",
    "gn:dem":1240,
    "gn:feature_class":"P",
    "gn:feature_code":"PPL",
    "gn:name":"Shat\u012b\u0101b-e J\u016br\u0101shtar",
    "gn:population":0,
    "gn:timezone":"Asia/Tehran",
    "iso:country":"IR",
    "name:fas_x_preferred":[
        "\u0634\u062a\u06cc\u0627\u0628 \u062c\u0648\u0631\u0627\u0634\u062a\u0631"
    ],
    "name:fas_x_variant":[
        "Shat\u012b\u0101b-e J\u016br\u0101shtar"
    ],
    "wof:name":"Shatiab-e Jurashtar",
    "wof:placetype":"locality"
},
  "geometry": {"coordinates":[62.8255,26.84789],"type":"Point"}
}