{
  "type": "Feature",
  "properties": {
    "gn:admin1_code":"33",
    "gn:asciiname":"Nazemabad",
    "gn:country_code":"IR",
    "gn:dem":1369,
    "gn:feature_class":"P",
    "gn:feature_code":"PPL",
    "gn:name":"N\u0101z\u0327em\u0101b\u0101d",
    "gn:population":0,
    "gn:timezone":"Asia/Tehran",
    "iso:country":"IR",
    "name:fas_x_preferred":[
        "N\u0101z\u0327em\u0101b\u0101d"
    ],
    "name:fas_x_variant":[
        "\u0646\u0627\u0638\u0645 \u0622\u0628\u0627\u062f",
        "\u0635\u0642\u0644\u06cc"
    ],
    "name:und_x_variant":[
        "\u015eaql\u00e1"
    ],
    "wof:name":"Nazemabad",
    "wof:placetype":"locality"
},
  "geometry": {"coordinates":[47.28404000000001,38.45239],"type":"Point"}
}