{
  "type": "Feature",
  "properties": {
    "gn:admin1_code":"29.0",
    "gn:asciiname":"Mazra`eh-ye Hanshin",
    "gn:country_code":"IR",
    "gn:dem":2864,
    "gn:feature_class":"P",
    "gn:feature_code":"PPLF",
    "gn:name":"Mazra\u2018eh-ye Hansh\u012bn",
    "gn:population":0,
    "gn:timezone":"Asia/Tehran",
    "iso:country":"IR",
    "name:fas_x_preferred":[
        "Zam\u012bn-e \u1e28oseyn"
    ],
    "name:fas_x_variant":[
        "\u0632\u0645\u06cc\u0646 \u062d\u0633\u06cc\u0646",
        "\u0645\u0632\u0631\u0639\u0647 \u0647\u0646\u0634\u064a\u0646"
    ],
    "name:und_x_variant":[
        "\u0632\u0645\u06cc\u0646 \u062d\u0633\u06cc\u0646",
        "Mazra\u2018eh-ye Hansh\u012bn"
    ],
    "wof:name":"Mazra`eh-ye Hanshin",
    "wof:placetype":"locality"
},
  "geometry": {"coordinates":[57.22201,29.18214],"type":"Point"}
}