{
  "type": "Feature",
  "properties": {
    "gn:admin1_code":"26",
    "gn:asciiname":"Dowtuyeh-ye Sofla",
    "gn:country_code":"IR",
    "gn:dem":946,
    "gn:feature_class":"P",
    "gn:feature_code":"PPL",
    "gn:name":"Dowt\u016byeh-ye Sofl\u00e1",
    "gn:population":0,
    "gn:timezone":"Asia/Tehran",
    "iso:country":"IR",
    "name:fas_x_preferred":[
        "\u062f\u0648\u067e\u0648\u06cc\u0647 \u067e\u0627\u0626\u064a\u0646"
    ],
    "name:fas_x_variant":[
        "Dot\u016byeh-ye P\u0101\u2019\u012bn",
        "Dowp\u016byeh-ye P\u0101\u2019\u012bn",
        "\u062f\u0648\u062a\u0648\u06cc\u0647 \u0633\u0641\u0644\u06cc",
        "\u062f\u0648\u062a\u0648\u0647\u0647 \u0633\u0641\u0644\u06cc"
    ],
    "name:und_x_variant":[
        "D\u016btuyeh P\u0101\u012bn",
        "D\u016bt\u016byeh-ye Sofl\u00e1",
        "Do T\u016byeh",
        "Do T\u016byeh-ye P\u0101\u2019\u012bn",
        "Dowt\u016byeh-ye Sofl\u00e1"
    ],
    "wof:name":"Dowtuyeh-ye Sofla",
    "wof:placetype":"locality"
},
  "geometry": {"coordinates":[51.44052,35.42126],"type":"Point"}
}