{
  "type": "Feature",
  "properties": {
    "gn:admin1_code":"29",
    "gn:asciiname":"Fandoqa",
    "gn:country_code":"IR",
    "gn:dem":2143,
    "gn:feature_class":"P",
    "gn:feature_code":"PPL",
    "gn:name":"Fandoq\u0101",
    "gn:population":0,
    "gn:timezone":"Asia/Tehran",
    "iso:country":"IR",
    "name:fas_x_preferred":[
        "Fandoq\u0101"
    ],
    "wof:name":"Fandoqa",
    "wof:placetype":"locality"
},
  "geometry": {"coordinates":[57.69056,29.98167],"type":"Point"}
}