{
  "type": "Feature",
  "properties": {
    "gn:admin1_code":"25",
    "gn:asciiname":"Haqin",
    "gn:country_code":"IR",
    "gn:dem":1154,
    "gn:feature_class":"P",
    "gn:feature_code":"PPL",
    "gn:name":"H\u0101q\u012bn",
    "gn:population":0,
    "gn:timezone":"Asia/Tehran",
    "iso:country":"IR",
    "name:fas_x_preferred":[
        "\u0647\u0627\u0642\u064a\u0646"
    ],
    "name:fas_x_variant":[
        "H\u0101q\u012bn"
    ],
    "wof:name":"Haqin",
    "wof:placetype":"locality"
},
  "geometry": {"coordinates":[53.17028000000001,35.44944],"type":"Point"}
}