{
  "type": "Feature",
  "properties": {
    "gn:admin1_code":"16",
    "gn:asciiname":"Patlidar",
    "gn:country_code":"IR",
    "gn:dem":1830,
    "gn:feature_class":"P",
    "gn:feature_code":"PPL",
    "gn:name":"Patl\u012bdar",
    "gn:population":0,
    "gn:timezone":"Asia/Tehran",
    "iso:country":"IR",
    "name:fas_x_preferred":[
        "\u067e\u064e\u062a\u0644\u064a\u062f\u064e\u0631"
    ],
    "name:fas_x_variant":[
        "\u067e\u062a\u0644\u06cc\u062f\u0631"
    ],
    "name:und_x_variant":[
        "Patliy\u0101r",
        "Potl\u012bdar",
        "Patl\u012bdar"
    ],
    "wof:name":"Patlidar",
    "wof:placetype":"locality"
},
  "geometry": {"coordinates":[46.8556,35.1933],"type":"Point"}
}