{
  "type": "Feature",
  "properties": {
    "gn:admin1_code":"7",
    "gn:asciiname":"Khvajeh",
    "gn:country_code":"IR",
    "gn:dem":1735,
    "gn:feature_class":"P",
    "gn:feature_code":"PPL",
    "gn:name":"Khv\u0101jeh",
    "gn:population":0,
    "gn:timezone":"Asia/Tehran",
    "iso:country":"IR",
    "name:fas_x_preferred":[
        "Khv\u0101jeh Yah\u016bd"
    ],
    "name:fas_x_variant":[
        "Khv\u0101jeh",
        "\u062e\u0648\u0627\u062c\u0647",
        "\u062e\u0648\u0627\u062c\u0647 \u0627\u06cc"
    ],
    "name:und_x_variant":[
        "\u062e\u0648\u0627\u062c\u0647",
        "Khv\u0101jeh\u2019\u012b"
    ],
    "wof:name":"Khvajeh",
    "wof:placetype":"locality"
},
  "geometry": {"coordinates":[52.2919,30.22300000000001],"type":"Point"}
}