{
  "type": "Feature",
  "properties": {
    "gn:admin1_code":"1",
    "gn:asciiname":"Vishlaq-e Sofla",
    "gn:country_code":"IR",
    "gn:dem":1036,
    "gn:feature_class":"P",
    "gn:feature_code":"PPL",
    "gn:name":"V\u012bshlaq-e Sofl\u00e1",
    "gn:population":0,
    "gn:timezone":"Asia/Tehran",
    "iso:country":"IR",
    "name:fas_x_preferred":[
        "\u0648\u064a\u0634\u0644\u0642 \u0633\u0641\u0644\u0649"
    ],
    "name:fas_x_variant":[
        "V\u012bshlaq-e P\u0101\u2019\u012bn",
        "V\u012bshlaq-e Sofl\u00e1"
    ],
    "name:und_x_variant":[
        "Ashaga Veshlya",
        "Vishlagh Sofla",
        "V\u012bshlaq Sofl\u0101",
        "Vaslar \u0100sh\u0101ghi",
        "V\u012bshlaq P\u0101\u2019\u012bn"
    ],
    "wof:name":"Vishlaq-e Sofla",
    "wof:placetype":"locality"
},
  "geometry": {"coordinates":[45.06186,38.62268],"type":"Point"}
}