{
  "type": "Feature",
  "properties": {
    "gn:admin1_code":"8",
    "gn:asciiname":"Shir Kuh",
    "gn:country_code":"IR",
    "gn:dem":411,
    "gn:feature_class":"P",
    "gn:feature_code":"PPL",
    "gn:name":"Sh\u012br K\u016bh",
    "gn:population":0,
    "gn:timezone":"Asia/Tehran",
    "iso:country":"IR",
    "name:fas_x_preferred":[
        "Sh\u012br K\u016bh"
    ],
    "name:fas_x_variant":[
        "\u0634\u06cc\u0631 \u06a9\u0648\u0647",
        "\u0634\u06cc\u0631\u06a9\u0648\u0647"
    ],
    "name:msa_x_preferred":[
        "Shir Kuh"
    ],
    "name:ukr_x_preferred":[
        "\u0428\u0456\u0440-\u041a\u0443\u0445"
    ],
    "name:und_x_variant":[
        "Shirkukh",
        "Sh\u012br\u0101k\u016bh",
        "\u0634\u06cc\u0631 \u06a9\u0648\u0647"
    ],
    "wof:name":"Shir Kuh",
    "wof:placetype":"locality"
},
  "geometry": {"coordinates":[49.56404000000001,36.89001],"type":"Point"}
}