{
  "type": "Feature",
  "properties": {
    "gn:admin1_code":"0",
    "gn:asciiname":"Shahr-e Sekandar",
    "gn:country_code":"IR",
    "gn:dem":1513,
    "gn:feature_class":"P",
    "gn:feature_code":"PPL",
    "gn:name":"Shahr-e Sekandar",
    "gn:population":0,
    "gn:timezone":"Asia/Tehran",
    "iso:country":"IR",
    "name:fas_x_preferred":[
        "\u0634\u0647\u0631 \u0633\u06a9\u0646\u062f\u0631"
    ],
    "wof:name":"Shahr-e Sekandar",
    "wof:placetype":"locality"
},
  "geometry": {"coordinates":[57.7743,26.8502],"type":"Point"}
}