{
  "type": "Feature",
  "properties": {
    "gn:admin1_code":"44.0",
    "gn:asciiname":"Seyfabad-e Bozorg",
    "gn:country_code":"IR",
    "gn:dem":1332,
    "gn:feature_class":"P",
    "gn:feature_code":"PPL",
    "gn:name":"Seyf\u0101b\u0101d-e Bozorg",
    "gn:population":0,
    "gn:timezone":"Asia/Tehran",
    "iso:country":"IR",
    "name:fas_x_preferred":[
        "\u067e\u0644 \u06a9\u0631\u062f\u0627\u0646"
    ],
    "name:fas_x_variant":[
        "Pol-e Kord\u0101n",
        "\u0633\u06cc\u0641 \u0622\u0628\u0627\u062f \u0628\u0632\u0631\u06af"
    ],
    "name:und_x_variant":[
        "Seyf\u0101b\u0101d-e Bozorg"
    ],
    "wof:name":"Seyfabad-e Bozorg",
    "wof:placetype":"locality"
},
  "geometry": {"coordinates":[50.7726,35.9144],"type":"Point"}
}