{
  "type": "Feature",
  "properties": {
    "gn:admin1_code":"35.0",
    "gn:asciiname":"Vav Darreh-ye Bozorg",
    "gn:country_code":"IR",
    "gn:dem":895,
    "gn:feature_class":"P",
    "gn:feature_code":"PPL",
    "gn:name":"V\u0101v Darreh-ye Bozorg",
    "gn:population":0,
    "gn:timezone":"Asia/Tehran",
    "iso:country":"IR",
    "name:ceb_x_preferred":[
        "V\u0101v Darreh-ye Bozorg"
    ],
    "name:fas_x_preferred":[
        "\u0648\u0627\u0648 \u062f\u064e\u0631\u0650\u0651\u0647"
    ],
    "name:fas_x_variant":[
        "\u0648\u0627\u0648 \u062f\u064e\u0631\u0650\u0651\u0647 \u0628\u064f\u0632\u064f\u0631\u06af",
        "\u0648\u0627\u0648 \u062f\u0631\u0651\u0647 \u0628\u0632\u0631\u06af",
        "V\u0101v Darreh",
        "V\u0101v Darreh-ye Bozorg",
        "\u0648\u0627\u0648\u062f\u0631\u0647"
    ],
    "name:mzn_x_preferred":[
        "\u0648\u0627\u0648\u062f\u0631\u0647"
    ],
    "name:swe_x_preferred":[
        "V\u0101v Darreh-ye Bozorg"
    ],
    "name:und_x_variant":[
        "V\u0101v Darreh Bozorg"
    ],
    "wof:name":"Vav Darreh-ye Bozorg",
    "wof:placetype":"locality"
},
  "geometry": {"coordinates":[53.24443,36.14775],"type":"Point"}
}