{
  "type": "Feature",
  "properties": {
    "gn:admin1_code":"13.0",
    "gn:asciiname":"Baskeleh-ye Khan Mirza",
    "gn:country_code":"IR",
    "gn:dem":1436,
    "gn:feature_class":"P",
    "gn:feature_code":"PPL",
    "gn:name":"B\u0101skeleh-ye Kh\u0101n M\u012brz\u0101",
    "gn:population":0,
    "gn:timezone":"Asia/Tehran",
    "iso:country":"IR",
    "name:ara_x_preferred":[
        "\u0628\u0627\u0633\u0643\u0644\u0647\u200c\u062e\u0627\u0646\u200c\u0645\u064a\u0631\u0632\u0627"
    ],
    "name:fas_x_preferred":[
        "\u0628\u0627\u0633\u06a9\u0644\u0647 \u062e\u0627\u0646 \u0645\u06cc\u0631\u0632\u0627"
    ],
    "name:fas_x_variant":[
        "B\u0101skeleh-ye Kh\u0101n M\u012brz\u0101",
        "\u0628\u0627\u0633\u06a9\u0644\u0647\u200c\u062e\u0627\u0646\u200c\u0645\u06cc\u0631\u0632\u0627"
    ],
    "wof:name":"Baskeleh-ye Khan Mirza",
    "wof:placetype":"locality"
},
  "geometry": {"coordinates":[46.488,33.9225],"type":"Point"}
}