{
  "type": "Feature",
  "properties": {
    "gn:admin1_code":"10",
    "gn:asciiname":"Kharabanan-e Sofla",
    "gn:country_code":"IR",
    "gn:dem":1254,
    "gn:feature_class":"P",
    "gn:feature_code":"PPL",
    "gn:name":"Khar\u0101b\u0101n\u0101n-e Sofl\u00e1",
    "gn:population":0,
    "gn:timezone":"Asia/Tehran",
    "iso:country":"IR",
    "name:fas_x_preferred":[
        "\u062e\u0631\u0627\u0628\u0627\u0646\u0627\u0646 \u0633\u0641\u0644\u0649\u0670"
    ],
    "name:fas_x_variant":[
        "Khar\u0101b\u0101n\u0101n-e Sofl\u00e1",
        "\u062e\u064e\u0631\u0627\u0628\u0627\u0646",
        "\u062e\u064e\u0631\u0627\u0628\u0627\u0646\u0627\u0646"
    ],
    "name:und_x_variant":[
        "Khar\u0101b\u0101n\u0101n",
        "Khar\u0101b\u0101n"
    ],
    "wof:name":"Kharabanan-e Sofla",
    "wof:placetype":"locality"
},
  "geometry": {"coordinates":[46.3412,33.7877],"type":"Point"}
}