{
  "type": "Feature",
  "properties": {
    "gn:admin1_code":"15",
    "gn:asciiname":"Chiseh-ye Bozorg",
    "gn:country_code":"IR",
    "gn:dem":29,
    "gn:feature_class":"P",
    "gn:feature_code":"PPL",
    "gn:name":"Ch\u012bseh-ye Bozorg",
    "gn:population":0,
    "gn:timezone":"Asia/Tehran",
    "iso:country":"IR",
    "name:fas_x_preferred":[
        "\u0686\u06cc\u0633\u0647 \u0628\u0632\u0631\u06af"
    ],
    "name:und_x_variant":[
        "Chopseh",
        "Chepseh-ye Bozorg",
        "Ch\u012bseh-ye Bozorg"
    ],
    "wof:name":"Chiseh-ye Bozorg",
    "wof:placetype":"locality"
},
  "geometry": {"coordinates":[48.56668,31.58009],"type":"Point"}
}