{
  "type": "Feature",
  "properties": {
    "gn:admin1_code":"25.0",
    "gn:asciiname":"Farinun-e Bala",
    "gn:country_code":"IR",
    "gn:dem":1369,
    "gn:feature_class":"P",
    "gn:feature_code":"PPL",
    "gn:name":"Far\u012bn\u016bn-e B\u0101l\u0101",
    "gn:population":0,
    "gn:timezone":"Asia/Tehran",
    "iso:country":"IR",
    "name:fas_x_preferred":[
        "\u0641\u0631\u064a\u0646\u0648 \u0628\u0627\u0644\u0627"
    ],
    "name:fas_x_variant":[
        "Far\u012bn\u016b-ye B\u0101l\u0101",
        "\u0641\u0631\u064a\u0646\u0648\u0646 \u0628\u0627\u0644\u0627",
        "\u0641\u064e\u0631\u064a\u0646\u0648"
    ],
    "name:und_x_variant":[
        "Far\u012bn\u016bn-e B\u0101l\u0101",
        "Far\u012bn\u016b"
    ],
    "wof:name":"Farinun-e Bala",
    "wof:placetype":"locality"
},
  "geometry": {"coordinates":[56.82791,35.43927],"type":"Point"}
}