{
  "type": "Feature",
  "properties": {
    "gn:admin1_code":"32.0",
    "gn:asciiname":"Jozv Naqdi-e `Olya",
    "gn:country_code":"IR",
    "gn:dem":1177,
    "gn:feature_class":"P",
    "gn:feature_code":"PPL",
    "gn:name":"Jozv Naqd\u012b-e \u2018Oly\u0101",
    "gn:population":0,
    "gn:timezone":"Asia/Tehran",
    "iso:country":"IR",
    "name:fas_x_preferred":[
        "\u062c\u0632\u0648 \u0646\u0642\u062f\u06cc \u0639\u0644\u06cc\u0627"
    ],
    "name:fas_x_variant":[
        "\u0646\u0642\u062f\u06cc \u0639\u0644\u06cc\u0627"
    ],
    "name:und_x_variant":[
        "Jozv Naqd\u012b-e \u2018Oly\u0101",
        "Naqd\u012b-e \u2018Oly\u0101"
    ],
    "wof:name":"Jozv Naqdi-e `Olya",
    "wof:placetype":"locality"
},
  "geometry": {"coordinates":[47.94372,38.51309000000001],"type":"Point"}
}