{
  "type": "Feature",
  "properties": {
    "gn:admin1_code":"15.0",
    "gn:asciiname":"Kalbadam",
    "gn:country_code":"IR",
    "gn:dem":491,
    "gn:feature_class":"P",
    "gn:feature_code":"PPL",
    "gn:name":"Kalb\u0101d\u0101m",
    "gn:population":0,
    "gn:timezone":"Asia/Tehran",
    "iso:country":"IR",
    "name:fas_x_preferred":[
        "\u06a9\u0644\u0628\u0627\u062f\u0627\u0645"
    ],
    "name:fas_x_variant":[
        "Kalb\u0101d\u0101m"
    ],
    "wof:name":"Kalbadam",
    "wof:placetype":"locality"
},
  "geometry": {"coordinates":[48.155,32.7011],"type":"Point"}
}