{
  "type": "Feature",
  "properties": {
    "gn:admin1_code":"36",
    "gn:asciiname":"Valayesh",
    "gn:country_code":"IR",
    "gn:dem":2022,
    "gn:feature_class":"P",
    "gn:feature_code":"PPL",
    "gn:name":"V\u0101l\u0101yesh",
    "gn:population":0,
    "gn:timezone":"Asia/Tehran",
    "iso:country":"IR",
    "name:ara_x_preferred":[
        "\u0648\u0627\u0644\u0627\u064a\u0634"
    ],
    "name:azb_x_preferred":[
        "\u0648\u0627\u0644\u0627\u06cc\u0634"
    ],
    "name:fas_x_preferred":[
        "\u0648\u0627\u0644\u0627\u06cc\u0634"
    ],
    "name:fas_x_variant":[
        "V\u0101l\u0101yesh",
        "\u0631\u0648\u0633\u062a\u0627\u06cc \u0648\u0627\u0644\u0627\u06cc\u0634"
    ],
    "name:und_x_variant":[
        "Vilaish",
        "Vilashi"
    ],
    "wof:name":"Valayesh",
    "wof:placetype":"locality"
},
  "geometry": {"coordinates":[48.98612,36.46288],"type":"Point"}
}