{
  "type": "Feature",
  "properties": {
    "gn:admin1_code":"41",
    "gn:admin2_code":"9525807",
    "gn:asciiname":"Charmeh",
    "gn:country_code":"IR",
    "gn:dem":1867,
    "gn:feature_class":"P",
    "gn:feature_code":"PPL",
    "gn:name":"Charmeh",
    "gn:population":0,
    "gn:timezone":"Asia/Tehran",
    "iso:country":"IR",
    "name:fas_x_preferred":[
        "\u0686\u0631\u0645\u0647"
    ],
    "wof:name":"Charmeh",
    "wof:placetype":"locality"
},
  "geometry": {"coordinates":[58.58488000000001,33.94221],"type":"Point"}
}