{
  "type": "Feature",
  "properties": {
    "gn:admin1_code":"15",
    "gn:asciiname":"Rudzir",
    "gn:country_code":"IR",
    "gn:dem":917,
    "gn:feature_class":"P",
    "gn:feature_code":"PPL",
    "gn:name":"R\u016bdz\u012br",
    "gn:population":0,
    "gn:timezone":"Asia/Tehran",
    "iso:country":"IR",
    "name:fas_x_preferred":[
        "R\u016bdz\u012br"
    ],
    "name:fas_x_variant":[
        "\u0631\u0648\u062f\u0632\u06cc\u0631"
    ],
    "wof:name":"Rudzir",
    "wof:placetype":"locality"
},
  "geometry": {"coordinates":[50.10767,31.3408],"type":"Point"}
}