{
  "type": "Feature",
  "properties": {
    "gn:admin1_code":"40",
    "gn:asciiname":"Esfandiar",
    "gn:country_code":"IR",
    "gn:dem":1313,
    "gn:feature_class":"P",
    "gn:feature_code":"PPL",
    "gn:name":"Esfand\u012b\u0101r",
    "gn:population":0,
    "gn:timezone":"Asia/Tehran",
    "iso:country":"IR",
    "name:fas_x_preferred":[
        "Esfand\u012b\u0101r"
    ],
    "name:fas_x_variant":[
        "\u0627\u0633\u0641\u0646\u062f\u06cc\u0627\u0631",
        "Isfandiy\u0101r",
        "Esfand\u012by\u0101r"
    ],
    "wof:name":"Esfandiar",
    "wof:placetype":"locality"
},
  "geometry": {"coordinates":[57.5585,33.03654],"type":"Point"}
}