{
  "type": "Feature",
  "properties": {
    "gn:admin1_code":"44.0",
    "gn:asciiname":"Asadabad",
    "gn:country_code":"IR",
    "gn:dem":1244,
    "gn:feature_class":"P",
    "gn:feature_code":"PPL",
    "gn:name":"Asad\u0101b\u0101d",
    "gn:population":0,
    "gn:timezone":"Asia/Tehran",
    "iso:country":"IR",
    "name:fas_x_preferred":[
        "\u0627\u0633\u062f \u0622\u0628\u0627\u062f"
    ],
    "name:fas_x_variant":[
        "Asad\u0101b\u0101d",
        "\u0634\u0639\u0628\u0627\u0646 \u0622\u0628\u0627\u062f",
        "\u0645\u0644\u06a9 \u0622\u0628\u0627\u062f"
    ],
    "name:und_x_variant":[
        "Sha\u2018b\u0101n\u0101b\u0101d",
        "Malek\u0101b\u0101d"
    ],
    "wof:name":"Asadabad",
    "wof:placetype":"locality"
},
  "geometry": {"coordinates":[50.88694,35.81876],"type":"Point"}
}