{
  "type": "Feature",
  "properties": {
    "gn:admin1_code":"40",
    "gn:asciiname":"Shahrasb",
    "gn:country_code":"IR",
    "gn:dem":1492,
    "gn:feature_class":"P",
    "gn:feature_code":"PPL",
    "gn:name":"Shahrasb",
    "gn:population":0,
    "gn:timezone":"Asia/Tehran",
    "iso:country":"IR",
    "name:ara_x_preferred":[
        "\u0634\u0647\u0631 \u0623\u0633\u0628"
    ],
    "name:ceb_x_preferred":[
        "Shahrasb"
    ],
    "name:fas_x_preferred":[
        "\u0634\u0647\u0631 \u0627\u0633\u0628"
    ],
    "name:fas_x_variant":[
        "\u0634\u0627\u0646 \u0631\u064e\u0633\u0645",
        "\u0634\u064e\u0647\u0631\u0627\u0628",
        "\u0634\u0627\u0647 \u0631\u064e\u0633\u0645",
        "\u0634\u064e\u0647\u0631 \u0622\u0633\u0628",
        "\u0634\u0647\u0631\u0633\u0628",
        "\u0634\u0647\u0631\u0627\u0633\u0628"
    ],
    "name:por_x_preferred":[
        "Shahr Asb"
    ],
    "name:swe_x_preferred":[
        "Shahrasb"
    ],
    "name:und_x_variant":[
        "Shahr \u0100sb",
        "Sh\u0101h Rasm",
        "Shahr\u0101b",
        "Sh\u0101n Rasm",
        "Shahr Asb",
        "Shahrasb"
    ],
    "wof:name":"Shahrasb",
    "wof:placetype":"locality"
},
  "geometry": {"coordinates":[53.331,31.1424],"type":"Point"}
}