{
  "type": "Feature",
  "properties": {
    "gn:admin1_code":"35.0",
    "gn:asciiname":"Parcheh-ye Pa'in",
    "gn:country_code":"IR",
    "gn:dem":473,
    "gn:feature_class":"P",
    "gn:feature_code":"PPL",
    "gn:name":"Parcheh-ye P\u0101\u2019\u012bn",
    "gn:population":0,
    "gn:timezone":"Asia/Tehran",
    "iso:country":"IR",
    "name:fas_x_preferred":[
        "Parcheh-ye P\u0101\u2019\u012bn"
    ],
    "name:fas_x_variant":[
        "\u067e\u0631\u0686\u0647 \u067e\u0627\u0626\u06cc\u0646"
    ],
    "wof:name":"Parcheh-ye Pa'in",
    "wof:placetype":"locality"
},
  "geometry": {"coordinates":[50.58121,36.89878],"type":"Point"}
}