{
  "type": "Feature",
  "properties": {
    "gn:admin1_code":"7",
    "gn:asciiname":"Chah Kushk",
    "gn:country_code":"IR",
    "gn:dem":1855,
    "gn:feature_class":"P",
    "gn:feature_code":"PPL",
    "gn:name":"Chah K\u016bshk",
    "gn:population":0,
    "gn:timezone":"Asia/Tehran",
    "iso:country":"IR",
    "name:fas_x_preferred":[
        "Chah K\u016bshk"
    ],
    "wof:name":"Chah Kushk",
    "wof:placetype":"locality"
},
  "geometry": {"coordinates":[52.88333000000001,28.88333],"type":"Point"}
}