{
  "type": "Feature",
  "properties": {
    "gn:admin1_code":"34",
    "gn:asciiname":"Jowjin",
    "gn:country_code":"IR",
    "gn:dem":989,
    "gn:feature_class":"P",
    "gn:feature_code":"PPL",
    "gn:name":"Jowj\u012bn",
    "gn:population":0,
    "gn:timezone":"Asia/Tehran",
    "iso:country":"IR",
    "name:fas_x_preferred":[
        "Jowj\u012bn"
    ],
    "name:fas_x_variant":[
        "\u062c\u0648\u062c\u064a\u0646"
    ],
    "name:und_x_variant":[
        "\u062c\u0648\u062c\u064a\u0646"
    ],
    "wof:name":"Jowjin",
    "wof:placetype":"locality"
},
  "geometry": {"coordinates":[50.3368,34.87096],"type":"Point"}
}