{
  "type": "Feature",
  "properties": {
    "gn:admin1_code":"35.0",
    "gn:asciiname":"Deh Shahr",
    "gn:country_code":"IR",
    "gn:dem":1086,
    "gn:feature_class":"P",
    "gn:feature_code":"PPL",
    "gn:name":"Deh Shahr",
    "gn:population":0,
    "gn:timezone":"Asia/Tehran",
    "iso:country":"IR",
    "name:fas_x_preferred":[
        "\u062f\u0647 \u0634\u0647\u0631"
    ],
    "name:und_x_variant":[
        "\u062f\u0647 \u0634\u0647\u0631"
    ],
    "wof:name":"Deh Shahr",
    "wof:placetype":"locality"
},
  "geometry": {"coordinates":[51.25996,36.40828],"type":"Point"}
}