{
  "type": "Feature",
  "properties": {
    "gn:admin1_code":"5",
    "gn:asciiname":"Sorkhun",
    "gn:country_code":"IR",
    "gn:dem":961,
    "gn:feature_class":"P",
    "gn:feature_code":"PPL",
    "gn:name":"Sorkh\u016bn",
    "gn:population":0,
    "gn:timezone":"Asia/Tehran",
    "iso:country":"IR",
    "name:fas_x_preferred":[
        "Sorkh\u016bn"
    ],
    "name:fas_x_variant":[
        "\u0633\u0631\u062e\u0648\u0646"
    ],
    "name:und_x_variant":[
        "\u0633\u0631\u062e\u0648\u0646"
    ],
    "wof:name":"Sorkhun",
    "wof:placetype":"locality"
},
  "geometry": {"coordinates":[50.58031,31.04013],"type":"Point"}
}