{
  "type": "Feature",
  "properties": {
    "gn:admin1_code":"33.0",
    "gn:asciiname":"Alkhalaj",
    "gn:country_code":"IR",
    "gn:dem":1783,
    "gn:feature_class":"P",
    "gn:feature_code":"PPL",
    "gn:name":"Alkhalaj",
    "gn:population":0,
    "gn:timezone":"Asia/Tehran",
    "iso:country":"IR",
    "name:ara_x_preferred":[
        "\u0627\u0644\u062e\u0644\u062c"
    ],
    "name:fas_x_preferred":[
        "\u0639\u0644\u06cc \u062e\u0644\u062c"
    ],
    "name:fas_x_variant":[
        "\u2018Al\u012b Khalaj",
        "\u0627\u0644\u062e\u0644\u062c"
    ],
    "name:msa_x_preferred":[
        "Alkhalaj"
    ],
    "wof:name":"Alkhalaj",
    "wof:placetype":"locality"
},
  "geometry": {"coordinates":[46.981,37.6962],"type":"Point"}
}