{
  "type": "Feature",
  "properties": {
    "gn:admin1_code":"15",
    "gn:asciiname":"Seyyed Sharif",
    "gn:country_code":"IR",
    "gn:dem":23,
    "gn:feature_class":"P",
    "gn:feature_code":"PPL",
    "gn:name":"Seyyed Shar\u012bf",
    "gn:population":0,
    "gn:timezone":"Asia/Tehran",
    "iso:country":"IR",
    "name:fas_x_preferred":[
        "\u06a9\u0648\u062a \u0633\u06cc\u0651\u062f \u0634\u0631\u06cc\u0641"
    ],
    "name:fas_x_variant":[
        "Seyyed Shar\u012bf",
        "K\u016bt-e Seyyed Shar\u012bf",
        "\u0633\u06cc\u062f \u0634\u0631\u06cc\u0641"
    ],
    "wof:name":"Seyyed Sharif",
    "wof:placetype":"locality"
},
  "geometry": {"coordinates":[48.82071,31.46277000000001],"type":"Point"}
}