{
  "type": "Feature",
  "properties": {
    "gn:admin1_code":"23",
    "gn:asciiname":"Hemmatabad-e Sofla",
    "gn:country_code":"IR",
    "gn:dem":1694,
    "gn:feature_class":"P",
    "gn:feature_code":"PPL",
    "gn:name":"Hemmat\u0101b\u0101d-e Sofl\u00e1",
    "gn:population":0,
    "gn:timezone":"Asia/Tehran",
    "iso:country":"IR",
    "name:fas_x_preferred":[
        "\u0647\u0645\u0651\u062a \u0622\u0628\u0627\u062f \u0633\u0641\u0644\u06cc"
    ],
    "name:fas_x_variant":[
        "Hemmat\u0101b\u0101d-e Sofl\u00e1"
    ],
    "wof:name":"Hemmatabad-e Sofla",
    "wof:placetype":"locality"
},
  "geometry": {"coordinates":[47.977,33.9865],"type":"Point"}
}