{
  "type": "Feature",
  "properties": {
    "gn:admin1_code":"5",
    "gn:asciiname":"Deh Makki",
    "gn:country_code":"IR",
    "gn:dem":1035,
    "gn:feature_class":"P",
    "gn:feature_code":"PPL",
    "gn:name":"Deh Makk\u012b",
    "gn:population":0,
    "gn:timezone":"Asia/Tehran",
    "iso:country":"IR",
    "name:fas_x_preferred":[
        "Deh Makk\u012b"
    ],
    "name:fas_x_variant":[
        "\u062f\u0647 \u0645\u0643\u06cc"
    ],
    "wof:name":"Deh Makki",
    "wof:placetype":"locality"
},
  "geometry": {"coordinates":[50.54885,30.92555],"type":"Point"}
}