{
  "type": "Feature",
  "properties": {
    "gn:admin1_code":"8",
    "gn:asciiname":"Mardomkadeh",
    "gn:country_code":"IR",
    "gn:dem":-13,
    "gn:feature_class":"P",
    "gn:feature_code":"PPL",
    "gn:name":"Mardomkadeh",
    "gn:population":0,
    "gn:timezone":"Asia/Tehran",
    "iso:country":"IR",
    "name:fas_x_preferred":[
        "\u0645\u0631\u062f\u0647 \u0645\u06a9\u062f\u0647"
    ],
    "name:fas_x_variant":[
        "\u0645\u0631\u062f\u0645\u06a9\u062f\u0647"
    ],
    "name:und_x_variant":[
        "Mardeh Makadeh",
        "\u0645\u0631\u062f\u0647 \u0645\u06a9\u062f\u0647",
        "Mardomkadeh"
    ],
    "wof:name":"Mardomkadeh",
    "wof:placetype":"locality"
},
  "geometry": {"coordinates":[49.98372,37.2606],"type":"Point"}
}