{
  "type": "Feature",
  "properties": {
    "gn:admin1_code":"8",
    "gn:asciiname":"Mardomkadeh",
    "gn:country_code":"IR",
    "gn:dem":-13,
    "gn:feature_class":"P",
    "gn:feature_code":"PPL",
    "gn:name":"Mardomkadeh",
    "gn:population":0,
    "gn:timezone":"Asia/Tehran",
    "iso:country":"IR",
    "name:ara_x_preferred":[
        "\u0645\u0631\u062f\u0645\u0643 \u062f\u0647"
    ],
    "name:ceb_x_preferred":[
        "Mardeh Makadeh"
    ],
    "name:fas_x_preferred":[
        "\u0645\u0631\u062f\u0647 \u0645\u06a9\u062f\u0647"
    ],
    "name:fas_x_variant":[
        "\u0645\u0631\u062f\u0645\u06a9\u062f\u0647",
        "\u0645\u0631\u062f\u0645\u06a9 \u062f\u0647"
    ],
    "name:msa_x_preferred":[
        "Mardomkadeh"
    ],
    "name:por_x_preferred":[
        "Mardomkadeh"
    ],
    "name:swe_x_preferred":[
        "Mardeh Makadeh"
    ],
    "name:ukr_x_preferred":[
        "\u041c\u0430\u0440\u0434\u043e\u043c\u043a\u0430\u0434\u0435\u0433"
    ],
    "wof:name":"Mardomkadeh",
    "wof:placetype":"locality"
},
  "geometry": {"coordinates":[49.98372,37.2606],"type":"Point"}
}