{
  "type": "Feature",
  "properties": {
    "gn:admin1_code":"13",
    "gn:asciiname":"Tayesh`i",
    "gn:country_code":"IR",
    "gn:dem":516,
    "gn:feature_class":"P",
    "gn:feature_code":"PPL",
    "gn:name":"\u0162\u0101yesh\u2018\u012b",
    "gn:population":0,
    "gn:timezone":"Asia/Tehran",
    "iso:country":"IR",
    "name:und_x_variant":[
        "Tayesheh-Ye-Mahm\u016bd",
        "Talesheh Mahmood Nazar\u012b",
        "\u0162\u0101\u2019esheh Ma\u1e29m\u016bd",
        "\u0637\u0627\u064a\u0634\u06cc",
        "Ta\u2019esheh Ma\u1e29m\u016bd Nazar\u012b",
        "\u0162\u0101yesh\u2018\u012b"
    ],
    "wof:name":"Tayesh`i",
    "wof:placetype":"locality"
},
  "geometry": {"coordinates":[45.78651,34.61243],"type":"Point"}
}