{
  "type": "Feature",
  "properties": {
    "gn:admin1_code":"43",
    "gn:asciiname":"Qarah Mosalla",
    "gn:country_code":"IR",
    "gn:dem":747,
    "gn:feature_class":"P",
    "gn:feature_code":"PPL",
    "gn:name":"Qarah Mo\u015fall\u00e1",
    "gn:population":0,
    "gn:timezone":"Asia/Tehran",
    "iso:country":"IR",
    "name:fas_x_preferred":[
        "Qarah Mo\u015fall\u00e1"
    ],
    "name:fas_x_variant":[
        "Qareh Mo\u015fall\u00e1",
        "\u0642\u0631\u0647 \u0645\u0635\u0644\u06cc"
    ],
    "name:und_x_variant":[
        "Gareh Mosalla",
        "\u0642\u0631\u0647 \u0645\u0635\u0644\u06cc"
    ],
    "wof:name":"Qarah Mosalla",
    "wof:placetype":"locality"
},
  "geometry": {"coordinates":[56.87765,37.55941],"type":"Point"}
}