{
  "type": "Feature",
  "properties": {
    "gn:admin1_code":"23",
    "gn:asciiname":"Nurabad-e Cheshmeh Barqi",
    "gn:country_code":"IR",
    "gn:dem":1629,
    "gn:feature_class":"P",
    "gn:feature_code":"PPL",
    "gn:name":"N\u016br\u0101b\u0101d-e Cheshmeh Barq\u012b",
    "gn:population":0,
    "gn:timezone":"Asia/Tehran",
    "iso:country":"IR",
    "name:fas_x_preferred":[
        "\u0646\u0648\u0631\u0627\u0628\u0627\u062f\u0650 \u0686\u0650\u0634\u0645\u0650\u0647 \u0628\u064e\u0631\u0642\u06cc"
    ],
    "name:fas_x_variant":[
        "N\u016br\u0101b\u0101d-e Cheshmeh Barq\u012b"
    ],
    "wof:name":"Nurabad-e Cheshmeh Barqi",
    "wof:placetype":"locality"
},
  "geometry": {"coordinates":[48.28333,33.86667],"type":"Point"}
}