{
  "type": "Feature",
  "properties": {
    "gn:admin1_code":"29.0",
    "gn:asciiname":"Mir Hasan",
    "gn:country_code":"IR",
    "gn:dem":2026,
    "gn:feature_class":"P",
    "gn:feature_code":"PPL",
    "gn:name":"M\u012br \u1e28asan",
    "gn:population":0,
    "gn:timezone":"Asia/Tehran",
    "iso:country":"IR",
    "name:ceb_x_preferred":[
        "M\u012br \u1e28asan"
    ],
    "name:fas_x_preferred":[
        "\u0645\u06cc\u0631\u062d\u0633\u0646"
    ],
    "name:swe_x_preferred":[
        "M\u012br \u1e28asan"
    ],
    "wof:name":"Mir Hasan",
    "wof:placetype":"locality"
},
  "geometry": {"coordinates":[56.32111,28.8175],"type":"Point"}
}