{
  "type": "Feature",
  "properties": {
    "gn:admin1_code":"7",
    "gn:asciiname":"Sehh Kadeh",
    "gn:country_code":"IR",
    "gn:dem":1667,
    "gn:feature_class":"P",
    "gn:feature_code":"PPL",
    "gn:name":"Sehh Kadeh",
    "gn:population":0,
    "gn:timezone":"Asia/Tehran",
    "iso:country":"IR",
    "name:fas_x_preferred":[
        "\u0633\u0647\u0651 \u06a9\u062f\u0647"
    ],
    "name:fas_x_variant":[
        "\u0633\u06a9\u062f\u0647"
    ],
    "name:und_x_variant":[
        "Sekdeh"
    ],
    "wof:name":"Sehh Kadeh",
    "wof:placetype":"locality"
},
  "geometry": {"coordinates":[53.6578,28.3913],"type":"Point"}
}