{
  "type": "Feature",
  "properties": {
    "gn:admin1_code":"1",
    "gn:asciiname":"Oruj-e Mohammad Kandi",
    "gn:country_code":"IR",
    "gn:dem":815,
    "gn:feature_class":"P",
    "gn:feature_code":"PPL",
    "gn:name":"Or\u016bj-e Mo\u1e29ammad Kand\u012b",
    "gn:population":0,
    "gn:timezone":"Asia/Tehran",
    "iso:country":"IR",
    "name:azb_x_preferred":[
        "\u0627\u0648\u0631\u0648\u062c \u0645\u0648\u062d\u0645\u0645\u062f\u06a9\u0646\u062f\u06cc"
    ],
    "name:aze_x_preferred":[
        "Oruc M\u0259h\u0259mm\u0259dk\u0259ndi"
    ],
    "name:ceb_x_preferred":[
        "Or\u016bj-e Mo\u1e29ammad Kand\u012b"
    ],
    "name:fas_x_preferred":[
        "\u0627\u064f\u0631\u0648\u062c \u0645\u064f\u0647\u064e\u0645\u0651\u0621\u062f \u0643\u064e\u0646\u062f\u06cc"
    ],
    "name:fas_x_variant":[
        "\u0627\u0631\u0648\u062c \u0645\u062d\u0645\u0651\u062f \u06a9\u0646\u062f\u06cc",
        "Or\u016bj-e Mo\u1e29ammad Kand\u012b",
        "\u0627\u064e\u0631\u064f\u0651\u0647 \u0645\u064f\u0647\u064e\u0645\u064e\u0651\u062f",
        "\u0627\u064f\u0631\u0648\u062c\u0650 \u0645\u064f\u062d\u064e\u0645\u064e\u0651\u062f",
        "\u0627\u064f\u0631\u0648\u062c\u0650 \u0645\u064f\u062d\u064e\u0645\u064e\u0651\u062f \u0643\u064e\u0646\u062f\u06cc",
        "\u0627\u064f\u0631\u0648\u062c \u0643\u064e\u0646\u062f",
        "\u0627\u0631\u0648\u062c\u200c\u0645\u062d\u0645\u062f\u06a9\u0646\u062f\u06cc"
    ],
    "name:msa_x_preferred":[
        "Oruj-e Mohammad Kandi"
    ],
    "name:swe_x_preferred":[
        "Or\u016bj-e Mo\u1e29ammad Kand\u012b"
    ],
    "name:und_x_variant":[
        "Arooh Mohammad",
        "Or\u016bj Mo\u1e29ammad",
        "Druj Muhammadkand",
        "Oruj Muhammad-Kend",
        "Druj Muhammad-Kend",
        "Or\u016bj Mohamm\u2019d Kand\u012b",
        "\u016ar\u016bi Mo\u1e29ammad Kand\u012b",
        "Or\u016bj Kand",
        "Or\u016bj-e Mo\u1e29ammad"
    ],
    "wof:name":"Oruj-e Mohammad Kandi",
    "wof:placetype":"locality"
},
  "geometry": {"coordinates":[45.0262,39.2686],"type":"Point"}
}