{
  "type": "Feature",
  "properties": {
    "gn:admin1_code":"7.0",
    "gn:asciiname":"Soleymani",
    "gn:country_code":"IR",
    "gn:dem":918,
    "gn:feature_class":"P",
    "gn:feature_code":"PPL",
    "gn:name":"Soleym\u0101n\u012b",
    "gn:population":0,
    "gn:timezone":"Asia/Tehran",
    "iso:country":"IR",
    "name:fas_x_preferred":[
        "\u0633\u0644\u06cc\u0645\u0627\u0646\u06cc"
    ],
    "name:fas_x_variant":[
        "Soleym\u0101n\u012b"
    ],
    "name:pol_x_preferred":[
        "Solejmani"
    ],
    "wof:name":"Soleymani",
    "wof:placetype":"locality"
},
  "geometry": {"coordinates":[52.0033,29.3417],"type":"Point"}
}