{
  "type": "Feature",
  "properties": {
    "gn:admin1_code":"4",
    "gn:asciiname":"Chah-e Ommidabad",
    "gn:country_code":"IR",
    "gn:dem":1461,
    "gn:feature_class":"P",
    "gn:feature_code":"PPL",
    "gn:name":"Ch\u0101h-e Omm\u012bd\u0101b\u0101d",
    "gn:population":0,
    "gn:timezone":"Asia/Tehran",
    "iso:country":"IR",
    "name:fas_x_preferred":[
        "\u0686\u0627\u0647 \u0627\u0645\u06cc\u062f \u0622\u0628\u0627\u062f"
    ],
    "name:fas_x_variant":[
        "Ch\u0101h-e Omm\u012bd\u0101b\u0101d"
    ],
    "wof:name":"Chah-e Ommidabad",
    "wof:placetype":"locality"
},
  "geometry": {"coordinates":[60.39414,28.63036],"type":"Point"}
}