{
  "type": "Feature",
  "properties": {
    "gn:admin1_code":"15",
    "gn:asciiname":"Qasem `Aziz",
    "gn:country_code":"IR",
    "gn:dem":10,
    "gn:feature_class":"P",
    "gn:feature_code":"PPL",
    "gn:name":"Q\u0101sem \u2018Az\u012bz",
    "gn:population":0,
    "gn:timezone":"Asia/Tehran",
    "iso:country":"IR",
    "name:fas_x_preferred":[
        "Q\u0101sem \u2018Az\u012bz"
    ],
    "wof:name":"Qasem `Aziz",
    "wof:placetype":"locality"
},
  "geometry": {"coordinates":[47.93333,31.71667],"type":"Point"}
}