{
  "type": "Feature",
  "properties": {
    "gn:admin1_code":"13",
    "gn:asciiname":"Zangisheh",
    "gn:country_code":"IR",
    "gn:dem":1420,
    "gn:feature_class":"P",
    "gn:feature_code":"PPL",
    "gn:name":"Zang\u012bsheh",
    "gn:population":0,
    "gn:timezone":"Asia/Tehran",
    "iso:country":"IR",
    "name:fas_x_preferred":[
        "Dazang\u012bsheh"
    ],
    "name:fas_x_variant":[
        "\u0632\u0646\u06af\u06cc\u0634\u0647"
    ],
    "name:und_x_variant":[
        "Zang\u012bsheh"
    ],
    "wof:name":"Zangisheh",
    "wof:placetype":"locality"
},
  "geometry": {"coordinates":[47.1787,34.22701],"type":"Point"}
}