{
  "type": "Feature",
  "properties": {
    "iso:country":"IR",
    "name:ara_x_preferred":[
        "\u0628\u0644 \u0633\u0641\u064a\u062f"
    ],
    "name:aze_x_preferred":[
        "Polsefid"
    ],
    "name:ceb_x_preferred":[
        "Pol-e Sef\u012bd"
    ],
    "name:deu_x_preferred":[
        "Pol-Sefid"
    ],
    "name:eng_x_preferred":[
        "PolSefid"
    ],
    "name:fas_x_preferred":[
        "\u067e\u0644 \u0633\u0641\u06cc\u062f"
    ],
    "name:fas_x_variant":[
        "\u067e\u0644 \u0633\u0641\u064a\u062f",
        "Pol-e Sef\u012bd"
    ],
    "name:fra_x_preferred":[
        "PolSefid"
    ],
    "name:ita_x_preferred":[
        "Pol-e Sefid"
    ],
    "name:mlg_x_preferred":[
        "Pol-e Sefid"
    ],
    "name:mzn_x_preferred":[
        "\u067e\u0644 \u0633\u0641\u06cc\u062f"
    ],
    "name:nld_x_preferred":[
        "PolSefid"
    ],
    "name:pol_x_preferred":[
        "Pol-e Sefid"
    ],
    "name:rus_x_preferred":[
        "\u041f\u043e\u043b\u0435-\u0421\u0435\u0444\u0438\u0434"
    ],
    "name:swe_x_preferred":[
        "Pol-e Sef\u012bd"
    ],
    "name:tur_x_preferred":[
        "Pol Sefid"
    ],
    "name:unk_x_variant":[
        "Pol Sefid"
    ],
    "qs:gn_country":"IR",
    "qs:gn_fcode":"PPL",
    "qs:gn_pop":0,
    "qs:name":"Pol-e Sefid",
    "qs:name_adm0":"Iran",
    "qs:name_adm1":"Mazandaran",
    "qs:photos":19,
    "qs:photos_1k":4,
    "qs:photos_9k":1,
    "qs:photos_9r":1,
    "qs:photos_all":19,
    "qs:photos_sr":1,
    "qs:placetype":"Town",
    "qs:pop_sr":"0",
    "qs:woe_adm0":23424851,
    "wd:wordcount":91,
    "wof:name":"Pol-e Sefid",
    "wof:placetype":"locality"
},
  "geometry": {"coordinates":[53.05531,36.11787],"type":"Point"}
}