{
  "type": "Feature",
  "properties": {
    "gn:admin1_code":"23",
    "gn:asciiname":"Nik Bar",
    "gn:country_code":"IR",
    "gn:dem":871,
    "gn:feature_class":"P",
    "gn:feature_code":"PPL",
    "gn:name":"N\u012bk Bar",
    "gn:population":0,
    "gn:timezone":"Asia/Tehran",
    "iso:country":"IR",
    "name:fas_x_preferred":[
        "\u0644\u06cc\u062a\u0628\u0631"
    ],
    "name:fas_x_variant":[
        "\u0646\u06cc\u06a9 \u0628\u0631"
    ],
    "name:und_x_variant":[
        "L\u012btbar",
        "N\u012bk Bar"
    ],
    "wof:name":"Nik Bar",
    "wof:placetype":"locality"
},
  "geometry": {"coordinates":[47.7874,33.3234],"type":"Point"}
}