{
  "type": "Feature",
  "properties": {
    "gn:admin1_code":"3",
    "gn:asciiname":"Patuf",
    "gn:country_code":"IR",
    "gn:dem":1092,
    "gn:feature_class":"P",
    "gn:feature_code":"PPL",
    "gn:name":"P\u0101t\u016bf",
    "gn:population":0,
    "gn:timezone":"Asia/Tehran",
    "iso:country":"IR",
    "name:fas_x_preferred":[
        "P\u0101t\u016bf"
    ],
    "name:fas_x_variant":[
        "\u067e\u0627\u062a\u0648\u0641"
    ],
    "name:und_x_variant":[
        "\u067e\u0627\u062a\u0648\u0641"
    ],
    "wof:name":"Patuf",
    "wof:placetype":"locality"
},
  "geometry": {"coordinates":[50.38585,31.76313],"type":"Point"}
}