{
  "type": "Feature",
  "properties": {
    "gn:admin1_code":"8",
    "gn:asciiname":"Khalyan",
    "gn:country_code":"IR",
    "gn:dem":783,
    "gn:feature_class":"P",
    "gn:feature_code":"PPL",
    "gn:name":"Khaly\u0101n",
    "gn:population":0,
    "gn:timezone":"Asia/Tehran",
    "iso:country":"IR",
    "name:fas_x_preferred":[
        "Khal\u012b\u0101n"
    ],
    "name:fas_x_variant":[
        "\u062e\u0644\u06cc\u0627\u0646"
    ],
    "name:und_x_variant":[
        "Khaly\u0101n"
    ],
    "wof:name":"Khalyan",
    "wof:placetype":"locality"
},
  "geometry": {"coordinates":[48.73161,37.67442],"type":"Point"}
}