{
  "type": "Feature",
  "properties": {
    "gn:admin1_code":"8",
    "gn:asciiname":"Hajj Amir-e Pa'in",
    "gn:country_code":"IR",
    "gn:dem":1026,
    "gn:feature_class":"P",
    "gn:feature_code":"PPL",
    "gn:name":"\u1e28\u0101jj Am\u012br-e P\u0101\u2019\u012bn",
    "gn:population":0,
    "gn:timezone":"Asia/Tehran",
    "iso:country":"IR",
    "name:fas_x_preferred":[
        "\u062d\u0627\u062c \u0627\u0645\u06cc\u0631 \u067e\u0627\u0626\u06cc\u0646"
    ],
    "name:fas_x_variant":[
        "\u1e28\u0101jj Am\u012br-e P\u0101\u2019\u012bn"
    ],
    "name:und_x_variant":[
        "\u1e28\u0101j \u0100m\u012br-e P\u0101\u2019\u012bn"
    ],
    "wof:name":"Hajj Amir-e Pa'in",
    "wof:placetype":"locality"
},
  "geometry": {"coordinates":[48.5971,38.4132],"type":"Point"}
}