{
  "type": "Feature",
  "properties": {
    "gn:admin1_code":"29",
    "gn:asciiname":"Rezvan",
    "gn:country_code":"IR",
    "gn:dem":582,
    "gn:feature_class":"P",
    "gn:feature_code":"PPL",
    "gn:name":"Re\u1e95v\u0101n",
    "gn:population":0,
    "gn:timezone":"Asia/Tehran",
    "iso:country":"IR",
    "name:fas_x_preferred":[
        "\u0631\u0636\u0648\u0627\u0646"
    ],
    "name:fas_x_variant":[
        "Re\u1e95v\u0101n"
    ],
    "name:rus_x_preferred":[
        "\u0420\u0435\u0437\u0432\u0430\u043d"
    ],
    "wof:name":"Rezvan",
    "wof:placetype":"locality"
},
  "geometry": {"coordinates":[59.15022,28.60156],"type":"Point"}
}