{
  "type": "Feature",
  "properties": {
    "gn:admin1_code":"13",
    "gn:asciiname":"Darshiyeh",
    "gn:country_code":"IR",
    "gn:dem":681,
    "gn:feature_class":"P",
    "gn:feature_code":"PPL",
    "gn:name":"D\u0101rsh\u012byeh",
    "gn:population":0,
    "gn:timezone":"Asia/Tehran",
    "iso:country":"IR",
    "name:fas_x_preferred":[
        "\u062f\u0627\u0631\u0634\u064a\u0647"
    ],
    "name:fas_x_variant":[
        "D\u0101r Reshteh",
        "D\u0101rsh\u012byeh"
    ],
    "name:und_x_variant":[
        "D\u0101r-e Reshteh"
    ],
    "wof:name":"Darshiyeh",
    "wof:placetype":"locality"
},
  "geometry": {"coordinates":[45.86121,34.65949000000001],"type":"Point"}
}