{
  "type": "Feature",
  "properties": {
    "gn:admin1_code":"15",
    "gn:asciiname":"Chay Varsham",
    "gn:country_code":"IR",
    "gn:dem":45,
    "gn:feature_class":"P",
    "gn:feature_code":"PPL",
    "gn:name":"Ch\u0101y Varsh\u0101m",
    "gn:population":0,
    "gn:timezone":"Asia/Tehran",
    "iso:country":"IR",
    "name:ara_x_preferred":[
        "\u062a\u0634\u0627\u064a \u0648\u0631\u0634\u0627\u0645"
    ],
    "name:azb_x_preferred":[
        "\u0686\u0627\u06cc \u0648\u0631\u0634\u0627\u0645(\u0627\u0647\u0648\u0627\u0632)"
    ],
    "name:fas_x_preferred":[
        "\u0648\u0631\u0634\u0627\u0646"
    ],
    "name:fas_x_variant":[
        "Ch\u0101y Varsh\u0101n",
        "Varsh\u0101n",
        "\u0686\u0627\u06cc \u0648\u0631\u0634\u0627\u0645",
        "\u0686\u0627\u06cc\u200c\u0648\u0631\u0634\u0627\u0645"
    ],
    "name:und_x_variant":[
        "Sh\u0101h Varsh\u0101n",
        "Ch\u0101h Varsh\u0101n",
        "Chay Varsham",
        "Ch\u0101y Varsh\u0101m"
    ],
    "wof:name":"Chay Varsham",
    "wof:placetype":"locality"
},
  "geometry": {"coordinates":[49.16964,31.35812],"type":"Point"}
}