{
  "type": "Feature",
  "properties": {
    "gn:admin1_code":"15.0",
    "gn:asciiname":"Do Gush Vajel",
    "gn:country_code":"IR",
    "gn:dem":1062,
    "gn:feature_class":"P",
    "gn:feature_code":"PPL",
    "gn:name":"Do G\u016bsh V\u0101jel",
    "gn:population":0,
    "gn:timezone":"Asia/Tehran",
    "iso:country":"IR",
    "name:fas_x_preferred":[
        "\u062f\u0648 \u06af\u0648\u0634 \u0648\u0627\u062c\u0644"
    ],
    "name:und_x_variant":[
        "Do G\u016bsh V\u0101jel"
    ],
    "wof:name":"Do Gush Vajel",
    "wof:placetype":"locality"
},
  "geometry": {"coordinates":[50.0671,31.41489],"type":"Point"}
}