{
  "type": "Feature",
  "properties": {
    "gn:admin1_code":"8",
    "gn:asciiname":"Tayer Sara",
    "gn:country_code":"IR",
    "gn:dem":77,
    "gn:feature_class":"P",
    "gn:feature_code":"PPL",
    "gn:name":"\u0162\u0101yer Sar\u0101",
    "gn:population":0,
    "gn:timezone":"Asia/Tehran",
    "iso:country":"IR",
    "name:fas_x_preferred":[
        "\u0162\u0101yer Sar\u0101"
    ],
    "name:fas_x_variant":[
        "\u0637\u0627\u06cc\u0631 \u0633\u0631\u0627"
    ],
    "name:und_x_variant":[
        "\u0637\u0627\u06cc\u0631 \u0633\u0631\u0627"
    ],
    "wof:name":"Tayer Sara",
    "wof:placetype":"locality"
},
  "geometry": {"coordinates":[50.06711,37.16222],"type":"Point"}
}