{
  "type": "Feature",
  "properties": {
    "gn:admin1_code":"35.0",
    "gn:asciiname":"Seyyed Mahalleh",
    "gn:country_code":"IR",
    "gn:dem":-21,
    "gn:feature_class":"P",
    "gn:feature_code":"PPL",
    "gn:name":"Seyyed Ma\u1e29alleh",
    "gn:population":0,
    "gn:timezone":"Asia/Tehran",
    "iso:country":"IR",
    "name:fas_x_preferred":[
        "Seyyed Ma\u1e29alleh"
    ],
    "name:fas_x_variant":[
        "\u0633\u064a\u062f \u0645\u062d\u0644\u0647"
    ],
    "wof:name":"Seyyed Mahalleh",
    "wof:placetype":"locality"
},
  "geometry": {"coordinates":[53.00565,36.71305],"type":"Point"}
}