{
  "type": "Feature",
  "properties": {
    "gn:admin1_code":"15",
    "gn:asciiname":"Kebeshk-e Sofla",
    "gn:country_code":"IR",
    "gn:dem":666,
    "gn:feature_class":"P",
    "gn:feature_code":"PPL",
    "gn:name":"Kebeshk-e Sofl\u00e1",
    "gn:population":0,
    "gn:timezone":"Asia/Tehran",
    "iso:country":"IR",
    "name:fas_x_preferred":[
        "Kebeshk-e Sofl\u00e1"
    ],
    "wof:name":"Kebeshk-e Sofla",
    "wof:placetype":"locality"
},
  "geometry": {"coordinates":[49.56139,32.10083],"type":"Point"}
}