{
  "type": "Feature",
  "properties": {
    "gn:admin1_code":"33",
    "gn:asciiname":"Chay Kandi",
    "gn:country_code":"IR",
    "gn:dem":737,
    "gn:feature_class":"P",
    "gn:feature_code":"PPL",
    "gn:name":"Ch\u0101y Kand\u012b",
    "gn:population":0,
    "gn:timezone":"Asia/Tehran",
    "iso:country":"IR",
    "name:aze_x_preferred":[
        "\u00c7ay k\u0259ndi"
    ],
    "name:fas_x_preferred":[
        "\u0686\u0627\u06cc \u06a9\u0646\u062f\u06cc"
    ],
    "name:fas_x_variant":[
        "Ch\u0101y Kand\u012b",
        "\u0686\u0627\u06cc\u200c\u06a9\u0646\u062f\u06cc"
    ],
    "name:und_x_variant":[
        "Ch\u0101ikh\u0101na",
        "Ch\u0101ykh\u0101neh",
        "Chaykendy"
    ],
    "wof:name":"Chay Kandi",
    "wof:placetype":"locality"
},
  "geometry": {"coordinates":[46.5632,38.7904],"type":"Point"}
}