{
  "type": "Feature",
  "properties": {
    "gn:admin1_code":"28.0",
    "gn:asciiname":"Ganj-e Qobad",
    "gn:country_code":"IR",
    "gn:dem":1811,
    "gn:feature_class":"P",
    "gn:feature_code":"PPL",
    "gn:name":"Ganj-e Qob\u0101d",
    "gn:population":0,
    "gn:timezone":"Asia/Tehran",
    "iso:country":"IR",
    "name:fas_x_preferred":[
        "Ganj-e Qob\u0101d"
    ],
    "name:fas_x_variant":[
        "\u06af\u0646\u062c \u0642\u0628\u0627\u062f"
    ],
    "name:und_x_variant":[
        "Ganj Qob\u0101d",
        "\u06af\u0646\u062c \u0642\u0628\u0627\u062f"
    ],
    "wof:name":"Ganj-e Qobad",
    "wof:placetype":"locality"
},
  "geometry": {"coordinates":[51.64706,32.1328],"type":"Point"}
}