{
  "type": "Feature",
  "properties": {
    "gn:admin1_code":"36",
    "gn:asciiname":"Sahleh",
    "gn:country_code":"IR",
    "gn:dem":1882,
    "gn:feature_class":"P",
    "gn:feature_code":"PPL",
    "gn:name":"Sahleh",
    "gn:population":0,
    "gn:timezone":"Asia/Tehran",
    "iso:country":"IR",
    "name:fas_x_preferred":[
        "\u0633\u0647\u0644\u0647"
    ],
    "name:fas_x_variant":[
        "\u0633\u064e\u06af\u0644\u064a\u064e",
        "\u0633\u064e\u0647\u0644\u0650\u0647"
    ],
    "name:und_x_variant":[
        "Saglya",
        "Sahila",
        "Sahleh",
        "Sahlah"
    ],
    "wof:name":"Sahleh",
    "wof:placetype":"locality"
},
  "geometry": {"coordinates":[48.48994,36.56844],"type":"Point"}
}