{
  "type": "Feature",
  "properties": {
    "gn:admin1_code":"36",
    "gn:asciiname":"Dash Bolagh",
    "gn:country_code":"IR",
    "gn:dem":1888,
    "gn:feature_class":"P",
    "gn:feature_code":"PPL",
    "gn:name":"D\u0101sh Bol\u0101gh",
    "gn:population":0,
    "gn:timezone":"Asia/Tehran",
    "iso:country":"IR",
    "name:azb_x_preferred":[
        "\u062f\u0627\u0634 \u0628\u0644\u0627\u063a"
    ],
    "name:fas_x_preferred":[
        "\u062f\u0627\u0634 \u0628\u0644\u0627\u063a"
    ],
    "name:fas_x_variant":[
        "D\u0101shbol\u0101gh",
        "D\u0101sh Bol\u0101gh",
        "\u062f\u0627\u0634\u200c\u0628\u0644\u0627\u063a"
    ],
    "name:und_x_variant":[
        "D\u0101shbul\u0101q",
        "Dash Bulag",
        "D\u0101shb\u016bl\u0101gh"
    ],
    "wof:name":"Dash Bolagh",
    "wof:placetype":"locality"
},
  "geometry": {"coordinates":[48.23707,37.10456],"type":"Point"}
}