{
  "type": "Feature",
  "properties": {
    "gn:admin1_code":"4.0",
    "gn:asciiname":"Bidak-e Vasati",
    "gn:country_code":"IR",
    "gn:dem":1796,
    "gn:feature_class":"P",
    "gn:feature_code":"PPL",
    "gn:name":"B\u012bdak-e Vasa\u0163\u012b",
    "gn:population":0,
    "gn:timezone":"Asia/Tehran",
    "iso:country":"IR",
    "name:fas_x_preferred":[
        "\u0628\u06cc\u062f\u06a9 \u0648\u0633\u0637\u06cc"
    ],
    "name:fas_x_variant":[
        "B\u012bdak-e B\u0101l\u0101",
        "B\u012bdak-e Vasa\u0163\u012b"
    ],
    "wof:name":"Bidak-e Vasati",
    "wof:placetype":"locality"
},
  "geometry": {"coordinates":[60.7283,28.656],"type":"Point"}
}