{
  "type": "Feature",
  "properties": {
    "gn:admin1_code":"3",
    "gn:asciiname":"Shir Mard",
    "gn:country_code":"IR",
    "gn:dem":2152,
    "gn:feature_class":"P",
    "gn:feature_code":"PPL",
    "gn:name":"Sh\u012br Mard",
    "gn:population":0,
    "gn:timezone":"Asia/Tehran",
    "iso:country":"IR",
    "name:fas_x_preferred":[
        "Sh\u012br Mard"
    ],
    "name:fas_x_variant":[
        "\u0634\u064a\u0631 \u0645\u0631\u062f"
    ],
    "name:und_x_variant":[
        "\u0634\u064a\u0631 \u0645\u0631\u062f"
    ],
    "wof:name":"Shir Mard",
    "wof:placetype":"locality"
},
  "geometry": {"coordinates":[51.21646,31.4138],"type":"Point"}
}