{
  "type": "Feature",
  "properties": {
    "gn:admin1_code":"33",
    "gn:asciiname":"Badam Yar",
    "gn:country_code":"IR",
    "gn:dem":1857,
    "gn:feature_class":"P",
    "gn:feature_code":"PPL",
    "gn:name":"B\u0101d\u0101m Y\u0101r",
    "gn:population":0,
    "gn:timezone":"Asia/Tehran",
    "iso:country":"IR",
    "name:fas_x_preferred":[
        "\u0628\u0627\u062f\u0627\u0645 \u06cc\u0627\u0631"
    ],
    "name:fas_x_variant":[
        "B\u0101d\u0101my\u0101r",
        "B\u0101d\u0101m Y\u0101r",
        "\u0642\u062f\u0645\u06af\u0627\u0647"
    ],
    "name:und_x_variant":[
        "Qadamg\u0101h"
    ],
    "wof:name":"Badam Yar",
    "wof:placetype":"locality"
},
  "geometry": {"coordinates":[46.0104,37.6826],"type":"Point"}
}