{
  "type": "Feature",
  "properties": {
    "gn:admin1_code":"8.0",
    "gn:asciiname":"Maskudeh",
    "gn:country_code":"IR",
    "gn:dem":-18,
    "gn:feature_class":"P",
    "gn:feature_code":"PPL",
    "gn:name":"Mask\u016bdeh",
    "gn:population":0,
    "gn:timezone":"Asia/Tehran",
    "iso:country":"IR",
    "name:fas_x_preferred":[
        "Mask\u016bdeh"
    ],
    "wof:name":"Maskudeh",
    "wof:placetype":"locality"
},
  "geometry": {"coordinates":[49.56889,37.33667],"type":"Point"}
}