{
  "type": "Feature",
  "properties": {
    "gn:admin1_code":"8.0",
    "gn:asciiname":"Rangineh Sar",
    "gn:country_code":"IR",
    "gn:dem":201,
    "gn:feature_class":"P",
    "gn:feature_code":"PPL",
    "gn:name":"Rang\u012bneh Sar",
    "gn:population":0,
    "gn:timezone":"Asia/Tehran",
    "iso:country":"IR",
    "name:fas_x_preferred":[
        "Sarahl\u012bvah"
    ],
    "name:fas_x_variant":[
        "\u0631\u0646\u06af\u06cc\u0646\u0647 \u0633\u0631",
        "\u0628\u06cc\u0627\u0628\u0646\u062f"
    ],
    "name:und_x_variant":[
        "Rang\u012bneh Sar",
        "B\u012b\u0101band"
    ],
    "wof:name":"Rangineh Sar",
    "wof:placetype":"locality"
},
  "geometry": {"coordinates":[48.81358,37.82035],"type":"Point"}
}