{
  "type": "Feature",
  "properties": {
    "gn:admin1_code":"13",
    "gn:asciiname":"Qasemabad",
    "gn:country_code":"IR",
    "gn:dem":1889,
    "gn:feature_class":"P",
    "gn:feature_code":"PPL",
    "gn:name":"Q\u0101sem\u0101b\u0101d",
    "gn:population":0,
    "gn:timezone":"Asia/Tehran",
    "iso:country":"IR",
    "name:fas_x_preferred":[
        "\u0642\u0627\u0633\u0645 \u0622\u0628\u0627\u062f"
    ],
    "name:fas_x_variant":[
        "Q\u0101sem\u0101b\u0101d",
        "\u0628\u0631\u062f\u06cc\u0646\u0647"
    ],
    "name:und_x_variant":[
        "Bard\u012bneh"
    ],
    "wof:name":"Qasemabad",
    "wof:placetype":"locality"
},
  "geometry": {"coordinates":[47.73009,34.55484000000001],"type":"Point"}
}