{
  "type": "Feature",
  "properties": {
    "gn:admin1_code":"4",
    "gn:asciiname":"Daram Bukan",
    "gn:cc2":"IR",
    "gn:country_code":"IR",
    "gn:dem":919,
    "gn:feature_class":"P",
    "gn:feature_code":"PPL",
    "gn:name":"Daram B\u016bk\u0101n",
    "gn:population":0,
    "gn:timezone":"Asia/Tehran",
    "iso:country":"IR",
    "name:fas_x_preferred":[
        "Daram B\u016bk\u0101n"
    ],
    "name:und_x_variant":[
        "Darambak\u0101n",
        "Daramb\u016bk\u0101n"
    ],
    "wof:name":"Daram Bukan",
    "wof:placetype":"locality"
},
  "geometry": {"coordinates":[59.40861,26.64111],"type":"Point"}
}