{
  "type": "Feature",
  "properties": {
    "gn:admin1_code":"5.0",
    "gn:asciiname":"Daleh Majin",
    "gn:country_code":"IR",
    "gn:dem":2302,
    "gn:feature_class":"P",
    "gn:feature_code":"PPL",
    "gn:name":"Daleh Maj\u012bn",
    "gn:population":0,
    "gn:timezone":"Asia/Tehran",
    "iso:country":"IR",
    "name:fas_x_preferred":[
        "Daleh Maj\u012bn"
    ],
    "name:fas_x_variant":[
        "\u062f\u0644\u0647 \u0645\u062c\u06cc\u0646"
    ],
    "wof:name":"Daleh Majin",
    "wof:placetype":"locality"
},
  "geometry": {"coordinates":[51.00932,31.13064],"type":"Point"}
}