{
  "type": "Feature",
  "properties": {
    "gn:admin1_code":"29",
    "gn:asciiname":"Mohammadabad-e Deh Gari",
    "gn:country_code":"IR",
    "gn:dem":567,
    "gn:feature_class":"P",
    "gn:feature_code":"PPL",
    "gn:name":"Mo\u1e29ammad\u0101b\u0101d-e Deh G\u0101r\u012b",
    "gn:population":0,
    "gn:timezone":"Asia/Tehran",
    "iso:country":"IR",
    "name:ara_x_preferred":[
        "\u0645\u062d\u0645\u062f\u0622\u0628\u0627\u062f \u062f\u0647\u063a\u0627\u0648\u064a"
    ],
    "name:ceb_x_preferred":[
        "Mo\u1e29ammad\u0101b\u0101d-e Deh G\u0101r\u012b"
    ],
    "name:fas_x_preferred":[
        "Mo\u1e29ammad\u0101b\u0101d-e Deh G\u0101r\u012b"
    ],
    "name:fas_x_variant":[
        "Mo\u1e29ammad\u0101b\u0101d-e Deh G\u0101v\u012b",
        "\u0645\u062d\u0645\u062f \u0622\u0628\u0627\u062f \u062f\u0647 \u06af\u0627\u0631\u06cc",
        "Mohammad \u0100b\u0101d",
        "\u0645\u062d\u0645\u062f\u0622\u0628\u0627\u062f \u062f\u0647\u06af\u0627\u0648\u06cc"
    ],
    "name:swe_x_preferred":[
        "Mo\u1e29ammad\u0101b\u0101d-e Deh G\u0101r\u012b"
    ],
    "name:und_x_variant":[
        "Mohammad \u0100b\u0101d",
        "\u0645\u062d\u0645\u062f \u0622\u0628\u0627\u062f \u062f\u0647 \u06af\u0627\u0631\u06cc"
    ],
    "wof:name":"Mohammadabad-e Deh Gari",
    "wof:placetype":"locality"
},
  "geometry": {"coordinates":[59.12889000000001,28.77833],"type":"Point"}
}