{
  "type": "Feature",
  "properties": {
    "gn:admin1_code":"4.0",
    "gn:asciiname":"Chorrak",
    "gn:country_code":"IR",
    "gn:dem":47,
    "gn:feature_class":"P",
    "gn:feature_code":"PPL",
    "gn:name":"Chorrak",
    "gn:population":0,
    "gn:timezone":"Asia/Tehran",
    "iso:country":"IR",
    "name:fas_x_preferred":[
        "\u0686\u0631\u0643"
    ],
    "name:fas_x_variant":[
        "\u0686\u0631\u06a9"
    ],
    "name:und_x_variant":[
        "Chork",
        "Chorrak",
        "\u0686\u0631\u0643",
        "Jowrak"
    ],
    "wof:name":"Chorrak",
    "wof:placetype":"locality"
},
  "geometry": {"coordinates":[61.00451999999999,25.78126],"type":"Point"}
}