{
  "type": "Feature",
  "properties": {
    "gn:admin1_code":"8.0",
    "gn:asciiname":"Zineh Poshteh",
    "gn:country_code":"IR",
    "gn:dem":1716,
    "gn:feature_class":"P",
    "gn:feature_code":"PPL",
    "gn:name":"Z\u012bneh Poshteh",
    "gn:population":0,
    "gn:timezone":"Asia/Tehran",
    "iso:country":"IR",
    "name:fas_x_preferred":[
        "Z\u012bn Poshteh"
    ],
    "name:fas_x_variant":[
        "\u0632\u06cc\u0646 \u067e\u0634\u062a\u0647",
        "\u0632\u06cc\u0646\u0647 \u067e\u0634\u062a\u0647"
    ],
    "name:und_x_variant":[
        "\u0632\u06cc\u0646 \u067e\u0634\u062a\u0647",
        "Z\u012bneh Poshteh"
    ],
    "wof:name":"Zineh Poshteh",
    "wof:placetype":"locality"
},
  "geometry": {"coordinates":[49.91088,36.79523],"type":"Point"}
}