{
  "type": "Feature",
  "properties": {
    "gn:admin1_code":"29",
    "gn:asciiname":"Deh-e Bala-ye Senjeh-ye Tu'i",
    "gn:country_code":"IR",
    "gn:dem":2190,
    "gn:feature_class":"P",
    "gn:feature_code":"PPL",
    "gn:name":"Deh-e B\u0101l\u0101-ye Senjeh-ye T\u016b\u2019\u012b",
    "gn:population":0,
    "gn:timezone":"Asia/Tehran",
    "iso:country":"IR",
    "name:fas_x_preferred":[
        "\u0633\u0646\u062c\u062a\u0648"
    ],
    "name:fas_x_variant":[
        "Senjen\u016b",
        "Senjet\u016b",
        "\u062f\u0647 \u0628\u0627\u0644\u0627 \u0633\u0646\u062c\u0647 \u062a\u0648\u064a\u06cc",
        "\u0633\u0646\u062c\u062f \u0639\u0644\u064a\u0627"
    ],
    "name:und_x_variant":[
        "Deh-e B\u0101l\u0101-ye Senjeh-ye T\u016b\u2019\u012b",
        "Senjed-e \u2018Oly\u0101"
    ],
    "wof:name":"Deh-e Bala-ye Senjeh-ye Tu'i",
    "wof:placetype":"locality"
},
  "geometry": {"coordinates":[55.4954,30.2187],"type":"Point"}
}