{
  "type": "Feature",
  "properties": {
    "gn:admin1_code":"15",
    "gn:asciiname":"Beyt-e Savadi",
    "gn:country_code":"IR",
    "gn:dem":56,
    "gn:feature_class":"P",
    "gn:feature_code":"PPL",
    "gn:name":"Beyt-e Sav\u0101d\u012b",
    "gn:population":0,
    "gn:timezone":"Asia/Tehran",
    "iso:country":"IR",
    "name:ceb_x_preferred":[
        "Qaryeh-ye Sa'v\u0101d\u012b"
    ],
    "name:fas_x_preferred":[
        "\u0642\u0631\u06cc\u0647 \u0633\u0624\u0627\u062f\u06cc"
    ],
    "name:fas_x_variant":[
        "Beyt-e Sav\u0101d\u012bp\u016br",
        "\u0628\u06cc\u062a \u0633\u0648\u0627\u062f\u06cc"
    ],
    "name:swe_x_preferred":[
        "Qaryeh-ye Sa'v\u0101d\u012b"
    ],
    "name:und_x_variant":[
        "Bait as Suwadi",
        "Beyt-e Sav\u0101d\u012b",
        "Qaryeh-ye Sa\u2019v\u0101d\u012b"
    ],
    "wof:name":"Beyt-e Savadi",
    "wof:placetype":"locality"
},
  "geometry": {"coordinates":[49.3006,31.19674],"type":"Point"}
}