{
  "type": "Feature",
  "properties": {
    "gn:admin1_code":"42",
    "gn:asciiname":"Salehiyeh",
    "gn:country_code":"IR",
    "gn:dem":819,
    "gn:feature_class":"P",
    "gn:feature_code":"PPL",
    "gn:name":"\u015e\u0101le\u1e29\u012byeh",
    "gn:population":0,
    "gn:timezone":"Asia/Tehran",
    "iso:country":"IR",
    "name:ara_x_preferred":[
        "\u0635\u0627\u0644\u062d\u064a\u0629"
    ],
    "name:ceb_x_preferred":[
        "\u015e\u0101le\u1e29\u012byeh"
    ],
    "name:fas_x_preferred":[
        "\u015e\u0101le\u1e29\u012byeh"
    ],
    "name:fas_x_variant":[
        "\u0635\u0627\u0644\u062d\u064a\u0647",
        "\u0635\u0627\u0644\u062d\u06cc\u0647"
    ],
    "name:mzn_x_preferred":[
        "\u0635\u0627\u0644\u062d\u06cc\u0647"
    ],
    "name:swe_x_preferred":[
        "\u015e\u0101le\u1e29\u012byeh"
    ],
    "wof:name":"Salehiyeh",
    "wof:placetype":"locality"
},
  "geometry": {"coordinates":[57.38671,35.1392],"type":"Point"}
}