{
  "type": "Feature",
  "properties": {
    "gn:admin1_code":"35.0",
    "gn:asciiname":"Sangtu",
    "gn:country_code":"IR",
    "gn:dem":0,
    "gn:feature_class":"P",
    "gn:feature_code":"PPL",
    "gn:name":"Sangt\u016b",
    "gn:population":0,
    "gn:timezone":"Asia/Tehran",
    "iso:country":"IR",
    "name:ceb_x_preferred":[
        "Sangt\u016b"
    ],
    "name:fas_x_preferred":[
        "Sangt\u016b"
    ],
    "name:fas_x_variant":[
        "\u0633\u0646\u06af\u062a\u0648"
    ],
    "name:swe_x_preferred":[
        "Sangt\u016b"
    ],
    "wof:name":"Sangtu",
    "wof:placetype":"locality"
},
  "geometry": {"coordinates":[51.54501,36.62013],"type":"Point"}
}