{
  "type": "Feature",
  "properties": {
    "gn:admin1_code":"35.0",
    "gn:asciiname":"Kashtell",
    "gn:country_code":"IR",
    "gn:dem":19,
    "gn:feature_class":"P",
    "gn:feature_code":"PPL",
    "gn:name":"Kashtell",
    "gn:population":0,
    "gn:timezone":"Asia/Tehran",
    "iso:country":"IR",
    "name:fas_x_preferred":[
        "\u0643\u064e\u0634\u062a\u0650\u0644\u0651"
    ],
    "wof:name":"Kashtell",
    "wof:placetype":"locality"
},
  "geometry": {"coordinates":[52.66417,36.45194],"type":"Point"}
}