{
  "type": "Feature",
  "properties": {
    "gn:admin1_code":"15",
    "gn:asciiname":"Ghoveyleh-ye Sadat",
    "gn:country_code":"IR",
    "gn:dem":112,
    "gn:feature_class":"P",
    "gn:feature_code":"PPL",
    "gn:name":"Ghoveyleh-ye S\u0101d\u0101t",
    "gn:population":0,
    "gn:timezone":"Asia/Tehran",
    "iso:country":"IR",
    "name:ara_x_preferred":[
        "\u063a\u0648\u064a\u0644\u0629 \u0646\u0627\u0642\u062f"
    ],
    "name:ceb_x_preferred":[
        "Ghoveyleh-ye S\u0101d\u0101t"
    ],
    "name:fas_x_preferred":[
        "Ghoveyleh-ye N\u0101qed"
    ],
    "name:fas_x_variant":[
        "Ghoveyleh-ye S\u0101d\u0101t",
        "\u063a\u0648\u06cc\u0644\u0647 \u0633\u0627\u062f\u0627\u062a",
        "\u063a\u0648\u06cc\u0644\u0647 \u0646\u0627\u0642\u062f"
    ],
    "name:swe_x_preferred":[
        "Ghoveyleh-ye S\u0101d\u0101t"
    ],
    "name:und_x_variant":[
        "Sheykh Ahmad"
    ],
    "wof:name":"Ghoveyleh-ye Sadat",
    "wof:placetype":"locality"
},
  "geometry": {"coordinates":[49.51378,31.27975],"type":"Point"}
}