{
  "type": "Feature",
  "properties": {
    "gn:admin1_code":"29",
    "gn:asciiname":"Gal-e Kuchak",
    "gn:country_code":"IR",
    "gn:dem":405,
    "gn:feature_class":"P",
    "gn:feature_code":"PPL",
    "gn:name":"Gal-e K\u016bchak",
    "gn:population":0,
    "gn:timezone":"Asia/Tehran",
    "iso:country":"IR",
    "name:fas_x_preferred":[
        "\u06af\u0644 \u06a9\u0648\u0686\u06a9"
    ],
    "name:fas_x_variant":[
        "Gal-e K\u016bchak"
    ],
    "wof:name":"Gal-e Kuchak",
    "wof:placetype":"locality"
},
  "geometry": {"coordinates":[57.8863,27.4644],"type":"Point"}
}