{
  "type": "Feature",
  "properties": {
    "gn:admin1_code":"29",
    "gn:asciiname":"Mohammadabad",
    "gn:country_code":"IR",
    "gn:dem":1024,
    "gn:feature_class":"P",
    "gn:feature_code":"PPL",
    "gn:name":"Mo\u1e29ammad\u0101b\u0101d",
    "gn:population":0,
    "gn:timezone":"Asia/Tehran",
    "iso:country":"IR",
    "name:fas_x_preferred":[
        "Mo\u1e29ammad\u0101b\u0101d"
    ],
    "name:fas_x_variant":[
        "\u0645\u062d\u0645\u062f \u0622\u0628\u0627\u062f"
    ],
    "name:und_x_variant":[
        "Mahd\u0101bad",
        "Mo\u1e29ammad\u0101b\u0101d-e Arz\u016b\u2019\u012byeh",
        "Mohammad Abad Arzoo\u2019eyeh",
        "Mahd\u0101b\u0101d"
    ],
    "wof:name":"Mohammadabad",
    "wof:placetype":"locality"
},
  "geometry": {"coordinates":[56.3367,28.4236],"type":"Point"}
}