{
  "type": "Feature",
  "properties": {
    "gn:admin1_code":"11",
    "gn:asciiname":"Faryab",
    "gn:country_code":"IR",
    "gn:dem":304,
    "gn:feature_class":"P",
    "gn:feature_code":"PPL",
    "gn:name":"F\u0101ry\u0101b",
    "gn:population":0,
    "gn:timezone":"Asia/Tehran",
    "iso:country":"IR",
    "name:fas_x_preferred":[
        "\u0641\u0627\u0631\u064a\u0627\u0628"
    ],
    "name:fas_x_variant":[
        "\u067e\u064e\u0631\u064a\u0627\u0628",
        "F\u0101ry\u0101b"
    ],
    "name:msa_x_preferred":[
        "Faryab"
    ],
    "name:und_x_variant":[
        "Par\u012b\u0101b",
        "Far\u012b\u0101b"
    ],
    "wof:name":"Faryab",
    "wof:placetype":"locality"
},
  "geometry": {"coordinates":[57.08407,27.47507],"type":"Point"}
}