{
  "type": "Feature",
  "properties": {
    "gn:admin1_code":"15.0",
    "gn:asciiname":"Khatt or Ravvas",
    "gn:country_code":"IR",
    "gn:dem":24,
    "gn:feature_class":"P",
    "gn:feature_code":"PPL",
    "gn:name":"Kha\u0163\u0163 or Ravv\u0101s",
    "gn:population":0,
    "gn:timezone":"Asia/Tehran",
    "iso:country":"IR",
    "name:fas_x_preferred":[
        "\u0634\u0647\u0631\u06a9 \u0634\u0647\u06cc\u062f \u0628\u0647\u0634\u062a\u06cc"
    ],
    "name:fas_x_variant":[
        "Shahrak-e Shah\u012bd Behesht\u012b",
        "\u062e\u0637 \u0627\u0644\u0631\u0648\u0627\u0633",
        "\u062e\u064a\u0637 \u0627\u0644\u0631\u0648\u0627\u0633"
    ],
    "name:und_x_variant":[
        "Kha\u0163\u0163 ol Ravv\u0101s",
        "Seyyed\u012bn-e Seh",
        "Kh\u012b\u0163 ol Ravv\u0101s",
        "Kha\u0163\u0163 or Ravv\u0101s",
        "Shahrak Shah\u012bd Behesht\u012b"
    ],
    "wof:name":"Khatt or Ravvas",
    "wof:placetype":"locality"
},
  "geometry": {"coordinates":[48.79225,31.38489],"type":"Point"}
}