{
  "type": "Feature",
  "properties": {
    "gn:admin1_code":"8.0",
    "gn:asciiname":"Gireyli Gus",
    "gn:country_code":"IR",
    "gn:dem":1664,
    "gn:feature_class":"P",
    "gn:feature_code":"PPL",
    "gn:name":"G\u012breyl\u012b G\u016bs",
    "gn:population":0,
    "gn:timezone":"Asia/Tehran",
    "iso:country":"IR",
    "name:fas_x_preferred":[
        "\u06af\u06cc\u0631\u06cc\u0644\u06cc \u06af\u0648\u0633"
    ],
    "name:und_x_variant":[
        "G\u012breyl\u012b G\u016bs"
    ],
    "wof:name":"Gireyli Gus",
    "wof:placetype":"locality"
},
  "geometry": {"coordinates":[48.78225,37.47816],"type":"Point"}
}