{
  "type": "Feature",
  "properties": {
    "gn:admin1_code":"42.0",
    "gn:asciiname":"Sahebdad",
    "gn:country_code":"IR",
    "gn:dem":777,
    "gn:feature_class":"P",
    "gn:feature_code":"PPL",
    "gn:name":"\u015e\u0101\u1e29ebd\u0101d",
    "gn:population":0,
    "gn:timezone":"Asia/Tehran",
    "iso:country":"IR",
    "name:ceb_x_preferred":[
        "\u015e\u0101\u1e29ebd\u0101d"
    ],
    "name:fas_x_preferred":[
        "\u0635\u0627\u062d\u0628\u062f\u0627\u062f"
    ],
    "name:fas_x_variant":[
        "\u015e\u0101\u1e29ebd\u0101d",
        "\u0635\u0627\u062d\u0628\u200c\u062f\u0627\u062f"
    ],
    "name:swe_x_preferred":[
        "\u015e\u0101\u1e29ebd\u0101d"
    ],
    "name:urd_x_preferred":[
        "\u0633\u06c1\u06cc\u0628\u062f\u0627\u062f"
    ],
    "wof:name":"Sahebdad",
    "wof:placetype":"locality"
},
  "geometry": {"coordinates":[60.92289,35.13211],"type":"Point"}
}