{
  "type": "Feature",
  "properties": {
    "gn:admin1_code":"1.0",
    "gn:asciiname":"Bagerdan",
    "gn:country_code":"IR",
    "gn:dem":1488,
    "gn:feature_class":"P",
    "gn:feature_code":"PPL",
    "gn:name":"B\u0101gerd\u0101n",
    "gn:population":0,
    "gn:timezone":"Asia/Tehran",
    "iso:country":"IR",
    "name:fas_x_preferred":[
        "\u0628\u0627\u06af\u0631\u062f\u0627\u0646"
    ],
    "name:fas_x_variant":[
        "B\u0101gerd\u0101n"
    ],
    "wof:name":"Bagerdan",
    "wof:placetype":"locality"
},
  "geometry": {"coordinates":[45.5504,36.6086],"type":"Point"}
}