{
  "type": "Feature",
  "properties": {
    "gn:admin1_code":"23",
    "gn:asciiname":"Ardesi",
    "gn:country_code":"IR",
    "gn:dem":1637,
    "gn:feature_class":"P",
    "gn:feature_code":"PPL",
    "gn:name":"Ardes\u012b",
    "gn:population":0,
    "gn:timezone":"Asia/Tehran",
    "iso:country":"IR",
    "name:ara_x_preferred":[
        "\u0623\u0631\u062f\u0633\u064a"
    ],
    "name:fas_x_preferred":[
        "\u0627\u0631\u062f\u0633\u06cc"
    ],
    "name:fas_x_variant":[
        "Ardes\u012b"
    ],
    "wof:name":"Ardesi",
    "wof:placetype":"locality"
},
  "geometry": {"coordinates":[48.99614,33.17302],"type":"Point"}
}