{
  "type": "Feature",
  "properties": {
    "gn:admin1_code":"42.0",
    "gn:asciiname":"Hajji Aman",
    "gn:country_code":"IR",
    "gn:dem":779,
    "gn:feature_class":"P",
    "gn:feature_code":"PPL",
    "gn:name":"\u1e28\u0101jj\u012b Am\u0101n",
    "gn:population":0,
    "gn:timezone":"Asia/Tehran",
    "iso:country":"IR",
    "name:fas_x_preferred":[
        "\u062d\u0627\u062c\u06cc \u0627\u0645\u0627\u0646"
    ],
    "name:fas_x_variant":[
        "Sam\u012b\u2018\u0101b\u0101d-e \u1e28\u0101jj\u012b Am\u0101n",
        "\u1e28\u0101jj\u012b Am\u0101n"
    ],
    "wof:name":"Hajji Aman",
    "wof:placetype":"locality"
},
  "geometry": {"coordinates":[60.91852,35.13627],"type":"Point"}
}