{
  "type": "Feature",
  "properties": {
    "gn:admin1_code":"11",
    "gn:asciiname":"Deralavi",
    "gn:country_code":"IR",
    "gn:dem":1081,
    "gn:feature_class":"P",
    "gn:feature_code":"PPL",
    "gn:name":"Der\u0101lav\u012b",
    "gn:population":0,
    "gn:timezone":"Asia/Tehran",
    "iso:country":"IR",
    "name:ara_x_preferred":[
        "\u062f\u0631\u0627\u0644\u0648\u064a"
    ],
    "name:ceb_x_preferred":[
        "Der\u0101lav\u012b"
    ],
    "name:fas_x_preferred":[
        "\u062f\u0631\u0627\u0644\u0648\u06cc"
    ],
    "name:fas_x_variant":[
        "Der\u0101lav\u012b"
    ],
    "name:msa_x_preferred":[
        "Deralavi"
    ],
    "name:swe_x_preferred":[
        "Der\u0101lav\u012b"
    ],
    "wof:name":"Deralavi",
    "wof:placetype":"locality"
},
  "geometry": {"coordinates":[57.7681,26.4728],"type":"Point"}
}