{
  "type": "Feature",
  "properties": {
    "iso:country":"IR",
    "name:ara_x_preferred":[
        "\u0646\u0647\u0627\u0648\u0646\u062f"
    ],
    "name:arz_x_preferred":[
        "\u0646\u0647\u0627\u0648\u0646\u062f"
    ],
    "name:aze_x_preferred":[
        "Nahav\u0259nd"
    ],
    "name:bul_x_preferred":[
        "\u041d\u0430\u0445\u043e\u0432\u0430\u043d\u0434"
    ],
    "name:cat_x_preferred":[
        "Nihawand"
    ],
    "name:chi_x_preferred":[
        "\u7d0d\u54c8\u842c\u5fb7"
    ],
    "name:deu_x_preferred":[
        "Nahavand"
    ],
    "name:dut_x_preferred":[
        "Nahavand"
    ],
    "name:ell_x_preferred":[
        "\u039d\u03b1\u03c7\u03b1\u03b2\u03ac\u03bd\u03c4"
    ],
    "name:eng_x_preferred":[
        "Nahavand"
    ],
    "name:fas_x_preferred":[
        "\u0646\u0647\u0627\u0648\u0646\u062f"
    ],
    "name:fas_x_variant":[
        "Nah\u0101vand"
    ],
    "name:fra_x_preferred":[
        "Nahavand"
    ],
    "name:fre_x_preferred":[
        "Nahavand"
    ],
    "name:ger_x_preferred":[
        "Neh\u0101wand"
    ],
    "name:gre_x_preferred":[
        "\u0391\u03bd\u03c4\u03b9\u03cc\u03c7\u03b5\u03b9\u03b1"
    ],
    "name:hak_x_preferred":[
        "Nah\u0101vand"
    ],
    "name:hin_x_preferred":[
        "\u0928\u0939\u093e\u0935\u0902\u0926"
    ],
    "name:ita_x_preferred":[
        "Nahavand"
    ],
    "name:jpn_x_preferred":[
        "\u30cb\u30cf\u30fc\u30f4\u30a1\u30f3\u30c9"
    ],
    "name:kor_x_preferred":[
        "\ub098\ud558\ubc18\ub4dc"
    ],
    "name:lat_x_preferred":[
        "Nahavand"
    ],
    "name:may_x_preferred":[
        "Nahavand"
    ],
    "name:mlg_x_preferred":[
        "Nahavand"
    ],
    "name:nob_x_preferred":[
        "Nahavand"
    ],
    "name:nor_x_preferred":[
        "Nahavand"
    ],
    "name:per_x_preferred":[
        "\u0646\u0647\u0627\u0648\u0646\u062f"
    ],
    "name:pnb_x_preferred":[
        "\u0646\u0647\u0627\u0648\u0646\u062f"
    ],
    "name:pol_x_preferred":[
        "Nahawand"
    ],
    "name:ron_x_preferred":[
        "Nahavand"
    ],
    "name:rum_x_preferred":[
        "Nahavand"
    ],
    "name:rus_x_preferred":[
        "\u041d\u0435\u0445\u0430\u0432\u0435\u043d\u0434"
    ],
    "name:rus_x_variant":[
        "\u041d\u0430\u0433\u0430\u0432\u0430\u043d\u0434\u0435"
    ],
    "name:swe_x_preferred":[
        "Nahavand"
    ],
    "name:tgk_x_preferred":[
        "\u041d\u0430\u04b3\u043e\u0432\u0430\u043d\u0434"
    ],
    "name:tur_x_preferred":[
        "Nihavend"
    ],
    "name:unk_x_variant":[
        "Neh\u0101vend"
    ],
    "name:urd_x_preferred":[
        "\u0646\u06c1\u0627\u0648\u0646\u062f"
    ],
    "name:zho_x_preferred":[
        "\u7d0d\u54c8\u842c\u5fb7"
    ],
    "qs:gn_country":"IR",
    "qs:gn_fcode":"PPL",
    "qs:gn_pop":76250,
    "qs:name":"Nahavand",
    "qs:name_adm0":"Iran",
    "qs:name_adm1":"Hamadan",
    "qs:photos":0,
    "qs:photos_1k":0,
    "qs:photos_9k":1,
    "qs:photos_9r":1,
    "qs:photos_all":1,
    "qs:photos_sr":0,
    "qs:placetype":"Town",
    "qs:pop_sr":"8",
    "qs:woe_adm0":23424851,
    "wd:wordcount":491,
    "wof:name":"Nahavand",
    "wof:placetype":"locality",
    "wof:population":76250
},
  "geometry": {"coordinates":[48.377,34.1885],"type":"Point"}
}