{
  "type": "Feature",
  "properties": {
    "gn:admin1_code":"4.0",
    "gn:asciiname":"Deh-e Fakhireh",
    "gn:country_code":"IR",
    "gn:dem":482,
    "gn:feature_class":"P",
    "gn:feature_code":"PPL",
    "gn:name":"Deh-e Fakh\u012breh",
    "gn:population":0,
    "gn:timezone":"Asia/Tehran",
    "iso:country":"IR",
    "name:fas_x_preferred":[
        "\u062f\u0647 \u0641\u062e\u06cc\u0631\u0647"
    ],
    "name:fas_x_variant":[
        "Fakh\u012breh-ye P\u0101\u2019\u012bn",
        "Deh-e Fakh\u012breh",
        "\u0641\u062e\u06cc\u0631\u0647 \u0633\u0641\u0644\u06cc"
    ],
    "name:und_x_variant":[
        "Fakh\u012breh-ye Sofl\u00e1"
    ],
    "wof:name":"Deh-e Fakhireh",
    "wof:placetype":"locality"
},
  "geometry": {"coordinates":[61.7312,31.0988],"type":"Point"}
}