{
  "type": "Feature",
  "properties": {
    "gn:admin1_code":"37",
    "gn:asciiname":"Yesaqi",
    "gn:country_code":"IR",
    "gn:dem":0,
    "gn:feature_class":"P",
    "gn:feature_code":"PPL",
    "gn:name":"Yes\u0101q\u012b",
    "gn:population":0,
    "gn:timezone":"Asia/Tehran",
    "iso:country":"IR",
    "name:fas_x_preferred":[
        "Yes\u0101q\u012b"
    ],
    "name:fas_x_variant":[
        "\u064a\u0633\u0627\u0642\u06cc"
    ],
    "name:und_x_variant":[
        "\u064a\u0633\u0627\u0642\u06cc"
    ],
    "wof:name":"Yesaqi",
    "wof:placetype":"locality"
},
  "geometry": {"coordinates":[54.24217,36.82925],"type":"Point"}
}