{
  "type": "Feature",
  "properties": {
    "gn:admin1_code":"15",
    "gn:asciiname":"Sar Masjed",
    "gn:country_code":"IR",
    "gn:dem":429,
    "gn:feature_class":"P",
    "gn:feature_code":"PPL",
    "gn:name":"Sar Masjed",
    "gn:population":0,
    "gn:timezone":"Asia/Tehran",
    "iso:country":"IR",
    "name:fas_x_preferred":[
        "\u0633\u0631\u0645\u0686"
    ],
    "name:fas_x_variant":[
        "\u0633\u0631 \u0645\u0633\u062c\u062f"
    ],
    "name:und_x_variant":[
        "Sarmach",
        "Sar Masjed"
    ],
    "wof:name":"Sar Masjed",
    "wof:placetype":"locality"
},
  "geometry": {"coordinates":[49.18613,32.28761],"type":"Point"}
}