{
  "type": "Feature",
  "properties": {
    "gn:admin1_code":"29",
    "gn:asciiname":"Sar Ta`avoneh",
    "gn:country_code":"IR",
    "gn:dem":1790,
    "gn:feature_class":"P",
    "gn:feature_code":"PPL",
    "gn:name":"Sar Ta\u2018\u0101voneh",
    "gn:population":0,
    "gn:timezone":"Asia/Tehran",
    "iso:country":"IR",
    "name:fas_x_preferred":[
        "Sar \u0162\u0101h\u016b\u2019\u012byeh"
    ],
    "name:fas_x_variant":[
        "\u0633\u0631 \u062a\u0639\u0627\u0648\u0646\u0647",
        "Sar \u0162\u0101veneh",
        "Sar Ta\u2018\u0101voneh"
    ],
    "wof:name":"Sar Ta`avoneh",
    "wof:placetype":"locality"
},
  "geometry": {"coordinates":[57.32677,30.48623],"type":"Point"}
}