{
  "type": "Feature",
  "properties": {
    "gn:admin1_code":"40",
    "gn:asciiname":"Zabar Kuh",
    "gn:country_code":"IR",
    "gn:dem":1274,
    "gn:feature_class":"P",
    "gn:feature_code":"PPL",
    "gn:name":"Zabar K\u016bh",
    "gn:population":0,
    "gn:timezone":"Asia/Tehran",
    "iso:country":"IR",
    "name:fas_x_preferred":[
        "Z\u012br K\u016bh"
    ],
    "name:fas_x_variant":[
        "Zabar K\u016bh",
        "\u0632\u0628\u0631 \u06a9\u0648\u0647"
    ],
    "name:und_x_variant":[
        "Zabar K\u016bh",
        "Zir Kooh",
        "\u0632\u0628\u0631 \u06a9\u0648\u0647"
    ],
    "wof:name":"Zabar Kuh",
    "wof:placetype":"locality"
},
  "geometry": {"coordinates":[57.43531,34.89296],"type":"Point"}
}