{
  "type": "Feature",
  "properties": {
    "gn:admin1_code":"30",
    "gn:asciiname":"Ark",
    "gn:country_code":"IR",
    "gn:dem":983,
    "gn:feature_class":"P",
    "gn:feature_code":"PPL",
    "gn:name":"Ark",
    "gn:population":0,
    "gn:timezone":"Asia/Tehran",
    "iso:country":"IR",
    "name:afr_x_preferred":[
        "Ark"
    ],
    "name:ceb_x_preferred":[
        "Ark"
    ],
    "name:ces_x_preferred":[
        "Ark"
    ],
    "name:dan_x_preferred":[
        "Ark"
    ],
    "name:deu_x_preferred":[
        "Ark"
    ],
    "name:ell_x_preferred":[
        "Ark"
    ],
    "name:nld_x_preferred":[
        "Ark"
    ],
    "name:nor_x_preferred":[
        "Ark"
    ],
    "name:pol_x_preferred":[
        "Ark"
    ],
    "name:por_x_preferred":[
        "Ark"
    ],
    "name:rus_x_preferred":[
        "Ark"
    ],
    "name:swe_x_preferred":[
        "Ark"
    ],
    "wof:name":"Ark",
    "wof:placetype":"locality"
},
  "geometry": {"coordinates":[57.00471999999999,37.075],"type":"Point"}
}