{
  "type": "Feature",
  "properties": {
    "gn:admin1_code":"30",
    "gn:asciiname":"Ark",
    "gn:country_code":"IR",
    "gn:dem":983,
    "gn:feature_class":"P",
    "gn:feature_code":"PPL",
    "gn:name":"Ark",
    "gn:population":0,
    "gn:timezone":"Asia/Tehran",
    "iso:country":"IR",
    "wof:name":"Ark",
    "wof:placetype":"locality"
},
  "geometry": {"coordinates":[57.00471999999999,37.075],"type":"Point"}
}