{
  "type": "Feature",
  "properties": {
    "gn:admin1_code":"26.0",
    "gn:asciiname":"Qal`eh Bashi-ye Rezakand",
    "gn:country_code":"IR",
    "gn:dem":1125,
    "gn:feature_class":"P",
    "gn:feature_code":"PPL",
    "gn:name":"Qal\u2018eh B\u0101sh\u012b-ye Re\u1e95\u0101kand",
    "gn:population":0,
    "gn:timezone":"Asia/Tehran",
    "iso:country":"IR",
    "name:fas_x_preferred":[
        "\u0642\u0644\u0639\u0647 \u0628\u0627\u0634\u06cc \u0631\u0636\u0627\u06a9\u0646\u062f"
    ],
    "name:fas_x_variant":[
        "Qal\u2018eh B\u0101sh\u012b-ye Re\u1e95\u0101kand"
    ],
    "wof:name":"Qal`eh Bashi-ye Rezakand",
    "wof:placetype":"locality"
},
  "geometry": {"coordinates":[51.0939,35.6328],"type":"Point"}
}