{
  "type": "Feature",
  "properties": {
    "gn:admin1_code":"4",
    "gn:asciiname":"Sarandukani",
    "gn:country_code":"IR",
    "gn:dem":1524,
    "gn:feature_class":"P",
    "gn:feature_code":"PPL",
    "gn:name":"Sarand\u016bk\u0101n\u012b",
    "gn:population":0,
    "gn:timezone":"Asia/Tehran",
    "iso:country":"IR",
    "name:fas_x_preferred":[
        "\u0633\u0631\u0646\u062f\u0648\u06a9\u0627\u0646\u06cc"
    ],
    "name:fas_x_variant":[
        "Sarand\u016bk\u0101n\u012b"
    ],
    "wof:name":"Sarandukani",
    "wof:placetype":"locality"
},
  "geometry": {"coordinates":[60.982,28.2851],"type":"Point"}
}