{
  "type": "Feature",
  "properties": {
    "gn:admin1_code":"33",
    "gn:asciiname":"Tokhtameshlu",
    "gn:country_code":"IR",
    "gn:dem":1729,
    "gn:feature_class":"P",
    "gn:feature_code":"PPL",
    "gn:name":"Tokhtameshl\u016b",
    "gn:population":0,
    "gn:timezone":"Asia/Tehran",
    "iso:country":"IR",
    "name:fas_x_preferred":[
        "\u062a\u062e\u062a\u0645\u0634\u0644\u0648"
    ],
    "name:fas_x_variant":[
        "Tokhtamoshl\u016b",
        "\u062a\u062e\u062a\u0645\u06cc\u0634\u0644\u0648"
    ],
    "name:msa_x_preferred":[
        "Tokhtamishlu"
    ],
    "name:und_x_variant":[
        "Tokhtamush",
        "Tokhtameshl\u016b",
        "T\u016bkhd\u0101mesh",
        "Tokhtam\u012bshl\u016b"
    ],
    "wof:name":"Tokhtameshlu",
    "wof:placetype":"locality"
},
  "geometry": {"coordinates":[48.09291,37.30701],"type":"Point"}
}