{
  "type": "Feature",
  "properties": {
    "gn:admin1_code":"37.0",
    "gn:asciiname":"Hivehchi-ye Bala",
    "gn:country_code":"IR",
    "gn:dem":50,
    "gn:feature_class":"P",
    "gn:feature_code":"PPL",
    "gn:name":"H\u012bvehch\u012b-ye B\u0101l\u0101",
    "gn:population":0,
    "gn:timezone":"Asia/Tehran",
    "iso:country":"IR",
    "name:ara_x_preferred":[
        "\u0647\u064a\u0648\u0647\u062a\u0634\u064a \u0628\u0627\u0644\u0627"
    ],
    "name:fas_x_preferred":[
        "Kh\u012bvehch\u012b-ye \u2018Oly\u0101"
    ],
    "name:fas_x_variant":[
        "\u0647\u06cc\u0648\u0647 \u0686\u06cc \u0628\u0627\u0644\u0627",
        "\u062e\u064a\u062f\u0647 \u0686\u06cc",
        "\u0647\u06cc\u0648\u0647\u200c\u0686\u06cc \u0628\u0627\u0644\u0627"
    ],
    "name:msa_x_preferred":[
        "Hivehchi-ye Bala"
    ],
    "name:und_x_variant":[
        "H\u012bvehch\u012b-ye B\u0101l\u0101",
        "Kheyvehch\u012b",
        "Kheydehch\u012b"
    ],
    "wof:name":"Hivehchi-ye Bala",
    "wof:placetype":"locality"
},
  "geometry": {"coordinates":[55.06921,37.14942],"type":"Point"}
}