{
  "type": "Feature",
  "properties": {
    "gn:admin1_code":"7",
    "gn:asciiname":"Tang-e Jashiri",
    "gn:country_code":"IR",
    "gn:dem":2177,
    "gn:feature_class":"P",
    "gn:feature_code":"PPL",
    "gn:name":"Tang-e J\u0101sh\u012br\u012b",
    "gn:population":0,
    "gn:timezone":"Asia/Tehran",
    "iso:country":"IR",
    "name:fas_x_preferred":[
        "Tang-e J\u0101sh\u012br\u012b"
    ],
    "wof:name":"Tang-e Jashiri",
    "wof:placetype":"locality"
},
  "geometry": {"coordinates":[52.33306,30.65639],"type":"Point"}
}