{
  "type": "Feature",
  "properties": {
    "gn:admin1_code":"0",
    "gn:asciiname":"Amrani",
    "gn:country_code":"IR",
    "gn:dem":782,
    "gn:feature_class":"P",
    "gn:feature_code":"PPL",
    "gn:name":"Amr\u0101n\u012b",
    "gn:population":0,
    "gn:timezone":"Asia/Tehran",
    "iso:country":"IR",
    "name:fas_x_preferred":[
        "\u0627\u0645\u0631\u0627\u0646\u06cc"
    ],
    "name:fas_x_variant":[
        "Amr\u0101n\u012b"
    ],
    "wof:name":"Amrani",
    "wof:placetype":"locality"
},
  "geometry": {"coordinates":[57.5673,27.6988],"type":"Point"}
}