{
  "type": "Feature",
  "properties": {
    "gn:admin1_code":"22",
    "gn:asciiname":"Mal-e Kharg-e Shomali",
    "gn:country_code":"IR",
    "gn:dem":27,
    "gn:feature_class":"P",
    "gn:feature_code":"PPL",
    "gn:name":"Mal-e Kharg-e Shom\u0101l\u012b",
    "gn:population":0,
    "gn:timezone":"Asia/Tehran",
    "iso:country":"IR",
    "name:ara_x_preferred":[
        "\u0645\u0644\u200c\u062e\u0631\u0643 \u0634\u0645\u0627\u0644\u064a"
    ],
    "name:fas_x_preferred":[
        "\u0645\u064e\u0644\u064e\u0643\u0650\u0647"
    ],
    "name:fas_x_variant":[
        "\u0645\u064f\u0644\u0650 \u062e\u064e\u0631\u06af",
        "\u0645\u064e\u0644 \u062e\u064e\u0631\u06af",
        "\u0645\u0644\u062e\u0631\u06af \u0634\u0645\u0627\u0644\u06cc",
        "\u0645\u064e\u0644\u0650 \u062e\u064e\u0631\u06af",
        "\u0645\u0644 \u062e\u0631",
        "\u0645\u0644\u200c\u062e\u0631\u06a9 \u0634\u0645\u0627\u0644\u06cc"
    ],
    "name:msa_x_preferred":[
        "Mal-e Kharg-e Shemali"
    ],
    "name:und_x_variant":[
        "Mol-e Kharg",
        "Mal Kharg",
        "Mal-e Kharg-e Shem\u0101l\u012b",
        "Mal-e Kharg",
        "Mal-e Kharg- Jan\u016bb\u012b",
        "Malakeh",
        "Mal-e Khar",
        "Mal-e Kharg-e Shom\u0101l\u012b"
    ],
    "wof:name":"Mal-e Kharg-e Shomali",
    "wof:placetype":"locality"
},
  "geometry": {"coordinates":[51.9355,27.9673],"type":"Point"}
}