{
  "type": "Feature",
  "properties": {
    "gn:admin1_code":"5",
    "gn:asciiname":"Darreh Ney",
    "gn:country_code":"IR",
    "gn:dem":529,
    "gn:feature_class":"P",
    "gn:feature_code":"PPL",
    "gn:name":"Darreh Ney",
    "gn:population":0,
    "gn:timezone":"Asia/Tehran",
    "iso:country":"IR",
    "name:fas_x_preferred":[
        "\u062f\u064e\u0631\u0650\u0651\u0647 \u0646\u0650\u06cc"
    ],
    "name:fas_x_variant":[
        "\u062f\u0631\u0647 \u0646\u06cc"
    ],
    "wof:name":"Darreh Ney",
    "wof:placetype":"locality"
},
  "geometry": {"coordinates":[50.54722,30.43361],"type":"Point"}
}