{
  "type": "Feature",
  "properties": {
    "gn:admin1_code":"33.0",
    "gn:asciiname":"Ammand",
    "gn:country_code":"IR",
    "gn:dem":1487,
    "gn:feature_class":"P",
    "gn:feature_code":"PPL",
    "gn:name":"Ammand",
    "gn:population":0,
    "gn:timezone":"Asia/Tehran",
    "iso:country":"IR",
    "name:fas_x_preferred":[
        "\u0627\u0645\u0651\u0646\u062f"
    ],
    "name:und_x_variant":[
        "Emmend",
        "Amand",
        "Ammend",
        "Ammand"
    ],
    "wof:name":"Ammand",
    "wof:placetype":"locality"
},
  "geometry": {"coordinates":[46.15954,38.23235],"type":"Point"}
}