{
  "type": "Feature",
  "properties": {
    "gn:admin1_code":"35",
    "gn:asciiname":"Sulin",
    "gn:country_code":"IR",
    "gn:dem":1395,
    "gn:feature_class":"P",
    "gn:feature_code":"PPL",
    "gn:name":"S\u016bl\u012bn",
    "gn:population":0,
    "gn:timezone":"Asia/Tehran",
    "iso:country":"IR",
    "name:fas_x_preferred":[
        "\u0633\u0648\u0644\u064a\u0646"
    ],
    "name:fas_x_variant":[
        "S\u016bl\u012bn"
    ],
    "name:fra_x_preferred":[
        "Sulin"
    ],
    "name:pol_x_preferred":[
        "Sulin"
    ],
    "name:ukr_x_preferred":[
        "\u0421\u0443\u043b\u0456\u043d"
    ],
    "wof:name":"Sulin",
    "wof:placetype":"locality"
},
  "geometry": {"coordinates":[52.97961,35.92395],"type":"Point"}
}