{
  "type": "Feature",
  "properties": {
    "gn:admin1_code":"4",
    "gn:asciiname":"Now Kaju",
    "gn:country_code":"IR",
    "gn:dem":1317,
    "gn:feature_class":"P",
    "gn:feature_code":"PPL",
    "gn:name":"Now Kaj\u016b",
    "gn:population":0,
    "gn:timezone":"Asia/Tehran",
    "iso:country":"IR",
    "name:fas_x_preferred":[
        "\u0646\u0648 \u06a9\u062c\u0648"
    ],
    "name:fas_x_variant":[
        "Now Kaj\u016b"
    ],
    "wof:name":"Now Kaju",
    "wof:placetype":"locality"
},
  "geometry": {"coordinates":[61.4493,28.33211],"type":"Point"}
}