{
  "type": "Feature",
  "properties": {
    "gn:admin1_code":"16",
    "gn:asciiname":"Mudi",
    "gn:country_code":"IR",
    "gn:dem":2270,
    "gn:feature_class":"P",
    "gn:feature_code":"PPL",
    "gn:name":"M\u016bd\u012b",
    "gn:population":0,
    "gn:timezone":"Asia/Tehran",
    "iso:country":"IR",
    "name:fas_x_preferred":[
        "\u0645\u0648\u062f\u06cc"
    ],
    "name:fas_x_variant":[
        "M\u016bd\u012b"
    ],
    "wof:name":"Mudi",
    "wof:placetype":"locality"
},
  "geometry": {"coordinates":[46.81354,36.04674],"type":"Point"}
}