{
  "type": "Feature",
  "properties": {
    "gn:admin1_code":"43.0",
    "gn:asciiname":"Baba Qodrat",
    "gn:country_code":"IR",
    "gn:dem":1477,
    "gn:feature_class":"P",
    "gn:feature_code":"PPL",
    "gn:name":"B\u0101b\u0101 Qodrat",
    "gn:population":0,
    "gn:timezone":"Asia/Tehran",
    "iso:country":"IR",
    "name:fas_x_preferred":[
        "B\u0101b\u0101 Qodrat"
    ],
    "name:fas_x_variant":[
        "\u0628\u0627\u0628\u0627 \u0642\u062f\u0631\u062a"
    ],
    "name:und_x_variant":[
        "Em\u0101mz\u0101deh B\u0101b\u0101 Qodrat",
        "\u0628\u0627\u0628\u0627 \u0642\u062f\u0631\u062a"
    ],
    "wof:name":"Baba Qodrat",
    "wof:placetype":"locality"
},
  "geometry": {"coordinates":[57.73642,36.92772],"type":"Point"}
}