{
  "type": "Feature",
  "properties": {
    "gn:admin1_code":"13",
    "gn:asciiname":"Shirazi-ye Tatlan",
    "gn:country_code":"IR",
    "gn:dem":1221,
    "gn:feature_class":"P",
    "gn:feature_code":"PPL",
    "gn:name":"Sh\u012br\u0101z\u012b-ye \u0162atl\u0101n",
    "gn:population":0,
    "gn:timezone":"Asia/Tehran",
    "iso:country":"IR",
    "name:fas_x_preferred":[
        "\u0634\u06cc\u0631\u0627\u0632\u06cc \u0637\u062a\u0644\u0627\u0646"
    ],
    "name:fas_x_variant":[
        "Sh\u012br\u0101z\u012b-ye \u0162atl\u0101n"
    ],
    "wof:name":"Shirazi-ye Tatlan",
    "wof:placetype":"locality"
},
  "geometry": {"coordinates":[47.4041,34.1283],"type":"Point"}
}