{
  "type": "Feature",
  "properties": {
    "gn:admin1_code":"32.0",
    "gn:asciiname":"Qal'eh-ye Barzand",
    "gn:country_code":"IR",
    "gn:dem":948,
    "gn:feature_class":"P",
    "gn:feature_code":"PPL",
    "gn:name":"Qal\u2019eh-ye Barzand",
    "gn:population":0,
    "gn:timezone":"Asia/Tehran",
    "iso:country":"IR",
    "wof:name":"Qal'eh-ye Barzand",
    "wof:placetype":"locality"
},
  "geometry": {"coordinates":[47.87333,39.00611],"type":"Point"}
}