{
  "type": "Feature",
  "properties": {
    "gn:admin1_code":"23",
    "gn:asciiname":"Qalavardin",
    "gn:country_code":"IR",
    "gn:dem":2124,
    "gn:feature_class":"P",
    "gn:feature_code":"PPL",
    "gn:name":"Qal\u0101vard\u012bn",
    "gn:population":0,
    "gn:timezone":"Asia/Tehran",
    "iso:country":"IR",
    "name:fas_x_preferred":[
        "\u0642\u064e\u0644\u0627\u0648\u064e\u0631\u062f\u064a\u0631"
    ],
    "name:fas_x_variant":[
        "Qal\u0101vard\u012br",
        "Qal\u2018eh Bard\u012b",
        "\u0642\u0644\u0639\u0647 \u0628\u0631\u062f\u06cc",
        "\u0642\u0644\u0627\u0648\u0631\u062f\u06cc\u0646"
    ],
    "name:und_x_variant":[
        "Ghal\u2018eh Bardi",
        "Qal\u0101vard\u012bn"
    ],
    "wof:name":"Qalavardin",
    "wof:placetype":"locality"
},
  "geometry": {"coordinates":[49.62796,33.35346],"type":"Point"}
}