{
  "type": "Feature",
  "properties": {
    "gn:admin1_code":"1",
    "gn:asciiname":"Galik",
    "gn:country_code":"IR",
    "gn:dem":2669,
    "gn:feature_class":"P",
    "gn:feature_code":"PPL",
    "gn:name":"G\u0101l\u012bk",
    "gn:population":0,
    "gn:timezone":"Asia/Tehran",
    "iso:country":"IR",
    "name:fas_x_preferred":[
        "G\u0101l\u012bk"
    ],
    "wof:name":"Galik",
    "wof:placetype":"locality"
},
  "geometry": {"coordinates":[44.33333,38.01667],"type":"Point"}
}