{
  "type": "Feature",
  "properties": {
    "gn:admin1_code":"13",
    "gn:asciiname":"Qeytag",
    "gn:country_code":"IR",
    "gn:dem":595,
    "gn:feature_class":"P",
    "gn:feature_code":"PPL",
    "gn:name":"Qey\u0163ag",
    "gn:population":0,
    "gn:timezone":"Asia/Tehran",
    "iso:country":"IR",
    "name:fas_x_preferred":[
        "\u0642\u06cc\u0637\u06af"
    ],
    "name:fas_x_variant":[
        "Qey\u0163ak",
        "Qey\u0163ag"
    ],
    "wof:name":"Qeytag",
    "wof:placetype":"locality"
},
  "geometry": {"coordinates":[45.86871,34.42181],"type":"Point"}
}