{
  "type": "Feature",
  "properties": {
    "gn:admin1_code":"42",
    "gn:asciiname":"Eshaqabad",
    "gn:country_code":"IR",
    "gn:dem":1178,
    "gn:feature_class":"P",
    "gn:feature_code":"PPL",
    "gn:name":"Es\u1e29\u0101q\u0101b\u0101d",
    "gn:population":0,
    "gn:timezone":"Asia/Tehran",
    "iso:country":"IR",
    "name:fas_x_preferred":[
        "\u062c\u0646\u062a \u0622\u0628\u0627\u062f"
    ],
    "name:fas_x_variant":[
        "Jannat\u0101b\u0101d",
        "\u0627\u0633\u062d\u0627\u0642 \u0622\u0628\u0627\u062f",
        "\u0627\u0633\u062d\u0642\u200c\u0622\u0628\u0627\u062f"
    ],
    "name:und_x_variant":[
        "Es\u1e29\u0101q\u0101b\u0101d"
    ],
    "wof:name":"Eshaqabad",
    "wof:placetype":"locality"
},
  "geometry": {"coordinates":[58.97548000000001,35.98281],"type":"Point"}
}