{
  "type": "Feature",
  "properties": {
    "gn:admin1_code":"42",
    "gn:asciiname":"Mehrabad",
    "gn:country_code":"IR",
    "gn:dem":1083,
    "gn:feature_class":"P",
    "gn:feature_code":"PPL",
    "gn:name":"Mehr\u0101b\u0101d",
    "gn:population":0,
    "gn:timezone":"Asia/Tehran",
    "iso:country":"IR",
    "name:ara_x_preferred":[
        "\u0645\u0647\u0631\u0622\u0628\u0627\u062f"
    ],
    "name:fas_x_preferred":[
        "\u0645\u0647\u0631 \u0622\u0628\u0627\u062f"
    ],
    "name:fas_x_variant":[
        "Mehr\u0101b\u0101d",
        "\u0645\u0647\u0631\u0622\u0628\u0627\u062f"
    ],
    "wof:name":"Mehrabad",
    "wof:placetype":"locality"
},
  "geometry": {"coordinates":[59.30799,36.59064],"type":"Point"}
}