{
  "type": "Feature",
  "properties": {
    "gn:admin1_code":"42",
    "gn:asciiname":"Qal`eh Sharaf",
    "gn:country_code":"IR",
    "gn:dem":1577,
    "gn:feature_class":"P",
    "gn:feature_code":"PPL",
    "gn:name":"Qal\u2018eh Sharaf",
    "gn:population":0,
    "gn:timezone":"Asia/Tehran",
    "iso:country":"IR",
    "name:fas_x_preferred":[
        "Qal\u2018eh Sharaf"
    ],
    "name:fas_x_variant":[
        "\u0642\u0644\u0639\u0647 \u0634\u0631\u0641"
    ],
    "name:und_x_variant":[
        "\u0642\u0644\u0639\u0647 \u0634\u0631\u0641"
    ],
    "wof:name":"Qal`eh Sharaf",
    "wof:placetype":"locality"
},
  "geometry": {"coordinates":[58.61818,37.25109000000001],"type":"Point"}
}