{
  "type": "Feature",
  "properties": {
    "gn:admin1_code":"29.0",
    "gn:asciiname":"Bab Gorg",
    "gn:country_code":"IR",
    "gn:dem":2951,
    "gn:feature_class":"P",
    "gn:feature_code":"PPL",
    "gn:name":"B\u0101b Gorg",
    "gn:population":0,
    "gn:timezone":"Asia/Tehran",
    "iso:country":"IR",
    "name:ceb_x_preferred":[
        "B\u0101b Gorg"
    ],
    "name:fas_x_preferred":[
        "\u0628\u0627\u0628 \u06af\u0631\u06af"
    ],
    "name:fas_x_variant":[
        "B\u0101b Gorg\u012b",
        "B\u0101b Gorg",
        "\u0628\u0627\u0628\u06af\u0631\u06af"
    ],
    "name:swe_x_preferred":[
        "B\u0101b Gorg"
    ],
    "wof:name":"Bab Gorg",
    "wof:placetype":"locality"
},
  "geometry": {"coordinates":[57.5499,29.1199],"type":"Point"}
}