{
  "type": "Feature",
  "properties": {
    "gn:admin1_code":"8",
    "gn:asciiname":"Mishkeh",
    "gn:country_code":"IR",
    "gn:dem":374,
    "gn:feature_class":"P",
    "gn:feature_code":"PPL",
    "gn:name":"M\u012bshkeh",
    "gn:population":0,
    "gn:timezone":"Asia/Tehran",
    "iso:country":"IR",
    "name:ara_x_preferred":[
        "\u0645\u064a\u0634\u0643\u0647"
    ],
    "name:fas_x_preferred":[
        "\u0645\u06cc\u0634\u06a9\u0647"
    ],
    "name:fas_x_variant":[
        "M\u012bshkeh",
        "M\u012bsheh",
        "\u0645\u06cc\u0634\u0647"
    ],
    "name:msa_x_preferred":[
        "Mishkeh"
    ],
    "name:ukr_x_preferred":[
        "\u041c\u0456\u0448\u043a\u0435"
    ],
    "wof:name":"Mishkeh",
    "wof:placetype":"locality"
},
  "geometry": {"coordinates":[49.10511,37.23224],"type":"Point"}
}