{
  "type": "Feature",
  "properties": {
    "gn:admin1_code":"35.0",
    "gn:asciiname":"Yektasara",
    "gn:country_code":"IR",
    "gn:dem":-2,
    "gn:feature_class":"P",
    "gn:feature_code":"PPL",
    "gn:name":"Yekt\u0101sar\u0101",
    "gn:population":0,
    "gn:timezone":"Asia/Tehran",
    "iso:country":"IR",
    "name:fas_x_preferred":[
        "Banjk\u016bl-e B\u0101l\u0101"
    ],
    "name:fas_x_variant":[
        "Benchk\u016bl-e B\u0101l\u0101",
        "\u0628\u0646\u0686\u06a9\u0648\u0644 \u0628\u0627\u0644\u0627",
        "\u06cc\u06a9\u062a\u0627\u0633\u0631\u0627"
    ],
    "name:und_x_variant":[
        "Yekt\u0101sar\u0101"
    ],
    "wof:name":"Yektasara",
    "wof:placetype":"locality"
},
  "geometry": {"coordinates":[51.91978,36.56063],"type":"Point"}
}