{
  "type": "Feature",
  "properties": {
    "gn:admin1_code":"1.0",
    "gn:asciiname":"Guranabad",
    "gn:country_code":"IR",
    "gn:dem":1259,
    "gn:feature_class":"P",
    "gn:feature_code":"PPL",
    "gn:name":"G\u016br\u0101n\u0101b\u0101d",
    "gn:population":0,
    "gn:timezone":"Asia/Tehran",
    "iso:country":"IR",
    "name:fas_x_preferred":[
        "\u06af\u0648\u0631\u0627\u0646 \u0622\u0628\u0627\u062f"
    ],
    "name:fas_x_variant":[
        "G\u016br\u0101n\u0101b\u0101d"
    ],
    "wof:name":"Guranabad",
    "wof:placetype":"locality"
},
  "geometry": {"coordinates":[45.4096,36.3568],"type":"Point"}
}