{
  "type": "Feature",
  "properties": {
    "gn:admin1_code":"29",
    "gn:asciiname":"Ahru'iyeh",
    "gn:country_code":"IR",
    "gn:dem":2551,
    "gn:feature_class":"P",
    "gn:feature_code":"PPL",
    "gn:name":"Ahr\u016b\u2019\u012byeh",
    "gn:population":0,
    "gn:timezone":"Asia/Tehran",
    "iso:country":"IR",
    "name:fas_x_preferred":[
        "\u0627\u0647\u0631\u0648\u0626\u06cc\u0647"
    ],
    "name:fas_x_variant":[
        "Ahr\u016b\u2019\u012byeh"
    ],
    "wof:name":"Ahru'iyeh",
    "wof:placetype":"locality"
},
  "geometry": {"coordinates":[56.6702,29.5512],"type":"Point"}
}