{
  "type": "Feature",
  "properties": {
    "gn:admin1_code":"9",
    "gn:asciiname":"Senaj",
    "gn:country_code":"IR",
    "gn:dem":1643,
    "gn:feature_class":"P",
    "gn:feature_code":"PPL",
    "gn:name":"Sen\u0101j",
    "gn:population":0,
    "gn:timezone":"Asia/Tehran",
    "iso:country":"IR",
    "name:fas_x_preferred":[
        "\u0633\u0646\u0627\u062c"
    ],
    "name:fas_x_variant":[
        "Sen\u0101j",
        "San\u0101j"
    ],
    "name:und_x_variant":[
        "Sin\u0101j"
    ],
    "wof:name":"Senaj",
    "wof:placetype":"locality"
},
  "geometry": {"coordinates":[49.02546,35.1222],"type":"Point"}
}