{
  "type": "Feature",
  "properties": {
    "gn:admin1_code":"4.0",
    "gn:asciiname":"Tudak",
    "gn:country_code":"IR",
    "gn:dem":1638,
    "gn:feature_class":"P",
    "gn:feature_code":"PPL",
    "gn:name":"T\u016bdak",
    "gn:population":0,
    "gn:timezone":"Asia/Tehran",
    "iso:country":"IR",
    "name:fas_x_preferred":[
        "\u062a\u0648\u062f\u06a9"
    ],
    "name:fas_x_variant":[
        "Taq\u012b\u0101b\u0101d",
        "T\u016bdak"
    ],
    "name:und_x_variant":[
        "Toodak"
    ],
    "wof:name":"Tudak",
    "wof:placetype":"locality"
},
  "geometry": {"coordinates":[60.834,28.4523],"type":"Point"}
}