{
  "type": "Feature",
  "properties": {
    "gn:admin1_code":"23",
    "gn:asciiname":"Dehnow Ali Gar",
    "gn:country_code":"IR",
    "gn:dem":2258,
    "gn:feature_class":"P",
    "gn:feature_code":"PPL",
    "gn:name":"Dehnow \u0100l\u012b Gar",
    "gn:population":0,
    "gn:timezone":"Asia/Tehran",
    "iso:country":"IR",
    "name:ara_x_preferred":[
        "\u062f\u0647 \u0646\u0648\u0627\u0644\u064a\u063a\u0631"
    ],
    "name:ceb_x_preferred":[
        "Dehnow Al\u012bgar"
    ],
    "name:fas_x_preferred":[
        "Dehnow Al\u012bgar"
    ],
    "name:fas_x_variant":[
        "\u062f\u0650\u0647 \u0646\u064f\u0648",
        "\u062f\u0647\u0646\u0648 \u0627\u0644\u064a\u06af\u0631",
        "\u062f\u0647 \u0646\u0648 \u0622\u0644\u06cc \u06af\u0631",
        "\u062f\u0647 \u062f\u0644\u0627\u06a9\u0627\u0646",
        "\u062f\u0647 \u0646\u0648\u0627\u0644\u06cc\u06af\u0631"
    ],
    "name:swe_x_preferred":[
        "Dehnow Al\u012bgar"
    ],
    "name:und_x_variant":[
        "\u062f\u0647\u0646\u0648 \u0627\u0644\u064a\u06af\u0631",
        "Deh Now",
        "Dehnow \u0100l\u012b Gar",
        "Deh-e Dal\u0101k\u0101n"
    ],
    "wof:name":"Dehnow Ali Gar",
    "wof:placetype":"locality"
},
  "geometry": {"coordinates":[49.57583,33.2157],"type":"Point"}
}