{
  "type": "Feature",
  "properties": {
    "gn:admin1_code":"11",
    "gn:asciiname":"Gerahvan",
    "gn:country_code":"IR",
    "gn:dem":718,
    "gn:feature_class":"P",
    "gn:feature_code":"PPLL",
    "gn:name":"Gerahvan",
    "gn:population":0,
    "gn:timezone":"Asia/Tehran",
    "iso:country":"IR",
    "name:fas_x_preferred":[
        "\u06af\u0631\u0647\u0648\u0646"
    ],
    "name:fas_x_variant":[
        "Gerahvan-e B\u0101l\u0101"
    ],
    "wof:name":"Gerahvan",
    "wof:placetype":"locality"
},
  "geometry": {"coordinates":[58.18945,26.41082],"type":"Point"}
}