{
  "type": "Feature",
  "properties": {
    "gn:admin1_code":"5",
    "gn:asciiname":"Laru",
    "gn:country_code":"IR",
    "gn:dem":1107,
    "gn:feature_class":"P",
    "gn:feature_code":"PPL",
    "gn:name":"L\u0101r\u016b",
    "gn:population":0,
    "gn:timezone":"Asia/Tehran",
    "iso:country":"IR",
    "name:fas_x_preferred":[
        "\u0644\u0627\u0631\u0627\u067e"
    ],
    "name:fas_x_variant":[
        "L\u0101r\u0101p",
        "L\u0101r\u016b",
        "\u0644\u0627\u0631\u0648",
        "\u0644\u0627\u0631\u0648\u0628"
    ],
    "name:und_x_variant":[
        "\u0644\u0627\u0631\u0648",
        "L\u0101r\u016bb"
    ],
    "wof:name":"Laru",
    "wof:placetype":"locality"
},
  "geometry": {"coordinates":[50.61109,31.05806],"type":"Point"}
}