{
  "type": "Feature",
  "properties": {
    "gn:admin1_code":"29.0",
    "gn:asciiname":"Astan",
    "gn:country_code":"IR",
    "gn:dem":1143,
    "gn:feature_class":"P",
    "gn:feature_code":"PPLL",
    "gn:name":"Ast\u0101n",
    "gn:population":0,
    "gn:timezone":"Asia/Tehran",
    "iso:country":"IR",
    "name:ara_x_preferred":[
        "\u0623\u0633\u062a\u0627\u0646"
    ],
    "name:fas_x_preferred":[
        "\u0627\u0633\u062a\u0627\u0646"
    ],
    "name:fas_x_variant":[
        "Ast\u0101n",
        "Est\u0101n",
        "\u0622\u0633\u062a\u0627\u0646"
    ],
    "name:kat_x_preferred":[
        "\u10d0\u10e1\u10e2\u10d0\u10dc\u10d8"
    ],
    "wof:name":"Astan",
    "wof:placetype":"locality"
},
  "geometry": {"coordinates":[58.08013,26.89438],"type":"Point"}
}