{
  "type": "Feature",
  "properties": {
    "gn:admin1_code":"43",
    "gn:asciiname":"Qarah Bashlu",
    "gn:country_code":"IR",
    "gn:dem":1285,
    "gn:feature_class":"P",
    "gn:feature_code":"PPL",
    "gn:name":"Qarah B\u0101shl\u016b",
    "gn:population":0,
    "gn:timezone":"Asia/Tehran",
    "iso:country":"IR",
    "name:fas_x_preferred":[
        "Qarah B\u0101shl\u016b"
    ],
    "name:fas_x_variant":[
        "Qareh B\u0101shl\u016b",
        "\u0642\u0631\u0647 \u0628\u0627\u0634\u0644\u0648"
    ],
    "name:und_x_variant":[
        "\u0642\u0631\u0647 \u0628\u0627\u0634\u0644\u0648"
    ],
    "wof:name":"Qarah Bashlu",
    "wof:placetype":"locality"
},
  "geometry": {"coordinates":[57.2808,37.37568],"type":"Point"}
}