{
  "type": "Feature",
  "properties": {
    "gn:admin1_code":"7",
    "gn:asciiname":"Chah Khargushi",
    "gn:country_code":"IR",
    "gn:dem":1602,
    "gn:feature_class":"P",
    "gn:feature_code":"PPL",
    "gn:name":"Ch\u0101h Kharg\u016bsh\u012b",
    "gn:population":0,
    "gn:timezone":"Asia/Tehran",
    "iso:country":"IR",
    "name:fas_x_preferred":[
        "\u0686\u0627\u0647 \u062e\u0631\u06af\u0648\u0634\u06cc"
    ],
    "name:fas_x_variant":[
        "Ch\u0101h Kharg\u016bsh\u012b",
        "\u0686\u0627\u0647\u200c\u062e\u0631\u06af\u0648\u0634\u06cc"
    ],
    "wof:name":"Chah Khargushi",
    "wof:placetype":"locality"
},
  "geometry": {"coordinates":[55.19516,28.95531],"type":"Point"}
}