{
  "type": "Feature",
  "properties": {
    "gn:admin1_code":"26",
    "gn:asciiname":"Vijin-e Pa'in",
    "gn:country_code":"IR",
    "gn:dem":951,
    "gn:feature_class":"P",
    "gn:feature_code":"PPL",
    "gn:name":"V\u012bj\u012bn-e P\u0101\u2019\u012bn",
    "gn:population":0,
    "gn:timezone":"Asia/Tehran",
    "iso:country":"IR",
    "name:fas_x_preferred":[
        "B\u012bj\u012bn-e P\u0101\u2019\u012bn"
    ],
    "name:fas_x_variant":[
        "\u0648\u06cc\u062c\u06cc\u0646 \u067e\u0627\u0626\u06cc\u0646"
    ],
    "name:und_x_variant":[
        "V\u012bj\u012bn-e P\u0101\u2019\u012bn"
    ],
    "wof:name":"Vijin-e Pa'in",
    "wof:placetype":"locality"
},
  "geometry": {"coordinates":[51.26667,35.38333],"type":"Point"}
}