{
  "type": "Feature",
  "properties": {
    "gn:admin1_code":"13",
    "gn:asciiname":"Sharafvand",
    "gn:country_code":"IR",
    "gn:dem":1323,
    "gn:feature_class":"P",
    "gn:feature_code":"PPL",
    "gn:name":"Sharafvand",
    "gn:population":0,
    "gn:timezone":"Asia/Tehran",
    "iso:country":"IR",
    "name:ceb_x_preferred":[
        "Sharafvand"
    ],
    "name:fas_x_preferred":[
        "\u0634\u0631\u0641 \u0648\u0646\u062f"
    ],
    "name:fas_x_variant":[
        "\u0634\u0631\u0641\u0648\u0646\u062f"
    ],
    "name:swe_x_preferred":[
        "Sharafvand"
    ],
    "wof:name":"Sharafvand",
    "wof:placetype":"locality"
},
  "geometry": {"coordinates":[46.6989,34.5087],"type":"Point"}
}