{
  "type": "Feature",
  "properties": {
    "gn:admin1_code":"5.0",
    "gn:asciiname":"Darreh Lam Darreh",
    "gn:country_code":"IR",
    "gn:dem":1244,
    "gn:feature_class":"P",
    "gn:feature_code":"PPL",
    "gn:name":"Darreh Lam Darreh",
    "gn:population":0,
    "gn:timezone":"Asia/Tehran",
    "iso:country":"IR",
    "name:fas_x_preferred":[
        "\u062f\u0631\u0647 \u0644\u0645 \u062f\u0631\u0647"
    ],
    "wof:name":"Darreh Lam Darreh",
    "wof:placetype":"locality"
},
  "geometry": {"coordinates":[50.14024000000001,31.08302],"type":"Point"}
}