{
  "type": "Feature",
  "properties": {
    "gn:admin1_code":"7",
    "gn:asciiname":"Heydarabad",
    "gn:country_code":"IR",
    "gn:dem":1683,
    "gn:feature_class":"P",
    "gn:feature_code":"PPL",
    "gn:name":"\u1e28eydar\u0101b\u0101d",
    "gn:population":0,
    "gn:timezone":"Asia/Tehran",
    "iso:country":"IR",
    "name:ara_x_preferred":[
        "\u062d\u064a\u062f\u0631\u0622\u0628\u0627\u062f"
    ],
    "name:fas_x_preferred":[
        "\u062d\u06cc\u062f\u0631 \u0622\u0628\u0627\u062f"
    ],
    "name:fas_x_variant":[
        "\u1e28eydar\u0101b\u0101d",
        "\u062d\u06cc\u062f\u0631\u0622\u0628\u0627\u062f"
    ],
    "name:msa_x_preferred":[
        "Heydarabad"
    ],
    "wof:name":"Heydarabad",
    "wof:placetype":"locality"
},
  "geometry": {"coordinates":[53.4983,29.2285],"type":"Point"}
}