{
  "type": "Feature",
  "properties": {
    "gn:admin1_code":"3",
    "gn:asciiname":"Darreh Ru Ab",
    "gn:country_code":"IR",
    "gn:dem":1202,
    "gn:feature_class":"P",
    "gn:feature_code":"PPL",
    "gn:name":"Darreh R\u016b \u0100b",
    "gn:population":0,
    "gn:timezone":"Asia/Tehran",
    "iso:country":"IR",
    "name:fas_x_preferred":[
        "Darreh R\u016bb\u0101h"
    ],
    "name:fas_x_variant":[
        "\u062f\u064e\u0631\u0650\u0651\u0647 \u0631\u0648\u0628\u0627\u0647",
        "Darreh R\u016b \u0100b",
        "\u062f\u0631\u0651\u0647 \u0631\u0648 \u0622\u0628"
    ],
    "wof:name":"Darreh Ru Ab",
    "wof:placetype":"locality"
},
  "geometry": {"coordinates":[50.68212,31.42189],"type":"Point"}
}