{
  "type": "Feature",
  "properties": {
    "gn:admin1_code":"4.0",
    "gn:asciiname":"`Omar Bazar",
    "gn:country_code":"IR",
    "gn:dem":29,
    "gn:feature_class":"P",
    "gn:feature_code":"PPL",
    "gn:name":"\u2018Omar B\u0101z\u0101r",
    "gn:population":0,
    "gn:timezone":"Asia/Tehran",
    "iso:country":"IR",
    "name:fas_x_preferred":[
        "\u2018Omar B\u0101z\u0101r"
    ],
    "wof:name":"`Omar Bazar",
    "wof:placetype":"locality"
},
  "geometry": {"coordinates":[61.33333,25.66667],"type":"Point"}
}