{
  "type": "Feature",
  "properties": {
    "gn:admin1_code":"29",
    "gn:asciiname":"Khalilabad",
    "gn:country_code":"IR",
    "gn:dem":1720,
    "gn:feature_class":"P",
    "gn:feature_code":"PPL",
    "gn:name":"Khal\u012bl\u0101b\u0101d",
    "gn:population":0,
    "gn:timezone":"Asia/Tehran",
    "iso:country":"IR",
    "name:aze_x_preferred":[
        "X\u0259lilabad"
    ],
    "name:ceb_x_preferred":[
        "Khalilabad"
    ],
    "name:fas_x_preferred":[
        "Khal\u012bl\u0101b\u0101d"
    ],
    "name:fas_x_variant":[
        "\u062e\u0644\u06cc\u0644 \u0622\u0628\u0627\u062f",
        "\u062e\u0644\u06cc\u0644\u200c\u0622\u0628\u0627\u062f"
    ],
    "name:swe_x_preferred":[
        "Khalilabad"
    ],
    "name:und_x_variant":[
        "\u062e\u0644\u06cc\u0644 \u0622\u0628\u0627\u062f"
    ],
    "wof:name":"Khalilabad",
    "wof:placetype":"locality"
},
  "geometry": {"coordinates":[55.56674,29.53266],"type":"Point"}
}