{
  "type": "Feature",
  "properties": {
    "gn:admin1_code":"13",
    "gn:asciiname":"Sarbagh Golin",
    "gn:country_code":"IR",
    "gn:dem":1065,
    "gn:feature_class":"P",
    "gn:feature_code":"PPL",
    "gn:name":"Sarb\u0101gh Gol\u012bn",
    "gn:population":0,
    "gn:timezone":"Asia/Tehran",
    "iso:country":"IR",
    "name:fas_x_preferred":[
        "\u0633\u0631\u0628\u0627\u063a \u06af\u0644\u06cc\u0646"
    ],
    "name:fas_x_variant":[
        "Sarb\u0101gh Gol\u012bn"
    ],
    "wof:name":"Sarbagh Golin",
    "wof:placetype":"locality"
},
  "geometry": {"coordinates":[46.00885,34.24028],"type":"Point"}
}