{
  "type": "Feature",
  "properties": {
    "gn:admin1_code":"28.0",
    "gn:asciiname":"Achak",
    "gn:country_code":"IR",
    "gn:dem":2590,
    "gn:feature_class":"P",
    "gn:feature_code":"PPL",
    "gn:name":"\u0100chak",
    "gn:population":0,
    "gn:timezone":"Asia/Tehran",
    "iso:country":"IR",
    "name:fas_x_preferred":[
        "\u0100chak"
    ],
    "name:fas_x_variant":[
        "\u0622\u0686\u06a9",
        "\u0627\u0628\u0686\u06a9"
    ],
    "name:und_x_variant":[
        "\u0622\u0686\u06a9",
        "Abchak"
    ],
    "wof:name":"Achak",
    "wof:placetype":"locality"
},
  "geometry": {"coordinates":[49.83052,32.88189000000001],"type":"Point"}
}