{
  "type": "Feature",
  "properties": {
    "gn:admin1_code":"26.0",
    "gn:asciiname":"Kabud Cheshmeh",
    "gn:country_code":"IR",
    "gn:dem":1853,
    "gn:elevation":"0.0",
    "gn:feature_class":"P",
    "gn:feature_code":"PPLF",
    "gn:name":"Kab\u016bd Cheshmeh",
    "gn:population":0,
    "gn:timezone":"Asia/Tehran",
    "iso:country":"IR",
    "name:fas_x_preferred":[
        "\u062a\u0646\u06af\u0647"
    ],
    "name:fas_x_variant":[
        "\u06a9\u0628\u0648\u062f \u0686\u0634\u0645\u0647"
    ],
    "name:und_x_variant":[
        "Tangeh",
        "Kab\u016bd Cheshmeh"
    ],
    "wof:name":"Kabud Cheshmeh",
    "wof:placetype":"locality"
},
  "geometry": {"coordinates":[51.1314,35.8079],"type":"Point"}
}