{
  "type": "Feature",
  "properties": {
    "gn:admin1_code":"33",
    "gn:asciiname":"Hoseyn Alan",
    "gn:country_code":"IR",
    "gn:dem":1802,
    "gn:feature_class":"P",
    "gn:feature_code":"PPL",
    "gn:name":"\u1e28oseyn \u0100l\u0101n",
    "gn:population":0,
    "gn:timezone":"Asia/Tehran",
    "iso:country":"IR",
    "name:azb_x_preferred":[
        "\u062d\u0648\u0633\u0626\u06cc\u0646\u200c\u0622\u0644\u0627\u0646"
    ],
    "name:fas_x_preferred":[
        "\u062d\u0633\u06cc\u0646 \u0622\u0644\u0627\u0646"
    ],
    "name:fas_x_variant":[
        "\u1e28oseyn \u0100l\u0101n",
        "\u062d\u0633\u06cc\u0646\u200c\u0622\u0644\u0627\u0646"
    ],
    "name:msa_x_preferred":[
        "Hoseyn Alan"
    ],
    "wof:name":"Hoseyn Alan",
    "wof:placetype":"locality"
},
  "geometry": {"coordinates":[47.213,37.3552],"type":"Point"}
}