{
  "type": "Feature",
  "properties": {
    "gn:admin1_code":"43.0",
    "gn:asciiname":"Kalat",
    "gn:country_code":"IR",
    "gn:dem":1563,
    "gn:feature_class":"P",
    "gn:feature_code":"PPL",
    "gn:name":"Kal\u0101t",
    "gn:population":0,
    "gn:timezone":"Asia/Tehran",
    "iso:country":"IR",
    "name:fas_x_preferred":[
        "Kal\u0101t"
    ],
    "name:fas_x_variant":[
        "\u06a9\u0644\u0627\u062a"
    ],
    "wof:name":"Kalat",
    "wof:placetype":"locality"
},
  "geometry": {"coordinates":[57.40991,37.21918],"type":"Point"}
}