{
  "type": "Feature",
  "properties": {
    "gn:admin1_code":"1.0",
    "gn:asciiname":"Gol Kanag",
    "gn:country_code":"IR",
    "gn:dem":1326,
    "gn:elevation":"0.0",
    "gn:feature_class":"P",
    "gn:feature_code":"PPL",
    "gn:name":"Gol Kanag",
    "gn:population":0,
    "gn:timezone":"Asia/Tehran",
    "iso:country":"IR",
    "name:azb_x_preferred":[
        "\u06af\u0644 \u0643\u0627\u0646\u06a9"
    ],
    "name:ceb_x_preferred":[
        "Gol Kanag"
    ],
    "name:fas_x_preferred":[
        "\u06af\u0644 \u06a9\u0646\u06af"
    ],
    "name:fas_x_variant":[
        "Golk\u0101nak",
        "\u06af\u0644\u200c\u06a9\u0627\u0646\u06a9"
    ],
    "name:msa_x_preferred":[
        "Golkanak"
    ],
    "name:swe_x_preferred":[
        "Gol Kanag"
    ],
    "wof:name":"Gol Kanag",
    "wof:placetype":"locality"
},
  "geometry": {"coordinates":[45.3474,36.2516],"type":"Point"}
}