{
  "type": "Feature",
  "properties": {
    "gn:admin1_code":"15",
    "gn:asciiname":"Qomeyjeh-ye Yek",
    "gn:country_code":"IR",
    "gn:dem":11,
    "gn:feature_class":"P",
    "gn:feature_code":"PPL",
    "gn:name":"Qomeyjeh-ye Yek",
    "gn:population":0,
    "gn:timezone":"Asia/Tehran",
    "iso:country":"IR",
    "name:fas_x_preferred":[
        "\u0642\u0645\u06cc\u062c\u0647 \u06cc\u06a9"
    ],
    "name:fas_x_variant":[
        "\u063a\u0645\u06cc\u062c\u0647"
    ],
    "name:und_x_variant":[
        "Qomeyjeh",
        "Qomeyjeh-ye Yek",
        "Ghomeyjeh"
    ],
    "wof:name":"Qomeyjeh-ye Yek",
    "wof:placetype":"locality"
},
  "geometry": {"coordinates":[48.0369,31.5185],"type":"Point"}
}