{
  "type": "Feature",
  "properties": {
    "gn:admin1_code":"7.0",
    "gn:asciiname":"`Abbasabad-e Quri",
    "gn:country_code":"IR",
    "gn:dem":1261,
    "gn:feature_class":"P",
    "gn:feature_code":"PPL",
    "gn:name":"\u2018Abb\u0101s\u0101b\u0101d-e Q\u016br\u012b",
    "gn:population":0,
    "gn:timezone":"Asia/Tehran",
    "iso:country":"IR",
    "name:fas_x_preferred":[
        "\u2018Abb\u0101s\u0101b\u0101d-e Q\u016br\u012b"
    ],
    "name:fas_x_variant":[
        "\u0639\u0628\u0627\u0633 \u0622\u0628\u0627\u062f \u0642\u0648\u0631\u06cc"
    ],
    "name:und_x_variant":[
        "\u0639\u0628\u0627\u0633 \u0622\u0628\u0627\u062f \u0642\u0648\u0631\u06cc"
    ],
    "wof:name":"`Abbasabad-e Quri",
    "wof:placetype":"locality"
},
  "geometry": {"coordinates":[51.51134,29.94478],"type":"Point"}
}