{
  "type": "Feature",
  "properties": {
    "gn:admin1_code":"3",
    "gn:asciiname":"Baz Garun",
    "gn:country_code":"IR",
    "gn:dem":1777,
    "gn:feature_class":"P",
    "gn:feature_code":"PPL",
    "gn:name":"B\u0101z Gar\u016bn",
    "gn:population":0,
    "gn:timezone":"Asia/Tehran",
    "iso:country":"IR",
    "name:fas_x_preferred":[
        "B\u0101z Gar\u016bn"
    ],
    "name:fas_x_variant":[
        "\u0628\u0627\u0632 \u06af\u0631\u0648\u0646"
    ],
    "wof:name":"Baz Garun",
    "wof:placetype":"locality"
},
  "geometry": {"coordinates":[49.98582,32.23923],"type":"Point"}
}