{
  "type": "Feature",
  "properties": {
    "gn:admin1_code":"15",
    "gn:asciiname":"Kuli Rostam",
    "gn:country_code":"IR",
    "gn:dem":201,
    "gn:feature_class":"P",
    "gn:feature_code":"PPL",
    "gn:name":"K\u016bl\u012b Rostam",
    "gn:population":0,
    "gn:timezone":"Asia/Tehran",
    "iso:country":"IR",
    "name:fas_x_preferred":[
        "K\u016bl\u012b Rostam"
    ],
    "name:fas_x_variant":[
        "\u06a9\u0648\u0644\u06cc \u0631\u0633\u062a\u0645"
    ],
    "name:und_x_variant":[
        "\u06a9\u0648\u0644\u06cc \u0631\u0633\u062a\u0645"
    ],
    "wof:name":"Kuli Rostam",
    "wof:placetype":"locality"
},
  "geometry": {"coordinates":[49.65099,31.26959],"type":"Point"}
}