{
  "type": "Feature",
  "properties": {
    "gn:admin1_code":"16",
    "gn:asciiname":"Nurabad",
    "gn:country_code":"IR",
    "gn:dem":1541,
    "gn:feature_class":"P",
    "gn:feature_code":"PPL",
    "gn:name":"N\u016br\u0101b\u0101d",
    "gn:population":0,
    "gn:timezone":"Asia/Tehran",
    "iso:country":"IR",
    "name:fas_x_preferred":[
        "\u0634\u0627\u0634\u0627"
    ],
    "name:fas_x_variant":[
        "Sh\u0101sh\u0101",
        "\u0646\u0648\u0631 \u0622\u0628\u0627\u062f",
        "\u0634\u0627\u0634\u0627\u06af\u0644"
    ],
    "name:und_x_variant":[
        "N\u016br\u0101b\u0101d",
        "Sh\u0101sh\u0101gol"
    ],
    "wof:name":"Nurabad",
    "wof:placetype":"locality"
},
  "geometry": {"coordinates":[46.58957,36.13062],"type":"Point"}
}