{
  "type": "Feature",
  "properties": {
    "gn:admin1_code":"8",
    "gn:asciiname":"Changlizeh Khuni",
    "gn:country_code":"IR",
    "gn:dem":1481,
    "gn:feature_class":"P",
    "gn:feature_code":"PPLL",
    "gn:name":"Changl\u012bzeh Kh\u016bn\u012b",
    "gn:population":0,
    "gn:timezone":"Asia/Tehran",
    "iso:country":"IR",
    "name:fas_x_preferred":[
        "\u0686\u0646\u06af\u06cc\u0632 \u062e\u0648\u0646\u06cc"
    ],
    "name:fas_x_variant":[
        "Chang\u012bz Kh\u016bn\u012b",
        "\u0686\u0646\u06af\u0644\u06cc\u0632\u0647 \u062e\u0648\u0646\u06cc"
    ],
    "name:und_x_variant":[
        "Changl\u012bzeh Kh\u016bn\u012b"
    ],
    "wof:name":"Changlizeh Khuni",
    "wof:placetype":"locality"
},
  "geometry": {"coordinates":[48.77809,37.52749],"type":"Point"}
}