{
  "type": "Feature",
  "properties": {
    "gn:admin1_code":"42",
    "gn:asciiname":"Kazem Khan",
    "gn:country_code":"IR",
    "gn:dem":1137,
    "gn:feature_class":"P",
    "gn:feature_code":"PPL",
    "gn:name":"K\u0101z\u0327em Kh\u0101n",
    "gn:population":0,
    "gn:timezone":"Asia/Tehran",
    "iso:country":"IR",
    "name:fas_x_preferred":[
        "\u06a9\u0627\u0638\u0645 \u062e\u0627\u0646"
    ],
    "name:fas_x_variant":[
        "K\u0101z\u0327em Kh\u0101n"
    ],
    "wof:name":"Kazem Khan",
    "wof:placetype":"locality"
},
  "geometry": {"coordinates":[59.2558,35.06521],"type":"Point"}
}