{
  "type": "Feature",
  "properties": {
    "gn:admin1_code":"29",
    "gn:asciiname":"Chah `Abbas",
    "gn:country_code":"IR",
    "gn:dem":441,
    "gn:feature_class":"P",
    "gn:feature_code":"PPL",
    "gn:name":"Ch\u0101h \u2018Abb\u0101s",
    "gn:population":0,
    "gn:timezone":"Asia/Tehran",
    "iso:country":"IR",
    "name:fas_x_preferred":[
        "\u0686\u0627\u0647 \u0639\u0628\u0627\u0633"
    ],
    "name:fas_x_variant":[
        "Ch\u0101h \u2018Abb\u0101s"
    ],
    "name:und_x_variant":[
        "Chah-e \u2018Abb\u0101s",
        "Ch\u0101h-e \u2018Abb\u0101s\u012b"
    ],
    "wof:name":"Chah `Abbas",
    "wof:placetype":"locality"
},
  "geometry": {"coordinates":[57.3931,27.6183],"type":"Point"}
}