{
  "type": "Feature",
  "properties": {
    "gn:admin1_code":"41",
    "gn:asciiname":"Tanak-e `Olya",
    "gn:country_code":"IR",
    "gn:dem":2001,
    "gn:feature_class":"P",
    "gn:feature_code":"PPL",
    "gn:name":"\u0162an\u0101k-e \u2018Oly\u0101",
    "gn:population":0,
    "gn:timezone":"Asia/Tehran",
    "iso:country":"IR",
    "name:fas_x_preferred":[
        "\u062a\u0646\u0627\u06a9 \u0628\u0627\u0644\u0627"
    ],
    "name:fas_x_variant":[
        "\u0162an\u0101k-e B\u0101l\u0101",
        "Tan\u0101k-e B\u0101l\u0101",
        "\u0637\u0646\u0627\u06a9 \u0639\u0644\u06cc\u0627"
    ],
    "name:und_x_variant":[
        "Tenak B\u0101l\u0101",
        "\u0162anak B\u0101l\u0101",
        "\u0162an\u0101k-e \u2018Oly\u0101"
    ],
    "wof:name":"Tanak-e `Olya",
    "wof:placetype":"locality"
},
  "geometry": {"coordinates":[59.61442,32.86537],"type":"Point"}
}