{
  "type": "Feature",
  "properties": {
    "gn:admin1_code":"8",
    "gn:asciiname":"Sar Sar",
    "gn:country_code":"IR",
    "gn:dem":4,
    "gn:feature_class":"P",
    "gn:feature_code":"PPL",
    "gn:name":"S\u0101r Sar",
    "gn:population":0,
    "gn:timezone":"Asia/Tehran",
    "iso:country":"IR",
    "name:fas_x_preferred":[
        "S\u0101r Sar\u0101"
    ],
    "name:fas_x_variant":[
        "\u0633\u0627\u0631 \u0633\u0631"
    ],
    "name:und_x_variant":[
        "S\u0101r Sar"
    ],
    "wof:name":"Sar Sar",
    "wof:placetype":"locality"
},
  "geometry": {"coordinates":[50.42858,37.04149],"type":"Point"}
}