{
  "type": "Feature",
  "properties": {
    "gn:admin1_code":"4",
    "gn:asciiname":"Shah-e Parandak",
    "gn:country_code":"IR",
    "gn:dem":791,
    "gn:feature_class":"P",
    "gn:feature_code":"PPL",
    "gn:name":"Sh\u0101h-e Parandak",
    "gn:population":0,
    "gn:timezone":"Asia/Tehran",
    "iso:country":"IR",
    "name:fas_x_preferred":[
        "\u0634\u0627\u0647 \u067e\u0631\u0646\u062f\u06a9"
    ],
    "name:fas_x_variant":[
        "Sh\u0101h-e Parandak"
    ],
    "wof:name":"Shah-e Parandak",
    "wof:placetype":"locality"
},
  "geometry": {"coordinates":[59.45581,27.92193],"type":"Point"}
}