{
  "type": "Feature",
  "properties": {
    "gn:admin1_code":"4.0",
    "gn:asciiname":"Sand-e Mirsuban",
    "gn:country_code":"IR",
    "gn:dem":13,
    "gn:feature_class":"P",
    "gn:feature_code":"PPL",
    "gn:name":"Sand-e M\u012brs\u016bb\u0101n",
    "gn:population":0,
    "gn:timezone":"Asia/Tehran",
    "iso:country":"IR",
    "name:fas_x_preferred":[
        "Sand-e M\u012brs\u0304\u016bb\u0101n"
    ],
    "name:fas_x_variant":[
        "Sand-e M\u012brs\u016bb\u0101n",
        "\u0633\u0646\u062f \u0645\u06cc\u0631\u0633\u0648\u0628\u0627\u0646"
    ],
    "name:und_x_variant":[
        "Sand M\u012br S\u016bb\u0101n",
        "Sand-e M\u012brsha\u2018b\u0101n",
        "Sand M\u012br Sha\u2018b\u0101n",
        "\u0633\u0646\u062f \u0645\u06cc\u0631\u0633\u0648\u0628\u0627\u0646"
    ],
    "wof:name":"Sand-e Mirsuban",
    "wof:placetype":"locality"
},
  "geometry": {"coordinates":[61.27316999999999,25.38221],"type":"Point"}
}