{
  "type": "Feature",
  "properties": {
    "gn:admin1_code":"4.0",
    "gn:asciiname":"Mur Kuh",
    "gn:country_code":"IR",
    "gn:dem":1874,
    "gn:feature_class":"P",
    "gn:feature_code":"PPL",
    "gn:name":"M\u016br K\u016bh",
    "gn:population":0,
    "gn:timezone":"Asia/Tehran",
    "iso:country":"IR",
    "name:fas_x_preferred":[
        "\u0645\u0648\u0631 \u06a9\u0648\u0647"
    ],
    "name:fas_x_variant":[
        "M\u016br K\u016bh"
    ],
    "wof:name":"Mur Kuh",
    "wof:placetype":"locality"
},
  "geometry": {"coordinates":[60.8165,29.2016],"type":"Point"}
}