{
  "type": "Feature",
  "properties": {
    "gn:admin1_code":"4.0",
    "gn:asciiname":"Radon",
    "gn:country_code":"IR",
    "gn:dem":42,
    "gn:feature_class":"P",
    "gn:feature_code":"PPL",
    "gn:name":"Radon",
    "gn:population":0,
    "gn:timezone":"Asia/Tehran",
    "iso:country":"IR",
    "name:fas_x_preferred":[
        "R\u0101d\u016b"
    ],
    "name:fas_x_variant":[
        "\u0631\u0627\u062f\u0648"
    ],
    "name:und_x_variant":[
        "Raden",
        "Radon",
        "\u0631\u0627\u062f\u0648"
    ],
    "wof:name":"Radon",
    "wof:placetype":"locality"
},
  "geometry": {"coordinates":[60.93312,25.61822],"type":"Point"}
}