{
  "type": "Feature",
  "properties": {
    "gn:admin1_code":"26.0",
    "gn:asciiname":"Shahrak-e Deh-e Bahar",
    "gn:country_code":"IR",
    "gn:dem":1151,
    "gn:feature_class":"P",
    "gn:feature_code":"PPL",
    "gn:name":"Shahrak-e Deh-e Bah\u0101r",
    "gn:population":0,
    "gn:timezone":"Asia/Tehran",
    "iso:country":"IR",
    "name:fas_x_preferred":[
        "\u0628\u064e\u0647\u0627\u0621"
    ],
    "name:fas_x_variant":[
        "Bah\u0101r",
        "Bah\u0101\u2019",
        "\u0628\u0647\u0627\u0631",
        "\u0634\u0647\u0631\u06a9 \u062f\u0647 \u0628\u0647\u0627\u0631",
        "\u062f\u0647 \u0628\u0647\u0627\u0621"
    ],
    "name:und_x_variant":[
        "Shahrak-e Deh-e Bah\u0101r",
        "Deh-e Bah\u0101\u2019"
    ],
    "wof:name":"Shahrak-e Deh-e Bahar",
    "wof:placetype":"locality"
},
  "geometry": {"coordinates":[51.0926,35.6699],"type":"Point"}
}