{
  "type": "Feature",
  "properties": {
    "gn:admin1_code":"41",
    "gn:asciiname":"Kalateh-ye Khan",
    "gn:country_code":"IR",
    "gn:dem":1685,
    "gn:feature_class":"P",
    "gn:feature_code":"PPL",
    "gn:name":"Kal\u0101teh-ye Kh\u0101n",
    "gn:population":0,
    "gn:timezone":"Asia/Tehran",
    "iso:country":"IR",
    "name:fas_x_preferred":[
        "Kal\u0101teh-ye Kh\u0101n"
    ],
    "name:fas_x_variant":[
        "\u06a9\u0644\u0627\u062a\u0647 \u062e\u0627\u0646"
    ],
    "name:und_x_variant":[
        "Kh\u0101n",
        "Kal\u0101teh-i-Kh\u0101n"
    ],
    "wof:name":"Kalateh-ye Khan",
    "wof:placetype":"locality"
},
  "geometry": {"coordinates":[59.2285,33.29149],"type":"Point"}
}