{
  "type": "Feature",
  "properties": {
    "gn:admin1_code":"8",
    "gn:asciiname":"Sekachel",
    "gn:country_code":"IR",
    "gn:dem":30,
    "gn:feature_class":"P",
    "gn:feature_code":"PPL",
    "gn:name":"Sek\u0101chel",
    "gn:population":0,
    "gn:timezone":"Asia/Tehran",
    "iso:country":"IR",
    "name:fas_x_preferred":[
        "Sek\u0101chel"
    ],
    "wof:name":"Sekachel",
    "wof:placetype":"locality"
},
  "geometry": {"coordinates":[49.70444000000001,37.17056],"type":"Point"}
}