{
  "type": "Feature",
  "properties": {
    "gn:admin1_code":"35.0",
    "gn:asciiname":"Poschal",
    "gn:country_code":"IR",
    "gn:dem":281,
    "gn:feature_class":"P",
    "gn:feature_code":"PPL",
    "gn:name":"Posch\u0101l",
    "gn:population":0,
    "gn:timezone":"Asia/Tehran",
    "iso:country":"IR",
    "name:fas_x_preferred":[
        "Posch\u0101l"
    ],
    "name:fas_x_variant":[
        "\u067e\u0633\u0686\u0627\u0644"
    ],
    "name:und_x_variant":[
        "\u067e\u0633\u0686\u0627\u0644"
    ],
    "wof:name":"Poschal",
    "wof:placetype":"locality"
},
  "geometry": {"coordinates":[50.74338,36.82784],"type":"Point"}
}