{
  "type": "Feature",
  "properties": {
    "gn:admin1_code":"41",
    "gn:asciiname":"Sarab",
    "gn:country_code":"IR",
    "gn:dem":1873,
    "gn:feature_class":"P",
    "gn:feature_code":"PPLF",
    "gn:name":"Sar\u0101b",
    "gn:population":0,
    "gn:timezone":"Asia/Tehran",
    "iso:country":"IR",
    "name:ceb_x_preferred":[
        "Sarab"
    ],
    "name:fas_x_preferred":[
        "Sar\u0101b"
    ],
    "name:fas_x_variant":[
        "\u0633\u0631\u0627\u0628"
    ],
    "name:msa_x_preferred":[
        "Serab"
    ],
    "name:swe_x_preferred":[
        "Sarab"
    ],
    "name:und_x_variant":[
        "\u0633\u0631\u0627\u0628"
    ],
    "wof:name":"Sarab",
    "wof:placetype":"locality"
},
  "geometry": {"coordinates":[58.56361,33.97214],"type":"Point"}
}