{
  "type": "Feature",
  "properties": {
    "gn:admin1_code":"15.0",
    "gn:asciiname":"Shalheh-ye Savamer",
    "gn:country_code":"IR",
    "gn:dem":3,
    "gn:feature_class":"P",
    "gn:feature_code":"PPL",
    "gn:name":"Shal\u1e29eh-ye Sav\u0101mer",
    "gn:population":0,
    "gn:timezone":"Asia/Tehran",
    "iso:country":"IR",
    "name:fas_x_preferred":[
        "\u0634\u0644\u062d\u0647 \u0633\u0648\u0627\u0645\u0631"
    ],
    "name:fas_x_variant":[
        "Shal\u1e29eh-ye Sav\u0101mer"
    ],
    "wof:name":"Shalheh-ye Savamer",
    "wof:placetype":"locality"
},
  "geometry": {"coordinates":[48.3781,30.2433],"type":"Point"}
}