{
  "type": "Feature",
  "properties": {
    "gn:admin1_code":"15",
    "gn:asciiname":"Cheshmeh-ye Zalunak",
    "gn:country_code":"IR",
    "gn:dem":333,
    "gn:feature_class":"P",
    "gn:feature_code":"PPL",
    "gn:name":"Cheshmeh-ye Z\u0101l\u016bnak",
    "gn:population":0,
    "gn:timezone":"Asia/Tehran",
    "iso:country":"IR",
    "name:fas_x_preferred":[
        "Darv\u0101zeh"
    ],
    "name:fas_x_variant":[
        "\u0686\u0634\u0645\u0647 \u0632\u0627\u0644\u0648\u0646\u06a9",
        "\u0686\u0634\u0645\u0647 \u0632\u0627\u0644\u0648\u0648\u06a9",
        "\u0686\u0634\u0645\u0647 \u0632\u0627\u0644\u0648\u06a9"
    ],
    "name:und_x_variant":[
        "Cheshmeh-ye Z\u0101l\u016bnak",
        "Cheshmeh Z\u0101l\u016bvak",
        "Cheshmeh Z\u0101l\u016bk"
    ],
    "wof:name":"Cheshmeh-ye Zalunak",
    "wof:placetype":"locality"
},
  "geometry": {"coordinates":[49.23417,31.99167000000001],"type":"Point"}
}