{
  "type": "Feature",
  "properties": {
    "gn:admin1_code":"35",
    "gn:asciiname":"Bala Baziar",
    "gn:country_code":"IR",
    "gn:dem":41,
    "gn:feature_class":"P",
    "gn:feature_code":"PPL",
    "gn:name":"B\u0101l\u0101 B\u0101z\u012b\u0101r",
    "gn:population":0,
    "gn:timezone":"Asia/Tehran",
    "iso:country":"IR",
    "name:fas_x_preferred":[
        "\u0628\u0627\u0644\u0627 \u0628\u0627\u0632\u064a\u0627\u0631"
    ],
    "name:fas_x_variant":[
        "B\u0101l\u0101 B\u0101z\u012b\u0101r",
        "\u0628\u0627\u0644\u0627\u0628\u0627\u0632\u06cc\u0627\u0631"
    ],
    "name:mzn_x_preferred":[
        "\u0628\u0627\u0644\u0627\u0628\u0627\u0632\u06cc\u0627\u0631"
    ],
    "name:und_x_variant":[
        "B\u0101zy\u0101r-e B\u0101l\u0101",
        "\u0628\u0627\u0632\u064a\u0627\u0631\u0650 \u0628\u0627\u0644\u0627"
    ],
    "wof:name":"Bala Baziar",
    "wof:placetype":"locality"
},
  "geometry": {"coordinates":[52.52922,36.41339],"type":"Point"}
}