{
  "type": "Feature",
  "properties": {
    "gn:admin1_code":"4",
    "gn:asciiname":"Gur Mardow",
    "gn:country_code":"IR",
    "gn:dem":935,
    "gn:feature_class":"P",
    "gn:feature_code":"PPL",
    "gn:name":"G\u016br Mardow",
    "gn:population":0,
    "gn:timezone":"Asia/Tehran",
    "iso:country":"IR",
    "name:fas_x_preferred":[
        "\u06af\u0648\u0631 \u0645\u0631\u062f\u0648"
    ],
    "name:fas_x_variant":[
        "G\u016br Mardow"
    ],
    "wof:name":"Gur Mardow",
    "wof:placetype":"locality"
},
  "geometry": {"coordinates":[60.80347,27.59988],"type":"Point"}
}