{
  "type": "Feature",
  "properties": {
    "gn:admin1_code":"13.0",
    "gn:asciiname":"Agah-e Sofla",
    "gn:country_code":"IR",
    "gn:dem":1637,
    "gn:feature_class":"P",
    "gn:feature_code":"PPL",
    "gn:name":"\u0100g\u0101h-e Sofl\u00e1",
    "gn:population":0,
    "gn:timezone":"Asia/Tehran",
    "iso:country":"IR",
    "name:fas_x_preferred":[
        "\u0622\u06af\u0627\u0647\u0650 \u0633\u064f\u0641\u0644\u064e\u0649"
    ],
    "name:fas_x_variant":[
        "\u0622\u06af\u0627\u0647 \u0633\u0641\u0644\u0649",
        "\u0100g\u0101h-e Sofl\u00e1"
    ],
    "wof:name":"Agah-e Sofla",
    "wof:placetype":"locality"
},
  "geometry": {"coordinates":[47.3381,34.9016],"type":"Point"}
}