{
  "type": "Feature",
  "properties": {
    "gn:admin1_code":"4.0",
    "gn:asciiname":"Deh-e Mirzang",
    "gn:country_code":"IR",
    "gn:dem":483,
    "gn:feature_class":"P",
    "gn:feature_code":"PPL",
    "gn:name":"Deh-e M\u012brzang",
    "gn:population":0,
    "gn:timezone":"Asia/Tehran",
    "iso:country":"IR",
    "name:fas_x_preferred":[
        "\u062f\u0647 \u0645\u06cc\u0631\u0632\u0646\u06af"
    ],
    "name:fas_x_variant":[
        "M\u012br Zang",
        "Deh-e M\u012brzang"
    ],
    "wof:name":"Deh-e Mirzang",
    "wof:placetype":"locality"
},
  "geometry": {"coordinates":[61.5293,31.0719],"type":"Point"}
}