{
  "type": "Feature",
  "properties": {
    "gn:admin1_code":"23",
    "gn:asciiname":"Ramavand",
    "gn:country_code":"IR",
    "gn:dem":629,
    "gn:feature_class":"P",
    "gn:feature_code":"PPL",
    "gn:name":"Ram\u0101vand",
    "gn:population":0,
    "gn:timezone":"Asia/Tehran",
    "iso:country":"IR",
    "name:fas_x_preferred":[
        "\u0631\u0645\u0627\u0648\u0646\u062f"
    ],
    "name:fas_x_variant":[
        "Ram\u0101vand"
    ],
    "wof:name":"Ramavand",
    "wof:placetype":"locality"
},
  "geometry": {"coordinates":[47.167,33.3241],"type":"Point"}
}