{
  "type": "Feature",
  "properties": {
    "gn:admin1_code":"4.0",
    "gn:asciiname":"Deh-e Hoseyn Zhandar",
    "gn:country_code":"IR",
    "gn:dem":480,
    "gn:feature_class":"P",
    "gn:feature_code":"PPL",
    "gn:name":"Deh-e \u1e28oseyn Zh\u0101nd\u0101r",
    "gn:population":0,
    "gn:timezone":"Asia/Tehran",
    "iso:country":"IR",
    "name:fas_x_preferred":[
        "\u062f\u0647 \u062d\u0633\u06cc\u0646 \u0698\u0627\u0646\u062f\u0627\u0631"
    ],
    "name:fas_x_variant":[
        "Deh-e \u1e28oseyn Zh\u0101nd\u0101r"
    ],
    "wof:name":"Deh-e Hoseyn Zhandar",
    "wof:placetype":"locality"
},
  "geometry": {"coordinates":[61.428,30.9035],"type":"Point"}
}