{
  "type": "Feature",
  "properties": {
    "gn:admin1_code":"32",
    "gn:asciiname":"Esma`il Kandi",
    "gn:country_code":"IR",
    "gn:dem":2015,
    "gn:feature_class":"P",
    "gn:feature_code":"PPL",
    "gn:name":"Esm\u0101\u2018\u012bl Kand\u012b",
    "gn:population":0,
    "gn:timezone":"Asia/Tehran",
    "iso:country":"IR",
    "name:fas_x_preferred":[
        "Esm\u0101\u2018\u012bl Kand\u012b"
    ],
    "wof:name":"Esma`il Kandi",
    "wof:placetype":"locality"
},
  "geometry": {"coordinates":[47.50583,38.29778],"type":"Point"}
}