{
  "type": "Feature",
  "properties": {
    "gn:admin1_code":"32",
    "gn:asciiname":"Aq Bolagh-e Pa'in",
    "gn:country_code":"IR",
    "gn:dem":1709,
    "gn:feature_class":"P",
    "gn:feature_code":"PPL",
    "gn:name":"\u0100q Bol\u0101gh-e P\u0101\u2019\u012bn",
    "gn:population":0,
    "gn:timezone":"Asia/Tehran",
    "iso:country":"IR",
    "name:fas_x_preferred":[
        "\u0622\u063a \u0628\u064f\u0644\u0627\u063a\u0650 \u067e\u0627\u0626\u064a\u0646"
    ],
    "name:fas_x_variant":[
        "\u0622\u0642 \u0628\u0644\u0627\u063a \u067e\u0627\u0626\u064a\u0646",
        "\u0100gh Bol\u0101gh-e P\u0101\u2019\u012bn",
        "\u0100q Bol\u0101gh-e P\u0101\u2019\u012bn"
    ],
    "wof:name":"Aq Bolagh-e Pa'in",
    "wof:placetype":"locality"
},
  "geometry": {"coordinates":[48.2599,38.6351],"type":"Point"}
}