{
  "type": "Feature",
  "properties": {
    "gn:admin1_code":"43.0",
    "gn:asciiname":"Tangeh-ye Raz",
    "gn:country_code":"IR",
    "gn:dem":1031,
    "gn:feature_class":"P",
    "gn:feature_code":"PPL",
    "gn:name":"Tangeh-ye R\u0101z",
    "gn:population":0,
    "gn:timezone":"Asia/Tehran",
    "iso:country":"IR",
    "name:ara_x_preferred":[
        "\u062a\u0646\u063a\u0629 \u0631\u0627\u0632"
    ],
    "name:ceb_x_preferred":[
        "Tangeh-ye R\u0101z"
    ],
    "name:fas_x_preferred":[
        "Tangeh-ye R\u0101z"
    ],
    "name:fas_x_variant":[
        "\u062a\u0646\u06af\u0647 \u0631\u0627\u0632",
        "Tangeh R\u0101z",
        "Tangeh-ye Z\u0101r",
        "\u062a\u0646\u06af\u0647\u200c\u0631\u0627\u0632"
    ],
    "name:swe_x_preferred":[
        "Tangeh-ye R\u0101z"
    ],
    "name:und_x_variant":[
        "Tangeh R\u0101z",
        "Tangeh-ye Z\u0101r",
        "\u062a\u0646\u06af\u0647 \u0631\u0627\u0632"
    ],
    "wof:name":"Tangeh-ye Raz",
    "wof:placetype":"locality"
},
  "geometry": {"coordinates":[56.93281999999999,37.95411],"type":"Point"}
}