{
  "type": "Feature",
  "properties": {
    "gn:admin1_code":"42",
    "gn:asciiname":"Kalateh-ye Dasht Khaneh",
    "gn:country_code":"IR",
    "gn:dem":1576,
    "gn:feature_class":"P",
    "gn:feature_code":"PPL",
    "gn:name":"Kal\u0101teh-ye Dasht Kh\u0101neh",
    "gn:population":0,
    "gn:timezone":"Asia/Tehran",
    "iso:country":"IR",
    "name:fas_x_preferred":[
        "Kal\u0101teh-ye Dasht Kh\u0101neh"
    ],
    "wof:name":"Kalateh-ye Dasht Khaneh",
    "wof:placetype":"locality"
},
  "geometry": {"coordinates":[58.67139,34.145],"type":"Point"}
}