{
  "type": "Feature",
  "properties": {
    "gn:admin1_code":"7.0",
    "gn:asciiname":"`Abbasabad",
    "gn:country_code":"IR",
    "gn:dem":1387,
    "gn:feature_class":"P",
    "gn:feature_code":"PPL",
    "gn:name":"\u2018Abb\u0101s\u0101b\u0101d",
    "gn:population":0,
    "gn:timezone":"Asia/Tehran",
    "iso:country":"IR",
    "name:ara_x_preferred":[
        "\u0639\u0628\u0627\u0633\u200c\u0622\u0628\u0627\u062f \u0627\u0633\u0643\u0646\u062f\u0631\u064a"
    ],
    "name:fas_x_preferred":[
        "\u0639\u0628\u0627\u0633 \u0622\u0628\u0627\u062f"
    ],
    "name:fas_x_variant":[
        "\u2018Abb\u0101s\u0101b\u0101d",
        "\u0639\u0628\u0627\u0633 \u0622\u0628\u0627\u062f \u0627\u0633\u06a9\u0646\u062f\u0631\u06cc",
        "\u0639\u0628\u0627\u0633\u200c\u0622\u0628\u0627\u062f \u0627\u0633\u06a9\u0646\u062f\u0631\u06cc"
    ],
    "name:msa_x_preferred":[
        "Abbasabad-e Eskandari"
    ],
    "name:pol_x_preferred":[
        "Abbasabad-e Eskandari"
    ],
    "name:und_x_variant":[
        "\u2018Abb\u0101s\u0101b\u0101d-e Eskandar\u012b"
    ],
    "wof:name":"`Abbasabad",
    "wof:placetype":"locality"
},
  "geometry": {"coordinates":[54.04115,28.91503],"type":"Point"}
}