{
  "type": "Feature",
  "properties": {
    "gn:admin1_code":"10.0",
    "gn:asciiname":"Chenar Sarab",
    "gn:country_code":"IR",
    "gn:dem":1326,
    "gn:feature_class":"P",
    "gn:feature_code":"PPL",
    "gn:name":"Chen\u0101r Sar\u0101b",
    "gn:population":0,
    "gn:timezone":"Asia/Tehran",
    "iso:country":"IR",
    "name:fas_x_preferred":[
        "Chen\u0101r Sar\u0101b"
    ],
    "name:fas_x_variant":[
        "\u0686\u0650\u0646\u0627\u0631 \u0633\u064e\u0631\u0627\u0628"
    ],
    "wof:name":"Chenar Sarab",
    "wof:placetype":"locality"
},
  "geometry": {"coordinates":[46.48333,33.73333],"type":"Point"}
}