{
  "type": "Feature",
  "properties": {
    "gn:admin1_code":"1",
    "gn:asciiname":"Quzlu-ye Khaneqah",
    "gn:country_code":"IR",
    "gn:dem":1773,
    "gn:feature_class":"P",
    "gn:feature_code":"PPL",
    "gn:name":"Q\u016bzl\u016b-ye Kh\u0101neq\u0101h",
    "gn:population":0,
    "gn:timezone":"Asia/Tehran",
    "iso:country":"IR",
    "name:fas_x_preferred":[
        "Q\u016bzl\u016b-ye Kh\u0101neq\u0101h"
    ],
    "name:fas_x_variant":[
        "\u0642\u0648\u0632\u0644\u0648 \u062e\u0627\u0646\u0642\u0627\u0647",
        "Q\u016bzl\u016b-ye Kh\u0101n\u012byeh"
    ],
    "wof:name":"Quzlu-ye Khaneqah",
    "wof:placetype":"locality"
},
  "geometry": {"coordinates":[44.9518,38.7949],"type":"Point"}
}