{
  "type": "Feature",
  "properties": {
    "gn:admin1_code":"40.0",
    "gn:asciiname":"Mazra`eh-ye Hajar-e Bala",
    "gn:country_code":"IR",
    "gn:dem":2246,
    "gn:feature_class":"P",
    "gn:feature_code":"PPLF",
    "gn:name":"Mazra\u2018eh-ye H\u0101jar-e B\u0101l\u0101",
    "gn:population":0,
    "gn:timezone":"Asia/Tehran",
    "iso:country":"IR",
    "name:fas_x_preferred":[
        "Mazra\u2018eh-ye H\u0101jar-e B\u0101l\u0101"
    ],
    "name:fas_x_variant":[
        "\u0645\u0632\u0631\u0639\u0647 \u0647\u0627\u062c\u0631 \u0628\u0627\u0644\u0627"
    ],
    "wof:name":"Mazra`eh-ye Hajar-e Bala",
    "wof:placetype":"locality"
},
  "geometry": {"coordinates":[54.35352,31.40175],"type":"Point"}
}