{
  "type": "Feature",
  "properties": {
    "gn:admin1_code":"34",
    "gn:asciiname":"Owjan",
    "gn:country_code":"IR",
    "gn:dem":973,
    "gn:feature_class":"P",
    "gn:feature_code":"PPL",
    "gn:name":"Owj\u0101n",
    "gn:population":0,
    "gn:timezone":"Asia/Tehran",
    "iso:country":"IR",
    "name:fas_x_preferred":[
        "Owj\u0101n"
    ],
    "name:fas_x_variant":[
        "\u0627\u0648\u062c\u0627\u0646"
    ],
    "wof:name":"Owjan",
    "wof:placetype":"locality"
},
  "geometry": {"coordinates":[50.37737,34.86946],"type":"Point"}
}