{
  "type": "Feature",
  "properties": {
    "gn:admin1_code":"15",
    "gn:asciiname":"Moti`at",
    "gn:country_code":"IR",
    "gn:dem":16,
    "gn:feature_class":"P",
    "gn:feature_code":"PPL",
    "gn:name":"Mo\u0163\u012b\u2018\u0101t",
    "gn:population":0,
    "gn:timezone":"Asia/Tehran",
    "iso:country":"IR",
    "name:fas_x_preferred":[
        "Mo\u0163\u012b\u2018\u0101t"
    ],
    "name:fas_x_variant":[
        "\u0645\u0637\u06cc\u0639\u0627\u062a"
    ],
    "name:und_x_variant":[
        "Mo\u0163e\u2019\u0101t",
        "Mo\u0163ey\u2018\u0101t"
    ],
    "wof:name":"Moti`at",
    "wof:placetype":"locality"
},
  "geometry": {"coordinates":[48.33936,31.49244],"type":"Point"}
}