{
  "type": "Feature",
  "properties": {
    "gn:admin1_code":"3.0",
    "gn:asciiname":"`Algi-ye Sofla",
    "gn:country_code":"IR",
    "gn:dem":1599,
    "gn:feature_class":"P",
    "gn:feature_code":"PPL",
    "gn:name":"\u2018Alg\u012b-ye Sofl\u00e1",
    "gn:population":0,
    "gn:timezone":"Asia/Tehran",
    "iso:country":"IR",
    "name:fas_x_preferred":[
        "\u2018Alg\u012b-ye Sofl\u00e1"
    ],
    "name:fas_x_variant":[
        "\u0639\u0644\u06af\u06cc \u0633\u0641\u0644\u06cc"
    ],
    "wof:name":"`Algi-ye Sofla",
    "wof:placetype":"locality"
},
  "geometry": {"coordinates":[50.00375,32.27973],"type":"Point"}
}