{
  "type": "Feature",
  "properties": {
    "gn:admin1_code":"15",
    "gn:asciiname":"Kuh-e Halil",
    "gn:country_code":"IR",
    "gn:dem":640,
    "gn:feature_class":"P",
    "gn:feature_code":"PPL",
    "gn:name":"K\u016bh-e Hal\u012bl",
    "gn:population":0,
    "gn:timezone":"Asia/Tehran",
    "iso:country":"IR",
    "name:fas_x_preferred":[
        "\u06a9\u0648\u0647 \u0647\u0644\u06cc\u0644"
    ],
    "name:fas_x_variant":[
        "Rag-e Hal\u012bl",
        "K\u016bh-e Hal\u012bl",
        "\u0631\u06af \u0647\u0644\u06cc\u0644"
    ],
    "wof:name":"Kuh-e Halil",
    "wof:placetype":"locality"
},
  "geometry": {"coordinates":[49.244,32.2044],"type":"Point"}
}