{
  "type": "Feature",
  "properties": {
    "gn:admin1_code":"8",
    "gn:asciiname":"Boq`eh-ye Pir Taher",
    "gn:country_code":"IR",
    "gn:dem":21,
    "gn:feature_class":"P",
    "gn:feature_code":"PPLL",
    "gn:name":"Boq\u2018eh-ye P\u012br \u0162\u0101her",
    "gn:population":0,
    "gn:timezone":"Asia/Tehran",
    "iso:country":"IR",
    "name:fas_x_preferred":[
        "\u0628\u0642\u0639\u0647 \u067e\u06cc\u0631 \u0637\u0627\u0647\u0631"
    ],
    "name:fas_x_variant":[
        "Boq\u2018eh-ye P\u012br \u0162\u0101her"
    ],
    "wof:name":"Boq`eh-ye Pir Taher",
    "wof:placetype":"locality"
},
  "geometry": {"coordinates":[49.37606,37.21751],"type":"Point"}
}