{
  "type": "Feature",
  "properties": {
    "gn:admin1_code":"28.0",
    "gn:asciiname":"Fardovan",
    "gn:country_code":"IR",
    "gn:dem":1576,
    "gn:feature_class":"P",
    "gn:feature_code":"PPL",
    "gn:name":"Fardov\u0101n",
    "gn:population":0,
    "gn:timezone":"Asia/Tehran",
    "iso:country":"IR",
    "name:fas_x_preferred":[
        "Nezd\u016bn"
    ],
    "name:fas_x_variant":[
        "Fardov\u0101n",
        "\u0641\u0631\u062f\u0648\u0627\u0646",
        "\u0641\u0631 \u062a\u0645\u0627\u0646"
    ],
    "name:und_x_variant":[
        "Far Tom\u0101n"
    ],
    "wof:name":"Fardovan",
    "wof:placetype":"locality"
},
  "geometry": {"coordinates":[51.64093,32.68458],"type":"Point"}
}