{
  "type": "Feature",
  "properties": {
    "gn:admin1_code":"8.0",
    "gn:asciiname":"Now Deh-e Pa'in",
    "gn:country_code":"IR",
    "gn:dem":1283,
    "gn:feature_class":"P",
    "gn:feature_code":"PPL",
    "gn:name":"Now Deh-e P\u0101\u2019\u012bn",
    "gn:population":0,
    "gn:timezone":"Asia/Tehran",
    "iso:country":"IR",
    "name:fas_x_preferred":[
        "\u0646\u0648 \u062f\u0647 \u067e\u0627\u0626\u06cc\u0646"
    ],
    "name:und_x_variant":[
        "Now Deh-e P\u0101\u2019\u012bn",
        "\u0646\u0648 \u062f\u0647 \u067e\u0627\u0626\u06cc\u0646",
        "Now Deh"
    ],
    "wof:name":"Now Deh-e Pa'in",
    "wof:placetype":"locality"
},
  "geometry": {"coordinates":[49.73342,36.67542],"type":"Point"}
}