{
  "type": "Feature",
  "properties": {
    "gn:admin1_code":"15",
    "gn:asciiname":"Nashalil-e Sofla",
    "gn:country_code":"IR",
    "gn:dem":1325,
    "gn:feature_class":"P",
    "gn:feature_code":"PPL",
    "gn:name":"N\u0101shal\u012bl-e Sofl\u00e1",
    "gn:population":0,
    "gn:timezone":"Asia/Tehran",
    "iso:country":"IR",
    "name:fas_x_preferred":[
        "N\u0101shal\u012bl-e Sofl\u00e1"
    ],
    "wof:name":"Nashalil-e Sofla",
    "wof:placetype":"locality"
},
  "geometry": {"coordinates":[49.86667,31.73333],"type":"Point"}
}