{
  "type": "Feature",
  "properties": {
    "gn:admin1_code":"23.0",
    "gn:asciiname":"Darreh Besar",
    "gn:country_code":"IR",
    "gn:dem":1749,
    "gn:feature_class":"P",
    "gn:feature_code":"PPL",
    "gn:name":"Darreh Besar",
    "gn:population":0,
    "gn:timezone":"Asia/Tehran",
    "iso:country":"IR",
    "name:fas_x_preferred":[
        "\u062f\u0631\u0651\u0647 \u0628\u0635\u0631 \u0628\u0627\u0644\u0627"
    ],
    "name:fas_x_variant":[
        "Darreh Besar-e B\u0101l\u0101",
        "Darreh Ba\u015far-e B\u0101l\u0101",
        "\u062f\u0631\u0647 \u0628\u0633\u0631",
        "\u062f\u0631\u0647 \u0628\u0633\u0631 \u0639\u0644\u064a\u0627"
    ],
    "name:und_x_variant":[
        "Darreh Besar-e \u2018Oly\u0101"
    ],
    "wof:name":"Darreh Besar",
    "wof:placetype":"locality"
},
  "geometry": {"coordinates":[48.5945,33.5909],"type":"Point"}
}