{
  "type": "Feature",
  "properties": {
    "gn:admin1_code":"40.0",
    "gn:asciiname":"`Aqda",
    "gn:country_code":"IR",
    "gn:dem":1152,
    "gn:feature_class":"P",
    "gn:feature_code":"PPL",
    "gn:name":"\u2018Aqd\u0101",
    "gn:population":0,
    "gn:timezone":"Asia/Tehran",
    "iso:country":"IR",
    "name:fas_x_preferred":[
        "\u0639\u0642\u062f\u0627"
    ],
    "name:fas_x_variant":[
        "\u0627\u064e\u063a\u062f\u064e",
        "\u2018Aqd\u0101"
    ],
    "name:und_x_variant":[
        "Aghda"
    ],
    "wof:name":"`Aqda",
    "wof:placetype":"locality"
},
  "geometry": {"coordinates":[53.6297,32.4409],"type":"Point"}
}