{
  "type": "Feature",
  "properties": {
    "gn:admin1_code":"4",
    "gn:asciiname":"Qal`eh-ye Ebik",
    "gn:country_code":"IR",
    "gn:dem":1100,
    "gn:feature_class":"P",
    "gn:feature_code":"PPL",
    "gn:name":"Qal\u2018eh-ye Eb\u012bk",
    "gn:population":0,
    "gn:timezone":"Asia/Tehran",
    "iso:country":"IR",
    "name:fas_x_preferred":[
        "\u0642\u0644\u0639\u0647 \u0627\u0628\u06cc\u06a9"
    ],
    "name:fas_x_variant":[
        "Qal\u2018eh-ye Eb\u012bk"
    ],
    "wof:name":"Qal`eh-ye Ebik",
    "wof:placetype":"locality"
},
  "geometry": {"coordinates":[62.7705,27.3624],"type":"Point"}
}