{
  "type": "Feature",
  "properties": {
    "gn:admin1_code":"29",
    "gn:asciiname":"Sefid Khani",
    "gn:country_code":"IR",
    "gn:dem":1510,
    "gn:feature_class":"P",
    "gn:feature_code":"PPL",
    "gn:name":"Sef\u012bd Kh\u0101n\u012b",
    "gn:population":0,
    "gn:timezone":"Asia/Tehran",
    "iso:country":"IR",
    "name:fas_x_preferred":[
        "\u0633\u0641\u06cc\u062f \u062e\u0627\u0646\u06cc"
    ],
    "name:fas_x_variant":[
        "Sef\u012bd Kh\u0101n\u012b",
        "\u0633\u0641\u06cc\u062f\u062e\u0627\u0646\u06cc"
    ],
    "wof:name":"Sefid Khani",
    "wof:placetype":"locality"
},
  "geometry": {"coordinates":[56.676,28.5263],"type":"Point"}
}