{
  "type": "Feature",
  "properties": {
    "gn:admin1_code":"11",
    "gn:asciiname":"Sarchil",
    "gn:country_code":"IR",
    "gn:dem":18,
    "gn:feature_class":"P",
    "gn:feature_code":"PPL",
    "gn:name":"Sarch\u012bl",
    "gn:population":0,
    "gn:timezone":"Asia/Tehran",
    "iso:country":"IR",
    "name:ara_x_preferred":[
        "\u0633\u0631\u062a\u0634\u064a\u0644"
    ],
    "name:fas_x_preferred":[
        "\u0633\u064e\u0631\u062c\u064a\u0646"
    ],
    "name:fas_x_variant":[
        "Sarj\u012bn",
        "\u0633\u0631\u0686\u064a\u0644",
        "\u0633\u0631\u0686\u064a\u0644 \u062c\u0644\u0627\u0628\u06cc",
        "\u0633\u0631\u0686\u06cc\u0644"
    ],
    "name:msa_x_preferred":[
        "Sarchil"
    ],
    "name:und_x_variant":[
        "Sarch\u012bl",
        "Sarch\u012bl Jall\u0101b\u012b",
        "Sarch\u012bl Jal\u0101b\u012b"
    ],
    "wof:name":"Sarchil",
    "wof:placetype":"locality"
},
  "geometry": {"coordinates":[56.66781999999999,27.34066],"type":"Point"}
}