{
  "type": "Feature",
  "properties": {
    "gn:admin1_code":"1",
    "gn:asciiname":"Uch Tappeh-ye Kord",
    "gn:country_code":"IR",
    "gn:dem":1291,
    "gn:feature_class":"P",
    "gn:feature_code":"PPL",
    "gn:name":"\u016ach Tappeh-ye Kord",
    "gn:population":0,
    "gn:timezone":"Asia/Tehran",
    "iso:country":"IR",
    "name:fas_x_preferred":[
        "\u0648\u0686 \u062a\u064e\u067e\u0650\u0651\u06c0 \u0643\u064f\u0631\u062f"
    ],
    "name:fas_x_variant":[
        "\u0627\u0648\u0686 \u062a\u067e\u0651\u0647 \u06a9\u0631\u062f",
        "\u016ach Tappeh-ye Kord"
    ],
    "wof:name":"Uch Tappeh-ye Kord",
    "wof:placetype":"locality"
},
  "geometry": {"coordinates":[46.0499,37.03542],"type":"Point"}
}