{
  "type": "Feature",
  "properties": {
    "gn:admin1_code":"28",
    "gn:asciiname":"Lor Kosh",
    "gn:country_code":"IR",
    "gn:dem":2229,
    "gn:feature_class":"P",
    "gn:feature_code":"PPL",
    "gn:name":"Lor Kosh",
    "gn:population":0,
    "gn:timezone":"Asia/Tehran",
    "iso:country":"IR",
    "name:fas_x_preferred":[
        "\u0644\u0631 \u06a9\u0634"
    ],
    "name:und_x_variant":[
        "L\u016br Kosh",
        "Lor Kosh"
    ],
    "wof:name":"Lor Kosh",
    "wof:placetype":"locality"
},
  "geometry": {"coordinates":[51.6865,30.92675],"type":"Point"}
}