{
  "type": "Feature",
  "properties": {
    "gn:admin1_code":"29",
    "gn:asciiname":"Deh-e `Abdi",
    "gn:country_code":"IR",
    "gn:dem":2402,
    "gn:feature_class":"P",
    "gn:feature_code":"PPL",
    "gn:name":"Deh-e \u2018Abd\u012b",
    "gn:population":0,
    "gn:timezone":"Asia/Tehran",
    "iso:country":"IR",
    "name:fas_x_preferred":[
        "\u062f\u0647 \u0639\u0628\u062f\u06cc"
    ],
    "name:fas_x_variant":[
        "Deh-e \u2018Abd\u012b"
    ],
    "wof:name":"Deh-e `Abdi",
    "wof:placetype":"locality"
},
  "geometry": {"coordinates":[56.0371,29.7604],"type":"Point"}
}