{
  "type": "Feature",
  "properties": {
    "gn:admin1_code":"29",
    "gn:asciiname":"Shoja`abad",
    "gn:country_code":"IR",
    "gn:dem":328,
    "gn:feature_class":"P",
    "gn:feature_code":"PPL",
    "gn:name":"Shoj\u0101\u2018\u0101b\u0101d",
    "gn:population":0,
    "gn:timezone":"Asia/Tehran",
    "iso:country":"IR",
    "name:fas_x_preferred":[
        "Shoj\u0101\u2018\u0101b\u0101d"
    ],
    "wof:name":"Shoja`abad",
    "wof:placetype":"locality"
},
  "geometry": {"coordinates":[57.81472,30.46278],"type":"Point"}
}