{
  "type": "Feature",
  "properties": {
    "gn:admin1_code":"8",
    "gn:asciiname":"Budian",
    "gn:country_code":"IR",
    "gn:dem":-12,
    "gn:feature_class":"P",
    "gn:feature_code":"PPL",
    "gn:name":"B\u016bd\u012b\u0101n",
    "gn:population":0,
    "gn:timezone":"Asia/Tehran",
    "iso:country":"IR",
    "name:ceb_x_preferred":[
        "B\u016bd\u012b\u0101n"
    ],
    "name:fas_x_preferred":[
        "\u0628\u0648\u062f\u06cc\u0627\u0646"
    ],
    "name:fas_x_variant":[
        "B\u016bd\u012b\u0101n"
    ],
    "name:msa_x_preferred":[
        "Budian"
    ],
    "name:swe_x_preferred":[
        "B\u016bd\u012b\u0101n"
    ],
    "name:ukr_x_preferred":[
        "\u0411\u0443\u0434\u0456\u044f\u043d"
    ],
    "name:und_x_variant":[
        "B\u016bd\u012b\u0101n"
    ],
    "wof:name":"Budian",
    "wof:placetype":"locality"
},
  "geometry": {"coordinates":[49.45607,37.315],"type":"Point"}
}