{
  "type": "Feature",
  "properties": {
    "gn:admin1_code":"32.0",
    "gn:asciiname":"`Alirezaabad-e Qadim",
    "gn:country_code":"IR",
    "gn:dem":76,
    "gn:feature_class":"P",
    "gn:feature_code":"PPL",
    "gn:name":"\u2018Al\u012bre\u1e95\u0101\u0101b\u0101d-e Qad\u012bm",
    "gn:population":0,
    "gn:timezone":"Asia/Tehran",
    "iso:country":"IR",
    "name:fas_x_preferred":[
        "\u0639\u064e\u0644\u064a\u0631\u0650\u0632\u0627\u0651\u0628\u0627\u062f\u0650 \u0642\u064e\u062f\u064a\u0645"
    ],
    "name:fas_x_variant":[
        "\u0639\u0644\u06cc\u0631\u0636\u0627 \u0622\u0628\u0627\u062f \u0642\u062f\u064a\u0645",
        "\u2018Al\u012brez\u0101\u0101b\u0101d-e Qad\u012bm",
        "\u2018Al\u012brez\u0101\u0101b\u0101d",
        "\u0639\u064e\u0644\u064a\u0631\u0650\u0632\u0627 \u0622\u0628\u0627\u062f",
        "\u2018Al\u012bre\u1e95\u0101\u0101b\u0101d-e Qad\u012bm"
    ],
    "wof:name":"`Alirezaabad-e Qadim",
    "wof:placetype":"locality"
},
  "geometry": {"coordinates":[47.7126,39.5838],"type":"Point"}
}