{
  "type": "Feature",
  "properties": {
    "gn:admin1_code":"7",
    "gn:asciiname":"Sharafabad",
    "gn:country_code":"IR",
    "gn:dem":2350,
    "gn:feature_class":"P",
    "gn:feature_code":"PPL",
    "gn:name":"Sharaf\u0101b\u0101d",
    "gn:population":0,
    "gn:timezone":"Asia/Tehran",
    "iso:country":"IR",
    "name:fas_x_preferred":[
        "\u0634\u064e\u0631\u064e\u0641 \u0622\u0628\u0627\u062f"
    ],
    "name:fas_x_variant":[
        "\u0634\u064e\u0631\u0641 \u0622\u0628\u0627\u062f",
        "Sharaf\u0101b\u0101d"
    ],
    "name:und_x_variant":[
        "Sharf\u0101b\u0101d"
    ],
    "wof:name":"Sharafabad",
    "wof:placetype":"locality"
},
  "geometry": {"coordinates":[52.93333000000001,30.61667000000001],"type":"Point"}
}