{
  "type": "Feature",
  "properties": {
    "gn:admin1_code":"35",
    "gn:asciiname":"Kardi Kola",
    "gn:country_code":"IR",
    "gn:dem":77,
    "gn:feature_class":"P",
    "gn:feature_code":"PPL",
    "gn:name":"K\u0101rd\u012b Kol\u0101",
    "gn:population":0,
    "gn:timezone":"Asia/Tehran",
    "iso:country":"IR",
    "name:ceb_x_preferred":[
        "K\u0101rd\u012b Kol\u0101"
    ],
    "name:fas_x_preferred":[
        "\u0643\u0627\u0631\u062f\u06cc \u0643\u064f\u0644\u0627\u06cc \u0634\u064e\u0631\u0642\u06cc"
    ],
    "name:fas_x_variant":[
        "K\u0101rd\u012b Kol\u0101-ye Sharq\u012b",
        "K\u0101rd\u012b Kol\u0101",
        "\u0643\u0627\u0631\u062f\u06cc \u0643\u0644\u0627",
        "\u06a9\u0627\u0631\u062f\u06cc\u200c\u06a9\u0644\u0627"
    ],
    "name:mzn_x_preferred":[
        "\u06a9\u0627\u0631\u062f\u06cc\u200c\u06a9\u0644\u0627"
    ],
    "name:swe_x_preferred":[
        "K\u0101rd\u012b Kol\u0101"
    ],
    "wof:name":"Kardi Kola",
    "wof:placetype":"locality"
},
  "geometry": {"coordinates":[52.58846,36.36739],"type":"Point"}
}