{
  "type": "Feature",
  "properties": {
    "gn:admin1_code":"8",
    "gn:asciiname":"Khaneh Sara-ye `Olya",
    "gn:country_code":"IR",
    "gn:dem":204,
    "gn:feature_class":"P",
    "gn:feature_code":"PPL",
    "gn:name":"Kh\u0101neh Sar\u0101-ye \u2018Oly\u0101",
    "gn:population":0,
    "gn:timezone":"Asia/Tehran",
    "iso:country":"IR",
    "name:fas_x_preferred":[
        "Kh\u0101neh K\u0101sar\u0101y"
    ],
    "name:fas_x_variant":[
        "\u062e\u0627\u0646\u0647 \u0633\u0631\u0627 \u0639\u0644\u06cc\u0627",
        "\u062e\u0627\u0646\u06a9\u0633\u0631\u0627\u06cc \u0639\u0644\u06cc\u0627",
        "\u062e\u0627\u0646\u06af\u0647 \u0633\u0631\u0627"
    ],
    "name:und_x_variant":[
        "Kh\u0101neh Sar\u0101-ye \u2018Oly\u0101",
        "Kh\u0101naksar\u0101-ye \u2018Oly\u0101",
        "Kh\u0101negeh Sar\u0101"
    ],
    "wof:name":"Khaneh Sara-ye `Olya",
    "wof:placetype":"locality"
},
  "geometry": {"coordinates":[50.27591,36.95589],"type":"Point"}
}