{
  "type": "Feature",
  "properties": {
    "gn:admin1_code":"42.0",
    "gn:asciiname":"Kalateh-ye Zeynal",
    "gn:country_code":"IR",
    "gn:dem":1392,
    "gn:feature_class":"P",
    "gn:feature_code":"PPL",
    "gn:name":"Kal\u0101teh-ye Zeynal",
    "gn:population":0,
    "gn:timezone":"Asia/Tehran",
    "iso:country":"IR",
    "name:ceb_x_preferred":[
        "Kal\u0101teh-ye Zeynal"
    ],
    "name:fas_x_preferred":[
        "\u06a9\u0644\u0627\u062a\u0647 \u0632\u06cc\u0646\u0644"
    ],
    "name:fas_x_variant":[
        "Kal\u0101teh Zeynal",
        "Kal\u0101teh-ye Zeynal"
    ],
    "name:swe_x_preferred":[
        "Kal\u0101teh-ye Zeynal"
    ],
    "wof:name":"Kalateh-ye Zeynal",
    "wof:placetype":"locality"
},
  "geometry": {"coordinates":[58.3529,36.46068],"type":"Point"}
}