{
  "type": "Feature",
  "properties": {
    "gn:admin1_code":"11",
    "gn:asciiname":"Mazru",
    "gn:country_code":"IR",
    "gn:dem":1162,
    "gn:feature_class":"P",
    "gn:feature_code":"PPL",
    "gn:name":"Mazr\u016b",
    "gn:population":0,
    "gn:timezone":"Asia/Tehran",
    "iso:country":"IR",
    "name:fas_x_preferred":[
        "\u0645\u0632\u0631\u0648"
    ],
    "name:fas_x_variant":[
        "Mazr\u016b"
    ],
    "name:msa_x_preferred":[
        "Mazru"
    ],
    "wof:name":"Mazru",
    "wof:placetype":"locality"
},
  "geometry": {"coordinates":[56.0993,27.9796],"type":"Point"}
}