{
  "type": "Feature",
  "properties": {
    "gn:admin1_code":"7",
    "gn:asciiname":"Hoseynabad-e Dardun",
    "gn:country_code":"IR",
    "gn:dem":1680,
    "gn:feature_class":"P",
    "gn:feature_code":"PPL",
    "gn:name":"\u1e28oseyn\u0101b\u0101d-e D\u0101rd\u016bn",
    "gn:population":0,
    "gn:timezone":"Asia/Tehran",
    "iso:country":"IR",
    "name:fas_x_preferred":[
        "\u062d\u0633\u06cc\u0646 \u0622\u0628\u0627\u062f \u062f\u0627\u0631\u062f\u0648\u0646"
    ],
    "name:fas_x_variant":[
        "\u1e28oseyn\u0101b\u0101d",
        "\u1e28oseyn\u0101b\u0101d-e D\u0101rd\u016bn",
        "\u062d\u0633\u06cc\u0646 \u0622\u0628\u0627\u062f \u062f\u0627\u0631\u062f\u0627\u0646",
        "\u062d\u0633\u06cc\u0646\u200c\u0622\u0628\u0627\u062f \u062f\u0627\u0631\u062f\u0627\u0646"
    ],
    "name:msa_x_preferred":[
        "Hoseynabad-e Dardan"
    ],
    "name:und_x_variant":[
        "\u1e28oseyn\u0101b\u0101d-e D\u0101rd\u0101n"
    ],
    "wof:name":"Hoseynabad-e Dardun",
    "wof:placetype":"locality"
},
  "geometry": {"coordinates":[52.4142,30.2894],"type":"Point"}
}