{
  "type": "Feature",
  "properties": {
    "gn:admin1_code":"41",
    "gn:asciiname":"Khung-e Bala",
    "gn:country_code":"IR",
    "gn:dem":2249,
    "gn:feature_class":"P",
    "gn:feature_code":"PPL",
    "gn:name":"Kh\u016bng-e B\u0101l\u0101",
    "gn:population":0,
    "gn:timezone":"Asia/Tehran",
    "iso:country":"IR",
    "name:fas_x_preferred":[
        "Kh\u016bng-e B\u0101l\u0101"
    ],
    "name:fas_x_variant":[
        "\u062e\u0648\u0646\u06af \u0628\u0627\u0644\u0627",
        "Kh\u016bn\u012bk",
        "\u0622\u064a\u0634\u06a9"
    ],
    "name:und_x_variant":[
        "Khurg",
        "Khung",
        "Khong",
        "Aishak",
        "\u0100yashk"
    ],
    "wof:name":"Khung-e Bala",
    "wof:placetype":"locality"
},
  "geometry": {"coordinates":[59.33218000000001,32.7374],"type":"Point"}
}