{
  "type": "Feature",
  "properties": {
    "gn:admin1_code":"42",
    "gn:asciiname":"Zingard",
    "gn:country_code":"IR",
    "gn:dem":1156,
    "gn:feature_class":"P",
    "gn:feature_code":"PPL",
    "gn:name":"Z\u012bngard",
    "gn:population":0,
    "gn:timezone":"Asia/Tehran",
    "iso:country":"IR",
    "name:ara_x_preferred":[
        "\u0632\u064a\u0646\u063a\u0631"
    ],
    "name:ceb_x_preferred":[
        "Zan\u012bgar"
    ],
    "name:fas_x_preferred":[
        "\u0632\u0646\u06cc\u06af\u0631"
    ],
    "name:fas_x_variant":[
        "Z\u012bnger",
        "Zan\u012bgar",
        "\u0632\u06cc\u0646\u06af\u0631\u062f",
        "\u0632\u06cc\u0646\u06af\u0631"
    ],
    "name:swe_x_preferred":[
        "Zan\u012bgar"
    ],
    "name:und_x_variant":[
        "Zang\u0101r",
        "Z\u012bngar",
        "Z\u012bngard"
    ],
    "wof:name":"Zingard",
    "wof:placetype":"locality"
},
  "geometry": {"coordinates":[59.02038,36.76215],"type":"Point"}
}