{
  "type": "Feature",
  "properties": {
    "gn:admin1_code":"40",
    "gn:asciiname":"Dehnow",
    "gn:country_code":"IR",
    "gn:dem":1246,
    "gn:feature_class":"P",
    "gn:feature_code":"PPL",
    "gn:name":"Dehnow",
    "gn:population":0,
    "gn:timezone":"Asia/Tehran",
    "iso:country":"IR",
    "name:azb_x_preferred":[
        "\u062f\u0647 \u0646\u0648"
    ],
    "name:ceb_x_preferred":[
        "Dehnow"
    ],
    "name:fas_x_preferred":[
        "\u062f\u0647\u0646\u0648"
    ],
    "name:fas_x_variant":[
        "\u062f\u0650\u0647 \u0646\u064f\u0648",
        "\u062f\u0650\u0647 \u0646\u064f\u0648 \u0647\u064f\u0651\u0645\u0650\u0647",
        "\u062f\u0647\u200c\u0646\u0648"
    ],
    "name:sco_x_preferred":[
        "Dehnow"
    ],
    "name:swe_x_preferred":[
        "Dehnow"
    ],
    "name:und_x_variant":[
        "Deh-i-Nau",
        "Dehnow",
        "Deh Now Hoomeh"
    ],
    "wof:name":"Dehnow",
    "wof:placetype":"locality"
},
  "geometry": {"coordinates":[54.43512,31.81502],"type":"Point"}
}