{
  "type": "Feature",
  "properties": {
    "gn:admin1_code":"28",
    "gn:asciiname":"`Aliabad-e Mansuriyeh",
    "gn:country_code":"IR",
    "gn:dem":1025,
    "gn:feature_class":"P",
    "gn:feature_code":"PPL",
    "gn:name":"\u2018Al\u012b\u0101b\u0101d-e Man\u015f\u016br\u012byeh",
    "gn:population":0,
    "gn:timezone":"Asia/Tehran",
    "iso:country":"IR",
    "name:fas_x_preferred":[
        "\u2018Al\u012b\u0101b\u0101d-e Man\u015f\u016br\u012byeh"
    ],
    "wof:name":"`Aliabad-e Mansuriyeh",
    "wof:placetype":"locality"
},
  "geometry": {"coordinates":[52.59917,33.38306],"type":"Point"}
}