{
  "type": "Feature",
  "properties": {
    "gn:admin1_code":"3",
    "gn:asciiname":"Shekar Ab",
    "gn:country_code":"IR",
    "gn:dem":1999,
    "gn:feature_class":"P",
    "gn:feature_code":"PPL",
    "gn:name":"Shekar \u0100b",
    "gn:population":0,
    "gn:timezone":"Asia/Tehran",
    "iso:country":"IR",
    "name:fas_x_preferred":[
        "\u0634\u0650\u0643\u064e\u0631 \u0622\u0628\u0627\u062f"
    ],
    "name:fas_x_variant":[
        "Shekar\u0101b\u0101d",
        "Shekar \u0100b",
        "\u0634\u0643\u0631 \u0622\u0628"
    ],
    "name:und_x_variant":[
        "\u0634\u0643\u0631 \u0622\u0628"
    ],
    "wof:name":"Shekar Ab",
    "wof:placetype":"locality"
},
  "geometry": {"coordinates":[50.5189,32.12164],"type":"Point"}
}