{
  "type": "Feature",
  "properties": {
    "gn:admin1_code":"29",
    "gn:asciiname":"Neyu",
    "gn:country_code":"IR",
    "gn:dem":2350,
    "gn:feature_class":"P",
    "gn:feature_code":"PPL",
    "gn:name":"Ney\u016b",
    "gn:population":0,
    "gn:timezone":"Asia/Tehran",
    "iso:country":"IR",
    "name:fas_x_preferred":[
        "\u0646\u06cc\u0648"
    ],
    "name:fas_x_variant":[
        "Ney\u016b"
    ],
    "wof:name":"Neyu",
    "wof:placetype":"locality"
},
  "geometry": {"coordinates":[56.28404000000001,29.85924],"type":"Point"}
}