{
  "type": "Feature",
  "properties": {
    "gn:admin1_code":"7.0",
    "gn:asciiname":"Sar Qanat",
    "gn:country_code":"IR",
    "gn:dem":1027,
    "gn:feature_class":"P",
    "gn:feature_code":"PPL",
    "gn:name":"Sar Qan\u0101t",
    "gn:population":0,
    "gn:timezone":"Asia/Tehran",
    "iso:country":"IR",
    "name:fas_x_preferred":[
        "Sar Qan\u0101t"
    ],
    "name:fas_x_variant":[
        "\u0633\u0631 \u0642\u0646\u0627\u062a"
    ],
    "wof:name":"Sar Qanat",
    "wof:placetype":"locality"
},
  "geometry": {"coordinates":[51.65466,30.17883],"type":"Point"}
}