{
  "type": "Feature",
  "properties": {
    "gn:admin1_code":"33",
    "gn:asciiname":"Baghjeghaz-e Bala",
    "gn:country_code":"IR",
    "gn:dem":1606,
    "gn:feature_class":"P",
    "gn:feature_code":"PPL",
    "gn:name":"B\u0101ghjegh\u0101z-e B\u0101l\u0101",
    "gn:population":0,
    "gn:timezone":"Asia/Tehran",
    "iso:country":"IR",
    "name:fas_x_preferred":[
        "\u0628\u0627\u063a\u062c\u063a\u0627\u0632 \u0628\u0627\u0644\u0627"
    ],
    "name:fas_x_variant":[
        "Baghchehq\u0101z-e B\u0101l\u0101",
        "B\u0101ghjegh\u0101z-e B\u0101l\u0101"
    ],
    "wof:name":"Baghjeghaz-e Bala",
    "wof:placetype":"locality"
},
  "geometry": {"coordinates":[47.9306,37.3253],"type":"Point"}
}