{
  "type": "Feature",
  "properties": {
    "gn:admin1_code":"15",
    "gn:asciiname":"Tall Geser-e Pa'in",
    "gn:country_code":"IR",
    "gn:dem":77,
    "gn:feature_class":"P",
    "gn:feature_code":"PPL",
    "gn:name":"Tall Geser-e P\u0101\u2019\u012bn",
    "gn:population":0,
    "gn:timezone":"Asia/Tehran",
    "iso:country":"IR",
    "name:fas_x_preferred":[
        "\u062a\u0644 \u06af\u0633\u0631 \u067e\u0627\u06cc\u06cc\u0646"
    ],
    "name:fas_x_variant":[
        "Talgasar-e P\u0101\u2019\u012bn",
        "\u062a\u0644 \u06af\u0633\u0631"
    ],
    "name:und_x_variant":[
        "Tal Geser",
        "Tal Gasar",
        "Tall Geser-e P\u0101\u2019\u012bn",
        "Tall Geser"
    ],
    "wof:name":"Tall Geser-e Pa'in",
    "wof:placetype":"locality"
},
  "geometry": {"coordinates":[49.41264,31.36026],"type":"Point"}
}