{
  "type": "Feature",
  "properties": {
    "gn:admin1_code":"41",
    "gn:asciiname":"Chahkand",
    "gn:country_code":"IR",
    "gn:dem":1562,
    "gn:feature_class":"P",
    "gn:feature_code":"PPL",
    "gn:name":"Chahkand",
    "gn:population":0,
    "gn:timezone":"Asia/Tehran",
    "iso:country":"IR",
    "name:fas_x_preferred":[
        "\u0686\u0647\u06a9\u0646\u062f"
    ],
    "name:und_x_variant":[
        "Chah Kand Shahabad",
        "Chahkand",
        "Ch\u0101h Kand"
    ],
    "wof:name":"Chahkand",
    "wof:placetype":"locality"
},
  "geometry": {"coordinates":[59.15535,32.84499],"type":"Point"}
}