{
  "type": "Feature",
  "properties": {
    "gn:admin1_code":"33",
    "gn:asciiname":"Jeldeh Bakhan",
    "gn:country_code":"IR",
    "gn:dem":1834,
    "gn:feature_class":"P",
    "gn:feature_code":"PPL",
    "gn:name":"Jeldeh B\u0101kh\u0101n",
    "gn:population":0,
    "gn:timezone":"Asia/Tehran",
    "iso:country":"IR",
    "name:azb_x_preferred":[
        "\u062c\u0644\u062f\u0647\u200c\u0628\u0627\u062e\u0627\u0646"
    ],
    "name:ceb_x_preferred":[
        "Jeldeh B\u0101kh\u0101n"
    ],
    "name:fas_x_preferred":[
        "\u062c\u0644\u062f\u0647 \u0628\u0627\u062e\u0627\u0646"
    ],
    "name:fas_x_variant":[
        "Jeldeh B\u0101kh\u0101n",
        "\u062c\u0644\u062f\u0647\u200c\u0628\u0627\u062e\u0627\u0646"
    ],
    "name:msa_x_preferred":[
        "Jeldeh Bakhan"
    ],
    "name:swe_x_preferred":[
        "Jeldeh B\u0101kh\u0101n"
    ],
    "name:und_x_variant":[
        "Jaldo Bakhan",
        "Jaldeh B\u0101kh\u0101n",
        "Jeldah B\u0101kh\u0101n"
    ],
    "wof:name":"Jeldeh Bakhan",
    "wof:placetype":"locality"
},
  "geometry": {"coordinates":[47.6779,37.8335],"type":"Point"}
}