{
  "type": "Feature",
  "properties": {
    "gn:admin1_code":"1",
    "gn:asciiname":"Tikmah `Ajam",
    "gn:country_code":"IR",
    "gn:dem":1916,
    "gn:feature_class":"P",
    "gn:feature_code":"PPL",
    "gn:name":"T\u012bkmah \u2018Ajam",
    "gn:population":0,
    "gn:timezone":"Asia/Tehran",
    "iso:country":"IR",
    "name:fas_x_preferred":[
        "\u062a\u064a\u0643\u0645\u064e\u0647 \u0639\u064e\u062c\u064e\u0645"
    ],
    "name:fas_x_variant":[
        "\u062a\u06cc\u06a9\u0645\u0647 \u0639\u062c\u0645",
        "T\u012bkmah \u2018Ajam"
    ],
    "wof:name":"Tikmah `Ajam",
    "wof:placetype":"locality"
},
  "geometry": {"coordinates":[44.5356,39.2288],"type":"Point"}
}