{
  "type": "Feature",
  "properties": {
    "gn:admin1_code":"7",
    "gn:asciiname":"Fahlian",
    "gn:country_code":"IR",
    "gn:dem":894,
    "gn:feature_class":"P",
    "gn:feature_code":"PPL",
    "gn:name":"Fahl\u012b\u0101n",
    "gn:population":0,
    "gn:timezone":"Asia/Tehran",
    "iso:country":"IR",
    "name:fas_x_preferred":[
        "Fahl\u012b\u0101n-e B\u0101l\u0101"
    ],
    "name:fas_x_variant":[
        "Fahl\u012b\u0101n",
        "\u0641\u0647\u0644\u06cc\u0627\u0646"
    ],
    "name:und_x_variant":[
        "Faley\u016bn-e Bozorg",
        "Fahl\u012b\u0101n",
        "Fahl\u012b\u0101n-e \u2018Oly\u00e1",
        "Fehli\u0101n",
        "Fahley\u0101n B\u0101l\u0101",
        "\u0641\u0647\u0644\u06cc\u0627\u0646"
    ],
    "wof:name":"Fahlian",
    "wof:placetype":"locality"
},
  "geometry": {"coordinates":[51.49788,30.19765],"type":"Point"}
}