{
  "type": "Feature",
  "properties": {
    "gn:admin1_code":"15",
    "gn:asciiname":"Shahrak-e Shamsabad",
    "gn:country_code":"IR",
    "gn:dem":95,
    "gn:feature_class":"P",
    "gn:feature_code":"PPL",
    "gn:name":"Shahrak-e Shams\u0101b\u0101d",
    "gn:population":0,
    "gn:timezone":"Asia/Tehran",
    "iso:country":"IR",
    "name:fas_x_preferred":[
        "\u0634\u0647\u0631\u06a9 \u0634\u0645\u0633 \u0622\u0628\u0627\u062f"
    ],
    "name:fas_x_variant":[
        "Shahrak-e Shams\u0101b\u0101d"
    ],
    "wof:name":"Shahrak-e Shamsabad",
    "wof:placetype":"locality"
},
  "geometry": {"coordinates":[48.44615,32.29359],"type":"Point"}
}