{
  "type": "Feature",
  "properties": {
    "gn:admin1_code":"34.0",
    "gn:asciiname":"Ortalekh",
    "gn:country_code":"IR",
    "gn:dem":2104,
    "gn:feature_class":"P",
    "gn:feature_code":"PPL",
    "gn:name":"Ort\u0101lekh",
    "gn:population":0,
    "gn:timezone":"Asia/Tehran",
    "iso:country":"IR",
    "name:fas_x_preferred":[
        "\u0627\u0631\u062a\u0627\u0644\u06cc\u0642"
    ],
    "name:fas_x_variant":[
        "Ertaleq-e Qob\u0101",
        "Avarn\u0101l\u016bq",
        "Ort\u0101l\u012bq",
        "\u0627\u0631\u062a\u0627\u0644\u062e",
        "\u0627\u0631\u062a\u0644\u0642 \u0622\u0628\u0627\u062f"
    ],
    "name:und_x_variant":[
        "Ort\u0101l\u016bq",
        "Alt\u0101 Lag\u016bbeh",
        "Ul T\u0101lg\u016bba",
        "Artalaq \u0100beh",
        "Artoloq Obbeh",
        "Ort\u0101lekh",
        "Artalaq\u0101b\u0101d"
    ],
    "wof:name":"Ortalekh",
    "wof:placetype":"locality"
},
  "geometry": {"coordinates":[49.449,33.7305],"type":"Point"}
}