{
  "type": "Feature",
  "properties": {
    "gn:admin1_code":"42",
    "gn:asciiname":"Torsizuk",
    "gn:country_code":"IR",
    "gn:dem":1866,
    "gn:feature_class":"P",
    "gn:feature_code":"PPL",
    "gn:name":"Tors\u012bz\u016bk",
    "gn:population":0,
    "gn:timezone":"Asia/Tehran",
    "iso:country":"IR",
    "name:ara_x_preferred":[
        "\u062a\u0631\u0634\u064a\u0632\u0648\u0643"
    ],
    "name:fas_x_preferred":[
        "Torsh Sh\u016bk"
    ],
    "name:fas_x_variant":[
        "Torsh\u012bz\u016bk",
        "\u062a\u0631\u0634 \u0634\u0648\u06a9",
        "\u062a\u0631\u0633\u064a\u0632\u0648\u06a9",
        "\u062a\u0631\u0634\u06cc\u0632\u0648\u06a9"
    ],
    "name:und_x_variant":[
        "Tors\u012bz\u016bk"
    ],
    "wof:name":"Torsizuk",
    "wof:placetype":"locality"
},
  "geometry": {"coordinates":[58.3948,34.1626],"type":"Point"}
}