{
  "type": "Feature",
  "properties": {
    "gn:admin1_code":"33.0",
    "gn:asciiname":"Avshar",
    "gn:country_code":"IR",
    "gn:dem":1156,
    "gn:feature_class":"P",
    "gn:feature_code":"PPL",
    "gn:name":"Avsh\u0101r",
    "gn:population":0,
    "gn:timezone":"Asia/Tehran",
    "iso:country":"IR",
    "name:fas_x_preferred":[
        "\u0627\u0648\u0634\u0627\u0631"
    ],
    "name:fas_x_variant":[
        "Afsh\u0101r",
        "Avsh\u0101r",
        "\u0627\u0641\u0634\u0627\u0631"
    ],
    "name:und_x_variant":[
        "Afsh\u0101i"
    ],
    "wof:name":"Avshar",
    "wof:placetype":"locality"
},
  "geometry": {"coordinates":[45.82,38.8496],"type":"Point"}
}