{
  "type": "Feature",
  "properties": {
    "gn:admin1_code":"22",
    "gn:asciiname":"Kheyrabad",
    "gn:country_code":"IR",
    "gn:dem":68,
    "gn:feature_class":"P",
    "gn:feature_code":"PPL",
    "gn:name":"Kheyr\u0101b\u0101d",
    "gn:population":0,
    "gn:timezone":"Asia/Tehran",
    "iso:country":"IR",
    "name:ara_x_preferred":[
        "\u062e\u064a\u0631\u0623\u0628\u0627\u062f"
    ],
    "name:fas_x_preferred":[
        "\u062d\u0650\u064a\u062f\u064e\u0631 \u0622\u0628\u0627\u062f"
    ],
    "name:fas_x_variant":[
        "\u1e28eydar\u0101b\u0101d",
        "\u062e\u064a\u0631 \u0622\u0628\u0627\u062f",
        "\u062e\u06cc\u0631\u0622\u0628\u0627\u062f"
    ],
    "name:msa_x_preferred":[
        "Kheyrabad"
    ],
    "name:und_x_variant":[
        "Kheyr\u0101b\u0101d"
    ],
    "wof:name":"Kheyrabad",
    "wof:placetype":"locality"
},
  "geometry": {"coordinates":[51.25554,29.3899],"type":"Point"}
}