{
  "type": "Feature",
  "properties": {
    "gn:admin1_code":"34",
    "gn:asciiname":"Neyneh",
    "gn:country_code":"IR",
    "gn:dem":1772,
    "gn:feature_class":"P",
    "gn:feature_code":"PPL",
    "gn:name":"Neyneh",
    "gn:population":0,
    "gn:timezone":"Asia/Tehran",
    "iso:country":"IR",
    "name:fas_x_preferred":[
        "\u0646\u064a\u0646\u0647"
    ],
    "name:fas_x_variant":[
        "\u0646\u064a\u0646\u0650\u0647"
    ],
    "name:und_x_variant":[
        "Naina",
        "N\u012bneh",
        "Neyneh"
    ],
    "wof:name":"Neyneh",
    "wof:placetype":"locality"
},
  "geometry": {"coordinates":[50.5223,34.0259],"type":"Point"}
}