{
  "type": "Feature",
  "properties": {
    "gn:admin1_code":"33",
    "gn:asciiname":"Sorkheh Gav-e Tazehkand",
    "gn:country_code":"IR",
    "gn:dem":1836,
    "gn:feature_class":"P",
    "gn:feature_code":"PPL",
    "gn:name":"Sorkheh G\u0101v-e T\u0101zehkand",
    "gn:population":0,
    "gn:timezone":"Asia/Tehran",
    "iso:country":"IR",
    "name:fas_x_preferred":[
        "Sorkheh G\u0101v-e T\u0101zehkand"
    ],
    "wof:name":"Sorkheh Gav-e Tazehkand",
    "wof:placetype":"locality"
},
  "geometry": {"coordinates":[46.68333,38.36667],"type":"Point"}
}