{
  "type": "Feature",
  "properties": {
    "gn:admin1_code":"5",
    "gn:asciiname":"Dozdak",
    "gn:country_code":"IR",
    "gn:dem":906,
    "gn:feature_class":"P",
    "gn:feature_code":"PPL",
    "gn:name":"Dozdak",
    "gn:population":0,
    "gn:timezone":"Asia/Tehran",
    "iso:country":"IR",
    "name:fas_x_preferred":[
        "\u062f\u0632\u062f\u06a9"
    ],
    "name:mzn_x_preferred":[
        "\u062f\u0632\u062f\u06a9"
    ],
    "wof:name":"Dozdak",
    "wof:placetype":"locality"
},
  "geometry": {"coordinates":[50.4999,30.8374],"type":"Point"}
}