{
  "type": "Feature",
  "properties": {
    "gn:admin1_code":"8.0",
    "gn:asciiname":"Rasteh Mazeh",
    "gn:country_code":"IR",
    "gn:dem":316,
    "gn:feature_class":"P",
    "gn:feature_code":"PPL",
    "gn:name":"R\u0101steh M\u0101zeh",
    "gn:population":0,
    "gn:timezone":"Asia/Tehran",
    "iso:country":"IR",
    "name:fas_x_preferred":[
        "\u0631\u0627\u0633\u062a\u0647 \u0645\u0627\u0632\u0647"
    ],
    "name:und_x_variant":[
        "R\u0101steh M\u0101zeh"
    ],
    "wof:name":"Rasteh Mazeh",
    "wof:placetype":"locality"
},
  "geometry": {"coordinates":[49.76337,37.04581],"type":"Point"}
}