{
  "type": "Feature",
  "properties": {
    "gn:admin1_code":"42",
    "gn:asciiname":"Kabir Kuh",
    "gn:country_code":"IR",
    "gn:dem":1095,
    "gn:feature_class":"P",
    "gn:feature_code":"PPL",
    "gn:name":"Kab\u012br K\u016bh",
    "gn:population":0,
    "gn:timezone":"Asia/Tehran",
    "iso:country":"IR",
    "name:ckb_x_preferred":[
        "\u0686\u06cc\u0627\u06cc \u06a9\u06a4\u06d5\u0631"
    ],
    "name:fas_x_preferred":[
        "Kab\u012br K\u016bh"
    ],
    "name:fas_x_variant":[
        "\u06a9\u0628\u06cc\u0631\u06a9\u0648\u0647"
    ],
    "name:fra_x_preferred":[
        "Kabir Kuh"
    ],
    "name:lrc_x_preferred":[
        "\u06a9\u06c9\u0626\u0631"
    ],
    "name:pol_x_preferred":[
        "Kabir Kuh"
    ],
    "wof:name":"Kabir Kuh",
    "wof:placetype":"locality"
},
  "geometry": {"coordinates":[59.77444000000001,34.155],"type":"Point"}
}