{
  "type": "Feature",
  "properties": {
    "gn:admin1_code":"7.0",
    "gn:asciiname":"Sangineh",
    "gn:country_code":"IR",
    "gn:dem":2004,
    "gn:feature_class":"P",
    "gn:feature_code":"PPL",
    "gn:name":"Sang\u012bneh",
    "gn:population":0,
    "gn:timezone":"Asia/Tehran",
    "iso:country":"IR",
    "name:fas_x_preferred":[
        "\u0633\u0646\u06af\u064a\u0646\u0647"
    ],
    "name:und_x_variant":[
        "Sang\u012bneh"
    ],
    "wof:name":"Sangineh",
    "wof:placetype":"locality"
},
  "geometry": {"coordinates":[55.12968000000001,28.69821],"type":"Point"}
}