{
  "type": "Feature",
  "properties": {
    "gn:admin1_code":"1",
    "gn:asciiname":"Gelaz",
    "gn:country_code":"IR",
    "gn:dem":1890,
    "gn:feature_class":"P",
    "gn:feature_code":"PPL",
    "gn:name":"Gel\u0101z",
    "gn:population":0,
    "gn:timezone":"Asia/Tehran",
    "iso:country":"IR",
    "name:azb_x_preferred":[
        "\u06af\u0644\u0627\u0632"
    ],
    "name:aze_x_preferred":[
        "G\u0259laz"
    ],
    "name:ceb_x_preferred":[
        "Gel\u0101z"
    ],
    "name:ckb_x_preferred":[
        "\u06af\u06d5\u06b5\u0627\u0632"
    ],
    "name:fas_x_preferred":[
        "\u06af\u0644\u0627\u0632"
    ],
    "name:fas_x_variant":[
        "Kel\u0101z",
        "Gel\u0101z"
    ],
    "name:msa_x_preferred":[
        "Gelaz"
    ],
    "name:swe_x_preferred":[
        "Gel\u0101z"
    ],
    "wof:name":"Gelaz",
    "wof:placetype":"locality"
},
  "geometry": {"coordinates":[45.0325,37.1225],"type":"Point"}
}