{
  "type": "Feature",
  "properties": {
    "gn:admin1_code":"16",
    "gn:asciiname":"Bam-e Qal`ehgah",
    "gn:country_code":"IR",
    "gn:dem":2072,
    "gn:feature_class":"P",
    "gn:feature_code":"PPL",
    "gn:name":"B\u0101m-e Qal\u2018ehg\u0101h",
    "gn:population":0,
    "gn:timezone":"Asia/Tehran",
    "iso:country":"IR",
    "name:fas_x_preferred":[
        "\u0635\u0627\u0644\u062d \u0622\u0628\u0627\u062f"
    ],
    "name:fas_x_variant":[
        "\u015e\u0101le\u1e29\u0101b\u0101d",
        "\u0628\u0627\u0645 \u0642\u0644\u0639\u0647 \u06af\u0627\u0647"
    ],
    "name:und_x_variant":[
        "B\u0101m-e Qal\u2018ehg\u0101h"
    ],
    "wof:name":"Bam-e Qal`ehgah",
    "wof:placetype":"locality"
},
  "geometry": {"coordinates":[46.7932,36.1683],"type":"Point"}
}