{
  "type": "Feature",
  "properties": {
    "gn:admin1_code":"33",
    "gn:asciiname":"Heydar Kanlu-ye Sofla",
    "gn:country_code":"IR",
    "gn:dem":466,
    "gn:feature_class":"P",
    "gn:feature_code":"PPL",
    "gn:name":"\u1e28eydar K\u0101nl\u016b-ye Sofl\u00e1",
    "gn:population":0,
    "gn:timezone":"Asia/Tehran",
    "iso:country":"IR",
    "name:aze_x_preferred":[
        "Heyd\u0259rxanl\u0131"
    ],
    "name:fas_x_preferred":[
        "\u062d\u0650\u064a\u062f\u064e\u0631 \u0643\u0627\u0646\u0644\u0648\u06cc \u0633\u064f\u0641\u0644\u064e\u0649"
    ],
    "name:fas_x_variant":[
        "\u062d\u06cc\u062f\u0631 \u06a9\u0627\u0646\u0644\u0648\u06cc \u0633\u0641\u0644\u06cc",
        "\u1e28eydar K\u0101nl\u016b-ye Sofl\u00e1"
    ],
    "wof:name":"Heydar Kanlu-ye Sofla",
    "wof:placetype":"locality"
},
  "geometry": {"coordinates":[46.9019,39.0835],"type":"Point"}
}