{
  "type": "Feature",
  "properties": {
    "gn:admin1_code":"22.0",
    "gn:asciiname":"Baghcheh-ye Shomali",
    "gn:country_code":"IR",
    "gn:dem":49,
    "gn:feature_class":"P",
    "gn:feature_code":"PPL",
    "gn:name":"B\u0101ghcheh-ye Shom\u0101l\u012b",
    "gn:population":0,
    "gn:timezone":"Asia/Tehran",
    "iso:country":"IR",
    "name:fas_x_preferred":[
        "\u0628\u0627\u063a\u0686\u0647 \u0634\u0645\u0627\u0644\u06cc"
    ],
    "name:fas_x_variant":[
        "B\u0101ghcheh-ye Shom\u0101l\u012b"
    ],
    "name:msa_x_preferred":[
        "Baghcheh-ye Shomali"
    ],
    "wof:name":"Baghcheh-ye Shomali",
    "wof:placetype":"locality"
},
  "geometry": {"coordinates":[51.21100000000001,28.8065],"type":"Point"}
}