{
  "type": "Feature",
  "properties": {
    "gn:admin1_code":"44.0",
    "gn:asciiname":"Emam Cheshmeh",
    "gn:country_code":"IR",
    "gn:dem":2199,
    "gn:feature_class":"P",
    "gn:feature_code":"PPL",
    "gn:name":"Em\u0101m Cheshmeh",
    "gn:population":0,
    "gn:timezone":"Asia/Tehran",
    "iso:country":"IR",
    "name:ceb_x_preferred":[
        "Em\u0101m Cheshmeh"
    ],
    "name:fas_x_preferred":[
        "\u0627\u0645\u0627\u0645 \u0686\u0634\u0645\u0647"
    ],
    "name:fas_x_variant":[
        "Em\u0101m Cheshmeh",
        "\u0634\u0627\u0647 \u0686\u0634\u0645\u0647",
        "\u0627\u0645\u0627\u0645\u200c\u0686\u0634\u0645\u0647"
    ],
    "name:msa_x_preferred":[
        "Emam Cheshmeh"
    ],
    "name:swe_x_preferred":[
        "Em\u0101m Cheshmeh"
    ],
    "name:und_x_variant":[
        "Sh\u0101h Cheshmeh"
    ],
    "wof:name":"Emam Cheshmeh",
    "wof:placetype":"locality"
},
  "geometry": {"coordinates":[51.31409,36.10073],"type":"Point"}
}