{
  "type": "Feature",
  "properties": {
    "gn:admin1_code":"1",
    "gn:asciiname":"Tazeh Kand",
    "gn:country_code":"IR",
    "gn:dem":1592,
    "gn:feature_class":"P",
    "gn:feature_code":"PPL",
    "gn:name":"T\u0101zeh Kand",
    "gn:population":0,
    "gn:timezone":"Asia/Tehran",
    "iso:country":"IR",
    "name:ceb_x_preferred":[
        "Tazeh Kand"
    ],
    "name:fas_x_preferred":[
        "\u062a\u0627\u0632\u0650\u0647 \u0643\u064e\u0646\u062f"
    ],
    "name:fas_x_variant":[
        "T\u0101zeh Kand",
        "\u062a\u0627\u0632\u0647 \u06a9\u0646\u062f",
        "\u062a\u0627\u0632\u0647\u200c\u06a9\u0646\u062f"
    ],
    "name:swe_x_preferred":[
        "Tazeh Kand"
    ],
    "name:und_x_variant":[
        "\u062a\u0627\u0632\u0647 \u06a9\u0646\u062f"
    ],
    "wof:name":"Tazeh Kand",
    "wof:placetype":"locality"
},
  "geometry": {"coordinates":[44.9635,37.2174],"type":"Point"}
}