{
  "type": "Feature",
  "properties": {
    "gn:admin1_code":"9",
    "gn:asciiname":"Gol Kabud",
    "gn:country_code":"IR",
    "gn:dem":1903,
    "gn:feature_class":"P",
    "gn:feature_code":"PPL",
    "gn:name":"Gol Kab\u016bd",
    "gn:population":0,
    "gn:timezone":"Asia/Tehran",
    "iso:country":"IR",
    "name:ceb_x_preferred":[
        "Gol Kab\u016bd"
    ],
    "name:fas_x_preferred":[
        "\u0643\u0644 \u0643\u0628\u0648\u062f"
    ],
    "name:fas_x_variant":[
        "\u06af\u0644 \u06a9\u0628\u0648\u062f",
        "Kal Kab\u016bd",
        "Gol Kab\u016bd",
        "\u06a9\u0644 \u06a9\u0628\u0648\u062f"
    ],
    "name:msa_x_preferred":[
        "Kal Kabud"
    ],
    "name:swe_x_preferred":[
        "Gol Kab\u016bd"
    ],
    "wof:name":"Gol Kabud",
    "wof:placetype":"locality"
},
  "geometry": {"coordinates":[48.85283,35.48074000000001],"type":"Point"}
}