{
  "type": "Feature",
  "properties": {
    "gn:admin1_code":"29",
    "gn:asciiname":"Bolbolabad",
    "gn:country_code":"IR",
    "gn:dem":417,
    "gn:feature_class":"P",
    "gn:feature_code":"PPL",
    "gn:name":"Bolbol\u0101b\u0101d",
    "gn:population":0,
    "gn:timezone":"Asia/Tehran",
    "iso:country":"IR",
    "name:fas_x_preferred":[
        "\u0628\u0644\u0628\u0644 \u0622\u0628\u0627\u062f"
    ],
    "name:fas_x_variant":[
        "Bolbol\u0101b\u0101d"
    ],
    "wof:name":"Bolbolabad",
    "wof:placetype":"locality"
},
  "geometry": {"coordinates":[57.9541,27.6439],"type":"Point"}
}