{
  "type": "Feature",
  "properties": {
    "gn:admin1_code":"42",
    "gn:asciiname":"Zeynabad",
    "gn:country_code":"IR",
    "gn:dem":1578,
    "gn:feature_class":"P",
    "gn:feature_code":"PPL",
    "gn:name":"Zeyn\u0101b\u0101d",
    "gn:population":0,
    "gn:timezone":"Asia/Tehran",
    "iso:country":"IR",
    "name:ara_x_preferred":[
        "\u0632\u064a\u0646 \u0623\u0628\u0627\u062f"
    ],
    "name:fas_x_preferred":[
        "Zeyn\u0101b\u0101d"
    ],
    "name:fas_x_variant":[
        "\u0632\u06cc\u0646 \u0622\u0628\u0627\u062f",
        "Z\u012bn\u0101b\u0101d",
        "Zain\u0101b\u0101d",
        "\u0632\u06cc\u0646\u200c\u0622\u0628\u0627\u062f"
    ],
    "name:und_x_variant":[
        "Z\u012bn\u0101b\u0101d",
        "Zain\u0101b\u0101d",
        "\u0632\u06cc\u0646 \u0622\u0628\u0627\u062f"
    ],
    "wof:name":"Zeynabad",
    "wof:placetype":"locality"
},
  "geometry": {"coordinates":[58.22557,34.38097],"type":"Point"}
}