{
  "type": "Feature",
  "properties": {
    "gn:admin1_code":"23",
    "gn:asciiname":"Bahram Shah",
    "gn:country_code":"IR",
    "gn:dem":1836,
    "gn:feature_class":"P",
    "gn:feature_code":"PPL",
    "gn:name":"Bahr\u0101m Sh\u0101h",
    "gn:population":0,
    "gn:timezone":"Asia/Tehran",
    "iso:country":"IR",
    "name:fas_x_preferred":[
        "Bahr\u0101m Sh\u0101h"
    ],
    "wof:name":"Bahram Shah",
    "wof:placetype":"locality"
},
  "geometry": {"coordinates":[48.03306,34.07528],"type":"Point"}
}