{
  "type": "Feature",
  "properties": {
    "gn:admin1_code":"7",
    "gn:asciiname":"Danicheh Kheyr",
    "gn:country_code":"IR",
    "gn:dem":2235,
    "gn:feature_class":"P",
    "gn:feature_code":"PPL",
    "gn:name":"Dan\u012bcheh Kheyr",
    "gn:population":0,
    "gn:timezone":"Asia/Tehran",
    "iso:country":"IR",
    "name:fas_x_preferred":[
        "\u062f\u0646\u06cc\u0686\u0647 \u062e\u06cc\u0631"
    ],
    "name:fas_x_variant":[
        "Dan\u012bcheh Kheyr",
        "\u062f\u06cc\u0646\u0686\u0647 \u062e\u06cc\u0631"
    ],
    "name:und_x_variant":[
        "Ma\u1e29m\u016bd\u0101b\u0101d-e Dan\u012bcheh Kheyr",
        "Dan\u012bcheh Kheyre",
        "D\u016bn\u012bcheh Kheyr",
        "Dunicheh Khair",
        "Deynacheh Kheyr"
    ],
    "wof:name":"Danicheh Kheyr",
    "wof:placetype":"locality"
},
  "geometry": {"coordinates":[53.1721,30.5617],"type":"Point"}
}