{
  "type": "Feature",
  "properties": {
    "gn:admin1_code":"44",
    "gn:asciiname":"Varian",
    "gn:country_code":"IR",
    "gn:dem":1807,
    "gn:feature_class":"P",
    "gn:feature_code":"PPL",
    "gn:name":"V\u0101r\u012b\u0101n",
    "gn:population":0,
    "gn:timezone":"Asia/Tehran",
    "iso:country":"IR",
    "name:fas_x_preferred":[
        "\u0648\u0627\u0631\u064a\u0627\u0646"
    ],
    "name:fas_x_variant":[
        "V\u0101r\u012b\u0101n",
        "V\u0101ry\u0101n-e Jad\u012bd",
        "\u0100ry\u0101n",
        "V\u0101ry\u0101n",
        "V\u0101r\u012by\u0101n",
        "\u0622\u0631\u064a\u0627\u0646"
    ],
    "name:und_x_variant":[
        "V\u0101r\u012by\u0101n",
        "\u0622\u0631\u064a\u0627\u0646"
    ],
    "wof:name":"Varian",
    "wof:placetype":"locality"
},
  "geometry": {"coordinates":[51.1148,35.9654],"type":"Point"}
}