{
  "type": "Feature",
  "properties": {
    "gn:admin1_code":"8.0",
    "gn:asciiname":"Figurasar",
    "gn:country_code":"IR",
    "gn:dem":1858,
    "gn:feature_class":"P",
    "gn:feature_code":"PPL",
    "gn:name":"F\u012bg\u016brasar",
    "gn:population":0,
    "gn:timezone":"Asia/Tehran",
    "iso:country":"IR",
    "name:fas_x_preferred":[
        "F\u012bg\u016brasar"
    ],
    "name:fas_x_variant":[
        "\u0641\u06cc\u06af\u0648\u0631\u0633\u0631"
    ],
    "name:und_x_variant":[
        "\u0641\u06cc\u06af\u0648\u0631\u0633\u0631"
    ],
    "wof:name":"Figurasar",
    "wof:placetype":"locality"
},
  "geometry": {"coordinates":[49.89686,36.83659],"type":"Point"}
}