{
  "type": "Feature",
  "properties": {
    "gn:admin1_code":"42",
    "gn:asciiname":"Siah Sang",
    "gn:country_code":"IR",
    "gn:dem":1457,
    "gn:feature_class":"P",
    "gn:feature_code":"PPL",
    "gn:name":"S\u012b\u0101h Sang",
    "gn:population":0,
    "gn:timezone":"Asia/Tehran",
    "iso:country":"IR",
    "name:ara_x_preferred":[
        "\u0633\u064a\u0627\u0629 \u0633\u0646\u063a"
    ],
    "name:fas_x_preferred":[
        "\u0633\u06cc\u0627\u0647 \u0633\u0646\u06af"
    ],
    "name:fas_x_variant":[
        "S\u012b\u0101h Sang"
    ],
    "wof:name":"Siah Sang",
    "wof:placetype":"locality"
},
  "geometry": {"coordinates":[59.89389,35.61155],"type":"Point"}
}