{
  "type": "Feature",
  "properties": {
    "gn:admin1_code":"8.0",
    "gn:asciiname":"Naz Langeh",
    "gn:country_code":"IR",
    "gn:dem":165,
    "gn:feature_class":"P",
    "gn:feature_code":"PPL",
    "gn:name":"N\u0101z Langeh",
    "gn:population":0,
    "gn:timezone":"Asia/Tehran",
    "iso:country":"IR",
    "name:fas_x_preferred":[
        "\u0646\u0627\u0632 \u0644\u0646\u06af\u0647"
    ],
    "name:und_x_variant":[
        "N\u0101z Langeh"
    ],
    "wof:name":"Naz Langeh",
    "wof:placetype":"locality"
},
  "geometry": {"coordinates":[49.80392,37.0785],"type":"Point"}
}