{
  "type": "Feature",
  "properties": {
    "gn:admin1_code":"29",
    "gn:asciiname":"Tolombeh-ye Seyyed Habib",
    "gn:country_code":"IR",
    "gn:dem":1707,
    "gn:feature_class":"P",
    "gn:feature_code":"PPL",
    "gn:name":"Tolombeh-ye Seyyed \u1e28ab\u012bb",
    "gn:population":0,
    "gn:timezone":"Asia/Tehran",
    "iso:country":"IR",
    "name:fas_x_preferred":[
        "Tolombeh-ye Seyyed \u1e28ab\u012bb"
    ],
    "wof:name":"Tolombeh-ye Seyyed Habib",
    "wof:placetype":"locality"
},
  "geometry": {"coordinates":[55.85,28.95],"type":"Point"}
}