{
  "type": "Feature",
  "properties": {
    "gn:admin1_code":"1.0",
    "gn:asciiname":"Darsavin",
    "gn:country_code":"IR",
    "gn:dem":1529,
    "gn:feature_class":"P",
    "gn:feature_code":"PPL",
    "gn:name":"Dars\u0101v\u012bn",
    "gn:population":0,
    "gn:timezone":"Asia/Tehran",
    "iso:country":"IR",
    "name:fas_x_preferred":[
        "\u062f\u0631\u0633\u0627\u0648\u06cc\u0646"
    ],
    "name:fas_x_variant":[
        "Dars\u0101v\u012bn"
    ],
    "wof:name":"Darsavin",
    "wof:placetype":"locality"
},
  "geometry": {"coordinates":[45.6336,36.1542],"type":"Point"}
}