{
  "type": "Feature",
  "properties": {
    "gn:admin1_code":"13",
    "gn:asciiname":"Mulini",
    "gn:country_code":"IR",
    "gn:dem":1547,
    "gn:feature_class":"P",
    "gn:feature_code":"PPL",
    "gn:name":"M\u016bl\u012bn\u012b",
    "gn:population":0,
    "gn:timezone":"Asia/Tehran",
    "iso:country":"IR",
    "name:fas_x_preferred":[
        "M\u016bl\u012bn\u012b"
    ],
    "wof:name":"Mulini",
    "wof:placetype":"locality"
},
  "geometry": {"coordinates":[46.43583,34.84472],"type":"Point"}
}