{
  "type": "Feature",
  "properties": {
    "gn:admin1_code":"29",
    "gn:asciiname":"Cheshmeh Mah",
    "gn:country_code":"IR",
    "gn:dem":2559,
    "gn:feature_class":"P",
    "gn:feature_code":"PPL",
    "gn:name":"Cheshmeh M\u0101h",
    "gn:population":0,
    "gn:timezone":"Asia/Tehran",
    "iso:country":"IR",
    "name:fas_x_preferred":[
        "\u0686\u0634\u0645\u0647 \u0645\u0627\u0647"
    ],
    "name:fas_x_variant":[
        "Cheshmeh M\u0101h"
    ],
    "wof:name":"Cheshmeh Mah",
    "wof:placetype":"locality"
},
  "geometry": {"coordinates":[56.832,29.2726],"type":"Point"}
}