{
  "type": "Feature",
  "properties": {
    "gn:admin1_code":"0",
    "gn:asciiname":"Bagh Zare`in",
    "gn:country_code":"IR",
    "gn:dem":1492,
    "gn:feature_class":"P",
    "gn:feature_code":"PPL",
    "gn:name":"B\u0101gh Z\u0101re\u2018\u012bn",
    "gn:population":0,
    "gn:timezone":"Asia/Tehran",
    "iso:country":"IR",
    "name:fas_x_preferred":[
        "\u0628\u0627\u063a \u0632\u0627\u0631\u0639\u06cc\u0646"
    ],
    "name:fas_x_variant":[
        "B\u0101gh Z\u0101re\u2018\u012bn"
    ],
    "wof:name":"Bagh Zare`in",
    "wof:placetype":"locality"
},
  "geometry": {"coordinates":[56.8549,28.3326],"type":"Point"}
}