{
  "type": "Feature",
  "properties": {
    "gn:admin1_code":"35",
    "gn:asciiname":"Qalabon",
    "gn:country_code":"IR",
    "gn:dem":1213,
    "gn:feature_class":"P",
    "gn:feature_code":"PPL",
    "gn:name":"Qal\u0101bon",
    "gn:population":0,
    "gn:timezone":"Asia/Tehran",
    "iso:country":"IR",
    "name:fas_x_preferred":[
        "\u0642\u064e\u0644\u064e\u0628\u064f\u0646"
    ],
    "name:fas_x_variant":[
        "\u0698\u064e\u0644\u064e\u0628\u064e\u0646",
        "\u0686\u064e\u0644\u064e\u0628\u064e\u0646",
        "\u063a\u064e\u0644\u064e\u0628\u064f\u0646",
        "\u0642\u0644\u0627\u0628\u0646"
    ],
    "name:und_x_variant":[
        "Chalaban",
        "Zhalaban",
        "Ghalabon",
        "Qalabon",
        "Qal\u0101bon"
    ],
    "wof:name":"Qalabon",
    "wof:placetype":"locality"
},
  "geometry": {"coordinates":[52.27721,35.97232],"type":"Point"}
}