{
  "type": "Feature",
  "properties": {
    "gn:admin1_code":"13",
    "gn:asciiname":"Deh Asiab",
    "gn:country_code":"IR",
    "gn:dem":1628,
    "gn:feature_class":"P",
    "gn:feature_code":"PPL",
    "gn:name":"Deh \u0100s\u012b\u0101b",
    "gn:population":0,
    "gn:timezone":"Asia/Tehran",
    "iso:country":"IR",
    "name:fas_x_preferred":[
        "\u062f\u0647 \u0622\u0633\u06cc\u0627\u0628 \u062f\u06cc\u0646\u0648\u0631"
    ],
    "name:fas_x_variant":[
        "Deh \u0100s\u012b\u0101b",
        "Deh \u0100s\u012b\u0101b-e D\u012bnvar",
        "\u062f\u0647 \u0622\u0633\u06cc\u0627\u0628",
        "\u062f\u0647\u200c\u0622\u0633\u06cc\u0627\u0628"
    ],
    "wof:name":"Deh Asiab",
    "wof:placetype":"locality"
},
  "geometry": {"coordinates":[47.54133,34.62868],"type":"Point"}
}