{
  "type": "Feature",
  "properties": {
    "gn:admin1_code":"33",
    "gn:asciiname":"Dari Lu",
    "gn:country_code":"IR",
    "gn:dem":379,
    "gn:feature_class":"P",
    "gn:feature_code":"PPL",
    "gn:name":"Dar\u012b L\u016b",
    "gn:population":0,
    "gn:timezone":"Asia/Tehran",
    "iso:country":"IR",
    "name:ara_x_preferred":[
        "\u062f\u0631\u064a\u0644\u0648"
    ],
    "name:aze_x_preferred":[
        "D\u0259rili"
    ],
    "name:fas_x_preferred":[
        "\u062f\u0631\u06cc \u0644\u0648"
    ],
    "name:fas_x_variant":[
        "Dar\u012bl\u016b",
        "Dar\u012b L\u016b",
        "\u062f\u0631\u06cc\u0644\u0648"
    ],
    "name:msa_x_preferred":[
        "Dari Lu"
    ],
    "name:und_x_variant":[
        "Dirili",
        "Derili"
    ],
    "wof:name":"Dari Lu",
    "wof:placetype":"locality"
},
  "geometry": {"coordinates":[46.8569,39.0997],"type":"Point"}
}