{
  "type": "Feature",
  "properties": {
    "gn:admin1_code":"9",
    "gn:asciiname":"Darvaz",
    "gn:country_code":"IR",
    "gn:dem":1882,
    "gn:feature_class":"P",
    "gn:feature_code":"PPL",
    "gn:name":"Darv\u0101z",
    "gn:population":0,
    "gn:timezone":"Asia/Tehran",
    "iso:country":"IR",
    "name:fas_x_preferred":[
        "\u062f\u0631\u0648\u0627\u0632"
    ],
    "name:fas_x_variant":[
        "Darv\u0101z"
    ],
    "name:msa_x_preferred":[
        "Darvaz"
    ],
    "name:und_x_variant":[
        "Darv\u0101zeh"
    ],
    "wof:name":"Darvaz",
    "wof:placetype":"locality"
},
  "geometry": {"coordinates":[48.43872,34.44027],"type":"Point"}
}