{
  "type": "Feature",
  "properties": {
    "gn:admin1_code":"4.0",
    "gn:asciiname":"Hajj Mohammad",
    "gn:country_code":"IR",
    "gn:dem":1135,
    "gn:feature_class":"P",
    "gn:feature_code":"PPL",
    "gn:name":"\u1e28\u0101jj Mo\u1e29ammad",
    "gn:population":0,
    "gn:timezone":"Asia/Tehran",
    "iso:country":"IR",
    "name:fas_x_preferred":[
        "\u062d\u0627\u062c \u0645\u062d\u0645\u0651\u062f"
    ],
    "name:fas_x_variant":[
        "Deh-e T\u0101j Mo\u1e29ammad",
        "\u1e28\u0101jj Mo\u1e29ammad"
    ],
    "wof:name":"Hajj Mohammad",
    "wof:placetype":"locality"
},
  "geometry": {"coordinates":[62.1187,27.2338],"type":"Point"}
}