{
  "type": "Feature",
  "properties": {
    "gn:admin1_code":"7",
    "gn:asciiname":"Mansurabad",
    "gn:country_code":"IR",
    "gn:dem":855,
    "gn:feature_class":"P",
    "gn:feature_code":"PPL",
    "gn:name":"Man\u015f\u016br\u0101b\u0101d",
    "gn:population":0,
    "gn:timezone":"Asia/Tehran",
    "iso:country":"IR",
    "name:ara_x_preferred":[
        "\u0645\u0646\u0635\u0648\u0631 \u0623\u0628\u0627\u062f"
    ],
    "name:fas_x_preferred":[
        "Man\u015f\u016br\u0101b\u0101d"
    ],
    "name:fas_x_variant":[
        "\u0645\u0646\u0635\u0648\u0631 \u0622\u0628\u0627\u062f",
        "\u0645\u0646\u0635\u0648\u0631\u0622\u0628\u0627\u062f"
    ],
    "name:msa_x_preferred":[
        "Mansurabad"
    ],
    "name:und_x_variant":[
        "Mansoor Abad",
        "\u0645\u0646\u0635\u0648\u0631 \u0622\u0628\u0627\u062f"
    ],
    "wof:name":"Mansurabad",
    "wof:placetype":"locality"
},
  "geometry": {"coordinates":[54.03542,28.25488],"type":"Point"}
}