{
  "type": "Feature",
  "properties": {
    "gn:admin1_code":"43.0",
    "gn:asciiname":"Asadli",
    "gn:country_code":"IR",
    "gn:dem":1787,
    "gn:feature_class":"P",
    "gn:feature_code":"PPL",
    "gn:name":"Asadl\u012b",
    "gn:population":0,
    "gn:timezone":"Asia/Tehran",
    "iso:country":"IR",
    "name:ara_x_preferred":[
        "\u0623\u0633\u062f\u0644\u064a"
    ],
    "name:ceb_x_preferred":[
        "Asadl\u012b"
    ],
    "name:fas_x_preferred":[
        "Asadl\u012b"
    ],
    "name:fas_x_variant":[
        "\u0627\u0633\u062f\u0644\u06cc"
    ],
    "name:swe_x_preferred":[
        "Asadl\u012b"
    ],
    "wof:name":"Asadli",
    "wof:placetype":"locality"
},
  "geometry": {"coordinates":[57.36066,37.29501],"type":"Point"}
}