{
  "type": "Feature",
  "properties": {
    "gn:admin1_code":"41",
    "gn:asciiname":"Seh Quch",
    "gn:country_code":"IR",
    "gn:dem":1546,
    "gn:feature_class":"P",
    "gn:feature_code":"PPLF",
    "gn:name":"Seh Q\u016bch",
    "gn:population":0,
    "gn:timezone":"Asia/Tehran",
    "iso:country":"IR",
    "name:fas_x_preferred":[
        "Seh Q\u016bch"
    ],
    "name:fas_x_variant":[
        "\u0633\u0647 \u0642\u0648\u0686",
        "Sug\u016brch",
        "\u0633\u0642\u0631\u0686"
    ],
    "name:und_x_variant":[
        "Soqorch"
    ],
    "wof:name":"Seh Quch",
    "wof:placetype":"locality"
},
  "geometry": {"coordinates":[58.5714,33.07104],"type":"Point"}
}