{
  "type": "Feature",
  "properties": {
    "gn:admin1_code":"9",
    "gn:asciiname":"Gug Qash",
    "gn:country_code":"IR",
    "gn:dem":1744,
    "gn:feature_class":"P",
    "gn:feature_code":"PPL",
    "gn:name":"G\u016bg Q\u0101sh",
    "gn:population":0,
    "gn:timezone":"Asia/Tehran",
    "iso:country":"IR",
    "name:fas_x_preferred":[
        "\u06af\u0648\u06af \u0642\u0627\u0634"
    ],
    "name:fas_x_variant":[
        "G\u016bg Q\u0101sh"
    ],
    "wof:name":"Gug Qash",
    "wof:placetype":"locality"
},
  "geometry": {"coordinates":[48.02532,35.68771],"type":"Point"}
}