{
  "type": "Feature",
  "properties": {
    "gn:admin1_code":"29.0",
    "gn:asciiname":"Baklan",
    "gn:country_code":"IR",
    "gn:dem":2892,
    "gn:feature_class":"P",
    "gn:feature_code":"PPL",
    "gn:name":"B\u0101kl\u0101n",
    "gn:population":0,
    "gn:timezone":"Asia/Tehran",
    "iso:country":"IR",
    "name:ceb_x_preferred":[
        "Baklan \u0130l\u00e7esi"
    ],
    "name:deu_x_preferred":[
        "Baklan"
    ],
    "name:diq_x_preferred":[
        "Baklan"
    ],
    "name:epo_x_preferred":[
        "Baklan"
    ],
    "name:fra_x_preferred":[
        "Baklan"
    ],
    "name:mrj_x_preferred":[
        "\u0411\u043e\u0437\u043a\u0443\u0440\u0442"
    ],
    "name:msa_x_preferred":[
        "Baklan"
    ],
    "name:nld_x_preferred":[
        "Baklan"
    ],
    "name:nor_x_preferred":[
        "Baklan"
    ],
    "name:pnb_x_preferred":[
        "\u0636\u0644\u0639 \u0628\u06a9\u0644\u0627\u0646"
    ],
    "name:swa_x_preferred":[
        "Baklan"
    ],
    "name:tur_x_preferred":[
        "Baklan"
    ],
    "name:vie_x_preferred":[
        "Baklan"
    ],
    "wof:name":"Baklan",
    "wof:placetype":"locality"
},
  "geometry": {"coordinates":[56.42556,29.52806],"type":"Point"}
}