{
  "type": "Feature",
  "properties": {
    "gn:admin1_code":"8.0",
    "gn:asciiname":"Guraju",
    "gn:country_code":"IR",
    "gn:dem":972,
    "gn:feature_class":"P",
    "gn:feature_code":"PPL",
    "gn:name":"G\u016br\u0101j\u016b",
    "gn:population":0,
    "gn:timezone":"Asia/Tehran",
    "iso:country":"IR",
    "name:fas_x_preferred":[
        "\u06af\u0648\u0631\u0627\u062c\u0648"
    ],
    "name:und_x_variant":[
        "G\u016br\u0101j\u016b"
    ],
    "wof:name":"Guraju",
    "wof:placetype":"locality"
},
  "geometry": {"coordinates":[48.76357,37.93145],"type":"Point"}
}