{
  "type": "Feature",
  "properties": {
    "gn:admin1_code":"33",
    "gn:asciiname":"Kehdolan",
    "gn:country_code":"IR",
    "gn:dem":2165,
    "gn:feature_class":"P",
    "gn:feature_code":"PPL",
    "gn:name":"Kehdol\u0101n",
    "gn:population":0,
    "gn:timezone":"Asia/Tehran",
    "iso:country":"IR",
    "name:ceb_x_preferred":[
        "Kehdol\u0101n"
    ],
    "name:fas_x_preferred":[
        "\u06a9\u0647\u062f\u0644\u0627\u0646"
    ],
    "name:fas_x_variant":[
        "Kehdol\u0101n"
    ],
    "name:msa_x_preferred":[
        "Kehdolan"
    ],
    "name:swe_x_preferred":[
        "Kehdol\u0101n"
    ],
    "wof:name":"Kehdolan",
    "wof:placetype":"locality"
},
  "geometry": {"coordinates":[47.1367,37.82],"type":"Point"}
}