{
  "type": "Feature",
  "properties": {
    "gn:admin1_code":"37.0",
    "gn:asciiname":"Tappeh Soleyman",
    "gn:country_code":"IR",
    "gn:dem":-20,
    "gn:feature_class":"P",
    "gn:feature_code":"PPL",
    "gn:name":"Tappeh Soleym\u0101n",
    "gn:population":0,
    "gn:timezone":"Asia/Tehran",
    "iso:country":"IR",
    "name:fas_x_preferred":[
        "\u062a\u067e\u0647 \u0633\u0644\u06cc\u0645\u0627\u0646"
    ],
    "name:fas_x_variant":[
        "\u0633\u0644\u06cc\u0645\u0627\u0646 \u062a\u067e\u0647"
    ],
    "name:und_x_variant":[
        "Tappeh Soleym\u0101n",
        "Soleym\u0101n Tappeh"
    ],
    "wof:name":"Tappeh Soleyman",
    "wof:placetype":"locality"
},
  "geometry": {"coordinates":[54.34269000000001,36.91843],"type":"Point"}
}