{
  "type": "Feature",
  "properties": {
    "gn:admin1_code":"33",
    "gn:asciiname":"Seyf od Din Rud",
    "gn:country_code":"IR",
    "gn:dem":1538,
    "gn:feature_class":"P",
    "gn:feature_code":"PPL",
    "gn:name":"Seyf od D\u012bn R\u016bd",
    "gn:population":0,
    "gn:timezone":"Asia/Tehran",
    "iso:country":"IR",
    "name:fas_x_preferred":[
        "\u0633\u06cc\u0641 \u0627\u0644\u062f\u06cc\u0646 \u0631\u0648\u062f"
    ],
    "name:fas_x_variant":[
        "Seyf ed D\u012bn R\u016bd",
        "Seyf od D\u012bn R\u016bd"
    ],
    "wof:name":"Seyf od Din Rud",
    "wof:placetype":"locality"
},
  "geometry": {"coordinates":[46.9803,37.4143],"type":"Point"}
}