{
  "type": "Feature",
  "properties": {
    "gn:admin1_code":"8",
    "gn:asciiname":"Diljeh Kan",
    "gn:country_code":"IR",
    "gn:dem":86,
    "gn:feature_class":"P",
    "gn:feature_code":"PPL",
    "gn:name":"D\u012bljeh Kan",
    "gn:population":0,
    "gn:timezone":"Asia/Tehran",
    "iso:country":"IR",
    "name:fas_x_preferred":[
        "\u062f\u06cc\u0644\u062c\u0647 \u06a9\u0646"
    ],
    "name:fas_x_variant":[
        "D\u012bljeh Kan"
    ],
    "wof:name":"Diljeh Kan",
    "wof:placetype":"locality"
},
  "geometry": {"coordinates":[48.8768,38.0397],"type":"Point"}
}