{
  "type": "Feature",
  "properties": {
    "gn:admin1_code":"1",
    "gn:asciiname":"Aqdarreh-ye Sofla",
    "gn:country_code":"IR",
    "gn:dem":1928,
    "gn:feature_class":"P",
    "gn:feature_code":"PPL",
    "gn:name":"\u0100qdarreh-ye Sofl\u00e1",
    "gn:population":0,
    "gn:timezone":"Asia/Tehran",
    "iso:country":"IR",
    "name:fas_x_preferred":[
        "\u0622\u063a \u062f\u0631\u0651\u0647 \u0633\u0641\u0644\u06cc"
    ],
    "name:fas_x_variant":[
        "\u0100qdarreh-ye Sofl\u00e1",
        "\u0100gh Darreh-ye Sofl\u00e1",
        "\u0622\u0642\u062f\u0631\u0647 \u0633\u0641\u0644\u06cc"
    ],
    "wof:name":"Aqdarreh-ye Sofla",
    "wof:placetype":"locality"
},
  "geometry": {"coordinates":[47.0753,36.6476],"type":"Point"}
}