{
  "type": "Feature",
  "properties": {
    "gn:admin1_code":"15.0",
    "gn:asciiname":"Gorg Su",
    "gn:country_code":"IR",
    "gn:dem":648,
    "gn:feature_class":"P",
    "gn:feature_code":"PPLL",
    "gn:name":"Gorg S\u016b",
    "gn:population":0,
    "gn:timezone":"Asia/Tehran",
    "iso:country":"IR",
    "name:fas_x_preferred":[
        "\u06af\u0631\u06af \u0633\u0648"
    ],
    "name:fas_x_variant":[
        "Gorg S\u016b"
    ],
    "wof:name":"Gorg Su",
    "wof:placetype":"locality"
},
  "geometry": {"coordinates":[48.56821,32.65532],"type":"Point"}
}