{
  "type": "Feature",
  "properties": {
    "gn:admin1_code":"29",
    "gn:asciiname":"Teydow'iyeh",
    "gn:country_code":"IR",
    "gn:dem":2194,
    "gn:feature_class":"P",
    "gn:feature_code":"PPL",
    "gn:name":"Teydow\u2019\u012byeh",
    "gn:population":0,
    "gn:timezone":"Asia/Tehran",
    "iso:country":"IR",
    "name:fas_x_preferred":[
        "B\u012bd\u016b\u2019\u012byeh"
    ],
    "name:fas_x_variant":[
        "\u062a\u064a\u062f\u0648\u0626\u064a\u0647",
        "\u062a\u06cc \u062f\u0648"
    ],
    "name:und_x_variant":[
        "Teydow\u2019\u012byeh",
        "Tey Dow"
    ],
    "wof:name":"Teydow'iyeh",
    "wof:placetype":"locality"
},
  "geometry": {"coordinates":[55.45051,30.26011],"type":"Point"}
}