{
  "type": "Feature",
  "properties": {
    "gn:admin1_code":"7",
    "gn:asciiname":"Seyyed Davud",
    "gn:country_code":"IR",
    "gn:dem":1547,
    "gn:feature_class":"P",
    "gn:feature_code":"PPL",
    "gn:name":"Seyyed D\u0101v\u016bd",
    "gn:population":0,
    "gn:timezone":"Asia/Tehran",
    "iso:country":"IR",
    "name:fas_x_preferred":[
        "\u0633\u06cc\u062f \u062f\u0627\u0648\u062f"
    ],
    "name:fas_x_variant":[
        "Seyyed D\u0101v\u016bd"
    ],
    "wof:name":"Seyyed Davud",
    "wof:placetype":"locality"
},
  "geometry": {"coordinates":[52.3766,28.9043],"type":"Point"}
}