{
  "type": "Feature",
  "properties": {
    "gn:admin1_code":"8",
    "gn:asciiname":"Charanguyeh",
    "gn:country_code":"IR",
    "gn:dem":116,
    "gn:feature_class":"P",
    "gn:feature_code":"PPL",
    "gn:name":"Charang\u016byeh",
    "gn:population":0,
    "gn:timezone":"Asia/Tehran",
    "iso:country":"IR",
    "name:fas_x_preferred":[
        "Charang\u016byeh"
    ],
    "name:fas_x_variant":[
        "\u0686\u0631\u0646\u06af\u0648\u06cc\u0647"
    ],
    "wof:name":"Charanguyeh",
    "wof:placetype":"locality"
},
  "geometry": {"coordinates":[50.4225,37.00046],"type":"Point"}
}