{
  "type": "Feature",
  "properties": {
    "gn:admin1_code":"22",
    "gn:asciiname":"Zir Rah",
    "gn:country_code":"IR",
    "gn:dem":72,
    "gn:feature_class":"P",
    "gn:feature_code":"PPL",
    "gn:name":"Z\u012br R\u0101h",
    "gn:population":0,
    "gn:timezone":"Asia/Tehran",
    "iso:country":"IR",
    "name:fas_x_preferred":[
        "\u0632\u064a\u0631\u0627\u0647"
    ],
    "name:fas_x_variant":[
        "\u0632\u064a\u0631 \u0631\u0627\u0647",
        "\u0633\u064a\u0631 \u0631\u0627\u0647",
        "\u0632\u064a\u0631\u0650\u0647",
        "Z\u012br\u0101h",
        "Z\u012br R\u0101h"
    ],
    "name:und_x_variant":[
        "S\u012br-e R\u0101h",
        "Z\u012breh",
        "Zira",
        "S\u012br R\u0101h"
    ],
    "wof:name":"Zir Rah",
    "wof:placetype":"locality"
},
  "geometry": {"coordinates":[51.1502,29.4141],"type":"Point"}
}