{
  "type": "Feature",
  "properties": {
    "gn:admin1_code":"4",
    "gn:asciiname":"Sorkhkan",
    "gn:country_code":"IR",
    "gn:dem":1239,
    "gn:feature_class":"P",
    "gn:feature_code":"PPL",
    "gn:name":"Sorkhk\u0101n",
    "gn:population":0,
    "gn:timezone":"Asia/Tehran",
    "iso:country":"IR",
    "name:fas_x_preferred":[
        "\u0633\u0631\u062e\u06a9\u0627\u0646"
    ],
    "name:fas_x_variant":[
        "Sorkhk\u0101n"
    ],
    "wof:name":"Sorkhkan",
    "wof:placetype":"locality"
},
  "geometry": {"coordinates":[61.09718,27.55993],"type":"Point"}
}