{
  "type": "Feature",
  "properties": {
    "gn:admin1_code":"28",
    "gn:asciiname":"Azvar",
    "gn:country_code":"IR",
    "gn:dem":1962,
    "gn:feature_class":"P",
    "gn:feature_code":"PPL",
    "gn:name":"Azv\u0101r",
    "gn:population":0,
    "gn:timezone":"Asia/Tehran",
    "iso:country":"IR",
    "name:fas_x_preferred":[
        "Azv\u0101r"
    ],
    "name:fas_x_variant":[
        "\u0627\u0632\u0648\u0627\u0631"
    ],
    "name:und_x_variant":[
        "Ozv\u0101r",
        "Azw\u0101r",
        "Owzv\u0101r"
    ],
    "wof:name":"Azvar",
    "wof:placetype":"locality"
},
  "geometry": {"coordinates":[51.1533,33.8164],"type":"Point"}
}