{
  "type": "Feature",
  "properties": {
    "gn:admin1_code":"29",
    "gn:asciiname":"Kahn Shahr-e `Olya",
    "gn:country_code":"IR",
    "gn:dem":1784,
    "gn:feature_class":"P",
    "gn:feature_code":"PPL",
    "gn:name":"Kahn Shahr-e \u2018Oly\u0101",
    "gn:population":0,
    "gn:timezone":"Asia/Tehran",
    "iso:country":"IR",
    "name:fas_x_preferred":[
        "\u06a9\u0647\u0646 \u0634\u0647\u0631 \u0628\u0627\u0644\u0627"
    ],
    "name:fas_x_variant":[
        "Kahn Shahr-e B\u0101l\u0101",
        "\u06a9\u0647\u0646 \u0634\u0647\u0631 \u0639\u0644\u064a\u0627"
    ],
    "name:und_x_variant":[
        "Kohan Shahr",
        "Kahn Shahr",
        "Kohneh Shahr",
        "Kahn Shahr-e \u2018Oly\u0101"
    ],
    "wof:name":"Kahn Shahr-e `Olya",
    "wof:placetype":"locality"
},
  "geometry": {"coordinates":[55.8953,29.4007],"type":"Point"}
}