{
  "type": "Feature",
  "properties": {
    "gn:admin1_code":"28",
    "gn:asciiname":"Faran",
    "gn:country_code":"IR",
    "gn:dem":2074,
    "gn:feature_class":"P",
    "gn:feature_code":"PPL",
    "gn:name":"Far\u0101n",
    "gn:population":0,
    "gn:timezone":"Asia/Tehran",
    "iso:country":"IR",
    "name:ara_x_preferred":[
        "\u0641\u0631\u0627\u0646"
    ],
    "name:fas_x_preferred":[
        "\u0641\u0631\u0627\u0646"
    ],
    "name:fas_x_variant":[
        "Far\u0101n",
        "Fer\u0101n"
    ],
    "name:und_x_variant":[
        "Har\u0101n",
        "Hor\u016bn"
    ],
    "wof:name":"Faran",
    "wof:placetype":"locality"
},
  "geometry": {"coordinates":[52.6252,32.9904],"type":"Point"}
}