{
  "type": "Feature",
  "properties": {
    "gn:admin1_code":"26",
    "gn:asciiname":"Amirabad",
    "gn:country_code":"IR",
    "gn:dem":1142,
    "gn:feature_class":"P",
    "gn:feature_code":"PPL",
    "gn:name":"Am\u012br\u0101b\u0101d",
    "gn:population":0,
    "gn:timezone":"Asia/Tehran",
    "iso:country":"IR",
    "name:fas_x_preferred":[
        "\u0627\u0645\u06cc\u0631\u06cc\u0647"
    ],
    "name:fas_x_variant":[
        "Am\u012br\u012byeh",
        "\u0627\u0645\u06cc\u0631 \u0622\u0628\u0627\u062f"
    ],
    "name:und_x_variant":[
        "Am\u012br\u0101b\u0101d"
    ],
    "wof:name":"Amirabad",
    "wof:placetype":"locality"
},
  "geometry": {"coordinates":[50.81846,35.65894],"type":"Point"}
}