{
  "type": "Feature",
  "properties": {
    "gn:admin1_code":"15.0",
    "gn:asciiname":"Shahrak-e Shahid Kamari",
    "gn:country_code":"IR",
    "gn:dem":63,
    "gn:feature_class":"P",
    "gn:feature_code":"PPL",
    "gn:name":"Shahrak-e Shah\u012bd Kamar\u012b",
    "gn:population":0,
    "gn:timezone":"Asia/Tehran",
    "iso:country":"IR",
    "name:fas_x_preferred":[
        "\u0634\u0647\u0631\u06a9 \u0634\u0647\u06cc\u062f \u06a9\u0633\u0631\u06cc"
    ],
    "name:fas_x_variant":[
        "Shahrak-e Shah\u012bd Ghol\u0101mre\u1e95\u0101 Kamar\u012b",
        "Shahrak-e Shah\u012bd Kasr\u00e1",
        "\u0634\u0647\u0631\u06a9 \u0634\u0647\u06cc\u062f \u06a9\u0645\u0631\u06cc",
        "\u0686\u0645 \u0639\u0631\u0628\u0647\u0627"
    ],
    "name:und_x_variant":[
        "Cham-e \u2018Arab\u0101n",
        "\u2018Arab\u0101n",
        "Arabha",
        "Shahrak-e Shah\u012bd Kamar\u012b",
        "Cham \u2018Arabh\u0101",
        "\u0686\u0645 \u0639\u0631\u0628\u0627\u0646"
    ],
    "wof:name":"Shahrak-e Shahid Kamari",
    "wof:placetype":"locality"
},
  "geometry": {"coordinates":[48.8481,32.1844],"type":"Point"}
}