{
  "type": "Feature",
  "properties": {
    "gn:admin1_code":"15.0",
    "gn:asciiname":"Chal Bardar",
    "gn:country_code":"IR",
    "gn:dem":444,
    "gn:feature_class":"P",
    "gn:feature_code":"PPL",
    "gn:name":"Ch\u0101l Bardar",
    "gn:population":0,
    "gn:timezone":"Asia/Tehran",
    "iso:country":"IR",
    "name:fas_x_preferred":[
        "\u0686\u0627\u0644\u0647 \u0628\u0698\u062f\u0631"
    ],
    "name:fas_x_variant":[
        "Ch\u0101leh Bezhdar",
        "\u0686\u0627\u0644 \u0628\u0631\u062f\u0631"
    ],
    "name:und_x_variant":[
        "Ch\u0101l Bardar"
    ],
    "wof:name":"Chal Bardar",
    "wof:placetype":"locality"
},
  "geometry": {"coordinates":[49.03858,32.45953],"type":"Point"}
}