{
  "type": "Feature",
  "properties": {
    "gn:admin1_code":"8",
    "gn:asciiname":"Kolfat",
    "gn:country_code":"IR",
    "gn:dem":59,
    "gn:feature_class":"P",
    "gn:feature_code":"PPL",
    "gn:name":"Kolfat",
    "gn:population":0,
    "gn:timezone":"Asia/Tehran",
    "iso:country":"IR",
    "name:fas_x_preferred":[
        "\u06a9\u0644\u0641\u062a"
    ],
    "wof:name":"Kolfat",
    "wof:placetype":"locality"
},
  "geometry": {"coordinates":[49.31597,37.17257],"type":"Point"}
}