{
  "type": "Feature",
  "properties": {
    "gn:admin1_code":"4.0",
    "gn:asciiname":"Deh-e Qazaq",
    "gn:country_code":"IR",
    "gn:dem":488,
    "gn:feature_class":"P",
    "gn:feature_code":"PPL",
    "gn:name":"Deh-e Qaz\u0101q",
    "gn:population":0,
    "gn:timezone":"Asia/Tehran",
    "iso:country":"IR",
    "name:fas_x_preferred":[
        "\u062f\u0647 \u0642\u0632\u0627\u0642"
    ],
    "name:fas_x_variant":[
        "Qaz\u0101q",
        "Deh-e Qaz\u0101q",
        "\u0642\u0632\u0627\u0642"
    ],
    "wof:name":"Deh-e Qazaq",
    "wof:placetype":"locality"
},
  "geometry": {"coordinates":[61.6246,30.9038],"type":"Point"}
}