{
  "type": "Feature",
  "properties": {
    "gn:admin1_code":"34",
    "gn:asciiname":"Mazra`eh-ye Pa'in",
    "gn:country_code":"IR",
    "gn:dem":2008,
    "gn:feature_class":"P",
    "gn:feature_code":"PPL",
    "gn:name":"Mazra\u2018eh-ye P\u0101\u2019\u012bn",
    "gn:population":0,
    "gn:timezone":"Asia/Tehran",
    "iso:country":"IR",
    "name:fas_x_preferred":[
        "\u0645\u064e\u0632\u0631\u0627\u0639"
    ],
    "name:fas_x_variant":[
        "\u0645\u064e\u0632\u0631\u064e\u0639\u0650\u0647",
        "Mazr\u0101\u2018-e Darreh Sh\u016br",
        "\u0645\u0632\u0631\u0627\u0639 \u062f\u0631\u0651\u0647 \u0634\u0648\u0631",
        "Mazr\u0101\u2018",
        "\u0645\u0632\u0631\u0639\u0647 \u067e\u0627\u0626\u06cc\u0646",
        "\u0645\u0632\u0627\u0631\u0639",
        "\u0645\u0632\u0631\u0627 \u067e\u0627\u06cc\u06cc\u0646"
    ],
    "name:und_x_variant":[
        "Mirza",
        "Mazra\u2018eh",
        "Mazra\u2018eh-ye P\u0101\u2019\u012bn",
        "Maz\u0101re\u2018",
        "Mazar\u0101-ye P\u0101\u2019\u012bn"
    ],
    "wof:name":"Mazra`eh-ye Pa'in",
    "wof:placetype":"locality"
},
  "geometry": {"coordinates":[49.94579,33.76001],"type":"Point"}
}