{
  "type": "Feature",
  "properties": {
    "gn:admin1_code":"13.0",
    "gn:asciiname":"Gareh",
    "gn:country_code":"IR",
    "gn:dem":1200,
    "gn:feature_class":"P",
    "gn:feature_code":"PPL",
    "gn:name":"G\u0101reh",
    "gn:population":0,
    "gn:timezone":"Asia/Tehran",
    "iso:country":"IR",
    "name:fas_x_preferred":[
        "\u06af\u0627\u0631\u0647"
    ],
    "name:fas_x_variant":[
        "G\u0101reh"
    ],
    "wof:name":"Gareh",
    "wof:placetype":"locality"
},
  "geometry": {"coordinates":[46.0292,34.6621],"type":"Point"}
}