{
  "type": "Feature",
  "properties": {
    "gn:admin1_code":"8",
    "gn:asciiname":"Talem Seh Shanbeh",
    "gn:country_code":"IR",
    "gn:dem":32,
    "gn:feature_class":"P",
    "gn:feature_code":"PPL",
    "gn:name":"\u0162\u0101lem Seh Shanbeh",
    "gn:population":0,
    "gn:timezone":"Asia/Tehran",
    "iso:country":"IR",
    "name:fas_x_preferred":[
        "T\u0101lem Seh Shanbeh"
    ],
    "name:fas_x_variant":[
        "\u062a\u0627\u0644\u0645 \u0633\u0647 \u0634\u0646\u0628\u0647",
        "\u0637\u0627\u0644\u0645 \u0633\u0647 \u0634\u0646\u0628\u0647",
        "\u0637\u0627\u0644\u0645 \u0633\u0647\u200c\u0634\u0646\u0628\u0647"
    ],
    "name:msa_x_preferred":[
        "Talem Seh Shanbeh"
    ],
    "name:ukr_x_preferred":[
        "\u0422\u0430\u043b\u0435\u043c-\u0421\u0435\u0448\u0430\u043d\u0431\u0435"
    ],
    "name:und_x_variant":[
        "Seh Shanbeh",
        "Sishkhambekh",
        "Sishambeh",
        "\u0162\u0101lem Seh Shanbeh"
    ],
    "wof:name":"Talem Seh Shanbeh",
    "wof:placetype":"locality"
},
  "geometry": {"coordinates":[49.69039,37.17048],"type":"Point"}
}