{
  "type": "Feature",
  "properties": {
    "gn:admin1_code":"42.0",
    "gn:asciiname":"Mazra`eh-ye 22 Bahman",
    "gn:country_code":"IR",
    "gn:dem":851,
    "gn:feature_class":"P",
    "gn:feature_code":"PPLF",
    "gn:name":"Mazra\u2018eh-ye 22 Bahman",
    "gn:population":0,
    "gn:timezone":"Asia/Tehran",
    "iso:country":"IR",
    "name:fas_x_preferred":[
        "\u0645\u0632\u0631\u0639\u0647 \u0662\u0662 \u0628\u0647\u0645\u0646"
    ],
    "name:und_x_variant":[
        "Mazra\u2018eh-ye 22 Bahman",
        "Mazra\u2018eh-ye B\u012bst-o Do Bahman"
    ],
    "wof:name":"Mazra`eh-ye 22 Bahman",
    "wof:placetype":"locality"
},
  "geometry": {"coordinates":[57.3368,34.01147],"type":"Point"}
}