{
  "type": "Feature",
  "properties": {
    "gn:admin1_code":"5.0",
    "gn:asciiname":"Nar Sorkh",
    "gn:country_code":"IR",
    "gn:dem":1186,
    "gn:feature_class":"P",
    "gn:feature_code":"PPL",
    "gn:name":"Nar Sorkh",
    "gn:population":0,
    "gn:timezone":"Asia/Tehran",
    "iso:country":"IR",
    "name:fas_x_preferred":[
        "\u0646\u0631 \u0633\u0631\u062e"
    ],
    "wof:name":"Nar Sorkh",
    "wof:placetype":"locality"
},
  "geometry": {"coordinates":[50.64311,31.40155],"type":"Point"}
}