{
  "type": "Feature",
  "properties": {
    "gn:admin1_code":"13.0",
    "gn:asciiname":"Sukhvor Shahbaz",
    "gn:country_code":"IR",
    "gn:dem":1095,
    "gn:feature_class":"P",
    "gn:feature_code":"PPL",
    "gn:name":"S\u016bkhvor Shahb\u0101z",
    "gn:population":0,
    "gn:timezone":"Asia/Tehran",
    "iso:country":"IR",
    "name:fas_x_preferred":[
        "\u0633\u0648\u062e\u0648\u0631 \u0634\u0647\u0628\u0627\u0632"
    ],
    "name:fas_x_variant":[
        "S\u016bkhvor Shahb\u0101z",
        "S\u016bkhar-e Kh\u0101n J\u0101n"
    ],
    "name:und_x_variant":[
        "S\u016bkhvor Shahb\u0101z"
    ],
    "wof:name":"Sukhvor Shahbaz",
    "wof:placetype":"locality"
},
  "geometry": {"coordinates":[46.13106,34.17648],"type":"Point"}
}