{
  "type": "Feature",
  "properties": {
    "gn:admin1_code":"29",
    "gn:asciiname":"Ahuan-e Bala",
    "gn:country_code":"IR",
    "gn:dem":430,
    "gn:feature_class":"P",
    "gn:feature_code":"PPL",
    "gn:name":"\u0100h\u016b\u0101n-e B\u0101l\u0101",
    "gn:population":0,
    "gn:timezone":"Asia/Tehran",
    "iso:country":"IR",
    "name:fas_x_preferred":[
        "\u0622\u0647\u0648\u0627\u0646 \u0628\u0627\u0644\u0627"
    ],
    "name:fas_x_variant":[
        "\u0100h\u016bg\u0101n",
        "\u0100h\u016b\u0101n-e B\u0101l\u0101"
    ],
    "wof:name":"Ahuan-e Bala",
    "wof:placetype":"locality"
},
  "geometry": {"coordinates":[57.9372,27.7062],"type":"Point"}
}