{
  "type": "Feature",
  "properties": {
    "gn:admin1_code":"8",
    "gn:asciiname":"Baltork",
    "gn:country_code":"IR",
    "gn:dem":1807,
    "gn:feature_class":"P",
    "gn:feature_code":"PPL",
    "gn:name":"Baltork",
    "gn:population":0,
    "gn:timezone":"Asia/Tehran",
    "iso:country":"IR",
    "name:fas_x_preferred":[
        "\u0628\u0644\u062a\u0631\u06a9"
    ],
    "name:fas_x_variant":[
        "\u0628\u0627\u0644 \u062a\u0631\u06a9"
    ],
    "name:und_x_variant":[
        "Beleh Tork",
        "Baltork",
        "B\u0101l Tark"
    ],
    "wof:name":"Baltork",
    "wof:placetype":"locality"
},
  "geometry": {"coordinates":[50.35648,36.72339],"type":"Point"}
}