{
  "type": "Feature",
  "properties": {
    "gn:admin1_code":"29",
    "gn:asciiname":"Shahrak-e Ma`dan Sowghan",
    "gn:country_code":"IR",
    "gn:dem":1611,
    "gn:feature_class":"P",
    "gn:feature_code":"PPL",
    "gn:name":"Shahrak-e Ma\u2018dan Sowgh\u0101n",
    "gn:population":0,
    "gn:timezone":"Asia/Tehran",
    "iso:country":"IR",
    "name:fas_x_preferred":[
        "\u0645\u0639\u062f\u0646 \u0635\u0648\u063a\u0627\u0646"
    ],
    "name:fas_x_variant":[
        "Ma\u2018dan \u015eowgh\u0101n",
        "\u0634\u0647\u0631\u06a9 \u0645\u0639\u062f\u0646 \u0633\u0648\u063a\u0627\u0646"
    ],
    "name:und_x_variant":[
        "Shahrak-e Ma\u2018dan Sowgh\u0101n"
    ],
    "wof:name":"Shahrak-e Ma`dan Sowghan",
    "wof:placetype":"locality"
},
  "geometry": {"coordinates":[56.8484,28.3578],"type":"Point"}
}