{
  "type": "Feature",
  "properties": {
    "gn:admin1_code":"13",
    "gn:asciiname":"Rezalak",
    "gn:country_code":"IR",
    "gn:dem":611,
    "gn:feature_class":"P",
    "gn:feature_code":"PPL",
    "gn:name":"Re\u1e95\u0101lak",
    "gn:population":0,
    "gn:timezone":"Asia/Tehran",
    "iso:country":"IR",
    "name:ceb_x_preferred":[
        "Re\u1e95\u0101lak"
    ],
    "name:fas_x_preferred":[
        "\u0631\u0636\u0627\u0644\u06a9"
    ],
    "name:fas_x_variant":[
        "Re\u1e95\u0101lak"
    ],
    "name:swe_x_preferred":[
        "Re\u1e95\u0101lak"
    ],
    "name:und_x_variant":[
        "\u2018Al\u012b Gardeh",
        "\u2018Al\u012b Gerdeh"
    ],
    "wof:name":"Rezalak",
    "wof:placetype":"locality"
},
  "geometry": {"coordinates":[45.89556,34.45112],"type":"Point"}
}