{
  "type": "Feature",
  "properties": {
    "gn:admin1_code":"4",
    "gn:asciiname":"Askan Dasht",
    "gn:country_code":"IR",
    "gn:dem":1086,
    "gn:feature_class":"P",
    "gn:feature_code":"PPL",
    "gn:name":"\u0100skan Dasht",
    "gn:population":0,
    "gn:timezone":"Asia/Tehran",
    "iso:country":"IR",
    "name:fas_x_preferred":[
        "\u0622\u0633\u06a9\u0646 \u062f\u0634\u062a"
    ],
    "name:fas_x_variant":[
        "\u0100skan Dasht"
    ],
    "wof:name":"Askan Dasht",
    "wof:placetype":"locality"
},
  "geometry": {"coordinates":[62.5078,27.0046],"type":"Point"}
}