{
  "type": "Feature",
  "properties": {
    "gn:admin1_code":"41",
    "gn:asciiname":"Astand",
    "gn:country_code":"IR",
    "gn:dem":1020,
    "gn:feature_class":"P",
    "gn:feature_code":"PPL",
    "gn:name":"Astand",
    "gn:population":0,
    "gn:timezone":"Asia/Tehran",
    "iso:country":"IR",
    "name:fas_x_preferred":[
        "\u0627\u0633\u062a\u0646\u062f"
    ],
    "name:fas_x_variant":[
        "\u0627\u0633\u062a\u0646\u062f\u062c\u062f\u06cc\u062f"
    ],
    "name:und_x_variant":[
        "Istind",
        "Estend",
        "Astand",
        "Astand-e Jad\u012bd"
    ],
    "wof:name":"Astand",
    "wof:placetype":"locality"
},
  "geometry": {"coordinates":[59.83334,33.85401],"type":"Point"}
}