{
  "type": "Feature",
  "properties": {
    "gn:admin1_code":"8",
    "gn:asciiname":"Zaklebar",
    "gn:country_code":"IR",
    "gn:dem":28,
    "gn:feature_class":"P",
    "gn:feature_code":"PPL",
    "gn:name":"Z\u0101klebar",
    "gn:population":0,
    "gn:timezone":"Asia/Tehran",
    "iso:country":"IR",
    "name:fas_x_preferred":[
        "Z\u0101klebar"
    ],
    "name:fas_x_variant":[
        "Z\u0101kl\u012bvar",
        "\u0632\u0627\u06a9\u0644\u0628\u0631"
    ],
    "wof:name":"Zaklebar",
    "wof:placetype":"locality"
},
  "geometry": {"coordinates":[49.99412,37.15825],"type":"Point"}
}