{
  "type": "Feature",
  "properties": {
    "gn:admin1_code":"29.0",
    "gn:asciiname":"Darzin",
    "gn:country_code":"IR",
    "gn:dem":1965,
    "gn:feature_class":"P",
    "gn:feature_code":"PPL",
    "gn:name":"D\u0101rz\u012bn",
    "gn:population":0,
    "gn:timezone":"Asia/Tehran",
    "iso:country":"IR",
    "wof:name":"Darzin",
    "wof:placetype":"locality"
},
  "geometry": {"coordinates":[57.96861,29.06222],"type":"Point"}
}