{
  "type": "Feature",
  "properties": {
    "gn:admin1_code":"4.0",
    "gn:asciiname":"Tomp",
    "gn:country_code":"IR",
    "gn:dem":1281,
    "gn:feature_class":"P",
    "gn:feature_code":"PPL",
    "gn:name":"Tomp",
    "gn:population":0,
    "gn:timezone":"Asia/Tehran",
    "iso:country":"IR",
    "name:fas_x_preferred":[
        "\u062a\u0645\u067e"
    ],
    "name:und_x_variant":[
        "Tonb",
        "Tomp"
    ],
    "wof:name":"Tomp",
    "wof:placetype":"locality"
},
  "geometry": {"coordinates":[61.04245,27.65453],"type":"Point"}
}