{
  "type": "Feature",
  "properties": {
    "gn:admin1_code":"8.0",
    "gn:asciiname":"Miran",
    "gn:country_code":"IR",
    "gn:dem":196,
    "gn:feature_class":"P",
    "gn:feature_code":"PPL",
    "gn:name":"M\u012br\u0101n",
    "gn:population":0,
    "gn:timezone":"Asia/Tehran",
    "iso:country":"IR",
    "name:ceb_x_preferred":[
        "Miran"
    ],
    "name:deu_x_preferred":[
        "Miran"
    ],
    "name:fas_x_preferred":[
        "M\u012br\u0101n"
    ],
    "name:fas_x_variant":[
        "\u0645\u06cc\u0631\u0627\u0646"
    ],
    "name:heb_x_preferred":[
        "\u05de\u05d9\u05e8\u05df"
    ],
    "name:ind_x_preferred":[
        "Miran"
    ],
    "name:swe_x_preferred":[
        "Miran"
    ],
    "wof:name":"Miran",
    "wof:placetype":"locality"
},
  "geometry": {"coordinates":[49.70474,36.97806],"type":"Point"}
}