{
  "type": "Feature",
  "properties": {
    "gn:admin1_code":"8",
    "gn:asciiname":"Dirakari Mahalleh",
    "gn:country_code":"IR",
    "gn:dem":-7,
    "gn:feature_class":"P",
    "gn:feature_code":"PPL",
    "gn:name":"D\u012br\u0101kar\u012b Ma\u1e29alleh",
    "gn:population":0,
    "gn:timezone":"Asia/Tehran",
    "iso:country":"IR",
    "name:ceb_x_preferred":[
        "D\u012br\u0101kar\u012b"
    ],
    "name:fas_x_preferred":[
        "D\u012br\u0101kar\u012b"
    ],
    "name:fas_x_variant":[
        "\u062f\u06cc\u0631\u0627\u06a9\u0631\u06cc \u0645\u062d\u0644\u0647",
        "\u062f\u06cc\u0631\u0627\u06a9\u0631\u06cc"
    ],
    "name:msa_x_preferred":[
        "Dirakari"
    ],
    "name:swe_x_preferred":[
        "D\u012br\u0101kar\u012b"
    ],
    "name:ukr_x_preferred":[
        "\u0414\u0456\u0440\u0430\u043a\u0430\u0440\u0456"
    ],
    "name:und_x_variant":[
        "Deyr\u0101 Kar\u012b",
        "D\u012br\u0101kar\u012b Ma\u1e29alleh"
    ],
    "wof:name":"Dirakari Mahalleh",
    "wof:placetype":"locality"
},
  "geometry": {"coordinates":[48.91515,37.89667],"type":"Point"}
}