{
  "type": "Feature",
  "properties": {
    "gn:admin1_code":"0",
    "gn:asciiname":"Khanlar Qeshlaqi-ye Sofla",
    "gn:country_code":"IR",
    "gn:dem":202,
    "gn:feature_class":"P",
    "gn:feature_code":"PPL",
    "gn:name":"Kh\u0101nlar Qeshl\u0101q\u012b-ye Sofl\u00e1",
    "gn:population":0,
    "gn:timezone":"Asia/Tehran",
    "iso:country":"IR",
    "name:fas_x_preferred":[
        "\u062e\u0627\u0646\u0644\u064e\u0631 \u0642\u0650\u0634\u0644\u0627\u0642\u0626 \u0633\u064f\u0641\u0644\u064e\u0649"
    ],
    "name:fas_x_variant":[
        "Kh\u0101nlar Qeshl\u0101q\u012b-ye Sofl\u00e1"
    ],
    "wof:name":"Khanlar Qeshlaqi-ye Sofla",
    "wof:placetype":"locality"
},
  "geometry": {"coordinates":[47.51667,39.46667],"type":"Point"}
}