{
  "type": "Feature",
  "properties": {
    "gn:admin1_code":"36",
    "gn:asciiname":"Sari Kand-e Sofla",
    "gn:country_code":"IR",
    "gn:dem":1311,
    "gn:feature_class":"P",
    "gn:feature_code":"PPL",
    "gn:name":"S\u0101r\u012b Kand-e Sofl\u00e1",
    "gn:population":0,
    "gn:timezone":"Asia/Tehran",
    "iso:country":"IR",
    "name:fas_x_preferred":[
        "\u0633\u0627\u0631\u06cc \u06a9\u0646\u062f \u0633\u0641\u0644\u06cc"
    ],
    "name:fas_x_variant":[
        "S\u0101r\u012b Kand-e Sofl\u00e1"
    ],
    "name:und_x_variant":[
        "S\u0101r\u012b Kand-e P\u0101\u2019\u012bn",
        "S\u0101r\u012b Kand"
    ],
    "wof:name":"Sari Kand-e Sofla",
    "wof:placetype":"locality"
},
  "geometry": {"coordinates":[47.5422,36.97565],"type":"Point"}
}