{
  "type": "Feature",
  "properties": {
    "gn:admin1_code":"23",
    "gn:asciiname":"Buryabaf",
    "gn:country_code":"IR",
    "gn:dem":1495,
    "gn:feature_class":"P",
    "gn:feature_code":"PPL",
    "gn:name":"B\u016bry\u0101b\u0101f",
    "gn:population":0,
    "gn:timezone":"Asia/Tehran",
    "iso:country":"IR",
    "name:ara_x_preferred":[
        "\u0628\u0648\u0631\u064a\u0627\u0628\u0627\u0641"
    ],
    "name:ceb_x_preferred":[
        "B\u016bry\u0101b\u0101f"
    ],
    "name:fas_x_preferred":[
        "\u0628\u0648\u0631\u064a\u0627\u0628\u0627\u0641"
    ],
    "name:fas_x_variant":[
        "B\u016bry\u0101b\u0101f",
        "\u0628\u0648\u0631\u06cc\u0627\u0628\u0627\u0641"
    ],
    "name:swe_x_preferred":[
        "B\u016bry\u0101b\u0101f"
    ],
    "name:und_x_variant":[
        "Bure Ab\u0101f",
        "B\u016br\u0101 B\u0101f",
        "B\u016br\u012b\u0101 B\u0101f"
    ],
    "wof:name":"Buryabaf",
    "wof:placetype":"locality"
},
  "geometry": {"coordinates":[48.7304,33.7991],"type":"Point"}
}