{
  "type": "Feature",
  "properties": {
    "gn:admin1_code":"4",
    "gn:asciiname":"Lal Mohammad",
    "gn:country_code":"IR",
    "gn:dem":1493,
    "gn:feature_class":"P",
    "gn:feature_code":"PPL",
    "gn:name":"L\u0101l Mo\u1e29ammad",
    "gn:population":0,
    "gn:timezone":"Asia/Tehran",
    "iso:country":"IR",
    "name:fas_x_preferred":[
        "\u0644\u0627\u0644 \u0645\u062d\u0645\u0651\u062f"
    ],
    "name:fas_x_variant":[
        "L\u0101l Mo\u1e29ammad"
    ],
    "wof:name":"Lal Mohammad",
    "wof:placetype":"locality"
},
  "geometry": {"coordinates":[60.41334000000001,29.23378],"type":"Point"}
}