{
  "type": "Feature",
  "properties": {
    "gn:admin1_code":"1.0",
    "gn:asciiname":"Kani Bi",
    "gn:country_code":"IR",
    "gn:dem":1596,
    "gn:feature_class":"P",
    "gn:feature_code":"PPL",
    "gn:name":"K\u0101n\u012b B\u012b",
    "gn:population":0,
    "gn:timezone":"Asia/Tehran",
    "iso:country":"IR",
    "name:fas_x_preferred":[
        "\u06a9\u0627\u0646\u06cc \u0628\u06cc"
    ],
    "name:fas_x_variant":[
        "K\u0101n\u012b B\u012b"
    ],
    "wof:name":"Kani Bi",
    "wof:placetype":"locality"
},
  "geometry": {"coordinates":[45.4285,36.1311],"type":"Point"}
}