{
  "type": "Feature",
  "properties": {
    "gn:admin1_code":"15",
    "gn:asciiname":"Nomreh-ye Yek-e Bala",
    "gn:country_code":"IR",
    "gn:dem":82,
    "gn:feature_class":"P",
    "gn:feature_code":"PPL",
    "gn:name":"Nomreh-ye Yek-e B\u0101l\u0101",
    "gn:population":0,
    "gn:timezone":"Asia/Tehran",
    "iso:country":"IR",
    "name:fas_x_preferred":[
        "\u0100yatoll\u0101h Montaz\u0327er\u012b-ye B\u0101l\u0101"
    ],
    "name:fas_x_variant":[
        "\u0646\u0645\u0631\u0647 \u06cc\u06a9 \u0628\u0627\u0644\u0627"
    ],
    "name:und_x_variant":[
        "Nomreh Yek",
        "Nomreh-ye Yek-e B\u0101l\u0101"
    ],
    "wof:name":"Nomreh-ye Yek-e Bala",
    "wof:placetype":"locality"
},
  "geometry": {"coordinates":[49.73864,30.76947],"type":"Point"}
}