{
  "type": "Feature",
  "properties": {
    "gn:admin1_code":"1",
    "gn:asciiname":"Babalu",
    "gn:country_code":"IR",
    "gn:dem":1868,
    "gn:feature_class":"P",
    "gn:feature_code":"PPL",
    "gn:name":"B\u0101b\u0101l\u016b",
    "gn:population":0,
    "gn:timezone":"Asia/Tehran",
    "iso:country":"IR",
    "name:fas_x_preferred":[
        "\u0628\u0627\u0628\u0627\u0644\u0648"
    ],
    "name:fas_x_variant":[
        "B\u0101b\u0101l\u016b"
    ],
    "wof:name":"Babalu",
    "wof:placetype":"locality"
},
  "geometry": {"coordinates":[44.5274,39.0665],"type":"Point"}
}