{
  "type": "Feature",
  "properties": {
    "gn:admin1_code":"4.0",
    "gn:asciiname":"Kohan-e `Olya",
    "gn:country_code":"IR",
    "gn:dem":265,
    "gn:feature_class":"P",
    "gn:feature_code":"PPL",
    "gn:name":"Kohan-e \u2018Oly\u0101",
    "gn:population":0,
    "gn:timezone":"Asia/Tehran",
    "iso:country":"IR",
    "name:fas_x_preferred":[
        "Kohan-e \u2018Oly\u0101"
    ],
    "name:fas_x_variant":[
        "Kahn-e B\u0101l\u0101",
        "\u06a9\u0647\u0646 \u0639\u0644\u06cc\u0627"
    ],
    "name:und_x_variant":[
        "Kahn-e Bar\u0101n\u012b",
        "Kahn-e B\u0101l\u0101\u2019\u012b"
    ],
    "wof:name":"Kohan-e `Olya",
    "wof:placetype":"locality"
},
  "geometry": {"coordinates":[60.89007,26.01397],"type":"Point"}
}