{
  "type": "Feature",
  "properties": {
    "gn:admin1_code":"16.0",
    "gn:asciiname":"Kani Tamar Khan",
    "gn:country_code":"IR",
    "gn:dem":1949,
    "gn:feature_class":"P",
    "gn:feature_code":"PPL",
    "gn:name":"K\u0101n\u012b Tamar Kh\u0101n",
    "gn:population":0,
    "gn:timezone":"Asia/Tehran",
    "iso:country":"IR",
    "name:ceb_x_preferred":[
        "K\u0101n\u012b Tamar Kh\u0101n"
    ],
    "name:ckb_x_preferred":[
        "\u06a9\u0627\u0646\u06cc\u062a\u06d5\u0645\u06d5\u0631\u062e\u0627\u0646"
    ],
    "name:fas_x_preferred":[
        "\u0643\u0627\u0646\u06cc \u062a\u064e\u0645\u064e\u0631 \u062e\u0627\u0646"
    ],
    "name:fas_x_variant":[
        "\u06a9\u0627\u0646\u06cc \u062a\u0645\u0631\u062e\u0627\u0646",
        "K\u0101n\u012b Tamar Kh\u0101n"
    ],
    "name:swe_x_preferred":[
        "K\u0101n\u012b Tamar Kh\u0101n"
    ],
    "wof:name":"Kani Tamar Khan",
    "wof:placetype":"locality"
},
  "geometry": {"coordinates":[46.4721,35.7222],"type":"Point"}
}