{
  "type": "Feature",
  "properties": {
    "gn:admin1_code":"11",
    "gn:asciiname":"Birsarki",
    "gn:cc2":"IR",
    "gn:country_code":"IR",
    "gn:dem":512,
    "gn:feature_class":"P",
    "gn:feature_code":"PPL",
    "gn:name":"B\u012brsark\u012b",
    "gn:population":0,
    "gn:timezone":"Asia/Tehran",
    "iso:country":"IR",
    "name:fas_x_preferred":[
        "\u0628\u064a\u0631\u0633\u064e\u0631\u0643\u06cc"
    ],
    "name:fas_x_variant":[
        "\u0628\u064a\u0631 \u0633\u064f\u0631\u064e\u0643\u06cc",
        "B\u012brsark\u012b"
    ],
    "name:und_x_variant":[
        "B\u012br Sorak\u012b"
    ],
    "wof:name":"Birsarki",
    "wof:placetype":"locality"
},
  "geometry": {"coordinates":[57.57528000000001,26.19889],"type":"Point"}
}