{
  "type": "Feature",
  "properties": {
    "gn:admin1_code":"15",
    "gn:asciiname":"Dabar-e Ruz `Ali",
    "gn:country_code":"IR",
    "gn:dem":495,
    "gn:feature_class":"P",
    "gn:feature_code":"PPL",
    "gn:name":"Dabar-e R\u016bz \u2018Al\u012b",
    "gn:population":0,
    "gn:timezone":"Asia/Tehran",
    "iso:country":"IR",
    "name:fas_x_preferred":[
        "\u062f\u0628\u0631 \u0631\u0648\u0632 \u0639\u0644\u06cc"
    ],
    "name:fas_x_variant":[
        "Derb-e R\u016bz \u2018Al\u012b",
        "Dabar-e R\u016bz \u2018Al\u012b",
        "\u0645\u0648\u0631\u06af\u0627\u0647"
    ],
    "name:und_x_variant":[
        "M\u016brg\u0101h"
    ],
    "wof:name":"Dabar-e Ruz `Ali",
    "wof:placetype":"locality"
},
  "geometry": {"coordinates":[50.1761,30.8421],"type":"Point"}
}