{
  "type": "Feature",
  "properties": {
    "gn:admin1_code":"4.0",
    "gn:asciiname":"Baghak",
    "gn:country_code":"IR",
    "gn:dem":481,
    "gn:feature_class":"P",
    "gn:feature_code":"PPL",
    "gn:name":"B\u0101ghak",
    "gn:population":0,
    "gn:timezone":"Asia/Tehran",
    "iso:country":"IR",
    "name:fas_x_preferred":[
        "\u0628\u0627\u063a\u06a9"
    ],
    "name:fas_x_variant":[
        "B\u0101ghak"
    ],
    "wof:name":"Baghak",
    "wof:placetype":"locality"
},
  "geometry": {"coordinates":[61.45997,30.93371],"type":"Point"}
}