{
  "type": "Feature",
  "properties": {
    "gn:admin1_code":"15",
    "gn:asciiname":"Shalu Rak`at-e `Olya",
    "gn:country_code":"IR",
    "gn:dem":908,
    "gn:feature_class":"P",
    "gn:feature_code":"PPL",
    "gn:name":"Sh\u0101l\u016b Rak\u2018at-e \u2018Oly\u0101",
    "gn:population":0,
    "gn:timezone":"Asia/Tehran",
    "iso:country":"IR",
    "name:fas_x_preferred":[
        "Sh\u0101l\u016b"
    ],
    "name:fas_x_variant":[
        "Sh\u0101l\u016b Rak\u2018at-e \u2018Oly\u0101",
        "Rak\u2018at",
        "Rak\u2018at-e Sh\u0101l\u016b",
        "\u0634\u0627\u0644\u0648 \u0631\u06a9\u0639\u062a \u0639\u0644\u06cc\u0627"
    ],
    "name:und_x_variant":[
        "\u0634\u0627\u0644\u0648 \u0631\u06a9\u0639\u062a \u0639\u0644\u06cc\u0627"
    ],
    "wof:name":"Shalu Rak`at-e `Olya",
    "wof:placetype":"locality"
},
  "geometry": {"coordinates":[50.16164000000001,31.75165],"type":"Point"}
}