{
  "type": "Feature",
  "properties": {
    "gn:admin1_code":"4.0",
    "gn:asciiname":"Morad Qoli",
    "gn:country_code":"IR",
    "gn:dem":483,
    "gn:feature_class":"P",
    "gn:feature_code":"PPL",
    "gn:name":"Mor\u0101d Qol\u012b",
    "gn:population":0,
    "gn:timezone":"Asia/Tehran",
    "iso:country":"IR",
    "name:fas_x_preferred":[
        "\u0645\u0631\u0627\u062f \u0642\u0644\u06cc"
    ],
    "name:fas_x_variant":[
        "Mor\u0101d Qol\u012b"
    ],
    "wof:name":"Morad Qoli",
    "wof:placetype":"locality"
},
  "geometry": {"coordinates":[61.7299,31.1301],"type":"Point"}
}