{
  "type": "Feature",
  "properties": {
    "gn:admin1_code":"3",
    "gn:asciiname":"Zirana",
    "gn:cc2":"IR",
    "gn:country_code":"IR",
    "gn:dem":1251,
    "gn:feature_class":"P",
    "gn:feature_code":"PPL",
    "gn:name":"Z\u012br\u0101n\u0101",
    "gn:population":0,
    "gn:timezone":"Asia/Tehran",
    "iso:country":"IR",
    "name:fas_x_preferred":[
        "\u0632\u064a\u0631 \u0627\u064e\u0646\u0651\u0627"
    ],
    "name:fas_x_variant":[
        "\u0632\u064a\u0631\u0646\u0627",
        "Z\u012br\u0101n\u0101"
    ],
    "name:und_x_variant":[
        "Z\u012brn\u0101",
        "Z\u012br Ann\u0101",
        "\u0632\u064a\u0631\u0627\u0646\u0627"
    ],
    "wof:name":"Zirana",
    "wof:placetype":"locality"
},
  "geometry": {"coordinates":[50.78556,31.30333],"type":"Point"}
}