{
  "type": "Feature",
  "properties": {
    "gn:admin1_code":"15",
    "gn:asciiname":"Beyt-e Fars",
    "gn:country_code":"IR",
    "gn:dem":43,
    "gn:feature_class":"P",
    "gn:feature_code":"PPL",
    "gn:name":"Beyt-e F\u0101rs",
    "gn:population":0,
    "gn:timezone":"Asia/Tehran",
    "iso:country":"IR",
    "name:fas_x_preferred":[
        "\u0634\u06cc\u062e \u0632\u0648\u06cc\u0631"
    ],
    "name:fas_x_variant":[
        "Sheykh \u2018Abdoll\u0101h",
        "\u0634\u06cc\u062e \u0639\u0628\u062f\u0627\u0644\u0644\u0651\u0647",
        "\u0628\u06cc\u062a \u0641\u0627\u0631\u0633"
    ],
    "name:und_x_variant":[
        "Sheykh Zeybak",
        "Sheykh Zoveyr",
        "Beyt-e F\u0101rs",
        "Sheykh F\u0101res",
        "\u0634\u06cc\u062e \u0641\u0627\u0631\u0633"
    ],
    "wof:name":"Beyt-e Fars",
    "wof:placetype":"locality"
},
  "geometry": {"coordinates":[48.33599,31.84169],"type":"Point"}
}