{
  "type": "Feature",
  "properties": {
    "gn:admin1_code":"7",
    "gn:asciiname":"Kazemi",
    "gn:country_code":"IR",
    "gn:dem":1572,
    "gn:feature_class":"P",
    "gn:feature_code":"PPL",
    "gn:name":"K\u0101z\u0327em\u012b",
    "gn:population":0,
    "gn:timezone":"Asia/Tehran",
    "iso:country":"IR",
    "name:ara_x_preferred":[
        "\u062a\u0644\u0645\u0628\u0629 \u06a9\u0627\u0638\u0645\u064a"
    ],
    "name:fas_x_preferred":[
        "\u06a9\u0627\u0638\u0645\u06cc"
    ],
    "name:fas_x_variant":[
        "K\u0101z\u0327em\u012b",
        "\u062a\u0644\u0645\u0628\u0647 \u06a9\u0627\u0638\u0645\u06cc"
    ],
    "name:msa_x_preferred":[
        "Tolombeh-ye Kazemi"
    ],
    "name:und_x_variant":[
        "Tolombeh-ye K\u0101z\u0327em\u012b"
    ],
    "wof:name":"Kazemi",
    "wof:placetype":"locality"
},
  "geometry": {"coordinates":[53.4406,29.7887],"type":"Point"}
}