{
  "type": "Feature",
  "properties": {
    "gn:admin1_code":"7",
    "gn:asciiname":"Hezar Darreh",
    "gn:country_code":"IR",
    "gn:dem":1482,
    "gn:feature_class":"P",
    "gn:feature_code":"PPL",
    "gn:name":"Hez\u0101r Darreh",
    "gn:population":0,
    "gn:timezone":"Asia/Tehran",
    "iso:country":"IR",
    "name:fas_x_preferred":[
        "\u0647\u0632\u0627\u0631 \u062f\u0647"
    ],
    "name:fas_x_variant":[
        "Hez\u0101r Darreh",
        "Hez\u0101r Deh",
        "\u0647\u0632\u0627\u0631 \u062f\u0631\u0647",
        "\u0647\u0632\u0627\u0631\u062f\u0631\u0647"
    ],
    "name:msa_x_preferred":[
        "Hezar Darreh"
    ],
    "wof:name":"Hezar Darreh",
    "wof:placetype":"locality"
},
  "geometry": {"coordinates":[53.037,29.1951],"type":"Point"}
}