{
  "type": "Feature",
  "properties": {
    "gn:admin1_code":"13",
    "gn:asciiname":"Sarab-e Shahini",
    "gn:country_code":"IR",
    "gn:dem":1425,
    "gn:feature_class":"P",
    "gn:feature_code":"PPL",
    "gn:name":"Sar\u0101b-e Sh\u0101h\u012bn\u012b",
    "gn:population":0,
    "gn:timezone":"Asia/Tehran",
    "iso:country":"IR",
    "name:ara_x_preferred":[
        "\u0633\u0631\u0627\u0628\u200c\u0634\u0627\u0647\u064a\u0646\u064a"
    ],
    "name:ceb_x_preferred":[
        "Sar\u0101b-e Sh\u0101h\u012bn\u012b"
    ],
    "name:fas_x_preferred":[
        "Sar\u0101b-e Sh\u0101h\u012bn\u012b"
    ],
    "name:fas_x_variant":[
        "\u0633\u0631\u0627\u0628\u200c\u0634\u0627\u0647\u06cc\u0646\u06cc"
    ],
    "name:swe_x_preferred":[
        "Sar\u0101b-e Sh\u0101h\u012bn\u012b"
    ],
    "wof:name":"Sarab-e Shahini",
    "wof:placetype":"locality"
},
  "geometry": {"coordinates":[46.805,34.06722],"type":"Point"}
}