{
  "type": "Feature",
  "properties": {
    "gn:admin1_code":"5",
    "gn:asciiname":"Gowd-e Nar",
    "gn:country_code":"IR",
    "gn:dem":1688,
    "gn:feature_class":"P",
    "gn:feature_code":"PPL",
    "gn:name":"Gowd-e N\u0101r",
    "gn:population":0,
    "gn:timezone":"Asia/Tehran",
    "iso:country":"IR",
    "name:fas_x_preferred":[
        "\u06af\u064f\u0648\u062f\u0650 \u0646\u0627\u0631"
    ],
    "wof:name":"Gowd-e Nar",
    "wof:placetype":"locality"
},
  "geometry": {"coordinates":[51.32389000000001,30.91417],"type":"Point"}
}