{
  "type": "Feature",
  "properties": {
    "gn:admin1_code":"15",
    "gn:asciiname":"Gharganeh",
    "gn:country_code":"IR",
    "gn:dem":68,
    "gn:feature_class":"P",
    "gn:feature_code":"PPL",
    "gn:name":"Gharg\u0101neh",
    "gn:population":0,
    "gn:timezone":"Asia/Tehran",
    "iso:country":"IR",
    "name:fas_x_preferred":[
        "Gharg\u0101neh"
    ],
    "name:fas_x_variant":[
        "\u063a\u0631\u06af\u0627\u0646\u0647"
    ],
    "wof:name":"Gharganeh",
    "wof:placetype":"locality"
},
  "geometry": {"coordinates":[49.37174,31.3637],"type":"Point"}
}