{
  "type": "Feature",
  "properties": {
    "gn:admin1_code":"15",
    "gn:asciiname":"`Abud Ma`ah",
    "gn:country_code":"IR",
    "gn:dem":744,
    "gn:feature_class":"P",
    "gn:feature_code":"PPL",
    "gn:name":"\u2018Ab\u016bd Ma\u2018ah",
    "gn:population":0,
    "gn:timezone":"Asia/Tehran",
    "iso:country":"IR",
    "name:fas_x_preferred":[
        "\u2018Ab\u016bd Ma\u2018ah"
    ],
    "wof:name":"`Abud Ma`ah",
    "wof:placetype":"locality"
},
  "geometry": {"coordinates":[49.81667,31.48333],"type":"Point"}
}