{
  "type": "Feature",
  "properties": {
    "gn:admin1_code":"42",
    "gn:asciiname":"Kalateh-ye Chah-e Tangoli",
    "gn:country_code":"IR",
    "gn:dem":1308,
    "gn:feature_class":"P",
    "gn:feature_code":"PPL",
    "gn:name":"Kal\u0101teh-ye Ch\u0101h-e Tangol\u012b",
    "gn:population":0,
    "gn:timezone":"Asia/Tehran",
    "iso:country":"IR",
    "name:fas_x_preferred":[
        "Ch\u0101h-e Tangol\u012b"
    ],
    "name:fas_x_variant":[
        "Ch\u0101h-e Tangol\u016b",
        "\u0686\u0627\u0647 \u062a\u0646\u06af\u0644\u06cc",
        "\u06a9\u0644\u0627\u062a\u0647 \u0686\u0627\u0647 \u062a\u0646\u06af\u0644\u06cc",
        "\u0686\u0627\u0647 \u062a\u0646\u06af\u0644\u0648"
    ],
    "name:und_x_variant":[
        "\u0686\u0627\u0647 \u062a\u0646\u06af\u0644\u06cc",
        "Kal\u0101teh-ye Ch\u0101h-e Tangol\u012b"
    ],
    "wof:name":"Kalateh-ye Chah-e Tangoli",
    "wof:placetype":"locality"
},
  "geometry": {"coordinates":[58.40968,35.92431],"type":"Point"}
}