{
  "type": "Feature",
  "properties": {
    "gn:admin1_code":"8.0",
    "gn:asciiname":"Keyfat",
    "gn:country_code":"IR",
    "gn:dem":676,
    "gn:feature_class":"P",
    "gn:feature_code":"PPL",
    "gn:name":"Keyfat",
    "gn:population":0,
    "gn:timezone":"Asia/Tehran",
    "iso:country":"IR",
    "name:fas_x_preferred":[
        "\u06a9\u06cc\u0641\u062a"
    ],
    "name:und_x_variant":[
        "\u06a9\u06cc\u0641\u062a"
    ],
    "wof:name":"Keyfat",
    "wof:placetype":"locality"
},
  "geometry": {"coordinates":[49.64779,36.9231],"type":"Point"}
}