{
  "type": "Feature",
  "properties": {
    "gn:admin1_code":"36",
    "gn:asciiname":"Bahman",
    "gn:country_code":"IR",
    "gn:dem":1585,
    "gn:feature_class":"P",
    "gn:feature_code":"PPL",
    "gn:name":"Bahman",
    "gn:population":0,
    "gn:timezone":"Asia/Tehran",
    "iso:country":"IR",
    "name:azb_x_preferred":[
        "\u0628\u0647\u0645\u0646"
    ],
    "name:aze_x_preferred":[
        "B\u0259hm\u0259n"
    ],
    "name:ceb_x_preferred":[
        "Bahman"
    ],
    "name:fas_x_preferred":[
        "\u0628\u0647\u0645\u0646"
    ],
    "name:fas_x_variant":[
        "\u0628\u0650\u0647\u0645\u0627\u0646",
        "\u0628\u064e\u062e\u0645\u064e\u0646"
    ],
    "name:und_x_variant":[
        "Behm\u0101n",
        "Bakhman"
    ],
    "wof:name":"Bahman",
    "wof:placetype":"locality"
},
  "geometry": {"coordinates":[48.25518,36.12622],"type":"Point"}
}