{
  "type": "Feature",
  "properties": {
    "gn:admin1_code":"11",
    "gn:asciiname":"Berentin",
    "gn:country_code":"IR",
    "gn:dem":156,
    "gn:feature_class":"P",
    "gn:feature_code":"PPL",
    "gn:name":"Beren\u0163\u012bn",
    "gn:population":0,
    "gn:timezone":"Asia/Tehran",
    "iso:country":"IR",
    "name:fas_x_preferred":[
        "\u0628\u0631\u0646\u0637\u064a\u0646"
    ],
    "name:fas_x_variant":[
        "Beren\u0163\u012bn"
    ],
    "name:und_x_variant":[
        "B\u012brinti"
    ],
    "wof:name":"Berentin",
    "wof:placetype":"locality"
},
  "geometry": {"coordinates":[57.22355,27.28317],"type":"Point"}
}