{
  "type": "Feature",
  "properties": {
    "gn:admin1_code":"8",
    "gn:asciiname":"Bala Tushi",
    "gn:country_code":"IR",
    "gn:dem":117,
    "gn:feature_class":"P",
    "gn:feature_code":"PPL",
    "gn:name":"B\u0101l\u0101 T\u016bsh\u012b",
    "gn:population":0,
    "gn:timezone":"Asia/Tehran",
    "iso:country":"IR",
    "name:ceb_x_preferred":[
        "T\u016bsh\u012b"
    ],
    "name:fas_x_preferred":[
        "T\u016bsh\u012b"
    ],
    "name:fas_x_variant":[
        "\u0628\u0627\u0644\u0627 \u062a\u0648\u0634\u06cc",
        "\u062a\u0648\u0634\u06cc"
    ],
    "name:msa_x_preferred":[
        "Tushi"
    ],
    "name:swe_x_preferred":[
        "T\u016bsh\u012b"
    ],
    "name:ukr_x_preferred":[
        "\u0422\u0443\u0448\u0456"
    ],
    "name:und_x_variant":[
        "B\u0101l\u0101 T\u016bsh\u012b"
    ],
    "wof:name":"Bala Tushi",
    "wof:placetype":"locality"
},
  "geometry": {"coordinates":[49.87239,37.10755],"type":"Point"}
}