{
  "type": "Feature",
  "properties": {
    "gn:admin1_code":"15.0",
    "gn:asciiname":"Gholam",
    "gn:country_code":"IR",
    "gn:dem":324,
    "gn:feature_class":"P",
    "gn:feature_code":"PPL",
    "gn:name":"Ghol\u0101m",
    "gn:population":0,
    "gn:timezone":"Asia/Tehran",
    "iso:country":"IR",
    "name:fas_x_preferred":[
        "\u06a9\u0644 \u0633\u0631\u062e"
    ],
    "name:fas_x_variant":[
        "\u063a\u0644\u0627\u0645"
    ],
    "name:und_x_variant":[
        "Kal-e Sorkh",
        "Ghol\u0101m"
    ],
    "wof:name":"Gholam",
    "wof:placetype":"locality"
},
  "geometry": {"coordinates":[48.11031,32.66017],"type":"Point"}
}