{
  "type": "Feature",
  "properties": {
    "gn:admin1_code":"33.0",
    "gn:asciiname":"Laleh Zar",
    "gn:country_code":"IR",
    "gn:dem":1790,
    "gn:feature_class":"P",
    "gn:feature_code":"PPL",
    "gn:name":"L\u0101leh Z\u0101r",
    "gn:population":0,
    "gn:timezone":"Asia/Tehran",
    "iso:country":"IR",
    "name:ara_x_preferred":[
        "\u0644\u0627\u0644\u0629 \u0632\u0627\u0631"
    ],
    "name:fas_x_preferred":[
        "\u0644\u0627\u0644\u0647 \u0632\u0627\u0631"
    ],
    "name:fas_x_variant":[
        "\u0644\u0627\u0644\u0647\u200c\u0632\u0627\u0631"
    ],
    "name:msa_x_preferred":[
        "Laleh Zar"
    ],
    "name:und_x_variant":[
        "L\u0101leh Z\u0101r"
    ],
    "name:urd_x_preferred":[
        "\u0644\u0627\u0644\u06c1 \u0632\u0627\u0631"
    ],
    "wof:name":"Laleh Zar",
    "wof:placetype":"locality"
},
  "geometry": {"coordinates":[46.5453,37.1431],"type":"Point"}
}