{
  "type": "Feature",
  "properties": {
    "gn:admin1_code":"11",
    "gn:asciiname":"Darjgi",
    "gn:cc2":"IR",
    "gn:country_code":"IR",
    "gn:dem":355,
    "gn:feature_class":"P",
    "gn:feature_code":"PPL",
    "gn:name":"Darjg\u012b",
    "gn:population":0,
    "gn:timezone":"Asia/Tehran",
    "iso:country":"IR",
    "name:fas_x_preferred":[
        "\u062f\u064e\u0631\u062c\u06af\u06cc"
    ],
    "name:fas_x_variant":[
        "\u062f\u064e\u0631\u0698\u0643\u06cc",
        "Darjg\u012b"
    ],
    "name:und_x_variant":[
        "Darzhk\u012b"
    ],
    "wof:name":"Darjgi",
    "wof:placetype":"locality"
},
  "geometry": {"coordinates":[56.37278000000001,27.50417],"type":"Point"}
}