{
  "type": "Feature",
  "properties": {
    "gn:admin1_code":"37",
    "gn:asciiname":"Mirza Panag",
    "gn:country_code":"IR",
    "gn:dem":155,
    "gn:feature_class":"P",
    "gn:feature_code":"PPL",
    "gn:name":"M\u012brz\u0101 P\u0101nag",
    "gn:population":0,
    "gn:timezone":"Asia/Tehran",
    "iso:country":"IR",
    "name:fas_x_preferred":[
        "\u0645\u064a\u0631\u0632\u0627 \u067e\u0627\u0646\u06af"
    ],
    "name:fas_x_variant":[
        "M\u012brz\u0101 P\u0101ng"
    ],
    "name:und_x_variant":[
        "M\u012brz\u0101 P\u0101nak",
        "M\u012brz\u0101 P\u0101nag"
    ],
    "wof:name":"Mirza Panag",
    "wof:placetype":"locality"
},
  "geometry": {"coordinates":[55.41193000000001,37.29152],"type":"Point"}
}