{
  "type": "Feature",
  "properties": {
    "gn:admin1_code":"7.0",
    "gn:asciiname":"Shahrak-e `Aliabad",
    "gn:country_code":"IR",
    "gn:dem":1634,
    "gn:feature_class":"P",
    "gn:feature_code":"PPL",
    "gn:name":"Shahrak-e \u2018Al\u012b\u0101b\u0101d",
    "gn:population":0,
    "gn:timezone":"Asia/Tehran",
    "iso:country":"IR",
    "name:fas_x_preferred":[
        "\u0634\u0647\u0631\u06a9 \u0639\u0644\u06cc \u0622\u0628\u0627\u062f"
    ],
    "name:fas_x_variant":[
        "Shahrak-e \u2018Al\u012b\u0101b\u0101d"
    ],
    "wof:name":"Shahrak-e `Aliabad",
    "wof:placetype":"locality"
},
  "geometry": {"coordinates":[52.8202,29.6015],"type":"Point"}
}