{
  "type": "Feature",
  "properties": {
    "gn:admin1_code":"32",
    "gn:asciiname":"Hajj Nasir",
    "gn:country_code":"IR",
    "gn:dem":138,
    "gn:feature_class":"P",
    "gn:feature_code":"PPL",
    "gn:name":"\u1e28\u0101jj Na\u015f\u012br",
    "gn:population":0,
    "gn:timezone":"Asia/Tehran",
    "iso:country":"IR",
    "name:fas_x_preferred":[
        "\u062d\u0627\u062c\u0651 \u0646\u064e\u0635\u064a\u0631"
    ],
    "name:fas_x_variant":[
        "\u1e28\u0101jj Na\u015f\u012br"
    ],
    "wof:name":"Hajj Nasir",
    "wof:placetype":"locality"
},
  "geometry": {"coordinates":[47.53861,39.48306],"type":"Point"}
}