{
  "type": "Feature",
  "properties": {
    "gn:admin1_code":"4.0",
    "gn:asciiname":"Surgaf",
    "gn:country_code":"IR",
    "gn:dem":733,
    "gn:feature_class":"P",
    "gn:feature_code":"PPLL",
    "gn:name":"S\u016brg\u0101f",
    "gn:population":0,
    "gn:timezone":"Asia/Tehran",
    "iso:country":"IR",
    "name:fas_x_preferred":[
        "\u0633\u0648\u0631\u06af\u0627\u0641"
    ],
    "name:und_x_variant":[
        "S\u016brg\u0101f"
    ],
    "wof:name":"Surgaf",
    "wof:placetype":"locality"
},
  "geometry": {"coordinates":[59.7095,26.81056],"type":"Point"}
}