{
  "type": "Feature",
  "properties": {
    "gn:admin1_code":"26.0",
    "gn:asciiname":"Qal`eh Beheshti",
    "gn:country_code":"IR",
    "gn:dem":1045,
    "gn:feature_class":"P",
    "gn:feature_code":"PPL",
    "gn:name":"Qal\u2018eh Behesht\u012b",
    "gn:population":0,
    "gn:timezone":"Asia/Tehran",
    "iso:country":"IR",
    "name:fas_x_preferred":[
        "\u0642\u0644\u0639\u0647 \u0628\u0647\u0634\u062a\u06cc"
    ],
    "name:fas_x_variant":[
        "Qal\u2018eh Behesht\u012b"
    ],
    "wof:name":"Qal`eh Beheshti",
    "wof:placetype":"locality"
},
  "geometry": {"coordinates":[51.4225,35.5758],"type":"Point"}
}