{
  "type": "Feature",
  "properties": {
    "gn:admin1_code":"43",
    "gn:asciiname":"Seh Yek Ab",
    "gn:country_code":"IR",
    "gn:dem":1108,
    "gn:feature_class":"P",
    "gn:feature_code":"PPL",
    "gn:name":"Seh Yek \u0100b",
    "gn:population":0,
    "gn:timezone":"Asia/Tehran",
    "iso:country":"IR",
    "name:fas_x_preferred":[
        "Seh Yek \u0100b"
    ],
    "name:fas_x_variant":[
        "\u1e28e\u015f\u0101r-e Seh Yek \u0100b",
        "\u0633\u0647 \u06cc\u06a9 \u0622\u0628"
    ],
    "name:und_x_variant":[
        "\u0633\u0647 \u06cc\u06a9 \u0622\u0628"
    ],
    "wof:name":"Seh Yek Ab",
    "wof:placetype":"locality"
},
  "geometry": {"coordinates":[57.94642,37.40978],"type":"Point"}
}