{
  "type": "Feature",
  "properties": {
    "gn:admin1_code":"16",
    "gn:asciiname":"Ab Barik",
    "gn:country_code":"IR",
    "gn:dem":1871,
    "gn:feature_class":"P",
    "gn:feature_code":"PPL",
    "gn:name":"\u0100b B\u0101r\u012bk",
    "gn:population":0,
    "gn:timezone":"Asia/Tehran",
    "iso:country":"IR",
    "name:fas_x_preferred":[
        "\u0622\u0628 \u0628\u0627\u0631\u064a\u0643"
    ],
    "name:fas_x_variant":[
        "\u0100b B\u0101r\u012bk"
    ],
    "wof:name":"Ab Barik",
    "wof:placetype":"locality"
},
  "geometry": {"coordinates":[47.41792,36.18252],"type":"Point"}
}