{
  "type": "Feature",
  "properties": {
    "gn:admin1_code":"22",
    "gn:asciiname":"Sakhar",
    "gn:country_code":"IR",
    "gn:dem":3,
    "gn:feature_class":"P",
    "gn:feature_code":"PPL",
    "gn:name":"\u015eakhar",
    "gn:population":0,
    "gn:timezone":"Asia/Tehran",
    "iso:country":"IR",
    "name:fas_x_preferred":[
        "\u0635\u064e\u062e\u064e\u0631"
    ],
    "name:fas_x_variant":[
        "\u015eakhar"
    ],
    "wof:name":"Sakhar",
    "wof:placetype":"locality"
},
  "geometry": {"coordinates":[50.6575,29.44111],"type":"Point"}
}