{
  "type": "Feature",
  "properties": {
    "gn:admin1_code":"9",
    "gn:asciiname":"Haryan",
    "gn:country_code":"IR",
    "gn:dem":1687,
    "gn:feature_class":"P",
    "gn:feature_code":"PPL",
    "gn:name":"Hary\u0101n",
    "gn:population":0,
    "gn:timezone":"Asia/Tehran",
    "iso:country":"IR",
    "name:fas_x_preferred":[
        "\u0647\u0631\u06cc\u0627\u0646"
    ],
    "name:fas_x_variant":[
        "\u0647\u064e\u0631\u064a\u0651\u0627\u0646",
        "Hary\u0101n"
    ],
    "name:msa_x_preferred":[
        "Haryan"
    ],
    "name:und_x_variant":[
        "Har\u012by\u0101n"
    ],
    "wof:name":"Haryan",
    "wof:placetype":"locality"
},
  "geometry": {"coordinates":[49.04699,35.20913],"type":"Point"}
}