{
  "type": "Feature",
  "properties": {
    "gn:admin1_code":"28.0",
    "gn:asciiname":"Tutachu'iyeh",
    "gn:country_code":"IR",
    "gn:dem":2241,
    "gn:feature_class":"P",
    "gn:feature_code":"PPL",
    "gn:name":"T\u016btach\u016b\u2019\u012byeh",
    "gn:population":0,
    "gn:timezone":"Asia/Tehran",
    "iso:country":"IR",
    "name:fas_x_preferred":[
        "\u062a\u0648\u062a\u0686\u0648\u0626\u06cc\u0647"
    ],
    "name:fas_x_variant":[
        "T\u016btach\u016b\u2019\u012byeh"
    ],
    "wof:name":"Tutachu'iyeh",
    "wof:placetype":"locality"
},
  "geometry": {"coordinates":[52.8784,32.7543],"type":"Point"}
}