{
  "type": "Feature",
  "properties": {
    "gn:admin1_code":"29.0",
    "gn:asciiname":"Zipa",
    "gn:country_code":"IR",
    "gn:dem":1997,
    "gn:feature_class":"P",
    "gn:feature_code":"PPL",
    "gn:name":"Z\u012bp\u0101",
    "gn:population":0,
    "gn:timezone":"Asia/Tehran",
    "iso:country":"IR",
    "name:fas_x_preferred":[
        "\u0632\u06cc\u067e\u0627"
    ],
    "name:fas_x_variant":[
        "Z\u012bp\u0101"
    ],
    "name:und_x_variant":[
        "Z\u012bb\u0101",
        "Z\u012brp\u0101"
    ],
    "wof:name":"Zipa",
    "wof:placetype":"locality"
},
  "geometry": {"coordinates":[57.8896,28.9038],"type":"Point"}
}