{
  "type": "Feature",
  "properties": {
    "gn:admin1_code":"26.0",
    "gn:asciiname":"Mantaqeh-ye Maskuni-ye Vila'i",
    "gn:country_code":"IR",
    "gn:dem":1651,
    "gn:feature_class":"P",
    "gn:feature_code":"PPL",
    "gn:name":"Man\u0163aqeh-ye Mask\u016bn\u012b-ye V\u012bl\u0101\u2019\u012b",
    "gn:population":0,
    "gn:timezone":"Asia/Tehran",
    "iso:country":"IR",
    "name:fas_x_preferred":[
        "\u0645\u0646\u0637\u0642\u0647 \u0645\u0633\u06a9\u0648\u0646\u06cc \u0648\u06cc\u0644\u0627\u06cc\u06cc"
    ],
    "name:und_x_variant":[
        "Man\u0163aqeh-ye Mask\u016bn\u012b-ye V\u012bl\u0101\u2019\u012b"
    ],
    "wof:name":"Mantaqeh-ye Maskuni-ye Vila'i",
    "wof:placetype":"locality"
},
  "geometry": {"coordinates":[51.90777,35.69036],"type":"Point"}
}