{
  "type": "Feature",
  "properties": {
    "gn:admin1_code":"35.0",
    "gn:asciiname":"Kiab Sar",
    "gn:country_code":"IR",
    "gn:dem":73,
    "gn:feature_class":"P",
    "gn:feature_code":"PPL",
    "gn:name":"K\u012b\u0101b Sar",
    "gn:population":0,
    "gn:timezone":"Asia/Tehran",
    "iso:country":"IR",
    "name:ceb_x_preferred":[
        "K\u012b\u0101 Besar"
    ],
    "name:fas_x_preferred":[
        "\u06a9\u06cc\u0627\u0628 \u0633\u0631"
    ],
    "name:fas_x_variant":[
        "K\u012b\u0101b Sar",
        "K\u012b\u0101 Besar",
        "\u0643\u064a\u0627 \u0628\u0633\u0631",
        "\u06a9\u06cc\u0627\u0628\u200c\u0633\u0631"
    ],
    "name:swe_x_preferred":[
        "K\u012b\u0101 Besar"
    ],
    "wof:name":"Kiab Sar",
    "wof:placetype":"locality"
},
  "geometry": {"coordinates":[52.2118,36.46114],"type":"Point"}
}