{
  "type": "Feature",
  "properties": {
    "gn:admin1_code":"11",
    "gn:asciiname":"Shur Abi",
    "gn:country_code":"IR",
    "gn:dem":620,
    "gn:elevation":"630.0",
    "gn:feature_class":"P",
    "gn:feature_code":"PPL",
    "gn:name":"Sh\u016br \u0100b\u012b",
    "gn:population":0,
    "gn:timezone":"Asia/Tehran",
    "iso:country":"IR",
    "name:fas_x_preferred":[
        "\u0634\u0648\u0631\u064e\u0628\u06cc"
    ],
    "name:fas_x_variant":[
        "\u0634\u0648\u0631 \u0622\u0628\u06cc",
        "Sh\u016brab\u012b",
        "Sh\u016br \u0100b\u012b"
    ],
    "wof:name":"Shur Abi",
    "wof:placetype":"locality"
},
  "geometry": {"coordinates":[56.0692,27.7259],"type":"Point"}
}