{
  "type": "Feature",
  "properties": {
    "gn:admin1_code":"15",
    "gn:asciiname":"Hufel-e Gharbi",
    "gn:country_code":"IR",
    "gn:dem":14,
    "gn:feature_class":"P",
    "gn:feature_code":"PPL",
    "gn:name":"H\u016bfel-e Gharb\u012b",
    "gn:population":0,
    "gn:timezone":"Asia/Tehran",
    "iso:country":"IR",
    "name:azb_x_preferred":[
        "\u0647\u0648\u0641\u0644 \u063a\u0631\u0628\u06cc"
    ],
    "name:fas_x_preferred":[
        "\u0647\u0648\u0641\u0644 \u063a\u0631\u0628\u06cc"
    ],
    "name:fas_x_variant":[
        "H\u016bfel-e Gharb\u012b"
    ],
    "name:und_x_variant":[
        "Howfel",
        "H\u016bfel",
        "Hoofol"
    ],
    "wof:name":"Hufel-e Gharbi",
    "wof:placetype":"locality"
},
  "geometry": {"coordinates":[48.18236,31.58976],"type":"Point"}
}