{
  "type": "Feature",
  "properties": {
    "gn:admin1_code":"7.0",
    "gn:asciiname":"Baba Sheykh `Ali",
    "gn:country_code":"IR",
    "gn:dem":1283,
    "gn:feature_class":"P",
    "gn:feature_code":"PPL",
    "gn:name":"B\u0101b\u0101 Sheykh \u2018Al\u012b",
    "gn:population":0,
    "gn:timezone":"Asia/Tehran",
    "iso:country":"IR",
    "name:fas_x_preferred":[
        "\u0628\u0627\u0628\u0627 \u0634\u06cc\u062e \u0639\u0644\u06cc"
    ],
    "name:fas_x_variant":[
        "B\u0101b\u0101 Sheykh \u2018Al\u012b"
    ],
    "wof:name":"Baba Sheykh `Ali",
    "wof:placetype":"locality"
},
  "geometry": {"coordinates":[53.8299,28.8787],"type":"Point"}
}