{
  "type": "Feature",
  "properties": {
    "gn:admin1_code":"32.0",
    "gn:asciiname":"Hemmatabad",
    "gn:country_code":"IR",
    "gn:dem":960,
    "gn:feature_class":"P",
    "gn:feature_code":"PPL",
    "gn:name":"\u1e28emmat\u0101b\u0101d",
    "gn:population":0,
    "gn:timezone":"Asia/Tehran",
    "iso:country":"IR",
    "wof:name":"Hemmatabad",
    "wof:placetype":"locality"
},
  "geometry": {"coordinates":[48.00417,39.025],"type":"Point"}
}