{
  "type": "Feature",
  "properties": {
    "gn:admin1_code":"13",
    "gn:asciiname":"Gah Maghal",
    "gn:country_code":"IR",
    "gn:dem":639,
    "gn:feature_class":"P",
    "gn:feature_code":"PPL",
    "gn:name":"G\u0101h Maghal",
    "gn:population":0,
    "gn:timezone":"Asia/Tehran",
    "iso:country":"IR",
    "name:fas_x_preferred":[
        "\u06af\u0627\u0647 \u0645\u063a\u0644"
    ],
    "name:fas_x_variant":[
        "G\u0101vmakhal",
        "G\u0101h Maghal"
    ],
    "name:und_x_variant":[
        "G\u0101mq\u0101l"
    ],
    "wof:name":"Gah Maghal",
    "wof:placetype":"locality"
},
  "geometry": {"coordinates":[45.82074,34.25902],"type":"Point"}
}