{
  "type": "Feature",
  "properties": {
    "gn:admin1_code":"4.0",
    "gn:asciiname":"Kaksuj",
    "gn:country_code":"IR",
    "gn:dem":43,
    "gn:feature_class":"P",
    "gn:feature_code":"PPL",
    "gn:name":"Kaks\u016bj",
    "gn:population":0,
    "gn:timezone":"Asia/Tehran",
    "iso:country":"IR",
    "name:fas_x_preferred":[
        "Kaks\u016bj"
    ],
    "name:fas_x_variant":[
        "\u06a9\u06a9\u0633\u0648\u062c"
    ],
    "wof:name":"Kaksuj",
    "wof:placetype":"locality"
},
  "geometry": {"coordinates":[61.45425,25.76182],"type":"Point"}
}