{
  "type": "Feature",
  "properties": {
    "gn:admin1_code":"40",
    "gn:asciiname":"Mazra`eh-ye Navvab",
    "gn:country_code":"IR",
    "gn:dem":1634,
    "gn:feature_class":"P",
    "gn:feature_code":"PPL",
    "gn:name":"Mazra\u2018eh-ye Navv\u0101b",
    "gn:population":0,
    "gn:timezone":"Asia/Tehran",
    "iso:country":"IR",
    "name:fas_x_preferred":[
        "\u0645\u064e\u0632\u0631\u064e\u0639\u0650\u06c0 \u0646\u064e\u0648\u0651\u0627\u0628"
    ],
    "name:fas_x_variant":[
        "Mazra\u2018eh-ye Navv\u0101b"
    ],
    "name:und_x_variant":[
        "Mazra\u2018eh Naw\u0101h"
    ],
    "wof:name":"Mazra`eh-ye Navvab",
    "wof:placetype":"locality"
},
  "geometry": {"coordinates":[54.16667,31.76667],"type":"Point"}
}