{
  "type": "Feature",
  "properties": {
    "gn:admin1_code":"15",
    "gn:asciiname":"Hanafareh",
    "gn:country_code":"IR",
    "gn:dem":8,
    "gn:feature_class":"P",
    "gn:feature_code":"PPL",
    "gn:name":"\u1e28an\u0101fareh",
    "gn:population":0,
    "gn:timezone":"Asia/Tehran",
    "iso:country":"IR",
    "name:fas_x_preferred":[
        "Khan\u0101fereh"
    ],
    "name:fas_x_variant":[
        "\u062d\u0646\u0627\u0641\u0631\u0647",
        "\u1e28an\u0101fareh"
    ],
    "name:und_x_variant":[
        "\u1e28an\u0101fareh",
        "\u062d\u0646\u0627\u0641\u0631\u0647",
        "Garmeh-ye Khan\u0101fereh"
    ],
    "wof:name":"Hanafareh",
    "wof:placetype":"locality"
},
  "geometry": {"coordinates":[48.6067,30.6108],"type":"Point"}
}