{
  "type": "Feature",
  "properties": {
    "gn:admin1_code":"3",
    "gn:asciiname":"Shahriar",
    "gn:cc2":"IR",
    "gn:country_code":"IR",
    "gn:dem":1856,
    "gn:feature_class":"P",
    "gn:feature_code":"PPL",
    "gn:name":"Shahr\u012b\u0101r",
    "gn:population":0,
    "gn:timezone":"Asia/Tehran",
    "iso:country":"IR",
    "name:fas_x_preferred":[
        "Shahr\u012b\u0101r"
    ],
    "name:fas_x_variant":[
        "\u0634\u064e\u0647\u0631\u064a\u0627\u0631"
    ],
    "name:und_x_variant":[
        "Shahry\u0101r"
    ],
    "wof:name":"Shahriar",
    "wof:placetype":"locality"
},
  "geometry": {"coordinates":[51.22444,31.34806],"type":"Point"}
}