{
  "type": "Feature",
  "properties": {
    "gn:admin1_code":"9",
    "gn:asciiname":"Daqdaqabad",
    "gn:country_code":"IR",
    "gn:dem":1654,
    "gn:feature_class":"P",
    "gn:feature_code":"PPL",
    "gn:name":"D\u0101qd\u0101q\u0101b\u0101d",
    "gn:population":0,
    "gn:timezone":"Asia/Tehran",
    "iso:country":"IR",
    "name:fas_x_preferred":[
        "\u062f\u0627\u0642\u062f\u0627\u0642 \u0622\u0628\u0627\u062f"
    ],
    "name:fas_x_variant":[
        "D\u0101qd\u0101q\u0101b\u0101d",
        "\u062f\u0627\u0642\u200c\u062f\u0627\u0642\u200c\u0622\u0628\u0627\u062f"
    ],
    "name:ita_x_preferred":[
        "Daqdaqabad"
    ],
    "name:msa_x_preferred":[
        "Daqdaqabad"
    ],
    "name:rus_x_preferred":[
        "\u0414\u0430\u043a\u0434\u0430\u043a\u0430\u0431\u0430\u0434"
    ],
    "wof:name":"Daqdaqabad",
    "wof:placetype":"locality"
},
  "geometry": {"coordinates":[48.78826,35.18281],"type":"Point"}
}