{
  "type": "Feature",
  "properties": {
    "gn:admin1_code":"11",
    "gn:asciiname":"Siah Moghan-e Bala",
    "gn:country_code":"IR",
    "gn:dem":637,
    "gn:feature_class":"P",
    "gn:feature_code":"PPL",
    "gn:name":"S\u012b\u0101h Mogh\u0101n-e B\u0101l\u0101",
    "gn:population":0,
    "gn:timezone":"Asia/Tehran",
    "iso:country":"IR",
    "name:fas_x_preferred":[
        "\u0633\u064a\u0627\u0647 \u0645\u063a\u0627\u0646 \u0628\u0627\u0644\u0627"
    ],
    "name:fas_x_variant":[
        "\u0633\u064a\u0627\u0647 \u0645\u064e\u063a\u0627\u0646\u0650 \u067e\u0627\u0626\u064a\u0646",
        "\u0633\u0650\u064a\u0627\u0646 \u0645\u064f\u063a\u0627\u0646",
        "\u0633\u064a\u0627\u0647 \u0645\u064e\u063a\u0627\u0646\u0650 \u0628\u0627\u0644\u0627",
        "\u0633\u064a\u0627\u0647 \u0645\u064f\u063a\u0627\u0646",
        "S\u012b\u0101h Mogh\u0101n-e B\u0101l\u0101",
        "\u0633\u06cc\u0627\u0647\u200c\u0645\u063a\u0627\u0646 \u0628\u0627\u0644\u0627"
    ],
    "name:msa_x_preferred":[
        "Siah Moghan-e Bala"
    ],
    "name:und_x_variant":[
        "Sey\u0101n Mogh\u0101n",
        "S\u012b\u0101h Magh\u0101n-e P\u0101\u2019\u012bn",
        "S\u012b\u0101h Mogh\u0101n",
        "S\u012b\u0101h Magh\u0101n-e B\u0101l\u0101"
    ],
    "wof:name":"Siah Moghan-e Bala",
    "wof:placetype":"locality"
},
  "geometry": {"coordinates":[57.2169,27.63],"type":"Point"}
}