{
  "type": "Feature",
  "properties": {
    "gn:admin1_code":"1",
    "gn:asciiname":"Demdem",
    "gn:country_code":"IR",
    "gn:dem":2178,
    "gn:feature_class":"P",
    "gn:feature_code":"PPL",
    "gn:name":"Demdem",
    "gn:population":0,
    "gn:timezone":"Asia/Tehran",
    "iso:country":"IR",
    "name:aze_x_preferred":[
        "D\u0259md\u0259m"
    ],
    "name:fas_x_preferred":[
        "\u062f\u0645 \u062f\u0645"
    ],
    "name:fas_x_variant":[
        "\u062f\u0645\u062f\u0645"
    ],
    "name:msa_x_preferred":[
        "Demdem"
    ],
    "name:und_x_variant":[
        "\u062f\u0645 \u062f\u0645"
    ],
    "wof:name":"Demdem",
    "wof:placetype":"locality"
},
  "geometry": {"coordinates":[44.4637,38.883],"type":"Point"}
}