{
  "type": "Feature",
  "properties": {
    "gn:admin1_code":"7",
    "gn:asciiname":"Dashtollah",
    "gn:country_code":"IR",
    "gn:dem":1234,
    "gn:feature_class":"P",
    "gn:feature_code":"PPL",
    "gn:name":"Dashtoll\u0101h",
    "gn:population":0,
    "gn:timezone":"Asia/Tehran",
    "iso:country":"IR",
    "name:fas_x_preferred":[
        "\u062f\u0634\u062a \u0627\u0644\u0644\u0647"
    ],
    "name:fas_x_variant":[
        "Dashtoll\u0101h"
    ],
    "wof:name":"Dashtollah",
    "wof:placetype":"locality"
},
  "geometry": {"coordinates":[54.2786,28.6342],"type":"Point"}
}