{
  "type": "Feature",
  "properties": {
    "gn:admin1_code":"5.0",
    "gn:asciiname":"Deh-e Now",
    "gn:country_code":"IR",
    "gn:dem":1902,
    "gn:feature_class":"P",
    "gn:feature_code":"PPL",
    "gn:name":"Deh-e Now",
    "gn:population":0,
    "gn:timezone":"Asia/Tehran",
    "iso:country":"IR",
    "name:fas_x_preferred":[
        "\u062f\u0647 \u0646\u0648"
    ],
    "name:und_x_variant":[
        "\u062f\u0647 \u0646\u0648"
    ],
    "wof:name":"Deh-e Now",
    "wof:placetype":"locality"
},
  "geometry": {"coordinates":[50.68178,31.24661],"type":"Point"}
}