{
  "type": "Feature",
  "properties": {
    "gn:admin1_code":"28.0",
    "gn:asciiname":"Firuzan",
    "gn:country_code":"IR",
    "gn:dem":1636,
    "gn:feature_class":"P",
    "gn:feature_code":"PPL",
    "gn:name":"F\u012br\u016bz\u0101n",
    "gn:population":0,
    "gn:timezone":"Asia/Tehran",
    "iso:country":"IR",
    "name:fas_x_preferred":[
        "\u0633\u064f\u0647\u0631\u0650 \u0641\u064a\u0631\u0648\u0632\u0627\u0646"
    ],
    "name:fas_x_variant":[
        "\u0633\u064e\u0641\u064a\u0648\u064e\u0632\u0627\u0646",
        "F\u012br\u016bz\u0101n",
        "Sohr F\u012br\u016bz\u0101n",
        "\u0641\u06cc\u0631\u0648\u0632\u0627\u0646"
    ],
    "name:und_x_variant":[
        "Safiruz\u0101n",
        "Sohr-e F\u012br\u016bz\u0101n",
        "Saf\u012bvaz\u0101n",
        "\u0641\u06cc\u0631\u0648\u0632\u0627\u0646"
    ],
    "wof:name":"Firuzan",
    "wof:placetype":"locality"
},
  "geometry": {"coordinates":[51.53229,32.45959000000001],"type":"Point"}
}