{
  "type": "Feature",
  "properties": {
    "gn:admin1_code":"40",
    "gn:asciiname":"Hajj-e Shams",
    "gn:country_code":"IR",
    "gn:dem":2265,
    "gn:feature_class":"P",
    "gn:feature_code":"PPLF",
    "gn:name":"\u1e28\u0101jj-e Shams",
    "gn:population":0,
    "gn:timezone":"Asia/Tehran",
    "iso:country":"IR",
    "name:fas_x_preferred":[
        "Mazra\u2018eh-ye \u2019\u0101jj\u012b Shams"
    ],
    "name:fas_x_variant":[
        "\u1e28\u0101jj\u012b Shams",
        "\u062d\u0627\u062c\u06cc \u0634\u0645\u0633",
        "\u062d\u0627\u062c \u0634\u0645\u0633"
    ],
    "name:und_x_variant":[
        "\u1e28\u0101jj-e Shams"
    ],
    "wof:name":"Hajj-e Shams",
    "wof:placetype":"locality"
},
  "geometry": {"coordinates":[54.34371,31.40693],"type":"Point"}
}