{
  "type": "Feature",
  "properties": {
    "gn:admin1_code":"8",
    "gn:asciiname":"Rik",
    "gn:country_code":"IR",
    "gn:dem":-6,
    "gn:feature_class":"P",
    "gn:feature_code":"PPL",
    "gn:name":"R\u012bk",
    "gn:population":0,
    "gn:timezone":"Asia/Tehran",
    "iso:country":"IR",
    "name:fas_x_preferred":[
        "\u0631\u06cc\u06a9"
    ],
    "name:fas_x_variant":[
        "R\u012bk Ma\u1e29alleh-ye \u1e28av\u012bq",
        "R\u012bk"
    ],
    "name:und_x_variant":[
        "R\u012bk-e No\u015frat\u0101b\u0101d"
    ],
    "wof:name":"Rik",
    "wof:placetype":"locality"
},
  "geometry": {"coordinates":[48.8939,38.1372],"type":"Point"}
}