{
  "type": "Feature",
  "properties": {
    "gn:admin1_code":"4",
    "gn:asciiname":"Barekatabad",
    "gn:country_code":"IR",
    "gn:dem":1158,
    "gn:feature_class":"P",
    "gn:feature_code":"PPL",
    "gn:name":"Barekat\u0101b\u0101d",
    "gn:population":0,
    "gn:timezone":"Asia/Tehran",
    "iso:country":"IR",
    "name:fas_x_preferred":[
        "\u0628\u0631\u06a9\u062a \u0622\u0628\u0627\u062f"
    ],
    "name:fas_x_variant":[
        "Barekat\u0101b\u0101d"
    ],
    "wof:name":"Barekatabad",
    "wof:placetype":"locality"
},
  "geometry": {"coordinates":[61.3077,28.9286],"type":"Point"}
}