{
  "type": "Feature",
  "properties": {
    "gn:admin1_code":"35.0",
    "gn:asciiname":"Kalayeh",
    "gn:country_code":"IR",
    "gn:dem":2134,
    "gn:feature_class":"P",
    "gn:feature_code":"PPL",
    "gn:name":"Kal\u0101yeh",
    "gn:population":0,
    "gn:timezone":"Asia/Tehran",
    "iso:country":"IR",
    "name:fas_x_preferred":[
        "Kal\u0101yeh"
    ],
    "name:fas_x_variant":[
        "\u06a9\u0644\u0627\u06cc\u0647"
    ],
    "name:und_x_variant":[
        "\u06a9\u0644\u0627\u06cc\u0647"
    ],
    "wof:name":"Kalayeh",
    "wof:placetype":"locality"
},
  "geometry": {"coordinates":[50.45464000000001,36.63194],"type":"Point"}
}