{
  "type": "Feature",
  "properties": {
    "gn:admin1_code":"25.0",
    "gn:asciiname":"Istgah-e Bon-e Kuh",
    "gn:country_code":"IR",
    "gn:dem":1014,
    "gn:feature_class":"P",
    "gn:feature_code":"PPL",
    "gn:name":"\u012astg\u0101h-e Bon-e K\u016bh",
    "gn:population":0,
    "gn:timezone":"Asia/Tehran",
    "iso:country":"IR",
    "name:fas_x_preferred":[
        "\u064a\u0633\u062a\u06af\u0627\u0647\u0650 \u0631\u0627\u0647 \u0622\u0647\u064e\u0646\u0650 \u0628\u064f\u0646\u0650 \u0643\u0648\u0647"
    ],
    "name:fas_x_variant":[
        "\u0627\u064a\u0633\u062a\u06af\u0627\u0647 \u0628\u0646 \u0643\u0648\u0647",
        "\u012astg\u0101h-e R\u0101h \u0100han-e Bon-e K\u016bh",
        "\u012astg\u0101h-e Bon-e K\u016bh"
    ],
    "name:und_x_variant":[
        "\u012astg\u0101h-e Bon-e K\u016bh"
    ],
    "wof:name":"Istgah-e Bon-e Kuh",
    "wof:placetype":"locality"
},
  "geometry": {"coordinates":[52.4292,35.30602000000001],"type":"Point"}
}