{
  "type": "Feature",
  "properties": {
    "gn:admin1_code":"13",
    "gn:asciiname":"Gol Darreh-ye `Olya",
    "gn:country_code":"IR",
    "gn:dem":1540,
    "gn:feature_class":"P",
    "gn:feature_code":"PPL",
    "gn:name":"Gol Darreh-ye \u2018Oly\u0101",
    "gn:population":0,
    "gn:timezone":"Asia/Tehran",
    "iso:country":"IR",
    "name:fas_x_preferred":[
        "\u06af\u0644 \u062f\u0631\u0651\u0647 \u0639\u0644\u06cc\u0627"
    ],
    "name:fas_x_variant":[
        "Gol Darreh-ye \u2018Oly\u0101"
    ],
    "wof:name":"Gol Darreh-ye `Olya",
    "wof:placetype":"locality"
},
  "geometry": {"coordinates":[46.5484,34.4171],"type":"Point"}
}