{
  "type": "Feature",
  "properties": {
    "gn:admin1_code":"29",
    "gn:asciiname":"Parnatabad",
    "gn:country_code":"IR",
    "gn:dem":1974,
    "gn:feature_class":"P",
    "gn:feature_code":"PPL",
    "gn:name":"Parnat\u0101b\u0101d",
    "gn:population":0,
    "gn:timezone":"Asia/Tehran",
    "iso:country":"IR",
    "name:fas_x_preferred":[
        "\u067e\u0631\u0646\u062a \u0622\u0628\u0627\u062f"
    ],
    "name:fas_x_variant":[
        "Parnat\u0101b\u0101d"
    ],
    "wof:name":"Parnatabad",
    "wof:placetype":"locality"
},
  "geometry": {"coordinates":[56.8828,28.4911],"type":"Point"}
}