{
  "type": "Feature",
  "properties": {
    "gn:admin1_code":"28.0",
    "gn:asciiname":"`Arusan Golestan",
    "gn:country_code":"IR",
    "gn:dem":925,
    "gn:feature_class":"P",
    "gn:feature_code":"PPL",
    "gn:name":"\u2018Ar\u016bs\u0101n Golest\u0101n",
    "gn:population":0,
    "gn:timezone":"Asia/Tehran",
    "iso:country":"IR",
    "name:fas_x_preferred":[
        "\u2018Ar\u016bs\u0101n"
    ],
    "name:fas_x_variant":[
        "\u0639\u0631\u0648\u0633\u0627\u0646",
        "Aras\u016bn",
        "\u0639\u0631\u0648\u0633\u0627\u0646 \u06af\u0644\u0633\u062a\u0627\u0646"
    ],
    "name:und_x_variant":[
        "\u2018Ar\u016bs\u0101n Golest\u0101n"
    ],
    "wof:name":"`Arusan Golestan",
    "wof:placetype":"locality"
},
  "geometry": {"coordinates":[55.0209,33.47517],"type":"Point"}
}