{
  "type": "Feature",
  "properties": {
    "gn:admin1_code":"11.0",
    "gn:asciiname":"Kal-e Zorat",
    "gn:country_code":"IR",
    "gn:dem":41,
    "gn:feature_class":"P",
    "gn:feature_code":"PPL",
    "gn:name":"Kal-e Z\u0304orat",
    "gn:population":0,
    "gn:timezone":"Asia/Tehran",
    "iso:country":"IR",
    "name:fas_x_preferred":[
        "\u0643\u0644 \u0630\u0631\u062a"
    ],
    "name:fas_x_variant":[
        "Kal-e Z\u0304orat"
    ],
    "wof:name":"Kal-e Zorat",
    "wof:placetype":"locality"
},
  "geometry": {"coordinates":[56.7761,27.4142],"type":"Point"}
}