{
  "type": "Feature",
  "properties": {
    "gn:admin1_code":"35.0",
    "gn:asciiname":"Shahrak-e Farhangian",
    "gn:country_code":"IR",
    "gn:dem":43,
    "gn:feature_class":"P",
    "gn:feature_code":"PPL",
    "gn:name":"Shahrak-e Farhang\u012b\u0101n",
    "gn:population":0,
    "gn:timezone":"Asia/Tehran",
    "iso:country":"IR",
    "name:fas_x_preferred":[
        "\u0634\u0647\u0631\u06a9 \u0641\u0631\u0647\u0646\u06af\u06cc\u0627\u0646"
    ],
    "name:und_x_variant":[
        "Shahrak-e Farhang\u012b\u0101n"
    ],
    "wof:name":"Shahrak-e Farhangian",
    "wof:placetype":"locality"
},
  "geometry": {"coordinates":[51.47463,36.6225],"type":"Point"}
}