{
  "type": "Feature",
  "properties": {
    "gn:admin1_code":"42",
    "gn:asciiname":"Qezlar",
    "gn:country_code":"IR",
    "gn:dem":1193,
    "gn:feature_class":"P",
    "gn:feature_code":"PPL",
    "gn:name":"Qezlar",
    "gn:population":0,
    "gn:timezone":"Asia/Tehran",
    "iso:country":"IR",
    "name:fas_x_preferred":[
        "\u0642\u0632\u0644\u0631"
    ],
    "name:und_x_variant":[
        "Qizl\u0101r",
        "Qazlar"
    ],
    "wof:name":"Qezlar",
    "wof:placetype":"locality"
},
  "geometry": {"coordinates":[59.04874,36.63682],"type":"Point"}
}