{
  "type": "Feature",
  "properties": {
    "gn:admin1_code":"32",
    "gn:asciiname":"Qarapalchaq",
    "gn:country_code":"IR",
    "gn:dem":2053,
    "gn:feature_class":"P",
    "gn:feature_code":"PPL",
    "gn:name":"Q\u0101r\u0101p\u0101lchaq",
    "gn:population":0,
    "gn:timezone":"Asia/Tehran",
    "iso:country":"IR",
    "name:fas_x_preferred":[
        "Qareh Y\u0101lcheq"
    ],
    "name:fas_x_variant":[
        "\u0642\u0627\u0631\u0627\u067e\u0627\u0644\u0686\u0642"
    ],
    "name:und_x_variant":[
        "Q\u0101r\u0101p\u0101lchaq"
    ],
    "wof:name":"Qarapalchaq",
    "wof:placetype":"locality"
},
  "geometry": {"coordinates":[48.68406,37.95871],"type":"Point"}
}