{
  "type": "Feature",
  "properties": {
    "gn:admin1_code":"23",
    "gn:asciiname":"Bardbol",
    "gn:country_code":"IR",
    "gn:dem":1716,
    "gn:feature_class":"P",
    "gn:feature_code":"PPL",
    "gn:name":"Bardbol",
    "gn:population":0,
    "gn:timezone":"Asia/Tehran",
    "iso:country":"IR",
    "name:fas_x_preferred":[
        "\u0628\u0627\u0631\u062f\u0628\u0627\u0644"
    ],
    "name:fas_x_variant":[
        "\u0628\u0631\u062f\u0628\u0644"
    ],
    "name:und_x_variant":[
        "B\u0101rdb\u0101l",
        "Bard Bal",
        "Bardbol"
    ],
    "wof:name":"Bardbol",
    "wof:placetype":"locality"
},
  "geometry": {"coordinates":[48.06841,33.76913],"type":"Point"}
}