{
  "type": "Feature",
  "properties": {
    "gn:admin1_code":"9",
    "gn:asciiname":"Gamasa",
    "gn:country_code":"IR",
    "gn:dem":2087,
    "gn:feature_class":"P",
    "gn:feature_code":"PPL",
    "gn:name":"Gam\u0101s\u0101",
    "gn:population":0,
    "gn:timezone":"Asia/Tehran",
    "iso:country":"IR",
    "name:ceb_x_preferred":[
        "Kam\u0101s\u0101"
    ],
    "name:fas_x_preferred":[
        "\u06a9\u0645\u0627\u0633\u0627"
    ],
    "name:fas_x_variant":[
        "Gam\u0101s\u0101",
        "Kam\u0101s\u0101",
        "\u06af\u0645\u0627\u0633\u0627"
    ],
    "name:msa_x_preferred":[
        "Gamasa"
    ],
    "name:swe_x_preferred":[
        "Kam\u0101s\u0101"
    ],
    "wof:name":"Gamasa",
    "wof:placetype":"locality"
},
  "geometry": {"coordinates":[49.08739,34.23024],"type":"Point"}
}