{
  "type": "Feature",
  "properties": {
    "gn:admin1_code":"9",
    "gn:asciiname":"Yaramjabagh",
    "gn:country_code":"IR",
    "gn:dem":2107,
    "gn:feature_class":"P",
    "gn:feature_code":"PPL",
    "gn:name":"Y\u0101ramjab\u0101gh",
    "gn:population":0,
    "gn:timezone":"Asia/Tehran",
    "iso:country":"IR",
    "name:fas_x_preferred":[
        "\u064a\u0627\u0631\u0645\u062c\u0647 \u0628\u0627\u063a"
    ],
    "name:fas_x_variant":[
        "Y\u0101romjeh B\u0101gh",
        "\u06cc\u0627\u0631\u0645\u062c\u0628\u0627\u063a"
    ],
    "name:und_x_variant":[
        "Y\u0101ramjah B\u0101gh",
        "Y\u0101remjeh B\u0101gh",
        "Y\u0101rmjeh Bol\u0101gh",
        "Yaramj\u0101bak",
        "Y\u0101ramjab\u0101gh"
    ],
    "wof:name":"Yaramjabagh",
    "wof:placetype":"locality"
},
  "geometry": {"coordinates":[48.67626,35.51697],"type":"Point"}
}