{
  "type": "Feature",
  "properties": {
    "gn:admin1_code":"35.0",
    "gn:asciiname":"Sorkh Valik",
    "gn:country_code":"IR",
    "gn:dem":869,
    "gn:feature_class":"P",
    "gn:feature_code":"PPL",
    "gn:name":"Sorkh Val\u012bk",
    "gn:population":0,
    "gn:timezone":"Asia/Tehran",
    "iso:country":"IR",
    "name:fas_x_preferred":[
        "\u0633\u064f\u0631\u062e \u0648\u064e\u0644\u064a\u0643"
    ],
    "name:fas_x_variant":[
        "\u0633\u064f\u0631\u062e \u0648\u064e\u0644\u062a\u064e\u0643",
        "Sorkh Val\u012bk",
        "Sorkh Val\u012b",
        "\u0633\u0631\u062e \u0648\u0644\u06cc"
    ],
    "name:und_x_variant":[
        "Sorkh Valtak",
        "Sorkh Val\u012b",
        "\u0633\u0631\u062e \u0648\u0644\u06cc"
    ],
    "wof:name":"Sorkh Valik",
    "wof:placetype":"locality"
},
  "geometry": {"coordinates":[53.29853000000001,36.31238],"type":"Point"}
}