{
  "type": "Feature",
  "properties": {
    "gn:admin1_code":"37",
    "gn:asciiname":"Deh `Abdollah",
    "gn:country_code":"IR",
    "gn:dem":96,
    "gn:feature_class":"P",
    "gn:feature_code":"PPL",
    "gn:name":"Deh \u2018Abdoll\u0101h",
    "gn:population":0,
    "gn:timezone":"Asia/Tehran",
    "iso:country":"IR",
    "name:fas_x_preferred":[
        "Deh \u2018Abdoll\u0101h"
    ],
    "name:fas_x_variant":[
        "\u062f\u0647 \u0639\u0628\u062f\u0627\u0644\u0644\u0647"
    ],
    "name:msa_x_preferred":[
        "Deh Abdollah"
    ],
    "wof:name":"Deh `Abdollah",
    "wof:placetype":"locality"
},
  "geometry": {"coordinates":[55.33065,37.24806],"type":"Point"}
}