{
  "type": "Feature",
  "properties": {
    "gn:admin1_code":"10.0",
    "gn:asciiname":"Kan Hajji",
    "gn:country_code":"IR",
    "gn:dem":1271,
    "gn:feature_class":"P",
    "gn:feature_code":"PPL",
    "gn:name":"K\u0101n \u1e28\u0101jj\u012b",
    "gn:population":0,
    "gn:timezone":"Asia/Tehran",
    "iso:country":"IR",
    "name:fas_x_preferred":[
        "K\u0101n \u1e28\u0101jj\u012b"
    ],
    "name:fas_x_variant":[
        "\u0643\u0627\u0646 \u062d\u0627\u062c\u0651\u06cc"
    ],
    "wof:name":"Kan Hajji",
    "wof:placetype":"locality"
},
  "geometry": {"coordinates":[46.18333,33.78333],"type":"Point"}
}