{
  "type": "Feature",
  "properties": {
    "gn:admin1_code":"15",
    "gn:asciiname":"Sagur Fari`",
    "gn:country_code":"IR",
    "gn:dem":22,
    "gn:feature_class":"P",
    "gn:feature_code":"PPL",
    "gn:name":"Sag\u016br Far\u012b\u2018",
    "gn:population":0,
    "gn:timezone":"Asia/Tehran",
    "iso:country":"IR",
    "name:fas_x_preferred":[
        "\u0633\u06af\u0648\u0631"
    ],
    "name:fas_x_variant":[
        "Sagowr-e \u1e28all\u0101f",
        "Sag\u016br",
        "\u0633\u06af\u0648\u0631 \u0641\u0631\u06cc\u0639",
        "\u0635\u06af\u0648\u0631 \u0641\u0631\u06cc\u0639 \u0645\u062d\u0645\u062f"
    ],
    "name:und_x_variant":[
        "\u1e28\u0101jj\u012b Khe\u1e95eyer",
        "S\u016br \u1e28all\u0101f",
        "Sag\u016b",
        "Sag\u016br Far\u012b\u2018",
        "\u015eag\u016br Far\u012b\u2018 Mo\u1e29ammad"
    ],
    "wof:name":"Sagur Fari`",
    "wof:placetype":"locality"
},
  "geometry": {"coordinates":[48.38057,31.48062],"type":"Point"}
}