{
  "type": "Feature",
  "properties": {
    "gn:admin1_code":"5",
    "gn:asciiname":"Kachlun",
    "gn:country_code":"IR",
    "gn:dem":1124,
    "gn:feature_class":"P",
    "gn:feature_code":"PPL",
    "gn:name":"Kachl\u016bn",
    "gn:population":0,
    "gn:timezone":"Asia/Tehran",
    "iso:country":"IR",
    "name:fas_x_preferred":[
        "Kachl\u0101n"
    ],
    "name:fas_x_variant":[
        "\u0643\u0686\u0644\u0627\u0646",
        "\u0643\u0686\u0644\u0648\u0646"
    ],
    "name:und_x_variant":[
        "\u0643\u0686\u0644\u0627\u0646",
        "Kachl\u016bn"
    ],
    "wof:name":"Kachlun",
    "wof:placetype":"locality"
},
  "geometry": {"coordinates":[50.17659,31.03667],"type":"Point"}
}