{
  "type": "Feature",
  "properties": {
    "gn:admin1_code":"1",
    "gn:asciiname":"Nergi",
    "gn:country_code":"IR",
    "gn:dem":1474,
    "gn:feature_class":"P",
    "gn:feature_code":"PPL",
    "gn:name":"Nerg\u012b",
    "gn:population":0,
    "gn:timezone":"Asia/Tehran",
    "iso:country":"IR",
    "name:aze_x_preferred":[
        "Nergi"
    ],
    "name:ceb_x_preferred":[
        "Nerg\u012b"
    ],
    "name:fas_x_preferred":[
        "\u0646\u0650\u0631\u06af\u06cc"
    ],
    "name:fas_x_variant":[
        "Nerg\u012b",
        "\u0646\u0631\u06af\u06cc"
    ],
    "name:msa_x_preferred":[
        "Nergi"
    ],
    "name:swe_x_preferred":[
        "Nerg\u012b"
    ],
    "name:und_x_variant":[
        "\u0646\u0631\u06af\u06cc"
    ],
    "wof:name":"Nergi",
    "wof:placetype":"locality"
},
  "geometry": {"coordinates":[44.9214,37.3363],"type":"Point"}
}