{
  "type": "Feature",
  "properties": {
    "gn:admin1_code":"11",
    "gn:asciiname":"Qanbarabad",
    "gn:country_code":"IR",
    "gn:dem":479,
    "gn:feature_class":"P",
    "gn:feature_code":"PPL",
    "gn:name":"Qanbar\u0101b\u0101d",
    "gn:population":0,
    "gn:timezone":"Asia/Tehran",
    "iso:country":"IR",
    "name:fas_x_preferred":[
        "\u0642\u0646\u0628\u0631 \u0622\u0628\u0627\u062f"
    ],
    "name:fas_x_variant":[
        "Qanbar\u0101b\u0101d",
        "\u0642\u0646\u0628\u0631\u0622\u0628\u0627\u062f"
    ],
    "wof:name":"Qanbarabad",
    "wof:placetype":"locality"
},
  "geometry": {"coordinates":[57.1994,27.7775],"type":"Point"}
}