{
  "type": "Feature",
  "properties": {
    "gn:admin1_code":"1",
    "gn:asciiname":"Eslamabad",
    "gn:country_code":"IR",
    "gn:dem":1281,
    "gn:feature_class":"P",
    "gn:feature_code":"PPL",
    "gn:name":"Esl\u0101m\u0101b\u0101d",
    "gn:population":0,
    "gn:timezone":"Asia/Tehran",
    "iso:country":"IR",
    "name:ara_x_preferred":[
        "\u0625\u0633\u0644\u0627\u0645 \u0622\u0628\u0627\u062f"
    ],
    "name:fas_x_preferred":[
        "\u0634\u0627\u0647 \u0622\u0628\u0627\u062f"
    ],
    "name:fas_x_variant":[
        "\u0627\u0633\u0644\u0627\u0645 \u0622\u0628\u0627\u062f",
        "\u0627\u0650\u0633\u0644\u0627\u0645 \u0622\u0628\u0627\u062f",
        "Esl\u0101m\u0101b\u0101d",
        "\u0627\u0633\u0644\u0627\u0645\u200c\u0622\u0628\u0627\u062f"
    ],
    "name:und_x_variant":[
        "Sh\u0101h\u0101b\u0101d",
        "Shaikh\u0101b\u0101d"
    ],
    "wof:name":"Eslamabad",
    "wof:placetype":"locality"
},
  "geometry": {"coordinates":[45.9364,37.0897],"type":"Point"}
}