{
  "type": "Feature",
  "properties": {
    "gn:admin1_code":"42",
    "gn:asciiname":"Kalat-e Gush Sang",
    "gn:country_code":"IR",
    "gn:dem":1899,
    "gn:feature_class":"P",
    "gn:feature_code":"PPLF",
    "gn:name":"Kal\u0101t-e G\u016bsh Sang",
    "gn:population":0,
    "gn:timezone":"Asia/Tehran",
    "iso:country":"IR",
    "name:fas_x_preferred":[
        "\u06af\u0648\u0634 \u0633\u0646\u06af"
    ],
    "name:fas_x_variant":[
        "G\u016bsheh Sang",
        "G\u016bsh Sang",
        "\u06a9\u0644\u0627\u062a\u0647 \u06af\u0648\u0634 \u0633\u0646\u06af"
    ],
    "name:und_x_variant":[
        "Kal\u0101t-e G\u016bsh Sang"
    ],
    "wof:name":"Kalat-e Gush Sang",
    "wof:placetype":"locality"
},
  "geometry": {"coordinates":[59.94803,35.34285999999999],"type":"Point"}
}