{
  "type": "Feature",
  "properties": {
    "gn:admin1_code":"4",
    "gn:asciiname":"Taleb Khan",
    "gn:country_code":"IR",
    "gn:dem":754,
    "gn:feature_class":"P",
    "gn:feature_code":"PPL",
    "gn:name":"\u0162aleb Kh\u0101n",
    "gn:population":0,
    "gn:timezone":"Asia/Tehran",
    "iso:country":"IR",
    "name:fas_x_preferred":[
        "\u06af\u0650\u0648\u0627\u0646\u0650 \u0637\u0627\u0644\u0650\u0628 \u062e\u0627\u0646"
    ],
    "name:fas_x_variant":[
        "\u062a\u0627\u0644\u0627\u0628 \u062e\u0627\u0646",
        "Gev\u0101n-e \u0162\u0101leb Kh\u0101n",
        "\u0637\u0644\u0628 \u062e\u0627\u0646",
        "\u0637\u0627\u0644\u0628\u062e\u0627\u0646"
    ],
    "name:msa_x_preferred":[
        "Taleb Khan"
    ],
    "name:und_x_variant":[
        "T\u0101l\u0101b Kh\u0101n",
        "Gv\u0101n-i-Talab Kh\u0101ni",
        "\u0162aleb Kh\u0101n"
    ],
    "wof:name":"Taleb Khan",
    "wof:placetype":"locality"
},
  "geometry": {"coordinates":[59.22113,27.87284],"type":"Point"}
}