{
  "type": "Feature",
  "properties": {
    "gn:admin1_code":"41.0",
    "gn:asciiname":"Dahaneh-ye Nasfandeh-ye Bala",
    "gn:country_code":"IR",
    "gn:dem":1250,
    "gn:feature_class":"P",
    "gn:feature_code":"PPL",
    "gn:name":"Dahaneh-ye N\u0101sfandeh-ye B\u0101l\u0101",
    "gn:population":0,
    "gn:timezone":"Asia/Tehran",
    "iso:country":"IR",
    "name:fas_x_preferred":[
        "Dahaneh-ye N\u0101sfandeh-ye B\u0101l\u0101"
    ],
    "wof:name":"Dahaneh-ye Nasfandeh-ye Bala",
    "wof:placetype":"locality"
},
  "geometry": {"coordinates":[60.16639,31.62111],"type":"Point"}
}