{
  "type": "Feature",
  "properties": {
    "gn:admin1_code":"13",
    "gn:asciiname":"Deh-e Bala",
    "gn:country_code":"IR",
    "gn:dem":1484,
    "gn:feature_class":"P",
    "gn:feature_code":"PPL",
    "gn:name":"Deh-e B\u0101l\u0101",
    "gn:population":0,
    "gn:timezone":"Asia/Tehran",
    "iso:country":"IR",
    "name:fas_x_preferred":[
        "Deh B\u0101l\u0101"
    ],
    "name:fas_x_variant":[
        "\u062f\u0647 \u0628\u0627\u0644\u0627"
    ],
    "name:und_x_variant":[
        "Deh-e B\u0101l\u0101"
    ],
    "wof:name":"Deh-e Bala",
    "wof:placetype":"locality"
},
  "geometry": {"coordinates":[48.07918,34.55123],"type":"Point"}
}