{
  "type": "Feature",
  "properties": {
    "gn:admin1_code":"11",
    "gn:asciiname":"Sang-e Siah",
    "gn:country_code":"IR",
    "gn:dem":34,
    "gn:feature_class":"P",
    "gn:feature_code":"PPL",
    "gn:name":"Sang-e S\u012b\u0101h",
    "gn:population":0,
    "gn:timezone":"Asia/Tehran",
    "iso:country":"IR",
    "name:fas_x_preferred":[
        "\u06af\u0648\u062f\u0645\u06cc\u0631\u06cc"
    ],
    "name:fas_x_variant":[
        "Gowdm\u012br\u012b",
        "\u0633\u0646\u06af \u0633\u064a\u0627\u0647"
    ],
    "name:und_x_variant":[
        "Sang-e S\u012b\u0101h"
    ],
    "wof:name":"Sang-e Siah",
    "wof:placetype":"locality"
},
  "geometry": {"coordinates":[55.3123,26.8993],"type":"Point"}
}