{
  "type": "Feature",
  "properties": {
    "gn:admin1_code":"37",
    "gn:asciiname":"Bolbol Tappeh",
    "gn:country_code":"IR",
    "gn:dem":-8,
    "gn:feature_class":"P",
    "gn:feature_code":"PPL",
    "gn:name":"Bolbol Tappeh",
    "gn:population":0,
    "gn:timezone":"Asia/Tehran",
    "iso:country":"IR",
    "name:fas_x_preferred":[
        "\u0628\u064f\u0644\u0628\u064f\u0644 \u062a\u064e\u067e\u0650\u0651\u0647"
    ],
    "wof:name":"Bolbol Tappeh",
    "wof:placetype":"locality"
},
  "geometry": {"coordinates":[54.56694,36.97833],"type":"Point"}
}