{
  "type": "Feature",
  "properties": {
    "gn:admin1_code":"29",
    "gn:asciiname":"Kohan",
    "gn:country_code":"IR",
    "gn:dem":705,
    "gn:feature_class":"P",
    "gn:feature_code":"PPL",
    "gn:name":"Kohan",
    "gn:population":0,
    "gn:timezone":"Asia/Tehran",
    "iso:country":"IR",
    "name:ceb_x_preferred":[
        "Kohan"
    ],
    "name:deu_x_preferred":[
        "Kohan"
    ],
    "name:fas_x_preferred":[
        "\u06a9\u0647\u0646"
    ],
    "name:fas_x_variant":[
        "\u062c\u0646\u06af\u0644 \u0622\u0628\u0627\u062f"
    ],
    "name:fra_x_preferred":[
        "Kohan"
    ],
    "name:und_x_variant":[
        "Jangal",
        "K\u016bhan",
        "Kahn",
        "Jangal\u0101b\u0101d"
    ],
    "wof:name":"Kohan",
    "wof:placetype":"locality"
},
  "geometry": {"coordinates":[57.49236,28.25976],"type":"Point"}
}