{
  "type": "Feature",
  "properties": {
    "gn:admin1_code":"41",
    "gn:asciiname":"Khorram",
    "gn:country_code":"IR",
    "gn:dem":1307,
    "gn:feature_class":"P",
    "gn:feature_code":"PPLF",
    "gn:name":"Khorram",
    "gn:population":0,
    "gn:timezone":"Asia/Tehran",
    "iso:country":"IR",
    "name:fas_x_preferred":[
        "\u062e\u06cc\u0631\u0645"
    ],
    "name:fas_x_variant":[
        "\u062e\u0631\u0645"
    ],
    "name:und_x_variant":[
        "Khairam",
        "Kheyram",
        "Khorram"
    ],
    "wof:name":"Khorram",
    "wof:placetype":"locality"
},
  "geometry": {"coordinates":[58.57294,32.98889],"type":"Point"}
}