{
  "type": "Feature",
  "properties": {
    "gn:admin1_code":"29",
    "gn:asciiname":"Dahaneh Zarnegar",
    "gn:country_code":"IR",
    "gn:dem":1804,
    "gn:feature_class":"P",
    "gn:feature_code":"PPL",
    "gn:name":"Dahaneh Zarneg\u0101r",
    "gn:population":0,
    "gn:timezone":"Asia/Tehran",
    "iso:country":"IR",
    "name:fas_x_preferred":[
        "\u062f\u0647\u0646\u0647 \u0632\u0631\u0646\u06af\u0627\u0631"
    ],
    "name:fas_x_variant":[
        "Dahaneh-ye Zang\u0101r",
        "Dahaneh Zarneg\u0101r"
    ],
    "name:und_x_variant":[
        "Zang\u0101r",
        "Dahaneh Zang\u0101r"
    ],
    "wof:name":"Dahaneh Zarnegar",
    "wof:placetype":"locality"
},
  "geometry": {"coordinates":[57.6196,28.9807],"type":"Point"}
}