{
  "type": "Feature",
  "properties": {
    "gn:admin1_code":"22",
    "gn:asciiname":"Geshni",
    "gn:country_code":"IR",
    "gn:dem":1234,
    "gn:feature_class":"P",
    "gn:feature_code":"PPL",
    "gn:name":"Geshn\u012b",
    "gn:population":0,
    "gn:timezone":"Asia/Tehran",
    "iso:country":"IR",
    "name:fas_x_preferred":[
        "\u06af\u0650\u0634\u0646\u06cc"
    ],
    "name:fas_x_variant":[
        "Geshn\u012b"
    ],
    "wof:name":"Geshni",
    "wof:placetype":"locality"
},
  "geometry": {"coordinates":[51.4025,29.36639000000001],"type":"Point"}
}