{
  "type": "Feature",
  "properties": {
    "gn:admin1_code":"23",
    "gn:asciiname":"Shabankosh",
    "gn:country_code":"IR",
    "gn:dem":1441,
    "gn:feature_class":"P",
    "gn:feature_code":"PPL",
    "gn:name":"Shab\u0101nkosh",
    "gn:population":0,
    "gn:timezone":"Asia/Tehran",
    "iso:country":"IR",
    "name:fas_x_preferred":[
        "\u0634\u0628\u0627\u0646 \u0643\u0634 \u0639\u0644\u064a\u0627"
    ],
    "name:fas_x_variant":[
        "Shab\u0101n Kosh-e \u2018Oly\u0101",
        "\u0634\u0628\u0627\u0646\u0643\u0634"
    ],
    "name:und_x_variant":[
        "Shab\u0101nkosh"
    ],
    "wof:name":"Shabankosh",
    "wof:placetype":"locality"
},
  "geometry": {"coordinates":[48.8115,33.2406],"type":"Point"}
}