{
  "type": "Feature",
  "properties": {
    "gn:admin1_code":"29",
    "gn:asciiname":"Gorgu'iyeh",
    "gn:country_code":"IR",
    "gn:dem":2238,
    "gn:feature_class":"P",
    "gn:feature_code":"PPL",
    "gn:name":"Gorg\u016b\u2019\u012byeh",
    "gn:population":0,
    "gn:timezone":"Asia/Tehran",
    "iso:country":"IR",
    "name:ara_x_preferred":[
        "\u063a\u0631\u063a\u0648\u0626\u064a\u0629"
    ],
    "name:fas_x_preferred":[
        "\u06af\u0631\u06af\u0648\u0626\u06cc\u0647"
    ],
    "name:fas_x_variant":[
        "Gorg\u016b\u2019\u012byeh"
    ],
    "name:und_x_variant":[
        "Karg\u016b\u2019\u012byeh",
        "Gorgnow\u2019\u012byeh"
    ],
    "wof:name":"Gorgu'iyeh",
    "wof:placetype":"locality"
},
  "geometry": {"coordinates":[56.533,29.2251],"type":"Point"}
}