{
  "type": "Feature",
  "properties": {
    "gn:admin1_code":"35.0",
    "gn:asciiname":"Dezir Kola",
    "gn:country_code":"IR",
    "gn:dem":95,
    "gn:feature_class":"P",
    "gn:feature_code":"PPL",
    "gn:name":"Dez\u012br Kol\u0101",
    "gn:population":0,
    "gn:timezone":"Asia/Tehran",
    "iso:country":"IR",
    "name:ceb_x_preferred":[
        "D\u012bzer Kol\u0101"
    ],
    "name:fas_x_preferred":[
        "\u062f\u064a\u0632\u0631 \u0643\u0644\u0627"
    ],
    "name:fas_x_variant":[
        "D\u012bzer Kol\u0101",
        "\u062f\u0632\u06cc\u0631 \u06a9\u0644\u0627",
        "\u062f\u06cc\u0632\u0631\u06a9\u0644\u0627"
    ],
    "name:swe_x_preferred":[
        "D\u012bzer Kol\u0101"
    ],
    "name:und_x_variant":[
        "Dez\u012br Kol\u0101"
    ],
    "wof:name":"Dezir Kola",
    "wof:placetype":"locality"
},
  "geometry": {"coordinates":[51.79357,36.55696],"type":"Point"}
}