{
  "type": "Feature",
  "properties": {
    "gn:admin1_code":"10",
    "gn:asciiname":"Baraftab-e Chalab Zard",
    "gn:country_code":"IR",
    "gn:dem":1002,
    "gn:feature_class":"P",
    "gn:feature_code":"PPL",
    "gn:name":"Bar\u0101ft\u0101b-e Ch\u0101l\u0101b Zard",
    "gn:population":0,
    "gn:timezone":"Asia/Tehran",
    "iso:country":"IR",
    "name:ara_x_preferred":[
        "\u0628\u0631\u0622\u0641\u062a\u0627\u0628 \u062a\u0634\u0627\u0644\u0627\u0628 \u0632\u0631\u062f"
    ],
    "name:fas_x_preferred":[
        "\u0628\u0631 \u0622\u0641\u062a\u0627\u0628 \u0686\u0627\u0644\u0627\u0628 \u0632\u0631\u062f"
    ],
    "name:fas_x_variant":[
        "Bar\u0101ft\u0101b-e Ch\u0101l\u0101b Zard",
        "\u0628\u0631\u0622\u0641\u062a\u0627\u0628 \u0686\u0627\u0644\u0627\u0628 \u0632\u0631\u062f"
    ],
    "name:msa_x_preferred":[
        "Baraftab-e Chalab Zard"
    ],
    "wof:name":"Baraftab-e Chalab Zard",
    "wof:placetype":"locality"
},
  "geometry": {"coordinates":[46.8631,33.6683],"type":"Point"}
}