{
  "type": "Feature",
  "properties": {
    "gn:admin1_code":"39.0",
    "gn:asciiname":"Anjileh",
    "gn:country_code":"IR",
    "gn:dem":2006,
    "gn:feature_class":"P",
    "gn:feature_code":"PPL",
    "gn:name":"Anj\u012bleh",
    "gn:population":0,
    "gn:timezone":"Asia/Tehran",
    "iso:country":"IR",
    "name:fas_x_preferred":[
        "Anj\u012bleh"
    ],
    "name:fas_x_variant":[
        "\u0627\u0646\u062c\u064a\u0644\u0647"
    ],
    "name:und_x_variant":[
        "\u0627\u0646\u062c\u064a\u0644\u0647"
    ],
    "wof:name":"Anjileh",
    "wof:placetype":"locality"
},
  "geometry": {"coordinates":[50.15667,34.73185],"type":"Point"}
}