{
  "type": "Feature",
  "properties": {
    "gn:admin1_code":"3",
    "gn:asciiname":"Gerdopineh",
    "gn:country_code":"IR",
    "gn:dem":2107,
    "gn:feature_class":"P",
    "gn:feature_code":"PPL",
    "gn:name":"Gerdop\u012bneh",
    "gn:population":0,
    "gn:timezone":"Asia/Tehran",
    "iso:country":"IR",
    "name:ara_x_preferred":[
        "\u063a\u0631\u062f\u0628\u064a\u0646\u0629"
    ],
    "name:ceb_x_preferred":[
        "Gerdop\u012bneh"
    ],
    "name:fas_x_preferred":[
        "\u06af\u0650\u0631\u062f\u067e\u064a\u0646\u0650\u0647"
    ],
    "name:fas_x_variant":[
        "Gerdop\u012bneh",
        "\u06af\u0631\u062f\u067e\u064a\u0646\u0647",
        "\u06af\u0631\u062f\u067e\u06cc\u0646\u0647"
    ],
    "name:msa_x_preferred":[
        "Gerdopineh"
    ],
    "name:swe_x_preferred":[
        "Gerdop\u012bneh"
    ],
    "name:und_x_variant":[
        "Gerdp\u012bneh"
    ],
    "wof:name":"Gerdopineh",
    "wof:placetype":"locality"
},
  "geometry": {"coordinates":[50.40328,32.05396],"type":"Point"}
}