{
  "type": "Feature",
  "properties": {
    "gn:admin1_code":"10",
    "gn:asciiname":"Bustaneh",
    "gn:country_code":"IR",
    "gn:dem":769,
    "gn:feature_class":"P",
    "gn:feature_code":"PPL",
    "gn:name":"B\u016bst\u0101neh",
    "gn:population":0,
    "gn:timezone":"Asia/Tehran",
    "iso:country":"IR",
    "name:fas_x_preferred":[
        "B\u016bst\u0101neh"
    ],
    "name:fas_x_variant":[
        "\u0628\u0648\u0633\u062a\u0627\u0646\u0650\u0647"
    ],
    "wof:name":"Bustaneh",
    "wof:placetype":"locality"
},
  "geometry": {"coordinates":[46.95694,32.97972],"type":"Point"}
}