{
  "type": "Feature",
  "properties": {
    "gn:admin1_code":"15",
    "gn:asciiname":"Eshgaft-e Bar Aftab",
    "gn:country_code":"IR",
    "gn:dem":375,
    "gn:feature_class":"P",
    "gn:feature_code":"PPL",
    "gn:name":"Eshgaft-e Bar \u0100ft\u0101b",
    "gn:population":0,
    "gn:timezone":"Asia/Tehran",
    "iso:country":"IR",
    "name:fas_x_preferred":[
        "Eshkaft-e Bar\u0101ft\u0101b"
    ],
    "name:fas_x_variant":[
        "\u0627\u0634\u06af\u0641\u062a \u0628\u0631 \u0622\u0641\u062a\u0627\u0628"
    ],
    "name:und_x_variant":[
        "Eshgaft-e Bar \u0100ft\u0101b"
    ],
    "wof:name":"Eshgaft-e Bar Aftab",
    "wof:placetype":"locality"
},
  "geometry": {"coordinates":[49.1035,32.40791],"type":"Point"}
}