{
  "type": "Feature",
  "properties": {
    "gn:admin1_code":"38",
    "gn:asciiname":"Kalayeh",
    "gn:country_code":"IR",
    "gn:dem":1975,
    "gn:feature_class":"P",
    "gn:feature_code":"PPL",
    "gn:name":"Kal\u0101yeh",
    "gn:population":0,
    "gn:timezone":"Asia/Tehran",
    "iso:country":"IR",
    "name:fas_x_preferred":[
        "Kal\u0101yeh"
    ],
    "name:fas_x_variant":[
        "\u0643\u0644\u0627\u064a\u0647"
    ],
    "name:und_x_variant":[
        "\u0643\u0644\u0627\u064a\u0647"
    ],
    "wof:name":"Kalayeh",
    "wof:placetype":"locality"
},
  "geometry": {"coordinates":[50.64419,36.45245],"type":"Point"}
}