{
  "type": "Feature",
  "properties": {
    "gn:admin1_code":"4",
    "gn:asciiname":"Kumbar-e A`zam",
    "gn:country_code":"IR",
    "gn:dem":393,
    "gn:feature_class":"P",
    "gn:feature_code":"PPLF",
    "gn:name":"K\u016bmb\u0101r-e A\u2018z\u0327am",
    "gn:population":0,
    "gn:timezone":"Asia/Tehran",
    "iso:country":"IR",
    "name:fas_x_preferred":[
        "\u06a9\u0648\u0645\u0628\u0627\u0631 \u0627\u0639\u0638\u0645"
    ],
    "name:fas_x_variant":[
        "K\u016bmb\u0101r-e A\u2018z\u0327am"
    ],
    "wof:name":"Kumbar-e A`zam",
    "wof:placetype":"locality"
},
  "geometry": {"coordinates":[59.0566,27.0874],"type":"Point"}
}