{
  "type": "Feature",
  "properties": {
    "gn:admin1_code":"4.0",
    "gn:asciiname":"Hajjiabad-e Ziaratgah",
    "gn:cc2":"IR",
    "gn:country_code":"IR",
    "gn:dem":1945,
    "gn:feature_class":"P",
    "gn:feature_code":"PPL",
    "gn:name":"\u1e28\u0101jj\u012b\u0101b\u0101d-e Z\u012b\u0101ratg\u0101h",
    "gn:population":0,
    "gn:timezone":"Asia/Tehran",
    "iso:country":"IR",
    "name:fas_x_preferred":[
        "\u1e28\u0101jj\u012b\u0101b\u0101d-e Z\u012b\u0101ratg\u0101h"
    ],
    "name:und_x_variant":[
        "\u1e28\u0101jj\u012b\u0101b\u0101d Z\u012b\u0101ratg\u0101h"
    ],
    "wof:name":"Hajjiabad-e Ziaratgah",
    "wof:placetype":"locality"
},
  "geometry": {"coordinates":[60.55,29.38333],"type":"Point"}
}