{
  "type": "Feature",
  "properties": {
    "gn:admin1_code":"42",
    "gn:asciiname":"Bidestan",
    "gn:country_code":"IR",
    "gn:dem":1853,
    "gn:feature_class":"P",
    "gn:feature_code":"PPL",
    "gn:name":"B\u012bdest\u0101n",
    "gn:population":0,
    "gn:timezone":"Asia/Tehran",
    "iso:country":"IR",
    "name:fas_x_preferred":[
        "\u0628\u06cc\u062f\u0633\u062a\u0627\u0646"
    ],
    "name:fas_x_variant":[
        "B\u012bdest\u0101n"
    ],
    "wof:name":"Bidestan",
    "wof:placetype":"locality"
},
  "geometry": {"coordinates":[59.15789,35.5187],"type":"Point"}
}