{
  "type": "Feature",
  "properties": {
    "gn:admin1_code":"8",
    "gn:asciiname":"Chambul Dasht",
    "gn:country_code":"IR",
    "gn:dem":1815,
    "gn:feature_class":"P",
    "gn:feature_code":"PPL",
    "gn:name":"Chamb\u016bl Dasht",
    "gn:population":0,
    "gn:timezone":"Asia/Tehran",
    "iso:country":"IR",
    "name:fas_x_preferred":[
        "Chamb\u016bl Dasht"
    ],
    "name:fas_x_variant":[
        "\u0686\u0645\u0628\u0648\u0644 \u062f\u0634\u062a"
    ],
    "name:und_x_variant":[
        "Chanbal Dasht"
    ],
    "wof:name":"Chambul Dasht",
    "wof:placetype":"locality"
},
  "geometry": {"coordinates":[49.99984,36.92978],"type":"Point"}
}