{
  "type": "Feature",
  "properties": {
    "gn:admin1_code":"4.0",
    "gn:asciiname":"Kalat-e Luchan",
    "gn:country_code":"IR",
    "gn:dem":1643,
    "gn:feature_class":"P",
    "gn:feature_code":"PPL",
    "gn:name":"Kal\u0101t-e L\u016bch\u0101n",
    "gn:population":0,
    "gn:timezone":"Asia/Tehran",
    "iso:country":"IR",
    "name:fas_x_preferred":[
        "\u06a9\u0644\u0627\u062a \u0644\u0648\u0686\u0627\u0646"
    ],
    "name:fas_x_variant":[
        "Kal\u0101t-e L\u016bch\u0101n"
    ],
    "wof:name":"Kalat-e Luchan",
    "wof:placetype":"locality"
},
  "geometry": {"coordinates":[60.7363,29.3153],"type":"Point"}
}