{
  "type": "Feature",
  "properties": {
    "gn:admin1_code":"29",
    "gn:asciiname":"Seh Gidi",
    "gn:country_code":"IR",
    "gn:dem":1610,
    "gn:feature_class":"P",
    "gn:feature_code":"PPL",
    "gn:name":"Seh G\u012bd\u012b",
    "gn:population":0,
    "gn:timezone":"Asia/Tehran",
    "iso:country":"IR",
    "name:fas_x_preferred":[
        "\u0633\u0647 \u06af\u06cc\u062f\u06cc"
    ],
    "name:fas_x_variant":[
        "Seh G\u012bd\u012b"
    ],
    "wof:name":"Seh Gidi",
    "wof:placetype":"locality"
},
  "geometry": {"coordinates":[57.6706,28.9495],"type":"Point"}
}