{
  "type": "Feature",
  "properties": {
    "gn:admin1_code":"32",
    "gn:asciiname":"Aq Qabaq",
    "gn:country_code":"IR",
    "gn:dem":126,
    "gn:feature_class":"P",
    "gn:feature_code":"PPL",
    "gn:name":"\u0100q Qab\u0101q",
    "gn:population":0,
    "gn:timezone":"Asia/Tehran",
    "iso:country":"IR",
    "name:azb_x_preferred":[
        "\u06cc\u0648\u062e\u0627\u0631\u06cc \u0622\u0642 \u0642\u0627\u0628\u0627\u0642"
    ],
    "name:fas_x_preferred":[
        "\u0622\u0642 \u0642\u064e\u0628\u0627\u0642\u0650 \u0639\u064f\u0644\u064a\u0627"
    ],
    "name:fas_x_variant":[
        "\u0622\u0642 \u0642\u0628\u0627\u0642",
        "\u0100q Qab\u0101q-e \u2018Oly\u0101",
        "\u0100q Qab\u0101q",
        "\u0622\u0642 \u0642\u0628\u0627\u0642 \u0639\u0644\u06cc\u0627"
    ],
    "name:msa_x_preferred":[
        "Aq Qabaq-e Olya"
    ],
    "wof:name":"Aq Qabaq",
    "wof:placetype":"locality"
},
  "geometry": {"coordinates":[47.5315,39.4934],"type":"Point"}
}