{
  "type": "Feature",
  "properties": {
    "gn:admin1_code":"1.0",
    "gn:asciiname":"Sheykh Yusof",
    "gn:country_code":"IR",
    "gn:dem":1616,
    "gn:feature_class":"P",
    "gn:feature_code":"PPL",
    "gn:name":"Sheykh Y\u016bsof",
    "gn:population":0,
    "gn:timezone":"Asia/Tehran",
    "iso:country":"IR",
    "name:ara_x_preferred":[
        "\u0634\u064a\u062e \u064a\u0648\u0633\u0641"
    ],
    "name:azb_x_preferred":[
        "\u0634\u06cc\u062e\u200c\u06cc\u0648\u0633\u0641(\u0633\u0648\u06cc\u0648\u0642\u200c\u0628\u0648\u0644\u0627\u0642)"
    ],
    "name:aze_x_preferred":[
        "\u015eeyx Yusif"
    ],
    "name:ckb_x_preferred":[
        "\u0634\u06ce\u062e \u06cc\u06c6\u0633\u0641"
    ],
    "name:fas_x_preferred":[
        "\u0634\u06cc\u062e \u06cc\u0648\u0633\u0641"
    ],
    "name:fas_x_variant":[
        "Sheykh Y\u016bsof",
        "\u0634\u06cc\u062e\u200c\u06cc\u0648\u0633\u0641"
    ],
    "name:kur_x_preferred":[
        "\u015e\u00eax yosif"
    ],
    "name:msa_x_preferred":[
        "Sheykh Yusof"
    ],
    "wof:name":"Sheykh Yusof",
    "wof:placetype":"locality"
},
  "geometry": {"coordinates":[45.8034,36.5337],"type":"Point"}
}