{
  "type": "Feature",
  "properties": {
    "gn:admin1_code":"1.0",
    "gn:asciiname":"Sheykh Yusof",
    "gn:country_code":"IR",
    "gn:dem":1616,
    "gn:feature_class":"P",
    "gn:feature_code":"PPL",
    "gn:name":"Sheykh Y\u016bsof",
    "gn:population":0,
    "gn:timezone":"Asia/Tehran",
    "iso:country":"IR",
    "name:fas_x_preferred":[
        "\u0634\u06cc\u062e \u06cc\u0648\u0633\u0641"
    ],
    "name:fas_x_variant":[
        "Sheykh Y\u016bsof"
    ],
    "wof:name":"Sheykh Yusof",
    "wof:placetype":"locality"
},
  "geometry": {"coordinates":[45.8034,36.5337],"type":"Point"}
}