{
  "type": "Feature",
  "properties": {
    "gn:admin1_code":"4",
    "gn:asciiname":"Jangal",
    "gn:country_code":"IR",
    "gn:dem":1036,
    "gn:feature_class":"P",
    "gn:feature_code":"PPL",
    "gn:name":"Jangal",
    "gn:population":0,
    "gn:timezone":"Asia/Tehran",
    "iso:country":"IR",
    "name:ara_x_preferred":[
        "\u062c\u0646\u063a\u0644"
    ],
    "name:aze_x_preferred":[
        "C\u0259ng\u0259l"
    ],
    "name:ceb_x_preferred":[
        "Jangal"
    ],
    "name:fas_x_preferred":[
        "\u062c\u0646\u06af\u0644"
    ],
    "name:ita_x_preferred":[
        "Jangal"
    ],
    "name:mlg_x_preferred":[
        "Jangal"
    ],
    "name:swe_x_preferred":[
        "Jangal"
    ],
    "name:tur_x_preferred":[
        "Cengel"
    ],
    "wof:name":"Jangal",
    "wof:placetype":"locality"
},
  "geometry": {"coordinates":[59.94111,26.64139],"type":"Point"}
}