{
  "type": "Feature",
  "properties": {
    "gn:admin1_code":"8",
    "gn:asciiname":"Pey Kesh",
    "gn:country_code":"IR",
    "gn:dem":61,
    "gn:feature_class":"P",
    "gn:feature_code":"PPL",
    "gn:name":"Pey Kesh",
    "gn:population":0,
    "gn:timezone":"Asia/Tehran",
    "iso:country":"IR",
    "name:fas_x_preferred":[
        "\u067e\u06cc \u06a9\u0634"
    ],
    "wof:name":"Pey Kesh",
    "wof:placetype":"locality"
},
  "geometry": {"coordinates":[48.8884,37.9507],"type":"Point"}
}