{
  "type": "Feature",
  "properties": {
    "gn:admin1_code":"4.0",
    "gn:asciiname":"Niam Sunt",
    "gn:cc2":"IR",
    "gn:country_code":"IR",
    "gn:dem":798,
    "gn:feature_class":"P",
    "gn:feature_code":"PPL",
    "gn:name":"N\u012b\u0101m S\u016bnt",
    "gn:population":0,
    "gn:timezone":"Asia/Tehran",
    "iso:country":"IR",
    "name:fas_x_preferred":[
        "N\u012b\u0101m S\u016bnt"
    ],
    "name:und_x_variant":[
        "N\u012b\u0101m Zand",
        "Ney\u0101m Zand"
    ],
    "wof:name":"Niam Sunt",
    "wof:placetype":"locality"
},
  "geometry": {"coordinates":[60.23472,26.40583],"type":"Point"}
}