{
  "type": "Feature",
  "properties": {
    "gn:admin1_code":"8",
    "gn:asciiname":"Ganjarud-e Sofla",
    "gn:country_code":"IR",
    "gn:dem":23,
    "gn:feature_class":"P",
    "gn:feature_code":"PPL",
    "gn:name":"Ganj\u0101r\u016bd-e Sofl\u00e1",
    "gn:population":0,
    "gn:timezone":"Asia/Tehran",
    "iso:country":"IR",
    "name:ceb_x_preferred":[
        "Ganj\u0101r\u016bd"
    ],
    "name:fas_x_preferred":[
        "Ganj\u0101r\u016bd"
    ],
    "name:fas_x_variant":[
        "\u06af\u0646\u062c\u0627\u0631\u0648\u062f",
        "\u06af\u0646\u062c\u0627\u0631\u0648\u062f \u0633\u0641\u0644\u06cc"
    ],
    "name:msa_x_preferred":[
        "Ganjarud"
    ],
    "name:swe_x_preferred":[
        "Ganj\u0101r\u016bd"
    ],
    "name:ukr_x_preferred":[
        "\u0490\u044f\u043d\u0434\u0436\u0430\u0440\u0443\u0434"
    ],
    "name:und_x_variant":[
        "\u06af\u0646\u062c\u0627\u0631\u0648\u062f",
        "Ganj\u0101r\u016bd-e Sofl\u00e1"
    ],
    "wof:name":"Ganjarud-e Sofla",
    "wof:placetype":"locality"
},
  "geometry": {"coordinates":[50.29601,37.05452],"type":"Point"}
}