{
  "type": "Feature",
  "properties": {
    "gn:admin1_code":"33",
    "gn:asciiname":"Shahrak-e Pa'in",
    "gn:country_code":"IR",
    "gn:dem":1586,
    "gn:feature_class":"P",
    "gn:feature_code":"PPL",
    "gn:name":"Shahrak-e P\u0101\u2019\u012bn",
    "gn:population":0,
    "gn:timezone":"Asia/Tehran",
    "iso:country":"IR",
    "name:fas_x_preferred":[
        "\u0634\u064e\u0647\u0631\u064e\u0643\u0650 \u067e\u0627\u0626\u064a\u0646"
    ],
    "name:fas_x_variant":[
        "\u0634\u0647\u0631\u06a9 \u067e\u0627\u0626\u06cc\u0646",
        "\u0634\u064e\u0647\u0631\u064e\u0643",
        "\u0634\u064e\u0647\u0631\u064e\u0643 \u062a\u0627\u0632\u0650\u0647",
        "\u0646\u064f\u0648 \u0634\u064e\u0647\u0631\u064e\u0643",
        "\u0634\u064e\u0628\u0631\u064e\u0643",
        "Shahrak-e P\u0101\u2019\u012bn"
    ],
    "name:und_x_variant":[
        "Nizhnyaya Shayryay",
        "Shabrak",
        "Now Shahrak",
        "Shahrak",
        "Shahrak T\u0101zeh",
        "Shahrak-e P\u0101\u2019\u012bn"
    ],
    "wof:name":"Shahrak-e Pa'in",
    "wof:placetype":"locality"
},
  "geometry": {"coordinates":[46.6978,38.1935],"type":"Point"}
}