{
  "type": "Feature",
  "properties": {
    "gn:admin1_code":"16.0",
    "gn:asciiname":"Dargah-e Sheykhan",
    "gn:country_code":"IR",
    "gn:dem":1650,
    "gn:elevation":"0.0",
    "gn:feature_class":"P",
    "gn:feature_code":"PPL",
    "gn:name":"Darg\u0101h-e Sheykh\u0101n",
    "gn:population":0,
    "gn:timezone":"Asia/Tehran",
    "iso:country":"IR",
    "name:fas_x_preferred":[
        "\u062f\u064e\u0631\u06af\u0627\u0647\u0650 \u0634\u064e\u064a\u062e\u0627\u0646"
    ],
    "name:fas_x_variant":[
        "\u062f\u0631\u06af\u0627\u0647 \u0634\u06cc\u062e\u0627\u0646",
        "Darg\u0101h-e Shaykh\u0101n",
        "Darg\u0101h-e Sheykh\u0101n"
    ],
    "wof:name":"Dargah-e Sheykhan",
    "wof:placetype":"locality"
},
  "geometry": {"coordinates":[45.92100000000001,35.9228],"type":"Point"}
}