{
  "type": "Feature",
  "properties": {
    "gn:admin1_code":"4",
    "gn:asciiname":"Sayyadan",
    "gn:country_code":"IR",
    "gn:dem":536,
    "gn:feature_class":"P",
    "gn:feature_code":"PPL",
    "gn:name":"\u015eayy\u0101d\u0101n",
    "gn:population":0,
    "gn:timezone":"Asia/Tehran",
    "iso:country":"IR",
    "name:fas_x_preferred":[
        "\u0635\u06cc\u0651\u0627\u062f\u0627\u0646"
    ],
    "name:fas_x_variant":[
        "\u015eayy\u0101d\u0101n"
    ],
    "wof:name":"Sayyadan",
    "wof:placetype":"locality"
},
  "geometry": {"coordinates":[62.7395,27.9838],"type":"Point"}
}