{
  "type": "Feature",
  "properties": {
    "gn:admin1_code":"7",
    "gn:asciiname":"Nasirabad-e Avval",
    "gn:country_code":"IR",
    "gn:dem":1566,
    "gn:feature_class":"P",
    "gn:feature_code":"PPL",
    "gn:name":"Na\u015f\u012br\u0101b\u0101d-e Avval",
    "gn:population":0,
    "gn:timezone":"Asia/Tehran",
    "iso:country":"IR",
    "name:fas_x_preferred":[
        "\u0646\u0635\u06cc\u0631 \u0622\u0628\u0627\u062f \u0627\u0648\u0644"
    ],
    "name:fas_x_variant":[
        "Na\u015f\u012br\u0101b\u0101d",
        "Na\u015f\u012br\u0101b\u0101d-e Avval",
        "\u0646\u0635\u06cc\u0631 \u0622\u0628\u0627\u062f",
        "\u0631\u062d\u06cc\u0645 \u0622\u0628\u0627\u062f",
        "\u0646\u0635\u06cc\u0631\u0622\u0628\u0627\u062f"
    ],
    "name:msa_x_preferred":[
        "Nasirabad"
    ],
    "name:und_x_variant":[
        "Na\u015fr\u0101b\u0101d",
        "Qal\u2018eh-ye Ra\u1e29\u012bm\u0101b\u0101d",
        "Ra\u1e29\u012bm\u0101b\u0101d"
    ],
    "wof:name":"Nasirabad-e Avval",
    "wof:placetype":"locality"
},
  "geometry": {"coordinates":[54.22792,29.22382],"type":"Point"}
}