{
  "type": "Feature",
  "properties": {
    "gn:admin1_code":"5",
    "gn:asciiname":"Dowput",
    "gn:country_code":"IR",
    "gn:dem":1994,
    "gn:feature_class":"P",
    "gn:feature_code":"PPL",
    "gn:name":"Dowp\u016bt",
    "gn:population":0,
    "gn:timezone":"Asia/Tehran",
    "iso:country":"IR",
    "name:ara_x_preferred":[
        "\u062f\u0648\u0628\u0648\u062a"
    ],
    "name:fas_x_preferred":[
        "\u062f\u0650\u0647\u067e\u0648\u062a"
    ],
    "name:fas_x_variant":[
        "Dowp\u016bt",
        "Dehp\u016bt",
        "\u062f\u0648\u067e\u0648\u062a"
    ],
    "name:und_x_variant":[
        "\u062f\u0648\u067e\u0648\u062a"
    ],
    "wof:name":"Dowput",
    "wof:placetype":"locality"
},
  "geometry": {"coordinates":[51.4556,30.6499],"type":"Point"}
}