{
  "type": "Feature",
  "properties": {
    "gn:admin1_code":"3",
    "gn:asciiname":"Chaleshtar",
    "gn:country_code":"IR",
    "gn:dem":2079,
    "gn:feature_class":"P",
    "gn:feature_code":"PPL",
    "gn:name":"Ch\u0101leshtar",
    "gn:population":0,
    "gn:timezone":"Asia/Tehran",
    "iso:country":"IR",
    "name:ara_x_preferred":[
        "\u062a\u0634\u0627\u0644\u0634\u062a\u0631"
    ],
    "name:fas_x_preferred":[
        "\u0686\u064e\u0644\u0650\u0634\u062a\u064e\u0631"
    ],
    "name:fas_x_variant":[
        "\u0686\u0627\u0644 \u0634\u064f\u062a\u064f\u0631",
        "Ch\u0101leshtar",
        "\u0686\u0627\u0644\u0634\u062a\u0631",
        "\u0686\u0627\u0644\u0634 \u062a\u0631"
    ],
    "name:ita_x_preferred":[
        "Chaleshtar"
    ],
    "name:msa_x_preferred":[
        "Chaleshtar"
    ],
    "name:rus_x_preferred":[
        "\u0427\u0430\u043b\u0435\u0448\u0442\u0430\u0440"
    ],
    "name:und_x_variant":[
        "Ch\u0101l Shotor"
    ],
    "wof:name":"Chaleshtar",
    "wof:placetype":"locality"
},
  "geometry": {"coordinates":[50.78663,32.37869],"type":"Point"}
}