{
  "type": "Feature",
  "properties": {
    "gn:admin1_code":"22.0",
    "gn:asciiname":"Mahalleh-ye Deymiti",
    "gn:country_code":"IR",
    "gn:dem":636,
    "gn:feature_class":"P",
    "gn:feature_code":"PPL",
    "gn:name":"Ma\u1e29alleh-ye Deym\u012bt\u012b",
    "gn:population":0,
    "gn:timezone":"Asia/Tehran",
    "iso:country":"IR",
    "name:fas_x_preferred":[
        "\u0645\u062d\u0644\u0647 \u062f\u06cc\u0645\u06cc\u062a\u06cc"
    ],
    "name:fas_x_variant":[
        "\u062f\u0648 \u0645\u06cc\u062a\u06cc"
    ],
    "name:und_x_variant":[
        "Ma\u1e29alleh-ye Deym\u012bt\u012b",
        "Do Meyt\u012b"
    ],
    "wof:name":"Mahalleh-ye Deymiti",
    "wof:placetype":"locality"
},
  "geometry": {"coordinates":[52.32285,27.84551],"type":"Point"}
}