{
  "type": "Feature",
  "properties": {
    "gn:admin1_code":"28",
    "gn:asciiname":"Kolijeh",
    "gn:country_code":"IR",
    "gn:dem":2692,
    "gn:feature_class":"P",
    "gn:feature_code":"PPL",
    "gn:name":"Kol\u012bjeh",
    "gn:population":0,
    "gn:timezone":"Asia/Tehran",
    "iso:country":"IR",
    "name:fas_x_preferred":[
        "Kol\u012bjeh"
    ],
    "wof:name":"Kolijeh",
    "wof:placetype":"locality"
},
  "geometry": {"coordinates":[51.39722,31.36722],"type":"Point"}
}