{
  "type": "Feature",
  "properties": {
    "gn:admin1_code":"15.0",
    "gn:asciiname":"Neyabad",
    "gn:country_code":"IR",
    "gn:dem":47,
    "gn:feature_class":"P",
    "gn:feature_code":"PPL",
    "gn:name":"Ney\u0101b\u0101d",
    "gn:population":0,
    "gn:timezone":"Asia/Tehran",
    "iso:country":"IR",
    "name:fas_x_preferred":[
        "\u0634\u0647\u0631\u06a9 \u0634\u0647\u06cc\u062f \u0628\u0647\u0634\u062a\u06cc \u0646\u06cc \u0622\u0628\u0627\u062f"
    ],
    "name:fas_x_variant":[
        "Shahrak-e Shah\u012bd Behesht\u012b-ye Ney\u0101b\u0101d",
        "\u0646\u06cc \u0622\u0628\u0627\u062f",
        "\u0634\u0647\u0631\u06a9 \u0634\u0647\u06cc\u062f \u0628\u0647\u0634\u062a\u06cc"
    ],
    "name:und_x_variant":[
        "Ney\u0101b\u0101d",
        "Shahrak-e Shah\u012bd Behesht\u012b"
    ],
    "wof:name":"Neyabad",
    "wof:placetype":"locality"
},
  "geometry": {"coordinates":[48.59486,32.10112],"type":"Point"}
}