{
  "type": "Feature",
  "properties": {
    "gn:admin1_code":"1",
    "gn:asciiname":"Shiva Kandi",
    "gn:country_code":"IR",
    "gn:dem":2013,
    "gn:feature_class":"P",
    "gn:feature_code":"PPL",
    "gn:name":"Sh\u012bv\u0101 Kand\u012b",
    "gn:population":0,
    "gn:timezone":"Asia/Tehran",
    "iso:country":"IR",
    "name:aze_x_preferred":[
        "\u015eivan"
    ],
    "name:ceb_x_preferred":[
        "Sh\u012bv\u0101 Kand\u012b"
    ],
    "name:fas_x_preferred":[
        "\u0634\u06cc\u0648\u0627 \u06a9\u0646\u062f\u06cc"
    ],
    "name:fas_x_variant":[
        "Sh\u012bv\u0101n Kand\u012b",
        "Sh\u012bv\u0101 Kand\u012b",
        "\u0634\u06cc\u0648\u0627\u0646\u200c\u06a9\u0646\u062f\u06cc"
    ],
    "name:msa_x_preferred":[
        "Shivan Kandi"
    ],
    "name:swe_x_preferred":[
        "Sh\u012bv\u0101 Kand\u012b"
    ],
    "wof:name":"Shiva Kandi",
    "wof:placetype":"locality"
},
  "geometry": {"coordinates":[44.7215,38.65],"type":"Point"}
}