{
  "type": "Feature",
  "properties": {
    "gn:admin1_code":"28",
    "gn:asciiname":"Baba Khosrow",
    "gn:country_code":"IR",
    "gn:dem":2380,
    "gn:feature_class":"P",
    "gn:feature_code":"PPL",
    "gn:name":"B\u0101b\u0101 Khosrow",
    "gn:population":0,
    "gn:timezone":"Asia/Tehran",
    "iso:country":"IR",
    "name:ara_x_preferred":[
        "\u0628\u0627\u0628\u0627\u062e\u0633\u0631\u0648"
    ],
    "name:fas_x_preferred":[
        "B\u0101b\u0101 Khosrow"
    ],
    "name:fas_x_variant":[
        "\u0628\u0627\u0628\u0627 \u062e\u0633\u0631\u0648",
        "\u0628\u0627\u0628\u0627\u062e\u0633\u0631\u0648"
    ],
    "wof:name":"Baba Khosrow",
    "wof:placetype":"locality"
},
  "geometry": {"coordinates":[49.79628,32.90553],"type":"Point"}
}