{
  "type": "Feature",
  "properties": {
    "gn:admin1_code":"15",
    "gn:asciiname":"Cheshmeh Morad",
    "gn:country_code":"IR",
    "gn:dem":106,
    "gn:feature_class":"P",
    "gn:feature_code":"PPL",
    "gn:name":"Cheshmeh Mor\u0101d",
    "gn:population":0,
    "gn:timezone":"Asia/Tehran",
    "iso:country":"IR",
    "name:azb_x_preferred":[
        "\u0686\u0634\u0645\u0647 \u0645\u0631\u0627\u062f(\u0628\u0647\u0628\u0647\u0627\u0646)"
    ],
    "name:ceb_x_preferred":[
        "Cheshmeh Mor\u0101d"
    ],
    "name:fas_x_preferred":[
        "\u0686\u0634\u0645\u0647 \u0645\u0631\u0627\u062f"
    ],
    "name:fas_x_variant":[
        "Cheshmeh Mor\u0101d",
        "\u0686\u0634\u0645\u0647\u200c\u0645\u0631\u0627\u062f"
    ],
    "name:swe_x_preferred":[
        "Cheshmeh Mor\u0101d"
    ],
    "name:und_x_variant":[
        "Chashmeh Mor\u0101d"
    ],
    "wof:name":"Cheshmeh Morad",
    "wof:placetype":"locality"
},
  "geometry": {"coordinates":[50.0161,30.3981],"type":"Point"}
}