{
  "type": "Feature",
  "properties": {
    "gn:admin1_code":"42",
    "gn:asciiname":"`Ali Kal-e Bala",
    "gn:country_code":"IR",
    "gn:dem":2670,
    "gn:feature_class":"P",
    "gn:feature_code":"PPL",
    "gn:name":"\u2018Al\u012b Kal-e B\u0101l\u0101",
    "gn:population":0,
    "gn:timezone":"Asia/Tehran",
    "iso:country":"IR",
    "name:fas_x_preferred":[
        "\u0639\u0644\u06cc \u06a9\u0644 \u0628\u0627\u0644\u0627"
    ],
    "name:fas_x_variant":[
        "\u2018Al\u012b Kal-e B\u0101l\u0101"
    ],
    "wof:name":"`Ali Kal-e Bala",
    "wof:placetype":"locality"
},
  "geometry": {"coordinates":[59.41438,36.96149000000001],"type":"Point"}
}