{
  "type": "Feature",
  "properties": {
    "gn:admin1_code":"15",
    "gn:asciiname":"Cham Karteh",
    "gn:country_code":"IR",
    "gn:dem":69,
    "gn:feature_class":"P",
    "gn:feature_code":"PPL",
    "gn:name":"Cham Karteh",
    "gn:population":0,
    "gn:timezone":"Asia/Tehran",
    "iso:country":"IR",
    "name:azb_x_preferred":[
        "\u0686\u0645 \u0643\u0631\u062a\u0647(\u0628\u0647\u0628\u0647\u0627\u0646)"
    ],
    "name:ceb_x_preferred":[
        "Cham Karteh"
    ],
    "name:fas_x_preferred":[
        "\u0686\u0645 \u06a9\u0631\u062a\u0647"
    ],
    "name:swe_x_preferred":[
        "Cham Karteh"
    ],
    "name:und_x_variant":[
        "Chamkarda",
        "Cham Kerteh",
        "Cham Karteh"
    ],
    "wof:name":"Cham Karteh",
    "wof:placetype":"locality"
},
  "geometry": {"coordinates":[49.95903,30.49305],"type":"Point"}
}