{
  "type": "Feature",
  "properties": {
    "gn:admin1_code":"28.0",
    "gn:asciiname":"Lajan Ab",
    "gn:country_code":"IR",
    "gn:dem":2228,
    "gn:feature_class":"P",
    "gn:feature_code":"PPL",
    "gn:name":"Lajan \u0100b",
    "gn:population":0,
    "gn:timezone":"Asia/Tehran",
    "iso:country":"IR",
    "name:fas_x_preferred":[
        "Lajan \u0100b"
    ],
    "name:fas_x_variant":[
        "\u0644\u062c\u0646 \u0622\u0628"
    ],
    "wof:name":"Lajan Ab",
    "wof:placetype":"locality"
},
  "geometry": {"coordinates":[51.93961,31.64734],"type":"Point"}
}