{
  "type": "Feature",
  "properties": {
    "gn:admin1_code":"29",
    "gn:asciiname":"Darb-e Behesht",
    "gn:country_code":"IR",
    "gn:dem":2633,
    "gn:feature_class":"P",
    "gn:feature_code":"PPL",
    "gn:name":"Darb-e Behesht",
    "gn:population":0,
    "gn:timezone":"Asia/Tehran",
    "iso:country":"IR",
    "name:fas_x_preferred":[
        "\u062f\u0631\u0628 \u0645\u0632\u0627\u0631"
    ],
    "name:fas_x_variant":[
        "Darb-e Maz\u0101r",
        "\u062f\u0631\u0628 \u0628\u0647\u0634\u062a"
    ],
    "name:und_x_variant":[
        "S\u0101rd\u016b\u012byeh",
        "Dar-i-Maz\u0101r",
        "Darbmaz\u0101r",
        "Darb-e Behesht",
        "\u062f\u0631\u0628 \u0628\u0647\u0634\u062a",
        "Dar Maz\u0101r"
    ],
    "wof:name":"Darb-e Behesht",
    "wof:placetype":"locality"
},
  "geometry": {"coordinates":[57.33216,29.2359],"type":"Point"}
}