{
  "type": "Feature",
  "properties": {
    "gn:admin1_code":"26.0",
    "gn:asciiname":"Qal`eh Sar Neza`",
    "gn:country_code":"IR",
    "gn:dem":2112,
    "gn:feature_class":"P",
    "gn:feature_code":"PPL",
    "gn:name":"Qal\u2018eh Sar Nez\u0101\u2018",
    "gn:population":0,
    "gn:timezone":"Asia/Tehran",
    "iso:country":"IR",
    "name:fas_x_preferred":[
        "Qal\u2018eh Sar Nez\u0101\u2018"
    ],
    "name:fas_x_variant":[
        "\u0642\u0644\u0639\u0647 \u0633\u0631 \u0646\u0632\u0627\u0639"
    ],
    "wof:name":"Qal`eh Sar Neza`",
    "wof:placetype":"locality"
},
  "geometry": {"coordinates":[52.88581,35.75819],"type":"Point"}
}