{
  "type": "Feature",
  "properties": {
    "gn:admin1_code":"4.0",
    "gn:asciiname":"Dukey",
    "gn:country_code":"IR",
    "gn:dem":1490,
    "gn:feature_class":"P",
    "gn:feature_code":"PPL",
    "gn:name":"D\u016bkey",
    "gn:population":0,
    "gn:timezone":"Asia/Tehran",
    "iso:country":"IR",
    "name:fas_x_preferred":[
        "\u062f\u0648\u06a9\u06cc"
    ],
    "name:fas_x_variant":[
        "Sh\u0101h Har\u0101h",
        "D\u016bkey"
    ],
    "wof:name":"Dukey",
    "wof:placetype":"locality"
},
  "geometry": {"coordinates":[61.36965,26.95669],"type":"Point"}
}