{
  "type": "Feature",
  "properties": {
    "gn:admin1_code":"35",
    "gn:asciiname":"Gilas",
    "gn:country_code":"IR",
    "gn:dem":1807,
    "gn:feature_class":"P",
    "gn:feature_code":"PPL",
    "gn:name":"G\u012bl\u0101s",
    "gn:population":0,
    "gn:timezone":"Asia/Tehran",
    "iso:country":"IR",
    "name:ara_x_preferred":[
        "\u0639\u064a\u0644\u0627\u0633"
    ],
    "name:fas_x_preferred":[
        "\u06af\u064a\u0644\u0627\u0633"
    ],
    "name:fas_x_variant":[
        "G\u012bl\u0101s",
        "\u06af\u06cc\u0644\u0627\u0633"
    ],
    "name:ukr_x_preferred":[
        "\u0490\u0456\u043b\u0430\u0441"
    ],
    "wof:name":"Gilas",
    "wof:placetype":"locality"
},
  "geometry": {"coordinates":[52.20101,35.88215],"type":"Point"}
}