{
  "type": "Feature",
  "properties": {
    "gn:admin1_code":"37",
    "gn:asciiname":"Livan-e Gharbi",
    "gn:country_code":"IR",
    "gn:dem":5,
    "gn:feature_class":"P",
    "gn:feature_code":"PPL",
    "gn:name":"L\u012bv\u0101n-e Gharb\u012b",
    "gn:population":0,
    "gn:timezone":"Asia/Tehran",
    "iso:country":"IR",
    "name:ara_x_preferred":[
        "\u0644\u064a\u0648\u0627\u0646 \u0627\u0644\u063a\u0631\u0628\u064a"
    ],
    "name:fas_x_preferred":[
        "\u0644\u064a\u0648\u0627\u0646"
    ],
    "name:fas_x_variant":[
        "\u0644\u064a\u062a\u0648\u0627\u0646",
        "\u0644\u064a\u0648\u0627\u0646 \u063a\u064e\u0631\u0628\u06cc",
        "L\u012bv\u0101n-e Gharb\u012b",
        "\u0644\u064a\u0648\u0627\u0646 \u063a\u0631\u0628\u06cc",
        "\u0644\u06cc\u0648\u0627\u0646 \u063a\u0631\u0628\u06cc"
    ],
    "name:msa_x_preferred":[
        "Livan-e Gharbi"
    ],
    "name:und_x_variant":[
        "L\u012bv\u0101n",
        "L\u012btv\u0101n",
        "L\u012bv\u0101n Gharb\u012b"
    ],
    "wof:name":"Livan-e Gharbi",
    "wof:placetype":"locality"
},
  "geometry": {"coordinates":[53.87455,36.73385],"type":"Point"}
}