{
  "type": "Feature",
  "properties": {
    "gn:admin1_code":"42",
    "gn:asciiname":"Kalateh-ye Shams",
    "gn:country_code":"IR",
    "gn:dem":1413,
    "gn:feature_class":"P",
    "gn:feature_code":"PPL",
    "gn:name":"Kal\u0101teh-ye Shams",
    "gn:population":0,
    "gn:timezone":"Asia/Tehran",
    "iso:country":"IR",
    "name:ara_x_preferred":[
        "\u0643\u0644\u0627\u062a\u0629 \u0634\u0645\u0633"
    ],
    "name:fas_x_preferred":[
        "Kal\u0101teh-ye Shams"
    ],
    "name:fas_x_variant":[
        "\u06a9\u0644\u0627\u062a\u0647 \u0634\u0645\u0633"
    ],
    "name:und_x_variant":[
        "\u06a9\u0644\u0627\u062a\u0647 \u0634\u0645\u0633"
    ],
    "wof:name":"Kalateh-ye Shams",
    "wof:placetype":"locality"
},
  "geometry": {"coordinates":[58.73878000000001,34.15295],"type":"Point"}
}