{
  "type": "Feature",
  "properties": {
    "gn:admin1_code":"29",
    "gn:asciiname":"Deh-e Safari",
    "gn:country_code":"IR",
    "gn:dem":2020,
    "gn:feature_class":"P",
    "gn:feature_code":"PPL",
    "gn:name":"Deh-e \u015eafar\u012b",
    "gn:population":0,
    "gn:timezone":"Asia/Tehran",
    "iso:country":"IR",
    "name:fas_x_preferred":[
        "\u062f\u0650\u0647\u0650 \u0635\u064e\u0641\u064e\u0631"
    ],
    "name:fas_x_variant":[
        "\u062f\u0650\u0647 \u0633\u064e\u0641\u064e\u0631",
        "\u062f\u0647 \u0635\u0641\u0631\u06cc",
        "Deh-e \u015eafar",
        "Deh-e \u015eafar\u012b"
    ],
    "name:und_x_variant":[
        "Deh Safar",
        "Deh-Latar"
    ],
    "wof:name":"Deh-e Safari",
    "wof:placetype":"locality"
},
  "geometry": {"coordinates":[57.5917,29.4322],"type":"Point"}
}