{
  "type": "Feature",
  "properties": {
    "gn:admin1_code":"8",
    "gn:asciiname":"Bozkuyeh",
    "gn:cc2":"IR",
    "gn:country_code":"IR",
    "gn:dem":757,
    "gn:feature_class":"P",
    "gn:feature_code":"PPL",
    "gn:name":"Bozk\u016byeh",
    "gn:population":0,
    "gn:timezone":"Asia/Tehran",
    "iso:country":"IR",
    "name:fas_x_preferred":[
        "Bozk\u016byeh"
    ],
    "name:und_x_variant":[
        "Boz-e Gav\u0101bar",
        "B\u016bzgovar"
    ],
    "wof:name":"Bozkuyeh",
    "wof:placetype":"locality"
},
  "geometry": {"coordinates":[50.15917,37.02472],"type":"Point"}
}