{
  "type": "Feature",
  "properties": {
    "gn:admin1_code":"41",
    "gn:asciiname":"Kalateh-ye Majid",
    "gn:country_code":"IR",
    "gn:dem":1925,
    "gn:feature_class":"P",
    "gn:feature_code":"PPL",
    "gn:name":"Kal\u0101teh-ye Maj\u012bd",
    "gn:population":0,
    "gn:timezone":"Asia/Tehran",
    "iso:country":"IR",
    "name:fas_x_preferred":[
        "Kal\u0101teh-ye Maj\u012bd"
    ],
    "name:und_x_variant":[
        "Kal\u0101teh Maj\u012bd",
        "Kalateh Majidi",
        "Kal\u0101teh Maj\u016bd"
    ],
    "wof:name":"Kalateh-ye Majid",
    "wof:placetype":"locality"
},
  "geometry": {"coordinates":[59.06944,32.74639000000001],"type":"Point"}
}