{
  "type": "Feature",
  "properties": {
    "gn:admin1_code":"1",
    "gn:asciiname":"Gerik",
    "gn:country_code":"IR",
    "gn:dem":1311,
    "gn:feature_class":"P",
    "gn:feature_code":"PPL",
    "gn:name":"Ger\u012bk",
    "gn:population":0,
    "gn:timezone":"Asia/Tehran",
    "iso:country":"IR",
    "name:fas_x_preferred":[
        "\u06af\u0650\u0631\u064a\u0643"
    ],
    "name:fas_x_variant":[
        "\u06af\u0650\u062c\u0650\u0647 \u0642\u0650\u0634\u0644\u0627\u0642",
        "\u0642\u0650\u0634\u0644\u0627\u0642 \u062c\u064a\u062c\u0648",
        "Ger\u012bk",
        "\u0642\u0650\u0634\u0644\u0627\u0642\u0650 \u06af\u064e\u0631\u064a\u06af",
        "\u0642\u0650\u0634\u0644\u0627\u0642\u0650 \u062c\u064a\u062c\u0648",
        "\u06af\u0631\u06cc\u06a9"
    ],
    "name:msa_x_preferred":[
        "Gerik"
    ],
    "name:tam_x_preferred":[
        "\u0b95\u0bbf\u0bb0\u0bbf\u0b95\u0bcd"
    ],
    "name:und_x_variant":[
        "Garik",
        "Gejeh Qeshl\u0101q",
        "Qeshl\u0101q-e Gar\u012bg",
        "Gijo Qishl\u0101q",
        "Qeshl\u0101q J\u012bj\u016b",
        "Qeshl\u0101q-e J\u012bj\u016b",
        "\u06af\u0631\u06cc\u06a9"
    ],
    "name:urd_x_preferred":[
        "\u06af\u0631\u06cc\u0642"
    ],
    "wof:name":"Gerik",
    "wof:placetype":"locality"
},
  "geometry": {"coordinates":[44.4625,39.5506],"type":"Point"}
}