{
  "type": "Feature",
  "properties": {
    "gn:admin1_code":"8",
    "gn:asciiname":"Pileh Bagh",
    "gn:country_code":"IR",
    "gn:dem":27,
    "gn:feature_class":"P",
    "gn:feature_code":"PPL",
    "gn:name":"P\u012bleh B\u0101gh",
    "gn:population":0,
    "gn:timezone":"Asia/Tehran",
    "iso:country":"IR",
    "name:fas_x_preferred":[
        "\u06a9\u0644\u0646\u06af\u0633\u062a\u0627\u0646"
    ],
    "name:fas_x_variant":[
        "Kolangest\u0101n",
        "\u067e\u06cc\u0644\u0647 \u0628\u0627\u063a"
    ],
    "name:und_x_variant":[
        "P\u012bleh B\u0101gh"
    ],
    "wof:name":"Pileh Bagh",
    "wof:placetype":"locality"
},
  "geometry": {"coordinates":[49.1633,37.383],"type":"Point"}
}