{
  "type": "Feature",
  "properties": {
    "gn:admin1_code":"10",
    "gn:asciiname":"Takhtan",
    "gn:country_code":"IR",
    "gn:dem":1086,
    "gn:feature_class":"P",
    "gn:feature_code":"PPL",
    "gn:name":"Takht\u0101n",
    "gn:population":0,
    "gn:timezone":"Asia/Tehran",
    "iso:country":"IR",
    "name:ara_x_preferred":[
        "\u062a\u062e\u062a\u0627\u0646"
    ],
    "name:ceb_x_preferred":[
        "\u0100b Takht\u0101n"
    ],
    "name:fas_x_preferred":[
        "\u062a\u062e\u062a\u0627\u0646"
    ],
    "name:fas_x_variant":[
        "\u0622\u0628 \u062a\u062e\u062a\u0627\u0646",
        "Takht\u0101n",
        "\u0100b Takht\u0101n"
    ],
    "name:msa_x_preferred":[
        "Takhtan"
    ],
    "name:swe_x_preferred":[
        "\u0100b Takht\u0101n"
    ],
    "wof:name":"Takhtan",
    "wof:placetype":"locality"
},
  "geometry": {"coordinates":[47.05535,33.14424],"type":"Point"}
}