{
  "type": "Feature",
  "properties": {
    "gn:admin1_code":"8.0",
    "gn:asciiname":"Milash",
    "gn:country_code":"IR",
    "gn:dem":643,
    "gn:feature_class":"P",
    "gn:feature_code":"PPL",
    "gn:name":"M\u012bl\u0101sh",
    "gn:population":0,
    "gn:timezone":"Asia/Tehran",
    "iso:country":"IR",
    "name:fas_x_preferred":[
        "M\u012bl\u0101sh"
    ],
    "name:fas_x_variant":[
        "\u0645\u06cc\u0644\u0627\u0634"
    ],
    "name:und_x_variant":[
        "\u0645\u06cc\u0644\u0627\u0634"
    ],
    "wof:name":"Milash",
    "wof:placetype":"locality"
},
  "geometry": {"coordinates":[50.21468,36.89386],"type":"Point"}
}