{
  "type": "Feature",
  "properties": {
    "gn:admin1_code":"35",
    "gn:asciiname":"Pa'in Gileh Kola",
    "gn:country_code":"IR",
    "gn:dem":-8,
    "gn:feature_class":"P",
    "gn:feature_code":"PPL",
    "gn:name":"P\u0101\u2019\u012bn G\u012bleh Kol\u0101",
    "gn:population":0,
    "gn:timezone":"Asia/Tehran",
    "iso:country":"IR",
    "name:fas_x_preferred":[
        "\u067e\u0627\u0626\u064a\u0646 \u06af\u064a\u0644\u0647 \u0643\u0644\u0627"
    ],
    "name:fas_x_variant":[
        "P\u0101\u2019\u012bn G\u012bleh Kol\u0101"
    ],
    "wof:name":"Pa'in Gileh Kola",
    "wof:placetype":"locality"
},
  "geometry": {"coordinates":[52.98076,36.61453],"type":"Point"}
}