{
  "type": "Feature",
  "properties": {
    "gn:admin1_code":"15.0",
    "gn:asciiname":"Girkutiv",
    "gn:country_code":"IR",
    "gn:dem":367,
    "gn:feature_class":"P",
    "gn:feature_code":"PPL",
    "gn:name":"G\u012brk\u016bt\u012bv",
    "gn:population":0,
    "gn:timezone":"Asia/Tehran",
    "iso:country":"IR",
    "name:fas_x_preferred":[
        "\u06af\u06cc\u0631\u06a9\u0648\u062a\u06cc\u0648"
    ],
    "name:fas_x_variant":[
        "G\u012brk\u016bt\u012bv"
    ],
    "wof:name":"Girkutiv",
    "wof:placetype":"locality"
},
  "geometry": {"coordinates":[49.1657,32.3236],"type":"Point"}
}