{
  "type": "Feature",
  "properties": {
    "gn:admin1_code":"29",
    "gn:asciiname":"Konatabad",
    "gn:country_code":"IR",
    "gn:dem":544,
    "gn:feature_class":"P",
    "gn:feature_code":"PPL",
    "gn:name":"Konat\u0101b\u0101d",
    "gn:population":0,
    "gn:timezone":"Asia/Tehran",
    "iso:country":"IR",
    "name:fas_x_preferred":[
        "\u06a9\u0646\u062a \u0622\u0628\u0627\u062f"
    ],
    "name:fas_x_variant":[
        "Konat\u0101b\u0101d"
    ],
    "wof:name":"Konatabad",
    "wof:placetype":"locality"
},
  "geometry": {"coordinates":[58.52004,27.98101],"type":"Point"}
}