{
  "type": "Feature",
  "properties": {
    "gn:admin1_code":"1.0",
    "gn:asciiname":"Qarah Qeshlaq",
    "gn:country_code":"IR",
    "gn:dem":1289,
    "gn:feature_class":"P",
    "gn:feature_code":"PPL",
    "gn:name":"Qarah Qeshl\u0101q",
    "gn:population":0,
    "gn:timezone":"Asia/Tehran",
    "iso:country":"IR",
    "name:aze_x_preferred":[
        "Qara Q\u0131\u015flaq"
    ],
    "name:fas_x_preferred":[
        "\u0642\u0631\u0647 \u0642\u0634\u0644\u0627\u0642"
    ],
    "name:fas_x_variant":[
        "Qareh Qeshl\u0101q",
        "Qarah Qeshl\u0101q",
        "\u0642\u0631\u0647\u200c\u0642\u0634\u0644\u0627\u0642"
    ],
    "wof:name":"Qarah Qeshlaq",
    "wof:placetype":"locality"
},
  "geometry": {"coordinates":[44.9519,38.2053],"type":"Point"}
}