{
  "type": "Feature",
  "properties": {
    "gn:admin1_code":"29",
    "gn:asciiname":"Jam`",
    "gn:country_code":"IR",
    "gn:dem":2781,
    "gn:feature_class":"P",
    "gn:feature_code":"PPLL",
    "gn:name":"Jam\u2018",
    "gn:population":0,
    "gn:timezone":"Asia/Tehran",
    "iso:country":"IR",
    "name:fas_x_preferred":[
        "Jam\u2018"
    ],
    "name:fas_x_variant":[
        "\u062c\u0645\u0639"
    ],
    "wof:name":"Jam`",
    "wof:placetype":"locality"
},
  "geometry": {"coordinates":[58.03809,28.73242],"type":"Point"}
}