{
  "type": "Feature",
  "properties": {
    "gn:admin1_code":"29",
    "gn:asciiname":"Gurchu'iyeh",
    "gn:country_code":"IR",
    "gn:dem":1770,
    "gn:feature_class":"P",
    "gn:feature_code":"PPL",
    "gn:name":"G\u016brch\u016b\u2019\u012byeh",
    "gn:population":0,
    "gn:timezone":"Asia/Tehran",
    "iso:country":"IR",
    "name:fas_x_preferred":[
        "G\u016brch\u016b\u2019\u012byeh"
    ],
    "name:fas_x_variant":[
        "\u06af\u0648\u0631\u0686\u0648\u0626\u064a\u0647",
        "Q\u016brch\u016b",
        "G\u016brchu",
        "Goorchoo\u2019eyeh"
    ],
    "name:und_x_variant":[
        "Q\u016brch\u016b",
        "Goorchoo\u2019eyeh",
        "G\u016brchu",
        "\u06af\u0648\u0631\u0686\u0648\u0626\u064a\u0647"
    ],
    "wof:name":"Gurchu'iyeh",
    "wof:placetype":"locality"
},
  "geometry": {"coordinates":[56.81438000000001,30.67041],"type":"Point"}
}