{
  "type": "Feature",
  "properties": {
    "gn:admin1_code":"42",
    "gn:asciiname":"Ebrahimabad",
    "gn:country_code":"IR",
    "gn:dem":1696,
    "gn:feature_class":"P",
    "gn:feature_code":"PPLF",
    "gn:name":"Ebr\u0101h\u012bm\u0101b\u0101d",
    "gn:population":0,
    "gn:timezone":"Asia/Tehran",
    "iso:country":"IR",
    "name:fas_x_preferred":[
        "Ebr\u0101h\u012bm\u0101b\u0101d"
    ],
    "name:fas_x_variant":[
        "\u0627\u0628\u0631\u0627\u0647\u064a\u0645 \u0622\u0628\u0627\u062f"
    ],
    "wof:name":"Ebrahimabad",
    "wof:placetype":"locality"
},
  "geometry": {"coordinates":[58.5925,34.15535],"type":"Point"}
}