{
  "type": "Feature",
  "properties": {
    "gn:admin1_code":"1",
    "gn:asciiname":"Bayram Kandi",
    "gn:country_code":"IR",
    "gn:dem":1104,
    "gn:feature_class":"P",
    "gn:feature_code":"PPL",
    "gn:name":"B\u0101yr\u0101m Kand\u012b",
    "gn:population":0,
    "gn:timezone":"Asia/Tehran",
    "iso:country":"IR",
    "name:aze_x_preferred":[
        "Bayramk\u0259nd"
    ],
    "name:fas_x_preferred":[
        "\u0628\u0627\u064a\u0631\u0627\u0645 \u0643\u0646\u062f\u06cc"
    ],
    "name:fas_x_variant":[
        "B\u0101yr\u0101m Kand\u012b",
        "\u0628\u0627\u06cc\u0631\u0645 \u06a9\u0646\u062f\u06cc"
    ],
    "name:und_x_variant":[
        "Bahr\u0101m Kand\u012b",
        "Bayramkend",
        "Bairamkand",
        "B\u0101yram Kand\u012b"
    ],
    "wof:name":"Bayram Kandi",
    "wof:placetype":"locality"
},
  "geometry": {"coordinates":[45.02347,38.52913],"type":"Point"}
}