{
  "type": "Feature",
  "properties": {
    "gn:admin1_code":"29.0",
    "gn:asciiname":"Bagh-e Cheshmeh Gu",
    "gn:country_code":"IR",
    "gn:dem":1854,
    "gn:feature_class":"P",
    "gn:feature_code":"PPL",
    "gn:name":"B\u0101gh-e Cheshmeh G\u016b",
    "gn:population":0,
    "gn:timezone":"Asia/Tehran",
    "iso:country":"IR",
    "name:fas_x_preferred":[
        "B\u0101gh-e Cheshmeh G\u016b"
    ],
    "wof:name":"Bagh-e Cheshmeh Gu",
    "wof:placetype":"locality"
},
  "geometry": {"coordinates":[57.30472,30.48167],"type":"Point"}
}