{
  "type": "Feature",
  "properties": {
    "gn:admin1_code":"7",
    "gn:asciiname":"Mahmudabad-e Sofla",
    "gn:country_code":"IR",
    "gn:dem":1613,
    "gn:feature_class":"P",
    "gn:feature_code":"PPL",
    "gn:name":"Ma\u1e29m\u016bd\u0101b\u0101d-e Sofl\u00e1",
    "gn:population":0,
    "gn:timezone":"Asia/Tehran",
    "iso:country":"IR",
    "name:ara_x_preferred":[
        "\u0645\u062d\u0645\u0648\u062f\u0622\u0628\u0627\u062f \u0633\u0641\u0644\u064a"
    ],
    "name:fas_x_preferred":[
        "\u0645\u062d\u0645\u0648\u062f \u0622\u0628\u0627\u062f"
    ],
    "name:fas_x_variant":[
        "Ma\u1e29m\u016bd\u0101b\u0101d",
        "\u0645\u062d\u0645\u0648\u062f \u0622\u0628\u0627\u062f \u0633\u0641\u0644\u06cc",
        "\u0645\u062d\u0645\u0648\u062f\u0622\u0628\u0627\u062f \u0633\u0641\u0644\u06cc"
    ],
    "name:msa_x_preferred":[
        "Mahmudabad-e Sofla"
    ],
    "name:pol_x_preferred":[
        "Mahmudabad-e Sofla"
    ],
    "name:und_x_variant":[
        "Ma\u1e29m\u016bd\u0101b\u0101d-e Sofl\u00e1"
    ],
    "wof:name":"Mahmudabad-e Sofla",
    "wof:placetype":"locality"
},
  "geometry": {"coordinates":[53.5058,29.1156],"type":"Point"}
}