{
  "type": "Feature",
  "properties": {
    "gn:admin1_code":"4",
    "gn:asciiname":"Khan Bibi",
    "gn:country_code":"IR",
    "gn:dem":1505,
    "gn:feature_class":"P",
    "gn:feature_code":"PPL",
    "gn:name":"Kh\u0101n B\u012bb\u012b",
    "gn:population":0,
    "gn:timezone":"Asia/Tehran",
    "iso:country":"IR",
    "name:fas_x_preferred":[
        "\u062e\u0627\u0646 \u0628\u06cc \u0628\u06cc"
    ],
    "name:fas_x_variant":[
        "Kh\u0101n B\u012bb\u012b",
        "\u062e\u0627\u0646 \u0628\u06cc\u200c\u0628\u06cc"
    ],
    "wof:name":"Khan Bibi",
    "wof:placetype":"locality"
},
  "geometry": {"coordinates":[61.16514,28.16487],"type":"Point"}
}