{
  "type": "Feature",
  "properties": {
    "gn:admin1_code":"11",
    "gn:asciiname":"Nowbast",
    "gn:country_code":"IR",
    "gn:dem":18,
    "gn:feature_class":"P",
    "gn:feature_code":"PPL",
    "gn:name":"Nowbast",
    "gn:population":0,
    "gn:timezone":"Asia/Tehran",
    "iso:country":"IR",
    "name:ara_x_preferred":[
        "\u0646\u0648\u0628\u0633\u062a"
    ],
    "name:ceb_x_preferred":[
        "Nowbast"
    ],
    "name:fas_x_preferred":[
        "\u0646\u0648\u0628\u0633\u062a"
    ],
    "name:msa_x_preferred":[
        "Nowbast"
    ],
    "name:swe_x_preferred":[
        "Nowbast"
    ],
    "wof:name":"Nowbast",
    "wof:placetype":"locality"
},
  "geometry": {"coordinates":[56.6855,27.3275],"type":"Point"}
}