{
  "type": "Feature",
  "properties": {
    "gn:admin1_code":"4",
    "gn:asciiname":"Karimabad-e Espeh",
    "gn:country_code":"IR",
    "gn:dem":1301,
    "gn:feature_class":"P",
    "gn:feature_code":"PPL",
    "gn:name":"Kar\u012bm\u0101b\u0101d-e Espeh",
    "gn:population":0,
    "gn:timezone":"Asia/Tehran",
    "iso:country":"IR",
    "name:fas_x_preferred":[
        "\u06a9\u0631\u06cc\u0645 \u0622\u0628\u0627\u062f \u0627\u0633\u067e\u0647"
    ],
    "name:fas_x_variant":[
        "Kar\u012bm\u0101b\u0101d-e Espeh",
        "\u0627\u0633\u067e\u0647"
    ],
    "name:und_x_variant":[
        "Espeh"
    ],
    "wof:name":"Karimabad-e Espeh",
    "wof:placetype":"locality"
},
  "geometry": {"coordinates":[61.01776,27.83661],"type":"Point"}
}