{
  "type": "Feature",
  "properties": {
    "gn:admin1_code":"33.0",
    "gn:asciiname":"Senowkesh",
    "gn:country_code":"IR",
    "gn:dem":1771,
    "gn:feature_class":"P",
    "gn:feature_code":"PPL",
    "gn:name":"Senowkesh",
    "gn:population":0,
    "gn:timezone":"Asia/Tehran",
    "iso:country":"IR",
    "name:ceb_x_preferred":[
        "Senowkesh"
    ],
    "name:fas_x_preferred":[
        "\u0633\u0646\u0648\u06a9\u0634"
    ],
    "name:msa_x_preferred":[
        "Senowkesh"
    ],
    "name:swe_x_preferred":[
        "Senowkesh"
    ],
    "wof:name":"Senowkesh",
    "wof:placetype":"locality"
},
  "geometry": {"coordinates":[46.2396,37.4753],"type":"Point"}
}