{
  "type": "Feature",
  "properties": {
    "gn:admin1_code":"15",
    "gn:asciiname":"Maslavi",
    "gn:country_code":"IR",
    "gn:dem":2,
    "gn:feature_class":"P",
    "gn:feature_code":"PPL",
    "gn:name":"Masl\u0101v\u012b",
    "gn:population":0,
    "gn:timezone":"Asia/Tehran",
    "iso:country":"IR",
    "name:fas_x_preferred":[
        "\u0645\u0633\u0644\u0627\u0648\u06cc"
    ],
    "name:fas_x_variant":[
        "Ma\u015fl\u0101v\u012b",
        "Masl\u0101v\u012b"
    ],
    "wof:name":"Maslavi",
    "wof:placetype":"locality"
},
  "geometry": {"coordinates":[48.13991,30.46787],"type":"Point"}
}