{
  "type": "Feature",
  "properties": {
    "gn:admin1_code":"43",
    "gn:asciiname":"Khorramdeh-e Sharqi",
    "gn:country_code":"IR",
    "gn:dem":521,
    "gn:feature_class":"P",
    "gn:feature_code":"PPL",
    "gn:name":"Khorramdeh-e Sharq\u012b",
    "gn:population":0,
    "gn:timezone":"Asia/Tehran",
    "iso:country":"IR",
    "name:fas_x_preferred":[
        "Khorramdeh-e Sharq\u012b"
    ],
    "name:fas_x_variant":[
        "Kharak\u012b-ye Kord",
        "\u062e\u0631\u06a9\u06cc \u06a9\u0631\u062f",
        "Kharak\u012b-ye Kordh\u0101",
        "\u062e\u0631\u0645 \u062f\u0647 \u0634\u0631\u0642\u06cc"
    ],
    "name:und_x_variant":[
        "Kharak\u012b-ye Kordh\u0101",
        "\u062e\u0631\u06a9\u06cc \u06a9\u0631\u062f"
    ],
    "wof:name":"Khorramdeh-e Sharqi",
    "wof:placetype":"locality"
},
  "geometry": {"coordinates":[56.79089000000001,37.70907],"type":"Point"}
}