{
  "type": "Feature",
  "properties": {
    "gn:admin1_code":"15",
    "gn:asciiname":"Kal Khvajeh",
    "gn:country_code":"IR",
    "gn:dem":1440,
    "gn:feature_class":"P",
    "gn:feature_code":"PPL",
    "gn:name":"Kal Khv\u0101jeh",
    "gn:population":0,
    "gn:timezone":"Asia/Tehran",
    "iso:country":"IR",
    "name:azb_x_preferred":[
        "\u0643\u0644 \u062e\u0648\u0627\u062c\u0647(\u0627\u06cc\u0630\u0647)"
    ],
    "name:fas_x_preferred":[
        "Kal Khv\u0101jeh"
    ],
    "name:fas_x_variant":[
        "\u06a9\u0644 \u062e\u0648\u0627\u062c\u0647",
        "\u06a9\u0644\u200c\u062e\u0648\u0627\u062c\u0647"
    ],
    "name:und_x_variant":[
        "\u06a9\u0644 \u062e\u0648\u0627\u062c\u0647"
    ],
    "wof:name":"Kal Khvajeh",
    "wof:placetype":"locality"
},
  "geometry": {"coordinates":[50.33317,31.66619],"type":"Point"}
}