{
  "type": "Feature",
  "properties": {
    "gn:admin1_code":"35",
    "gn:asciiname":"Mian Mahalleh",
    "gn:country_code":"IR",
    "gn:dem":21,
    "gn:feature_class":"P",
    "gn:feature_code":"PPL",
    "gn:name":"M\u012b\u0101n Ma\u1e29alleh",
    "gn:population":0,
    "gn:timezone":"Asia/Tehran",
    "iso:country":"IR",
    "name:fas_x_preferred":[
        "\u0645\u06cc\u0627\u0646 \u0645\u062d\u0644\u0647"
    ],
    "name:fas_x_variant":[
        "M\u012b\u0101n Ma\u1e29alleh"
    ],
    "name:und_x_variant":[
        "\u0645\u064a\u0627\u0646 \u0645\u064e\u062d\u064e\u0644\u0650\u0651\u0647"
    ],
    "wof:name":"Mian Mahalleh",
    "wof:placetype":"locality"
},
  "geometry": {"coordinates":[52.56749,36.45824],"type":"Point"}
}