{
  "type": "Feature",
  "properties": {
    "gn:admin1_code":"23",
    "gn:asciiname":"Khan Amir",
    "gn:country_code":"IR",
    "gn:dem":1915,
    "gn:feature_class":"P",
    "gn:feature_code":"PPL",
    "gn:name":"Kh\u0101n Am\u012br",
    "gn:population":0,
    "gn:timezone":"Asia/Tehran",
    "iso:country":"IR",
    "name:fas_x_preferred":[
        "\u062e\u0627\u0646 \u0645\u064a\u0631"
    ],
    "name:fas_x_variant":[
        "\u062e\u0627\u0646 \u0627\u0645\u06cc\u0631",
        "Kh\u0101n M\u012br",
        "Kh\u0101n Am\u012br"
    ],
    "wof:name":"Khan Amir",
    "wof:placetype":"locality"
},
  "geometry": {"coordinates":[48.76341,33.6394],"type":"Point"}
}