{
  "type": "Feature",
  "properties": {
    "gn:admin1_code":"42.0",
    "gn:asciiname":"Mazra`eh-ye Shahid Kabutari",
    "gn:country_code":"IR",
    "gn:dem":929,
    "gn:feature_class":"P",
    "gn:feature_code":"PPLF",
    "gn:name":"Mazra\u2018eh-ye Shah\u012bd Kab\u016btar\u012b",
    "gn:population":0,
    "gn:timezone":"Asia/Tehran",
    "iso:country":"IR",
    "name:fas_x_preferred":[
        "\u0645\u0632\u0631\u0639\u0647 \u0634\u0647\u064a\u062f \u06a9\u0628\u0648\u062a\u0631\u06cc"
    ],
    "name:fas_x_variant":[
        "\u0645\u0634\u0627\u0639 \u0634\u0647\u064a\u062f \u06a9\u0628\u0648\u062a\u0631\u06cc"
    ],
    "name:und_x_variant":[
        "Mazra\u2018eh-ye Shah\u012bd Kab\u016btar\u012b",
        "Mosh\u0101\u2018-e Shah\u012bd Kab\u016btar\u012b"
    ],
    "wof:name":"Mazra`eh-ye Shahid Kabutari",
    "wof:placetype":"locality"
},
  "geometry": {"coordinates":[57.44201,33.7685],"type":"Point"}
}