{
  "type": "Feature",
  "properties": {
    "gn:admin1_code":"29.0",
    "gn:asciiname":"Ab Rigu",
    "gn:country_code":"IR",
    "gn:dem":1835,
    "gn:feature_class":"P",
    "gn:feature_code":"PPL",
    "gn:name":"\u0100b R\u012bg\u016b",
    "gn:population":0,
    "gn:timezone":"Asia/Tehran",
    "iso:country":"IR",
    "name:fas_x_preferred":[
        "\u0622\u0628 \u0631\u064a\u06af\u0648"
    ],
    "name:und_x_variant":[
        "\u0100b R\u012bg\u016b"
    ],
    "wof:name":"Ab Rigu",
    "wof:placetype":"locality"
},
  "geometry": {"coordinates":[56.71305,31.01079],"type":"Point"}
}