{
  "type": "Feature",
  "properties": {
    "gn:admin1_code":"1.0",
    "gn:asciiname":"Khalisan",
    "gn:country_code":"IR",
    "gn:dem":1159,
    "gn:feature_class":"P",
    "gn:feature_code":"PPL",
    "gn:name":"Khal\u012bs\u0101n",
    "gn:population":0,
    "gn:timezone":"Asia/Tehran",
    "iso:country":"IR",
    "name:fas_x_preferred":[
        "\u062e\u0644\u06cc\u0633\u0627\u0646"
    ],
    "name:fas_x_variant":[
        "Khal\u012bs\u0101n"
    ],
    "wof:name":"Khalisan",
    "wof:placetype":"locality"
},
  "geometry": {"coordinates":[45.4905,36.2963],"type":"Point"}
}