{
  "type": "Feature",
  "properties": {
    "gn:admin1_code":"15.0",
    "gn:asciiname":"Shabishi-ye Bozorg",
    "gn:country_code":"IR",
    "gn:dem":8,
    "gn:feature_class":"P",
    "gn:feature_code":"PPL",
    "gn:name":"Shab\u012bsh\u012b-ye Bozorg",
    "gn:population":0,
    "gn:timezone":"Asia/Tehran",
    "iso:country":"IR",
    "name:fas_x_preferred":[
        "\u0634\u0628\u06cc\u0634\u06cc \u0628\u0632\u0631\u06af"
    ],
    "name:und_x_variant":[
        "Shab\u012bsh\u012b-ye Bozorg"
    ],
    "wof:name":"Shabishi-ye Bozorg",
    "wof:placetype":"locality"
},
  "geometry": {"coordinates":[48.64178,30.69986],"type":"Point"}
}