{
  "type": "Feature",
  "properties": {
    "gn:admin1_code":"41",
    "gn:asciiname":"Tablow",
    "gn:country_code":"IR",
    "gn:dem":1737,
    "gn:feature_class":"P",
    "gn:feature_code":"PPLF",
    "gn:name":"Tablow",
    "gn:population":0,
    "gn:timezone":"Asia/Tehran",
    "iso:country":"IR",
    "name:fas_x_preferred":[
        "Tabl\u0101n"
    ],
    "name:fas_x_variant":[
        "\u062a\u0628\u0644\u0648",
        "\u062a\u0628\u0644\u0627\u0646"
    ],
    "name:ita_x_preferred":[
        "Tablan"
    ],
    "name:und_x_variant":[
        "Tahbalu"
    ],
    "wof:name":"Tablow",
    "wof:placetype":"locality"
},
  "geometry": {"coordinates":[58.85045,33.85758],"type":"Point"}
}