{
  "type": "Feature",
  "properties": {
    "gn:admin1_code":"13",
    "gn:asciiname":"Fuladi-ye `Olya",
    "gn:country_code":"IR",
    "gn:dem":1324,
    "gn:feature_class":"P",
    "gn:feature_code":"PPL",
    "gn:name":"F\u016bl\u0101d\u012b-ye \u2018Oly\u0101",
    "gn:population":0,
    "gn:timezone":"Asia/Tehran",
    "iso:country":"IR",
    "name:fas_x_preferred":[
        "\u0641\u0648\u0644\u0627\u062f\u06cc \u0639\u0644\u064a\u0627"
    ],
    "name:fas_x_variant":[
        "F\u016bl\u0101d\u012b-ye \u2018Oly\u0101"
    ],
    "name:und_x_variant":[
        "F\u016bl\u0101d\u012b-ye B\u0101l\u0101"
    ],
    "wof:name":"Fuladi-ye `Olya",
    "wof:placetype":"locality"
},
  "geometry": {"coordinates":[46.4005,34.7577],"type":"Point"}
}