{
  "type": "Feature",
  "properties": {
    "gn:admin1_code":"7.0",
    "gn:asciiname":"Mazra`eh",
    "gn:country_code":"IR",
    "gn:dem":547,
    "gn:feature_class":"P",
    "gn:feature_code":"PPL",
    "gn:name":"Mazra\u2018eh",
    "gn:population":0,
    "gn:timezone":"Asia/Tehran",
    "iso:country":"IR",
    "name:fas_x_preferred":[
        "Mazra\u2018eh"
    ],
    "wof:name":"Mazra`eh",
    "wof:placetype":"locality"
},
  "geometry": {"coordinates":[53.11333000000001,27.84528],"type":"Point"}
}