{
  "type": "Feature",
  "properties": {
    "gn:admin1_code":"26",
    "gn:asciiname":"Hamamak",
    "gn:country_code":"IR",
    "gn:dem":1168,
    "gn:feature_class":"P",
    "gn:feature_code":"PPL",
    "gn:name":"\u1e28am\u0101mak",
    "gn:population":0,
    "gn:timezone":"Asia/Tehran",
    "iso:country":"IR",
    "name:ceb_x_preferred":[
        "\u1e28am\u0101mak"
    ],
    "name:fas_x_preferred":[
        "\u062d\u0645\u0627\u0645\u06a9"
    ],
    "name:fas_x_variant":[
        "\u1e28am\u0101mak"
    ],
    "name:swe_x_preferred":[
        "\u1e28am\u0101mak"
    ],
    "wof:name":"Hamamak",
    "wof:placetype":"locality"
},
  "geometry": {"coordinates":[51.787,35.51448],"type":"Point"}
}