{
  "type": "Feature",
  "properties": {
    "gn:admin1_code":"1.0",
    "gn:asciiname":"Dowlehtu",
    "gn:country_code":"IR",
    "gn:dem":1375,
    "gn:feature_class":"P",
    "gn:feature_code":"PPL",
    "gn:name":"Dowleht\u016b",
    "gn:population":0,
    "gn:timezone":"Asia/Tehran",
    "iso:country":"IR",
    "name:fas_x_preferred":[
        "\u062f\u0648\u0644\u0647 \u062a\u0648"
    ],
    "name:fas_x_variant":[
        "Dowleht\u016b"
    ],
    "wof:name":"Dowlehtu",
    "wof:placetype":"locality"
},
  "geometry": {"coordinates":[45.4888,36.3648],"type":"Point"}
}