{
  "type": "Feature",
  "properties": {
    "gn:admin1_code":"1",
    "gn:asciiname":"Heydarlu-ye Beyglar",
    "gn:country_code":"IR",
    "gn:dem":1296,
    "gn:feature_class":"P",
    "gn:feature_code":"PPL",
    "gn:name":"\u1e28eydarl\u016b-ye Beyglar",
    "gn:population":0,
    "gn:timezone":"Asia/Tehran",
    "iso:country":"IR",
    "name:fas_x_preferred":[
        "\u062d\u0650\u064a\u062f\u064e\u0631\u0644\u0648\u06cc \u0628\u064a\u06af\u0644\u064e\u0631"
    ],
    "name:fas_x_variant":[
        "\u062d\u06cc\u062f\u0631\u0644\u0648 \u0628\u06cc\u06af\u0644\u0631",
        "\u1e28eydarl\u016b-ye B\u012bglar",
        "\u0628\u064a\u06af\u0644\u064e\u0631",
        "\u1e28eydarl\u016b-ye Beyglar"
    ],
    "name:und_x_variant":[
        "B\u012bglar"
    ],
    "wof:name":"Heydarlu-ye Beyglar",
    "wof:placetype":"locality"
},
  "geometry": {"coordinates":[45.0969,37.7226],"type":"Point"}
}