{
  "type": "Feature",
  "properties": {
    "gn:admin1_code":"29.0",
    "gn:asciiname":"Chah-e Jalal",
    "gn:country_code":"IR",
    "gn:dem":383,
    "gn:feature_class":"P",
    "gn:feature_code":"PPLL",
    "gn:name":"Ch\u0101h-e Jal\u0101l",
    "gn:population":0,
    "gn:timezone":"Asia/Tehran",
    "iso:country":"IR",
    "name:fas_x_preferred":[
        "\u0686\u0627\u0647 \u062c\u0644\u0627\u0644"
    ],
    "name:und_x_variant":[
        "Ch\u0101h-e Jal\u0101l"
    ],
    "wof:name":"Chah-e Jalal",
    "wof:placetype":"locality"
},
  "geometry": {"coordinates":[58.88566,27.71985],"type":"Point"}
}