{
  "type": "Feature",
  "properties": {
    "gn:admin1_code":"8",
    "gn:asciiname":"Ziaz Mahalleh",
    "gn:country_code":"IR",
    "gn:dem":6,
    "gn:feature_class":"P",
    "gn:feature_code":"PPL",
    "gn:name":"Z\u012b\u0101z Ma\u1e29alleh",
    "gn:population":0,
    "gn:timezone":"Asia/Tehran",
    "iso:country":"IR",
    "name:fas_x_preferred":[
        "Z\u012b\u0101r Ma\u1e29alleh"
    ],
    "name:fas_x_variant":[
        "\u0632\u06cc\u0627\u0632 \u0645\u062d\u0644\u0647",
        "\u0632\u06cc\u0627\u0632\u0645\u062d\u0644\u0647"
    ],
    "name:msa_x_preferred":[
        "Ziaz Mahalleh"
    ],
    "name:ukr_x_preferred":[
        "\u0417\u0456\u044f\u0437-\u041c\u0430\u0445\u0430\u043b\u0435"
    ],
    "name:und_x_variant":[
        "Z\u012b\u0101z Ma\u1e29alleh"
    ],
    "wof:name":"Ziaz Mahalleh",
    "wof:placetype":"locality"
},
  "geometry": {"coordinates":[50.31535,37.07508],"type":"Point"}
}