{
  "type": "Feature",
  "properties": {
    "gn:admin1_code":"7.0",
    "gn:asciiname":"Deh Gerdu",
    "gn:country_code":"IR",
    "gn:dem":1744,
    "gn:feature_class":"P",
    "gn:feature_code":"PPL",
    "gn:name":"Deh Gerd\u016b",
    "gn:population":0,
    "gn:timezone":"Asia/Tehran",
    "iso:country":"IR",
    "name:fas_x_preferred":[
        "Deh Gerd\u016b"
    ],
    "name:fas_x_variant":[
        "\u062f\u0647 \u06af\u0631\u062f\u0648"
    ],
    "wof:name":"Deh Gerdu",
    "wof:placetype":"locality"
},
  "geometry": {"coordinates":[51.664,30.35138],"type":"Point"}
}