{
  "type": "Feature",
  "properties": {
    "gn:admin1_code":"23",
    "gn:asciiname":"Gallehvand",
    "gn:country_code":"IR",
    "gn:dem":2089,
    "gn:feature_class":"P",
    "gn:feature_code":"PPL",
    "gn:name":"Gallehvand",
    "gn:population":0,
    "gn:timezone":"Asia/Tehran",
    "iso:country":"IR",
    "name:ara_x_preferred":[
        "\u063a\u0644\u0629 \u0648\u0646\u062f"
    ],
    "name:ceb_x_preferred":[
        "Gallehvand"
    ],
    "name:fas_x_preferred":[
        "\u06af\u064e\u0644\u0650\u0647\u0628\u064e\u0646\u062f"
    ],
    "name:fas_x_variant":[
        "\u06af\u064e\u0644\u0650\u0651\u0647 \u0628\u064e\u0646\u062f",
        "\u06af\u0644\u0647 \u0648\u0646\u062f",
        "\u06af\u0644\u0627\u0648\u0646\u062f"
    ],
    "name:swe_x_preferred":[
        "Gallehvand"
    ],
    "name:und_x_variant":[
        "Galleh Band",
        "Galehband",
        "Gal\u0101vand"
    ],
    "wof:name":"Gallehvand",
    "wof:placetype":"locality"
},
  "geometry": {"coordinates":[49.70391,33.16189],"type":"Point"}
}