{
  "type": "Feature",
  "properties": {
    "gn:admin1_code":"29",
    "gn:asciiname":"Boluk-e Pa'in",
    "gn:country_code":"IR",
    "gn:dem":624,
    "gn:feature_class":"P",
    "gn:feature_code":"PPL",
    "gn:name":"Bol\u016bk-e P\u0101\u2019\u012bn",
    "gn:population":0,
    "gn:timezone":"Asia/Tehran",
    "iso:country":"IR",
    "name:fas_x_preferred":[
        "Bol\u016bk-e P\u0101\u2019\u012bn"
    ],
    "name:und_x_variant":[
        "Bol\u016bk P\u0101\u2019\u012bn",
        "Bolook"
    ],
    "wof:name":"Boluk-e Pa'in",
    "wof:placetype":"locality"
},
  "geometry": {"coordinates":[57.54556,28.22306],"type":"Point"}
}