{
  "type": "Feature",
  "properties": {
    "gn:admin1_code":"5",
    "gn:asciiname":"Zar Tol",
    "gn:country_code":"IR",
    "gn:dem":1769,
    "gn:feature_class":"P",
    "gn:feature_code":"PPL",
    "gn:name":"Zar Tol",
    "gn:population":0,
    "gn:timezone":"Asia/Tehran",
    "iso:country":"IR",
    "name:fas_x_preferred":[
        "\u0632\u064e\u0631 \u062a\u064f\u0644"
    ],
    "wof:name":"Zar Tol",
    "wof:placetype":"locality"
},
  "geometry": {"coordinates":[51.56139,30.665],"type":"Point"}
}