{
  "type": "Feature",
  "properties": {
    "gn:admin1_code":"29",
    "gn:asciiname":"Kapari Noqsan",
    "gn:country_code":"IR",
    "gn:dem":390,
    "gn:feature_class":"P",
    "gn:feature_code":"PPLF",
    "gn:name":"Kapar\u012b Noq\u015f\u0101n",
    "gn:population":0,
    "gn:timezone":"Asia/Tehran",
    "iso:country":"IR",
    "name:fas_x_preferred":[
        "\u0646\u0642\u0635\u0627\u0646 \u06a9\u067e\u0631\u06cc"
    ],
    "name:fas_x_variant":[
        "Noq\u015f\u0101n Kapar\u012b",
        "\u06a9\u067e\u0631\u06cc \u0646\u0642\u0635\u0627\u0646"
    ],
    "name:und_x_variant":[
        "Kapar\u012b Noq\u015f\u0101n"
    ],
    "wof:name":"Kapari Noqsan",
    "wof:placetype":"locality"
},
  "geometry": {"coordinates":[58.55085,27.78387],"type":"Point"}
}