{
  "type": "Feature",
  "properties": {
    "gn:admin1_code":"28.0",
    "gn:asciiname":"Cham Rud",
    "gn:country_code":"IR",
    "gn:dem":1628,
    "gn:feature_class":"P",
    "gn:feature_code":"PPL",
    "gn:name":"Cham R\u016bd",
    "gn:population":0,
    "gn:timezone":"Asia/Tehran",
    "iso:country":"IR",
    "name:fas_x_preferred":[
        "Cham R\u016bd"
    ],
    "name:fas_x_variant":[
        "\u0686\u0645 \u0631\u0648\u062f"
    ],
    "name:und_x_variant":[
        "\u0686\u0645 \u0631\u0648\u062f",
        "Cham"
    ],
    "wof:name":"Cham Rud",
    "wof:placetype":"locality"
},
  "geometry": {"coordinates":[51.52538,32.47424],"type":"Point"}
}