{
  "type": "Feature",
  "properties": {
    "gn:admin1_code":"36",
    "gn:asciiname":"Qol`ali",
    "gn:country_code":"IR",
    "gn:dem":1863,
    "gn:feature_class":"P",
    "gn:feature_code":"PPL",
    "gn:name":"Qol\u2018al\u012b",
    "gn:population":0,
    "gn:timezone":"Asia/Tehran",
    "iso:country":"IR",
    "name:azb_x_preferred":[
        "\u06af\u0648\u0627\u0644\u06cc"
    ],
    "name:ceb_x_preferred":[
        "Gow \u0100l\u012b"
    ],
    "name:fas_x_preferred":[
        "\u0642\u0644\u0639\u0644\u06cc"
    ],
    "name:fas_x_variant":[
        "Qol\u2018al\u012b",
        "\u06af\u0648\u0627\u0644\u06cc"
    ],
    "name:swe_x_preferred":[
        "Gow \u0100l\u012b"
    ],
    "name:und_x_variant":[
        "Kul\u0101lu",
        "Gholali",
        "Qowl \u2018Al\u012b",
        "Gol\u2018al\u012b",
        "Q\u016bl \u2018Al\u012b"
    ],
    "wof:name":"Qol`ali",
    "wof:placetype":"locality"
},
  "geometry": {"coordinates":[48.54775,35.94085],"type":"Point"}
}