{
  "type": "Feature",
  "properties": {
    "gn:admin1_code":"10",
    "gn:asciiname":"Gach Kuban",
    "gn:country_code":"IR",
    "gn:dem":1041,
    "gn:feature_class":"P",
    "gn:feature_code":"PPL",
    "gn:name":"Gach K\u016bb\u0101n",
    "gn:population":0,
    "gn:timezone":"Asia/Tehran",
    "iso:country":"IR",
    "name:ara_x_preferred":[
        "\u063a\u062a\u0634 \u0643\u0648\u0628\u0627\u0646"
    ],
    "name:ceb_x_preferred":[
        "Gachk\u016bp\u0101n"
    ],
    "name:fas_x_preferred":[
        "\u06af\u0686 \u06a9\u0648\u0628\u0627\u0646"
    ],
    "name:fas_x_variant":[
        "\u06af\u0686\u06a9\u0648\u067e\u0627\u0646",
        "Gach K\u016bb\u0101n",
        "Gachk\u016bp\u0101n"
    ],
    "name:msa_x_preferred":[
        "Gach Kuban"
    ],
    "name:swe_x_preferred":[
        "Gachk\u016bp\u0101n"
    ],
    "wof:name":"Gach Kuban",
    "wof:placetype":"locality"
},
  "geometry": {"coordinates":[47.10133,33.29611],"type":"Point"}
}