{
  "type": "Feature",
  "properties": {
    "gn:admin1_code":"37",
    "gn:asciiname":"Hajji Qushan",
    "gn:country_code":"IR",
    "gn:dem":105,
    "gn:feature_class":"P",
    "gn:feature_code":"PPL",
    "gn:name":"\u1e28\u0101jj\u012b Q\u016bsh\u0101n",
    "gn:population":0,
    "gn:timezone":"Asia/Tehran",
    "iso:country":"IR",
    "name:ara_x_preferred":[
        "\u062d\u0627\u062c\u064a\u0642\u0648\u0634\u0627\u0646"
    ],
    "name:fas_x_preferred":[
        "\u1e28\u0101jj\u012b Q\u016bshan"
    ],
    "name:fas_x_variant":[
        "H\u0101jj\u012b Q\u016bshan",
        "\u1e28\u0101jj\u012b Q\u016bsh\u0101nd\u0101z",
        "\u062d\u0627\u062c\u06cc \u0642\u0648\u0634\u0646",
        "\u062d\u0627\u062c\u06cc \u0642\u0648\u0634\u0627\u0646",
        "\u062d\u0627\u062c\u06cc\u200c\u0642\u0648\u0634\u0627\u0646"
    ],
    "name:msa_x_preferred":[
        "Hajji Qushan"
    ],
    "name:und_x_variant":[
        "\u1e28\u0101j\u012b Q\u016bsh\u0101n Der\u0101z",
        "\u1e28\u0101jj\u012b Q\u016bsh",
        "H\u0101j\u012b Q\u016bshan",
        "\u062d\u0627\u062c\u06cc \u0642\u0648\u0634\u0646",
        "\u1e28\u0101jj\u012b Q\u016bsh\u0101n"
    ],
    "wof:name":"Hajji Qushan",
    "wof:placetype":"locality"
},
  "geometry": {"coordinates":[55.36133,37.42778],"type":"Point"}
}