{
  "type": "Feature",
  "properties": {
    "gn:admin1_code":"35.0",
    "gn:asciiname":"Makarud",
    "gn:country_code":"IR",
    "gn:dem":769,
    "gn:feature_class":"P",
    "gn:feature_code":"PPL",
    "gn:name":"Mak\u0101r\u016bd",
    "gn:population":0,
    "gn:timezone":"Asia/Tehran",
    "iso:country":"IR",
    "name:fas_x_preferred":[
        "\u0645\u06a9\u0627 \u0631\u0648\u062f"
    ],
    "name:fas_x_variant":[
        "Mak\u0101 R\u016bd",
        "\u0645\u06a9\u0627\u0631\u0648\u062f"
    ],
    "name:und_x_variant":[
        "Mak\u0101r\u016bd"
    ],
    "wof:name":"Makarud",
    "wof:placetype":"locality"
},
  "geometry": {"coordinates":[51.25947,36.34791],"type":"Point"}
}