{
  "type": "Feature",
  "properties": {
    "gn:admin1_code":"43",
    "gn:asciiname":"Qalandar Beyk",
    "gn:country_code":"IR",
    "gn:dem":1056,
    "gn:feature_class":"P",
    "gn:feature_code":"PPL",
    "gn:name":"Qalandar Beyk",
    "gn:population":0,
    "gn:timezone":"Asia/Tehran",
    "iso:country":"IR",
    "name:fas_x_preferred":[
        "\u0642\u0644\u0646\u062f\u0631 \u0628\u06cc\u06a9"
    ],
    "name:und_x_variant":[
        "\u0642\u0644\u0646\u062f\u0631 \u0628\u06cc\u06a9"
    ],
    "wof:name":"Qalandar Beyk",
    "wof:placetype":"locality"
},
  "geometry": {"coordinates":[57.39155,37.47977],"type":"Point"}
}