{
  "type": "Feature",
  "properties": {
    "gn:admin1_code":"40",
    "gn:asciiname":"Ashkuh",
    "gn:country_code":"IR",
    "gn:dem":1673,
    "gn:feature_class":"P",
    "gn:feature_code":"PPL",
    "gn:name":"Ashk\u016bh",
    "gn:population":0,
    "gn:timezone":"Asia/Tehran",
    "iso:country":"IR",
    "name:fas_x_preferred":[
        "\u0627\u064e\u0634\u0643\u0648\u0647"
    ],
    "name:fas_x_variant":[
        "Ashk\u016bh",
        "\u0627\u0634\u06a9\u0648\u0647"
    ],
    "wof:name":"Ashkuh",
    "wof:placetype":"locality"
},
  "geometry": {"coordinates":[53.91667,31.88333],"type":"Point"}
}