{
  "type": "Feature",
  "properties": {
    "gn:admin1_code":"4.0",
    "gn:asciiname":"Deh-e Gholam",
    "gn:country_code":"IR",
    "gn:dem":481,
    "gn:feature_class":"P",
    "gn:feature_code":"PPL",
    "gn:name":"Deh-e Gholam",
    "gn:population":0,
    "gn:timezone":"Asia/Tehran",
    "iso:country":"IR",
    "wof:name":"Deh-e Gholam",
    "wof:placetype":"locality"
},
  "geometry": {"coordinates":[61.41083,31.12056],"type":"Point"}
}