{
  "type": "Feature",
  "properties": {
    "gn:admin1_code":"10",
    "gn:asciiname":"Shahid Raja'i",
    "gn:country_code":"IR",
    "gn:dem":401,
    "gn:feature_class":"P",
    "gn:feature_code":"PPL",
    "gn:name":"S\u0304hah\u012bd Raj\u0101\u2019\u012b",
    "gn:population":0,
    "gn:timezone":"Asia/Tehran",
    "iso:country":"IR",
    "name:fas_x_preferred":[
        "\u0634\u0647\u06cc\u062f \u0631\u062c\u0627\u06cc\u06cc"
    ],
    "name:und_x_variant":[
        "S\u0304hah\u012bd Raj\u0101\u2019\u012b"
    ],
    "wof:name":"Shahid Raja'i",
    "wof:placetype":"locality"
},
  "geometry": {"coordinates":[47.81175,32.96285],"type":"Point"}
}