{
  "type": "Feature",
  "properties": {
    "gn:admin1_code":"29",
    "gn:asciiname":"Menukin",
    "gn:cc2":"IR",
    "gn:country_code":"IR",
    "gn:dem":2517,
    "gn:feature_class":"P",
    "gn:feature_code":"PPL",
    "gn:name":"Men\u016bk\u012bn",
    "gn:population":0,
    "gn:timezone":"Asia/Tehran",
    "iso:country":"IR",
    "name:fas_x_preferred":[
        "Men\u016bk\u012bn"
    ],
    "name:fas_x_variant":[
        "\u0645\u0646\u0648\u06a9\u06cc\u0646"
    ],
    "name:und_x_variant":[
        "Nanook",
        "Man\u016bk\u012b",
        "N\u0101nu",
        "Nan\u016bk"
    ],
    "wof:name":"Menukin",
    "wof:placetype":"locality"
},
  "geometry": {"coordinates":[56.86194,29.32028],"type":"Point"}
}