{
  "type": "Feature",
  "properties": {
    "gn:admin1_code":"29",
    "gn:asciiname":"Deh Sheykh",
    "gn:country_code":"IR",
    "gn:dem":681,
    "gn:feature_class":"P",
    "gn:feature_code":"PPL",
    "gn:name":"Deh Sheykh",
    "gn:population":0,
    "gn:timezone":"Asia/Tehran",
    "iso:country":"IR",
    "name:fas_x_preferred":[
        "\u062f\u0647 \u0634\u06cc\u062e"
    ],
    "name:und_x_variant":[
        "Deh-i-Sha\u012bkh",
        "Deh-e Sheykh",
        "Deh Sheykh"
    ],
    "wof:name":"Deh Sheykh",
    "wof:placetype":"locality"
},
  "geometry": {"coordinates":[57.8121,28.6725],"type":"Point"}
}