{
  "type": "Feature",
  "properties": {
    "gn:admin1_code":"22.0",
    "gn:asciiname":"Girqalat",
    "gn:country_code":"IR",
    "gn:dem":711,
    "gn:feature_class":"P",
    "gn:feature_code":"PPL",
    "gn:name":"G\u012brqal\u0101t",
    "gn:population":0,
    "gn:timezone":"Asia/Tehran",
    "iso:country":"IR",
    "name:fas_x_preferred":[
        "\u06af\u06cc\u0631\u0642\u0644\u0627\u062a"
    ],
    "name:msa_x_preferred":[
        "Girqalat"
    ],
    "name:und_x_variant":[
        "G\u012brqal\u0101t"
    ],
    "wof:name":"Girqalat",
    "wof:placetype":"locality"
},
  "geometry": {"coordinates":[52.27105,27.82971],"type":"Point"}
}