{
  "type": "Feature",
  "properties": {
    "gn:admin1_code":"35.0",
    "gn:asciiname":"Sar Asbi",
    "gn:country_code":"IR",
    "gn:dem":992,
    "gn:feature_class":"P",
    "gn:feature_code":"PPL",
    "gn:name":"Sar Asb\u012b",
    "gn:population":0,
    "gn:timezone":"Asia/Tehran",
    "iso:country":"IR",
    "name:fas_x_preferred":[
        "Sar Asb\u012b"
    ],
    "name:fas_x_variant":[
        "\u0633\u0631 \u0627\u0633\u0628\u06cc",
        "\u0633\u0631 \u0627\u0633\u0628\u06cc \u0644\u0627\u062a"
    ],
    "name:und_x_variant":[
        "Sar Asb\u012b L\u0101t"
    ],
    "wof:name":"Sar Asbi",
    "wof:placetype":"locality"
},
  "geometry": {"coordinates":[50.83466,36.58644],"type":"Point"}
}