{
  "type": "Feature",
  "properties": {
    "gn:admin1_code":"37",
    "gn:asciiname":"Hivehchi-ye Markazi",
    "gn:country_code":"IR",
    "gn:dem":48,
    "gn:feature_class":"P",
    "gn:feature_code":"PPL",
    "gn:name":"H\u012bvehch\u012b-ye Markaz\u012b",
    "gn:population":0,
    "gn:timezone":"Asia/Tehran",
    "iso:country":"IR",
    "name:fas_x_preferred":[
        "H\u012bvehch\u012b"
    ],
    "name:fas_x_variant":[
        "\u0647\u06cc\u0648\u0647 \u0686\u06cc \u0645\u0631\u06a9\u0632\u06cc"
    ],
    "name:und_x_variant":[
        "H\u012bvehch\u012b-ye Markaz\u012b"
    ],
    "wof:name":"Hivehchi-ye Markazi",
    "wof:placetype":"locality"
},
  "geometry": {"coordinates":[55.06437,37.1599],"type":"Point"}
}