{
  "type": "Feature",
  "properties": {
    "gn:admin1_code":"23",
    "gn:asciiname":"Bardeh Si",
    "gn:cc2":"IR",
    "gn:country_code":"IR",
    "gn:dem":1674,
    "gn:feature_class":"P",
    "gn:feature_code":"PPL",
    "gn:name":"Bardeh S\u012b",
    "gn:population":0,
    "gn:timezone":"Asia/Tehran",
    "iso:country":"IR",
    "name:fas_x_preferred":[
        "Bardeh S\u012b"
    ],
    "name:und_x_variant":[
        "Bard-e S\u012b"
    ],
    "wof:name":"Bardeh Si",
    "wof:placetype":"locality"
},
  "geometry": {"coordinates":[49.19278,33.08389],"type":"Point"}
}