{
  "type": "Feature",
  "properties": {
    "gn:admin1_code":"42.0",
    "gn:asciiname":"Razdab",
    "gn:country_code":"IR",
    "gn:dem":1420,
    "gn:feature_class":"P",
    "gn:feature_code":"PPL",
    "gn:name":"Razd\u0101b",
    "gn:population":0,
    "gn:timezone":"Asia/Tehran",
    "iso:country":"IR",
    "name:fas_x_preferred":[
        "\u0631\u0632\u062f\u0622\u0628"
    ],
    "name:fas_x_variant":[
        "Razd\u0101b",
        "Rezd\u0101b",
        "\u0631\u0632\u062f\u0627\u0628"
    ],
    "wof:name":"Razdab",
    "wof:placetype":"locality"
},
  "geometry": {"coordinates":[60.12081,34.81264],"type":"Point"}
}