{
  "type": "Feature",
  "properties": {
    "gn:admin1_code":"29",
    "gn:asciiname":"Gohard",
    "gn:country_code":"IR",
    "gn:dem":2162,
    "gn:feature_class":"P",
    "gn:feature_code":"PPL",
    "gn:name":"Gohard",
    "gn:population":0,
    "gn:timezone":"Asia/Tehran",
    "iso:country":"IR",
    "name:epo_x_preferred":[
        "Gohord"
    ],
    "name:fas_x_preferred":[
        "\u06af\u0647\u0631\u062f"
    ],
    "name:und_x_variant":[
        "Kahr\u016b",
        "Gohort",
        "Gohard"
    ],
    "wof:name":"Gohard",
    "wof:placetype":"locality"
},
  "geometry": {"coordinates":[56.2146,29.3987],"type":"Point"}
}