{
  "type": "Feature",
  "properties": {
    "gn:admin1_code":"42",
    "gn:asciiname":"Esfandian",
    "gn:country_code":"IR",
    "gn:dem":997,
    "gn:feature_class":"P",
    "gn:feature_code":"PPL",
    "gn:name":"Esfand\u012b\u0101n",
    "gn:population":0,
    "gn:timezone":"Asia/Tehran",
    "iso:country":"IR",
    "name:ceb_x_preferred":[
        "Esfand\u012b\u0101n"
    ],
    "name:fas_x_preferred":[
        "\u0627\u0633\u0641\u0646\u062f\u06cc\u0627\u0646"
    ],
    "name:fas_x_variant":[
        "Esfand\u012b\u0101n"
    ],
    "name:swe_x_preferred":[
        "Esfand\u012b\u0101n"
    ],
    "name:und_x_variant":[
        "Esfandey\u0101n"
    ],
    "wof:name":"Esfandian",
    "wof:placetype":"locality"
},
  "geometry": {"coordinates":[59.527,36.4745],"type":"Point"}
}