{
  "type": "Feature",
  "properties": {
    "gn:admin1_code":"13",
    "gn:asciiname":"Deh Gol",
    "gn:country_code":"IR",
    "gn:dem":1321,
    "gn:feature_class":"P",
    "gn:feature_code":"PPL",
    "gn:name":"Deh Gol",
    "gn:population":0,
    "gn:timezone":"Asia/Tehran",
    "iso:country":"IR",
    "name:fas_x_preferred":[
        "\u062f\u0647 \u06af\u0644"
    ],
    "wof:name":"Deh Gol",
    "wof:placetype":"locality"
},
  "geometry": {"coordinates":[46.9417,34.6121],"type":"Point"}
}