{
  "type": "Feature",
  "properties": {
    "gn:admin1_code":"23",
    "gn:asciiname":"Deh-e Now-e Pa'in",
    "gn:country_code":"IR",
    "gn:dem":1761,
    "gn:feature_class":"P",
    "gn:feature_code":"PPL",
    "gn:name":"Deh-e Now-e P\u0101\u2019\u012bn",
    "gn:population":0,
    "gn:timezone":"Asia/Tehran",
    "iso:country":"IR",
    "name:ceb_x_preferred":[
        "Deh-e Now-e P\u0101'\u012bn"
    ],
    "name:fas_x_preferred":[
        "\u0627\u064a\u0648\u0627\u0646\u06cc"
    ],
    "name:fas_x_variant":[
        "\u062d\u0628\u0648\u0627\u0646\u06cc",
        "\u1e28eyv\u0101n\u012b",
        "Eyv\u0101n\u012b",
        "Haiw\u0101ni",
        "\u1e28abv\u0101n\u012b",
        "\u062f\u0647 \u0646\u0648 \u067e\u0627\u0626\u06cc\u0646",
        "\u0627\u06cc\u0648\u0627\u0646\u06cc"
    ],
    "name:swe_x_preferred":[
        "Deh-e Now-e P\u0101'\u012bn"
    ],
    "name:und_x_variant":[
        "Deh-e Now-e P\u0101\u2019\u012bn"
    ],
    "wof:name":"Deh-e Now-e Pa'in",
    "wof:placetype":"locality"
},
  "geometry": {"coordinates":[48.77733,33.51327],"type":"Point"}
}