{
  "type": "Feature",
  "properties": {
    "gn:admin1_code":"23",
    "gn:asciiname":"Khasiabad",
    "gn:country_code":"IR",
    "gn:dem":1091,
    "gn:feature_class":"P",
    "gn:feature_code":"PPL",
    "gn:name":"Kh\u0101s\u012b\u0101b\u0101d",
    "gn:population":0,
    "gn:timezone":"Asia/Tehran",
    "iso:country":"IR",
    "name:fas_x_preferred":[
        "\u062e\u0627\u0635\u06cc \u0622\u0628\u0627\u062f"
    ],
    "name:fas_x_variant":[
        "Kh\u0101\u015f\u012b\u0101b\u0101d",
        "\u062e\u0627\u0633\u06cc \u0622\u0628\u0627\u062f",
        "\u0646\u0633\u0627\u0631 \u062e\u0627\u0635\u06cc \u0622\u0628\u0627\u062f"
    ],
    "name:und_x_variant":[
        "Kh\u0101s\u012b\u0101b\u0101d",
        "Nes\u0101r Kh\u0101\u015f\u012b\u0101b\u0101d"
    ],
    "wof:name":"Khasiabad",
    "wof:placetype":"locality"
},
  "geometry": {"coordinates":[47.41027,33.30907],"type":"Point"}
}