{
  "type": "Feature",
  "properties": {
    "gn:admin1_code":"41.0",
    "gn:asciiname":"Chenaran",
    "gn:country_code":"IR",
    "gn:dem":1170,
    "gn:feature_class":"P",
    "gn:feature_code":"PPL",
    "gn:name":"Chen\u0101r\u0101n",
    "gn:population":0,
    "gn:timezone":"Asia/Tehran",
    "iso:country":"IR",
    "name:fas_x_preferred":[
        "\u0686\u0646\u0627\u0631\u0627\u0646"
    ],
    "name:und_x_variant":[
        "Chen\u0101r\u0101n"
    ],
    "wof:name":"Chenaran",
    "wof:placetype":"locality"
},
  "geometry": {"coordinates":[59.96851,33.64579000000001],"type":"Point"}
}