{
  "type": "Feature",
  "properties": {
    "gn:admin1_code":"43",
    "gn:asciiname":"Joghdi",
    "gn:country_code":"IR",
    "gn:dem":1308,
    "gn:feature_class":"P",
    "gn:feature_code":"PPL",
    "gn:name":"Joghd\u012b",
    "gn:population":0,
    "gn:timezone":"Asia/Tehran",
    "iso:country":"IR",
    "name:ceb_x_preferred":[
        "Joghd\u012b"
    ],
    "name:fas_x_preferred":[
        "Joghd\u012b"
    ],
    "name:fas_x_variant":[
        "\u062c\u063a\u062f\u06cc"
    ],
    "name:swe_x_preferred":[
        "Joghd\u012b"
    ],
    "name:und_x_variant":[
        "Joghdt"
    ],
    "wof:name":"Joghdi",
    "wof:placetype":"locality"
},
  "geometry": {"coordinates":[56.81296999999999,37.34963],"type":"Point"}
}