{
  "type": "Feature",
  "properties": {
    "gn:admin1_code":"1",
    "gn:asciiname":"Pahlavan",
    "gn:country_code":"IR",
    "gn:dem":1739,
    "gn:feature_class":"P",
    "gn:feature_code":"PPL",
    "gn:name":"Pahlav\u0101n",
    "gn:population":0,
    "gn:timezone":"Asia/Tehran",
    "iso:country":"IR",
    "name:aze_x_preferred":[
        "P\u0259hl\u0259van"
    ],
    "name:fas_x_preferred":[
        "\u067e\u0647\u0644\u0648\u0627\u0646"
    ],
    "name:fas_x_variant":[
        "Pahlav\u0101n",
        "\u067e\u0647\u0644\u0648\u0627\u0646 \u0645\u0632\u0631\u0639\u0647"
    ],
    "name:und_x_variant":[
        "Pahlw\u0101n",
        "Pahalw\u0101n",
        "Pahlav\u0101n-e Mazra\u2018eh"
    ],
    "wof:name":"Pahlavan",
    "wof:placetype":"locality"
},
  "geometry": {"coordinates":[47.07011,36.44762],"type":"Point"}
}