{
  "type": "Feature",
  "properties": {
    "gn:admin1_code":"36",
    "gn:asciiname":"Zaker",
    "gn:country_code":"IR",
    "gn:dem":1898,
    "gn:feature_class":"P",
    "gn:feature_code":"PPL",
    "gn:name":"Z\u0101ker",
    "gn:population":0,
    "gn:timezone":"Asia/Tehran",
    "iso:country":"IR",
    "name:azb_x_preferred":[
        "\u0630\u0627\u06a9\u0631"
    ],
    "name:fas_x_preferred":[
        "\u0630\u0627\u0643\u0631"
    ],
    "name:fas_x_variant":[
        "Z\u0304\u0101ker",
        "\u0632\u0627\u06a9\u0631",
        "\u0630\u0627\u06a9\u0631"
    ],
    "name:und_x_variant":[
        "Zakir",
        "Z\u0101ker"
    ],
    "wof:name":"Zaker",
    "wof:placetype":"locality"
},
  "geometry": {"coordinates":[48.71864,36.64525],"type":"Point"}
}