{
  "type": "Feature",
  "properties": {
    "gn:admin1_code":"41.0",
    "gn:asciiname":"Qa'emabad",
    "gn:country_code":"IR",
    "gn:dem":1474,
    "gn:feature_class":"P",
    "gn:feature_code":"PPL",
    "gn:name":"Q\u0101\u2019em\u0101b\u0101d",
    "gn:population":0,
    "gn:timezone":"Asia/Tehran",
    "iso:country":"IR",
    "name:fas_x_preferred":[
        "\u0642\u0627\u0626\u0645 \u0622\u0628\u0627\u062f"
    ],
    "name:fas_x_variant":[
        "Ebr\u0101h\u012bm\u0101b\u0101d",
        "Q\u0101\u2019em\u0101b\u0101d"
    ],
    "name:und_x_variant":[
        "Gha\u2019em Abad",
        "Q\u0101imabad",
        "Q\u0101yem\u0101b\u0101d"
    ],
    "wof:name":"Qa'emabad",
    "wof:placetype":"locality"
},
  "geometry": {"coordinates":[60.07518,31.73969],"type":"Point"}
}