{
  "type": "Feature",
  "properties": {
    "gn:admin1_code":"7",
    "gn:asciiname":"Gardaneh Chah Now",
    "gn:country_code":"IR",
    "gn:dem":1768,
    "gn:feature_class":"P",
    "gn:feature_code":"PPL",
    "gn:name":"Gardaneh Ch\u0101h Now",
    "gn:population":0,
    "gn:timezone":"Asia/Tehran",
    "iso:country":"IR",
    "name:fas_x_preferred":[
        "\u0686\u0627\u0647 \u0646\u0648 \u062a\u0639\u0648\u06cc\u0642"
    ],
    "name:fas_x_variant":[
        "\u06af\u0631\u062f\u0646\u0647 \u0686\u0627\u0647 \u0646\u0648",
        "\u0686\u0627\u0647 \u0646\u0648"
    ],
    "name:und_x_variant":[
        "Ch\u0101h Now-e Ta\u2018v\u012bq",
        "Gardaneh Ch\u0101h Now",
        "Ch\u0101h Now"
    ],
    "wof:name":"Gardaneh Chah Now",
    "wof:placetype":"locality"
},
  "geometry": {"coordinates":[55.2641,28.5897],"type":"Point"}
}