{
  "type": "Feature",
  "properties": {
    "gn:admin1_code":"32",
    "gn:asciiname":"Shur Daraq-e Pa'in",
    "gn:country_code":"IR",
    "gn:dem":800,
    "gn:feature_class":"P",
    "gn:feature_code":"PPL",
    "gn:name":"Sh\u016br Daraq-e P\u0101\u2019\u012bn",
    "gn:population":0,
    "gn:timezone":"Asia/Tehran",
    "iso:country":"IR",
    "name:ara_x_preferred":[
        "\u0634\u0648\u0631 \u062f\u0631\u0627\u0642 \u0634\u0648\u0631 \u062f\u0631\u0627\u0642 \u0633\u0641\u0644\u064a"
    ],
    "name:azb_x_preferred":[
        "\u0622\u0634\u0627\u063a\u0627 \u0634\u0648\u0631\u062f\u0631\u0647"
    ],
    "name:ceb_x_preferred":[
        "Sh\u016br Daraq-e P\u0101'\u012bn"
    ],
    "name:fas_x_preferred":[
        "\u0634\u0648\u0631 \u062f\u064e\u0631\u064e\u0642\u0650 \u0633\u064f\u0641\u0644\u064e\u0649"
    ],
    "name:fas_x_variant":[
        "\u0634\u0648\u0631 \u062f\u064e\u0631\u064e\u0642",
        "\u0634\u0648\u0631 \u062f\u0631\u0642 \u067e\u0627\u0626\u06cc\u0646",
        "Sh\u016br Daraq-e Sofl\u00e1",
        "\u0634\u0648\u0631\u062f\u0631\u0642 \u0633\u0641\u0644\u06cc"
    ],
    "name:msa_x_preferred":[
        "Shur Daraq-e Sofla"
    ],
    "name:swe_x_preferred":[
        "Sh\u016br Daraq-e P\u0101'\u012bn"
    ],
    "name:und_x_variant":[
        "Sh\u016br Daraq",
        "Sh\u016br Daraq-e P\u0101\u2019\u012bn"
    ],
    "wof:name":"Shur Daraq-e Pa'in",
    "wof:placetype":"locality"
},
  "geometry": {"coordinates":[47.8158,39.0447],"type":"Point"}
}