{
  "type": "Feature",
  "properties": {
    "gn:admin1_code":"42",
    "gn:asciiname":"Ab Barg",
    "gn:country_code":"IR",
    "gn:dem":1352,
    "gn:feature_class":"P",
    "gn:feature_code":"PPL",
    "gn:name":"\u0100b Barg",
    "gn:population":0,
    "gn:timezone":"Asia/Tehran",
    "iso:country":"IR",
    "name:fas_x_preferred":[
        "\u0100b Barg"
    ],
    "name:fas_x_variant":[
        "\u0622\u0628 \u0628\u0631\u06af"
    ],
    "name:urd_x_preferred":[
        "\u0622\u0628 \u0628\u0631\u06af"
    ],
    "wof:name":"Ab Barg",
    "wof:placetype":"locality"
},
  "geometry": {"coordinates":[58.56494,37.11433],"type":"Point"}
}