{
  "type": "Feature",
  "properties": {
    "gn:admin1_code":"0",
    "gn:asciiname":"Chah Muzi",
    "gn:country_code":"IR",
    "gn:dem":354,
    "gn:feature_class":"P",
    "gn:feature_code":"PPL",
    "gn:name":"Ch\u0101h M\u016bz\u012b",
    "gn:population":0,
    "gn:timezone":"Asia/Tehran",
    "iso:country":"IR",
    "name:fas_x_preferred":[
        "\u0686\u0627\u0647 \u0645\u0648\u0632\u06cc"
    ],
    "name:fas_x_variant":[
        "Ch\u0101h M\u016bz\u012b"
    ],
    "wof:name":"Chah Muzi",
    "wof:placetype":"locality"
},
  "geometry": {"coordinates":[57.5903,27.4317],"type":"Point"}
}