{
  "type": "Feature",
  "properties": {
    "gn:admin1_code":"33",
    "gn:asciiname":"Dash Bolagh",
    "gn:country_code":"IR",
    "gn:dem":1774,
    "gn:feature_class":"P",
    "gn:feature_code":"PPL",
    "gn:name":"D\u0101sh Bol\u0101gh",
    "gn:population":0,
    "gn:timezone":"Asia/Tehran",
    "iso:country":"IR",
    "name:fas_x_preferred":[
        "\u062f\u0627\u0634 \u0628\u0644\u0627\u063a"
    ],
    "name:fas_x_variant":[
        "D\u0101sh Bol\u0101gh"
    ],
    "wof:name":"Dash Bolagh",
    "wof:placetype":"locality"
},
  "geometry": {"coordinates":[47.203,37.4696],"type":"Point"}
}