{
  "type": "Feature",
  "properties": {
    "gn:admin1_code":"26.0",
    "gn:asciiname":"Shahrak-e Baba Salman",
    "gn:country_code":"IR",
    "gn:dem":1136,
    "gn:feature_class":"P",
    "gn:feature_code":"PPL",
    "gn:name":"Shahrak-e B\u0101b\u0101 Salm\u0101n",
    "gn:population":0,
    "gn:timezone":"Asia/Tehran",
    "iso:country":"IR",
    "name:fas_x_preferred":[
        "\u0634\u0647\u0631\u06a9 \u0628\u0627\u0628\u0627 \u0633\u0644\u0645\u0627\u0646"
    ],
    "name:fas_x_variant":[
        "\u0639\u0650\u0635\u0645\u064e\u062a \u0622\u0628\u0627\u062f",
        "\u0628\u0627\u0628\u0627\u0633\u0644\u0645\u0627\u0646"
    ],
    "name:und_x_variant":[
        "\u2018E\u015fmat\u0101b\u0101d",
        "Shahrak-e B\u0101b\u0101 Salm\u0101n"
    ],
    "wof:name":"Shahrak-e Baba Salman",
    "wof:placetype":"locality"
},
  "geometry": {"coordinates":[51.115,35.6637],"type":"Point"}
}