{
  "type": "Feature",
  "properties": {
    "gn:admin1_code":"15",
    "gn:asciiname":"Kheyrabad-e Gohar",
    "gn:country_code":"IR",
    "gn:dem":388,
    "gn:feature_class":"P",
    "gn:feature_code":"PPL",
    "gn:name":"Kheyr\u0101b\u0101d-e Gohar",
    "gn:population":0,
    "gn:timezone":"Asia/Tehran",
    "iso:country":"IR",
    "name:fas_x_preferred":[
        "\u062e\u064a\u0631\u0627\u0628\u0627\u062f \u06af\u0647\u0631"
    ],
    "name:fas_x_variant":[
        "Kheyr\u0101b\u0101d-e Gohar"
    ],
    "name:und_x_variant":[
        "Khair\u0101b\u0101d",
        "Kheyr\u0101b\u0101d-e Gahar",
        "Kheyr\u0101b\u0101d"
    ],
    "wof:name":"Kheyrabad-e Gohar",
    "wof:placetype":"locality"
},
  "geometry": {"coordinates":[50.4078,30.5309],"type":"Point"}
}