{
  "type": "Feature",
  "properties": {
    "gn:admin1_code":"7",
    "gn:asciiname":"Tang-e Chug",
    "gn:country_code":"IR",
    "gn:dem":1536,
    "gn:feature_class":"P",
    "gn:feature_code":"PPL",
    "gn:name":"Tang-e Ch\u016bg",
    "gn:population":0,
    "gn:timezone":"Asia/Tehran",
    "iso:country":"IR",
    "name:fas_x_preferred":[
        "Tang-e Ch\u016bg"
    ],
    "name:fas_x_variant":[
        "\u062a\u0646\u06af \u0686\u0648\u06af"
    ],
    "wof:name":"Tang-e Chug",
    "wof:placetype":"locality"
},
  "geometry": {"coordinates":[51.2439,30.52608],"type":"Point"}
}