{
  "type": "Feature",
  "properties": {
    "gn:admin1_code":"7",
    "gn:asciiname":"Tolombeh-ye `Askar-e Khosravi",
    "gn:country_code":"IR",
    "gn:dem":957,
    "gn:feature_class":"P",
    "gn:feature_code":"PPL",
    "gn:name":"Tolombeh-ye \u2018Askar-e Khosrav\u012b",
    "gn:population":0,
    "gn:timezone":"Asia/Tehran",
    "iso:country":"IR",
    "name:fas_x_preferred":[
        "Tolombeh-ye \u2018Askar-e Khosrav\u012b"
    ],
    "wof:name":"Tolombeh-ye `Askar-e Khosravi",
    "wof:placetype":"locality"
},
  "geometry": {"coordinates":[55.51971999999999,27.95972],"type":"Point"}
}