{
  "type": "Feature",
  "properties": {
    "gn:admin1_code":"15.0",
    "gn:asciiname":"Farahani-ye Moqaddam",
    "gn:country_code":"IR",
    "gn:dem":14,
    "gn:feature_class":"P",
    "gn:feature_code":"PPL",
    "gn:name":"Farah\u0101n\u012b-ye Moqaddam",
    "gn:population":0,
    "gn:timezone":"Asia/Tehran",
    "iso:country":"IR",
    "name:fas_x_preferred":[
        "\u0641\u0631\u0647\u0627\u0646\u06cc \u0645\u0642\u0651\u062f\u0645"
    ],
    "name:und_x_variant":[
        "Farah\u0101n\u012b-ye Moqaddam"
    ],
    "wof:name":"Farahani-ye Moqaddam",
    "wof:placetype":"locality"
},
  "geometry": {"coordinates":[48.87537,30.7676],"type":"Point"}
}