{
  "type": "Feature",
  "properties": {
    "gn:admin1_code":"42",
    "gn:asciiname":"Kalateh-ye Jal Galan",
    "gn:country_code":"IR",
    "gn:dem":1743,
    "gn:feature_class":"P",
    "gn:feature_code":"PPL",
    "gn:name":"Kal\u0101teh-ye Jal Gal\u0101n",
    "gn:population":0,
    "gn:timezone":"Asia/Tehran",
    "iso:country":"IR",
    "name:fas_x_preferred":[
        "\u06a9\u0644\u0627\u062a\u0647 \u062c\u0644 \u06af\u0644\u0627\u0646"
    ],
    "name:fas_x_variant":[
        "Kal\u0101teh-ye Jal Gal\u0101n"
    ],
    "wof:name":"Kalateh-ye Jal Galan",
    "wof:placetype":"locality"
},
  "geometry": {"coordinates":[58.51445,36.87806],"type":"Point"}
}