{
  "type": "Feature",
  "properties": {
    "gn:admin1_code":"32.0",
    "gn:asciiname":"Ani-ye Pa'in",
    "gn:country_code":"IR",
    "gn:dem":1209,
    "gn:feature_class":"P",
    "gn:feature_code":"PPL",
    "gn:name":"An\u012b-ye P\u0101\u2019\u012bn",
    "gn:population":0,
    "gn:timezone":"Asia/Tehran",
    "iso:country":"IR",
    "name:ara_x_preferred":[
        "\u0627\u0646\u064a \u0633\u0641\u0644\u064a"
    ],
    "name:azb_x_preferred":[
        "\u0622\u0634\u0627\u063a\u0627 \u0627\u06cc\u0646\u06cc"
    ],
    "name:ceb_x_preferred":[
        "An\u012b-ye P\u0101'\u012bn"
    ],
    "name:fas_x_preferred":[
        "\u0622\u0646\u0626 \u0633\u064f\u0641\u0644\u064e\u0649"
    ],
    "name:fas_x_variant":[
        "\u0627\u064e\u0646\u0651\u0626 \u067e\u0627\u0626\u064a\u0646",
        "\u0627\u064e\u0646\u06cc \u0633\u064f\u0641\u0644\u064e\u0649",
        "\u0627\u0646\u06cc \u067e\u0627\u0626\u06cc\u0646",
        "\u0100n\u012b-ye Sofl\u00e1",
        "An\u012b-ye P\u0101\u2019\u012bn",
        "\u0627\u0646\u06cc \u0633\u0641\u0644\u06cc"
    ],
    "name:msa_x_preferred":[
        "Ani-ye Sofla"
    ],
    "name:mzn_x_preferred":[
        "\u0627\u0646\u06cc \u0633\u0641\u0644\u06cc"
    ],
    "name:swe_x_preferred":[
        "An\u012b-ye P\u0101'\u012bn"
    ],
    "name:und_x_variant":[
        "An\u012b Sofl\u00e1",
        "Ann\u012b-ye P\u0101\u2019\u012bn"
    ],
    "wof:name":"Ani-ye Pa'in",
    "wof:placetype":"locality"
},
  "geometry": {"coordinates":[48.1429,38.981],"type":"Point"}
}