{
  "type": "Feature",
  "properties": {
    "gn:admin1_code":"22",
    "gn:asciiname":"Sar Cheshmeh",
    "gn:country_code":"IR",
    "gn:dem":193,
    "gn:feature_class":"P",
    "gn:feature_code":"PPL",
    "gn:name":"Sar Cheshmeh",
    "gn:population":0,
    "gn:timezone":"Asia/Tehran",
    "iso:country":"IR",
    "name:ceb_x_preferred":[
        "Sar Cheshmeh"
    ],
    "name:fas_x_preferred":[
        "\u0633\u0631 \u0686\u0634\u0645\u0647"
    ],
    "name:fas_x_variant":[
        "\u0633\u0631\u0686\u0634\u0645\u0647"
    ],
    "name:msa_x_preferred":[
        "Sar Cheshmeh"
    ],
    "name:swe_x_preferred":[
        "Sar Cheshmeh"
    ],
    "name:und_x_variant":[
        "Sar Chashmeh"
    ],
    "wof:name":"Sar Cheshmeh",
    "wof:placetype":"locality"
},
  "geometry": {"coordinates":[51.91449,28.12781],"type":"Point"}
}