{
  "type": "Feature",
  "properties": {
    "gn:admin1_code":"5",
    "gn:asciiname":"Kharestan",
    "gn:country_code":"IR",
    "gn:dem":579,
    "gn:feature_class":"P",
    "gn:feature_code":"PPL",
    "gn:name":"Kh\u0101rest\u0101n",
    "gn:population":0,
    "gn:timezone":"Asia/Tehran",
    "iso:country":"IR",
    "name:fas_x_preferred":[
        "Kh\u0101rest\u0101n"
    ],
    "name:fas_x_variant":[
        "\u062e\u0627\u0631\u0633\u062a\u0627\u0646"
    ],
    "name:und_x_variant":[
        "\u062e\u0627\u0631\u0633\u062a\u0627\u0646"
    ],
    "wof:name":"Kharestan",
    "wof:placetype":"locality"
},
  "geometry": {"coordinates":[50.01699,31.02456],"type":"Point"}
}