{
  "type": "Feature",
  "properties": {
    "gn:admin1_code":"35.0",
    "gn:asciiname":"Pa'in Zarandin",
    "gn:country_code":"IR",
    "gn:dem":86,
    "gn:feature_class":"P",
    "gn:feature_code":"PPL",
    "gn:name":"P\u0101\u2019\u012bn Zarand\u012bn",
    "gn:population":0,
    "gn:timezone":"Asia/Tehran",
    "iso:country":"IR",
    "name:fas_x_preferred":[
        "\u0632\u064e\u0631\u064e\u0646\u062f\u064a\u0646\u0650 \u067e\u0627\u0626\u064a\u0646"
    ],
    "name:fas_x_variant":[
        "Zarand\u012bn-e P\u0101\u2019\u012bn",
        "P\u0101\u2019\u012bn Zarand\u012bn",
        "\u067e\u0627\u0626\u064a\u0646 \u0632\u0631\u0646\u062f\u064a\u0646"
    ],
    "wof:name":"Pa'in Zarandin",
    "wof:placetype":"locality"
},
  "geometry": {"coordinates":[53.32734,36.62293],"type":"Point"}
}