{
  "type": "Feature",
  "properties": {
    "gn:admin1_code":"23",
    "gn:asciiname":"Kashkak",
    "gn:country_code":"IR",
    "gn:dem":1947,
    "gn:feature_class":"P",
    "gn:feature_code":"PPL",
    "gn:name":"Kashkak",
    "gn:population":0,
    "gn:timezone":"Asia/Tehran",
    "iso:country":"IR",
    "name:fas_x_preferred":[
        "\u06a9\u0634\u06a9\u06a9"
    ],
    "name:fas_x_variant":[
        "\u0642\u0650\u0634\u0644\u0627\u0642"
    ],
    "name:und_x_variant":[
        "Qeshl\u0101q",
        "Qishl\u0101q",
        "Kashkak"
    ],
    "wof:name":"Kashkak",
    "wof:placetype":"locality"
},
  "geometry": {"coordinates":[49.60742,33.38519],"type":"Point"}
}