{
  "type": "Feature",
  "properties": {
    "gn:admin1_code":"28.0",
    "gn:asciiname":"La Kuheh",
    "gn:country_code":"IR",
    "gn:dem":1584,
    "gn:feature_class":"P",
    "gn:feature_code":"PPL",
    "gn:name":"L\u0101 K\u016bheh",
    "gn:population":0,
    "gn:timezone":"Asia/Tehran",
    "iso:country":"IR",
    "name:ara_x_preferred":[
        "\u0644\u0634\u063a\u0631\u06a9\u0648\u0647"
    ],
    "name:fas_x_preferred":[
        "\u0644\u0634\u06af\u0631 \u06a9\u0648\u0647"
    ],
    "name:fas_x_variant":[
        "L\u0101k\u016bh",
        "Lashgar K\u016bh",
        "\u0644\u0627 \u06a9\u0648\u0647\u0647",
        "\u0644\u0634\u06af\u0631\u06a9\u0648\u0647"
    ],
    "name:und_x_variant":[
        "L\u0101 K\u016bheh"
    ],
    "name:urd_x_preferred":[
        "\u0644\u0634\u06a9\u0631 \u06a9\u0648\u06c1"
    ],
    "wof:name":"La Kuheh",
    "wof:placetype":"locality"
},
  "geometry": {"coordinates":[52.2435,33.3088],"type":"Point"}
}