{
  "type": "Feature",
  "properties": {
    "gn:admin1_code":"29",
    "gn:asciiname":"Deh-e Now",
    "gn:country_code":"IR",
    "gn:dem":1514,
    "gn:feature_class":"P",
    "gn:feature_code":"PPLF",
    "gn:name":"Deh-e Now",
    "gn:population":0,
    "gn:timezone":"Asia/Tehran",
    "iso:country":"IR",
    "name:fas_x_preferred":[
        "\u062f\u0647\u0646\u0648"
    ],
    "name:fas_x_variant":[
        "\u062f\u0647 \u0646\u0648",
        "\u062f\u0647 \u0646\u0648 \u0645\u064a\u0686"
    ],
    "name:und_x_variant":[
        "Dehnow",
        "Deh-e Now",
        "Deh-e Now-e M\u012bch"
    ],
    "wof:name":"Deh-e Now",
    "wof:placetype":"locality"
},
  "geometry": {"coordinates":[58.3095,28.8221],"type":"Point"}
}