{
  "type": "Feature",
  "properties": {
    "gn:admin1_code":"33",
    "gn:asciiname":"Janbahan",
    "gn:country_code":"IR",
    "gn:dem":1927,
    "gn:feature_class":"P",
    "gn:feature_code":"PPL",
    "gn:name":"J\u0101nbah\u0101n",
    "gn:population":0,
    "gn:timezone":"Asia/Tehran",
    "iso:country":"IR",
    "name:fas_x_preferred":[
        "J\u0101nbah\u0101n"
    ],
    "wof:name":"Janbahan",
    "wof:placetype":"locality"
},
  "geometry": {"coordinates":[46.68333,37.91667],"type":"Point"}
}