{
  "type": "Feature",
  "properties": {
    "gn:admin1_code":"8",
    "gn:asciiname":"Molla Bagh",
    "gn:country_code":"IR",
    "gn:dem":1248,
    "gn:feature_class":"P",
    "gn:feature_code":"PPL",
    "gn:name":"Moll\u0101 B\u0101gh",
    "gn:population":0,
    "gn:timezone":"Asia/Tehran",
    "iso:country":"IR",
    "name:fas_x_preferred":[
        "Moll\u0101 B\u0101gh"
    ],
    "name:fas_x_variant":[
        "\u0645\u0644\u0627 \u0628\u0627\u063a"
    ],
    "wof:name":"Molla Bagh",
    "wof:placetype":"locality"
},
  "geometry": {"coordinates":[49.00965,37.15193],"type":"Point"}
}