{
  "type": "Feature",
  "properties": {
    "gn:admin1_code":"15",
    "gn:asciiname":"Chazi",
    "gn:country_code":"IR",
    "gn:dem":670,
    "gn:feature_class":"P",
    "gn:feature_code":"PPL",
    "gn:name":"Chaz\u012b",
    "gn:population":0,
    "gn:timezone":"Asia/Tehran",
    "iso:country":"IR",
    "name:fas_x_preferred":[
        "\u0686\u06cc\u0632\u06cc"
    ],
    "name:fas_x_variant":[
        "Chaz\u012b",
        "Men\u0101r",
        "Chez\u012b-ye \u2018Oly\u0101",
        "\u0645\u0646\u0627\u0631",
        "Ch\u012bz\u012b",
        "\u0686\u0632\u06cc",
        "\u0686\u0632\u06cc \u0639\u0644\u06cc\u0627"
    ],
    "wof:name":"Chazi",
    "wof:placetype":"locality"
},
  "geometry": {"coordinates":[49.38321,32.0806],"type":"Point"}
}