{
  "type": "Feature",
  "properties": {
    "gn:admin1_code":"29",
    "gn:asciiname":"Javadiyeh-ye Fallah",
    "gn:country_code":"IR",
    "gn:dem":1309,
    "gn:feature_class":"P",
    "gn:feature_code":"PPL",
    "gn:name":"Jav\u0101d\u012byeh-ye Fall\u0101\u1e29",
    "gn:population":0,
    "gn:timezone":"Asia/Tehran",
    "iso:country":"IR",
    "name:fas_x_preferred":[
        "Jav\u0101d\u012byeh"
    ],
    "name:fas_x_variant":[
        "Jav\u0101d\u012byeh-ye Fall\u0101\u1e29",
        "\u062c\u0648\u0627\u062f\u064a\u0647 \u0641\u0644\u0627\u062d"
    ],
    "wof:name":"Javadiyeh-ye Fallah",
    "wof:placetype":"locality"
},
  "geometry": {"coordinates":[55.56155,31.01465],"type":"Point"}
}