{
  "type": "Feature",
  "properties": {
    "gn:admin1_code":"15.0",
    "gn:asciiname":"Shahrak-e Asadpur",
    "gn:country_code":"IR",
    "gn:dem":810,
    "gn:feature_class":"P",
    "gn:feature_code":"PPL",
    "gn:name":"Shahrak-e Asadp\u016br",
    "gn:population":0,
    "gn:timezone":"Asia/Tehran",
    "iso:country":"IR",
    "name:fas_x_preferred":[
        "Shahrak-e Shah\u012bd Asadp\u016br"
    ],
    "name:fas_x_variant":[
        "\u0634\u0647\u0631\u0643 \u0634\u0647\u06cc\u062f \u0627\u0633\u062f\u067e\u0648\u0631",
        "\u0634\u0647\u0631\u06a9 \u0627\u0633\u062f\u067e\u0648\u0631",
        "\u0634\u0647\u0631\u06a9 \u0645\u062d\u0645\u062f \u0631\u0636\u0627 \u0627\u0633\u062f\u067e\u0648\u0631"
    ],
    "name:und_x_variant":[
        "\u0634\u0647\u0631\u0643 \u0634\u0647\u06cc\u062f \u0627\u0633\u062f\u067e\u0648\u0631",
        "Shahrak-e Asadp\u016br",
        "Shahrak-e Mo\u1e29ammad Re\u1e95\u0101 Asadp\u016br"
    ],
    "wof:name":"Shahrak-e Asadpur",
    "wof:placetype":"locality"
},
  "geometry": {"coordinates":[49.53853,32.16077],"type":"Point"}
}