{
  "type": "Feature",
  "properties": {
    "gn:admin1_code":"15.0",
    "gn:asciiname":"Dimeh-ye Bon Sa`id",
    "gn:country_code":"IR",
    "gn:dem":107,
    "gn:feature_class":"P",
    "gn:feature_code":"PPL",
    "gn:name":"D\u012bmeh-ye Bon Sa\u2018\u012bd",
    "gn:population":0,
    "gn:timezone":"Asia/Tehran",
    "iso:country":"IR",
    "name:fas_x_preferred":[
        "D\u012bmeh"
    ],
    "name:fas_x_variant":[
        "\u062f\u06cc\u0645\u0647",
        "\u062f\u06cc\u0645\u0647 \u0628\u0646 \u0633\u0639\u06cc\u062f"
    ],
    "name:und_x_variant":[
        "\u062f\u06cc\u0645\u0647",
        "Dambeh",
        "D\u012bmeh-ye Bon Sa\u2018\u012bd"
    ],
    "wof:name":"Dimeh-ye Bon Sa`id",
    "wof:placetype":"locality"
},
  "geometry": {"coordinates":[49.58059,31.11376],"type":"Point"}
}