{
  "type": "Feature",
  "properties": {
    "gn:admin1_code":"28.0",
    "gn:asciiname":"Timyart",
    "gn:cc2":"IR",
    "gn:country_code":"IR",
    "gn:dem":1520,
    "gn:feature_class":"P",
    "gn:feature_code":"PPL",
    "gn:name":"T\u012bmy\u0101rt",
    "gn:population":0,
    "gn:timezone":"Asia/Tehran",
    "iso:country":"IR",
    "name:fas_x_preferred":[
        "T\u012bmy\u0101rt"
    ],
    "name:und_x_variant":[
        "T\u012bm\u0101rt",
        "Temy\u0101rt"
    ],
    "wof:name":"Timyart",
    "wof:placetype":"locality"
},
  "geometry": {"coordinates":[52.01667,32.55],"type":"Point"}
}