{
  "type": "Feature",
  "properties": {
    "gn:admin1_code":"36",
    "gn:asciiname":"Kabud Cheshmeh",
    "gn:country_code":"IR",
    "gn:dem":1868,
    "gn:feature_class":"P",
    "gn:feature_code":"PPL",
    "gn:name":"Kab\u016bd Cheshmeh",
    "gn:population":0,
    "gn:timezone":"Asia/Tehran",
    "iso:country":"IR",
    "name:ara_x_preferred":[
        "\u0643\u0628\u0648\u062f \u062c\u0634\u0645\u0629"
    ],
    "name:azb_x_preferred":[
        "\u06a9\u0628\u0648\u062f\u0686\u0634\u0645\u0647"
    ],
    "name:fas_x_preferred":[
        "\u0643\u0628\u0648\u062f \u0686\u0634\u0645\u0647"
    ],
    "name:fas_x_variant":[
        "Kab\u016bd Cheshmeh",
        "\u06a9\u0628\u0648\u062f\u0686\u0634\u0645\u0647"
    ],
    "name:und_x_variant":[
        "Khal\u012bfehl\u016b",
        "Kab\u016bd Chashmeh",
        "Khalifali",
        "Khal\u012bfeh \u2018Al\u012b",
        "Khalif\u2018alu"
    ],
    "wof:name":"Kabud Cheshmeh",
    "wof:placetype":"locality"
},
  "geometry": {"coordinates":[49.0326,36.25439],"type":"Point"}
}