{
  "type": "Feature",
  "properties": {
    "gn:admin1_code":"4.0",
    "gn:asciiname":"Shuhdar",
    "gn:country_code":"IR",
    "gn:dem":683,
    "gn:feature_class":"P",
    "gn:feature_code":"PPL",
    "gn:name":"Sh\u016bhdar",
    "gn:population":0,
    "gn:timezone":"Asia/Tehran",
    "iso:country":"IR",
    "name:fas_x_preferred":[
        "\u0634\u0648\u0647\u062f\u0631"
    ],
    "name:und_x_variant":[
        "Sh\u016bhdar"
    ],
    "wof:name":"Shuhdar",
    "wof:placetype":"locality"
},
  "geometry": {"coordinates":[59.57021,26.4622],"type":"Point"}
}