{
  "type": "Feature",
  "properties": {
    "gn:admin1_code":"15",
    "gn:asciiname":"Darreh Eshkaft-e Bala",
    "gn:country_code":"IR",
    "gn:dem":581,
    "gn:feature_class":"P",
    "gn:feature_code":"PPL",
    "gn:name":"Darreh Eshkaft-e B\u0101l\u0101",
    "gn:population":0,
    "gn:timezone":"Asia/Tehran",
    "iso:country":"IR",
    "name:fas_x_preferred":[
        "Dareshgaft-e \u2018Oly\u0101"
    ],
    "name:fas_x_variant":[
        "Darreh Eshkaft-e B\u0101l\u0101",
        "\u062f\u0631\u0651\u0647 \u0627\u0634\u06a9\u0641\u062a \u0628\u0627\u0644\u0627",
        "\u062f\u0631\u0647 \u0627\u0634\u06af\u0641\u062a"
    ],
    "name:und_x_variant":[
        "Darreh Eshgaft"
    ],
    "wof:name":"Darreh Eshkaft-e Bala",
    "wof:placetype":"locality"
},
  "geometry": {"coordinates":[49.65965,31.94082],"type":"Point"}
}