{
  "type": "Feature",
  "properties": {
    "gn:admin1_code":"29",
    "gn:asciiname":"Deh-e Biram",
    "gn:country_code":"IR",
    "gn:dem":2157,
    "gn:feature_class":"P",
    "gn:feature_code":"PPL",
    "gn:name":"Deh-e B\u012bram",
    "gn:population":0,
    "gn:timezone":"Asia/Tehran",
    "iso:country":"IR",
    "name:ara_x_preferred":[
        "\u062f\u0647 \u0628\u064a\u0631\u0645"
    ],
    "name:fas_x_preferred":[
        "\u062f\u0647 \u0628\u06cc\u0631\u0645"
    ],
    "name:fas_x_variant":[
        "Deh-e Bahr\u0101m",
        "Deh-e B\u012bram"
    ],
    "wof:name":"Deh-e Biram",
    "wof:placetype":"locality"
},
  "geometry": {"coordinates":[56.4142,29.9392],"type":"Point"}
}