{
  "type": "Feature",
  "properties": {
    "gn:admin1_code":"26.0",
    "gn:asciiname":"Gelahak",
    "gn:country_code":"IR",
    "gn:dem":1918,
    "gn:feature_class":"P",
    "gn:feature_code":"PPL",
    "gn:name":"Gel\u0101hak",
    "gn:population":0,
    "gn:timezone":"Asia/Tehran",
    "iso:country":"IR",
    "name:ara_x_preferred":[
        "\u063a\u0644 \u0623\u0647\u0643"
    ],
    "name:ceb_x_preferred":[
        "Gel\u0101hak"
    ],
    "name:fas_x_preferred":[
        "\u06af\u0644 \u0622\u0647\u06a9"
    ],
    "name:fas_x_variant":[
        "Gel \u0100hak",
        "\u06af\u0644\u0627\u0647\u06a9"
    ],
    "name:swe_x_preferred":[
        "Gel\u0101hak"
    ],
    "name:und_x_variant":[
        "Gel\u0101hak"
    ],
    "wof:name":"Gelahak",
    "wof:placetype":"locality"
},
  "geometry": {"coordinates":[51.9449,35.7178],"type":"Point"}
}