{
  "type": "Feature",
  "properties": {
    "gn:admin1_code":"4",
    "gn:asciiname":"Dowlatabad-e Do",
    "gn:country_code":"IR",
    "gn:dem":1187,
    "gn:feature_class":"P",
    "gn:feature_code":"PPL",
    "gn:name":"Dowlat\u0101b\u0101d-e Do",
    "gn:population":0,
    "gn:timezone":"Asia/Tehran",
    "iso:country":"IR",
    "name:fas_x_preferred":[
        "\u062f\u0648\u0644\u062a \u0622\u0628\u0627\u062f"
    ],
    "name:fas_x_variant":[
        "Dowlat\u0101b\u0101d",
        "\u062f\u0648\u0644\u062a \u0622\u0628\u0627\u062f \u062f\u0648",
        "\u062d\u0627\u062c \u0645\u0631\u0627\u062f \u0628\u062e\u0634"
    ],
    "name:und_x_variant":[
        "Dowlat\u0101b\u0101d-e Do",
        "\u1e28\u0101jj Mor\u0101d Bakhsh"
    ],
    "wof:name":"Dowlatabad-e Do",
    "wof:placetype":"locality"
},
  "geometry": {"coordinates":[61.8171,27.43291],"type":"Point"}
}