{
  "type": "Feature",
  "properties": {
    "gn:admin1_code":"15",
    "gn:asciiname":"Sar Eshgaft",
    "gn:country_code":"IR",
    "gn:dem":478,
    "gn:feature_class":"P",
    "gn:feature_code":"PPL",
    "gn:name":"Sar Eshgaft",
    "gn:population":0,
    "gn:timezone":"Asia/Tehran",
    "iso:country":"IR",
    "name:fas_x_preferred":[
        "\u0633\u0631 \u0627\u0634\u06a9\u0641\u062a"
    ],
    "name:fas_x_variant":[
        "Sar Eshkaft\u012b",
        "\u0633\u0631 \u0627\u0634\u06af\u0641\u062a",
        "\u0633\u0631\u0627\u0634\u06a9\u0641\u062a"
    ],
    "name:und_x_variant":[
        "Sar Eshkaft",
        "Sar Eshkaft-e Darak\u012b",
        "Sar Eshgaft"
    ],
    "wof:name":"Sar Eshgaft",
    "wof:placetype":"locality"
},
  "geometry": {"coordinates":[48.3305,32.79068],"type":"Point"}
}