{
  "type": "Feature",
  "properties": {
    "gn:admin1_code":"11",
    "gn:asciiname":"Sar Zeh",
    "gn:country_code":"IR",
    "gn:dem":499,
    "gn:feature_class":"P",
    "gn:feature_code":"PPL",
    "gn:name":"Sar Zeh",
    "gn:population":0,
    "gn:timezone":"Asia/Tehran",
    "iso:country":"IR",
    "name:fas_x_preferred":[
        "\u0633\u0631 \u0632\u0647"
    ],
    "name:fas_x_variant":[
        "\u0633\u0631\u0632\u0647"
    ],
    "name:msa_x_preferred":[
        "Sar Zeh"
    ],
    "wof:name":"Sar Zeh",
    "wof:placetype":"locality"
},
  "geometry": {"coordinates":[57.1424,27.7937],"type":"Point"}
}