{
  "type": "Feature",
  "properties": {
    "gn:admin1_code":"38.0",
    "gn:asciiname":"Adar",
    "gn:country_code":"IR",
    "gn:dem":2214,
    "gn:feature_class":"P",
    "gn:feature_code":"PPL",
    "gn:name":"\u0100d\u0101r",
    "gn:population":0,
    "gn:timezone":"Asia/Tehran",
    "iso:country":"IR",
    "name:fas_x_preferred":[
        "\u0622\u062f\u0627\u0631"
    ],
    "name:fas_x_variant":[
        "\u0627\u064e\u062f\u0627\u062f",
        "\u0622\u0648\u0627\u0631",
        "\u0100d\u0101r"
    ],
    "name:und_x_variant":[
        "\u0100v\u0101r",
        "Ad\u0101d"
    ],
    "wof:name":"Adar",
    "wof:placetype":"locality"
},
  "geometry": {"coordinates":[48.82789,35.73336],"type":"Point"}
}