{
  "type": "Feature",
  "properties": {
    "gn:admin1_code":"29.0",
    "gn:asciiname":"Kalami",
    "gn:cc2":"IR",
    "gn:country_code":"IR",
    "gn:dem":2108,
    "gn:feature_class":"P",
    "gn:feature_code":"PPL",
    "gn:name":"Kalam\u012b",
    "gn:population":0,
    "gn:timezone":"Asia/Tehran",
    "iso:country":"IR",
    "name:fas_x_preferred":[
        "Kalam\u012b"
    ],
    "name:und_x_variant":[
        "Kalmi"
    ],
    "wof:name":"Kalami",
    "wof:placetype":"locality"
},
  "geometry": {"coordinates":[57.89222,28.94583],"type":"Point"}
}