{
  "type": "Feature",
  "properties": {
    "gn:admin1_code":"28",
    "gn:asciiname":"Mast Bandi",
    "gn:country_code":"IR",
    "gn:dem":1695,
    "gn:feature_class":"P",
    "gn:feature_code":"PPL",
    "gn:name":"M\u0101st Band\u012b",
    "gn:population":0,
    "gn:timezone":"Asia/Tehran",
    "iso:country":"IR",
    "name:ara_x_preferred":[
        "\u0645\u0633\u062a \u0628\u0646\u062f\u064a"
    ],
    "name:fas_x_preferred":[
        "\u0645\u0627\u0633\u062a \u0628\u0646\u062f\u06cc"
    ],
    "name:fas_x_variant":[
        "M\u0101st Band\u012b",
        "\u0645\u0627\u0633\u062a\u200c\u0628\u0646\u062f\u06cc"
    ],
    "wof:name":"Mast Bandi",
    "wof:placetype":"locality"
},
  "geometry": {"coordinates":[52.3323,33.2226],"type":"Point"}
}