{
  "type": "Feature",
  "properties": {
    "gn:admin1_code":"29",
    "gn:asciiname":"Hoseynabad-e Shah Gol",
    "gn:country_code":"IR",
    "gn:dem":654,
    "gn:feature_class":"P",
    "gn:feature_code":"PPL",
    "gn:name":"\u1e28oseyn\u0101b\u0101d-e Shah Gol",
    "gn:population":0,
    "gn:timezone":"Asia/Tehran",
    "iso:country":"IR",
    "name:fas_x_preferred":[
        "\u062d\u0633\u06cc\u0646 \u0622\u0628\u0627\u062f \u0634\u0647 \u06af\u0644"
    ],
    "name:fas_x_variant":[
        "\u1e28oseyn\u0101b\u0101d",
        "\u1e28oseyn\u0101b\u0101d-e Shah Gol",
        "\u062d\u0633\u06cc\u0646 \u0622\u0628\u0627\u062f \u0634\u0647\u06a9\u0644"
    ],
    "name:und_x_variant":[
        "\u1e28oseyn\u0101b\u0101d-e Shahkol"
    ],
    "wof:name":"Hoseynabad-e Shah Gol",
    "wof:placetype":"locality"
},
  "geometry": {"coordinates":[58.98,28.6468],"type":"Point"}
}