{
  "type": "Feature",
  "properties": {
    "gn:admin1_code":"11.0",
    "gn:asciiname":"Kalut",
    "gn:country_code":"IR",
    "gn:dem":21,
    "gn:feature_class":"P",
    "gn:feature_code":"PPL",
    "gn:name":"Kal\u016bt",
    "gn:population":0,
    "gn:timezone":"Asia/Tehran",
    "iso:country":"IR",
    "name:fas_x_preferred":[
        "\u0643\u0644\u0648\u062a"
    ],
    "name:fas_x_variant":[
        "Kal\u016bt"
    ],
    "wof:name":"Kalut",
    "wof:placetype":"locality"
},
  "geometry": {"coordinates":[57.06706,27.05829],"type":"Point"}
}