{
  "type": "Feature",
  "properties": {
    "gn:admin1_code":"23",
    "gn:asciiname":"Deh Sefid-e Latifi",
    "gn:country_code":"IR",
    "gn:dem":1499,
    "gn:feature_class":"P",
    "gn:feature_code":"PPL",
    "gn:name":"Deh Sef\u012bd-e La\u0163\u012bf\u012b",
    "gn:population":0,
    "gn:timezone":"Asia/Tehran",
    "iso:country":"IR",
    "name:fas_x_preferred":[
        "\u062f\u0647 \u0633\u0641\u06cc\u062f \u0644\u0637\u06cc\u0641\u06cc"
    ],
    "name:fas_x_variant":[
        "Deh Sef\u012bd-e La\u0163\u012bf\u012b"
    ],
    "wof:name":"Deh Sefid-e Latifi",
    "wof:placetype":"locality"
},
  "geometry": {"coordinates":[48.526,33.5032],"type":"Point"}
}