{
  "type": "Feature",
  "properties": {
    "gn:admin1_code":"29.0",
    "gn:asciiname":"Kahn Changar",
    "gn:country_code":"IR",
    "gn:dem":613,
    "gn:feature_class":"P",
    "gn:feature_code":"PPLF",
    "gn:name":"Kahn Changar",
    "gn:population":0,
    "gn:timezone":"Asia/Tehran",
    "iso:country":"IR",
    "name:fas_x_preferred":[
        "\u06a9\u0647\u0646 \u0686\u0646\u06af\u0631"
    ],
    "name:fas_x_variant":[
        "\u062f\u0627\u0632\u0648\u0644\u06cc\u0646"
    ],
    "name:und_x_variant":[
        "D\u0101z\u016bl\u012bn"
    ],
    "wof:name":"Kahn Changar",
    "wof:placetype":"locality"
},
  "geometry": {"coordinates":[58.65489,26.96706],"type":"Point"}
}