{
  "type": "Feature",
  "properties": {
    "gn:admin1_code":"13",
    "gn:asciiname":"Eshaqvand-e `Olya",
    "gn:country_code":"IR",
    "gn:dem":1470,
    "gn:feature_class":"P",
    "gn:feature_code":"PPL",
    "gn:name":"Es\u1e29\u0101qvand-e \u2018Oly\u0101",
    "gn:population":0,
    "gn:timezone":"Asia/Tehran",
    "iso:country":"IR",
    "name:fas_x_preferred":[
        "\u2018\u012as\u00e1 Kh\u0101n-e \u2018Oly\u0101"
    ],
    "name:fas_x_variant":[
        "\u0627\u0633\u062d\u0642\u0648\u0646\u062f \u0639\u0644\u06cc\u0627",
        "Es\u1e29\u0101qvand-e \u2018Oly\u0101"
    ],
    "name:und_x_variant":[
        "\u2018\u012as\u00e1 Kh\u0101n B\u0101l\u0101"
    ],
    "wof:name":"Eshaqvand-e `Olya",
    "wof:placetype":"locality"
},
  "geometry": {"coordinates":[47.4479,34.2393],"type":"Point"}
}