{
  "type": "Feature",
  "properties": {
    "gn:admin1_code":"8.0",
    "gn:asciiname":"Tirkalashk",
    "gn:country_code":"IR",
    "gn:dem":662,
    "gn:feature_class":"P",
    "gn:feature_code":"PPL",
    "gn:name":"T\u012brk\u0101lashk",
    "gn:population":0,
    "gn:timezone":"Asia/Tehran",
    "iso:country":"IR",
    "name:fas_x_preferred":[
        "T\u012brk\u0101lashk"
    ],
    "wof:name":"Tirkalashk",
    "wof:placetype":"locality"
},
  "geometry": {"coordinates":[49.61667,36.86667],"type":"Point"}
}