{
  "type": "Feature",
  "properties": {
    "gn:admin1_code":"33",
    "gn:asciiname":"Bala Sang",
    "gn:country_code":"IR",
    "gn:dem":1139,
    "gn:feature_class":"P",
    "gn:feature_code":"PPL",
    "gn:name":"B\u0101l\u0101 Sang",
    "gn:population":0,
    "gn:timezone":"Asia/Tehran",
    "iso:country":"IR",
    "name:fas_x_preferred":[
        "\u0628\u0627\u0644\u0627 \u0633\u0646\u06af"
    ],
    "name:fas_x_variant":[
        "B\u0101l\u0101 Sang",
        "\u0628\u0627\u0644\u0627\u0633\u0646\u06af"
    ],
    "name:msa_x_preferred":[
        "Bala Sang"
    ],
    "name:und_x_variant":[
        "Balasa"
    ],
    "wof:name":"Bala Sang",
    "wof:placetype":"locality"
},
  "geometry": {"coordinates":[46.9573,38.9169],"type":"Point"}
}