{
  "type": "Feature",
  "properties": {
    "gn:admin1_code":"29.0",
    "gn:asciiname":"Zir Kuh",
    "gn:country_code":"IR",
    "gn:dem":2240,
    "gn:feature_class":"P",
    "gn:feature_code":"PPL",
    "gn:name":"Z\u012br K\u016bh",
    "gn:population":0,
    "gn:timezone":"Asia/Tehran",
    "iso:country":"IR",
    "name:fas_x_preferred":[
        "\u0632\u064a\u0631 \u06a9\u0648\u0647"
    ],
    "name:und_x_variant":[
        "Z\u012br K\u016bh"
    ],
    "wof:name":"Zir Kuh",
    "wof:placetype":"locality"
},
  "geometry": {"coordinates":[55.48835,30.45479000000001],"type":"Point"}
}