{
  "type": "Feature",
  "properties": {
    "gn:admin1_code":"4.0",
    "gn:asciiname":"Palang Kuh",
    "gn:country_code":"IR",
    "gn:dem":1607,
    "gn:feature_class":"P",
    "gn:feature_code":"PPL",
    "gn:name":"Palang K\u016bh",
    "gn:population":0,
    "gn:timezone":"Asia/Tehran",
    "iso:country":"IR",
    "name:fas_x_preferred":[
        "Palang K\u016bh"
    ],
    "wof:name":"Palang Kuh",
    "wof:placetype":"locality"
},
  "geometry": {"coordinates":[60.61478,30.7323],"type":"Point"}
}