{
  "type": "Feature",
  "properties": {
    "gn:admin1_code":"37.0",
    "gn:asciiname":"Aqabad",
    "gn:country_code":"IR",
    "gn:dem":52,
    "gn:feature_class":"P",
    "gn:feature_code":"PPL",
    "gn:name":"\u0100q\u0101b\u0101d",
    "gn:population":0,
    "gn:timezone":"Asia/Tehran",
    "iso:country":"IR",
    "name:ara_x_preferred":[
        "\u0622\u0642\u200c\u0622\u0628\u0627\u062f"
    ],
    "name:fas_x_preferred":[
        "\u0100q\u0101b\u0101d"
    ],
    "name:fas_x_variant":[
        "\u0622\u0642 \u0622\u0628\u0627\u062f",
        "\u0622\u0642\u200c\u0622\u0628\u0627\u062f"
    ],
    "name:msa_x_preferred":[
        "Aqabad"
    ],
    "wof:name":"Aqabad",
    "wof:placetype":"locality"
},
  "geometry": {"coordinates":[55.24229,37.29957],"type":"Point"}
}