{
  "type": "Feature",
  "properties": {
    "gn:admin1_code":"23",
    "gn:asciiname":"Eyvan Darreh",
    "gn:country_code":"IR",
    "gn:dem":1567,
    "gn:feature_class":"P",
    "gn:feature_code":"PPL",
    "gn:name":"Eyv\u0101n Darreh",
    "gn:population":0,
    "gn:timezone":"Asia/Tehran",
    "iso:country":"IR",
    "name:ceb_x_preferred":[
        "Eyv\u0101n Darreh"
    ],
    "name:fas_x_preferred":[
        "\u0627\u06cc\u0648\u0627\u0646\u062f\u0631"
    ],
    "name:fas_x_variant":[
        "Eyv\u0101n Darreh",
        "Eyv\u0101ndar",
        "\u0627\u06cc\u0648\u0627\u0646 \u062f\u0631\u0647",
        "\u0627\u06cc\u0648\u0627\u0646 \u062f\u0631"
    ],
    "name:swe_x_preferred":[
        "Eyv\u0101n Darreh"
    ],
    "name:und_x_variant":[
        "Eyv\u0101n Dar"
    ],
    "wof:name":"Eyvan Darreh",
    "wof:placetype":"locality"
},
  "geometry": {"coordinates":[48.2382,33.7122],"type":"Point"}
}