{
  "type": "Feature",
  "properties": {
    "gn:admin1_code":"43",
    "gn:asciiname":"Karkuli",
    "gn:country_code":"IR",
    "gn:dem":952,
    "gn:feature_class":"P",
    "gn:feature_code":"PPL",
    "gn:name":"Kark\u016bl\u012b",
    "gn:population":0,
    "gn:timezone":"Asia/Tehran",
    "iso:country":"IR",
    "name:ara_x_preferred":[
        "\u06a9\u0631\u06a9\u0648\u0644\u064a"
    ],
    "name:ceb_x_preferred":[
        "Kark\u016bl\u012b"
    ],
    "name:fas_x_preferred":[
        "Kark\u016bl\u012b"
    ],
    "name:fas_x_variant":[
        "\u06a9\u0631\u06a9\u0648 \u0644\u06cc",
        "\u06a9\u0631\u06a9\u0648\u0644\u06cc"
    ],
    "name:swe_x_preferred":[
        "Kark\u016bl\u012b"
    ],
    "name:und_x_variant":[
        "\u06a9\u0631\u06a9\u0648 \u0644\u06cc"
    ],
    "wof:name":"Karkuli",
    "wof:placetype":"locality"
},
  "geometry": {"coordinates":[56.72424,38.16872],"type":"Point"}
}