{
  "type": "Feature",
  "properties": {
    "gn:admin1_code":"15",
    "gn:asciiname":"Ab Darreh-ye Tazeh",
    "gn:country_code":"IR",
    "gn:dem":1492,
    "gn:feature_class":"P",
    "gn:feature_code":"PPL",
    "gn:name":"\u0100b Darreh-ye T\u0101zeh",
    "gn:population":0,
    "gn:timezone":"Asia/Tehran",
    "iso:country":"IR",
    "name:fas_x_preferred":[
        "\u0100b Darreh-ye T\u0101zeh"
    ],
    "name:fas_x_variant":[
        "\u0622\u0628 \u062f\u0631\u0647 \u062a\u0627\u0632\u0647"
    ],
    "wof:name":"Ab Darreh-ye Tazeh",
    "wof:placetype":"locality"
},
  "geometry": {"coordinates":[49.33124,32.64511],"type":"Point"}
}