{
  "type": "Feature",
  "properties": {
    "gn:admin1_code":"35.0",
    "gn:asciiname":"Khatib Kola",
    "gn:country_code":"IR",
    "gn:dem":717,
    "gn:feature_class":"P",
    "gn:feature_code":"PPL",
    "gn:name":"Kha\u0163\u012bb Kol\u0101",
    "gn:population":0,
    "gn:timezone":"Asia/Tehran",
    "iso:country":"IR",
    "name:fas_x_preferred":[
        "\u062e\u0637\u06cc\u0628 \u06a9\u0644\u0627"
    ],
    "name:fas_x_variant":[
        "Kha\u0163\u012bb Kol\u0101"
    ],
    "wof:name":"Khatib Kola",
    "wof:placetype":"locality"
},
  "geometry": {"coordinates":[52.03259,36.37497000000001],"type":"Point"}
}