{
  "type": "Feature",
  "properties": {
    "gn:admin1_code":"29",
    "gn:asciiname":"Fakhrabad",
    "gn:country_code":"IR",
    "gn:dem":1715,
    "gn:feature_class":"P",
    "gn:feature_code":"PPL",
    "gn:name":"Fakhr\u0101b\u0101d",
    "gn:population":0,
    "gn:timezone":"Asia/Tehran",
    "iso:country":"IR",
    "name:fas_x_preferred":[
        "\u0641\u062e\u0631 \u0622\u0628\u0627\u062f"
    ],
    "name:fas_x_variant":[
        "Tolombeh-ye Fakhr\u0101b\u0101d",
        "Fakhr\u0101b\u0101d"
    ],
    "wof:name":"Fakhrabad",
    "wof:placetype":"locality"
},
  "geometry": {"coordinates":[55.60511,29.47004],"type":"Point"}
}