{
  "type": "Feature",
  "properties": {
    "gn:admin1_code":"23.0",
    "gn:asciiname":"`Asgaran",
    "gn:country_code":"IR",
    "gn:dem":2242,
    "gn:feature_class":"P",
    "gn:feature_code":"PPL",
    "gn:name":"\u2018Asgar\u0101n",
    "gn:population":0,
    "gn:timezone":"Asia/Tehran",
    "iso:country":"IR",
    "name:fas_x_preferred":[
        "\u0639\u064e\u0633\u0643\u064e\u0631\u0627\u0646"
    ],
    "name:fas_x_variant":[
        "\u0639\u064e\u0633\u06af\u0627\u0631\u0627\u0646",
        "\u2018Askar\u0101n",
        "\u2018Asgar\u0101n",
        "\u0639\u0633\u06af\u0631\u0627\u0646"
    ],
    "name:und_x_variant":[
        "\u2018Asg\u0101r\u0101n",
        "\u0639\u0633\u06af\u0631\u0627\u0646"
    ],
    "wof:name":"`Asgaran",
    "wof:placetype":"locality"
},
  "geometry": {"coordinates":[49.83429,33.31513],"type":"Point"}
}