{
  "type": "Feature",
  "properties": {
    "gn:admin1_code":"29",
    "gn:asciiname":"Mohammadabad",
    "gn:country_code":"IR",
    "gn:dem":1615,
    "gn:feature_class":"P",
    "gn:feature_code":"PPLF",
    "gn:name":"Mo\u1e29ammad\u0101b\u0101d",
    "gn:population":0,
    "gn:timezone":"Asia/Tehran",
    "iso:country":"IR",
    "name:fas_x_preferred":[
        "Mo\u1e29ammad\u0101b\u0101d"
    ],
    "name:fas_x_variant":[
        "\u0645\u062d\u0645\u0651\u062f \u0622\u0628\u0627\u062f",
        "Qaryeh \u2018Al\u012b",
        "Muhammad\u0101b\u0101d",
        "\u0639\u0628\u0627\u0633 \u0622\u0628\u0627\u062f"
    ],
    "name:und_x_variant":[
        "Muhammad\u0101b\u0101d",
        "Qaryeh \u2018Al\u012b",
        "\u2018Abb\u0101s\u0101b\u0101d"
    ],
    "wof:name":"Mohammadabad",
    "wof:placetype":"locality"
},
  "geometry": {"coordinates":[56.01718,31.34088],"type":"Point"}
}