{
  "type": "Feature",
  "properties": {
    "gn:admin1_code":"9",
    "gn:asciiname":"Qeshlaq",
    "gn:country_code":"IR",
    "gn:dem":1660,
    "gn:feature_class":"P",
    "gn:feature_code":"PPL",
    "gn:name":"Qeshl\u0101q",
    "gn:population":0,
    "gn:timezone":"Asia/Tehran",
    "iso:country":"IR",
    "name:ceb_x_preferred":[
        "Qeshl\u0101q"
    ],
    "name:fas_x_preferred":[
        "\u0642\u0634\u0644\u0627\u0642 \u0628\u0627\u0628\u0627 \u0631\u0633\u062a\u0645"
    ],
    "name:fas_x_variant":[
        "Qeshl\u0101q",
        "\u0642\u0634\u0644\u0627\u0642",
        "\u0642\u0634\u0644\u0627\u0642 \u0628\u0627\u0628\u0627\u0631\u0633\u062a\u0645"
    ],
    "name:und_x_variant":[
        "Qeshl\u0101q B\u0101b\u0101 Rostam"
    ],
    "wof:name":"Qeshlaq",
    "wof:placetype":"locality"
},
  "geometry": {"coordinates":[48.36285,34.14193],"type":"Point"}
}