{
  "type": "Feature",
  "properties": {
    "gn:admin1_code":"23",
    "gn:asciiname":"Chaleh Chuleh",
    "gn:country_code":"IR",
    "gn:dem":1749,
    "gn:feature_class":"P",
    "gn:feature_code":"PPL",
    "gn:name":"Ch\u0101leh Ch\u016bleh",
    "gn:population":0,
    "gn:timezone":"Asia/Tehran",
    "iso:country":"IR",
    "name:fas_x_preferred":[
        "\u0627\u0633\u0645\u0627\u0639\u06cc\u0644 \u062e\u0627\u0646"
    ],
    "name:fas_x_variant":[
        "Esm\u0101\u2018\u012bl Kh\u0101n",
        "\u0686\u0627\u0644\u0647 \u0686\u0648\u0644\u0647"
    ],
    "name:und_x_variant":[
        "Ch\u0101leh Ch\u016bleh"
    ],
    "wof:name":"Chaleh Chuleh",
    "wof:placetype":"locality"
},
  "geometry": {"coordinates":[47.9255,33.9876],"type":"Point"}
}