{
  "type": "Feature",
  "properties": {
    "gn:admin1_code":"32",
    "gn:asciiname":"Kuramalu",
    "gn:country_code":"IR",
    "gn:dem":839,
    "gn:feature_class":"P",
    "gn:feature_code":"PPL",
    "gn:name":"K\u016br\u0101m\u0101l\u016b",
    "gn:population":0,
    "gn:timezone":"Asia/Tehran",
    "iso:country":"IR",
    "name:fas_x_preferred":[
        "\u0643\u0648\u0631\u0627\u0645\u0627\u0644\u0648"
    ],
    "name:fas_x_variant":[
        "K\u016br\u0101m\u0101l\u016b"
    ],
    "wof:name":"Kuramalu",
    "wof:placetype":"locality"
},
  "geometry": {"coordinates":[47.7872,39.0757],"type":"Point"}
}