{
  "type": "Feature",
  "properties": {
    "gn:admin1_code":"23",
    "gn:asciiname":"Pileh Gar",
    "gn:country_code":"IR",
    "gn:dem":1164,
    "gn:feature_class":"P",
    "gn:feature_code":"PPL",
    "gn:name":"P\u012bleh Gar",
    "gn:population":0,
    "gn:timezone":"Asia/Tehran",
    "iso:country":"IR",
    "name:ceb_x_preferred":[
        "P\u012bleh Gar"
    ],
    "name:fas_x_preferred":[
        "\u067e\u064a\u0644\u0650\u0647\u06af\u0627\u0647"
    ],
    "name:fas_x_variant":[
        "\u067e\u06cc\u0644\u06af",
        "P\u012blehg\u0101h",
        "P\u012blag",
        "\u067e\u06cc\u0644\u0647 \u06af\u0631",
        "\u067e\u064a\u0644\u06af\u0627\u0647",
        "\u067e\u06cc\u0644\u06af\u0627\u0647"
    ],
    "name:swe_x_preferred":[
        "P\u012bleh Gar"
    ],
    "name:und_x_variant":[
        "P\u012bleh Gar",
        "P\u012bleg\u0101h"
    ],
    "wof:name":"Pileh Gar",
    "wof:placetype":"locality"
},
  "geometry": {"coordinates":[48.6009,33.1979],"type":"Point"}
}