{
  "type": "Feature",
  "properties": {
    "gn:admin1_code":"43",
    "gn:asciiname":"Taftazan",
    "gn:country_code":"IR",
    "gn:dem":1601,
    "gn:feature_class":"P",
    "gn:feature_code":"PPL",
    "gn:name":"Taft\u0101z\u0101n",
    "gn:population":0,
    "gn:timezone":"Asia/Tehran",
    "iso:country":"IR",
    "name:ceb_x_preferred":[
        "Taft\u0101z\u0101n"
    ],
    "name:fas_x_preferred":[
        "Taft\u0101z\u0101n"
    ],
    "name:fas_x_variant":[
        "\u062a\u0641\u062a\u0627\u0632\u0627\u0646"
    ],
    "name:swe_x_preferred":[
        "Taft\u0101z\u0101n"
    ],
    "name:und_x_variant":[
        "\u062a\u0641\u062a\u0627\u0632\u0627\u0646"
    ],
    "name:urd_x_preferred":[
        "\u062a\u0641\u062a\u0627\u0632\u0627\u0646"
    ],
    "wof:name":"Taftazan",
    "wof:placetype":"locality"
},
  "geometry": {"coordinates":[57.81567,37.76215],"type":"Point"}
}