{
  "type": "Feature",
  "properties": {
    "gn:admin1_code":"23",
    "gn:asciiname":"Panesar Barani",
    "gn:country_code":"IR",
    "gn:dem":1290,
    "gn:feature_class":"P",
    "gn:feature_code":"PPL",
    "gn:name":"P\u0101nes\u0304\u0101r B\u0101r\u0101n\u012b",
    "gn:population":0,
    "gn:timezone":"Asia/Tehran",
    "iso:country":"IR",
    "name:fas_x_preferred":[
        "\u067e\u0627\u0646\u0650\u0633\u0627\u0631\u0650 \u062a\u064e\u0634\u0643\u064e\u0646"
    ],
    "name:fas_x_variant":[
        "P\u0101nes\u0101r-e Tashkan",
        "B\u0101r\u0101n\u012b",
        "\u067e\u0627\u0646\u062b\u0627\u0631 \u0628\u0627\u0631\u0627\u0646\u06cc",
        "\u0628\u0627\u0631\u0627\u0646\u06cc"
    ],
    "name:und_x_variant":[
        "P\u0101nes\u0304\u0101r B\u0101r\u0101n\u012b"
    ],
    "wof:name":"Panesar Barani",
    "wof:placetype":"locality"
},
  "geometry": {"coordinates":[47.8801,33.6725],"type":"Point"}
}