{
  "type": "Feature",
  "properties": {
    "gn:admin1_code":"41.0",
    "gn:asciiname":"Band-e Now",
    "gn:country_code":"IR",
    "gn:dem":1336,
    "gn:feature_class":"P",
    "gn:feature_code":"PPLL",
    "gn:name":"Band-e Now",
    "gn:population":0,
    "gn:timezone":"Asia/Tehran",
    "iso:country":"IR",
    "name:fas_x_preferred":[
        "\u0628\u0646\u062f\u0646\u0648"
    ],
    "wof:name":"Band-e Now",
    "wof:placetype":"locality"
},
  "geometry": {"coordinates":[58.79156999999999,33.34941],"type":"Point"}
}