{
  "type": "Feature",
  "properties": {
    "gn:admin1_code":"10",
    "gn:asciiname":"Sulavi",
    "gn:country_code":"IR",
    "gn:dem":1177,
    "gn:feature_class":"P",
    "gn:feature_code":"PPL",
    "gn:name":"S\u016bl\u0101v\u012b",
    "gn:population":0,
    "gn:timezone":"Asia/Tehran",
    "iso:country":"IR",
    "name:fas_x_preferred":[
        "\u067e\u064a\u0627\u0645\u0650\u0646\u0650 \u0639\u064f\u0644\u064a\u0627"
    ],
    "name:fas_x_variant":[
        "\u067e\u064a\u0627\u0645\u0650\u0646",
        "\u067e\u064a\u0651\u0627\u0645\u0650\u0646",
        "\u067e\u06cc\u0627\u0645\u0646 \u0639\u0644\u06cc\u0627",
        "P\u012b\u0101men-e \u2018Oly\u0101",
        "\u0633\u0648\u0644\u0627\u0648\u06cc",
        "\u067e\u064a\u0627\u0645\u064e\u0646\u0650 \u0633\u064f\u0641\u0644\u064e\u0649",
        "\u067e\u06cc\u0627\u0645\u0646 \u0633\u0641\u0644\u06cc",
        "\u067e\u06cc\u0627\u0645\u0646 \u0648\u0633\u0637\u06cc"
    ],
    "name:und_x_variant":[
        "P\u012b\u0101men",
        "P\u012by\u0101men",
        "S\u016bl\u0101v\u012b",
        "P\u012b\u0101man-e Sofl\u00e1",
        "P\u012b\u0101men-Sofl\u00e1",
        "P\u012b\u0101men-e Vos\u0163\u00e1"
    ],
    "wof:name":"Sulavi",
    "wof:placetype":"locality"
},
  "geometry": {"coordinates":[47.44011,33.81947],"type":"Point"}
}