{
  "type": "Feature",
  "properties": {
    "gn:admin1_code":"23",
    "gn:asciiname":"Leylan Cham",
    "gn:country_code":"IR",
    "gn:dem":757,
    "gn:feature_class":"P",
    "gn:feature_code":"PPL",
    "gn:name":"Leyl\u0101n Cham",
    "gn:population":0,
    "gn:timezone":"Asia/Tehran",
    "iso:country":"IR",
    "name:ceb_x_preferred":[
        "Leyl\u0101n Cham"
    ],
    "name:fas_x_preferred":[
        "Leyl\u0101n Cham"
    ],
    "name:fas_x_variant":[
        "\u0644\u06cc\u0644\u0627\u0646 \u0686\u0645",
        "\u0639\u0628\u062f\u0627\u0644\u0639\u0644\u06cc \u0647\u0627"
    ],
    "name:swe_x_preferred":[
        "Leyl\u0101n Cham"
    ],
    "name:und_x_variant":[
        "\u2018Abdol\u2018al\u012bh\u0101"
    ],
    "wof:name":"Leylan Cham",
    "wof:placetype":"locality"
},
  "geometry": {"coordinates":[47.80678,33.27766],"type":"Point"}
}