{
  "type": "Feature",
  "properties": {
    "gn:admin1_code":"42",
    "gn:asciiname":"Sar Nakhvab",
    "gn:country_code":"IR",
    "gn:dem":1097,
    "gn:feature_class":"P",
    "gn:feature_code":"PPL",
    "gn:name":"Sar Nakhv\u0101b",
    "gn:population":0,
    "gn:timezone":"Asia/Tehran",
    "iso:country":"IR",
    "name:fas_x_preferred":[
        "Sar Nakh\u0101b-e P\u0101\u2019\u012bn"
    ],
    "name:fas_x_variant":[
        "\u0633\u0631 \u0646\u062e\u0648\u0627\u0628 \u067e\u0627\u0626\u064a\u0646",
        "Sar Nakhv\u0101b",
        "Sarankh\u0101b",
        "\u0633\u0631 \u0646\u062e\u0648\u0627\u0628",
        "\u0633\u0631 \u0646\u062e\u0648\u0627\u0628 \u0633\u0641\u0644\u06cc"
    ],
    "name:und_x_variant":[
        "Sar Nakhv\u0101b",
        "Sarankh\u0101b",
        "\u0633\u0631 \u0646\u062e\u0648\u0627\u0628 \u067e\u0627\u0626\u064a\u0646",
        "Sar Nakhv\u0101b-e P\u0101\u2019\u012bn",
        "Sar Nakhv\u0101b-e Sofl\u00e1"
    ],
    "wof:name":"Sar Nakhvab",
    "wof:placetype":"locality"
},
  "geometry": {"coordinates":[57.54753,35.25398],"type":"Point"}
}