{
  "type": "Feature",
  "properties": {
    "gn:admin1_code":"35",
    "gn:asciiname":"Palang Abrud",
    "gn:country_code":"IR",
    "gn:dem":449,
    "gn:feature_class":"P",
    "gn:feature_code":"PPL",
    "gn:name":"Palang \u0100br\u016bd",
    "gn:population":0,
    "gn:timezone":"Asia/Tehran",
    "iso:country":"IR",
    "name:und_x_variant":[
        "Palang \u0100br\u016bd",
        "Palang \u0100br\u016b"
    ],
    "wof:name":"Palang Abrud",
    "wof:placetype":"locality"
},
  "geometry": {"coordinates":[51.26083,36.63833],"type":"Point"}
}