{
  "type": "Feature",
  "properties": {
    "gn:admin1_code":"9.0",
    "gn:asciiname":"Aq Kand",
    "gn:country_code":"IR",
    "gn:dem":1783,
    "gn:feature_class":"P",
    "gn:feature_code":"PPL",
    "gn:name":"\u0100q Kand",
    "gn:population":0,
    "gn:timezone":"Asia/Tehran",
    "iso:country":"IR",
    "name:fas_x_preferred":[
        "\u0622\u0642 \u0643\u0646\u062f"
    ],
    "name:fas_x_variant":[
        "\u0100q Kand"
    ],
    "name:und_x_variant":[
        "Agh Kand Mehraban"
    ],
    "wof:name":"Aq Kand",
    "wof:placetype":"locality"
},
  "geometry": {"coordinates":[48.32528,35.48721],"type":"Point"}
}