{
  "type": "Feature",
  "properties": {
    "gn:admin1_code":"3",
    "gn:asciiname":"Sar Mazeh",
    "gn:country_code":"IR",
    "gn:dem":1413,
    "gn:feature_class":"P",
    "gn:feature_code":"PPL",
    "gn:name":"Sar M\u0101zeh",
    "gn:population":0,
    "gn:timezone":"Asia/Tehran",
    "iso:country":"IR",
    "name:ara_x_preferred":[
        "\u0633\u0631\u0645\u0627\u0632\u0629"
    ],
    "name:ceb_x_preferred":[
        "Sar M\u0101zeh"
    ],
    "name:fas_x_preferred":[
        "Sar M\u0101zeh"
    ],
    "name:fas_x_variant":[
        "\u0633\u0631 \u0645\u0627\u0632\u0647",
        "\u0633\u0631\u0645\u0627\u0632\u0647"
    ],
    "name:msa_x_preferred":[
        "Sar Mazeh"
    ],
    "name:swe_x_preferred":[
        "Sar M\u0101zeh"
    ],
    "name:und_x_variant":[
        "\u0633\u0631 \u0645\u0627\u0632\u0647"
    ],
    "wof:name":"Sar Mazeh",
    "wof:placetype":"locality"
},
  "geometry": {"coordinates":[50.59972,31.70502],"type":"Point"}
}