{
  "type": "Feature",
  "properties": {
    "gn:admin1_code":"11",
    "gn:asciiname":"Kukherd",
    "gn:country_code":"IR",
    "gn:dem":301,
    "gn:feature_class":"P",
    "gn:feature_code":"PPL",
    "gn:name":"K\u016bkherd",
    "gn:population":0,
    "gn:timezone":"Asia/Tehran",
    "iso:country":"IR",
    "name:fas_x_preferred":[
        "\u0686\u0627\u0644\u0650\u0647 \u0643\u0648\u062e\u0650\u0631\u062f"
    ],
    "name:fas_x_variant":[
        "Ch\u0101leh K\u016bkherd",
        "K\u016bkherd",
        "\u06a9\u0648\u062e\u0631\u062f"
    ],
    "name:und_x_variant":[
        "K\u016bkherd",
        "Kuhkhird",
        "\u06a9\u0648\u062e\u0631\u062f"
    ],
    "wof:name":"Kukherd",
    "wof:placetype":"locality"
},
  "geometry": {"coordinates":[54.49165,27.08711],"type":"Point"}
}