{
  "type": "Feature",
  "properties": {
    "gn:admin1_code":"35.0",
    "gn:asciiname":"Eram",
    "gn:country_code":"IR",
    "gn:dem":-8,
    "gn:feature_class":"P",
    "gn:feature_code":"PPL",
    "gn:name":"Eram",
    "gn:population":0,
    "gn:timezone":"Asia/Tehran",
    "iso:country":"IR",
    "name:fas_x_preferred":[
        "\u0627\u0631\u0645"
    ],
    "name:fas_x_variant":[
        "\u0100ram",
        "\u0622\u0631\u064e\u0645"
    ],
    "wof:name":"Eram",
    "wof:placetype":"locality"
},
  "geometry": {"coordinates":[52.32971,36.6019],"type":"Point"}
}