{
  "type": "Feature",
  "properties": {
    "gn:admin1_code":"15",
    "gn:asciiname":"Michegan",
    "gn:country_code":"IR",
    "gn:dem":246,
    "gn:feature_class":"P",
    "gn:feature_code":"PPL",
    "gn:name":"M\u012bcheg\u0101n",
    "gn:population":0,
    "gn:timezone":"Asia/Tehran",
    "iso:country":"IR",
    "name:fas_x_preferred":[
        "\u0645\u0648\u0631\u0686\u06af\u0627\u0646"
    ],
    "name:fas_x_variant":[
        "M\u016brcheg\u0101n",
        "\u0645\u06cc\u0686\u06af\u0627\u0646"
    ],
    "name:und_x_variant":[
        "Moochkan",
        "M\u016bcheg\u0101n",
        "M\u012bcheg\u0101n"
    ],
    "wof:name":"Michegan",
    "wof:placetype":"locality"
},
  "geometry": {"coordinates":[49.17215,32.08097],"type":"Point"}
}