{
  "type": "Feature",
  "properties": {
    "gn:admin1_code":"15",
    "gn:asciiname":"Nial Nabi",
    "gn:country_code":"IR",
    "gn:dem":71,
    "gn:feature_class":"P",
    "gn:feature_code":"PPL",
    "gn:name":"N\u012b\u0101l Nab\u012b",
    "gn:population":0,
    "gn:timezone":"Asia/Tehran",
    "iso:country":"IR",
    "name:fas_x_preferred":[
        "N\u012b\u0101l Nab\u012b"
    ],
    "wof:name":"Nial Nabi",
    "wof:placetype":"locality"
},
  "geometry": {"coordinates":[48.21667,32.18333],"type":"Point"}
}