{
  "type": "Feature",
  "properties": {
    "gn:admin1_code":"13",
    "gn:asciiname":"Qal`eh-ye Zakaria",
    "gn:country_code":"IR",
    "gn:dem":1320,
    "gn:feature_class":"P",
    "gn:feature_code":"PPL",
    "gn:name":"Qal\u2018eh-ye Z\u0304akar\u012b\u0101",
    "gn:population":0,
    "gn:timezone":"Asia/Tehran",
    "iso:country":"IR",
    "name:fas_x_preferred":[
        "\u0642\u0644\u0639\u0647 \u0630\u06a9\u0631\u06cc\u0627"
    ],
    "name:fas_x_variant":[
        "Qal\u2018eh-ye Z\u0304akar\u012by\u0101",
        "Qal\u2018eh-ye Z\u0304akar\u012b\u0101"
    ],
    "wof:name":"Qal`eh-ye Zakaria",
    "wof:placetype":"locality"
},
  "geometry": {"coordinates":[46.6837,34.6024],"type":"Point"}
}