{
  "type": "Feature",
  "properties": {
    "gn:admin1_code":"41",
    "gn:asciiname":"Akhundan",
    "gn:country_code":"IR",
    "gn:dem":1957,
    "gn:feature_class":"P",
    "gn:feature_code":"PPL",
    "gn:name":"\u0100kh\u016bnd\u0101n",
    "gn:population":0,
    "gn:timezone":"Asia/Tehran",
    "iso:country":"IR",
    "name:fas_x_preferred":[
        "\u0100kh\u016bnd\u0101n"
    ],
    "name:und_x_variant":[
        "Shaft\u0101luist\u0101n",
        "Akhvond\u0101n",
        "Shaftaloostan",
        "Akhownd\u0101n",
        "Shaft\u0101l\u016bhest\u0101n"
    ],
    "wof:name":"Akhundan",
    "wof:placetype":"locality"
},
  "geometry": {"coordinates":[59.59111,32.46722],"type":"Point"}
}