{
  "type": "Feature",
  "properties": {
    "gn:admin1_code":"33",
    "gn:asciiname":"Gonzanaq",
    "gn:country_code":"IR",
    "gn:dem":1772,
    "gn:feature_class":"P",
    "gn:feature_code":"PPL",
    "gn:name":"Gonzanaq",
    "gn:population":0,
    "gn:timezone":"Asia/Tehran",
    "iso:country":"IR",
    "name:fas_x_preferred":[
        "\u06a9\u0646\u0632\u0646\u0642"
    ],
    "name:fas_x_variant":[
        "\u06af\u0646\u0632\u0646\u0642"
    ],
    "name:und_x_variant":[
        "Kanzana",
        "Kanzanagh",
        "Kanzanaq",
        "Konzanaq",
        "Gonzanaq",
        "Gazang"
    ],
    "wof:name":"Gonzanaq",
    "wof:placetype":"locality"
},
  "geometry": {"coordinates":[46.3081,38.3689],"type":"Point"}
}