{
  "type": "Feature",
  "properties": {
    "gn:admin1_code":"28",
    "gn:asciiname":"Hirmand",
    "gn:country_code":"IR",
    "gn:dem":1426,
    "gn:feature_class":"P",
    "gn:feature_code":"PPL",
    "gn:name":"H\u012brmand",
    "gn:population":0,
    "gn:timezone":"Asia/Tehran",
    "iso:country":"IR",
    "name:fas_x_preferred":[
        "\u0647\u06cc\u0631\u0645\u0646\u062f"
    ],
    "name:fas_x_variant":[
        "H\u012brmand"
    ],
    "wof:name":"Hirmand",
    "wof:placetype":"locality"
},
  "geometry": {"coordinates":[51.1814,33.9926],"type":"Point"}
}