{
  "type": "Feature",
  "properties": {
    "gn:admin1_code":"35.0",
    "gn:asciiname":"Margi Chal",
    "gn:country_code":"IR",
    "gn:dem":452,
    "gn:feature_class":"P",
    "gn:feature_code":"PPL",
    "gn:name":"Marg\u012b Ch\u0101l",
    "gn:population":0,
    "gn:timezone":"Asia/Tehran",
    "iso:country":"IR",
    "name:fas_x_preferred":[
        "\u0645\u0650\u0631\u06af \u0686\u0627\u0644"
    ],
    "name:fas_x_variant":[
        "Merg Ch\u0101l",
        "Marg\u012b Ch\u0101l",
        "\u0645\u0631\u06af\u06cc \u0686\u0627\u0644"
    ],
    "wof:name":"Margi Chal",
    "wof:placetype":"locality"
},
  "geometry": {"coordinates":[52.8499,36.2039],"type":"Point"}
}