{
  "type": "Feature",
  "properties": {
    "gn:admin1_code":"42",
    "gn:asciiname":"Kalateh-ye Khuni",
    "gn:country_code":"IR",
    "gn:dem":1883,
    "gn:feature_class":"P",
    "gn:feature_code":"PPL",
    "gn:name":"Kal\u0101teh-ye Kh\u016bn\u012b",
    "gn:population":0,
    "gn:timezone":"Asia/Tehran",
    "iso:country":"IR",
    "name:ara_x_preferred":[
        "\u0643\u0644\u0627\u062a\u0629 \u062e\u0648\u0646\u064a"
    ],
    "name:fas_x_preferred":[
        "\u06a9\u0644\u0627\u062a\u0647 \u062e\u0648\u0646\u06cc"
    ],
    "name:fas_x_variant":[
        "Kal\u0101teh-ye \u1e28\u016bn\u012b",
        "\u06a9\u0644\u0627\u062a\u0647 \u062d\u0648\u0646\u06cc",
        "Kal\u0101teh-ye Kh\u016bn\u012b"
    ],
    "wof:name":"Kalateh-ye Khuni",
    "wof:placetype":"locality"
},
  "geometry": {"coordinates":[59.52452,35.63334000000001],"type":"Point"}
}