{
  "type": "Feature",
  "properties": {
    "gn:admin1_code":"41",
    "gn:asciiname":"Chah Kand",
    "gn:country_code":"IR",
    "gn:dem":1801,
    "gn:feature_class":"P",
    "gn:feature_code":"PPL",
    "gn:name":"Ch\u0101h Kand",
    "gn:population":0,
    "gn:timezone":"Asia/Tehran",
    "iso:country":"IR",
    "name:fas_x_preferred":[
        "\u0686\u06a9\u0646\u062f"
    ],
    "name:fas_x_variant":[
        "Ch\u0101kand",
        "\u0686\u0627\u0647 \u06a9\u0646\u062f",
        "\u0686\u0647\u06a9\u0646\u062f"
    ],
    "name:und_x_variant":[
        "Chahand",
        "Ch\u0101kand",
        "Chakand",
        "\u0686\u06a9\u0646\u062f",
        "Chahkand",
        "Ch\u0101h Kand"
    ],
    "wof:name":"Chah Kand",
    "wof:placetype":"locality"
},
  "geometry": {"coordinates":[59.23477,33.18833],"type":"Point"}
}