{
  "type": "Feature",
  "properties": {
    "gn:admin1_code":"15",
    "gn:asciiname":"Seyyed Shavur",
    "gn:country_code":"IR",
    "gn:dem":37,
    "gn:feature_class":"P",
    "gn:feature_code":"PPL",
    "gn:name":"Seyyed Sh\u0101v\u016br",
    "gn:population":0,
    "gn:timezone":"Asia/Tehran",
    "iso:country":"IR",
    "name:fas_x_preferred":[
        "\u0634\u0627\u0648\u0648\u0631"
    ],
    "name:fas_x_variant":[
        "Sadd-e Sh\u0101v\u016br",
        "Sh\u0101v\u016br",
        "\u0633\u06cc\u062f \u0634\u0627\u0648\u0648\u0631",
        "\u0633\u062f \u0634\u0627\u0648\u0648\u0631"
    ],
    "name:und_x_variant":[
        "Alsad",
        "Sh\u0101h\u016br",
        "Sadd-e Sh\u0101h\u016br",
        "Seyyed Sh\u0101v\u016br"
    ],
    "name:urd_x_preferred":[
        "\u0635\u062f\u062f-\u0634\u0648\u0631"
    ],
    "wof:name":"Seyyed Shavur",
    "wof:placetype":"locality"
},
  "geometry": {"coordinates":[48.45249,31.83212],"type":"Point"}
}