{
  "type": "Feature",
  "properties": {
    "gn:admin1_code":"15",
    "gn:asciiname":"Bandar-e Emam Khomeyni",
    "gn:country_code":"IR",
    "gn:dem":6,
    "gn:feature_class":"P",
    "gn:feature_code":"PPL",
    "gn:name":"Bandar-e Em\u0101m Khomeyn\u012b",
    "gn:population":0,
    "gn:timezone":"Asia/Tehran",
    "iso:country":"IR",
    "name:fas_x_preferred":[
        "\u0633\u0631 \u0628\u0646\u062f\u0631"
    ],
    "name:fas_x_variant":[
        "\u0628\u0646\u062f\u0631 \u0627\u0645\u0627\u0645 \u062e\u0645\u06cc\u0646\u06cc"
    ],
    "name:und_x_variant":[
        "Sar Bandar-e Now",
        "Sar Bandar",
        "Bandar-e Em\u0101m Khomeyn\u012b"
    ],
    "wof:name":"Bandar-e Emam Khomeyni",
    "wof:placetype":"locality"
},
  "geometry": {"coordinates":[49.05221,30.55232],"type":"Point"}
}