{
  "type": "Feature",
  "properties": {
    "gn:admin1_code":"1.0",
    "gn:asciiname":"Hajji Ghaldeh",
    "gn:country_code":"IR",
    "gn:dem":1595,
    "gn:feature_class":"P",
    "gn:feature_code":"PPL",
    "gn:name":"\u1e28\u0101jj\u012b Ghaldeh",
    "gn:population":0,
    "gn:timezone":"Asia/Tehran",
    "iso:country":"IR",
    "name:azb_x_preferred":[
        "\u062d\u0627\u062c\u06cc \u063a\u0644\u062f\u0647"
    ],
    "name:aze_x_preferred":[
        "Hac\u0131q\u0259ld\u0259"
    ],
    "name:ceb_x_preferred":[
        "\u1e28\u0101jj\u012b Ghaldeh"
    ],
    "name:fas_x_preferred":[
        "\u062d\u0627\u062c\u06cc \u063a\u0644\u062f\u0647"
    ],
    "name:fas_x_variant":[
        "\u1e28\u0101jj\u012b Ghaldeh",
        "\u062d\u0627\u062c\u06cc\u200c\u063a\u0644\u062f\u0647"
    ],
    "name:msa_x_preferred":[
        "Hajji Ghaldeh"
    ],
    "name:swe_x_preferred":[
        "\u1e28\u0101jj\u012b Ghaldeh"
    ],
    "wof:name":"Hajji Ghaldeh",
    "wof:placetype":"locality"
},
  "geometry": {"coordinates":[45.4176,36.7556],"type":"Point"}
}