{
  "type": "Feature",
  "properties": {
    "gn:admin1_code":"35",
    "gn:asciiname":"Pesteh Kal",
    "gn:country_code":"IR",
    "gn:dem":1635,
    "gn:feature_class":"P",
    "gn:feature_code":"PPL",
    "gn:name":"Pesteh Kal",
    "gn:population":0,
    "gn:timezone":"Asia/Tehran",
    "iso:country":"IR",
    "name:fas_x_preferred":[
        "\u067e\u0634\u062a\u06af\u0644"
    ],
    "name:fas_x_variant":[
        "\u067e\u0633\u062a\u0647 \u06a9\u0644"
    ],
    "name:und_x_variant":[
        "Poshtgol",
        "Pesteh Kal"
    ],
    "wof:name":"Pesteh Kal",
    "wof:placetype":"locality"
},
  "geometry": {"coordinates":[52.98027,35.96054],"type":"Point"}
}