{
  "type": "Feature",
  "properties": {
    "gn:admin1_code":"25",
    "gn:asciiname":"Yatari-ye `Olya",
    "gn:country_code":"IR",
    "gn:dem":887,
    "gn:feature_class":"P",
    "gn:feature_code":"PPL",
    "gn:name":"Y\u0101tar\u012b-ye \u2018Oly\u0101",
    "gn:population":0,
    "gn:timezone":"Asia/Tehran",
    "iso:country":"IR",
    "name:ara_x_preferred":[
        "\u064a\u0627\u062a\u0631\u064a \u0628\u0627\u0644\u0627"
    ],
    "name:ceb_x_preferred":[
        "Y\u0101tar\u012b-ye \u2018Oly\u0101"
    ],
    "name:fas_x_preferred":[
        "\u064a\u0627\u062a\u0631\u06cc \u0628\u0627\u0644\u0627"
    ],
    "name:fas_x_variant":[
        "Y\u0101ter\u012b-ye B\u0101l\u0101",
        "Y\u0101tar\u012b\u0101b\u0101d-e \u2018Oly\u0101",
        "\u06cc\u0627\u062a\u0631\u06cc \u0622\u0628\u0627\u062f \u0639\u0644\u06cc\u0627",
        "\u06cc\u0627\u062a\u0631\u06cc \u0639\u0644\u06cc\u0627",
        "\u06cc\u0627\u062a\u0631\u06cc \u0628\u0627\u0644\u0627"
    ],
    "name:swe_x_preferred":[
        "Y\u0101tar\u012b-ye \u2018Oly\u0101"
    ],
    "name:und_x_variant":[
        "Y\u0101tr\u012b B\u0101l\u0101"
    ],
    "name:urd_x_preferred":[
        "\u06cc\u0627\u062a\u0631\u06cc-\u0628\u0644\u0627"
    ],
    "wof:name":"Yatari-ye `Olya",
    "wof:placetype":"locality"
},
  "geometry": {"coordinates":[52.46029,35.23097999999999],"type":"Point"}
}