{
  "type": "Feature",
  "properties": {
    "gn:admin1_code":"7",
    "gn:asciiname":"Meleh Galeh-ye Jadid",
    "gn:country_code":"IR",
    "gn:dem":1932,
    "gn:feature_class":"P",
    "gn:feature_code":"PPL",
    "gn:name":"Meleh G\u0101leh-ye Jad\u012bd",
    "gn:population":0,
    "gn:timezone":"Asia/Tehran",
    "iso:country":"IR",
    "name:fas_x_preferred":[
        "\u0645\u0644\u0647 \u06af\u0627\u0644\u0647 \u062c\u062f\u06cc\u062f"
    ],
    "name:fas_x_variant":[
        "Moleh G\u0101leh",
        "Meleh G\u0101leh-ye Jad\u012bd"
    ],
    "name:und_x_variant":[
        "Mol-e G\u0101leh"
    ],
    "wof:name":"Meleh Galeh-ye Jadid",
    "wof:placetype":"locality"
},
  "geometry": {"coordinates":[52.2654,29.3207],"type":"Point"}
}