{
  "type": "Feature",
  "properties": {
    "gn:admin1_code":"33",
    "gn:asciiname":"Tubin",
    "gn:country_code":"IR",
    "gn:dem":1113,
    "gn:elevation":"0.0",
    "gn:feature_class":"P",
    "gn:feature_code":"PPL",
    "gn:name":"T\u016bb\u012bn",
    "gn:population":0,
    "gn:timezone":"Asia/Tehran",
    "iso:country":"IR",
    "name:fas_x_preferred":[
        "\u062a\u0648\u0628\u06cc\u0646"
    ],
    "name:fas_x_variant":[
        "T\u016bb\u012bn"
    ],
    "wof:name":"Tubin",
    "wof:placetype":"locality"
},
  "geometry": {"coordinates":[47.37993,38.98287],"type":"Point"}
}