{
  "type": "Feature",
  "properties": {
    "gn:admin1_code":"35.0",
    "gn:asciiname":"Pitka",
    "gn:country_code":"IR",
    "gn:dem":58,
    "gn:feature_class":"P",
    "gn:feature_code":"PPL",
    "gn:name":"P\u012btk\u0101",
    "gn:population":0,
    "gn:timezone":"Asia/Tehran",
    "iso:country":"IR",
    "name:fas_x_preferred":[
        "\u067e\u064a\u062a\u0643\u0627"
    ],
    "name:fas_x_variant":[
        "P\u012btk\u0101",
        "Petk\u0101",
        "\u067e\u0650\u062a\u0643\u0627"
    ],
    "wof:name":"Pitka",
    "wof:placetype":"locality"
},
  "geometry": {"coordinates":[52.72725,36.36981],"type":"Point"}
}