{
  "type": "Feature",
  "properties": {
    "gn:admin1_code":"35",
    "gn:asciiname":"Sang Kiab Sar",
    "gn:country_code":"IR",
    "gn:dem":-1,
    "gn:feature_class":"P",
    "gn:feature_code":"PPL",
    "gn:name":"Sang K\u012b\u0101b Sar",
    "gn:population":0,
    "gn:timezone":"Asia/Tehran",
    "iso:country":"IR",
    "name:fas_x_preferred":[
        "\u0633\u064e\u0646\u06af \u0643\u064a\u0627\u0628 \u0633\u064e\u0631"
    ],
    "wof:name":"Sang Kiab Sar",
    "wof:placetype":"locality"
},
  "geometry": {"coordinates":[53.66667,36.71667],"type":"Point"}
}