{
  "type": "Feature",
  "properties": {
    "gn:admin1_code":"4.0",
    "gn:asciiname":"Chah-e Allahdad",
    "gn:country_code":"IR",
    "gn:dem":1166,
    "gn:feature_class":"P",
    "gn:feature_code":"PPLF",
    "gn:name":"Ch\u0101h-e All\u0101hd\u0101d",
    "gn:population":0,
    "gn:timezone":"Asia/Tehran",
    "iso:country":"IR",
    "name:fas_x_preferred":[
        "\u0686\u0627\u0647 \u0627\u0644\u0644\u0651\u0647 \u062f\u0627\u062f"
    ],
    "name:fas_x_variant":[
        "\u0686\u0627\u0647 \u0627\u0644\u0647 \u062f\u0627\u062f"
    ],
    "name:und_x_variant":[
        "Ch\u0101h-e All\u0101hd\u0101d"
    ],
    "wof:name":"Chah-e Allahdad",
    "wof:placetype":"locality"
},
  "geometry": {"coordinates":[61.90044,27.35913],"type":"Point"}
}