{
  "type": "Feature",
  "properties": {
    "gn:admin1_code":"1",
    "gn:asciiname":"Dash Khaneh",
    "gn:country_code":"IR",
    "gn:dem":1278,
    "gn:feature_class":"P",
    "gn:feature_code":"PPL",
    "gn:name":"D\u0101sh Kh\u0101neh",
    "gn:population":0,
    "gn:timezone":"Asia/Tehran",
    "iso:country":"IR",
    "name:fas_x_preferred":[
        "\u062f\u0627\u0634\u062e\u0627\u0646\u0650\u0647"
    ],
    "name:fas_x_variant":[
        "\u062f\u0627\u0634 \u062e\u0627\u0646\u0647",
        "D\u0101shkh\u0101neh",
        "D\u0101sh Kh\u0101neh"
    ],
    "wof:name":"Dash Khaneh",
    "wof:placetype":"locality"
},
  "geometry": {"coordinates":[45.6916,37.0176],"type":"Point"}
}