{
  "type": "Feature",
  "properties": {
    "gn:admin1_code":"4.0",
    "gn:asciiname":"Deh-e Molla `Abdollah",
    "gn:country_code":"IR",
    "gn:dem":482,
    "gn:feature_class":"P",
    "gn:feature_code":"PPL",
    "gn:name":"Deh-e Moll\u0101 \u2018Abdoll\u0101h",
    "gn:population":0,
    "gn:timezone":"Asia/Tehran",
    "iso:country":"IR",
    "name:fas_x_preferred":[
        "\u062f\u0647 \u0645\u0644\u0627 \u0639\u0628\u062f\u0627\u0644\u0644\u0647"
    ],
    "name:fas_x_variant":[
        "Deh-e Moll\u0101 \u2018Abdoll\u0101h",
        "\u0645\u0644\u0627 \u0639\u0628\u062f\u0627\u0644\u0644\u0647"
    ],
    "name:und_x_variant":[
        "Moll\u0101 \u2018Abdoll\u0101h"
    ],
    "wof:name":"Deh-e Molla `Abdollah",
    "wof:placetype":"locality"
},
  "geometry": {"coordinates":[61.7411,31.1899],"type":"Point"}
}