{
  "type": "Feature",
  "properties": {
    "gn:admin1_code":"10",
    "gn:asciiname":"Sofreh",
    "gn:country_code":"IR",
    "gn:dem":401,
    "gn:feature_class":"P",
    "gn:feature_code":"PPL",
    "gn:name":"Sofreh",
    "gn:population":0,
    "gn:timezone":"Asia/Tehran",
    "iso:country":"IR",
    "name:fas_x_preferred":[
        "\u0633\u0641\u0631\u0647"
    ],
    "wof:name":"Sofreh",
    "wof:placetype":"locality"
},
  "geometry": {"coordinates":[47.0635,32.786],"type":"Point"}
}