{
  "type": "Feature",
  "properties": {
    "gn:admin1_code":"42",
    "gn:asciiname":"Neyzeh",
    "gn:country_code":"IR",
    "gn:dem":940,
    "gn:feature_class":"P",
    "gn:feature_code":"PPL",
    "gn:name":"Neyzeh",
    "gn:population":0,
    "gn:timezone":"Asia/Tehran",
    "iso:country":"IR",
    "name:fas_x_preferred":[
        "\u0646\u064a\u0632\u0647"
    ],
    "name:und_x_variant":[
        "N\u012bzeh",
        "Neyzeh"
    ],
    "wof:name":"Neyzeh",
    "wof:placetype":"locality"
},
  "geometry": {"coordinates":[59.67916,36.30566],"type":"Point"}
}