{
  "type": "Feature",
  "properties": {
    "gn:admin1_code":"4.0",
    "gn:asciiname":"Mirabad",
    "gn:cc2":"IR",
    "gn:country_code":"IR",
    "gn:dem":1256,
    "gn:feature_class":"P",
    "gn:feature_code":"PPL",
    "gn:name":"M\u012br\u0101b\u0101d",
    "gn:population":0,
    "gn:timezone":"Asia/Tehran",
    "iso:country":"IR",
    "name:fas_x_preferred":[
        "M\u012br\u0101b\u0101d"
    ],
    "name:und_x_variant":[
        "Mehr \u0100b\u0101d"
    ],
    "wof:name":"Mirabad",
    "wof:placetype":"locality"
},
  "geometry": {"coordinates":[61.64861,27.5525],"type":"Point"}
}