{
  "type": "Feature",
  "properties": {
    "gn:admin1_code":"8",
    "gn:asciiname":"Tuleh Gund",
    "gn:country_code":"IR",
    "gn:dem":1058,
    "gn:feature_class":"P",
    "gn:feature_code":"PPL",
    "gn:name":"T\u016bleh G\u016bnd",
    "gn:population":0,
    "gn:timezone":"Asia/Tehran",
    "iso:country":"IR",
    "name:fas_x_preferred":[
        "T\u016bleh G\u016bnd"
    ],
    "wof:name":"Tuleh Gund",
    "wof:placetype":"locality"
},
  "geometry": {"coordinates":[48.83028,37.49778],"type":"Point"}
}