{
  "type": "Feature",
  "properties": {
    "gn:admin1_code":"42",
    "gn:asciiname":"Sandan",
    "gn:country_code":"IR",
    "gn:dem":1833,
    "gn:feature_class":"P",
    "gn:feature_code":"PPL",
    "gn:name":"Sand\u0101n",
    "gn:population":0,
    "gn:timezone":"Asia/Tehran",
    "iso:country":"IR",
    "name:ceb_x_preferred":[
        "Sandan"
    ],
    "name:fas_x_preferred":[
        "Sand\u0101n"
    ],
    "name:fas_x_variant":[
        "\u0633\u0646\u062f\u0627\u0646"
    ],
    "name:ita_x_preferred":[
        "Sandan"
    ],
    "name:swe_x_preferred":[
        "Sandan"
    ],
    "name:und_x_variant":[
        "\u0633\u0646\u062f\u0627\u0646"
    ],
    "wof:name":"Sandan",
    "wof:placetype":"locality"
},
  "geometry": {"coordinates":[58.78529,33.75386],"type":"Point"}
}