{
  "type": "Feature",
  "properties": {
    "gn:admin1_code":"4.0",
    "gn:asciiname":"Anjiri",
    "gn:country_code":"IR",
    "gn:dem":1783,
    "gn:feature_class":"P",
    "gn:feature_code":"PPL",
    "gn:name":"Anj\u012br\u012b",
    "gn:population":0,
    "gn:timezone":"Asia/Tehran",
    "iso:country":"IR",
    "name:fas_x_preferred":[
        "\u0627\u0646\u062c\u06cc\u0631\u06cc"
    ],
    "name:und_x_variant":[
        "Anj\u012br\u012b"
    ],
    "wof:name":"Anjiri",
    "wof:placetype":"locality"
},
  "geometry": {"coordinates":[61.84115,27.93265],"type":"Point"}
}