{
  "type": "Feature",
  "properties": {
    "gn:admin1_code":"4.0",
    "gn:asciiname":"Hushag-e Bala",
    "gn:country_code":"IR",
    "gn:dem":1184,
    "gn:feature_class":"P",
    "gn:feature_code":"PPL",
    "gn:name":"H\u016bshag-e B\u0101l\u0101",
    "gn:population":0,
    "gn:timezone":"Asia/Tehran",
    "iso:country":"IR",
    "name:fas_x_preferred":[
        "\u0647\u0648\u0634\u06af \u0628\u0627\u0644\u0627"
    ],
    "name:und_x_variant":[
        "H\u016bshag-e B\u0101l\u0101"
    ],
    "wof:name":"Hushag-e Bala",
    "wof:placetype":"locality"
},
  "geometry": {"coordinates":[62.29981,27.4072],"type":"Point"}
}