{
  "type": "Feature",
  "properties": {
    "gn:admin1_code":"7",
    "gn:asciiname":"Qazian",
    "gn:country_code":"IR",
    "gn:dem":2140,
    "gn:feature_class":"P",
    "gn:feature_code":"PPL",
    "gn:name":"Q\u0101\u1e95\u012b\u0101n",
    "gn:population":0,
    "gn:timezone":"Asia/Tehran",
    "iso:country":"IR",
    "name:fas_x_preferred":[
        "Q\u0101\u1e95\u012b\u0101n-e P\u0101\u2019\u012bn"
    ],
    "name:fas_x_variant":[
        "Q\u0101\u1e95\u012b\u0101n",
        "\u0642\u0627\u0636\u06cc\u0627\u0646",
        "Gh\u0101z\u012b\u0101n-e P\u0101\u2019\u012bn",
        "Qa\u015fr-e Jad\u012bd",
        "Q\u0101\u1e95\u012b\u0101n-e Sofl\u00e1",
        "\u0642\u0627\u0636\u06cc\u0627\u0646 \u0633\u0641\u0644\u06cc"
    ],
    "name:msa_x_preferred":[
        "Qazian-e Sofla"
    ],
    "wof:name":"Qazian",
    "wof:placetype":"locality"
},
  "geometry": {"coordinates":[53.12453000000001,30.48153],"type":"Point"}
}