{
  "type": "Feature",
  "properties": {
    "gn:admin1_code":"8",
    "gn:asciiname":"Mazukaleh Poshteh-ye Bala",
    "gn:country_code":"IR",
    "gn:dem":214,
    "gn:feature_class":"P",
    "gn:feature_code":"PPL",
    "gn:name":"M\u0101z\u016bkaleh Poshteh-ye B\u0101l\u0101",
    "gn:population":0,
    "gn:timezone":"Asia/Tehran",
    "iso:country":"IR",
    "name:fas_x_preferred":[
        "M\u0101zokaleh Poshteh-ye B\u0101l\u0101"
    ],
    "name:fas_x_variant":[
        "M\u0101z\u016bkaleh Poshteh-ye B\u0101l\u0101",
        "\u0645\u0627\u0632\u0648\u06a9\u0644\u0647 \u067e\u0634\u062a\u0647 \u0628\u0627\u0644\u0627"
    ],
    "name:und_x_variant":[
        "M\u0101zokaleh",
        "\u0645\u0627\u0632\u0648\u06a9\u0644\u0647 \u067e\u0634\u062a\u0647 \u0628\u0627\u0644\u0627"
    ],
    "wof:name":"Mazukaleh Poshteh-ye Bala",
    "wof:placetype":"locality"
},
  "geometry": {"coordinates":[50.39878,37.00562],"type":"Point"}
}