{
  "type": "Feature",
  "properties": {
    "gn:admin1_code":"42.0",
    "gn:asciiname":"Sami`abad-e Pa'in",
    "gn:country_code":"IR",
    "gn:dem":777,
    "gn:feature_class":"P",
    "gn:feature_code":"PPL",
    "gn:name":"Sam\u012b\u2018\u0101b\u0101d-e P\u0101\u2019\u012bn",
    "gn:population":0,
    "gn:timezone":"Asia/Tehran",
    "iso:country":"IR",
    "name:fas_x_preferred":[
        "Sam\u012b\u2018\u0101b\u0101d-e P\u0101\u2019\u012bn"
    ],
    "wof:name":"Sami`abad-e Pa'in",
    "wof:placetype":"locality"
},
  "geometry": {"coordinates":[60.91028000000001,35.13194],"type":"Point"}
}