{
  "type": "Feature",
  "properties": {
    "gn:admin1_code":"4",
    "gn:asciiname":"Palushi",
    "gn:country_code":"IR",
    "gn:dem":1404,
    "gn:feature_class":"P",
    "gn:feature_code":"PPL",
    "gn:name":"Pal\u016bsh\u012b",
    "gn:population":0,
    "gn:timezone":"Asia/Tehran",
    "iso:country":"IR",
    "name:fas_x_preferred":[
        "\u067e\u0644\u0648\u0634\u06cc"
    ],
    "name:fas_x_variant":[
        "Pal\u016bsh\u012b"
    ],
    "wof:name":"Palushi",
    "wof:placetype":"locality"
},
  "geometry": {"coordinates":[61.17581,27.06156],"type":"Point"}
}