{
  "type": "Feature",
  "properties": {
    "gn:admin1_code":"3",
    "gn:asciiname":"Bustan",
    "gn:country_code":"IR",
    "gn:dem":1129,
    "gn:feature_class":"P",
    "gn:feature_code":"PPL",
    "gn:name":"B\u016bst\u0101n",
    "gn:population":0,
    "gn:timezone":"Asia/Tehran",
    "iso:country":"IR",
    "name:fas_x_preferred":[
        "B\u016bst\u0101n"
    ],
    "name:fas_x_variant":[
        "\u0628\u0648\u0633\u062a\u0627\u0646"
    ],
    "wof:name":"Bustan",
    "wof:placetype":"locality"
},
  "geometry": {"coordinates":[50.38804,31.76005],"type":"Point"}
}