{
  "type": "Feature",
  "properties": {
    "gn:admin1_code":"8.0",
    "gn:asciiname":"Vazmi",
    "gn:country_code":"IR",
    "gn:dem":1620,
    "gn:feature_class":"P",
    "gn:feature_code":"PPL",
    "gn:name":"Vazm\u012b",
    "gn:population":0,
    "gn:timezone":"Asia/Tehran",
    "iso:country":"IR",
    "name:fas_x_preferred":[
        "\u0648\u0632\u0645\u06cc"
    ],
    "name:msa_x_preferred":[
        "Vazmi"
    ],
    "name:ukr_x_preferred":[
        "\u0412\u0430\u0437\u043c\u0456"
    ],
    "name:und_x_variant":[
        "Vazm\u012b"
    ],
    "wof:name":"Vazmi",
    "wof:placetype":"locality"
},
  "geometry": {"coordinates":[48.83969,37.40153],"type":"Point"}
}