{
  "type": "Feature",
  "properties": {
    "gn:admin1_code":"0",
    "gn:asciiname":"Dar Gaz",
    "gn:country_code":"IR",
    "gn:dem":613,
    "gn:feature_class":"P",
    "gn:feature_code":"PPL",
    "gn:name":"Dar Gaz",
    "gn:population":0,
    "gn:timezone":"Asia/Tehran",
    "iso:country":"IR",
    "name:fas_x_preferred":[
        "\u062f\u0631 \u06af\u0632"
    ],
    "wof:name":"Dar Gaz",
    "wof:placetype":"locality"
},
  "geometry": {"coordinates":[57.5943,27.0057],"type":"Point"}
}