{
  "type": "Feature",
  "properties": {
    "gn:admin1_code":"35.0",
    "gn:asciiname":"Towshkun",
    "gn:country_code":"IR",
    "gn:dem":30,
    "gn:feature_class":"P",
    "gn:feature_code":"PPL",
    "gn:name":"Towshk\u016bn",
    "gn:population":0,
    "gn:timezone":"Asia/Tehran",
    "iso:country":"IR",
    "name:fas_x_preferred":[
        "\u062a\u0648\u0634\u06a9\u0648\u0646"
    ],
    "name:fas_x_variant":[
        "\u062a\u0634\u06a9\u0648\u0646"
    ],
    "name:und_x_variant":[
        "Tashkadan",
        "Towshk\u016bn",
        "Toshk\u016bn"
    ],
    "wof:name":"Towshkun",
    "wof:placetype":"locality"
},
  "geometry": {"coordinates":[50.88429,36.74375],"type":"Point"}
}