{
  "type": "Feature",
  "properties": {
    "gn:admin1_code":"7",
    "gn:asciiname":"Sokunatgah-e `Ashayeri-ye Seh Darreh",
    "gn:country_code":"IR",
    "gn:dem":1173,
    "gn:feature_class":"P",
    "gn:feature_code":"PPL",
    "gn:name":"Sok\u016bnatg\u0101h-e \u2018Ash\u0101yer\u012b-ye Seh Darreh",
    "gn:population":0,
    "gn:timezone":"Asia/Tehran",
    "iso:country":"IR",
    "name:fas_x_preferred":[
        "\u0633\u0647\u0651 \u062f\u0631\u0647"
    ],
    "name:fas_x_variant":[
        "\u0633\u06a9\u0648\u0646\u062a\u06af\u0627\u0647 \u0639\u0634\u0627\u06cc\u0631\u06cc \u0633\u0647 \u062f\u0631\u0647"
    ],
    "name:und_x_variant":[
        "Sehh Darreh",
        "Sok\u016bnatg\u0101h-e \u2018Ash\u0101yer\u012b-ye Seh Darreh"
    ],
    "wof:name":"Sokunatgah-e `Ashayeri-ye Seh Darreh",
    "wof:placetype":"locality"
},
  "geometry": {"coordinates":[53.65205,28.488],"type":"Point"}
}