{
  "type": "Feature",
  "properties": {
    "gn:admin1_code":"8",
    "gn:asciiname":"Kurbur",
    "gn:country_code":"IR",
    "gn:dem":623,
    "gn:feature_class":"P",
    "gn:feature_code":"PPL",
    "gn:name":"K\u016brb\u016br",
    "gn:population":0,
    "gn:timezone":"Asia/Tehran",
    "iso:country":"IR",
    "name:fas_x_preferred":[
        "\u06a9\u0648\u0631\u0628\u0648\u0631"
    ],
    "name:fas_x_variant":[
        "K\u016brb\u016br"
    ],
    "wof:name":"Kurbur",
    "wof:placetype":"locality"
},
  "geometry": {"coordinates":[49.0498,37.37152],"type":"Point"}
}