{
  "type": "Feature",
  "properties": {
    "gn:admin1_code":"15",
    "gn:asciiname":"Khamzeh-ye `Olya",
    "gn:country_code":"IR",
    "gn:dem":15,
    "gn:feature_class":"P",
    "gn:feature_code":"PPL",
    "gn:name":"Khamzeh-ye \u2018Oly\u0101",
    "gn:population":0,
    "gn:timezone":"Asia/Tehran",
    "iso:country":"IR",
    "name:fas_x_preferred":[
        "\u062d\u0645\u0632\u0647 \u0639\u0644\u06cc\u0627"
    ],
    "name:fas_x_variant":[
        "Khamzeh-ye B\u0101l\u0101",
        "\u1e28amzeh-ye \u2018Oly\u0101",
        "\u062e\u0645\u0632\u0647 \u0639\u0644\u06cc\u0627"
    ],
    "name:und_x_variant":[
        "Khamzeh-ye \u2018Oly\u0101"
    ],
    "wof:name":"Khamzeh-ye `Olya",
    "wof:placetype":"locality"
},
  "geometry": {"coordinates":[49.07925,30.71082],"type":"Point"}
}