{
  "type": "Feature",
  "properties": {
    "gn:admin1_code":"34.0",
    "gn:asciiname":"Aqcheh Kahriz",
    "gn:country_code":"IR",
    "gn:dem":1683,
    "gn:feature_class":"P",
    "gn:feature_code":"PPL",
    "gn:name":"\u0100qcheh Kahr\u012bz",
    "gn:population":0,
    "gn:timezone":"Asia/Tehran",
    "iso:country":"IR",
    "name:aze_x_preferred":[
        "A\u011fcak\u0259hriz"
    ],
    "name:fas_x_preferred":[
        "\u0622\u0642\u0686\u0647 \u0643\u0647\u0631\u064a\u0632"
    ],
    "name:fas_x_variant":[
        "\u0100qcheh Kahr\u012bz",
        "\u0622\u0642\u0686\u0647 \u06a9\u0647\u0631\u06cc\u0632"
    ],
    "name:ukr_x_preferred":[
        "\u0410\u043a\u0447\u0435-\u041a\u0430\u0433\u0440\u0456\u0437"
    ],
    "name:und_x_variant":[
        "\u0100qjeh Kahr\u012bz"
    ],
    "wof:name":"Aqcheh Kahriz",
    "wof:placetype":"locality"
},
  "geometry": {"coordinates":[49.25899999999999,34.6864],"type":"Point"}
}