{
  "type": "Feature",
  "properties": {
    "gn:admin1_code":"29.0",
    "gn:asciiname":"Hoseynabad-e Bala",
    "gn:country_code":"IR",
    "gn:dem":1755,
    "gn:feature_class":"P",
    "gn:feature_code":"PPL",
    "gn:name":"\u1e28oseyn\u0101b\u0101d-e B\u0101l\u0101",
    "gn:population":0,
    "gn:timezone":"Asia/Tehran",
    "iso:country":"IR",
    "name:fas_x_preferred":[
        "\u1e28oseyn\u0101b\u0101d-e B\u0101l\u0101"
    ],
    "wof:name":"Hoseynabad-e Bala",
    "wof:placetype":"locality"
},
  "geometry": {"coordinates":[55.60889,29.59806],"type":"Point"}
}