{
  "type": "Feature",
  "properties": {
    "gn:admin1_code":"16.0",
    "gn:asciiname":"Ayaghchi",
    "gn:country_code":"IR",
    "gn:dem":1656,
    "gn:feature_class":"P",
    "gn:feature_code":"PPL",
    "gn:name":"\u0100y\u0101ghch\u012b",
    "gn:population":0,
    "gn:timezone":"Asia/Tehran",
    "iso:country":"IR",
    "name:fas_x_preferred":[
        "\u0622\u064a\u0627\u062e\u0686\u06cc"
    ],
    "name:fas_x_variant":[
        "\u0627\u064a\u0627\u063a\u0686\u06cc",
        "\u0100y\u0101khch\u012b",
        "Ay\u0101ghch\u012b",
        "\u0622\u06cc\u0627\u0642\u0686\u06cc"
    ],
    "name:und_x_variant":[
        "\u0100y\u0101ghch\u012b"
    ],
    "wof:name":"Ayaghchi",
    "wof:placetype":"locality"
},
  "geometry": {"coordinates":[46.77226,36.39006],"type":"Point"}
}