{
  "type": "Feature",
  "properties": {
    "gn:admin1_code":"1",
    "gn:asciiname":"Guzik",
    "gn:country_code":"IR",
    "gn:dem":2010,
    "gn:feature_class":"P",
    "gn:feature_code":"PPL",
    "gn:name":"G\u016bz\u012bk",
    "gn:population":0,
    "gn:timezone":"Asia/Tehran",
    "iso:country":"IR",
    "name:fas_x_preferred":[
        "G\u016bz\u012bk"
    ],
    "wof:name":"Guzik",
    "wof:placetype":"locality"
},
  "geometry": {"coordinates":[44.53333,38.25],"type":"Point"}
}