{
  "type": "Feature",
  "properties": {
    "gn:admin1_code":"1",
    "gn:asciiname":"Guzik",
    "gn:country_code":"IR",
    "gn:dem":2010,
    "gn:feature_class":"P",
    "gn:feature_code":"PPL",
    "gn:name":"G\u016bz\u012bk",
    "gn:population":0,
    "gn:timezone":"Asia/Tehran",
    "iso:country":"IR",
    "name:ces_x_preferred":[
        "Guzik"
    ],
    "name:deu_x_preferred":[
        "Guzik"
    ],
    "name:fas_x_preferred":[
        "G\u016bz\u012bk"
    ],
    "name:fas_x_variant":[
        "\u06af\u0648\u0632\u06cc\u06a9"
    ],
    "name:nds_x_preferred":[
        "Guzik"
    ],
    "name:rus_x_preferred":[
        "\u0413\u0443\u0437\u0438\u043a"
    ],
    "name:ukr_x_preferred":[
        "\u0413\u0443\u0437\u0438\u043a"
    ],
    "wof:name":"Guzik",
    "wof:placetype":"locality"
},
  "geometry": {"coordinates":[44.53333,38.25],"type":"Point"}
}