{
  "type": "Feature",
  "properties": {
    "gn:admin1_code":"40",
    "gn:asciiname":"Ahmadabad",
    "gn:country_code":"IR",
    "gn:dem":773,
    "gn:feature_class":"P",
    "gn:feature_code":"PPL",
    "gn:name":"A\u1e29mad\u0101b\u0101d",
    "gn:population":0,
    "gn:timezone":"Asia/Tehran",
    "iso:country":"IR",
    "name:fas_x_preferred":[
        "A\u1e29mad\u0101b\u0101d-e Dastgerd\u0101n"
    ],
    "name:fas_x_variant":[
        "A\u1e29mad\u0101b\u0101d",
        "\u0627\u062d\u0645\u062f \u0622\u0628\u0627\u062f \u062f\u0633\u062a\u06af\u0631\u062f\u0627\u0646",
        "\u0627\u062d\u0645\u062f \u0622\u0628\u0627\u062f"
    ],
    "name:und_x_variant":[
        "\u0627\u062d\u0645\u062f \u0622\u0628\u0627\u062f \u062f\u0633\u062a\u06af\u0631\u062f\u0627\u0646"
    ],
    "wof:name":"Ahmadabad",
    "wof:placetype":"locality"
},
  "geometry": {"coordinates":[56.9523,34.37304],"type":"Point"}
}