{
  "type": "Feature",
  "properties": {
    "gn:admin1_code":"35.0",
    "gn:asciiname":"Dehgah",
    "gn:country_code":"IR",
    "gn:dem":446,
    "gn:feature_class":"P",
    "gn:feature_code":"PPLF",
    "gn:name":"Dehg\u0101h",
    "gn:population":0,
    "gn:timezone":"Asia/Tehran",
    "iso:country":"IR",
    "name:fas_x_preferred":[
        "Do G\u0101h"
    ],
    "name:fas_x_variant":[
        "\u062f\u0648 \u06af\u0627\u0647",
        "\u062f\u0647\u06af\u0627\u0647"
    ],
    "name:und_x_variant":[
        "\u062f\u0648 \u06af\u0627\u0647",
        "Dehg\u0101h"
    ],
    "wof:name":"Dehgah",
    "wof:placetype":"locality"
},
  "geometry": {"coordinates":[50.88723,36.67247],"type":"Point"}
}