{
  "type": "Feature",
  "properties": {
    "gn:admin1_code":"42",
    "gn:asciiname":"Salimabad",
    "gn:country_code":"IR",
    "gn:dem":1001,
    "gn:feature_class":"P",
    "gn:feature_code":"PPL",
    "gn:name":"Sal\u012bm\u0101b\u0101d",
    "gn:population":0,
    "gn:timezone":"Asia/Tehran",
    "iso:country":"IR",
    "name:fas_x_preferred":[
        "Sal\u012bm\u0101b\u0101d"
    ],
    "wof:name":"Salimabad",
    "wof:placetype":"locality"
},
  "geometry": {"coordinates":[59.88333000000001,36.31667],"type":"Point"}
}