{
  "type": "Feature",
  "properties": {
    "gn:admin1_code":"9.0",
    "gn:asciiname":"Akleh",
    "gn:country_code":"IR",
    "gn:dem":1691,
    "gn:feature_class":"P",
    "gn:feature_code":"PPL",
    "gn:name":"Akleh",
    "gn:population":0,
    "gn:timezone":"Asia/Tehran",
    "iso:country":"IR",
    "name:ara_x_preferred":[
        "\u0627\u0643\u0644\u0629"
    ],
    "name:ceb_x_preferred":[
        "Akleh"
    ],
    "name:fas_x_preferred":[
        "\u0627\u06a9\u0644\u0647"
    ],
    "name:fas_x_variant":[
        "\u0647\u064e\u0631\u0650\u064a\u0627\u0646 \u0627\u064e\u0643\u0644\u0650\u0647"
    ],
    "name:msa_x_preferred":[
        "Akleh"
    ],
    "name:swe_x_preferred":[
        "Akleh"
    ],
    "name:und_x_variant":[
        "Harey\u0101n Akleh",
        "Aquel"
    ],
    "wof:name":"Akleh",
    "wof:placetype":"locality"
},
  "geometry": {"coordinates":[49.08341,35.20369],"type":"Point"}
}