{
  "type": "Feature",
  "properties": {
    "gn:admin1_code":"33",
    "gn:asciiname":"Takanlu-ye Sofla",
    "gn:country_code":"IR",
    "gn:dem":1757,
    "gn:feature_class":"P",
    "gn:feature_code":"PPL",
    "gn:name":"Tak\u0101nl\u016b-ye Sofl\u00e1",
    "gn:population":0,
    "gn:timezone":"Asia/Tehran",
    "iso:country":"IR",
    "name:azb_x_preferred":[
        "\u0622\u0634\u0627\u063a\u0627 \u062a\u06cc\u06a9\u0627\u0646\u0644\u06cc"
    ],
    "name:fas_x_preferred":[
        "\u062a\u06a9\u0627\u0646\u0644\u0648\u06cc \u0633\u0641\u0644\u06cc"
    ],
    "name:fas_x_variant":[
        "Tak\u0101nl\u016b-ye Sofl\u00e1",
        "\u062a\u06a9\u0627\u0646\u0644\u0648 \u0633\u0641\u0644\u06cc"
    ],
    "name:msa_x_preferred":[
        "Takanlu-ye Sofla"
    ],
    "wof:name":"Takanlu-ye Sofla",
    "wof:placetype":"locality"
},
  "geometry": {"coordinates":[46.8882,37.2318],"type":"Point"}
}