{
  "type": "Feature",
  "properties": {
    "gn:admin1_code":"42",
    "gn:asciiname":"Ojnurd",
    "gn:country_code":"IR",
    "gn:dem":1376,
    "gn:feature_class":"P",
    "gn:feature_code":"PPL",
    "gn:name":"Ojn\u016brd",
    "gn:population":0,
    "gn:timezone":"Asia/Tehran",
    "iso:country":"IR",
    "name:ceb_x_preferred":[
        "Ojnowrd"
    ],
    "name:fas_x_preferred":[
        "\u0627\u062c\u0646\u0648\u0631\u062f"
    ],
    "name:swe_x_preferred":[
        "Ojnowrd"
    ],
    "name:und_x_variant":[
        "\u016ajn\u016brd",
        "Ojn\u016brd"
    ],
    "wof:name":"Ojnurd",
    "wof:placetype":"locality"
},
  "geometry": {"coordinates":[57.2394,35.77655],"type":"Point"}
}