{
  "type": "Feature",
  "properties": {
    "gn:admin1_code":"5",
    "gn:asciiname":"Kuh-e Tangti",
    "gn:country_code":"IR",
    "gn:dem":2207,
    "gn:feature_class":"P",
    "gn:feature_code":"PPL",
    "gn:name":"K\u016bh-e Tangt\u012b",
    "gn:population":0,
    "gn:timezone":"Asia/Tehran",
    "iso:country":"IR",
    "name:fas_x_preferred":[
        "\u0643\u0648\u0647\u0650 \u062a\u064e\u0646\u06af\u062a\u06cc"
    ],
    "name:fas_x_variant":[
        "K\u016bh-e Tangt\u012b"
    ],
    "wof:name":"Kuh-e Tangti",
    "wof:placetype":"locality"
},
  "geometry": {"coordinates":[51.16944,30.94639],"type":"Point"}
}