{
  "type": "Feature",
  "properties": {
    "gn:admin1_code":"16.0",
    "gn:asciiname":"Mirabad-e `Olya",
    "gn:country_code":"IR",
    "gn:dem":1639,
    "gn:elevation":"0.0",
    "gn:feature_class":"P",
    "gn:feature_code":"PPL",
    "gn:name":"M\u012br\u0101b\u0101d-e \u2018Oly\u0101",
    "gn:population":0,
    "gn:timezone":"Asia/Tehran",
    "iso:country":"IR",
    "name:fas_x_preferred":[
        "\u0645\u064a\u0631\u0627\u0628\u0627\u062f\u0650 \u0628\u0627\u0644\u0627"
    ],
    "name:fas_x_variant":[
        "\u0645\u06cc\u0631\u0622\u0628\u0627\u062f \u0639\u0644\u06cc\u0627",
        "M\u012br\u0101b\u0101d-e B\u0101l\u0101",
        "M\u012br\u0101b\u0101d-e \u2018Oly\u0101"
    ],
    "wof:name":"Mirabad-e `Olya",
    "wof:placetype":"locality"
},
  "geometry": {"coordinates":[45.8304,36.0588],"type":"Point"}
}