{
  "type": "Feature",
  "properties": {
    "gn:admin1_code":"11",
    "gn:asciiname":"Surak",
    "gn:cc2":"IR",
    "gn:country_code":"IR",
    "gn:dem":35,
    "gn:feature_class":"P",
    "gn:feature_code":"PPL",
    "gn:name":"S\u016brak",
    "gn:population":0,
    "gn:timezone":"Asia/Tehran",
    "iso:country":"IR",
    "name:cat_x_preferred":[
        "Surak"
    ],
    "name:fas_x_preferred":[
        "S\u016brak"
    ],
    "name:ita_x_preferred":[
        "Surak"
    ],
    "name:nld_x_preferred":[
        "Surak"
    ],
    "name:und_x_variant":[
        "S\u016br\u0101q",
        "S\u016brag"
    ],
    "wof:name":"Surak",
    "wof:placetype":"locality"
},
  "geometry": {"coordinates":[58.84083,25.72],"type":"Point"}
}