{
  "type": "Feature",
  "properties": {
    "gn:admin1_code":"16",
    "gn:asciiname":"Midul",
    "gn:country_code":"IR",
    "gn:dem":1648,
    "gn:feature_class":"P",
    "gn:feature_code":"PPL",
    "gn:name":"M\u012bd\u016bl",
    "gn:population":0,
    "gn:timezone":"Asia/Tehran",
    "iso:country":"IR",
    "name:fas_x_preferred":[
        "\u0645\u064a\u062f\u0648\u0644"
    ],
    "name:fas_x_variant":[
        "\u0645\u0650\u06cc\u062f\u064f\u0644",
        "M\u012bd\u016bl"
    ],
    "name:und_x_variant":[
        "Midool",
        "Meydol"
    ],
    "wof:name":"Midul",
    "wof:placetype":"locality"
},
  "geometry": {"coordinates":[46.5558,35.58],"type":"Point"}
}