{
  "type": "Feature",
  "properties": {
    "gn:admin1_code":"8.0",
    "gn:asciiname":"Kotamjan-e Yusef`ali",
    "gn:country_code":"IR",
    "gn:dem":-16,
    "gn:feature_class":"P",
    "gn:feature_code":"PPL",
    "gn:name":"Kotamj\u0101n-e Y\u016bsef\u2018al\u012b",
    "gn:population":0,
    "gn:timezone":"Asia/Tehran",
    "iso:country":"IR",
    "name:fas_x_preferred":[
        "\u06a9\u0648\u062a\u0645\u062c\u0627\u0646"
    ],
    "name:fas_x_variant":[
        "Kotamj\u0101n-e Seyyed \u2018Abd ol Vahh\u0101b",
        "Kowtamj\u0101n",
        "\u06a9\u062a\u0645\u062c\u0627\u0646 \u06cc\u0648\u0633\u0641\u0639\u0644\u06cc"
    ],
    "name:und_x_variant":[
        "Kotamj\u0101n-e Y\u016bsef\u2018al\u012b"
    ],
    "wof:name":"Kotamjan-e Yusef`ali",
    "wof:placetype":"locality"
},
  "geometry": {"coordinates":[49.24889,37.41191],"type":"Point"}
}