{
  "type": "Feature",
  "properties": {
    "gn:admin1_code":"29",
    "gn:asciiname":"Tolombeh-ye Yari",
    "gn:country_code":"IR",
    "gn:dem":1649,
    "gn:feature_class":"P",
    "gn:feature_code":"PPL",
    "gn:name":"Tolombeh-ye Y\u0101r\u012b",
    "gn:population":0,
    "gn:timezone":"Asia/Tehran",
    "iso:country":"IR",
    "name:fas_x_preferred":[
        "\u062a\u0644\u0645\u0628\u0647 \u06cc\u0627\u0631\u06cc"
    ],
    "name:fas_x_variant":[
        "Tolombeh-ye Y\u0101r\u012b"
    ],
    "wof:name":"Tolombeh-ye Yari",
    "wof:placetype":"locality"
},
  "geometry": {"coordinates":[56.4416,30.3102],"type":"Point"}
}