{
  "type": "Feature",
  "properties": {
    "gn:admin1_code":"33",
    "gn:asciiname":"Qezeljeh",
    "gn:country_code":"IR",
    "gn:dem":1750,
    "gn:feature_class":"P",
    "gn:feature_code":"PPL",
    "gn:name":"Qezeljeh",
    "gn:population":0,
    "gn:timezone":"Asia/Tehran",
    "iso:country":"IR",
    "name:ceb_x_preferred":[
        "Qezeljeh"
    ],
    "name:fas_x_preferred":[
        "\u0642\u0632\u0644\u0686\u0647"
    ],
    "name:fas_x_variant":[
        "\u0642\u0632\u0644\u062c\u0647"
    ],
    "name:swe_x_preferred":[
        "Qezeljeh"
    ],
    "name:und_x_variant":[
        "Kyzyldzha",
        "Qizilja",
        "Qezelcheh"
    ],
    "wof:name":"Qezeljeh",
    "wof:placetype":"locality"
},
  "geometry": {"coordinates":[46.8032,38.4436],"type":"Point"}
}