{
  "type": "Feature",
  "properties": {
    "gn:admin1_code":"15",
    "gn:asciiname":"Jughband",
    "gn:country_code":"IR",
    "gn:dem":803,
    "gn:feature_class":"P",
    "gn:feature_code":"PPL",
    "gn:name":"J\u016bghband",
    "gn:population":0,
    "gn:timezone":"Asia/Tehran",
    "iso:country":"IR",
    "name:azb_x_preferred":[
        "\u062c\u0648\u063a \u0628\u0646\u062f(\u0627\u06cc\u0630\u0647)"
    ],
    "name:ceb_x_preferred":[
        "J\u016bghban"
    ],
    "name:fas_x_preferred":[
        "J\u016bghband"
    ],
    "name:fas_x_variant":[
        "J\u016bghban",
        "\u062c\u0648\u063a\u0628\u0646",
        "\u062c\u0648\u063a\u0628\u0646\u062f",
        "\u062c\u0648\u063a\u200c\u0628\u0646\u062f"
    ],
    "name:swe_x_preferred":[
        "J\u016bghban"
    ],
    "wof:name":"Jughband",
    "wof:placetype":"locality"
},
  "geometry": {"coordinates":[49.78058,31.70034],"type":"Point"}
}