{
  "type": "Feature",
  "properties": {
    "gn:admin1_code":"16",
    "gn:asciiname":"Negarestan",
    "gn:country_code":"IR",
    "gn:dem":1889,
    "gn:feature_class":"P",
    "gn:feature_code":"PPL",
    "gn:name":"Neg\u0101rest\u0101n",
    "gn:population":0,
    "gn:timezone":"Asia/Tehran",
    "iso:country":"IR",
    "name:fas_x_preferred":[
        "\u0646\u06af\u0627\u0631\u0633\u062a\u0627\u0646"
    ],
    "name:fas_x_variant":[
        "\u0646\u0650\u0642\u0627\u0631\u0650\u0633\u062a\u0627\u0646",
        "Neg\u0101rest\u0101n"
    ],
    "name:und_x_variant":[
        "N\u012bg\u0101r Husa\u012bn",
        "Neq\u0101rest\u0101n"
    ],
    "wof:name":"Negarestan",
    "wof:placetype":"locality"
},
  "geometry": {"coordinates":[47.76784,35.8431],"type":"Point"}
}