{
  "type": "Feature",
  "properties": {
    "gn:admin1_code":"38.0",
    "gn:asciiname":"Shurestan-e Pa'in",
    "gn:country_code":"IR",
    "gn:dem":1313,
    "gn:feature_class":"P",
    "gn:feature_code":"PPL",
    "gn:name":"Sh\u016brest\u0101n-e P\u0101\u2019\u012bn",
    "gn:population":0,
    "gn:timezone":"Asia/Tehran",
    "iso:country":"IR",
    "name:fas_x_preferred":[
        "Sh\u016brest\u0101n-e Sofl\u00e1"
    ],
    "name:fas_x_variant":[
        "\u0634\u0648\u0631\u0633\u062a\u0627\u0646 \u0633\u0641\u0644\u06cc",
        "\u0634\u0648\u0631\u0633\u062a\u0627\u0646 \u067e\u0627\u0626\u06cc\u0646"
    ],
    "name:und_x_variant":[
        "Sh\u016brest\u0101n-e P\u0101\u2019\u012bn"
    ],
    "wof:name":"Shurestan-e Pa'in",
    "wof:placetype":"locality"
},
  "geometry": {"coordinates":[50.5061,36.38847],"type":"Point"}
}