{
  "type": "Feature",
  "properties": {
    "gn:admin1_code":"16",
    "gn:asciiname":"Ne`matabad-e `Olya",
    "gn:country_code":"IR",
    "gn:dem":2052,
    "gn:feature_class":"P",
    "gn:feature_code":"PPL",
    "gn:name":"Ne\u2018mat\u0101b\u0101d-e \u2018Oly\u0101",
    "gn:population":0,
    "gn:timezone":"Asia/Tehran",
    "iso:country":"IR",
    "name:fas_x_preferred":[
        "\u0646\u0639\u0645\u062a \u0622\u0628\u0627\u062f \u0639\u0644\u06cc\u0627"
    ],
    "name:fas_x_variant":[
        "Ne\u2018mat\u0101b\u0101d-e \u2018Oly\u0101",
        "\u067e\u0627\u067e\u062a\u06cc"
    ],
    "name:und_x_variant":[
        "Ne\u2018mat\u0101b\u0101d",
        "Nihamad\u0101b\u0101d",
        "P\u0101pat\u012b"
    ],
    "wof:name":"Ne`matabad-e `Olya",
    "wof:placetype":"locality"
},
  "geometry": {"coordinates":[47.48973,35.89232],"type":"Point"}
}