{
  "type": "Feature",
  "properties": {
    "gn:admin1_code":"15.0",
    "gn:asciiname":"Boneh-ye Qeytas",
    "gn:country_code":"IR",
    "gn:dem":96,
    "gn:feature_class":"P",
    "gn:feature_code":"PPL",
    "gn:name":"Boneh-ye Qey\u0163\u0101s",
    "gn:population":0,
    "gn:timezone":"Asia/Tehran",
    "iso:country":"IR",
    "name:ara_x_preferred":[
        "\u0628\u0646\u0629 \u0642\u064a\u0637\u0627\u0633"
    ],
    "name:ceb_x_preferred":[
        "Boneh-ye Qey\u0163\u0101s"
    ],
    "name:fas_x_preferred":[
        "Boneh-ye Qey\u0163\u0101s"
    ],
    "name:fas_x_variant":[
        "\u0628\u0646\u0647 \u0642\u06cc\u0637\u0627\u0633"
    ],
    "name:swe_x_preferred":[
        "Boneh-ye Qey\u0163\u0101s"
    ],
    "name:und_x_variant":[
        "\u0628\u0646\u0647 \u0642\u06cc\u0637\u0627\u0633"
    ],
    "wof:name":"Boneh-ye Qeytas",
    "wof:placetype":"locality"
},
  "geometry": {"coordinates":[49.69886,31.06045],"type":"Point"}
}