{
  "type": "Feature",
  "properties": {
    "gn:admin1_code":"8",
    "gn:asciiname":"Chubar",
    "gn:country_code":"IR",
    "gn:dem":51,
    "gn:feature_class":"P",
    "gn:feature_code":"PPL",
    "gn:name":"Ch\u016bbar",
    "gn:population":0,
    "gn:timezone":"Asia/Tehran",
    "iso:country":"IR",
    "name:ara_x_preferred":[
        "\u062a\u0634\u0648\u0628\u0631"
    ],
    "name:aze_x_preferred":[
        "\u00c7ub\u0259r"
    ],
    "name:ceb_x_preferred":[
        "Ch\u016bbar"
    ],
    "name:fas_x_preferred":[
        "\u0686\u0648\u0628\u0631"
    ],
    "name:fas_x_variant":[
        "Ch\u016bbar"
    ],
    "name:mlg_x_preferred":[
        "Chubar"
    ],
    "name:msa_x_preferred":[
        "Chubar"
    ],
    "name:mzn_x_preferred":[
        "\u0686\u0648\u0628\u0631"
    ],
    "name:pol_x_preferred":[
        "Czubar"
    ],
    "name:swe_x_preferred":[
        "Ch\u016bbar"
    ],
    "wof:name":"Chubar",
    "wof:placetype":"locality"
},
  "geometry": {"coordinates":[49.4202,37.1165],"type":"Point"}
}