{
  "type": "Feature",
  "properties": {
    "gn:admin1_code":"42.0",
    "gn:asciiname":"Anavi",
    "gn:country_code":"IR",
    "gn:dem":977,
    "gn:feature_class":"P",
    "gn:feature_code":"PPL",
    "gn:name":"An\u0101v\u012b",
    "gn:population":0,
    "gn:timezone":"Asia/Tehran",
    "iso:country":"IR",
    "name:ceb_x_preferred":[
        "An\u0101v\u012b"
    ],
    "name:fas_x_preferred":[
        "An\u0101v\u012b"
    ],
    "name:fas_x_variant":[
        "\u0627\u0646\u0627\u0648\u06cc"
    ],
    "name:swe_x_preferred":[
        "An\u0101v\u012b"
    ],
    "name:und_x_variant":[
        "\u0627\u0646\u0627\u0648\u06cc"
    ],
    "wof:name":"Anavi",
    "wof:placetype":"locality"
},
  "geometry": {"coordinates":[56.84434,36.79561],"type":"Point"}
}