{
  "type": "Feature",
  "properties": {
    "gn:admin1_code":"1",
    "gn:asciiname":"Naserabad",
    "gn:country_code":"IR",
    "gn:dem":2038,
    "gn:feature_class":"P",
    "gn:feature_code":"PPL",
    "gn:name":"N\u0101\u015fer\u0101b\u0101d",
    "gn:population":0,
    "gn:timezone":"Asia/Tehran",
    "iso:country":"IR",
    "name:fas_x_preferred":[
        "\u0646\u0627\u0635\u0631 \u0622\u0628\u0627\u062f"
    ],
    "name:fas_x_variant":[
        "N\u0101\u015fer\u0101b\u0101d"
    ],
    "wof:name":"Naserabad",
    "wof:placetype":"locality"
},
  "geometry": {"coordinates":[46.7209,36.6194],"type":"Point"}
}