{
  "type": "Feature",
  "properties": {
    "gn:admin1_code":"33",
    "gn:asciiname":"Markid",
    "gn:country_code":"IR",
    "gn:dem":1522,
    "gn:feature_class":"P",
    "gn:feature_code":"PPL",
    "gn:name":"Mark\u012bd",
    "gn:population":0,
    "gn:timezone":"Asia/Tehran",
    "iso:country":"IR",
    "name:fas_x_preferred":[
        "\u0645\u064e\u0631\u0643\u064a\u062f"
    ],
    "name:fas_x_variant":[
        "\u0645\u0631\u06a9\u06cc\u062f",
        "Mark\u012bd",
        "\u0645\u064e\u0631\u06af\u064a\u062f"
    ],
    "name:und_x_variant":[
        "Markit",
        "Marg\u012bd"
    ],
    "wof:name":"Markid",
    "wof:placetype":"locality"
},
  "geometry": {"coordinates":[46.8245,38.169],"type":"Point"}
}