{
  "type": "Feature",
  "properties": {
    "gn:admin1_code":"8.0",
    "gn:asciiname":"Vazneh Sar",
    "gn:country_code":"IR",
    "gn:dem":1032,
    "gn:feature_class":"P",
    "gn:feature_code":"PPL",
    "gn:name":"Vazneh Sar",
    "gn:population":0,
    "gn:timezone":"Asia/Tehran",
    "iso:country":"IR",
    "name:fas_x_preferred":[
        "\u0648\u0632\u0646\u0647 \u0633\u0631"
    ],
    "wof:name":"Vazneh Sar",
    "wof:placetype":"locality"
},
  "geometry": {"coordinates":[48.72203,37.75198],"type":"Point"}
}