{
  "type": "Feature",
  "properties": {
    "gn:admin1_code":"16.0",
    "gn:asciiname":"Sarpir",
    "gn:country_code":"IR",
    "gn:dem":1568,
    "gn:feature_class":"P",
    "gn:feature_code":"PPL",
    "gn:name":"Sarp\u012br",
    "gn:population":0,
    "gn:timezone":"Asia/Tehran",
    "iso:country":"IR",
    "name:fas_x_preferred":[
        "\u0633\u0631\u067e\u064a\u0631"
    ],
    "name:fas_x_variant":[
        "Sarp\u012br"
    ],
    "wof:name":"Sarpir",
    "wof:placetype":"locality"
},
  "geometry": {"coordinates":[46.2669,35.256],"type":"Point"}
}