{
  "type": "Feature",
  "properties": {
    "gn:admin1_code":"35.0",
    "gn:asciiname":"Pasha Kola",
    "gn:country_code":"IR",
    "gn:dem":32,
    "gn:feature_class":"P",
    "gn:feature_code":"PPL",
    "gn:name":"P\u0101sh\u0101 Kol\u0101",
    "gn:population":0,
    "gn:timezone":"Asia/Tehran",
    "iso:country":"IR",
    "name:fas_x_preferred":[
        "\u067e\u0627\u0634\u0627 \u0643\u0644\u0627"
    ],
    "name:fas_x_variant":[
        "\u067e\u0627\u0634\u0627 \u0643\u064e\u0644\u0627",
        "\u067e\u0627\u0634\u0627 \u0643\u0648\u0644\u0627",
        "P\u0101sh\u0101 Kol\u0101"
    ],
    "name:und_x_variant":[
        "P\u0101sh\u0101 Kal\u0101",
        "P\u0101sh\u0101 K\u016bl\u0101"
    ],
    "wof:name":"Pasha Kola",
    "wof:placetype":"locality"
},
  "geometry": {"coordinates":[52.91443,36.4827],"type":"Point"}
}