{
  "type": "Feature",
  "properties": {
    "gn:admin1_code":"13",
    "gn:asciiname":"Tajjar Akbar-e Mush Kosh",
    "gn:country_code":"IR",
    "gn:dem":1320,
    "gn:feature_class":"P",
    "gn:feature_code":"PPL",
    "gn:name":"Tajjar Akbar-e M\u016bsh Kosh",
    "gn:population":0,
    "gn:timezone":"Asia/Tehran",
    "iso:country":"IR",
    "name:fas_x_preferred":[
        "\u062a\u062c\u0651\u0631\u0627\u06a9\u0628\u0631\u0645\u0648\u0634 \u06a9\u0634"
    ],
    "name:fas_x_variant":[
        "M\u016bsh Kosh",
        "Tajjar Akbar-e M\u016bsh Kosh"
    ],
    "wof:name":"Tajjar Akbar-e Mush Kosh",
    "wof:placetype":"locality"
},
  "geometry": {"coordinates":[46.6121,34.0393],"type":"Point"}
}