{
  "type": "Feature",
  "properties": {
    "gn:admin1_code":"40",
    "gn:asciiname":"Jowdestan",
    "gn:country_code":"IR",
    "gn:dem":2478,
    "gn:feature_class":"P",
    "gn:feature_code":"PPL",
    "gn:name":"Jowdest\u0101n",
    "gn:population":0,
    "gn:timezone":"Asia/Tehran",
    "iso:country":"IR",
    "name:fas_x_preferred":[
        "Jowdest\u0101n"
    ],
    "name:fas_x_variant":[
        "\u062c\u0648\u0632\u0633\u062a\u0627\u0646"
    ],
    "wof:name":"Jowdestan",
    "wof:placetype":"locality"
},
  "geometry": {"coordinates":[54.06611,31.49984000000001],"type":"Point"}
}