{
  "type": "Feature",
  "properties": {
    "gn:admin1_code":"15",
    "gn:asciiname":"Beyt-e Sa`id",
    "gn:country_code":"IR",
    "gn:dem":27,
    "gn:feature_class":"P",
    "gn:feature_code":"PPL",
    "gn:name":"Beyt-e Sa\u2018\u012bd",
    "gn:population":0,
    "gn:timezone":"Asia/Tehran",
    "iso:country":"IR",
    "name:fas_x_preferred":[
        "Beyt-e Sa\u2018\u012bd"
    ],
    "name:und_x_variant":[
        "Bait Sai\u2018d"
    ],
    "wof:name":"Beyt-e Sa`id",
    "wof:placetype":"locality"
},
  "geometry": {"coordinates":[48.63333,31.56667],"type":"Point"}
}