{
  "type": "Feature",
  "properties": {
    "gn:admin1_code":"29",
    "gn:asciiname":"Shahababad",
    "gn:country_code":"IR",
    "gn:dem":593,
    "gn:feature_class":"P",
    "gn:feature_code":"PPLL",
    "gn:name":"Shahab\u0101b\u0101d",
    "gn:population":0,
    "gn:timezone":"Asia/Tehran",
    "iso:country":"IR",
    "name:fas_x_preferred":[
        "\u0634\u0647\u0628 \u0622\u0628\u0627\u062f"
    ],
    "name:fas_x_variant":[
        "Shahab\u0101b\u0101d"
    ],
    "wof:name":"Shahababad",
    "wof:placetype":"locality"
},
  "geometry": {"coordinates":[58.50559000000001,28.02996],"type":"Point"}
}