{
  "type": "Feature",
  "properties": {
    "gn:admin1_code":"42",
    "gn:asciiname":"Beyhut",
    "gn:country_code":"IR",
    "gn:dem":1654,
    "gn:feature_class":"P",
    "gn:feature_code":"PPL",
    "gn:name":"Beyh\u016bt",
    "gn:population":0,
    "gn:timezone":"Asia/Tehran",
    "iso:country":"IR",
    "name:ara_x_preferred":[
        "\u0628\u064a\u0647\u0648\u062f"
    ],
    "name:fas_x_preferred":[
        "Beyh\u016bt"
    ],
    "name:fas_x_variant":[
        "Beyh\u016bd",
        "\u0628\u06cc\u0647\u0648\u062a",
        "\u0628\u06cc\u0647\u0648\u062f"
    ],
    "wof:name":"Beyhut",
    "wof:placetype":"locality"
},
  "geometry": {"coordinates":[58.36796999999999,34.34324],"type":"Point"}
}