{
  "type": "Feature",
  "properties": {
    "gn:admin1_code":"33",
    "gn:asciiname":"Beneh Kohol",
    "gn:country_code":"IR",
    "gn:dem":1788,
    "gn:feature_class":"P",
    "gn:feature_code":"PPL",
    "gn:name":"Beneh Kohol",
    "gn:population":0,
    "gn:timezone":"Asia/Tehran",
    "iso:country":"IR",
    "name:fas_x_preferred":[
        "\u0646\u0628\u0647 \u06a9\u0647\u0644"
    ],
    "name:fas_x_variant":[
        "\u0628\u0646\u0647 \u06a9\u0647\u0644"
    ],
    "name:und_x_variant":[
        "Nebeh Kohol"
    ],
    "wof:name":"Beneh Kohol",
    "wof:placetype":"locality"
},
  "geometry": {"coordinates":[46.8131,37.7899],"type":"Point"}
}