{
  "type": "Feature",
  "properties": {
    "gn:admin1_code":"33",
    "gn:asciiname":"Owrtasu",
    "gn:country_code":"IR",
    "gn:dem":1537,
    "gn:feature_class":"P",
    "gn:feature_code":"PPL",
    "gn:name":"Owrt\u0101s\u016b",
    "gn:population":0,
    "gn:timezone":"Asia/Tehran",
    "iso:country":"IR",
    "name:ara_x_preferred":[
        "\u0627\u0648\u0631\u062a\u0627\u0633\u0648"
    ],
    "name:fas_x_preferred":[
        "\u0648\u0631\u062a\u0627\u0633\u0648"
    ],
    "name:fas_x_variant":[
        "\u0627\u0648\u0631\u062a\u0627\u0633\u0648",
        "\u016art\u0101s\u016b",
        "Owrt\u0101s\u016b"
    ],
    "name:msa_x_preferred":[
        "Owrtasu"
    ],
    "wof:name":"Owrtasu",
    "wof:placetype":"locality"
},
  "geometry": {"coordinates":[47.4242,37.0251],"type":"Point"}
}