{
  "type": "Feature",
  "properties": {
    "gn:admin1_code":"32",
    "gn:asciiname":"Khamunli",
    "gn:country_code":"IR",
    "gn:dem":1018,
    "gn:feature_class":"P",
    "gn:feature_code":"PPL",
    "gn:name":"Kham\u016bnl\u012b",
    "gn:population":0,
    "gn:timezone":"Asia/Tehran",
    "iso:country":"IR",
    "name:fas_x_preferred":[
        "\u062e\u064e\u0645\u0648\u0646\u0644\u06cc"
    ],
    "name:fas_x_variant":[
        "Kham\u016bnl\u012b"
    ],
    "wof:name":"Khamunli",
    "wof:placetype":"locality"
},
  "geometry": {"coordinates":[47.77583,38.9925],"type":"Point"}
}