{
  "type": "Feature",
  "properties": {
    "gn:admin1_code":"11",
    "gn:asciiname":"Mohammadabad",
    "gn:country_code":"IR",
    "gn:dem":1398,
    "gn:feature_class":"P",
    "gn:feature_code":"PPL",
    "gn:name":"Mo\u1e29ammad\u0101b\u0101d",
    "gn:population":0,
    "gn:timezone":"Asia/Tehran",
    "iso:country":"IR",
    "name:fas_x_preferred":[
        "\u0645\u062d\u0645\u062f \u0622\u0628\u0627\u062f"
    ],
    "name:fas_x_variant":[
        "\u0645\u064e\u0647\u062f \u0622\u0628\u0627\u062f",
        "\u0645\u0650\u0647\u062f\u06cc \u0622\u0628\u0627\u062f",
        "Mo\u1e29ammad\u0101b\u0101d"
    ],
    "name:und_x_variant":[
        "Mehd\u012b\u0101b\u0101d",
        "Mahd\u0101b\u0101d"
    ],
    "wof:name":"Mohammadabad",
    "wof:placetype":"locality"
},
  "geometry": {"coordinates":[55.8377,28.5642],"type":"Point"}
}