{
  "type": "Feature",
  "properties": {
    "gn:admin1_code":"5",
    "gn:asciiname":"Dowpar-e Qabr",
    "gn:country_code":"IR",
    "gn:dem":741,
    "gn:feature_class":"P",
    "gn:feature_code":"PPL",
    "gn:name":"Dowpar-e Qabr",
    "gn:population":0,
    "gn:timezone":"Asia/Tehran",
    "iso:country":"IR",
    "name:fas_x_preferred":[
        "\u062f\u064f\u0648 \u067e\u064e\u0631"
    ],
    "name:fas_x_variant":[
        "\u062f\u0648\u067e\u0631 \u0642\u0628\u0631"
    ],
    "name:und_x_variant":[
        "\u062f\u0648\u067e\u0631 \u0642\u0628\u0631",
        "Do Par"
    ],
    "wof:name":"Dowpar-e Qabr",
    "wof:placetype":"locality"
},
  "geometry": {"coordinates":[50.5098,30.73638],"type":"Point"}
}