{
  "type": "Feature",
  "properties": {
    "gn:admin1_code":"35.0",
    "gn:asciiname":"Sheykh Nur od Din",
    "gn:country_code":"IR",
    "gn:dem":1237,
    "gn:feature_class":"P",
    "gn:feature_code":"PPL",
    "gn:name":"Sheykh N\u016br od D\u012bn",
    "gn:population":0,
    "gn:timezone":"Asia/Tehran",
    "iso:country":"IR",
    "name:fas_x_preferred":[
        "\u0634\u0650\u064a\u062e \u0646\u0648\u0631 \u0627\u0644\u062f\u0651\u064a\u0646"
    ],
    "name:fas_x_variant":[
        "Sheykh N\u016br od D\u012bn"
    ],
    "wof:name":"Sheykh Nur od Din",
    "wof:placetype":"locality"
},
  "geometry": {"coordinates":[53.73333,36.58333],"type":"Point"}
}