{
  "type": "Feature",
  "properties": {
    "gn:admin1_code":"29",
    "gn:asciiname":"Manzelabad",
    "gn:country_code":"IR",
    "gn:dem":1599,
    "gn:feature_class":"P",
    "gn:feature_code":"PPL",
    "gn:name":"Manzel\u0101b\u0101d",
    "gn:population":0,
    "gn:timezone":"Asia/Tehran",
    "iso:country":"IR",
    "name:fas_x_preferred":[
        "Manzel\u0101b\u0101d"
    ],
    "name:fas_x_variant":[
        "\u0645\u0646\u0632\u0644 \u0622\u0628\u0627\u062f"
    ],
    "name:und_x_variant":[
        "Manzil\u0101b\u0101d"
    ],
    "wof:name":"Manzelabad",
    "wof:placetype":"locality"
},
  "geometry": {"coordinates":[54.76951999999999,30.06783],"type":"Point"}
}