{
  "type": "Feature",
  "properties": {
    "gn:admin1_code":"8",
    "gn:asciiname":"Sadat Mahalleh",
    "gn:country_code":"IR",
    "gn:dem":21,
    "gn:feature_class":"P",
    "gn:feature_code":"PPL",
    "gn:name":"S\u0101d\u0101t Ma\u1e29alleh",
    "gn:population":0,
    "gn:timezone":"Asia/Tehran",
    "iso:country":"IR",
    "name:fas_x_preferred":[
        "Sh\u0101h Mor\u0101d Ma\u1e29alleh"
    ],
    "name:fas_x_variant":[
        "\u0634\u0627\u0647 \u0645\u0631\u0627\u062f \u0645\u062d\u0644\u0647",
        "\u0633\u0627\u062f\u0627\u062a \u0645\u062d\u0644\u0647"
    ],
    "name:und_x_variant":[
        "Sh\u0101h Mor\u0101d Ma\u1e29alleh",
        "\u0634\u0627\u0647 \u0645\u0631\u0627\u062f \u0645\u062d\u0644\u0647",
        "S\u0101d\u0101t Ma\u1e29alleh"
    ],
    "wof:name":"Sadat Mahalleh",
    "wof:placetype":"locality"
},
  "geometry": {"coordinates":[50.44389,37.0311],"type":"Point"}
}