{
  "type": "Feature",
  "properties": {
    "gn:admin1_code":"10",
    "gn:asciiname":"Pardeh",
    "gn:country_code":"IR",
    "gn:dem":1210,
    "gn:feature_class":"P",
    "gn:feature_code":"PPL",
    "gn:name":"P\u0101rdeh",
    "gn:population":0,
    "gn:timezone":"Asia/Tehran",
    "iso:country":"IR",
    "name:fas_x_preferred":[
        "\u067e\u0627\u0631\u062f\u0647"
    ],
    "name:fas_x_variant":[
        "P\u0101rdeh"
    ],
    "wof:name":"Pardeh",
    "wof:placetype":"locality"
},
  "geometry": {"coordinates":[46.0943,33.7842],"type":"Point"}
}