{
  "type": "Feature",
  "properties": {
    "gn:admin1_code":"8.0",
    "gn:asciiname":"Su Kacha",
    "gn:country_code":"IR",
    "gn:dem":33,
    "gn:feature_class":"P",
    "gn:feature_code":"PPL",
    "gn:name":"S\u016b K\u0101ch\u0101",
    "gn:population":0,
    "gn:timezone":"Asia/Tehran",
    "iso:country":"IR",
    "name:fas_x_preferred":[
        "S\u016b K\u0101ch\u0101"
    ],
    "name:fas_x_variant":[
        "\u0633\u0648 \u06a9\u0627\u0686\u0627"
    ],
    "name:und_x_variant":[
        "\u0633\u0648 \u06a9\u0627\u0686\u0627",
        "Sek\u0101chel"
    ],
    "wof:name":"Su Kacha",
    "wof:placetype":"locality"
},
  "geometry": {"coordinates":[49.70052,37.16166],"type":"Point"}
}