{
  "type": "Feature",
  "properties": {
    "gn:admin1_code":"23",
    "gn:asciiname":"Sari-ye Kuchek",
    "gn:country_code":"IR",
    "gn:dem":1164,
    "gn:feature_class":"P",
    "gn:feature_code":"PPL",
    "gn:name":"S\u0101r\u012b-ye K\u016bchek",
    "gn:population":0,
    "gn:timezone":"Asia/Tehran",
    "iso:country":"IR",
    "name:ceb_x_preferred":[
        "S\u0101r\u012b-ye K\u016bchek"
    ],
    "name:fas_x_preferred":[
        "\u0633\u0627\u0631\u06cc \u0643\u0648\u0686\u064e\u0643\u0650\u0647"
    ],
    "name:fas_x_variant":[
        "\u0633\u0627\u0631\u06cc",
        "S\u0101r\u012b K\u016bchakeh",
        "S\u0101r\u012b",
        "\u0633\u0627\u0631\u06cc \u06a9\u0648\u0686\u06a9",
        "\u0686\u0645 \u06a9\u0628\u0648\u062f \u0633\u0641\u0644\u06cc",
        "\u0633\u0627\u0631\u06cc \u06a9\u0648\u0686\u06a9\u0647"
    ],
    "name:swe_x_preferred":[
        "S\u0101r\u012b-ye K\u016bchek"
    ],
    "name:und_x_variant":[
        "S\u0101r\u0101n",
        "\u0633\u0627\u0631\u0627\u0646",
        "S\u0101r\u012b-ye K\u016bchek",
        "Cham Kab\u016bd-e Sofl\u00e1"
    ],
    "wof:name":"Sari-ye Kuchek",
    "wof:placetype":"locality"
},
  "geometry": {"coordinates":[47.61614,33.46651],"type":"Point"}
}