{
  "type": "Feature",
  "properties": {
    "gn:admin1_code":"8",
    "gn:asciiname":"Gazkhowran",
    "gn:country_code":"IR",
    "gn:dem":1476,
    "gn:feature_class":"P",
    "gn:feature_code":"PPL",
    "gn:name":"Gazkhowr\u0101n",
    "gn:population":0,
    "gn:timezone":"Asia/Tehran",
    "iso:country":"IR",
    "name:fas_x_preferred":[
        "\u06af\u0632\u062e\u0648\u0631\u0627\u0646"
    ],
    "name:und_x_variant":[
        "Gazkhowr\u0101n"
    ],
    "wof:name":"Gazkhowran",
    "wof:placetype":"locality"
},
  "geometry": {"coordinates":[48.798,37.4738],"type":"Point"}
}