{
  "type": "Feature",
  "properties": {
    "gn:admin1_code":"3",
    "gn:asciiname":"Gerd Bisheh",
    "gn:country_code":"IR",
    "gn:dem":1900,
    "gn:feature_class":"P",
    "gn:feature_code":"PPL",
    "gn:name":"Gerd B\u012bsheh",
    "gn:population":0,
    "gn:timezone":"Asia/Tehran",
    "iso:country":"IR",
    "name:fas_x_preferred":[
        "Gerd-e B\u012bsheh"
    ],
    "name:fas_x_variant":[
        "\u06af\u0650\u0631\u062f\u0650 \u0628\u064a\u0634\u0650\u0647",
        "\u06af\u0650\u0631\u062f \u067e\u064a\u0634\u0650\u0647",
        "Gerd B\u012bsheh",
        "\u06af\u0631\u062f \u0628\u064a\u0634\u0647"
    ],
    "name:und_x_variant":[
        "Gerd B\u012bsheh",
        "Gird-i-B\u012bsheh",
        "Gerd P\u012bsheh",
        "\u06af\u0631\u062f \u0628\u064a\u0634\u0647"
    ],
    "wof:name":"Gerd Bisheh",
    "wof:placetype":"locality"
},
  "geometry": {"coordinates":[51.20099,31.57624],"type":"Point"}
}