{
  "type": "Feature",
  "properties": {
    "gn:admin1_code":"32",
    "gn:asciiname":"Gilar",
    "gn:country_code":"IR",
    "gn:dem":984,
    "gn:feature_class":"P",
    "gn:feature_code":"PPL",
    "gn:name":"G\u012blar",
    "gn:population":0,
    "gn:timezone":"Asia/Tehran",
    "iso:country":"IR",
    "name:aze_x_preferred":[
        "Gilar"
    ],
    "name:fas_x_preferred":[
        "Gellar-e Mo\u1e29ammad\u1e29asan"
    ],
    "name:fas_x_variant":[
        "\u06af\u06cc\u0644\u0631",
        "\u06af\u0644\u0631 \u0645\u062d\u0645\u062f \u062d\u0633\u0646",
        "\u06af\u0644\u0644\u0631\u0645\u062d\u0645\u062f\u062d\u0633\u0646"
    ],
    "name:ita_x_preferred":[
        "Gilar"
    ],
    "name:msa_x_preferred":[
        "Gilar"
    ],
    "name:mzn_x_preferred":[
        "\u06af\u0644\u0644\u0631\u0645\u062d\u0645\u062f\u062d\u0633\u0646"
    ],
    "name:tur_x_preferred":[
        "Gilar"
    ],
    "name:und_x_variant":[
        "G\u012blar",
        "Gelar-e Mo\u1e29ammad \u1e28asan"
    ],
    "wof:name":"Gilar",
    "wof:placetype":"locality"
},
  "geometry": {"coordinates":[47.55325,38.44209],"type":"Point"}
}