{
  "type": "Feature",
  "properties": {
    "gn:admin1_code":"1",
    "gn:asciiname":"Shirvan Shahlu-ye Sofla",
    "gn:country_code":"IR",
    "gn:dem":1336,
    "gn:feature_class":"P",
    "gn:feature_code":"PPL",
    "gn:name":"Sh\u012brv\u0101n Sh\u0101hl\u016b-ye Sofl\u00e1",
    "gn:population":0,
    "gn:timezone":"Asia/Tehran",
    "iso:country":"IR",
    "name:fas_x_preferred":[
        "Sh\u012brv\u0101n Sh\u0101hl\u016b-ye Sofl\u00e1"
    ],
    "name:fas_x_variant":[
        "\u0634\u064a\u0631\u0648\u0627\u0646 \u0634\u0627\u0647\u0644\u0648\u06cc \u0633\u064f\u0641\u0644\u064e\u0649"
    ],
    "wof:name":"Shirvan Shahlu-ye Sofla",
    "wof:placetype":"locality"
},
  "geometry": {"coordinates":[45.43333,37.11667],"type":"Point"}
}