{
  "type": "Feature",
  "properties": {
    "gn:admin1_code":"4.0",
    "gn:asciiname":"Gijan",
    "gn:cc2":"IR",
    "gn:country_code":"IR",
    "gn:dem":416,
    "gn:feature_class":"P",
    "gn:feature_code":"PPL",
    "gn:name":"G\u012bj\u0101n",
    "gn:population":0,
    "gn:timezone":"Asia/Tehran",
    "iso:country":"IR",
    "name:fas_x_preferred":[
        "G\u012bj\u0101n"
    ],
    "name:und_x_variant":[
        "Geyj\u0101n"
    ],
    "wof:name":"Gijan",
    "wof:placetype":"locality"
},
  "geometry": {"coordinates":[60.64471999999999,26.20306],"type":"Point"}
}