{
  "type": "Feature",
  "properties": {
    "gn:admin1_code":"4.0",
    "gn:asciiname":"Deh-e Reza Shah Beyk",
    "gn:country_code":"IR",
    "gn:dem":488,
    "gn:feature_class":"P",
    "gn:feature_code":"PPL",
    "gn:name":"Deh-e Re\u1e95\u0101 Sh\u0101h Beyk",
    "gn:population":0,
    "gn:timezone":"Asia/Tehran",
    "iso:country":"IR",
    "name:fas_x_preferred":[
        "Deh-e Re\u1e95\u0101 Sh\u0101h Beyk"
    ],
    "wof:name":"Deh-e Reza Shah Beyk",
    "wof:placetype":"locality"
},
  "geometry": {"coordinates":[61.63333000000001,30.91667],"type":"Point"}
}