{
  "type": "Feature",
  "properties": {
    "gn:admin1_code":"37",
    "gn:asciiname":"Shirabad",
    "gn:country_code":"IR",
    "gn:dem":99,
    "gn:feature_class":"P",
    "gn:feature_code":"PPL",
    "gn:name":"Sh\u012br\u0101b\u0101d",
    "gn:population":0,
    "gn:timezone":"Asia/Tehran",
    "iso:country":"IR",
    "name:fas_x_preferred":[
        "\u0634\u064a\u0631 \u0622\u0628\u0627\u062f"
    ],
    "name:fas_x_variant":[
        "Sh\u012br\u0101b\u0101d",
        "\u0634\u06cc\u0631\u0622\u0628\u0627\u062f"
    ],
    "wof:name":"Shirabad",
    "wof:placetype":"locality"
},
  "geometry": {"coordinates":[55.0218,36.9732],"type":"Point"}
}