{
  "type": "Feature",
  "properties": {
    "gn:admin1_code":"11",
    "gn:asciiname":"Chahestan",
    "gn:country_code":"IR",
    "gn:dem":55,
    "gn:feature_class":"P",
    "gn:feature_code":"PPL",
    "gn:name":"Ch\u0101hest\u0101n",
    "gn:population":0,
    "gn:timezone":"Asia/Tehran",
    "iso:country":"IR",
    "name:ara_x_preferred":[
        "\u062a\u0634\u0627\u0647\u0633\u062a\u0627\u0646"
    ],
    "name:fas_x_preferred":[
        "\u0686\u0627\u0647\u0633\u062a\u0627\u0646"
    ],
    "name:fas_x_variant":[
        "\u0634\u0627\u0647\u0650\u0633\u062a\u0627\u0646",
        "Ch\u0101hest\u0101n"
    ],
    "name:msa_x_preferred":[
        "Chahestan"
    ],
    "name:und_x_variant":[
        "Sh\u0101hest\u0101n",
        "Ch\u0101hist\u0101n"
    ],
    "wof:name":"Chahestan",
    "wof:placetype":"locality"
},
  "geometry": {"coordinates":[56.7179,27.5141],"type":"Point"}
}