{
  "type": "Feature",
  "properties": {
    "gn:admin1_code":"15.0",
    "gn:asciiname":"Tal Ant",
    "gn:country_code":"IR",
    "gn:dem":3,
    "gn:feature_class":"P",
    "gn:feature_code":"PPL",
    "gn:name":"\u0162al Ant",
    "gn:population":0,
    "gn:timezone":"Asia/Tehran",
    "iso:country":"IR",
    "name:fas_x_preferred":[
        "\u0637\u0644 \u0627\u0646\u062a"
    ],
    "name:fas_x_variant":[
        "\u0162al Ant"
    ],
    "wof:name":"Tal Ant",
    "wof:placetype":"locality"
},
  "geometry": {"coordinates":[48.4895,30.0147],"type":"Point"}
}