{
  "type": "Feature",
  "properties": {
    "gn:admin1_code":"7",
    "gn:asciiname":"Qal`eh-ye `Ali",
    "gn:country_code":"IR",
    "gn:dem":2029,
    "gn:feature_class":"P",
    "gn:feature_code":"PPL",
    "gn:name":"Qal\u2018eh-ye \u2018\u0100l\u012b",
    "gn:population":0,
    "gn:timezone":"Asia/Tehran",
    "iso:country":"IR",
    "name:fas_x_preferred":[
        "\u0642\u0644\u0639\u0647 \u0639\u0627\u0644\u06cc"
    ],
    "name:fas_x_variant":[
        "Qal\u2018eh-ye \u2018\u0100l\u012b"
    ],
    "wof:name":"Qal`eh-ye `Ali",
    "wof:placetype":"locality"
},
  "geometry": {"coordinates":[52.0663,30.1541],"type":"Point"}
}