{
  "type": "Feature",
  "properties": {
    "gn:admin1_code":"9.0",
    "gn:asciiname":"Baghcheh",
    "gn:country_code":"IR",
    "gn:dem":1863,
    "gn:feature_class":"P",
    "gn:feature_code":"PPL",
    "gn:name":"B\u0101ghcheh",
    "gn:population":0,
    "gn:timezone":"Asia/Tehran",
    "iso:country":"IR",
    "name:fas_x_preferred":[
        "\u0628\u0627\u063a\u0686\u0647"
    ],
    "name:fas_x_variant":[
        "B\u0101ghcheh"
    ],
    "name:msa_x_preferred":[
        "Baghcheh"
    ],
    "name:und_x_variant":[
        "Baghcheh Mehraban",
        "B\u0101ghicheh"
    ],
    "wof:name":"Baghcheh",
    "wof:placetype":"locality"
},
  "geometry": {"coordinates":[48.2631,35.44434000000001],"type":"Point"}
}