{
  "type": "Feature",
  "properties": {
    "gn:admin1_code":"32",
    "gn:asciiname":"Rahimlu",
    "gn:country_code":"IR",
    "gn:dem":899,
    "gn:feature_class":"P",
    "gn:feature_code":"PPL",
    "gn:name":"Ra\u1e29\u012bml\u016b",
    "gn:population":0,
    "gn:timezone":"Asia/Tehran",
    "iso:country":"IR",
    "name:ara_x_preferred":[
        "\u0631\u062d\u064a\u0645\u0644\u0648"
    ],
    "name:ceb_x_preferred":[
        "Ra\u1e29\u012bml\u016b"
    ],
    "name:fas_x_preferred":[
        "\u0631\u062d\u064a\u0645 \u0644\u0648"
    ],
    "name:fas_x_variant":[
        "Ra\u1e29\u012bml\u016b",
        "\u0631\u062d\u06cc\u0645\u0644\u0648"
    ],
    "name:msa_x_preferred":[
        "Rahimlu"
    ],
    "name:swe_x_preferred":[
        "Ra\u1e29\u012bml\u016b"
    ],
    "wof:name":"Rahimlu",
    "wof:placetype":"locality"
},
  "geometry": {"coordinates":[48.051,39.0354],"type":"Point"}
}