{
  "type": "Feature",
  "properties": {
    "gn:admin1_code":"11.0",
    "gn:asciiname":"Hasan Langi",
    "gn:country_code":"IR",
    "gn:dem":26,
    "gn:feature_class":"P",
    "gn:feature_code":"PPL",
    "gn:name":"\u1e28asan Lang\u012b",
    "gn:population":0,
    "gn:timezone":"Asia/Tehran",
    "iso:country":"IR",
    "name:fas_x_preferred":[
        "\u062d\u0633\u0646 \u0644\u0646\u06af\u06cc"
    ],
    "name:fas_x_variant":[
        "\u1e28asan Lang\u012b"
    ],
    "wof:name":"Hasan Langi",
    "wof:placetype":"locality"
},
  "geometry": {"coordinates":[56.8576,27.3616],"type":"Point"}
}