{
  "type": "Feature",
  "properties": {
    "gn:admin1_code":"9.0",
    "gn:asciiname":"Aghcheh-ye Seyyedan",
    "gn:cc2":"IR",
    "gn:country_code":"IR",
    "gn:dem":1854,
    "gn:feature_class":"P",
    "gn:feature_code":"PPL",
    "gn:name":"\u0100ghcheh-ye Seyyed\u0101n",
    "gn:population":0,
    "gn:timezone":"Asia/Tehran",
    "iso:country":"IR",
    "name:fas_x_preferred":[
        "\u0622\u063a\u0686\u0650\u06c0 \u0633\u0650\u064a\u0650\u0651\u062f\u0627\u0646"
    ],
    "name:fas_x_variant":[
        "\u0622\u063a\u062c\u0650\u0647 \u062e\u064e\u0631\u0627\u0628\u0650\u06c0 \u0633\u0650\u064a\u0650\u0651\u062f\u200c\u0647\u064e\u0627",
        "\u0622\u063a\u062c\u0650\u0647 \u062e\u064e\u0631\u0627\u0628\u0650\u0647",
        "\u0622\u063a\u0686\u0650\u0647 \u062e\u064e\u0631\u0627\u0628\u0650\u0647",
        "\u0100ghcheh-ye Seyyed\u0101n",
        "\u0627\u063a\u062c\u0647 \u0633\u06cc\u062f\u0627\u0646"
    ],
    "name:msa_x_preferred":[
        "Aghjeh-ye Seyyedan"
    ],
    "name:und_x_variant":[
        "\u0100ghjeh Khar\u0101beh-ye Seyyedh\u0101",
        "\u0100ghcheh Khar\u0101beh",
        "\u0100ghjeh Khar\u0101beh"
    ],
    "wof:name":"Aghcheh-ye Seyyedan",
    "wof:placetype":"locality"
},
  "geometry": {"coordinates":[48.66278,34.85333],"type":"Point"}
}