{
  "type": "Feature",
  "properties": {
    "gn:admin1_code":"23",
    "gn:asciiname":"Farah Kosh-e Seyyedan",
    "gn:country_code":"IR",
    "gn:dem":1910,
    "gn:feature_class":"P",
    "gn:feature_code":"PPL",
    "gn:name":"Farah Kosh-e Seyyed\u0101n",
    "gn:population":0,
    "gn:timezone":"Asia/Tehran",
    "iso:country":"IR",
    "name:fas_x_preferred":[
        "\u0641\u0631\u062d \u06a9\u0634 \u0639\u0644\u06cc\u0627"
    ],
    "name:fas_x_variant":[
        "Fara\u1e29 Kosh-e \u2018Oly\u0101",
        "\u0641\u0631\u0647 \u06a9\u0634 \u0633\u064a\u062f\u0627\u0646",
        "\u0641\u0631\u062d \u06a9\u0634 \u0648\u0633\u0637\u06cc",
        "\u0641\u0631\u0647 \u06a9\u0634 \u0639\u0644\u064a\u0627",
        "\u0641\u0631\u0647 \u06a9\u0634 \u0628\u0627\u0644\u0627\u06cc\u06cc"
    ],
    "name:und_x_variant":[
        "Fara\u1e29kesh-e B\u0101l\u0101",
        "F\u0101r\u0101kash",
        "Fara\u1e29 Kash-e \u2018Oly\u0101",
        "Fara\u1e29 Kash",
        "Farah Kosh-e Seyyed\u0101n",
        "Fara\u1e29 Kosh-e Vos\u0163\u00e1",
        "Farah Kosh-e \u2018Oly\u0101",
        "Farah Kosh-e B\u0101l\u0101\u2019\u012b"
    ],
    "wof:name":"Farah Kosh-e Seyyedan",
    "wof:placetype":"locality"
},
  "geometry": {"coordinates":[48.6703,33.5013],"type":"Point"}
}