{
  "type": "Feature",
  "properties": {
    "gn:admin1_code":"1.0",
    "gn:asciiname":"Sakhasi Tappeh",
    "gn:country_code":"IR",
    "gn:dem":1291,
    "gn:elevation":"0.0",
    "gn:feature_class":"P",
    "gn:feature_code":"PPL",
    "gn:name":"S\u0101khas\u012b Tappeh",
    "gn:population":0,
    "gn:timezone":"Asia/Tehran",
    "iso:country":"IR",
    "name:azb_x_preferred":[
        "\u0633\u0627\u062e\u0633\u06cc \u062a\u067e\u0647"
    ],
    "name:aze_x_preferred":[
        "Saxs\u0131t\u0259p\u0259"
    ],
    "name:ceb_x_preferred":[
        "S\u0101khas\u012b Tappeh"
    ],
    "name:fas_x_preferred":[
        "\u0633\u0627\u062e\u0633\u06cc \u062a\u067e\u0647"
    ],
    "name:fas_x_variant":[
        "\u0633\u0627\u062e\u064e\u0633\u06cc \u062a\u064e\u067e\u0650\u0651\u0647",
        "S\u0101khas\u012b Tappeh",
        "\u0633\u0627\u062e\u0633\u06cc\u200c\u062a\u067e\u0647"
    ],
    "name:fra_x_preferred":[
        "Sakhasi Tappeh"
    ],
    "name:msa_x_preferred":[
        "Sakhasi Tappeh"
    ],
    "name:swe_x_preferred":[
        "S\u0101khas\u012b Tappeh"
    ],
    "wof:name":"Sakhasi Tappeh",
    "wof:placetype":"locality"
},
  "geometry": {"coordinates":[45.5081,36.9371],"type":"Point"}
}