{
  "type": "Feature",
  "properties": {
    "gn:admin1_code":"8.0",
    "gn:asciiname":"Hari Mochaleh",
    "gn:country_code":"IR",
    "gn:dem":1566,
    "gn:feature_class":"P",
    "gn:feature_code":"PPL",
    "gn:name":"Har\u012b Moch\u0101leh",
    "gn:population":0,
    "gn:timezone":"Asia/Tehran",
    "iso:country":"IR",
    "name:fas_x_preferred":[
        "\u0647\u0631\u06cc \u0645\u0686\u0627\u0644\u0647"
    ],
    "name:und_x_variant":[
        "Har\u012b Moch\u0101leh"
    ],
    "wof:name":"Hari Mochaleh",
    "wof:placetype":"locality"
},
  "geometry": {"coordinates":[48.70058,37.74198],"type":"Point"}
}