{
  "type": "Feature",
  "properties": {
    "gn:admin1_code":"22",
    "gn:asciiname":"Bidkhvar",
    "gn:country_code":"IR",
    "gn:dem":699,
    "gn:feature_class":"P",
    "gn:feature_code":"PPL",
    "gn:name":"B\u012bdkhv\u0101r",
    "gn:population":0,
    "gn:timezone":"Asia/Tehran",
    "iso:country":"IR",
    "name:fas_x_preferred":[
        "\u0628\u064a\u062f\u0650\u0647 \u062e\u0648\u0627\u0631"
    ],
    "name:fas_x_variant":[
        "\u0628\u064a\u062f\u064e \u062e\u064e\u0631",
        "\u0628\u064a\u062f\u062e\u0648\u0627\u0631",
        "\u0628\u0627\u062f\u062e\u0648\u0627\u0631",
        "B\u012bdeh Khv\u0101r"
    ],
    "name:und_x_variant":[
        "B\u012bda Khar",
        "Bid Khar",
        "B\u012bdkhv\u0101r",
        "B\u0101dkhv\u0101r"
    ],
    "wof:name":"Bidkhvar",
    "wof:placetype":"locality"
},
  "geometry": {"coordinates":[52.3503,27.7923],"type":"Point"}
}