{
  "type": "Feature",
  "properties": {
    "gn:admin1_code":"15",
    "gn:asciiname":"Maqsud",
    "gn:country_code":"IR",
    "gn:dem":126,
    "gn:feature_class":"P",
    "gn:feature_code":"PPL",
    "gn:name":"Maq\u015f\u016bd",
    "gn:population":0,
    "gn:timezone":"Asia/Tehran",
    "iso:country":"IR",
    "name:fas_x_preferred":[
        "Maq\u015f\u016bd"
    ],
    "wof:name":"Maqsud",
    "wof:placetype":"locality"
},
  "geometry": {"coordinates":[48.61667,32.31667],"type":"Point"}
}