{
  "type": "Feature",
  "properties": {
    "gn:admin1_code":"7",
    "gn:asciiname":"Garpach",
    "gn:country_code":"IR",
    "gn:dem":1670,
    "gn:feature_class":"P",
    "gn:feature_code":"PPL",
    "gn:name":"Garp\u0101ch",
    "gn:population":0,
    "gn:timezone":"Asia/Tehran",
    "iso:country":"IR",
    "name:fas_x_preferred":[
        "Garp\u0101ch"
    ],
    "wof:name":"Garpach",
    "wof:placetype":"locality"
},
  "geometry": {"coordinates":[52.35583,30.23556],"type":"Point"}
}