{
  "type": "Feature",
  "properties": {
    "gn:admin1_code":"16",
    "gn:asciiname":"Dalu",
    "gn:country_code":"IR",
    "gn:dem":1452,
    "gn:feature_class":"P",
    "gn:feature_code":"PPL",
    "gn:name":"D\u0101l\u016b",
    "gn:population":0,
    "gn:timezone":"Asia/Tehran",
    "iso:country":"IR",
    "name:ceb_x_preferred":[
        "Dalu"
    ],
    "name:deu_x_preferred":[
        "Dalu"
    ],
    "name:fas_x_preferred":[
        "\u062f\u0627\u0644\u0648"
    ],
    "name:fas_x_variant":[
        "D\u0101l\u016b"
    ],
    "wof:name":"Dalu",
    "wof:placetype":"locality"
},
  "geometry": {"coordinates":[46.60932,36.27018],"type":"Point"}
}