{
  "type": "Feature",
  "properties": {
    "gn:admin1_code":"15.0",
    "gn:asciiname":"Milan",
    "gn:country_code":"IR",
    "gn:dem":12,
    "gn:feature_class":"P",
    "gn:feature_code":"PPL",
    "gn:name":"M\u012bl\u0101n",
    "gn:population":0,
    "gn:timezone":"Asia/Tehran",
    "iso:country":"IR",
    "name:fas_x_preferred":[
        "\u0645\u06cc\u0644\u0627\u0646"
    ],
    "name:fas_x_variant":[
        "\u0645\u0633\u062e\u0631"
    ],
    "name:und_x_variant":[
        "M\u012bl\u0101n",
        "Maskhar"
    ],
    "wof:name":"Milan",
    "wof:placetype":"locality"
},
  "geometry": {"coordinates":[48.76306,30.75651],"type":"Point"}
}