{
  "type": "Feature",
  "properties": {
    "iso:country":"IR",
    "qs:gn_pop":0,
    "qs:name":"Gazvin",
    "qs:name_adm0":"Iran",
    "qs:name_adm1":"Qazvin",
    "qs:photos":258,
    "qs:photos_1k":52,
    "qs:photos_9k":1,
    "qs:photos_9r":4,
    "qs:photos_all":258,
    "qs:photos_sr":5,
    "qs:placetype":"Town",
    "qs:pop_sr":"0",
    "qs:woe_adm0":23424851,
    "wof:name":"Gazvin",
    "wof:placetype":"locality"
},
  "geometry": {"coordinates":[50.0036975,36.266819],"type":"Point"}
}