{
  "type": "Feature",
  "properties": {
    "gn:admin1_code":"35.0",
    "gn:asciiname":"Qa'emiyeh",
    "gn:country_code":"IR",
    "gn:dem":-3,
    "gn:feature_class":"P",
    "gn:feature_code":"PPL",
    "gn:name":"Q\u0101\u2019em\u012byeh",
    "gn:population":0,
    "gn:timezone":"Asia/Tehran",
    "iso:country":"IR",
    "name:fas_x_preferred":[
        "\u0642\u0627\u0626\u0650\u0645\u064a\u0650\u0651\u06c0 \u0639\u064f\u0644\u064a\u0627"
    ],
    "name:fas_x_variant":[
        "Q\u0101\u2019em\u012byeh-ye \u2018Oly\u0101",
        "Q\u0101\u2019em\u012byeh",
        "\u0642\u0627\u0626\u0645\u064a\u0647"
    ],
    "wof:name":"Qa'emiyeh",
    "wof:placetype":"locality"
},
  "geometry": {"coordinates":[52.50126,36.55714],"type":"Point"}
}