{
  "type": "Feature",
  "properties": {
    "gn:admin1_code":"8",
    "gn:asciiname":"Chakan",
    "gn:country_code":"IR",
    "gn:dem":1992,
    "gn:feature_class":"P",
    "gn:feature_code":"PPL",
    "gn:name":"Ch\u0101k\u0101n",
    "gn:population":0,
    "gn:timezone":"Asia/Tehran",
    "iso:country":"IR",
    "name:fas_x_preferred":[
        "Ch\u0101k\u0101n"
    ],
    "name:fas_x_variant":[
        "\u0686\u0627\u06a9\u0627\u0646"
    ],
    "name:msa_x_preferred":[
        "Chakan"
    ],
    "name:ukr_x_preferred":[
        "\u0427\u0430\u043a\u0430\u043d"
    ],
    "wof:name":"Chakan",
    "wof:placetype":"locality"
},
  "geometry": {"coordinates":[50.18548,36.76235],"type":"Point"}
}