{
  "type": "Feature",
  "properties": {
    "gn:admin1_code":"8",
    "gn:asciiname":"Azarestan",
    "gn:country_code":"IR",
    "gn:dem":1580,
    "gn:feature_class":"P",
    "gn:feature_code":"PPL",
    "gn:name":"\u0100z\u0101rest\u0101n",
    "gn:population":0,
    "gn:timezone":"Asia/Tehran",
    "iso:country":"IR",
    "name:fas_x_preferred":[
        "\u0100z\u0101rest\u0101n"
    ],
    "name:fas_x_variant":[
        "\u0100z\u0101rest\u0101nak",
        "\u0622\u0632\u0627\u0631\u0633\u062a\u0627\u0646",
        "\u0622\u0632\u0627\u0631\u0633\u062a\u0627\u0646\u06a9"
    ],
    "name:msa_x_preferred":[
        "Azarestanak"
    ],
    "name:ukr_x_preferred":[
        "\u0410\u0437\u0430\u0440\u0435\u0441\u0442\u0430\u043d\u0430\u043a"
    ],
    "wof:name":"Azarestan",
    "wof:placetype":"locality"
},
  "geometry": {"coordinates":[49.8637,36.89838],"type":"Point"}
}