{
  "type": "Feature",
  "properties": {
    "gn:admin1_code":"41",
    "gn:asciiname":"Gavulag",
    "gn:country_code":"IR",
    "gn:dem":1788,
    "gn:feature_class":"P",
    "gn:feature_code":"PPL",
    "gn:name":"Gav\u016blag",
    "gn:population":0,
    "gn:timezone":"Asia/Tehran",
    "iso:country":"IR",
    "name:fas_x_preferred":[
        "\u06af\u0648\u0644\u06af"
    ],
    "name:fas_x_variant":[
        "G\u016blak",
        "\u06af\u0648\u0648\u0644\u06af"
    ],
    "name:und_x_variant":[
        "Gauwalg",
        "Goolag",
        "Goualg",
        "Gowlag",
        "Gav\u016blag"
    ],
    "wof:name":"Gavulag",
    "wof:placetype":"locality"
},
  "geometry": {"coordinates":[59.03253,32.43019],"type":"Point"}
}