{
  "type": "Feature",
  "properties": {
    "gn:admin1_code":"15.0",
    "gn:asciiname":"Chamim",
    "gn:country_code":"IR",
    "gn:dem":29,
    "gn:feature_class":"P",
    "gn:feature_code":"PPL",
    "gn:name":"Cham\u012bm",
    "gn:population":0,
    "gn:timezone":"Asia/Tehran",
    "iso:country":"IR",
    "name:ara_x_preferred":[
        "\u062a\u0634\u0645\u064a\u0645"
    ],
    "name:azb_x_preferred":[
        "\u0686\u0645\u06cc\u0645(\u0627\u0647\u0648\u0627\u0632)"
    ],
    "name:ceb_x_preferred":[
        "Cham\u012bm"
    ],
    "name:fas_x_preferred":[
        "\u0686\u0645\u06cc\u0645"
    ],
    "name:fas_x_variant":[
        "Cham\u012bm"
    ],
    "name:swe_x_preferred":[
        "Cham\u012bm"
    ],
    "wof:name":"Chamim",
    "wof:placetype":"locality"
},
  "geometry": {"coordinates":[48.4743,31.5581],"type":"Point"}
}