{
  "type": "Feature",
  "properties": {
    "gn:admin1_code":"42",
    "gn:asciiname":"Baghju",
    "gn:country_code":"IR",
    "gn:dem":1136,
    "gn:feature_class":"P",
    "gn:feature_code":"PPL",
    "gn:name":"B\u0101ghj\u016b",
    "gn:population":0,
    "gn:timezone":"Asia/Tehran",
    "iso:country":"IR",
    "name:fas_x_preferred":[
        "\u0628\u0627\u063a \u062c\u0627\u0646"
    ],
    "name:fas_x_variant":[
        "B\u0101gh J\u0101n",
        "\u0628\u0627\u063a\u062c\u0648"
    ],
    "name:und_x_variant":[
        "B\u0101ghj\u016b"
    ],
    "wof:name":"Baghju",
    "wof:placetype":"locality"
},
  "geometry": {"coordinates":[58.61789,36.00814000000001],"type":"Point"}
}