{
  "type": "Feature",
  "properties": {
    "gn:admin1_code":"1",
    "gn:asciiname":"Najibabad",
    "gn:country_code":"IR",
    "gn:dem":2058,
    "gn:feature_class":"P",
    "gn:feature_code":"PPL",
    "gn:name":"Naj\u012bb\u0101b\u0101d",
    "gn:population":0,
    "gn:timezone":"Asia/Tehran",
    "iso:country":"IR",
    "name:fas_x_preferred":[
        "Naj\u012bb\u0101b\u0101d"
    ],
    "name:fas_x_variant":[
        "\u0646\u062c\u06cc\u0628 \u0622\u0628\u0627\u062f"
    ],
    "name:und_x_variant":[
        "\u0646\u062c\u06cc\u0628 \u0622\u0628\u0627\u062f"
    ],
    "wof:name":"Najibabad",
    "wof:placetype":"locality"
},
  "geometry": {"coordinates":[44.4895,38.5179],"type":"Point"}
}