{
  "type": "Feature",
  "properties": {
    "gn:admin1_code":"1",
    "gn:asciiname":"Najibabad",
    "gn:country_code":"IR",
    "gn:dem":2058,
    "gn:feature_class":"P",
    "gn:feature_code":"PPL",
    "gn:name":"Naj\u012bb\u0101b\u0101d",
    "gn:population":0,
    "gn:timezone":"Asia/Tehran",
    "iso:country":"IR",
    "name:bih_x_preferred":[
        "\u0928\u091c\u0940\u092c\u093e\u092c\u093e\u0926"
    ],
    "name:bpy_x_preferred":[
        "\u09a8\u09be\u099c\u09bf\u09ac\u09be\u09ac\u09be\u09a6"
    ],
    "name:cat_x_preferred":[
        "Najidabad"
    ],
    "name:ceb_x_preferred":[
        "Naj\u012bb\u0101b\u0101d"
    ],
    "name:fas_x_preferred":[
        "Naj\u012bb\u0101b\u0101d"
    ],
    "name:fas_x_variant":[
        "\u0646\u062c\u06cc\u0628 \u0622\u0628\u0627\u062f",
        "\u0646\u062c\u06cc\u0628\u200c\u0622\u0628\u0627\u062f"
    ],
    "name:hif_x_preferred":[
        "Najibabad"
    ],
    "name:hin_x_preferred":[
        "\u0928\u091c\u0940\u092c\u093e\u092c\u093e\u0926"
    ],
    "name:ita_x_preferred":[
        "Najibabad"
    ],
    "name:jpn_x_preferred":[
        "\u30ca\u30b8\u30fc\u30d0\u30fc\u30d0\u30fc\u30c9"
    ],
    "name:mlg_x_preferred":[
        "Najibabad"
    ],
    "name:msa_x_preferred":[
        "Najibabad"
    ],
    "name:new_x_preferred":[
        "\u0928\u091c\u093f\u092c\u093e\u092c\u093e\u0926"
    ],
    "name:nld_x_preferred":[
        "Najibabad"
    ],
    "name:ori_x_preferred":[
        "\u0b28\u0b3e\u0b1c\u0b3f\u0b2c\u0b3e\u0b2c\u0b3e\u0b26\u0b4d"
    ],
    "name:pnb_x_preferred":[
        "\u0646\u062c\u06cc\u0628 \u0622\u0628\u0627\u062f"
    ],
    "name:pol_x_preferred":[
        "Najibabad"
    ],
    "name:swe_x_preferred":[
        "Najibabad"
    ],
    "name:urd_x_preferred":[
        "\u0646\u062c\u06cc\u0628 \u0622\u0628\u0627\u062f"
    ],
    "name:vie_x_preferred":[
        "Najibabad"
    ],
    "name:zho_x_preferred":[
        "\u7eb3\u5409\u5df4\u5df4\u5fb7"
    ],
    "wof:name":"Najibabad",
    "wof:placetype":"locality"
},
  "geometry": {"coordinates":[44.4895,38.5179],"type":"Point"}
}