{
  "type": "Feature",
  "properties": {
    "gn:admin1_code":"28",
    "gn:asciiname":"Mazra`eh-ye Shirabad",
    "gn:country_code":"IR",
    "gn:dem":888,
    "gn:feature_class":"P",
    "gn:feature_code":"PPLF",
    "gn:name":"Mazra\u2018eh-ye Sh\u012br\u0101b\u0101d",
    "gn:population":0,
    "gn:timezone":"Asia/Tehran",
    "iso:country":"IR",
    "name:fas_x_preferred":[
        "\u0645\u0632\u0631\u0639\u0647 \u0634\u064a\u0631 \u0622\u0628\u0627\u062f"
    ],
    "name:fas_x_variant":[
        "\u0634\u064a\u0631 \u0622\u0628\u0627\u062f",
        "Mazra\u2018eh-ye Sh\u012br\u0101b\u0101d",
        "\u0634\u0645\u0633 \u0622\u0628\u0627\u062f \u067e\u06cc\u0631\u0627",
        "\u0634\u0645\u0633 \u0622\u0628\u0627\u062f \u067e\u06cc\u0631\u0647"
    ],
    "name:und_x_variant":[
        "Sh\u012br\u0101b\u0101d",
        "Shams\u0101b\u0101d-e P\u012br\u0101",
        "Shams\u0101b\u0101d-e P\u012breh"
    ],
    "wof:name":"Mazra`eh-ye Shirabad",
    "wof:placetype":"locality"
},
  "geometry": {"coordinates":[51.4677,34.0947],"type":"Point"}
}