{
  "type": "Feature",
  "properties": {
    "gn:admin1_code":"13.0",
    "gn:asciiname":"Fashkhowran",
    "gn:country_code":"IR",
    "gn:dem":1533,
    "gn:feature_class":"P",
    "gn:feature_code":"PPL",
    "gn:name":"Fashkhowr\u0101n",
    "gn:population":0,
    "gn:timezone":"Asia/Tehran",
    "iso:country":"IR",
    "name:fas_x_preferred":[
        "\u0641\u0634\u062e\u0648\u0631\u0627\u0646"
    ],
    "name:fas_x_variant":[
        "Fashkhvor\u0101n"
    ],
    "name:und_x_variant":[
        "Fashkhowr\u0101n"
    ],
    "wof:name":"Fashkhowran",
    "wof:placetype":"locality"
},
  "geometry": {"coordinates":[47.94517000000001,34.55231],"type":"Point"}
}