{
  "type": "Feature",
  "properties": {
    "gn:admin1_code":"11",
    "gn:asciiname":"Demilu",
    "gn:country_code":"IR",
    "gn:dem":33,
    "gn:feature_class":"P",
    "gn:feature_code":"PPL",
    "gn:name":"Dem\u012bl\u016b",
    "gn:population":0,
    "gn:timezone":"Asia/Tehran",
    "iso:country":"IR",
    "name:ara_x_preferred":[
        "\u062f\u0645\u064a\u0644\u0648"
    ],
    "name:fas_x_preferred":[
        "\u062f\u0645\u064a\u0644\u0648"
    ],
    "name:fas_x_variant":[
        "\u062f\u064f\u0645\u064a\u0644\u0648",
        "Dem\u012bl\u016b",
        "\u062f\u0645\u06cc\u0644\u0648"
    ],
    "name:msa_x_preferred":[
        "Demilu"
    ],
    "name:und_x_variant":[
        "Damiloo",
        "Dom\u012bl\u016b"
    ],
    "wof:name":"Demilu",
    "wof:placetype":"locality"
},
  "geometry": {"coordinates":[55.8304,27.1809],"type":"Point"}
}