{
  "type": "Feature",
  "properties": {
    "gn:admin1_code":"29",
    "gn:asciiname":"Kalani",
    "gn:country_code":"IR",
    "gn:dem":2694,
    "gn:feature_class":"P",
    "gn:feature_code":"PPL",
    "gn:name":"Kal\u0101n\u012b",
    "gn:population":0,
    "gn:timezone":"Asia/Tehran",
    "iso:country":"IR",
    "name:fas_x_preferred":[
        "Kal\u0101n\u012b"
    ],
    "wof:name":"Kalani",
    "wof:placetype":"locality"
},
  "geometry": {"coordinates":[57.06667,29.35],"type":"Point"}
}