{
  "type": "Feature",
  "properties": {
    "gn:admin1_code":"13",
    "gn:asciiname":"`Amaleh-ye Bala",
    "gn:country_code":"IR",
    "gn:dem":1306,
    "gn:feature_class":"P",
    "gn:feature_code":"PPL",
    "gn:name":"\u2018Amaleh-ye B\u0101l\u0101",
    "gn:population":0,
    "gn:timezone":"Asia/Tehran",
    "iso:country":"IR",
    "name:fas_x_preferred":[
        "\u0639\u0645\u0644\u0647 \u0628\u0627\u0644\u0627"
    ],
    "name:fas_x_variant":[
        "\u2018Amaleh-ye \u2018Oly\u0101",
        "\u2018Amaleh-ye B\u0101l\u0101"
    ],
    "wof:name":"`Amaleh-ye Bala",
    "wof:placetype":"locality"
},
  "geometry": {"coordinates":[47.0227,34.5133],"type":"Point"}
}