{
  "type": "Feature",
  "properties": {
    "gn:admin1_code":"1",
    "gn:asciiname":"Sarenj",
    "gn:country_code":"IR",
    "gn:dem":809,
    "gn:feature_class":"P",
    "gn:feature_code":"PPL",
    "gn:name":"S\u0101renj",
    "gn:population":0,
    "gn:timezone":"Asia/Tehran",
    "iso:country":"IR",
    "name:azb_x_preferred":[
        "\u0633\u0627\u0631\u06cc\u0646\u062c"
    ],
    "name:aze_x_preferred":[
        "Sar\u0131nc"
    ],
    "name:fas_x_preferred":[
        "\u0633\u0627\u0631\u0646\u062c"
    ],
    "name:fas_x_variant":[
        "S\u0101renj"
    ],
    "name:msa_x_preferred":[
        "Sarenj"
    ],
    "wof:name":"Sarenj",
    "wof:placetype":"locality"
},
  "geometry": {"coordinates":[44.774,39.591],"type":"Point"}
}