{
  "type": "Feature",
  "properties": {
    "gn:admin1_code":"41",
    "gn:asciiname":"Sankert",
    "gn:country_code":"IR",
    "gn:dem":1855,
    "gn:feature_class":"P",
    "gn:feature_code":"PPL",
    "gn:name":"Sankert",
    "gn:population":0,
    "gn:timezone":"Asia/Tehran",
    "iso:country":"IR",
    "name:fas_x_preferred":[
        "\u0633\u0631 \u06a9\u0631\u062f"
    ],
    "name:fas_x_variant":[
        "\u0633\u0646\u06a9\u0631\u062a",
        "\u0633\u0627\u06af\u0631\u062f"
    ],
    "name:und_x_variant":[
        "Sar Kord",
        "Sankert",
        "S\u0101gerd"
    ],
    "wof:name":"Sankert",
    "wof:placetype":"locality"
},
  "geometry": {"coordinates":[59.85003,31.78547],"type":"Point"}
}