{
  "type": "Feature",
  "properties": {
    "gn:admin1_code":"8",
    "gn:asciiname":"Bojra",
    "gn:country_code":"IR",
    "gn:dem":560,
    "gn:feature_class":"P",
    "gn:feature_code":"PPLL",
    "gn:name":"Bojr\u0101",
    "gn:population":0,
    "gn:timezone":"Asia/Tehran",
    "iso:country":"IR",
    "name:fas_x_preferred":[
        "\u0628\u062c\u0631\u0627"
    ],
    "name:fas_x_variant":[
        "Bojr\u0101"
    ],
    "wof:name":"Bojra",
    "wof:placetype":"locality"
},
  "geometry": {"coordinates":[49.0856,37.3751],"type":"Point"}
}