{
  "type": "Feature",
  "properties": {
    "gn:admin1_code":"13",
    "gn:asciiname":"Bansulab-e Shir Mohammad",
    "gn:country_code":"IR",
    "gn:dem":1287,
    "gn:feature_class":"P",
    "gn:feature_code":"PPL",
    "gn:name":"B\u0101ns\u016bl\u0101b-e Sh\u012br Mo\u1e29ammad",
    "gn:population":0,
    "gn:timezone":"Asia/Tehran",
    "iso:country":"IR",
    "name:ara_x_preferred":[
        "\u0628\u0627\u0646\u200c\u0633\u0648\u0644\u0627\u0628 \u0634\u064a\u0631\u0645\u062d\u0645\u062f"
    ],
    "name:fas_x_preferred":[
        "\u0628\u0627\u0646\u0633\u0648\u0644\u0627\u0628 \u0634\u064a\u0631\u0645\u062d\u0645\u0651\u062f"
    ],
    "name:fas_x_variant":[
        "B\u0101ns\u016bl\u0101b-e Sh\u012br Mo\u1e29ammad",
        "\u0628\u0627\u0646\u200c\u0633\u0648\u0644\u0627\u0628 \u0634\u06cc\u0631\u0645\u062d\u0645\u062f"
    ],
    "name:und_x_variant":[
        "Malek \u2018Al\u012b Veys\u012b"
    ],
    "wof:name":"Bansulab-e Shir Mohammad",
    "wof:placetype":"locality"
},
  "geometry": {"coordinates":[46.3552,34.5422],"type":"Point"}
}