{
  "type": "Feature",
  "properties": {
    "gn:admin1_code":"41",
    "gn:asciiname":"Qias od Din",
    "gn:country_code":"IR",
    "gn:dem":2068,
    "gn:feature_class":"P",
    "gn:feature_code":"PPL",
    "gn:name":"Q\u012b\u0101s od D\u012bn",
    "gn:population":0,
    "gn:timezone":"Asia/Tehran",
    "iso:country":"IR",
    "name:fas_x_preferred":[
        "Gh\u012b\u0101s\u0304 od D\u012bn"
    ],
    "name:fas_x_variant":[
        "Gh\u012b\u0101s\u0304 ed D\u012bn",
        "\u063a\u064a\u0627\u062b \u0627\u0644\u062f\u064a\u0646",
        "\u0642\u064a\u0627\u0633 \u0627\u0644\u062f\u064a\u0646"
    ],
    "name:und_x_variant":[
        "\u063a\u064a\u0627\u062b \u0627\u0644\u062f\u064a\u0646",
        "Q\u012b\u0101s od D\u012bn"
    ],
    "wof:name":"Qias od Din",
    "wof:placetype":"locality"
},
  "geometry": {"coordinates":[59.47421,32.66886],"type":"Point"}
}