{
  "type": "Feature",
  "properties": {
    "gn:admin1_code":"5.0",
    "gn:asciiname":"Akhtar Moqadam",
    "gn:country_code":"IR",
    "gn:dem":2206,
    "gn:feature_class":"P",
    "gn:feature_code":"PPL",
    "gn:name":"Akhtar Moqadam",
    "gn:population":0,
    "gn:timezone":"Asia/Tehran",
    "iso:country":"IR",
    "name:fas_x_preferred":[
        "\u0627\u062e\u062a\u0631 \u0645\u0642\u062f\u0645"
    ],
    "wof:name":"Akhtar Moqadam",
    "wof:placetype":"locality"
},
  "geometry": {"coordinates":[51.03744,31.05294],"type":"Point"}
}