{
  "type": "Feature",
  "properties": {
    "gn:admin1_code":"4.0",
    "gn:asciiname":"Sukhteh Gaz",
    "gn:country_code":"IR",
    "gn:dem":1045,
    "gn:feature_class":"P",
    "gn:feature_code":"PPL",
    "gn:name":"S\u016bkhteh Gaz",
    "gn:population":0,
    "gn:timezone":"Asia/Tehran",
    "iso:country":"IR",
    "name:fas_x_preferred":[
        "\u0633\u0648\u062e\u062a\u0647 \u06af\u0632"
    ],
    "name:fas_x_variant":[
        "S\u016bkhteh Gaz"
    ],
    "name:und_x_variant":[
        "Tang-e Posht"
    ],
    "wof:name":"Sukhteh Gaz",
    "wof:placetype":"locality"
},
  "geometry": {"coordinates":[61.7069,26.692],"type":"Point"}
}