{
  "type": "Feature",
  "properties": {
    "gn:admin1_code":"8",
    "gn:asciiname":"Salimabad",
    "gn:country_code":"IR",
    "gn:dem":428,
    "gn:feature_class":"P",
    "gn:feature_code":"PPLL",
    "gn:name":"Sal\u012bm\u0101b\u0101d",
    "gn:population":0,
    "gn:timezone":"Asia/Tehran",
    "iso:country":"IR",
    "name:fas_x_preferred":[
        "\u0633\u0644\u06cc\u0645 \u0622\u0628\u0627\u062f"
    ],
    "name:fas_x_variant":[
        "Sal\u012bm\u0101b\u0101d"
    ],
    "wof:name":"Salimabad",
    "wof:placetype":"locality"
},
  "geometry": {"coordinates":[49.01300000000001,37.30893],"type":"Point"}
}