{
  "type": "Feature",
  "properties": {
    "gn:admin1_code":"1",
    "gn:asciiname":"Dizaj",
    "gn:country_code":"IR",
    "gn:dem":1525,
    "gn:feature_class":"P",
    "gn:feature_code":"PPL",
    "gn:name":"D\u012bzaj",
    "gn:population":0,
    "gn:timezone":"Asia/Tehran",
    "iso:country":"IR",
    "name:fas_x_preferred":[
        "\u062f\u064a\u0632\u064e\u062c"
    ],
    "name:fas_x_variant":[
        "\u062f\u064a\u0632\u0650\u0647",
        "D\u012bzaj",
        "\u062f\u064a\u0632\u064e\u062c \u067e\u064e\u0633\u064e\u0643",
        "\u062f\u064a\u0632\u064e\u062c\u0650 \u067e\u064e\u0633\u064e\u0643",
        "\u062f\u06cc\u0632\u062c"
    ],
    "name:und_x_variant":[
        "D\u012bzaj Pasak",
        "D\u012bzeh",
        "D\u012bzaj-e Pasak",
        "\u062f\u06cc\u0632\u062c"
    ],
    "wof:name":"Dizaj",
    "wof:placetype":"locality"
},
  "geometry": {"coordinates":[44.7648,38.6427],"type":"Point"}
}