{
  "type": "Feature",
  "properties": {
    "gn:admin1_code":"29.0",
    "gn:asciiname":"Kowsar Riz",
    "gn:country_code":"IR",
    "gn:dem":1462,
    "gn:feature_class":"P",
    "gn:feature_code":"PPL",
    "gn:name":"Kows\u0304ar R\u012bz",
    "gn:population":0,
    "gn:timezone":"Asia/Tehran",
    "iso:country":"IR",
    "name:fas_x_preferred":[
        "\u06a9\u0648\u062b\u0631 \u0631\u06cc\u0632"
    ],
    "name:fas_x_variant":[
        "Kows\u0304ar R\u012bz",
        "\u06a9\u0648\u062b\u0631\u0631\u06cc\u0632"
    ],
    "wof:name":"Kowsar Riz",
    "wof:placetype":"locality"
},
  "geometry": {"coordinates":[55.8322,30.4227],"type":"Point"}
}