{
  "type": "Feature",
  "properties": {
    "gn:admin1_code":"1",
    "gn:asciiname":"Kahel-e Sofla",
    "gn:country_code":"IR",
    "gn:dem":1636,
    "gn:feature_class":"P",
    "gn:feature_code":"PPL",
    "gn:name":"Kahel-e Sofl\u00e1",
    "gn:population":0,
    "gn:timezone":"Asia/Tehran",
    "iso:country":"IR",
    "name:fas_x_preferred":[
        "\u06a9\u0647\u0648\u0644 \u067e\u0627\u0626\u06cc\u0646"
    ],
    "name:fas_x_variant":[
        "Kahel-e Sofl\u00e1",
        "\u06a9\u0647\u0644 \u0633\u0641\u0644\u06cc"
    ],
    "name:und_x_variant":[
        "Kah\u016bl-e P\u0101\u2019\u012bn"
    ],
    "wof:name":"Kahel-e Sofla",
    "wof:placetype":"locality"
},
  "geometry": {"coordinates":[46.62498,36.75257],"type":"Point"}
}