{
  "type": "Feature",
  "properties": {
    "gn:admin1_code":"5",
    "gn:asciiname":"Moradi",
    "gn:country_code":"IR",
    "gn:dem":1823,
    "gn:feature_class":"P",
    "gn:feature_code":"PPL",
    "gn:name":"Mor\u0101d\u012b",
    "gn:population":0,
    "gn:timezone":"Asia/Tehran",
    "iso:country":"IR",
    "name:deu_x_preferred":[
        "Moradi"
    ],
    "name:fas_x_preferred":[
        "Mor\u0101d\u012b"
    ],
    "name:fas_x_variant":[
        "\u0645\u0631\u0627\u062f\u06cc"
    ],
    "name:fra_x_preferred":[
        "Moradi"
    ],
    "name:rus_x_preferred":[
        "\u041c\u043e\u0440\u0430\u0434\u0438"
    ],
    "name:und_x_variant":[
        "\u0645\u0631\u0627\u062f\u06cc"
    ],
    "wof:name":"Moradi",
    "wof:placetype":"locality"
},
  "geometry": {"coordinates":[51.27406,30.70797],"type":"Point"}
}