{
  "type": "Feature",
  "properties": {
    "gn:admin1_code":"8",
    "gn:asciiname":"Shiva",
    "gn:country_code":"IR",
    "gn:dem":13,
    "gn:feature_class":"P",
    "gn:feature_code":"PPL",
    "gn:name":"Sh\u012bv\u0101",
    "gn:population":0,
    "gn:timezone":"Asia/Tehran",
    "iso:country":"IR",
    "name:fas_x_preferred":[
        "Sh\u012bv\u0101"
    ],
    "name:msa_x_preferred":[
        "Shiva"
    ],
    "name:ukr_x_preferred":[
        "\u0428\u0456\u0432\u0430"
    ],
    "wof:name":"Shiva",
    "wof:placetype":"locality"
},
  "geometry": {"coordinates":[49.79028,37.21],"type":"Point"}
}