{
  "type": "Feature",
  "properties": {
    "gn:admin1_code":"11",
    "gn:asciiname":"Sarju'iyeh-ye Pa'in",
    "gn:country_code":"IR",
    "gn:dem":199,
    "gn:feature_class":"P",
    "gn:feature_code":"PPL",
    "gn:name":"Sarj\u016b\u2019\u012byeh-ye P\u0101\u2019\u012bn",
    "gn:population":0,
    "gn:timezone":"Asia/Tehran",
    "iso:country":"IR",
    "name:fas_x_preferred":[
        "\u0633\u0631\u062c\u0648\u0626\u064a\u0647 \u067e\u0627\u0626\u064a\u0646"
    ],
    "name:fas_x_variant":[
        "Sarj\u016b\u2019\u012byeh-ye P\u0101\u2019\u012bn"
    ],
    "name:und_x_variant":[
        "Sarj\u016b\u2019\u012byeh P\u0101\u2019\u012bn"
    ],
    "wof:name":"Sarju'iyeh-ye Pa'in",
    "wof:placetype":"locality"
},
  "geometry": {"coordinates":[57.2366,27.4249],"type":"Point"}
}