{
  "type": "Feature",
  "properties": {
    "gn:admin1_code":"1",
    "gn:asciiname":"Masu",
    "gn:country_code":"IR",
    "gn:dem":1495,
    "gn:feature_class":"P",
    "gn:feature_code":"PPL",
    "gn:name":"M\u0101s\u016b",
    "gn:population":0,
    "gn:timezone":"Asia/Tehran",
    "iso:country":"IR",
    "name:fas_x_preferred":[
        "\u0645\u0627\u0633\u0648"
    ],
    "name:fas_x_variant":[
        "M\u0101s\u016b"
    ],
    "wof:name":"Masu",
    "wof:placetype":"locality"
},
  "geometry": {"coordinates":[45.5631,36.8049],"type":"Point"}
}