{
  "type": "Feature",
  "properties": {
    "gn:admin1_code":"28.0",
    "gn:asciiname":"Shahrak-e Yaser",
    "gn:country_code":"IR",
    "gn:dem":2096,
    "gn:feature_class":"P",
    "gn:feature_code":"PPL",
    "gn:name":"Shahrak-e Y\u0101ser",
    "gn:population":0,
    "gn:timezone":"Asia/Tehran",
    "iso:country":"IR",
    "name:fas_x_preferred":[
        "Shahrak-e Y\u0101ser"
    ],
    "name:fas_x_variant":[
        "\u0634\u0647\u0631\u0643 \u06cc\u0627\u0633\u0631",
        "\u0634\u0647\u0631\u0643 \u06cc\u0627\u0633\u0631 \u062f\u0648"
    ],
    "name:und_x_variant":[
        "\u0634\u0647\u0631\u0643 \u06cc\u0627\u0633\u0631",
        "Shahrak-e Y\u0101ser-e Do"
    ],
    "wof:name":"Shahrak-e Yaser",
    "wof:placetype":"locality"
},
  "geometry": {"coordinates":[50.3301,33.29],"type":"Point"}
}