{
  "type": "Feature",
  "properties": {
    "gn:admin1_code":"29",
    "gn:asciiname":"Zamin Anjir",
    "gn:country_code":"IR",
    "gn:dem":2225,
    "gn:feature_class":"P",
    "gn:feature_code":"PPL",
    "gn:name":"Zam\u012bn Anj\u012br",
    "gn:population":0,
    "gn:timezone":"Asia/Tehran",
    "iso:country":"IR",
    "name:fas_x_preferred":[
        "\u0632\u0645\u06cc\u0646 \u0627\u0646\u062c\u06cc\u0631"
    ],
    "name:fas_x_variant":[
        "Zam\u012bn Anj\u012br"
    ],
    "name:und_x_variant":[
        "Zam\u012bn-e Anj\u012br"
    ],
    "wof:name":"Zamin Anjir",
    "wof:placetype":"locality"
},
  "geometry": {"coordinates":[56.9626,29.2904],"type":"Point"}
}