{
  "type": "Feature",
  "properties": {
    "gn:admin1_code":"29",
    "gn:asciiname":"Qal`eh Khan",
    "gn:country_code":"IR",
    "gn:dem":769,
    "gn:feature_class":"P",
    "gn:feature_code":"PPL",
    "gn:name":"Qal\u2018eh Kh\u0101n",
    "gn:population":0,
    "gn:timezone":"Asia/Tehran",
    "iso:country":"IR",
    "name:fas_x_preferred":[
        "\u0642\u0644\u0639\u0647 \u062e\u0627\u0646"
    ],
    "name:fas_x_variant":[
        "Kallehg\u0101n",
        "Qal\u2018eh Kh\u0101n",
        "\u06a9\u0644\u0647 \u06af\u0627\u0646"
    ],
    "name:und_x_variant":[
        "Kalagan"
    ],
    "wof:name":"Qal`eh Khan",
    "wof:placetype":"locality"
},
  "geometry": {"coordinates":[58.8034,26.79874],"type":"Point"}
}