{
  "type": "Feature",
  "properties": {
    "gn:admin1_code":"28",
    "gn:asciiname":"Darkan",
    "gn:country_code":"IR",
    "gn:dem":1962,
    "gn:feature_class":"P",
    "gn:feature_code":"PPL",
    "gn:name":"Dark\u0101n",
    "gn:population":0,
    "gn:timezone":"Asia/Tehran",
    "iso:country":"IR",
    "name:ara_x_preferred":[
        "\u062f\u0631\u0643\u0627\u0646"
    ],
    "name:fas_x_preferred":[
        "\u062f\u0650\u0631\u0643\u0627\u0646"
    ],
    "name:fas_x_variant":[
        "Dark\u0101n",
        "\u062f\u064e\u0631\u064e\u0643\u0627\u0646",
        "\u062f\u064e\u0631\u0643\u0627\u0646",
        "Deh Kh\u0101n",
        "\u062f\u0650\u0647 \u062e\u0627\u0646",
        "\u062f\u0631\u06a9\u0627\u0646"
    ],
    "name:und_x_variant":[
        "Derk\u0101n",
        "Darak\u0101n"
    ],
    "wof:name":"Darkan",
    "wof:placetype":"locality"
},
  "geometry": {"coordinates":[50.80126,32.70904],"type":"Point"}
}