{
  "type": "Feature",
  "properties": {
    "gn:admin1_code":"33",
    "gn:asciiname":"Kalaleh-ye Bala",
    "gn:country_code":"IR",
    "gn:dem":1116,
    "gn:feature_class":"P",
    "gn:feature_code":"PPL",
    "gn:name":"Kal\u0101leh-ye B\u0101l\u0101",
    "gn:population":0,
    "gn:timezone":"Asia/Tehran",
    "iso:country":"IR",
    "name:fas_x_preferred":[
        "Kal\u0101leh-ye B\u0101l\u0101"
    ],
    "name:und_x_variant":[
        "Kalaleh Olya",
        "Kal\u0101leh-ye \u2018Oly\u0101"
    ],
    "wof:name":"Kalaleh-ye Bala",
    "wof:placetype":"locality"
},
  "geometry": {"coordinates":[46.76667,38.95],"type":"Point"}
}