{
  "type": "Feature",
  "properties": {
    "gn:admin1_code":"43",
    "gn:asciiname":"Dehgah",
    "gn:country_code":"IR",
    "gn:dem":1297,
    "gn:feature_class":"P",
    "gn:feature_code":"PPL",
    "gn:name":"Dehg\u0101h",
    "gn:population":0,
    "gn:timezone":"Asia/Tehran",
    "iso:country":"IR",
    "name:fas_x_preferred":[
        "Dehg\u0101h"
    ],
    "wof:name":"Dehgah",
    "wof:placetype":"locality"
},
  "geometry": {"coordinates":[57.06083,37.47222],"type":"Point"}
}