{
  "type": "Feature",
  "properties": {
    "gn:admin1_code":"10",
    "gn:asciiname":"Sefid Khani",
    "gn:country_code":"IR",
    "gn:dem":1139,
    "gn:feature_class":"P",
    "gn:feature_code":"PPL",
    "gn:name":"Sef\u012bd Kh\u0101n\u012b",
    "gn:population":0,
    "gn:timezone":"Asia/Tehran",
    "iso:country":"IR",
    "name:fas_x_preferred":[
        "\u0633\u0641\u06cc\u062f\u062e\u0627\u0646\u06cc \u0639\u0644\u06cc\u0627"
    ],
    "name:fas_x_variant":[
        "Sef\u012bd Kh\u0101n\u012b-ye \u2018Oly\u0101",
        "\u0633\u0641\u06cc\u062f\u062e\u0627\u0646\u06cc"
    ],
    "name:und_x_variant":[
        "Sef\u012bd Kh\u0101n\u012b"
    ],
    "wof:name":"Sefid Khani",
    "wof:placetype":"locality"
},
  "geometry": {"coordinates":[46.60223,33.66411],"type":"Point"}
}