{
  "type": "Feature",
  "properties": {
    "gn:admin1_code":"33",
    "gn:asciiname":"Kolamarz Chay",
    "gn:country_code":"IR",
    "gn:dem":1344,
    "gn:feature_class":"P",
    "gn:feature_code":"PPL",
    "gn:name":"Kol\u0101marz Ch\u0101y",
    "gn:population":0,
    "gn:timezone":"Asia/Tehran",
    "iso:country":"IR",
    "name:fas_x_preferred":[
        "Kol\u0101marz Ch\u0101y"
    ],
    "wof:name":"Kolamarz Chay",
    "wof:placetype":"locality"
},
  "geometry": {"coordinates":[47.71667,37.55],"type":"Point"}
}