{
  "type": "Feature",
  "properties": {
    "gn:admin1_code":"1.0",
    "gn:asciiname":"Silu Ma`qul",
    "gn:country_code":"IR",
    "gn:dem":2337,
    "gn:feature_class":"P",
    "gn:feature_code":"PPL",
    "gn:name":"S\u012bl\u016b Ma\u2018q\u016bl",
    "gn:population":0,
    "gn:timezone":"Asia/Tehran",
    "iso:country":"IR",
    "name:fas_x_preferred":[
        "\u0633\u06cc\u0644\u0648 \u0645\u0639\u0642\u0648\u0644"
    ],
    "name:fas_x_variant":[
        "S\u012bl\u016b Ma\u2018q\u016bl"
    ],
    "wof:name":"Silu Ma`qul",
    "wof:placetype":"locality"
},
  "geometry": {"coordinates":[44.0504,39.3821],"type":"Point"}
}