{
  "type": "Feature",
  "properties": {
    "gn:admin1_code":"13",
    "gn:asciiname":"Bulan",
    "gn:country_code":"IR",
    "gn:dem":1768,
    "gn:feature_class":"P",
    "gn:feature_code":"PPL",
    "gn:name":"B\u016bl\u0101n",
    "gn:population":0,
    "gn:timezone":"Asia/Tehran",
    "iso:country":"IR",
    "name:ceb_x_preferred":[
        "Bulan"
    ],
    "name:deu_x_preferred":[
        "Bulan"
    ],
    "name:fas_x_preferred":[
        "\u0628\u0648\u0644\u0627\u0646"
    ],
    "name:fas_x_variant":[
        "B\u016bl\u0101n"
    ],
    "name:fra_x_preferred":[
        "Bulan"
    ],
    "name:ind_x_preferred":[
        "Bulan"
    ],
    "name:ita_x_preferred":[
        "Bulan"
    ],
    "name:msa_x_preferred":[
        "Bulan"
    ],
    "name:nld_x_preferred":[
        "Bulan"
    ],
    "name:rus_x_preferred":[
        "\u0411\u0443\u043b\u0430\u043d"
    ],
    "name:sun_x_preferred":[
        "Bulan"
    ],
    "name:swe_x_preferred":[
        "Bulan"
    ],
    "name:tgl_x_preferred":[
        "Buwan"
    ],
    "name:war_x_preferred":[
        "Bulan"
    ],
    "wof:name":"Bulan",
    "wof:placetype":"locality"
},
  "geometry": {"coordinates":[47.1749,34.6858],"type":"Point"}
}