{
  "type": "Feature",
  "properties": {
    "gn:admin1_code":"35.0",
    "gn:asciiname":"Peymur",
    "gn:country_code":"IR",
    "gn:dem":1347,
    "gn:feature_class":"P",
    "gn:feature_code":"PPL",
    "gn:name":"Peym\u016br",
    "gn:population":0,
    "gn:timezone":"Asia/Tehran",
    "iso:country":"IR",
    "name:ara_x_preferred":[
        "\u0628\u064a\u0645\u0628\u0648\u0631"
    ],
    "name:fas_x_preferred":[
        "\u067e\u0650\u064a\u0645\u0628\u0648\u0631"
    ],
    "name:fas_x_variant":[
        "\u067e\u06cc\u0645\u0648\u0631",
        "Peyamb\u016br",
        "\u067e\u0650\u064a\u0645 \u0628\u0648\u0631",
        "\u067e\u06cc \u0645\u0648\u0631",
        "\u067e\u06cc\u0645\u0628\u0648\u0631"
    ],
    "name:und_x_variant":[
        "Peym\u016br",
        "Pey M\u016br",
        "Peyam B\u016br"
    ],
    "wof:name":"Peymur",
    "wof:placetype":"locality"
},
  "geometry": {"coordinates":[51.20295,36.57324000000001],"type":"Point"}
}