{
  "type": "Feature",
  "properties": {
    "gn:admin1_code":"32",
    "gn:asciiname":"Seh Saran",
    "gn:country_code":"IR",
    "gn:dem":1933,
    "gn:feature_class":"P",
    "gn:feature_code":"PPL",
    "gn:name":"Seh Sar\u0101n",
    "gn:population":0,
    "gn:timezone":"Asia/Tehran",
    "iso:country":"IR",
    "name:fas_x_preferred":[
        "\u0633\u0647 \u0633\u0631\u0627\u0646"
    ],
    "name:fas_x_variant":[
        "Seh Sar\u0101n"
    ],
    "wof:name":"Seh Saran",
    "wof:placetype":"locality"
},
  "geometry": {"coordinates":[48.8864,37.302],"type":"Point"}
}