{
  "type": "Feature",
  "properties": {
    "gn:admin1_code":"34",
    "gn:asciiname":"Qeshlaq Qotbabad",
    "gn:country_code":"IR",
    "gn:dem":1863,
    "gn:feature_class":"P",
    "gn:feature_code":"PPL",
    "gn:name":"Qeshl\u0101q Qo\u0163b\u0101b\u0101d",
    "gn:population":0,
    "gn:timezone":"Asia/Tehran",
    "iso:country":"IR",
    "name:fas_x_preferred":[
        "\u0642\u0634\u0644\u0627\u0642 \u0642\u0637\u0628 \u0622\u0628\u0627\u062f"
    ],
    "name:fas_x_variant":[
        "\u0642\u064f\u0637\u0628 \u0622\u0628\u0627\u062f"
    ],
    "name:und_x_variant":[
        "Qo\u0163b\u0101b\u0101d",
        "Qeshl\u0101q Qo\u0163b\u0101b\u0101d"
    ],
    "wof:name":"Qeshlaq Qotbabad",
    "wof:placetype":"locality"
},
  "geometry": {"coordinates":[49.2067,34.4253],"type":"Point"}
}