{
  "type": "Feature",
  "properties": {
    "gn:admin1_code":"37",
    "gn:asciiname":"Galikesh",
    "gn:country_code":"IR",
    "gn:dem":195,
    "gn:feature_class":"P",
    "gn:feature_code":"PPLA2",
    "gn:name":"G\u0101l\u012bkesh",
    "gn:population":0,
    "gn:timezone":"Asia/Tehran",
    "iso:country":"IR",
    "name:ara_x_preferred":[
        "\u063a\u0627\u0644\u064a\u0643\u0634"
    ],
    "name:aze_x_preferred":[
        "Galik\u0259\u015f"
    ],
    "name:ceb_x_preferred":[
        "G\u0101l\u012bkesh"
    ],
    "name:fas_x_preferred":[
        "G\u0101l\u012bkash"
    ],
    "name:fas_x_variant":[
        "\u06af\u0627\u0644\u064a\u0643\u0634",
        "\u06af\u0627\u0644\u06cc\u06a9\u0634"
    ],
    "name:ita_x_preferred":[
        "Galikash"
    ],
    "name:mlg_x_preferred":[
        "Galikash"
    ],
    "name:msa_x_preferred":[
        "Galikash"
    ],
    "name:tur_x_preferred":[
        "Galike\u015f"
    ],
    "name:und_x_variant":[
        "Gal\u012bkesh"
    ],
    "wof:name":"Galikesh",
    "wof:placetype":"locality"
},
  "geometry": {"coordinates":[55.43394,37.27259],"type":"Point"}
}