{
  "type": "Feature",
  "properties": {
    "gn:admin1_code":"8.0",
    "gn:asciiname":"Sarum",
    "gn:country_code":"IR",
    "gn:dem":861,
    "gn:feature_class":"P",
    "gn:feature_code":"PPL",
    "gn:name":"S\u0101r\u016bm",
    "gn:population":0,
    "gn:timezone":"Asia/Tehran",
    "iso:country":"IR",
    "name:fas_x_preferred":[
        "S\u0101r\u016bm"
    ],
    "name:fas_x_variant":[
        "\u0633\u0627\u0631\u0648\u0645"
    ],
    "name:und_x_variant":[
        "\u0633\u0627\u0631\u0648\u0645"
    ],
    "wof:name":"Sarum",
    "wof:placetype":"locality"
},
  "geometry": {"coordinates":[49.7402,36.66034000000001],"type":"Point"}
}