{
  "type": "Feature",
  "properties": {
    "gn:admin1_code":"23",
    "gn:asciiname":"Namju",
    "gn:country_code":"IR",
    "gn:dem":1239,
    "gn:feature_class":"P",
    "gn:feature_code":"PPL",
    "gn:name":"N\u0101mj\u016b",
    "gn:population":0,
    "gn:timezone":"Asia/Tehran",
    "iso:country":"IR",
    "name:ceb_x_preferred":[
        "N\u0101mj\u016b"
    ],
    "name:fas_x_preferred":[
        "N\u0101mj\u016b"
    ],
    "name:fas_x_variant":[
        "\u0646\u0627\u0645\u062c\u0648"
    ],
    "name:swe_x_preferred":[
        "N\u0101mj\u016b"
    ],
    "wof:name":"Namju",
    "wof:placetype":"locality"
},
  "geometry": {"coordinates":[47.4683,33.697],"type":"Point"}
}