{
  "type": "Feature",
  "properties": {
    "gn:admin1_code":"29.0",
    "gn:asciiname":"Bab Karas",
    "gn:country_code":"IR",
    "gn:dem":2756,
    "gn:feature_class":"P",
    "gn:feature_code":"PPLL",
    "gn:name":"B\u0101b Karas",
    "gn:population":0,
    "gn:timezone":"Asia/Tehran",
    "iso:country":"IR",
    "name:fas_x_preferred":[
        "B\u0101b Karafs"
    ],
    "name:fas_x_variant":[
        "\u0628\u0627\u0628 \u06a9\u0631\u0641\u0633",
        "\u0628\u0627\u0628 \u06a9\u0631\u0633"
    ],
    "name:und_x_variant":[
        "\u0628\u0627\u0628 \u06a9\u0631\u0641\u0633",
        "B\u0101b Karas"
    ],
    "wof:name":"Bab Karas",
    "wof:placetype":"locality"
},
  "geometry": {"coordinates":[57.23362,29.27092],"type":"Point"}
}