{
  "type": "Feature",
  "properties": {
    "gn:admin1_code":"7.0",
    "gn:asciiname":"Dasht-e Ahmad",
    "gn:country_code":"IR",
    "gn:dem":1346,
    "gn:feature_class":"P",
    "gn:feature_code":"PPL",
    "gn:name":"Dasht-e A\u1e29mad",
    "gn:population":0,
    "gn:timezone":"Asia/Tehran",
    "iso:country":"IR",
    "name:ara_x_preferred":[
        "\u062f\u0634\u062a \u0627\u062d\u0645\u062f"
    ],
    "name:fas_x_preferred":[
        "\u062f\u0634\u062a \u0627\u062d\u0645\u062f"
    ],
    "name:fas_x_variant":[
        "Dasht-e A\u1e29mad"
    ],
    "name:msa_x_preferred":[
        "Dasht-e Ahmad"
    ],
    "wof:name":"Dasht-e Ahmad",
    "wof:placetype":"locality"
},
  "geometry": {"coordinates":[53.6757,28.92585],"type":"Point"}
}