{
  "type": "Feature",
  "properties": {
    "gn:admin1_code":"23",
    "gn:asciiname":"Bareh Kaleg",
    "gn:country_code":"IR",
    "gn:dem":1560,
    "gn:feature_class":"P",
    "gn:feature_code":"PPL",
    "gn:name":"Bareh Kaleg",
    "gn:population":0,
    "gn:timezone":"Asia/Tehran",
    "iso:country":"IR",
    "name:fas_x_preferred":[
        "\u0628\u0631\u0647 \u06a9\u0644\u06a9"
    ],
    "name:fas_x_variant":[
        "\u0628\u0631\u0647 \u06a9\u0644\u06af"
    ],
    "name:und_x_variant":[
        "Bareh Kalak",
        "Bareh Kaleg"
    ],
    "wof:name":"Bareh Kaleg",
    "wof:placetype":"locality"
},
  "geometry": {"coordinates":[47.2947,33.6434],"type":"Point"}
}