{
  "type": "Feature",
  "properties": {
    "gn:admin1_code":"8.0",
    "gn:asciiname":"Gorchan Kesh",
    "gn:country_code":"IR",
    "gn:dem":158,
    "gn:feature_class":"P",
    "gn:feature_code":"PPL",
    "gn:name":"Gorchan Kesh",
    "gn:population":0,
    "gn:timezone":"Asia/Tehran",
    "iso:country":"IR",
    "name:fas_x_preferred":[
        "\u06af\u0631\u0686\u0646 \u06a9\u0634"
    ],
    "name:fas_x_variant":[
        "\u06af\u06cc\u062c\u0627\u0648"
    ],
    "name:und_x_variant":[
        "G\u012bj\u0101v"
    ],
    "wof:name":"Gorchan Kesh",
    "wof:placetype":"locality"
},
  "geometry": {"coordinates":[48.88158,37.70264],"type":"Point"}
}