{
  "type": "Feature",
  "properties": {
    "gn:admin1_code":"8",
    "gn:asciiname":"Damash",
    "gn:country_code":"IR",
    "gn:dem":1741,
    "gn:feature_class":"P",
    "gn:feature_code":"PPL",
    "gn:name":"D\u0101m\u0101sh",
    "gn:population":0,
    "gn:timezone":"Asia/Tehran",
    "iso:country":"IR",
    "name:ceb_x_preferred":[
        "D\u0101m\u0101sh"
    ],
    "name:fas_x_preferred":[
        "D\u0101mash"
    ],
    "name:fas_x_variant":[
        "D\u0101m\u0101shak",
        "\u062f\u0627\u0645\u0634",
        "\u062f\u0627\u0645\u0627\u0634"
    ],
    "name:msa_x_preferred":[
        "Damash"
    ],
    "name:swe_x_preferred":[
        "D\u0101m\u0101sh"
    ],
    "name:ukr_x_preferred":[
        "\u0414\u0430\u043c\u0430\u0448"
    ],
    "name:und_x_variant":[
        "D\u0101m\u0101sh",
        "\u062f\u0627\u0645\u0634"
    ],
    "wof:name":"Damash",
    "wof:placetype":"locality"
},
  "geometry": {"coordinates":[49.81,36.75482],"type":"Point"}
}