{
  "type": "Feature",
  "properties": {
    "gn:admin1_code":"42.0",
    "gn:asciiname":"Qal`eh-ye Now",
    "gn:country_code":"IR",
    "gn:dem":933,
    "gn:feature_class":"P",
    "gn:feature_code":"PPL",
    "gn:name":"Qal\u2018eh-ye Now",
    "gn:population":0,
    "gn:timezone":"Asia/Tehran",
    "iso:country":"IR",
    "name:fas_x_preferred":[
        "\u0642\u0644\u0639\u0647 \u0646\u0648"
    ],
    "name:und_x_variant":[
        "Qal\u2018eh-ye Now"
    ],
    "wof:name":"Qal`eh-ye Now",
    "wof:placetype":"locality"
},
  "geometry": {"coordinates":[56.63544,36.72207],"type":"Point"}
}