{
  "type": "Feature",
  "properties": {
    "gn:admin1_code":"15.0",
    "gn:asciiname":"Meydan-e Khodaverdi",
    "gn:country_code":"IR",
    "gn:dem":506,
    "gn:feature_class":"P",
    "gn:feature_code":"PPL",
    "gn:name":"Meyd\u0101n-e Khod\u0101verd\u012b",
    "gn:population":0,
    "gn:timezone":"Asia/Tehran",
    "iso:country":"IR",
    "name:fas_x_preferred":[
        "\u0645\u06cc\u062f\u0627\u0646 \u062e\u062f\u0627\u0648\u0631\u062f\u06cc"
    ],
    "name:fas_x_variant":[
        "Meyd\u0101n-e Khod\u0101verd\u012b"
    ],
    "wof:name":"Meydan-e Khodaverdi",
    "wof:placetype":"locality"
},
  "geometry": {"coordinates":[48.2505,32.7809],"type":"Point"}
}