{
  "type": "Feature",
  "properties": {
    "gn:admin1_code":"34",
    "gn:asciiname":"Tahereh Khatun",
    "gn:country_code":"IR",
    "gn:dem":1587,
    "gn:feature_class":"P",
    "gn:feature_code":"PPL",
    "gn:name":"\u0162\u0101hereh Kh\u0101t\u016bn",
    "gn:population":0,
    "gn:timezone":"Asia/Tehran",
    "iso:country":"IR",
    "name:ceb_x_preferred":[
        "\u0162\u0101hereh Kh\u0101t\u016bn"
    ],
    "name:fas_x_preferred":[
        "\u0637\u0627\u0647\u0631\u0647 \u062e\u0627\u062a\u0648\u0646"
    ],
    "name:fas_x_variant":[
        "\u0162\u0101hereh Kh\u0101t\u016bn",
        "\u0637\u0627\u0647\u0631\u0647\u200c\u062e\u0627\u062a\u0648\u0646"
    ],
    "name:swe_x_preferred":[
        "\u0162\u0101hereh Kh\u0101t\u016bn"
    ],
    "name:ukr_x_preferred":[
        "\u0422\u0430\u0433\u0435\u0440\u0435-\u0425\u0430\u0442\u0443\u043d"
    ],
    "name:und_x_variant":[
        "Tafrakaman"
    ],
    "wof:name":"Tahereh Khatun",
    "wof:placetype":"locality"
},
  "geometry": {"coordinates":[49.71816,35.09476],"type":"Point"}
}