{
  "type": "Feature",
  "properties": {
    "gn:admin1_code":"10.0",
    "gn:asciiname":"Mar Barreh",
    "gn:country_code":"IR",
    "gn:dem":1291,
    "gn:feature_class":"P",
    "gn:feature_code":"PPL",
    "gn:name":"M\u0101r Barreh",
    "gn:population":0,
    "gn:timezone":"Asia/Tehran",
    "iso:country":"IR",
    "name:ceb_x_preferred":[
        "M\u0101r Barreh"
    ],
    "name:fas_x_preferred":[
        "\u0645\u0627\u064a\u0650\u0631\u0650\u0647"
    ],
    "name:fas_x_variant":[
        "\u0645\u0627\u0631 \u0628\u0631\u0651\u0647",
        "M\u0101r Bereh",
        "M\u0101r Barreh",
        "\u0645\u0627\u0631\u0628\u0631\u0647"
    ],
    "name:msa_x_preferred":[
        "Mar Barreh"
    ],
    "name:swe_x_preferred":[
        "M\u0101r Barreh"
    ],
    "name:und_x_variant":[
        "M\u0101yereh"
    ],
    "wof:name":"Mar Barreh",
    "wof:placetype":"locality"
},
  "geometry": {"coordinates":[46.3422,33.5458],"type":"Point"}
}