{
  "type": "Feature",
  "properties": {
    "gn:admin1_code":"8",
    "gn:asciiname":"Hend Khaleh",
    "gn:country_code":"IR",
    "gn:dem":-21,
    "gn:feature_class":"P",
    "gn:feature_code":"PPL",
    "gn:name":"Hend Kh\u0101leh",
    "gn:population":0,
    "gn:timezone":"Asia/Tehran",
    "iso:country":"IR",
    "name:fas_x_preferred":[
        "\u0647\u0646\u062f \u062e\u0627\u0644\u0647"
    ],
    "name:fas_x_variant":[
        "Hend Kh\u0101leh"
    ],
    "wof:name":"Hend Khaleh",
    "wof:placetype":"locality"
},
  "geometry": {"coordinates":[49.44408,37.3617],"type":"Point"}
}