{
  "type": "Feature",
  "properties": {
    "gn:admin1_code":"5",
    "gn:asciiname":"Talgehi Bala",
    "gn:country_code":"IR",
    "gn:dem":1962,
    "gn:feature_class":"P",
    "gn:feature_code":"PPL",
    "gn:name":"Talgeh\u012b B\u0101l\u0101",
    "gn:population":0,
    "gn:timezone":"Asia/Tehran",
    "iso:country":"IR",
    "name:fas_x_preferred":[
        "\u062a\u064e\u0644\u06af\u0650\u0647\u06cc \u0628\u0627\u0644\u0627"
    ],
    "name:fas_x_variant":[
        "Talgeh\u012b B\u0101l\u0101"
    ],
    "wof:name":"Talgehi Bala",
    "wof:placetype":"locality"
},
  "geometry": {"coordinates":[51.36444,30.7275],"type":"Point"}
}