{
  "type": "Feature",
  "properties": {
    "gn:admin1_code":"13",
    "gn:asciiname":"Ashrafabad",
    "gn:country_code":"IR",
    "gn:dem":1503,
    "gn:feature_class":"P",
    "gn:feature_code":"PPL",
    "gn:name":"Ashraf\u0101b\u0101d",
    "gn:population":0,
    "gn:timezone":"Asia/Tehran",
    "iso:country":"IR",
    "name:fas_x_preferred":[
        "Ashraf\u0101b\u0101d"
    ],
    "name:fas_x_variant":[
        "\u0627\u0634\u0631\u0641\u200c\u0622\u0628\u0627\u062f"
    ],
    "wof:name":"Ashrafabad",
    "wof:placetype":"locality"
},
  "geometry": {"coordinates":[47.36417,34.37417],"type":"Point"}
}