{
  "type": "Feature",
  "properties": {
    "gn:admin1_code":"16",
    "gn:asciiname":"Mavian",
    "gn:country_code":"IR",
    "gn:dem":1497,
    "gn:feature_class":"P",
    "gn:feature_code":"PPL",
    "gn:name":"M\u0101v\u012b\u0101n",
    "gn:population":0,
    "gn:timezone":"Asia/Tehran",
    "iso:country":"IR",
    "name:fas_x_preferred":[
        "\u0645\u0627\u0648\u06cc\u0627\u0646"
    ],
    "name:fas_x_variant":[
        "M\u0101v\u012b\u0101n"
    ],
    "name:und_x_variant":[
        "M\u0101vey\u0101n"
    ],
    "wof:name":"Mavian",
    "wof:placetype":"locality"
},
  "geometry": {"coordinates":[46.8371,34.8488],"type":"Point"}
}