{
  "type": "Feature",
  "properties": {
    "gn:admin1_code":"13",
    "gn:asciiname":"Daryacheh",
    "gn:country_code":"IR",
    "gn:dem":1335,
    "gn:feature_class":"P",
    "gn:feature_code":"PPL",
    "gn:name":"Dary\u0101cheh",
    "gn:population":0,
    "gn:timezone":"Asia/Tehran",
    "iso:country":"IR",
    "name:fas_x_preferred":[
        "\u062f\u0631\u06cc\u0627\u0686\u0647"
    ],
    "name:fas_x_variant":[
        "Dary\u0101cheh"
    ],
    "wof:name":"Daryacheh",
    "wof:placetype":"locality"
},
  "geometry": {"coordinates":[47.3971,34.4729],"type":"Point"}
}