{
  "type": "Feature",
  "properties": {
    "gn:admin1_code":"32.0",
    "gn:asciiname":"Pichak-e Sofla",
    "gn:country_code":"IR",
    "gn:dem":1497,
    "gn:feature_class":"P",
    "gn:feature_code":"PPL",
    "gn:name":"P\u012bchak-e Sofl\u00e1",
    "gn:population":0,
    "gn:timezone":"Asia/Tehran",
    "iso:country":"IR",
    "name:fas_x_preferred":[
        "\u067e\u06cc\u0686\u06a9 \u0633\u0641\u0644\u06cc"
    ],
    "name:fas_x_variant":[
        "\u062f\u0627\u063a \u06a9\u0646\u062f\u06cc \u0633\u0641\u0644\u06cc"
    ],
    "name:und_x_variant":[
        "P\u012bchak-e Sofl\u00e1",
        "D\u0101gh Kand\u012b-ye Sofl\u00e1"
    ],
    "wof:name":"Pichak-e Sofla",
    "wof:placetype":"locality"
},
  "geometry": {"coordinates":[47.38457,38.33948],"type":"Point"}
}