{
  "type": "Feature",
  "properties": {
    "gn:admin1_code":"9",
    "gn:asciiname":"Zamanabad",
    "gn:country_code":"IR",
    "gn:dem":2008,
    "gn:feature_class":"P",
    "gn:feature_code":"PPL",
    "gn:name":"Zam\u0101n\u0101b\u0101d",
    "gn:population":0,
    "gn:timezone":"Asia/Tehran",
    "iso:country":"IR",
    "name:fas_x_preferred":[
        "Zam\u0101n\u0101b\u0101d"
    ],
    "name:fas_x_variant":[
        "\u0632\u0645\u0627\u0646 \u0622\u0628\u0627\u062f"
    ],
    "name:und_x_variant":[
        "Zam\u0101n\u0101b\u0101d-e Em\u0101m Qol\u012bkh\u0101n",
        "\u0632\u0645\u0627\u0646 \u0622\u0628\u0627\u062f"
    ],
    "wof:name":"Zamanabad",
    "wof:placetype":"locality"
},
  "geometry": {"coordinates":[48.73531,34.59584],"type":"Point"}
}