{
  "type": "Feature",
  "properties": {
    "gn:admin1_code":"15",
    "gn:asciiname":"Takht-e Sar Ab",
    "gn:country_code":"IR",
    "gn:dem":1201,
    "gn:feature_class":"P",
    "gn:feature_code":"PPLL",
    "gn:name":"Takht-e Sar \u0100b",
    "gn:population":0,
    "gn:timezone":"Asia/Tehran",
    "iso:country":"IR",
    "name:fas_x_preferred":[
        "Takht-e Sar \u0100b"
    ],
    "name:fas_x_variant":[
        "\u062a\u062e\u062a \u0633\u0631 \u0622\u0628"
    ],
    "name:und_x_variant":[
        "\u062a\u062e\u062a \u0633\u0631 \u0622\u0628"
    ],
    "wof:name":"Takht-e Sar Ab",
    "wof:placetype":"locality"
},
  "geometry": {"coordinates":[49.75951,32.06726],"type":"Point"}
}