{
  "type": "Feature",
  "properties": {
    "gn:admin1_code":"7",
    "gn:asciiname":"Amir Salari",
    "gn:country_code":"IR",
    "gn:dem":1452,
    "gn:feature_class":"P",
    "gn:feature_code":"PPL",
    "gn:name":"Am\u012br S\u0101l\u0101r\u012b",
    "gn:population":0,
    "gn:timezone":"Asia/Tehran",
    "iso:country":"IR",
    "name:fas_x_preferred":[
        "\u0627\u0645\u06cc\u0631 \u0633\u0627\u0644\u0627\u0631\u06cc"
    ],
    "name:fas_x_variant":[
        "Am\u012br S\u0101l\u0101r\u012b",
        "\u0627\u0645\u06cc\u0631\u0633\u0627\u0644\u0627\u0631\u06cc"
    ],
    "name:msa_x_preferred":[
        "Amir Salari"
    ],
    "wof:name":"Amir Salari",
    "wof:placetype":"locality"
},
  "geometry": {"coordinates":[53.0739,28.8885],"type":"Point"}
}