{
  "type": "Feature",
  "properties": {
    "gn:admin1_code":"44.0",
    "gn:asciiname":"Varian",
    "gn:country_code":"IR",
    "gn:dem":1909,
    "gn:feature_class":"P",
    "gn:feature_code":"PPL",
    "gn:name":"V\u0101r\u012b\u0101n",
    "gn:population":0,
    "gn:timezone":"Asia/Tehran",
    "iso:country":"IR",
    "name:deu_x_preferred":[
        "Varian"
    ],
    "name:fas_x_preferred":[
        "\u0648\u0627\u0631\u06cc\u0627\u0646"
    ],
    "name:fra_x_preferred":[
        "Varian"
    ],
    "name:und_x_variant":[
        "V\u0101r\u012b\u0101n"
    ],
    "wof:name":"Varian",
    "wof:placetype":"locality"
},
  "geometry": {"coordinates":[51.23003,36.03177],"type":"Point"}
}