{
  "type": "Feature",
  "properties": {
    "gn:admin1_code":"1",
    "gn:asciiname":"Bi Bakran",
    "gn:country_code":"IR",
    "gn:dem":1458,
    "gn:feature_class":"P",
    "gn:feature_code":"PPL",
    "gn:name":"B\u012b Bakr\u0101n",
    "gn:population":0,
    "gn:timezone":"Asia/Tehran",
    "iso:country":"IR",
    "name:ara_x_preferred":[
        "\u0628\u064a\u0628\u0643\u0631\u0627\u0646"
    ],
    "name:azb_x_preferred":[
        "\u0628\u06cc \u0628\u06a9\u0631\u0627\u0646"
    ],
    "name:aze_x_preferred":[
        "Bibakran"
    ],
    "name:ceb_x_preferred":[
        "B\u012b Bakr\u0101n"
    ],
    "name:ckb_x_preferred":[
        "\u0628\u06cc\u0628\u06d5\u06a9\u0631\u0627\u0646"
    ],
    "name:fas_x_preferred":[
        "\u0628\u064a\u0628\u064e\u0643\u0631\u0627\u0646"
    ],
    "name:fas_x_variant":[
        "\u0628\u0648\u0646\u0643\u064e\u0631\u0627\u0646",
        "B\u012b Bakr\u0101n",
        "\u0628\u06cc \u0628\u06a9\u0631\u0627\u0646",
        "B\u012bbakr\u0101n",
        "\u0628\u06cc\u200c\u0628\u06a9\u0631\u0627\u0646"
    ],
    "name:kur_x_preferred":[
        "B\u00eebekran"
    ],
    "name:msa_x_preferred":[
        "Bi Bakran"
    ],
    "name:swe_x_preferred":[
        "B\u012b Bakr\u0101n"
    ],
    "name:und_x_variant":[
        "B\u016bnkar\u0101n",
        "Bibikeran",
        "B\u016bbakr\u0101n"
    ],
    "wof:name":"Bi Bakran",
    "wof:placetype":"locality"
},
  "geometry": {"coordinates":[44.9325,37.3018],"type":"Point"}
}