{
  "type": "Feature",
  "properties": {
    "gn:admin1_code":"29.0",
    "gn:asciiname":"Gugu'iyeh",
    "gn:country_code":"IR",
    "gn:dem":561,
    "gn:feature_class":"P",
    "gn:feature_code":"PPL",
    "gn:name":"G\u016bg\u016b\u2019\u012byeh",
    "gn:population":0,
    "gn:timezone":"Asia/Tehran",
    "iso:country":"IR",
    "name:ara_x_preferred":[
        "\u0643\u0648\u063a\u0648\u0626\u064a\u0629"
    ],
    "name:fas_x_preferred":[
        "\u06af\u0648\u06af\u0648\u0626\u06cc\u0647"
    ],
    "name:fas_x_variant":[
        "K\u016bg\u016b\u2019\u012byeh",
        "G\u016bg\u016b\u2019\u012byeh",
        "\u06a9\u0648\u06af\u0648\u0626\u06cc\u0647"
    ],
    "name:und_x_variant":[
        "K\u016bg\u016b"
    ],
    "wof:name":"Gugu'iyeh",
    "wof:placetype":"locality"
},
  "geometry": {"coordinates":[57.7115,28.3485],"type":"Point"}
}