{
  "type": "Feature",
  "properties": {
    "gn:admin1_code":"33",
    "gn:asciiname":"Sanduqlu",
    "gn:country_code":"IR",
    "gn:dem":2313,
    "gn:feature_class":"P",
    "gn:feature_code":"PPL",
    "gn:name":"\u015eand\u016bql\u016b",
    "gn:population":0,
    "gn:timezone":"Asia/Tehran",
    "iso:country":"IR",
    "name:azb_x_preferred":[
        "\u0635\u0646\u062f\u0648\u0642\u0644\u0648"
    ],
    "name:aze_x_preferred":[
        "Sand\u0131ql\u0131"
    ],
    "name:fas_x_preferred":[
        "\u0635\u0646\u062f\u0648\u0642\u0644\u0648"
    ],
    "name:fas_x_variant":[
        "\u015eand\u016bql\u016b"
    ],
    "name:msa_x_preferred":[
        "Sanduqlu"
    ],
    "wof:name":"Sanduqlu",
    "wof:placetype":"locality"
},
  "geometry": {"coordinates":[47.8331,38.1178],"type":"Point"}
}