{
  "type": "Feature",
  "properties": {
    "gn:admin1_code":"15",
    "gn:asciiname":"`Eyn Korreh",
    "gn:country_code":"IR",
    "gn:dem":111,
    "gn:feature_class":"P",
    "gn:feature_code":"PPL",
    "gn:name":"\u2018Eyn Korreh",
    "gn:population":0,
    "gn:timezone":"Asia/Tehran",
    "iso:country":"IR",
    "name:fas_x_preferred":[
        "Cheshmeh Bad\u012br"
    ],
    "name:fas_x_variant":[
        "\u0686\u0634\u0645\u0647 \u0628\u062f\u0631",
        "\u0639\u06cc\u0646 \u06a9\u0631\u0647",
        "\u0686\u0634\u0645\u0647 \u0628\u062f\u06cc\u0631"
    ],
    "name:und_x_variant":[
        "Cheshmeh Bedar",
        "\u0686\u0634\u0645\u0647 \u0628\u062f\u0631",
        "\u2018Eyn Korreh"
    ],
    "wof:name":"`Eyn Korreh",
    "wof:placetype":"locality"
},
  "geometry": {"coordinates":[49.56707,31.13762],"type":"Point"}
}