{
  "type": "Feature",
  "properties": {
    "gn:admin1_code":"15.0",
    "gn:asciiname":"Chalak-e Bala",
    "gn:country_code":"IR",
    "gn:dem":445,
    "gn:feature_class":"P",
    "gn:feature_code":"PPL",
    "gn:name":"Chalak-e B\u0101l\u0101",
    "gn:population":0,
    "gn:timezone":"Asia/Tehran",
    "iso:country":"IR",
    "name:fas_x_preferred":[
        "Chalak-e B\u0101l\u0101"
    ],
    "wof:name":"Chalak-e Bala",
    "wof:placetype":"locality"
},
  "geometry": {"coordinates":[48.51667,32.78333],"type":"Point"}
}