{
  "type": "Feature",
  "properties": {
    "gn:admin1_code":"32",
    "gn:asciiname":"Kavich",
    "gn:country_code":"IR",
    "gn:dem":1258,
    "gn:feature_class":"P",
    "gn:feature_code":"PPL",
    "gn:name":"Kav\u012bch",
    "gn:population":0,
    "gn:timezone":"Asia/Tehran",
    "iso:country":"IR",
    "name:fas_x_preferred":[
        "\u0643\u0648\u064a\u0686"
    ],
    "name:fas_x_variant":[
        "Kav\u012bch"
    ],
    "name:und_x_variant":[
        "G\u016b\u2019\u012bj"
    ],
    "wof:name":"Kavich",
    "wof:placetype":"locality"
},
  "geometry": {"coordinates":[47.8869,38.4947],"type":"Point"}
}