{
  "type": "Feature",
  "properties": {
    "gn:admin1_code":"15.0",
    "gn:asciiname":"Kham Karabad",
    "gn:country_code":"IR",
    "gn:dem":762,
    "gn:feature_class":"P",
    "gn:feature_code":"PPL",
    "gn:name":"Kham K\u0101r\u0101b\u0101d",
    "gn:population":0,
    "gn:timezone":"Asia/Tehran",
    "iso:country":"IR",
    "name:fas_x_preferred":[
        "A\u1e29mad\u0101b\u0101d"
    ],
    "name:fas_x_variant":[
        "\u0627\u062d\u0645\u062f \u0622\u0628\u0627\u062f",
        "\u062e\u0645 \u06a9\u0627\u0631 \u0622\u0628\u0627\u062f",
        "\u062e\u0645\u06a9\u0627\u0631"
    ],
    "name:und_x_variant":[
        "\u0627\u062d\u0645\u062f \u0622\u0628\u0627\u062f",
        "Kham K\u0101r\u0101b\u0101d",
        "Khamk\u0101r"
    ],
    "wof:name":"Kham Karabad",
    "wof:placetype":"locality"
},
  "geometry": {"coordinates":[49.51844000000001,32.20362],"type":"Point"}
}