{
  "type": "Feature",
  "properties": {
    "gn:admin1_code":"4.0",
    "gn:asciiname":"Deh-e Mir Khan",
    "gn:country_code":"IR",
    "gn:dem":489,
    "gn:feature_class":"P",
    "gn:feature_code":"PPL",
    "gn:name":"Deh-e M\u012br Kh\u0101n",
    "gn:population":0,
    "gn:timezone":"Asia/Tehran",
    "iso:country":"IR",
    "name:fas_x_preferred":[
        "\u062f\u0647 \u0645\u06cc\u0631 \u062e\u0627\u0646"
    ],
    "name:fas_x_variant":[
        "\u1e28\u0101jj\u012b M\u012brkh\u0101n",
        "Deh-e M\u012br Kh\u0101n",
        "\u0645\u06cc\u0631 \u062e\u0627\u0646 \u062c\u0647\u0627\u0646\u062a\u06cc\u062e"
    ],
    "name:und_x_variant":[
        "M\u012br Kh\u0101n Jah\u0101nt\u012bkh"
    ],
    "wof:name":"Deh-e Mir Khan",
    "wof:placetype":"locality"
},
  "geometry": {"coordinates":[61.6676,30.9609],"type":"Point"}
}