{
  "type": "Feature",
  "properties": {
    "gn:admin1_code":"5.0",
    "gn:asciiname":"Sarfayab-e Markazi",
    "gn:country_code":"IR",
    "gn:dem":1217,
    "gn:feature_class":"P",
    "gn:feature_code":"PPL",
    "gn:name":"Sarf\u0101y\u0101b-e Markaz\u012b",
    "gn:population":0,
    "gn:timezone":"Asia/Tehran",
    "iso:country":"IR",
    "name:fas_x_preferred":[
        "Sarf\u0101y\u0101b-e Markaz\u012b"
    ],
    "name:fas_x_variant":[
        "\u0633\u0631\u0641\u0627\u06cc\u0627\u0628 \u0645\u0631\u06a9\u0632\u06cc"
    ],
    "wof:name":"Sarfayab-e Markazi",
    "wof:placetype":"locality"
},
  "geometry": {"coordinates":[50.85237,30.80417000000001],"type":"Point"}
}