{
  "type": "Feature",
  "properties": {
    "gn:admin1_code":"15",
    "gn:asciiname":"Garmeh",
    "gn:country_code":"IR",
    "gn:dem":6,
    "gn:feature_class":"P",
    "gn:feature_code":"PPL",
    "gn:name":"Garmeh",
    "gn:population":0,
    "gn:timezone":"Asia/Tehran",
    "iso:country":"IR",
    "name:ara_x_preferred":[
        "\u063a\u0631\u0645\u0629"
    ],
    "name:fas_x_preferred":[
        "\u06af\u0631\u0645\u0647"
    ],
    "name:und_x_variant":[
        "Garm\u0101",
        "Garmeh",
        "\u06af\u0631\u0645\u0647"
    ],
    "wof:name":"Garmeh",
    "wof:placetype":"locality"
},
  "geometry": {"coordinates":[48.64205,30.78718],"type":"Point"}
}