{
  "type": "Feature",
  "properties": {
    "gn:admin1_code":"9",
    "gn:asciiname":"Tarkhinabad",
    "gn:country_code":"IR",
    "gn:dem":1703,
    "gn:feature_class":"P",
    "gn:feature_code":"PPL",
    "gn:name":"Tarkh\u012bn\u0101b\u0101d",
    "gn:population":0,
    "gn:timezone":"Asia/Tehran",
    "iso:country":"IR",
    "name:ara_x_preferred":[
        "\u062a\u0631\u062e\u064a\u0646 \u0623\u0628\u0627\u062f"
    ],
    "name:ceb_x_preferred":[
        "Tarf\u012bn\u0101b\u0101d"
    ],
    "name:fas_x_preferred":[
        "\u062a\u064e\u0631\u062e\u064a\u0646 \u0622\u0628\u0627\u062f"
    ],
    "name:fas_x_variant":[
        "Tarf\u012bn\u0101b\u0101d",
        "Tarkh\u012bn\u0101b\u0101d",
        "\u062a\u0631\u0641\u06cc\u0646 \u0622\u0628\u0627\u062f",
        "\u062a\u0631\u062e\u06cc\u0646 \u0622\u0628\u0627\u062f",
        "\u062a\u0631\u062e\u06cc\u0646\u200c\u0622\u0628\u0627\u062f"
    ],
    "name:msa_x_preferred":[
        "Tarkhinabad"
    ],
    "name:swe_x_preferred":[
        "Tarf\u012bn\u0101b\u0101d"
    ],
    "name:und_x_variant":[
        "Tarkhis\u0101bad",
        "\u062a\u0631\u0641\u06cc\u0646 \u0622\u0628\u0627\u062f"
    ],
    "wof:name":"Tarkhinabad",
    "wof:placetype":"locality"
},
  "geometry": {"coordinates":[48.12241,34.81545999999999],"type":"Point"}
}