{
  "type": "Feature",
  "properties": {
    "gn:admin1_code":"16",
    "gn:asciiname":"Qeru Chay",
    "gn:country_code":"IR",
    "gn:dem":1846,
    "gn:feature_class":"P",
    "gn:feature_code":"PPL",
    "gn:name":"Qer\u016b Ch\u0101y",
    "gn:population":0,
    "gn:timezone":"Asia/Tehran",
    "iso:country":"IR",
    "name:fas_x_preferred":[
        "\u0642\u0648\u0631\u06cc \u0686\u0627\u06cc"
    ],
    "name:fas_x_variant":[
        "\u0642\u0631\u0648 \u0686\u0627\u06cc",
        "Q\u016br\u012b Ch\u0101y",
        "Qer\u016b Ch\u0101y"
    ],
    "name:und_x_variant":[
        "Karreh Ch\u012byeh",
        "Q\u016br\u012bch\u0101\u2019\u012b",
        "Kurreh Ch\u012ba",
        "Q\u016br\u012b Ch\u0101\u2019\u012b"
    ],
    "wof:name":"Qeru Chay",
    "wof:placetype":"locality"
},
  "geometry": {"coordinates":[47.29988,35.37262],"type":"Point"}
}