{
  "type": "Feature",
  "properties": {
    "gn:admin1_code":"29",
    "gn:asciiname":"Pa-ye Ab",
    "gn:cc2":"IR",
    "gn:country_code":"IR",
    "gn:dem":1835,
    "gn:feature_class":"P",
    "gn:feature_code":"PPL",
    "gn:name":"P\u0101-ye \u0100b",
    "gn:population":0,
    "gn:timezone":"Asia/Tehran",
    "iso:country":"IR",
    "name:fas_x_preferred":[
        "\u067e\u0627\u06cc \u0622\u0628"
    ],
    "name:fas_x_variant":[
        "P\u0101-ye \u0100b"
    ],
    "name:und_x_variant":[
        "Pai\u0101b",
        "Pa yi \u0100b"
    ],
    "wof:name":"Pa-ye Ab",
    "wof:placetype":"locality"
},
  "geometry": {"coordinates":[57.23333,30.18333],"type":"Point"}
}