{
  "type": "Feature",
  "properties": {
    "gn:admin1_code":"33",
    "gn:asciiname":"Dibaklu",
    "gn:country_code":"IR",
    "gn:dem":2123,
    "gn:feature_class":"P",
    "gn:feature_code":"PPL",
    "gn:name":"D\u012bbakl\u016b",
    "gn:population":0,
    "gn:timezone":"Asia/Tehran",
    "iso:country":"IR",
    "name:fas_x_preferred":[
        "\u062f\u064a\u0628\u0643\u0644\u0648"
    ],
    "name:fas_x_variant":[
        "D\u012bbakl\u016b"
    ],
    "wof:name":"Dibaklu",
    "wof:placetype":"locality"
},
  "geometry": {"coordinates":[47.7926,38.048],"type":"Point"}
}