{
  "type": "Feature",
  "properties": {
    "gn:admin1_code":"41",
    "gn:asciiname":"Ratuk-e `Olya",
    "gn:country_code":"IR",
    "gn:dem":1518,
    "gn:feature_class":"P",
    "gn:feature_code":"PPL",
    "gn:name":"R\u0101t\u016bk-e \u2018Oly\u0101",
    "gn:population":0,
    "gn:timezone":"Asia/Tehran",
    "iso:country":"IR",
    "name:fas_x_preferred":[
        "\u0631\u0627\u062a\u0648\u06a9 \u0639\u0644\u064a\u0627"
    ],
    "name:fas_x_variant":[
        "R\u0101t\u016bk-e \u2018Oly\u0101"
    ],
    "wof:name":"Ratuk-e `Olya",
    "wof:placetype":"locality"
},
  "geometry": {"coordinates":[60.24394,32.61417],"type":"Point"}
}