{
  "type": "Feature",
  "properties": {
    "gn:admin1_code":"8",
    "gn:asciiname":"Bala Rudposht",
    "gn:country_code":"IR",
    "gn:dem":-8,
    "gn:feature_class":"P",
    "gn:feature_code":"PPL",
    "gn:name":"B\u0101l\u0101 R\u016bdposht",
    "gn:population":0,
    "gn:timezone":"Asia/Tehran",
    "iso:country":"IR",
    "name:fas_x_preferred":[
        "B\u0101l\u0101 R\u016bdposht"
    ],
    "name:fas_x_variant":[
        "\u0628\u0627\u0644\u0627 \u0631\u0648\u062f \u067e\u0634\u062a",
        "\u0628\u0627\u0644\u0627\u0631\u0648\u062f\u067e\u0634\u062a"
    ],
    "name:msa_x_preferred":[
        "Bala Rudposht"
    ],
    "name:ukr_x_preferred":[
        "\u0411\u0430\u043b\u0430-\u0420\u0443\u0434\u043f\u043e\u0448\u0442"
    ],
    "wof:name":"Bala Rudposht",
    "wof:placetype":"locality"
},
  "geometry": {"coordinates":[50.10451,37.277],"type":"Point"}
}