{
  "type": "Feature",
  "properties": {
    "gn:admin1_code":"10.0",
    "gn:asciiname":"Birast",
    "gn:country_code":"IR",
    "gn:dem":1351,
    "gn:feature_class":"P",
    "gn:feature_code":"PPL",
    "gn:name":"B\u012br\u0101st",
    "gn:population":0,
    "gn:timezone":"Asia/Tehran",
    "iso:country":"IR",
    "name:fas_x_preferred":[
        "\u0628\u06cc\u0631\u0627\u0633\u062a"
    ],
    "name:fas_x_variant":[
        "B\u012br\u0101st"
    ],
    "wof:name":"Birast",
    "wof:placetype":"locality"
},
  "geometry": {"coordinates":[46.0871,34.0111],"type":"Point"}
}