{
  "type": "Feature",
  "properties": {
    "gn:admin1_code":"35",
    "gn:asciiname":"Talar Sarband",
    "gn:country_code":"IR",
    "gn:dem":1613,
    "gn:feature_class":"P",
    "gn:feature_code":"PPL",
    "gn:name":"Tal\u0101r Sarband",
    "gn:population":0,
    "gn:timezone":"Asia/Tehran",
    "iso:country":"IR",
    "name:fas_x_preferred":[
        "\u062a\u0644\u0627\u0631 \u0633\u0631\u0628\u0646\u062f"
    ],
    "name:fas_x_variant":[
        "Tal\u0101r Sarband"
    ],
    "wof:name":"Talar Sarband",
    "wof:placetype":"locality"
},
  "geometry": {"coordinates":[53.22407,36.02804000000001],"type":"Point"}
}