{
  "type": "Feature",
  "properties": {
    "gn:admin1_code":"42.0",
    "gn:asciiname":"Giami",
    "gn:country_code":"IR",
    "gn:dem":1239,
    "gn:feature_class":"P",
    "gn:feature_code":"PPL",
    "gn:name":"G\u012b\u0101m\u012b",
    "gn:population":0,
    "gn:timezone":"Asia/Tehran",
    "iso:country":"IR",
    "name:fas_x_preferred":[
        "\u06af\u06cc\u0627\u0645\u06cc"
    ],
    "name:fas_x_variant":[
        "K\u012b\u0101mey",
        "G\u012b\u0101m\u012b",
        "Gey\u0101mey",
        "G\u012by\u0101m\u012b"
    ],
    "name:und_x_variant":[
        "G\u012by\u0101m\u012b",
        "Gey\u0101mey"
    ],
    "wof:name":"Giami",
    "wof:placetype":"locality"
},
  "geometry": {"coordinates":[60.0892,35.85413],"type":"Point"}
}