{
  "type": "Feature",
  "properties": {
    "gn:admin1_code":"29",
    "gn:asciiname":"Rigan",
    "gn:country_code":"IR",
    "gn:dem":639,
    "gn:feature_class":"P",
    "gn:feature_code":"PPL",
    "gn:name":"R\u012bg\u0101n",
    "gn:population":0,
    "gn:timezone":"Asia/Tehran",
    "iso:country":"IR",
    "name:fas_x_preferred":[
        "\u0631\u06cc\u06af\u0627\u0646"
    ],
    "name:fas_x_variant":[
        "R\u012bg\u0101n"
    ],
    "wof:name":"Rigan",
    "wof:placetype":"locality"
},
  "geometry": {"coordinates":[59.01982,28.64937],"type":"Point"}
}