{
  "type": "Feature",
  "properties": {
    "gn:admin1_code":"36",
    "gn:asciiname":"Incheh",
    "gn:country_code":"IR",
    "gn:dem":1807,
    "gn:feature_class":"P",
    "gn:feature_code":"PPL",
    "gn:name":"\u012ancheh",
    "gn:population":0,
    "gn:timezone":"Asia/Tehran",
    "iso:country":"IR",
    "name:fas_x_preferred":[
        "\u0627\u06cc\u0646\u0686\u0647"
    ],
    "name:fas_x_variant":[
        "\u012ancheh-ye Khod\u0101 Bandehl\u016b",
        "\u012ancheh",
        "\u0627\u06cc\u0646\u0686\u0647 \u062e\u062f\u0627\u0628\u0646\u062f\u0647\u200c\u0644\u0648"
    ],
    "name:und_x_variant":[
        "Aincha",
        "\u0627\u06cc\u0646\u0686\u0647 \u062e\u062f\u0627\u0628\u0646\u062f\u0647 \u0644\u0648"
    ],
    "wof:name":"Incheh",
    "wof:placetype":"locality"
},
  "geometry": {"coordinates":[48.64597,36.01672999999999],"type":"Point"}
}