{
  "type": "Feature",
  "properties": {
    "gn:admin1_code":"5.0",
    "gn:asciiname":"Baba Kalan",
    "gn:country_code":"IR",
    "gn:dem":484,
    "gn:feature_class":"P",
    "gn:feature_code":"PPL",
    "gn:name":"B\u0101b\u0101 Kal\u0101n",
    "gn:population":0,
    "gn:timezone":"Asia/Tehran",
    "iso:country":"IR",
    "name:fas_x_preferred":[
        "\u0628\u0627\u0628\u0627 \u0643\u0644\u0627\u0646"
    ],
    "name:fas_x_variant":[
        "\u0628\u0627\u0628\u0627 \u0643\u064e\u0644\u0648",
        "\u0628\u0627\u0628\u0627\u06cc \u0643\u064e\u0644\u0627\u0646",
        "\u0686\u0650\u0634\u0645\u0650\u064a\u06cc \u0628\u0627\u0628\u0627 \u0643\u064e\u0644\u0627\u0646",
        "\u0686\u064e\u0634\u0645\u0650\u06c0 \u0628\u0627\u0628\u0627 \u0643\u0627\u0644\u0627\u0646",
        "\u0628\u0627\u0628\u064e \u0643\u0650\u0644\u0646",
        "\u0686\u0650\u0634\u0645\u0650\u06c0 \u0628\u0627\u0628\u0627 \u0643\u064e\u0644\u0627\u0646",
        "B\u0101b\u0101 Kal\u0101n",
        "\u0628\u0627\u0628\u0627\u06a9\u0644\u0627\u0646"
    ],
    "name:und_x_variant":[
        "Cheshmey-ye B\u0101b\u0101 Kal\u0101n",
        "B\u0101ba Keln",
        "Chashmeh-ye B\u0101b\u0101 K\u0101l\u0101n",
        "B\u0101b\u0101 Kal\u016b",
        "Cheshmeh-ye B\u0101b\u0101 Kal\u0101n",
        "B\u0101b\u0101-ye Kal\u0101n",
        "B\u0101ba Kelu"
    ],
    "wof:name":"Baba Kalan",
    "wof:placetype":"locality"
},
  "geometry": {"coordinates":[50.8199,30.1163],"type":"Point"}
}