{
  "type": "Feature",
  "properties": {
    "gn:admin1_code":"23",
    "gn:asciiname":"Malekabad",
    "gn:country_code":"IR",
    "gn:dem":1603,
    "gn:feature_class":"P",
    "gn:feature_code":"PPL",
    "gn:name":"Malek\u0101b\u0101d",
    "gn:population":0,
    "gn:timezone":"Asia/Tehran",
    "iso:country":"IR",
    "name:fas_x_preferred":[
        "\u0645\u0644\u06a9 \u0622\u0628\u0627\u062f"
    ],
    "name:fas_x_variant":[
        "Malek\u0101b\u0101d"
    ],
    "wof:name":"Malekabad",
    "wof:placetype":"locality"
},
  "geometry": {"coordinates":[48.2271,33.887],"type":"Point"}
}