{
  "type": "Feature",
  "properties": {
    "gn:admin1_code":"3",
    "gn:asciiname":"Qal`eh-ye Madraseh",
    "gn:country_code":"IR",
    "gn:dem":1857,
    "gn:feature_class":"P",
    "gn:feature_code":"PPL",
    "gn:name":"Qal\u2018eh-ye Madraseh",
    "gn:population":0,
    "gn:timezone":"Asia/Tehran",
    "iso:country":"IR",
    "name:fas_x_preferred":[
        "Qal\u2018eh-ye Madraseh"
    ],
    "name:fas_x_variant":[
        "\u0642\u0644\u0639\u0647 \u0645\u062f\u0631\u0633\u0647"
    ],
    "wof:name":"Qal`eh-ye Madraseh",
    "wof:placetype":"locality"
},
  "geometry": {"coordinates":[50.5545,31.48766],"type":"Point"}
}