{
  "type": "Feature",
  "properties": {
    "gn:admin1_code":"1.0",
    "gn:asciiname":"Kazheh",
    "gn:country_code":"IR",
    "gn:dem":1275,
    "gn:feature_class":"P",
    "gn:feature_code":"PPL",
    "gn:name":"K\u0101zheh",
    "gn:population":0,
    "gn:timezone":"Asia/Tehran",
    "iso:country":"IR",
    "name:azb_x_preferred":[
        "\u0643\u0627\u0698\u0647"
    ],
    "name:ceb_x_preferred":[
        "K\u0101zheh"
    ],
    "name:ckb_x_preferred":[
        "\u06a9\u0627\u0698\u06ce"
    ],
    "name:fas_x_preferred":[
        "\u06a9\u0627\u0698\u0647"
    ],
    "name:fas_x_variant":[
        "K\u0101zheh"
    ],
    "name:kur_x_preferred":[
        "Kaje"
    ],
    "name:msa_x_preferred":[
        "Kazheh"
    ],
    "name:swe_x_preferred":[
        "K\u0101zheh"
    ],
    "wof:name":"Kazheh",
    "wof:placetype":"locality"
},
  "geometry": {"coordinates":[45.4634,36.2618],"type":"Point"}
}