{
  "type": "Feature",
  "properties": {
    "gn:admin1_code":"28.0",
    "gn:asciiname":"Shiran",
    "gn:country_code":"IR",
    "gn:dem":2066,
    "gn:feature_class":"P",
    "gn:feature_code":"PPL",
    "gn:name":"Sh\u012br\u0101n",
    "gn:population":0,
    "gn:timezone":"Asia/Tehran",
    "iso:country":"IR",
    "name:fas_x_preferred":[
        "\u0634\u06cc\u0631\u0627\u0646"
    ],
    "name:fas_x_variant":[
        "Sh\u012br\u0101n"
    ],
    "wof:name":"Shiran",
    "wof:placetype":"locality"
},
  "geometry": {"coordinates":[52.7247,32.6982],"type":"Point"}
}