{
  "type": "Feature",
  "properties": {
    "gn:admin1_code":"15",
    "gn:asciiname":"Kabutaran",
    "gn:country_code":"IR",
    "gn:dem":793,
    "gn:feature_class":"P",
    "gn:feature_code":"PPL",
    "gn:name":"Kab\u016btar\u0101n",
    "gn:population":0,
    "gn:timezone":"Asia/Tehran",
    "iso:country":"IR",
    "name:fas_x_preferred":[
        "Kab\u016btar\u012b"
    ],
    "name:fas_x_variant":[
        "\u06a9\u0628\u0648\u062a\u0631\u0627\u0646",
        "\u0633\u0631\u062a\u062e\u062a \u062f\u0648\u0631\u0627\u0647\u0627\u0646",
        "\u0633\u0631\u062a\u062e\u062a"
    ],
    "name:und_x_variant":[
        "Kab\u016btar\u0101n",
        "Sartakht D\u016br\u0101h\u0101n",
        "Sartakht"
    ],
    "wof:name":"Kabutaran",
    "wof:placetype":"locality"
},
  "geometry": {"coordinates":[48.2787,32.88201],"type":"Point"}
}