{
  "type": "Feature",
  "properties": {
    "gn:admin1_code":"9",
    "gn:asciiname":"Hoseynabad-e Shamlu",
    "gn:country_code":"IR",
    "gn:dem":1698,
    "gn:feature_class":"P",
    "gn:feature_code":"PPL",
    "gn:name":"\u1e28oseyn\u0101b\u0101d-e Sh\u0101ml\u016b",
    "gn:population":0,
    "gn:timezone":"Asia/Tehran",
    "iso:country":"IR",
    "name:fas_x_preferred":[
        "\u062d\u064f\u0633\u0650\u064a\u0646 \u0622\u0628\u0627\u062f"
    ],
    "name:fas_x_variant":[
        "\u1e28asan\u0101b\u0101d-e Sh\u0101ml\u016b",
        "\u1e28oseyn\u0101b\u0101d-e Sh\u0101ml\u016b",
        "\u062d\u0633\u0646 \u0622\u0628\u0627\u062f \u0634\u0627\u0645\u0644\u0648",
        "\u062d\u0633\u06cc\u0646 \u0622\u0628\u0627\u062f \u0634\u0627\u0645\u0644\u0648",
        "\u062d\u0633\u06cc\u0646\u200c\u0622\u0628\u0627\u062f \u0634\u0627\u0645\u0644\u0648"
    ],
    "name:msa_x_preferred":[
        "Hoseynabad-e Shamlu"
    ],
    "name:und_x_variant":[
        "\u1e28oseyn\u0101b\u0101d",
        "H\u016bsa\u012bn\u0101b\u0101d"
    ],
    "wof:name":"Hoseynabad-e Shamlu",
    "wof:placetype":"locality"
},
  "geometry": {"coordinates":[48.62038,34.44595],"type":"Point"}
}