{
  "type": "Feature",
  "properties": {
    "gn:admin1_code":"10",
    "gn:asciiname":"Kaleh Qatar-e Sofla",
    "gn:country_code":"IR",
    "gn:dem":826,
    "gn:feature_class":"P",
    "gn:feature_code":"PPL",
    "gn:name":"Kaleh Qa\u0163\u0101r-e Sofl\u00e1",
    "gn:population":0,
    "gn:timezone":"Asia/Tehran",
    "iso:country":"IR",
    "name:fas_x_preferred":[
        "\u06a9\u0644\u0647 \u0642\u0637\u0627\u0631 \u0633\u0641\u0644\u06cc"
    ],
    "name:fas_x_variant":[
        "Kal-e Qa\u0163\u0101r-e Sofl\u00e1",
        "Kaleh Qa\u0163\u0101r-e Sofl\u00e1"
    ],
    "name:und_x_variant":[
        "Kaleh Qa\u0163\u0101r"
    ],
    "wof:name":"Kaleh Qatar-e Sofla",
    "wof:placetype":"locality"
},
  "geometry": {"coordinates":[46.7471,33.666],"type":"Point"}
}