{
  "type": "Feature",
  "properties": {
    "gn:admin1_code":"13.0",
    "gn:asciiname":"Somakhestan",
    "gn:country_code":"IR",
    "gn:dem":1817,
    "gn:feature_class":"P",
    "gn:feature_code":"PPL",
    "gn:name":"Som\u0101khest\u0101n",
    "gn:population":0,
    "gn:timezone":"Asia/Tehran",
    "iso:country":"IR",
    "name:fas_x_preferred":[
        "Som\u0101qest\u0101n-e \u2018Oly\u0101"
    ],
    "name:fas_x_variant":[
        "\u0633\u0645\u0627\u062e\u0633\u062a\u0627\u0646",
        "\u0633\u0645\u0627\u0642\u0633\u062a\u0627\u0646",
        "\u0633\u0645\u0627\u0642\u0633\u062a\u0627\u0646 \u0639\u0644\u06cc\u0627"
    ],
    "name:und_x_variant":[
        "Som\u0101khest\u0101n",
        "Som\u0101qest\u0101n"
    ],
    "wof:name":"Somakhestan",
    "wof:placetype":"locality"
},
  "geometry": {"coordinates":[47.58541,34.60686],"type":"Point"}
}