{
  "type": "Feature",
  "properties": {
    "gn:admin1_code":"5",
    "gn:asciiname":"Kapar Torab",
    "gn:country_code":"IR",
    "gn:dem":828,
    "gn:feature_class":"P",
    "gn:feature_code":"PPL",
    "gn:name":"Kapar Tor\u0101b",
    "gn:population":0,
    "gn:timezone":"Asia/Tehran",
    "iso:country":"IR",
    "name:fas_x_preferred":[
        "Kapar Tor\u0101b"
    ],
    "wof:name":"Kapar Torab",
    "wof:placetype":"locality"
},
  "geometry": {"coordinates":[50.46667,30.95],"type":"Point"}
}