{
  "type": "Feature",
  "properties": {
    "gn:admin1_code":"16",
    "gn:asciiname":"Diraklu",
    "gn:country_code":"IR",
    "gn:dem":1972,
    "gn:feature_class":"P",
    "gn:feature_code":"PPL",
    "gn:name":"D\u012brakl\u016b",
    "gn:population":0,
    "gn:timezone":"Asia/Tehran",
    "iso:country":"IR",
    "name:ceb_x_preferred":[
        "D\u012brakl\u016b"
    ],
    "name:fas_x_preferred":[
        "D\u012brakl\u016b"
    ],
    "name:fas_x_variant":[
        "\u062f\u06cc\u0631\u06a9\u0644\u0648"
    ],
    "name:swe_x_preferred":[
        "D\u012brakl\u016b"
    ],
    "name:und_x_variant":[
        "Thirk \u2018Ali",
        "Tork \u2018Al\u012b"
    ],
    "wof:name":"Diraklu",
    "wof:placetype":"locality"
},
  "geometry": {"coordinates":[47.91048,35.39796],"type":"Point"}
}