{
  "type": "Feature",
  "properties": {
    "gn:admin1_code":"28",
    "gn:asciiname":"Akbarabad-e Lashaneh",
    "gn:country_code":"IR",
    "gn:dem":2222,
    "gn:feature_class":"P",
    "gn:feature_code":"PPL",
    "gn:name":"Akbar\u0101b\u0101d-e L\u0101sh\u0101neh",
    "gn:population":0,
    "gn:timezone":"Asia/Tehran",
    "iso:country":"IR",
    "name:fas_x_preferred":[
        "\u0627\u06a9\u0628\u0631 \u0622\u0628\u0627\u062f \u0644\u0627\u0634\u0627\u0646\u0647"
    ],
    "name:fas_x_variant":[
        "Akbar\u0101b\u0101d-e L\u0101sh\u0101neh"
    ],
    "wof:name":"Akbarabad-e Lashaneh",
    "wof:placetype":"locality"
},
  "geometry": {"coordinates":[52.5936,33.1875],"type":"Point"}
}