{
  "type": "Feature",
  "properties": {
    "gn:admin1_code":"15.0",
    "gn:asciiname":"Din Rak",
    "gn:country_code":"IR",
    "gn:dem":776,
    "gn:feature_class":"P",
    "gn:feature_code":"PPL",
    "gn:name":"D\u012bn R\u0101k",
    "gn:population":0,
    "gn:timezone":"Asia/Tehran",
    "iso:country":"IR",
    "name:fas_x_preferred":[
        "D\u012bn R\u0101k"
    ],
    "name:fas_x_variant":[
        "Boneh-ye R\u0101k",
        "\u062f\u06cc\u0646 \u0631\u0627\u0643",
        "\u0628\u0646\u0647 \u0631\u0627\u0643"
    ],
    "name:und_x_variant":[
        "\u062f\u06cc\u0646 \u0631\u0627\u0643",
        "\u0628\u0646\u0647 \u0631\u0627\u0643"
    ],
    "wof:name":"Din Rak",
    "wof:placetype":"locality"
},
  "geometry": {"coordinates":[49.50857,32.21158],"type":"Point"}
}