{
  "type": "Feature",
  "properties": {
    "gn:admin1_code":"23",
    "gn:asciiname":"Khalaj-e `Olya",
    "gn:country_code":"IR",
    "gn:dem":2066,
    "gn:feature_class":"P",
    "gn:feature_code":"PPL",
    "gn:name":"Khalaj-e \u2018Oly\u0101",
    "gn:population":0,
    "gn:timezone":"Asia/Tehran",
    "iso:country":"IR",
    "name:fas_x_preferred":[
        "\u062e\u0644\u062c \u0628\u0627\u0644\u0627"
    ],
    "name:fas_x_variant":[
        "Khalaj-e \u2018Oly\u0101",
        "Khalaj-e B\u0101l\u0101",
        "\u062e\u0644\u062c \u0639\u0644\u06cc\u0627"
    ],
    "wof:name":"Khalaj-e `Olya",
    "wof:placetype":"locality"
},
  "geometry": {"coordinates":[49.36105,33.69539],"type":"Point"}
}