{
  "type": "Feature",
  "properties": {
    "gn:admin1_code":"5",
    "gn:asciiname":"Dam Chenar-e Maskur",
    "gn:country_code":"IR",
    "gn:dem":2245,
    "gn:feature_class":"P",
    "gn:feature_code":"PPL",
    "gn:name":"Dam Chen\u0101r-e Mask\u016br",
    "gn:population":0,
    "gn:timezone":"Asia/Tehran",
    "iso:country":"IR",
    "name:fas_x_preferred":[
        "\u062f\u064e\u0645 \u0686\u0650\u0646\u0627\u0631\u0650 \u0645\u064e\u0633\u0643\u0648\u0631"
    ],
    "name:fas_x_variant":[
        "Dam Chen\u0101r-e Mask\u016br"
    ],
    "wof:name":"Dam Chenar-e Maskur",
    "wof:placetype":"locality"
},
  "geometry": {"coordinates":[51.16667,30.88333],"type":"Point"}
}