{
  "type": "Feature",
  "properties": {
    "gn:admin1_code":"37.0",
    "gn:asciiname":"Bolanjeq",
    "gn:country_code":"IR",
    "gn:dem":283,
    "gn:feature_class":"P",
    "gn:feature_code":"PPL",
    "gn:name":"Bol\u0101njeq",
    "gn:population":0,
    "gn:timezone":"Asia/Tehran",
    "iso:country":"IR",
    "name:fas_x_preferred":[
        "\u0628\u064f\u0644\u0627\u0646\u062c\u0650\u0642"
    ],
    "name:fas_x_variant":[
        "Bol\u0101njeq"
    ],
    "wof:name":"Bolanjeq",
    "wof:placetype":"locality"
},
  "geometry": {"coordinates":[55.55,37.41667],"type":"Point"}
}