{
  "type": "Feature",
  "properties": {
    "gn:admin1_code":"42",
    "gn:asciiname":"Sar Chah",
    "gn:country_code":"IR",
    "gn:dem":1624,
    "gn:feature_class":"P",
    "gn:feature_code":"PPL",
    "gn:name":"Sar Ch\u0101h",
    "gn:population":0,
    "gn:timezone":"Asia/Tehran",
    "iso:country":"IR",
    "name:fas_x_preferred":[
        "Sar Ch\u0101h"
    ],
    "name:fas_x_variant":[
        "\u0633\u0631 \u0686\u0627\u0647"
    ],
    "name:und_x_variant":[
        "\u0633\u0631 \u0686\u0627\u0647"
    ],
    "wof:name":"Sar Chah",
    "wof:placetype":"locality"
},
  "geometry": {"coordinates":[58.41091,36.54177],"type":"Point"}
}