{
  "type": "Feature",
  "properties": {
    "gn:admin1_code":"8",
    "gn:asciiname":"Ishkuh-e Bala",
    "gn:country_code":"IR",
    "gn:dem":1397,
    "gn:feature_class":"P",
    "gn:feature_code":"PPL",
    "gn:name":"\u012ashkuh-e B\u0101l\u0101",
    "gn:population":0,
    "gn:timezone":"Asia/Tehran",
    "iso:country":"IR",
    "name:fas_x_preferred":[
        "\u012ashk\u016bh"
    ],
    "name:fas_x_variant":[
        "B\u0101l\u0101 \u012ashk\u016bh",
        "\u0627\u06cc\u0634\u06a9\u0648\u0647",
        "\u0627\u06cc\u0634\u06a9\u0648\u0647 \u0628\u0627\u0644\u0627"
    ],
    "name:und_x_variant":[
        "\u012ashek\u016bh",
        "Ayshakhku",
        "\u0627\u06cc\u0634\u06a9\u0648\u0647",
        "\u012ashkuh-e B\u0101l\u0101"
    ],
    "wof:name":"Ishkuh-e Bala",
    "wof:placetype":"locality"
},
  "geometry": {"coordinates":[49.89549,36.86425],"type":"Point"}
}