{
  "type": "Feature",
  "properties": {
    "gn:admin1_code":"4.0",
    "gn:asciiname":"Doz Bagan",
    "gn:country_code":"IR",
    "gn:dem":716,
    "gn:feature_class":"P",
    "gn:feature_code":"PPL",
    "gn:name":"Doz Bag\u0101n",
    "gn:population":0,
    "gn:timezone":"Asia/Tehran",
    "iso:country":"IR",
    "name:fas_x_preferred":[
        "Doz Bag\u0101n"
    ],
    "name:fas_x_variant":[
        "Dezbag\u0101n",
        "\u062f\u0632 \u0628\u06af\u0627\u0646"
    ],
    "name:und_x_variant":[
        "Doz\u012bg\u0101n",
        "Dizbur\u0101n",
        "Dezeh Bogh\u0101n"
    ],
    "wof:name":"Doz Bagan",
    "wof:placetype":"locality"
},
  "geometry": {"coordinates":[61.22764,26.47393],"type":"Point"}
}