{
  "type": "Feature",
  "properties": {
    "gn:admin1_code":"15",
    "gn:asciiname":"Anbarkeh",
    "gn:country_code":"IR",
    "gn:dem":278,
    "gn:feature_class":"P",
    "gn:feature_code":"PPL",
    "gn:name":"Anb\u0101rkeh",
    "gn:population":0,
    "gn:timezone":"Asia/Tehran",
    "iso:country":"IR",
    "name:fas_x_preferred":[
        "Seyyed H\u0101d\u012b"
    ],
    "name:fas_x_variant":[
        "\u0627\u0646\u0628\u0627\u0631\u06a9\u0647",
        "\u0637\u0627\u0642 \u062d\u0633\u06cc\u0646 \u0633\u06cc\u062f \u0647\u0627\u062f\u06cc",
        "\u0639\u0646\u0628\u0631\u06a9\u0647"
    ],
    "name:und_x_variant":[
        "Anb\u0101rkeh",
        "\u0162\u0101q \u1e28oseyn Seyyed H\u0101d\u012b"
    ],
    "wof:name":"Anbarkeh",
    "wof:placetype":"locality"
},
  "geometry": {"coordinates":[48.17376,32.60432],"type":"Point"}
}