{
  "type": "Feature",
  "properties": {
    "gn:admin1_code":"29",
    "gn:asciiname":"Deh-e Kaneh",
    "gn:country_code":"IR",
    "gn:dem":2305,
    "gn:feature_class":"P",
    "gn:feature_code":"PPL",
    "gn:name":"Deh-e K\u0101neh",
    "gn:population":0,
    "gn:timezone":"Asia/Tehran",
    "iso:country":"IR",
    "name:fas_x_preferred":[
        "\u062f\u0647 \u06a9\u0627\u0646\u0647"
    ],
    "name:fas_x_variant":[
        "Deh-e K\u0101neh"
    ],
    "name:und_x_variant":[
        "Deh-e Kohneh"
    ],
    "wof:name":"Deh-e Kaneh",
    "wof:placetype":"locality"
},
  "geometry": {"coordinates":[55.7142,30.0355],"type":"Point"}
}