{
  "type": "Feature",
  "properties": {
    "gn:admin1_code":"29",
    "gn:asciiname":"Chah-e Ziarat",
    "gn:country_code":"IR",
    "gn:dem":668,
    "gn:feature_class":"P",
    "gn:feature_code":"PPL",
    "gn:name":"Ch\u0101h-e Z\u012b\u0101rat",
    "gn:population":0,
    "gn:timezone":"Asia/Tehran",
    "iso:country":"IR",
    "name:fas_x_preferred":[
        "\u0686\u0627\u0647 \u0632\u06cc\u0627\u0631\u062a"
    ],
    "name:fas_x_variant":[
        "Ch\u0101h-e Z\u012b\u0101rat"
    ],
    "wof:name":"Chah-e Ziarat",
    "wof:placetype":"locality"
},
  "geometry": {"coordinates":[57.3444,28.2042],"type":"Point"}
}