{
  "type": "Feature",
  "properties": {
    "gn:admin1_code":"13",
    "gn:asciiname":"Faraman",
    "gn:country_code":"IR",
    "gn:dem":1277,
    "gn:feature_class":"P",
    "gn:feature_code":"PPL",
    "gn:name":"Far\u0101m\u0101n",
    "gn:population":0,
    "gn:timezone":"Asia/Tehran",
    "iso:country":"IR",
    "name:ceb_x_preferred":[
        "Far\u0101m\u0101n"
    ],
    "name:fas_x_preferred":[
        "\u0641\u0631\u0627\u0645\u0627\u0646"
    ],
    "name:fas_x_variant":[
        "Parvareshg\u0101h-e Far\u0101m\u0101n",
        "Far\u0101m\u0101n"
    ],
    "name:fra_x_preferred":[
        "Faraman"
    ],
    "name:swe_x_preferred":[
        "Far\u0101m\u0101n"
    ],
    "wof:name":"Faraman",
    "wof:placetype":"locality"
},
  "geometry": {"coordinates":[47.2859,34.2151],"type":"Point"}
}