{
  "type": "Feature",
  "properties": {
    "gn:admin1_code":"23",
    "gn:asciiname":"Zesht",
    "gn:country_code":"IR",
    "gn:dem":1800,
    "gn:feature_class":"P",
    "gn:feature_code":"PPL",
    "gn:name":"Zesht",
    "gn:population":0,
    "gn:timezone":"Asia/Tehran",
    "iso:country":"IR",
    "name:fas_x_preferred":[
        "\u0632\u0650\u0634\u062a"
    ],
    "wof:name":"Zesht",
    "wof:placetype":"locality"
},
  "geometry": {"coordinates":[48.00444,33.81722],"type":"Point"}
}