{
  "type": "Feature",
  "properties": {
    "gn:admin1_code":"25.0",
    "gn:asciiname":"Hemmatabad",
    "gn:country_code":"IR",
    "gn:dem":1049,
    "gn:feature_class":"P",
    "gn:feature_code":"PPLF",
    "gn:name":"Hemmat\u0101b\u0101d",
    "gn:population":0,
    "gn:timezone":"Asia/Tehran",
    "iso:country":"IR",
    "name:fas_x_preferred":[
        "Hemmat\u0101b\u0101d Mo\u0163ahhar\u012b"
    ],
    "name:fas_x_variant":[
        "\u0647\u0645\u062a \u0622\u0628\u0627\u062f \u0645\u0637\u0647\u0631\u06cc",
        "\u0647\u0645\u062a \u0622\u0628\u0627\u062f"
    ],
    "name:und_x_variant":[
        "Hemmat\u0101b\u0101d"
    ],
    "wof:name":"Hemmatabad",
    "wof:placetype":"locality"
},
  "geometry": {"coordinates":[55.75725,36.4576],"type":"Point"}
}