{
  "type": "Feature",
  "properties": {
    "gn:admin1_code":"1.0",
    "gn:asciiname":"Qurlu Bolagh",
    "gn:country_code":"IR",
    "gn:dem":1786,
    "gn:feature_class":"P",
    "gn:feature_code":"PPL",
    "gn:name":"Q\u016brl\u016b Bol\u0101gh",
    "gn:population":0,
    "gn:timezone":"Asia/Tehran",
    "iso:country":"IR",
    "name:fas_x_preferred":[
        "\u0642\u0648\u0631\u0644\u0648 \u0628\u064f\u0644\u0627\u063a"
    ],
    "name:und_x_variant":[
        "Q\u016brl\u016b Bol\u0101gh"
    ],
    "wof:name":"Qurlu Bolagh",
    "wof:placetype":"locality"
},
  "geometry": {"coordinates":[44.29944,39.32972],"type":"Point"}
}