{
  "type": "Feature",
  "properties": {
    "gn:country":"IR",
    "gn:fcode":"PPLX",
    "gn:population":0,
    "iso:country":"IR",
    "name:eng_x_colloquial":[
        "Davudiyyeh",
        "Daaudiyeh",
        "Daudiyeh",
        "Davudiyeh"
    ],
    "name:eng_x_preferred":[
        "D\u0101v\u016bd\u012byeh"
    ],
    "name:eng_x_variant":[
        "D\u0101v\u016bd\u012byyeh",
        "D\u00e5udiyeh"
    ],
    "name:fas_x_preferred":[
        "\u062f\u0627\u0648\u0648\u062f\u064a\u0650\u0651\u0647"
    ],
    "name:fas_x_variant":[
        "\u062f\u0627\u0648\u0648\u062f\u064a\u0651\u064a\u0650\u0647",
        "\u0645\u062d\u0644\u0647 \u062f\u0627\u0648\u062f\u06cc\u0647",
        "D\u0101udiyeh",
        "D\u0101v\u016bd\u012byyeh",
        "D\u0101v\u016bd\u012byeh"
    ],
    "qs:gn_adm0_cc":"IR",
    "qs:gn_fcode":"PPLX",
    "qs:gn_local":112931,
    "qs:gn_nam_loc":"Tehran, Tehran, IR",
    "qs:gn_namadm1":"26",
    "qs:gn_name":"Ma\u1e29alleh-ye D\u0101vod\u012byeh",
    "qs:local_max":2427,
    "qs:local_sum":3725,
    "qs:localhoods":6,
    "qs:name":"D\u0101v\u016bd\u012byeh",
    "qs:name_adm0":"Iran",
    "qs:name_adm1":"Tehran",
    "qs:name_local":"Tehran",
    "qs:photo_max":49,
    "qs:photo_sum":215,
    "qs:placetype":"Suburb",
    "qs:quad_count":56,
    "qs:woe_adm0":23424851,
    "qs:woe_adm1":2345785,
    "qs:woe_adm2":0,
    "qs:woe_lau":0,
    "qs:woe_local":2251945,
    "qs:woe_ver":"7.10.0",
    "qs_pg:aaroncc":"IR",
    "qs_pg:gn_country":"IR",
    "qs_pg:gn_fcode":"PPLX",
    "qs_pg:gn_pop":0,
    "qs_pg:name":"D\u0101v\u016bd\u012byeh",
    "qs_pg:name_adm0":"Iran",
    "qs_pg:name_adm1":"Tehran",
    "qs_pg:photos":200,
    "qs_pg:photos_1k":41,
    "qs_pg:photos_9k":1,
    "qs_pg:photos_9r":4,
    "qs_pg:photos_all":200,
    "qs_pg:photos_sr":4,
    "qs_pg:pop_sr":0,
    "qs_pg:qs_pg_placetype":"neighbourhood",
    "qs_pg:qs_pg_placetype_gp":"Suburb",
    "qs_pg:woe_adm0":23424851,
    "wof:lang":[
        "eng"
    ],
    "wof:name":"D\u0101v\u016bd\u012byeh",
    "wof:placetype":"neighbourhood"
},
  "geometry": {"coordinates":[51.430649,35.762731],"type":"Point"}
}