{
  "type": "Feature",
  "properties": {
    "iso:country":"IR",
    "name:ara_x_preferred":[
        "\u0646\u0627\u0626\u064a\u0646"
    ],
    "name:arz_x_preferred":[
        "\u0646\u0627\u0626\u064a\u0646"
    ],
    "name:azb_x_preferred":[
        "\u0646\u0627\u06cc\u06cc\u0646"
    ],
    "name:aze_x_preferred":[
        "Nain"
    ],
    "name:cat_x_preferred":[
        "Nayin"
    ],
    "name:ceb_x_preferred":[
        "N\u0101'\u012bn"
    ],
    "name:deu_x_preferred":[
        "Nain"
    ],
    "name:deu_x_variant":[
        "N\u0101'in"
    ],
    "name:eng_x_preferred":[
        "N\u0101'in"
    ],
    "name:fas_x_preferred":[
        "\u0646\u0627\u06cc\u06cc\u0646"
    ],
    "name:fas_x_variant":[
        "N\u0101\u2019\u012bn",
        "\u0646\u0627\u0626\u06cc\u0646"
    ],
    "name:fra_x_preferred":[
        "Nain"
    ],
    "name:ita_x_preferred":[
        "Na'in"
    ],
    "name:jpn_x_preferred":[
        "\u30ca\u30fc\u30a4\u30fc\u30f3"
    ],
    "name:mlg_x_preferred":[
        "Nain"
    ],
    "name:nld_x_preferred":[
        "Nain"
    ],
    "name:pol_x_preferred":[
        "Na\u2019in"
    ],
    "name:por_x_preferred":[
        "Na'in"
    ],
    "name:ron_x_preferred":[
        "Nain"
    ],
    "name:rus_x_preferred":[
        "\u041d\u0430\u0438\u043d"
    ],
    "name:spa_x_preferred":[
        "Nain"
    ],
    "name:swe_x_preferred":[
        "N\u0101'\u012bn"
    ],
    "name:tgk_x_preferred":[
        "\u041d\u043e\u0438\u043d"
    ],
    "name:tur_x_preferred":[
        "Nain"
    ],
    "name:unk_x_variant":[
        "N\u0101eyn"
    ],
    "name:urd_x_preferred":[
        "\u0646\u0627\u06cc\u06cc\u0646"
    ],
    "name:zho_x_preferred":[
        "\u7d0d\u56e0"
    ],
    "qs:gn_country":"IR",
    "qs:gn_fcode":"PPL",
    "qs:gn_pop":0,
    "qs:name":"Nain",
    "qs:name_adm0":"Iran",
    "qs:name_adm1":"Esfahan",
    "qs:photos":214,
    "qs:photos_1k":43,
    "qs:photos_9k":1,
    "qs:photos_9r":4,
    "qs:photos_all":214,
    "qs:photos_sr":4,
    "qs:placetype":"Town",
    "qs:pop_sr":"7",
    "qs:woe_adm0":23424851,
    "wd:wordcount":3204,
    "wof:name":"Nain",
    "wof:placetype":"locality"
},
  "geometry": {"coordinates":[53.08749,32.86006],"type":"Point"}
}