{
  "type": "Feature",
  "properties": {
    "gn:admin1_code":"34",
    "gn:asciiname":"Khanabad",
    "gn:country_code":"IR",
    "gn:dem":1832,
    "gn:feature_class":"P",
    "gn:feature_code":"PPL",
    "gn:name":"Kh\u0101n\u0101b\u0101d",
    "gn:population":0,
    "gn:timezone":"Asia/Tehran",
    "iso:country":"IR",
    "name:fas_x_preferred":[
        "\u062e\u0627\u0646 \u0622\u0628\u0627\u062f"
    ],
    "name:fas_x_variant":[
        "Kh\u0101n\u0101b\u0101d",
        "J\u0101n\u0101b\u0101d",
        "\u062c\u0627\u0646 \u0622\u0628\u0627\u062f",
        "\u062d\u0645\u06cc\u062f\u06cc\u0647"
    ],
    "name:und_x_variant":[
        "\u062c\u0627\u0646 \u0622\u0628\u0627\u062f",
        "\u1e28am\u012bd\u012byeh"
    ],
    "wof:name":"Khanabad",
    "wof:placetype":"locality"
},
  "geometry": {"coordinates":[49.5108,35.23059],"type":"Point"}
}