{
  "type": "Feature",
  "properties": {
    "gn:admin1_code":"35.0",
    "gn:asciiname":"Tahamtan Kola",
    "gn:country_code":"IR",
    "gn:dem":163,
    "gn:feature_class":"P",
    "gn:feature_code":"PPL",
    "gn:name":"Tahamtan Kol\u0101",
    "gn:population":0,
    "gn:timezone":"Asia/Tehran",
    "iso:country":"IR",
    "name:ceb_x_preferred":[
        "Tahamtan Kol\u0101"
    ],
    "name:fas_x_preferred":[
        "\u062a\u0647\u0645\u062a\u0646 \u0643\u0644\u0627"
    ],
    "name:fas_x_variant":[
        "Tahamtan Kol\u0101",
        "\u062a\u0647\u0645\u062a\u0646\u200c\u06a9\u0644\u0627"
    ],
    "name:mzn_x_preferred":[
        "\u062a\u0647\u0645\u062a\u0646\u200c\u06a9\u0644\u0627"
    ],
    "name:swe_x_preferred":[
        "Tahamtan Kol\u0101"
    ],
    "name:und_x_variant":[
        "\u062a\u064e\u0647\u064e\u0645\u062a\u064e\u0646 \u0643\u064f\u0644\u0627"
    ],
    "wof:name":"Tahamtan Kola",
    "wof:placetype":"locality"
},
  "geometry": {"coordinates":[52.63665,36.32304],"type":"Point"}
}