{
  "type": "Feature",
  "properties": {
    "gn:admin1_code":"7",
    "gn:asciiname":"Tizdang-e `Olya",
    "gn:country_code":"IR",
    "gn:dem":1288,
    "gn:feature_class":"P",
    "gn:feature_code":"PPL",
    "gn:name":"T\u012bzdang-e \u2018Oly\u0101",
    "gn:population":0,
    "gn:timezone":"Asia/Tehran",
    "iso:country":"IR",
    "name:fas_x_preferred":[
        "T\u012bzdang-e \u2018Oly\u0101"
    ],
    "name:fas_x_variant":[
        "T\u012bzd\u012bng-e B\u0101l\u0101",
        "\u062a\u06cc\u0632\u062f\u0646\u06af \u0639\u0644\u06cc\u0627"
    ],
    "name:und_x_variant":[
        "Tez D\u012bng",
        "\u062a\u06cc\u0632\u062f\u0646\u06af \u0639\u0644\u06cc\u0627"
    ],
    "wof:name":"Tizdang-e `Olya",
    "wof:placetype":"locality"
},
  "geometry": {"coordinates":[51.3182,30.00946],"type":"Point"}
}