{
  "type": "Feature",
  "properties": {
    "gn:admin1_code":"40",
    "gn:asciiname":"Zarju`",
    "gn:country_code":"IR",
    "gn:dem":1843,
    "gn:feature_class":"P",
    "gn:feature_code":"PPL",
    "gn:name":"Zarj\u016b\u2018",
    "gn:population":0,
    "gn:timezone":"Asia/Tehran",
    "iso:country":"IR",
    "name:ara_x_preferred":[
        "\u0632\u0631\u062c\u0648\u0639"
    ],
    "name:fas_x_preferred":[
        "\u0632\u0631\u062c\u0648\u0639"
    ],
    "name:fas_x_variant":[
        "\u0632\u064e\u0631\u062e\u0648\u0639",
        "\u0632\u064e\u0631\u062c\u0648\u0647",
        "Zarj\u016b\u2018",
        "Zarj\u016bh"
    ],
    "name:und_x_variant":[
        "Zarkh\u016b\u2018"
    ],
    "wof:name":"Zarju`",
    "wof:placetype":"locality"
},
  "geometry": {"coordinates":[53.6011,32.3333],"type":"Point"}
}