{
  "type": "Feature",
  "properties": {
    "gn:admin1_code":"26.0",
    "gn:asciiname":"Naseriyeh",
    "gn:country_code":"IR",
    "gn:dem":1083,
    "gn:feature_class":"P",
    "gn:feature_code":"PPL",
    "gn:name":"N\u0101\u015fer\u012byeh",
    "gn:population":0,
    "gn:timezone":"Asia/Tehran",
    "iso:country":"IR",
    "name:fas_x_preferred":[
        "\u0646\u0627\u0635\u0631 \u0622\u0628\u0627\u062f"
    ],
    "name:fas_x_variant":[
        "N\u0101\u015fer\u0101b\u0101d",
        "N\u0101\u015fer\u012byeh",
        "\u0646\u0627\u0635\u0631\u064a\u0647"
    ],
    "wof:name":"Naseriyeh",
    "wof:placetype":"locality"
},
  "geometry": {"coordinates":[51.29422,35.59038],"type":"Point"}
}