{
  "type": "Feature",
  "properties": {
    "gn:admin1_code":"16",
    "gn:asciiname":"Qeshlaq-e Aqa Gureh",
    "gn:country_code":"IR",
    "gn:dem":1588,
    "gn:feature_class":"P",
    "gn:feature_code":"PPL",
    "gn:name":"Qeshl\u0101q-e \u0100q\u0101 G\u016breh",
    "gn:population":0,
    "gn:timezone":"Asia/Tehran",
    "iso:country":"IR",
    "name:ara_x_preferred":[
        "\u0642\u0634\u0644\u0627\u062e \u0622\u063a\u0647 \u063a\u0648\u0631\u0647"
    ],
    "name:ceb_x_preferred":[
        "Qeshl\u0101q"
    ],
    "name:ckb_x_preferred":[
        "\u0642\u0634\u06b5\u0627\u062e \u0626\u0627\u063a\u06d5\u06af\u06d5\u0648\u0631\u06d5"
    ],
    "name:fas_x_preferred":[
        "\u0642\u0634\u0644\u0627\u0642"
    ],
    "name:fas_x_variant":[
        "Qeshl\u0101q-e \u0100q\u0101 G\u016breh",
        "Qeshl\u0101q",
        "\u0642\u0634\u0644\u0627\u0642 \u0622\u0642\u0627 \u06af\u0648\u0631\u0647",
        "\u0642\u0634\u0644\u0627\u0642 \u0622\u0642\u0627\u06af\u0648\u0631\u0647"
    ],
    "name:kur_x_preferred":[
        "Qi\u015flaq Axegewre"
    ],
    "wof:name":"Qeshlaq-e Aqa Gureh",
    "wof:placetype":"locality"
},
  "geometry": {"coordinates":[46.52331,36.04613],"type":"Point"}
}