{
  "type": "Feature",
  "properties": {
    "gn:admin1_code":"29",
    "gn:asciiname":"Sar Mowr",
    "gn:country_code":"IR",
    "gn:dem":2270,
    "gn:feature_class":"P",
    "gn:feature_code":"PPLF",
    "gn:name":"Sar Mowr",
    "gn:population":0,
    "gn:timezone":"Asia/Tehran",
    "iso:country":"IR",
    "name:fas_x_preferred":[
        "\u0633\u0631 \u0645\u0648\u0631"
    ],
    "wof:name":"Sar Mowr",
    "wof:placetype":"locality"
},
  "geometry": {"coordinates":[56.37866,30.59497],"type":"Point"}
}