{
  "type": "Feature",
  "properties": {
    "gn:admin1_code":"7",
    "gn:asciiname":"Shahrak-e Ardkapan",
    "gn:country_code":"IR",
    "gn:dem":2171,
    "gn:feature_class":"P",
    "gn:feature_code":"PPL",
    "gn:name":"Shahrak-e \u0100rdkap\u0101n",
    "gn:population":0,
    "gn:timezone":"Asia/Tehran",
    "iso:country":"IR",
    "name:fas_x_preferred":[
        "\u0634\u0647\u0631\u06a9 \u0622\u0631\u062f\u06a9\u067e\u0627\u0646"
    ],
    "name:fas_x_variant":[
        "Shahrak-e \u0100rdkap\u0101n"
    ],
    "wof:name":"Shahrak-e Ardkapan",
    "wof:placetype":"locality"
},
  "geometry": {"coordinates":[52.3046,30.5108],"type":"Point"}
}