{
  "type": "Feature",
  "properties": {
    "gn:admin1_code":"16.0",
    "gn:asciiname":"Gorgeh'i",
    "gn:country_code":"IR",
    "gn:dem":1324,
    "gn:feature_class":"P",
    "gn:feature_code":"PPL",
    "gn:name":"Gorgeh\u2019\u012b",
    "gn:population":0,
    "gn:timezone":"Asia/Tehran",
    "iso:country":"IR",
    "name:fas_x_preferred":[
        "Gorgeh\u2019\u012b"
    ],
    "name:und_x_variant":[
        "Gorg\u012b"
    ],
    "wof:name":"Gorgeh'i",
    "wof:placetype":"locality"
},
  "geometry": {"coordinates":[46.34694,35.32222],"type":"Point"}
}