{
  "type": "Feature",
  "properties": {
    "gn:admin1_code":"22",
    "gn:asciiname":"Gurak Sadat",
    "gn:country_code":"IR",
    "gn:dem":14,
    "gn:feature_class":"P",
    "gn:feature_code":"PPL",
    "gn:name":"G\u016brak S\u0101d\u0101t",
    "gn:population":0,
    "gn:timezone":"Asia/Tehran",
    "iso:country":"IR",
    "name:fas_x_preferred":[
        "\u0645\u064e\u0639\u0646\u0627\u0626\u06cc"
    ],
    "name:fas_x_variant":[
        "\u06af\u0648\u0631\u06a9 \u0633\u0627\u062f\u0627\u062a",
        "\u06af\u0648\u0631\u064e\u0643",
        "\u06af\u064f\u0651\u0631\u064e\u0643",
        "\u0643\u0648\u0631\u064e\u0643",
        "Ma\u2018n\u0101\u2019\u012b",
        "G\u016brak S\u0101d\u0101t"
    ],
    "name:und_x_variant":[
        "Mah\u0101ni",
        "G\u016brak",
        "K\u016brak",
        "Goorak"
    ],
    "wof:name":"Gurak Sadat",
    "wof:placetype":"locality"
},
  "geometry": {"coordinates":[51.0528,28.9458],"type":"Point"}
}