{
  "type": "Feature",
  "properties": {
    "gn:admin1_code":"1",
    "gn:asciiname":"Mirza Dulmaz",
    "gn:cc2":"IR",
    "gn:country_code":"IR",
    "gn:dem":1357,
    "gn:feature_class":"P",
    "gn:feature_code":"PPL",
    "gn:name":"M\u012brz\u0101 D\u016blm\u0101z",
    "gn:population":0,
    "gn:timezone":"Asia/Tehran",
    "iso:country":"IR",
    "name:azb_x_preferred":[
        "\u0645\u06cc\u0631\u0632\u0627\u062f\u0648\u0644\u0645\u0627\u0632"
    ],
    "name:aze_x_preferred":[
        "Mirz\u0259dolmaz"
    ],
    "name:fas_x_preferred":[
        "\u0645\u064a\u0631\u0632\u0627 \u062f\u0648\u0644\u0645\u0627\u0632"
    ],
    "name:fas_x_variant":[
        "\u062a\u0648\u0632\u0648",
        "M\u012brz\u0101 D\u016blm\u0101z",
        "\u0645\u06cc\u0631\u0632\u0627\u062f\u0648\u0644\u0645\u0627\u0632"
    ],
    "name:msa_x_preferred":[
        "Mirza Dulmaz"
    ],
    "name:und_x_variant":[
        "T\u016bz\u016b"
    ],
    "wof:name":"Mirza Dulmaz",
    "wof:placetype":"locality"
},
  "geometry": {"coordinates":[44.71667,39.36667],"type":"Point"}
}