{
  "type": "Feature",
  "properties": {
    "gn:admin1_code":"43",
    "gn:asciiname":"Khorramdeh-e Gharbi",
    "gn:country_code":"IR",
    "gn:dem":527,
    "gn:feature_class":"P",
    "gn:feature_code":"PPL",
    "gn:name":"Khorramdeh-e Gharb\u012b",
    "gn:population":0,
    "gn:timezone":"Asia/Tehran",
    "iso:country":"IR",
    "name:fas_x_preferred":[
        "Khorramdeh-e Gharb\u012b"
    ],
    "name:fas_x_variant":[
        "Kharak\u012b-ye Barbarh\u0101",
        "\u062e\u0631\u06a9\u06cc \u0628\u0631\u0628\u0631\u0647\u0627",
        "\u062e\u0631\u0645 \u062f\u0647 \u063a\u0631\u0628\u06cc"
    ],
    "name:und_x_variant":[
        "Khar\u0101qi",
        "Kharak\u012b",
        "Kharak\u012b-ye Barbarh\u0101",
        "\u062e\u0631\u06a9\u06cc \u0628\u0631\u0628\u0631\u0647\u0627"
    ],
    "wof:name":"Khorramdeh-e Gharbi",
    "wof:placetype":"locality"
},
  "geometry": {"coordinates":[56.78491,37.7181],"type":"Point"}
}