{
  "type": "Feature",
  "properties": {
    "gn:admin1_code":"4.0",
    "gn:asciiname":"Vashnam",
    "gn:country_code":"IR",
    "gn:dem":15,
    "gn:feature_class":"P",
    "gn:feature_code":"PPL",
    "gn:name":"Vashn\u0101m",
    "gn:population":0,
    "gn:timezone":"Asia/Tehran",
    "iso:country":"IR",
    "name:fas_x_preferred":[
        "\u0648\u0634\u0646\u0627\u0645"
    ],
    "name:fas_x_variant":[
        "Vashn\u0101m"
    ],
    "name:und_x_variant":[
        "Vashn\u0101m Khar\u0101beh"
    ],
    "wof:name":"Vashnam",
    "wof:placetype":"locality"
},
  "geometry": {"coordinates":[60.8091,25.3698],"type":"Point"}
}