{
  "type": "Feature",
  "properties": {
    "gn:admin1_code":"43",
    "gn:asciiname":"Chalekanlu",
    "gn:country_code":"IR",
    "gn:dem":1456,
    "gn:feature_class":"P",
    "gn:feature_code":"PPL",
    "gn:name":"Chalek\u0101nl\u016b",
    "gn:population":0,
    "gn:timezone":"Asia/Tehran",
    "iso:country":"IR",
    "name:fas_x_preferred":[
        "Chalek\u0101nl\u016b"
    ],
    "name:fas_x_variant":[
        "\u0686\u0644\u06a9\u0627\u0646\u0644\u0648"
    ],
    "name:und_x_variant":[
        "Chalkanl\u012b",
        "Ch\u0101lk\u0101nl\u016b",
        "\u0686\u0644\u06a9\u0627\u0646\u0644\u0648"
    ],
    "wof:name":"Chalekanlu",
    "wof:placetype":"locality"
},
  "geometry": {"coordinates":[57.96846,37.61719],"type":"Point"}
}