{
  "type": "Feature",
  "properties": {
    "gn:admin1_code":"37",
    "gn:asciiname":"Qal`eh Mahmud",
    "gn:country_code":"IR",
    "gn:dem":10,
    "gn:feature_class":"P",
    "gn:feature_code":"PPL",
    "gn:name":"Qal\u2018eh Ma\u1e29m\u016bd",
    "gn:population":0,
    "gn:timezone":"Asia/Tehran",
    "iso:country":"IR",
    "name:fas_x_preferred":[
        "\u0642\u0644\u0639\u0647 \u0645\u062d\u0645\u0648\u062f"
    ],
    "name:fas_x_variant":[
        "Qal\u2018eh Ma\u1e29m\u016bd"
    ],
    "wof:name":"Qal`eh Mahmud",
    "wof:placetype":"locality"
},
  "geometry": {"coordinates":[54.37015,36.88701],"type":"Point"}
}