{
  "type": "Feature",
  "properties": {
    "gn:admin1_code":"35",
    "gn:asciiname":"Kuy-e Kheyl",
    "gn:country_code":"IR",
    "gn:dem":0,
    "gn:feature_class":"P",
    "gn:feature_code":"PPL",
    "gn:name":"K\u016by-e Kheyl",
    "gn:population":0,
    "gn:timezone":"Asia/Tehran",
    "iso:country":"IR",
    "name:fas_x_preferred":[
        "K\u016by-e Kheyl"
    ],
    "name:fas_x_variant":[
        "K\u016b-ye Kheyl",
        "\u0643\u0648\u06cc \u062e\u064a\u0644"
    ],
    "wof:name":"Kuy-e Kheyl",
    "wof:placetype":"locality"
},
  "geometry": {"coordinates":[53.09457,36.64043],"type":"Point"}
}