{
  "type": "Feature",
  "properties": {
    "gn:admin1_code":"38",
    "gn:asciiname":"Narendeh",
    "gn:country_code":"IR",
    "gn:dem":1437,
    "gn:feature_class":"P",
    "gn:feature_code":"PPL",
    "gn:name":"N\u0101rendeh",
    "gn:population":0,
    "gn:timezone":"Asia/Tehran",
    "iso:country":"IR",
    "name:fas_x_preferred":[
        "\u0646\u0627\u0631\u064a\u0646\u062f\u0650\u0647"
    ],
    "name:fas_x_variant":[
        "\u0646\u0627\u0631\u064e\u0646\u062f\u0650\u0647",
        "\u0646\u0627\u0631\u0650\u0646\u0634\u0650\u062f",
        "N\u0101rendeh",
        "\u0646\u0627\u0631\u0646\u062f\u0647"
    ],
    "name:und_x_variant":[
        "Narin-Dekh",
        "N\u0101renshed",
        "N\u0101r\u012bndeh",
        "N\u0101randeh"
    ],
    "wof:name":"Narendeh",
    "wof:placetype":"locality"
},
  "geometry": {"coordinates":[49.76344,36.50121],"type":"Point"}
}