{
  "type": "Feature",
  "properties": {
    "gn:admin1_code":"10.0",
    "gn:asciiname":"Jusheh",
    "gn:country_code":"IR",
    "gn:dem":1142,
    "gn:feature_class":"P",
    "gn:feature_code":"PPL",
    "gn:name":"J\u016bsheh",
    "gn:population":0,
    "gn:timezone":"Asia/Tehran",
    "iso:country":"IR",
    "name:fas_x_preferred":[
        "\u062c\u0648\u0634\u0650\u0647"
    ],
    "name:fas_x_variant":[
        "J\u016bsheh"
    ],
    "wof:name":"Jusheh",
    "wof:placetype":"locality"
},
  "geometry": {"coordinates":[46.28333,33.83333],"type":"Point"}
}