{
  "type": "Feature",
  "properties": {
    "gn:admin1_code":"4.0",
    "gn:asciiname":"Bon Kuh",
    "gn:country_code":"IR",
    "gn:dem":724,
    "gn:feature_class":"P",
    "gn:feature_code":"PPL",
    "gn:name":"Bon K\u016bh",
    "gn:population":0,
    "gn:timezone":"Asia/Tehran",
    "iso:country":"IR",
    "name:ceb_x_preferred":[
        "Bon Kuh"
    ],
    "name:fas_x_preferred":[
        "\u0628\u0646 \u06a9\u0648\u0647"
    ],
    "name:swe_x_preferred":[
        "Bon Kuh"
    ],
    "name:und_x_variant":[
        "Bon K\u016bh"
    ],
    "wof:name":"Bon Kuh",
    "wof:placetype":"locality"
},
  "geometry": {"coordinates":[59.323,27.89513],"type":"Point"}
}