{
  "type": "Feature",
  "properties": {
    "gn:admin1_code":"28.0",
    "gn:asciiname":"Mirza Bashi",
    "gn:country_code":"IR",
    "gn:dem":1816,
    "gn:feature_class":"P",
    "gn:feature_code":"PPL",
    "gn:name":"M\u012brz\u0101 B\u0101sh\u012b",
    "gn:population":0,
    "gn:timezone":"Asia/Tehran",
    "iso:country":"IR",
    "name:fas_x_preferred":[
        "\u0645\u06cc\u0631\u0632\u0627 \u0628\u0627\u0634\u06cc"
    ],
    "name:fas_x_variant":[
        "M\u012brz\u0101 B\u0101sh\u012b"
    ],
    "wof:name":"Mirza Bashi",
    "wof:placetype":"locality"
},
  "geometry": {"coordinates":[53.0878,32.6515],"type":"Point"}
}