{
  "type": "Feature",
  "properties": {
    "gn:admin1_code":"41.0",
    "gn:asciiname":"Kalateh-ye Bidelak",
    "gn:country_code":"IR",
    "gn:dem":2327,
    "gn:feature_class":"P",
    "gn:feature_code":"PPL",
    "gn:name":"Kal\u0101teh-ye B\u012bdelak",
    "gn:population":0,
    "gn:timezone":"Asia/Tehran",
    "iso:country":"IR",
    "name:fas_x_preferred":[
        "\u06a9\u0644\u0627\u062a\u0647 \u0628\u064a\u062f\u0644\u06a9"
    ],
    "name:und_x_variant":[
        "Kal\u0101teh-ye B\u012bdelak"
    ],
    "wof:name":"Kalateh-ye Bidelak",
    "wof:placetype":"locality"
},
  "geometry": {"coordinates":[59.45655,32.63203],"type":"Point"}
}