{
  "type": "Feature",
  "properties": {
    "gn:admin1_code":"32",
    "gn:asciiname":"Lalahlu",
    "gn:country_code":"IR",
    "gn:dem":1487,
    "gn:feature_class":"P",
    "gn:feature_code":"PPL",
    "gn:name":"Lalahl\u016b",
    "gn:population":0,
    "gn:timezone":"Asia/Tehran",
    "iso:country":"IR",
    "name:fas_x_preferred":[
        "\u0644\u064e\u0644\u064e\u0647\u0644\u0648"
    ],
    "name:fas_x_variant":[
        "\u0644\u0644\u0647 \u0644\u0648",
        "Lalahl\u016b"
    ],
    "wof:name":"Lalahlu",
    "wof:placetype":"locality"
},
  "geometry": {"coordinates":[48.1923,38.4924],"type":"Point"}
}