{
  "type": "Feature",
  "properties": {
    "gn:admin1_code":"16",
    "gn:asciiname":"Aqyazi",
    "gn:country_code":"IR",
    "gn:dem":1795,
    "gn:feature_class":"P",
    "gn:feature_code":"PPL",
    "gn:name":"\u0100qy\u0101z\u012b",
    "gn:population":0,
    "gn:timezone":"Asia/Tehran",
    "iso:country":"IR",
    "name:ara_x_preferred":[
        "\u0623\u063a \u064a\u0627\u0632\u064a"
    ],
    "name:fas_x_preferred":[
        "\u0622\u063a \u064a\u0627\u0632\u06cc"
    ],
    "name:fas_x_variant":[
        "\u0622\u0642\u06cc\u0627\u0632\u06cc",
        "\u0100ghy\u0101z\u012b",
        "\u0100qy\u0101z\u012b",
        "\u0622\u063a \u06cc\u0627\u0632\u06cc"
    ],
    "wof:name":"Aqyazi",
    "wof:placetype":"locality"
},
  "geometry": {"coordinates":[47.6271,36.34627],"type":"Point"}
}