{
  "type": "Feature",
  "properties": {
    "gn:admin1_code":"10.0",
    "gn:asciiname":"Linjab",
    "gn:country_code":"IR",
    "gn:dem":1162,
    "gn:feature_class":"P",
    "gn:feature_code":"PPL",
    "gn:name":"L\u012bnj\u0101b",
    "gn:population":0,
    "gn:timezone":"Asia/Tehran",
    "iso:country":"IR",
    "name:fas_x_preferred":[
        "\u0644\u064a\u0646\u062c\u0627\u0648 \u0634\u064e\u0631\u064a\u0641"
    ],
    "name:fas_x_variant":[
        "\u0644\u06cc\u0646\u062c\u0627\u0628",
        "L\u012bnj\u0101v Shar\u012bf",
        "\u0648\u0650\u0646\u064a\u062a \u0634\u064e\u0631\u064a\u0641",
        "L\u012bnj\u0101b"
    ],
    "name:und_x_variant":[
        "Ven\u012bt Shar\u012bf"
    ],
    "wof:name":"Linjab",
    "wof:placetype":"locality"
},
  "geometry": {"coordinates":[46.2354,33.8366],"type":"Point"}
}