{
  "type": "Feature",
  "properties": {
    "gn:admin1_code":"9.0",
    "gn:asciiname":"Avarzaman",
    "gn:country_code":"IR",
    "gn:dem":1715,
    "gn:feature_class":"P",
    "gn:feature_code":"PPL",
    "gn:name":"\u0100varzam\u0101n",
    "gn:population":0,
    "gn:timezone":"Asia/Tehran",
    "iso:country":"IR",
    "name:fas_x_preferred":[
        "\u0622\u0628 \u0632\u064e\u0645\u0627\u0645"
    ],
    "name:fas_x_variant":[
        "\u0627\u064e\u0648\u0632\u064e\u0645\u0627\u0646",
        "\u0622\u0648\u064e\u0631 \u0632\u064e\u0645\u0627\u0646 \u062a\u064e\u067e\u0650\u0651\u0647 \u0642\u064e\u064a\u0650\u0644\u06cc",
        "\u0627\u064e\u0631\u0648\u0632\u064e\u0645\u0627\u0646",
        "\u0100varzam\u0101n",
        "\u0622\u0648\u0631\u0632\u0645\u0627\u0646",
        "\u0627\u0648\u0631\u0632\u0645\u0627\u0646"
    ],
    "name:msa_x_preferred":[
        "Avarzaman"
    ],
    "name:und_x_variant":[
        "Ar\u016bzam\u0101n",
        "Avzam\u0101n",
        "\u0100b-\u012b-Zam\u0101n",
        "\u0100var Zam\u0101n Tappeh Qayel\u012b",
        "\u0100b Zam\u0101m"
    ],
    "wof:name":"Avarzaman",
    "wof:placetype":"locality"
},
  "geometry": {"coordinates":[48.51185,34.26614],"type":"Point"}
}