{
  "type": "Feature",
  "properties": {
    "gn:admin1_code":"28.0",
    "gn:asciiname":"Zinatabad",
    "gn:country_code":"IR",
    "gn:dem":2207,
    "gn:feature_class":"P",
    "gn:feature_code":"PPL",
    "gn:name":"Z\u012bnat\u0101b\u0101d",
    "gn:population":0,
    "gn:timezone":"Asia/Tehran",
    "iso:country":"IR",
    "name:fas_x_preferred":[
        "\u0632\u06cc\u0646\u062a \u0622\u0628\u0627\u062f"
    ],
    "name:fas_x_variant":[
        "Z\u012bnat\u0101b\u0101d",
        "\u0632\u06cc\u0646\u062a\u200c\u0622\u0628\u0627\u062f"
    ],
    "name:und_x_variant":[
        "Zeynat\u0101b\u0101d"
    ],
    "wof:name":"Zinatabad",
    "wof:placetype":"locality"
},
  "geometry": {"coordinates":[52.7504,32.73],"type":"Point"}
}