{
  "type": "Feature",
  "properties": {
    "gn:admin1_code":"40",
    "gn:asciiname":"Sheytur",
    "gn:country_code":"IR",
    "gn:dem":1872,
    "gn:feature_class":"P",
    "gn:feature_code":"PPL",
    "gn:name":"Shey\u0163\u016br",
    "gn:population":0,
    "gn:timezone":"Asia/Tehran",
    "iso:country":"IR",
    "name:ceb_x_preferred":[
        "Shey\u0163\u016br"
    ],
    "name:fas_x_preferred":[
        "\u0634\u06cc\u0637\u0648\u0631"
    ],
    "name:swe_x_preferred":[
        "Shey\u0163\u016br"
    ],
    "name:und_x_variant":[
        "Shey\u0163\u016br",
        "Shait\u016br"
    ],
    "wof:name":"Sheytur",
    "wof:placetype":"locality"
},
  "geometry": {"coordinates":[55.91639,31.54107],"type":"Point"}
}