{
  "type": "Feature",
  "properties": {
    "gn:admin1_code":"36",
    "gn:asciiname":"Chang Almas",
    "gn:country_code":"IR",
    "gn:dem":1962,
    "gn:feature_class":"P",
    "gn:feature_code":"PPL",
    "gn:name":"Chang Alm\u0101s",
    "gn:population":0,
    "gn:timezone":"Asia/Tehran",
    "iso:country":"IR",
    "name:fas_x_preferred":[
        "\u0686\u0646\u06af \u0627\u0644\u0645\u0627\u0633"
    ],
    "name:fas_x_variant":[
        "Chang Alm\u0101s"
    ],
    "name:und_x_variant":[
        "Changarm\u0101s",
        "Changm\u0101s",
        "Changam\u0101s"
    ],
    "wof:name":"Chang Almas",
    "wof:placetype":"locality"
},
  "geometry": {"coordinates":[49.09157,36.00412],"type":"Point"}
}