{
  "type": "Feature",
  "properties": {
    "gn:admin1_code":"7",
    "gn:asciiname":"Mazu",
    "gn:country_code":"IR",
    "gn:dem":449,
    "gn:feature_class":"P",
    "gn:feature_code":"PPL",
    "gn:name":"M\u0101z\u016b",
    "gn:population":0,
    "gn:timezone":"Asia/Tehran",
    "iso:country":"IR",
    "name:fas_x_preferred":[
        "\u0645\u0632\u06cc\u062c\u0627\u0646"
    ],
    "name:fas_x_variant":[
        "M\u0101z\u016b",
        "Mazeyj\u0101n",
        "Mez\u012bj\u0101n",
        "\u0645\u0627\u0632\u0648",
        "\u0645\u0632\u0648"
    ],
    "name:msa_x_preferred":[
        "Mezijan"
    ],
    "name:und_x_variant":[
        "Maz\u016b"
    ],
    "wof:name":"Mazu",
    "wof:placetype":"locality"
},
  "geometry": {"coordinates":[52.746,27.6875],"type":"Point"}
}