{
  "type": "Feature",
  "properties": {
    "gn:admin1_code":"23",
    "gn:asciiname":"Hezarmani",
    "gn:country_code":"IR",
    "gn:dem":1417,
    "gn:feature_class":"P",
    "gn:feature_code":"PPL",
    "gn:name":"Hez\u0101rman\u012b",
    "gn:population":0,
    "gn:timezone":"Asia/Tehran",
    "iso:country":"IR",
    "name:fas_x_preferred":[
        "\u0647\u0632\u0627\u0631\u0645\u0646\u06cc"
    ],
    "name:und_x_variant":[
        "Hez\u0101rman\u012b"
    ],
    "wof:name":"Hezarmani",
    "wof:placetype":"locality"
},
  "geometry": {"coordinates":[48.19189,33.67205],"type":"Point"}
}