{
  "type": "Feature",
  "properties": {
    "gn:admin1_code":"29",
    "gn:asciiname":"Hashemabad",
    "gn:country_code":"IR",
    "gn:dem":267,
    "gn:feature_class":"P",
    "gn:feature_code":"PPL",
    "gn:name":"H\u0101shem\u0101b\u0101d",
    "gn:population":0,
    "gn:timezone":"Asia/Tehran",
    "iso:country":"IR",
    "name:fas_x_preferred":[
        "\u0647\u0627\u0634\u0645 \u0622\u0628\u0627\u062f"
    ],
    "name:fas_x_variant":[
        "H\u0101shem\u0101b\u0101d",
        "\u0647\u0627\u0634\u0645\u200c\u0622\u0628\u0627\u062f"
    ],
    "wof:name":"Hashemabad",
    "wof:placetype":"locality"
},
  "geometry": {"coordinates":[57.99803000000001,30.29931],"type":"Point"}
}