{
  "type": "Feature",
  "properties": {
    "gn:admin1_code":"26",
    "gn:asciiname":"Hesarak-e Pa'in",
    "gn:country_code":"IR",
    "gn:dem":1057,
    "gn:feature_class":"P",
    "gn:feature_code":"PPL",
    "gn:name":"\u1e28e\u015f\u0101rak-e P\u0101\u2019\u012bn",
    "gn:population":0,
    "gn:timezone":"Asia/Tehran",
    "iso:country":"IR",
    "name:fas_x_preferred":[
        "\u062d\u0650\u0635\u0627\u0631\u064e\u0643"
    ],
    "name:fas_x_variant":[
        "\u1e28e\u015f\u0101rak",
        "\u062d\u0635\u0627\u0631\u06a9 \u067e\u0627\u0626\u06cc\u0646"
    ],
    "name:und_x_variant":[
        "\u1e28e\u015f\u0101rak-e P\u0101\u2019\u012bn"
    ],
    "wof:name":"Hesarak-e Pa'in",
    "wof:placetype":"locality"
},
  "geometry": {"coordinates":[51.19115,35.54150999999999],"type":"Point"}
}