{
  "type": "Feature",
  "properties": {
    "gn:admin1_code":"23.0",
    "gn:asciiname":"`Abbas Khan",
    "gn:country_code":"IR",
    "gn:dem":1677,
    "gn:feature_class":"P",
    "gn:feature_code":"PPL",
    "gn:name":"\u2018Abb\u0101s Kh\u0101n",
    "gn:population":0,
    "gn:timezone":"Asia/Tehran",
    "iso:country":"IR",
    "name:est_x_preferred":[
        "\u2018Abb\u0101s\u0101b\u0101d"
    ],
    "name:fas_x_preferred":[
        "\u0639\u064e\u0628\u0651\u0627\u0633 \u062e\u0627\u0646"
    ],
    "name:fas_x_variant":[
        "\u0627\u064e\u0628\u0651\u0627\u0633 \u0622\u0628\u0627\u062f",
        "\u0639\u0628\u0627\u0633\u200c\u0622\u0628\u0627\u062f"
    ],
    "name:fra_x_preferred":[
        "Abbas Abad"
    ],
    "name:por_x_preferred":[
        "Abbas Abad"
    ],
    "name:und_x_variant":[
        "Abb\u0101s \u0100b\u0101d",
        "\u2018Abb\u0101s Kh\u0101n"
    ],
    "wof:name":"`Abbas Khan",
    "wof:placetype":"locality"
},
  "geometry": {"coordinates":[47.61278,33.79389],"type":"Point"}
}