{
  "type": "Feature",
  "properties": {
    "gn:admin1_code":"4.0",
    "gn:asciiname":"Shiru Bazar",
    "gn:country_code":"IR",
    "gn:dem":24,
    "gn:feature_class":"P",
    "gn:feature_code":"PPL",
    "gn:name":"Sh\u012br\u016b B\u0101z\u0101r",
    "gn:population":0,
    "gn:timezone":"Asia/Tehran",
    "iso:country":"IR",
    "name:fas_x_preferred":[
        "Sh\u012br\u016b B\u0101z\u0101r"
    ],
    "name:fas_x_variant":[
        "\u0634\u06cc\u0631\u0648 \u0628\u0627\u0632\u0627\u0631"
    ],
    "name:und_x_variant":[
        "\u0634\u06cc\u0631\u0648 \u0628\u0627\u0632\u0627\u0631"
    ],
    "wof:name":"Shiru Bazar",
    "wof:placetype":"locality"
},
  "geometry": {"coordinates":[61.16136,25.5373],"type":"Point"}
}