{
  "type": "Feature",
  "properties": {
    "gn:admin1_code":"33",
    "gn:asciiname":"Boledgan",
    "gn:country_code":"IR",
    "gn:dem":1872,
    "gn:feature_class":"P",
    "gn:feature_code":"PPL",
    "gn:name":"Boledg\u0101n",
    "gn:population":0,
    "gn:timezone":"Asia/Tehran",
    "iso:country":"IR",
    "name:azb_x_preferred":[
        "\u0628\u0648\u0644\u0648\u06a9\u0627\u0646"
    ],
    "name:ceb_x_preferred":[
        "Boledg\u0101n"
    ],
    "name:fas_x_preferred":[
        "\u0628\u0644\u062f\u06af\u0627\u0646"
    ],
    "name:fas_x_variant":[
        "Bol\u016bk\u0101n",
        "Boledg\u0101n",
        "\u0628\u0644\u0648\u06a9\u0627\u0646"
    ],
    "name:msa_x_preferred":[
        "Bolukan"
    ],
    "name:swe_x_preferred":[
        "Boledg\u0101n"
    ],
    "wof:name":"Boledgan",
    "wof:placetype":"locality"
},
  "geometry": {"coordinates":[47.4821,37.6584],"type":"Point"}
}