{
  "type": "Feature",
  "properties": {
    "gn:admin1_code":"15",
    "gn:asciiname":"Chapar Khaneh",
    "gn:cc2":"IR",
    "gn:country_code":"IR",
    "gn:dem":77,
    "gn:feature_class":"P",
    "gn:feature_code":"PPL",
    "gn:name":"Chapar Kh\u0101neh",
    "gn:population":0,
    "gn:timezone":"Asia/Tehran",
    "iso:country":"IR",
    "name:fas_x_preferred":[
        "Chapar Kh\u0101neh"
    ],
    "name:fas_x_variant":[
        "\u0686\u0627\u067e\u0627\u0631\u062e\u0627\u0646\u0647"
    ],
    "name:ita_x_preferred":[
        "Chapar Khaneh"
    ],
    "name:mzn_x_preferred":[
        "\u0686\u0627\u067e\u0627\u0631 \u062e\u0646\u0647"
    ],
    "name:por_x_preferred":[
        "Chapar Khaneh"
    ],
    "name:und_x_variant":[
        "Ch\u0101p\u0101rkh\u0101neh-ye Sar"
    ],
    "wof:name":"Chapar Khaneh",
    "wof:placetype":"locality"
},
  "geometry": {"coordinates":[48.75917000000001,32.09639],"type":"Point"}
}