{
  "type": "Feature",
  "properties": {
    "gn:admin1_code":"29",
    "gn:asciiname":"Deldar-e Bala",
    "gn:country_code":"IR",
    "gn:dem":1088,
    "gn:feature_class":"P",
    "gn:feature_code":"PPL",
    "gn:name":"Deldar-e B\u0101l\u0101",
    "gn:population":0,
    "gn:timezone":"Asia/Tehran",
    "iso:country":"IR",
    "name:fas_x_preferred":[
        "\u062f\u0644 \u062f\u0631 \u0628\u0627\u0644\u0627"
    ],
    "name:fas_x_variant":[
        "Deldar-e B\u0101l\u0101"
    ],
    "wof:name":"Deldar-e Bala",
    "wof:placetype":"locality"
},
  "geometry": {"coordinates":[58.20019,26.88932],"type":"Point"}
}