{
  "type": "Feature",
  "properties": {
    "gn:admin1_code":"8",
    "gn:asciiname":"Kul Deh",
    "gn:cc2":"IR",
    "gn:country_code":"IR",
    "gn:dem":63,
    "gn:feature_class":"P",
    "gn:feature_code":"PPL",
    "gn:name":"K\u016bl Deh",
    "gn:population":0,
    "gn:timezone":"Asia/Tehran",
    "iso:country":"IR",
    "name:fas_x_preferred":[
        "K\u016bl Deh"
    ],
    "name:und_x_variant":[
        "Koldeh",
        "Kuldi"
    ],
    "wof:name":"Kul Deh",
    "wof:placetype":"locality"
},
  "geometry": {"coordinates":[49.98333,37.16667],"type":"Point"}
}