{
  "type": "Feature",
  "properties": {
    "gn:admin1_code":"15.0",
    "gn:asciiname":"Seyyed Hoseyn-e Ahmadi",
    "gn:country_code":"IR",
    "gn:dem":43,
    "gn:feature_class":"P",
    "gn:feature_code":"PPL",
    "gn:name":"Seyyed \u1e28oseyn-e A\u1e29mad\u012b",
    "gn:population":0,
    "gn:timezone":"Asia/Tehran",
    "iso:country":"IR",
    "name:fas_x_preferred":[
        "\u0633\u06cc\u0651\u062f \u062d\u0633\u06cc\u0646"
    ],
    "name:fas_x_variant":[
        "Seyyed \u1e28oseyn",
        "\u0633\u06cc\u062f \u062d\u0633\u06cc\u0646 \u0627\u062d\u0645\u062f\u06cc"
    ],
    "name:und_x_variant":[
        "Seyyed \u1e28oseyn",
        "Seyyed \u1e28oseyn-e A\u1e29mad\u012b"
    ],
    "wof:name":"Seyyed Hoseyn-e Ahmadi",
    "wof:placetype":"locality"
},
  "geometry": {"coordinates":[48.42337,31.94195],"type":"Point"}
}