{
  "type": "Feature",
  "properties": {
    "gn:admin1_code":"8",
    "gn:asciiname":"Gachehvar",
    "gn:country_code":"IR",
    "gn:dem":-4,
    "gn:feature_class":"P",
    "gn:feature_code":"PPL",
    "gn:name":"G\u0101chehvar",
    "gn:population":0,
    "gn:timezone":"Asia/Tehran",
    "iso:country":"IR",
    "name:fas_x_preferred":[
        "G\u0101chehvar"
    ],
    "name:fas_x_variant":[
        "\u06af\u0627\u0686\u0647 \u0648\u0631",
        "\u06af\u0627\u0686\u0647\u200c\u0648\u0631"
    ],
    "name:msa_x_preferred":[
        "Gachehvar"
    ],
    "wof:name":"Gachehvar",
    "wof:placetype":"locality"
},
  "geometry": {"coordinates":[50.07111,37.23021],"type":"Point"}
}