{
  "type": "Feature",
  "properties": {
    "gn:admin1_code":"1",
    "gn:asciiname":"`Ali Yara",
    "gn:country_code":"IR",
    "gn:dem":1635,
    "gn:feature_class":"P",
    "gn:feature_code":"PPL",
    "gn:name":"\u2018Al\u012b Y\u0101r\u0101",
    "gn:population":0,
    "gn:timezone":"Asia/Tehran",
    "iso:country":"IR",
    "name:fas_x_preferred":[
        "\u0639\u064e\u0644\u06cc \u064a\u0627\u0631"
    ],
    "name:fas_x_variant":[
        "\u0639\u0644\u06cc \u06cc\u0627\u0631\u0627",
        "\u2018Al\u012b Y\u0101r",
        "\u2018Al\u012b Y\u0101r\u0101"
    ],
    "wof:name":"`Ali Yara",
    "wof:placetype":"locality"
},
  "geometry": {"coordinates":[44.7319,39.1117],"type":"Point"}
}