{
  "type": "Feature",
  "properties": {
    "gn:admin1_code":"29",
    "gn:asciiname":"Hushfat",
    "gn:country_code":"IR",
    "gn:dem":805,
    "gn:feature_class":"P",
    "gn:feature_code":"PPLF",
    "gn:name":"H\u016bshfat",
    "gn:population":0,
    "gn:timezone":"Asia/Tehran",
    "iso:country":"IR",
    "name:fas_x_preferred":[
        "\u0647\u0648\u0634\u0641\u062a"
    ],
    "name:fas_x_variant":[
        "H\u016bshfat"
    ],
    "wof:name":"Hushfat",
    "wof:placetype":"locality"
},
  "geometry": {"coordinates":[58.60195,28.19029],"type":"Point"}
}