{
  "type": "Feature",
  "properties": {
    "gn:admin1_code":"34.0",
    "gn:asciiname":"Arqadeh",
    "gn:country_code":"IR",
    "gn:dem":1585,
    "gn:feature_class":"P",
    "gn:feature_code":"PPL",
    "gn:name":"Arqadeh",
    "gn:population":0,
    "gn:timezone":"Asia/Tehran",
    "iso:country":"IR",
    "name:fas_x_preferred":[
        "\u0627\u064e\u0631\u06af\u064f\u062f\u0650\u0647"
    ],
    "name:fas_x_variant":[
        "\u0627\u064e\u0631\u064e\u063a\u062f\u0650\u0647",
        "\u0627\u064e\u0631\u064e\u0642\u062f\u0650\u0647",
        "\u0627\u0631\u0642\u062f\u0647"
    ],
    "name:ukr_x_preferred":[
        "\u0410\u0440\u043a\u0430\u0434\u0435"
    ],
    "name:und_x_variant":[
        "Argodeh",
        "Araghdeh",
        "Araqdeh",
        "Arqadeh"
    ],
    "wof:name":"Arqadeh",
    "wof:placetype":"locality"
},
  "geometry": {"coordinates":[50.41641,33.80054000000001],"type":"Point"}
}