{
  "type": "Feature",
  "properties": {
    "gn:admin1_code":"23",
    "gn:asciiname":"Emamzadeh Qasem",
    "gn:country_code":"IR",
    "gn:dem":1965,
    "gn:feature_class":"P",
    "gn:feature_code":"PPL",
    "gn:name":"Em\u0101mz\u0101deh Q\u0101sem",
    "gn:population":0,
    "gn:timezone":"Asia/Tehran",
    "iso:country":"IR",
    "name:fas_x_preferred":[
        "\u0627\u0650\u0645\u064e\u0645\u0632\u064e\u062f\u0650\u0647 \u063a\u064e\u0633\u0650\u0645"
    ],
    "name:fas_x_variant":[
        "Em\u0101mz\u0101deh Q\u0101sem",
        "\u0627\u0645\u0627\u0645\u0632\u0627\u062f\u0647 \u0642\u0627\u0633\u0645"
    ],
    "name:und_x_variant":[
        "Im\u0101mz\u0101deh Q\u0101sim",
        "Emamzadeh Ghasem"
    ],
    "wof:name":"Emamzadeh Qasem",
    "wof:placetype":"locality"
},
  "geometry": {"coordinates":[49.51234,33.67009],"type":"Point"}
}