{
  "type": "Feature",
  "properties": {
    "gn:admin1_code":"40",
    "gn:asciiname":"Gidistan",
    "gn:country_code":"IR",
    "gn:dem":2567,
    "gn:feature_class":"P",
    "gn:feature_code":"PPL",
    "gn:name":"Gidist\u0101n",
    "gn:population":0,
    "gn:timezone":"Asia/Tehran",
    "iso:country":"IR",
    "name:fas_x_preferred":[
        "Gidist\u0101n"
    ],
    "wof:name":"Gidistan",
    "wof:placetype":"locality"
},
  "geometry": {"coordinates":[53.65,31.68333],"type":"Point"}
}