{
  "type": "Feature",
  "properties": {
    "gn:admin1_code":"41.0",
    "gn:asciiname":"Hamand",
    "gn:country_code":"IR",
    "gn:dem":1670,
    "gn:feature_class":"P",
    "gn:feature_code":"PPL",
    "gn:name":"Hamand",
    "gn:population":0,
    "gn:timezone":"Asia/Tehran",
    "iso:country":"IR",
    "name:fas_x_preferred":[
        "\u0647\u0645\u0646\u062f"
    ],
    "name:und_x_variant":[
        "Homand",
        "Hamand"
    ],
    "wof:name":"Hamand",
    "wof:placetype":"locality"
},
  "geometry": {"coordinates":[60.01095,31.77081],"type":"Point"}
}