{
  "type": "Feature",
  "properties": {
    "gn:admin1_code":"40.0",
    "gn:asciiname":"Qal`eh Chah Bolagh",
    "gn:country_code":"IR",
    "gn:dem":1558,
    "gn:feature_class":"P",
    "gn:feature_code":"PPL",
    "gn:name":"Qal\u2018eh Ch\u0101h Bol\u0101gh",
    "gn:population":0,
    "gn:timezone":"Asia/Tehran",
    "iso:country":"IR",
    "name:fas_x_preferred":[
        "Qal\u2018eh Ch\u0101h Bol\u0101gh"
    ],
    "name:fas_x_variant":[
        "\u0642\u0644\u0639\u0647 \u0686\u0627\u0647 \u0628\u0644\u0627\u063a"
    ],
    "wof:name":"Qal`eh Chah Bolagh",
    "wof:placetype":"locality"
},
  "geometry": {"coordinates":[53.08598000000001,31.21194],"type":"Point"}
}