{
  "type": "Feature",
  "properties": {
    "gn:admin1_code":"29",
    "gn:asciiname":"Mehru'iyeh-ye Pa'in",
    "gn:country_code":"IR",
    "gn:dem":649,
    "gn:feature_class":"P",
    "gn:feature_code":"PPL",
    "gn:name":"Mehr\u016b\u2019\u012byeh-ye P\u0101\u2019\u012bn",
    "gn:population":0,
    "gn:timezone":"Asia/Tehran",
    "iso:country":"IR",
    "name:fas_x_preferred":[
        "\u0645\u0647\u0631\u0648\u06cc\u0647"
    ],
    "name:fas_x_variant":[
        "Mehr\u016b\u2019\u012byeh",
        "Mehr\u016byeh",
        "\u0645\u0647\u0631\u0648\u0626\u064a\u0647 \u067e\u0627\u0626\u064a\u0646"
    ],
    "name:und_x_variant":[
        "M\u0101hru",
        "Mehr\u016b\u2019\u012byeh-ye P\u0101\u2019\u012bn",
        "Mahr\u016b\u2019\u012byeh-ye B\u0101l\u0101",
        "Mahr\u016b\u2019\u012byeh"
    ],
    "wof:name":"Mehru'iyeh-ye Pa'in",
    "wof:placetype":"locality"
},
  "geometry": {"coordinates":[57.40791,28.09242],"type":"Point"}
}