{
  "type": "Feature",
  "properties": {
    "gn:admin1_code":"15.0",
    "gn:asciiname":"Moribi",
    "gn:country_code":"IR",
    "gn:dem":41,
    "gn:feature_class":"P",
    "gn:feature_code":"PPL",
    "gn:name":"Mor\u012bb\u012b",
    "gn:population":0,
    "gn:timezone":"Asia/Tehran",
    "iso:country":"IR",
    "name:fas_x_preferred":[
        "\u0645\u0631\u0627\u0628\u06cc"
    ],
    "name:fas_x_variant":[
        "Mor\u0101b\u012b",
        "\u0645\u0631\u06cc\u0628\u06cc"
    ],
    "name:und_x_variant":[
        "Mor\u012bb\u012b"
    ],
    "wof:name":"Moribi",
    "wof:placetype":"locality"
},
  "geometry": {"coordinates":[49.46487,31.03875],"type":"Point"}
}