{
  "type": "Feature",
  "properties": {
    "gn:admin1_code":"42",
    "gn:asciiname":"Ferezq",
    "gn:country_code":"IR",
    "gn:dem":1421,
    "gn:feature_class":"P",
    "gn:feature_code":"PPL",
    "gn:name":"Ferezq",
    "gn:population":0,
    "gn:timezone":"Asia/Tehran",
    "iso:country":"IR",
    "name:fas_x_preferred":[
        "\u0641\u0631\u0632\u0642"
    ],
    "wof:name":"Ferezq",
    "wof:placetype":"locality"
},
  "geometry": {"coordinates":[59.21974,35.31478],"type":"Point"}
}