{
  "type": "Feature",
  "properties": {
    "gn:admin1_code":"4.0",
    "gn:asciiname":"Siah Tefaq",
    "gn:country_code":"IR",
    "gn:dem":1380,
    "gn:feature_class":"P",
    "gn:feature_code":"PPL",
    "gn:name":"S\u012b\u0101h Tef\u0101q",
    "gn:population":0,
    "gn:timezone":"Asia/Tehran",
    "iso:country":"IR",
    "name:fas_x_preferred":[
        "\u0633\u064a\u0627\u0647 \u062a\u0641\u0627\u0642"
    ],
    "name:fas_x_variant":[
        "S\u012b\u0101h Ettef\u0101q-e P\u0101\u2019\u012bn",
        "S\u012b\u0101h Tef\u0101q"
    ],
    "wof:name":"Siah Tefaq",
    "wof:placetype":"locality"
},
  "geometry": {"coordinates":[61.40075,27.24808],"type":"Point"}
}