{
  "type": "Feature",
  "properties": {
    "gn:admin1_code":"40",
    "gn:asciiname":"Rabi`abad",
    "gn:country_code":"IR",
    "gn:dem":2399,
    "gn:feature_class":"P",
    "gn:feature_code":"PPL",
    "gn:name":"Rab\u012b\u2018\u0101b\u0101d",
    "gn:population":0,
    "gn:timezone":"Asia/Tehran",
    "iso:country":"IR",
    "name:fas_x_preferred":[
        "Rab\u012b\u2018\u0101b\u0101d"
    ],
    "name:fas_x_variant":[
        "\u0631\u0628\u064a\u0639 \u0622\u0628\u0627\u062f"
    ],
    "wof:name":"Rabi`abad",
    "wof:placetype":"locality"
},
  "geometry": {"coordinates":[54.24844,31.43631],"type":"Point"}
}