{
  "type": "Feature",
  "properties": {
    "gn:admin1_code":"8",
    "gn:asciiname":"Delah Khani",
    "gn:country_code":"IR",
    "gn:dem":933,
    "gn:feature_class":"P",
    "gn:feature_code":"PPL",
    "gn:name":"Delah Kh\u0101n\u012b",
    "gn:population":0,
    "gn:timezone":"Asia/Tehran",
    "iso:country":"IR",
    "name:ara_x_preferred":[
        "\u062f\u0644\u0629 \u062e\u0627\u0646\u064a"
    ],
    "name:fas_x_preferred":[
        "Delah Kh\u0101n\u012b"
    ],
    "name:fas_x_variant":[
        "\u062f\u0644\u0647 \u062e\u0627\u0646\u06cc"
    ],
    "name:msa_x_preferred":[
        "Delah Khani"
    ],
    "name:ukr_x_preferred":[
        "\u0414\u0435\u043b\u0435-\u0425\u0430\u043d\u0456"
    ],
    "name:und_x_variant":[
        "Daleh Kh\u0101n\u012b"
    ],
    "wof:name":"Delah Khani",
    "wof:placetype":"locality"
},
  "geometry": {"coordinates":[49.05265,37.1486],"type":"Point"}
}