{
  "type": "Feature",
  "properties": {
    "gn:admin1_code":"29",
    "gn:asciiname":"Chah Dahir",
    "gn:country_code":"IR",
    "gn:dem":1604,
    "gn:feature_class":"P",
    "gn:feature_code":"PPL",
    "gn:name":"Ch\u0101h Dah\u012br",
    "gn:population":0,
    "gn:timezone":"Asia/Tehran",
    "iso:country":"IR",
    "name:fas_x_preferred":[
        "\u0686\u0627\u0647 \u062f\u0647\u06cc\u0631"
    ],
    "name:fas_x_variant":[
        "Ch\u0101h Dah\u012br"
    ],
    "wof:name":"Chah Dahir",
    "wof:placetype":"locality"
},
  "geometry": {"coordinates":[56.8468,28.2906],"type":"Point"}
}