{
  "type": "Feature",
  "properties": {
    "gn:admin1_code":"40",
    "gn:asciiname":"Gongu",
    "gn:country_code":"IR",
    "gn:dem":1782,
    "gn:feature_class":"P",
    "gn:feature_code":"PPL",
    "gn:name":"Gong\u016b",
    "gn:population":0,
    "gn:timezone":"Asia/Tehran",
    "iso:country":"IR",
    "name:ara_x_preferred":[
        "\u063a\u0646 \u063a\u0627\u0648"
    ],
    "name:fas_x_preferred":[
        "\u06af\u0650\u0646\u0650\u06af\u0627\u0648"
    ],
    "name:fas_x_variant":[
        "Geneg\u0101v",
        "\u06af\u0646\u06af\u0648",
        "\u06af\u0646 \u06af\u0627\u0648"
    ],
    "name:und_x_variant":[
        "Gong\u016b"
    ],
    "wof:name":"Gongu",
    "wof:placetype":"locality"
},
  "geometry": {"coordinates":[55.99423,31.80009],"type":"Point"}
}