{
  "type": "Feature",
  "properties": {
    "gn:admin1_code":"15",
    "gn:asciiname":"Qaryeh-ye Teymur",
    "gn:country_code":"IR",
    "gn:dem":1327,
    "gn:feature_class":"P",
    "gn:feature_code":"PPL",
    "gn:name":"Qaryeh-ye Teym\u016br",
    "gn:population":0,
    "gn:timezone":"Asia/Tehran",
    "iso:country":"IR",
    "name:azb_x_preferred":[
        "\u0642\u0631\u06cc\u0647 \u062a\u06cc\u0645\u0648\u0631(\u0627\u06cc\u0630\u0647)"
    ],
    "name:ceb_x_preferred":[
        "Qaryeh-ye Teym\u016br"
    ],
    "name:fas_x_preferred":[
        "Qaryeh-ye Teym\u016br"
    ],
    "name:fas_x_variant":[
        "\u0642\u0631\u06cc\u0647\u200c\u062a\u06cc\u0645\u0648\u0631"
    ],
    "name:swe_x_preferred":[
        "Qaryeh-ye Teym\u016br"
    ],
    "wof:name":"Qaryeh-ye Teymur",
    "wof:placetype":"locality"
},
  "geometry": {"coordinates":[50.03111,31.96306],"type":"Point"}
}