{
  "type": "Feature",
  "properties": {
    "gn:admin1_code":"15",
    "gn:asciiname":"Qaryeh-ye Teymur",
    "gn:country_code":"IR",
    "gn:dem":1327,
    "gn:feature_class":"P",
    "gn:feature_code":"PPL",
    "gn:name":"Qaryeh-ye Teym\u016br",
    "gn:population":0,
    "gn:timezone":"Asia/Tehran",
    "iso:country":"IR",
    "name:fas_x_preferred":[
        "Qaryeh-ye Teym\u016br"
    ],
    "wof:name":"Qaryeh-ye Teymur",
    "wof:placetype":"locality"
},
  "geometry": {"coordinates":[50.03111,31.96306],"type":"Point"}
}