{
  "type": "Feature",
  "properties": {
    "gn:admin1_code":"42.0",
    "gn:asciiname":"Dezg",
    "gn:country_code":"IR",
    "gn:dem":1712,
    "gn:feature_class":"P",
    "gn:feature_code":"PPL",
    "gn:name":"Dezg",
    "gn:population":0,
    "gn:timezone":"Asia/Tehran",
    "iso:country":"IR",
    "name:fas_x_preferred":[
        "Qal\u2018eh Dijag"
    ],
    "name:fas_x_variant":[
        "\u062f\u0632\u06af",
        "Dezg-e B\u0101l\u0101",
        "\u062f\u0632\u06af \u0628\u0627\u0644\u0627"
    ],
    "name:und_x_variant":[
        "Dozq",
        "Desok",
        "Dezak",
        "Dezq",
        "Dezg"
    ],
    "wof:name":"Dezg",
    "wof:placetype":"locality"
},
  "geometry": {"coordinates":[60.09693000000001,33.34047],"type":"Point"}
}