{
  "type": "Feature",
  "properties": {
    "gn:admin1_code":"4.0",
    "gn:asciiname":"Valiabad",
    "gn:country_code":"IR",
    "gn:dem":1341,
    "gn:feature_class":"P",
    "gn:feature_code":"PPL",
    "gn:name":"Val\u012b\u0101b\u0101d",
    "gn:population":0,
    "gn:timezone":"Asia/Tehran",
    "iso:country":"IR",
    "name:fas_x_preferred":[
        "Val\u012b\u0101b\u0101d"
    ],
    "name:fas_x_variant":[
        "\u0648\u0644\u06cc\u200c\u0622\u0628\u0627\u062f"
    ],
    "wof:name":"Valiabad",
    "wof:placetype":"locality"
},
  "geometry": {"coordinates":[60.41667,28.33333],"type":"Point"}
}