{
  "type": "Feature",
  "properties": {
    "gn:admin1_code":"29",
    "gn:asciiname":"Shahrak-e Arg-e Jadid-e Bam",
    "gn:country_code":"IR",
    "gn:dem":925,
    "gn:feature_class":"P",
    "gn:feature_code":"PPL",
    "gn:name":"Shahrak-e Arg-e Jad\u012bd-e Bam",
    "gn:population":0,
    "gn:timezone":"Asia/Tehran",
    "iso:country":"IR",
    "name:fas_x_preferred":[
        "\u0645\u062c\u062a\u0645\u0639 \u0645\u0633\u06a9\u0648\u0646\u06cc \u0635\u062f\u0641"
    ],
    "name:fas_x_variant":[
        "Mojtame\u2018-e Mask\u016bn\u012b-ye \u015eadaf",
        "\u0634\u0647\u0631\u06a9 \u0627\u0631\u06af \u062c\u062f\u064a\u062f \u0628\u0645"
    ],
    "name:und_x_variant":[
        "Shahrak-e Arg-e Jad\u012bd-e Bam"
    ],
    "wof:name":"Shahrak-e Arg-e Jadid-e Bam",
    "wof:placetype":"locality"
},
  "geometry": {"coordinates":[58.4705,29.0314],"type":"Point"}
}