{
  "type": "Feature",
  "properties": {
    "gn:admin1_code":"8",
    "gn:asciiname":"Darreh Vari",
    "gn:country_code":"IR",
    "gn:dem":23,
    "gn:feature_class":"P",
    "gn:feature_code":"PPL",
    "gn:name":"Darreh V\u0101r\u012b",
    "gn:population":0,
    "gn:timezone":"Asia/Tehran",
    "iso:country":"IR",
    "name:fas_x_preferred":[
        "\u062f\u0631\u0647 \u0648\u0627\u0631\u06cc"
    ],
    "name:fas_x_variant":[
        "Darrehv\u0101r Ma\u1e29alleh-ye Ch\u016bbar",
        "Darreh V\u0101r\u012b"
    ],
    "wof:name":"Darreh Vari",
    "wof:placetype":"locality"
},
  "geometry": {"coordinates":[48.877,38.165],"type":"Point"}
}