{
  "type": "Feature",
  "properties": {
    "gn:admin1_code":"9",
    "gn:asciiname":"Garak",
    "gn:country_code":"IR",
    "gn:dem":1760,
    "gn:feature_class":"P",
    "gn:feature_code":"PPL",
    "gn:name":"Garak",
    "gn:population":0,
    "gn:timezone":"Asia/Tehran",
    "iso:country":"IR",
    "name:ceb_x_preferred":[
        "Garak"
    ],
    "name:fas_x_preferred":[
        "\u06af\u0631\u06a9"
    ],
    "name:swe_x_preferred":[
        "Garak"
    ],
    "name:und_x_variant":[
        "Garrak",
        "Gorg"
    ],
    "wof:name":"Garak",
    "wof:placetype":"locality"
},
  "geometry": {"coordinates":[48.45655,34.0599],"type":"Point"}
}