{
  "type": "Feature",
  "properties": {
    "gn:admin1_code":"16.0",
    "gn:asciiname":"Kani Sefid",
    "gn:country_code":"IR",
    "gn:dem":1714,
    "gn:feature_class":"P",
    "gn:feature_code":"PPL",
    "gn:name":"K\u0101n\u012b Sef\u012bd",
    "gn:population":0,
    "gn:timezone":"Asia/Tehran",
    "iso:country":"IR",
    "name:ckb_x_preferred":[
        "\u06a9\u0627\u0646\u06cc \u0633\u067e\u06cc"
    ],
    "name:fas_x_preferred":[
        "\u06a9\u0627\u0646\u06cc \u0633\u0641\u06cc\u062f"
    ],
    "name:fas_x_variant":[
        "K\u0101n\u012b Sef\u012bd",
        "\u06a9\u0627\u0646\u06cc\u200c\u0633\u0641\u06cc\u062f"
    ],
    "name:kur_x_preferred":[
        "Kan\u00eesp\u00ee"
    ],
    "wof:name":"Kani Sefid",
    "wof:placetype":"locality"
},
  "geometry": {"coordinates":[45.987,36.2242],"type":"Point"}
}