{
  "type": "Feature",
  "properties": {
    "gn:admin1_code":"40.0",
    "gn:asciiname":"Mazra`eh-ye Qods",
    "gn:country_code":"IR",
    "gn:dem":1749,
    "gn:feature_class":"P",
    "gn:feature_code":"PPLF",
    "gn:name":"Mazra\u2018eh-ye Qods",
    "gn:population":0,
    "gn:timezone":"Asia/Tehran",
    "iso:country":"IR",
    "name:fas_x_preferred":[
        "Ch\u0101h Qods"
    ],
    "name:fas_x_variant":[
        "\u0686\u0627\u0647 \u0642\u062f\u0633",
        "\u0645\u0632\u0631\u0639\u0647 \u0642\u062f\u0633",
        "\u06af\u0631\u0648\u0647 \u06a9\u0634\u0627\u0648\u0631\u0632\u06cc \u0642\u062f\u0633"
    ],
    "name:und_x_variant":[
        "Mazra\u2018eh-ye Qods",
        "Gor\u016bh-e Kesh\u0101varz\u012b-ye Qods"
    ],
    "wof:name":"Mazra`eh-ye Qods",
    "wof:placetype":"locality"
},
  "geometry": {"coordinates":[54.32362,29.88029],"type":"Point"}
}