{
  "type": "Feature",
  "properties": {
    "gn:admin1_code":"33",
    "gn:asciiname":"Qeshlaq",
    "gn:country_code":"IR",
    "gn:dem":1278,
    "gn:feature_class":"P",
    "gn:feature_code":"PPL",
    "gn:name":"Qeshl\u0101q",
    "gn:population":0,
    "gn:timezone":"Asia/Tehran",
    "iso:country":"IR",
    "name:fas_x_preferred":[
        "Qeshl\u0101q"
    ],
    "name:fas_x_variant":[
        "Qeshl\u0101q-e P\u012b\u0101z\u012b",
        "\u0642\u0634\u0644\u0627\u0642"
    ],
    "name:und_x_variant":[
        "\u0642\u0634\u0644\u0627\u0642"
    ],
    "wof:name":"Qeshlaq",
    "wof:placetype":"locality"
},
  "geometry": {"coordinates":[45.871,37.7731],"type":"Point"}
}