{
  "type": "Feature",
  "properties": {
    "gn:admin1_code":"33",
    "gn:asciiname":"Maranu",
    "gn:country_code":"IR",
    "gn:dem":1580,
    "gn:feature_class":"P",
    "gn:feature_code":"PPL",
    "gn:name":"Maran\u016b",
    "gn:population":0,
    "gn:timezone":"Asia/Tehran",
    "iso:country":"IR",
    "name:fas_x_preferred":[
        "\u0645\u0631\u0646\u0627\u0628"
    ],
    "name:fas_x_variant":[
        "Marn\u0101b",
        "\u0645\u0631\u0646\u0648"
    ],
    "name:und_x_variant":[
        "Maran\u016b"
    ],
    "wof:name":"Maranu",
    "wof:placetype":"locality"
},
  "geometry": {"coordinates":[46.4423,38.1783],"type":"Point"}
}