{
  "type": "Feature",
  "properties": {
    "gn:admin1_code":"7.0",
    "gn:asciiname":"Safadeh",
    "gn:country_code":"IR",
    "gn:dem":995,
    "gn:feature_class":"P",
    "gn:feature_code":"PPL",
    "gn:name":"Saf\u0101deh",
    "gn:population":0,
    "gn:timezone":"Asia/Tehran",
    "iso:country":"IR",
    "name:fas_x_preferred":[
        "Saf\u0101deh"
    ],
    "wof:name":"Safadeh",
    "wof:placetype":"locality"
},
  "geometry": {"coordinates":[53.05167,28.65028],"type":"Point"}
}