{
  "type": "Feature",
  "properties": {
    "gn:admin1_code":"23",
    "gn:asciiname":"Shah Valeh",
    "gn:country_code":"IR",
    "gn:dem":1983,
    "gn:feature_class":"P",
    "gn:feature_code":"PPL",
    "gn:name":"Sh\u0101h Valeh",
    "gn:population":0,
    "gn:timezone":"Asia/Tehran",
    "iso:country":"IR",
    "name:ceb_x_preferred":[
        "Sh\u0101h Valeh"
    ],
    "name:fas_x_preferred":[
        "\u0634\u0627\u0647 \u0648\u0644\u0647"
    ],
    "name:fas_x_variant":[
        "Sh\u0101hveleh",
        "Sh\u0101h Valeh",
        "\u0634\u0627\u0647\u0648\u0644\u0647"
    ],
    "name:swe_x_preferred":[
        "Sh\u0101h Valeh"
    ],
    "name:und_x_variant":[
        "Sh\u0101h Val\u012b",
        "Sh\u0101h Waleh",
        "Sh\u0101h Valad"
    ],
    "wof:name":"Shah Valeh",
    "wof:placetype":"locality"
},
  "geometry": {"coordinates":[49.4389,33.57495],"type":"Point"}
}