{
  "type": "Feature",
  "properties": {
    "gn:admin1_code":"37.0",
    "gn:asciiname":"Mohammad-e Farabi",
    "gn:country_code":"IR",
    "gn:dem":49,
    "gn:feature_class":"P",
    "gn:feature_code":"PPL",
    "gn:name":"Mo\u1e29ammad-e F\u0101r\u0101b\u012b",
    "gn:population":0,
    "gn:timezone":"Asia/Tehran",
    "iso:country":"IR",
    "name:fas_x_preferred":[
        "Mo\u1e29ammad-e F\u0101r\u0101b\u012b"
    ],
    "wof:name":"Mohammad-e Farabi",
    "wof:placetype":"locality"
},
  "geometry": {"coordinates":[55.25,37.25],"type":"Point"}
}