{
  "type": "Feature",
  "properties": {
    "gn:admin1_code":"35.0",
    "gn:asciiname":"Kolah Safa",
    "gn:country_code":"IR",
    "gn:dem":38,
    "gn:feature_class":"P",
    "gn:feature_code":"PPL",
    "gn:name":"Kolah \u015eaf\u0101",
    "gn:population":0,
    "gn:timezone":"Asia/Tehran",
    "iso:country":"IR",
    "name:fas_x_preferred":[
        "\u0643\u064f\u0644\u064e\u0647 \u0635\u064e\u0641\u0627"
    ],
    "name:fas_x_variant":[
        "Kolah \u015eaf\u0101"
    ],
    "wof:name":"Kolah Safa",
    "wof:placetype":"locality"
},
  "geometry": {"coordinates":[52.33333,36.51667],"type":"Point"}
}