{
  "type": "Feature",
  "properties": {
    "gn:admin1_code":"16.0",
    "gn:asciiname":"Masidar-e `Olya",
    "gn:country_code":"IR",
    "gn:dem":1646,
    "gn:feature_class":"P",
    "gn:feature_code":"PPL",
    "gn:name":"M\u0101s\u012bdar-e \u2018Oly\u0101",
    "gn:population":0,
    "gn:timezone":"Asia/Tehran",
    "iso:country":"IR",
    "name:fas_x_preferred":[
        "\u0645\u0627\u0633\u06cc\u062f\u0631 \u0639\u0644\u06cc\u0627"
    ],
    "name:fas_x_variant":[
        "M\u0101s\u012bdar-e \u2018Oly\u0101"
    ],
    "wof:name":"Masidar-e `Olya",
    "wof:placetype":"locality"
},
  "geometry": {"coordinates":[46.4658,36.0037],"type":"Point"}
}