{
  "type": "Feature",
  "properties": {
    "gn:admin1_code":"7",
    "gn:asciiname":"Bidak",
    "gn:country_code":"IR",
    "gn:dem":1470,
    "gn:feature_class":"P",
    "gn:feature_code":"PPL",
    "gn:name":"B\u012bdak",
    "gn:population":0,
    "gn:timezone":"Asia/Tehran",
    "iso:country":"IR",
    "name:fas_x_preferred":[
        "B\u012bdak"
    ],
    "wof:name":"Bidak",
    "wof:placetype":"locality"
},
  "geometry": {"coordinates":[52.64,29.49],"type":"Point"}
}