{
  "type": "Feature",
  "properties": {
    "gn:admin1_code":"8",
    "gn:asciiname":"Laseh Posht",
    "gn:country_code":"IR",
    "gn:dem":2331,
    "gn:feature_class":"P",
    "gn:feature_code":"PPL",
    "gn:name":"L\u0101seh Posht",
    "gn:population":0,
    "gn:timezone":"Asia/Tehran",
    "iso:country":"IR",
    "name:fas_x_preferred":[
        "\u0633\u0646\u06af \u0628\u0646"
    ],
    "name:fas_x_variant":[
        "\u0644\u0627\u0633\u0647 \u067e\u0634\u062a"
    ],
    "name:und_x_variant":[
        "Sang Bon",
        "L\u0101seh Posht"
    ],
    "wof:name":"Laseh Posht",
    "wof:placetype":"locality"
},
  "geometry": {"coordinates":[49.11094,37.04016],"type":"Point"}
}