{
  "type": "Feature",
  "properties": {
    "gn:admin1_code":"26.0",
    "gn:asciiname":"Hamand",
    "gn:country_code":"IR",
    "gn:dem":2050,
    "gn:feature_class":"P",
    "gn:feature_code":"PPL",
    "gn:name":"Hamand",
    "gn:population":0,
    "gn:timezone":"Asia/Tehran",
    "iso:country":"IR",
    "name:fas_x_preferred":[
        "\u0647\u0648\u0645\u064e\u0646\u062f"
    ],
    "name:fas_x_variant":[
        "H\u016bmand",
        "\u0647\u0645\u0646\u062f"
    ],
    "wof:name":"Hamand",
    "wof:placetype":"locality"
},
  "geometry": {"coordinates":[52.17868,35.65247],"type":"Point"}
}