{
  "type": "Feature",
  "properties": {
    "gn:admin1_code":"37.0",
    "gn:asciiname":"Ghoznavi",
    "gn:country_code":"IR",
    "gn:dem":962,
    "gn:feature_class":"P",
    "gn:feature_code":"PPL",
    "gn:name":"Ghoznav\u012b",
    "gn:population":0,
    "gn:timezone":"Asia/Tehran",
    "iso:country":"IR",
    "name:fas_x_preferred":[
        "\u063a\u064f\u0632\u0646\u064e\u0648\u06cc"
    ],
    "wof:name":"Ghoznavi",
    "wof:placetype":"locality"
},
  "geometry": {"coordinates":[55.45,36.93333],"type":"Point"}
}