{
  "type": "Feature",
  "properties": {
    "gn:admin1_code":"11",
    "gn:asciiname":"Mehr Jushan",
    "gn:country_code":"IR",
    "gn:dem":1545,
    "gn:feature_class":"P",
    "gn:feature_code":"PPL",
    "gn:name":"Mehr J\u016bsh\u0101n",
    "gn:population":0,
    "gn:timezone":"Asia/Tehran",
    "iso:country":"IR",
    "name:fas_x_preferred":[
        "\u0645\u0647\u0631 \u062e\u0648\u0634\u0627\u0646"
    ],
    "name:fas_x_variant":[
        "\u0645\u064e\u0647\u0631 \u0631\u064e\u0643\u0634\u0627\u0646",
        "\u0645\u0650\u0647\u0631 \u0631\u064e\u062e\u0634\u0627\u0646",
        "\u0645\u0650\u0647\u0631 \u0631\u0627\u0643\u064a\u0634\u0627\u0646",
        "\u0645\u064e\u0647\u0631 \u0631\u064e\u062e\u0634\u0627\u0646",
        "\u0645\u0650\u0647\u0631 \u0628\u064e\u062e\u0634\u0627\u0646",
        "\u0645\u0647\u0631 \u062c\u0648\u0634\u0627\u0646",
        "Mehr Khowsh\u0101n",
        "Mehr J\u016bsh\u0101n",
        "\u0645\u0647\u0631\u062e\u0648\u0634\u0627\u0646"
    ],
    "name:msa_x_preferred":[
        "Mehr Khowshan"
    ],
    "name:und_x_variant":[
        "Mahr Raksh\u0101n",
        "Mehr Rakhsh\u0101n",
        "Mahr Rakhsh\u0101n",
        "Mehr Bakhsh\u0101n",
        "Mehr R\u0101k\u012bsh\u0101n"
    ],
    "wof:name":"Mehr Jushan",
    "wof:placetype":"locality"
},
  "geometry": {"coordinates":[55.5902,28.6461],"type":"Point"}
}