{
  "type": "Feature",
  "properties": {
    "gn:admin1_code":"15.0",
    "gn:asciiname":"Rahimi-ye Seh",
    "gn:country_code":"IR",
    "gn:dem":12,
    "gn:feature_class":"P",
    "gn:feature_code":"PPL",
    "gn:name":"Ra\u1e29\u012bm\u012b-ye Seh",
    "gn:population":0,
    "gn:timezone":"Asia/Tehran",
    "iso:country":"IR",
    "name:fas_x_preferred":[
        "\u0631\u062d\u06cc\u0645\u06cc \u0633\u0647"
    ],
    "name:fas_x_variant":[
        "Ra\u1e29\u012bm\u012b-ye Seh",
        "\u062f\u062d\u06cc\u0645\u06cc \u0633\u0647"
    ],
    "name:und_x_variant":[
        "Da\u1e29\u012bm\u012b-ye Seh"
    ],
    "wof:name":"Rahimi-ye Seh",
    "wof:placetype":"locality"
},
  "geometry": {"coordinates":[48.0516,31.606],"type":"Point"}
}