{
  "type": "Feature",
  "properties": {
    "gn:admin1_code":"29",
    "gn:asciiname":"Khora'iyeh",
    "gn:country_code":"IR",
    "gn:dem":2103,
    "gn:feature_class":"P",
    "gn:feature_code":"PPL",
    "gn:name":"Khor\u0101\u2019\u012byeh",
    "gn:population":0,
    "gn:timezone":"Asia/Tehran",
    "iso:country":"IR",
    "name:fas_x_preferred":[
        "\u062e\u0631\u0627\u0626\u06cc\u0647"
    ],
    "name:fas_x_variant":[
        "Khor\u0101\u2019",
        "Khor\u0101\u2019\u012byeh"
    ],
    "name:und_x_variant":[
        "Kh\u0101r\u0101"
    ],
    "wof:name":"Khora'iyeh",
    "wof:placetype":"locality"
},
  "geometry": {"coordinates":[56.5119,29.1144],"type":"Point"}
}