{
  "type": "Feature",
  "properties": {
    "gn:admin1_code":"4",
    "gn:asciiname":"Shekahem",
    "gn:cc2":"IR",
    "gn:country_code":"IR",
    "gn:dem":584,
    "gn:feature_class":"P",
    "gn:feature_code":"PPL",
    "gn:name":"Shek\u0101hem",
    "gn:population":0,
    "gn:timezone":"Asia/Tehran",
    "iso:country":"IR",
    "name:fas_x_preferred":[
        "Shek\u0101hem"
    ],
    "name:und_x_variant":[
        "Shak\u0101hem"
    ],
    "wof:name":"Shekahem",
    "wof:placetype":"locality"
},
  "geometry": {"coordinates":[59.84,26.36917],"type":"Point"}
}