{
  "type": "Feature",
  "properties": {
    "gn:admin1_code":"29",
    "gn:asciiname":"Chah-e Sahu",
    "gn:country_code":"IR",
    "gn:dem":407,
    "gn:feature_class":"P",
    "gn:feature_code":"PPLL",
    "gn:name":"Ch\u0101h-e Sah\u016b",
    "gn:population":0,
    "gn:timezone":"Asia/Tehran",
    "iso:country":"IR",
    "name:fas_x_preferred":[
        "\u0686\u0627\u0647 \u0633\u0647\u0648"
    ],
    "name:fas_x_variant":[
        "Ch\u0101h-e Sah\u016b"
    ],
    "wof:name":"Chah-e Sahu",
    "wof:placetype":"locality"
},
  "geometry": {"coordinates":[58.12729,27.32862],"type":"Point"}
}