{
  "type": "Feature",
  "properties": {
    "gn:admin1_code":"16.0",
    "gn:asciiname":"Karimabad",
    "gn:country_code":"IR",
    "gn:dem":1617,
    "gn:elevation":"0.0",
    "gn:feature_class":"P",
    "gn:feature_code":"PPL",
    "gn:name":"Kar\u012bm\u0101b\u0101d",
    "gn:population":0,
    "gn:timezone":"Asia/Tehran",
    "iso:country":"IR",
    "name:aze_x_preferred":[
        "K\u0259rimabad"
    ],
    "name:deu_x_preferred":[
        "Karimabad"
    ],
    "name:fas_x_preferred":[
        "\u0643\u064e\u0631\u064a\u0645 \u0622\u0628\u0627\u062f"
    ],
    "name:fas_x_variant":[
        "\u06a9\u0631\u06cc\u0645 \u0622\u0628\u0627\u062f",
        "Kar\u012bm\u0101b\u0101d",
        "\u06a9\u0631\u06cc\u0645\u200c\u0622\u0628\u0627\u062f"
    ],
    "name:ita_x_preferred":[
        "Karimabad"
    ],
    "wof:name":"Karimabad",
    "wof:placetype":"locality"
},
  "geometry": {"coordinates":[45.9153,35.9601],"type":"Point"}
}