{
  "type": "Feature",
  "properties": {
    "gn:admin1_code":"35.0",
    "gn:asciiname":"Rudbast",
    "gn:country_code":"IR",
    "gn:dem":-18,
    "gn:feature_class":"P",
    "gn:feature_code":"PPL",
    "gn:name":"R\u016bdbast",
    "gn:population":0,
    "gn:timezone":"Asia/Tehran",
    "iso:country":"IR",
    "name:fas_x_preferred":[
        "R\u016bdbast"
    ],
    "name:fas_x_variant":[
        "\u0631\u0648\u062f\u0628\u0633\u062a"
    ],
    "wof:name":"Rudbast",
    "wof:placetype":"locality"
},
  "geometry": {"coordinates":[52.59846999999999,36.66791],"type":"Point"}
}