{
  "type": "Feature",
  "properties": {
    "gn:admin1_code":"7.0",
    "gn:asciiname":"Qeshlaq-e Asiyeh Kushk",
    "gn:country_code":"IR",
    "gn:dem":624,
    "gn:feature_class":"P",
    "gn:feature_code":"PPLL",
    "gn:name":"Qeshl\u0101q-e \u0100s\u012byeh K\u016bshk",
    "gn:population":0,
    "gn:timezone":"Asia/Tehran",
    "iso:country":"IR",
    "name:fas_x_preferred":[
        "\u0642\u0634\u0644\u0627\u0642 \u0622\u0633\u06cc\u0647 \u06a9\u0648\u0634\u06a9"
    ],
    "name:und_x_variant":[
        "Qeshl\u0101q-e \u0100s\u012byeh K\u016bshk"
    ],
    "wof:name":"Qeshlaq-e Asiyeh Kushk",
    "wof:placetype":"locality"
},
  "geometry": {"coordinates":[53.36308,27.82325],"type":"Point"}
}