{
  "type": "Feature",
  "properties": {
    "gn:admin1_code":"13",
    "gn:asciiname":"Gazaf-e `Olya",
    "gn:country_code":"IR",
    "gn:dem":1482,
    "gn:feature_class":"P",
    "gn:feature_code":"PPL",
    "gn:name":"Gaz\u0101f-e \u2018Oly\u0101",
    "gn:population":0,
    "gn:timezone":"Asia/Tehran",
    "iso:country":"IR",
    "name:fas_x_preferred":[
        "\u06af\u0632\u0627\u0641 \u0639\u0644\u06cc\u0627"
    ],
    "name:fas_x_variant":[
        "Gaz\u0101f-e \u2018Oly\u0101"
    ],
    "wof:name":"Gazaf-e `Olya",
    "wof:placetype":"locality"
},
  "geometry": {"coordinates":[47.0966,34.105],"type":"Point"}
}