{
  "type": "Feature",
  "properties": {
    "gn:admin1_code":"37.0",
    "gn:asciiname":"Jelin-e Sofla",
    "gn:country_code":"IR",
    "gn:dem":90,
    "gn:feature_class":"P",
    "gn:feature_code":"PPL",
    "gn:name":"Jel\u012bn-e Sofl\u00e1",
    "gn:population":0,
    "gn:timezone":"Asia/Tehran",
    "iso:country":"IR",
    "name:fas_x_preferred":[
        "\u062c\u0644\u06cc\u0646 \u0633\u0641\u0644\u06cc"
    ],
    "name:und_x_variant":[
        "Jel\u012bn-e Sofl\u00e1"
    ],
    "wof:name":"Jelin-e Sofla",
    "wof:placetype":"locality"
},
  "geometry": {"coordinates":[54.54019,36.87921],"type":"Point"}
}