{
  "type": "Feature",
  "properties": {
    "gn:admin1_code":"29",
    "gn:asciiname":"Khoruskabad",
    "gn:country_code":"IR",
    "gn:dem":784,
    "gn:feature_class":"P",
    "gn:feature_code":"PPL",
    "gn:name":"Khor\u016bsk\u0101b\u0101d",
    "gn:population":0,
    "gn:timezone":"Asia/Tehran",
    "iso:country":"IR",
    "name:fas_x_preferred":[
        "\u0642\u0644\u0639\u0647 \u062c\u0645\u0627\u0644\u06cc"
    ],
    "name:fas_x_variant":[
        "Qal\u2018eh-ye Jam\u0101l\u012b",
        "\u062e\u0631\u0648\u0633\u06a9 \u0622\u0628\u0627\u062f"
    ],
    "name:und_x_variant":[
        "Khor\u016bsk\u0101b\u0101d"
    ],
    "wof:name":"Khoruskabad",
    "wof:placetype":"locality"
},
  "geometry": {"coordinates":[58.63782,28.93245],"type":"Point"}
}