{
  "type": "Feature",
  "properties": {
    "gn:admin1_code":"40",
    "gn:asciiname":"Karkas Ow",
    "gn:country_code":"IR",
    "gn:dem":984,
    "gn:feature_class":"P",
    "gn:feature_code":"PPL",
    "gn:name":"Karkas Ow",
    "gn:population":0,
    "gn:timezone":"Asia/Tehran",
    "iso:country":"IR",
    "name:fas_x_preferred":[
        "Karkas \u0100b"
    ],
    "name:fas_x_variant":[
        "\u06a9\u0631\u06a9\u0633 \u0622\u0628",
        "\u06a9\u0631\u06a9\u0633 \u0627\u0648"
    ],
    "name:und_x_variant":[
        "\u06a9\u0631\u06a9\u0633 \u0622\u0628",
        "Karkas Ow"
    ],
    "wof:name":"Karkas Ow",
    "wof:placetype":"locality"
},
  "geometry": {"coordinates":[57.35746999999999,34.74496],"type":"Point"}
}