{
  "type": "Feature",
  "properties": {
    "gn:admin1_code":"23.0",
    "gn:asciiname":"`Alishah",
    "gn:country_code":"IR",
    "gn:dem":1186,
    "gn:feature_class":"P",
    "gn:feature_code":"PPLL",
    "gn:name":"\u2018Al\u012bsh\u0101h",
    "gn:population":0,
    "gn:timezone":"Asia/Tehran",
    "iso:country":"IR",
    "name:fas_x_preferred":[
        "D\u016bl-e Sorkh"
    ],
    "name:fas_x_variant":[
        "\u062f\u0648\u0644 \u0633\u0631\u062e",
        "\u0639\u0644\u064a\u0634\u0627\u0647"
    ],
    "name:und_x_variant":[
        "\u2018Al\u012bsh\u0101h"
    ],
    "wof:name":"`Alishah",
    "wof:placetype":"locality"
},
  "geometry": {"coordinates":[48.0616,33.24045],"type":"Point"}
}