{
  "type": "Feature",
  "properties": {
    "gn:admin1_code":"15",
    "gn:asciiname":"Jahanshahi",
    "gn:country_code":"IR",
    "gn:dem":366,
    "gn:feature_class":"P",
    "gn:feature_code":"PPL",
    "gn:name":"Jah\u0101nsh\u0101h\u012b",
    "gn:population":0,
    "gn:timezone":"Asia/Tehran",
    "iso:country":"IR",
    "name:fas_x_preferred":[
        "Jah\u0101nsh\u0101h\u012b"
    ],
    "name:fas_x_variant":[
        "\u062c\u0647\u0627\u0646\u0634\u0627\u0647\u06cc"
    ],
    "wof:name":"Jahanshahi",
    "wof:placetype":"locality"
},
  "geometry": {"coordinates":[49.27667,31.86889],"type":"Point"}
}