{
  "type": "Feature",
  "properties": {
    "gn:admin1_code":"33",
    "gn:asciiname":"Qarah `Owrat",
    "gn:country_code":"IR",
    "gn:dem":1636,
    "gn:feature_class":"P",
    "gn:feature_code":"PPL",
    "gn:name":"Qarah \u2018Owrat",
    "gn:population":0,
    "gn:timezone":"Asia/Tehran",
    "iso:country":"IR",
    "name:fas_x_preferred":[
        "\u0642\u0631\u0647 \u0639\u0648\u0631\u062a"
    ],
    "name:fas_x_variant":[
        "Qarah \u2018Owrat",
        "\u0642\u0631\u0647 \u063a\u0648\u0631\u062a"
    ],
    "name:und_x_variant":[
        "Qarah Ghowrat"
    ],
    "wof:name":"Qarah `Owrat",
    "wof:placetype":"locality"
},
  "geometry": {"coordinates":[46.7683,37.4055],"type":"Point"}
}