{
  "type": "Feature",
  "properties": {
    "gn:admin1_code":"8",
    "gn:asciiname":"Namakin",
    "gn:country_code":"IR",
    "gn:dem":292,
    "gn:feature_class":"P",
    "gn:feature_code":"PPL",
    "gn:name":"Namak\u012bn",
    "gn:population":0,
    "gn:timezone":"Asia/Tehran",
    "iso:country":"IR",
    "name:fas_x_preferred":[
        "\u0646\u0645\u0643\u064a\u0646"
    ],
    "name:fas_x_variant":[
        "Namak\u012bn",
        "\u0646\u0645\u06a9\u06cc\u0646"
    ],
    "wof:name":"Namakin",
    "wof:placetype":"locality"
},
  "geometry": {"coordinates":[49.1812,36.7629],"type":"Point"}
}