{
  "type": "Feature",
  "properties": {
    "gn:admin1_code":"29",
    "gn:asciiname":"Gowd-e Shuru",
    "gn:country_code":"IR",
    "gn:dem":2119,
    "gn:feature_class":"P",
    "gn:feature_code":"PPL",
    "gn:name":"Gowd-e Sh\u016br\u016b",
    "gn:population":0,
    "gn:timezone":"Asia/Tehran",
    "iso:country":"IR",
    "name:fas_x_preferred":[
        "Gowd-e Sh\u016br\u016b"
    ],
    "name:fas_x_variant":[
        "Gowd-e Sh\u016br \u0100b",
        "\u06af\u0648\u062f \u0634\u0648\u0631 \u0622\u0628",
        "\u06af\u0648\u062f \u0634\u0648\u0631\u0648",
        "\u06af\u0648\u062f \u0634\u0648\u0631"
    ],
    "name:und_x_variant":[
        "Gowd-e Sh\u016br"
    ],
    "wof:name":"Gowd-e Shuru",
    "wof:placetype":"locality"
},
  "geometry": {"coordinates":[56.31129,31.5161],"type":"Point"}
}