{
  "type": "Feature",
  "properties": {
    "gn:admin1_code":"15.0",
    "gn:asciiname":"Naruz",
    "gn:country_code":"IR",
    "gn:dem":16,
    "gn:feature_class":"P",
    "gn:feature_code":"PPL",
    "gn:name":"Nar\u016bz",
    "gn:population":0,
    "gn:timezone":"Asia/Tehran",
    "iso:country":"IR",
    "name:fas_x_preferred":[
        "\u0646\u0631\u0648\u0632"
    ],
    "name:fas_x_variant":[
        "Nar\u016bz"
    ],
    "wof:name":"Naruz",
    "wof:placetype":"locality"
},
  "geometry": {"coordinates":[48.24737,31.57075],"type":"Point"}
}