{
  "type": "Feature",
  "properties": {
    "gn:admin1_code":"41",
    "gn:asciiname":"`Aliabad",
    "gn:country_code":"IR",
    "gn:dem":1314,
    "gn:feature_class":"P",
    "gn:feature_code":"PPL",
    "gn:name":"\u2018Al\u012b\u0101b\u0101d",
    "gn:population":0,
    "gn:timezone":"Asia/Tehran",
    "iso:country":"IR",
    "name:fas_x_preferred":[
        "\u2018Al\u012b\u0101b\u0101d"
    ],
    "wof:name":"`Aliabad",
    "wof:placetype":"locality"
},
  "geometry": {"coordinates":[58.35,33.76667],"type":"Point"}
}