{
  "type": "Feature",
  "properties": {
    "gn:admin1_code":"4.0",
    "gn:asciiname":"Bon Deh",
    "gn:country_code":"IR",
    "gn:dem":1898,
    "gn:feature_class":"P",
    "gn:feature_code":"PPL",
    "gn:name":"Bon Deh",
    "gn:population":0,
    "gn:timezone":"Asia/Tehran",
    "iso:country":"IR",
    "name:fas_x_preferred":[
        "\u0628\u0646 \u062f\u0647"
    ],
    "name:und_x_variant":[
        "Bandeh",
        "Bon Deh"
    ],
    "wof:name":"Bon Deh",
    "wof:placetype":"locality"
},
  "geometry": {"coordinates":[61.1696,28.7069],"type":"Point"}
}