{
  "type": "Feature",
  "properties": {
    "gn:admin1_code":"15.0",
    "gn:asciiname":"Sar Julagi",
    "gn:country_code":"IR",
    "gn:dem":247,
    "gn:feature_class":"P",
    "gn:feature_code":"PPL",
    "gn:name":"Sar J\u016blag\u012b",
    "gn:population":0,
    "gn:timezone":"Asia/Tehran",
    "iso:country":"IR",
    "name:fas_x_preferred":[
        "\u0622\u0628 \u0628\u0627\u0631\u0627\u0646"
    ],
    "name:fas_x_variant":[
        "\u0100b B\u0101r\u0101n-e Yek",
        "\u0100b B\u0101r\u0101n",
        "\u0633\u0631 \u062c\u0648\u0644\u06af\u06cc",
        "\u0622\u0628 \u0628\u0627\u0631\u0627\u0646 \u062f\u0648"
    ],
    "name:und_x_variant":[
        "\u0100b-e-B\u0101r\u0101n",
        "Sar J\u016blag\u012b",
        "\u0100b B\u0101r\u0101n-e Do"
    ],
    "wof:name":"Sar Julagi",
    "wof:placetype":"locality"
},
  "geometry": {"coordinates":[49.9262,30.7541],"type":"Point"}
}