{
  "type": "Feature",
  "properties": {
    "gn:admin1_code":"42",
    "gn:asciiname":"Mazra`eh-ye Duk",
    "gn:country_code":"IR",
    "gn:dem":1112,
    "gn:feature_class":"P",
    "gn:feature_code":"PPLF",
    "gn:name":"Mazra\u2018eh-ye D\u016bk",
    "gn:population":0,
    "gn:timezone":"Asia/Tehran",
    "iso:country":"IR",
    "name:fas_x_preferred":[
        "D\u016bk"
    ],
    "name:fas_x_variant":[
        "\u062f\u0648\u06a9",
        "\u0645\u0632\u0631\u0639\u0647 \u062f\u0648\u06a9"
    ],
    "name:und_x_variant":[
        "\u062f\u0648\u06a9",
        "Mazra\u2018eh-ye D\u016bk"
    ],
    "wof:name":"Mazra`eh-ye Duk",
    "wof:placetype":"locality"
},
  "geometry": {"coordinates":[57.1867,33.97817],"type":"Point"}
}