{
  "type": "Feature",
  "properties": {
    "gn:admin1_code":"15.0",
    "gn:asciiname":"Abu Tavij",
    "gn:country_code":"IR",
    "gn:dem":29,
    "gn:feature_class":"P",
    "gn:feature_code":"PPL",
    "gn:name":"Ab\u016b \u0162av\u012bj",
    "gn:population":0,
    "gn:timezone":"Asia/Tehran",
    "iso:country":"IR",
    "name:ceb_x_preferred":[
        "Ab\u016b \u0162avayoj"
    ],
    "name:fas_x_preferred":[
        "\u0627\u0628\u0648 \u0637\u0648\u06cc\u062c"
    ],
    "name:fas_x_variant":[
        "Ab\u016b \u0162avayoj",
        "\u0627\u0628\u0648 \u062a\u0648\u06cc\u062c",
        "\u0627\u0628\u0648\u062a\u0648\u06cc\u062c"
    ],
    "name:swe_x_preferred":[
        "Ab\u016b \u0162avayoj"
    ],
    "name:und_x_variant":[
        "Ab\u016b \u0162av\u012bj",
        "Ab\u016b \u0162ovayyej",
        "Ab\u016b \u0162oveyj",
        "Ab\u016b Tav\u012bj"
    ],
    "wof:name":"Abu Tavij",
    "wof:placetype":"locality"
},
  "geometry": {"coordinates":[49.41018,30.92834],"type":"Point"}
}