{
  "type": "Feature",
  "properties": {
    "gn:admin1_code":"13",
    "gn:asciiname":"Namivand-e `Olya",
    "gn:country_code":"IR",
    "gn:dem":1342,
    "gn:feature_class":"P",
    "gn:feature_code":"PPL",
    "gn:name":"N\u0101m\u012bvand-e \u2018Oly\u0101",
    "gn:population":0,
    "gn:timezone":"Asia/Tehran",
    "iso:country":"IR",
    "name:fas_x_preferred":[
        "\u0646\u0627\u0645\u06cc\u0648\u0646\u062f \u0639\u0644\u06cc\u0627"
    ],
    "name:fas_x_variant":[
        "N\u0101m\u012bvand Qal\u2018eh",
        "N\u0101m\u012bvand-e \u2018Oly\u0101"
    ],
    "name:und_x_variant":[
        "N\u0101mvand-e Qal\u2018eh"
    ],
    "wof:name":"Namivand-e `Olya",
    "wof:placetype":"locality"
},
  "geometry": {"coordinates":[46.7383,34.4027],"type":"Point"}
}