{
  "type": "Feature",
  "properties": {
    "gn:admin1_code":"33",
    "gn:asciiname":"Tork Ilan",
    "gn:country_code":"IR",
    "gn:dem":907,
    "gn:elevation":"0.0",
    "gn:feature_class":"P",
    "gn:feature_code":"PPL",
    "gn:name":"Tork \u012al\u0101n",
    "gn:population":0,
    "gn:timezone":"Asia/Tehran",
    "iso:country":"IR",
    "name:fas_x_preferred":[
        "\u062a\u0631\u06a9\u0644\u0627\u0646"
    ],
    "name:fas_x_variant":[
        "Torkl\u0101n",
        "\u062a\u0631\u06a9 \u0627\u06cc\u0644\u0627\u0646"
    ],
    "name:und_x_variant":[
        "Tork \u012al\u0101n"
    ],
    "wof:name":"Tork Ilan",
    "wof:placetype":"locality"
},
  "geometry": {"coordinates":[47.48794,38.67661],"type":"Point"}
}