{
  "type": "Feature",
  "properties": {
    "gn:admin1_code":"37",
    "gn:asciiname":"Bala Ab Darreh",
    "gn:country_code":"IR",
    "gn:dem":1825,
    "gn:feature_class":"P",
    "gn:feature_code":"PPL",
    "gn:name":"B\u0101l\u0101 \u0100b Darreh",
    "gn:population":0,
    "gn:timezone":"Asia/Tehran",
    "iso:country":"IR",
    "name:fas_x_preferred":[
        "\u0628\u0627\u0644\u0627 \u0622\u0628 \u062f\u0631\u0647"
    ],
    "name:fas_x_variant":[
        "B\u0101l\u0101 \u0100b Darreh"
    ],
    "wof:name":"Bala Ab Darreh",
    "wof:placetype":"locality"
},
  "geometry": {"coordinates":[54.2882,36.67332],"type":"Point"}
}