{
  "type": "Feature",
  "properties": {
    "gn:admin1_code":"43.0",
    "gn:asciiname":"Pesteh",
    "gn:country_code":"IR",
    "gn:dem":1173,
    "gn:feature_class":"P",
    "gn:feature_code":"PPL",
    "gn:name":"Pesteh",
    "gn:population":0,
    "gn:timezone":"Asia/Tehran",
    "iso:country":"IR",
    "name:fas_x_preferred":[
        "\u067e\u0633\u062a\u0647"
    ],
    "wof:name":"Pesteh",
    "wof:placetype":"locality"
},
  "geometry": {"coordinates":[57.25588000000001,37.45265],"type":"Point"}
}