{
  "type": "Feature",
  "properties": {
    "gn:admin1_code":"13",
    "gn:asciiname":"Gura Jub-e Morad Beyg",
    "gn:country_code":"IR",
    "gn:dem":1520,
    "gn:feature_class":"P",
    "gn:feature_code":"PPL",
    "gn:name":"G\u016br\u0101 J\u016bb-e Mor\u0101d Beyg",
    "gn:population":0,
    "gn:timezone":"Asia/Tehran",
    "iso:country":"IR",
    "name:fas_x_preferred":[
        "\u06af\u0648\u0631\u0627 \u062c\u0648\u0628 \u0645\u0631\u0627\u062f \u0628\u06cc\u06af"
    ],
    "name:fas_x_variant":[
        "G\u016br\u0101 J\u016bb-e Mor\u0101d Beyg"
    ],
    "name:und_x_variant":[
        "G\u016br\u0101j\u016b Mor\u0101d Bak"
    ],
    "wof:name":"Gura Jub-e Morad Beyg",
    "wof:placetype":"locality"
},
  "geometry": {"coordinates":[46.3596,34.3231],"type":"Point"}
}