{
  "type": "Feature",
  "properties": {
    "gn:admin1_code":"5.0",
    "gn:asciiname":"Badengan-e Pa'in",
    "gn:country_code":"IR",
    "gn:dem":1606,
    "gn:feature_class":"P",
    "gn:feature_code":"PPL",
    "gn:name":"B\u0101deng\u0101n-e P\u0101\u2019\u012bn",
    "gn:population":0,
    "gn:timezone":"Asia/Tehran",
    "iso:country":"IR",
    "name:ara_x_preferred":[
        "\u0628\u0627\u062f\u0646\u063a\u0627\u0646 \u0627\u0644\u0633\u0641\u0644\u064a"
    ],
    "name:ceb_x_preferred":[
        "B\u0101deng\u0101n-e P\u0101'\u012bn"
    ],
    "name:fas_x_preferred":[
        "\u0628\u0627\u062f\u0650\u0646\u06af\u0627\u0646\u0650 \u067e\u0627\u0626\u064a\u0646"
    ],
    "name:fas_x_variant":[
        "\u0628\u0627\u062f\u0650\u0646\u06af\u0627\u0646\u0650 \u0633\u064f\u0641\u0644\u064e\u0649",
        "\u0628\u0627\u062f\u064e\u0646\u06af\u0648\u0646\u0650 \u067e\u0627\u0626\u064a\u0646",
        "\u0628\u0627\u062f\u0650\u0646\u06af\u0648\u0646 \u0633\u064f\u0641\u0644\u064e\u0649",
        "B\u0101deng\u0101n-e P\u0101\u2019\u012bn",
        "\u0628\u0627\u062f\u0646\u06af\u0627\u0646 \u0633\u0641\u0644\u06cc"
    ],
    "name:swe_x_preferred":[
        "B\u0101deng\u0101n-e P\u0101'\u012bn"
    ],
    "name:und_x_variant":[
        "B\u0101deng\u016bn Sofl\u00e1",
        "B\u0101deng\u0101n-e Sofl\u00e1",
        "B\u0101dang\u016bn-e P\u0101\u2019\u012bn"
    ],
    "wof:name":"Badengan-e Pa'in",
    "wof:placetype":"locality"
},
  "geometry": {"coordinates":[51.24472,30.97528],"type":"Point"}
}