{
  "type": "Feature",
  "properties": {
    "gn:admin1_code":"25",
    "gn:asciiname":"Sel Lazur",
    "gn:country_code":"IR",
    "gn:dem":2796,
    "gn:feature_class":"P",
    "gn:feature_code":"PPL",
    "gn:name":"Sel L\u0101z\u016br",
    "gn:population":0,
    "gn:timezone":"Asia/Tehran",
    "iso:country":"IR",
    "name:fas_x_preferred":[
        "\u0633\u0650\u0644 \u0644\u0627\u0632\u0648\u0631"
    ],
    "name:fas_x_variant":[
        "Sel L\u0101z\u016br"
    ],
    "wof:name":"Sel Lazur",
    "wof:placetype":"locality"
},
  "geometry": {"coordinates":[52.76988000000001,35.52148],"type":"Point"}
}