{
  "type": "Feature",
  "properties": {
    "gn:admin1_code":"28",
    "gn:asciiname":"Lushab",
    "gn:country_code":"IR",
    "gn:dem":2229,
    "gn:feature_class":"P",
    "gn:feature_code":"PPL",
    "gn:name":"L\u016bsh\u0101b",
    "gn:population":0,
    "gn:timezone":"Asia/Tehran",
    "iso:country":"IR",
    "name:fas_x_preferred":[
        "\u0644\u0648\u0634\u0627\u0628"
    ],
    "name:fas_x_variant":[
        "L\u016bsh\u0101b"
    ],
    "wof:name":"Lushab",
    "wof:placetype":"locality"
},
  "geometry": {"coordinates":[50.7671,33.435],"type":"Point"}
}