{
  "type": "Feature",
  "properties": {
    "gn:admin1_code":"44.0",
    "gn:asciiname":"Helah Gereh",
    "gn:country_code":"IR",
    "gn:dem":2394,
    "gn:feature_class":"P",
    "gn:feature_code":"PPL",
    "gn:name":"Helah Gereh",
    "gn:population":0,
    "gn:timezone":"Asia/Tehran",
    "iso:country":"IR",
    "name:fas_x_preferred":[
        "\u0647\u0644\u06af\u0631"
    ],
    "name:fas_x_variant":[
        "\u0647\u0644\u0647 \u06af\u0631\u0647"
    ],
    "name:und_x_variant":[
        "Helgar",
        "Helah Gereh"
    ],
    "wof:name":"Helah Gereh",
    "wof:placetype":"locality"
},
  "geometry": {"coordinates":[51.37275,36.08387000000001],"type":"Point"}
}