{
  "type": "Feature",
  "properties": {
    "gn:admin1_code":"10",
    "gn:asciiname":"Varbar",
    "gn:country_code":"IR",
    "gn:dem":1012,
    "gn:feature_class":"P",
    "gn:feature_code":"PPL",
    "gn:name":"Varbar",
    "gn:population":0,
    "gn:timezone":"Asia/Tehran",
    "iso:country":"IR",
    "name:ara_x_preferred":[
        "\u0648\u0631\u0628\u0631"
    ],
    "name:ceb_x_preferred":[
        "Varbar"
    ],
    "name:fas_x_preferred":[
        "\u0648\u0631\u0628\u0631\u0647\u0644\u06cc\u0644\u0627\u0646"
    ],
    "name:fas_x_variant":[
        "\u0648\u064e\u0631\u0628\u064e\u0631",
        "Varbar-e Hel\u012bl\u0101n",
        "\u0648\u0631\u0628\u0631"
    ],
    "name:swe_x_preferred":[
        "Varbar"
    ],
    "wof:name":"Varbar",
    "wof:placetype":"locality"
},
  "geometry": {"coordinates":[47.0833,33.7935],"type":"Point"}
}