{
  "type": "Feature",
  "properties": {
    "gn:admin1_code":"0",
    "gn:asciiname":"Qeshlaq-e Hajji Akbar",
    "gn:country_code":"IR",
    "gn:dem":421,
    "gn:feature_class":"P",
    "gn:feature_code":"PPL",
    "gn:name":"Qeshl\u0101q-e \u1e28\u0101jj\u012b Akbar",
    "gn:population":0,
    "gn:timezone":"Asia/Tehran",
    "iso:country":"IR",
    "name:fas_x_preferred":[
        "\u0642\u0650\u0634\u0644\u0627\u0642\u0650 \u062d\u0627\u062c\u0651\u06cc \u0627\u064e\u0643\u0628\u064e\u0631"
    ],
    "name:fas_x_variant":[
        "Qeshl\u0101q-e \u1e28\u0101jj\u012b Akbar"
    ],
    "wof:name":"Qeshlaq-e Hajji Akbar",
    "wof:placetype":"locality"
},
  "geometry": {"coordinates":[47.45,39.25],"type":"Point"}
}