{
  "type": "Feature",
  "properties": {
    "gn:admin1_code":"37",
    "gn:asciiname":"Yekkeh Quz-e `Olya",
    "gn:country_code":"IR",
    "gn:dem":408,
    "gn:feature_class":"P",
    "gn:feature_code":"PPL",
    "gn:name":"Yekkeh Q\u016bz-e \u2018Oly\u0101",
    "gn:population":0,
    "gn:timezone":"Asia/Tehran",
    "iso:country":"IR",
    "name:fas_x_preferred":[
        "\u064a\u0650\u0643\u0650\u0651\u0647 \u0642\u0648\u0632"
    ],
    "name:fas_x_variant":[
        "Yekkeh Q\u016bz-e B\u0101l\u0101",
        "\u064a\u0643\u0647 \u0642\u0648\u0632 \u0628\u0627\u0644\u0627",
        "\u064a\u0643\u0647 \u0642\u0648\u0632 \u0639\u0644\u06cc\u0627",
        "\u06cc\u06a9\u0647\u200c\u0642\u0648\u0632 \u0628\u0627\u0644\u0627"
    ],
    "name:msa_x_preferred":[
        "Yekkeh Quz-e Bala"
    ],
    "name:und_x_variant":[
        "Yekkeh Q\u016bz",
        "Yakigov",
        "Yekkeh Q\u016bz-e \u2018Oly\u0101"
    ],
    "name:urd_x_preferred":[
        "\u06cc\u06a9\u06c1 \u0642\u0632-\u0628\u0644\u0627"
    ],
    "wof:name":"Yekkeh Quz-e `Olya",
    "wof:placetype":"locality"
},
  "geometry": {"coordinates":[55.62316,37.47415],"type":"Point"}
}