{
  "type": "Feature",
  "properties": {
    "gn:admin1_code":"5.0",
    "gn:asciiname":"Amirabad-e `Olya",
    "gn:country_code":"IR",
    "gn:dem":2096,
    "gn:feature_class":"P",
    "gn:feature_code":"PPL",
    "gn:name":"Am\u012br\u0101b\u0101d-e \u2018Oly\u0101",
    "gn:population":0,
    "gn:timezone":"Asia/Tehran",
    "iso:country":"IR",
    "name:fas_x_preferred":[
        "Am\u012br\u0101b\u0101d-e \u2018Oly\u0101"
    ],
    "name:fas_x_variant":[
        "\u0627\u0645\u064a\u0631 \u0622\u0628\u0627\u062f \u0639\u0644\u06cc\u0627"
    ],
    "name:und_x_variant":[
        "\u0627\u0645\u064a\u0631 \u0622\u0628\u0627\u062f \u0639\u0644\u06cc\u0627"
    ],
    "wof:name":"Amirabad-e `Olya",
    "wof:placetype":"locality"
},
  "geometry": {"coordinates":[51.44498,30.61565],"type":"Point"}
}