{
  "type": "Feature",
  "properties": {
    "gn:admin1_code":"4.0",
    "gn:asciiname":"Aspagan",
    "gn:cc2":"IR",
    "gn:country_code":"IR",
    "gn:dem":1251,
    "gn:feature_class":"P",
    "gn:feature_code":"PPL",
    "gn:name":"Aspag\u0101n",
    "gn:population":0,
    "gn:timezone":"Asia/Tehran",
    "iso:country":"IR",
    "name:fas_x_preferred":[
        "Aspag\u0101n"
    ],
    "name:und_x_variant":[
        "Aspak\u0101n"
    ],
    "wof:name":"Aspagan",
    "wof:placetype":"locality"
},
  "geometry": {"coordinates":[60.43333000000001,26.71667],"type":"Point"}
}