{
  "type": "Feature",
  "properties": {
    "gn:admin1_code":"22",
    "gn:asciiname":"Mahalleh-ye Qal`eh Kohneh",
    "gn:country_code":"IR",
    "gn:dem":633,
    "gn:feature_class":"P",
    "gn:feature_code":"PPL",
    "gn:name":"Ma\u1e29alleh-ye Qal\u2018eh Kohneh",
    "gn:population":0,
    "gn:timezone":"Asia/Tehran",
    "iso:country":"IR",
    "name:fas_x_preferred":[
        "\u0642\u064e\u0644\u0639\u0650\u06c0 \u0643\u064f\u0647\u0646\u0650\u0647"
    ],
    "name:fas_x_variant":[
        "\u063a\u064e\u0644\u0639\u0650\u0647 \u0643\u064f\u0647\u0646\u0650\u0647",
        "\u0645\u062d\u0644\u0647 \u0642\u0644\u0639\u0647 \u0643\u0647\u0646\u0647",
        "Qal\u2018eh-ye Kohneh"
    ],
    "name:und_x_variant":[
        "Ghal\u2018eh Kohneh",
        "Ma\u1e29alleh-ye Qal\u2018eh Kohneh"
    ],
    "wof:name":"Mahalleh-ye Qal`eh Kohneh",
    "wof:placetype":"locality"
},
  "geometry": {"coordinates":[52.32174000000001,27.83443],"type":"Point"}
}