{
  "type": "Feature",
  "properties": {
    "gn:admin1_code":"4.0",
    "gn:asciiname":"Espakeh",
    "gn:country_code":"IR",
    "gn:dem":771,
    "gn:feature_class":"P",
    "gn:feature_code":"PPL",
    "gn:name":"Espakeh",
    "gn:population":0,
    "gn:timezone":"Asia/Tehran",
    "iso:country":"IR",
    "name:fas_x_preferred":[
        "\u0627\u0633\u067e\u06a9\u0647"
    ],
    "name:und_x_variant":[
        "Ispakeh",
        "Aspakeh",
        "Isfakeh",
        "Esfakeh",
        "Espakeh"
    ],
    "wof:name":"Espakeh",
    "wof:placetype":"locality"
},
  "geometry": {"coordinates":[60.1731,26.84004],"type":"Point"}
}