{
  "type": "Feature",
  "properties": {
    "gn:admin1_code":"13",
    "gn:asciiname":"Parian",
    "gn:country_code":"IR",
    "gn:dem":1792,
    "gn:feature_class":"P",
    "gn:feature_code":"PPL",
    "gn:name":"Par\u012b\u0101n",
    "gn:population":0,
    "gn:timezone":"Asia/Tehran",
    "iso:country":"IR",
    "name:fas_x_preferred":[
        "\u067e\u0631\u06cc\u0627\u0646"
    ],
    "name:fas_x_variant":[
        "Par\u012b\u0101n"
    ],
    "wof:name":"Parian",
    "wof:placetype":"locality"
},
  "geometry": {"coordinates":[47.2211,34.6614],"type":"Point"}
}