{
  "type": "Feature",
  "properties": {
    "gn:admin1_code":"4",
    "gn:asciiname":"Posht Kur",
    "gn:country_code":"IR",
    "gn:dem":519,
    "gn:feature_class":"P",
    "gn:feature_code":"PPL",
    "gn:name":"Posht K\u016br",
    "gn:population":0,
    "gn:timezone":"Asia/Tehran",
    "iso:country":"IR",
    "name:fas_x_preferred":[
        "\u067e\u0634\u062a \u06a9\u0648\u0631"
    ],
    "name:fas_x_variant":[
        "Posht K\u016br"
    ],
    "wof:name":"Posht Kur",
    "wof:placetype":"locality"
},
  "geometry": {"coordinates":[60.49584,27.17737],"type":"Point"}
}