{
  "type": "Feature",
  "properties": {
    "gn:admin1_code":"4.0",
    "gn:asciiname":"Gazafi Jan Mohammad",
    "gn:country_code":"IR",
    "gn:dem":31,
    "gn:feature_class":"P",
    "gn:feature_code":"PPL",
    "gn:name":"Gaz\u0101f\u012b J\u0101n Mo\u1e29ammad",
    "gn:population":0,
    "gn:timezone":"Asia/Tehran",
    "iso:country":"IR",
    "name:fas_x_preferred":[
        "Gaz\u0101n\u012b"
    ],
    "name:fas_x_variant":[
        "Gaz\u0101f\u012b J\u0101n Mo\u1e29ammad",
        "\u06af\u0632\u0627\u0641\u06cc \u062c\u0627\u0646 \u0645\u062d\u0645\u062f"
    ],
    "name:und_x_variant":[
        "Golla",
        "Goly\u0101",
        "Goz\u0101n\u012b",
        "\u06af\u0632\u0627\u0641\u06cc \u062c\u0627\u0646 \u0645\u062d\u0645\u062f"
    ],
    "wof:name":"Gazafi Jan Mohammad",
    "wof:placetype":"locality"
},
  "geometry": {"coordinates":[61.07575,25.601],"type":"Point"}
}