{
  "type": "Feature",
  "properties": {
    "gn:admin1_code":"3.0",
    "gn:asciiname":"Moradabad",
    "gn:country_code":"IR",
    "gn:dem":2018,
    "gn:feature_class":"P",
    "gn:feature_code":"PPL",
    "gn:name":"Mor\u0101d\u0101b\u0101d",
    "gn:population":0,
    "gn:timezone":"Asia/Tehran",
    "iso:country":"IR",
    "name:fas_x_preferred":[
        "Mor\u0101d\u0101b\u0101d"
    ],
    "name:fas_x_variant":[
        "\u0645\u064f\u0631\u0627\u062f \u0622\u0628\u0627\u062f"
    ],
    "wof:name":"Moradabad",
    "wof:placetype":"locality"
},
  "geometry": {"coordinates":[50.38472,32.00444],"type":"Point"}
}