{
  "type": "Feature",
  "properties": {
    "gn:admin1_code":"15",
    "gn:asciiname":"Shian Sakhi",
    "gn:country_code":"IR",
    "gn:dem":40,
    "gn:feature_class":"P",
    "gn:feature_code":"PPL",
    "gn:name":"Sh\u012b\u0101n Sakh\u012b",
    "gn:population":0,
    "gn:timezone":"Asia/Tehran",
    "iso:country":"IR",
    "name:ceb_x_preferred":[
        "Yash\u0101nsakh\u012b"
    ],
    "name:fas_x_preferred":[
        "\u06cc\u0634\u0627\u0646\u0633\u062e\u06cc"
    ],
    "name:fas_x_variant":[
        "Yesh\u0101n Sakh\u012b",
        "Yash\u0101nsakh\u012b",
        "\u0634\u06cc\u0627\u0646 \u0633\u062e\u06cc",
        "\u06cc\u0634\u0627\u0646 \u0633\u062e\u06cc"
    ],
    "name:swe_x_preferred":[
        "Yash\u0101nsakh\u012b"
    ],
    "name:und_x_variant":[
        "Maj\u012bd",
        "Sh\u012b\u0101n Sakh\u012b"
    ],
    "name:urd_x_preferred":[
        "\u06cc\u0634\u0646\u0633\u0627\u06a9\u06be\u06cc"
    ],
    "wof:name":"Shian Sakhi",
    "wof:placetype":"locality"
},
  "geometry": {"coordinates":[48.5912,31.95898],"type":"Point"}
}