{
  "type": "Feature",
  "properties": {
    "gn:admin1_code":"5",
    "gn:asciiname":"Mazra`eh-ye Meleh Shahab",
    "gn:country_code":"IR",
    "gn:dem":1303,
    "gn:feature_class":"P",
    "gn:feature_code":"PPL",
    "gn:name":"Mazra\u2018eh-ye Meleh Shah\u0101b",
    "gn:population":0,
    "gn:timezone":"Asia/Tehran",
    "iso:country":"IR",
    "name:fas_x_preferred":[
        "\u0645\u0644\u0647 \u0634\u0647\u0627\u0628"
    ],
    "name:fas_x_variant":[
        "\u0645\u0632\u0631\u0639\u0647 \u0645\u0644\u0647 \u0634\u0647\u0627\u0628"
    ],
    "name:und_x_variant":[
        "Meleh Shah\u0101b",
        "Mazra\u2018eh-ye Meleh Shah\u0101b"
    ],
    "wof:name":"Mazra`eh-ye Meleh Shahab",
    "wof:placetype":"locality"
},
  "geometry": {"coordinates":[50.44186,31.19974],"type":"Point"}
}