{
  "type": "Feature",
  "properties": {
    "gn:admin1_code":"33",
    "gn:asciiname":"Heykalabad",
    "gn:country_code":"IR",
    "gn:dem":2170,
    "gn:feature_class":"P",
    "gn:feature_code":"PPL",
    "gn:name":"Heykal\u0101b\u0101d",
    "gn:population":0,
    "gn:timezone":"Asia/Tehran",
    "iso:country":"IR",
    "name:fas_x_preferred":[
        "\u0647\u06cc\u06a9\u0644 \u0622\u0628\u0627\u062f"
    ],
    "name:fas_x_variant":[
        "Heykal\u0101b\u0101d"
    ],
    "wof:name":"Heykalabad",
    "wof:placetype":"locality"
},
  "geometry": {"coordinates":[46.6614,37.659],"type":"Point"}
}