{
  "type": "Feature",
  "properties": {
    "gn:admin1_code":"4.0",
    "gn:asciiname":"Safar",
    "gn:country_code":"IR",
    "gn:dem":487,
    "gn:feature_class":"P",
    "gn:feature_code":"PPL",
    "gn:name":"\u015eafar",
    "gn:population":0,
    "gn:timezone":"Asia/Tehran",
    "iso:country":"IR",
    "name:fas_x_preferred":[
        "\u0635\u0641\u0631"
    ],
    "name:fas_x_variant":[
        "\u015eafar"
    ],
    "wof:name":"Safar",
    "wof:placetype":"locality"
},
  "geometry": {"coordinates":[61.63046,30.83998],"type":"Point"}
}