{
  "type": "Feature",
  "properties": {
    "gn:admin1_code":"23.0",
    "gn:asciiname":"Bagh",
    "gn:country_code":"IR",
    "gn:dem":1998,
    "gn:feature_class":"P",
    "gn:feature_code":"PPL",
    "gn:name":"B\u0101gh",
    "gn:population":0,
    "gn:timezone":"Asia/Tehran",
    "iso:country":"IR",
    "name:fas_x_preferred":[
        "\u0628\u0627\u063a"
    ],
    "name:fas_x_variant":[
        "B\u0101gh",
        "\u0628\u0627\u063a \u0635\u0641\u06cc\u0646"
    ],
    "name:und_x_variant":[
        "B\u0101gh-e \u015eaf\u012bn"
    ],
    "wof:name":"Bagh",
    "wof:placetype":"locality"
},
  "geometry": {"coordinates":[48.8639,33.4791],"type":"Point"}
}