{
  "type": "Feature",
  "properties": {
    "gn:admin1_code":"28",
    "gn:asciiname":"Zarab",
    "gn:country_code":"IR",
    "gn:dem":1515,
    "gn:feature_class":"P",
    "gn:feature_code":"PPL",
    "gn:name":"Zar\u0101b",
    "gn:population":0,
    "gn:timezone":"Asia/Tehran",
    "iso:country":"IR",
    "name:fas_x_preferred":[
        "Zar\u0101b"
    ],
    "wof:name":"Zarab",
    "wof:placetype":"locality"
},
  "geometry": {"coordinates":[53.43333000000001,33.43333],"type":"Point"}
}