{
  "type": "Feature",
  "properties": {
    "gn:admin1_code":"11",
    "gn:asciiname":"Nowruz Kar",
    "gn:country_code":"IR",
    "gn:dem":17,
    "gn:feature_class":"P",
    "gn:feature_code":"PPL",
    "gn:name":"Nowr\u016bz K\u0101r",
    "gn:population":0,
    "gn:timezone":"Asia/Tehran",
    "iso:country":"IR",
    "name:ceb_x_preferred":[
        "Nowr\u016bz K\u0101r"
    ],
    "name:fas_x_preferred":[
        "\u0646\u064f\u0648\u0631\u0648\u0632 \u0643\u0627\u0631"
    ],
    "name:fas_x_variant":[
        "Nowr\u016bz K\u0101r",
        "\u0646\u0648\u0631\u0648\u0632\u06a9\u0627\u0631"
    ],
    "name:msa_x_preferred":[
        "Nowruz Kar"
    ],
    "name:swe_x_preferred":[
        "Nowr\u016bz K\u0101r"
    ],
    "wof:name":"Nowruz Kar",
    "wof:placetype":"locality"
},
  "geometry": {"coordinates":[58.44278000000001,25.74861],"type":"Point"}
}