{
  "type": "Feature",
  "properties": {
    "gn:admin1_code":"34",
    "gn:asciiname":"Khaneqah-e `Olya",
    "gn:country_code":"IR",
    "gn:dem":1798,
    "gn:feature_class":"P",
    "gn:feature_code":"PPL",
    "gn:name":"Kh\u0101neq\u0101h-e \u2018Oly\u0101",
    "gn:population":0,
    "gn:timezone":"Asia/Tehran",
    "iso:country":"IR",
    "name:fas_x_preferred":[
        "\u062e\u0627\u0646\u0642\u0627\u0647 \u0639\u0644\u064a\u0627"
    ],
    "name:fas_x_variant":[
        "Kh\u0101nq\u0101h-e \u2018Oly\u0101",
        "Kh\u0101neq\u0101h-e \u2018Oly\u0101"
    ],
    "wof:name":"Khaneqah-e `Olya",
    "wof:placetype":"locality"
},
  "geometry": {"coordinates":[49.3496,34.2542],"type":"Point"}
}