{
  "type": "Feature",
  "properties": {
    "gn:admin1_code":"40",
    "gn:asciiname":"Kuh-e Qor Sorkh Neyur",
    "gn:country_code":"IR",
    "gn:dem":1616,
    "gn:feature_class":"P",
    "gn:feature_code":"PPL",
    "gn:name":"K\u016bh-e Qor Sorkh Ney\u016br",
    "gn:population":0,
    "gn:timezone":"Asia/Tehran",
    "iso:country":"IR",
    "name:fas_x_preferred":[
        "\u06a9\u0648\u0647 \u0642\u0631 \u0633\u0631\u062e \u0646\u064a\u0648\u0631"
    ],
    "name:und_x_variant":[
        "K\u016bh-e Qor Sorkh Ney\u016br",
        "Qar Sorkh"
    ],
    "wof:name":"Kuh-e Qor Sorkh Neyur",
    "wof:placetype":"locality"
},
  "geometry": {"coordinates":[57.21694,34.64722],"type":"Point"}
}