{
  "type": "Feature",
  "properties": {
    "gn:admin1_code":"4.0",
    "gn:asciiname":"Kaliran",
    "gn:country_code":"IR",
    "gn:dem":697,
    "gn:feature_class":"P",
    "gn:feature_code":"PPL",
    "gn:name":"Kal\u012br\u0101n",
    "gn:population":0,
    "gn:timezone":"Asia/Tehran",
    "iso:country":"IR",
    "name:fas_x_preferred":[
        "\u06a9\u0644\u064a\u0631\u0627\u0646"
    ],
    "name:fas_x_variant":[
        "Kal\u012br\u0101n",
        "\u06a9\u0644\u06cc\u0631\u0627\u0646"
    ],
    "wof:name":"Kaliran",
    "wof:placetype":"locality"
},
  "geometry": {"coordinates":[60.8869,27.26421],"type":"Point"}
}