{
  "type": "Feature",
  "properties": {
    "gn:admin1_code":"42",
    "gn:asciiname":"Seyyedabad",
    "gn:country_code":"IR",
    "gn:dem":1183,
    "gn:feature_class":"P",
    "gn:feature_code":"PPL",
    "gn:name":"Seyyed\u0101b\u0101d",
    "gn:population":0,
    "gn:timezone":"Asia/Tehran",
    "iso:country":"IR",
    "name:fas_x_preferred":[
        "\u0633\u06cc\u062f \u0622\u0628\u0627\u062f"
    ],
    "name:fas_x_variant":[
        "Seyyed\u0101b\u0101d"
    ],
    "wof:name":"Seyyedabad",
    "wof:placetype":"locality"
},
  "geometry": {"coordinates":[58.68324000000001,36.27965],"type":"Point"}
}