{
  "type": "Feature",
  "properties": {
    "gn:admin1_code":"43.0",
    "gn:asciiname":"Malek",
    "gn:country_code":"IR",
    "gn:dem":927,
    "gn:feature_class":"P",
    "gn:feature_code":"PPL",
    "gn:name":"Malek",
    "gn:population":0,
    "gn:timezone":"Asia/Tehran",
    "iso:country":"IR",
    "name:ceb_x_preferred":[
        "Malek"
    ],
    "name:deu_x_preferred":[
        "Malek"
    ],
    "name:fas_x_preferred":[
        "\u0645\u0644\u06a9"
    ],
    "name:fra_x_preferred":[
        "Malek"
    ],
    "name:nds_x_preferred":[
        "Malek"
    ],
    "name:pol_x_preferred":[
        "Malek"
    ],
    "name:spa_x_preferred":[
        "Malek"
    ],
    "name:swe_x_preferred":[
        "Malek"
    ],
    "name:und_x_variant":[
        "\u0645\u0644\u06a9"
    ],
    "wof:name":"Malek",
    "wof:placetype":"locality"
},
  "geometry": {"coordinates":[56.68383000000001,38.18045],"type":"Point"}
}