{
  "type": "Feature",
  "properties": {
    "gn:admin1_code":"23",
    "gn:asciiname":"Vargeh Pahneh",
    "gn:country_code":"IR",
    "gn:dem":2385,
    "gn:feature_class":"P",
    "gn:feature_code":"PPL",
    "gn:name":"V\u0101rgeh Pahneh",
    "gn:population":0,
    "gn:timezone":"Asia/Tehran",
    "iso:country":"IR",
    "name:ara_x_preferred":[
        "\u0648\u0627\u0631\u063a\u0629 \u0628\u0647\u0646\u0647"
    ],
    "name:fas_x_preferred":[
        "V\u0101rkah-e Pahneh"
    ],
    "name:fas_x_variant":[
        "V\u0101rgeh Pahneh",
        "\u0648\u0627\u0631\u06af\u0647 \u067e\u0647\u0646\u0647"
    ],
    "wof:name":"Vargeh Pahneh",
    "wof:placetype":"locality"
},
  "geometry": {"coordinates":[49.76556,33.0528],"type":"Point"}
}