{
  "type": "Feature",
  "properties": {
    "gn:admin1_code":"13",
    "gn:asciiname":"Mian Choqa",
    "gn:country_code":"IR",
    "gn:dem":1254,
    "gn:feature_class":"P",
    "gn:feature_code":"PPL",
    "gn:name":"M\u012b\u0101n Choq\u0101",
    "gn:population":0,
    "gn:timezone":"Asia/Tehran",
    "iso:country":"IR",
    "name:fas_x_preferred":[
        "\u0645\u06cc\u0627\u0646 \u0686\u0642\u0627"
    ],
    "name:fas_x_variant":[
        "M\u012b\u0101n Choq\u0101"
    ],
    "name:und_x_variant":[
        "M\u012b\u0101n Chaq\u0101",
        "M\u012by\u0101n Cheq\u0101"
    ],
    "wof:name":"Mian Choqa",
    "wof:placetype":"locality"
},
  "geometry": {"coordinates":[46.7601,33.8335],"type":"Point"}
}