{
  "type": "Feature",
  "properties": {
    "gn:admin1_code":"1.0",
    "gn:asciiname":"Dowzan",
    "gn:country_code":"IR",
    "gn:dem":1387,
    "gn:feature_class":"P",
    "gn:feature_code":"PPL",
    "gn:name":"Dowzan",
    "gn:population":0,
    "gn:timezone":"Asia/Tehran",
    "iso:country":"IR",
    "name:fas_x_preferred":[
        "\u062f\u0648\u0632\u0646"
    ],
    "wof:name":"Dowzan",
    "wof:placetype":"locality"
},
  "geometry": {"coordinates":[44.8243,38.8267],"type":"Point"}
}