{
  "type": "Feature",
  "properties": {
    "gn:admin1_code":"15",
    "gn:asciiname":"Chahar Borji",
    "gn:country_code":"IR",
    "gn:dem":366,
    "gn:feature_class":"P",
    "gn:feature_code":"PPL",
    "gn:name":"Chah\u0101r Borj\u012b",
    "gn:population":0,
    "gn:timezone":"Asia/Tehran",
    "iso:country":"IR",
    "name:ara_x_preferred":[
        "\u062a\u0634\u0647\u0627\u0631\u0628\u0631\u062c\u064a"
    ],
    "name:fas_x_preferred":[
        "Chah\u0101r Borj\u012b"
    ],
    "name:fas_x_variant":[
        "\u0686\u0647\u0627\u0631\u0628\u0631\u062c\u06cc"
    ],
    "wof:name":"Chahar Borji",
    "wof:placetype":"locality"
},
  "geometry": {"coordinates":[48.25,32.66667],"type":"Point"}
}