{
  "type": "Feature",
  "properties": {
    "gn:admin1_code":"8",
    "gn:asciiname":"Barand",
    "gn:country_code":"IR",
    "gn:dem":694,
    "gn:feature_class":"P",
    "gn:feature_code":"PPL",
    "gn:name":"Barand",
    "gn:population":0,
    "gn:timezone":"Asia/Tehran",
    "iso:country":"IR",
    "name:fas_x_preferred":[
        "\u0628\u0631\u0646\u062f"
    ],
    "name:und_x_variant":[
        "\u0628\u0631\u0646\u062f"
    ],
    "wof:name":"Barand",
    "wof:placetype":"locality"
},
  "geometry": {"coordinates":[49.54448,36.6778],"type":"Point"}
}