{
  "type": "Feature",
  "properties": {
    "gn:admin1_code":"5",
    "gn:asciiname":"Murdak",
    "gn:country_code":"IR",
    "gn:dem":1563,
    "gn:feature_class":"P",
    "gn:feature_code":"PPL",
    "gn:name":"M\u016brdak",
    "gn:population":0,
    "gn:timezone":"Asia/Tehran",
    "iso:country":"IR",
    "name:fas_x_preferred":[
        "M\u016brdak"
    ],
    "name:fas_x_variant":[
        "\u0645\u0648\u0631\u062f\u0643",
        "\u0645\u0648\u0631\u062f\u06a9"
    ],
    "wof:name":"Murdak",
    "wof:placetype":"locality"
},
  "geometry": {"coordinates":[50.89157,30.9517],"type":"Point"}
}