{
  "type": "Feature",
  "properties": {
    "gn:admin1_code":"1",
    "gn:asciiname":"Shirakan",
    "gn:country_code":"IR",
    "gn:dem":1558,
    "gn:feature_class":"P",
    "gn:feature_code":"PPL",
    "gn:name":"Sh\u012brak\u0101n",
    "gn:population":0,
    "gn:timezone":"Asia/Tehran",
    "iso:country":"IR",
    "name:fas_x_preferred":[
        "\u0634\u06cc\u0631\u06a9\u0627\u0646"
    ],
    "name:fas_x_variant":[
        "\u0634\u064a\u0631\u064e\u0643\u0627\u0646",
        "Sh\u012brak\u0101n"
    ],
    "wof:name":"Shirakan",
    "wof:placetype":"locality"
},
  "geometry": {"coordinates":[44.9635,37.2974],"type":"Point"}
}