{
  "type": "Feature",
  "properties": {
    "gn:admin1_code":"29",
    "gn:asciiname":"Kuy-e Lay-e Zirumesinan",
    "gn:country_code":"IR",
    "gn:dem":2763,
    "gn:feature_class":"P",
    "gn:feature_code":"PPL",
    "gn:name":"K\u016by-e L\u0101y-e Z\u012br\u016bmes\u012bn\u0101n",
    "gn:population":0,
    "gn:timezone":"Asia/Tehran",
    "iso:country":"IR",
    "name:fas_x_preferred":[
        "K\u016by-e L\u0101y-e Z\u012br\u016bmes\u012bn\u0101n"
    ],
    "name:fas_x_variant":[
        "\u06a9\u0648\u06cc \u0644\u0627\u06cc \u0632\u064a\u0631\u0648\u0645\u0633\u064a\u0646\u0627\u0646"
    ],
    "wof:name":"Kuy-e Lay-e Zirumesinan",
    "wof:placetype":"locality"
},
  "geometry": {"coordinates":[55.25,30.38278],"type":"Point"}
}