{
  "type": "Feature",
  "properties": {
    "gn:admin1_code":"37",
    "gn:asciiname":"Qarah Gol",
    "gn:country_code":"IR",
    "gn:dem":126,
    "gn:feature_class":"P",
    "gn:feature_code":"PPL",
    "gn:name":"Qarah Gol",
    "gn:population":0,
    "gn:timezone":"Asia/Tehran",
    "iso:country":"IR",
    "name:ceb_x_preferred":[
        "Qarah Gol"
    ],
    "name:fas_x_preferred":[
        "\u0642\u0631\u0647 \u06af\u0644"
    ],
    "name:swe_x_preferred":[
        "Qarah Gol"
    ],
    "wof:name":"Qarah Gol",
    "wof:placetype":"locality"
},
  "geometry": {"coordinates":[55.6529,37.91991],"type":"Point"}
}