{
  "type": "Feature",
  "properties": {
    "gn:admin1_code":"42",
    "gn:asciiname":"Nowchah",
    "gn:country_code":"IR",
    "gn:dem":1181,
    "gn:feature_class":"P",
    "gn:feature_code":"PPL",
    "gn:name":"Nowch\u0101h",
    "gn:population":0,
    "gn:timezone":"Asia/Tehran",
    "iso:country":"IR",
    "name:fas_x_preferred":[
        "\u0646\u0648\u0686\u0627\u0647"
    ],
    "name:fas_x_variant":[
        "Nowch\u0101h"
    ],
    "wof:name":"Nowchah",
    "wof:placetype":"locality"
},
  "geometry": {"coordinates":[59.4279,36.3424],"type":"Point"}
}