{
  "type": "Feature",
  "properties": {
    "gn:admin1_code":"9.0",
    "gn:asciiname":"`Alamdar",
    "gn:country_code":"IR",
    "gn:dem":1529,
    "gn:feature_class":"P",
    "gn:feature_code":"PPL",
    "gn:name":"\u2018Alamd\u0101r",
    "gn:population":0,
    "gn:timezone":"Asia/Tehran",
    "iso:country":"IR",
    "name:fas_x_preferred":[
        "\u0639\u0644\u0645\u062f\u0627\u0631"
    ],
    "name:fas_x_variant":[
        "\u2018Alamd\u0101r"
    ],
    "wof:name":"`Alamdar",
    "wof:placetype":"locality"
},
  "geometry": {"coordinates":[48.26664,34.25887],"type":"Point"}
}