{
  "type": "Feature",
  "properties": {
    "gn:admin1_code":"35.0",
    "gn:asciiname":"Andarvar",
    "gn:country_code":"IR",
    "gn:dem":-17,
    "gn:feature_class":"P",
    "gn:feature_code":"PPL",
    "gn:name":"Andarvar",
    "gn:population":0,
    "gn:timezone":"Asia/Tehran",
    "iso:country":"IR",
    "name:fas_x_preferred":[
        "\u0627\u0646\u062f\u0631\u0648\u0631"
    ],
    "name:fas_x_variant":[
        "\u0100ndarvar"
    ],
    "name:und_x_variant":[
        "Andar\u016bd",
        "Andarood",
        "Andarvar"
    ],
    "wof:name":"Andarvar",
    "wof:placetype":"locality"
},
  "geometry": {"coordinates":[51.73466,36.58239],"type":"Point"}
}