{
  "type": "Feature",
  "properties": {
    "gn:admin1_code":"29",
    "gn:asciiname":"Sar Bak",
    "gn:country_code":"IR",
    "gn:dem":2322,
    "gn:feature_class":"P",
    "gn:feature_code":"PPL",
    "gn:name":"Sar Bak",
    "gn:population":0,
    "gn:timezone":"Asia/Tehran",
    "iso:country":"IR",
    "name:fas_x_preferred":[
        "\u0633\u0631 \u0628\u06a9"
    ],
    "wof:name":"Sar Bak",
    "wof:placetype":"locality"
},
  "geometry": {"coordinates":[57.8897,29.0666],"type":"Point"}
}