{
  "type": "Feature",
  "properties": {
    "gn:admin1_code":"10",
    "gn:asciiname":"Bon Baba Jan",
    "gn:country_code":"IR",
    "gn:dem":614,
    "gn:feature_class":"P",
    "gn:feature_code":"PPL",
    "gn:name":"Bon B\u0101b\u0101 J\u0101n",
    "gn:population":0,
    "gn:timezone":"Asia/Tehran",
    "iso:country":"IR",
    "name:ara_x_preferred":[
        "\u0628\u0646 \u0628\u0627\u0628\u0627\u062c\u0627\u0646"
    ],
    "name:ceb_x_preferred":[
        "Bon B\u0101b\u0101 J\u0101n"
    ],
    "name:fas_x_preferred":[
        "Bon B\u0101b\u0101 J\u0101n"
    ],
    "name:fas_x_variant":[
        "\u0628\u064f\u0646 \u0628\u0627\u0628\u0627 \u062c\u0627\u0646",
        "\u0628\u0646 \u0628\u0627\u0628\u0627\u062c\u0627\u0646"
    ],
    "name:msa_x_preferred":[
        "Bon Baba Jan"
    ],
    "name:swe_x_preferred":[
        "Bon B\u0101b\u0101 J\u0101n"
    ],
    "wof:name":"Bon Baba Jan",
    "wof:placetype":"locality"
},
  "geometry": {"coordinates":[47.55,33.06667],"type":"Point"}
}