{
  "type": "Feature",
  "properties": {
    "gn:admin1_code":"1",
    "gn:asciiname":"Dilanchi Arkhi-ye `Olya",
    "gn:country_code":"IR",
    "gn:dem":1336,
    "gn:feature_class":"P",
    "gn:feature_code":"PPL",
    "gn:name":"D\u012bl\u0101nch\u012b Arkh\u012b-ye \u2018Oly\u0101",
    "gn:population":0,
    "gn:timezone":"Asia/Tehran",
    "iso:country":"IR",
    "name:fas_x_preferred":[
        "\u062f\u06cc\u0644\u0627\u0646\u0686\u06cc \u0627\u0631\u062e\u06cc \u0639\u0644\u06cc\u0627"
    ],
    "name:fas_x_variant":[
        "D\u012blanch\u012b Arkh\u012b-ye\u2018oly\u0101",
        "D\u012bl\u0101nch\u012b Arkh\u012b-ye \u2018Oly\u0101"
    ],
    "wof:name":"Dilanchi Arkhi-ye `Olya",
    "wof:placetype":"locality"
},
  "geometry": {"coordinates":[45.2862,37.0084],"type":"Point"}
}