{
  "type": "Feature",
  "properties": {
    "gn:admin1_code":"28.0",
    "gn:asciiname":"Qudar",
    "gn:country_code":"IR",
    "gn:dem":2087,
    "gn:feature_class":"P",
    "gn:feature_code":"PPL",
    "gn:name":"Q\u016bd\u0101r",
    "gn:population":0,
    "gn:timezone":"Asia/Tehran",
    "iso:country":"IR",
    "name:fas_x_preferred":[
        "Q\u016bd\u0101r"
    ],
    "wof:name":"Qudar",
    "wof:placetype":"locality"
},
  "geometry": {"coordinates":[52.98333,32.65555999999999],"type":"Point"}
}