{
  "type": "Feature",
  "properties": {
    "gn:admin1_code":"26.0",
    "gn:asciiname":"Shahrak-e Mohammadiyeh",
    "gn:country_code":"IR",
    "gn:dem":1181,
    "gn:feature_class":"P",
    "gn:feature_code":"PPL",
    "gn:name":"Shahrak-e Mo\u1e29ammad\u012byeh",
    "gn:population":0,
    "gn:timezone":"Asia/Tehran",
    "iso:country":"IR",
    "name:fas_x_preferred":[
        "\u0634\u0647\u0631\u06a9 \u0645\u062d\u0645\u062f\u06cc\u0647"
    ],
    "name:fas_x_variant":[
        "Shahrak-e Mo\u1e29ammad\u012byeh"
    ],
    "wof:name":"Shahrak-e Mohammadiyeh",
    "wof:placetype":"locality"
},
  "geometry": {"coordinates":[51.0498,35.6874],"type":"Point"}
}