{
  "type": "Feature",
  "properties": {
    "gn:admin1_code":"16",
    "gn:asciiname":"`Arab Lang",
    "gn:country_code":"IR",
    "gn:dem":1617,
    "gn:feature_class":"P",
    "gn:feature_code":"PPL",
    "gn:name":"\u2018Arab Lang",
    "gn:population":0,
    "gn:timezone":"Asia/Tehran",
    "iso:country":"IR",
    "name:fas_x_preferred":[
        "\u067e\u064e\u0644\u064e\u0646\u06af \u062f\u0650\u0698"
    ],
    "name:fas_x_variant":[
        "\u0639\u064e\u0631\u064e\u0628\u0650 \u0644\u064e\u0646\u06af",
        "\u0639\u064e\u0631\u064e\u0628 \u0644\u064e\u0646\u06af",
        "\u0639\u0631\u0628 \u0644\u0646\u06af",
        "\u2018Arab Lang"
    ],
    "name:und_x_variant":[
        "\u2018Arab-e Lang",
        "Palang Dezh"
    ],
    "wof:name":"`Arab Lang",
    "wof:placetype":"locality"
},
  "geometry": {"coordinates":[46.2593,36.0876],"type":"Point"}
}