{
  "type": "Feature",
  "properties": {
    "gn:admin1_code":"39",
    "gn:asciiname":"Zizgan",
    "gn:country_code":"IR",
    "gn:dem":1920,
    "gn:feature_class":"P",
    "gn:feature_code":"PPL",
    "gn:name":"Z\u012bzg\u0101n",
    "gn:population":0,
    "gn:timezone":"Asia/Tehran",
    "iso:country":"IR",
    "name:ceb_x_preferred":[
        "Z\u012bzg\u0101n"
    ],
    "name:fas_x_preferred":[
        "\u0632\u064a\u0632\u06af\u0627\u0646"
    ],
    "name:fas_x_variant":[
        "Z\u012bzg\u0101n",
        "\u0632\u06cc\u0632\u06af\u0627\u0646"
    ],
    "name:swe_x_preferred":[
        "Z\u012bzg\u0101n"
    ],
    "wof:name":"Zizgan",
    "wof:placetype":"locality"
},
  "geometry": {"coordinates":[50.17821,34.52109],"type":"Point"}
}