{
  "type": "Feature",
  "properties": {
    "gn:admin1_code":"8.0",
    "gn:asciiname":"Sardel",
    "gn:country_code":"IR",
    "gn:dem":1772,
    "gn:feature_class":"P",
    "gn:feature_code":"PPL",
    "gn:name":"Sardel",
    "gn:population":0,
    "gn:timezone":"Asia/Tehran",
    "iso:country":"IR",
    "name:fas_x_preferred":[
        "\u0633\u0631\u062f\u0644"
    ],
    "wof:name":"Sardel",
    "wof:placetype":"locality"
},
  "geometry": {"coordinates":[48.83708,37.41654000000001],"type":"Point"}
}