{
  "type": "Feature",
  "properties": {
    "gn:admin1_code":"15",
    "gn:asciiname":"Kuy-e Bimarestan-e Vali-ye `Asr",
    "gn:country_code":"IR",
    "gn:dem":312,
    "gn:feature_class":"P",
    "gn:feature_code":"PPL",
    "gn:name":"K\u016by-e B\u012bm\u0101rest\u0101n-e Val\u012b-ye \u2018A\u015fr",
    "gn:population":0,
    "gn:timezone":"Asia/Tehran",
    "iso:country":"IR",
    "name:fas_x_preferred":[
        "\u06a9\u0648\u06cc \u0628\u06cc\u0645\u0627\u0631\u0633\u062a\u0627\u0646 \u0648\u0644\u06cc \u0639\u0635\u0631"
    ],
    "name:fas_x_variant":[
        "K\u016by-e B\u012bm\u0101rest\u0101n-e Val\u012b-ye \u2018A\u015fr"
    ],
    "wof:name":"Kuy-e Bimarestan-e Vali-ye `Asr",
    "wof:placetype":"locality"
},
  "geometry": {"coordinates":[50.1988,30.6159],"type":"Point"}
}