{
  "type": "Feature",
  "properties": {
    "gn:admin1_code":"4.0",
    "gn:asciiname":"Ahmadabad",
    "gn:country_code":"IR",
    "gn:dem":230,
    "gn:feature_class":"P",
    "gn:feature_code":"PPLL",
    "gn:name":"A\u1e29mad\u0101b\u0101d",
    "gn:population":0,
    "gn:timezone":"Asia/Tehran",
    "iso:country":"IR",
    "name:fas_x_preferred":[
        "\u0627\u062d\u0645\u062f \u0622\u0628\u0627\u062f"
    ],
    "name:und_x_variant":[
        "A\u1e29mad\u0101b\u0101d"
    ],
    "wof:name":"Ahmadabad",
    "wof:placetype":"locality"
},
  "geometry": {"coordinates":[59.59655,26.09205],"type":"Point"}
}