{
  "type": "Feature",
  "properties": {
    "gn:admin1_code":"23",
    "gn:asciiname":"Kolah Zard",
    "gn:country_code":"IR",
    "gn:dem":1618,
    "gn:feature_class":"P",
    "gn:feature_code":"PPL",
    "gn:name":"Kol\u0101h Zard",
    "gn:population":0,
    "gn:timezone":"Asia/Tehran",
    "iso:country":"IR",
    "name:fas_x_preferred":[
        "\u06a9\u0644\u0627\u0647 \u0632\u0631\u062f"
    ],
    "name:fas_x_variant":[
        "Kol\u0101h Zard"
    ],
    "wof:name":"Kolah Zard",
    "wof:placetype":"locality"
},
  "geometry": {"coordinates":[48.2833,33.78916],"type":"Point"}
}