{
  "type": "Feature",
  "properties": {
    "gn:admin1_code":"38",
    "gn:asciiname":"Mahmudabad",
    "gn:country_code":"IR",
    "gn:dem":1262,
    "gn:feature_class":"P",
    "gn:feature_code":"PPL",
    "gn:name":"Ma\u1e29m\u016bd\u0101b\u0101d",
    "gn:population":0,
    "gn:timezone":"Asia/Tehran",
    "iso:country":"IR",
    "name:fas_x_preferred":[
        "Ma\u1e29m\u016bd\u0101b\u0101d-e Sh\u0101r\u012bn"
    ],
    "name:fas_x_variant":[
        "Ma\u1e29m\u016bd\u0101b\u0101d",
        "\u0645\u062d\u0645\u0648\u062f \u0622\u0628\u0627\u062f",
        "\u0645\u062d\u0645\u0648\u062f\u0622\u0628\u0627\u062f"
    ],
    "wof:name":"Mahmudabad",
    "wof:placetype":"locality"
},
  "geometry": {"coordinates":[49.73715,35.98311],"type":"Point"}
}