{
  "type": "Feature",
  "properties": {
    "gn:admin1_code":"29",
    "gn:asciiname":"Diz",
    "gn:country_code":"IR",
    "gn:dem":2240,
    "gn:feature_class":"P",
    "gn:feature_code":"PPL",
    "gn:name":"D\u012bz",
    "gn:population":0,
    "gn:timezone":"Asia/Tehran",
    "iso:country":"IR",
    "name:fas_x_preferred":[
        "D\u012bz"
    ],
    "wof:name":"Diz",
    "wof:placetype":"locality"
},
  "geometry": {"coordinates":[57.0975,30.76778],"type":"Point"}
}