{
  "type": "Feature",
  "properties": {
    "gn:admin1_code":"33",
    "gn:asciiname":"Golehin",
    "gn:country_code":"IR",
    "gn:dem":1684,
    "gn:feature_class":"P",
    "gn:feature_code":"PPL",
    "gn:name":"Goleh\u012bn",
    "gn:population":0,
    "gn:timezone":"Asia/Tehran",
    "iso:country":"IR",
    "name:ara_x_preferred":[
        "\u063a\u0644\u0647\u064a\u0646"
    ],
    "name:ceb_x_preferred":[
        "Goleh\u012bn"
    ],
    "name:fas_x_preferred":[
        "\u06af\u0644\u0647\u06cc\u0646"
    ],
    "name:fas_x_variant":[
        "Goleh\u012bn"
    ],
    "name:msa_x_preferred":[
        "Golehin"
    ],
    "name:swe_x_preferred":[
        "Goleh\u012bn"
    ],
    "name:tur_x_preferred":[
        "Gilehin"
    ],
    "name:und_x_variant":[
        "Kalin",
        "Geleh\u012bn"
    ],
    "wof:name":"Golehin",
    "wof:placetype":"locality"
},
  "geometry": {"coordinates":[47.1177,37.6464],"type":"Point"}
}