{
  "type": "Feature",
  "properties": {
    "gn:admin1_code":"15",
    "gn:asciiname":"Soltanabad",
    "gn:cc2":"IR",
    "gn:country_code":"IR",
    "gn:dem":122,
    "gn:feature_class":"P",
    "gn:feature_code":"PPL",
    "gn:name":"Sol\u0163\u0101n\u0101b\u0101d",
    "gn:population":0,
    "gn:timezone":"Asia/Tehran",
    "iso:country":"IR",
    "name:fas_x_preferred":[
        "Sol\u0163\u0101n\u0101b\u0101d"
    ],
    "name:und_x_variant":[
        "Sult\u0101n\u0101b\u0101d"
    ],
    "wof:name":"Soltanabad",
    "wof:placetype":"locality"
},
  "geometry": {"coordinates":[49.79806,30.9675],"type":"Point"}
}