{
  "type": "Feature",
  "properties": {
    "gn:admin1_code":"29",
    "gn:asciiname":"Mazra`eh Khomrutu'iyeh",
    "gn:country_code":"IR",
    "gn:dem":2374,
    "gn:feature_class":"P",
    "gn:feature_code":"PPLF",
    "gn:name":"Mazra\u2018eh Khomr\u016bt\u016b\u2019\u012byeh",
    "gn:population":0,
    "gn:timezone":"Asia/Tehran",
    "iso:country":"IR",
    "name:fas_x_preferred":[
        "\u062e\u0645\u0631\u0648\u062f"
    ],
    "name:fas_x_variant":[
        "Khomr\u016bd\u016b\u2019\u012byeh",
        "Khomr\u016bd",
        "\u0645\u0632\u0631\u063a\u0647 \u062e\u0645\u0631\u0648\u062a\u0648\u0626\u064a\u0647",
        "\u062e\u0645\u0631\u0648\u062a\u0648\u0626\u064a\u0647"
    ],
    "name:und_x_variant":[
        "Mazra\u2018eh Khomr\u016bt\u016b\u2019\u012byeh",
        "M\u0101n\u012b"
    ],
    "wof:name":"Mazra`eh Khomrutu'iyeh",
    "wof:placetype":"locality"
},
  "geometry": {"coordinates":[55.73054000000001,30.02637],"type":"Point"}
}