{
  "type": "Feature",
  "properties": {
    "gn:admin1_code":"41",
    "gn:asciiname":"Mowrutak",
    "gn:country_code":"IR",
    "gn:dem":2033,
    "gn:feature_class":"P",
    "gn:feature_code":"PPLL",
    "gn:name":"Mowr\u016btak",
    "gn:population":0,
    "gn:timezone":"Asia/Tehran",
    "iso:country":"IR",
    "name:fas_x_preferred":[
        "M\u016brtak-e B\u0101l\u0101"
    ],
    "name:fas_x_variant":[
        "Mowr\u016btak",
        "\u0645\u0648\u0631\u062a\u06a9 \u0628\u0627\u0644\u0627",
        "M\u016br\u016btak",
        "Mor\u016btak",
        "\u0645\u0648\u0631\u0648\u062a\u06a9"
    ],
    "name:und_x_variant":[
        "M\u016br\u016btak",
        "Mor\u016btak",
        "\u0645\u0648\u0631\u062a\u06a9 \u0628\u0627\u0644\u0627"
    ],
    "wof:name":"Mowrutak",
    "wof:placetype":"locality"
},
  "geometry": {"coordinates":[59.47666,32.68142],"type":"Point"}
}