{
  "type": "Feature",
  "properties": {
    "gn:admin1_code":"1",
    "gn:asciiname":"Sarujeh-ye Sofla",
    "gn:country_code":"IR",
    "gn:dem":1448,
    "gn:feature_class":"P",
    "gn:feature_code":"PPL",
    "gn:name":"S\u0101r\u016bjeh-ye Sofl\u00e1",
    "gn:population":0,
    "gn:timezone":"Asia/Tehran",
    "iso:country":"IR",
    "name:aze_x_preferred":[
        "A\u015fa\u011f\u0131 Sar\u0131ca"
    ],
    "name:ceb_x_preferred":[
        "S\u0101r\u016bjeh-ye Sofl\u00e1"
    ],
    "name:ckb_x_preferred":[
        "\u0633\u0627\u0631\u0648\u062c\u06d5\u06cc \u062e\u0648\u0627\u0631\u0648\u0648"
    ],
    "name:fas_x_preferred":[
        "\u0633\u0627\u0631\u0648\u062c\u0647 \u0633\u0641\u0644\u06cc"
    ],
    "name:fas_x_variant":[
        "S\u0101r\u016bjeh-ye Sofl\u00e1"
    ],
    "name:msa_x_preferred":[
        "Sarujeh-ye Sofla"
    ],
    "name:swe_x_preferred":[
        "S\u0101r\u016bjeh-ye Sofl\u00e1"
    ],
    "wof:name":"Sarujeh-ye Sofla",
    "wof:placetype":"locality"
},
  "geometry": {"coordinates":[46.5325,36.63],"type":"Point"}
}