{
  "type": "Feature",
  "properties": {
    "gn:admin1_code":"35.0",
    "gn:asciiname":"Astaneh Sar",
    "gn:country_code":"IR",
    "gn:dem":28,
    "gn:feature_class":"P",
    "gn:feature_code":"PPL",
    "gn:name":"\u0100st\u0101neh Sar",
    "gn:population":0,
    "gn:timezone":"Asia/Tehran",
    "iso:country":"IR",
    "name:fas_x_preferred":[
        "\u0622\u0633\u062a\u0627\u0646\u0647 \u0633\u0631"
    ],
    "name:fas_x_variant":[
        "\u0100st\u0101neh Sar",
        "\u0622\u0633\u062a\u0627\u0646\u0647\u200c\u0633\u0631"
    ],
    "name:und_x_variant":[
        "\u0622\u0633\u062a\u0627\u0646\u0650\u0647 \u0633\u064e\u0631"
    ],
    "wof:name":"Astaneh Sar",
    "wof:placetype":"locality"
},
  "geometry": {"coordinates":[52.54388,36.43281],"type":"Point"}
}