{
  "type": "Feature",
  "properties": {
    "gn:admin1_code":"15",
    "gn:asciiname":"Jadvalkan",
    "gn:country_code":"IR",
    "gn:dem":1083,
    "gn:feature_class":"P",
    "gn:feature_code":"PPL",
    "gn:name":"Jadvalk\u0101n",
    "gn:population":0,
    "gn:timezone":"Asia/Tehran",
    "iso:country":"IR",
    "name:fas_x_preferred":[
        "Jadvalk\u0101n"
    ],
    "name:fas_x_variant":[
        "\u062c\u062f\u0648\u0644\u06a9\u0627\u0646"
    ],
    "wof:name":"Jadvalkan",
    "wof:placetype":"locality"
},
  "geometry": {"coordinates":[50.28804,31.56079],"type":"Point"}
}