{
  "type": "Feature",
  "properties": {
    "gn:admin1_code":"5.0",
    "gn:asciiname":"Ab Lami",
    "gn:country_code":"IR",
    "gn:dem":1442,
    "gn:feature_class":"P",
    "gn:feature_code":"PPL",
    "gn:name":"\u0100b Lam\u012b",
    "gn:population":0,
    "gn:timezone":"Asia/Tehran",
    "iso:country":"IR",
    "name:fas_x_preferred":[
        "\u0100b Lam\u012b"
    ],
    "name:fas_x_variant":[
        "\u0622\u0628 \u0644\u0645\u06cc"
    ],
    "wof:name":"Ab Lami",
    "wof:placetype":"locality"
},
  "geometry": {"coordinates":[50.82892,30.97634],"type":"Point"}
}