{
  "type": "Feature",
  "properties": {
    "gn:admin1_code":"1.0",
    "gn:asciiname":"Jan Aqa",
    "gn:country_code":"IR",
    "gn:dem":1418,
    "gn:feature_class":"P",
    "gn:feature_code":"PPL",
    "gn:name":"J\u0101n \u0100q\u0101",
    "gn:population":0,
    "gn:timezone":"Asia/Tehran",
    "iso:country":"IR",
    "name:azb_x_preferred":[
        "\u062c\u0627\u0646\u200c\u0627\u0642\u0627(\u0642\u0648\u0634\u0627\u0686\u0627\u06cc)"
    ],
    "name:aze_x_preferred":[
        "Cana\u011fa"
    ],
    "name:ceb_x_preferred":[
        "J\u0101n \u0100q\u0101"
    ],
    "name:fas_x_preferred":[
        "\u062c\u0627\u0646 \u0622\u0642\u0627"
    ],
    "name:fas_x_variant":[
        "J\u0101n \u0100q\u0101",
        "\u062c\u0627\u0646\u200c\u0627\u0642\u0627"
    ],
    "name:msa_x_preferred":[
        "Jan Aqa"
    ],
    "name:swe_x_preferred":[
        "J\u0101n \u0100q\u0101"
    ],
    "name:urd_x_preferred":[
        "\u062c\u0627\u0646 \u0627\u0642\u0627"
    ],
    "wof:name":"Jan Aqa",
    "wof:placetype":"locality"
},
  "geometry": {"coordinates":[46.4696,36.9193],"type":"Point"}
}