{
  "type": "Feature",
  "properties": {
    "gn:admin1_code":"41",
    "gn:asciiname":"Gaz",
    "gn:country_code":"IR",
    "gn:dem":1744,
    "gn:feature_class":"P",
    "gn:feature_code":"PPL",
    "gn:name":"Gaz",
    "gn:population":0,
    "gn:timezone":"Asia/Tehran",
    "iso:country":"IR",
    "name:aze_x_preferred":[
        "Qaz"
    ],
    "name:ceb_x_preferred":[
        "Gaz"
    ],
    "name:fas_x_preferred":[
        "\u06af\u0632"
    ],
    "name:fra_x_preferred":[
        "Gaz"
    ],
    "name:hrv_x_preferred":[
        "Gaz"
    ],
    "name:pol_x_preferred":[
        "Gaz"
    ],
    "name:ron_x_preferred":[
        "Gaz"
    ],
    "name:slv_x_preferred":[
        "Gaz"
    ],
    "name:swe_x_preferred":[
        "Gaz"
    ],
    "name:uzb_x_preferred":[
        "Gaz"
    ],
    "name:vep_x_preferred":[
        "Gaz"
    ],
    "wof:name":"Gaz",
    "wof:placetype":"locality"
},
  "geometry": {"coordinates":[59.35014,32.59541],"type":"Point"}
}