{
  "type": "Feature",
  "properties": {
    "gn:admin1_code":"5",
    "gn:asciiname":"Emamzadeh Ja`far",
    "gn:country_code":"IR",
    "gn:dem":678,
    "gn:feature_class":"P",
    "gn:feature_code":"PPL",
    "gn:name":"Em\u0101mz\u0101deh Ja\u2018far",
    "gn:population":0,
    "gn:timezone":"Asia/Tehran",
    "iso:country":"IR",
    "name:fas_x_preferred":[
        "\u0627\u0645\u0627\u0645\u0632\u0627\u062f\u0647 \u062c\u0639\u0641\u0631"
    ],
    "name:fas_x_variant":[
        "Em\u0101mz\u0101deh Ja\u2018far"
    ],
    "wof:name":"Emamzadeh Ja`far",
    "wof:placetype":"locality"
},
  "geometry": {"coordinates":[50.9738,30.3113],"type":"Point"}
}