{
  "type": "Feature",
  "properties": {
    "gn:admin1_code":"8.0",
    "gn:asciiname":"Hojjat Mahalleh",
    "gn:country_code":"IR",
    "gn:dem":-21,
    "gn:feature_class":"P",
    "gn:feature_code":"PPL",
    "gn:name":"\u1e28ojjat Ma\u1e29alleh",
    "gn:population":0,
    "gn:timezone":"Asia/Tehran",
    "iso:country":"IR",
    "name:fas_x_preferred":[
        "\u062d\u062c\u062a \u0645\u062d\u0644\u0647"
    ],
    "name:und_x_variant":[
        "\u1e28ojjat Ma\u1e29alleh"
    ],
    "wof:name":"Hojjat Mahalleh",
    "wof:placetype":"locality"
},
  "geometry": {"coordinates":[48.91854,37.99314],"type":"Point"}
}