{
  "type": "Feature",
  "properties": {
    "gn:admin1_code":"5.0",
    "gn:asciiname":"Vahdatabad",
    "gn:country_code":"IR",
    "gn:dem":2087,
    "gn:feature_class":"P",
    "gn:feature_code":"PPL",
    "gn:name":"Va\u1e29dat\u0101b\u0101d",
    "gn:population":0,
    "gn:timezone":"Asia/Tehran",
    "iso:country":"IR",
    "name:fas_x_preferred":[
        "Va\u1e29dat\u0101b\u0101d"
    ],
    "name:fas_x_variant":[
        "\u0648\u062d\u062f\u062a \u0622\u0628\u0627\u062f"
    ],
    "wof:name":"Vahdatabad",
    "wof:placetype":"locality"
},
  "geometry": {"coordinates":[51.39696,30.56955],"type":"Point"}
}