{
  "type": "Feature",
  "properties": {
    "gn:admin1_code":"37.0",
    "gn:asciiname":"Dikli Dash",
    "gn:country_code":"IR",
    "gn:dem":289,
    "gn:feature_class":"P",
    "gn:feature_code":"PPL",
    "gn:name":"D\u012bkl\u012b D\u0101sh",
    "gn:population":0,
    "gn:timezone":"Asia/Tehran",
    "iso:country":"IR",
    "name:ceb_x_preferred":[
        "D\u012bkl\u012b D\u0101sh"
    ],
    "name:fas_x_preferred":[
        "\u062f\u06cc\u06a9\u0644\u06cc \u062f\u0627\u0634"
    ],
    "name:fas_x_variant":[
        "Dekl\u012bd\u0101sh",
        "D\u012bkl\u012b D\u0101sh",
        "\u062f\u0643\u0644\u06cc \u062f\u0627\u0634",
        "\u062f\u06a9\u0644\u06cc \u062f\u0627\u0634"
    ],
    "name:msa_x_preferred":[
        "Deklidash"
    ],
    "name:swe_x_preferred":[
        "D\u012bkl\u012b D\u0101sh"
    ],
    "name:und_x_variant":[
        "Dekl\u012b D\u0101sh"
    ],
    "wof:name":"Dikli Dash",
    "wof:placetype":"locality"
},
  "geometry": {"coordinates":[55.87871,37.82018],"type":"Point"}
}