{
  "type": "Feature",
  "properties": {
    "gn:admin1_code":"8",
    "gn:asciiname":"Qeshlaq",
    "gn:country_code":"IR",
    "gn:dem":1399,
    "gn:feature_class":"P",
    "gn:feature_code":"PPL",
    "gn:name":"Qeshl\u0101q",
    "gn:population":0,
    "gn:timezone":"Asia/Tehran",
    "iso:country":"IR",
    "name:fas_x_preferred":[
        "Qeshl\u0101q"
    ],
    "name:fas_x_variant":[
        "\u0642\u0634\u0644\u0627\u0642"
    ],
    "name:msa_x_preferred":[
        "Qeshlaq"
    ],
    "name:ukr_x_preferred":[
        "\u041a\u0435\u0448\u043b\u0430\u043a"
    ],
    "name:und_x_variant":[
        "Kishlak",
        "\u0642\u0634\u0644\u0627\u0642"
    ],
    "wof:name":"Qeshlaq",
    "wof:placetype":"locality"
},
  "geometry": {"coordinates":[49.86709000000001,36.86035],"type":"Point"}
}