{
  "type": "Feature",
  "properties": {
    "gn:admin1_code":"13",
    "gn:asciiname":"Choqa Golan",
    "gn:country_code":"IR",
    "gn:dem":1286,
    "gn:feature_class":"P",
    "gn:feature_code":"PPL",
    "gn:name":"Choq\u0101 Gol\u0101n",
    "gn:population":0,
    "gn:timezone":"Asia/Tehran",
    "iso:country":"IR",
    "name:ceb_x_preferred":[
        "Choq\u0101 Gol\u0101n"
    ],
    "name:fas_x_preferred":[
        "\u0686\u0642\u0627 \u06af\u0644\u0627\u0646"
    ],
    "name:fas_x_variant":[
        "Choq\u0101 Gol\u0101n",
        "\u0686\u0642\u0627\u06af\u0644\u0627\u0646"
    ],
    "name:swe_x_preferred":[
        "Choq\u0101 Gol\u0101n"
    ],
    "wof:name":"Choqa Golan",
    "wof:placetype":"locality"
},
  "geometry": {"coordinates":[47.5228,34.4614],"type":"Point"}
}