{
  "type": "Feature",
  "properties": {
    "gn:admin1_code":"42",
    "gn:asciiname":"`Aqar-e Pa'in",
    "gn:country_code":"IR",
    "gn:dem":1380,
    "gn:feature_class":"P",
    "gn:feature_code":"PPL",
    "gn:name":"\u2018Aqar-e P\u0101\u2019\u012bn",
    "gn:population":0,
    "gn:timezone":"Asia/Tehran",
    "iso:country":"IR",
    "name:fas_x_preferred":[
        "\u0639\u0642\u0631 \u067e\u0627\u0626\u06cc\u0646"
    ],
    "name:fas_x_variant":[
        "\u2018Aqar-e P\u0101\u2019\u012bn"
    ],
    "wof:name":"`Aqar-e Pa'in",
    "wof:placetype":"locality"
},
  "geometry": {"coordinates":[59.93165,35.7481],"type":"Point"}
}