{
  "type": "Feature",
  "properties": {
    "gn:admin1_code":"40",
    "gn:asciiname":"Sa`idabad",
    "gn:country_code":"IR",
    "gn:dem":1073,
    "gn:feature_class":"P",
    "gn:feature_code":"PPL",
    "gn:name":"Sa\u2018\u012bd\u0101b\u0101d",
    "gn:population":0,
    "gn:timezone":"Asia/Tehran",
    "iso:country":"IR",
    "name:fas_x_preferred":[
        "Sa\u2018\u012bd\u0101b\u0101d"
    ],
    "name:fas_x_variant":[
        "Seyyed\u0101b\u0101d",
        "\u0633\u06cc\u062f \u0622\u0628\u0627\u062f",
        "Saiyid\u0101b\u0101d",
        "\u0633\u0639\u064a\u062f \u0622\u0628\u0627\u062f",
        "\u0633\u06cc\u062f\u0622\u0628\u0627\u062f"
    ],
    "name:und_x_variant":[
        "Seyyed\u0101b\u0101d",
        "Saiyid\u0101b\u0101d",
        "\u0633\u06cc\u062f \u0622\u0628\u0627\u062f"
    ],
    "wof:name":"Sa`idabad",
    "wof:placetype":"locality"
},
  "geometry": {"coordinates":[57.67748,33.12856],"type":"Point"}
}