{
  "type": "Feature",
  "properties": {
    "gn:admin1_code":"32",
    "gn:asciiname":"Moradlu",
    "gn:country_code":"IR",
    "gn:dem":1372,
    "gn:feature_class":"P",
    "gn:feature_code":"PPL",
    "gn:name":"Mor\u0101dl\u016b",
    "gn:population":0,
    "gn:timezone":"Asia/Tehran",
    "iso:country":"IR",
    "name:fas_x_preferred":[
        "Mer\u2019\u0101t\u012b"
    ],
    "name:fas_x_variant":[
        "\u0645\u0631\u0627\u062f\u0644\u0648"
    ],
    "name:msa_x_preferred":[
        "Moradlu"
    ],
    "name:mzn_x_preferred":[
        "\u0645\u0631\u0627\u062f\u0644\u0648"
    ],
    "name:pol_x_preferred":[
        "Moradlu"
    ],
    "name:und_x_variant":[
        "Mor\u0101dl\u016b"
    ],
    "wof:name":"Moradlu",
    "wof:placetype":"locality"
},
  "geometry": {"coordinates":[47.7478,38.7471],"type":"Point"}
}