{
  "type": "Feature",
  "properties": {
    "gn:admin1_code":"15",
    "gn:asciiname":"Tali",
    "gn:country_code":"IR",
    "gn:dem":561,
    "gn:feature_class":"P",
    "gn:feature_code":"PPL",
    "gn:name":"T\u0101l\u012b",
    "gn:population":0,
    "gn:timezone":"Asia/Tehran",
    "iso:country":"IR",
    "name:ceb_x_preferred":[
        "Tali"
    ],
    "name:deu_x_preferred":[
        "Tali"
    ],
    "name:fas_x_preferred":[
        "T\u0101l\u012b"
    ],
    "name:fas_x_variant":[
        "T\u016bl\u012b"
    ],
    "name:fin_x_preferred":[
        "Tali"
    ],
    "name:fra_x_preferred":[
        "Tali"
    ],
    "name:heb_x_preferred":[
        "\u05d8\u05dc\u05d9"
    ],
    "name:nld_x_preferred":[
        "Tali"
    ],
    "name:ron_x_preferred":[
        "Tali"
    ],
    "name:rus_x_preferred":[
        "\u0422\u0430\u043b\u0438"
    ],
    "name:swe_x_preferred":[
        "Tali"
    ],
    "name:und_x_variant":[
        "T\u016bl\u012b"
    ],
    "wof:name":"Tali",
    "wof:placetype":"locality"
},
  "geometry": {"coordinates":[49.6625,32.21111],"type":"Point"}
}