{
  "type": "Feature",
  "properties": {
    "gn:admin1_code":"15",
    "gn:asciiname":"Tali",
    "gn:country_code":"IR",
    "gn:dem":561,
    "gn:feature_class":"P",
    "gn:feature_code":"PPL",
    "gn:name":"T\u0101l\u012b",
    "gn:population":0,
    "gn:timezone":"Asia/Tehran",
    "iso:country":"IR",
    "name:fas_x_preferred":[
        "T\u0101l\u012b"
    ],
    "name:fas_x_variant":[
        "T\u016bl\u012b"
    ],
    "name:und_x_variant":[
        "T\u016bl\u012b"
    ],
    "wof:name":"Tali",
    "wof:placetype":"locality"
},
  "geometry": {"coordinates":[49.6625,32.21111],"type":"Point"}
}