{
  "type": "Feature",
  "properties": {
    "gn:admin1_code":"29",
    "gn:asciiname":"Sharifabad",
    "gn:country_code":"IR",
    "gn:dem":1889,
    "gn:feature_class":"P",
    "gn:feature_code":"PPL",
    "gn:name":"Shar\u012bf\u0101b\u0101d",
    "gn:population":0,
    "gn:timezone":"Asia/Tehran",
    "iso:country":"IR",
    "name:aze_x_preferred":[
        "\u015e\u0259rifabad"
    ],
    "name:fas_x_preferred":[
        "\u0634\u0631\u06cc\u06a9 \u0622\u0628\u0627\u062f"
    ],
    "name:fas_x_variant":[
        "Shar\u012bk\u0101b\u0101d",
        "\u0634\u0631\u06cc\u0641 \u0622\u0628\u0627\u062f",
        "\u0634\u0631\u06cc\u0641\u200c\u0622\u0628\u0627\u062f"
    ],
    "name:rus_x_preferred":[
        "\u0428\u0435\u0440\u0438\u0444\u0430\u0431\u0430\u0434"
    ],
    "name:und_x_variant":[
        "Shar\u012bf\u0101b\u0101d"
    ],
    "wof:name":"Sharifabad",
    "wof:placetype":"locality"
},
  "geometry": {"coordinates":[56.9649,28.2077],"type":"Point"}
}