{
  "type": "Feature",
  "properties": {
    "gn:admin1_code":"43",
    "gn:asciiname":"Shurak",
    "gn:country_code":"IR",
    "gn:dem":1218,
    "gn:feature_class":"P",
    "gn:feature_code":"PPL",
    "gn:name":"Sh\u016brak",
    "gn:population":0,
    "gn:timezone":"Asia/Tehran",
    "iso:country":"IR",
    "name:ceb_x_preferred":[
        "Shurak"
    ],
    "name:fas_x_preferred":[
        "Sh\u016br\u012bk-e Takmar\u0101n"
    ],
    "name:fas_x_variant":[
        "Sh\u016brak",
        "\u0634\u0648\u0631\u06a9"
    ],
    "name:swe_x_preferred":[
        "Shurak"
    ],
    "wof:name":"Shurak",
    "wof:placetype":"locality"
},
  "geometry": {"coordinates":[57.69226999999999,37.37665],"type":"Point"}
}