{
  "type": "Feature",
  "properties": {
    "gn:admin1_code":"30",
    "gn:asciiname":"Baleshabad",
    "gn:country_code":"IR",
    "gn:dem":1503,
    "gn:feature_class":"P",
    "gn:feature_code":"PPL",
    "gn:name":"B\u0101lesh\u0101b\u0101d",
    "gn:population":0,
    "gn:timezone":"Asia/Tehran",
    "iso:country":"IR",
    "wof:name":"Baleshabad",
    "wof:placetype":"locality"
},
  "geometry": {"coordinates":[57.52139,36.37639],"type":"Point"}
}