{
  "type": "Feature",
  "properties": {
    "gn:admin1_code":"29",
    "gn:asciiname":"Godar-e `Eyn od Din",
    "gn:country_code":"IR",
    "gn:dem":2703,
    "gn:feature_class":"P",
    "gn:feature_code":"PPL",
    "gn:name":"God\u0101r-e \u2018Eyn od D\u012bn",
    "gn:population":0,
    "gn:timezone":"Asia/Tehran",
    "iso:country":"IR",
    "name:fas_x_preferred":[
        "God\u0101r-e \u2018Eyn od D\u012bn"
    ],
    "name:fas_x_variant":[
        "\u06af\u062f\u0627\u0631 \u0639\u064a\u0646 \u0627\u0644\u062f\u064a\u0646"
    ],
    "wof:name":"Godar-e `Eyn od Din",
    "wof:placetype":"locality"
},
  "geometry": {"coordinates":[55.3425,30.33194],"type":"Point"}
}