{
  "type": "Feature",
  "properties": {
    "gn:admin1_code":"4.0",
    "gn:asciiname":"Radu-ye Bala",
    "gn:country_code":"IR",
    "gn:dem":30,
    "gn:feature_class":"P",
    "gn:feature_code":"PPL",
    "gn:name":"R\u0101d\u016b-ye B\u0101l\u0101",
    "gn:population":0,
    "gn:timezone":"Asia/Tehran",
    "iso:country":"IR",
    "name:fas_x_preferred":[
        "R\u0101d\u016b-ye B\u0101l\u0101"
    ],
    "name:fas_x_variant":[
        "\u0631\u0627\u062f\u0648 \u0628\u0627\u0644\u0627"
    ],
    "name:und_x_variant":[
        "\u0631\u0627\u062f\u0648 \u0628\u0627\u0644\u0627"
    ],
    "wof:name":"Radu-ye Bala",
    "wof:placetype":"locality"
},
  "geometry": {"coordinates":[61.12009000000001,25.61234],"type":"Point"}
}