{
  "type": "Feature",
  "properties": {
    "gn:admin1_code":"1",
    "gn:asciiname":"Sari Ojaq",
    "gn:country_code":"IR",
    "gn:dem":2163,
    "gn:feature_class":"P",
    "gn:feature_code":"PPL",
    "gn:name":"S\u0101r\u012b Oj\u0101q",
    "gn:population":0,
    "gn:timezone":"Asia/Tehran",
    "iso:country":"IR",
    "name:ara_x_preferred":[
        "\u0633\u0627\u0631\u064a\u0627\u062c\u0627\u0642"
    ],
    "name:aze_x_preferred":[
        "Sar\u0131 Ocaq"
    ],
    "name:ceb_x_preferred":[
        "S\u0101r\u012b Oj\u0101q"
    ],
    "name:fas_x_preferred":[
        "\u0633\u0627\u0631\u06cc \u0627\u064f\u062c\u0627\u0642"
    ],
    "name:fas_x_variant":[
        "S\u0101r\u012b Oj\u0101q",
        "\u0633\u0627\u0631\u06cc \u0627\u062c\u0627\u0642",
        "\u0633\u0627\u0631\u06cc\u200c\u0627\u062c\u0627\u0642"
    ],
    "name:msa_x_preferred":[
        "Sari Ojaq"
    ],
    "name:swe_x_preferred":[
        "S\u0101r\u012b Oj\u0101q"
    ],
    "wof:name":"Sari Ojaq",
    "wof:placetype":"locality"
},
  "geometry": {"coordinates":[44.262,39.3807],"type":"Point"}
}