{
  "type": "Feature",
  "properties": {
    "gn:admin1_code":"26",
    "gn:asciiname":"Mahalleh-ye Darabad",
    "gn:country_code":"IR",
    "gn:dem":1703,
    "gn:feature_class":"P",
    "gn:feature_code":"PPL",
    "gn:name":"Ma\u1e29alleh-ye D\u0101r\u0101b\u0101d",
    "gn:population":0,
    "gn:timezone":"Asia/Tehran",
    "iso:country":"IR",
    "name:fas_x_preferred":[
        "\u0645\u062d\u0644\u0645\u0647 \u062f\u0627\u0631 \u0622\u0628\u0627\u062f"
    ],
    "name:und_x_variant":[
        "Ma\u1e29alleh-ye D\u0101r\u0101b\u0101d"
    ],
    "wof:name":"Mahalleh-ye Darabad",
    "wof:placetype":"locality"
},
  "geometry": {"coordinates":[51.4914,35.8183],"type":"Point"}
}