{
  "type": "Feature",
  "properties": {
    "gn:admin1_code":"15",
    "gn:asciiname":"Yadi",
    "gn:country_code":"IR",
    "gn:dem":33,
    "gn:feature_class":"P",
    "gn:feature_code":"PPL",
    "gn:name":"Yad\u012b",
    "gn:population":0,
    "gn:timezone":"Asia/Tehran",
    "iso:country":"IR",
    "name:fas_x_preferred":[
        "\u0628\u06cc\u062a \u06cc\u062f\u06cc"
    ],
    "name:fas_x_variant":[
        "Yad\u012b",
        "Beyt-e Yad\u012b",
        "\u06cc\u062f\u06cc"
    ],
    "wof:name":"Yadi",
    "wof:placetype":"locality"
},
  "geometry": {"coordinates":[48.63421,31.82797],"type":"Point"}
}