{
  "type": "Feature",
  "properties": {
    "gn:admin1_code":"28",
    "gn:asciiname":"Panj",
    "gn:country_code":"IR",
    "gn:dem":2001,
    "gn:feature_class":"P",
    "gn:feature_code":"PPL",
    "gn:name":"Panj",
    "gn:population":0,
    "gn:timezone":"Asia/Tehran",
    "iso:country":"IR",
    "name:ara_x_preferred":[
        "\u0628\u0646\u062c"
    ],
    "name:fas_x_preferred":[
        "\u067e\u0646\u062c"
    ],
    "wof:name":"Panj",
    "wof:placetype":"locality"
},
  "geometry": {"coordinates":[52.5389,33.1853],"type":"Point"}
}