{
  "type": "Feature",
  "properties": {
    "gn:admin1_code":"16",
    "gn:asciiname":"Namshir",
    "gn:country_code":"IR",
    "gn:dem":1366,
    "gn:feature_class":"P",
    "gn:feature_code":"PPL",
    "gn:name":"Namsh\u012br",
    "gn:population":0,
    "gn:timezone":"Asia/Tehran",
    "iso:country":"IR",
    "name:fas_x_preferred":[
        "\u0646\u064e\u0645\u064e\u0634\u064a\u0631"
    ],
    "name:fas_x_variant":[
        "\u0646\u064e\u0645\u0634\u064a\u0631",
        "\u0646\u0645\u0634\u06cc\u0631",
        "Namash\u012br",
        "Namsh\u012br"
    ],
    "wof:name":"Namshir",
    "wof:placetype":"locality"
},
  "geometry": {"coordinates":[45.7358,36.1319],"type":"Point"}
}