{
  "type": "Feature",
  "properties": {
    "gn:admin1_code":"29.0",
    "gn:asciiname":"Borjak",
    "gn:country_code":"IR",
    "gn:dem":593,
    "gn:feature_class":"P",
    "gn:feature_code":"PPLL",
    "gn:name":"Borjak",
    "gn:population":0,
    "gn:timezone":"Asia/Tehran",
    "iso:country":"IR",
    "name:fas_x_preferred":[
        "\u0639\u0628\u0627\u0633 \u0622\u0628\u0627\u062f \u0628\u0631\u062c\u06a9"
    ],
    "name:fas_x_variant":[
        "\u2018Abb\u0101s\u0101b\u0101d",
        "\u2018Abb\u0101s\u0101b\u0101d-e Borjak",
        "\u0628\u0631\u062c\u06a9",
        "\u0628\u0631\u062c \u0639\u0628\u0627\u0633 \u0622\u0628\u0627\u062f"
    ],
    "name:und_x_variant":[
        "Borj \u2018Abb\u0101s\u0101b\u0101d"
    ],
    "wof:name":"Borjak",
    "wof:placetype":"locality"
},
  "geometry": {"coordinates":[58.52132,28.02771],"type":"Point"}
}