{
  "type": "Feature",
  "properties": {
    "gn:admin1_code":"34",
    "gn:asciiname":"Khorramabad-e Qar Kariz",
    "gn:country_code":"IR",
    "gn:dem":2138,
    "gn:feature_class":"P",
    "gn:feature_code":"PPL",
    "gn:name":"Khorram\u0101b\u0101d-e Q\u0101r K\u0101r\u012bz",
    "gn:population":0,
    "gn:timezone":"Asia/Tehran",
    "iso:country":"IR",
    "name:fas_x_preferred":[
        "\u062e\u0648\u0631\u064e\u0651\u0645 \u0622\u0628\u0627\u062f"
    ],
    "name:fas_x_variant":[
        "Khorram\u0101b\u0101d",
        "\u062e\u0631\u0645 \u0622\u0628\u0627\u062f",
        "\u062e\u0631\u0645 \u0622\u0628\u0627\u062f \u0642\u0627\u0631 \u06a9\u0627\u0631\u06cc\u0632"
    ],
    "name:und_x_variant":[
        "Kh\u016brram\u0101b\u0101d",
        "\u062e\u0631\u0645 \u0622\u0628\u0627\u062f",
        "Khorram\u0101b\u0101d-e Q\u0101r K\u0101r\u012bz"
    ],
    "wof:name":"Khorramabad-e Qar Kariz",
    "wof:placetype":"locality"
},
  "geometry": {"coordinates":[49.71464,33.78998],"type":"Point"}
}