{
  "type": "Feature",
  "properties": {
    "gn:admin1_code":"33",
    "gn:asciiname":"Do Deh",
    "gn:country_code":"IR",
    "gn:dem":1675,
    "gn:feature_class":"P",
    "gn:feature_code":"PPL",
    "gn:name":"Do Deh",
    "gn:population":0,
    "gn:timezone":"Asia/Tehran",
    "iso:country":"IR",
    "name:ceb_x_preferred":[
        "Do Deh"
    ],
    "name:fas_x_preferred":[
        "\u062f\u0648 \u062f\u0647"
    ],
    "name:fas_x_variant":[
        "\u062f\u0648\u062f\u0647"
    ],
    "name:msa_x_preferred":[
        "Do Deh"
    ],
    "name:swe_x_preferred":[
        "Do Deh"
    ],
    "name:und_x_variant":[
        "Dodeh"
    ],
    "wof:name":"Do Deh",
    "wof:placetype":"locality"
},
  "geometry": {"coordinates":[47.1658,37.4234],"type":"Point"}
}