{
  "type": "Feature",
  "properties": {
    "gn:admin1_code":"41",
    "gn:asciiname":"Kalateh-ye Hoseyn Mohammad Qasem",
    "gn:country_code":"IR",
    "gn:dem":1737,
    "gn:feature_class":"P",
    "gn:feature_code":"PPL",
    "gn:name":"Kal\u0101teh-ye \u1e28oseyn Mo\u1e29ammad Q\u0101sem",
    "gn:population":0,
    "gn:timezone":"Asia/Tehran",
    "iso:country":"IR",
    "name:fas_x_preferred":[
        "Kal\u0101teh-ye Mashhad\u012b \u1e28oseyn"
    ],
    "name:fas_x_variant":[
        "\u06a9\u0644\u0627\u062a\u0647 \u062d\u0633\u06cc\u0646 \u0645\u062d\u0645\u062f \u0642\u0627\u0633\u0645",
        "\u06a9\u0644\u0627\u062a\u0647 \u0645\u0634\u0647\u062f\u06cc \u062d\u0633\u06cc\u0646"
    ],
    "name:und_x_variant":[
        "Qal\u0101teh Meshedi Husain",
        "Kal\u0101teh-ye \u1e28oseyn Mo\u1e29ammad Q\u0101sem"
    ],
    "wof:name":"Kalateh-ye Hoseyn Mohammad Qasem",
    "wof:placetype":"locality"
},
  "geometry": {"coordinates":[59.63444000000001,31.79859],"type":"Point"}
}