{
  "type": "Feature",
  "properties": {
    "gn:admin1_code":"4.0",
    "gn:asciiname":"Abtorsh",
    "gn:country_code":"IR",
    "gn:dem":1405,
    "gn:feature_class":"P",
    "gn:feature_code":"PPL",
    "gn:name":"\u0100btorsh",
    "gn:population":0,
    "gn:timezone":"Asia/Tehran",
    "iso:country":"IR",
    "name:fas_x_preferred":[
        "\u0622\u0628\u062a\u0631\u0634"
    ],
    "name:und_x_variant":[
        "\u0100btorsh"
    ],
    "wof:name":"Abtorsh",
    "wof:placetype":"locality"
},
  "geometry": {"coordinates":[61.2312,28.213],"type":"Point"}
}