{
  "type": "Feature",
  "properties": {
    "gn:admin1_code":"23",
    "gn:asciiname":"Aqa Abul",
    "gn:country_code":"IR",
    "gn:dem":1899,
    "gn:feature_class":"P",
    "gn:feature_code":"PPL",
    "gn:name":"\u0100q\u0101 Ab\u016bl",
    "gn:population":0,
    "gn:timezone":"Asia/Tehran",
    "iso:country":"IR",
    "name:fas_x_preferred":[
        "\u0100q\u0101 Ab\u016bl"
    ],
    "name:und_x_variant":[
        "\u0100gha \u2018Abul"
    ],
    "wof:name":"Aqa Abul",
    "wof:placetype":"locality"
},
  "geometry": {"coordinates":[48.13333,34.05],"type":"Point"}
}