{
  "type": "Feature",
  "properties": {
    "gn:admin1_code":"33",
    "gn:asciiname":"Eshaqlu",
    "gn:country_code":"IR",
    "gn:dem":2141,
    "gn:feature_class":"P",
    "gn:feature_code":"PPL",
    "gn:name":"Eshaql\u016b",
    "gn:population":0,
    "gn:timezone":"Asia/Tehran",
    "iso:country":"IR",
    "name:fas_x_preferred":[
        "\u0627\u0634\u0642\u0644\u0648"
    ],
    "name:fas_x_variant":[
        "\u012ashaql\u016b",
        "Eshaql\u016b",
        "\u0627\u06cc\u0634\u0642\u0644\u0648"
    ],
    "name:msa_x_preferred":[
        "Eshaqlu"
    ],
    "name:und_x_variant":[
        "Ishikhli",
        "Ashghaloo",
        "Esheql\u016b"
    ],
    "wof:name":"Eshaqlu",
    "wof:placetype":"locality"
},
  "geometry": {"coordinates":[46.5698,38.4319],"type":"Point"}
}