{
  "type": "Feature",
  "properties": {
    "gn:admin1_code":"4.0",
    "gn:asciiname":"Dust Mohammad Khan",
    "gn:country_code":"IR",
    "gn:dem":483,
    "gn:feature_class":"P",
    "gn:feature_code":"PPLA2",
    "gn:name":"D\u016bst Mo\u1e29ammad Kh\u0101n",
    "gn:population":0,
    "gn:timezone":"Asia/Tehran",
    "iso:country":"IR",
    "name:fas_x_preferred":[
        "\u062f\u0648\u0633\u062a \u0645\u062d\u0645\u062f \u062e\u0627\u0646"
    ],
    "name:fas_x_variant":[
        "D\u016bst Mo\u1e29ammad Kh\u0101n"
    ],
    "wof:name":"Dust Mohammad Khan",
    "wof:placetype":"locality"
},
  "geometry": {"coordinates":[61.7925,31.1447],"type":"Point"}
}