{
  "type": "Feature",
  "properties": {
    "gn:admin1_code":"7",
    "gn:asciiname":"Katas Bes",
    "gn:cc2":"IR",
    "gn:country_code":"IR",
    "gn:dem":1521,
    "gn:feature_class":"P",
    "gn:feature_code":"PPL",
    "gn:name":"Katas Bes",
    "gn:population":0,
    "gn:timezone":"Asia/Tehran",
    "iso:country":"IR",
    "name:und_x_variant":[
        "Katispis",
        "Katas Bes"
    ],
    "wof:name":"Katas Bes",
    "wof:placetype":"locality"
},
  "geometry": {"coordinates":[52.5275,29.56472],"type":"Point"}
}