{
  "type": "Feature",
  "properties": {
    "gn:admin1_code":"37",
    "gn:asciiname":"Turang Tappeh",
    "gn:country_code":"IR",
    "gn:dem":143,
    "gn:feature_class":"P",
    "gn:feature_code":"PPL",
    "gn:name":"T\u016brang Tappeh",
    "gn:population":0,
    "gn:timezone":"Asia/Tehran",
    "iso:country":"IR",
    "name:ara_x_preferred":[
        "\u062a\u0648\u0631\u0627\u0646\u063a \u062a\u0628\u0629"
    ],
    "name:fas_x_preferred":[
        "T\u016brang Tappeh"
    ],
    "name:fas_x_variant":[
        "\u062a\u0648\u0631\u0646\u06af \u062a\u067e\u0647"
    ],
    "name:msa_x_preferred":[
        "Turang Tappeh"
    ],
    "wof:name":"Turang Tappeh",
    "wof:placetype":"locality"
},
  "geometry": {"coordinates":[55.46554,37.32482],"type":"Point"}
}