{
  "type": "Feature",
  "properties": {
    "gn:admin1_code":"16",
    "gn:asciiname":"Doveyseh",
    "gn:country_code":"IR",
    "gn:dem":1675,
    "gn:feature_class":"P",
    "gn:feature_code":"PPL",
    "gn:name":"Doveyseh",
    "gn:population":0,
    "gn:timezone":"Asia/Tehran",
    "iso:country":"IR",
    "name:fas_x_preferred":[
        "\u062f\u0648\u06cc\u0633\u0647"
    ],
    "name:und_x_variant":[
        "Duvizeh",
        "Duwizeh",
        "Dow V\u012bseh",
        "Dow Veyseh",
        "Doosiyeh",
        "D\u016b\u012bseh",
        "Doveyseh"
    ],
    "wof:name":"Doveyseh",
    "wof:placetype":"locality"
},
  "geometry": {"coordinates":[46.8945,35.4559],"type":"Point"}
}