{
  "type": "Feature",
  "properties": {
    "gn:admin1_code":"22",
    "gn:asciiname":"Bidu",
    "gn:country_code":"IR",
    "gn:dem":583,
    "gn:feature_class":"P",
    "gn:feature_code":"PPL",
    "gn:name":"B\u012bd\u016b",
    "gn:population":0,
    "gn:timezone":"Asia/Tehran",
    "iso:country":"IR",
    "name:ara_x_preferred":[
        "\u0628\u064a\u062f\u0648"
    ],
    "name:fas_x_preferred":[
        "\u0628\u064a\u062f\u0648 \u0633\u064e\u0631\u062d\u064e\u062f"
    ],
    "name:fas_x_variant":[
        "B\u012bd\u016b",
        "B\u012bd\u016b Sar\u1e29ad",
        "\u0628\u064a\u062f\u0648",
        "\u0628\u06cc\u062f\u0648"
    ],
    "name:msa_x_preferred":[
        "Bidu"
    ],
    "wof:name":"Bidu",
    "wof:placetype":"locality"
},
  "geometry": {"coordinates":[52.272,27.9776],"type":"Point"}
}