{
  "type": "Feature",
  "properties": {
    "gn:admin1_code":"11",
    "gn:asciiname":"Gashk",
    "gn:country_code":"IR",
    "gn:dem":47,
    "gn:feature_class":"P",
    "gn:feature_code":"PPL",
    "gn:name":"Gashk",
    "gn:population":0,
    "gn:timezone":"Asia/Tehran",
    "iso:country":"IR",
    "name:fas_x_preferred":[
        "\u06af\u0634\u06a9"
    ],
    "name:fas_x_variant":[
        "\u06af\u0634\u0645\u06cc \u0628\u0627\u0644\u0627"
    ],
    "name:und_x_variant":[
        "Gashmak",
        "Gashk",
        "Gashm\u012b-ye B\u0101l\u0101"
    ],
    "wof:name":"Gashk",
    "wof:placetype":"locality"
},
  "geometry": {"coordinates":[58.8912,25.71632],"type":"Point"}
}