{
  "type": "Feature",
  "properties": {
    "gn:admin1_code":"7",
    "gn:asciiname":"Eslamabad",
    "gn:country_code":"IR",
    "gn:dem":1084,
    "gn:feature_class":"P",
    "gn:feature_code":"PPL",
    "gn:name":"Esl\u0101m\u0101b\u0101d",
    "gn:population":0,
    "gn:timezone":"Asia/Tehran",
    "iso:country":"IR",
    "name:fas_x_preferred":[
        "\u0627\u0633\u0644\u0627\u0645 \u0622\u0628\u0627\u062f"
    ],
    "name:fas_x_variant":[
        "Esl\u0101m\u0101b\u0101d"
    ],
    "wof:name":"Eslamabad",
    "wof:placetype":"locality"
},
  "geometry": {"coordinates":[54.4149,28.732],"type":"Point"}
}