{
  "type": "Feature",
  "properties": {
    "gn:admin1_code":"33",
    "gn:asciiname":"Kond Rud",
    "gn:country_code":"IR",
    "gn:dem":1705,
    "gn:feature_class":"P",
    "gn:feature_code":"PPL",
    "gn:name":"Kond R\u016bd",
    "gn:population":0,
    "gn:timezone":"Asia/Tehran",
    "iso:country":"IR",
    "name:fas_x_preferred":[
        "\u06a9\u0646\u062f \u0631\u0648\u062f"
    ],
    "name:fas_x_variant":[
        "Kondo R\u016bd",
        "Kond R\u016bd",
        "\u06a9\u0646\u062f\u0631\u0648\u062f"
    ],
    "name:msa_x_preferred":[
        "Kond Rud"
    ],
    "name:und_x_variant":[
        "Kand Rood\u00e9 Mehranrood",
        "Kondor\u012b",
        "Kunduri"
    ],
    "wof:name":"Kond Rud",
    "wof:placetype":"locality"
},
  "geometry": {"coordinates":[46.4785,38.0097],"type":"Point"}
}