{
  "type": "Feature",
  "properties": {
    "gn:admin1_code":"41",
    "gn:asciiname":"Ivask",
    "gn:country_code":"IR",
    "gn:dem":1484,
    "gn:feature_class":"P",
    "gn:feature_code":"PPL",
    "gn:name":"\u012av\u0101sk",
    "gn:population":0,
    "gn:timezone":"Asia/Tehran",
    "iso:country":"IR",
    "name:fas_x_preferred":[
        "\u012av\u0101sk"
    ],
    "name:fas_x_variant":[
        "\u0627\u06cc\u0648\u0627\u0633\u06a9",
        "\u06a9\u0644\u0627\u062a\u0647 \u0622\u0648\u0627\u0632"
    ],
    "name:und_x_variant":[
        "Hivask",
        "\u0100v\u0101z",
        "Kal\u0101teh-ye \u0100v\u0101z"
    ],
    "wof:name":"Ivask",
    "wof:placetype":"locality"
},
  "geometry": {"coordinates":[59.41928000000001,31.64788],"type":"Point"}
}