{
  "type": "Feature",
  "properties": {
    "gn:admin1_code":"15",
    "gn:asciiname":"Ramseh",
    "gn:country_code":"IR",
    "gn:dem":19,
    "gn:feature_class":"P",
    "gn:feature_code":"PPL",
    "gn:name":"R\u0101mseh",
    "gn:population":0,
    "gn:timezone":"Asia/Tehran",
    "iso:country":"IR",
    "name:fas_x_preferred":[
        "R\u0101mseh"
    ],
    "name:fas_x_variant":[
        "\u0631\u0627\u0645\u0633\u0647",
        "\u0631\u0645\u0633\u0647 \u06cc\u06a9",
        "\u0631\u0627\u0645\u0633\u0647 \u06cc\u06a9"
    ],
    "name:und_x_variant":[
        "Rameseh",
        "Ramseh-ye Yek",
        "R\u0101mseh-ye Yek"
    ],
    "wof:name":"Ramseh",
    "wof:placetype":"locality"
},
  "geometry": {"coordinates":[48.45641,31.37327],"type":"Point"}
}