{
  "type": "Feature",
  "properties": {
    "gn:admin1_code":"40.0",
    "gn:asciiname":"Bafru'iyeh",
    "gn:country_code":"IR",
    "gn:dem":1058,
    "gn:feature_class":"P",
    "gn:feature_code":"PPL",
    "gn:name":"Bafr\u016b\u2019\u012byeh",
    "gn:population":0,
    "gn:timezone":"Asia/Tehran",
    "iso:country":"IR",
    "name:fas_x_preferred":[
        "\u0628\u0641\u0631\u0648\u0626\u064a\u0647"
    ],
    "name:fas_x_variant":[
        "Bafr\u016b\u2019\u012byeh"
    ],
    "name:und_x_variant":[
        "Bafruyeh"
    ],
    "wof:name":"Bafru'iyeh",
    "wof:placetype":"locality"
},
  "geometry": {"coordinates":[53.9942,32.2766],"type":"Point"}
}