{
  "type": "Feature",
  "properties": {
    "gn:admin1_code":"11",
    "gn:asciiname":"Keshar-e Chamardan",
    "gn:country_code":"IR",
    "gn:dem":38,
    "gn:feature_class":"P",
    "gn:feature_code":"PPL",
    "gn:name":"Kesh\u0101r-e Chamard\u0101n",
    "gn:population":0,
    "gn:timezone":"Asia/Tehran",
    "iso:country":"IR",
    "name:ceb_x_preferred":[
        "Kesh\u0101r-e Chamard\u0101n"
    ],
    "name:fas_x_preferred":[
        "\u0643\u0634\u0627\u0631 \u0686\u0645\u0631\u062f\u0627\u0646"
    ],
    "name:fas_x_variant":[
        "\u06a9\u0634\u0627\u0631\u0686\u0645\u0631\u062f\u0627\u0646"
    ],
    "name:msa_x_preferred":[
        "Keshar-e Chemerdan"
    ],
    "name:swe_x_preferred":[
        "Kesh\u0101r-e Chamard\u0101n"
    ],
    "wof:name":"Keshar-e Chamardan",
    "wof:placetype":"locality"
},
  "geometry": {"coordinates":[55.97656,27.2463],"type":"Point"}
}