{
  "type": "Feature",
  "properties": {
    "gn:admin1_code":"15",
    "gn:asciiname":"Khadijeh",
    "gn:country_code":"IR",
    "gn:dem":321,
    "gn:feature_class":"P",
    "gn:feature_code":"PPLF",
    "gn:name":"Khad\u012bjeh",
    "gn:population":0,
    "gn:timezone":"Asia/Tehran",
    "iso:country":"IR",
    "name:fas_x_preferred":[
        "\u062e\u062f\u06cc\u062c\u0647"
    ],
    "name:fas_x_variant":[
        "\u062f\u0645 \u062f\u0631\u0627\u0632"
    ],
    "name:und_x_variant":[
        "Barshgoft",
        "Khad\u012bjeh",
        "Dom Der\u0101z"
    ],
    "wof:name":"Khadijeh",
    "wof:placetype":"locality"
},
  "geometry": {"coordinates":[49.83758,31.10785],"type":"Point"}
}