{
  "type": "Feature",
  "properties": {
    "gn:admin1_code":"32",
    "gn:asciiname":"Bileh Daraq",
    "gn:country_code":"IR",
    "gn:dem":1886,
    "gn:feature_class":"P",
    "gn:feature_code":"PPL",
    "gn:name":"B\u012bleh Daraq",
    "gn:population":0,
    "gn:timezone":"Asia/Tehran",
    "iso:country":"IR",
    "name:fas_x_preferred":[
        "\u0628\u06cc\u0644\u0647 \u062f\u0631\u0642"
    ],
    "name:fas_x_variant":[
        "B\u012bleh Daraq"
    ],
    "name:und_x_variant":[
        "B\u012blah Daraq"
    ],
    "wof:name":"Bileh Daraq",
    "wof:placetype":"locality"
},
  "geometry": {"coordinates":[48.6037,38.1434],"type":"Point"}
}