{
  "type": "Feature",
  "properties": {
    "gn:admin1_code":"4.0",
    "gn:asciiname":"Sar Deh",
    "gn:country_code":"IR",
    "gn:dem":2065,
    "gn:feature_class":"P",
    "gn:feature_code":"PPL",
    "gn:name":"Sar Deh",
    "gn:population":0,
    "gn:timezone":"Asia/Tehran",
    "iso:country":"IR",
    "name:fas_x_preferred":[
        "\u0633\u0631 \u062f\u0647"
    ],
    "wof:name":"Sar Deh",
    "wof:placetype":"locality"
},
  "geometry": {"coordinates":[61.15423000000001,28.67872],"type":"Point"}
}