{
  "type": "Feature",
  "properties": {
    "gn:admin1_code":"4.0",
    "gn:asciiname":"Shahbaz",
    "gn:country_code":"IR",
    "gn:dem":490,
    "gn:feature_class":"P",
    "gn:feature_code":"PPL",
    "gn:name":"Shahb\u0101z",
    "gn:population":0,
    "gn:timezone":"Asia/Tehran",
    "iso:country":"IR",
    "name:fas_x_preferred":[
        "\u0634\u0647\u0628\u0627\u0632"
    ],
    "name:fas_x_variant":[
        "Deh-e M\u016bs\u00e1 Shahb\u0101z",
        "Shahb\u0101z",
        "\u0645\u0648\u0633\u06cc \u0634\u0647\u0628\u0627\u0632"
    ],
    "name:und_x_variant":[
        "M\u016bs\u00e1 Shahb\u0101z"
    ],
    "wof:name":"Shahbaz",
    "wof:placetype":"locality"
},
  "geometry": {"coordinates":[61.6672,30.9127],"type":"Point"}
}