{
  "type": "Feature",
  "properties": {
    "gn:admin1_code":"5.0",
    "gn:asciiname":"Ab Mu-ye Sofla",
    "gn:country_code":"IR",
    "gn:dem":662,
    "gn:feature_class":"P",
    "gn:feature_code":"PPL",
    "gn:name":"\u0100b M\u016b-ye Sofl\u00e1",
    "gn:population":0,
    "gn:timezone":"Asia/Tehran",
    "iso:country":"IR",
    "name:fas_x_preferred":[
        "\u0622\u0628 \u0645\u0648\u06cc \u0639\u0644\u06cc\u0627"
    ],
    "name:fas_x_variant":[
        "\u0100bm\u016b \u2018Oly\u0101",
        "\u0100b M\u016b-ye \u2018Oly\u0101",
        "\u0100b Mow",
        "\u0622\u0628 \u0645\u0648 \u0633\u0641\u0644\u06cc"
    ],
    "name:und_x_variant":[
        "\u0100b Mow",
        "\u0100b M\u016b-ye Sofl\u00e1",
        "\u0100bm\u016b Sofl\u00e1"
    ],
    "wof:name":"Ab Mu-ye Sofla",
    "wof:placetype":"locality"
},
  "geometry": {"coordinates":[50.3783,30.869],"type":"Point"}
}