{
  "type": "Feature",
  "properties": {
    "gn:admin1_code":"1",
    "gn:asciiname":"Khaledabad",
    "gn:country_code":"IR",
    "gn:dem":1390,
    "gn:feature_class":"P",
    "gn:feature_code":"PPL",
    "gn:name":"Kh\u0101led\u0101b\u0101d",
    "gn:population":0,
    "gn:timezone":"Asia/Tehran",
    "iso:country":"IR",
    "name:ara_x_preferred":[
        "\u062e\u0627\u0644\u062f\u0623\u0628\u0627\u062f"
    ],
    "name:aze_x_preferred":[
        "Xalidabad"
    ],
    "name:ceb_x_preferred":[
        "Kh\u0101led\u0101b\u0101d"
    ],
    "name:fas_x_preferred":[
        "\u062e\u0627\u0644\u062f \u0622\u0628\u0627\u062f"
    ],
    "name:fas_x_variant":[
        "Kh\u0101led\u0101b\u0101d",
        "\u062e\u0627\u0644\u062f\u0622\u0628\u0627\u062f"
    ],
    "name:mlg_x_preferred":[
        "Khaledabad"
    ],
    "name:rus_x_preferred":[
        "\u0425\u0430\u043b\u0435\u0434\u0430\u0431\u0430\u0434"
    ],
    "name:swe_x_preferred":[
        "Kh\u0101led\u0101b\u0101d"
    ],
    "name:tur_x_preferred":[
        "Halidabad"
    ],
    "wof:name":"Khaledabad",
    "wof:placetype":"locality"
},
  "geometry": {"coordinates":[45.1529,37.0173],"type":"Point"}
}