{
  "type": "Feature",
  "properties": {
    "gn:admin1_code":"38",
    "gn:asciiname":"Mir Khvand-e Sofla",
    "gn:country_code":"IR",
    "gn:dem":304,
    "gn:feature_class":"P",
    "gn:feature_code":"PPL",
    "gn:name":"M\u012br Khv\u0101nd-e Sofl\u00e1",
    "gn:population":0,
    "gn:timezone":"Asia/Tehran",
    "iso:country":"IR",
    "name:fas_x_preferred":[
        "\u0645\u064a\u0631 \u062e\u0648\u0627\u0646 \u067e\u0627\u0626\u064a\u0646"
    ],
    "name:fas_x_variant":[
        "M\u012br Kh\u016bnd-e P\u0101\u2019\u012bn",
        "M\u012br Khv\u0101n-e P\u0101\u2019\u012bn",
        "\u0645\u06cc\u0631 \u062e\u0648\u0627\u0646\u062f \u0633\u0641\u0644\u06cc"
    ],
    "name:und_x_variant":[
        "M\u012br Khov\u0101n-e P\u0101\u2019\u012bn",
        "M\u012br Khov\u0101n P\u0101\u2019\u012bn",
        "M\u012br Khovand-e Sofl\u00e1",
        "M\u012br Khv\u0101nd-e Sofl\u00e1"
    ],
    "wof:name":"Mir Khvand-e Sofla",
    "wof:placetype":"locality"
},
  "geometry": {"coordinates":[49.41629,36.66653],"type":"Point"}
}