{
  "type": "Feature",
  "properties": {
    "gn:admin1_code":"11",
    "gn:asciiname":"Patkonan-e Bala",
    "gn:country_code":"IR",
    "gn:dem":487,
    "gn:feature_class":"P",
    "gn:feature_code":"PPL",
    "gn:name":"Patkon\u0101n-e B\u0101l\u0101",
    "gn:population":0,
    "gn:timezone":"Asia/Tehran",
    "iso:country":"IR",
    "name:ara_x_preferred":[
        "\u0628\u062a\u06a9\u0646\u0627\u0646 \u0628\u0627\u0644\u0627"
    ],
    "name:fas_x_preferred":[
        "\u067e\u062a\u0643\u0646\u0648\u06cc \u0628\u0627\u0644\u0627"
    ],
    "name:fas_x_variant":[
        "\u067e\u064e\u062a\u0643\u064f\u0646\u064f\u0648\u06cc \u0628\u0627\u0644\u0627",
        "\u067e\u062a\u06a9\u0646\u0627\u0646 \u0628\u0627\u0644\u0627",
        "Patkon\u0101n",
        "Patkon\u016b-ye B\u0101l\u0101",
        "Napkon\u0101n",
        "\u067e\u062a\u0643\u0646\u0627\u0646",
        "\u0646\u067e\u0643\u0646\u0627\u0646",
        "Patkon\u0101n-e B\u0101l\u0101"
    ],
    "name:msa_x_preferred":[
        "Patkonan-e Bala"
    ],
    "name:und_x_variant":[
        "Patkonow-ye B\u0101l\u0101"
    ],
    "wof:name":"Patkonan-e Bala",
    "wof:placetype":"locality"
},
  "geometry": {"coordinates":[56.5284,27.7258],"type":"Point"}
}