{
  "type": "Feature",
  "properties": {
    "gn:admin1_code":"4.0",
    "gn:asciiname":"Jahan Tigh",
    "gn:country_code":"IR",
    "gn:dem":484,
    "gn:feature_class":"P",
    "gn:feature_code":"PPL",
    "gn:name":"Jah\u0101n T\u012bgh",
    "gn:population":0,
    "gn:timezone":"Asia/Tehran",
    "iso:country":"IR",
    "name:fas_x_preferred":[
        "\u062c\u0647\u0627\u0646 \u062a\u06cc\u063a"
    ],
    "name:fas_x_variant":[
        "Jah\u0101n T\u012bgh",
        "\u062c\u0647\u0627\u0646\u062a\u06cc\u063a",
        "\u062c\u0647\u0627\u0646\u200c\u062a\u06cc\u063a"
    ],
    "name:und_x_variant":[
        "Jah\u0101nt\u012bgh"
    ],
    "name:urd_x_preferred":[
        "\u062c\u06c1\u0627\u06ba \u062a\u06cc\u063a"
    ],
    "wof:name":"Jahan Tigh",
    "wof:placetype":"locality"
},
  "geometry": {"coordinates":[61.6765,31.0827],"type":"Point"}
}