{
  "type": "Feature",
  "properties": {
    "gn:admin1_code":"35.0",
    "gn:asciiname":"Lowlak-e Kaslian",
    "gn:country_code":"IR",
    "gn:dem":673,
    "gn:feature_class":"P",
    "gn:feature_code":"PPL",
    "gn:name":"Lowl\u0101k-e Kasl\u012b\u0101n",
    "gn:population":0,
    "gn:timezone":"Asia/Tehran",
    "iso:country":"IR",
    "name:ceb_x_preferred":[
        "Lowl\u0101k-e Kasl\u012b\u0101n"
    ],
    "name:fas_x_preferred":[
        "\u0644\u0648\u0644\u0627\u0643 \u0643\u0633\u0644\u064a\u0627\u0646"
    ],
    "name:fas_x_variant":[
        "\u0644\u0648\u0644\u064e\u0643\u0650 \u0643\u0650\u0633\u0650\u0644\u064a\u0627\u0646",
        "\u0644\u0648\u0644\u064e\u0643\u0650 \u0643\u0650\u0633\u0650\u0644\u0650\u064a\u0627\u0646",
        "Lowl\u0101k-e Kasl\u012b\u0101n",
        "\u0644\u0648\u0644\u0627\u06a9"
    ],
    "name:swe_x_preferred":[
        "Lowl\u0101k-e Kasl\u012b\u0101n"
    ],
    "name:und_x_variant":[
        "L\u016blak-e Keseley\u0101n",
        "L\u016blak-e Kesel\u012b\u0101n"
    ],
    "wof:name":"Lowlak-e Kaslian",
    "wof:placetype":"locality"
},
  "geometry": {"coordinates":[53.03536999999999,36.19964],"type":"Point"}
}