{
  "type": "Feature",
  "properties": {
    "gn:admin1_code":"4",
    "gn:asciiname":"Fiselabad",
    "gn:country_code":"IR",
    "gn:dem":1373,
    "gn:feature_class":"P",
    "gn:feature_code":"PPL",
    "gn:name":"F\u012b\u015fel\u0101b\u0101d",
    "gn:population":0,
    "gn:timezone":"Asia/Tehran",
    "iso:country":"IR",
    "name:fas_x_preferred":[
        "\u0641\u06cc\u0635\u0644 \u0622\u0628\u0627\u062f"
    ],
    "name:fas_x_variant":[
        "F\u012b\u015fel\u0101b\u0101d",
        "\u0641\u06cc\u0635\u0644\u200c\u0622\u0628\u0627\u062f"
    ],
    "wof:name":"Fiselabad",
    "wof:placetype":"locality"
},
  "geometry": {"coordinates":[60.48595,28.30642000000001],"type":"Point"}
}