{
  "type": "Feature",
  "properties": {
    "gn:admin1_code":"40",
    "gn:asciiname":"Kheskok",
    "gn:country_code":"IR",
    "gn:dem":2547,
    "gn:feature_class":"P",
    "gn:feature_code":"PPL",
    "gn:name":"Kheskok",
    "gn:population":0,
    "gn:timezone":"Asia/Tehran",
    "iso:country":"IR",
    "name:ceb_x_preferred":[
        "Kheskok"
    ],
    "name:fas_x_preferred":[
        "\u062e\u0650\u0633\u064f\u0643"
    ],
    "name:fas_x_variant":[
        "\u062e\u064f\u0633\u0643\u064e\u0643",
        "\u062e\u064f\u0633\u064f\u0643",
        "\u062e\u0633\u06a9\u06a9"
    ],
    "name:swe_x_preferred":[
        "Kheskok"
    ],
    "name:und_x_variant":[
        "Khoskak",
        "Khosok",
        "Khesok"
    ],
    "wof:name":"Kheskok",
    "wof:placetype":"locality"
},
  "geometry": {"coordinates":[54.07128,31.50961],"type":"Point"}
}