{
  "type": "Feature",
  "properties": {
    "gn:admin1_code":"5",
    "gn:asciiname":"Bilukhar",
    "gn:country_code":"IR",
    "gn:dem":1850,
    "gn:feature_class":"P",
    "gn:feature_code":"PPL",
    "gn:name":"B\u012bl\u016bkhar",
    "gn:population":0,
    "gn:timezone":"Asia/Tehran",
    "iso:country":"IR",
    "name:ara_x_preferred":[
        "\u0628\u064a\u0644\u0648\u062e\u0631"
    ],
    "name:ceb_x_preferred":[
        "B\u012bl\u016bkhar"
    ],
    "name:fas_x_preferred":[
        "\u0628\u064a\u0631\u0648\u062e\u0650\u0631"
    ],
    "name:fas_x_variant":[
        "\u0628\u064a\u0631\u064f\u0648\u062e\u0650\u0631",
        "B\u012br\u016bkher",
        "B\u012bl\u016bkhar",
        "\u0628\u06cc\u0644\u0648\u062e\u0631"
    ],
    "name:swe_x_preferred":[
        "B\u012bl\u016bkhar"
    ],
    "name:und_x_variant":[
        "B\u012browkher",
        "\u0628\u06cc\u0644\u0648\u062e\u0631"
    ],
    "wof:name":"Bilukhar",
    "wof:placetype":"locality"
},
  "geometry": {"coordinates":[51.00369,31.02613],"type":"Point"}
}