{
  "type": "Feature",
  "properties": {
    "gn:admin1_code":"42",
    "gn:asciiname":"Sangan",
    "gn:country_code":"IR",
    "gn:dem":1192,
    "gn:feature_class":"P",
    "gn:feature_code":"PPL",
    "gn:name":"Sang\u0101n",
    "gn:population":0,
    "gn:timezone":"Asia/Tehran",
    "iso:country":"IR",
    "name:ara_x_preferred":[
        "\u0633\u0646\u063a\u0627\u0646"
    ],
    "name:aze_x_preferred":[
        "S\u0259ngan"
    ],
    "name:ceb_x_preferred":[
        "Sang\u0101n"
    ],
    "name:fas_x_preferred":[
        "\u0633\u0646\u06af\u0627\u0646"
    ],
    "name:fas_x_variant":[
        "Sang\u0101n"
    ],
    "name:ita_x_preferred":[
        "Sangan"
    ],
    "name:mlg_x_preferred":[
        "Sangan"
    ],
    "name:swe_x_preferred":[
        "Sang\u0101n"
    ],
    "name:tur_x_preferred":[
        "Sengan"
    ],
    "name:und_x_variant":[
        "Sang\u016bn",
        "S\u0101ng\u016bn-e B\u0101l\u0101"
    ],
    "wof:name":"Sangan",
    "wof:placetype":"locality"
},
  "geometry": {"coordinates":[59.43666999999999,35.11528],"type":"Point"}
}