{
  "type": "Feature",
  "properties": {
    "gn:admin1_code":"1",
    "gn:asciiname":"Mamdal",
    "gn:country_code":"IR",
    "gn:dem":1299,
    "gn:feature_class":"P",
    "gn:feature_code":"PPL",
    "gn:name":"Mamdal",
    "gn:population":0,
    "gn:timezone":"Asia/Tehran",
    "iso:country":"IR",
    "name:fas_x_preferred":[
        "\u0645\u0645\u062f\u0644"
    ],
    "wof:name":"Mamdal",
    "wof:placetype":"locality"
},
  "geometry": {"coordinates":[46.14867,37.01646],"type":"Point"}
}