{
  "type": "Feature",
  "properties": {
    "gn:admin1_code":"0",
    "gn:asciiname":"Shahrak-e Godar Takhti",
    "gn:country_code":"IR",
    "gn:dem":654,
    "gn:feature_class":"P",
    "gn:feature_code":"PPL",
    "gn:name":"Shahrak-e God\u0101r Takht\u012b",
    "gn:population":0,
    "gn:timezone":"Asia/Tehran",
    "iso:country":"IR",
    "name:fas_x_preferred":[
        "\u0634\u0647\u0631\u06a9 \u06af\u062f\u0627\u0631 \u062a\u062e\u062a\u06cc"
    ],
    "name:fas_x_variant":[
        "Shahrak-e God\u0101r Takht\u012b"
    ],
    "wof:name":"Shahrak-e Godar Takhti",
    "wof:placetype":"locality"
},
  "geometry": {"coordinates":[50.0482,30.9865],"type":"Point"}
}