{
  "type": "Feature",
  "properties": {
    "gn:admin1_code":"15.0",
    "gn:asciiname":"`Ashireh-ye Beyt-e Yebareh",
    "gn:country_code":"IR",
    "gn:dem":34,
    "gn:feature_class":"P",
    "gn:feature_code":"PPL",
    "gn:name":"\u2018Ash\u012breh-ye Beyt-e Yeb\u0101reh",
    "gn:population":0,
    "gn:timezone":"Asia/Tehran",
    "iso:country":"IR",
    "name:fas_x_preferred":[
        "\u0628\u06cc\u062a \u06cc\u0628\u0627\u0631\u0647"
    ],
    "name:fas_x_variant":[
        "Beyt-e Yab\u0101reh",
        "\u0639\u0634\u06cc\u0631\u0647 \u0628\u06cc\u062a \u06cc\u0628\u0627\u0631\u0647",
        "\u0639\u0634\u0627\u0631\u0647 \u0628\u06cc\u062a \u06cc\u0628\u0627\u0631\u0647"
    ],
    "name:und_x_variant":[
        "\u2018Ash\u012breh-ye Beyt-e Yeb\u0101reh",
        "\u2018Ash\u0101reh-ye Beyt-e Yeb\u0101reh"
    ],
    "wof:name":"`Ashireh-ye Beyt-e Yebareh",
    "wof:placetype":"locality"
},
  "geometry": {"coordinates":[48.60915,31.8154],"type":"Point"}
}