{
  "type": "Feature",
  "properties": {
    "gn:admin1_code":"7",
    "gn:asciiname":"Sheshdeh",
    "gn:country_code":"IR",
    "gn:dem":1383,
    "gn:feature_class":"P",
    "gn:feature_code":"PPL",
    "gn:name":"Sheshdeh",
    "gn:population":0,
    "gn:timezone":"Asia/Tehran",
    "iso:country":"IR",
    "name:ara_x_preferred":[
        "\u0634\u0634\u062f\u0647"
    ],
    "name:aze_x_preferred":[
        "\u015ee\u015fdeh"
    ],
    "name:ceb_x_preferred":[
        "Sheshdeh"
    ],
    "name:fas_x_preferred":[
        "\u0634\u0634\u062f\u0647"
    ],
    "name:ita_x_preferred":[
        "Sheshdeh"
    ],
    "name:mlg_x_preferred":[
        "Sheshdeh"
    ],
    "name:msa_x_preferred":[
        "Sheshdeh"
    ],
    "name:rus_x_preferred":[
        "\u0428\u0435\u0448\u0434\u0435"
    ],
    "name:swe_x_preferred":[
        "Sheshdeh"
    ],
    "name:tur_x_preferred":[
        "\u015ee\u015fdeh"
    ],
    "name:und_x_variant":[
        "Shish Deh",
        "Shash Deh",
        "Shesh Deh",
        "Sheshdeh"
    ],
    "name:urd_x_preferred":[
        "\u0634\u0634\u062f\u06c1"
    ],
    "wof:name":"Sheshdeh",
    "wof:placetype":"locality"
},
  "geometry": {"coordinates":[53.99469000000001,28.94729],"type":"Point"}
}