{
  "type": "Feature",
  "properties": {
    "gn:admin1_code":"7",
    "gn:asciiname":"Sheshdeh",
    "gn:country_code":"IR",
    "gn:dem":1383,
    "gn:feature_class":"P",
    "gn:feature_code":"PPL",
    "gn:name":"Sheshdeh",
    "gn:population":0,
    "gn:timezone":"Asia/Tehran",
    "iso:country":"IR",
    "name:fas_x_preferred":[
        "\u0634\u0634\u062f\u0647"
    ],
    "name:und_x_variant":[
        "Shish Deh",
        "Shash Deh",
        "Shesh Deh",
        "Sheshdeh"
    ],
    "wof:name":"Sheshdeh",
    "wof:placetype":"locality"
},
  "geometry": {"coordinates":[53.99469000000001,28.94729],"type":"Point"}
}