{
  "type": "Feature",
  "properties": {
    "gn:admin1_code":"7",
    "gn:asciiname":"Keteh Nan",
    "gn:country_code":"IR",
    "gn:dem":963,
    "gn:feature_class":"P",
    "gn:feature_code":"PPL",
    "gn:name":"Keteh N\u0101n",
    "gn:population":0,
    "gn:timezone":"Asia/Tehran",
    "iso:country":"IR",
    "name:fas_x_preferred":[
        "Keteh N\u0101n"
    ],
    "name:fas_x_variant":[
        "Keten\u0101n",
        "\u06a9\u062a\u0647 \u0646\u0627\u0646"
    ],
    "name:und_x_variant":[
        "\u06a9\u062a\u0647 \u0646\u0627\u0646"
    ],
    "wof:name":"Keteh Nan",
    "wof:placetype":"locality"
},
  "geometry": {"coordinates":[51.51189,30.05949],"type":"Point"}
}