{
  "type": "Feature",
  "properties": {
    "gn:admin1_code":"10",
    "gn:asciiname":"Negel",
    "gn:country_code":"IR",
    "gn:dem":923,
    "gn:feature_class":"P",
    "gn:feature_code":"PPL",
    "gn:name":"Negel",
    "gn:population":0,
    "gn:timezone":"Asia/Tehran",
    "iso:country":"IR",
    "name:fas_x_preferred":[
        "\u0646\u0650\u06af\u0650\u0644"
    ],
    "name:fas_x_variant":[
        "\u0646\u06af\u0644"
    ],
    "name:msa_x_preferred":[
        "Negel"
    ],
    "wof:name":"Negel",
    "wof:placetype":"locality"
},
  "geometry": {"coordinates":[46.75,33.56667],"type":"Point"}
}