{
  "type": "Feature",
  "properties": {
    "gn:admin1_code":"8.0",
    "gn:asciiname":"Jir Sara",
    "gn:country_code":"IR",
    "gn:dem":-19,
    "gn:feature_class":"P",
    "gn:feature_code":"PPL",
    "gn:name":"J\u012br Sar\u0101",
    "gn:population":0,
    "gn:timezone":"Asia/Tehran",
    "iso:country":"IR",
    "name:fas_x_preferred":[
        "\u062c\u06cc\u0631 \u0633\u0631\u0627"
    ],
    "name:und_x_variant":[
        "J\u012br Sar\u0101"
    ],
    "wof:name":"Jir Sara",
    "wof:placetype":"locality"
},
  "geometry": {"coordinates":[49.61628,37.35322],"type":"Point"}
}