{
  "type": "Feature",
  "properties": {
    "gn:admin1_code":"29",
    "gn:asciiname":"Mur Pahn-e Bala",
    "gn:country_code":"IR",
    "gn:dem":2219,
    "gn:feature_class":"P",
    "gn:feature_code":"PPL",
    "gn:name":"M\u016br Pahn-e B\u0101l\u0101",
    "gn:population":0,
    "gn:timezone":"Asia/Tehran",
    "iso:country":"IR",
    "name:fas_x_preferred":[
        "M\u016brpahn"
    ],
    "name:fas_x_variant":[
        "\u0645\u0648\u0631 \u067e\u0647\u0646 \u0628\u0627\u0644\u0627",
        "\u0645\u0648\u0631\u06cc\u0646"
    ],
    "name:und_x_variant":[
        "M\u016br Pahn-e B\u0101l\u0101",
        "M\u016breyn"
    ],
    "wof:name":"Mur Pahn-e Bala",
    "wof:placetype":"locality"
},
  "geometry": {"coordinates":[55.05763,30.48729],"type":"Point"}
}