{
  "type": "Feature",
  "properties": {
    "gn:admin1_code":"11",
    "gn:asciiname":"Kavaran",
    "gn:country_code":"IR",
    "gn:dem":814,
    "gn:feature_class":"P",
    "gn:feature_code":"PPL",
    "gn:name":"Kav\u0101r\u0101n",
    "gn:population":0,
    "gn:timezone":"Asia/Tehran",
    "iso:country":"IR",
    "name:fas_x_preferred":[
        "\u06a9\u0648\u0627\u0631\u0627\u0646"
    ],
    "name:fas_x_variant":[
        "Kav\u0101r\u0101n"
    ],
    "wof:name":"Kavaran",
    "wof:placetype":"locality"
},
  "geometry": {"coordinates":[57.7362,26.3451],"type":"Point"}
}