{
  "type": "Feature",
  "properties": {
    "gn:admin1_code":"15",
    "gn:asciiname":"Turahi",
    "gn:country_code":"IR",
    "gn:dem":469,
    "gn:feature_class":"P",
    "gn:feature_code":"PPL",
    "gn:name":"T\u016brah\u012b",
    "gn:population":0,
    "gn:timezone":"Asia/Tehran",
    "iso:country":"IR",
    "name:azb_x_preferred":[
        "\u062a\u0648\u0631\u0647\u06cc(\u0628\u0647\u0628\u0647\u0627\u0646)"
    ],
    "name:fas_x_preferred":[
        "\u062a\u0648\u0631\u0647\u06cc"
    ],
    "name:fas_x_variant":[
        "T\u016brah\u012b",
        "\u0642\u0644\u0627\u062a \u062a\u0648\u0631\u06cc"
    ],
    "name:und_x_variant":[
        "T\u016brah\u012b",
        "Qal\u0101t-e T\u016br\u012b"
    ],
    "wof:name":"Turahi",
    "wof:placetype":"locality"
},
  "geometry": {"coordinates":[50.1821,30.8337],"type":"Point"}
}