{
  "type": "Feature",
  "properties": {
    "gn:admin1_code":"8",
    "gn:asciiname":"Ahandan",
    "gn:country_code":"IR",
    "gn:dem":24,
    "gn:feature_class":"P",
    "gn:feature_code":"PPL",
    "gn:name":"\u0100hand\u0101n",
    "gn:population":0,
    "gn:timezone":"Asia/Tehran",
    "iso:country":"IR",
    "name:fas_x_preferred":[
        "\u0100hand\u0101n"
    ],
    "name:fas_x_variant":[
        "\u0622\u0647\u0646\u062f\u0627\u0646"
    ],
    "name:msa_x_preferred":[
        "Ahandan"
    ],
    "name:ukr_x_preferred":[
        "\u0410\u0433\u0430\u043d\u0434\u0430\u043d"
    ],
    "name:und_x_variant":[
        "\u0622\u0647\u0646\u062f\u0627\u0646"
    ],
    "wof:name":"Ahandan",
    "wof:placetype":"locality"
},
  "geometry": {"coordinates":[49.98527,37.17466],"type":"Point"}
}