{
  "type": "Feature",
  "properties": {
    "gn:admin1_code":"29",
    "gn:asciiname":"Daneshabad",
    "gn:country_code":"IR",
    "gn:dem":2105,
    "gn:feature_class":"P",
    "gn:feature_code":"PPL",
    "gn:name":"D\u0101nesh\u0101b\u0101d",
    "gn:population":0,
    "gn:timezone":"Asia/Tehran",
    "iso:country":"IR",
    "name:fas_x_preferred":[
        "D\u0101nesh\u0101b\u0101d"
    ],
    "wof:name":"Daneshabad",
    "wof:placetype":"locality"
},
  "geometry": {"coordinates":[57.28222,30.24167000000001],"type":"Point"}
}