{
  "type": "Feature",
  "properties": {
    "gn:admin1_code":"1.0",
    "gn:asciiname":"Mohammad Shah-e Bala",
    "gn:country_code":"IR",
    "gn:dem":1373,
    "gn:feature_class":"P",
    "gn:feature_code":"PPL",
    "gn:name":"Mo\u1e29ammad Sh\u0101h-e B\u0101l\u0101",
    "gn:population":0,
    "gn:timezone":"Asia/Tehran",
    "iso:country":"IR",
    "name:fas_x_preferred":[
        "\u0645\u062d\u0645\u062f \u0634\u0627\u0647 \u0628\u0627\u0644\u0627"
    ],
    "name:fas_x_variant":[
        "Mo\u1e29ammad Sh\u0101h-e B\u0101l\u0101"
    ],
    "wof:name":"Mohammad Shah-e Bala",
    "wof:placetype":"locality"
},
  "geometry": {"coordinates":[45.5638,36.8716],"type":"Point"}
}