{
  "type": "Feature",
  "properties": {
    "gn:admin1_code":"8",
    "gn:asciiname":"Khalil Hayati-ye Mahalleh",
    "gn:country_code":"IR",
    "gn:dem":24,
    "gn:feature_class":"P",
    "gn:feature_code":"PPL",
    "gn:name":"Khal\u012bl \u1e28ay\u0101\u0163\u012b-ye Ma\u1e29alleh",
    "gn:population":0,
    "gn:timezone":"Asia/Tehran",
    "iso:country":"IR",
    "name:fas_x_preferred":[
        "\u062e\u0644\u06cc\u0644 \u062d\u06cc\u0627\u0637\u06cc \u0645\u062d\u0644\u0647"
    ],
    "name:fas_x_variant":[
        "Khal\u012bl Sar\u0101-ye \u1e28av\u012bq",
        "Khal\u012bl \u1e28ay\u0101\u0163\u012b-ye Ma\u1e29alleh"
    ],
    "wof:name":"Khalil Hayati-ye Mahalleh",
    "wof:placetype":"locality"
},
  "geometry": {"coordinates":[48.8734,38.1455],"type":"Point"}
}