{
  "type": "Feature",
  "properties": {
    "gn:admin1_code":"1.0",
    "gn:asciiname":"Jandaran",
    "gn:country_code":"IR",
    "gn:dem":1766,
    "gn:elevation":"0.0",
    "gn:feature_class":"P",
    "gn:feature_code":"PPL",
    "gn:name":"J\u0101nd\u0101r\u0101n",
    "gn:population":0,
    "gn:timezone":"Asia/Tehran",
    "iso:country":"IR",
    "name:fas_x_preferred":[
        "\u062c\u0627\u0646\u062f\u0627\u0631\u0627\u0646"
    ],
    "name:fas_x_variant":[
        "J\u0101nd\u0101r\u0101n"
    ],
    "wof:name":"Jandaran",
    "wof:placetype":"locality"
},
  "geometry": {"coordinates":[45.5177,36.4166],"type":"Point"}
}