{
  "type": "Feature",
  "properties": {
    "gn:admin1_code":"32.0",
    "gn:asciiname":"Yengejeh-ye Qeshlaq",
    "gn:country_code":"IR",
    "gn:dem":1276,
    "gn:feature_class":"P",
    "gn:feature_code":"PPL",
    "gn:name":"Yengejeh-ye Qeshl\u0101q",
    "gn:population":0,
    "gn:timezone":"Asia/Tehran",
    "iso:country":"IR",
    "name:ceb_x_preferred":[
        "Yengejeh-ye Qeshl\u0101q"
    ],
    "name:fas_x_preferred":[
        "\u06cc\u0646\u06af\u062c\u0647 \u0642\u0634\u0644\u0627\u0642"
    ],
    "name:fas_x_variant":[
        "Yengejeh-ye Qeshl\u0101q",
        "\u06cc\u0646\u06af\u0647 \u0642\u0634\u0644\u0627\u0642"
    ],
    "name:msa_x_preferred":[
        "Yengejeh-ye Qeshlaq"
    ],
    "name:und_x_variant":[
        "Yengeh Qeshl\u0101q"
    ],
    "name:urd_x_preferred":[
        "\u06cc\u0646\u06af\u062c\u06cc\u06c1-\u0642\u0634\u0644\u0642"
    ],
    "wof:name":"Yengejeh-ye Qeshlaq",
    "wof:placetype":"locality"
},
  "geometry": {"coordinates":[48.19673,37.62542],"type":"Point"}
}