{
  "type": "Feature",
  "properties": {
    "gn:admin1_code":"42",
    "gn:asciiname":"Rud-e Rus",
    "gn:country_code":"IR",
    "gn:dem":1147,
    "gn:feature_class":"P",
    "gn:feature_code":"PPL",
    "gn:name":"R\u016bd-e R\u016bs",
    "gn:population":0,
    "gn:timezone":"Asia/Tehran",
    "iso:country":"IR",
    "name:fas_x_preferred":[
        "\u0631\u0648\u062f \u0631\u0648\u0633"
    ],
    "name:fas_x_variant":[
        "R\u016bd-e R\u016bs"
    ],
    "wof:name":"Rud-e Rus",
    "wof:placetype":"locality"
},
  "geometry": {"coordinates":[60.45644,34.99839],"type":"Point"}
}