{
  "type": "Feature",
  "properties": {
    "gn:admin1_code":"42",
    "gn:asciiname":"Cheshmeh Sabz",
    "gn:country_code":"IR",
    "gn:dem":1563,
    "gn:feature_class":"P",
    "gn:feature_code":"PPL",
    "gn:name":"Cheshmeh Sabz",
    "gn:population":0,
    "gn:timezone":"Asia/Tehran",
    "iso:country":"IR",
    "name:ara_x_preferred":[
        "\u062c\u0634\u0645\u0629"
    ],
    "name:ceb_x_preferred":[
        "Cheshmeh Sabz-e Gowghar"
    ],
    "name:fas_x_preferred":[
        "\u0686\u0634\u0645\u0647 \u0633\u0628\u0632"
    ],
    "name:swe_x_preferred":[
        "Cheshmeh Sabz-e Gowghar"
    ],
    "wof:name":"Cheshmeh Sabz",
    "wof:placetype":"locality"
},
  "geometry": {"coordinates":[59.98339,35.51045999999999],"type":"Point"}
}