{
  "type": "Feature",
  "properties": {
    "gn:admin1_code":"11",
    "gn:asciiname":"Turan",
    "gn:country_code":"IR",
    "gn:dem":35,
    "gn:feature_class":"P",
    "gn:feature_code":"PPL",
    "gn:name":"T\u016br\u0101n",
    "gn:population":0,
    "gn:timezone":"Asia/Tehran",
    "iso:country":"IR",
    "name:fas_x_preferred":[
        "\u062a\u0648\u0631\u064a\u0627\u0646"
    ],
    "name:fas_x_variant":[
        "T\u016br\u012b\u0101n",
        "\u062a\u0648\u0631\u0627\u0646"
    ],
    "name:und_x_variant":[
        "T\u016brey\u0101n",
        "T\u016br\u012by\u0101n",
        "T\u016bry\u0101n",
        "T\u016br\u0101n"
    ],
    "wof:name":"Turan",
    "wof:placetype":"locality"
},
  "geometry": {"coordinates":[56.0174,26.8726],"type":"Point"}
}