{
  "type": "Feature",
  "properties": {
    "gn:admin1_code":"29",
    "gn:asciiname":"Shekarabad",
    "gn:country_code":"IR",
    "gn:dem":1919,
    "gn:feature_class":"P",
    "gn:feature_code":"PPLF",
    "gn:name":"Shekar\u0101b\u0101d",
    "gn:population":0,
    "gn:timezone":"Asia/Tehran",
    "iso:country":"IR",
    "name:fas_x_preferred":[
        "Shekar\u0101b\u0101d"
    ],
    "name:fas_x_variant":[
        "\u0634\u06a9\u0631 \u0622\u0628\u0627\u062f",
        "Shokr\u0101b\u0101d"
    ],
    "name:und_x_variant":[
        "Shokr\u0101b\u0101d"
    ],
    "wof:name":"Shekarabad",
    "wof:placetype":"locality"
},
  "geometry": {"coordinates":[56.12359,31.43816],"type":"Point"}
}