{
  "type": "Feature",
  "properties": {
    "gn:admin1_code":"29",
    "gn:asciiname":"Tolombeh-ye Sherkatabad",
    "gn:country_code":"IR",
    "gn:dem":2077,
    "gn:feature_class":"P",
    "gn:feature_code":"PPL",
    "gn:name":"Tolombeh-ye Sherkat\u0101b\u0101d",
    "gn:population":0,
    "gn:timezone":"Asia/Tehran",
    "iso:country":"IR",
    "name:fas_x_preferred":[
        "Tolombeh-ye Sherkat\u0101b\u0101d"
    ],
    "wof:name":"Tolombeh-ye Sherkatabad",
    "wof:placetype":"locality"
},
  "geometry": {"coordinates":[56.71639,29.87611],"type":"Point"}
}