{
  "type": "Feature",
  "properties": {
    "gn:admin1_code":"41",
    "gn:asciiname":"Pey Rud",
    "gn:country_code":"IR",
    "gn:dem":1388,
    "gn:feature_class":"P",
    "gn:feature_code":"PPL",
    "gn:name":"Pey R\u016bd",
    "gn:population":0,
    "gn:timezone":"Asia/Tehran",
    "iso:country":"IR",
    "name:fas_x_preferred":[
        "Pey R\u016bd"
    ],
    "name:fas_x_variant":[
        "\u067e\u06cc \u0631\u0648\u062f",
        "\u0642\u0631\u06cc\u0627\u0646",
        "\u067e\u06cc\u0631\u0648\u062f"
    ],
    "name:und_x_variant":[
        "Pai-R\u016bd",
        "Zen\u016br",
        "Pa yi R\u016bd",
        "Pay-ye R\u016bd",
        "Qory\u0101n",
        "Peyr\u016bd"
    ],
    "wof:name":"Pey Rud",
    "wof:placetype":"locality"
},
  "geometry": {"coordinates":[58.97168000000001,32.58876],"type":"Point"}
}