{
  "type": "Feature",
  "properties": {
    "gn:admin1_code":"7",
    "gn:asciiname":"Dasht Konar",
    "gn:country_code":"IR",
    "gn:dem":682,
    "gn:feature_class":"P",
    "gn:feature_code":"PPL",
    "gn:name":"Dasht Kon\u0101r",
    "gn:population":0,
    "gn:timezone":"Asia/Tehran",
    "iso:country":"IR",
    "name:ara_x_preferred":[
        "\u062f\u0634\u062a \u0643\u0646\u0627\u0631"
    ],
    "name:fas_x_preferred":[
        "\u062f\u0634\u062a \u06a9\u0646\u0627\u0631"
    ],
    "name:fas_x_variant":[
        "Dasht Kon\u0101r",
        "\u062f\u0634\u062a\u200c\u06a9\u0646\u0627\u0631"
    ],
    "name:msa_x_preferred":[
        "Dasht Konar"
    ],
    "name:und_x_variant":[
        "Dasht-i-Kan\u0101r",
        "Dasht Kan\u0101r",
        "Dasht-e Ken\u0101r",
        "Dasht-e Kon\u0101r",
        "Dasht-e Kan\u0101r"
    ],
    "wof:name":"Dasht Konar",
    "wof:placetype":"locality"
},
  "geometry": {"coordinates":[55.3333,28.0757],"type":"Point"}
}