{
  "type": "Feature",
  "properties": {
    "gn:admin1_code":"25.0",
    "gn:asciiname":"Nowveh",
    "gn:country_code":"IR",
    "gn:dem":1236,
    "gn:feature_class":"P",
    "gn:feature_code":"PPL",
    "gn:name":"Nowveh",
    "gn:population":0,
    "gn:timezone":"Asia/Tehran",
    "iso:country":"IR",
    "name:fas_x_preferred":[
        "\u0646\u064f\u0648\u0650\u0647"
    ],
    "name:fas_x_variant":[
        "\u0646\u0648\u0648\u0647"
    ],
    "name:und_x_variant":[
        "Noveh",
        "Nowveh",
        "\u0646\u0648\u0648\u0647"
    ],
    "wof:name":"Nowveh",
    "wof:placetype":"locality"
},
  "geometry": {"coordinates":[56.77752,35.55665],"type":"Point"}
}