{
  "type": "Feature",
  "properties": {
    "gn:admin1_code":"9",
    "gn:asciiname":"Qasemabad",
    "gn:country_code":"IR",
    "gn:dem":1524,
    "gn:feature_class":"P",
    "gn:feature_code":"PPL",
    "gn:name":"Q\u0101sem\u0101b\u0101d",
    "gn:population":0,
    "gn:timezone":"Asia/Tehran",
    "iso:country":"IR",
    "name:ceb_x_preferred":[
        "Q\u0101sem\u0101b\u0101d"
    ],
    "name:fas_x_preferred":[
        "\u0642\u0627\u0633\u0650\u0645\u0627\u0628\u0627\u062f\u0650 \u0644\u064e\u0643\u0644\u064e\u0643"
    ],
    "name:fas_x_variant":[
        "\u0642\u0627\u0633\u0645 \u0622\u0628\u0627\u062f",
        "Q\u0101sem\u0101b\u0101d-e Laklak",
        "Q\u0101sem\u0101b\u0101d",
        "\u0642\u0627\u0633\u0645 \u0622\u0628\u0627\u062f \u0644\u06a9 \u0644\u06a9\u0647",
        "\u0642\u0627\u0633\u0645\u200c\u0622\u0628\u0627\u062f \u0644\u06a9\u200c\u0644\u06a9"
    ],
    "name:msa_x_preferred":[
        "Qasemabad-e Laklak"
    ],
    "name:und_x_variant":[
        "Q\u0101sem\u0101b\u0101d-e Laklakeh"
    ],
    "wof:name":"Qasemabad",
    "wof:placetype":"locality"
},
  "geometry": {"coordinates":[47.97214,34.67527],"type":"Point"}
}