{
  "type": "Feature",
  "properties": {
    "gn:admin1_code":"4",
    "gn:asciiname":"Landi-ye Bala",
    "gn:country_code":"IR",
    "gn:dem":1522,
    "gn:feature_class":"P",
    "gn:feature_code":"PPL",
    "gn:name":"Land\u012b-ye B\u0101l\u0101",
    "gn:population":0,
    "gn:timezone":"Asia/Tehran",
    "iso:country":"IR",
    "name:fas_x_preferred":[
        "\u0644\u0646\u062f\u06cc \u0628\u0627\u0644\u0627"
    ],
    "name:fas_x_variant":[
        "Land\u012b-ye B\u0101l\u0101"
    ],
    "wof:name":"Landi-ye Bala",
    "wof:placetype":"locality"
},
  "geometry": {"coordinates":[61.68237,26.86732],"type":"Point"}
}