{
  "type": "Feature",
  "properties": {
    "gn:admin1_code":"35.0",
    "gn:asciiname":"Owjiabad",
    "gn:country_code":"IR",
    "gn:dem":39,
    "gn:feature_class":"P",
    "gn:feature_code":"PPL",
    "gn:name":"Owj\u012b\u0101b\u0101d",
    "gn:population":0,
    "gn:timezone":"Asia/Tehran",
    "iso:country":"IR",
    "name:ara_x_preferred":[
        "\u0623\u0648\u062c\u064a \u0623\u0628\u0627\u062f"
    ],
    "name:fas_x_preferred":[
        "Owj\u012b\u0101b\u0101d"
    ],
    "name:fas_x_variant":[
        "\u0627\u0648\u062c\u06cc \u0622\u0628\u0627\u062f",
        "\u0627\u0648\u062c\u06cc\u200c\u0622\u0628\u0627\u062f"
    ],
    "name:ukr_x_preferred":[
        "\u041e\u0432\u0434\u0436\u0456\u044f\u0431\u0430\u0434"
    ],
    "wof:name":"Owjiabad",
    "wof:placetype":"locality"
},
  "geometry": {"coordinates":[52.34769,36.51973],"type":"Point"}
}