{
  "type": "Feature",
  "properties": {
    "gn:admin1_code":"41",
    "gn:asciiname":"Chashmeh Zar",
    "gn:country_code":"IR",
    "gn:dem":2044,
    "gn:feature_class":"P",
    "gn:feature_code":"PPL",
    "gn:name":"Chashmeh Z\u0101r",
    "gn:population":0,
    "gn:timezone":"Asia/Tehran",
    "iso:country":"IR",
    "name:fas_x_preferred":[
        "\u0686\u064e\u0634\u0645\u0650\u0647 \u0632\u0627\u0631"
    ],
    "name:fas_x_variant":[
        "Chashmeh Z\u0101r"
    ],
    "name:und_x_variant":[
        "Chashmeh-i-Zari"
    ],
    "wof:name":"Chashmeh Zar",
    "wof:placetype":"locality"
},
  "geometry": {"coordinates":[59.48333,33.28333],"type":"Point"}
}