{
  "type": "Feature",
  "properties": {
    "gn:admin1_code":"5",
    "gn:asciiname":"Munah",
    "gn:country_code":"IR",
    "gn:dem":1171,
    "gn:feature_class":"P",
    "gn:feature_code":"PPL",
    "gn:name":"M\u016bnah",
    "gn:population":0,
    "gn:timezone":"Asia/Tehran",
    "iso:country":"IR",
    "name:ceb_x_preferred":[
        "M\u016bnah"
    ],
    "name:fas_x_preferred":[
        "M\u016bnah"
    ],
    "name:fas_x_variant":[
        "\u0645\u0648\u0646\u0647",
        "M\u016bneh"
    ],
    "name:swe_x_preferred":[
        "M\u016bnah"
    ],
    "name:und_x_variant":[
        "M\u016bneh"
    ],
    "wof:name":"Munah",
    "wof:placetype":"locality"
},
  "geometry": {"coordinates":[50.3855,31.03036],"type":"Point"}
}