{
  "type": "Feature",
  "properties": {
    "gn:admin1_code":"13",
    "gn:asciiname":"Kuyaki-ye Majid",
    "gn:country_code":"IR",
    "gn:dem":559,
    "gn:feature_class":"P",
    "gn:feature_code":"PPL",
    "gn:name":"K\u016byak\u012b-ye Maj\u012bd",
    "gn:population":0,
    "gn:timezone":"Asia/Tehran",
    "iso:country":"IR",
    "name:fas_x_preferred":[
        "\u06a9\u0648\u064a\u06a9\u06cc \u0645\u062c\u064a\u062f"
    ],
    "name:fas_x_variant":[
        "K\u016byak\u012b Maj\u012bd",
        "K\u016byak\u012b-ye Maj\u012bd"
    ],
    "name:und_x_variant":[
        "K\u016byek\u012b-ye Maj\u012bd"
    ],
    "wof:name":"Kuyaki-ye Majid",
    "wof:placetype":"locality"
},
  "geometry": {"coordinates":[45.85745,34.55442],"type":"Point"}
}