{
  "type": "Feature",
  "properties": {
    "gn:admin1_code":"15.0",
    "gn:asciiname":"Mashlush",
    "gn:country_code":"IR",
    "gn:dem":110,
    "gn:feature_class":"P",
    "gn:feature_code":"PPL",
    "gn:name":"Mashl\u016bsh",
    "gn:population":0,
    "gn:timezone":"Asia/Tehran",
    "iso:country":"IR",
    "name:fas_x_preferred":[
        "Mashl\u016bsh"
    ],
    "name:fas_x_variant":[
        "\u0645\u0634\u0644\u0648\u0634"
    ],
    "name:und_x_variant":[
        "\u0645\u0634\u0644\u0648\u0634"
    ],
    "wof:name":"Mashlush",
    "wof:placetype":"locality"
},
  "geometry": {"coordinates":[49.61126,31.14132],"type":"Point"}
}