{
  "type": "Feature",
  "properties": {
    "gn:admin1_code":"1",
    "gn:asciiname":"Bastam",
    "gn:country_code":"IR",
    "gn:dem":1150,
    "gn:feature_class":"P",
    "gn:feature_code":"PPL",
    "gn:name":"Bas\u0163\u0101m",
    "gn:population":284,
    "gn:timezone":"Asia/Tehran",
    "iso:country":"IR",
    "name:deu_x_preferred":[
        "Bastam"
    ],
    "name:epo_x_preferred":[
        "Bastam"
    ],
    "name:fas_x_preferred":[
        "Bas\u0163\u0101m"
    ],
    "name:fas_x_variant":[
        "\u0628\u0633\u0637\u0627\u0645",
        "\u062f\u0698 \u0628\u0633\u0637\u0627\u0645"
    ],
    "name:fra_x_preferred":[
        "Bastam"
    ],
    "name:nor_x_preferred":[
        "Bastamborgen"
    ],
    "name:spa_x_preferred":[
        "Bastam"
    ],
    "name:und_x_variant":[
        "\u0628\u0633\u0637\u0627\u0645"
    ],
    "wof:name":"Bastam",
    "wof:placetype":"locality",
    "wof:population":284
},
  "geometry": {"coordinates":[44.9544,38.8851],"type":"Point"}
}