{
  "type": "Feature",
  "properties": {
    "gn:admin1_code":"3",
    "gn:asciiname":"Chaqahast",
    "gn:country_code":"IR",
    "gn:dem":2003,
    "gn:feature_class":"P",
    "gn:feature_code":"PPL",
    "gn:name":"Chaq\u0101hast",
    "gn:population":0,
    "gn:timezone":"Asia/Tehran",
    "iso:country":"IR",
    "name:fas_x_preferred":[
        "Chaq\u0101hast"
    ],
    "name:fas_x_variant":[
        "\u0686\u0650\u0642\u0627\u0647\u064e\u0633\u062a",
        "Cheq\u0101hast",
        "\u0686\u064e\u063a\u064e \u0647\u064e\u0633\u062a",
        "\u0686\u0642\u0627\u0647\u0633\u062a"
    ],
    "name:und_x_variant":[
        "Chagha Hast",
        "Cheq\u0101 Hast",
        "\u0686\u0642\u0627\u0647\u0633\u062a"
    ],
    "wof:name":"Chaqahast",
    "wof:placetype":"locality"
},
  "geometry": {"coordinates":[50.62218,32.19473],"type":"Point"}
}