{
  "type": "Feature",
  "properties": {
    "gn:admin1_code":"29.0",
    "gn:asciiname":"Cheshmeh Ab Band",
    "gn:country_code":"IR",
    "gn:dem":826,
    "gn:feature_class":"P",
    "gn:feature_code":"PPLF",
    "gn:name":"Cheshmeh \u0100b Band",
    "gn:population":0,
    "gn:timezone":"Asia/Tehran",
    "iso:country":"IR",
    "name:fas_x_preferred":[
        "\u0686\u0634\u0645\u0647 \u0622\u0628 \u0628\u0646\u062f"
    ],
    "name:und_x_variant":[
        "Cheshmeh \u0100b Band"
    ],
    "wof:name":"Cheshmeh Ab Band",
    "wof:placetype":"locality"
},
  "geometry": {"coordinates":[58.78625,28.13156],"type":"Point"}
}