{
  "type": "Feature",
  "properties": {
    "gn:admin1_code":"44.0",
    "gn:asciiname":"Do Khanavari",
    "gn:country_code":"IR",
    "gn:dem":1923,
    "gn:feature_class":"P",
    "gn:feature_code":"PPL",
    "gn:name":"Do Kh\u0101nav\u0101r\u012b",
    "gn:population":0,
    "gn:timezone":"Asia/Tehran",
    "iso:country":"IR",
    "name:fas_x_preferred":[
        "\u062f\u0648 \u062e\u0627\u0646\u0648\u0627\u0631\u06cc"
    ],
    "name:fas_x_variant":[
        "\u062f\u0648\u062e\u0627\u0646\u0648\u0627\u0631\u06cc"
    ],
    "name:msa_x_preferred":[
        "Do Khanvari"
    ],
    "name:und_x_variant":[
        "Do Kh\u0101nav\u0101r\u012b"
    ],
    "wof:name":"Do Khanavari",
    "wof:placetype":"locality"
},
  "geometry": {"coordinates":[51.24216,36.02800999999999],"type":"Point"}
}