{
  "type": "Feature",
  "properties": {
    "gn:admin1_code":"8.0",
    "gn:asciiname":"Aqa Mahalleh",
    "gn:country_code":"IR",
    "gn:dem":19,
    "gn:feature_class":"P",
    "gn:feature_code":"PPL",
    "gn:name":"\u0100q\u0101 Ma\u1e29alleh",
    "gn:population":0,
    "gn:timezone":"Asia/Tehran",
    "iso:country":"IR",
    "name:fas_x_preferred":[
        "\u0622\u0642\u0627 \u0628\u0627\u0628\u0627 \u0645\u062d\u0644\u0647"
    ],
    "name:fas_x_variant":[
        "\u0100q\u0101 B\u0101b\u0101 Ma\u1e29alleh",
        "\u0622\u0642\u0627 \u0645\u062d\u0644\u0647"
    ],
    "name:und_x_variant":[
        "\u0100q\u0101 Ma\u1e29alleh"
    ],
    "wof:name":"Aqa Mahalleh",
    "wof:placetype":"locality"
},
  "geometry": {"coordinates":[48.96856,37.69119],"type":"Point"}
}