{
  "type": "Feature",
  "properties": {
    "gn:admin1_code":"15",
    "gn:asciiname":"Qal`eh A`la",
    "gn:country_code":"IR",
    "gn:dem":931,
    "gn:feature_class":"P",
    "gn:feature_code":"PPL",
    "gn:name":"Qal\u2018eh A\u2018l\u0101",
    "gn:population":0,
    "gn:timezone":"Asia/Tehran",
    "iso:country":"IR",
    "name:fas_x_preferred":[
        "A\u2018l\u0101"
    ],
    "name:fas_x_variant":[
        "\u0627\u0639\u0644\u0627",
        "\u0642\u0644\u0639\u0647 \u0627\u0639\u0644\u0627"
    ],
    "name:und_x_variant":[
        "Qal\u2018eh A\u2018l\u0101"
    ],
    "wof:name":"Qal`eh A`la",
    "wof:placetype":"locality"
},
  "geometry": {"coordinates":[50.10647,31.32818],"type":"Point"}
}