{
  "type": "Feature",
  "properties": {
    "gn:admin1_code":"7",
    "gn:asciiname":"Qal`eh-ye Fereydun",
    "gn:country_code":"IR",
    "gn:dem":411,
    "gn:feature_class":"P",
    "gn:feature_code":"PPL",
    "gn:name":"Qal\u2018eh-ye Fereyd\u016bn",
    "gn:population":0,
    "gn:timezone":"Asia/Tehran",
    "iso:country":"IR",
    "name:fas_x_preferred":[
        "\u0642\u0644\u0639\u0647 \u0641\u0631\u06cc\u062f\u0648\u0646"
    ],
    "name:fas_x_variant":[
        "Qal\u2018eh-e Fereyd\u016bn",
        "Qal\u2018eh-ye Fereyd\u016bn"
    ],
    "name:und_x_variant":[
        "Ma\u1e29m\u016bd Sh\u0101b\u012b",
        "Mo\u1e29m\u016bd Sh\u0101b\u012b",
        "Ma\u1e29m\u016bd Sh\u0101h\u012b"
    ],
    "wof:name":"Qal`eh-ye Fereydun",
    "wof:placetype":"locality"
},
  "geometry": {"coordinates":[53.1732,27.4252],"type":"Point"}
}