{
  "type": "Feature",
  "properties": {
    "gn:admin1_code":"29.0",
    "gn:asciiname":"Sagin",
    "gn:country_code":"IR",
    "gn:dem":714,
    "gn:feature_class":"P",
    "gn:feature_code":"PPLF",
    "gn:name":"Sag\u012bn",
    "gn:population":0,
    "gn:timezone":"Asia/Tehran",
    "iso:country":"IR",
    "name:fas_x_preferred":[
        "\u0633\u06af\u064a\u0646"
    ],
    "name:und_x_variant":[
        "Sag\u012bn"
    ],
    "wof:name":"Sagin",
    "wof:placetype":"locality"
},
  "geometry": {"coordinates":[58.21166,28.21443],"type":"Point"}
}