{
  "type": "Feature",
  "properties": {
    "gn:admin1_code":"32",
    "gn:asciiname":"Karnakh",
    "gn:country_code":"IR",
    "gn:dem":1431,
    "gn:feature_class":"P",
    "gn:feature_code":"PPL",
    "gn:name":"Karnakh",
    "gn:population":0,
    "gn:timezone":"Asia/Tehran",
    "iso:country":"IR",
    "name:ceb_x_preferred":[
        "Karnaq"
    ],
    "name:fas_x_preferred":[
        "\u06a9\u0631\u0646\u062e"
    ],
    "name:fas_x_variant":[
        "\u06a9\u0631\u0646\u0642"
    ],
    "name:msa_x_preferred":[
        "Karnaq"
    ],
    "name:mzn_x_preferred":[
        "\u06a9\u0631\u0646\u0642"
    ],
    "name:swe_x_preferred":[
        "Karnaq"
    ],
    "name:und_x_variant":[
        "Kizmya",
        "Karneh",
        "Karnakh"
    ],
    "wof:name":"Karnakh",
    "wof:placetype":"locality"
},
  "geometry": {"coordinates":[48.61647,37.26671],"type":"Point"}
}