{
  "type": "Feature",
  "properties": {
    "gn:admin1_code":"23",
    "gn:asciiname":"Namdarabad",
    "gn:country_code":"IR",
    "gn:dem":1594,
    "gn:feature_class":"P",
    "gn:feature_code":"PPL",
    "gn:name":"N\u0101md\u0101r\u0101b\u0101d",
    "gn:population":0,
    "gn:timezone":"Asia/Tehran",
    "iso:country":"IR",
    "name:fas_x_preferred":[
        "N\u0101md\u0101r\u0101b\u0101d"
    ],
    "name:fas_x_variant":[
        "\u0646\u0627\u0645\u062f\u0627\u0631 \u0622\u0628\u0627\u062f"
    ],
    "wof:name":"Namdarabad",
    "wof:placetype":"locality"
},
  "geometry": {"coordinates":[48.1988,33.891],"type":"Point"}
}