{
  "type": "Feature",
  "properties": {
    "gn:admin1_code":"7",
    "gn:asciiname":"Kushk-e Sar Tang",
    "gn:country_code":"IR",
    "gn:dem":1371,
    "gn:feature_class":"P",
    "gn:feature_code":"PPL",
    "gn:name":"K\u016bshk-e Sar Tang",
    "gn:population":0,
    "gn:timezone":"Asia/Tehran",
    "iso:country":"IR",
    "name:fas_x_preferred":[
        "\u06a9\u0648\u0634\u06a9 \u0633\u0631 \u062a\u0646\u06af"
    ],
    "name:fas_x_variant":[
        "K\u016bshk",
        "K\u016bshk-e Sar Tang",
        "\u06a9\u0648\u0634\u06a9 \u0633\u0631\u062a\u0646\u06af"
    ],
    "name:msa_x_preferred":[
        "Kushk-e Sar Tang"
    ],
    "name:und_x_variant":[
        "Am\u012br S\u0101l\u0101r-e Sar Tang",
        "K\u016bshk-i-Sartang"
    ],
    "wof:name":"Kushk-e Sar Tang",
    "wof:placetype":"locality"
},
  "geometry": {"coordinates":[52.8506,28.7508],"type":"Point"}
}