{
  "type": "Feature",
  "properties": {
    "gn:admin1_code":"7",
    "gn:asciiname":"Pir Ashkaft",
    "gn:country_code":"IR",
    "gn:dem":1892,
    "gn:feature_class":"P",
    "gn:feature_code":"PPL",
    "gn:name":"P\u012br Ashkaft",
    "gn:population":0,
    "gn:timezone":"Asia/Tehran",
    "iso:country":"IR",
    "name:fas_x_preferred":[
        "P\u012br Ashkaft"
    ],
    "wof:name":"Pir Ashkaft",
    "wof:placetype":"locality"
},
  "geometry": {"coordinates":[51.63333,30.35],"type":"Point"}
}