{
  "type": "Feature",
  "properties": {
    "gn:admin1_code":"13",
    "gn:asciiname":"Samangan",
    "gn:country_code":"IR",
    "gn:dem":1374,
    "gn:feature_class":"P",
    "gn:feature_code":"PPL",
    "gn:name":"Samang\u0101n",
    "gn:population":0,
    "gn:timezone":"Asia/Tehran",
    "iso:country":"IR",
    "name:cat_x_preferred":[
        "Samangan"
    ],
    "name:deu_x_preferred":[
        "Aybak"
    ],
    "name:epo_x_preferred":[
        "Ajbak"
    ],
    "name:est_x_preferred":[
        "Aybak"
    ],
    "name:fas_x_preferred":[
        "\u0633\u0645\u0646\u06af\u0627\u0646"
    ],
    "name:fas_x_variant":[
        "Samang\u0101n",
        "\u0627\u06cc\u0628\u06a9"
    ],
    "name:fin_x_preferred":[
        "Samangan"
    ],
    "name:ita_x_preferred":[
        "Aybak"
    ],
    "name:nld_x_preferred":[
        "Aybak"
    ],
    "name:pol_x_preferred":[
        "Ajbak"
    ],
    "name:por_x_preferred":[
        "Aybak"
    ],
    "name:ron_x_preferred":[
        "Aybak"
    ],
    "name:rus_x_preferred":[
        "\u0410\u0439\u0431\u0430\u043a"
    ],
    "name:tam_x_preferred":[
        "\u0b9a\u0bae\u0b99\u0bcd\u0b95\u0ba9\u0bcd"
    ],
    "name:tat_x_preferred":[
        "\u0410\u0439\u0431\u04d9\u043a"
    ],
    "name:tur_x_preferred":[
        "Aybek"
    ],
    "name:urd_x_preferred":[
        "\u0633\u0645\u0646\u06af\u0627\u0646"
    ],
    "name:zho_x_preferred":[
        "\u827e\u5df4\u514b"
    ],
    "wof:name":"Samangan",
    "wof:placetype":"locality"
},
  "geometry": {"coordinates":[46.7923,34.5808],"type":"Point"}
}