{
  "type": "Feature",
  "properties": {
    "gn:admin1_code":"13",
    "gn:asciiname":"Samangan",
    "gn:country_code":"IR",
    "gn:dem":1374,
    "gn:feature_class":"P",
    "gn:feature_code":"PPL",
    "gn:name":"Samang\u0101n",
    "gn:population":0,
    "gn:timezone":"Asia/Tehran",
    "iso:country":"IR",
    "name:fas_x_preferred":[
        "\u0633\u0645\u0646\u06af\u0627\u0646"
    ],
    "name:fas_x_variant":[
        "Samang\u0101n"
    ],
    "wof:name":"Samangan",
    "wof:placetype":"locality"
},
  "geometry": {"coordinates":[46.7923,34.5808],"type":"Point"}
}