{
  "type": "Feature",
  "properties": {
    "gn:admin1_code":"5.0",
    "gn:asciiname":"Deli Ab Barm",
    "gn:country_code":"IR",
    "gn:dem":1058,
    "gn:feature_class":"P",
    "gn:feature_code":"PPL",
    "gn:name":"Del\u012b \u0100b Barm",
    "gn:population":0,
    "gn:timezone":"Asia/Tehran",
    "iso:country":"IR",
    "name:fas_x_preferred":[
        "Del\u012b \u0100b Barm"
    ],
    "name:fas_x_variant":[
        "\u062f\u0644\u06cc \u0622\u0628 \u0628\u0631\u0645"
    ],
    "name:und_x_variant":[
        "\u062f\u0644\u06cc \u0622\u0628 \u0628\u0631\u0645"
    ],
    "wof:name":"Deli Ab Barm",
    "wof:placetype":"locality"
},
  "geometry": {"coordinates":[50.84035,30.73194],"type":"Point"}
}