{
  "type": "Feature",
  "properties": {
    "gn:admin1_code":"11.0",
    "gn:asciiname":"Shiveh'i",
    "gn:country_code":"IR",
    "gn:dem":264,
    "gn:feature_class":"P",
    "gn:feature_code":"PPL",
    "gn:name":"Sh\u012bveh\u2019\u012b",
    "gn:population":0,
    "gn:timezone":"Asia/Tehran",
    "iso:country":"IR",
    "name:fas_x_preferred":[
        "\u0634\u06cc\u0648\u0647 \u0627\u06cc"
    ],
    "name:fas_x_variant":[
        "\u0634\u06cc\u0648\u0647\u200c\u0627\u06cc"
    ],
    "name:msa_x_preferred":[
        "Shivehi"
    ],
    "name:und_x_variant":[
        "Sh\u012bveh\u2019\u012b"
    ],
    "wof:name":"Shiveh'i",
    "wof:placetype":"locality"
},
  "geometry": {"coordinates":[57.4298,26.8926],"type":"Point"}
}