{
  "type": "Feature",
  "properties": {
    "gn:admin1_code":"26",
    "gn:asciiname":"Tares",
    "gn:country_code":"IR",
    "gn:dem":2052,
    "gn:feature_class":"P",
    "gn:feature_code":"PPL",
    "gn:name":"\u0162\u0101res",
    "gn:population":0,
    "gn:timezone":"Asia/Tehran",
    "iso:country":"IR",
    "name:fas_x_preferred":[
        "\u0637\u0627\u0631\u0633"
    ],
    "name:fas_x_variant":[
        "\u0162\u0101res"
    ],
    "name:und_x_variant":[
        "T\u0101res",
        "T\u0101ras"
    ],
    "wof:name":"Tares",
    "wof:placetype":"locality"
},
  "geometry": {"coordinates":[52.65444,35.79281],"type":"Point"}
}