{
  "type": "Feature",
  "properties": {
    "gn:admin1_code":"28.0",
    "gn:asciiname":"Hoseynabad",
    "gn:country_code":"IR",
    "gn:dem":1533,
    "gn:feature_class":"P",
    "gn:feature_code":"PPL",
    "gn:name":"\u1e28oseyn\u0101b\u0101d",
    "gn:population":0,
    "gn:timezone":"Asia/Tehran",
    "iso:country":"IR",
    "name:fas_x_preferred":[
        "\u1e28oseyn\u0101b\u0101d"
    ],
    "name:fas_x_variant":[
        "\u062d\u0633\u06cc\u0646 \u0622\u0628\u0627\u062f",
        "\u062d\u0633\u06cc\u0646 \u0622\u0628\u0627\u062f \u0622\u0634\u06a9\u0634\u0627\u0646"
    ],
    "name:und_x_variant":[
        "\u062d\u0633\u06cc\u0646 \u0622\u0628\u0627\u062f",
        "\u1e28oseyn\u0101b\u0101d-e \u0100shkesh\u0101n"
    ],
    "wof:name":"Hoseynabad",
    "wof:placetype":"locality"
},
  "geometry": {"coordinates":[51.88868,32.571],"type":"Point"}
}