{
  "type": "Feature",
  "properties": {
    "gn:admin1_code":"4.0",
    "gn:asciiname":"Kachki",
    "gn:country_code":"IR",
    "gn:dem":710,
    "gn:feature_class":"P",
    "gn:feature_code":"PPL",
    "gn:name":"Kachk\u012b",
    "gn:population":0,
    "gn:timezone":"Asia/Tehran",
    "iso:country":"IR",
    "name:fas_x_preferred":[
        "\u06a9\u0686\u06a9\u06cc"
    ],
    "name:fas_x_variant":[
        "Kojk\u012b",
        "Kachk\u012b",
        "K\u016bchek\u012b",
        "Kajk\u012b"
    ],
    "name:und_x_variant":[
        "K\u016bchek\u012b",
        "Kajk\u012b"
    ],
    "wof:name":"Kachki",
    "wof:placetype":"locality"
},
  "geometry": {"coordinates":[60.2046,26.89014],"type":"Point"}
}