{
  "type": "Feature",
  "properties": {
    "gn:admin1_code":"41.0",
    "gn:asciiname":"Tageshtrow",
    "gn:country_code":"IR",
    "gn:dem":2276,
    "gn:feature_class":"P",
    "gn:feature_code":"PPL",
    "gn:name":"T\u0101geshtrow",
    "gn:population":0,
    "gn:timezone":"Asia/Tehran",
    "iso:country":"IR",
    "name:fas_x_preferred":[
        "T\u0101geshtrow"
    ],
    "name:fas_x_variant":[
        "\u062a\u0627\u06af\u0634\u062a\u0631\u0648"
    ],
    "wof:name":"Tageshtrow",
    "wof:placetype":"locality"
},
  "geometry": {"coordinates":[59.28004,32.75359],"type":"Point"}
}