{
  "type": "Feature",
  "properties": {
    "gn:admin1_code":"4.0",
    "gn:asciiname":"Modir",
    "gn:country_code":"IR",
    "gn:dem":562,
    "gn:feature_class":"P",
    "gn:feature_code":"PPL",
    "gn:name":"Mod\u012br",
    "gn:population":0,
    "gn:timezone":"Asia/Tehran",
    "iso:country":"IR",
    "name:fas_x_preferred":[
        "Mod\u012br"
    ],
    "wof:name":"Modir",
    "wof:placetype":"locality"
},
  "geometry": {"coordinates":[60.76639,26.26417],"type":"Point"}
}