{
  "type": "Feature",
  "properties": {
    "gn:admin1_code":"33",
    "gn:asciiname":"Tazeh Kand",
    "gn:country_code":"IR",
    "gn:dem":1810,
    "gn:elevation":"0.0",
    "gn:feature_class":"P",
    "gn:feature_code":"PPL",
    "gn:name":"T\u0101zeh Kand",
    "gn:population":0,
    "gn:timezone":"Asia/Tehran",
    "iso:country":"IR",
    "name:ceb_x_preferred":[
        "Tazeh Kand"
    ],
    "name:fas_x_preferred":[
        "\u062a\u0627\u0632\u0647 \u06a9\u0646\u062f"
    ],
    "name:fas_x_variant":[
        "T\u0101zeh Kand",
        "\u062a\u0627\u0632\u0647\u200c\u06a9\u0646\u062f"
    ],
    "name:swe_x_preferred":[
        "Tazeh Kand"
    ],
    "wof:name":"Tazeh Kand",
    "wof:placetype":"locality"
},
  "geometry": {"coordinates":[47.0799,38.2046],"type":"Point"}
}