{
  "type": "Feature",
  "properties": {
    "gn:admin1_code":"39",
    "gn:asciiname":"Vasfownjerd",
    "gn:country_code":"IR",
    "gn:dem":1569,
    "gn:feature_class":"P",
    "gn:feature_code":"PPL",
    "gn:name":"Vasfownjerd",
    "gn:population":0,
    "gn:timezone":"Asia/Tehran",
    "iso:country":"IR",
    "name:ceb_x_preferred":[
        "Vasfownjerd"
    ],
    "name:fas_x_preferred":[
        "\u0648\u0633\u0641\u0648\u0646\u062c\u0631\u062f"
    ],
    "name:swe_x_preferred":[
        "Vasfownjerd"
    ],
    "name:und_x_variant":[
        "\u0648\u0633\u0641\u0648\u0646\u062c\u0631\u062f",
        "Vasfownjerd"
    ],
    "wof:name":"Vasfownjerd",
    "wof:placetype":"locality"
},
  "geometry": {"coordinates":[50.28688,34.67351],"type":"Point"}
}