{
  "type": "Feature",
  "properties": {
    "gn:admin1_code":"33",
    "gn:asciiname":"Kalleh Quzi",
    "gn:country_code":"IR",
    "gn:dem":1956,
    "gn:feature_class":"P",
    "gn:feature_code":"PPL",
    "gn:name":"Kalleh Q\u016bz\u012b",
    "gn:population":0,
    "gn:timezone":"Asia/Tehran",
    "iso:country":"IR",
    "name:fas_x_preferred":[
        "\u0643\u0644\u06cc \u0642\u0648\u0632\u06cc"
    ],
    "name:fas_x_variant":[
        "\u06af\u064f\u0644\u06cc \u0642\u0648\u0632\u06cc",
        "\u0643\u064f\u0644\u0651\u06cc",
        "\u0643\u064f\u0644\u06cc",
        "Kal\u012b Q\u016bz\u012b",
        "\u0643\u0644\u0647 \u0642\u0648\u0632\u06cc"
    ],
    "name:und_x_variant":[
        "Kol\u012b",
        "Gol\u012b Q\u016bz\u012b",
        "Koll\u012b",
        "Kalleh Q\u016bz\u012b"
    ],
    "wof:name":"Kalleh Quzi",
    "wof:placetype":"locality"
},
  "geometry": {"coordinates":[47.17502,38.82182],"type":"Point"}
}