{
  "type": "Feature",
  "properties": {
    "gn:admin1_code":"32",
    "gn:asciiname":"Ebrahimabad-e Qadim",
    "gn:country_code":"IR",
    "gn:dem":65,
    "gn:feature_class":"P",
    "gn:feature_code":"PPL",
    "gn:name":"Ebr\u0101h\u012bm\u0101b\u0101d-e Qad\u012bm",
    "gn:population":0,
    "gn:timezone":"Asia/Tehran",
    "iso:country":"IR",
    "name:fas_x_preferred":[
        "\u0627\u0628\u0631\u0627\u0647\u06cc\u0645 \u0622\u0628\u0627\u062f \u0642\u062f\u06cc\u0645"
    ],
    "name:fas_x_variant":[
        "Ebr\u0101h\u012bm\u0101b\u0101d-e Qad\u012bm"
    ],
    "wof:name":"Ebrahimabad-e Qadim",
    "wof:placetype":"locality"
},
  "geometry": {"coordinates":[47.8408,39.6223],"type":"Point"}
}