{
  "type": "Feature",
  "properties": {
    "gn:admin1_code":"7.0",
    "gn:asciiname":"Anjireh",
    "gn:country_code":"IR",
    "gn:dem":1136,
    "gn:feature_class":"P",
    "gn:feature_code":"PPL",
    "gn:name":"Anj\u012breh",
    "gn:population":0,
    "gn:timezone":"Asia/Tehran",
    "iso:country":"IR",
    "name:fas_x_preferred":[
        "Anj\u012breh"
    ],
    "name:fas_x_variant":[
        "\u0627\u0646\u062c\u06cc\u0631\u0647"
    ],
    "wof:name":"Anjireh",
    "wof:placetype":"locality"
},
  "geometry": {"coordinates":[51.51744,30.33951],"type":"Point"}
}