{
  "type": "Feature",
  "properties": {
    "gn:admin1_code":"42",
    "gn:asciiname":"Barmuk",
    "gn:country_code":"IR",
    "gn:dem":1409,
    "gn:feature_class":"P",
    "gn:feature_code":"PPLF",
    "gn:name":"Barm\u016bk",
    "gn:population":0,
    "gn:timezone":"Asia/Tehran",
    "iso:country":"IR",
    "name:fas_x_preferred":[
        "\u0628\u0631\u0645\u0648\u06a9"
    ],
    "name:fas_x_variant":[
        "Bar M\u016bk"
    ],
    "name:und_x_variant":[
        "Barm\u016bk"
    ],
    "wof:name":"Barmuk",
    "wof:placetype":"locality"
},
  "geometry": {"coordinates":[59.76067,35.01661],"type":"Point"}
}