{
  "type": "Feature",
  "properties": {
    "gn:admin1_code":"7.0",
    "gn:asciiname":"Deh-e Kuhyar",
    "gn:country_code":"IR",
    "gn:dem":1978,
    "gn:feature_class":"P",
    "gn:feature_code":"PPL",
    "gn:name":"Deh-e K\u016bhy\u0101r",
    "gn:population":0,
    "gn:timezone":"Asia/Tehran",
    "iso:country":"IR",
    "name:fas_x_preferred":[
        "Deh-e K\u016bhy\u0101r"
    ],
    "name:fas_x_variant":[
        "\u062f\u0647 \u06a9\u0648\u0647\u06cc\u0627\u0631"
    ],
    "wof:name":"Deh-e Kuhyar",
    "wof:placetype":"locality"
},
  "geometry": {"coordinates":[51.32195,30.56444],"type":"Point"}
}