{
  "type": "Feature",
  "properties": {
    "gn:admin1_code":"13",
    "gn:asciiname":"Gerdakaneh-ye `Olya",
    "gn:country_code":"IR",
    "gn:dem":1998,
    "gn:feature_class":"P",
    "gn:feature_code":"PPL",
    "gn:name":"Gerdak\u0101neh-ye \u2018Oly\u0101",
    "gn:population":0,
    "gn:timezone":"Asia/Tehran",
    "iso:country":"IR",
    "name:fas_x_preferred":[
        "Gerdk\u0101n\u012b-ye \u2018Oly\u0101"
    ],
    "name:fas_x_variant":[
        "Gerdak\u0101neh-ye \u2018Oly\u0101",
        "\u06af\u0631\u062f\u06a9\u0627\u0646\u0647 \u0639\u0644\u06cc\u0627"
    ],
    "name:und_x_variant":[
        "G\u012brdehk\u0101n\u012b B\u0101la",
        "Gerdeh Kan\u012b-ye B\u0101l\u0101",
        "Gerdkan\u012b-ye B\u0101l\u0101",
        "\u06af\u0631\u062f\u06a9\u0627\u0646\u0647 \u0639\u0644\u06cc\u0627"
    ],
    "wof:name":"Gerdakaneh-ye `Olya",
    "wof:placetype":"locality"
},
  "geometry": {"coordinates":[47.58337,35.06433],"type":"Point"}
}