{
  "type": "Feature",
  "properties": {
    "gn:admin1_code":"25",
    "gn:asciiname":"Hamru",
    "gn:country_code":"IR",
    "gn:dem":1916,
    "gn:feature_class":"P",
    "gn:feature_code":"PPL",
    "gn:name":"\u1e28amr\u016b",
    "gn:population":0,
    "gn:timezone":"Asia/Tehran",
    "iso:country":"IR",
    "name:fas_x_preferred":[
        "\u062d\u064e\u0645\u0631\u0648"
    ],
    "name:fas_x_variant":[
        "\u1e28amr\u016b"
    ],
    "wof:name":"Hamru",
    "wof:placetype":"locality"
},
  "geometry": {"coordinates":[53.83333,35.71667],"type":"Point"}
}