{
  "type": "Feature",
  "properties": {
    "gn:admin1_code":"35",
    "gn:asciiname":"Now Pichar Mahalleh",
    "gn:country_code":"IR",
    "gn:dem":-4,
    "gn:feature_class":"P",
    "gn:feature_code":"PPL",
    "gn:name":"Now P\u012bch\u0101r Ma\u1e29alleh",
    "gn:population":0,
    "gn:timezone":"Asia/Tehran",
    "iso:country":"IR",
    "name:fas_x_preferred":[
        "\u0646\u064f\u0648 \u067e\u064a\u0686\u0627\u0631 \u0645\u064e\u062d\u064e\u0644\u0650\u0651\u0647"
    ],
    "name:fas_x_variant":[
        "Now P\u012bch\u0101r Ma\u1e29alleh"
    ],
    "wof:name":"Now Pichar Mahalleh",
    "wof:placetype":"locality"
},
  "geometry": {"coordinates":[52.68333000000001,36.56667],"type":"Point"}
}