{
  "type": "Feature",
  "properties": {
    "gn:admin1_code":"11",
    "gn:asciiname":"Ziarat-e `Ali",
    "gn:country_code":"IR",
    "gn:dem":478,
    "gn:feature_class":"P",
    "gn:feature_code":"PPL",
    "gn:name":"Z\u012b\u0101rat-e \u2018Al\u012b",
    "gn:population":0,
    "gn:timezone":"Asia/Tehran",
    "iso:country":"IR",
    "name:fas_x_preferred":[
        "\u0632\u064a\u0627\u0631\u062a \u0639\u0644\u06cc"
    ],
    "name:fas_x_variant":[
        "\u0632\u0650\u064a\u0627\u0631\u064e\u062a\u0650 \u0639\u064e\u0644\u06cc",
        "\u062f\u064e\u0631\u0650 \u062e\u0648\u0646\u0650\u06c0 \u0639\u064e\u0644\u06cc",
        "\u0632\u064a\u064e\u0651\u0631\u064e\u062a \u0627\u064e\u0644\u06cc",
        "\u0632\u064a\u0627\u0631\u064e\u062a\u0650 \u0639\u064e\u0644\u0626 \u0639\u064f\u0644\u064a\u0627",
        "Z\u012b\u0101rat-e \u2018Al\u012b"
    ],
    "name:und_x_variant":[
        "Dar-e Kh\u016bneh-ye \u2018Al\u012b",
        "Zey\u0101rat-e \u2018Al\u012b",
        "Z\u012byarat Al\u012b",
        "Z\u012b\u0101rat-e \u2018Al\u012b-ye \u2018Oly\u0101"
    ],
    "wof:name":"Ziarat-e `Ali",
    "wof:placetype":"locality"
},
  "geometry": {"coordinates":[57.2238,27.7422],"type":"Point"}
}