{
  "type": "Feature",
  "properties": {
    "gn:admin1_code":"13",
    "gn:asciiname":"Bavaleh",
    "gn:country_code":"IR",
    "gn:dem":1829,
    "gn:feature_class":"P",
    "gn:feature_code":"PPL",
    "gn:name":"B\u0101valeh",
    "gn:population":0,
    "gn:timezone":"Asia/Tehran",
    "iso:country":"IR",
    "name:fas_x_preferred":[
        "\u0628\u0627\u0648\u0644\u0647"
    ],
    "name:fas_x_variant":[
        "B\u0101valeh"
    ],
    "name:und_x_variant":[
        "B\u0101valeh-ye Fa\u2018leh Kor\u012b",
        "B\u0101wali"
    ],
    "wof:name":"Bavaleh",
    "wof:placetype":"locality"
},
  "geometry": {"coordinates":[47.71677,34.89115],"type":"Point"}
}