{
  "type": "Feature",
  "properties": {
    "gn:admin1_code":"43",
    "gn:asciiname":"Jan Ahmadi",
    "gn:country_code":"IR",
    "gn:dem":1412,
    "gn:feature_class":"P",
    "gn:feature_code":"PPL",
    "gn:name":"J\u0101n A\u1e29mad\u012b",
    "gn:population":0,
    "gn:timezone":"Asia/Tehran",
    "iso:country":"IR",
    "name:ara_x_preferred":[
        "\u062c\u0627\u0646 \u0627\u062d\u0645\u062f\u064a"
    ],
    "name:fas_x_preferred":[
        "J\u0101n A\u1e29mad\u012b"
    ],
    "name:fas_x_variant":[
        "\u062c\u0627\u0646 \u0627\u062d\u0645\u062f\u06cc"
    ],
    "name:urd_x_preferred":[
        "\u062c\u0627\u0646 \u0627\u062d\u0645\u062f\u06cc"
    ],
    "wof:name":"Jan Ahmadi",
    "wof:placetype":"locality"
},
  "geometry": {"coordinates":[57.59546,37.07859000000001],"type":"Point"}
}