{
  "type": "Feature",
  "properties": {
    "gn:admin1_code":"28.0",
    "gn:asciiname":"Qal`eh-e Hajji",
    "gn:country_code":"IR",
    "gn:dem":1914,
    "gn:feature_class":"P",
    "gn:feature_code":"PPL",
    "gn:name":"Qal\u2018eh-e \u1e28\u0101jj\u012b",
    "gn:population":0,
    "gn:timezone":"Asia/Tehran",
    "iso:country":"IR",
    "name:fas_x_preferred":[
        "Qal\u2018eh-e \u1e28\u0101jj\u012b"
    ],
    "name:und_x_variant":[
        "Qal\u2018eh-ye \u1e28\u0101jj\u012b"
    ],
    "wof:name":"Qal`eh-e Hajji",
    "wof:placetype":"locality"
},
  "geometry": {"coordinates":[51.21833,32.29167],"type":"Point"}
}