{
  "type": "Feature",
  "properties": {
    "gn:admin1_code":"9",
    "gn:asciiname":"Mahmudabad",
    "gn:country_code":"IR",
    "gn:dem":1999,
    "gn:feature_class":"P",
    "gn:feature_code":"PPL",
    "gn:name":"Ma\u1e29m\u016bd\u0101b\u0101d",
    "gn:population":0,
    "gn:timezone":"Asia/Tehran",
    "iso:country":"IR",
    "name:fas_x_preferred":[
        "Ma\u1e29m\u016bd\u0101b\u0101d"
    ],
    "name:fas_x_variant":[
        "\u0645\u062d\u0645\u0648\u062f \u0622\u0628\u0627\u062f",
        "\u0645\u062d\u0645\u0648\u062f\u0622\u0628\u0627\u062f"
    ],
    "name:msa_x_preferred":[
        "Mahmudabad"
    ],
    "name:und_x_variant":[
        "\u0645\u062d\u0645\u0648\u062f \u0622\u0628\u0627\u062f"
    ],
    "wof:name":"Mahmudabad",
    "wof:placetype":"locality"
},
  "geometry": {"coordinates":[48.70734,34.16005],"type":"Point"}
}