{
  "type": "Feature",
  "properties": {
    "gn:admin1_code":"4.0",
    "gn:asciiname":"Khvajeh Mesk",
    "gn:country_code":"IR",
    "gn:dem":1697,
    "gn:feature_class":"P",
    "gn:feature_code":"PPL",
    "gn:name":"Khv\u0101jeh Mesk",
    "gn:population":0,
    "gn:timezone":"Asia/Tehran",
    "iso:country":"IR",
    "name:fas_x_preferred":[
        "\u062e\u0648\u0627\u062c\u0647 \u0645\u0633\u06a9"
    ],
    "name:fas_x_variant":[
        "Khv\u0101jeh Mesk"
    ],
    "wof:name":"Khvajeh Mesk",
    "wof:placetype":"locality"
},
  "geometry": {"coordinates":[60.8422,29.2762],"type":"Point"}
}