{
  "type": "Feature",
  "properties": {
    "gn:admin1_code":"4.0",
    "gn:asciiname":"Deh-e Azad",
    "gn:country_code":"IR",
    "gn:dem":486,
    "gn:feature_class":"P",
    "gn:feature_code":"PPL",
    "gn:name":"Deh-e \u0100z\u0101d",
    "gn:population":0,
    "gn:timezone":"Asia/Tehran",
    "iso:country":"IR",
    "name:fas_x_preferred":[
        "Deh-e \u0100z\u0101d"
    ],
    "name:fas_x_variant":[
        "\u0100z\u0101d",
        "\u062f\u0647 \u0622\u0632\u0627\u062f",
        "\u062f\u0647\u200c\u0622\u0632\u0627\u062f"
    ],
    "wof:name":"Deh-e Azad",
    "wof:placetype":"locality"
},
  "geometry": {"coordinates":[61.7611,31.0542],"type":"Point"}
}