{
  "type": "Feature",
  "properties": {
    "gn:admin1_code":"8",
    "gn:asciiname":"Makalvan",
    "gn:country_code":"IR",
    "gn:dem":149,
    "gn:feature_class":"P",
    "gn:feature_code":"PPL",
    "gn:name":"M\u0101kalv\u0101n",
    "gn:population":0,
    "gn:timezone":"Asia/Tehran",
    "iso:country":"IR",
    "name:ara_x_preferred":[
        "\u0645\u0627\u0643\u0644\u0648\u0627\u0646"
    ],
    "name:aze_x_preferred":[
        "Makl\u0259van"
    ],
    "name:fas_x_preferred":[
        "\u0645\u0627\u06a9\u0644\u0648\u0627\u0646"
    ],
    "name:fas_x_variant":[
        "P\u0101\u2019\u012bn M\u0101klav\u0101n",
        "M\u0101kalv\u0101n"
    ],
    "name:msa_x_preferred":[
        "Maklavan"
    ],
    "name:und_x_variant":[
        "M\u0101klav\u0101n",
        "Moklavan",
        "M\u0101hlav\u0101n"
    ],
    "wof:name":"Makalvan",
    "wof:placetype":"locality"
},
  "geometry": {"coordinates":[49.1887,37.1894],"type":"Point"}
}