{
  "type": "Feature",
  "properties": {
    "gn:admin1_code":"16.0",
    "gn:asciiname":"Ajgareh",
    "gn:country_code":"IR",
    "gn:dem":1643,
    "gn:elevation":"0.0",
    "gn:feature_class":"P",
    "gn:feature_code":"PPL",
    "gn:name":"\u0100jgareh",
    "gn:population":0,
    "gn:timezone":"Asia/Tehran",
    "iso:country":"IR",
    "name:ceb_x_preferred":[
        "\u0100jgareh"
    ],
    "name:fas_x_preferred":[
        "\u0627\u064e\u062c\u06af\u064e\u0631\u0650\u0647"
    ],
    "name:fas_x_variant":[
        "\u0647\u064e\u0698 \u06af\u064e\u0631\u0650\u0651\u0647",
        "\u0647\u064e\u0698\u06af\u064e\u0631\u064e",
        "\u0622\u062c\u06af\u0631\u0647",
        "\u0100jgareh",
        "\u0627\u062c\u06af\u0631\u0647"
    ],
    "name:swe_x_preferred":[
        "\u0100jgareh"
    ],
    "name:und_x_variant":[
        "Hazh Garreh",
        "Hazhgara",
        "Ajgareh"
    ],
    "wof:name":"Ajgareh",
    "wof:placetype":"locality"
},
  "geometry": {"coordinates":[46.9616,35.3733],"type":"Point"}
}