{
  "type": "Feature",
  "properties": {
    "gn:admin1_code":"15",
    "gn:asciiname":"Toreyfeh",
    "gn:country_code":"IR",
    "gn:dem":115,
    "gn:feature_class":"P",
    "gn:feature_code":"PPL",
    "gn:name":"\u0162oreyfeh",
    "gn:population":0,
    "gn:timezone":"Asia/Tehran",
    "iso:country":"IR",
    "name:ara_x_preferred":[
        "\u0637\u0631\u064a\u0641\u0629"
    ],
    "name:fas_x_preferred":[
        "\u0162oreyfeh"
    ],
    "name:fas_x_variant":[
        "\u0637\u0631\u06cc\u0641\u0647",
        "\u0638\u0647\u06cc\u0631\u06cc"
    ],
    "name:und_x_variant":[
        "\u0637\u0631\u06cc\u0641\u0647",
        "Z\u0327oheyr\u012b"
    ],
    "wof:name":"Toreyfeh",
    "wof:placetype":"locality"
},
  "geometry": {"coordinates":[49.54154000000001,31.33198],"type":"Point"}
}