{
  "type": "Feature",
  "properties": {
    "gn:admin1_code":"42",
    "gn:asciiname":"Chenar Sukhteh",
    "gn:country_code":"IR",
    "gn:dem":1096,
    "gn:feature_class":"P",
    "gn:feature_code":"PPL",
    "gn:name":"Chen\u0101r S\u016bkhteh",
    "gn:population":0,
    "gn:timezone":"Asia/Tehran",
    "iso:country":"IR",
    "name:fas_x_preferred":[
        "\u0686\u0646\u0627\u0631 \u0633\u0648\u062e\u062a\u0647"
    ],
    "name:fas_x_variant":[
        "Chen\u0101r S\u016bkhteh"
    ],
    "name:und_x_variant":[
        "S\u016bkhteh Chin\u0101r",
        "S\u016bkhteh Chen\u0101r"
    ],
    "wof:name":"Chenar Sukhteh",
    "wof:placetype":"locality"
},
  "geometry": {"coordinates":[59.33709,36.53212],"type":"Point"}
}