{
  "type": "Feature",
  "properties": {
    "gn:admin1_code":"8",
    "gn:asciiname":"Shahrak-e Emam Khomeyni",
    "gn:country_code":"IR",
    "gn:dem":35,
    "gn:feature_class":"P",
    "gn:feature_code":"PPL",
    "gn:name":"Shahrak-e Em\u0101m Khomeyn\u012b",
    "gn:population":0,
    "gn:timezone":"Asia/Tehran",
    "iso:country":"IR",
    "name:fas_x_preferred":[
        "Shahrak-e Em\u0101m Khomeyn\u012b"
    ],
    "name:fas_x_variant":[
        "\u0634\u0647\u0631\u06a9 \u0627\u0645\u0627\u0645 \u062e\u0645\u06cc\u0646\u06cc"
    ],
    "name:und_x_variant":[
        "Shahrak-e Sh\u0101hp\u016br Ghol\u0101mre\u1e95\u0101"
    ],
    "wof:name":"Shahrak-e Emam Khomeyni",
    "wof:placetype":"locality"
},
  "geometry": {"coordinates":[49.81314,37.14442],"type":"Point"}
}