{
  "type": "Feature",
  "properties": {
    "gn:admin1_code":"23",
    "gn:asciiname":"Darreh Zardi",
    "gn:country_code":"IR",
    "gn:dem":1462,
    "gn:feature_class":"P",
    "gn:feature_code":"PPL",
    "gn:name":"Darreh Zard\u012b",
    "gn:population":0,
    "gn:timezone":"Asia/Tehran",
    "iso:country":"IR",
    "name:fas_x_preferred":[
        "\u062f\u0631\u0651\u0647 \u0632\u0631\u062f\u06cc"
    ],
    "name:fas_x_variant":[
        "Darreh Zard\u012b"
    ],
    "wof:name":"Darreh Zardi",
    "wof:placetype":"locality"
},
  "geometry": {"coordinates":[48.4525,33.5542],"type":"Point"}
}