{
  "type": "Feature",
  "properties": {
    "gn:admin1_code":"25",
    "gn:asciiname":"Dowzahir",
    "gn:country_code":"IR",
    "gn:dem":1624,
    "gn:feature_class":"P",
    "gn:feature_code":"PPL",
    "gn:name":"Dowzah\u012br",
    "gn:population":0,
    "gn:timezone":"Asia/Tehran",
    "iso:country":"IR",
    "name:ceb_x_preferred":[
        "Dowzah\u012br"
    ],
    "name:fas_x_preferred":[
        "\u062f\u0648\u0632\u0647\u064a\u0631"
    ],
    "name:fas_x_variant":[
        "Dowzah\u012br",
        "\u062f\u0648\u0632\u0647\u06cc\u0631"
    ],
    "name:swe_x_preferred":[
        "Dowzah\u012br"
    ],
    "name:und_x_variant":[
        "D\u016bzah\u012br",
        "Dozair"
    ],
    "wof:name":"Dowzahir",
    "wof:placetype":"locality"
},
  "geometry": {"coordinates":[53.89771999999999,35.6373],"type":"Point"}
}