{
  "type": "Feature",
  "properties": {
    "gn:admin1_code":"26",
    "gn:asciiname":"Karimabad",
    "gn:country_code":"IR",
    "gn:dem":999,
    "gn:feature_class":"P",
    "gn:feature_code":"PPL",
    "gn:name":"Kar\u012bm\u0101b\u0101d",
    "gn:population":0,
    "gn:timezone":"Asia/Tehran",
    "iso:country":"IR",
    "name:fas_x_preferred":[
        "\u0643\u0631\u064a\u0645 \u0622\u0628\u0627\u062f"
    ],
    "name:fas_x_variant":[
        "\u0643\u064e\u0631\u064a\u0645\u0627\u0628\u0627\u062f\u0650 \u062e\u0627\u0644\u0650\u0635\u0650\u0647",
        "Kar\u012bm\u0101b\u0101d",
        "\u0643\u064e\u0631\u064a\u0645 \u0622\u0628\u0627\u062f"
    ],
    "name:und_x_variant":[
        "Kar\u012bm\u0101b\u0101d-e Kh\u0101le\u015feh"
    ],
    "wof:name":"Karimabad",
    "wof:placetype":"locality"
},
  "geometry": {"coordinates":[51.805,35.3892],"type":"Point"}
}