{
  "type": "Feature",
  "properties": {
    "gn:admin1_code":"8",
    "gn:asciiname":"Degoli",
    "gn:country_code":"IR",
    "gn:dem":684,
    "gn:feature_class":"P",
    "gn:feature_code":"PPL",
    "gn:name":"Degol\u012b",
    "gn:population":0,
    "gn:timezone":"Asia/Tehran",
    "iso:country":"IR",
    "name:fas_x_preferred":[
        "\u0631\u0632\u0647"
    ],
    "name:fas_x_variant":[
        "\u062f\u06af\u0644\u06cc",
        "\u062f\u06cc\u06af\u0644\u06cc"
    ],
    "name:und_x_variant":[
        "Rezeh",
        "Razeh",
        "Degol\u012b",
        "D\u012bgol\u012b"
    ],
    "wof:name":"Degoli",
    "wof:placetype":"locality"
},
  "geometry": {"coordinates":[48.7962,37.8684],"type":"Point"}
}