{
  "type": "Feature",
  "properties": {
    "gn:admin1_code":"8",
    "gn:asciiname":"Shalasheh Darreh",
    "gn:country_code":"IR",
    "gn:dem":186,
    "gn:feature_class":"P",
    "gn:feature_code":"PPL",
    "gn:name":"Shalasheh Darreh",
    "gn:population":0,
    "gn:timezone":"Asia/Tehran",
    "iso:country":"IR",
    "name:ara_x_preferred":[
        "\u0634\u0644\u0634\u0629 \u062f\u0631\u0647"
    ],
    "name:ceb_x_preferred":[
        "Shal\u0101sh Darreh"
    ],
    "name:fas_x_preferred":[
        "Shal\u0101sh Darreh"
    ],
    "name:fas_x_variant":[
        "\u0634\u0644\u0634\u0647 \u062f\u0631\u0647",
        "\u0634\u0627\u0644\u0634 \u062f\u0631\u0647"
    ],
    "name:msa_x_preferred":[
        "Shalash Darreh"
    ],
    "name:swe_x_preferred":[
        "Shal\u0101sh Darreh"
    ],
    "name:ukr_x_preferred":[
        "\u0428\u0430\u043b\u0430\u0448\u0435-\u0414\u0430\u0440\u0435"
    ],
    "name:und_x_variant":[
        "Sh\u0101lesh Darreh",
        "Shalasheh Darreh"
    ],
    "wof:name":"Shalasheh Darreh",
    "wof:placetype":"locality"
},
  "geometry": {"coordinates":[49.16598,37.2321],"type":"Point"}
}