{
  "type": "Feature",
  "properties": {
    "gn:admin1_code":"44.0",
    "gn:asciiname":"Daryush",
    "gn:country_code":"IR",
    "gn:dem":1487,
    "gn:feature_class":"P",
    "gn:feature_code":"PPL",
    "gn:name":"D\u0101ry\u016bsh",
    "gn:population":0,
    "gn:timezone":"Asia/Tehran",
    "iso:country":"IR",
    "name:fas_x_preferred":[
        "\u062f\u0627\u0631\u064a\u0648\u0634"
    ],
    "name:und_x_variant":[
        "D\u0101ry\u016bsh"
    ],
    "wof:name":"Daryush",
    "wof:placetype":"locality"
},
  "geometry": {"coordinates":[50.99917,35.855],"type":"Point"}
}