{
  "type": "Feature",
  "properties": {
    "gn:admin1_code":"43.0",
    "gn:asciiname":"Kalat-e Hajj Rahmat",
    "gn:country_code":"IR",
    "gn:dem":1210,
    "gn:feature_class":"P",
    "gn:feature_code":"PPL",
    "gn:name":"Kal\u0101t-e \u1e28\u0101jj Ra\u1e29mat",
    "gn:population":0,
    "gn:timezone":"Asia/Tehran",
    "iso:country":"IR",
    "name:fas_x_preferred":[
        "Kal\u0101teh-ye \u1e28\u0101jj Ra\u1e29mat"
    ],
    "name:fas_x_variant":[
        "\u06a9\u0644\u0627\u062a \u062d\u0627\u062c \u0631\u062d\u0645\u062a",
        "\u06a9\u0644\u0627\u062a\u0647 \u062d\u0627\u062c \u0639\u0644\u06cc \u0627\u06a9\u0628\u0631"
    ],
    "name:und_x_variant":[
        "Kal\u0101t-e \u1e28\u0101jj Ra\u1e29mat",
        "Kal\u0101teh-ye \u1e28\u0101jj \u2018Al\u012b Akbar"
    ],
    "wof:name":"Kalat-e Hajj Rahmat",
    "wof:placetype":"locality"
},
  "geometry": {"coordinates":[56.75953000000001,37.30032],"type":"Point"}
}