{
  "type": "Feature",
  "properties": {
    "gn:admin1_code":"29",
    "gn:asciiname":"Hezar Buteh",
    "gn:country_code":"IR",
    "gn:dem":655,
    "gn:feature_class":"P",
    "gn:feature_code":"PPL",
    "gn:name":"Hez\u0101r B\u016bteh",
    "gn:population":0,
    "gn:timezone":"Asia/Tehran",
    "iso:country":"IR",
    "name:fas_x_preferred":[
        "\u0686\u0627\u0647 \u06af\u0644\u06cc"
    ],
    "name:fas_x_variant":[
        "Ch\u0101h Gol\u012b",
        "\u0647\u0632\u0627\u0631 \u0628\u0648\u062a\u0647",
        "\u0645\u0648\u062a\u0648\u0631 \u0647\u0632\u0627\u0631 \u0628\u0648\u062a\u0647 \u062d\u0648\u0631"
    ],
    "name:und_x_variant":[
        "Hez\u0101r B\u016bteh",
        "Mowtowr-e Hez\u0101r B\u016bteh \u1e28owr"
    ],
    "wof:name":"Hezar Buteh",
    "wof:placetype":"locality"
},
  "geometry": {"coordinates":[57.25431,28.1248],"type":"Point"}
}