{
  "type": "Feature",
  "properties": {
    "gn:admin1_code":"42.0",
    "gn:asciiname":"Kalateh-ye Gaz",
    "gn:country_code":"IR",
    "gn:dem":982,
    "gn:feature_class":"P",
    "gn:feature_code":"PPL",
    "gn:name":"Kal\u0101teh-ye Gaz",
    "gn:population":0,
    "gn:timezone":"Asia/Tehran",
    "iso:country":"IR",
    "name:ceb_x_preferred":[
        "Kal\u0101teh-ye Gaz"
    ],
    "name:fas_x_preferred":[
        "Kal\u0101teh-ye Gaz"
    ],
    "name:fas_x_variant":[
        "\u06a9\u0644\u0627\u062a\u0647 \u06af\u0632"
    ],
    "name:swe_x_preferred":[
        "Kal\u0101teh-ye Gaz"
    ],
    "wof:name":"Kalateh-ye Gaz",
    "wof:placetype":"locality"
},
  "geometry": {"coordinates":[56.8752,36.80442],"type":"Point"}
}