{
  "type": "Feature",
  "properties": {
    "gn:admin1_code":"3",
    "gn:asciiname":"Eslamabad",
    "gn:country_code":"IR",
    "gn:dem":1774,
    "gn:feature_class":"P",
    "gn:feature_code":"PPL",
    "gn:name":"Esl\u0101m\u0101b\u0101d",
    "gn:population":0,
    "gn:timezone":"Asia/Tehran",
    "iso:country":"IR",
    "name:fas_x_preferred":[
        "Esl\u0101m\u0101b\u0101d-e D\u016bder\u0101\u2019"
    ],
    "name:fas_x_variant":[
        "Esl\u0101m\u0101b\u0101d",
        "\u0627\u0633\u0644\u0627\u0645 \u0622\u0628\u0627\u062f"
    ],
    "name:und_x_variant":[
        "\u0627\u0633\u0644\u0627\u0645 \u0622\u0628\u0627\u062f"
    ],
    "wof:name":"Eslamabad",
    "wof:placetype":"locality"
},
  "geometry": {"coordinates":[50.87365,31.33054000000001],"type":"Point"}
}