{
  "type": "Feature",
  "properties": {
    "gn:admin1_code":"35",
    "gn:asciiname":"Vash Sara",
    "gn:country_code":"IR",
    "gn:dem":408,
    "gn:feature_class":"P",
    "gn:feature_code":"PPL",
    "gn:name":"V\u0101sh Sar\u0101",
    "gn:population":0,
    "gn:timezone":"Asia/Tehran",
    "iso:country":"IR",
    "name:fas_x_preferred":[
        "\u0648\u0627\u0634 \u0633\u064e\u0631\u0627"
    ],
    "name:fas_x_variant":[
        "V\u0101sh Sar\u0101"
    ],
    "wof:name":"Vash Sara",
    "wof:placetype":"locality"
},
  "geometry": {"coordinates":[52.63333000000001,36.23333],"type":"Point"}
}