{
  "type": "Feature",
  "properties": {
    "gn:admin1_code":"23",
    "gn:asciiname":"Golbahar-e Ahmadabad",
    "gn:country_code":"IR",
    "gn:dem":2489,
    "gn:feature_class":"P",
    "gn:feature_code":"PPL",
    "gn:name":"Golbah\u0101r-e A\u1e29mad\u0101b\u0101d",
    "gn:population":0,
    "gn:timezone":"Asia/Tehran",
    "iso:country":"IR",
    "name:fas_x_preferred":[
        "\u06af\u064f\u0644\u0628\u064e\u0647\u0627\u0631\u0650 \u0627\u064e\u062d\u0645\u064e\u062f \u0622\u0628\u0627\u062f"
    ],
    "name:fas_x_variant":[
        "Golbah\u0101r-e A\u1e29mad\u0101b\u0101d"
    ],
    "wof:name":"Golbahar-e Ahmadabad",
    "wof:placetype":"locality"
},
  "geometry": {"coordinates":[49.615,33.18083],"type":"Point"}
}