{
  "type": "Feature",
  "properties": {
    "gn:admin1_code":"4.0",
    "gn:asciiname":"Sohrak",
    "gn:country_code":"IR",
    "gn:dem":1573,
    "gn:feature_class":"P",
    "gn:feature_code":"PPL",
    "gn:name":"Sohrak",
    "gn:population":0,
    "gn:timezone":"Asia/Tehran",
    "iso:country":"IR",
    "name:fas_x_preferred":[
        "\u0633\u0647\u0631\u06a9"
    ],
    "wof:name":"Sohrak",
    "wof:placetype":"locality"
},
  "geometry": {"coordinates":[61.60352,27.2634],"type":"Point"}
}