{
  "type": "Feature",
  "properties": {
    "gn:admin1_code":"16.0",
    "gn:asciiname":"Gonbad-e Hajji",
    "gn:country_code":"IR",
    "gn:dem":1642,
    "gn:feature_class":"P",
    "gn:feature_code":"PPL",
    "gn:name":"Gonbad-e \u1e28\u0101jj\u012b",
    "gn:population":0,
    "gn:timezone":"Asia/Tehran",
    "iso:country":"IR",
    "name:fas_x_preferred":[
        "\u06af\u0646\u0628\u062f"
    ],
    "name:fas_x_variant":[
        "\u06af\u0646\u0628\u062f \u062d\u0627\u062c\u06cc"
    ],
    "name:und_x_variant":[
        "Gonbad",
        "Gonbad-e \u1e28\u0101jj\u012b",
        "Gunbad"
    ],
    "wof:name":"Gonbad-e Hajji",
    "wof:placetype":"locality"
},
  "geometry": {"coordinates":[47.4291,35.9802],"type":"Point"}
}