{
  "type": "Feature",
  "properties": {
    "gn:admin1_code":"41",
    "gn:asciiname":"Kamrud",
    "gn:country_code":"IR",
    "gn:dem":1304,
    "gn:feature_class":"P",
    "gn:feature_code":"PPL",
    "gn:name":"K\u0101mr\u016bd",
    "gn:population":0,
    "gn:timezone":"Asia/Tehran",
    "iso:country":"IR",
    "name:fas_x_preferred":[
        "K\u0101mr\u016bd-e \u2018Oly\u0101"
    ],
    "name:fas_x_variant":[
        "K\u0101mr\u016bd",
        "\u06a9\u0627\u0645\u0631\u0648\u062f"
    ],
    "name:und_x_variant":[
        "Kamruth"
    ],
    "wof:name":"Kamrud",
    "wof:placetype":"locality"
},
  "geometry": {"coordinates":[58.37742,33.6909],"type":"Point"}
}