{
  "type": "Feature",
  "properties": {
    "gn:admin1_code":"10.0",
    "gn:asciiname":"Chahar Meleh",
    "gn:country_code":"IR",
    "gn:dem":1336,
    "gn:feature_class":"P",
    "gn:feature_code":"PPL",
    "gn:name":"Chah\u0101r Meleh",
    "gn:population":0,
    "gn:timezone":"Asia/Tehran",
    "iso:country":"IR",
    "name:ara_x_preferred":[
        "\u062a\u0634\u0647\u0627\u0631\u0645\u0644\u0629"
    ],
    "name:fas_x_preferred":[
        "\u0686\u0647\u0627\u0631 \u0645\u0644\u0647"
    ],
    "name:fas_x_variant":[
        "Chah\u0101r Meleh",
        "\u0686\u0647\u0627\u0631\u0645\u0644\u0647"
    ],
    "name:msa_x_preferred":[
        "Chahar Meleh"
    ],
    "wof:name":"Chahar Meleh",
    "wof:placetype":"locality"
},
  "geometry": {"coordinates":[46.2905,33.9407],"type":"Point"}
}