{
  "type": "Feature",
  "properties": {
    "gn:admin1_code":"15.0",
    "gn:asciiname":"Shahrak-e Bahram",
    "gn:country_code":"IR",
    "gn:dem":96,
    "gn:feature_class":"P",
    "gn:feature_code":"PPL",
    "gn:name":"Shahrak-e Bahr\u0101m",
    "gn:population":0,
    "gn:timezone":"Asia/Tehran",
    "iso:country":"IR",
    "name:fas_x_preferred":[
        "Shahrak-e Bahr\u0101m"
    ],
    "name:fas_x_variant":[
        "\u0634\u0647\u0631\u06a9 \u0628\u0647\u0631\u0627\u0645"
    ],
    "wof:name":"Shahrak-e Bahram",
    "wof:placetype":"locality"
},
  "geometry": {"coordinates":[48.22378,32.32735],"type":"Point"}
}