{
  "type": "Feature",
  "properties": {
    "gn:admin1_code":"16",
    "gn:asciiname":"Tilku",
    "gn:country_code":"IR",
    "gn:dem":1465,
    "gn:feature_class":"P",
    "gn:feature_code":"PPL",
    "gn:name":"T\u012blk\u016b",
    "gn:population":0,
    "gn:timezone":"Asia/Tehran",
    "iso:country":"IR",
    "name:ara_x_preferred":[
        "\u062a\u064a\u0644\u06d5 \u0643\u0648"
    ],
    "name:ceb_x_preferred":[
        "T\u012blk\u016b"
    ],
    "name:ckb_x_preferred":[
        "\u062a\u06cc\u0644\u06d5\u06a9\u06c6"
    ],
    "name:fas_x_preferred":[
        "\u062a\u064a\u0644\u0643\u0648\u0647"
    ],
    "name:fas_x_variant":[
        "\u062a\u064a\u0644\u0650\u0647 \u0643\u0648\u0647",
        "\u062a\u06cc\u0644\u06a9\u0648",
        "T\u012blk\u016bh",
        "T\u012blk\u016b",
        "\u062a\u06cc\u0644\u06a9\u0648\u0647"
    ],
    "name:kur_x_preferred":[
        "T\u00eeleko"
    ],
    "name:swe_x_preferred":[
        "T\u012blk\u016b"
    ],
    "name:und_x_variant":[
        "T\u012bleh K\u016bh"
    ],
    "wof:name":"Tilku",
    "wof:placetype":"locality"
},
  "geometry": {"coordinates":[46.6642,34.9541],"type":"Point"}
}