{
  "type": "Feature",
  "properties": {
    "gn:admin1_code":"33",
    "gn:asciiname":"Qadchi",
    "gn:country_code":"IR",
    "gn:dem":1934,
    "gn:feature_class":"P",
    "gn:feature_code":"PPL",
    "gn:name":"Qadch\u012b",
    "gn:population":0,
    "gn:timezone":"Asia/Tehran",
    "iso:country":"IR",
    "name:fas_x_preferred":[
        "\u0642\u0648\u062c\u0651\u0648"
    ],
    "name:fas_x_variant":[
        "Q\u016bdch\u012b",
        "\u0642\u0648\u062f\u0686\u06cc",
        "Q\u016bjj\u016b",
        "\u0642\u062f\u0686\u06cc"
    ],
    "name:und_x_variant":[
        "Qadch\u012b"
    ],
    "wof:name":"Qadchi",
    "wof:placetype":"locality"
},
  "geometry": {"coordinates":[46.9966,36.9013],"type":"Point"}
}