{
  "type": "Feature",
  "properties": {
    "gn:admin1_code":"35.0",
    "gn:asciiname":"Sang-e Tajan",
    "gn:country_code":"IR",
    "gn:dem":12,
    "gn:feature_class":"P",
    "gn:feature_code":"PPL",
    "gn:name":"Sang-e Tajan",
    "gn:population":0,
    "gn:timezone":"Asia/Tehran",
    "iso:country":"IR",
    "name:fas_x_preferred":[
        "\u0633\u0646\u06af \u062a\u062c\u0646"
    ],
    "name:fas_x_variant":[
        "\u0633\u0646\u06af\u200c\u062a\u062c\u0646"
    ],
    "name:und_x_variant":[
        "Sang-e Tajan"
    ],
    "wof:name":"Sang-e Tajan",
    "wof:placetype":"locality"
},
  "geometry": {"coordinates":[51.49435,36.62468],"type":"Point"}
}