{
  "type": "Feature",
  "properties": {
    "gn:admin1_code":"5",
    "gn:asciiname":"Mambi",
    "gn:cc2":"IR",
    "gn:country_code":"IR",
    "gn:dem":1479,
    "gn:feature_class":"P",
    "gn:feature_code":"PPL",
    "gn:name":"Mamb\u012b",
    "gn:population":0,
    "gn:timezone":"Asia/Tehran",
    "iso:country":"IR",
    "name:fas_x_preferred":[
        "\u0645\u064e\u0645\u0628\u06cc"
    ],
    "name:fas_x_variant":[
        "\u0642\u064e\u0644\u0639\u0650\u06c0 \u0645\u0648\u0645\u0628\u06cc",
        "Mamb\u012b"
    ],
    "name:und_x_variant":[
        "Mombi",
        "Qal\u2018eh-i-M\u016bmbi",
        "Qal\u2018eh-ye M\u016bmb\u012b"
    ],
    "wof:name":"Mambi",
    "wof:placetype":"locality"
},
  "geometry": {"coordinates":[50.46833,31.10194000000001],"type":"Point"}
}