{
  "type": "Feature",
  "properties": {
    "gn:admin1_code":"15.0",
    "gn:asciiname":"Bahiyeh-ye Najm Divao",
    "gn:country_code":"IR",
    "gn:dem":2,
    "gn:feature_class":"P",
    "gn:feature_code":"PPL",
    "gn:name":"Bahiyeh-ye Najm D\u012bv\u0101o",
    "gn:population":0,
    "gn:timezone":"Asia/Tehran",
    "iso:country":"IR",
    "name:fas_x_preferred":[
        "Bahiyeh-ye Najm D\u012bv\u0101o"
    ],
    "wof:name":"Bahiyeh-ye Najm Divao",
    "wof:placetype":"locality"
},
  "geometry": {"coordinates":[48.20194,30.34167],"type":"Point"}
}