{
  "type": "Feature",
  "properties": {
    "gn:admin1_code":"13",
    "gn:asciiname":"Nowsud",
    "gn:country_code":"IR",
    "gn:dem":1223,
    "gn:feature_class":"P",
    "gn:feature_code":"PPL",
    "gn:name":"Nows\u016bd",
    "gn:population":0,
    "gn:timezone":"Asia/Tehran",
    "iso:country":"IR",
    "name:ara_x_preferred":[
        "\u0646\u0648\u0633\u0648\u062f"
    ],
    "name:aze_x_preferred":[
        "Novsud"
    ],
    "name:ceb_x_preferred":[
        "Nows\u016bd"
    ],
    "name:ckb_x_preferred":[
        "\u0646\u06d5\u0648\u0633\u0648\u0648\u062f"
    ],
    "name:fas_x_preferred":[
        "\u0646\u0648\u0633\u0648\u062f"
    ],
    "name:fas_x_variant":[
        "Nows\u016bd"
    ],
    "name:kur_x_preferred":[
        "Nos\u00fbde"
    ],
    "name:mlg_x_preferred":[
        "Nowsud"
    ],
    "name:swe_x_preferred":[
        "Nows\u016bd"
    ],
    "name:tur_x_preferred":[
        "Novsud"
    ],
    "name:und_x_variant":[
        "Naws\u016bd"
    ],
    "wof:name":"Nowsud",
    "wof:placetype":"locality"
},
  "geometry": {"coordinates":[46.20413,35.16212],"type":"Point"}
}