{
  "type": "Feature",
  "properties": {
    "gn:admin1_code":"7",
    "gn:asciiname":"Maqsudabad",
    "gn:country_code":"IR",
    "gn:dem":1608,
    "gn:feature_class":"P",
    "gn:feature_code":"PPL",
    "gn:name":"Maq\u015f\u016bd\u0101b\u0101d",
    "gn:population":0,
    "gn:timezone":"Asia/Tehran",
    "iso:country":"IR",
    "name:fas_x_preferred":[
        "\u0645\u0642\u0635\u0648\u062f\u0622\u0628\u0627\u062f"
    ],
    "name:fas_x_variant":[
        "Maq\u015f\u016bd\u0101b\u0101d"
    ],
    "wof:name":"Maqsudabad",
    "wof:placetype":"locality"
},
  "geometry": {"coordinates":[52.4208,29.9537],"type":"Point"}
}