{
  "type": "Feature",
  "properties": {
    "gn:admin1_code":"4.0",
    "gn:asciiname":"Yusefabad-e Sadk",
    "gn:country_code":"IR",
    "gn:dem":1484,
    "gn:feature_class":"P",
    "gn:feature_code":"PPL",
    "gn:name":"Y\u016bsef\u0101b\u0101d-e Sadk",
    "gn:population":0,
    "gn:timezone":"Asia/Tehran",
    "iso:country":"IR",
    "name:fas_x_preferred":[
        "\u06cc\u0648\u0633\u0641 \u0622\u0628\u0627\u062f \u0633\u062f\u06a9"
    ],
    "name:fas_x_variant":[
        "Y\u016bsef\u0101b\u0101d-e Sadk"
    ],
    "name:und_x_variant":[
        "Sadk"
    ],
    "wof:name":"Yusefabad-e Sadk",
    "wof:placetype":"locality"
},
  "geometry": {"coordinates":[60.7109,28.3814],"type":"Point"}
}