{
  "type": "Feature",
  "properties": {
    "gn:admin1_code":"33",
    "gn:asciiname":"Varduq",
    "gn:country_code":"IR",
    "gn:dem":1392,
    "gn:feature_class":"P",
    "gn:feature_code":"PPL",
    "gn:name":"Vard\u016bq",
    "gn:population":0,
    "gn:timezone":"Asia/Tehran",
    "iso:country":"IR",
    "name:fas_x_preferred":[
        "\u0648\u0631\u062f\u0648\u0642"
    ],
    "name:fas_x_variant":[
        "Vard\u016bq"
    ],
    "name:und_x_variant":[
        "Wardavaq",
        "Vardavaq",
        "Vardevaq"
    ],
    "wof:name":"Varduq",
    "wof:placetype":"locality"
},
  "geometry": {"coordinates":[47.8907,37.4018],"type":"Point"}
}