{
  "type": "Feature",
  "properties": {
    "gn:admin1_code":"32",
    "gn:asciiname":"Galin Bolaghi",
    "gn:country_code":"IR",
    "gn:dem":1223,
    "gn:feature_class":"P",
    "gn:feature_code":"PPL",
    "gn:name":"Gal\u012bn Bol\u0101gh\u012b",
    "gn:population":0,
    "gn:timezone":"Asia/Tehran",
    "iso:country":"IR",
    "name:fas_x_preferred":[
        "Kal\u012bm Bol\u0101gh"
    ],
    "name:fas_x_variant":[
        "\u06af\u0644\u064a\u0646 \u0628\u0644\u0627\u063a\u06cc"
    ],
    "name:und_x_variant":[
        "Kel\u012bm Bol\u0101gh",
        "Gal\u012bn Bol\u0101gh\u012b"
    ],
    "wof:name":"Galin Bolaghi",
    "wof:placetype":"locality"
},
  "geometry": {"coordinates":[47.65006,38.90442],"type":"Point"}
}