{
  "type": "Feature",
  "properties": {
    "gn:admin1_code":"1",
    "gn:asciiname":"Del Del Bolaghi",
    "gn:country_code":"IR",
    "gn:dem":2041,
    "gn:feature_class":"P",
    "gn:feature_code":"PPL",
    "gn:name":"Del Del Bol\u0101gh\u012b",
    "gn:population":0,
    "gn:timezone":"Asia/Tehran",
    "iso:country":"IR",
    "name:fas_x_preferred":[
        "\u062f\u0644 \u062f\u0644 \u0628\u0644\u0627\u063a\u06cc"
    ],
    "name:fas_x_variant":[
        "Doldol Bol\u0101gh\u012b",
        "Dol Dol Bol\u0101gh\u012b"
    ],
    "name:und_x_variant":[
        "Del Del Bol\u0101gh\u012b"
    ],
    "wof:name":"Del Del Bolaghi",
    "wof:placetype":"locality"
},
  "geometry": {"coordinates":[46.9791,36.528],"type":"Point"}
}