{
  "type": "Feature",
  "properties": {
    "gn:admin1_code":"38.0",
    "gn:asciiname":"Ameshk",
    "gn:country_code":"IR",
    "gn:dem":1232,
    "gn:feature_class":"P",
    "gn:feature_code":"PPL",
    "gn:name":"\u0100meshk",
    "gn:population":0,
    "gn:timezone":"Asia/Tehran",
    "iso:country":"IR",
    "name:fas_x_preferred":[
        "\u0622\u0645\u0634\u06a9"
    ],
    "name:fas_x_variant":[
        "\u0100meshk"
    ],
    "wof:name":"Ameshk",
    "wof:placetype":"locality"
},
  "geometry": {"coordinates":[50.4353,36.3699],"type":"Point"}
}