{
  "type": "Feature",
  "properties": {
    "gn:admin1_code":"37",
    "gn:asciiname":"Majdabad-e Sofla",
    "gn:country_code":"IR",
    "gn:dem":-1,
    "gn:feature_class":"P",
    "gn:feature_code":"PPL",
    "gn:name":"Majd\u0101b\u0101d-e Sofl\u00e1",
    "gn:population":0,
    "gn:timezone":"Asia/Tehran",
    "iso:country":"IR",
    "name:fas_x_preferred":[
        "\u0645\u062d\u0645\u0651\u062f \u0622\u0628\u0627\u062f"
    ],
    "name:fas_x_variant":[
        "Mo\u1e29ammad\u0101b\u0101d",
        "\u0645\u062c\u062f \u0622\u0628\u0627\u062f \u0633\u0641\u0644\u06cc",
        "\u0645\u062d\u0645\u062f \u0622\u0628\u0627\u062f \u0633\u0641\u0644\u06cc"
    ],
    "name:und_x_variant":[
        "Majd\u0101b\u0101d-e Sofl\u00e1",
        "Mo\u1e29ammad\u0101b\u0101d-e Sofl\u00e1"
    ],
    "wof:name":"Majdabad-e Sofla",
    "wof:placetype":"locality"
},
  "geometry": {"coordinates":[54.56509000000001,36.97211],"type":"Point"}
}