{
  "type": "Feature",
  "properties": {
    "gn:admin1_code":"7",
    "gn:asciiname":"Gishiabad",
    "gn:country_code":"IR",
    "gn:dem":1632,
    "gn:feature_class":"P",
    "gn:feature_code":"PPL",
    "gn:name":"G\u012bsh\u012b\u0101b\u0101d",
    "gn:population":0,
    "gn:timezone":"Asia/Tehran",
    "iso:country":"IR",
    "name:fas_x_preferred":[
        "\u06af\u064a\u0634\u06cc \u0622\u0628\u0627\u062f"
    ],
    "name:fas_x_variant":[
        "G\u012bsh\u012b\u0101b\u0101d"
    ],
    "wof:name":"Gishiabad",
    "wof:placetype":"locality"
},
  "geometry": {"coordinates":[52.53333000000001,30.13333],"type":"Point"}
}