{
  "type": "Feature",
  "properties": {
    "gn:admin1_code":"41",
    "gn:asciiname":"Bihud",
    "gn:country_code":"IR",
    "gn:dem":1788,
    "gn:feature_class":"P",
    "gn:feature_code":"PPL",
    "gn:name":"B\u012bh\u016bd",
    "gn:population":0,
    "gn:timezone":"Asia/Tehran",
    "iso:country":"IR",
    "name:fas_x_preferred":[
        "B\u012bh\u016bd"
    ],
    "name:fas_x_variant":[
        "\u0628\u06cc\u0647\u0648\u062f"
    ],
    "name:und_x_variant":[
        "\u0628\u06cc\u0647\u0648\u062f"
    ],
    "wof:name":"Bihud",
    "wof:placetype":"locality"
},
  "geometry": {"coordinates":[58.86006999999999,33.77483],"type":"Point"}
}