{
  "type": "Feature",
  "properties": {
    "gn:admin1_code":"26.0",
    "gn:asciiname":"Darband sq",
    "gn:country_code":"IR",
    "gn:dem":1797,
    "gn:elevation":"1807.0",
    "gn:feature_class":"P",
    "gn:feature_code":"PPL",
    "gn:name":"Darband sq",
    "gn:population":0,
    "gn:timezone":"Asia/Tehran",
    "iso:country":"IR",
    "name:fas_x_preferred":[
        "\u0645\u06cc\u062f\u0627\u0646 \u0645\u062c\u0633\u0645\u0647 \u062f\u0631\u0628\u0646\u062f"
    ],
    "wof:name":"Darband sq",
    "wof:placetype":"locality"
},
  "geometry": {"coordinates":[51.42664,35.82822],"type":"Point"}
}