{
  "type": "Feature",
  "properties": {
    "gn:admin1_code":"35",
    "gn:asciiname":"Qa'emiyeh",
    "gn:country_code":"IR",
    "gn:dem":-24,
    "gn:feature_class":"P",
    "gn:feature_code":"PPL",
    "gn:name":"Q\u0101\u2019em\u012byeh",
    "gn:population":0,
    "gn:timezone":"Asia/Tehran",
    "iso:country":"IR",
    "name:fas_x_preferred":[
        "\u0642\u064e\u0639\u0650\u0645\u064a\u0650\u0651\u0647"
    ],
    "name:fas_x_variant":[
        "Qa\u2018em\u012byeh",
        "Q\u0101\u2019em\u012byeh",
        "\u0642\u0627\u0626\u0645\u064a\u0647"
    ],
    "wof:name":"Qa'emiyeh",
    "wof:placetype":"locality"
},
  "geometry": {"coordinates":[52.68612,36.70487],"type":"Point"}
}