{
  "type": "Feature",
  "properties": {
    "gn:admin1_code":"5",
    "gn:asciiname":"Chah Taqi",
    "gn:country_code":"IR",
    "gn:dem":906,
    "gn:feature_class":"P",
    "gn:feature_code":"PPL",
    "gn:name":"Ch\u0101h Taq\u012b",
    "gn:population":0,
    "gn:timezone":"Asia/Tehran",
    "iso:country":"IR",
    "name:fas_x_preferred":[
        "Ch\u0101h Taq\u012b"
    ],
    "name:fas_x_variant":[
        "\u0686\u0627\u0647 \u062a\u0642\u06cc"
    ],
    "name:und_x_variant":[
        "\u0686\u0627\u0647 \u062a\u0642\u06cc"
    ],
    "wof:name":"Chah Taqi",
    "wof:placetype":"locality"
},
  "geometry": {"coordinates":[51.14513,30.28894],"type":"Point"}
}