{
  "type": "Feature",
  "properties": {
    "gn:admin1_code":"1",
    "gn:asciiname":"Shahrak-e Uch Tappeh-ye Kord",
    "gn:country_code":"IR",
    "gn:dem":1287,
    "gn:feature_class":"P",
    "gn:feature_code":"PPL",
    "gn:name":"Shahrak-e \u016ach Tappeh-ye Kord",
    "gn:population":0,
    "gn:timezone":"Asia/Tehran",
    "iso:country":"IR",
    "name:fas_x_preferred":[
        "\u0634\u0647\u0631\u06a9 \u0627\u0648\u0686 \u062a\u067e\u0651\u0647 \u06a9\u0631\u062f"
    ],
    "name:fas_x_variant":[
        "\u0634\u064e\u0647\u0631\u064e\u0643\u0650 \u0648\u0686 \u062a\u064e\u067e\u0650\u0651\u06c0 \u0643\u064f\u0631\u062f",
        "Shahrak-e \u016ach Tappeh-ye Kord"
    ],
    "wof:name":"Shahrak-e Uch Tappeh-ye Kord",
    "wof:placetype":"locality"
},
  "geometry": {"coordinates":[46.021,37.0156],"type":"Point"}
}