{
  "type": "Feature",
  "properties": {
    "gn:admin1_code":"1",
    "gn:asciiname":"Keshtar",
    "gn:country_code":"IR",
    "gn:dem":1644,
    "gn:feature_class":"P",
    "gn:feature_code":"PPL",
    "gn:name":"Kesht\u0101r",
    "gn:population":0,
    "gn:timezone":"Asia/Tehran",
    "iso:country":"IR",
    "name:ara_x_preferred":[
        "\u0643\u0634\u062a\u0627\u0632"
    ],
    "name:aze_x_preferred":[
        "Ke\u015ftaz"
    ],
    "name:fas_x_preferred":[
        "\u0643\u0650\u0634\u062a\u0627\u0632"
    ],
    "name:fas_x_variant":[
        "Kesht\u0101r",
        "Kesht\u0101z",
        "\u06a9\u0634\u062a\u0627\u0631",
        "\u06a9\u0634\u062a\u0627\u0632"
    ],
    "name:msa_x_preferred":[
        "Keshtaz"
    ],
    "wof:name":"Keshtar",
    "wof:placetype":"locality"
},
  "geometry": {"coordinates":[44.275,39.3399],"type":"Point"}
}