{
  "type": "Feature",
  "properties": {
    "gn:admin1_code":"5",
    "gn:asciiname":"Sar Mur",
    "gn:country_code":"IR",
    "gn:dem":746,
    "gn:feature_class":"P",
    "gn:feature_code":"PPL",
    "gn:name":"Sar M\u016br",
    "gn:population":0,
    "gn:timezone":"Asia/Tehran",
    "iso:country":"IR",
    "name:fas_x_preferred":[
        "Sar M\u016br"
    ],
    "name:fas_x_variant":[
        "\u0633\u064e\u0631\u0650 \u0645\u0627\u0647\u0648\u0631",
        "Sar-e M\u0101h\u016br",
        "\u0633\u0631 \u0645\u0648\u0631"
    ],
    "name:und_x_variant":[
        "\u0633\u0631 \u0645\u0648\u0631"
    ],
    "wof:name":"Sar Mur",
    "wof:placetype":"locality"
},
  "geometry": {"coordinates":[50.52382,30.68848],"type":"Point"}
}