{
  "type": "Feature",
  "properties": {
    "gn:admin1_code":"9",
    "gn:asciiname":"Veyar",
    "gn:country_code":"IR",
    "gn:dem":1976,
    "gn:feature_class":"P",
    "gn:feature_code":"PPL",
    "gn:name":"Veyar",
    "gn:population":0,
    "gn:timezone":"Asia/Tehran",
    "iso:country":"IR",
    "name:fas_x_preferred":[
        "\u0648\u06cc\u0631"
    ],
    "name:msa_x_preferred":[
        "Veyar"
    ],
    "wof:name":"Veyar",
    "wof:placetype":"locality"
},
  "geometry": {"coordinates":[48.89682,35.41538],"type":"Point"}
}