{
  "type": "Feature",
  "properties": {
    "gn:admin1_code":"37",
    "gn:asciiname":"Ramian",
    "gn:country_code":"IR",
    "gn:dem":222,
    "gn:feature_class":"P",
    "gn:feature_code":"PPLA2",
    "gn:name":"R\u0101m\u012b\u0101n",
    "gn:population":0,
    "gn:timezone":"Asia/Tehran",
    "iso:country":"IR",
    "name:ara_x_preferred":[
        "\u0631\u0627\u0645\u064a\u0627\u0646"
    ],
    "name:aze_x_preferred":[
        "Ramiyan"
    ],
    "name:ceb_x_preferred":[
        "R\u0101m\u012b\u0101n"
    ],
    "name:fas_x_preferred":[
        "\u0631\u0627\u0645\u064a\u0627\u0646"
    ],
    "name:fas_x_variant":[
        "R\u0101m\u012b\u0101n",
        "\u0631\u0627\u0645\u06cc\u0627\u0646"
    ],
    "name:ita_x_preferred":[
        "Ramyan"
    ],
    "name:mlg_x_preferred":[
        "Ramian"
    ],
    "name:msa_x_preferred":[
        "Ramian"
    ],
    "name:mzn_x_preferred":[
        "\u0631\u0627\u0645\u06cc\u0627\u0646"
    ],
    "name:pnb_x_preferred":[
        "\u0631\u0627\u0645\u06cc\u0627\u0646"
    ],
    "name:tur_x_preferred":[
        "Ramiyan"
    ],
    "name:und_x_variant":[
        "R\u0101m\u012by\u0101n",
        "R\u0101mey\u0101n"
    ],
    "wof:name":"Ramian",
    "wof:placetype":"locality"
},
  "geometry": {"coordinates":[55.14123000000001,37.01598],"type":"Point"}
}