{
  "type": "Feature",
  "properties": {
    "gn:admin1_code":"11",
    "gn:asciiname":"Berbar",
    "gn:country_code":"IR",
    "gn:dem":358,
    "gn:feature_class":"P",
    "gn:feature_code":"PPL",
    "gn:name":"Berb\u0101r",
    "gn:population":0,
    "gn:timezone":"Asia/Tehran",
    "iso:country":"IR",
    "name:fas_x_preferred":[
        "Berb\u0101r"
    ],
    "name:fas_x_variant":[
        "\u0628\u0631\u0628\u0627\u0631"
    ],
    "name:und_x_variant":[
        "\u0628\u0631\u0628\u0627\u0631"
    ],
    "wof:name":"Berbar",
    "wof:placetype":"locality"
},
  "geometry": {"coordinates":[54.58179000000001,27.10454],"type":"Point"}
}