{
  "type": "Feature",
  "properties": {
    "gn:admin1_code":"28",
    "gn:asciiname":"Suran",
    "gn:country_code":"IR",
    "gn:dem":2053,
    "gn:feature_class":"P",
    "gn:feature_code":"PPL",
    "gn:name":"S\u016br\u0101n",
    "gn:population":0,
    "gn:timezone":"Asia/Tehran",
    "iso:country":"IR",
    "name:fas_x_preferred":[
        "S\u016br\u0101n"
    ],
    "name:fas_x_variant":[
        "\u0633\u0648\u0631\u0627\u0646"
    ],
    "name:und_x_variant":[
        "\u0633\u0648\u0631\u0627\u0646"
    ],
    "wof:name":"Suran",
    "wof:placetype":"locality"
},
  "geometry": {"coordinates":[50.93531,32.8023],"type":"Point"}
}