{
  "type": "Feature",
  "properties": {
    "gn:admin1_code":"28.0",
    "gn:asciiname":"Duk",
    "gn:country_code":"IR",
    "gn:dem":1688,
    "gn:feature_class":"P",
    "gn:feature_code":"PPL",
    "gn:name":"D\u016bk",
    "gn:population":0,
    "gn:timezone":"Asia/Tehran",
    "iso:country":"IR",
    "name:fas_x_preferred":[
        "\u062f\u0648\u0643"
    ],
    "name:fas_x_variant":[
        "D\u016bk"
    ],
    "wof:name":"Duk",
    "wof:placetype":"locality"
},
  "geometry": {"coordinates":[52.2712,33.2717],"type":"Point"}
}