{
  "type": "Feature",
  "properties": {
    "gn:admin1_code":"7",
    "gn:asciiname":"Qal`eh-ye Ra'isi",
    "gn:country_code":"IR",
    "gn:dem":1319,
    "gn:feature_class":"P",
    "gn:feature_code":"PPL",
    "gn:name":"Qal\u2018eh-ye Ra\u2019\u012bs\u012b",
    "gn:population":0,
    "gn:timezone":"Asia/Tehran",
    "iso:country":"IR",
    "name:fas_x_preferred":[
        "Qal\u2018eh-ye Ra\u2019\u012bs\u012b"
    ],
    "name:fas_x_variant":[
        "\u0642\u0644\u0639\u0647 \u0631\u0626\u06cc\u0633\u06cc"
    ],
    "name:und_x_variant":[
        "Qal\u2018eh-ye Ra\u2019\u012bs\u0101n"
    ],
    "wof:name":"Qal`eh-ye Ra'isi",
    "wof:placetype":"locality"
},
  "geometry": {"coordinates":[53.64139,28.86833],"type":"Point"}
}