{
  "type": "Feature",
  "properties": {
    "gn:admin1_code":"1",
    "gn:asciiname":"Qerekhleq",
    "gn:country_code":"IR",
    "gn:dem":1917,
    "gn:feature_class":"P",
    "gn:feature_code":"PPL",
    "gn:name":"Qerekhleq",
    "gn:population":0,
    "gn:timezone":"Asia/Tehran",
    "iso:country":"IR",
    "name:fas_x_preferred":[
        "\u0642\u0631\u062e\u0644\u0648"
    ],
    "name:fas_x_variant":[
        "Qerkhl\u016b",
        "\u0642\u0631\u062e\u0644\u0642"
    ],
    "wof:name":"Qerekhleq",
    "wof:placetype":"locality"
},
  "geometry": {"coordinates":[47.17794,36.33624],"type":"Point"}
}