{
  "type": "Feature",
  "properties": {
    "gn:admin1_code":"32",
    "gn:asciiname":"Dowlatabad",
    "gn:country_code":"IR",
    "gn:dem":1302,
    "gn:feature_class":"P",
    "gn:feature_code":"PPL",
    "gn:name":"Dowlat\u0101b\u0101d",
    "gn:population":0,
    "gn:timezone":"Asia/Tehran",
    "iso:country":"IR",
    "name:aze_x_preferred":[
        "D\u00f6vl\u0259tabad"
    ],
    "name:ceb_x_preferred":[
        "Dowlatabad"
    ],
    "name:fas_x_preferred":[
        "\u062f\u0648\u0644\u062a \u0622\u0628\u0627\u062f"
    ],
    "name:fas_x_variant":[
        "Dowlat\u0101b\u0101d",
        "\u062f\u0648\u0644\u062a\u200c\u0622\u0628\u0627\u062f"
    ],
    "name:swe_x_preferred":[
        "Dowlatabad"
    ],
    "wof:name":"Dowlatabad",
    "wof:placetype":"locality"
},
  "geometry": {"coordinates":[48.3156,38.3699],"type":"Point"}
}