{
  "type": "Feature",
  "properties": {
    "gn:admin1_code":"7",
    "gn:asciiname":"Chah Rigi",
    "gn:country_code":"IR",
    "gn:dem":633,
    "gn:feature_class":"P",
    "gn:feature_code":"PPL",
    "gn:name":"Ch\u0101h R\u012bg\u012b",
    "gn:population":0,
    "gn:timezone":"Asia/Tehran",
    "iso:country":"IR",
    "name:ara_x_preferred":[
        "\u062c\u0627\u0647 \u0631\u064a\u0643\u064a"
    ],
    "name:fas_x_preferred":[
        "\u0686\u0627\u0647 \u0631\u06cc\u06af\u06cc"
    ],
    "name:fas_x_variant":[
        "Ch\u0101h R\u012bg\u012b"
    ],
    "name:msa_x_preferred":[
        "Chah Rigi"
    ],
    "name:und_x_variant":[
        "Ch\u0101h Rang\u012b"
    ],
    "wof:name":"Chah Rigi",
    "wof:placetype":"locality"
},
  "geometry": {"coordinates":[53.8993,27.4961],"type":"Point"}
}