{
  "type": "Feature",
  "properties": {
    "gn:admin1_code":"42",
    "gn:asciiname":"Sheykh-e Lun",
    "gn:country_code":"IR",
    "gn:dem":1201,
    "gn:feature_class":"P",
    "gn:feature_code":"PPL",
    "gn:name":"Sheykh-e L\u016bn",
    "gn:population":0,
    "gn:timezone":"Asia/Tehran",
    "iso:country":"IR",
    "name:fas_x_preferred":[
        "\u0634\u06cc\u062e\u0644\u0648"
    ],
    "name:fas_x_variant":[
        "Sheykhl\u0101n",
        "Sheykhl\u016b",
        "\u0634\u06cc\u062e \u0644\u0648\u0646",
        "\u0634\u06cc\u062e\u0644\u0627\u0646"
    ],
    "name:und_x_variant":[
        "Sheykh-e L\u016bn"
    ],
    "wof:name":"Sheykh-e Lun",
    "wof:placetype":"locality"
},
  "geometry": {"coordinates":[58.86239000000001,36.16987],"type":"Point"}
}