{
  "type": "Feature",
  "properties": {
    "gn:admin1_code":"4.0",
    "gn:asciiname":"Gowdan",
    "gn:cc2":"IR",
    "gn:country_code":"IR",
    "gn:dem":1228,
    "gn:feature_class":"P",
    "gn:feature_code":"PPL",
    "gn:name":"Gowdan",
    "gn:population":0,
    "gn:timezone":"Asia/Tehran",
    "iso:country":"IR",
    "name:fas_x_preferred":[
        "\u06af\u0648\u062f\u0646"
    ],
    "name:und_x_variant":[
        "Goaden",
        "Gowdan"
    ],
    "wof:name":"Gowdan",
    "wof:placetype":"locality"
},
  "geometry": {"coordinates":[62.03333000000001,27.36667000000001],"type":"Point"}
}