{
  "type": "Feature",
  "properties": {
    "gn:admin1_code":"28.0",
    "gn:asciiname":"Shahabad",
    "gn:country_code":"IR",
    "gn:dem":1528,
    "gn:feature_class":"P",
    "gn:feature_code":"PPL",
    "gn:name":"Sh\u0101h\u0101b\u0101d",
    "gn:population":0,
    "gn:timezone":"Asia/Tehran",
    "iso:country":"IR",
    "name:ben_x_preferred":[
        "\u09b6\u09be\u09b9\u09be\u09ac\u09be\u09a6"
    ],
    "name:ceb_x_preferred":[
        "Shahabad"
    ],
    "name:fas_x_preferred":[
        "Sh\u0101h\u0101b\u0101d"
    ],
    "name:fas_x_variant":[
        "\u0634\u0627\u0647\u200c\u0622\u0628\u0627\u062f"
    ],
    "name:nld_x_preferred":[
        "Shahabad"
    ],
    "name:pol_x_preferred":[
        "Shahabad"
    ],
    "name:swe_x_preferred":[
        "Shahabad"
    ],
    "wof:name":"Shahabad",
    "wof:placetype":"locality"
},
  "geometry": {"coordinates":[51.91917,32.62],"type":"Point"}
}