{
  "type": "Feature",
  "properties": {
    "gn:admin1_code":"28.0",
    "gn:asciiname":"Shahabad",
    "gn:country_code":"IR",
    "gn:dem":1528,
    "gn:feature_class":"P",
    "gn:feature_code":"PPL",
    "gn:name":"Sh\u0101h\u0101b\u0101d",
    "gn:population":0,
    "gn:timezone":"Asia/Tehran",
    "iso:country":"IR",
    "name:fas_x_preferred":[
        "Sh\u0101h\u0101b\u0101d"
    ],
    "wof:name":"Shahabad",
    "wof:placetype":"locality"
},
  "geometry": {"coordinates":[51.91917,32.62],"type":"Point"}
}