{
  "type": "Feature",
  "properties": {
    "gn:admin1_code":"13",
    "gn:asciiname":"Bagh-e Zeynab",
    "gn:country_code":"IR",
    "gn:dem":1342,
    "gn:feature_class":"P",
    "gn:feature_code":"PPL",
    "gn:name":"B\u0101gh-e Zeynab",
    "gn:population":0,
    "gn:timezone":"Asia/Tehran",
    "iso:country":"IR",
    "name:fas_x_preferred":[
        "\u0628\u0627\u063a \u0632\u06cc\u0646\u0628"
    ],
    "name:fas_x_variant":[
        "B\u0101gh-e Zeynab"
    ],
    "wof:name":"Bagh-e Zeynab",
    "wof:placetype":"locality"
},
  "geometry": {"coordinates":[47.3996,34.1712],"type":"Point"}
}