{
  "type": "Feature",
  "properties": {
    "gn:admin1_code":"1.0",
    "gn:asciiname":"Baveh",
    "gn:country_code":"IR",
    "gn:dem":1621,
    "gn:feature_class":"P",
    "gn:feature_code":"PPL",
    "gn:name":"B\u0101veh",
    "gn:population":0,
    "gn:timezone":"Asia/Tehran",
    "iso:country":"IR",
    "name:azb_x_preferred":[
        "\u0628\u0627\u0648\u0647"
    ],
    "name:ceb_x_preferred":[
        "B\u0101veh"
    ],
    "name:ckb_x_preferred":[
        "\u0628\u0627\u0648\u06d5"
    ],
    "name:fas_x_preferred":[
        "\u0628\u0627\u0648\u0647"
    ],
    "name:fas_x_variant":[
        "B\u0101veh"
    ],
    "name:kur_x_preferred":[
        "Bawe"
    ],
    "name:msa_x_preferred":[
        "Baveh"
    ],
    "name:swe_x_preferred":[
        "B\u0101veh"
    ],
    "wof:name":"Baveh",
    "wof:placetype":"locality"
},
  "geometry": {"coordinates":[45.3951,36.1697],"type":"Point"}
}