{
  "type": "Feature",
  "properties": {
    "gn:admin1_code":"29.0",
    "gn:asciiname":"Owraf",
    "gn:country_code":"IR",
    "gn:dem":1858,
    "gn:feature_class":"P",
    "gn:feature_code":"PPL",
    "gn:name":"Owr\u0101f",
    "gn:population":0,
    "gn:timezone":"Asia/Tehran",
    "iso:country":"IR",
    "name:fas_x_preferred":[
        "\u0627\u0648\u0631\u0627\u0641"
    ],
    "name:fas_x_variant":[
        "\u0634\u0648\u0631 \u0622\u0628"
    ],
    "name:und_x_variant":[
        "Do Garm",
        "Owr\u0101f",
        "Sh\u016br \u0100b"
    ],
    "wof:name":"Owraf",
    "wof:placetype":"locality"
},
  "geometry": {"coordinates":[55.98972,30.22472],"type":"Point"}
}