{
  "type": "Feature",
  "properties": {
    "gn:admin1_code":"3",
    "gn:asciiname":"Chal-e Deraz",
    "gn:country_code":"IR",
    "gn:dem":1748,
    "gn:feature_class":"P",
    "gn:feature_code":"PPL",
    "gn:name":"Ch\u0101l-e Der\u0101z",
    "gn:population":0,
    "gn:timezone":"Asia/Tehran",
    "iso:country":"IR",
    "name:fas_x_preferred":[
        "\u0686\u0627\u0644\u0650\u0647 \u062f\u0650\u0631\u0627\u0632\u0650 \u0646\u0650\u0639\u0645\u064e\u062a \u0627\u0644\u0644\u064e\u0651\u0647"
    ],
    "name:fas_x_variant":[
        "Ch\u0101l-e Der\u0101z",
        "\u0686\u0627\u0644 \u062f\u0631\u0627\u0632",
        "\u0686\u0627\u0644 \u062f\u0631\u0627\u0632 \u06cc\u062f\u0627\u0644\u0644\u0647"
    ],
    "name:und_x_variant":[
        "Ch\u0101leh Der\u0101z-e Ne\u2018matoll\u0101h",
        "\u0686\u0627\u0644 \u062f\u0631\u0627\u0632",
        "Ch\u0101l-e Der\u0101z Yadoll\u0101h"
    ],
    "wof:name":"Chal-e Deraz",
    "wof:placetype":"locality"
},
  "geometry": {"coordinates":[50.50319,31.51054],"type":"Point"}
}