{
  "type": "Feature",
  "properties": {
    "gn:admin1_code":"15.0",
    "gn:asciiname":"Maharem Yazdi",
    "gn:country_code":"IR",
    "gn:dem":96,
    "gn:feature_class":"P",
    "gn:feature_code":"PPL",
    "gn:name":"Ma\u1e29\u0101rem Yazd\u012b",
    "gn:population":0,
    "gn:timezone":"Asia/Tehran",
    "iso:country":"IR",
    "name:fas_x_preferred":[
        "Ma\u1e29\u0101reb"
    ],
    "name:fas_x_variant":[
        "\u0645\u062d\u0627\u0631\u0645 \u06cc\u0632\u062f\u06cc",
        "\u0645\u062d\u0627\u0631\u0628",
        "\u0634\u0647\u0631\u06a9 \u0622\u0632\u0627\u062f\u06cc"
    ],
    "name:und_x_variant":[
        "Ma\u1e29\u0101rem Yazd\u012b",
        "Shahrak-e \u0100z\u0101d\u012b"
    ],
    "wof:name":"Maharem Yazdi",
    "wof:placetype":"locality"
},
  "geometry": {"coordinates":[48.05379,32.01599],"type":"Point"}
}