{
  "type": "Feature",
  "properties": {
    "gn:admin1_code":"15",
    "gn:asciiname":"Omm ot Torfeh",
    "gn:country_code":"IR",
    "gn:dem":12,
    "gn:feature_class":"P",
    "gn:feature_code":"PPL",
    "gn:name":"Omm o\u0163 \u0162orfeh",
    "gn:population":0,
    "gn:timezone":"Asia/Tehran",
    "iso:country":"IR",
    "name:fas_x_preferred":[
        "Omm o\u0163 \u0162orfeh"
    ],
    "name:fas_x_variant":[
        "\u0627\u0645 \u0627\u0644\u0637\u0631\u0641\u0647"
    ],
    "name:und_x_variant":[
        "Omm ol \u0162arfeh",
        "Mutarfa",
        "Mo\u0163rafeh"
    ],
    "wof:name":"Omm ot Torfeh",
    "wof:placetype":"locality"
},
  "geometry": {"coordinates":[48.8173,31.20245],"type":"Point"}
}