{
  "type": "Feature",
  "properties": {
    "gn:admin1_code":"28",
    "gn:asciiname":"Tahlehgi",
    "gn:country_code":"IR",
    "gn:dem":2409,
    "gn:feature_class":"P",
    "gn:feature_code":"PPL",
    "gn:name":"Tahlehg\u012b",
    "gn:population":0,
    "gn:timezone":"Asia/Tehran",
    "iso:country":"IR",
    "name:fas_x_preferred":[
        "Tahlehg\u012b"
    ],
    "name:fas_x_variant":[
        "\u062a\u0647\u0644\u0647 \u06af\u06cc"
    ],
    "wof:name":"Tahlehgi",
    "wof:placetype":"locality"
},
  "geometry": {"coordinates":[50.27388,32.64968],"type":"Point"}
}