{
  "type": "Feature",
  "properties": {
    "gn:admin1_code":"15",
    "gn:asciiname":"Mezlageh-ye Sofla",
    "gn:country_code":"IR",
    "gn:dem":12,
    "gn:feature_class":"P",
    "gn:feature_code":"PPL",
    "gn:name":"Mezl\u0101geh-ye Sofl\u00e1",
    "gn:population":0,
    "gn:timezone":"Asia/Tehran",
    "iso:country":"IR",
    "name:fas_x_preferred":[
        "\u0645\u0632\u0644\u0627\u06af\u0647 \u0633\u0641\u0644\u06cc"
    ],
    "name:fas_x_variant":[
        "Mezl\u0101geh-ye P\u0101\u2019\u012bn",
        "Mezl\u0101geh-ye Sofl\u00e1"
    ],
    "name:und_x_variant":[
        "Muzl\u0101gi\u0101",
        "Mesl\u0101geh",
        "Mazl\u0101geh",
        "Mezl\u0101geh",
        "Mezl\u0101geh-ye Sofl\u00e1"
    ],
    "wof:name":"Mezlageh-ye Sofla",
    "wof:placetype":"locality"
},
  "geometry": {"coordinates":[49.31845,30.73091],"type":"Point"}
}