{
  "type": "Feature",
  "properties": {
    "gn:admin1_code":"42",
    "gn:asciiname":"Rishkhvar",
    "gn:country_code":"IR",
    "gn:dem":1724,
    "gn:feature_class":"P",
    "gn:feature_code":"PPL",
    "gn:name":"R\u012bshkhv\u0101r",
    "gn:population":0,
    "gn:timezone":"Asia/Tehran",
    "iso:country":"IR",
    "name:fas_x_preferred":[
        "R\u012bshkhv\u0101r"
    ],
    "name:fas_x_variant":[
        "\u0631\u06cc\u0634\u062e\u0648\u0627\u0631",
        "R\u016bshkh\u012b",
        "R\u012bshkh\u0101r"
    ],
    "name:und_x_variant":[
        "Rushkhei"
    ],
    "wof:name":"Rishkhvar",
    "wof:placetype":"locality"
},
  "geometry": {"coordinates":[59.10486,37.09124],"type":"Point"}
}