{
  "type": "Feature",
  "properties": {
    "gn:admin1_code":"23.0",
    "gn:asciiname":"Hasan",
    "gn:country_code":"IR",
    "gn:dem":713,
    "gn:feature_class":"P",
    "gn:feature_code":"PPL",
    "gn:name":"\u1e28asan",
    "gn:population":0,
    "gn:timezone":"Asia/Tehran",
    "iso:country":"IR",
    "name:fas_x_preferred":[
        "\u062d\u0633\u0646"
    ],
    "name:und_x_variant":[
        "\u1e28asan"
    ],
    "wof:name":"Hasan",
    "wof:placetype":"locality"
},
  "geometry": {"coordinates":[46.8925,33.50597],"type":"Point"}
}