{
  "type": "Feature",
  "properties": {
    "gn:admin1_code":"23",
    "gn:asciiname":"Razbashi",
    "gn:country_code":"IR",
    "gn:dem":1673,
    "gn:feature_class":"P",
    "gn:feature_code":"PPL",
    "gn:name":"R\u0101zb\u0101sh\u012b",
    "gn:population":0,
    "gn:timezone":"Asia/Tehran",
    "iso:country":"IR",
    "name:fas_x_preferred":[
        "\u0631\u0627\u0632\u0628\u0627\u0634\u06cc"
    ],
    "name:fas_x_variant":[
        "R\u0101zb\u0101sh\u012b"
    ],
    "name:und_x_variant":[
        "R\u0101zb\u0101sh\u012b"
    ],
    "wof:name":"Razbashi",
    "wof:placetype":"locality"
},
  "geometry": {"coordinates":[48.4518,33.6926],"type":"Point"}
}