{
  "type": "Feature",
  "properties": {
    "gn:admin1_code":"8",
    "gn:asciiname":"Mahalleh-ye Sefid Mazgi-ye Shalma",
    "gn:country_code":"IR",
    "gn:dem":125,
    "gn:feature_class":"P",
    "gn:feature_code":"PPL",
    "gn:name":"Ma\u1e29alleh-ye Sef\u012bd Mazg\u012b-ye Sh\u0101lm\u0101",
    "gn:population":0,
    "gn:timezone":"Asia/Tehran",
    "iso:country":"IR",
    "name:ceb_x_preferred":[
        "Sef\u012bd Mazg\u012b"
    ],
    "name:fas_x_preferred":[
        "\u0633\u0641\u06cc\u062f \u0645\u0632\u06af\u06cc"
    ],
    "name:fas_x_variant":[
        "Sef\u012bd Mazg\u012b",
        "\u0645\u062d\u0644\u0647 \u0633\u0641\u06cc\u062f \u0645\u0632\u06af\u06cc \u0634\u0627\u0644\u0645\u0627"
    ],
    "name:msa_x_preferred":[
        "Sefid Mazgi"
    ],
    "name:swe_x_preferred":[
        "Sef\u012bd Mazg\u012b"
    ],
    "name:und_x_variant":[
        "Sef\u012bd Mazg\u012b",
        "Ma\u1e29alleh-ye Sef\u012bd Mazg\u012b-ye Sh\u0101lm\u0101"
    ],
    "wof:name":"Mahalleh-ye Sefid Mazgi-ye Shalma",
    "wof:placetype":"locality"
},
  "geometry": {"coordinates":[49.32100000000001,37.10399],"type":"Point"}
}