{
  "type": "Feature",
  "properties": {
    "gn:admin1_code":"33",
    "gn:asciiname":"Khuy Saraq",
    "gn:country_code":"IR",
    "gn:dem":1586,
    "gn:elevation":"0.0",
    "gn:feature_class":"P",
    "gn:feature_code":"PPL",
    "gn:name":"Kh\u016by Saraq",
    "gn:population":0,
    "gn:timezone":"Asia/Tehran",
    "iso:country":"IR",
    "name:fas_x_preferred":[
        "\u062e\u0648\u06cc \u0633\u0631\u0647"
    ],
    "name:fas_x_variant":[
        "Kh\u016by B\u016br\u016bq",
        "\u062e\u0648\u06cc \u0633\u0631\u0642",
        "\u062e\u0648\u06cc \u0633\u0648\u0631\u0642"
    ],
    "name:und_x_variant":[
        "Khowy Sareh",
        "Kh\u016by Saraq",
        "Kh\u016by S\u016braq",
        "Kh\u016by Sareh"
    ],
    "wof:name":"Khuy Saraq",
    "wof:placetype":"locality"
},
  "geometry": {"coordinates":[47.3646,38.9507],"type":"Point"}
}