{
  "type": "Feature",
  "properties": {
    "gn:admin1_code":"38",
    "gn:asciiname":"Emamzadeh Danial",
    "gn:country_code":"IR",
    "gn:dem":420,
    "gn:feature_class":"P",
    "gn:feature_code":"PPL",
    "gn:name":"Em\u0101mz\u0101deh D\u0101n\u012b\u0101l",
    "gn:population":0,
    "gn:timezone":"Asia/Tehran",
    "iso:country":"IR",
    "name:fas_x_preferred":[
        "Em\u0101mz\u0101deh D\u0101n\u012b\u0101l"
    ],
    "wof:name":"Emamzadeh Danial",
    "wof:placetype":"locality"
},
  "geometry": {"coordinates":[49.53333,36.58333],"type":"Point"}
}