{
  "type": "Feature",
  "properties": {
    "gn:admin1_code":"1.0",
    "gn:asciiname":"Qal`eh-ye Mutabad",
    "gn:country_code":"IR",
    "gn:dem":1394,
    "gn:feature_class":"P",
    "gn:feature_code":"PPL",
    "gn:name":"Qal\u2018eh-ye M\u016bt\u0101b\u0101d",
    "gn:population":0,
    "gn:timezone":"Asia/Tehran",
    "iso:country":"IR",
    "name:fas_x_preferred":[
        "\u0642\u0644\u0639\u0647 \u0645\u0648\u062a \u0622\u0628\u0627\u062f"
    ],
    "name:fas_x_variant":[
        "Qal\u2018eh-ye M\u016bt\u0101b\u0101d"
    ],
    "wof:name":"Qal`eh-ye Mutabad",
    "wof:placetype":"locality"
},
  "geometry": {"coordinates":[45.1681,36.6475],"type":"Point"}
}