{
  "type": "Feature",
  "properties": {
    "gn:admin1_code":"3",
    "gn:asciiname":"Zeverdegan",
    "gn:country_code":"IR",
    "gn:dem":2273,
    "gn:feature_class":"P",
    "gn:feature_code":"PPL",
    "gn:name":"Zeverdeg\u0101n",
    "gn:population":0,
    "gn:timezone":"Asia/Tehran",
    "iso:country":"IR",
    "name:ceb_x_preferred":[
        "Zeverdeg\u0101n"
    ],
    "name:fas_x_preferred":[
        "\u0634\u0647\u0631\u06a9 \u0632\u0650\u0648\u0650\u0631\u062f\u06af\u0627\u0646"
    ],
    "name:fas_x_variant":[
        "Shahrak-e Zeverdeg\u0101n",
        "Zeverdeg\u0101n",
        "\u0632\u0648\u0631\u062f\u06af\u0627\u0646",
        "\u0634\u0647\u0631\u06a9 \u0632\u0648\u0631\u062f\u06af\u0627\u0646"
    ],
    "name:msa_x_preferred":[
        "Shahrak-e Zeverdegan"
    ],
    "name:swe_x_preferred":[
        "Zeverdeg\u0101n"
    ],
    "wof:name":"Zeverdegan",
    "wof:placetype":"locality"
},
  "geometry": {"coordinates":[50.86341,31.96775],"type":"Point"}
}