{
  "type": "Feature",
  "properties": {
    "gn:admin1_code":"0",
    "gn:asciiname":"Howlmuk",
    "gn:country_code":"IR",
    "gn:dem":1433,
    "gn:feature_class":"P",
    "gn:feature_code":"PPL",
    "gn:name":"Howlm\u016bk",
    "gn:population":0,
    "gn:timezone":"Asia/Tehran",
    "iso:country":"IR",
    "name:fas_x_preferred":[
        "\u0647\u0648\u0644\u0645\u0648\u06a9"
    ],
    "name:fas_x_variant":[
        "Howlm\u016bk"
    ],
    "wof:name":"Howlmuk",
    "wof:placetype":"locality"
},
  "geometry": {"coordinates":[57.8249,26.8241],"type":"Point"}
}