{
  "type": "Feature",
  "properties": {
    "gn:admin1_code":"23",
    "gn:asciiname":"Tang Goraz",
    "gn:country_code":"IR",
    "gn:dem":1364,
    "gn:feature_class":"P",
    "gn:feature_code":"PPL",
    "gn:name":"Tang Gor\u0101z",
    "gn:population":0,
    "gn:timezone":"Asia/Tehran",
    "iso:country":"IR",
    "name:fas_x_preferred":[
        "\u062a\u0646\u06af \u06af\u0631\u0627\u0632"
    ],
    "name:und_x_variant":[
        "Tang Gor\u0101z"
    ],
    "wof:name":"Tang Goraz",
    "wof:placetype":"locality"
},
  "geometry": {"coordinates":[47.7285,33.55],"type":"Point"}
}