{
  "type": "Feature",
  "properties": {
    "gn:admin1_code":"40",
    "gn:asciiname":"Torkabad",
    "gn:country_code":"IR",
    "gn:dem":1019,
    "gn:feature_class":"P",
    "gn:feature_code":"PPL",
    "gn:name":"Tork\u0101b\u0101d",
    "gn:population":0,
    "gn:timezone":"Asia/Tehran",
    "iso:country":"IR",
    "name:fas_x_preferred":[
        "\u062a\u0631\u0643 \u0622\u0628\u0627\u062f"
    ],
    "name:fas_x_variant":[
        "\u062a\u064e\u0631\u0643 \u0622\u0628\u0627\u062f",
        "Tork\u0101b\u0101d"
    ],
    "name:und_x_variant":[
        "Tark\u0101b\u0101d",
        "Turk\u0101b\u0101d"
    ],
    "wof:name":"Torkabad",
    "wof:placetype":"locality"
},
  "geometry": {"coordinates":[53.9677,32.3406],"type":"Point"}
}