{
  "type": "Feature",
  "properties": {
    "gn:admin1_code":"26.0",
    "gn:asciiname":"Yakhchiabad",
    "gn:country_code":"IR",
    "gn:dem":1089,
    "gn:feature_class":"P",
    "gn:feature_code":"PPL",
    "gn:name":"Y\u0101khch\u012b\u0101b\u0101d",
    "gn:population":0,
    "gn:timezone":"Asia/Tehran",
    "iso:country":"IR",
    "name:fas_x_preferred":[
        "\u06cc\u0627\u062e\u0686\u06cc \u0622\u0628\u0627\u062f"
    ],
    "name:fas_x_variant":[
        "Y\u0101khch\u012b\u0101b\u0101d"
    ],
    "wof:name":"Yakhchiabad",
    "wof:placetype":"locality"
},
  "geometry": {"coordinates":[51.4052,35.6218],"type":"Point"}
}