{
  "type": "Feature",
  "properties": {
    "gn:admin1_code":"34",
    "gn:asciiname":"Mishjan-e `Olya",
    "gn:country_code":"IR",
    "gn:dem":1772,
    "gn:feature_class":"P",
    "gn:feature_code":"PPL",
    "gn:name":"M\u012bshj\u0101n-e \u2018Oly\u0101",
    "gn:population":0,
    "gn:timezone":"Asia/Tehran",
    "iso:country":"IR",
    "name:fas_x_preferred":[
        "\u0645\u064a\u0634\u062c\u0627\u0646\u0650 \u0628\u0627\u0644\u0627"
    ],
    "name:fas_x_variant":[
        "\u0645\u064a\u0634\u064e\u062c\u0627\u0646 \u0628\u0627\u0644\u0627",
        "\u0645\u064a\u0634\u064a\u062c\u0627\u0646\u0650 \u0639\u064f\u0644\u064a\u0627",
        "\u0645\u0648\u0634\u064a\u062c\u0627\u0646",
        "\u0645\u0650\u064a\u0634\u06cc \u062c\u0627\u0646",
        "\u0645\u064a\u0634\u064a\u062c\u064e\u0646 \u0639\u064f\u0644\u064a\u064e",
        "M\u012bshj\u0101n-e \u2018Oly\u0101",
        "M\u012bshj\u0101n-e B\u0101l\u0101",
        "\u0645\u064a\u0634\u062c\u0627\u0646 \u0639\u0644\u06cc\u0627"
    ],
    "name:und_x_variant":[
        "M\u016bsh\u012bj\u0101n",
        "M\u012bshaj\u0101n B\u0101l\u0101",
        "M\u014dsh\u012b\u0101n",
        "M\u012bsh\u012bjan \u2018Olya",
        "M\u012bsh\u012bj\u0101n-e \u2018Oly\u0101",
        "Meysh\u012b J\u0101n",
        "\u0645\u064a\u0634\u062c\u0627\u0646 \u0639\u0644\u06cc\u0627"
    ],
    "wof:name":"Mishjan-e `Olya",
    "wof:placetype":"locality"
},
  "geometry": {"coordinates":[50.12601,33.67828],"type":"Point"}
}