{
  "type": "Feature",
  "properties": {
    "gn:admin1_code":"22",
    "gn:asciiname":"Samal-e Shomali",
    "gn:country_code":"IR",
    "gn:dem":72,
    "gn:feature_class":"P",
    "gn:feature_code":"PPL",
    "gn:name":"Samal-e Shom\u0101l\u012b",
    "gn:population":0,
    "gn:timezone":"Asia/Tehran",
    "iso:country":"IR",
    "name:ceb_x_preferred":[
        "Samal-e Shom\u0101l\u012b"
    ],
    "name:fas_x_preferred":[
        "\u0633\u0645\u0644 \u0634\u0645\u0627\u0644\u06cc"
    ],
    "name:fas_x_variant":[
        "\u0633\u064e\u0645\u064e\u0644",
        "Samal-e Shom\u0101l\u012b"
    ],
    "name:msa_x_preferred":[
        "Samal-e Shomali"
    ],
    "name:swe_x_preferred":[
        "Samal-e Shom\u0101l\u012b"
    ],
    "name:und_x_variant":[
        "Samal"
    ],
    "wof:name":"Samal-e Shomali",
    "wof:placetype":"locality"
},
  "geometry": {"coordinates":[51.2263,29.1066],"type":"Point"}
}