{
  "type": "Feature",
  "properties": {
    "gn:admin1_code":"36",
    "gn:asciiname":"Baqcheh",
    "gn:country_code":"IR",
    "gn:dem":1817,
    "gn:feature_class":"P",
    "gn:feature_code":"PPL",
    "gn:name":"B\u0101qcheh",
    "gn:population":0,
    "gn:timezone":"Asia/Tehran",
    "iso:country":"IR",
    "name:fas_x_preferred":[
        "B\u0101ghcheh"
    ],
    "name:fas_x_variant":[
        "\u0628\u0627\u0642\u0686\u0647",
        "\u0628\u0627\u063a\u0686\u0647"
    ],
    "name:und_x_variant":[
        "B\u0101qcheh"
    ],
    "wof:name":"Baqcheh",
    "wof:placetype":"locality"
},
  "geometry": {"coordinates":[47.5424,36.81979000000001],"type":"Point"}
}