{
  "type": "Feature",
  "properties": {
    "gn:admin1_code":"41.0",
    "gn:asciiname":"Do Chahi-ye Chah Dabbeh",
    "gn:country_code":"IR",
    "gn:dem":929,
    "gn:feature_class":"P",
    "gn:feature_code":"PPL",
    "gn:name":"Do Ch\u0101h\u012b-ye Ch\u0101h Dabbeh",
    "gn:population":0,
    "gn:timezone":"Asia/Tehran",
    "iso:country":"IR",
    "name:fas_x_preferred":[
        "\u062f\u0648 \u0686\u0627\u0647\u06cc \u0686\u0627\u0647 \u062f\u0628\u0647"
    ],
    "name:und_x_variant":[
        "Do Ch\u0101h\u012b-ye Ch\u0101h Dabbeh"
    ],
    "wof:name":"Do Chahi-ye Chah Dabbeh",
    "wof:placetype":"locality"
},
  "geometry": {"coordinates":[58.62891,32.00035],"type":"Point"}
}