{
  "type": "Feature",
  "properties": {
    "gn:admin1_code":"23",
    "gn:asciiname":"Gireh Kardeh",
    "gn:country_code":"IR",
    "gn:dem":1342,
    "gn:feature_class":"P",
    "gn:feature_code":"PPL",
    "gn:name":"G\u012breh Kardeh",
    "gn:population":0,
    "gn:timezone":"Asia/Tehran",
    "iso:country":"IR",
    "name:fas_x_preferred":[
        "G\u012bj Gardan"
    ],
    "name:fas_x_variant":[
        "G\u012brj Gereh",
        "\u06a9\u0686 \u06a9\u0631\u062f\u0647",
        "\u06af\u064a\u0631\u0647 \u06a9\u0631\u062f\u0647",
        "\u06af\u064a\u0698 \u06af\u0631\u062f\u0647",
        "\u06af\u064a\u0631\u062c \u06af\u0631\u062f\u0647"
    ],
    "name:und_x_variant":[
        "Gr\u012bj Gerdeh",
        "G\u012bj Gerdeh",
        "Kach Kardeh",
        "\u06a9\u0686 \u06a9\u0631\u062f\u0647",
        "G\u012breh Kardeh",
        "G\u012bzh Gerdeh",
        "G\u012brj Gerdeh"
    ],
    "wof:name":"Gireh Kardeh",
    "wof:placetype":"locality"
},
  "geometry": {"coordinates":[48.4662,33.3789],"type":"Point"}
}