{
  "type": "Feature",
  "properties": {
    "gn:admin1_code":"7",
    "gn:asciiname":"Kikomidan-e Bala",
    "gn:cc2":"IR",
    "gn:country_code":"IR",
    "gn:dem":1687,
    "gn:feature_class":"P",
    "gn:feature_code":"PPL",
    "gn:name":"K\u012bkom\u012bd\u0101n-e B\u0101l\u0101",
    "gn:population":0,
    "gn:timezone":"Asia/Tehran",
    "iso:country":"IR",
    "name:fas_x_preferred":[
        "K\u012bkom\u012bd\u0101n-e B\u0101l\u0101"
    ],
    "name:und_x_variant":[
        "K\u012bkom\u012bd\u0101n-e \u2018Oly\u0101"
    ],
    "wof:name":"Kikomidan-e Bala",
    "wof:placetype":"locality"
},
  "geometry": {"coordinates":[51.8475,30.00472],"type":"Point"}
}