{
  "type": "Feature",
  "properties": {
    "gn:admin1_code":"7",
    "gn:asciiname":"Mal-e Mahmud",
    "gn:country_code":"IR",
    "gn:dem":879,
    "gn:feature_class":"P",
    "gn:feature_code":"PPL",
    "gn:name":"M\u0101l-e Ma\u1e29m\u016bd",
    "gn:population":0,
    "gn:timezone":"Asia/Tehran",
    "iso:country":"IR",
    "name:fas_x_preferred":[
        "M\u0101l Ma\u1e29m\u016bd"
    ],
    "name:fas_x_variant":[
        "M\u0101l-e Ma\u1e29m\u016bd",
        "\u0645\u0627\u0644 \u0645\u062d\u0645\u0648\u062f"
    ],
    "name:und_x_variant":[
        "M\u0101l-e Ma\u1e29m\u016bd",
        "\u0645\u0627\u0644 \u0645\u062d\u0645\u0648\u062f"
    ],
    "wof:name":"Mal-e Mahmud",
    "wof:placetype":"locality"
},
  "geometry": {"coordinates":[51.4294,30.12704],"type":"Point"}
}