{
  "type": "Feature",
  "properties": {
    "gn:admin1_code":"15",
    "gn:asciiname":"Shahrak-e Mohajerin",
    "gn:country_code":"IR",
    "gn:dem":131,
    "gn:feature_class":"P",
    "gn:feature_code":"PPL",
    "gn:name":"Shahrak-e Moh\u0101jer\u012bn",
    "gn:population":0,
    "gn:timezone":"Asia/Tehran",
    "iso:country":"IR",
    "name:fas_x_preferred":[
        "\u0634\u0647\u0631\u06a9 \u0645\u0647\u0627\u062c\u0631\u0627\u0646"
    ],
    "name:fas_x_variant":[
        "Shahrak-e Moh\u0101jer\u012bn",
        "Shahrak-e Moh\u0101jer\u0101n",
        "\u0634\u0647\u0631\u06a9 \u0645\u0647\u0627\u062c\u0631\u06cc\u0646"
    ],
    "wof:name":"Shahrak-e Mohajerin",
    "wof:placetype":"locality"
},
  "geometry": {"coordinates":[48.46087,32.34994],"type":"Point"}
}