{
  "type": "Feature",
  "properties": {
    "gn:admin1_code":"8",
    "gn:asciiname":"Dastak",
    "gn:country_code":"IR",
    "gn:dem":-13,
    "gn:feature_class":"P",
    "gn:feature_code":"PPL",
    "gn:name":"Dastak",
    "gn:population":0,
    "gn:timezone":"Asia/Tehran",
    "iso:country":"IR",
    "name:fas_x_preferred":[
        "\u062f\u0633\u062a\u06a9"
    ],
    "name:und_x_variant":[
        "\u062f\u0633\u062a\u06a9"
    ],
    "wof:name":"Dastak",
    "wof:placetype":"locality"
},
  "geometry": {"coordinates":[50.14304,37.38598],"type":"Point"}
}