{
  "type": "Feature",
  "properties": {
    "gn:admin1_code":"29",
    "gn:asciiname":"Bolbolu",
    "gn:country_code":"IR",
    "gn:dem":552,
    "gn:feature_class":"P",
    "gn:feature_code":"PPL",
    "gn:name":"Bolbol\u016b",
    "gn:population":0,
    "gn:timezone":"Asia/Tehran",
    "iso:country":"IR",
    "name:fas_x_preferred":[
        "\u0628\u0644\u0628\u0644\u0648"
    ],
    "name:fas_x_variant":[
        "Bolbol\u016b"
    ],
    "wof:name":"Bolbolu",
    "wof:placetype":"locality"
},
  "geometry": {"coordinates":[57.7179,28.228],"type":"Point"}
}