{
  "type": "Feature",
  "properties": {
    "gn:admin1_code":"33",
    "gn:asciiname":"Molla Qasem",
    "gn:country_code":"IR",
    "gn:dem":1833,
    "gn:feature_class":"P",
    "gn:feature_code":"PPL",
    "gn:name":"Moll\u0101 Q\u0101sem",
    "gn:population":0,
    "gn:timezone":"Asia/Tehran",
    "iso:country":"IR",
    "name:fas_x_preferred":[
        "\u0645\u0644\u0627 \u0642\u0627\u0633\u0645"
    ],
    "name:fas_x_variant":[
        "Moll\u0101 Q\u0101sem"
    ],
    "wof:name":"Molla Qasem",
    "wof:placetype":"locality"
},
  "geometry": {"coordinates":[46.75781,37.59754],"type":"Point"}
}