{
  "type": "Feature",
  "properties": {
    "gn:admin1_code":"29",
    "gn:asciiname":"Ferdows",
    "gn:country_code":"IR",
    "gn:dem":700,
    "gn:feature_class":"P",
    "gn:feature_code":"PPL",
    "gn:name":"Ferdows",
    "gn:population":0,
    "gn:timezone":"Asia/Tehran",
    "iso:country":"IR",
    "name:fas_x_preferred":[
        "\u0641\u0631\u062f\u0648\u0633"
    ],
    "wof:name":"Ferdows",
    "wof:placetype":"locality"
},
  "geometry": {"coordinates":[58.8697,28.7543],"type":"Point"}
}