{
  "type": "Feature",
  "properties": {
    "gn:admin1_code":"29",
    "gn:asciiname":"Ferdows",
    "gn:country_code":"IR",
    "gn:dem":700,
    "gn:feature_class":"P",
    "gn:feature_code":"PPL",
    "gn:name":"Ferdows",
    "gn:population":0,
    "gn:timezone":"Asia/Tehran",
    "iso:country":"IR",
    "name:ara_x_preferred":[
        "\u0641\u0631\u062f\u0648\u0633"
    ],
    "name:arz_x_preferred":[
        "\u0641\u0631\u062f\u0648\u0633"
    ],
    "name:aze_x_preferred":[
        "Firdovs"
    ],
    "name:cat_x_preferred":[
        "Ferdows"
    ],
    "name:ceb_x_preferred":[
        "Ferdows"
    ],
    "name:deu_x_preferred":[
        "Ferdows"
    ],
    "name:fas_x_preferred":[
        "\u0641\u0631\u062f\u0648\u0633"
    ],
    "name:fin_x_preferred":[
        "Ferdows"
    ],
    "name:fra_x_preferred":[
        "Ferdows"
    ],
    "name:ita_x_preferred":[
        "Ferdows"
    ],
    "name:jpn_x_preferred":[
        "\u30d5\u30a7\u30eb\u30c9\u30a5\u30fc\u30b9"
    ],
    "name:kor_x_preferred":[
        "\ud398\ub974\ub450\uc2a4"
    ],
    "name:mlg_x_preferred":[
        "Ferdows"
    ],
    "name:nld_x_preferred":[
        "Ferdows"
    ],
    "name:pnb_x_preferred":[
        "\u0641\u0631\u062f\u0648\u0633"
    ],
    "name:pol_x_preferred":[
        "Ferdous"
    ],
    "name:ron_x_preferred":[
        "Ferdows"
    ],
    "name:rus_x_preferred":[
        "\u0424\u0435\u0440\u0434\u043e\u0443\u0441"
    ],
    "name:spa_x_preferred":[
        "Ferdows"
    ],
    "name:swe_x_preferred":[
        "Ferdows"
    ],
    "name:tgk_x_preferred":[
        "\u0424\u0438\u0440\u0434\u0430\u0432\u0441"
    ],
    "name:tur_x_preferred":[
        "Firdevs"
    ],
    "name:urd_x_preferred":[
        "\u0641\u0631\u062f\u0648\u0633"
    ],
    "name:zho_x_preferred":[
        "\u8cbb\u723e\u9053\u65af"
    ],
    "wof:name":"Ferdows",
    "wof:placetype":"locality"
},
  "geometry": {"coordinates":[58.8697,28.7543],"type":"Point"}
}