{
  "type": "Feature",
  "properties": {
    "gn:admin1_code":"16",
    "gn:asciiname":"Aqbolagh",
    "gn:country_code":"IR",
    "gn:dem":2047,
    "gn:feature_class":"P",
    "gn:feature_code":"PPL",
    "gn:name":"\u0100qbol\u0101gh",
    "gn:population":0,
    "gn:timezone":"Asia/Tehran",
    "iso:country":"IR",
    "name:fas_x_preferred":[
        "\u0622\u0642\u0628\u0644\u0627\u063a \u0637\u0642\u0627\u0645\u064a\u0646"
    ],
    "name:fas_x_variant":[
        "\u0100qbol\u0101gh-e \u0162agh\u0101m\u012bn",
        "\u0100qbol\u0101gh-e \u0162aq\u0101m\u012bn",
        "\u0622\u0642\u0628\u0644\u0627\u063a",
        "\u0622\u0642\u0628\u0644\u0627\u063a \u0637\u063a\u0627\u0645\u064a\u0646"
    ],
    "name:und_x_variant":[
        "\u0100qbol\u0101gh"
    ],
    "wof:name":"Aqbolagh",
    "wof:placetype":"locality"
},
  "geometry": {"coordinates":[47.50733,36.28977],"type":"Point"}
}