{
  "type": "Feature",
  "properties": {
    "gn:admin1_code":"29.0",
    "gn:asciiname":"`Abdolabad",
    "gn:country_code":"IR",
    "gn:dem":2679,
    "gn:feature_class":"P",
    "gn:feature_code":"PPL",
    "gn:name":"\u2018Abdol\u0101b\u0101d",
    "gn:population":0,
    "gn:timezone":"Asia/Tehran",
    "iso:country":"IR",
    "name:fas_x_preferred":[
        "\u2018Abdol\u0101b\u0101d"
    ],
    "name:fas_x_variant":[
        "\u0639\u0628\u062f\u0644 \u0622\u0628\u0627\u062f"
    ],
    "wof:name":"`Abdolabad",
    "wof:placetype":"locality"
},
  "geometry": {"coordinates":[56.97653,29.53873],"type":"Point"}
}