{
  "type": "Feature",
  "properties": {
    "gn:admin1_code":"43.0",
    "gn:asciiname":"Qarah Aghaj",
    "gn:country_code":"IR",
    "gn:dem":972,
    "gn:feature_class":"P",
    "gn:feature_code":"PPL",
    "gn:name":"Qarah \u0100gh\u0101j",
    "gn:population":0,
    "gn:timezone":"Asia/Tehran",
    "iso:country":"IR",
    "name:fas_x_preferred":[
        "Qarah \u0100q\u0101j-e \u1e28\u0101jj\u012b Nafas"
    ],
    "name:fas_x_variant":[
        "Qarah \u0100gh\u0101j-e \u1e28\u0101jj\u012b Nafas",
        "\u0642\u0631\u0647 \u0622\u0642\u0627\u062c \u062d\u0627\u062c\u06cc \u0646\u0641\u0633",
        "\u0642\u0631\u0647 \u0622\u063a\u0627\u062c"
    ],
    "name:und_x_variant":[
        "\u0642\u0631\u0647 \u0622\u0642\u0627\u062c \u062d\u0627\u062c\u06cc \u0646\u0641\u0633",
        "Qarah \u0100gh\u0101j"
    ],
    "wof:name":"Qarah Aghaj",
    "wof:placetype":"locality"
},
  "geometry": {"coordinates":[56.64483000000001,38.14579000000001],"type":"Point"}
}