{
  "type": "Feature",
  "properties": {
    "gn:admin1_code":"5.0",
    "gn:asciiname":"`Ana'",
    "gn:country_code":"IR",
    "gn:dem":1025,
    "gn:feature_class":"P",
    "gn:feature_code":"PPL",
    "gn:name":"\u2018An\u0101\u2019",
    "gn:population":0,
    "gn:timezone":"Asia/Tehran",
    "iso:country":"IR",
    "name:fas_x_preferred":[
        "\u2018An\u0101\u2019"
    ],
    "name:fas_x_variant":[
        "\u0639\u064e\u0646\u0651\u0627",
        "\u0639\u0646\u0627\u0621",
        "\u0627\u064e\u0646\u0627",
        "\u2018Ann\u0101"
    ],
    "name:und_x_variant":[
        "An\u0101"
    ],
    "wof:name":"`Ana'",
    "wof:placetype":"locality"
},
  "geometry": {"coordinates":[51.23957,30.41403],"type":"Point"}
}