{
  "type": "Feature",
  "properties": {
    "gn:admin1_code":"23",
    "gn:asciiname":"Kaleh Gavara",
    "gn:country_code":"IR",
    "gn:dem":1027,
    "gn:feature_class":"P",
    "gn:feature_code":"PPL",
    "gn:name":"Kaleh G\u0101var\u0101",
    "gn:population":0,
    "gn:timezone":"Asia/Tehran",
    "iso:country":"IR",
    "name:fas_x_preferred":[
        "Gel G\u016br\u0101"
    ],
    "name:fas_x_variant":[
        "\u06a9\u0644\u0647 \u06af\u0627\u0648\u0631\u0627",
        "\u06a9\u0644\u0647 \u06af\u0627\u0631\u06cc"
    ],
    "name:und_x_variant":[
        "Kaleh G\u0101var\u0101",
        "Kaleh G\u0101r\u012b"
    ],
    "wof:name":"Kaleh Gavara",
    "wof:placetype":"locality"
},
  "geometry": {"coordinates":[47.12588,33.42794],"type":"Point"}
}