{
  "type": "Feature",
  "properties": {
    "gn:admin1_code":"13",
    "gn:asciiname":"Lenjab",
    "gn:country_code":"IR",
    "gn:dem":1769,
    "gn:feature_class":"P",
    "gn:feature_code":"PPL",
    "gn:name":"Lenj\u0101b",
    "gn:population":0,
    "gn:timezone":"Asia/Tehran",
    "iso:country":"IR",
    "name:ceb_x_preferred":[
        "Lenj\u0101b"
    ],
    "name:fas_x_preferred":[
        "\u0644\u0646\u062c\u0627\u0628"
    ],
    "name:fas_x_variant":[
        "Lenj\u0101b"
    ],
    "name:swe_x_preferred":[
        "Lenj\u0101b"
    ],
    "name:und_x_variant":[
        "Lanj\u0101b"
    ],
    "wof:name":"Lenjab",
    "wof:placetype":"locality"
},
  "geometry": {"coordinates":[47.2828,34.8758],"type":"Point"}
}