{
  "type": "Feature",
  "properties": {
    "gn:admin1_code":"35",
    "gn:asciiname":"Kafshgar Kola",
    "gn:country_code":"IR",
    "gn:dem":19,
    "gn:feature_class":"P",
    "gn:feature_code":"PPL",
    "gn:name":"Kafshgar Kol\u0101",
    "gn:population":0,
    "gn:timezone":"Asia/Tehran",
    "iso:country":"IR",
    "name:fas_x_preferred":[
        "\u0643\u064e\u0641\u0634\u06af\u064e\u0631 \u0643\u064f\u0644\u0627\u06cc \u0627\u064e\u0631\u0637\u0650\u0647"
    ],
    "name:fas_x_variant":[
        "Kafshgar Kol\u0101-ye Ar\u0163eh",
        "Kafshgar Kol\u0101",
        "\u0643\u0641\u0634\u06af\u0631 \u0643\u0644\u0627"
    ],
    "wof:name":"Kafshgar Kola",
    "wof:placetype":"locality"
},
  "geometry": {"coordinates":[52.95143,36.5014],"type":"Point"}
}