{
  "type": "Feature",
  "properties": {
    "gn:admin1_code":"29",
    "gn:asciiname":"Dasht-e Shaqin",
    "gn:country_code":"IR",
    "gn:dem":2893,
    "gn:feature_class":"P",
    "gn:feature_code":"PPL",
    "gn:name":"Dasht-e Shaq\u012bn",
    "gn:population":0,
    "gn:timezone":"Asia/Tehran",
    "iso:country":"IR",
    "name:fas_x_preferred":[
        "Dasht-e Shaq\u012bn"
    ],
    "name:fas_x_variant":[
        "Dasht-e Shagh\u012bn",
        "\u062f\u0634\u062a \u0634\u0642\u06cc\u0646"
    ],
    "name:und_x_variant":[
        "Sagh\u012bn",
        "Dasht-e Shaq\u012b",
        "Dasht-i-Shaghin",
        "Dasht Sheq\u012b",
        "\u062f\u0634\u062a \u0634\u0642\u06cc\u0646"
    ],
    "wof:name":"Dasht-e Shaqin",
    "wof:placetype":"locality"
},
  "geometry": {"coordinates":[57.30963000000001,29.36078],"type":"Point"}
}