{
  "type": "Feature",
  "properties": {
    "gn:admin1_code":"8",
    "gn:asciiname":"Fathollah Mahalleh-e Haviq",
    "gn:country_code":"IR",
    "gn:dem":342,
    "gn:feature_class":"P",
    "gn:feature_code":"PPL",
    "gn:name":"Fat\u1e29oll\u0101h Ma\u1e29alleh-e \u1e28av\u012bq",
    "gn:population":0,
    "gn:timezone":"Asia/Tehran",
    "iso:country":"IR",
    "name:fas_x_preferred":[
        "Fat\u1e29oll\u0101h Ma\u1e29alleh-e \u1e28av\u012bq"
    ],
    "wof:name":"Fathollah Mahalleh-e Haviq",
    "wof:placetype":"locality"
},
  "geometry": {"coordinates":[48.83333,38.11667],"type":"Point"}
}