{
  "type": "Feature",
  "properties": {
    "gn:admin1_code":"13",
    "gn:asciiname":"Mohammadi-ye Sofla",
    "gn:country_code":"IR",
    "gn:dem":991,
    "gn:feature_class":"P",
    "gn:feature_code":"PPL",
    "gn:name":"Mo\u1e29ammad\u012b-ye Sofl\u00e1",
    "gn:population":0,
    "gn:timezone":"Asia/Tehran",
    "iso:country":"IR",
    "name:ara_x_preferred":[
        "\u0645\u062d\u0645\u062f\u064a \u0633\u0641\u0644\u064a"
    ],
    "name:ceb_x_preferred":[
        "Mo\u1e29ammad\u012b-ye Sofl\u00e1"
    ],
    "name:fas_x_preferred":[
        "\u0645\u062d\u0645\u0651\u062f\u06cc \u0633\u0641\u0644\u06cc"
    ],
    "name:fas_x_variant":[
        "Mo\u1e29ammad\u012b-ye Sofl\u00e1",
        "\u0645\u062d\u0645\u062f\u06cc \u0633\u0641\u0644\u06cc"
    ],
    "name:swe_x_preferred":[
        "Mo\u1e29ammad\u012b-ye Sofl\u00e1"
    ],
    "wof:name":"Mohammadi-ye Sofla",
    "wof:placetype":"locality"
},
  "geometry": {"coordinates":[46.0685,34.2079],"type":"Point"}
}