{
  "type": "Feature",
  "properties": {
    "gn:admin1_code":"10",
    "gn:asciiname":"Cheshmeh-ye Nurollah",
    "gn:country_code":"IR",
    "gn:dem":1277,
    "gn:feature_class":"P",
    "gn:feature_code":"PPL",
    "gn:name":"Cheshmeh-ye N\u016broll\u0101h",
    "gn:population":0,
    "gn:timezone":"Asia/Tehran",
    "iso:country":"IR",
    "name:fas_x_preferred":[
        "\u0686\u0650\u0634\u0645\u0650\u06c0 \u0646\u0648\u0631 \u0627\u0644\u0644\u064e\u0651\u0647"
    ],
    "name:fas_x_variant":[
        "Cheshmeh-ye N\u016broll\u0101h"
    ],
    "wof:name":"Cheshmeh-ye Nurollah",
    "wof:placetype":"locality"
},
  "geometry": {"coordinates":[46.51667,33.76667],"type":"Point"}
}