{
  "type": "Feature",
  "properties": {
    "gn:admin1_code":"42",
    "gn:asciiname":"Kuy-e Gorgani",
    "gn:country_code":"IR",
    "gn:dem":998,
    "gn:feature_class":"P",
    "gn:feature_code":"PPL",
    "gn:name":"K\u016by-e Gorg\u0101n\u012b",
    "gn:population":0,
    "gn:timezone":"Asia/Tehran",
    "iso:country":"IR",
    "name:fas_x_preferred":[
        "K\u016by-e Gorg\u0101n\u012b"
    ],
    "wof:name":"Kuy-e Gorgani",
    "wof:placetype":"locality"
},
  "geometry": {"coordinates":[59.58278000000001,36.32472],"type":"Point"}
}