{
  "type": "Feature",
  "properties": {
    "gn:admin1_code":"7.0",
    "gn:asciiname":"Lucha",
    "gn:country_code":"IR",
    "gn:dem":1094,
    "gn:feature_class":"P",
    "gn:feature_code":"PPL",
    "gn:name":"L\u016bch\u0101",
    "gn:population":0,
    "gn:timezone":"Asia/Tehran",
    "iso:country":"IR",
    "name:ast_x_preferred":[
        "Llucha"
    ],
    "name:ceb_x_preferred":[
        "Lucha"
    ],
    "name:deu_x_preferred":[
        "Lucha"
    ],
    "name:fas_x_preferred":[
        "L\u016bch\u0101"
    ],
    "name:fas_x_variant":[
        "\u0644\u0648\u0686\u0627"
    ],
    "name:spa_x_preferred":[
        "Lucha"
    ],
    "name:und_x_variant":[
        "\u0644\u0648\u0686\u0627"
    ],
    "wof:name":"Lucha",
    "wof:placetype":"locality"
},
  "geometry": {"coordinates":[51.29102,30.09445],"type":"Point"}
}