{
  "type": "Feature",
  "properties": {
    "gn:admin1_code":"42.0",
    "gn:asciiname":"Qal`eh Gak",
    "gn:country_code":"IR",
    "gn:dem":1039,
    "gn:feature_class":"P",
    "gn:feature_code":"PPL",
    "gn:name":"Qal\u2018eh Gak",
    "gn:population":0,
    "gn:timezone":"Asia/Tehran",
    "iso:country":"IR",
    "name:fas_x_preferred":[
        "\u0642\u0644\u0639\u0647 \u06af\u06a9"
    ],
    "name:fas_x_variant":[
        "Qal\u2018eh Gak"
    ],
    "name:und_x_variant":[
        "Ghal\u2019eh Kek"
    ],
    "wof:name":"Qal`eh Gak",
    "wof:placetype":"locality"
},
  "geometry": {"coordinates":[60.88907,35.31426],"type":"Point"}
}