{
  "type": "Feature",
  "properties": {
    "gn:admin1_code":"4.0",
    "gn:asciiname":"Ziaratgah-e Hazrat-e `Abbas",
    "gn:country_code":"IR",
    "gn:dem":475,
    "gn:feature_class":"P",
    "gn:feature_code":"PPL",
    "gn:name":"Z\u012b\u0101ratg\u0101h-e \u1e28a\u1e95rat-e \u2018Abb\u0101s",
    "gn:population":0,
    "gn:timezone":"Asia/Tehran",
    "iso:country":"IR",
    "name:fas_x_preferred":[
        "\u0632\u064a\u0627\u0631\u062b\u06af\u0627\u0647 \u062d\u0636\u0631\u062a \u0639\u0628\u0651\u0627\u0633"
    ],
    "name:fas_x_variant":[
        "Z\u012b\u0101ratg\u0101h-e \u1e28a\u1e95rat-e \u2018Abb\u0101s"
    ],
    "wof:name":"Ziaratgah-e Hazrat-e `Abbas",
    "wof:placetype":"locality"
},
  "geometry": {"coordinates":[61.55,31.2833],"type":"Point"}
}