{
  "type": "Feature",
  "properties": {
    "gn:admin1_code":"29.0",
    "gn:asciiname":"`Ameriyeh",
    "gn:country_code":"IR",
    "gn:dem":2000,
    "gn:feature_class":"P",
    "gn:feature_code":"PPL",
    "gn:name":"\u2018\u0100mer\u012byeh",
    "gn:population":0,
    "gn:timezone":"Asia/Tehran",
    "iso:country":"IR",
    "name:fas_x_preferred":[
        "\u0639\u0627\u0645\u0631\u06cc\u0647"
    ],
    "name:fas_x_variant":[
        "\u2018\u0100mer\u012byeh"
    ],
    "name:und_x_variant":[
        "Am\u012br\u0101b\u0101d"
    ],
    "wof:name":"`Ameriyeh",
    "wof:placetype":"locality"
},
  "geometry": {"coordinates":[57.63,29.5076],"type":"Point"}
}