{
  "type": "Feature",
  "properties": {
    "gn:admin1_code":"4.0",
    "gn:asciiname":"Karim Golzar",
    "gn:country_code":"IR",
    "gn:dem":486,
    "gn:feature_class":"P",
    "gn:feature_code":"PPL",
    "gn:name":"Kar\u012bm Golz\u0101r",
    "gn:population":0,
    "gn:timezone":"Asia/Tehran",
    "iso:country":"IR",
    "name:fas_x_preferred":[
        "\u06a9\u0631\u06cc\u0645 \u06af\u0644\u0632\u0627\u0631"
    ],
    "name:fas_x_variant":[
        "Kar\u012bm Golz\u0101r"
    ],
    "wof:name":"Karim Golzar",
    "wof:placetype":"locality"
},
  "geometry": {"coordinates":[61.7384,31.0998],"type":"Point"}
}