{
  "type": "Feature",
  "properties": {
    "gn:admin1_code":"0",
    "gn:asciiname":"Terish",
    "gn:country_code":"IR",
    "gn:dem":1314,
    "gn:feature_class":"P",
    "gn:feature_code":"PPL",
    "gn:name":"Ter\u012bsh",
    "gn:population":0,
    "gn:timezone":"Asia/Tehran",
    "iso:country":"IR",
    "name:ara_x_preferred":[
        "\u062a\u0631\u064a\u0634"
    ],
    "name:fas_x_preferred":[
        "\u062a\u0631\u06cc\u0634"
    ],
    "name:fas_x_variant":[
        "Ter\u012bsh"
    ],
    "name:msa_x_preferred":[
        "Terish"
    ],
    "wof:name":"Terish",
    "wof:placetype":"locality"
},
  "geometry": {"coordinates":[57.7838,26.9256],"type":"Point"}
}