{
  "type": "Feature",
  "properties": {
    "gn:admin1_code":"29",
    "gn:asciiname":"Zahru'iyeh-ye Borz",
    "gn:country_code":"IR",
    "gn:dem":2577,
    "gn:feature_class":"P",
    "gn:feature_code":"PPLF",
    "gn:name":"Zahr\u016b\u2019\u012byeh-ye Borz",
    "gn:population":0,
    "gn:timezone":"Asia/Tehran",
    "iso:country":"IR",
    "name:fas_x_preferred":[
        "\u0632\u0647\u0631\u0648\u0626\u06cc\u0647 \u0639\u0644\u06cc\u0627"
    ],
    "name:fas_x_variant":[
        "Zahr\u016b\u2019\u012byeh-ye \u2018Oly\u0101",
        "\u0632\u0647\u0631\u0648\u0626\u06cc\u0647 \u0628\u0631\u0632",
        "\u0632\u0647\u0631\u0648\u0626\u06cc\u0647 \u0633\u0641\u0644\u06cc"
    ],
    "name:und_x_variant":[
        "Zahr\u016b\u2019\u012byeh-ye Borz",
        "Zahr\u016b\u2019\u012byeh-ye Sofl\u00e1"
    ],
    "wof:name":"Zahru'iyeh-ye Borz",
    "wof:placetype":"locality"
},
  "geometry": {"coordinates":[55.38106,30.41928],"type":"Point"}
}