{
  "type": "Feature",
  "properties": {
    "gn:admin1_code":"4.0",
    "gn:asciiname":"Khodadadabad",
    "gn:country_code":"IR",
    "gn:dem":1387,
    "gn:feature_class":"P",
    "gn:feature_code":"PPLF",
    "gn:name":"Khod\u0101d\u0101d\u0101b\u0101d",
    "gn:population":0,
    "gn:timezone":"Asia/Tehran",
    "iso:country":"IR",
    "name:fas_x_preferred":[
        "\u062e\u062f\u0627\u062f\u0627\u062f \u0622\u0628\u0627\u062f"
    ],
    "name:fas_x_variant":[
        "Khod\u0101d\u0101d\u0101b\u0101d"
    ],
    "wof:name":"Khodadadabad",
    "wof:placetype":"locality"
},
  "geometry": {"coordinates":[61.25946,28.1756],"type":"Point"}
}