{
  "type": "Feature",
  "properties": {
    "gn:admin1_code":"44",
    "gn:asciiname":"Kalleh-ye Bahram",
    "gn:country_code":"IR",
    "gn:dem":1173,
    "gn:feature_class":"P",
    "gn:feature_code":"PPL",
    "gn:name":"Kalleh-ye Bahr\u0101m",
    "gn:population":0,
    "gn:timezone":"Asia/Tehran",
    "iso:country":"IR",
    "name:fas_x_preferred":[
        "\u0643\u0644\u0647 \u0628\u0647\u0631\u0627\u0645"
    ],
    "name:fas_x_variant":[
        "Koleh Bahr\u0101m",
        "Kalleh-ye Bahr\u0101m",
        "\u06a9\u0644\u0647 \u0628\u0647\u0631\u0627\u0645"
    ],
    "name:msa_x_preferred":[
        "Kalleh-ye Bahram"
    ],
    "name:und_x_variant":[
        "Qal\u2018eh Bahr\u0101m",
        "Qal\u2018eh-ye Bahr\u0101m"
    ],
    "wof:name":"Kalleh-ye Bahram",
    "wof:placetype":"locality"
},
  "geometry": {"coordinates":[50.4989,35.9881],"type":"Point"}
}