{
  "type": "Feature",
  "properties": {
    "gn:admin1_code":"13",
    "gn:asciiname":"Dar Derafsh-e Ebrahim Beygi",
    "gn:country_code":"IR",
    "gn:dem":1317,
    "gn:feature_class":"P",
    "gn:feature_code":"PPL",
    "gn:name":"D\u0101r Derafsh-e Ebr\u0101h\u012bm Beyg\u012b",
    "gn:population":0,
    "gn:timezone":"Asia/Tehran",
    "iso:country":"IR",
    "name:ceb_x_preferred":[
        "D\u0101r Derafsh-e Ebr\u0101h\u012bm Beyg\u012b"
    ],
    "name:fas_x_preferred":[
        "\u062f\u0627\u0631\u062f\u0631\u0641\u0634 \u0627\u0628\u0631\u0627\u0647\u06cc\u0645 \u0628\u06cc\u06af\u06cc"
    ],
    "name:fas_x_variant":[
        "D\u0101r Derafsh-e Ebr\u0101h\u012bm Beyg\u012b",
        "\u062f\u0627\u0631\u062f\u0631\u0641\u0634 \u0627\u0628\u0631\u0627\u0647\u06cc\u0645\u200c\u0628\u06cc\u06af\u06cc"
    ],
    "name:swe_x_preferred":[
        "D\u0101r Derafsh-e Ebr\u0101h\u012bm Beyg\u012b"
    ],
    "wof:name":"Dar Derafsh-e Ebrahim Beygi",
    "wof:placetype":"locality"
},
  "geometry": {"coordinates":[46.7915,34.5025],"type":"Point"}
}