{
  "type": "Feature",
  "properties": {
    "gn:admin1_code":"38.0",
    "gn:asciiname":"Lotar",
    "gn:country_code":"IR",
    "gn:dem":1865,
    "gn:feature_class":"P",
    "gn:feature_code":"PPL",
    "gn:name":"Lo\u0163ar",
    "gn:population":0,
    "gn:timezone":"Asia/Tehran",
    "iso:country":"IR",
    "name:fas_x_preferred":[
        "\u0644\u0637\u0631"
    ],
    "name:fas_x_variant":[
        "Lo\u0163ar",
        "\u0644\u062a\u0631"
    ],
    "name:und_x_variant":[
        "\u0644\u062a\u0631"
    ],
    "wof:name":"Lotar",
    "wof:placetype":"locality"
},
  "geometry": {"coordinates":[50.28224,36.59198],"type":"Point"}
}