{
  "type": "Feature",
  "properties": {
    "gn:admin1_code":"26",
    "gn:asciiname":"Barg-e Jahan",
    "gn:country_code":"IR",
    "gn:dem":2001,
    "gn:feature_class":"P",
    "gn:feature_code":"PPL",
    "gn:name":"Barg-e Jah\u0101n",
    "gn:population":0,
    "gn:timezone":"Asia/Tehran",
    "iso:country":"IR",
    "name:ceb_x_preferred":[
        "Barg-e Jah\u0101n"
    ],
    "name:fas_x_preferred":[
        "\u0628\u0631\u06af \u062c\u0647\u0627\u0646"
    ],
    "name:fas_x_variant":[
        "\u0628\u064e\u0641\u0643\u0650\u062c\u064e\u0646",
        "Barg-e Jah\u0101n"
    ],
    "name:swe_x_preferred":[
        "Barg-e Jah\u0101n"
    ],
    "name:und_x_variant":[
        "Bafkijan",
        "Bafkejan"
    ],
    "wof:name":"Barg-e Jahan",
    "wof:placetype":"locality"
},
  "geometry": {"coordinates":[51.7337,35.8433],"type":"Point"}
}