{
  "type": "Feature",
  "properties": {
    "gn:admin1_code":"7",
    "gn:asciiname":"Zarakabad",
    "gn:cc2":"IR",
    "gn:country_code":"IR",
    "gn:dem":1458,
    "gn:feature_class":"P",
    "gn:feature_code":"PPL",
    "gn:name":"Zarak\u0101b\u0101d",
    "gn:population":0,
    "gn:timezone":"Asia/Tehran",
    "iso:country":"IR",
    "name:fas_x_preferred":[
        "Zarak\u0101b\u0101d"
    ],
    "name:und_x_variant":[
        "Zark\u0101b\u0101d"
    ],
    "wof:name":"Zarakabad",
    "wof:placetype":"locality"
},
  "geometry": {"coordinates":[53.86528000000001,28.40694],"type":"Point"}
}