{
  "type": "Feature",
  "properties": {
    "gn:admin1_code":"41",
    "gn:asciiname":"Gukchin",
    "gn:country_code":"IR",
    "gn:dem":2024,
    "gn:feature_class":"P",
    "gn:feature_code":"PPL",
    "gn:name":"G\u016bkch\u012bn",
    "gn:population":0,
    "gn:timezone":"Asia/Tehran",
    "iso:country":"IR",
    "name:ara_x_preferred":[
        "\u063a\u0648\u063a\u062a\u0634\u064a\u0646"
    ],
    "name:ceb_x_preferred":[
        "G\u016bgch\u012bn"
    ],
    "name:fas_x_preferred":[
        "\u06af\u0648\u06af\u0686\u06cc\u0646"
    ],
    "name:fas_x_variant":[
        "G\u016bgch\u012bn",
        "\u06af\u0648\u06a9\u0686\u06cc\u0646"
    ],
    "name:swe_x_preferred":[
        "G\u016bgch\u012bn"
    ],
    "name:und_x_variant":[
        "G\u016bgch\u012b",
        "Gukchin",
        "G\u016bkch\u012bn"
    ],
    "wof:name":"Gukchin",
    "wof:placetype":"locality"
},
  "geometry": {"coordinates":[59.55284,33.07201],"type":"Point"}
}