{
  "type": "Feature",
  "properties": {
    "gn:admin1_code":"34",
    "gn:asciiname":"Nur `Ali Beyg",
    "gn:country_code":"IR",
    "gn:dem":1157,
    "gn:feature_class":"P",
    "gn:feature_code":"PPL",
    "gn:name":"N\u016br \u2018Al\u012b Beyg",
    "gn:population":0,
    "gn:timezone":"Asia/Tehran",
    "iso:country":"IR",
    "name:fas_x_preferred":[
        "\u0646\u0648\u0631 \u0639\u0644\u06cc \u0628\u064a\u06af"
    ],
    "name:fas_x_variant":[
        "N\u016br \u2018Al\u012b Beyg"
    ],
    "name:und_x_variant":[
        "N\u016br \u2018Al\u012b Beg"
    ],
    "wof:name":"Nur `Ali Beyg",
    "wof:placetype":"locality"
},
  "geometry": {"coordinates":[50.2899,35.0526],"type":"Point"}
}