{
  "type": "Feature",
  "properties": {
    "gn:admin1_code":"22.0",
    "gn:asciiname":"Malurik",
    "gn:country_code":"IR",
    "gn:dem":33,
    "gn:feature_class":"P",
    "gn:feature_code":"PPL",
    "gn:name":"Mal\u016br\u012bk",
    "gn:population":0,
    "gn:timezone":"Asia/Tehran",
    "iso:country":"IR",
    "name:fas_x_preferred":[
        "\u0645\u0644\u0648\u0631\u064a\u06a9"
    ],
    "name:fas_x_variant":[
        "\u0645\u0644\u0628\u0627\u0631\u06cc\u06a9"
    ],
    "name:und_x_variant":[
        "Mal\u016br\u012bk",
        "Malb\u0101r\u012bk"
    ],
    "wof:name":"Malurik",
    "wof:placetype":"locality"
},
  "geometry": {"coordinates":[51.14983,28.91637],"type":"Point"}
}