{
  "type": "Feature",
  "properties": {
    "gn:admin1_code":"29",
    "gn:asciiname":"Labidu",
    "gn:country_code":"IR",
    "gn:dem":2532,
    "gn:feature_class":"P",
    "gn:feature_code":"PPL",
    "gn:name":"L\u0101b\u012bd\u016b",
    "gn:population":0,
    "gn:timezone":"Asia/Tehran",
    "iso:country":"IR",
    "name:fas_x_preferred":[
        "Torsh K\u016bh"
    ],
    "name:fas_x_variant":[
        "\u0644\u0627\u0628\u064a\u062f\u0648",
        "\u062a\u0631\u0634\u06a9\u0648\u0647"
    ],
    "name:und_x_variant":[
        "L\u0101b\u012bd\u016b",
        "Torshk\u016bh"
    ],
    "wof:name":"Labidu",
    "wof:placetype":"locality"
},
  "geometry": {"coordinates":[55.23799,30.43777],"type":"Point"}
}