{
  "type": "Feature",
  "properties": {
    "gn:admin1_code":"9",
    "gn:asciiname":"Samen",
    "gn:country_code":"IR",
    "gn:dem":1855,
    "gn:feature_class":"P",
    "gn:feature_code":"PPL",
    "gn:name":"S\u0101men",
    "gn:population":0,
    "gn:timezone":"Asia/Tehran",
    "iso:country":"IR",
    "name:ara_x_preferred":[
        "\u0633\u0627\u0645\u0646"
    ],
    "name:aze_x_preferred":[
        "Samin"
    ],
    "name:ceb_x_preferred":[
        "S\u0101men"
    ],
    "name:fas_x_preferred":[
        "S\u0101men"
    ],
    "name:fas_x_variant":[
        "S\u0101man",
        "\u0633\u0627\u0645\u0646"
    ],
    "name:ita_x_preferred":[
        "Samen"
    ],
    "name:mlg_x_preferred":[
        "Samen"
    ],
    "name:msa_x_preferred":[
        "Samen"
    ],
    "name:swe_x_preferred":[
        "S\u0101men"
    ],
    "name:tur_x_preferred":[
        "Samen"
    ],
    "name:urd_x_preferred":[
        "\u0633\u0627\u0645\u0646"
    ],
    "wof:name":"Samen",
    "wof:placetype":"locality"
},
  "geometry": {"coordinates":[48.70513,34.20885],"type":"Point"}
}