{
  "type": "Feature",
  "properties": {
    "gn:admin1_code":"29",
    "gn:asciiname":"Zamin-e Barzrafi`abad",
    "gn:country_code":"IR",
    "gn:dem":852,
    "gn:feature_class":"P",
    "gn:feature_code":"PPL",
    "gn:name":"Zam\u012bn-e Barzraf\u012b\u2018\u0101b\u0101d",
    "gn:population":0,
    "gn:timezone":"Asia/Tehran",
    "iso:country":"IR",
    "name:fas_x_preferred":[
        "\u0631\u0641\u06cc\u0639 \u0622\u0628\u0627\u062f"
    ],
    "name:fas_x_variant":[
        "Raf\u012b\u2018\u0101b\u0101d",
        "\u0632\u0645\u06cc\u0646 \u0628\u0631\u0632\u0631\u0641\u06cc\u0639 \u0622\u0628\u0627\u062f"
    ],
    "name:und_x_variant":[
        "Zam\u012bn-e Barzraf\u012b\u2018\u0101b\u0101d"
    ],
    "wof:name":"Zamin-e Barzrafi`abad",
    "wof:placetype":"locality"
},
  "geometry": {"coordinates":[58.51545,28.89155],"type":"Point"}
}