{
  "type": "Feature",
  "properties": {
    "gn:admin1_code":"8",
    "gn:asciiname":"Shiri Hayati",
    "gn:country_code":"IR",
    "gn:dem":400,
    "gn:feature_class":"P",
    "gn:feature_code":"PPL",
    "gn:name":"Sh\u012br\u012b \u1e28ay\u0101\u0163\u012b",
    "gn:population":0,
    "gn:timezone":"Asia/Tehran",
    "iso:country":"IR",
    "name:fas_x_preferred":[
        "\u0634\u06cc\u0631\u06cc \u062d\u06cc\u0627\u0637\u06cc"
    ],
    "name:fas_x_variant":[
        "Sh\u012br\u012b \u1e28ay\u0101\u0163\u012b"
    ],
    "wof:name":"Shiri Hayati",
    "wof:placetype":"locality"
},
  "geometry": {"coordinates":[48.7703,38.2876],"type":"Point"}
}