{
  "type": "Feature",
  "properties": {
    "gn:admin1_code":"33",
    "gn:asciiname":"Aqa Baba-ye Faramarzi",
    "gn:country_code":"IR",
    "gn:dem":1716,
    "gn:feature_class":"P",
    "gn:feature_code":"PPL",
    "gn:name":"\u0100q\u0101 B\u0101b\u0101-ye Far\u0101marz\u012b",
    "gn:population":0,
    "gn:timezone":"Asia/Tehran",
    "iso:country":"IR",
    "name:azb_x_preferred":[
        "\u0622\u0642\u0627\u0628\u0627\u0628\u0627\u0641\u0631\u0627\u0645\u0631\u0632\u06cc"
    ],
    "name:ceb_x_preferred":[
        "\u0100q\u0101 B\u0101b\u0101-ye Far\u0101marz\u012b"
    ],
    "name:fas_x_preferred":[
        "\u0622\u0642\u0627 \u0628\u0627\u0628\u0627\u06cc \u0641\u0631\u0627\u0645\u064e\u0631\u0632\u06cc"
    ],
    "name:fas_x_variant":[
        "\u0622\u0642\u0627 \u0628\u0627\u0628\u0627\u06cc \u0641\u0631\u0627\u0645\u0631\u0632\u06cc",
        "\u0100q\u0101 B\u0101b\u0101-ye Fr\u0101marz\u012b",
        "\u0100q\u0101 B\u0101b\u0101-ye Far\u0101marz\u012b",
        "\u0622\u0642\u0627\u0628\u0627\u0628\u0627\u0641\u0631\u0627\u0645\u0631\u0632\u06cc"
    ],
    "name:msa_x_preferred":[
        "Aqa Baba-ye Faramarzi"
    ],
    "name:swe_x_preferred":[
        "\u0100q\u0101 B\u0101b\u0101-ye Far\u0101marz\u012b"
    ],
    "wof:name":"Aqa Baba-ye Faramarzi",
    "wof:placetype":"locality"
},
  "geometry": {"coordinates":[46.5465,38.5231],"type":"Point"}
}