{
  "type": "Feature",
  "properties": {
    "gn:admin1_code":"11",
    "gn:asciiname":"Qavamabad",
    "gn:cc2":"IR",
    "gn:country_code":"IR",
    "gn:dem":673,
    "gn:feature_class":"P",
    "gn:feature_code":"PPL",
    "gn:name":"Qav\u0101m\u0101b\u0101d",
    "gn:population":0,
    "gn:timezone":"Asia/Tehran",
    "iso:country":"IR",
    "name:fas_x_preferred":[
        "\u0642\u064e\u0648\u0627\u0645 \u0622\u0628\u0627\u062f"
    ],
    "name:fas_x_variant":[
        "Qav\u0101m\u0101b\u0101d"
    ],
    "name:und_x_variant":[
        "Qaww\u0101m\u0101b\u0101d"
    ],
    "wof:name":"Qavamabad",
    "wof:placetype":"locality"
},
  "geometry": {"coordinates":[55.41667,28.11667000000001],"type":"Point"}
}