{
  "type": "Feature",
  "properties": {
    "gn:admin1_code":"7",
    "gn:asciiname":"Sisnian",
    "gn:country_code":"IR",
    "gn:dem":1623,
    "gn:feature_class":"P",
    "gn:feature_code":"PPL",
    "gn:name":"S\u012bsn\u012b\u0101n",
    "gn:population":0,
    "gn:timezone":"Asia/Tehran",
    "iso:country":"IR",
    "name:fas_x_preferred":[
        "Sesn\u012b\u0101n"
    ],
    "name:fas_x_variant":[
        "S\u012bsn\u012b\u0101n",
        "\u0633\u0633\u0646\u06cc\u0627\u0646",
        "\u0633\u06cc\u0633\u0646\u06cc\u0627\u0646"
    ],
    "name:und_x_variant":[
        "\u0633\u0633\u0646\u06cc\u0627\u0646"
    ],
    "wof:name":"Sisnian",
    "wof:placetype":"locality"
},
  "geometry": {"coordinates":[52.40614,30.02588],"type":"Point"}
}