{
  "type": "Feature",
  "properties": {
    "gn:admin1_code":"34",
    "gn:asciiname":"Lowzdar-e `Olya",
    "gn:country_code":"IR",
    "gn:dem":2103,
    "gn:feature_class":"P",
    "gn:feature_code":"PPL",
    "gn:name":"Lowzdar-e \u2018Oly\u0101",
    "gn:population":0,
    "gn:timezone":"Asia/Tehran",
    "iso:country":"IR",
    "name:fas_x_preferred":[
        "\u0644\u0648\u0632\u062f\u0631 \u0628\u0627\u0644\u0627"
    ],
    "name:fas_x_variant":[
        "L\u016bzdar-e \u2018Oly\u0101",
        "L\u016bzdarb\u0101",
        "Lowzdar-e B\u0101l\u0101",
        "\u0644\u0648\u0632\u062f\u0631 \u0639\u0644\u06cc\u0627"
    ],
    "name:und_x_variant":[
        "Nuzd\u0101r",
        "Luzdar",
        "Lowzdar",
        "Lowzdar-e \u2018Oly\u0101"
    ],
    "wof:name":"Lowzdar-e `Olya",
    "wof:placetype":"locality"
},
  "geometry": {"coordinates":[49.31573,33.72894],"type":"Point"}
}