{
  "type": "Feature",
  "properties": {
    "gn:admin1_code":"4.0",
    "gn:asciiname":"Yar Mohammad Bazar",
    "gn:country_code":"IR",
    "gn:dem":33,
    "gn:feature_class":"P",
    "gn:feature_code":"PPL",
    "gn:name":"Y\u0101r Mo\u1e29ammad B\u0101z\u0101r",
    "gn:population":0,
    "gn:timezone":"Asia/Tehran",
    "iso:country":"IR",
    "name:ara_x_preferred":[
        "\u064a\u0627\u0631\u0645\u062d\u0645\u062f\u0628\u0627\u0632\u0627\u0631"
    ],
    "name:fas_x_preferred":[
        "Y\u0101r Mo\u1e29ammad B\u0101z\u0101r"
    ],
    "name:fas_x_variant":[
        "\u06cc\u0627\u0631 \u0645\u062d\u0645\u062f \u0628\u0627\u0632\u0627\u0631",
        "\u06cc\u0627\u0631\u0645\u062d\u0645\u062f\u0628\u0627\u0632\u0627\u0631"
    ],
    "name:und_x_variant":[
        "\u06cc\u0627\u0631 \u0645\u062d\u0645\u062f \u0628\u0627\u0632\u0627\u0631"
    ],
    "name:urd_x_preferred":[
        "\u06cc\u0627\u0631 \u0645\u062d\u0645\u062f \u0628\u0627\u0632\u0627\u0631"
    ],
    "wof:name":"Yar Mohammad Bazar",
    "wof:placetype":"locality"
},
  "geometry": {"coordinates":[61.08521,25.58285],"type":"Point"}
}