{
  "type": "Feature",
  "properties": {
    "gn:admin1_code":"33",
    "gn:asciiname":"Aydinlu",
    "gn:country_code":"IR",
    "gn:dem":1209,
    "gn:elevation":"0.0",
    "gn:feature_class":"P",
    "gn:feature_code":"PPL",
    "gn:name":"\u0100yd\u012bnl\u016b",
    "gn:population":0,
    "gn:timezone":"Asia/Tehran",
    "iso:country":"IR",
    "name:ara_x_preferred":[
        "\u0623\u064a\u062f\u064a\u0646 \u0644\u0648"
    ],
    "name:azb_x_preferred":[
        "\u0622\u06cc\u062f\u06cc\u0646\u200c\u0644\u0648"
    ],
    "name:fas_x_preferred":[
        "\u0622\u06cc\u062f\u06cc\u0646 \u0644\u0648"
    ],
    "name:fas_x_variant":[
        "\u0100yd\u012bnl\u016b",
        "\u0622\u06cc\u062f\u06cc\u0646\u200c\u0644\u0648"
    ],
    "name:msa_x_preferred":[
        "Aydinlu"
    ],
    "wof:name":"Aydinlu",
    "wof:placetype":"locality"
},
  "geometry": {"coordinates":[47.3146,38.666],"type":"Point"}
}