{
  "type": "Feature",
  "properties": {
    "gn:admin1_code":"23",
    "gn:asciiname":"Balut Ban",
    "gn:country_code":"IR",
    "gn:dem":1195,
    "gn:feature_class":"P",
    "gn:feature_code":"PPL",
    "gn:name":"Bal\u016b\u0163 B\u0101n",
    "gn:population":0,
    "gn:timezone":"Asia/Tehran",
    "iso:country":"IR",
    "name:fas_x_preferred":[
        "\u0628\u0644\u0648\u0637 \u0628\u0627\u0646"
    ],
    "name:und_x_variant":[
        "Bal\u016b\u0163 B\u0101n"
    ],
    "wof:name":"Balut Ban",
    "wof:placetype":"locality"
},
  "geometry": {"coordinates":[47.8035,33.7286],"type":"Point"}
}