{
  "type": "Feature",
  "properties": {
    "gn:admin1_code":"32",
    "gn:asciiname":"Qezel Gusheh Qeshlaq",
    "gn:country_code":"IR",
    "gn:dem":1118,
    "gn:feature_class":"P",
    "gn:feature_code":"PPLL",
    "gn:name":"Qezel G\u016bsheh Qeshl\u0101q",
    "gn:population":0,
    "gn:timezone":"Asia/Tehran",
    "iso:country":"IR",
    "name:fas_x_preferred":[
        "\u0642\u0632\u0644 \u06af\u0648\u0634\u0647"
    ],
    "name:fas_x_variant":[
        "Qezel G\u016bsheh",
        "\u0642\u0632\u0644 \u06af\u0648\u0634\u0647 \u0642\u0634\u0644\u0627\u0642"
    ],
    "name:und_x_variant":[
        "Qezel G\u016bsheh Qeshl\u0101q"
    ],
    "wof:name":"Qezel Gusheh Qeshlaq",
    "wof:placetype":"locality"
},
  "geometry": {"coordinates":[47.8325,38.6894],"type":"Point"}
}