{
  "type": "Feature",
  "properties": {
    "gn:admin1_code":"1",
    "gn:asciiname":"Malekli",
    "gn:country_code":"IR",
    "gn:dem":1656,
    "gn:feature_class":"P",
    "gn:feature_code":"PPL",
    "gn:name":"Malekl\u012b",
    "gn:population":0,
    "gn:timezone":"Asia/Tehran",
    "iso:country":"IR",
    "name:fas_x_preferred":[
        "\u0645\u064e\u0644\u0650\u0643\u0644\u0648"
    ],
    "name:fas_x_variant":[
        "\u0645\u0644\u06a9\u0644\u06cc",
        "Malekl\u016b",
        "Malekl\u012b"
    ],
    "wof:name":"Malekli",
    "wof:placetype":"locality"
},
  "geometry": {"coordinates":[44.8108,39.007],"type":"Point"}
}