{
  "type": "Feature",
  "properties": {
    "gn:admin1_code":"25",
    "gn:asciiname":"Shamsabad",
    "gn:country_code":"IR",
    "gn:dem":1099,
    "gn:feature_class":"P",
    "gn:feature_code":"PPLF",
    "gn:name":"Shams\u0101b\u0101d",
    "gn:population":0,
    "gn:timezone":"Asia/Tehran",
    "iso:country":"IR",
    "name:fas_x_preferred":[
        "\u0634\u0645\u0633 \u0622\u0628\u0627\u062f"
    ],
    "name:fas_x_variant":[
        "Shams\u0101b\u0101d"
    ],
    "wof:name":"Shamsabad",
    "wof:placetype":"locality"
},
  "geometry": {"coordinates":[54.3967,36.1293],"type":"Point"}
}