{
  "type": "Feature",
  "properties": {
    "gn:admin1_code":"4.0",
    "gn:asciiname":"Kan",
    "gn:country_code":"IR",
    "gn:dem":881,
    "gn:feature_class":"P",
    "gn:feature_code":"PPL",
    "gn:name":"K\u0101n",
    "gn:population":0,
    "gn:timezone":"Asia/Tehran",
    "iso:country":"IR",
    "name:fas_x_preferred":[
        "\u06a9\u0627\u0646"
    ],
    "name:fas_x_variant":[
        "K\u0101n"
    ],
    "wof:name":"Kan",
    "wof:placetype":"locality"
},
  "geometry": {"coordinates":[61.23309,26.61041],"type":"Point"}
}