{
  "type": "Feature",
  "properties": {
    "gn:admin1_code":"4.0",
    "gn:asciiname":"Kan",
    "gn:country_code":"IR",
    "gn:dem":881,
    "gn:feature_class":"P",
    "gn:feature_code":"PPL",
    "gn:name":"K\u0101n",
    "gn:population":0,
    "gn:timezone":"Asia/Tehran",
    "iso:country":"IR",
    "name:bel_x_preferred":[
        "\u041a\u0430\u043d"
    ],
    "name:bre_x_preferred":[
        "Kan"
    ],
    "name:bul_x_preferred":[
        "\u041a\u0430\u043d"
    ],
    "name:cat_x_preferred":[
        "Kan"
    ],
    "name:ceb_x_preferred":[
        "Kan"
    ],
    "name:deu_x_preferred":[
        "Kan"
    ],
    "name:fas_x_preferred":[
        "\u06a9\u0627\u0646"
    ],
    "name:fas_x_variant":[
        "K\u0101n"
    ],
    "name:fra_x_preferred":[
        "Kan"
    ],
    "name:heb_x_preferred":[
        "\u05e7\u05d0\u05df"
    ],
    "name:kaz_x_preferred":[
        "\u041a\u0430\u043d"
    ],
    "name:mya_x_preferred":[
        "\u1000\u1014\u103a"
    ],
    "name:nld_x_preferred":[
        "Kan"
    ],
    "name:pol_x_preferred":[
        "Kan"
    ],
    "name:rus_x_preferred":[
        "\u041a\u0430\u043d"
    ],
    "name:slv_x_preferred":[
        "Kan"
    ],
    "name:spa_x_preferred":[
        "Kan"
    ],
    "name:srp_x_preferred":[
        "\u041a\u0430\u043d"
    ],
    "name:swe_x_preferred":[
        "Kan"
    ],
    "name:tur_x_preferred":[
        "Kan"
    ],
    "name:ukr_x_preferred":[
        "\u041a\u0430\u043d"
    ],
    "name:zho_x_preferred":[
        "Kan"
    ],
    "wof:name":"Kan",
    "wof:placetype":"locality"
},
  "geometry": {"coordinates":[61.23309,26.61041],"type":"Point"}
}