{
  "type": "Feature",
  "properties": {
    "gn:admin1_code":"33",
    "gn:asciiname":"Kalu",
    "gn:country_code":"IR",
    "gn:dem":1901,
    "gn:feature_class":"P",
    "gn:feature_code":"PPL",
    "gn:name":"Kal\u016b",
    "gn:population":0,
    "gn:timezone":"Asia/Tehran",
    "iso:country":"IR",
    "name:cat_x_preferred":[
        "Kalu"
    ],
    "name:ceb_x_preferred":[
        "Kalu"
    ],
    "name:deu_x_preferred":[
        "Kalu"
    ],
    "name:fas_x_preferred":[
        "\u06a9\u0644\u0648"
    ],
    "name:fas_x_variant":[
        "Kal\u016b"
    ],
    "name:fin_x_preferred":[
        "Kalu"
    ],
    "name:fra_x_preferred":[
        "Kalu"
    ],
    "name:rus_x_preferred":[
        "\u041a\u0430\u043b\u0443"
    ],
    "name:srp_x_preferred":[
        "\u041a\u0430\u043b\u0443"
    ],
    "name:swe_x_preferred":[
        "Kalu"
    ],
    "wof:name":"Kalu",
    "wof:placetype":"locality"
},
  "geometry": {"coordinates":[46.8952,37.8546],"type":"Point"}
}