{
  "type": "Feature",
  "properties": {
    "gn:admin1_code":"7",
    "gn:asciiname":"Zir-e Zard",
    "gn:country_code":"IR",
    "gn:dem":1122,
    "gn:feature_class":"P",
    "gn:feature_code":"PPL",
    "gn:name":"Z\u012br-e Zard",
    "gn:population":0,
    "gn:timezone":"Asia/Tehran",
    "iso:country":"IR",
    "name:fas_x_preferred":[
        "Z\u012br Zard-e \u2018Al\u012bsh\u0101h\u012b"
    ],
    "name:fas_x_variant":[
        "Z\u012br-e Zard",
        "\u0632\u06cc\u0631 \u0632\u0631\u062f"
    ],
    "name:und_x_variant":[
        "Z\u012br-e Zard",
        "Zir-e R\u016bd",
        "\u0632\u06cc\u0631 \u0632\u0631\u062f"
    ],
    "wof:name":"Zir-e Zard",
    "wof:placetype":"locality"
},
  "geometry": {"coordinates":[51.71278,30.18167],"type":"Point"}
}