{
  "type": "Feature",
  "properties": {
    "gn:admin1_code":"29",
    "gn:asciiname":"Dushan",
    "gn:country_code":"IR",
    "gn:dem":1115,
    "gn:feature_class":"P",
    "gn:feature_code":"PPLL",
    "gn:name":"D\u016bshan",
    "gn:population":0,
    "gn:timezone":"Asia/Tehran",
    "iso:country":"IR",
    "name:ceb_x_preferred":[
        "Dushan"
    ],
    "name:deu_x_preferred":[
        "Dushan"
    ],
    "name:fas_x_preferred":[
        "\u062f\u0648\u0634\u0646"
    ],
    "name:fas_x_variant":[
        "D\u016bshan",
        "\u0647\u06cc\u0631 \u06a9\u0644\u0627 \u06a9\u0648\u0646"
    ],
    "name:und_x_variant":[
        "H\u012br Kol\u0101 K\u016bn"
    ],
    "wof:name":"Dushan",
    "wof:placetype":"locality"
},
  "geometry": {"coordinates":[58.17337,26.86757],"type":"Point"}
}