{
  "type": "Feature",
  "properties": {
    "gn:admin1_code":"29",
    "gn:asciiname":"Hojjatabad-e Robat",
    "gn:country_code":"IR",
    "gn:dem":1652,
    "gn:feature_class":"P",
    "gn:feature_code":"PPL",
    "gn:name":"\u1e28ojjat\u0101b\u0101d-e Rob\u0101\u0163",
    "gn:population":0,
    "gn:timezone":"Asia/Tehran",
    "iso:country":"IR",
    "name:fas_x_preferred":[
        "\u062d\u062c\u062a \u0622\u0628\u0627\u062f \u0631\u0628\u0627\u0637"
    ],
    "name:fas_x_variant":[
        "\u1e28ojjat\u0101b\u0101d-e Rob\u0101\u0163"
    ],
    "wof:name":"Hojjatabad-e Robat",
    "wof:placetype":"locality"
},
  "geometry": {"coordinates":[56.5211,30.2692],"type":"Point"}
}