{
  "type": "Feature",
  "properties": {
    "gn:admin1_code":"23",
    "gn:asciiname":"Naveh Shiravand",
    "gn:country_code":"IR",
    "gn:dem":1299,
    "gn:feature_class":"P",
    "gn:feature_code":"PPL",
    "gn:name":"N\u0101veh Sh\u012br\u0101vand",
    "gn:population":0,
    "gn:timezone":"Asia/Tehran",
    "iso:country":"IR",
    "name:fas_x_preferred":[
        "\u0646\u0627\u0648\u0650\u06c0 \u0634\u064a\u0631\u0627\u0648\u064e\u0646\u062f"
    ],
    "name:fas_x_variant":[
        "\u0646\u0627\u0648\u0647 \u0634\u06cc\u0631\u0627\u0648\u0646\u062f",
        "\u0646\u0627\u0648\u0647 \u0634\u06cc\u0631\u0622\u0648\u0646\u062f",
        "\u0646\u0627\u0648\u0647 \u0628\u0633\u0627\u0637"
    ],
    "name:und_x_variant":[
        "N\u0101veh Sh\u012br\u0101vand",
        "N\u0101veh-ye Bes\u0101\u0163",
        "N\u0101veh Sh\u012bravand"
    ],
    "wof:name":"Naveh Shiravand",
    "wof:placetype":"locality"
},
  "geometry": {"coordinates":[47.4739,33.5144],"type":"Point"}
}