{
  "type": "Feature",
  "properties": {
    "gn:admin1_code":"4",
    "gn:asciiname":"Zimadan",
    "gn:country_code":"IR",
    "gn:dem":1383,
    "gn:feature_class":"P",
    "gn:feature_code":"PPL",
    "gn:name":"Z\u012bmad\u0101n",
    "gn:population":0,
    "gn:timezone":"Asia/Tehran",
    "iso:country":"IR",
    "name:fas_x_preferred":[
        "\u0632\u064a\u0645\u062f\u0627\u0646"
    ],
    "name:und_x_variant":[
        "Z\u012bmad\u0101n"
    ],
    "wof:name":"Zimadan",
    "wof:placetype":"locality"
},
  "geometry": {"coordinates":[60.9813,26.83749000000001],"type":"Point"}
}