{
  "type": "Feature",
  "properties": {
    "gn:admin1_code":"23",
    "gn:asciiname":"Choghabur-e Hajjiabad",
    "gn:country_code":"IR",
    "gn:dem":1087,
    "gn:feature_class":"P",
    "gn:feature_code":"PPL",
    "gn:name":"Chogh\u0101b\u016br-e H\u0101jj\u012b\u0101b\u0101d",
    "gn:population":0,
    "gn:timezone":"Asia/Tehran",
    "iso:country":"IR",
    "name:fas_x_preferred":[
        "\u0686\u063a\u0627\u0628\u0648\u0631 \u062d\u0627\u062c\u06cc \u0622\u0628\u0627\u062f"
    ],
    "name:fas_x_variant":[
        "\u0686\u063a\u0627\u0628\u0648\u0631 \u0639\u0627\u0644\u06cc \u0622\u0628\u0627\u062f"
    ],
    "name:und_x_variant":[
        "Chogh\u0101b\u016br-e H\u0101jj\u012b\u0101b\u0101d",
        "Chogh\u0101b\u016br-e \u2018\u0100l\u012b\u0101b\u0101d"
    ],
    "wof:name":"Choghabur-e Hajjiabad",
    "wof:placetype":"locality"
},
  "geometry": {"coordinates":[47.4766,33.2902],"type":"Point"}
}