{
  "type": "Feature",
  "properties": {
    "gn:admin1_code":"16.0",
    "gn:asciiname":"Al Darreh",
    "gn:country_code":"IR",
    "gn:dem":2021,
    "gn:feature_class":"P",
    "gn:feature_code":"PPL",
    "gn:name":"\u0100l Darreh",
    "gn:population":0,
    "gn:timezone":"Asia/Tehran",
    "iso:country":"IR",
    "name:fas_x_preferred":[
        "\u0622\u0644 \u062f\u0631\u0651\u0647"
    ],
    "name:fas_x_variant":[
        "\u0100l Darreh",
        "\u0627\u0644\u200c\u062f\u0631\u0647"
    ],
    "name:mzn_x_preferred":[
        "\u0627\u0644\u200c\u062f\u0631\u0647"
    ],
    "wof:name":"Al Darreh",
    "wof:placetype":"locality"
},
  "geometry": {"coordinates":[46.9711,35.6969],"type":"Point"}
}