{
  "type": "Feature",
  "properties": {
    "gn:admin1_code":"23",
    "gn:asciiname":"Amrabi-ye Musa Bak",
    "gn:country_code":"IR",
    "gn:dem":673,
    "gn:feature_class":"P",
    "gn:feature_code":"PPL",
    "gn:name":"Amr\u0101b\u012b-ye M\u016bs\u0101 Bak",
    "gn:population":0,
    "gn:timezone":"Asia/Tehran",
    "iso:country":"IR",
    "name:fas_x_preferred":[
        "\u0686\u0645 \u062e\u0632\u06cc\u0646\u0647"
    ],
    "name:fas_x_variant":[
        "Cham Khaz\u012bneh",
        "\u0627\u0645\u0631\u0627\u0628\u06cc \u0645\u0648\u0633\u06cc \u0628\u06a9"
    ],
    "name:und_x_variant":[
        "Amr\u0101b\u012b-ye M\u016bs\u0101 Bak"
    ],
    "wof:name":"Amrabi-ye Musa Bak",
    "wof:placetype":"locality"
},
  "geometry": {"coordinates":[47.1969,33.3361],"type":"Point"}
}