{
  "type": "Feature",
  "properties": {
    "gn:admin1_code":"35.0",
    "gn:asciiname":"Dadu Kola",
    "gn:country_code":"IR",
    "gn:dem":1261,
    "gn:feature_class":"P",
    "gn:feature_code":"PPL",
    "gn:name":"D\u0101d\u016b Kol\u0101",
    "gn:population":0,
    "gn:timezone":"Asia/Tehran",
    "iso:country":"IR",
    "name:ceb_x_preferred":[
        "D\u0101d\u016b Kol\u0101"
    ],
    "name:fas_x_preferred":[
        "\u062f\u0627\u0648\u0648\u062f \u0643\u064f\u0644\u0627"
    ],
    "name:fas_x_variant":[
        "\u062f\u0627\u062f\u0648 \u0643\u0644\u0627",
        "\u062f\u0627\u062f\u0648 \u0643\u0648\u0644\u0627",
        "\u062f\u0627\u062f\u0648 \u0643\u064e\u0644\u0627",
        "D\u0101v\u016bd Kol\u0101",
        "D\u0101d\u016b Kol\u0101",
        "\u062f\u0627\u062f\u0648\u06a9\u0644\u0627"
    ],
    "name:mzn_x_preferred":[
        "\u062f\u0627\u062f\u0648\u06a9\u0644\u0627"
    ],
    "name:swe_x_preferred":[
        "D\u0101d\u016b Kol\u0101"
    ],
    "name:und_x_variant":[
        "D\u0101d\u016b K\u016bl\u0101",
        "D\u0101d\u016b Kal\u0101"
    ],
    "wof:name":"Dadu Kola",
    "wof:placetype":"locality"
},
  "geometry": {"coordinates":[53.19712,36.0966],"type":"Point"}
}