{
  "type": "Feature",
  "properties": {
    "gn:admin1_code":"35",
    "gn:asciiname":"Kohneh Deh",
    "gn:country_code":"IR",
    "gn:dem":688,
    "gn:feature_class":"P",
    "gn:feature_code":"PPL",
    "gn:name":"Kohneh Deh",
    "gn:population":0,
    "gn:timezone":"Asia/Tehran",
    "iso:country":"IR",
    "name:ceb_x_preferred":[
        "Kohneh Deh"
    ],
    "name:fas_x_preferred":[
        "\u0643\u0647\u0646\u0647 \u062f\u0647"
    ],
    "name:swe_x_preferred":[
        "Kohneh Deh"
    ],
    "wof:name":"Kohneh Deh",
    "wof:placetype":"locality"
},
  "geometry": {"coordinates":[53.28377,36.17144],"type":"Point"}
}