{
  "type": "Feature",
  "properties": {
    "gn:admin1_code":"5",
    "gn:asciiname":"Ayuk",
    "gn:country_code":"IR",
    "gn:dem":1487,
    "gn:feature_class":"P",
    "gn:feature_code":"PPL",
    "gn:name":"Ay\u016bk",
    "gn:population":0,
    "gn:timezone":"Asia/Tehran",
    "iso:country":"IR",
    "name:fas_x_preferred":[
        "R\u016bd-e Ay\u016bk"
    ],
    "name:fas_x_variant":[
        "\u0631\u0648\u062f \u0627\u064a\u0648\u0643",
        "\u0627\u064a\u0648\u06a9"
    ],
    "name:und_x_variant":[
        "R\u016bd-e Ayy\u016bk",
        "Ay\u016bk"
    ],
    "wof:name":"Ayuk",
    "wof:placetype":"locality"
},
  "geometry": {"coordinates":[50.28096,31.26909],"type":"Point"}
}