{
  "type": "Feature",
  "properties": {
    "gn:admin1_code":"23",
    "gn:asciiname":"Cham Seydi-ye Sofla",
    "gn:country_code":"IR",
    "gn:dem":1670,
    "gn:feature_class":"P",
    "gn:feature_code":"PPL",
    "gn:name":"Cham \u015eeyd\u012b-ye Sofl\u00e1",
    "gn:population":0,
    "gn:timezone":"Asia/Tehran",
    "iso:country":"IR",
    "name:fas_x_preferred":[
        "\u0686\u0645 \u0633\u06cc\u062f\u06cc \u0633\u0641\u0644\u06cc"
    ],
    "name:fas_x_variant":[
        "Cham \u015eeyd-e Sofl\u00e1",
        "Cham Seyyed\u012b-ye Sofl\u00e1",
        "\u0686\u0645 \u0635\u06cc\u062f\u06cc \u0633\u0641\u0644\u06cc"
    ],
    "name:und_x_variant":[
        "Cham \u015eeyd\u012b-ye Sofl\u00e1"
    ],
    "wof:name":"Cham Seydi-ye Sofla",
    "wof:placetype":"locality"
},
  "geometry": {"coordinates":[48.6732,33.7628],"type":"Point"}
}