{
  "type": "Feature",
  "properties": {
    "gn:admin1_code":"7.0",
    "gn:asciiname":"Kuh-e Bazan",
    "gn:country_code":"IR",
    "gn:dem":1119,
    "gn:feature_class":"P",
    "gn:feature_code":"PPL",
    "gn:name":"K\u016bh-e Baz\u0101n",
    "gn:population":0,
    "gn:timezone":"Asia/Tehran",
    "iso:country":"IR",
    "name:fas_x_preferred":[
        "K\u016bh-e Baz\u0101n"
    ],
    "name:fas_x_variant":[
        "\u06a9\u0648\u0647 \u0628\u0632\u0627\u0646"
    ],
    "wof:name":"Kuh-e Bazan",
    "wof:placetype":"locality"
},
  "geometry": {"coordinates":[51.25361,30.04246],"type":"Point"}
}