{
  "type": "Feature",
  "properties": {
    "gn:admin1_code":"29",
    "gn:asciiname":"Mokhtarabad",
    "gn:cc2":"IR",
    "gn:country_code":"IR",
    "gn:dem":1728,
    "gn:feature_class":"P",
    "gn:feature_code":"PPL",
    "gn:name":"Mokht\u0101r\u0101b\u0101d",
    "gn:population":0,
    "gn:timezone":"Asia/Tehran",
    "iso:country":"IR",
    "name:fas_x_preferred":[
        "\u0645\u064f\u062e\u062a\u0627\u0631 \u0622\u0628\u0627\u062f"
    ],
    "name:fas_x_variant":[
        "Mokht\u0101r\u0101b\u0101d",
        "\u0645\u062e\u062a\u0627\u0631\u0622\u0628\u0627\u062f"
    ],
    "name:und_x_variant":[
        "Mukht\u0101r\u0101b\u0101d"
    ],
    "wof:name":"Mokhtarabad",
    "wof:placetype":"locality"
},
  "geometry": {"coordinates":[56.86666999999999,30.58333],"type":"Point"}
}