{
  "type": "Feature",
  "properties": {
    "gn:admin1_code":"43",
    "gn:asciiname":"Bash Mahalleh",
    "gn:country_code":"IR",
    "gn:dem":1899,
    "gn:feature_class":"P",
    "gn:feature_code":"PPL",
    "gn:name":"B\u0101sh Ma\u1e29alleh",
    "gn:population":0,
    "gn:timezone":"Asia/Tehran",
    "iso:country":"IR",
    "name:fas_x_preferred":[
        "\u0628\u0627\u0634 \u0645\u062d\u0644\u0651\u0647"
    ],
    "name:und_x_variant":[
        "B\u0101sh Ma\u1e29alleh"
    ],
    "wof:name":"Bash Mahalleh",
    "wof:placetype":"locality"
},
  "geometry": {"coordinates":[58.12897,36.98401],"type":"Point"}
}