{
  "type": "Feature",
  "properties": {
    "gn:admin1_code":"15.0",
    "gn:asciiname":"Hasan Vand",
    "gn:country_code":"IR",
    "gn:dem":261,
    "gn:feature_class":"P",
    "gn:feature_code":"PPLL",
    "gn:name":"\u1e28asan Vand",
    "gn:population":0,
    "gn:timezone":"Asia/Tehran",
    "iso:country":"IR",
    "name:fas_x_preferred":[
        "\u062d\u0633\u0646 \u0648\u0646\u062f"
    ],
    "name:und_x_variant":[
        "\u1e28asan Vand"
    ],
    "wof:name":"Hasan Vand",
    "wof:placetype":"locality"
},
  "geometry": {"coordinates":[48.22621,32.55886],"type":"Point"}
}