{
  "type": "Feature",
  "properties": {
    "gn:admin1_code":"4.0",
    "gn:asciiname":"Surak",
    "gn:country_code":"IR",
    "gn:dem":1288,
    "gn:feature_class":"P",
    "gn:feature_code":"PPL",
    "gn:name":"S\u016brak",
    "gn:population":0,
    "gn:timezone":"Asia/Tehran",
    "iso:country":"IR",
    "name:fas_x_preferred":[
        "\u0633\u0648\u0631\u06a9"
    ],
    "name:und_x_variant":[
        "S\u016brak"
    ],
    "wof:name":"Surak",
    "wof:placetype":"locality"
},
  "geometry": {"coordinates":[61.62935,27.3772],"type":"Point"}
}