{
  "type": "Feature",
  "properties": {
    "gn:admin1_code":"15",
    "gn:asciiname":"Halaf-e Yek",
    "gn:country_code":"IR",
    "gn:dem":31,
    "gn:feature_class":"P",
    "gn:feature_code":"PPL",
    "gn:name":"\u1e28alaf-e Yek",
    "gn:population":0,
    "gn:timezone":"Asia/Tehran",
    "iso:country":"IR",
    "name:fas_x_preferred":[
        "\u062d\u0644\u0627\u0641 \u06cc\u06a9"
    ],
    "name:fas_x_variant":[
        "\u1e28al\u0101f-e Yek",
        "\u062d\u0644\u0641 \u06cc\u06a9"
    ],
    "name:und_x_variant":[
        "\u1e28alaf-e Yek"
    ],
    "wof:name":"Halaf-e Yek",
    "wof:placetype":"locality"
},
  "geometry": {"coordinates":[48.56244,31.59227000000001],"type":"Point"}
}