{
  "type": "Feature",
  "properties": {
    "gn:admin1_code":"15",
    "gn:asciiname":"Tang-e Moshki",
    "gn:country_code":"IR",
    "gn:dem":374,
    "gn:feature_class":"P",
    "gn:feature_code":"PPLL",
    "gn:name":"Tang-e Moshk\u012b",
    "gn:population":0,
    "gn:timezone":"Asia/Tehran",
    "iso:country":"IR",
    "name:fas_x_preferred":[
        "\u062a\u0646\u06af \u0645\u0634\u06a9\u06cc"
    ],
    "name:fas_x_variant":[
        "Tang-e Moshk\u012b",
        "\u062a\u0646\u06af \u0645\u0634\u06af\u06cc"
    ],
    "name:und_x_variant":[
        "Tang-e Magas",
        "Tang-i-Mask",
        "Tang-e Moshg\u012b"
    ],
    "wof:name":"Tang-e Moshki",
    "wof:placetype":"locality"
},
  "geometry": {"coordinates":[49.24086,32.06986],"type":"Point"}
}