{
  "type": "Feature",
  "properties": {
    "iso:country":"IR",
    "name:ara_x_preferred":[
        "\u0648\u0631\u0632\u0646\u0647"
    ],
    "name:aze_x_preferred":[
        "V\u0259rz\u0259n\u0259"
    ],
    "name:ceb_x_preferred":[
        "Varzaneh"
    ],
    "name:eng_x_preferred":[
        "Varzaneh"
    ],
    "name:fas_x_preferred":[
        "\u0648\u0631\u0632\u0646\u0647"
    ],
    "name:fra_x_preferred":[
        "Varzaneh"
    ],
    "name:ita_x_preferred":[
        "Varzaneh"
    ],
    "name:mlg_x_preferred":[
        "Varzaneh"
    ],
    "name:nld_x_preferred":[
        "Varzaneh"
    ],
    "name:rus_x_preferred":[
        "\u0412\u0430\u0440\u0437\u0430\u043d\u0435"
    ],
    "name:rus_x_variant":[
        "\u0412\u0435\u0440\u0437\u0435\u043d\u0435"
    ],
    "name:swe_x_preferred":[
        "Varzaneh"
    ],
    "name:tur_x_preferred":[
        "Verzene"
    ],
    "name:zho_x_preferred":[
        "\u74e6\u5c14\u624e"
    ],
    "qs:gn_country":"IR",
    "qs:gn_fcode":"PPL",
    "qs:gn_pop":0,
    "qs:name":"Varzaneh",
    "qs:name_adm0":"Iran",
    "qs:name_adm1":"Esfahan",
    "qs:photos":21,
    "qs:photos_1k":4,
    "qs:photos_9k":1,
    "qs:photos_9r":1,
    "qs:photos_all":21,
    "qs:photos_sr":1,
    "qs:placetype":"Town",
    "qs:pop_sr":"0",
    "qs:woe_adm0":23424851,
    "wd:wordcount":94,
    "wof:name":"Varzaneh",
    "wof:placetype":"locality"
},
  "geometry": {"coordinates":[52.6483,32.4196],"type":"Point"}
}