{
  "type": "Feature",
  "properties": {
    "gn:admin1_code":"29",
    "gn:asciiname":"Maduhi",
    "gn:country_code":"IR",
    "gn:dem":857,
    "gn:feature_class":"P",
    "gn:feature_code":"PPL",
    "gn:name":"Mad\u016b\u1e29\u012b",
    "gn:population":0,
    "gn:timezone":"Asia/Tehran",
    "iso:country":"IR",
    "name:fas_x_preferred":[
        "\u0645\u062f\u0648\u062d\u06cc"
    ],
    "name:fas_x_variant":[
        "Mad\u016b\u1e29\u012b"
    ],
    "wof:name":"Maduhi",
    "wof:placetype":"locality"
},
  "geometry": {"coordinates":[58.7958,28.12349],"type":"Point"}
}