{
  "type": "Feature",
  "properties": {
    "gn:admin1_code":"29",
    "gn:asciiname":"Magasi",
    "gn:country_code":"IR",
    "gn:dem":628,
    "gn:feature_class":"P",
    "gn:feature_code":"PPL",
    "gn:name":"Magas\u012b",
    "gn:population":0,
    "gn:timezone":"Asia/Tehran",
    "iso:country":"IR",
    "name:fas_x_preferred":[
        "\u0645\u06af\u0633\u06cc"
    ],
    "name:fas_x_variant":[
        "Magas\u012b"
    ],
    "wof:name":"Magasi",
    "wof:placetype":"locality"
},
  "geometry": {"coordinates":[57.7595,28.5993],"type":"Point"}
}