{
  "type": "Feature",
  "properties": {
    "gn:admin1_code":"8.0",
    "gn:asciiname":"Peleh Bagh",
    "gn:country_code":"IR",
    "gn:dem":3,
    "gn:feature_class":"P",
    "gn:feature_code":"PPL",
    "gn:name":"Peleh B\u0101gh",
    "gn:population":0,
    "gn:timezone":"Asia/Tehran",
    "iso:country":"IR",
    "name:fas_x_preferred":[
        "Qolleh B\u0101gh"
    ],
    "name:fas_x_variant":[
        "\u0642\u0644\u0647 \u0628\u0627\u063a",
        "\u067e\u0644\u0647 \u0628\u0627\u063a"
    ],
    "name:und_x_variant":[
        "\u0642\u0644\u0647 \u0628\u0627\u063a",
        "Peleh B\u0101gh"
    ],
    "wof:name":"Peleh Bagh",
    "wof:placetype":"locality"
},
  "geometry": {"coordinates":[50.2507,37.09059],"type":"Point"}
}