{
  "type": "Feature",
  "properties": {
    "gn:admin1_code":"35.0",
    "gn:asciiname":"Garasba Sar",
    "gn:country_code":"IR",
    "gn:dem":2140,
    "gn:feature_class":"P",
    "gn:feature_code":"PPL",
    "gn:name":"Garasb\u0101 Sar",
    "gn:population":0,
    "gn:timezone":"Asia/Tehran",
    "iso:country":"IR",
    "name:fas_x_preferred":[
        "Garasb\u0101 Sar"
    ],
    "name:fas_x_variant":[
        "\u06af\u0631\u0633\u0628\u0627 \u0633\u0631"
    ],
    "wof:name":"Garasba Sar",
    "wof:placetype":"locality"
},
  "geometry": {"coordinates":[50.56368,36.81397],"type":"Point"}
}