{
  "type": "Feature",
  "properties": {
    "gn:admin1_code":"1",
    "gn:asciiname":"Sarujeh-ye `Olya",
    "gn:country_code":"IR",
    "gn:dem":1441,
    "gn:feature_class":"P",
    "gn:feature_code":"PPL",
    "gn:name":"S\u0101r\u016bjeh-ye \u2018Oly\u0101",
    "gn:population":0,
    "gn:timezone":"Asia/Tehran",
    "iso:country":"IR",
    "name:fas_x_preferred":[
        "\u0633\u0627\u0631\u0648\u062c\u0647 \u0639\u0644\u06cc\u0627"
    ],
    "name:fas_x_variant":[
        "S\u0101r\u016bjeh-ye \u2018Oly\u0101"
    ],
    "wof:name":"Sarujeh-ye `Olya",
    "wof:placetype":"locality"
},
  "geometry": {"coordinates":[46.504,36.6527],"type":"Point"}
}