{
  "type": "Feature",
  "properties": {
    "gn:admin1_code":"16.0",
    "gn:asciiname":"Mianeh",
    "gn:country_code":"IR",
    "gn:dem":1775,
    "gn:feature_class":"P",
    "gn:feature_code":"PPL",
    "gn:name":"M\u012b\u0101neh",
    "gn:population":0,
    "gn:timezone":"Asia/Tehran",
    "iso:country":"IR",
    "name:fas_x_preferred":[
        "M\u012b\u0101neh"
    ],
    "name:fas_x_variant":[
        "\u0645\u06cc\u0627\u0646\u0647"
    ],
    "name:und_x_variant":[
        "\u0645\u06cc\u0627\u0646\u0647"
    ],
    "wof:name":"Mianeh",
    "wof:placetype":"locality"
},
  "geometry": {"coordinates":[46.49987,35.32399],"type":"Point"}
}