{
  "type": "Feature",
  "properties": {
    "gn:admin1_code":"33",
    "gn:asciiname":"Mesrov",
    "gn:country_code":"IR",
    "gn:dem":1802,
    "gn:feature_class":"P",
    "gn:feature_code":"PPL",
    "gn:name":"Mesrov",
    "gn:population":0,
    "gn:timezone":"Asia/Tehran",
    "iso:country":"IR",
    "name:fas_x_preferred":[
        "\u0645\u0633\u0631\u0648"
    ],
    "name:fas_x_variant":[
        "Na\u015f\u012br\u0101b\u0101d"
    ],
    "name:und_x_variant":[
        "Misrov",
        "Nasir Abad Ozomdel",
        "Me\u015fr\u0101b",
        "Mesrov"
    ],
    "wof:name":"Mesrov",
    "wof:placetype":"locality"
},
  "geometry": {"coordinates":[46.7404,38.4838],"type":"Point"}
}