{
  "type": "Feature",
  "properties": {
    "gn:admin1_code":"32",
    "gn:asciiname":"Nir",
    "gn:country_code":"IR",
    "gn:dem":1623,
    "gn:feature_class":"P",
    "gn:feature_code":"PPLA2",
    "gn:name":"N\u012br",
    "gn:population":0,
    "gn:timezone":"Asia/Tehran",
    "iso:country":"IR",
    "name:ara_x_preferred":[
        "\u0646\u064a\u0631"
    ],
    "name:arz_x_preferred":[
        "\u0646\u064a\u0631"
    ],
    "name:azb_x_preferred":[
        "\u0646\u06cc\u0631"
    ],
    "name:aze_x_preferred":[
        "Nir"
    ],
    "name:ceb_x_preferred":[
        "N\u012br"
    ],
    "name:diq_x_preferred":[
        "Nir"
    ],
    "name:fas_x_preferred":[
        "\u0646\u064a\u0631"
    ],
    "name:fas_x_variant":[
        "N\u012br",
        "\u0634\u0647\u0631\u0633\u062a\u0627\u0646 \u0646\u064a\u0631",
        "\u0646\u06cc\u0631"
    ],
    "name:ita_x_preferred":[
        "Nir"
    ],
    "name:mlg_x_preferred":[
        "Nir"
    ],
    "name:msa_x_preferred":[
        "Nir"
    ],
    "name:pol_x_preferred":[
        "Nir"
    ],
    "name:ron_x_preferred":[
        "Nir"
    ],
    "name:swe_x_preferred":[
        "N\u012br"
    ],
    "name:tur_x_preferred":[
        "Nir"
    ],
    "name:und_x_variant":[
        "Shahrest\u0101n-e N\u012br"
    ],
    "name:urd_x_preferred":[
        "\u0646\u06cc\u0631"
    ],
    "name:zho_x_preferred":[
        "\u5c3c\u723e"
    ],
    "wof:name":"Nir",
    "wof:placetype":"locality"
},
  "geometry": {"coordinates":[47.9986,38.0346],"type":"Point"}
}