{
  "type": "Feature",
  "properties": {
    "gn:admin1_code":"8.0",
    "gn:asciiname":"Pa'in Mahaleh-ye Taromsar",
    "gn:country_code":"IR",
    "gn:dem":-6,
    "gn:feature_class":"P",
    "gn:feature_code":"PPL",
    "gn:name":"P\u0101\u2019\u012bn Ma\u1e29aleh-ye \u0162\u0101romsar",
    "gn:population":0,
    "gn:timezone":"Asia/Tehran",
    "iso:country":"IR",
    "name:fas_x_preferred":[
        "\u067e\u0627\u0626\u06cc\u0646 \u0645\u062d\u0644\u0647 \u0637\u0627\u0631\u0645\u0633\u0631"
    ],
    "name:und_x_variant":[
        "P\u0101\u2019\u012bn Ma\u1e29aleh-ye \u0162\u0101romsar"
    ],
    "wof:name":"Pa'in Mahaleh-ye Taromsar",
    "wof:placetype":"locality"
},
  "geometry": {"coordinates":[49.85433,37.29998],"type":"Point"}
}