{
  "type": "Feature",
  "properties": {
    "gn:admin1_code":"35",
    "gn:asciiname":"Lak Tarash",
    "gn:country_code":"IR",
    "gn:dem":687,
    "gn:feature_class":"P",
    "gn:feature_code":"PPL",
    "gn:name":"L\u0101k Tar\u0101sh",
    "gn:population":0,
    "gn:timezone":"Asia/Tehran",
    "iso:country":"IR",
    "name:fas_x_preferred":[
        "\u0644\u0627\u0643\u062a\u0650\u0631\u0627\u0634"
    ],
    "name:fas_x_variant":[
        "L\u0101k Tar\u0101sh",
        "\u0644\u0627\u0643 \u062a\u0631\u0627\u0634"
    ],
    "name:und_x_variant":[
        "L\u0101kter\u0101sh",
        "\u0644\u0627\u0643 \u062a\u0631\u0627\u0634"
    ],
    "wof:name":"Lak Tarash",
    "wof:placetype":"locality"
},
  "geometry": {"coordinates":[53.61086,36.5532],"type":"Point"}
}