{
  "type": "Feature",
  "properties": {
    "gn:admin1_code":"16.0",
    "gn:asciiname":"alwt",
    "gn:country_code":"IR",
    "gn:dem":1025,
    "gn:feature_class":"P",
    "gn:feature_code":"PPL",
    "gn:name":"\u0622\u0644\u0648\u062a",
    "gn:population":0,
    "gn:timezone":"Asia/Tehran",
    "iso:country":"IR",
    "name:fas_x_preferred":[
        "\u0100l\u016bt"
    ],
    "name:fas_x_variant":[
        "\u0622\u0644\u0648\u062a"
    ],
    "wof:name":"alwt",
    "wof:placetype":"locality"
},
  "geometry": {"coordinates":[45.5763,36.0212],"type":"Point"}
}