{
  "type": "Feature",
  "properties": {
    "gn:admin1_code":"15.0",
    "gn:asciiname":"Dar Balut",
    "gn:country_code":"IR",
    "gn:dem":448,
    "gn:feature_class":"P",
    "gn:feature_code":"PPL",
    "gn:name":"D\u0101r Bal\u016b\u0163",
    "gn:population":0,
    "gn:timezone":"Asia/Tehran",
    "iso:country":"IR",
    "name:fas_x_preferred":[
        "\u062f\u0627\u0631 \u0628\u0644\u0648\u0637"
    ],
    "name:fas_x_variant":[
        "\u062f\u0627\u0631\u0628\u0644\u0648\u0637"
    ],
    "name:und_x_variant":[
        "D\u0101r Bal\u016b\u0163"
    ],
    "wof:name":"Dar Balut",
    "wof:placetype":"locality"
},
  "geometry": {"coordinates":[48.44054000000001,32.56233],"type":"Point"}
}