{
  "type": "Feature",
  "properties": {
    "gn:admin1_code":"28",
    "gn:asciiname":"Shahrak-e Bist-o Seh-ye Bahman",
    "gn:country_code":"IR",
    "gn:dem":1007,
    "gn:feature_class":"P",
    "gn:feature_code":"PPL",
    "gn:name":"Shahrak-e B\u012bst-o Seh-ye Bahman",
    "gn:population":0,
    "gn:timezone":"Asia/Tehran",
    "iso:country":"IR",
    "name:fas_x_preferred":[
        "\u0634\u0647\u0631\u0643 \u0628\u06cc\u0633\u062a \u0648 \u0633\u0647 \u0628\u0647\u0645\u0646"
    ],
    "name:fas_x_variant":[
        "\u0634\u0647\u0631\u0643 \u06f2\u06f3 \u0628\u0647\u0645\u0646",
        "Shahrak-e B\u012bst-o Seh-ye Bahman"
    ],
    "name:und_x_variant":[
        "Shahrak-e 23 Bahman"
    ],
    "wof:name":"Shahrak-e Bist-o Seh-ye Bahman",
    "wof:placetype":"locality"
},
  "geometry": {"coordinates":[51.4627,33.9298],"type":"Point"}
}