{
  "type": "Feature",
  "properties": {
    "gn:admin1_code":"34",
    "gn:asciiname":"Haqqaniyeh",
    "gn:country_code":"IR",
    "gn:dem":1218,
    "gn:feature_class":"P",
    "gn:feature_code":"PPL",
    "gn:name":"\u1e28aqq\u0101n\u012byeh",
    "gn:population":0,
    "gn:timezone":"Asia/Tehran",
    "iso:country":"IR",
    "name:fas_x_preferred":[
        "\u062d\u0642\u0627\u0646\u064a\u0647"
    ],
    "name:fas_x_variant":[
        "\u1e28aqq\u0101n\u012byeh",
        "\u1e28aq\u0101n\u012byeh"
    ],
    "wof:name":"Haqqaniyeh",
    "wof:placetype":"locality"
},
  "geometry": {"coordinates":[50.1052,35.0114],"type":"Point"}
}