{
  "type": "Feature",
  "properties": {
    "gn:admin1_code":"29",
    "gn:asciiname":"`Ezzatabad",
    "gn:country_code":"IR",
    "gn:dem":1694,
    "gn:feature_class":"P",
    "gn:feature_code":"PPL",
    "gn:name":"\u2018Ezzat\u0101b\u0101d",
    "gn:population":0,
    "gn:timezone":"Asia/Tehran",
    "iso:country":"IR",
    "name:fas_x_preferred":[
        "\u2018Ezzat\u0101b\u0101d"
    ],
    "wof:name":"`Ezzatabad",
    "wof:placetype":"locality"
},
  "geometry": {"coordinates":[57.93917,28.72944],"type":"Point"}
}