{
  "type": "Feature",
  "properties": {
    "gn:admin1_code":"33.0",
    "gn:asciiname":"Sambaran",
    "gn:country_code":"IR",
    "gn:dem":1231,
    "gn:feature_class":"P",
    "gn:feature_code":"PPL",
    "gn:name":"S\u0101mbar\u0101n",
    "gn:population":0,
    "gn:timezone":"Asia/Tehran",
    "iso:country":"IR",
    "name:ara_x_preferred":[
        "\u0633\u0645\u0627\u0628\u0627\u0631\u0627\u0646"
    ],
    "name:ceb_x_preferred":[
        "S\u0101mbar\u0101n"
    ],
    "name:fas_x_preferred":[
        "\u0633\u0627\u0645\u0628\u0631\u0627\u0646"
    ],
    "name:msa_x_preferred":[
        "Sambaran"
    ],
    "name:swe_x_preferred":[
        "S\u0101mbar\u0101n"
    ],
    "name:und_x_variant":[
        "S\u0101mbar\u0101n"
    ],
    "wof:name":"Sambaran",
    "wof:placetype":"locality"
},
  "geometry": {"coordinates":[45.76078,38.49779],"type":"Point"}
}