{
  "type": "Feature",
  "properties": {
    "gn:admin1_code":"41",
    "gn:asciiname":"Dastgerd-e Bala",
    "gn:country_code":"IR",
    "gn:dem":2429,
    "gn:feature_class":"P",
    "gn:feature_code":"PPL",
    "gn:name":"Dastgerd-e B\u0101l\u0101",
    "gn:population":0,
    "gn:timezone":"Asia/Tehran",
    "iso:country":"IR",
    "name:fas_x_preferred":[
        "Dastgerd-e B\u0101l\u0101"
    ],
    "wof:name":"Dastgerd-e Bala",
    "wof:placetype":"locality"
},
  "geometry": {"coordinates":[59.75,32.83333],"type":"Point"}
}