{
  "type": "Feature",
  "properties": {
    "gn:admin1_code":"16.0",
    "gn:asciiname":"Kapuleh",
    "gn:country_code":"IR",
    "gn:dem":1588,
    "gn:feature_class":"P",
    "gn:feature_code":"PPL",
    "gn:name":"Kap\u016bleh",
    "gn:population":0,
    "gn:timezone":"Asia/Tehran",
    "iso:country":"IR",
    "name:fas_x_preferred":[
        "\u06a9\u067e\u0648\u0644\u0647"
    ],
    "name:fas_x_variant":[
        "Kap\u016bleh"
    ],
    "wof:name":"Kapuleh",
    "wof:placetype":"locality"
},
  "geometry": {"coordinates":[45.985,35.9468],"type":"Point"}
}