{
  "type": "Feature",
  "properties": {
    "gn:admin1_code":"34",
    "gn:asciiname":"Khaltabad",
    "gn:country_code":"IR",
    "gn:dem":1817,
    "gn:feature_class":"P",
    "gn:feature_code":"PPL",
    "gn:name":"Khalt\u0101b\u0101d",
    "gn:population":0,
    "gn:timezone":"Asia/Tehran",
    "iso:country":"IR",
    "name:ara_x_preferred":[
        "\u062e\u0644\u062a\u200c\u0622\u0628\u0627\u062f"
    ],
    "name:ceb_x_preferred":[
        "Khalt\u0101b\u0101d"
    ],
    "name:fas_x_preferred":[
        "Khalt\u0101b\u0101d"
    ],
    "name:fas_x_variant":[
        "\u062e\u0644\u062a \u0622\u0628\u0627\u062f",
        "\u062e\u0644\u062a\u200c\u0622\u0628\u0627\u062f"
    ],
    "name:swe_x_preferred":[
        "Khalt\u0101b\u0101d"
    ],
    "name:ukr_x_preferred":[
        "\u0425\u0430\u043b\u0442\u0430\u0431\u0430\u0434"
    ],
    "name:und_x_variant":[
        "\u062e\u0644\u062a \u0622\u0628\u0627\u062f"
    ],
    "wof:name":"Khaltabad",
    "wof:placetype":"locality"
},
  "geometry": {"coordinates":[49.6704,34.55413],"type":"Point"}
}