{
  "type": "Feature",
  "properties": {
    "gn:admin1_code":"23",
    "gn:asciiname":"Vali-ye `Asr",
    "gn:country_code":"IR",
    "gn:dem":1063,
    "gn:feature_class":"P",
    "gn:feature_code":"PPL",
    "gn:name":"Val\u012b-ye \u2018A\u015fr",
    "gn:population":0,
    "gn:timezone":"Asia/Tehran",
    "iso:country":"IR",
    "name:fas_x_preferred":[
        "\u0642\u0627\u0637\u0631\u0686\u06cc"
    ],
    "name:fas_x_variant":[
        "\u0648\u0644\u06cc \u0639\u0635\u0631",
        "Q\u0101\u0163erch\u012b",
        "Val\u012b-ye \u2018A\u015fr",
        "\u0633\u0648\u0631\u06cc"
    ],
    "name:und_x_variant":[
        "Q\u0101tarch",
        "S\u016br\u012b"
    ],
    "wof:name":"Vali-ye `Asr",
    "wof:placetype":"locality"
},
  "geometry": {"coordinates":[47.37586,33.33181],"type":"Point"}
}