{
  "type": "Feature",
  "properties": {
    "gn:admin1_code":"35.0",
    "gn:asciiname":"Michkar",
    "gn:country_code":"IR",
    "gn:dem":906,
    "gn:feature_class":"P",
    "gn:feature_code":"PPL",
    "gn:name":"M\u012bchk\u0101r",
    "gn:population":0,
    "gn:timezone":"Asia/Tehran",
    "iso:country":"IR",
    "name:ara_x_preferred":[
        "\u0645\u064a\u062a\u0634\u0643\u0627\u0631"
    ],
    "name:ceb_x_preferred":[
        "M\u012bchk\u0101r"
    ],
    "name:fas_x_preferred":[
        "\u0645\u06cc\u0686\u06a9\u0627\u0631"
    ],
    "name:fas_x_variant":[
        "M\u012bchk\u0101r",
        "M\u012bchar",
        "\u0645\u064a\u0686\u064e\u0631"
    ],
    "name:swe_x_preferred":[
        "M\u012bchk\u0101r"
    ],
    "wof:name":"Michkar",
    "wof:placetype":"locality"
},
  "geometry": {"coordinates":[51.27514,36.43999],"type":"Point"}
}