{
  "type": "Feature",
  "properties": {
    "gn:admin1_code":"15",
    "gn:asciiname":"Shuhan-e Sofla",
    "gn:country_code":"IR",
    "gn:dem":97,
    "gn:feature_class":"P",
    "gn:feature_code":"PPL",
    "gn:name":"Sh\u016bh\u0101n-e Sofl\u00e1",
    "gn:population":0,
    "gn:timezone":"Asia/Tehran",
    "iso:country":"IR",
    "name:fas_x_preferred":[
        "\u0634\u0627\u0647\u0648\u0646 \u0633\u0641\u0644\u06cc"
    ],
    "name:fas_x_variant":[
        "Sh\u016bh\u0101n-e Sofl\u00e1",
        "Sh\u0101h\u016bn-e Sofl\u00e1",
        "\u0634\u0648\u0647\u0627\u0646 \u0633\u0641\u0644\u06cc"
    ],
    "name:und_x_variant":[
        "\u0162orf\u012b\u0101n",
        "Sh\u016bh\u0101n",
        "Shoohan"
    ],
    "wof:name":"Shuhan-e Sofla",
    "wof:placetype":"locality"
},
  "geometry": {"coordinates":[48.30385,32.3293],"type":"Point"}
}