{
  "type": "Feature",
  "properties": {
    "gn:admin1_code":"38",
    "gn:asciiname":"Gorgin",
    "gn:country_code":"IR",
    "gn:dem":1849,
    "gn:feature_class":"P",
    "gn:feature_code":"PPL",
    "gn:name":"Gorg\u012bn",
    "gn:population":0,
    "gn:timezone":"Asia/Tehran",
    "iso:country":"IR",
    "name:ceb_x_preferred":[
        "Gork\u012bn"
    ],
    "name:fas_x_preferred":[
        "\u06af\u0631\u06af\u06cc\u0646"
    ],
    "name:fas_x_variant":[
        "\u06af\u0631\u06a9\u06cc\u0646",
        "Garag\u012bn",
        "Gork\u012bn"
    ],
    "name:swe_x_preferred":[
        "Gork\u012bn"
    ],
    "name:und_x_variant":[
        "Gorg\u012bn",
        "Gorkin",
        "Garakin"
    ],
    "wof:name":"Gorgin",
    "wof:placetype":"locality"
},
  "geometry": {"coordinates":[49.96961,36.43307],"type":"Point"}
}