{
  "type": "Feature",
  "properties": {
    "gn:admin1_code":"28",
    "gn:asciiname":"Sangij",
    "gn:country_code":"IR",
    "gn:dem":2099,
    "gn:feature_class":"P",
    "gn:feature_code":"PPL",
    "gn:name":"Sang\u012bj",
    "gn:population":0,
    "gn:timezone":"Asia/Tehran",
    "iso:country":"IR",
    "name:fas_x_preferred":[
        "\u0633\u0646\u06af\u06cc\u062c"
    ],
    "name:fas_x_variant":[
        "Sang\u012bj"
    ],
    "name:und_x_variant":[
        "Sangieh"
    ],
    "wof:name":"Sangij",
    "wof:placetype":"locality"
},
  "geometry": {"coordinates":[52.8279,32.835],"type":"Point"}
}