{
  "type": "Feature",
  "properties": {
    "gn:admin1_code":"15",
    "gn:asciiname":"Sahayyem",
    "gn:country_code":"IR",
    "gn:dem":80,
    "gn:feature_class":"P",
    "gn:feature_code":"PPL",
    "gn:name":"Sahayyem",
    "gn:population":0,
    "gn:timezone":"Asia/Tehran",
    "iso:country":"IR",
    "wof:name":"Sahayyem",
    "wof:placetype":"locality"
},
  "geometry": {"coordinates":[49.42028,31.36722],"type":"Point"}
}