{
  "type": "Feature",
  "properties": {
    "gn:admin1_code":"35.0",
    "gn:asciiname":"Van-e Now",
    "gn:country_code":"IR",
    "gn:dem":1680,
    "gn:feature_class":"P",
    "gn:feature_code":"PPL",
    "gn:name":"Van-e Now",
    "gn:population":0,
    "gn:timezone":"Asia/Tehran",
    "iso:country":"IR",
    "name:fas_x_preferred":[
        "\u0648\u0646 \u0646\u0648"
    ],
    "wof:name":"Van-e Now",
    "wof:placetype":"locality"
},
  "geometry": {"coordinates":[51.07673,36.45448],"type":"Point"}
}