{
  "type": "Feature",
  "properties": {
    "gn:admin1_code":"29",
    "gn:asciiname":"Sar Ashk",
    "gn:country_code":"IR",
    "gn:dem":1778,
    "gn:feature_class":"P",
    "gn:feature_code":"PPL",
    "gn:name":"Sar Ashk",
    "gn:population":0,
    "gn:timezone":"Asia/Tehran",
    "iso:country":"IR",
    "name:fas_x_preferred":[
        "\u0633\u0631 \u0627\u0634\u06a9"
    ],
    "name:fas_x_variant":[
        "Sar \u2018Arsh",
        "\u0633\u0631\u0627\u0634\u06a9"
    ],
    "wof:name":"Sar Ashk",
    "wof:placetype":"locality"
},
  "geometry": {"coordinates":[57.03953000000001,30.82451],"type":"Point"}
}