{
  "type": "Feature",
  "properties": {
    "gn:admin1_code":"41.0",
    "gn:asciiname":"Lanoo",
    "gn:country_code":"IR",
    "gn:dem":1381,
    "gn:feature_class":"P",
    "gn:feature_code":"PPL",
    "gn:name":"Lanoo",
    "gn:population":0,
    "gn:timezone":"Asia/Tehran",
    "iso:country":"IR",
    "name:ceb_x_preferred":[
        "Lanoo"
    ],
    "name:fas_x_preferred":[
        "\u0644\u0627\u0646\u0648"
    ],
    "name:fas_x_variant":[
        "L\u0101n\u016b"
    ],
    "name:swe_x_preferred":[
        "Lanoo"
    ],
    "name:und_x_variant":[
        "L\u0101hn\u016b"
    ],
    "name:urd_x_preferred":[
        "\u0644\u0627\u0646\u0648"
    ],
    "wof:name":"Lanoo",
    "wof:placetype":"locality"
},
  "geometry": {"coordinates":[60.5354,32.4877],"type":"Point"}
}