{
  "type": "Feature",
  "properties": {
    "gn:admin1_code":"4.0",
    "gn:asciiname":"Sar Shur",
    "gn:country_code":"IR",
    "gn:dem":904,
    "gn:feature_class":"P",
    "gn:feature_code":"PPL",
    "gn:name":"Sar Sh\u016br",
    "gn:population":0,
    "gn:timezone":"Asia/Tehran",
    "iso:country":"IR",
    "name:fas_x_preferred":[
        "Sar Sh\u016br"
    ],
    "wof:name":"Sar Shur",
    "wof:placetype":"locality"
},
  "geometry": {"coordinates":[61.93389000000001,26.68472],"type":"Point"}
}