{
  "type": "Feature",
  "properties": {
    "gn:admin1_code":"7",
    "gn:asciiname":"Bid Shahrak",
    "gn:country_code":"IR",
    "gn:dem":1468,
    "gn:feature_class":"P",
    "gn:feature_code":"PPL",
    "gn:name":"B\u012bd Shahrak",
    "gn:population":0,
    "gn:timezone":"Asia/Tehran",
    "iso:country":"IR",
    "name:ara_x_preferred":[
        "\u0628\u064a\u062f\u0634\u0647\u0631\u0643"
    ],
    "name:fas_x_preferred":[
        "\u0628\u06cc\u062f \u0634\u0647\u0631\u06a9"
    ],
    "name:fas_x_variant":[
        "B\u012bd Shahrak",
        "\u0628\u06cc\u062f\u0634\u0647\u0631\u06a9"
    ],
    "name:msa_x_preferred":[
        "Bid Shahrak"
    ],
    "wof:name":"Bid Shahrak",
    "wof:placetype":"locality"
},
  "geometry": {"coordinates":[52.8015,28.6662],"type":"Point"}
}