{
  "type": "Feature",
  "properties": {
    "gn:admin1_code":"8.0",
    "gn:asciiname":"Siah Belash",
    "gn:country_code":"IR",
    "gn:dem":26,
    "gn:feature_class":"P",
    "gn:feature_code":"PPL",
    "gn:name":"S\u012b\u0101h Belash",
    "gn:population":0,
    "gn:timezone":"Asia/Tehran",
    "iso:country":"IR",
    "name:fas_x_preferred":[
        "\u0633\u06cc\u0627\u0647 \u0628\u0644\u0627\u0634"
    ],
    "name:fas_x_variant":[
        "S\u012b\u0101h Bel\u0101sh",
        "\u0633\u06cc\u0627\u0647 \u0628\u0644\u0634"
    ],
    "name:und_x_variant":[
        "S\u012b\u0101h Belash"
    ],
    "wof:name":"Siah Belash",
    "wof:placetype":"locality"
},
  "geometry": {"coordinates":[49.13921,37.53871],"type":"Point"}
}