{
  "type": "Feature",
  "properties": {
    "gn:admin1_code":"23",
    "gn:asciiname":"Bosheh Zard",
    "gn:country_code":"IR",
    "gn:dem":1021,
    "gn:feature_class":"P",
    "gn:feature_code":"PPL",
    "gn:name":"Bosheh Zard",
    "gn:population":0,
    "gn:timezone":"Asia/Tehran",
    "iso:country":"IR",
    "name:ceb_x_preferred":[
        "Bosheh Zard"
    ],
    "name:fas_x_preferred":[
        "\u0628\u064a\u0634\u0650\u0647 \u0632\u064e\u0631\u062f\u0650\u0647"
    ],
    "name:fas_x_variant":[
        "B\u012bsheh Zardeh",
        "\u0628\u0634\u0647 \u0632\u0631\u062f",
        "\u0628\u06cc\u0634\u0647 \u0632\u0631\u062f\u0647"
    ],
    "name:swe_x_preferred":[
        "Bosheh Zard"
    ],
    "wof:name":"Bosheh Zard",
    "wof:placetype":"locality"
},
  "geometry": {"coordinates":[47.97748,33.24023],"type":"Point"}
}