{
  "type": "Feature",
  "properties": {
    "gn:admin1_code":"4.0",
    "gn:asciiname":"Kaleh Begar",
    "gn:country_code":"IR",
    "gn:dem":1105,
    "gn:feature_class":"P",
    "gn:feature_code":"PPL",
    "gn:name":"Kaleh Begar",
    "gn:population":0,
    "gn:timezone":"Asia/Tehran",
    "iso:country":"IR",
    "wof:name":"Kaleh Begar",
    "wof:placetype":"locality"
},
  "geometry": {"coordinates":[61.81194,26.75139],"type":"Point"}
}