{
  "type": "Feature",
  "properties": {
    "gn:admin1_code":"7",
    "gn:asciiname":"Gashak",
    "gn:cc2":"IR",
    "gn:country_code":"IR",
    "gn:dem":1599,
    "gn:feature_class":"P",
    "gn:feature_code":"PPL",
    "gn:name":"Gashak",
    "gn:population":0,
    "gn:timezone":"Asia/Tehran",
    "iso:country":"IR",
    "name:und_x_variant":[
        "Qash\u0101k",
        "Gashak"
    ],
    "wof:name":"Gashak",
    "wof:placetype":"locality"
},
  "geometry": {"coordinates":[52.92028000000001,29.88333],"type":"Point"}
}