{
  "type": "Feature",
  "properties": {
    "gn:admin1_code":"1.0",
    "gn:asciiname":"Shur",
    "gn:country_code":"IR",
    "gn:dem":1834,
    "gn:feature_class":"P",
    "gn:feature_code":"PPL",
    "gn:name":"Sh\u016br",
    "gn:population":0,
    "gn:timezone":"Asia/Tehran",
    "iso:country":"IR",
    "name:ceb_x_preferred":[
        "Shur"
    ],
    "name:fas_x_preferred":[
        "\u0634\u0648\u0631"
    ],
    "name:swe_x_preferred":[
        "Shur"
    ],
    "name:und_x_variant":[
        "Sh\u016br"
    ],
    "wof:name":"Shur",
    "wof:placetype":"locality"
},
  "geometry": {"coordinates":[47.12473,36.45674],"type":"Point"}
}