{
  "type": "Feature",
  "properties": {
    "gn:admin1_code":"35.0",
    "gn:asciiname":"Dizeh Posht",
    "gn:country_code":"IR",
    "gn:dem":159,
    "gn:feature_class":"P",
    "gn:feature_code":"PPLF",
    "gn:name":"D\u012bzeh Posht",
    "gn:population":0,
    "gn:timezone":"Asia/Tehran",
    "iso:country":"IR",
    "name:fas_x_preferred":[
        "D\u012bzeh Posht"
    ],
    "name:fas_x_variant":[
        "\u062f\u06cc\u0632\u0647 \u067e\u0634\u062a",
        "\u062f\u06cc\u0632 \u067e\u0634\u062a"
    ],
    "name:und_x_variant":[
        "\u062f\u06cc\u0632\u0647 \u067e\u0634\u062a",
        "D\u012bz Posht"
    ],
    "wof:name":"Dizeh Posht",
    "wof:placetype":"locality"
},
  "geometry": {"coordinates":[50.97398,36.6957],"type":"Point"}
}