{
  "type": "Feature",
  "properties": {
    "gn:admin1_code":"23.0",
    "gn:asciiname":"Baba Mahmud-e `Olya",
    "gn:country_code":"IR",
    "gn:dem":1611,
    "gn:feature_class":"P",
    "gn:feature_code":"PPL",
    "gn:name":"B\u0101b\u0101 Ma\u1e29m\u016bd-e \u2018Oly\u0101",
    "gn:population":0,
    "gn:timezone":"Asia/Tehran",
    "iso:country":"IR",
    "name:fas_x_preferred":[
        "\u0628\u0627\u0628\u0627 \u0645\u062d\u0645\u0648\u062f \u0639\u0644\u064a\u0627"
    ],
    "name:fas_x_variant":[
        "\u0628\u0627\u0628\u0627 \u0645\u064e\u062d\u0645\u0648\u062f",
        "B\u0101b\u0101 Ma\u1e29m\u016bd-e \u2018Oly\u0101"
    ],
    "name:und_x_variant":[
        "B\u0101b\u0101 Ma\u1e29m\u016bd"
    ],
    "wof:name":"Baba Mahmud-e `Olya",
    "wof:placetype":"locality"
},
  "geometry": {"coordinates":[48.5468,33.478],"type":"Point"}
}