{
  "type": "Feature",
  "properties": {
    "gn:admin1_code":"5.0",
    "gn:asciiname":"Sadat Bidak",
    "gn:country_code":"IR",
    "gn:dem":1087,
    "gn:feature_class":"P",
    "gn:feature_code":"PPL",
    "gn:name":"S\u0101d\u0101t B\u012bdak",
    "gn:population":0,
    "gn:timezone":"Asia/Tehran",
    "iso:country":"IR",
    "name:fas_x_preferred":[
        "S\u0101d\u0101t B\u012bdak"
    ],
    "name:fas_x_variant":[
        "\u0633\u0627\u062f\u0627\u062a \u0628\u06cc\u062f\u0643"
    ],
    "name:und_x_variant":[
        "\u0633\u0627\u062f\u0627\u062a \u0628\u06cc\u062f\u0643"
    ],
    "wof:name":"Sadat Bidak",
    "wof:placetype":"locality"
},
  "geometry": {"coordinates":[51.12198,30.43507],"type":"Point"}
}