{
  "type": "Feature",
  "properties": {
    "gn:admin1_code":"36",
    "gn:asciiname":"Avarneh",
    "gn:country_code":"IR",
    "gn:dem":1840,
    "gn:feature_class":"P",
    "gn:feature_code":"PPL",
    "gn:name":"Avarneh",
    "gn:population":0,
    "gn:timezone":"Asia/Tehran",
    "iso:country":"IR",
    "name:fas_x_preferred":[
        "\u0627\u0648\u0631\u0646\u0647"
    ],
    "name:und_x_variant":[
        "\u016arneh",
        "Abarna\u016b",
        "\u016araneh",
        "Awarneh",
        "Owr\u016bneh",
        "Owraneh",
        "Oorneh",
        "Avarneh"
    ],
    "wof:name":"Avarneh",
    "wof:placetype":"locality"
},
  "geometry": {"coordinates":[49.26085,35.9515],"type":"Point"}
}