{
  "type": "Feature",
  "properties": {
    "gn:admin1_code":"25.0",
    "gn:asciiname":"Aftar",
    "gn:country_code":"IR",
    "gn:dem":1776,
    "gn:feature_class":"P",
    "gn:feature_code":"PPL",
    "gn:name":"Aftar",
    "gn:population":0,
    "gn:timezone":"Asia/Tehran",
    "iso:country":"IR",
    "name:ceb_x_preferred":[
        "Aftar"
    ],
    "name:fas_x_preferred":[
        "\u0627\u0641\u062a\u0631"
    ],
    "name:swe_x_preferred":[
        "Aftar"
    ],
    "wof:name":"Aftar",
    "wof:placetype":"locality"
},
  "geometry": {"coordinates":[53.1104,35.60352],"type":"Point"}
}