{
  "type": "Feature",
  "properties": {
    "gn:admin1_code":"4",
    "gn:asciiname":"Moradi Gashk",
    "gn:country_code":"IR",
    "gn:dem":17,
    "gn:feature_class":"P",
    "gn:feature_code":"PPL",
    "gn:name":"Mor\u0101d\u012b Gashk",
    "gn:population":0,
    "gn:timezone":"Asia/Tehran",
    "iso:country":"IR",
    "name:fas_x_preferred":[
        "Mor\u0101d\u012b Gashk"
    ],
    "name:fas_x_variant":[
        "\u0645\u0631\u0627\u062f\u06cc \u06af\u0634\u06a9"
    ],
    "name:und_x_variant":[
        "\u0645\u0631\u0627\u062f\u06cc \u06af\u0634\u06a9"
    ],
    "wof:name":"Moradi Gashk",
    "wof:placetype":"locality"
},
  "geometry": {"coordinates":[59.36223,25.65041],"type":"Point"}
}