{
  "type": "Feature",
  "properties": {
    "gn:admin1_code":"7.0",
    "gn:asciiname":"Mahmudiyeh",
    "gn:country_code":"IR",
    "gn:dem":1621,
    "gn:feature_class":"P",
    "gn:feature_code":"PPL",
    "gn:name":"Ma\u1e29m\u016bd\u012byeh",
    "gn:population":0,
    "gn:timezone":"Asia/Tehran",
    "iso:country":"IR",
    "name:fas_x_preferred":[
        "\u0645\u062d\u0645\u0648\u062f\u06cc\u0647"
    ],
    "name:und_x_variant":[
        "Ma\u1e29m\u016bd\u012byeh"
    ],
    "wof:name":"Mahmudiyeh",
    "wof:placetype":"locality"
},
  "geometry": {"coordinates":[52.49309,29.66802],"type":"Point"}
}