{
  "type": "Feature",
  "properties": {
    "gn:admin1_code":"33",
    "gn:asciiname":"Sardrud",
    "gn:country_code":"IR",
    "gn:dem":1364,
    "gn:feature_class":"P",
    "gn:feature_code":"PPL",
    "gn:name":"Sardr\u016bd",
    "gn:population":0,
    "gn:timezone":"Asia/Tehran",
    "iso:country":"IR",
    "name:ara_x_preferred":[
        "\u0633\u0631\u062f\u0631\u0648\u062f"
    ],
    "name:azb_x_preferred":[
        "\u0633\u0631\u062f\u0631\u0648\u062f"
    ],
    "name:aze_x_preferred":[
        "S\u0259rdrud"
    ],
    "name:ceb_x_preferred":[
        "Sardr\u016bd"
    ],
    "name:fas_x_preferred":[
        "\u0633\u0631\u062f\u0631\u0648\u062f"
    ],
    "name:fas_x_variant":[
        "Sardr\u016bd",
        "\u0633\u064e\u0631\u062f\u0627\u0631\u0648\u062f",
        "\u0633\u064e\u0631\u062f \u0631\u064f\u0651\u062f"
    ],
    "name:ita_x_preferred":[
        "Sardrud"
    ],
    "name:mlg_x_preferred":[
        "Sardrud"
    ],
    "name:msa_x_preferred":[
        "Sardrud"
    ],
    "name:swe_x_preferred":[
        "Sardr\u016bd"
    ],
    "name:tur_x_preferred":[
        "Serdrud"
    ],
    "name:und_x_variant":[
        "Sard\u0101r\u016bd",
        "Sardari",
        "Sard Rood"
    ],
    "name:urd_x_preferred":[
        "\u0633\u0631\u062f\u0631\u0648\u062f"
    ],
    "wof:name":"Sardrud",
    "wof:placetype":"locality"
},
  "geometry": {"coordinates":[46.14763,38.02613],"type":"Point"}
}