{
  "type": "Feature",
  "properties": {
    "gn:admin1_code":"35.0",
    "gn:asciiname":"Kand Sark",
    "gn:country_code":"IR",
    "gn:dem":63,
    "gn:feature_class":"P",
    "gn:feature_code":"PPL",
    "gn:name":"Kand Sark",
    "gn:population":0,
    "gn:timezone":"Asia/Tehran",
    "iso:country":"IR",
    "name:fas_x_preferred":[
        "\u06a9\u0646\u062f \u0633\u0631\u06a9"
    ],
    "wof:name":"Kand Sark",
    "wof:placetype":"locality"
},
  "geometry": {"coordinates":[50.81508,36.7863],"type":"Point"}
}