{
  "type": "Feature",
  "properties": {
    "gn:admin1_code":"5.0",
    "gn:asciiname":"Cherri",
    "gn:country_code":"IR",
    "gn:dem":1672,
    "gn:feature_class":"P",
    "gn:feature_code":"PPL",
    "gn:name":"Cherr\u012b",
    "gn:population":0,
    "gn:timezone":"Asia/Tehran",
    "iso:country":"IR",
    "name:fas_x_preferred":[
        "Cherr\u012b"
    ],
    "name:fas_x_variant":[
        "\u0686\u0631\u06cc"
    ],
    "wof:name":"Cherri",
    "wof:placetype":"locality"
},
  "geometry": {"coordinates":[50.62189,31.33973],"type":"Point"}
}