{
  "type": "Feature",
  "properties": {
    "gn:admin1_code":"1.0",
    "gn:asciiname":"Dowlpambeh",
    "gn:country_code":"IR",
    "gn:dem":1741,
    "gn:feature_class":"P",
    "gn:feature_code":"PPL",
    "gn:name":"Dowlpambeh",
    "gn:population":0,
    "gn:timezone":"Asia/Tehran",
    "iso:country":"IR",
    "name:fas_x_preferred":[
        "\u062f\u064f\u0648\u0644\u067e\u064e\u0646\u0628\u0648"
    ],
    "name:fas_x_variant":[
        "\u062f\u0648\u0644\u067e\u0645\u0628\u0647",
        "Dowlpanb\u016b"
    ],
    "wof:name":"Dowlpambeh",
    "wof:placetype":"locality"
},
  "geometry": {"coordinates":[45.7099,36.5803],"type":"Point"}
}