{
  "type": "Feature",
  "properties": {
    "gn:admin1_code":"22",
    "gn:asciiname":"Dalaki",
    "gn:country_code":"IR",
    "gn:dem":106,
    "gn:feature_class":"P",
    "gn:feature_code":"PPL",
    "gn:name":"D\u0101lak\u012b",
    "gn:population":0,
    "gn:timezone":"Asia/Tehran",
    "iso:country":"IR",
    "name:fas_x_preferred":[
        "\u062f\u0627\u0644\u0643\u06cc"
    ],
    "name:fas_x_variant":[
        "D\u0101lak\u012b"
    ],
    "name:und_x_variant":[
        "Daliki"
    ],
    "wof:name":"Dalaki",
    "wof:placetype":"locality"
},
  "geometry": {"coordinates":[51.2931,29.4294],"type":"Point"}
}