{
  "type": "Feature",
  "properties": {
    "gn:admin1_code":"40",
    "gn:asciiname":"Deh Dork",
    "gn:country_code":"IR",
    "gn:dem":2309,
    "gn:feature_class":"P",
    "gn:feature_code":"PPL",
    "gn:name":"Deh Dork",
    "gn:population":0,
    "gn:timezone":"Asia/Tehran",
    "iso:country":"IR",
    "name:fas_x_preferred":[
        "\u062f\u0650\u0647 \u062f\u064f\u0631\u0643"
    ],
    "wof:name":"Deh Dork",
    "wof:placetype":"locality"
},
  "geometry": {"coordinates":[55.95,31.78333],"type":"Point"}
}