{
  "type": "Feature",
  "properties": {
    "gn:admin1_code":"37",
    "gn:asciiname":"Kolijeh",
    "gn:country_code":"IR",
    "gn:dem":61,
    "gn:feature_class":"P",
    "gn:feature_code":"PPL",
    "gn:name":"Kol\u012bjeh",
    "gn:population":0,
    "gn:timezone":"Asia/Tehran",
    "iso:country":"IR",
    "name:fas_x_preferred":[
        "Kol\u012bcheh"
    ],
    "name:fas_x_variant":[
        "\u06a9\u0644\u064a\u062c\u0647"
    ],
    "name:und_x_variant":[
        "Kol\u012bjeh",
        "Goll\u012bjeh",
        "Gol\u012bjeh"
    ],
    "wof:name":"Kolijeh",
    "wof:placetype":"locality"
},
  "geometry": {"coordinates":[55.11238,37.92311],"type":"Point"}
}