{
  "type": "Feature",
  "properties": {
    "gn:admin1_code":"16.0",
    "gn:asciiname":"Chuman",
    "gn:country_code":"IR",
    "gn:dem":907,
    "gn:elevation":"0.0",
    "gn:feature_class":"P",
    "gn:feature_code":"PPL",
    "gn:name":"Ch\u016bm\u0101n",
    "gn:population":0,
    "gn:timezone":"Asia/Tehran",
    "iso:country":"IR",
    "name:ara_x_preferred":[
        "\u062a\u0634\u0648\u0645\u0627\u0646"
    ],
    "name:ceb_x_preferred":[
        "Ch\u016bm\u0101n"
    ],
    "name:ckb_x_preferred":[
        "\u0686\u06c6\u0645\u0627\u0646"
    ],
    "name:fas_x_preferred":[
        "Ch\u016bm\u0101n"
    ],
    "name:fas_x_variant":[
        "\u0686\u0648\u0645\u0627\u0646"
    ],
    "name:swe_x_preferred":[
        "Ch\u016bm\u0101n"
    ],
    "wof:name":"Chuman",
    "wof:placetype":"locality"
},
  "geometry": {"coordinates":[45.5827,35.9736],"type":"Point"}
}