{
  "type": "Feature",
  "properties": {
    "gn:admin1_code":"23",
    "gn:asciiname":"Kalam",
    "gn:country_code":"IR",
    "gn:dem":1873,
    "gn:feature_class":"P",
    "gn:feature_code":"PPL",
    "gn:name":"Kal\u0101m",
    "gn:population":0,
    "gn:timezone":"Asia/Tehran",
    "iso:country":"IR",
    "name:als_x_preferred":[
        "Kal\u0101m"
    ],
    "name:ara_x_preferred":[
        "\u0639\u0644\u0645 \u0627\u0644\u0643\u0644\u0627\u0645"
    ],
    "name:ast_x_preferred":[
        "Calam"
    ],
    "name:azb_x_preferred":[
        "\u06a9\u0644\u0627\u0645 \u0628\u06cc\u0644\u06af\u06cc\u200c\u0633\u06cc"
    ],
    "name:aze_x_preferred":[
        "K\u0259lam"
    ],
    "name:cat_x_preferred":[
        "Kalam"
    ],
    "name:deu_x_preferred":[
        "Kal\u0101m"
    ],
    "name:diq_x_preferred":[
        "Kelam"
    ],
    "name:div_x_preferred":[
        "\u0786\u07a6\u078d\u07a7\u0789\u07b0"
    ],
    "name:epo_x_preferred":[
        "Kalam"
    ],
    "name:fas_x_preferred":[
        "\u0643\u064e\u0644\u0627\u0645"
    ],
    "name:fas_x_variant":[
        "Kal\u0101m",
        "\u0639\u0644\u0645 \u06a9\u0644\u0627\u0645"
    ],
    "name:fin_x_preferred":[
        "Kalam"
    ],
    "name:fra_x_preferred":[
        "Kal\u00e2m"
    ],
    "name:heb_x_preferred":[
        "\u05db\u05dc\u05d0\u05dd"
    ],
    "name:hun_x_preferred":[
        "Kal\u00e1m"
    ],
    "name:hye_x_preferred":[
        "\u0554\u0561\u056c\u0561\u0574"
    ],
    "name:ind_x_preferred":[
        "Ilmu kalam"
    ],
    "name:ita_x_preferred":[
        "Kal\u0101m"
    ],
    "name:jpn_x_preferred":[
        "\u30ab\u30e9\u30fc\u30e0"
    ],
    "name:kaz_x_preferred":[
        "\u041a\u0430\u043b\u0430\u043c"
    ],
    "name:kur_x_preferred":[
        "Kelam"
    ],
    "name:mal_x_preferred":[
        "\u0d07\u0d7d\u0d2e\u0d41\u0d7d \u0d15\u0d32\u0d3e\u0d02"
    ],
    "name:mkd_x_preferred":[
        "\u041a\u0435\u043b\u0430\u043c"
    ],
    "name:msa_x_preferred":[
        "Ilmu kalam"
    ],
    "name:nld_x_preferred":[
        "Kalam"
    ],
    "name:nor_x_preferred":[
        "Kalam"
    ],
    "name:pol_x_preferred":[
        "Kalam"
    ],
    "name:por_x_preferred":[
        "Calam"
    ],
    "name:ron_x_preferred":[
        "Kalam"
    ],
    "name:rus_x_preferred":[
        "\u041a\u0430\u043b\u0430\u043c"
    ],
    "name:slk_x_preferred":[
        "Kal\u00e1m"
    ],
    "name:spa_x_preferred":[
        "Kalam"
    ],
    "name:swe_x_preferred":[
        "Kalam"
    ],
    "name:tam_x_preferred":[
        "\u0b95\u0bb2\u0bbe\u0bae\u0bcd"
    ],
    "name:tat_x_preferred":[
        "\u041a\u0430\u043b\u0430\u043c"
    ],
    "name:tgk_x_preferred":[
        "\u041a\u0430\u043b\u043e\u043c"
    ],
    "name:tur_x_preferred":[
        "Kel\u00e2m"
    ],
    "name:uig_x_preferred":[
        "\u0626\u0649\u0644\u0645\u0649 \u0643\u06d5\u0644\u0627\u0645"
    ],
    "name:ukr_x_preferred":[
        "\u041a\u0430\u043b\u0430\u043c"
    ],
    "name:urd_x_preferred":[
        "\u0639\u0644\u0645 \u06a9\u0644\u0627\u0645"
    ],
    "name:zho_x_preferred":[
        "\u4f0a\u65af\u5170\u6559\u4e49\u5b66"
    ],
    "wof:name":"Kalam",
    "wof:placetype":"locality"
},
  "geometry": {"coordinates":[47.98333,34.15],"type":"Point"}
}