{
  "type": "Feature",
  "properties": {
    "gn:admin1_code":"37.0",
    "gn:asciiname":"Charabad",
    "gn:country_code":"IR",
    "gn:dem":323,
    "gn:feature_class":"P",
    "gn:feature_code":"PPL",
    "gn:name":"Ch\u0101r\u0101b\u0101d",
    "gn:population":0,
    "gn:timezone":"Asia/Tehran",
    "iso:country":"IR",
    "name:fas_x_preferred":[
        "\u0686\u0627\u0631 \u0622\u0628\u0627\u062f"
    ],
    "name:fas_x_variant":[
        "Ch\u0101r\u0101b\u0101d"
    ],
    "wof:name":"Charabad",
    "wof:placetype":"locality"
},
  "geometry": {"coordinates":[55.55,37.48333],"type":"Point"}
}