{
  "type": "Feature",
  "properties": {
    "gn:admin1_code":"41",
    "gn:asciiname":"Ranishk",
    "gn:country_code":"IR",
    "gn:dem":2130,
    "gn:feature_class":"P",
    "gn:feature_code":"PPL",
    "gn:name":"Ran\u012bshk",
    "gn:population":0,
    "gn:timezone":"Asia/Tehran",
    "iso:country":"IR",
    "name:fas_x_preferred":[
        "Ran\u012bshk"
    ],
    "name:fas_x_variant":[
        "\u0631\u0646\u06cc\u0634\u06a9"
    ],
    "name:und_x_variant":[
        "\u0631\u0646\u06cc\u0634\u06a9"
    ],
    "wof:name":"Ranishk",
    "wof:placetype":"locality"
},
  "geometry": {"coordinates":[59.49195,33.24529],"type":"Point"}
}