{
  "type": "Feature",
  "properties": {
    "gn:admin1_code":"7",
    "gn:asciiname":"Mohammad Taheri",
    "gn:country_code":"IR",
    "gn:dem":476,
    "gn:feature_class":"P",
    "gn:feature_code":"PPL",
    "gn:name":"Mo\u1e29ammad \u0162\u0101her\u012b",
    "gn:population":0,
    "gn:timezone":"Asia/Tehran",
    "iso:country":"IR",
    "name:fas_x_preferred":[
        "\u0645\u062d\u0645\u062f \u0637\u0627\u0647\u0631\u06cc"
    ],
    "name:fas_x_variant":[
        "Qal\u2018eh-e Mo\u1e29ammad \u0162\u0101her",
        "Mo\u1e29ammad \u0162\u0101her\u012b",
        "\u0642\u0644\u0639\u0647 \u0645\u062d\u0645\u062f \u0637\u0627\u0647\u0631\u06cc"
    ],
    "name:und_x_variant":[
        "Qal\u2018eh-e Mo\u1e29ammad \u0162\u0101her\u012b"
    ],
    "wof:name":"Mohammad Taheri",
    "wof:placetype":"locality"
},
  "geometry": {"coordinates":[53.2518,27.5165],"type":"Point"}
}