{
  "type": "Feature",
  "properties": {
    "gn:admin1_code":"1",
    "gn:asciiname":"Qareh Papaq",
    "gn:country_code":"IR",
    "gn:dem":1275,
    "gn:feature_class":"P",
    "gn:feature_code":"PPL",
    "gn:name":"Qareh P\u0101p\u0101q",
    "gn:population":0,
    "gn:timezone":"Asia/Tehran",
    "iso:country":"IR",
    "name:azb_x_preferred":[
        "\u0642\u0631\u0647\u200c\u067e\u0627\u067e\u0627\u0642"
    ],
    "name:aze_x_preferred":[
        "Qarapapaq"
    ],
    "name:ceb_x_preferred":[
        "Qareh P\u0101p\u0101q"
    ],
    "name:fas_x_preferred":[
        "\u0642\u064e\u0631\u064e\u0647 \u067e\u0627\u067e\u0627\u0642"
    ],
    "name:fas_x_variant":[
        "\u0642\u0631\u0647 \u067e\u0627\u067e\u0627\u0642",
        "Qarah P\u0101p\u0101q",
        "Qareh P\u0101p\u0101q"
    ],
    "name:msa_x_preferred":[
        "Qareh Papaq"
    ],
    "name:swe_x_preferred":[
        "Qareh P\u0101p\u0101q"
    ],
    "wof:name":"Qareh Papaq",
    "wof:placetype":"locality"
},
  "geometry": {"coordinates":[45.849,37.0793],"type":"Point"}
}