{
  "type": "Feature",
  "properties": {
    "gn:admin1_code":"7",
    "gn:asciiname":"Bavarian",
    "gn:country_code":"IR",
    "gn:dem":1555,
    "gn:feature_class":"P",
    "gn:feature_code":"PPL",
    "gn:name":"B\u0101var\u012b\u0101n",
    "gn:population":0,
    "gn:timezone":"Asia/Tehran",
    "iso:country":"IR",
    "name:ara_x_preferred":[
        "\u0628\u0627\u0648\u0631\u064a\u0627\u0646"
    ],
    "name:fas_x_preferred":[
        "B\u0101var\u012b\u0101n"
    ],
    "name:fas_x_variant":[
        "\u0628\u0627\u0648\u0631\u06cc\u0627\u0646"
    ],
    "name:msa_x_preferred":[
        "Bavarian"
    ],
    "name:und_x_variant":[
        "B\u0101varey\u0101n",
        "B\u0101vary\u0101n",
        "B\u0101var\u012by\u0101n"
    ],
    "wof:name":"Bavarian",
    "wof:placetype":"locality"
},
  "geometry": {"coordinates":[52.5509,29.0733],"type":"Point"}
}