{
  "type": "Feature",
  "properties": {
    "gn:admin1_code":"38",
    "gn:asciiname":"Khoshkeh Chal",
    "gn:country_code":"IR",
    "gn:dem":2409,
    "gn:feature_class":"P",
    "gn:feature_code":"PPL",
    "gn:name":"Khoshkeh Ch\u0101l",
    "gn:population":0,
    "gn:timezone":"Asia/Tehran",
    "iso:country":"IR",
    "name:ceb_x_preferred":[
        "Khoshkeh Ch\u0101l"
    ],
    "name:fas_x_preferred":[
        "Khoshkeh Ch\u0101l"
    ],
    "name:fas_x_variant":[
        "Khoshk Ch\u0101l",
        "\u062e\u0634\u0643\u0647 \u0686\u0627\u0644",
        "\u062e\u0634\u0643 \u0686\u0627\u0644",
        "\u062e\u0634\u0643\u0686\u0627\u0644",
        "\u062e\u0634\u06a9\u0686\u0627\u0644"
    ],
    "name:swe_x_preferred":[
        "Khoshkeh Ch\u0101l"
    ],
    "name:und_x_variant":[
        "Khoshkch\u0101l"
    ],
    "wof:name":"Khoshkeh Chal",
    "wof:placetype":"locality"
},
  "geometry": {"coordinates":[50.57507,36.4633],"type":"Point"}
}