{
  "type": "Feature",
  "properties": {
    "gn:admin1_code":"34.0",
    "gn:asciiname":"Andarpa",
    "gn:country_code":"IR",
    "gn:dem":2247,
    "gn:feature_class":"P",
    "gn:feature_code":"PPL",
    "gn:name":"Andarp\u0101",
    "gn:population":0,
    "gn:timezone":"Asia/Tehran",
    "iso:country":"IR",
    "name:ceb_x_preferred":[
        "Andarp\u0101"
    ],
    "name:fas_x_preferred":[
        "Andarp\u0101"
    ],
    "name:fas_x_variant":[
        "\u0627\u0646\u062f\u0631\u067e\u0627"
    ],
    "name:swe_x_preferred":[
        "Andarp\u0101"
    ],
    "name:ukr_x_preferred":[
        "\u0410\u043d\u0434\u0430\u0440\u043f\u0430"
    ],
    "wof:name":"Andarpa",
    "wof:placetype":"locality"
},
  "geometry": {"coordinates":[49.86886,33.80177],"type":"Point"}
}