{
  "type": "Feature",
  "properties": {
    "gn:admin1_code":"10",
    "gn:asciiname":"Pahneh Bor",
    "gn:country_code":"IR",
    "gn:dem":1012,
    "gn:feature_class":"P",
    "gn:feature_code":"PPL",
    "gn:name":"Pahneh Bor",
    "gn:population":0,
    "gn:timezone":"Asia/Tehran",
    "iso:country":"IR",
    "name:fas_x_preferred":[
        "\u067e\u0647\u0646\u0647 \u0628\u0631"
    ],
    "name:und_x_variant":[
        "Pan\u0101bar"
    ],
    "wof:name":"Pahneh Bor",
    "wof:placetype":"locality"
},
  "geometry": {"coordinates":[46.6734,33.6515],"type":"Point"}
}