{
  "type": "Feature",
  "properties": {
    "gn:admin1_code":"4.0",
    "gn:asciiname":"Dargeyabad",
    "gn:cc2":"IR",
    "gn:country_code":"IR",
    "gn:dem":1807,
    "gn:feature_class":"P",
    "gn:feature_code":"PPL",
    "gn:name":"Dargey\u0101b\u0101d",
    "gn:population":0,
    "gn:timezone":"Asia/Tehran",
    "iso:country":"IR",
    "name:fas_x_preferred":[
        "Dargey\u0101b\u0101d"
    ],
    "name:und_x_variant":[
        "Dorg\u012b\u0101b\u0101d"
    ],
    "wof:name":"Dargeyabad",
    "wof:placetype":"locality"
},
  "geometry": {"coordinates":[60.73333,29.05],"type":"Point"}
}