{
  "type": "Feature",
  "properties": {
    "gn:admin1_code":"1.0",
    "gn:asciiname":"Duliniyeh",
    "gn:country_code":"IR",
    "gn:dem":1803,
    "gn:feature_class":"P",
    "gn:feature_code":"PPL",
    "gn:name":"D\u016bl\u012bn\u012byeh",
    "gn:population":0,
    "gn:timezone":"Asia/Tehran",
    "iso:country":"IR",
    "name:fas_x_preferred":[
        "\u062f\u0648\u0644\u06cc\u0646\u06cc\u0647"
    ],
    "name:fas_x_variant":[
        "D\u016bl\u012bn\u012byeh"
    ],
    "wof:name":"Duliniyeh",
    "wof:placetype":"locality"
},
  "geometry": {"coordinates":[45.1553,36.5441],"type":"Point"}
}