{
  "type": "Feature",
  "properties": {
    "gn:admin1_code":"29",
    "gn:asciiname":"Galumaran",
    "gn:country_code":"IR",
    "gn:dem":785,
    "gn:feature_class":"P",
    "gn:feature_code":"PPL",
    "gn:name":"Gal\u016bm\u0101r\u0101n",
    "gn:population":0,
    "gn:timezone":"Asia/Tehran",
    "iso:country":"IR",
    "name:fas_x_preferred":[
        "Gal\u016bm\u0101r\u0101n"
    ],
    "wof:name":"Galumaran",
    "wof:placetype":"locality"
},
  "geometry": {"coordinates":[57.65,28.66667],"type":"Point"}
}