{
  "type": "Feature",
  "properties": {
    "gn:admin1_code":"15",
    "gn:asciiname":"Qal`eh Makhrubeh",
    "gn:country_code":"IR",
    "gn:dem":774,
    "gn:feature_class":"P",
    "gn:feature_code":"PPL",
    "gn:name":"Qal\u2018eh Makhr\u016bbeh",
    "gn:population":0,
    "gn:timezone":"Asia/Tehran",
    "iso:country":"IR",
    "name:fas_x_preferred":[
        "Qal\u2018eh Sorkheh"
    ],
    "name:fas_x_variant":[
        "\u0642\u0644\u0639\u0647 \u0633\u0631\u062e\u0647",
        "\u0642\u0644\u0639\u0647 \u0645\u062e\u0631\u0648\u0628\u0647"
    ],
    "name:und_x_variant":[
        "Qal\u2018eh Makhr\u016bbeh"
    ],
    "wof:name":"Qal`eh Makhrubeh",
    "wof:placetype":"locality"
},
  "geometry": {"coordinates":[49.72619,31.83822],"type":"Point"}
}