{
  "type": "Feature",
  "properties": {
    "gn:admin1_code":"42",
    "gn:asciiname":"Kalateh-ye Kal Sar",
    "gn:country_code":"IR",
    "gn:dem":1357,
    "gn:feature_class":"P",
    "gn:feature_code":"PPL",
    "gn:name":"Kal\u0101teh-ye K\u0101l S\u0101r",
    "gn:population":0,
    "gn:timezone":"Asia/Tehran",
    "iso:country":"IR",
    "name:fas_x_preferred":[
        "Kal\u0101teh-ye K\u0101l S\u0101r"
    ],
    "wof:name":"Kalateh-ye Kal Sar",
    "wof:placetype":"locality"
},
  "geometry": {"coordinates":[59.37583000000001,35.29472],"type":"Point"}
}