{
  "type": "Feature",
  "properties": {
    "gn:admin1_code":"40",
    "gn:asciiname":"Mirza Hakim",
    "gn:country_code":"IR",
    "gn:dem":1092,
    "gn:feature_class":"P",
    "gn:feature_code":"PPL",
    "gn:name":"M\u012brz\u0101 \u1e28ak\u012bm",
    "gn:population":0,
    "gn:timezone":"Asia/Tehran",
    "iso:country":"IR",
    "name:fas_x_preferred":[
        "\u0645\u064a\u0631\u0632\u0627 \u062d\u0643\u064a\u0645"
    ],
    "name:fas_x_variant":[
        "\u0645\u064a\u0631\u0632\u0627 \u062d\u0627\u0643\u0650\u0645",
        "M\u012brz\u0101 \u1e28ak\u012bm"
    ],
    "name:und_x_variant":[
        "M\u012brz\u0101 \u1e28\u0101kem"
    ],
    "wof:name":"Mirza Hakim",
    "wof:placetype":"locality"
},
  "geometry": {"coordinates":[53.8304,32.3913],"type":"Point"}
}