{
  "type": "Feature",
  "properties": {
    "gn:admin1_code":"8.0",
    "gn:asciiname":"Kuleh Sareh",
    "gn:country_code":"IR",
    "gn:dem":140,
    "gn:feature_class":"P",
    "gn:feature_code":"PPL",
    "gn:name":"K\u016bleh Sareh",
    "gn:population":0,
    "gn:timezone":"Asia/Tehran",
    "iso:country":"IR",
    "name:fas_x_preferred":[
        "K\u016bleh Sareh"
    ],
    "name:fas_x_variant":[
        "\u06a9\u0648\u0644\u0647 \u0633\u0631\u0647",
        "\u06a9\u0648\u0644\u0647 \u0633\u0627\u0631\u0647"
    ],
    "name:und_x_variant":[
        "Khasehp\u012bsht"
    ],
    "wof:name":"Kuleh Sareh",
    "wof:placetype":"locality"
},
  "geometry": {"coordinates":[48.90413,37.71105],"type":"Point"}
}