{
  "type": "Feature",
  "properties": {
    "gn:admin1_code":"11.0",
    "gn:asciiname":"Darkhaneh",
    "gn:country_code":"IR",
    "gn:dem":21,
    "gn:feature_class":"P",
    "gn:feature_code":"PPL",
    "gn:name":"Darkh\u0101neh",
    "gn:population":0,
    "gn:timezone":"Asia/Tehran",
    "iso:country":"IR",
    "name:fas_x_preferred":[
        "\u062f\u0631\u062e\u0627\u0646\u0647"
    ],
    "name:fas_x_variant":[
        "Darkh\u0101neh"
    ],
    "wof:name":"Darkhaneh",
    "wof:placetype":"locality"
},
  "geometry": {"coordinates":[56.9919,27.1907],"type":"Point"}
}