{
  "type": "Feature",
  "properties": {
    "gn:admin1_code":"15",
    "gn:asciiname":"Cham Qasem`ali-ye Sofla",
    "gn:country_code":"IR",
    "gn:dem":394,
    "gn:feature_class":"P",
    "gn:feature_code":"PPL",
    "gn:name":"Cham Q\u0101sem\u2018al\u012b-ye Sofl\u00e1",
    "gn:population":0,
    "gn:timezone":"Asia/Tehran",
    "iso:country":"IR",
    "name:fas_x_preferred":[
        "Cham Q\u0101sem \u2018Al\u012b"
    ],
    "name:fas_x_variant":[
        "Cham Q\u0101sem\u2018al\u012b",
        "\u0686\u0645 \u0642\u0627\u0633\u0645\u0639\u0644\u06cc",
        "\u0686\u0645 \u0642\u0627\u0633\u0645\u0639\u0644\u06cc \u0633\u0641\u0644\u06cc"
    ],
    "name:und_x_variant":[
        "\u0686\u0645 \u0642\u0627\u0633\u0645\u0639\u0644\u06cc",
        "Cham Q\u0101sem\u2018al\u012b-ye Sofl\u00e1"
    ],
    "wof:name":"Cham Qasem`ali-ye Sofla",
    "wof:placetype":"locality"
},
  "geometry": {"coordinates":[49.7565,31.38651],"type":"Point"}
}