{
  "type": "Feature",
  "properties": {
    "gn:admin1_code":"35.0",
    "gn:asciiname":"Kharabeh-ye Mian Rud",
    "gn:country_code":"IR",
    "gn:dem":25,
    "gn:feature_class":"P",
    "gn:feature_code":"PPL",
    "gn:name":"Khar\u0101beh-ye M\u012b\u0101n R\u016bd",
    "gn:population":0,
    "gn:timezone":"Asia/Tehran",
    "iso:country":"IR",
    "name:fas_x_preferred":[
        "\u062e\u0631\u0627\u0628\u0647 \u0645\u064a\u0627\u0646 \u0631\u0648\u062f"
    ],
    "name:fas_x_variant":[
        "Khar\u0101beh-ye M\u012b\u0101n R\u016bd"
    ],
    "wof:name":"Kharabeh-ye Mian Rud",
    "wof:placetype":"locality"
},
  "geometry": {"coordinates":[52.37106,36.53164],"type":"Point"}
}