{
  "type": "Feature",
  "properties": {
    "gn:admin1_code":"4",
    "gn:asciiname":"Narun",
    "gn:country_code":"IR",
    "gn:dem":1948,
    "gn:feature_class":"P",
    "gn:feature_code":"PPL",
    "gn:name":"N\u0101r\u016bn",
    "gn:population":0,
    "gn:timezone":"Asia/Tehran",
    "iso:country":"IR",
    "name:fas_x_preferred":[
        "\u0646\u0627\u0631\u0648\u0646"
    ],
    "name:fas_x_variant":[
        "N\u0101r\u016bn"
    ],
    "wof:name":"Narun",
    "wof:placetype":"locality"
},
  "geometry": {"coordinates":[60.9001,28.5793],"type":"Point"}
}