{
  "type": "Feature",
  "properties": {
    "iso:country":"IR",
    "name:ara_x_preferred":[
        "\u062e\u0631\u0627\u0646\u0642"
    ],
    "name:ceb_x_preferred":[
        "Khar\u0101naq"
    ],
    "name:ell_x_preferred":[
        "\u039a\u03b1\u03c1\u03b1\u03bd\u03ac\u03ba"
    ],
    "name:eng_x_preferred":[
        "Kharanaq"
    ],
    "name:epo_x_preferred":[
        "\u0124aranak"
    ],
    "name:fas_x_preferred":[
        "\u062e\u0631\u0627\u0646\u0642"
    ],
    "name:fas_x_variant":[
        "\u062e\u064f\u0648\u0631\u0627\u0646\u0650\u0642",
        "\u062e\u064e\u0631\u0627\u0646\u0650\u0642",
        "\u062e\u064e\u0631\u0627\u0646\u064f\u0642",
        "Khar\u0101naq",
        "Khur\u016bnaq",
        "Khowr\u0101neq",
        "Khar\u0101noq",
        "Khar\u0101neq"
    ],
    "name:fra_x_preferred":[
        "Kharanaq"
    ],
    "name:ita_x_preferred":[
        "Kharanaq"
    ],
    "name:nld_x_preferred":[
        "Kharanaq"
    ],
    "name:rus_x_preferred":[
        "\u0425\u0435\u0440\u0430\u043d\u0435\u043a"
    ],
    "name:swe_x_preferred":[
        "Khar\u0101naq"
    ],
    "name:unk_x_variant":[
        "Khar\u0101neq"
    ],
    "qs:gn_country":"IR",
    "qs:gn_fcode":"PPL",
    "qs:gn_pop":0,
    "qs:name":"Kharanaq",
    "qs:name_adm0":"Iran",
    "qs:name_adm1":"Yazd",
    "qs:photos":39,
    "qs:photos_1k":8,
    "qs:photos_9k":1,
    "qs:photos_9r":2,
    "qs:photos_all":39,
    "qs:photos_sr":2,
    "qs:placetype":"Town",
    "qs:pop_sr":"4",
    "qs:woe_adm0":23424851,
    "wd:wordcount":109,
    "wof:name":"Kharanaq",
    "wof:placetype":"locality"
},
  "geometry": {"coordinates":[54.66575,32.3462],"type":"Point"}
}