{
  "type": "Feature",
  "properties": {
    "gn:admin1_code":"13",
    "gn:asciiname":"Sarab-e Khoshkeh-ye Sofla",
    "gn:country_code":"IR",
    "gn:dem":1300,
    "gn:feature_class":"P",
    "gn:feature_code":"PPL",
    "gn:name":"Sar\u0101b-e Khoshkeh-ye Sofl\u00e1",
    "gn:population":0,
    "gn:timezone":"Asia/Tehran",
    "iso:country":"IR",
    "name:fas_x_preferred":[
        "\u0633\u0631\u0627\u0628 \u062e\u0634\u06a9\u0647 \u067e\u0627\u0626\u06cc\u0646"
    ],
    "name:fas_x_variant":[
        "Sar\u0101b-e Khoshkeh-ye Sofl\u00e1",
        "Sar\u0101b Khoshkeh-ye P\u0101\u2019\u012bn",
        "\u0633\u0631\u0627\u0628 \u062e\u0634\u06a9\u0647 \u0633\u0641\u0644\u06cc"
    ],
    "wof:name":"Sarab-e Khoshkeh-ye Sofla",
    "wof:placetype":"locality"
},
  "geometry": {"coordinates":[47.0256,34.3965],"type":"Point"}
}