{
  "type": "Feature",
  "properties": {
    "gn:admin1_code":"16.0",
    "gn:asciiname":"Sarberah",
    "gn:country_code":"IR",
    "gn:dem":1456,
    "gn:feature_class":"P",
    "gn:feature_code":"PPL",
    "gn:name":"Sarber\u0101h",
    "gn:population":0,
    "gn:timezone":"Asia/Tehran",
    "iso:country":"IR",
    "name:fas_x_preferred":[
        "\u0633\u064e\u0631\u0628\u0650\u0631\u0627\u0647"
    ],
    "name:fas_x_variant":[
        "Sarber\u0101h"
    ],
    "wof:name":"Sarberah",
    "wof:placetype":"locality"
},
  "geometry": {"coordinates":[46.84917,35.10472],"type":"Point"}
}