{
  "type": "Feature",
  "properties": {
    "gn:admin1_code":"4.0",
    "gn:asciiname":"Kuhpareh",
    "gn:cc2":"IR",
    "gn:country_code":"IR",
    "gn:dem":1295,
    "gn:feature_class":"P",
    "gn:feature_code":"PPL",
    "gn:name":"K\u016bhp\u0101reh",
    "gn:population":0,
    "gn:timezone":"Asia/Tehran",
    "iso:country":"IR",
    "name:fas_x_preferred":[
        "K\u016bhp\u0101reh"
    ],
    "name:und_x_variant":[
        "Koh P\u0101r\u0101",
        "K\u016bh B\u0101reh"
    ],
    "wof:name":"Kuhpareh",
    "wof:placetype":"locality"
},
  "geometry": {"coordinates":[61.72861,27.17194000000001],"type":"Point"}
}