{
  "type": "Feature",
  "properties": {
    "gn:admin1_code":"8",
    "gn:asciiname":"Asiab Sar",
    "gn:country_code":"IR",
    "gn:dem":-1,
    "gn:feature_class":"P",
    "gn:feature_code":"PPL",
    "gn:name":"\u0100s\u012b\u0101b Sar",
    "gn:population":0,
    "gn:timezone":"Asia/Tehran",
    "iso:country":"IR",
    "name:fas_x_preferred":[
        "\u0622\u0633\u06cc\u0627\u0628 \u0633\u0631"
    ],
    "name:fas_x_variant":[
        "\u0100s\u012b\u0101b Sar",
        "\u0622\u0633\u06cc\u0627\u0628\u200c\u0633\u0631"
    ],
    "name:msa_x_preferred":[
        "Asiab Sar"
    ],
    "name:ukr_x_preferred":[
        "\u0410\u0441\u0456\u044f\u0431-\u0421\u0430\u0440"
    ],
    "name:und_x_variant":[
        "\u0100s\u012b\u0101b Sar"
    ],
    "wof:name":"Asiab Sar",
    "wof:placetype":"locality"
},
  "geometry": {"coordinates":[49.21793,37.37088],"type":"Point"}
}