{
  "type": "Feature",
  "properties": {
    "gn:admin1_code":"15",
    "gn:asciiname":"Karta",
    "gn:cc2":"IR",
    "gn:country_code":"IR",
    "gn:dem":1310,
    "gn:feature_class":"P",
    "gn:feature_code":"PPL",
    "gn:name":"K\u0101rt\u0101",
    "gn:population":0,
    "gn:timezone":"Asia/Tehran",
    "iso:country":"IR",
    "name:fas_x_preferred":[
        "K\u0101rt\u0101"
    ],
    "name:und_x_variant":[
        "Kartaz"
    ],
    "wof:name":"Karta",
    "wof:placetype":"locality"
},
  "geometry": {"coordinates":[49.74167,32.24278],"type":"Point"}
}