{
  "type": "Feature",
  "properties": {
    "gn:admin1_code":"15",
    "gn:asciiname":"Karta",
    "gn:cc2":"IR",
    "gn:country_code":"IR",
    "gn:dem":1310,
    "gn:feature_class":"P",
    "gn:feature_code":"PPL",
    "gn:name":"K\u0101rt\u0101",
    "gn:population":0,
    "gn:timezone":"Asia/Tehran",
    "iso:country":"IR",
    "name:bos_x_preferred":[
        "Karta"
    ],
    "name:ceb_x_preferred":[
        "Karta"
    ],
    "name:ces_x_preferred":[
        "Karta"
    ],
    "name:epo_x_preferred":[
        "Karto"
    ],
    "name:fas_x_preferred":[
        "K\u0101rt\u0101"
    ],
    "name:heb_x_preferred":[
        "\u05e7\u05e8\u05ea\u05d0"
    ],
    "name:hrv_x_preferred":[
        "Karta"
    ],
    "name:ido_x_preferred":[
        "Karto"
    ],
    "name:nld_x_preferred":[
        "Karta"
    ],
    "name:pol_x_preferred":[
        "Karta"
    ],
    "name:que_x_preferred":[
        "Karta"
    ],
    "name:slk_x_preferred":[
        "Karta"
    ],
    "name:slv_x_preferred":[
        "Karta"
    ],
    "name:swe_x_preferred":[
        "Karta"
    ],
    "name:tgl_x_preferred":[
        "Karta"
    ],
    "name:und_x_variant":[
        "Kartaz"
    ],
    "wof:name":"Karta",
    "wof:placetype":"locality"
},
  "geometry": {"coordinates":[49.74167,32.24278],"type":"Point"}
}