{
  "type": "Feature",
  "properties": {
    "gn:admin1_code":"15.0",
    "gn:asciiname":"Boneh-ye Jaz `Ali",
    "gn:country_code":"IR",
    "gn:dem":570,
    "gn:feature_class":"P",
    "gn:feature_code":"PPLL",
    "gn:name":"Boneh-ye J\u0101z \u2018Al\u012b",
    "gn:population":0,
    "gn:timezone":"Asia/Tehran",
    "iso:country":"IR",
    "name:fas_x_preferred":[
        "\u0628\u0646\u0647 \u062c\u0627\u0632 \u0639\u0644\u06cc"
    ],
    "name:fas_x_variant":[
        "Boneh-ye J\u0101z \u2018Al\u012b"
    ],
    "wof:name":"Boneh-ye Jaz `Ali",
    "wof:placetype":"locality"
},
  "geometry": {"coordinates":[48.7771,32.5473],"type":"Point"}
}