{
  "type": "Feature",
  "properties": {
    "gn:admin1_code":"42",
    "gn:asciiname":"Andanjerd",
    "gn:country_code":"IR",
    "gn:dem":1060,
    "gn:feature_class":"P",
    "gn:feature_code":"PPL",
    "gn:name":"Andanjerd",
    "gn:population":0,
    "gn:timezone":"Asia/Tehran",
    "iso:country":"IR",
    "name:fas_x_preferred":[
        "\u0627\u0646\u062f\u0646\u06af\u0631\u062f"
    ],
    "name:fas_x_variant":[
        "\u0627\u0646\u062f\u0646\u062c\u0631\u062f"
    ],
    "name:und_x_variant":[
        "Andangerd",
        "\u0627\u0646\u062f\u0646\u06af\u0631\u062f",
        "Andanjerd"
    ],
    "wof:name":"Andanjerd",
    "wof:placetype":"locality"
},
  "geometry": {"coordinates":[59.73664,34.88627],"type":"Point"}
}