{
  "type": "Feature",
  "properties": {
    "gn:admin1_code":"38",
    "gn:asciiname":"Shur Ab",
    "gn:country_code":"IR",
    "gn:dem":1777,
    "gn:feature_class":"P",
    "gn:feature_code":"PPL",
    "gn:name":"Sh\u016br \u0100b",
    "gn:population":0,
    "gn:timezone":"Asia/Tehran",
    "iso:country":"IR",
    "name:fas_x_preferred":[
        "\u0634\u0648\u0631\u0627\u0628"
    ],
    "name:fas_x_variant":[
        "Sh\u016br \u0100b"
    ],
    "name:und_x_variant":[
        "Shoorab"
    ],
    "wof:name":"Shur Ab",
    "wof:placetype":"locality"
},
  "geometry": {"coordinates":[49.10512,35.71452],"type":"Point"}
}