{
  "type": "Feature",
  "properties": {
    "gn:admin1_code":"36.0",
    "gn:asciiname":"Qarah Zeki",
    "gn:country_code":"IR",
    "gn:dem":1837,
    "gn:feature_class":"P",
    "gn:feature_code":"PPL",
    "gn:name":"Qarah Zek\u012b",
    "gn:population":0,
    "gn:timezone":"Asia/Tehran",
    "iso:country":"IR",
    "name:azb_x_preferred":[
        "\u0642\u0631\u0647 \u0632\u06a9\u06cc"
    ],
    "name:fas_x_preferred":[
        "\u0642\u0631\u0647 \u0632\u0627\u06a9\u0631"
    ],
    "name:fas_x_variant":[
        "Qareh Zek\u012b",
        "Qarah Z\u0101ker",
        "\u0642\u0631\u0647 \u0632\u06a9\u06cc",
        "\u0642\u0631\u0647\u200c\u0632\u06a9\u06cc"
    ],
    "name:und_x_variant":[
        "Qarah Zek\u012b",
        "Z\u0101ker"
    ],
    "wof:name":"Qarah Zeki",
    "wof:placetype":"locality"
},
  "geometry": {"coordinates":[47.48026,36.65956],"type":"Point"}
}