{
  "type": "Feature",
  "properties": {
    "gn:admin1_code":"41",
    "gn:asciiname":"Eshbak",
    "gn:country_code":"IR",
    "gn:dem":1609,
    "gn:feature_class":"P",
    "gn:feature_code":"PPL",
    "gn:name":"Eshb\u0101k",
    "gn:population":0,
    "gn:timezone":"Asia/Tehran",
    "iso:country":"IR",
    "name:fas_x_preferred":[
        "\u0627\u0634\u06a9"
    ],
    "name:fas_x_variant":[
        "Eshb\u0101k",
        "Ish\u0101k",
        "Ashb\u0101k",
        "\u0627\u0634\u0628\u0627\u06a9"
    ],
    "name:und_x_variant":[
        "Ish\u0101k",
        "Ashb\u0101k",
        "Eshak"
    ],
    "wof:name":"Eshbak",
    "wof:placetype":"locality"
},
  "geometry": {"coordinates":[59.37675,31.60952],"type":"Point"}
}