{
  "type": "Feature",
  "properties": {
    "gn:admin1_code":"23",
    "gn:asciiname":"Khareh Siah",
    "gn:country_code":"IR",
    "gn:dem":1638,
    "gn:feature_class":"P",
    "gn:feature_code":"PPL",
    "gn:name":"Khareh S\u012b\u0101h",
    "gn:population":0,
    "gn:timezone":"Asia/Tehran",
    "iso:country":"IR",
    "name:fas_x_preferred":[
        "\u062e\u0631\u0647 \u0633\u06cc\u0627\u0647"
    ],
    "name:fas_x_variant":[
        "Khareh S\u012b\u0101h"
    ],
    "wof:name":"Khareh Siah",
    "wof:placetype":"locality"
},
  "geometry": {"coordinates":[48.4253,33.7175],"type":"Point"}
}