{
  "type": "Feature",
  "properties": {
    "gn:admin1_code":"16",
    "gn:asciiname":"Amir Aslan",
    "gn:country_code":"IR",
    "gn:dem":1703,
    "gn:feature_class":"P",
    "gn:feature_code":"PPL",
    "gn:name":"Am\u012br A\u015fl\u0101n",
    "gn:population":0,
    "gn:timezone":"Asia/Tehran",
    "iso:country":"IR",
    "name:ara_x_preferred":[
        "\u0623\u0645\u064a\u0631 \u0623\u0635\u0644\u0627\u0646"
    ],
    "name:ceb_x_preferred":[
        "Am\u012br A\u015fl\u0101n"
    ],
    "name:fas_x_preferred":[
        "\u0627\u0645\u06cc\u0631 \u0627\u0635\u0644\u0627\u0646"
    ],
    "name:fas_x_variant":[
        "Am\u012br Asl\u0101n",
        "\u0627\u0645\u064a\u0631 \u0627\u0633\u0644\u0627\u0646",
        "Am\u012br A\u015fl\u0101n",
        "\u0627\u0645\u06cc\u0631\u0627\u0635\u0644\u0627\u0646"
    ],
    "name:swe_x_preferred":[
        "Am\u012br A\u015fl\u0101n"
    ],
    "wof:name":"Amir Aslan",
    "wof:placetype":"locality"
},
  "geometry": {"coordinates":[47.62889000000001,36.30385],"type":"Point"}
}