{
  "type": "Feature",
  "properties": {
    "gn:admin1_code":"4.0",
    "gn:asciiname":"Sitar",
    "gn:country_code":"IR",
    "gn:dem":17,
    "gn:feature_class":"P",
    "gn:feature_code":"PPL",
    "gn:name":"S\u012bt\u0101r",
    "gn:population":0,
    "gn:timezone":"Asia/Tehran",
    "iso:country":"IR",
    "name:ara_x_preferred":[
        "\u0633\u064a\u062a\u0627\u0631"
    ],
    "name:fas_x_preferred":[
        "S\u012bt\u0101r-e \u2018Omar"
    ],
    "name:fas_x_variant":[
        "S\u012bt\u0101r",
        "\u0633\u06cc\u062a\u0627\u0631"
    ],
    "name:und_x_variant":[
        "Sait\u0101r",
        "S\u012bt\u0101r",
        "S\u012bt\u0101r-e \u2018Oly\u0101",
        "\u0633\u06cc\u062a\u0627\u0631"
    ],
    "wof:name":"Sitar",
    "wof:placetype":"locality"
},
  "geometry": {"coordinates":[61.24101999999999,25.42217],"type":"Point"}
}