{
  "type": "Feature",
  "properties": {
    "gn:admin1_code":"41",
    "gn:asciiname":"Kalateh-ye Davud",
    "gn:country_code":"IR",
    "gn:dem":1959,
    "gn:feature_class":"P",
    "gn:feature_code":"PPLF",
    "gn:name":"Kal\u0101teh-ye D\u0101v\u016bd",
    "gn:population":0,
    "gn:timezone":"Asia/Tehran",
    "iso:country":"IR",
    "name:fas_x_preferred":[
        "\u06a9\u0644\u0627\u062a\u0647 \u062f\u0627\u0648\u062f"
    ],
    "name:fas_x_variant":[
        "Kal\u0101teh-ye D\u0101vod"
    ],
    "name:und_x_variant":[
        "Kal\u0101teh-ye D\u0101v\u016bd"
    ],
    "wof:name":"Kalateh-ye Davud",
    "wof:placetype":"locality"
},
  "geometry": {"coordinates":[59.59738,32.65854],"type":"Point"}
}