{
  "type": "Feature",
  "properties": {
    "gn:admin1_code":"13.0",
    "gn:asciiname":"Holul",
    "gn:country_code":"IR",
    "gn:dem":1496,
    "gn:feature_class":"P",
    "gn:feature_code":"PPL",
    "gn:name":"\u1e28ol\u016bl",
    "gn:population":0,
    "gn:timezone":"Asia/Tehran",
    "iso:country":"IR",
    "name:fas_x_preferred":[
        "\u062d\u0644\u0648\u0644"
    ],
    "name:fas_x_variant":[
        "\u1e28ol\u016bl",
        "\u0647\u0644\u0648\u0644"
    ],
    "name:und_x_variant":[
        "Hal\u016bl"
    ],
    "wof:name":"Holul",
    "wof:placetype":"locality"
},
  "geometry": {"coordinates":[46.3668,34.6146],"type":"Point"}
}