{
  "type": "Feature",
  "properties": {
    "gn:admin1_code":"33",
    "gn:asciiname":"Sharvenu",
    "gn:country_code":"IR",
    "gn:dem":1023,
    "gn:feature_class":"P",
    "gn:feature_code":"PPL",
    "gn:name":"Sharven\u016b",
    "gn:population":0,
    "gn:timezone":"Asia/Tehran",
    "iso:country":"IR",
    "name:fas_x_preferred":[
        "\u0634\u064e\u0631\u0648\u0650\u0646\u0648"
    ],
    "name:fas_x_variant":[
        "Sharven\u016b"
    ],
    "wof:name":"Sharvenu",
    "wof:placetype":"locality"
},
  "geometry": {"coordinates":[47.42194,38.64528],"type":"Point"}
}