{
  "type": "Feature",
  "properties": {
    "gn:admin1_code":"8",
    "gn:asciiname":"Lor",
    "gn:country_code":"IR",
    "gn:dem":1375,
    "gn:feature_class":"P",
    "gn:feature_code":"PPL",
    "gn:name":"Lor",
    "gn:population":0,
    "gn:timezone":"Asia/Tehran",
    "iso:country":"IR",
    "name:fas_x_preferred":[
        "\u0644\u0631"
    ],
    "wof:name":"Lor",
    "wof:placetype":"locality"
},
  "geometry": {"coordinates":[48.6983,37.72669000000001],"type":"Point"}
}