{
  "type": "Feature",
  "properties": {
    "gn:admin1_code":"13",
    "gn:asciiname":"Fuladi",
    "gn:country_code":"IR",
    "gn:dem":810,
    "gn:feature_class":"P",
    "gn:feature_code":"PPL",
    "gn:name":"F\u016bl\u0101d\u012b",
    "gn:population":0,
    "gn:timezone":"Asia/Tehran",
    "iso:country":"IR",
    "name:fas_x_preferred":[
        "\u0641\u0648\u0644\u0627\u062f\u06cc"
    ],
    "name:fas_x_variant":[
        "F\u016bl\u0101d\u012b"
    ],
    "wof:name":"Fuladi",
    "wof:placetype":"locality"
},
  "geometry": {"coordinates":[45.98925,34.40456],"type":"Point"}
}