{
  "type": "Feature",
  "properties": {
    "gn:admin1_code":"28",
    "gn:asciiname":"Singerd",
    "gn:country_code":"IR",
    "gn:dem":2139,
    "gn:feature_class":"P",
    "gn:feature_code":"PPL",
    "gn:name":"S\u012bngerd",
    "gn:population":0,
    "gn:timezone":"Asia/Tehran",
    "iso:country":"IR",
    "name:ara_x_preferred":[
        "\u0633\u064a\u0646\u063a\u0631\u062f"
    ],
    "name:fas_x_preferred":[
        "S\u012bngerd"
    ],
    "name:fas_x_variant":[
        "\u0633\u06cc\u0646\u06af\u0631\u062f"
    ],
    "name:und_x_variant":[
        "Sangird",
        "S\u012bngard"
    ],
    "wof:name":"Singerd",
    "wof:placetype":"locality"
},
  "geometry": {"coordinates":[50.43428,32.78901],"type":"Point"}
}