{
  "type": "Feature",
  "properties": {
    "gn:admin1_code":"7",
    "gn:asciiname":"Zarak",
    "gn:country_code":"IR",
    "gn:dem":1249,
    "gn:feature_class":"P",
    "gn:feature_code":"PPL",
    "gn:name":"Zarak",
    "gn:population":0,
    "gn:timezone":"Asia/Tehran",
    "iso:country":"IR",
    "name:fas_x_preferred":[
        "\u0632\u0631\u06a9"
    ],
    "name:ita_x_preferred":[
        "Zarak Khan"
    ],
    "name:nld_x_preferred":[
        "Zarak"
    ],
    "name:und_x_variant":[
        "Rizak",
        "Razak"
    ],
    "wof:name":"Zarak",
    "wof:placetype":"locality"
},
  "geometry": {"coordinates":[53.93659,28.37065],"type":"Point"}
}