{
  "type": "Feature",
  "properties": {
    "gn:admin1_code":"7",
    "gn:asciiname":"Gav Piazi",
    "gn:country_code":"IR",
    "gn:dem":982,
    "gn:feature_class":"P",
    "gn:feature_code":"PPL",
    "gn:name":"G\u0101v P\u012b\u0101z\u012b",
    "gn:population":0,
    "gn:timezone":"Asia/Tehran",
    "iso:country":"IR",
    "name:fas_x_preferred":[
        "G\u0101v P\u012b\u0101z\u012b"
    ],
    "name:fas_x_variant":[
        "\u06af\u0627\u0648 \u067e\u06cc\u0627\u0632\u06cc",
        "Bardey\u0101l\u012b",
        "\u06af\u0627\u0648\u067e\u06cc\u0627\u0632\u06cc"
    ],
    "name:msa_x_preferred":[
        "Gav Piazi"
    ],
    "wof:name":"Gav Piazi",
    "wof:placetype":"locality"
},
  "geometry": {"coordinates":[51.59639,30.18763],"type":"Point"}
}