{
  "type": "Feature",
  "properties": {
    "gn:admin1_code":"16",
    "gn:asciiname":"Qalucheh",
    "gn:country_code":"IR",
    "gn:dem":1989,
    "gn:feature_class":"P",
    "gn:feature_code":"PPL",
    "gn:name":"Q\u0101l\u016bcheh",
    "gn:population":0,
    "gn:timezone":"Asia/Tehran",
    "iso:country":"IR",
    "name:fas_x_preferred":[
        "\u0642\u0627\u0644\u0648\u062c\u0650\u0647"
    ],
    "name:fas_x_variant":[
        "\u0642\u0627\u0644\u0648\u0686\u0647",
        "Q\u0101l\u016bjeh",
        "Q\u0101l\u016bcheh"
    ],
    "wof:name":"Qalucheh",
    "wof:placetype":"locality"
},
  "geometry": {"coordinates":[47.0943,36.1121],"type":"Point"}
}