{
  "type": "Feature",
  "properties": {
    "gn:admin1_code":"42",
    "gn:asciiname":"Chakaneh-ye Sofla",
    "gn:country_code":"IR",
    "gn:dem":1597,
    "gn:feature_class":"P",
    "gn:feature_code":"PPL",
    "gn:name":"Chakaneh-ye Sofl\u00e1",
    "gn:population":0,
    "gn:timezone":"Asia/Tehran",
    "iso:country":"IR",
    "name:fas_x_preferred":[
        "\u0686\u06a9\u0646\u0647 \u067e\u0627\u0626\u06cc\u0646"
    ],
    "name:fas_x_variant":[
        "Chakaneh P\u0101\u2019\u012bin",
        "Chakaneh-ye P\u0101\u2019\u012bin",
        "\u0686\u06a9\u0646\u0647 \u0633\u0641\u0644\u06cc"
    ],
    "name:und_x_variant":[
        "Chakaneh Sofl\u0101",
        "Chakaneh-ye Sofl\u00e1"
    ],
    "wof:name":"Chakaneh-ye Sofla",
    "wof:placetype":"locality"
},
  "geometry": {"coordinates":[58.50425,36.81768],"type":"Point"}
}