{
  "type": "Feature",
  "properties": {
    "gn:admin1_code":"38",
    "gn:asciiname":"Tofak",
    "gn:country_code":"IR",
    "gn:dem":1376,
    "gn:feature_class":"P",
    "gn:feature_code":"PPL",
    "gn:name":"Tofak",
    "gn:population":0,
    "gn:timezone":"Asia/Tehran",
    "iso:country":"IR",
    "name:fas_x_preferred":[
        "\u062a\u0641\u06a9"
    ],
    "name:und_x_variant":[
        "Daf\u0101j",
        "Tofak"
    ],
    "wof:name":"Tofak",
    "wof:placetype":"locality"
},
  "geometry": {"coordinates":[49.97618,35.70917],"type":"Point"}
}