{
  "type": "Feature",
  "properties": {
    "gn:admin1_code":"13",
    "gn:asciiname":"Niaruq",
    "gn:country_code":"IR",
    "gn:dem":352,
    "gn:feature_class":"P",
    "gn:feature_code":"PPL",
    "gn:name":"N\u012b\u0101r\u016bq",
    "gn:population":0,
    "gn:timezone":"Asia/Tehran",
    "iso:country":"IR",
    "name:fas_x_preferred":[
        "N\u012b\u0101r\u016bq"
    ],
    "wof:name":"Niaruq",
    "wof:placetype":"locality"
},
  "geometry": {"coordinates":[45.61667,34.55],"type":"Point"}
}