{
  "type": "Feature",
  "properties": {
    "gn:admin1_code":"29",
    "gn:asciiname":"Ganjabad-e Bala",
    "gn:country_code":"IR",
    "gn:dem":457,
    "gn:feature_class":"P",
    "gn:feature_code":"PPL",
    "gn:name":"Ganj\u0101b\u0101d-e B\u0101l\u0101",
    "gn:population":0,
    "gn:timezone":"Asia/Tehran",
    "iso:country":"IR",
    "name:fas_x_preferred":[
        "Ganj\u0101b\u0101d-e B\u0101l\u0101"
    ],
    "wof:name":"Ganjabad-e Bala",
    "wof:placetype":"locality"
},
  "geometry": {"coordinates":[57.90778,27.88028],"type":"Point"}
}