{
  "type": "Feature",
  "properties": {
    "gn:admin1_code":"15.0",
    "gn:asciiname":"Tighen-e Sofla",
    "gn:country_code":"IR",
    "gn:dem":534,
    "gn:feature_class":"P",
    "gn:feature_code":"PPL",
    "gn:name":"T\u012bghen-e Sofl\u00e1",
    "gn:population":0,
    "gn:timezone":"Asia/Tehran",
    "iso:country":"IR",
    "name:ceb_x_preferred":[
        "T\u012bghen-e Sofl\u00e1"
    ],
    "name:fas_x_preferred":[
        "\u062a\u06cc\u063a\u0646 \u0633\u0641\u0644\u06cc"
    ],
    "name:swe_x_preferred":[
        "T\u012bghen-e Sofl\u00e1"
    ],
    "wof:name":"Tighen-e Sofla",
    "wof:placetype":"locality"
},
  "geometry": {"coordinates":[49.85545,31.3791],"type":"Point"}
}