{
  "type": "Feature",
  "properties": {
    "gn:admin1_code":"38",
    "gn:asciiname":"Sakaznab",
    "gn:country_code":"IR",
    "gn:dem":1497,
    "gn:feature_class":"P",
    "gn:feature_code":"PPL",
    "gn:name":"Sakazn\u0101b",
    "gn:population":0,
    "gn:timezone":"Asia/Tehran",
    "iso:country":"IR",
    "name:fas_x_preferred":[
        "\u0633\u064e\u0643\u064a\u0632\u0646\u0627\u0628"
    ],
    "name:fas_x_variant":[
        "\u0633\u06a9\u0632\u0646\u0627\u0628",
        "Sak\u012bzn\u0101b",
        "Sakazn\u0101b"
    ],
    "name:und_x_variant":[
        "Sakkezn\u0101b",
        "Sakezn\u0101b",
        "Sakznab",
        "\u0633\u064e\u0643\u0650\u0651\u0632\u0646\u0627\u0628",
        "\u0633\u064e\u0643\u0650\u0632\u0646\u0627\u0628",
        "\u0633\u064e\u0643\u0632\u0646\u064e\u0628"
    ],
    "wof:name":"Sakaznab",
    "wof:placetype":"locality"
},
  "geometry": {"coordinates":[49.37289000000001,35.78782],"type":"Point"}
}