{
  "type": "Feature",
  "properties": {
    "gn:admin1_code":"7",
    "gn:asciiname":"Marvashkan",
    "gn:country_code":"IR",
    "gn:dem":2040,
    "gn:feature_class":"P",
    "gn:feature_code":"PPL",
    "gn:name":"Marvashk\u0101n",
    "gn:population":0,
    "gn:timezone":"Asia/Tehran",
    "iso:country":"IR",
    "name:ara_x_preferred":[
        "\u0645\u0631\u0648\u0634\u06a9\u0627\u0646"
    ],
    "name:fas_x_preferred":[
        "\u0645\u0631\u0648\u0634\u06a9\u0627\u0646"
    ],
    "name:fas_x_variant":[
        "Marvashk\u0101n"
    ],
    "name:msa_x_preferred":[
        "Marvashkan"
    ],
    "name:und_x_variant":[
        "Marveshk\u0101n"
    ],
    "wof:name":"Marvashkan",
    "wof:placetype":"locality"
},
  "geometry": {"coordinates":[53.9337,29.9284],"type":"Point"}
}