{
  "type": "Feature",
  "properties": {
    "gn:admin1_code":"33",
    "gn:asciiname":"Kalian",
    "gn:country_code":"IR",
    "gn:dem":1874,
    "gn:feature_class":"P",
    "gn:feature_code":"PPL",
    "gn:name":"Kal\u012b\u0101n",
    "gn:population":0,
    "gn:timezone":"Asia/Tehran",
    "iso:country":"IR",
    "name:fas_x_preferred":[
        "\u06a9\u0644\u06cc\u0627\u0646"
    ],
    "name:fas_x_variant":[
        "Kal\u012b\u0101n"
    ],
    "wof:name":"Kalian",
    "wof:placetype":"locality"
},
  "geometry": {"coordinates":[47.75899999999999,37.9708],"type":"Point"}
}