{
  "type": "Feature",
  "properties": {
    "gn:admin1_code":"23",
    "gn:asciiname":"Rahman Shah",
    "gn:country_code":"IR",
    "gn:dem":1766,
    "gn:feature_class":"P",
    "gn:feature_code":"PPL",
    "gn:name":"Ra\u1e29m\u0101n Sh\u0101h",
    "gn:population":0,
    "gn:timezone":"Asia/Tehran",
    "iso:country":"IR",
    "name:fas_x_preferred":[
        "\u0631\u064e\u062d\u0645\u0627\u0646 \u0634\u0627\u0647"
    ],
    "name:fas_x_variant":[
        "Ra\u1e29m\u0101n Sh\u0101h"
    ],
    "wof:name":"Rahman Shah",
    "wof:placetype":"locality"
},
  "geometry": {"coordinates":[48.44167,33.7175],"type":"Point"}
}