{
  "type": "Feature",
  "properties": {
    "gn:admin1_code":"42",
    "gn:asciiname":"Chahar Takhteh Guk",
    "gn:country_code":"IR",
    "gn:dem":1619,
    "gn:feature_class":"P",
    "gn:feature_code":"PPL",
    "gn:name":"Chah\u0101r Takhteh G\u016bk",
    "gn:population":0,
    "gn:timezone":"Asia/Tehran",
    "iso:country":"IR",
    "name:fas_x_preferred":[
        "\u0686\u0647\u0627\u0631 \u062a\u062e\u062a\u0647 \u06af\u0648\u06a9"
    ],
    "name:fas_x_variant":[
        "Chah\u0101r Takht-e G\u016bk",
        "Chah\u0101r Takhteh G\u016bk"
    ],
    "wof:name":"Chahar Takhteh Guk",
    "wof:placetype":"locality"
},
  "geometry": {"coordinates":[59.07461,35.63126],"type":"Point"}
}