{
  "type": "Feature",
  "properties": {
    "gn:admin1_code":"29",
    "gn:asciiname":"Piru'iyeh",
    "gn:country_code":"IR",
    "gn:dem":2394,
    "gn:feature_class":"P",
    "gn:feature_code":"PPL",
    "gn:name":"P\u012br\u016b\u2019\u012byeh",
    "gn:population":0,
    "gn:timezone":"Asia/Tehran",
    "iso:country":"IR",
    "name:fas_x_preferred":[
        "\u067e\u06cc\u0631\u0648\u0626\u06cc\u0647"
    ],
    "name:fas_x_variant":[
        "P\u012br\u016b\u2019\u012byeh"
    ],
    "wof:name":"Piru'iyeh",
    "wof:placetype":"locality"
},
  "geometry": {"coordinates":[56.6438,29.2834],"type":"Point"}
}