{
  "type": "Feature",
  "properties": {
    "gn:admin1_code":"25",
    "gn:asciiname":"Chay Jam",
    "gn:country_code":"IR",
    "gn:dem":1078,
    "gn:feature_class":"P",
    "gn:feature_code":"PPLF",
    "gn:name":"Ch\u0101y J\u0101m",
    "gn:population":0,
    "gn:timezone":"Asia/Tehran",
    "iso:country":"IR",
    "name:fas_x_preferred":[
        "\u0686\u0627\u0647 \u0686\u064e\u0645"
    ],
    "name:fas_x_variant":[
        "\u0686\u062c\u0627\u0645",
        "Ch\u0101h-e J\u0101m",
        "\u0686\u0627\u0647 \u062c\u0627\u0645",
        "Chej\u0101m",
        "Ch\u0101h Cham",
        "\u0686\u0627\u06cc \u062c\u0627\u0645"
    ],
    "name:und_x_variant":[
        "Ch\u0101y J\u0101m",
        "Chaj\u0101m"
    ],
    "wof:name":"Chay Jam",
    "wof:placetype":"locality"
},
  "geometry": {"coordinates":[55.13408,35.82199],"type":"Point"}
}