{
  "type": "Feature",
  "properties": {
    "gn:admin1_code":"25.0",
    "gn:asciiname":"Deh-e Qazi",
    "gn:country_code":"IR",
    "gn:dem":1100,
    "gn:feature_class":"P",
    "gn:feature_code":"PPLF",
    "gn:name":"Deh-e Q\u0101\u1e95\u012b",
    "gn:population":0,
    "gn:timezone":"Asia/Tehran",
    "iso:country":"IR",
    "name:fas_x_preferred":[
        "\u062f\u0647 \u0642\u0627\u0636\u06cc"
    ],
    "name:fas_x_variant":[
        "Deh-e Q\u0101\u1e95\u012b"
    ],
    "name:und_x_variant":[
        "Deh-e Q\u0101\u1e95\u012b"
    ],
    "wof:name":"Deh-e Qazi",
    "wof:placetype":"locality"
},
  "geometry": {"coordinates":[54.28657,35.98782999999999],"type":"Point"}
}