{
  "type": "Feature",
  "properties": {
    "gn:admin1_code":"29",
    "gn:asciiname":"Esfand",
    "gn:country_code":"IR",
    "gn:dem":2106,
    "gn:feature_class":"P",
    "gn:feature_code":"PPL",
    "gn:name":"Esfand",
    "gn:population":0,
    "gn:timezone":"Asia/Tehran",
    "iso:country":"IR",
    "name:fas_x_preferred":[
        "\u0627\u0633\u0641\u0646\u062f"
    ],
    "wof:name":"Esfand",
    "wof:placetype":"locality"
},
  "geometry": {"coordinates":[55.7566,29.8041],"type":"Point"}
}