{
  "type": "Feature",
  "properties": {
    "gn:admin1_code":"32",
    "gn:asciiname":"Hoseyn Khanlu",
    "gn:country_code":"IR",
    "gn:dem":1144,
    "gn:feature_class":"P",
    "gn:feature_code":"PPL",
    "gn:name":"\u1e28oseyn Kh\u0101nl\u016b",
    "gn:population":0,
    "gn:timezone":"Asia/Tehran",
    "iso:country":"IR",
    "name:ara_x_preferred":[
        "\u062d\u0633\u064a\u0646 \u062e\u0627\u0646\u0644\u0648"
    ],
    "name:fas_x_preferred":[
        "\u062d\u0633\u06cc\u0646 \u062e\u0627\u0646\u0644\u0648"
    ],
    "name:fas_x_variant":[
        "\u1e28oseyn Kh\u0101nl\u016b"
    ],
    "name:msa_x_preferred":[
        "Hoseyn Khanlu"
    ],
    "wof:name":"Hoseyn Khanlu",
    "wof:placetype":"locality"
},
  "geometry": {"coordinates":[47.855,38.9704],"type":"Point"}
}