{
  "type": "Feature",
  "properties": {
    "gn:admin1_code":"23",
    "gn:asciiname":"Posht Meleh Baqela Kuh",
    "gn:country_code":"IR",
    "gn:dem":1827,
    "gn:feature_class":"P",
    "gn:feature_code":"PPL",
    "gn:name":"Posht Meleh B\u0101qel\u0101 K\u016bh",
    "gn:population":0,
    "gn:timezone":"Asia/Tehran",
    "iso:country":"IR",
    "name:fas_x_preferred":[
        "\u1e28amzeh\u0101b\u0101d"
    ],
    "name:fas_x_variant":[
        "\u067e\u0634\u062a \u0645\u0644\u0647 \u0628\u0627\u0642\u0644\u0627 \u06a9\u0648\u0647"
    ],
    "name:und_x_variant":[
        "B\u0101qel\u0101 K\u016bh-e \u1e28amzeh",
        "B\u0101qel\u0101k\u0101n-e P\u0101\u2019\u012bn",
        "B\u0101qel\u0101k\u016bb-e Sofl\u00e1",
        "Posht Meleh B\u0101qel\u0101 K\u016bh",
        "B\u0101ql\u0101k\u016bb-e Sofl\u00e1",
        "Posht Meleh"
    ],
    "wof:name":"Posht Meleh Baqela Kuh",
    "wof:placetype":"locality"
},
  "geometry": {"coordinates":[48.68642,33.64536],"type":"Point"}
}