{
  "type": "Feature",
  "properties": {
    "gn:admin1_code":"8.0",
    "gn:asciiname":"Areh Panjeh Dowshaneh",
    "gn:country_code":"IR",
    "gn:dem":823,
    "gn:feature_class":"P",
    "gn:feature_code":"PPL",
    "gn:name":"Areh Panjeh Dowsh\u0101neh",
    "gn:population":0,
    "gn:timezone":"Asia/Tehran",
    "iso:country":"IR",
    "name:fas_x_preferred":[
        "Sam\u012bshbon"
    ],
    "name:fas_x_variant":[
        "\u0633\u0645\u06cc\u0634\u0628\u0646",
        "\u0627\u0631\u0647 \u067e\u0646\u062c\u0647 \u062f\u0648\u0634\u0627\u0646\u0647"
    ],
    "name:und_x_variant":[
        "\u0633\u0645\u06cc\u0634\u0628\u0646",
        "Areh Panjeh Dowsh\u0101neh"
    ],
    "wof:name":"Areh Panjeh Dowshaneh",
    "wof:placetype":"locality"
},
  "geometry": {"coordinates":[49.77252,36.93024000000001],"type":"Point"}
}