{
  "type": "Feature",
  "properties": {
    "gn:admin1_code":"9",
    "gn:asciiname":"Seydabad",
    "gn:country_code":"IR",
    "gn:dem":1634,
    "gn:feature_class":"P",
    "gn:feature_code":"PPL",
    "gn:name":"\u015eeyd\u0101b\u0101d",
    "gn:population":0,
    "gn:timezone":"Asia/Tehran",
    "iso:country":"IR",
    "name:fas_x_preferred":[
        "\u0635\u06cc\u062f \u0622\u0628\u0627\u062f"
    ],
    "name:fas_x_variant":[
        "\u0633\u0650\u064a\u0650\u0651\u062f \u0622\u0628\u0627\u062f",
        "\u015eeyd\u0101b\u0101d"
    ],
    "name:und_x_variant":[
        "Saiyid\u0101b\u0101d",
        "Seid Abad",
        "Seyyed\u0101b\u0101d"
    ],
    "wof:name":"Seydabad",
    "wof:placetype":"locality"
},
  "geometry": {"coordinates":[49.30186,35.15526],"type":"Point"}
}