{
  "type": "Feature",
  "properties": {
    "gn:admin1_code":"8.0",
    "gn:asciiname":"Kangacherk",
    "gn:country_code":"IR",
    "gn:dem":-10,
    "gn:feature_class":"P",
    "gn:feature_code":"PPL",
    "gn:name":"Kang\u0101cherk",
    "gn:population":0,
    "gn:timezone":"Asia/Tehran",
    "iso:country":"IR",
    "name:fas_x_preferred":[
        "Kang\u0101char"
    ],
    "name:fas_x_variant":[
        "\u06a9\u0646\u06af\u0627\u0686\u0631",
        "\u06a9\u0646\u06af\u0627\u0686\u0631\u06a9"
    ],
    "name:und_x_variant":[
        "\u06a9\u0646\u06af\u0627\u0686\u0631",
        "Kang\u0101cherk"
    ],
    "wof:name":"Kangacherk",
    "wof:placetype":"locality"
},
  "geometry": {"coordinates":[50.41461,37.05085],"type":"Point"}
}