{
  "type": "Feature",
  "properties": {
    "gn:admin1_code":"23",
    "gn:asciiname":"Goldasht",
    "gn:country_code":"IR",
    "gn:dem":1594,
    "gn:feature_class":"P",
    "gn:feature_code":"PPL",
    "gn:name":"Goldasht",
    "gn:population":0,
    "gn:timezone":"Asia/Tehran",
    "iso:country":"IR",
    "name:fas_x_preferred":[
        "\u0648\u06cc\u0644\u0627\u0647\u0627\u06cc \u0645\u0627\u0647\u062f\u0634\u062a"
    ],
    "name:fas_x_variant":[
        "V\u012bl\u0101h\u0101-ye M\u0101hdasht",
        "\u06af\u0644\u062f\u0634\u062a",
        "\u0645\u062c\u062a\u0645\u0639 \u0648\u06cc\u0644\u0627\u0626\u06cc \u06af\u0644\u062f\u0634\u062a"
    ],
    "name:und_x_variant":[
        "Mojtame\u2018-e V\u012bl\u0101\u2019\u012b Goldasht"
    ],
    "wof:name":"Goldasht",
    "wof:placetype":"locality"
},
  "geometry": {"coordinates":[48.7085,33.9088],"type":"Point"}
}