{
  "type": "Feature",
  "properties": {
    "gn:admin1_code":"15",
    "gn:asciiname":"Shahrak-e Emam Khomeyni",
    "gn:country_code":"IR",
    "gn:dem":708,
    "gn:feature_class":"P",
    "gn:feature_code":"PPL",
    "gn:name":"Shahrak-e Em\u0101m Khomeyn\u012b",
    "gn:population":0,
    "gn:timezone":"Asia/Tehran",
    "iso:country":"IR",
    "name:fas_x_preferred":[
        "Rostam\u0101b\u0101d"
    ],
    "name:fas_x_variant":[
        "Shahrak-e Em\u0101m Khomeyn\u012b",
        "\u0634\u0647\u0631\u06a9 \u0627\u0645\u0627\u0645 \u062e\u0645\u06cc\u0646\u06cc",
        "\u0631\u0633\u062a\u0645 \u0622\u0628\u0627\u062f"
    ],
    "wof:name":"Shahrak-e Emam Khomeyni",
    "wof:placetype":"locality"
},
  "geometry": {"coordinates":[49.50132,32.18595],"type":"Point"}
}