{
  "type": "Feature",
  "properties": {
    "gn:admin1_code":"35.0",
    "gn:asciiname":"Turan Kola",
    "gn:country_code":"IR",
    "gn:dem":2090,
    "gn:feature_class":"P",
    "gn:feature_code":"PPL",
    "gn:name":"T\u016br\u0101n Kol\u0101",
    "gn:population":0,
    "gn:timezone":"Asia/Tehran",
    "iso:country":"IR",
    "name:fas_x_preferred":[
        "\u062a\u0648\u0631\u0627\u0646 \u06a9\u0644\u0627"
    ],
    "name:fas_x_variant":[
        "T\u016br\u0101n Kol\u0101",
        "\u062a\u0648\u0631\u0627\u0646\u200c\u06a9\u0644\u0627"
    ],
    "wof:name":"Turan Kola",
    "wof:placetype":"locality"
},
  "geometry": {"coordinates":[52.21358,36.27518],"type":"Point"}
}