{
  "type": "Feature",
  "properties": {
    "gn:admin1_code":"15",
    "gn:asciiname":"Salmanvand-e Bala",
    "gn:country_code":"IR",
    "gn:dem":680,
    "gn:feature_class":"P",
    "gn:feature_code":"PPL",
    "gn:name":"Salm\u0101nvand-e B\u0101l\u0101",
    "gn:population":0,
    "gn:timezone":"Asia/Tehran",
    "iso:country":"IR",
    "name:fas_x_preferred":[
        "Salm\u0101vand-e \u2018Oly\u0101"
    ],
    "name:fas_x_variant":[
        "\u0633\u0644\u0645\u0627\u0648\u0646\u062f \u0639\u0644\u06cc\u0627",
        "\u0633\u0644\u0645\u0627\u0646 \u0648\u0646\u062f \u0628\u0627\u0644\u0627",
        "\u0628\u0627\u0644\u0648\u0646"
    ],
    "name:und_x_variant":[
        "\u0633\u0644\u0645\u0627\u0648\u0646\u062f \u0639\u0644\u06cc\u0627",
        "Salm\u0101nvand-e B\u0101l\u0101",
        "B\u0101l\u016bn"
    ],
    "wof:name":"Salmanvand-e Bala",
    "wof:placetype":"locality"
},
  "geometry": {"coordinates":[49.80374000000001,31.55962],"type":"Point"}
}