{
  "type": "Feature",
  "properties": {
    "gn:admin1_code":"3",
    "gn:asciiname":"Sar Pir",
    "gn:country_code":"IR",
    "gn:dem":2156,
    "gn:feature_class":"P",
    "gn:feature_code":"PPL",
    "gn:name":"Sar P\u012br",
    "gn:population":0,
    "gn:timezone":"Asia/Tehran",
    "iso:country":"IR",
    "name:fas_x_preferred":[
        "Sar P\u012br"
    ],
    "name:fas_x_variant":[
        "\u0633\u0631 \u067e\u064a\u0631",
        "\u0633\u0631\u067e\u06cc\u0631"
    ],
    "name:und_x_variant":[
        "Sar-\u012b-P\u012br",
        "\u0633\u0631 \u067e\u064a\u0631"
    ],
    "wof:name":"Sar Pir",
    "wof:placetype":"locality"
},
  "geometry": {"coordinates":[50.44288,32.17998],"type":"Point"}
}