{
  "type": "Feature",
  "properties": {
    "gn:admin1_code":"36",
    "gn:asciiname":"Golijeh",
    "gn:country_code":"IR",
    "gn:dem":1994,
    "gn:feature_class":"P",
    "gn:feature_code":"PPL",
    "gn:name":"Gol\u012bjeh",
    "gn:population":0,
    "gn:timezone":"Asia/Tehran",
    "iso:country":"IR",
    "name:azb_x_preferred":[
        "\u06af\u0644\u06cc\u062c\u0647"
    ],
    "name:fas_x_preferred":[
        "\u06af\u0644\u06cc\u062c\u0647"
    ],
    "name:fas_x_variant":[
        "Goll\u012bjeh-ye Em\u0101m",
        "Goll\u012bjeh",
        "\u06af\u0644\u06cc\u062c\u0647 \u0639\u0644\u06cc\u0627"
    ],
    "name:und_x_variant":[
        "Guludzhan",
        "Goljeh",
        "Gul\u016bja",
        "Gol\u012bjeh",
        "Goll\u016bjeh",
        "Gol\u012bjeh-ye \u2018Oly\u0101"
    ],
    "wof:name":"Golijeh",
    "wof:placetype":"locality"
},
  "geometry": {"coordinates":[48.80596,36.66986],"type":"Point"}
}