{
  "type": "Feature",
  "properties": {
    "gn:admin1_code":"1.0",
    "gn:asciiname":"Hajji Mamian",
    "gn:country_code":"IR",
    "gn:dem":1533,
    "gn:feature_class":"P",
    "gn:feature_code":"PPL",
    "gn:name":"\u1e28\u0101jj\u012b M\u0101m\u012b\u0101n",
    "gn:population":0,
    "gn:timezone":"Asia/Tehran",
    "iso:country":"IR",
    "name:ara_x_preferred":[
        "\u062d\u0627\u062c\u064a \u0645\u0627\u0645\u064a\u0627\u0646"
    ],
    "name:azb_x_preferred":[
        "\u062d\u0627\u062c\u06cc\u200c\u0645\u0627\u0645\u06cc\u0627\u0646(\u0633\u0648\u06cc\u0648\u0642\u200c\u0628\u0648\u0644\u0627\u0642)"
    ],
    "name:aze_x_preferred":[
        "Hac\u0131mamiyan"
    ],
    "name:ceb_x_preferred":[
        "\u1e28\u0101jj\u012b M\u0101m\u012b\u0101n"
    ],
    "name:ckb_x_preferred":[
        "\u062d\u0627\u062c\u06cc \u0645\u0627\u0645\u06cc\u0627\u0646"
    ],
    "name:fas_x_preferred":[
        "\u062d\u0627\u062c\u0651\u06cc \u0645\u0627 \u0645\u064a\u0627\u0646"
    ],
    "name:fas_x_variant":[
        "\u062d\u0627\u062c\u0651\u06cc \u0645\u0627\u0645\u06cc\u0627\u0646",
        "\u1e28\u0101jj\u012b M\u0101 M\u012b\u0101n",
        "\u1e28\u0101jj\u012b M\u0101m\u012b\u0101n",
        "\u062d\u0627\u062c\u06cc\u200c\u0645\u0627\u0645\u06cc\u0627\u0646"
    ],
    "name:kur_x_preferred":[
        "\u1e26ac\u00ee Mamiyan"
    ],
    "name:msa_x_preferred":[
        "Hajji Mamian"
    ],
    "name:swe_x_preferred":[
        "\u1e28\u0101jj\u012b M\u0101m\u012b\u0101n"
    ],
    "name:und_x_variant":[
        "\u1e28\u0101jj\u012b Mamiyan"
    ],
    "wof:name":"Hajji Mamian",
    "wof:placetype":"locality"
},
  "geometry": {"coordinates":[45.6633,36.6841],"type":"Point"}
}