{
  "type": "Feature",
  "properties": {
    "gn:admin1_code":"40",
    "gn:asciiname":"Torghinan",
    "gn:country_code":"IR",
    "gn:dem":667,
    "gn:feature_class":"P",
    "gn:feature_code":"PPL",
    "gn:name":"Torgh\u012bn\u0101n",
    "gn:population":0,
    "gn:timezone":"Asia/Tehran",
    "iso:country":"IR",
    "name:fas_x_preferred":[
        "Behesht\u0101b\u0101d"
    ],
    "name:fas_x_variant":[
        "\u0628\u0647\u0634\u062a \u0622\u0628\u0627\u062f",
        "Torgh\u012bn\u0101n",
        "\u062a\u0631\u063a\u064a\u0646\u0627\u0646",
        "Darq\u012bn\u0101n"
    ],
    "name:und_x_variant":[
        "Targhinan"
    ],
    "wof:name":"Torghinan",
    "wof:placetype":"locality"
},
  "geometry": {"coordinates":[56.83237,33.70694],"type":"Point"}
}