{
  "type": "Feature",
  "properties": {
    "gn:admin1_code":"35.0",
    "gn:asciiname":"Saldeh-e Sofla",
    "gn:country_code":"IR",
    "gn:dem":0,
    "gn:feature_class":"P",
    "gn:feature_code":"PPL",
    "gn:name":"S\u0101ldeh-e Sofl\u00e1",
    "gn:population":0,
    "gn:timezone":"Asia/Tehran",
    "iso:country":"IR",
    "name:ceb_x_preferred":[
        "S\u0101ldeh-e Sofl\u00e1"
    ],
    "name:fas_x_preferred":[
        "\u067e\u0627\u0626\u064a\u0646 \u0633\u0627\u0644\u062f\u0650\u0647"
    ],
    "name:fas_x_variant":[
        "P\u0101\u2019\u012bn S\u0101ldeh",
        "S\u0101ldeh-e Sofl\u00e1",
        "\u0633\u0627\u0644\u062f\u0647 \u0633\u0641\u0644\u06cc"
    ],
    "name:swe_x_preferred":[
        "S\u0101ldeh-e Sofl\u00e1"
    ],
    "wof:name":"Saldeh-e Sofla",
    "wof:placetype":"locality"
},
  "geometry": {"coordinates":[52.17459,36.53005],"type":"Point"}
}