{
  "type": "Feature",
  "properties": {
    "gn:admin1_code":"15",
    "gn:asciiname":"Khames",
    "gn:cc2":"IR",
    "gn:country_code":"IR",
    "gn:dem":88,
    "gn:feature_class":"P",
    "gn:feature_code":"PPL",
    "gn:name":"Kh\u0101mes",
    "gn:population":0,
    "gn:timezone":"Asia/Tehran",
    "iso:country":"IR",
    "name:fas_x_preferred":[
        "Kh\u0101mes"
    ],
    "name:und_x_variant":[
        "Kamaisi",
        "Kham\u012bs"
    ],
    "wof:name":"Khames",
    "wof:placetype":"locality"
},
  "geometry": {"coordinates":[49.38333,31.33333],"type":"Point"}
}