{
  "type": "Feature",
  "properties": {
    "gn:admin1_code":"29",
    "gn:asciiname":"Qantureqeh'i",
    "gn:country_code":"IR",
    "gn:dem":2561,
    "gn:feature_class":"P",
    "gn:feature_code":"PPL",
    "gn:name":"Qant\u016breqeh\u2019\u012b",
    "gn:population":0,
    "gn:timezone":"Asia/Tehran",
    "iso:country":"IR",
    "name:fas_x_preferred":[
        "\u0642\u0646\u062a\u0648\u0631\u0642\u0647 \u0627\u06cc"
    ],
    "name:fas_x_variant":[
        "Qant\u016breqeh\u2019\u012b"
    ],
    "wof:name":"Qantureqeh'i",
    "wof:placetype":"locality"
},
  "geometry": {"coordinates":[56.2299,29.8338],"type":"Point"}
}