{
  "type": "Feature",
  "properties": {
    "gn:admin1_code":"16.0",
    "gn:asciiname":"Gardgilan",
    "gn:country_code":"IR",
    "gn:dem":1458,
    "gn:feature_class":"P",
    "gn:feature_code":"PPL",
    "gn:name":"Gardg\u012bl\u0101n",
    "gn:population":0,
    "gn:timezone":"Asia/Tehran",
    "iso:country":"IR",
    "name:fas_x_preferred":[
        "\u06af\u0631\u062f\u06af\u06cc\u0644\u0627\u0646"
    ],
    "name:fas_x_variant":[
        "Gardg\u012bl\u0101n"
    ],
    "wof:name":"Gardgilan",
    "wof:placetype":"locality"
},
  "geometry": {"coordinates":[46.0589,36.3972],"type":"Point"}
}