{
  "type": "Feature",
  "properties": {
    "gn:admin1_code":"8",
    "gn:asciiname":"Yasur",
    "gn:country_code":"IR",
    "gn:dem":1680,
    "gn:feature_class":"P",
    "gn:feature_code":"PPL",
    "gn:name":"Y\u0101s\u016br",
    "gn:population":0,
    "gn:timezone":"Asia/Tehran",
    "iso:country":"IR",
    "name:fas_x_preferred":[
        "Y\u0101s\u016br"
    ],
    "name:fas_x_variant":[
        "\u06cc\u0627\u0633\u0648\u0631"
    ],
    "name:msa_x_preferred":[
        "Yasur"
    ],
    "name:ukr_x_preferred":[
        "\u042f\u0441\u0443\u0440"
    ],
    "wof:name":"Yasur",
    "wof:placetype":"locality"
},
  "geometry": {"coordinates":[50.31721,36.78047],"type":"Point"}
}