{
  "type": "Feature",
  "properties": {
    "gn:admin1_code":"7",
    "gn:asciiname":"Kachalha",
    "gn:country_code":"IR",
    "gn:dem":421,
    "gn:feature_class":"P",
    "gn:feature_code":"PPL",
    "gn:name":"Kachalh\u0101",
    "gn:population":0,
    "gn:timezone":"Asia/Tehran",
    "iso:country":"IR",
    "name:fas_x_preferred":[
        "\u0642\u0644\u0639\u0647 \u06a9\u0686\u0644\u0627\u0646"
    ],
    "name:fas_x_variant":[
        "Kachahl\u0101",
        "Qal\u2018eh-ye Kachal\u0101n",
        "\u06a9\u0686\u0644\u0647\u0627",
        "\u0642\u0644\u0639\u0647 \u06a9\u0686\u0644\u0647\u0627"
    ],
    "name:und_x_variant":[
        "Kachalh\u0101",
        "Qal\u2018eh-ye Kachalh\u0101"
    ],
    "wof:name":"Kachalha",
    "wof:placetype":"locality"
},
  "geometry": {"coordinates":[53.0891,27.3928],"type":"Point"}
}