{
  "type": "Feature",
  "properties": {
    "gn:admin1_code":"9",
    "gn:asciiname":"Barakatabad",
    "gn:cc2":"IR",
    "gn:country_code":"IR",
    "gn:dem":1935,
    "gn:feature_class":"P",
    "gn:feature_code":"PPL",
    "gn:name":"Barakat\u0101b\u0101d",
    "gn:population":0,
    "gn:timezone":"Asia/Tehran",
    "iso:country":"IR",
    "name:fas_x_preferred":[
        "\u0628\u064e\u0631\u064e\u0643\u064e\u062a \u0622\u0628\u0627\u062f"
    ],
    "name:fas_x_variant":[
        "\u0628\u064e\u0631\u0650\u0643\u064e\u062a \u0622\u0628\u0627\u062f",
        "\u0628\u0631\u06a9\u062a\u200c\u0622\u0628\u0627\u062f"
    ],
    "name:und_x_variant":[
        "Barekat \u0100b\u0101d"
    ],
    "wof:name":"Barakatabad",
    "wof:placetype":"locality"
},
  "geometry": {"coordinates":[48.88833,34.78361],"type":"Point"}
}