{
  "type": "Feature",
  "properties": {
    "gn:admin1_code":"8.0",
    "gn:asciiname":"Chaleh Sara",
    "gn:country_code":"IR",
    "gn:dem":1859,
    "gn:feature_class":"P",
    "gn:feature_code":"PPLL",
    "gn:name":"Ch\u0101leh Sar\u0101",
    "gn:population":0,
    "gn:timezone":"Asia/Tehran",
    "iso:country":"IR",
    "name:fas_x_preferred":[
        "\u0686\u0627\u0644\u0647 \u0633\u0631\u0627"
    ],
    "name:und_x_variant":[
        "Ch\u0101leh Sar\u0101"
    ],
    "wof:name":"Chaleh Sara",
    "wof:placetype":"locality"
},
  "geometry": {"coordinates":[49.34465,36.91174],"type":"Point"}
}