{
  "type": "Feature",
  "properties": {
    "gn:admin1_code":"23.0",
    "gn:asciiname":"Kikeh",
    "gn:country_code":"IR",
    "gn:dem":1083,
    "gn:feature_class":"P",
    "gn:feature_code":"PPL",
    "gn:name":"K\u012bkeh",
    "gn:population":0,
    "gn:timezone":"Asia/Tehran",
    "iso:country":"IR",
    "name:fas_x_preferred":[
        "\u06a9\u064a\u06a9\u0647"
    ],
    "name:und_x_variant":[
        "K\u012bkeh"
    ],
    "wof:name":"Kikeh",
    "wof:placetype":"locality"
},
  "geometry": {"coordinates":[48.77272,33.10202],"type":"Point"}
}