{
  "type": "Feature",
  "properties": {
    "gn:admin1_code":"15",
    "gn:asciiname":"Malgah-e Re'is",
    "gn:country_code":"IR",
    "gn:dem":758,
    "gn:feature_class":"P",
    "gn:feature_code":"PPL",
    "gn:name":"M\u0101lgah-e Re\u2019\u012bs",
    "gn:population":0,
    "gn:timezone":"Asia/Tehran",
    "iso:country":"IR",
    "name:fas_x_preferred":[
        "M\u0101lgah-e Re\u2019\u012bs"
    ],
    "wof:name":"Malgah-e Re'is",
    "wof:placetype":"locality"
},
  "geometry": {"coordinates":[48.75,32.81667],"type":"Point"}
}