{
  "type": "Feature",
  "properties": {
    "gn:admin1_code":"42.0",
    "gn:asciiname":"Chah-e Kheyr Khvah",
    "gn:country_code":"IR",
    "gn:dem":862,
    "gn:feature_class":"P",
    "gn:feature_code":"PPL",
    "gn:name":"Ch\u0101h-e Kheyr Khv\u0101h",
    "gn:population":0,
    "gn:timezone":"Asia/Tehran",
    "iso:country":"IR",
    "name:fas_x_preferred":[
        "Ch\u0101h-e Kheyr Khv\u0101h"
    ],
    "wof:name":"Chah-e Kheyr Khvah",
    "wof:placetype":"locality"
},
  "geometry": {"coordinates":[60.71666999999999,34.75],"type":"Point"}
}