{
  "type": "Feature",
  "properties": {
    "gn:admin1_code":"33",
    "gn:asciiname":"Kalaghay",
    "gn:country_code":"IR",
    "gn:dem":1376,
    "gn:feature_class":"P",
    "gn:feature_code":"PPL",
    "gn:name":"Kalagh\u0101y",
    "gn:population":0,
    "gn:timezone":"Asia/Tehran",
    "iso:country":"IR",
    "name:fas_x_preferred":[
        "Kalagh\u0101y"
    ],
    "wof:name":"Kalaghay",
    "wof:placetype":"locality"
},
  "geometry": {"coordinates":[46.38333,38.63333],"type":"Point"}
}