{
  "type": "Feature",
  "properties": {
    "gn:admin1_code":"7",
    "gn:asciiname":"Shur-e Bakesh",
    "gn:country_code":"IR",
    "gn:dem":1263,
    "gn:feature_class":"P",
    "gn:feature_code":"PPL",
    "gn:name":"Sh\u016br-e Bakesh",
    "gn:population":0,
    "gn:timezone":"Asia/Tehran",
    "iso:country":"IR",
    "name:fas_x_preferred":[
        "Sh\u016br-e Bakesh"
    ],
    "wof:name":"Shur-e Bakesh",
    "wof:placetype":"locality"
},
  "geometry": {"coordinates":[51.53028,30.02556],"type":"Point"}
}