{
  "type": "Feature",
  "properties": {
    "gn:admin1_code":"8.0",
    "gn:asciiname":"Taher Mahalleh",
    "gn:country_code":"IR",
    "gn:dem":-8,
    "gn:feature_class":"P",
    "gn:feature_code":"PPL",
    "gn:name":"\u0162\u0101her Ma\u1e29alleh",
    "gn:population":0,
    "gn:timezone":"Asia/Tehran",
    "iso:country":"IR",
    "name:fas_x_preferred":[
        "\u0162\u0101her\u012b Ma\u1e29alleh"
    ],
    "name:fas_x_variant":[
        "\u0637\u0627\u0647\u0631 \u0645\u062d\u0644\u0647"
    ],
    "name:und_x_variant":[
        "Goldasht",
        "\u0162\u0101her Ma\u1e29alleh"
    ],
    "wof:name":"Taher Mahalleh",
    "wof:placetype":"locality"
},
  "geometry": {"coordinates":[48.92084000000001,37.97334],"type":"Point"}
}