{
  "type": "Feature",
  "properties": {
    "gn:admin1_code":"38.0",
    "gn:asciiname":"Saraj Kala",
    "gn:country_code":"IR",
    "gn:dem":1641,
    "gn:feature_class":"P",
    "gn:feature_code":"PPL",
    "gn:name":"Sar\u0101j Kal\u0101",
    "gn:population":0,
    "gn:timezone":"Asia/Tehran",
    "iso:country":"IR",
    "name:fas_x_preferred":[
        "Sar\u0101j Kal\u0101"
    ],
    "name:fas_x_variant":[
        "\u0633\u0631\u0627\u062c \u06a9\u0644\u0627",
        "\u0633\u0631\u0627\u062c \u06a9\u0644\u0627\u06cc\u0647"
    ],
    "name:und_x_variant":[
        "\u0633\u0631\u0627\u062c \u06a9\u0644\u0627",
        "Sar\u0101j Kal\u0101yeh"
    ],
    "wof:name":"Saraj Kala",
    "wof:placetype":"locality"
},
  "geometry": {"coordinates":[50.68058,36.3976],"type":"Point"}
}