{
  "type": "Feature",
  "properties": {
    "gn:admin1_code":"35.0",
    "gn:asciiname":"Rudbar Sara",
    "gn:country_code":"IR",
    "gn:dem":440,
    "gn:feature_class":"P",
    "gn:feature_code":"PPL",
    "gn:name":"R\u016bdb\u0101r Sar\u0101",
    "gn:population":0,
    "gn:timezone":"Asia/Tehran",
    "iso:country":"IR",
    "name:fas_x_preferred":[
        "\u0631\u0648\u062f\u0628\u0627\u0631 \u0633\u064e\u0631\u0627"
    ],
    "name:fas_x_variant":[
        "R\u016bdb\u0101r Sar\u0101"
    ],
    "wof:name":"Rudbar Sara",
    "wof:placetype":"locality"
},
  "geometry": {"coordinates":[52.86666999999999,36.18333],"type":"Point"}
}