{
  "type": "Feature",
  "properties": {
    "gn:admin1_code":"13.0",
    "gn:asciiname":"Banjia",
    "gn:country_code":"IR",
    "gn:dem":1449,
    "gn:feature_class":"P",
    "gn:feature_code":"PPL",
    "gn:name":"B\u0101nj\u012b\u0101",
    "gn:population":0,
    "gn:timezone":"Asia/Tehran",
    "iso:country":"IR",
    "name:fas_x_preferred":[
        "\u0628\u0627\u0646\u062c\u06cc\u0627"
    ],
    "wof:name":"Banjia",
    "wof:placetype":"locality"
},
  "geometry": {"coordinates":[46.534,34.7091],"type":"Point"}
}