{
  "type": "Feature",
  "properties": {
    "gn:admin1_code":"33",
    "gn:asciiname":"Hashem",
    "gn:country_code":"IR",
    "gn:dem":1640,
    "gn:feature_class":"P",
    "gn:feature_code":"PPL",
    "gn:name":"H\u0101shem",
    "gn:population":0,
    "gn:timezone":"Asia/Tehran",
    "iso:country":"IR",
    "name:fas_x_preferred":[
        "H\u0101shem"
    ],
    "wof:name":"Hashem",
    "wof:placetype":"locality"
},
  "geometry": {"coordinates":[47.91667,37.61667],"type":"Point"}
}