{
  "type": "Feature",
  "properties": {
    "gn:admin1_code":"8",
    "gn:asciiname":"Shirju Posht",
    "gn:country_code":"IR",
    "gn:dem":-3,
    "gn:feature_class":"P",
    "gn:feature_code":"PPL",
    "gn:name":"Sh\u012brj\u016b Posht",
    "gn:population":0,
    "gn:timezone":"Asia/Tehran",
    "iso:country":"IR",
    "name:fas_x_preferred":[
        "Sh\u012brj\u016b Posht-e P\u0101\u2019\u012bn Ma\u1e29alleh"
    ],
    "name:fas_x_variant":[
        "\u0634\u06cc\u0631\u062c\u0648 \u067e\u0634\u062a",
        "\u0634\u06cc\u0631\u062c\u0648 \u067e\u0634\u062a \u067e\u0627\u0626\u06cc\u0646",
        "\u0634\u06cc\u0631\u062c\u0648\u067e\u0634\u062a \u067e\u0627\u06cc\u06cc\u0646"
    ],
    "name:msa_x_preferred":[
        "Shirju Posht-e Pain"
    ],
    "name:ukr_x_preferred":[
        "\u0428\u0456\u0440\u0434\u0436\u0443-\u041f\u043e\u0448\u0442-\u0435-\u041f\u0430\u0457\u043d"
    ],
    "name:und_x_variant":[
        "Sh\u012brj\u016b Posht",
        "Sh\u012brj\u016b Posht-e P\u0101\u2019\u012bn"
    ],
    "wof:name":"Shirju Posht",
    "wof:placetype":"locality"
},
  "geometry": {"coordinates":[50.08335,37.26528],"type":"Point"}
}