{
  "type": "Feature",
  "properties": {
    "gn:admin1_code":"36",
    "gn:asciiname":"Bu'in",
    "gn:country_code":"IR",
    "gn:dem":1981,
    "gn:feature_class":"P",
    "gn:feature_code":"PPL",
    "gn:name":"B\u016b\u2019\u012bn",
    "gn:population":0,
    "gn:timezone":"Asia/Tehran",
    "iso:country":"IR",
    "name:fas_x_preferred":[
        "\u0628\u0648\u0626\u06cc\u0646"
    ],
    "name:fas_x_variant":[
        "B\u016b\u2019\u012bn"
    ],
    "name:und_x_variant":[
        "B\u016by\u012bn"
    ],
    "wof:name":"Bu'in",
    "wof:placetype":"locality"
},
  "geometry": {"coordinates":[48.90324,36.51502],"type":"Point"}
}