{
  "type": "Feature",
  "properties": {
    "gn:admin1_code":"42",
    "gn:asciiname":"`Azimabad",
    "gn:country_code":"IR",
    "gn:dem":923,
    "gn:feature_class":"P",
    "gn:feature_code":"PPL",
    "gn:name":"\u2018Az\u0327\u012bm\u0101b\u0101d",
    "gn:population":0,
    "gn:timezone":"Asia/Tehran",
    "iso:country":"IR",
    "name:fas_x_preferred":[
        "\u2018Az\u0327\u012bm\u0101b\u0101d"
    ],
    "name:fas_x_variant":[
        "\u0639\u0638\u06cc\u0645 \u0622\u0628\u0627\u062f"
    ],
    "name:und_x_variant":[
        "\u0639\u0638\u06cc\u0645 \u0622\u0628\u0627\u062f"
    ],
    "wof:name":"`Azimabad",
    "wof:placetype":"locality"
},
  "geometry": {"coordinates":[58.07113,35.15426],"type":"Point"}
}