{
  "type": "Feature",
  "properties": {
    "gn:admin1_code":"1.0",
    "gn:asciiname":"Shatqar",
    "gn:country_code":"IR",
    "gn:dem":1293,
    "gn:feature_class":"P",
    "gn:feature_code":"PPL",
    "gn:name":"Shatq\u0101r",
    "gn:population":0,
    "gn:timezone":"Asia/Tehran",
    "iso:country":"IR",
    "name:fas_x_preferred":[
        "Shatq\u0101r"
    ],
    "wof:name":"Shatqar",
    "wof:placetype":"locality"
},
  "geometry": {"coordinates":[45.48333,36.98333],"type":"Point"}
}