{
  "type": "Feature",
  "properties": {
    "gn:admin1_code":"4.0",
    "gn:asciiname":"Kahuran Gevash",
    "gn:country_code":"IR",
    "gn:dem":558,
    "gn:feature_class":"P",
    "gn:feature_code":"PPL",
    "gn:name":"Kah\u016br\u0101n Gev\u0101sh",
    "gn:population":0,
    "gn:timezone":"Asia/Tehran",
    "iso:country":"IR",
    "name:fas_x_preferred":[
        "Kah\u016br \u0100ngav\u0101sh"
    ],
    "name:fas_x_variant":[
        "Kah\u016br\u0101n Gev\u0101sh",
        "\u06a9\u0647\u0648\u0631\u0627\u0646 \u06af\u0648\u0627\u0634"
    ],
    "name:und_x_variant":[
        "Tah\u016br\u0101n Gev\u0101sh",
        "Kah\u016br\u0101n Gev\u0101sh",
        "Tah\u016br\u0101ne Gov\u0101sh",
        "\u06a9\u0647\u0648\u0631\u0627\u0646 \u06af\u0648\u0627\u0634"
    ],
    "wof:name":"Kahuran Gevash",
    "wof:placetype":"locality"
},
  "geometry": {"coordinates":[60.77668000000001,26.27378],"type":"Point"}
}