{
  "type": "Feature",
  "properties": {
    "gn:admin1_code":"8",
    "gn:asciiname":"Lusha Deh",
    "gn:country_code":"IR",
    "gn:dem":335,
    "gn:feature_class":"P",
    "gn:feature_code":"PPL",
    "gn:name":"L\u016bsh\u0101 Deh",
    "gn:population":0,
    "gn:timezone":"Asia/Tehran",
    "iso:country":"IR",
    "name:fas_x_preferred":[
        "L\u016bsh\u0101 Deh"
    ],
    "name:fas_x_variant":[
        "L\u016bsh\u0101d\u012b",
        "\u0644\u0648\u0634\u0627\u062f\u06cc",
        "\u0644\u0648\u0634\u0627\u062f\u0647"
    ],
    "name:und_x_variant":[
        "L\u016bsh\u0101d\u012b",
        "\u0644\u0648\u0634\u0627\u062f\u06cc"
    ],
    "wof:name":"Lusha Deh",
    "wof:placetype":"locality"
},
  "geometry": {"coordinates":[49.9232,37.04404],"type":"Point"}
}