{
  "type": "Feature",
  "properties": {
    "gn:admin1_code":"33",
    "gn:asciiname":"Chelan-e Sofla",
    "gn:country_code":"IR",
    "gn:dem":1798,
    "gn:feature_class":"P",
    "gn:feature_code":"PPL",
    "gn:name":"Chel\u0101n-e Sofl\u00e1",
    "gn:population":0,
    "gn:timezone":"Asia/Tehran",
    "iso:country":"IR",
    "name:fas_x_preferred":[
        "\u0686\u0644\u0627\u0646 \u0633\u0641\u0644\u06cc"
    ],
    "name:fas_x_variant":[
        "Chel\u0101n-e Sofl\u00e1"
    ],
    "wof:name":"Chelan-e Sofla",
    "wof:placetype":"locality"
},
  "geometry": {"coordinates":[46.5485,37.3686],"type":"Point"}
}