{
  "type": "Feature",
  "properties": {
    "gn:admin1_code":"42.0",
    "gn:asciiname":"Cheshmeh-ye Gol",
    "gn:country_code":"IR",
    "gn:dem":805,
    "gn:feature_class":"P",
    "gn:feature_code":"PPL",
    "gn:name":"Cheshmeh-ye Gol",
    "gn:population":0,
    "gn:timezone":"Asia/Tehran",
    "iso:country":"IR",
    "name:fas_x_preferred":[
        "\u0686\u0634\u0645\u0647 \u06af\u0644"
    ],
    "name:und_x_variant":[
        "\u0686\u0634\u0645\u0647 \u06af\u0644"
    ],
    "wof:name":"Cheshmeh-ye Gol",
    "wof:placetype":"locality"
},
  "geometry": {"coordinates":[60.65797,35.93926],"type":"Point"}
}