{
  "type": "Feature",
  "properties": {
    "gn:admin1_code":"9",
    "gn:asciiname":"Hoseynabad",
    "gn:country_code":"IR",
    "gn:dem":1923,
    "gn:feature_class":"P",
    "gn:feature_code":"PPL",
    "gn:name":"\u1e28oseyn\u0101b\u0101d",
    "gn:population":0,
    "gn:timezone":"Asia/Tehran",
    "iso:country":"IR",
    "name:fas_x_preferred":[
        "\u062d\u0633\u06cc\u0646 \u0622\u0628\u0627\u062f"
    ],
    "name:fas_x_variant":[
        "\u1e28oseyn\u0101b\u0101d",
        "\u062d\u0633\u06cc\u0646 \u0622\u0628\u0627\u062f \u0628\u0627\u0628\u0627 \u062e\u0646\u062c\u0631"
    ],
    "name:und_x_variant":[
        "Hasan\u0101b\u0101d",
        "Husain\u0101b\u0101d",
        "Hosein Abad Mehraban",
        "\u1e28oseyn\u0101b\u0101d B\u0101b\u0101 Khanjar"
    ],
    "wof:name":"Hoseynabad",
    "wof:placetype":"locality"
},
  "geometry": {"coordinates":[48.53095,35.56105],"type":"Point"}
}