{
  "type": "Feature",
  "properties": {
    "gn:admin1_code":"35.0",
    "gn:asciiname":"Ahankoti",
    "gn:country_code":"IR",
    "gn:dem":31,
    "gn:feature_class":"P",
    "gn:feature_code":"PPL",
    "gn:name":"\u0100hankot\u012b",
    "gn:population":0,
    "gn:timezone":"Asia/Tehran",
    "iso:country":"IR",
    "name:ara_x_preferred":[
        "\u0622\u0647\u0646 \u06a9\u062a\u064a"
    ],
    "name:ceb_x_preferred":[
        "\u0100hankot\u012b"
    ],
    "name:fas_x_preferred":[
        "\u0622\u0647\u064e\u0646\u0643\u064f\u062a\u06cc"
    ],
    "name:fas_x_variant":[
        "\u0100hankot\u012b",
        "\u0622\u0647\u0646\u200c\u06a9\u062a\u06cc"
    ],
    "name:swe_x_preferred":[
        "\u0100hankot\u012b"
    ],
    "name:ukr_x_preferred":[
        "\u0410\u0433\u0430\u043d\u043a\u043e\u0442\u0456"
    ],
    "wof:name":"Ahankoti",
    "wof:placetype":"locality"
},
  "geometry": {"coordinates":[52.31667,36.51667],"type":"Point"}
}