{
  "type": "Feature",
  "properties": {
    "gn:admin1_code":"32.0",
    "gn:asciiname":"Azabeyg Qeshlaq",
    "gn:country_code":"IR",
    "gn:dem":1395,
    "gn:feature_class":"P",
    "gn:feature_code":"PPL",
    "gn:name":"Az\u0101beyg Qeshl\u0101q",
    "gn:population":0,
    "gn:timezone":"Asia/Tehran",
    "iso:country":"IR",
    "name:fas_x_preferred":[
        "\u0627\u064e\u0632\u0627\u0628\u0650\u064a\u06af \u0642\u0650\u0634\u0644\u0627\u0642"
    ],
    "name:und_x_variant":[
        "Az\u0101beyg Qeshl\u0101q"
    ],
    "wof:name":"Azabeyg Qeshlaq",
    "wof:placetype":"locality"
},
  "geometry": {"coordinates":[48.05028,38.66528],"type":"Point"}
}