{
  "type": "Feature",
  "properties": {
    "gn:admin1_code":"4.0",
    "gn:asciiname":"Teymurabad-e Sheykhi",
    "gn:country_code":"IR",
    "gn:dem":481,
    "gn:feature_class":"P",
    "gn:feature_code":"PPL",
    "gn:name":"Teym\u016br\u0101b\u0101d-e Sheykh\u012b",
    "gn:population":0,
    "gn:timezone":"Asia/Tehran",
    "iso:country":"IR",
    "name:fas_x_preferred":[
        "Teym\u016br\u0101b\u0101d-e Sheykh\u012b"
    ],
    "name:fas_x_variant":[
        "\u062a\u06cc\u0645\u0648\u0631 \u0622\u0628\u0627\u062f \u0634\u06cc\u062e\u06cc",
        "Teym\u016br\u0101b\u0101d"
    ],
    "wof:name":"Teymurabad-e Sheykhi",
    "wof:placetype":"locality"
},
  "geometry": {"coordinates":[61.3886,31.0567],"type":"Point"}
}