{
  "type": "Feature",
  "properties": {
    "gn:admin1_code":"7",
    "gn:asciiname":"Mahdiabad",
    "gn:country_code":"IR",
    "gn:dem":1652,
    "gn:feature_class":"P",
    "gn:feature_code":"PPL",
    "gn:name":"Mahd\u012b\u0101b\u0101d",
    "gn:population":0,
    "gn:timezone":"Asia/Tehran",
    "iso:country":"IR",
    "name:fas_x_preferred":[
        "\u0645\u0647\u062f\u06cc \u0622\u0628\u0627\u062f"
    ],
    "name:und_x_variant":[
        "Mahd\u012b\u0101b\u0101d"
    ],
    "wof:name":"Mahdiabad",
    "wof:placetype":"locality"
},
  "geometry": {"coordinates":[52.4736,30.2207],"type":"Point"}
}