{
  "type": "Feature",
  "properties": {
    "gn:admin1_code":"1",
    "gn:asciiname":"Sufian",
    "gn:country_code":"IR",
    "gn:dem":1494,
    "gn:feature_class":"P",
    "gn:feature_code":"PPL",
    "gn:name":"\u015e\u016bf\u012b\u0101n",
    "gn:population":0,
    "gn:timezone":"Asia/Tehran",
    "iso:country":"IR",
    "name:ara_x_preferred":[
        "\u0635\u0648\u0641\u064a\u0627\u0646"
    ],
    "name:azb_x_preferred":[
        "\u0635\u0648\u0641\u06cc\u0627\u0646"
    ],
    "name:aze_x_preferred":[
        "Sufiyan"
    ],
    "name:ceb_x_preferred":[
        "Soofian"
    ],
    "name:fas_x_preferred":[
        "\u0635\u0648\u0641\u06cc\u0627\u0646"
    ],
    "name:fas_x_variant":[
        "\u015e\u016bf\u012b\u0101n"
    ],
    "name:ita_x_preferred":[
        "Sufian"
    ],
    "name:mlg_x_preferred":[
        "Sufian"
    ],
    "name:msa_x_preferred":[
        "Sufian"
    ],
    "name:rus_x_preferred":[
        "\u0421\u0443\u0444\u044c\u044f\u043d"
    ],
    "name:swe_x_preferred":[
        "Soofian"
    ],
    "name:tur_x_preferred":[
        "Sufiyan"
    ],
    "name:und_x_variant":[
        "\u015eowfy\u0101n",
        "S\u016bf\u012by\u0101n"
    ],
    "name:urd_x_preferred":[
        "\u0635\u0648\u0641\u06cc\u0627\u0646"
    ],
    "name:zho_x_preferred":[
        "\u8607\u83f2\u5b89"
    ],
    "wof:name":"Sufian",
    "wof:placetype":"locality"
},
  "geometry": {"coordinates":[45.155,36.9069],"type":"Point"}
}