{
  "type": "Feature",
  "properties": {
    "gn:admin1_code":"1",
    "gn:asciiname":"Sufian",
    "gn:country_code":"IR",
    "gn:dem":1494,
    "gn:feature_class":"P",
    "gn:feature_code":"PPL",
    "gn:name":"\u015e\u016bf\u012b\u0101n",
    "gn:population":0,
    "gn:timezone":"Asia/Tehran",
    "iso:country":"IR",
    "name:fas_x_preferred":[
        "\u0635\u0648\u0641\u06cc\u0627\u0646"
    ],
    "name:fas_x_variant":[
        "\u015e\u016bf\u012b\u0101n"
    ],
    "name:und_x_variant":[
        "\u015eowfy\u0101n",
        "S\u016bf\u012by\u0101n"
    ],
    "wof:name":"Sufian",
    "wof:placetype":"locality"
},
  "geometry": {"coordinates":[45.155,36.9069],"type":"Point"}
}