{
  "type": "Feature",
  "properties": {
    "gn:admin1_code":"4.0",
    "gn:asciiname":"Machkowr",
    "gn:country_code":"IR",
    "gn:dem":1232,
    "gn:feature_class":"P",
    "gn:feature_code":"PPL",
    "gn:name":"Machkowr",
    "gn:population":0,
    "gn:timezone":"Asia/Tehran",
    "iso:country":"IR",
    "name:fas_x_preferred":[
        "\u0645\u0686\u06a9\u0648\u0631"
    ],
    "name:fas_x_variant":[
        "Manchek\u0101",
        "Mahchek\u0101"
    ],
    "name:und_x_variant":[
        "Machkowr"
    ],
    "wof:name":"Machkowr",
    "wof:placetype":"locality"
},
  "geometry": {"coordinates":[61.04858,26.78815],"type":"Point"}
}