{
  "type": "Feature",
  "properties": {
    "gn:admin1_code":"32",
    "gn:asciiname":"Niaraq",
    "gn:country_code":"IR",
    "gn:dem":1423,
    "gn:feature_class":"P",
    "gn:feature_code":"PPL",
    "gn:name":"N\u012b\u0101raq",
    "gn:population":0,
    "gn:timezone":"Asia/Tehran",
    "iso:country":"IR",
    "name:azb_x_preferred":[
        "\u0646\u06cc\u0627\u0631\u0642(\u0646\u0645\u06cc\u0646)"
    ],
    "name:fas_x_preferred":[
        "\u0646\u064a\u0627\u0631\u0642"
    ],
    "name:fas_x_variant":[
        "N\u012b\u0101raq",
        "\u0646\u0650\u064a\u0627\u0631\u0627\u0642",
        "\u0646\u06cc\u0627\u0631\u0642"
    ],
    "name:msa_x_preferred":[
        "Niaraq"
    ],
    "name:und_x_variant":[
        "Niara",
        "Ney\u0101r\u0101q",
        "Ney\u0101raq",
        "N\u012by\u0101raq"
    ],
    "wof:name":"Niaraq",
    "wof:placetype":"locality"
},
  "geometry": {"coordinates":[48.632,38.2678],"type":"Point"}
}