{
  "type": "Feature",
  "properties": {
    "gn:admin1_code":"41",
    "gn:asciiname":"Hardeng",
    "gn:country_code":"IR",
    "gn:dem":1670,
    "gn:feature_class":"P",
    "gn:feature_code":"PPL",
    "gn:name":"Hardeng",
    "gn:population":0,
    "gn:timezone":"Asia/Tehran",
    "iso:country":"IR",
    "name:fas_x_preferred":[
        "\u0647\u0631\u062f\u0646\u06af"
    ],
    "name:fas_x_variant":[
        "Hard\u012bng",
        "\u0647\u0631\u062f\u064a\u0646\u06af"
    ],
    "name:und_x_variant":[
        "Hard\u012bng",
        "Hardang",
        "Hardeng",
        "\u0647\u0631\u062f\u0646\u06af"
    ],
    "wof:name":"Hardeng",
    "wof:placetype":"locality"
},
  "geometry": {"coordinates":[59.21899000000001,32.42135],"type":"Point"}
}