{
  "type": "Feature",
  "properties": {
    "gn:admin1_code":"29",
    "gn:asciiname":"Deh Nazar",
    "gn:country_code":"IR",
    "gn:dem":1409,
    "gn:feature_class":"P",
    "gn:feature_code":"PPLL",
    "gn:name":"Deh Naz\u0327ar",
    "gn:population":0,
    "gn:timezone":"Asia/Tehran",
    "iso:country":"IR",
    "name:fas_x_preferred":[
        "\u0686\u0634\u0645\u0647 \u0646\u0638\u0631"
    ],
    "name:fas_x_variant":[
        "Cheshmeh Naz\u0327ar",
        "\u062f\u0647 \u0646\u0638\u0631"
    ],
    "name:und_x_variant":[
        "Deh Naz\u0327ar"
    ],
    "wof:name":"Deh Nazar",
    "wof:placetype":"locality"
},
  "geometry": {"coordinates":[56.50623,28.52627],"type":"Point"}
}