{
  "type": "Feature",
  "properties": {
    "gn:admin1_code":"26",
    "gn:asciiname":"Torpaq Tappeh",
    "gn:country_code":"IR",
    "gn:dem":1112,
    "gn:feature_class":"P",
    "gn:feature_code":"PPL",
    "gn:name":"Torp\u0101q Tappeh",
    "gn:population":0,
    "gn:timezone":"Asia/Tehran",
    "iso:country":"IR",
    "name:ceb_x_preferred":[
        "Torp\u0101q Tappeh"
    ],
    "name:fas_x_preferred":[
        "\u062a\u0631\u067e\u0627\u0642 \u062a\u067e\u0647"
    ],
    "name:fas_x_variant":[
        "\u062a\u064e\u0631\u064a\u0627\u0642 \u062a\u064e\u067e\u0650\u0651\u0647",
        "\u062a\u0648\u0631\u067e\u0627\u062e \u062a\u064e\u067e\u0650\u0651\u0647",
        "Torp\u0101q Tappeh"
    ],
    "name:swe_x_preferred":[
        "Torp\u0101q Tappeh"
    ],
    "name:und_x_variant":[
        "Tary\u0101q Tappeh",
        "Turp\u0101kh Tepe",
        "Tarp\u0101q Tappeh",
        "T\u016brp\u0101kh Tappeh"
    ],
    "wof:name":"Torpaq Tappeh",
    "wof:placetype":"locality"
},
  "geometry": {"coordinates":[50.9829,35.588],"type":"Point"}
}