{
  "type": "Feature",
  "properties": {
    "gn:admin1_code":"5",
    "gn:asciiname":"Kheyrmand",
    "gn:country_code":"IR",
    "gn:dem":791,
    "gn:feature_class":"P",
    "gn:feature_code":"PPL",
    "gn:name":"Kheyrmand",
    "gn:population":0,
    "gn:timezone":"Asia/Tehran",
    "iso:country":"IR",
    "name:ara_x_preferred":[
        "\u062e\u064a\u0645\u0646\u062f"
    ],
    "name:ceb_x_preferred":[
        "Kheyrmand"
    ],
    "name:fas_x_preferred":[
        "\u062e\u0650\u064a\u0645\u064e\u0646\u062f"
    ],
    "name:fas_x_variant":[
        "\u062e\u06cc\u0631\u0645\u0646\u062f",
        "\u062e\u06cc\u0645\u0646\u062f"
    ],
    "name:swe_x_preferred":[
        "Kheyrmand"
    ],
    "name:und_x_variant":[
        "Kheymand"
    ],
    "wof:name":"Kheyrmand",
    "wof:placetype":"locality"
},
  "geometry": {"coordinates":[50.79644,30.65],"type":"Point"}
}