{
  "type": "Feature",
  "properties": {
    "gn:admin1_code":"36",
    "gn:asciiname":"Baranqur",
    "gn:country_code":"IR",
    "gn:dem":1573,
    "gn:feature_class":"P",
    "gn:feature_code":"PPL",
    "gn:name":"Baranq\u016br",
    "gn:population":0,
    "gn:timezone":"Asia/Tehran",
    "iso:country":"IR",
    "name:fas_x_preferred":[
        "\u067e\u0631\u0646\u0642\u0648\u0631"
    ],
    "name:fas_x_variant":[
        "Paranq\u016br",
        "\u0628\u0631\u0646\u0642\u0648\u0631"
    ],
    "name:und_x_variant":[
        "Baranq\u016br",
        "Peranq\u016br",
        "Parangu",
        "Paranghoor"
    ],
    "wof:name":"Baranqur",
    "wof:placetype":"locality"
},
  "geometry": {"coordinates":[48.95719,36.63631],"type":"Point"}
}