{
  "type": "Feature",
  "properties": {
    "gn:admin1_code":"9.0",
    "gn:asciiname":"Mahalleh-ye Golestan",
    "gn:country_code":"IR",
    "gn:dem":1897,
    "gn:feature_class":"P",
    "gn:feature_code":"PPL",
    "gn:name":"Ma\u1e29alleh-ye Golest\u0101n",
    "gn:population":0,
    "gn:timezone":"Asia/Tehran",
    "iso:country":"IR",
    "name:fas_x_preferred":[
        "\u0645\u062d\u0644\u0647 \u06af\u0644\u0633\u062a\u0627\u0646"
    ],
    "name:und_x_variant":[
        "Ma\u1e29alleh-ye Golest\u0101n"
    ],
    "wof:name":"Mahalleh-ye Golestan",
    "wof:placetype":"locality"
},
  "geometry": {"coordinates":[48.44875,34.57465999999999],"type":"Point"}
}