{
  "type": "Feature",
  "properties": {
    "gn:admin1_code":"41.0",
    "gn:asciiname":"Chahar Tang",
    "gn:country_code":"IR",
    "gn:dem":1507,
    "gn:feature_class":"P",
    "gn:feature_code":"PPL",
    "gn:name":"Chah\u0101r Tang",
    "gn:population":0,
    "gn:timezone":"Asia/Tehran",
    "iso:country":"IR",
    "name:fas_x_preferred":[
        "\u0686\u0647\u0627\u0631 \u062a\u0646\u06af"
    ],
    "name:fas_x_variant":[
        "Chah\u0101r Tang",
        "Cheh\u0101r Ting"
    ],
    "wof:name":"Chahar Tang",
    "wof:placetype":"locality"
},
  "geometry": {"coordinates":[60.10089,32.66469],"type":"Point"}
}