{
  "type": "Feature",
  "properties": {
    "gn:admin1_code":"1",
    "gn:asciiname":"Baras Payan",
    "gn:country_code":"IR",
    "gn:dem":1706,
    "gn:feature_class":"P",
    "gn:feature_code":"PPL",
    "gn:name":"Baras Pay\u0101n",
    "gn:population":0,
    "gn:timezone":"Asia/Tehran",
    "iso:country":"IR",
    "name:azb_x_preferred":[
        "\u0628\u0631\u0633\u067e\u06cc"
    ],
    "name:ceb_x_preferred":[
        "Baras Pay\u0101n"
    ],
    "name:fas_x_preferred":[
        "\u0628\u0631\u0633 \u067e\u06cc\u0627\u0646"
    ],
    "name:fas_x_variant":[
        "Barasp\u012b",
        "Baras Pay\u0101n",
        "\u0628\u0631\u0633\u067e\u06cc"
    ],
    "name:msa_x_preferred":[
        "Baraspi"
    ],
    "name:swe_x_preferred":[
        "Baras Pay\u0101n"
    ],
    "wof:name":"Baras Payan",
    "wof:placetype":"locality"
},
  "geometry": {"coordinates":[44.8493,38.0511],"type":"Point"}
}