{
  "type": "Feature",
  "properties": {
    "gn:admin1_code":"16",
    "gn:asciiname":"Khoshkamrud-e Sofla",
    "gn:country_code":"IR",
    "gn:dem":1772,
    "gn:feature_class":"P",
    "gn:feature_code":"PPL",
    "gn:name":"Khoshkamr\u016bd-e Sofl\u00e1",
    "gn:population":0,
    "gn:timezone":"Asia/Tehran",
    "iso:country":"IR",
    "name:fas_x_preferred":[
        "Khoshkemr\u016bd-e Sofl\u00e1"
    ],
    "name:fas_x_variant":[
        "Khoshkeh Marr\u016bd-e Sofl\u00e1",
        "\u062e\u0634\u0643\u0647 \u0645\u0651\u0631\u0648\u062f \u0633\u0641\u0644\u0649",
        "\u062e\u0634\u06a9\u0645\u0631\u0648\u062f \u0633\u0641\u0644\u06cc"
    ],
    "name:und_x_variant":[
        "Voshkamar\u016b-ye P\u0101\u2019\u012bn",
        "Khoshkamr\u016bd-e Sofl\u00e1",
        "Khoshkamr\u016bd-e P\u0101\u2019\u012bn",
        "Khoshkeh Mar\u016bd"
    ],
    "wof:name":"Khoshkamrud-e Sofla",
    "wof:placetype":"locality"
},
  "geometry": {"coordinates":[47.63562,35.32315999999999],"type":"Point"}
}