{
  "type": "Feature",
  "properties": {
    "gn:admin1_code":"8",
    "gn:asciiname":"Bazar Deh",
    "gn:country_code":"IR",
    "gn:dem":-2,
    "gn:feature_class":"P",
    "gn:feature_code":"PPL",
    "gn:name":"B\u0101z\u0101r Deh",
    "gn:population":0,
    "gn:timezone":"Asia/Tehran",
    "iso:country":"IR",
    "name:fas_x_preferred":[
        "B\u0101z\u0101r Deh"
    ],
    "name:fas_x_variant":[
        "\u0628\u0627\u0632\u0627\u0631 \u062f\u0647",
        "\u0628\u0627\u0632\u0627\u0631 \u062f\u0647 \u06af\u0644\u0628\u0627\u063a",
        "\u0628\u0627\u0632\u0627\u0631\u062f\u0647"
    ],
    "name:msa_x_preferred":[
        "Bazar Deh"
    ],
    "name:ukr_x_preferred":[
        "\u0411\u0430\u0437\u0430\u0440-\u0414\u0435\u0433"
    ],
    "name:und_x_variant":[
        "\u0628\u0627\u0632\u0627\u0631 \u062f\u0647",
        "B\u0101z\u0101r Deh Golb\u0101gh"
    ],
    "wof:name":"Bazar Deh",
    "wof:placetype":"locality"
},
  "geometry": {"coordinates":[50.16777,37.20891],"type":"Point"}
}