{
  "type": "Feature",
  "properties": {
    "gn:admin1_code":"34.0",
    "gn:asciiname":"Duzaj",
    "gn:country_code":"IR",
    "gn:dem":2046,
    "gn:feature_class":"P",
    "gn:feature_code":"PPL",
    "gn:name":"D\u016bzaj",
    "gn:population":0,
    "gn:timezone":"Asia/Tehran",
    "iso:country":"IR",
    "name:ceb_x_preferred":[
        "D\u016bzaj"
    ],
    "name:fas_x_preferred":[
        "\u062f\u0648\u0632\u062c"
    ],
    "name:fas_x_variant":[
        "D\u016bzaj"
    ],
    "name:swe_x_preferred":[
        "D\u016bzaj"
    ],
    "name:ukr_x_preferred":[
        "\u0414\u0443\u0437\u0430\u0434\u0436"
    ],
    "wof:name":"Duzaj",
    "wof:placetype":"locality"
},
  "geometry": {"coordinates":[49.82267,35.39538],"type":"Point"}
}