{
  "type": "Feature",
  "properties": {
    "gn:admin1_code":"7",
    "gn:asciiname":"Tavi ol Taft",
    "gn:country_code":"IR",
    "gn:dem":1250,
    "gn:feature_class":"P",
    "gn:feature_code":"PPL",
    "gn:name":"T\u0101v\u012b ol Taft",
    "gn:population":0,
    "gn:timezone":"Asia/Tehran",
    "iso:country":"IR",
    "name:fas_x_preferred":[
        "T\u0101v\u012b ol Taft"
    ],
    "name:fas_x_variant":[
        "T\u0101veh Ta\u1e29t",
        "\u062a\u0627\u0648\u06cc \u0627\u0644\u062a\u0641\u062a",
        "\u062a\u0641\u062a"
    ],
    "name:und_x_variant":[
        "Taft"
    ],
    "wof:name":"Tavi ol Taft",
    "wof:placetype":"locality"
},
  "geometry": {"coordinates":[51.42343,30.42263],"type":"Point"}
}