{
  "type": "Feature",
  "properties": {
    "gn:admin1_code":"29",
    "gn:asciiname":"Sohran-e Vasat",
    "gn:country_code":"IR",
    "gn:dem":514,
    "gn:feature_class":"P",
    "gn:feature_code":"PPL",
    "gn:name":"Sohr\u0101n-e Vasa\u0163",
    "gn:population":0,
    "gn:timezone":"Asia/Tehran",
    "iso:country":"IR",
    "name:fas_x_preferred":[
        "\u0633\u0647\u0631\u0627\u0646 \u0648\u0633\u0637"
    ],
    "name:fas_x_variant":[
        "Sohr\u0101n-e Vasa\u0163"
    ],
    "wof:name":"Sohran-e Vasat",
    "wof:placetype":"locality"
},
  "geometry": {"coordinates":[57.8387,28.1243],"type":"Point"}
}