{
  "type": "Feature",
  "properties": {
    "gn:admin1_code":"1.0",
    "gn:asciiname":"Akhtetar",
    "gn:country_code":"IR",
    "gn:dem":1462,
    "gn:feature_class":"P",
    "gn:feature_code":"PPL",
    "gn:name":"Akhtetar",
    "gn:population":0,
    "gn:timezone":"Asia/Tehran",
    "iso:country":"IR",
    "name:aze_x_preferred":[
        "\u018fxtitar"
    ],
    "name:ceb_x_preferred":[
        "Akhtetar"
    ],
    "name:fas_x_preferred":[
        "\u0627\u064e\u062e\u062a\u0650\u062a\u064e\u0631"
    ],
    "name:fas_x_variant":[
        "\u0627\u062e\u062a\u062a\u0631"
    ],
    "name:msa_x_preferred":[
        "Akhtetar"
    ],
    "name:swe_x_preferred":[
        "Akhtetar"
    ],
    "wof:name":"Akhtetar",
    "wof:placetype":"locality"
},
  "geometry": {"coordinates":[46.1218,36.5537],"type":"Point"}
}