{
  "type": "Feature",
  "properties": {
    "gn:admin1_code":"1",
    "gn:asciiname":"Qasrik",
    "gn:country_code":"IR",
    "gn:dem":1742,
    "gn:feature_class":"P",
    "gn:feature_code":"PPL",
    "gn:name":"Qa\u015fr\u012bk",
    "gn:population":0,
    "gn:timezone":"Asia/Tehran",
    "iso:country":"IR",
    "name:fas_x_preferred":[
        "\u0642\u064e\u0635\u0631\u064a\u0643"
    ],
    "name:fas_x_variant":[
        "\u0642\u0635\u0631\u06cc\u06a9",
        "Qa\u015fr\u012bk"
    ],
    "wof:name":"Qasrik",
    "wof:placetype":"locality"
},
  "geometry": {"coordinates":[44.6954,37.8845],"type":"Point"}
}