{
  "type": "Feature",
  "properties": {
    "gn:admin1_code":"13",
    "gn:asciiname":"Kaparkeh",
    "gn:country_code":"IR",
    "gn:dem":1740,
    "gn:feature_class":"P",
    "gn:feature_code":"PPL",
    "gn:name":"Kaparkeh",
    "gn:population":0,
    "gn:timezone":"Asia/Tehran",
    "iso:country":"IR",
    "name:fas_x_preferred":[
        "\u06af\u067e\u0631\u06af\u0647 \u0633\u0645\u0627\u0642\u0633\u062a\u0627\u0646"
    ],
    "name:fas_x_variant":[
        "Kaparg\u0101h",
        "\u06a9\u067e\u0631\u06a9\u0647",
        "\u06a9\u067e\u0631\u06af\u0647"
    ],
    "name:und_x_variant":[
        "Kapargeh-e Som\u0101qest\u0101n",
        "Kaparkeh",
        "Kapargeh"
    ],
    "wof:name":"Kaparkeh",
    "wof:placetype":"locality"
},
  "geometry": {"coordinates":[47.57013,34.60001],"type":"Point"}
}