{
  "type": "Feature",
  "properties": {
    "gn:admin1_code":"7",
    "gn:asciiname":"Dar-e Emamzadeh",
    "gn:country_code":"IR",
    "gn:dem":1510,
    "gn:feature_class":"P",
    "gn:feature_code":"PPL",
    "gn:name":"Dar-e Em\u0101mz\u0101deh",
    "gn:population":0,
    "gn:timezone":"Asia/Tehran",
    "iso:country":"IR",
    "name:ara_x_preferred":[
        "\u062f\u0631\u0628 \u0627\u0645\u0627\u0645\u0632\u0627\u062f\u0629"
    ],
    "name:fas_x_preferred":[
        "\u062f\u0631\u0628 \u0627\u0645\u0627\u0645\u0632\u0627\u062f\u0647"
    ],
    "name:fas_x_variant":[
        "Darb-e Em\u0101mz\u0101deh",
        "\u062f\u0631 \u0627\u0645\u0627\u0645\u0632\u0627\u062f\u0647"
    ],
    "name:msa_x_preferred":[
        "Darb-e Emamzadeh"
    ],
    "name:und_x_variant":[
        "Dar-e Em\u0101mz\u0101deh"
    ],
    "wof:name":"Dar-e Emamzadeh",
    "wof:placetype":"locality"
},
  "geometry": {"coordinates":[54.2874,29.0435],"type":"Point"}
}