{
  "type": "Feature",
  "properties": {
    "gn:admin1_code":"15",
    "gn:asciiname":"Sar Gach",
    "gn:country_code":"IR",
    "gn:dem":1052,
    "gn:feature_class":"P",
    "gn:feature_code":"PPL",
    "gn:name":"Sar Gach",
    "gn:population":0,
    "gn:timezone":"Asia/Tehran",
    "iso:country":"IR",
    "name:ceb_x_preferred":[
        "Sar Gach"
    ],
    "name:fas_x_preferred":[
        "\u0633\u0631 \u06af\u0686"
    ],
    "name:swe_x_preferred":[
        "Sar Gach"
    ],
    "wof:name":"Sar Gach",
    "wof:placetype":"locality"
},
  "geometry": {"coordinates":[49.70908,31.73603],"type":"Point"}
}