{
  "type": "Feature",
  "properties": {
    "gn:admin1_code":"4.0",
    "gn:asciiname":"Giti",
    "gn:country_code":"IR",
    "gn:dem":32,
    "gn:feature_class":"P",
    "gn:feature_code":"PPL",
    "gn:name":"G\u012bt\u012b",
    "gn:population":0,
    "gn:timezone":"Asia/Tehran",
    "iso:country":"IR",
    "name:fas_x_preferred":[
        "G\u012btak"
    ],
    "name:fas_x_variant":[
        "G\u012bt\u012b",
        "\u06af\u06cc\u062a\u06cc"
    ],
    "name:und_x_variant":[
        "\u06af\u06cc\u062a\u06cc"
    ],
    "wof:name":"Giti",
    "wof:placetype":"locality"
},
  "geometry": {"coordinates":[61.07674,25.56625],"type":"Point"}
}