{
  "type": "Feature",
  "properties": {
    "gn:admin1_code":"3",
    "gn:asciiname":"Chand Deh",
    "gn:country_code":"IR",
    "gn:dem":1006,
    "gn:feature_class":"P",
    "gn:feature_code":"PPL",
    "gn:name":"Chand Deh",
    "gn:population":0,
    "gn:timezone":"Asia/Tehran",
    "iso:country":"IR",
    "name:fas_x_preferred":[
        "\u0686\u0650\u0646\u062f\u0650\u0647"
    ],
    "name:fas_x_variant":[
        "\u0686\u064e\u0646\u062f \u062f\u0650\u0647",
        "\u0686\u0646\u062f \u062f\u0647"
    ],
    "name:und_x_variant":[
        "Chendeh",
        "\u0686\u0646\u062f \u062f\u0647",
        "Chand Deh"
    ],
    "wof:name":"Chand Deh",
    "wof:placetype":"locality"
},
  "geometry": {"coordinates":[50.38426,31.75978],"type":"Point"}
}