{
  "type": "Feature",
  "properties": {
    "gn:admin1_code":"44",
    "gn:asciiname":"Khur",
    "gn:country_code":"IR",
    "gn:dem":2341,
    "gn:feature_class":"P",
    "gn:feature_code":"PPL",
    "gn:name":"Kh\u016br",
    "gn:population":0,
    "gn:timezone":"Asia/Tehran",
    "iso:country":"IR",
    "name:fas_x_preferred":[
        "\u062e\u0648\u0631"
    ],
    "name:fas_x_variant":[
        "Kh\u016br"
    ],
    "name:und_x_variant":[
        "G\u016bra"
    ],
    "wof:name":"Khur",
    "wof:placetype":"locality"
},
  "geometry": {"coordinates":[51.1572,35.9149],"type":"Point"}
}