{
  "type": "Feature",
  "properties": {
    "gn:admin1_code":"4.0",
    "gn:asciiname":"Gorgij",
    "gn:country_code":"IR",
    "gn:dem":22,
    "gn:feature_class":"P",
    "gn:feature_code":"PPL",
    "gn:name":"Gorg\u012bj",
    "gn:population":0,
    "gn:timezone":"Asia/Tehran",
    "iso:country":"IR",
    "name:fas_x_preferred":[
        "Gorg\u012bj"
    ],
    "name:fas_x_variant":[
        "\u06af\u0631\u06af\u06cc\u062c"
    ],
    "name:und_x_variant":[
        "Gorg-e \u016am\u0101r",
        "G\u016brg\u012bj",
        "Gorgej Um\u0101r",
        "Korak\u012b J\u0101n",
        "\u06af\u0631\u06af\u06cc\u062c"
    ],
    "wof:name":"Gorgij",
    "wof:placetype":"locality"
},
  "geometry": {"coordinates":[61.21893000000001,25.54371],"type":"Point"}
}