{
  "type": "Feature",
  "properties": {
    "gn:admin1_code":"4",
    "gn:asciiname":"Zahan",
    "gn:country_code":"IR",
    "gn:dem":1203,
    "gn:feature_class":"P",
    "gn:feature_code":"PPL",
    "gn:name":"Zah\u0101n",
    "gn:population":0,
    "gn:timezone":"Asia/Tehran",
    "iso:country":"IR",
    "name:fas_x_preferred":[
        "\u0632\u0647\u0627\u0646"
    ],
    "name:fas_x_variant":[
        "Zah\u0101n"
    ],
    "wof:name":"Zahan",
    "wof:placetype":"locality"
},
  "geometry": {"coordinates":[61.34206,26.77476],"type":"Point"}
}