{
  "type": "Feature",
  "properties": {
    "gn:admin1_code":"29",
    "gn:asciiname":"Vali-ye `Asr",
    "gn:country_code":"IR",
    "gn:dem":1100,
    "gn:feature_class":"P",
    "gn:feature_code":"PPL",
    "gn:name":"Val\u012b-ye \u2018A\u015fr",
    "gn:population":0,
    "gn:timezone":"Asia/Tehran",
    "iso:country":"IR",
    "name:fas_x_preferred":[
        "\u0648\u0644\u06cc \u0639\u0635\u0631"
    ],
    "name:fas_x_variant":[
        "Val\u012b-ye \u2018A\u015fr"
    ],
    "wof:name":"Vali-ye `Asr",
    "wof:placetype":"locality"
},
  "geometry": {"coordinates":[58.3196,29.117],"type":"Point"}
}