{
  "type": "Feature",
  "properties": {
    "gn:admin1_code":"36",
    "gn:asciiname":"Lagahi",
    "gn:country_code":"IR",
    "gn:dem":1944,
    "gn:feature_class":"P",
    "gn:feature_code":"PPL",
    "gn:name":"Lag\u0101h\u012b",
    "gn:population":0,
    "gn:timezone":"Asia/Tehran",
    "iso:country":"IR",
    "name:azb_x_preferred":[
        "\u0644\u06af\u0627\u0647\u06cc"
    ],
    "name:ceb_x_preferred":[
        "Leg\u0101h\u012b"
    ],
    "name:fas_x_preferred":[
        "\u0644\u06af\u0627\u0647\u06cc"
    ],
    "name:fas_x_variant":[
        "Leg\u0101h\u012b",
        "\u0644\u064e\u06af\u0627\u0647\u06cc"
    ],
    "name:swe_x_preferred":[
        "Leg\u0101h\u012b"
    ],
    "name:und_x_variant":[
        "Nak\u0101h\u012b",
        "Lyakyagi",
        "Lag\u0101h\u012b"
    ],
    "wof:name":"Lagahi",
    "wof:placetype":"locality"
},
  "geometry": {"coordinates":[48.40619,36.89301],"type":"Point"}
}