{
  "type": "Feature",
  "properties": {
    "gn:admin1_code":"23",
    "gn:asciiname":"Chal-e Seyd `Ali",
    "gn:country_code":"IR",
    "gn:dem":1866,
    "gn:feature_class":"P",
    "gn:feature_code":"PPL",
    "gn:name":"Ch\u0101l-e \u015eeyd \u2018Al\u012b",
    "gn:population":0,
    "gn:timezone":"Asia/Tehran",
    "iso:country":"IR",
    "name:fas_x_preferred":[
        "\u0686\u0627\u0644\u0650 \u0635\u0650\u064a\u062f \u0639\u064e\u0644\u06cc"
    ],
    "name:fas_x_variant":[
        "\u0686\u0627\u0644 \u0635\u06cc\u062f \u0639\u0644\u06cc",
        "Ch\u0101l-e \u015eeyd \u2018Al\u012b"
    ],
    "wof:name":"Chal-e Seyd `Ali",
    "wof:placetype":"locality"
},
  "geometry": {"coordinates":[47.8593,34.1813],"type":"Point"}
}