{
  "type": "Feature",
  "properties": {
    "gn:admin1_code":"4",
    "gn:asciiname":"Si Sani",
    "gn:country_code":"IR",
    "gn:dem":1658,
    "gn:feature_class":"P",
    "gn:feature_code":"PPL",
    "gn:name":"S\u012b San\u012b",
    "gn:population":0,
    "gn:timezone":"Asia/Tehran",
    "iso:country":"IR",
    "name:fas_x_preferred":[
        "\u0633\u06cc \u0633\u0646\u06cc"
    ],
    "name:fas_x_variant":[
        "S\u012b San\u012b"
    ],
    "wof:name":"Si Sani",
    "wof:placetype":"locality"
},
  "geometry": {"coordinates":[60.18628,29.00076],"type":"Point"}
}