{
  "type": "Feature",
  "properties": {
    "gn:admin1_code":"22",
    "gn:asciiname":"Now Kan",
    "gn:country_code":"IR",
    "gn:dem":34,
    "gn:feature_class":"P",
    "gn:feature_code":"PPL",
    "gn:name":"Now Kan",
    "gn:population":0,
    "gn:timezone":"Asia/Tehran",
    "iso:country":"IR",
    "name:fas_x_preferred":[
        "\u0646\u064f\u0648 \u0643\u064e\u0647\u064e\u0646\u062f"
    ],
    "name:fas_x_variant":[
        "\u0646\u0648 \u0643\u0646",
        "\u0646\u064f\u0648\u0643\u064e\u0646"
    ],
    "name:und_x_variant":[
        "Now Kahand",
        "Nauk\u0101n"
    ],
    "wof:name":"Now Kan",
    "wof:placetype":"locality"
},
  "geometry": {"coordinates":[51.75815,28.01114],"type":"Point"}
}