{
  "type": "Feature",
  "properties": {
    "gn:admin1_code":"26.0",
    "gn:asciiname":"Now Deh",
    "gn:country_code":"IR",
    "gn:dem":1698,
    "gn:feature_class":"P",
    "gn:feature_code":"PPL",
    "gn:name":"Now Deh",
    "gn:population":0,
    "gn:timezone":"Asia/Tehran",
    "iso:country":"IR",
    "name:ara_x_preferred":[
        "\u0646\u0648 \u062f\u0647"
    ],
    "name:fas_x_preferred":[
        "\u0646\u0648 \u062f\u0647"
    ],
    "name:fas_x_variant":[
        "\u0646\u0648\u062f\u0647"
    ],
    "wof:name":"Now Deh",
    "wof:placetype":"locality"
},
  "geometry": {"coordinates":[51.9209,35.6889],"type":"Point"}
}