{
  "type": "Feature",
  "properties": {
    "gn:admin1_code":"34",
    "gn:asciiname":"Tayyebabad",
    "gn:country_code":"IR",
    "gn:dem":2039,
    "gn:feature_class":"P",
    "gn:feature_code":"PPL",
    "gn:name":"\u0162ayyeb\u0101b\u0101d",
    "gn:population":0,
    "gn:timezone":"Asia/Tehran",
    "iso:country":"IR",
    "name:ceb_x_preferred":[
        "\u0162ayyeb\u0101b\u0101d"
    ],
    "name:fas_x_preferred":[
        "\u0637\u064e\u064a\u0650\u0651\u0628"
    ],
    "name:fas_x_variant":[
        "\u0637\u064a\u0628",
        "\u062a\u0650\u064a\u0628 \u0622\u0628\u0627\u062f",
        "\u0162ayyeb\u0101b\u0101d",
        "\u0637\u064a\u0628 \u0622\u0628\u0627\u062f",
        "\u0637\u06cc\u0628\u200c\u0622\u0628\u0627\u062f"
    ],
    "name:swe_x_preferred":[
        "\u0162ayyeb\u0101b\u0101d"
    ],
    "name:ukr_x_preferred":[
        "\u0422\u0430\u0439\u0454\u0431\u0430\u0431\u0430\u0434"
    ],
    "name:und_x_variant":[
        "\u0162\u012bb",
        "\u0162ayyeb",
        "Teyb\u0101b\u0101d",
        "\u0637\u064a\u0628 \u0622\u0628\u0627\u062f"
    ],
    "wof:name":"Tayyebabad",
    "wof:placetype":"locality"
},
  "geometry": {"coordinates":[49.78882,33.68657],"type":"Point"}
}