{
  "type": "Feature",
  "properties": {
    "gn:admin1_code":"13",
    "gn:asciiname":"Chahardah Jofteh",
    "gn:country_code":"IR",
    "gn:dem":1298,
    "gn:feature_class":"P",
    "gn:feature_code":"PPL",
    "gn:name":"Chah\u0101rdah Jofteh",
    "gn:population":0,
    "gn:timezone":"Asia/Tehran",
    "iso:country":"IR",
    "name:ara_x_preferred":[
        "\u062a\u0634\u0647\u0627\u0631\u062f\u0647\u200c\u062c\u0641\u062a\u0629"
    ],
    "name:ceb_x_preferred":[
        "Chah\u0101rdah Jofteh"
    ],
    "name:fas_x_preferred":[
        "\u0686\u0647\u0627\u0631\u062f\u0647 \u062c\u0641\u062a\u0647"
    ],
    "name:fas_x_variant":[
        "Chah\u0101rdah Jofteh",
        "\u0686\u0647\u0627\u0631\u062f\u0647\u200c\u062c\u0641\u062a\u0647"
    ],
    "name:swe_x_preferred":[
        "Chah\u0101rdah Jofteh"
    ],
    "wof:name":"Chahardah Jofteh",
    "wof:placetype":"locality"
},
  "geometry": {"coordinates":[46.8156,33.8662],"type":"Point"}
}