{
  "type": "Feature",
  "properties": {
    "gn:admin1_code":"33",
    "gn:asciiname":"Shah Bolagh-e Bala",
    "gn:country_code":"IR",
    "gn:dem":2331,
    "gn:feature_class":"P",
    "gn:feature_code":"PPL",
    "gn:name":"Sh\u0101h Bol\u0101gh-e B\u0101l\u0101",
    "gn:population":0,
    "gn:timezone":"Asia/Tehran",
    "iso:country":"IR",
    "name:fas_x_preferred":[
        "\u0634\u0627\u0647 \u0628\u0644\u0627\u063a \u0628\u0627\u0644\u0627"
    ],
    "name:fas_x_variant":[
        "Sh\u0101h Bol\u0101gh-e B\u0101l\u0101",
        "\u0643\u0648\u06cc \u0628\u064f\u0644\u0627\u063a\u0650 \u0628\u0627\u0644\u0627",
        "\u0634\u0627\u0647\u0628\u0644\u0627\u063a \u0628\u0627\u0644\u0627"
    ],
    "name:und_x_variant":[
        "Sh\u0101kh Bul\u0101gh",
        "Shah Bolagh Olya",
        "Sheykh Bol\u0101gh",
        "Sh\u0101hbol\u0101gh\u012b B\u0101l\u0101",
        "Shakh-Bulag",
        "Sh\u0101h Bol\u0101gh",
        "Sh\u0101h Bol\u0101gh B\u0101l\u0101",
        "Sh\u0101h Bol\u0101gh\u012b-ye B\u0101l\u0101",
        "K\u016by Bol\u0101gh-e B\u0101l\u0101"
    ],
    "wof:name":"Shah Bolagh-e Bala",
    "wof:placetype":"locality"
},
  "geometry": {"coordinates":[46.3912,38.4626],"type":"Point"}
}