{
  "type": "Feature",
  "properties": {
    "gn:admin1_code":"7",
    "gn:asciiname":"Galleh Dar",
    "gn:country_code":"IR",
    "gn:dem":468,
    "gn:feature_class":"P",
    "gn:feature_code":"PPL",
    "gn:name":"Galleh D\u0101r",
    "gn:population":0,
    "gn:timezone":"Asia/Tehran",
    "iso:country":"IR",
    "name:fas_x_preferred":[
        "\u06af\u0644\u0647 \u062f\u0627\u0631"
    ],
    "name:fas_x_variant":[
        "Galehd\u0101r",
        "Galleh D\u0101r"
    ],
    "name:und_x_variant":[
        "Kaleh D\u0101r",
        "Gilehd\u0101r"
    ],
    "wof:name":"Galleh Dar",
    "wof:placetype":"locality"
},
  "geometry": {"coordinates":[52.6575,27.6595],"type":"Point"}
}