{
  "type": "Feature",
  "properties": {
    "gn:admin1_code":"7",
    "gn:asciiname":"Galleh Dar",
    "gn:country_code":"IR",
    "gn:dem":468,
    "gn:feature_class":"P",
    "gn:feature_code":"PPL",
    "gn:name":"Galleh D\u0101r",
    "gn:population":0,
    "gn:timezone":"Asia/Tehran",
    "iso:country":"IR",
    "name:ara_x_preferred":[
        "\u063a\u0644\u0647\u200c\u062f\u0627\u0631"
    ],
    "name:aze_x_preferred":[
        "G\u0259ll\u0259dar"
    ],
    "name:ceb_x_preferred":[
        "Galleh D\u0101r"
    ],
    "name:fas_x_preferred":[
        "\u06af\u0644\u0647 \u062f\u0627\u0631"
    ],
    "name:fas_x_variant":[
        "Galehd\u0101r",
        "Galleh D\u0101r",
        "\u06af\u0644\u0647\u200c\u062f\u0627\u0631"
    ],
    "name:ita_x_preferred":[
        "Gallehdar"
    ],
    "name:mlg_x_preferred":[
        "Galleh Dar"
    ],
    "name:msa_x_preferred":[
        "Galleh Dar"
    ],
    "name:rus_x_preferred":[
        "\u0413\u0430\u043b\u043b\u0435\u0434\u0430\u0440"
    ],
    "name:swe_x_preferred":[
        "Galleh D\u0101r"
    ],
    "name:tur_x_preferred":[
        "Gelledar"
    ],
    "name:und_x_variant":[
        "Kaleh D\u0101r",
        "Gilehd\u0101r"
    ],
    "name:urd_x_preferred":[
        "\u06af\u0644\u06c1\u200c\u062f\u0627\u0631"
    ],
    "wof:name":"Galleh Dar",
    "wof:placetype":"locality"
},
  "geometry": {"coordinates":[52.6575,27.6595],"type":"Point"}
}