{
  "type": "Feature",
  "properties": {
    "gn:admin1_code":"29",
    "gn:asciiname":"Firuzabad",
    "gn:country_code":"IR",
    "gn:dem":2040,
    "gn:feature_class":"P",
    "gn:feature_code":"PPL",
    "gn:name":"F\u012br\u016bz\u0101b\u0101d",
    "gn:population":0,
    "gn:timezone":"Asia/Tehran",
    "iso:country":"IR",
    "name:fas_x_preferred":[
        "F\u012br\u016bz\u0101b\u0101d"
    ],
    "name:fas_x_variant":[
        "\u0641\u06cc\u0631\u0648\u0632 \u0622\u0628\u0627\u062f"
    ],
    "name:und_x_variant":[
        "\u0641\u06cc\u0631\u0648\u0632 \u0622\u0628\u0627\u062f"
    ],
    "wof:name":"Firuzabad",
    "wof:placetype":"locality"
},
  "geometry": {"coordinates":[55.90243,29.59139],"type":"Point"}
}