{
  "type": "Feature",
  "properties": {
    "gn:admin1_code":"29",
    "gn:asciiname":"Golzar",
    "gn:country_code":"IR",
    "gn:dem":2326,
    "gn:feature_class":"P",
    "gn:feature_code":"PPL",
    "gn:name":"Golz\u0101r",
    "gn:population":0,
    "gn:timezone":"Asia/Tehran",
    "iso:country":"IR",
    "name:fas_x_preferred":[
        "\u062f\u0647 \u062a\u0627\u0632\u06cc\u0627\u0646"
    ],
    "name:fas_x_variant":[
        "Deh T\u0101z\u012b\u0101n",
        "\u06af\u0644\u0632\u0627\u0631",
        "\u0642\u0631\u064a\u0647 \u0627\u0644\u0639\u0631\u0628"
    ],
    "name:und_x_variant":[
        "Kar\u012b\u0101l ul \u2018Arab",
        "Deh-e T\u0101z\u012b\u0101n",
        "T\u0101z\u012b\u0101n",
        "Deh T\u0101zey\u0101n",
        "Qaryatol \u2018Arab",
        "Qaryat ol \u2018Arab",
        "Qari\u0101t al Arab",
        "Qar\u012bya-tol-\u2019Arab",
        "Golz\u0101r",
        "Qaryeh ol \u2018Arab"
    ],
    "wof:name":"Golzar",
    "wof:placetype":"locality"
},
  "geometry": {"coordinates":[57.0394,29.7113],"type":"Point"}
}