{
  "type": "Feature",
  "properties": {
    "gn:admin1_code":"15.0",
    "gn:asciiname":"`Ali Yar-e Dowrab",
    "gn:country_code":"IR",
    "gn:dem":627,
    "gn:feature_class":"P",
    "gn:feature_code":"PPL",
    "gn:name":"\u2018Al\u012b Y\u0101r-e Dowr\u0101b",
    "gn:population":0,
    "gn:timezone":"Asia/Tehran",
    "iso:country":"IR",
    "name:fas_x_preferred":[
        "\u0639\u0644\u06cc \u064a\u0627\u0631 \u062f\u0648\u0631\u0627\u0628"
    ],
    "name:fas_x_variant":[
        "Sh\u012brkosh",
        "\u0634\u06cc\u0631\u06a9\u0634"
    ],
    "wof:name":"`Ali Yar-e Dowrab",
    "wof:placetype":"locality"
},
  "geometry": {"coordinates":[49.3726,32.2506],"type":"Point"}
}