{
  "type": "Feature",
  "properties": {
    "gn:admin1_code":"16.0",
    "gn:asciiname":"Sheykh Heydar",
    "gn:country_code":"IR",
    "gn:dem":1820,
    "gn:feature_class":"P",
    "gn:feature_code":"PPL",
    "gn:name":"Sheykh \u1e28eydar",
    "gn:population":0,
    "gn:timezone":"Asia/Tehran",
    "iso:country":"IR",
    "name:fas_x_preferred":[
        "\u0634\u0650\u064a\u062e \u062d\u064a\u062f\u0631"
    ],
    "name:fas_x_variant":[
        "Sheykh \u1e28eydar"
    ],
    "wof:name":"Sheykh Heydar",
    "wof:placetype":"locality"
},
  "geometry": {"coordinates":[46.94532,35.85824],"type":"Point"}
}