{
  "type": "Feature",
  "properties": {
    "gn:admin1_code":"13",
    "gn:asciiname":"Divan",
    "gn:country_code":"IR",
    "gn:dem":1269,
    "gn:feature_class":"P",
    "gn:feature_code":"PPL",
    "gn:name":"D\u012bvan",
    "gn:population":0,
    "gn:timezone":"Asia/Tehran",
    "iso:country":"IR",
    "name:ara_x_preferred":[
        "\u0627\u0644\u062f\u064a\u0648\u0627\u0646"
    ],
    "name:bul_x_preferred":[
        "\u0414\u0438\u0432\u0430\u043d"
    ],
    "name:dan_x_preferred":[
        "Divan"
    ],
    "name:deu_x_preferred":[
        "Diwan"
    ],
    "name:fas_x_preferred":[
        "\u062f\u06cc\u0648\u0646\u062f"
    ],
    "name:fas_x_variant":[
        "D\u012bvand",
        "\u062f\u06cc\u0648\u0646",
        "\u062f\u06cc\u0648\u0627\u0646"
    ],
    "name:fra_x_preferred":[
        "Divan"
    ],
    "name:hun_x_preferred":[
        "Div\u00e1n"
    ],
    "name:ita_x_preferred":[
        "Diwan"
    ],
    "name:kat_x_preferred":[
        "\u10d3\u10d8\u10d5\u10d0\u10dc\u10d8"
    ],
    "name:lav_x_preferred":[
        "Div\u0101ns"
    ],
    "name:nld_x_preferred":[
        "Divan"
    ],
    "name:nno_x_preferred":[
        "Diwan"
    ],
    "name:pol_x_preferred":[
        "Dywan"
    ],
    "name:por_x_preferred":[
        "Div\u00e3"
    ],
    "name:ron_x_preferred":[
        "Divan"
    ],
    "name:rus_x_preferred":[
        "\u0414\u0438\u0432\u0430\u043d"
    ],
    "name:spa_x_preferred":[
        "Div\u00e1n"
    ],
    "name:srp_x_preferred":[
        "\u0414\u0438\u0432\u0430\u043d"
    ],
    "name:tat_x_preferred":[
        "Diwan"
    ],
    "name:ukr_x_preferred":[
        "\u0414\u0438\u0432\u0430\u043d"
    ],
    "name:und_x_variant":[
        "Dehvand",
        "D\u012bvan"
    ],
    "name:urd_x_preferred":[
        "\u062f\u06cc\u0648\u0627\u0646"
    ],
    "name:uzb_x_preferred":[
        "Devon"
    ],
    "wof:name":"Divan",
    "wof:placetype":"locality"
},
  "geometry": {"coordinates":[47.2139,33.8692],"type":"Point"}
}