{
  "type": "Feature",
  "properties": {
    "gn:admin1_code":"13",
    "gn:asciiname":"Divan",
    "gn:country_code":"IR",
    "gn:dem":1269,
    "gn:feature_class":"P",
    "gn:feature_code":"PPL",
    "gn:name":"D\u012bvan",
    "gn:population":0,
    "gn:timezone":"Asia/Tehran",
    "iso:country":"IR",
    "name:fas_x_preferred":[
        "\u062f\u06cc\u0648\u0646\u062f"
    ],
    "name:fas_x_variant":[
        "D\u012bvand",
        "\u062f\u06cc\u0648\u0646"
    ],
    "name:und_x_variant":[
        "Dehvand",
        "D\u012bvan"
    ],
    "wof:name":"Divan",
    "wof:placetype":"locality"
},
  "geometry": {"coordinates":[47.2139,33.8692],"type":"Point"}
}