{
  "type": "Feature",
  "properties": {
    "gn:admin1_code":"8.0",
    "gn:asciiname":"Donbaleh Deh",
    "gn:country_code":"IR",
    "gn:dem":1638,
    "gn:feature_class":"P",
    "gn:feature_code":"PPL",
    "gn:name":"Donb\u0101leh Deh",
    "gn:population":0,
    "gn:timezone":"Asia/Tehran",
    "iso:country":"IR",
    "name:fas_x_preferred":[
        "Donb\u0101leh Deh"
    ],
    "name:fas_x_variant":[
        "\u062f\u0646\u0628\u0627\u0644\u0647 \u062f\u0647"
    ],
    "wof:name":"Donbaleh Deh",
    "wof:placetype":"locality"
},
  "geometry": {"coordinates":[49.80215,36.79834],"type":"Point"}
}