{
  "type": "Feature",
  "properties": {
    "gn:admin1_code":"29",
    "gn:asciiname":"Bondar",
    "gn:country_code":"IR",
    "gn:dem":2698,
    "gn:feature_class":"P",
    "gn:feature_code":"PPLL",
    "gn:name":"Bondar",
    "gn:population":0,
    "gn:timezone":"Asia/Tehran",
    "iso:country":"IR",
    "name:bel_x_preferred":[
        "\u0411\u043e\u043d\u0434\u0430\u0440"
    ],
    "name:deu_x_preferred":[
        "Bondar"
    ],
    "name:fas_x_preferred":[
        "\u0628\u0646\u062f\u0631"
    ],
    "name:fra_x_preferred":[
        "Bondar"
    ],
    "name:jpn_x_preferred":[
        "\u30dc\u30f3\u30c0\u30eb"
    ],
    "name:rus_x_preferred":[
        "\u0411\u043e\u043d\u0434\u0430\u0440\u044c"
    ],
    "name:ukr_x_preferred":[
        "\u0411\u043e\u043d\u0434\u0430\u0440"
    ],
    "name:und_x_variant":[
        "\u0628\u0646\u062f\u0631",
        "B\u0101b Sakk\u0101k\u0101n",
        "Bab Sakakan",
        "B\u0101b-e Sakk\u0101k\u0101n",
        "B\u0101b Sk\u0101k\u0101n",
        "Darreh Sehg\u016b",
        "B\u0101b-e Sak\u0101k\u0101n"
    ],
    "wof:name":"Bondar",
    "wof:placetype":"locality"
},
  "geometry": {"coordinates":[57.34761999999999,29.20229],"type":"Point"}
}