{
  "type": "Feature",
  "properties": {
    "gn:admin1_code":"34",
    "gn:asciiname":"Now Deh",
    "gn:country_code":"IR",
    "gn:dem":1976,
    "gn:feature_class":"P",
    "gn:feature_code":"PPL",
    "gn:name":"Now Deh",
    "gn:population":0,
    "gn:timezone":"Asia/Tehran",
    "iso:country":"IR",
    "name:ceb_x_preferred":[
        "Now Deh"
    ],
    "name:fas_x_preferred":[
        "\u0646\u0648 \u062f\u0647"
    ],
    "name:fas_x_variant":[
        "\u0646\u0648 \u062f\u0647 \u0646\u0645\u06a9 \u06a9\u0648\u0631"
    ],
    "name:swe_x_preferred":[
        "Now Deh"
    ],
    "name:und_x_variant":[
        "Now Deh Namak K\u016br"
    ],
    "wof:name":"Now Deh",
    "wof:placetype":"locality"
},
  "geometry": {"coordinates":[49.4813,34.105],"type":"Point"}
}