{
  "type": "Feature",
  "properties": {
    "gn:admin1_code":"7.0",
    "gn:asciiname":"Pay-e Nal",
    "gn:country_code":"IR",
    "gn:dem":646,
    "gn:feature_class":"P",
    "gn:feature_code":"PPL",
    "gn:name":"P\u0101y-e N\u0101l",
    "gn:population":0,
    "gn:timezone":"Asia/Tehran",
    "iso:country":"IR",
    "name:fas_x_preferred":[
        "\u067e\u0627\u06cc \u0646\u0627\u0644"
    ],
    "name:fas_x_variant":[
        "P\u0101y-e N\u0101l"
    ],
    "wof:name":"Pay-e Nal",
    "wof:placetype":"locality"
},
  "geometry": {"coordinates":[51.3032,29.782],"type":"Point"}
}