{
  "type": "Feature",
  "properties": {
    "gn:admin1_code":"37.0",
    "gn:asciiname":"Kamlar",
    "gn:country_code":"IR",
    "gn:dem":-23,
    "gn:feature_class":"P",
    "gn:feature_code":"PPL",
    "gn:name":"Kamlar",
    "gn:population":0,
    "gn:timezone":"Asia/Tehran",
    "iso:country":"IR",
    "name:fas_x_preferred":[
        "\u06a9\u0645\u0644\u0631"
    ],
    "name:fas_x_variant":[
        "Ka\u015flar"
    ],
    "name:und_x_variant":[
        "Kemler"
    ],
    "wof:name":"Kamlar",
    "wof:placetype":"locality"
},
  "geometry": {"coordinates":[54.14596,37.00082],"type":"Point"}
}