{
  "type": "Feature",
  "properties": {
    "gn:admin1_code":"8",
    "gn:asciiname":"Chamesqal",
    "gn:country_code":"IR",
    "gn:dem":-21,
    "gn:feature_class":"P",
    "gn:feature_code":"PPL",
    "gn:name":"Chames\u0304q\u0101l",
    "gn:population":0,
    "gn:timezone":"Asia/Tehran",
    "iso:country":"IR",
    "name:ceb_x_preferred":[
        "Ch\u016bmes\u0304q\u0101l"
    ],
    "name:fas_x_preferred":[
        "\u0686\u0648\u0645\u062b\u0642\u0627\u0644"
    ],
    "name:fas_x_variant":[
        "Chomes\u0304q\u0101l",
        "Ch\u016bmes\u0304q\u0101l",
        "\u0686\u0645\u062b\u0642\u0627\u0644"
    ],
    "name:msa_x_preferred":[
        "Chomesqal"
    ],
    "name:swe_x_preferred":[
        "Ch\u016bmes\u0304q\u0101l"
    ],
    "name:ukr_x_preferred":[
        "\u0427\u043e\u043c\u0435\u0441\u043a\u0430\u043b\u044c"
    ],
    "name:und_x_variant":[
        "Chams\u0304aq\u0101l",
        "Ch\u016bmes\u0304q\u0101l",
        "Chames\u0304q\u0101l"
    ],
    "wof:name":"Chamesqal",
    "wof:placetype":"locality"
},
  "geometry": {"coordinates":[49.36559000000001,37.36989000000001],"type":"Point"}
}