{
  "type": "Feature",
  "properties": {
    "gn:admin1_code":"4.0",
    "gn:asciiname":"Deh-e Mohammadi",
    "gn:country_code":"IR",
    "gn:dem":1136,
    "gn:feature_class":"P",
    "gn:feature_code":"PPL",
    "gn:name":"Deh-e Mo\u1e29ammad\u012b",
    "gn:population":0,
    "gn:timezone":"Asia/Tehran",
    "iso:country":"IR",
    "name:fas_x_preferred":[
        "\u062f\u0634\u062a\u0648\u06a9"
    ],
    "name:fas_x_variant":[
        "Dasht\u016bk",
        "\u062f\u0647 \u0645\u062d\u0645\u062f\u06cc",
        "\u0645\u062d\u0645\u0651\u062f\u06cc",
        "\u062f\u0634\u062a\u06a9"
    ],
    "name:und_x_variant":[
        "Poshtak",
        "Poshtok",
        "Deh-e Mo\u1e29ammad\u012b",
        "Muhammad\u012b",
        "Mo\u1e29ammad\u012b",
        "Mo\u1e29ammad\u012b Deh",
        "Dashtak"
    ],
    "wof:name":"Deh-e Mohammadi",
    "wof:placetype":"locality"
},
  "geometry": {"coordinates":[62.3796,27.3167],"type":"Point"}
}