{
  "type": "Feature",
  "properties": {
    "gn:admin1_code":"1",
    "gn:asciiname":"Nari",
    "gn:country_code":"IR",
    "gn:dem":1667,
    "gn:feature_class":"P",
    "gn:feature_code":"PPL",
    "gn:name":"N\u0101r\u012b",
    "gn:population":0,
    "gn:timezone":"Asia/Tehran",
    "iso:country":"IR",
    "name:ceb_x_preferred":[
        "Nari"
    ],
    "name:deu_x_preferred":[
        "Nari"
    ],
    "name:fas_x_preferred":[
        "\u062e\u0627\u0631\u06cc"
    ],
    "name:fas_x_variant":[
        "\u0646\u0627\u0631\u06cc",
        "N\u0101r\u012b"
    ],
    "name:swe_x_preferred":[
        "Nari"
    ],
    "name:ukr_x_preferred":[
        "\u041d\u0430\u0440\u0456"
    ],
    "name:und_x_variant":[
        "Kh\u0101r\u012b"
    ],
    "wof:name":"Nari",
    "wof:placetype":"locality"
},
  "geometry": {"coordinates":[44.869,37.3325],"type":"Point"}
}