{
  "type": "Feature",
  "properties": {
    "gn:admin1_code":"3",
    "gn:asciiname":"Mian Dahan-e Sofla",
    "gn:country_code":"IR",
    "gn:dem":1635,
    "gn:feature_class":"P",
    "gn:feature_code":"PPL",
    "gn:name":"M\u012b\u0101n Dah\u0101n-e Sofl\u00e1",
    "gn:population":0,
    "gn:timezone":"Asia/Tehran",
    "iso:country":"IR",
    "name:fas_x_preferred":[
        "M\u012b\u0101n Dah\u0101n-e Sofl\u00e1"
    ],
    "name:fas_x_variant":[
        "\u0645\u064a\u0627\u0646 \u062f\u0647\u0627\u0646 \u0633\u0641\u0644\u0649"
    ],
    "name:und_x_variant":[
        "\u0645\u064a\u0627\u0646 \u062f\u0647\u0627\u0646 \u0633\u0641\u0644\u0649"
    ],
    "wof:name":"Mian Dahan-e Sofla",
    "wof:placetype":"locality"
},
  "geometry": {"coordinates":[50.08676,32.20079],"type":"Point"}
}