{
  "type": "Feature",
  "properties": {
    "gn:admin1_code":"1.0",
    "gn:asciiname":"Khaneqah",
    "gn:country_code":"IR",
    "gn:dem":1639,
    "gn:feature_class":"P",
    "gn:feature_code":"PPL",
    "gn:name":"Kh\u0101neq\u0101h",
    "gn:population":0,
    "gn:timezone":"Asia/Tehran",
    "iso:country":"IR",
    "name:fas_x_preferred":[
        "\u062e\u0627\u0646\u0642\u0627\u0647"
    ],
    "name:fas_x_variant":[
        "Kh\u0101neq\u0101h"
    ],
    "wof:name":"Khaneqah",
    "wof:placetype":"locality"
},
  "geometry": {"coordinates":[45.9611,36.615],"type":"Point"}
}