{
  "type": "Feature",
  "properties": {
    "gn:admin1_code":"36",
    "gn:asciiname":"Sa`idabad-e Sofla",
    "gn:country_code":"IR",
    "gn:dem":1937,
    "gn:feature_class":"P",
    "gn:feature_code":"PPL",
    "gn:name":"Sa\u2018\u012bd\u0101b\u0101d-e Sofl\u00e1",
    "gn:population":0,
    "gn:timezone":"Asia/Tehran",
    "iso:country":"IR",
    "name:fas_x_preferred":[
        "\u0633\u064e\u0639\u064a\u062f\u0627\u0628\u0627\u062f\u0650 \u067e\u0627\u0626\u064a\u0646"
    ],
    "name:fas_x_variant":[
        "\u0633\u064e\u0641\u064a\u062f\u0627\u0628\u0627\u062f\u0650 \u0633\u064f\u0641\u0644\u064e\u0649",
        "\u0633\u0639\u064a\u062f \u0622\u0628\u0627\u062f \u0633\u0641\u0644\u0649",
        "Sa\u2018\u012bd\u0101b\u0101d-e P\u0101\u2019\u012bn",
        "Sa\u2018\u012bd\u0101b\u0101d-e Sofl\u00e1"
    ],
    "name:und_x_variant":[
        "Sa\u2018id Abad Sofla",
        "Saf\u012bd\u0101b\u0101d-e Sofl\u00e1"
    ],
    "wof:name":"Sa`idabad-e Sofla",
    "wof:placetype":"locality"
},
  "geometry": {"coordinates":[48.1061,36.3861],"type":"Point"}
}