{
  "type": "Feature",
  "properties": {
    "gn:admin1_code":"42.0",
    "gn:asciiname":"Bazangan",
    "gn:country_code":"IR",
    "gn:dem":1035,
    "gn:feature_class":"P",
    "gn:feature_code":"PPL",
    "gn:name":"Bazang\u0101n",
    "gn:population":0,
    "gn:timezone":"Asia/Tehran",
    "iso:country":"IR",
    "name:fas_x_preferred":[
        "\u0628\u0632\u0646\u06af\u0627\u0646"
    ],
    "name:fas_x_variant":[
        "Bazang\u0101n"
    ],
    "name:hrv_x_preferred":[
        "Bazangan"
    ],
    "name:und_x_variant":[
        "Mazang\u0101n",
        "Bezang\u0101n",
        "Bozang\u0101n",
        "Bezamg\u0101n"
    ],
    "wof:name":"Bazangan",
    "wof:placetype":"locality"
},
  "geometry": {"coordinates":[60.4315,36.2959],"type":"Point"}
}