{
  "type": "Feature",
  "properties": {
    "gn:admin1_code":"32",
    "gn:asciiname":"Qelimp",
    "gn:country_code":"IR",
    "gn:dem":1757,
    "gn:feature_class":"P",
    "gn:feature_code":"PPL",
    "gn:name":"Qel\u012bmp",
    "gn:population":0,
    "gn:timezone":"Asia/Tehran",
    "iso:country":"IR",
    "name:fas_x_preferred":[
        "Qel\u012bmp"
    ],
    "wof:name":"Qelimp",
    "wof:placetype":"locality"
},
  "geometry": {"coordinates":[48.25,38.11667],"type":"Point"}
}