{
  "type": "Feature",
  "properties": {
    "gn:admin1_code":"42",
    "gn:asciiname":"Gol Aqa",
    "gn:country_code":"IR",
    "gn:dem":1804,
    "gn:feature_class":"P",
    "gn:feature_code":"PPL",
    "gn:name":"Gol \u0100q\u0101",
    "gn:population":0,
    "gn:timezone":"Asia/Tehran",
    "iso:country":"IR",
    "name:fas_x_preferred":[
        "Gol \u0100q\u0101"
    ],
    "wof:name":"Gol Aqa",
    "wof:placetype":"locality"
},
  "geometry": {"coordinates":[58.63083,34.12222],"type":"Point"}
}