{
  "type": "Feature",
  "properties": {
    "gn:admin1_code":"15",
    "gn:asciiname":"Kal Parah",
    "gn:country_code":"IR",
    "gn:dem":600,
    "gn:feature_class":"P",
    "gn:feature_code":"PPL",
    "gn:name":"Kal P\u0101r\u0101h",
    "gn:population":0,
    "gn:timezone":"Asia/Tehran",
    "iso:country":"IR",
    "name:fas_x_preferred":[
        "N\u016bnangen\u0101n"
    ],
    "name:fas_x_variant":[
        "N\u016bnangan\u016bn",
        "\u0646\u0648\u0646\u0646\u06af\u0646\u0648\u0646",
        "\u06a9\u0644 \u067e\u0627\u0631\u0627\u0647"
    ],
    "name:und_x_variant":[
        "Kal P\u0101r\u0101h"
    ],
    "wof:name":"Kal Parah",
    "wof:placetype":"locality"
},
  "geometry": {"coordinates":[49.90986,31.99097],"type":"Point"}
}