{
  "type": "Feature",
  "properties": {
    "gn:admin1_code":"23",
    "gn:asciiname":"Jorjor",
    "gn:country_code":"IR",
    "gn:dem":977,
    "gn:feature_class":"P",
    "gn:feature_code":"PPL",
    "gn:name":"Jorjor",
    "gn:population":0,
    "gn:timezone":"Asia/Tehran",
    "iso:country":"IR",
    "name:fas_x_preferred":[
        "\u062c\u0631\u062c\u0631"
    ],
    "name:fas_x_variant":[
        "\u062c\u064f\u0631\u062c\u064f\u0631 \u062f\u064e\u0631\u0633\u0648\u0646"
    ],
    "name:und_x_variant":[
        "Jorjor Dars\u016bn",
        "Jorjor"
    ],
    "wof:name":"Jorjor",
    "wof:placetype":"locality"
},
  "geometry": {"coordinates":[48.89107,33.21637],"type":"Point"}
}