{
  "type": "Feature",
  "properties": {
    "gn:admin1_code":"8",
    "gn:asciiname":"Dastevil",
    "gn:country_code":"IR",
    "gn:dem":283,
    "gn:feature_class":"P",
    "gn:feature_code":"PPL",
    "gn:name":"Dastev\u012bl",
    "gn:population":0,
    "gn:timezone":"Asia/Tehran",
    "iso:country":"IR",
    "name:fas_x_preferred":[
        "\u062f\u0633\u062a\u0648\u06cc\u0644"
    ],
    "name:und_x_variant":[
        "Dasht-e Veyl",
        "Dastev\u012bl"
    ],
    "wof:name":"Dastevil",
    "wof:placetype":"locality"
},
  "geometry": {"coordinates":[49.59731,36.84591],"type":"Point"}
}