{
  "type": "Feature",
  "properties": {
    "gn:admin1_code":"23",
    "gn:asciiname":"Sirak",
    "gn:country_code":"IR",
    "gn:dem":2003,
    "gn:feature_class":"P",
    "gn:feature_code":"PPL",
    "gn:name":"S\u012brak",
    "gn:population":0,
    "gn:timezone":"Asia/Tehran",
    "iso:country":"IR",
    "name:ceb_x_preferred":[
        "Sirak"
    ],
    "name:fas_x_preferred":[
        "\u0633\u064a\u0631\u06a9"
    ],
    "name:fas_x_variant":[
        "\u0633\u064a\u0631\u0643\u0650\u0647",
        "S\u012brak"
    ],
    "name:fin_x_preferred":[
        "Sirak"
    ],
    "name:fra_x_preferred":[
        "Sirak"
    ],
    "name:swe_x_preferred":[
        "Sirak"
    ],
    "name:und_x_variant":[
        "S\u012brkeh"
    ],
    "wof:name":"Sirak",
    "wof:placetype":"locality"
},
  "geometry": {"coordinates":[48.71371,33.43781],"type":"Point"}
}