{
  "type": "Feature",
  "properties": {
    "gn:admin1_code":"37.0",
    "gn:asciiname":"Owlang",
    "gn:country_code":"IR",
    "gn:dem":994,
    "gn:feature_class":"P",
    "gn:feature_code":"PPL",
    "gn:name":"Owlang",
    "gn:population":0,
    "gn:timezone":"Asia/Tehran",
    "iso:country":"IR",
    "name:fas_x_preferred":[
        "\u0627\u0648\u0644\u0646\u06af"
    ],
    "name:und_x_variant":[
        "\u0627\u0648\u0644\u0646\u06af",
        "Owlang"
    ],
    "wof:name":"Owlang",
    "wof:placetype":"locality"
},
  "geometry": {"coordinates":[55.62197,37.14909],"type":"Point"}
}