{
  "type": "Feature",
  "properties": {
    "gn:admin1_code":"5",
    "gn:asciiname":"Biareh",
    "gn:country_code":"IR",
    "gn:dem":2048,
    "gn:feature_class":"P",
    "gn:feature_code":"PPL",
    "gn:name":"B\u012b\u0101reh",
    "gn:population":0,
    "gn:timezone":"Asia/Tehran",
    "iso:country":"IR",
    "name:ara_x_preferred":[
        "\u0628\u064a\u0627\u0631\u0629"
    ],
    "name:ceb_x_preferred":[
        "B\u012b\u0101reh"
    ],
    "name:fas_x_preferred":[
        "\u0628\u064a\u0651\u0627\u0631\u0650\u0647"
    ],
    "name:fas_x_variant":[
        "\u0628\u0650\u064a\u0627\u0631\u0650",
        "\u0628\u0650\u064a\u0627\u0631\u0650\u0647",
        "B\u012b\u0101reh",
        "\u0628\u064a\u0627\u0631\u0647",
        "\u0628\u06cc\u0627\u0631\u0647"
    ],
    "name:swe_x_preferred":[
        "B\u012b\u0101reh"
    ],
    "name:und_x_variant":[
        "B\u012by\u0101reh",
        "Bey\u0101re",
        "Bey\u0101reh",
        "\u0628\u064a\u0627\u0631\u0647"
    ],
    "wof:name":"Biareh",
    "wof:placetype":"locality"
},
  "geometry": {"coordinates":[51.45218,30.83514000000001],"type":"Point"}
}