{
  "type": "Feature",
  "properties": {
    "gn:admin1_code":"4.0",
    "gn:asciiname":"Chah-e Hajji Dar Bakhsh",
    "gn:cc2":"IR",
    "gn:country_code":"IR",
    "gn:dem":1161,
    "gn:feature_class":"P",
    "gn:feature_code":"PPL",
    "gn:name":"Ch\u0101h-e \u1e28\u0101jj\u012b D\u0101r Bakhsh",
    "gn:population":0,
    "gn:timezone":"Asia/Tehran",
    "iso:country":"IR",
    "name:fas_x_preferred":[
        "Ch\u0101h-e \u1e28\u0101jj\u012b D\u0101r Bakhsh"
    ],
    "name:und_x_variant":[
        "Ch\u0101h-e A\u1e29mad\u0101b\u0101d"
    ],
    "wof:name":"Chah-e Hajji Dar Bakhsh",
    "wof:placetype":"locality"
},
  "geometry": {"coordinates":[61.88333000000001,27.33333],"type":"Point"}
}