{
  "type": "Feature",
  "properties": {
    "gn:admin1_code":"29",
    "gn:asciiname":"Rezvan",
    "gn:country_code":"IR",
    "gn:dem":2400,
    "gn:feature_class":"P",
    "gn:feature_code":"PPL",
    "gn:name":"Re\u1e95v\u0101n",
    "gn:population":0,
    "gn:timezone":"Asia/Tehran",
    "iso:country":"IR",
    "name:fas_x_preferred":[
        "\u0631\u0636\u0648\u0627\u0646"
    ],
    "name:fas_x_variant":[
        "Re\u1e95v\u0101n"
    ],
    "wof:name":"Rezvan",
    "wof:placetype":"locality"
},
  "geometry": {"coordinates":[56.2004,29.6923],"type":"Point"}
}