{
  "type": "Feature",
  "properties": {
    "gn:admin1_code":"16.0",
    "gn:asciiname":"Kandulan",
    "gn:country_code":"IR",
    "gn:dem":1660,
    "gn:feature_class":"P",
    "gn:feature_code":"PPL",
    "gn:name":"Kand\u016bl\u0101n",
    "gn:population":0,
    "gn:timezone":"Asia/Tehran",
    "iso:country":"IR",
    "name:ara_x_preferred":[
        "\u0643\u0646\u0648\u0644\u0627\u0646"
    ],
    "name:ceb_x_preferred":[
        "Kand\u016bl\u0101n"
    ],
    "name:ckb_x_preferred":[
        "\u06a9\u06d5\u0646\u06c6\u06b5\u0627\u0646"
    ],
    "name:fas_x_preferred":[
        "\u06a9\u0646\u062f\u0648\u0644\u0627\u0646"
    ],
    "name:fas_x_variant":[
        "Kand\u016bl\u0101n"
    ],
    "name:kur_x_preferred":[
        "Kenollan"
    ],
    "name:swe_x_preferred":[
        "Kand\u016bl\u0101n"
    ],
    "wof:name":"Kandulan",
    "wof:placetype":"locality"
},
  "geometry": {"coordinates":[46.4362,36.1118],"type":"Point"}
}