{
  "type": "Feature",
  "properties": {
    "gn:admin1_code":"29",
    "gn:asciiname":"Meymand",
    "gn:country_code":"IR",
    "gn:dem":2209,
    "gn:feature_class":"P",
    "gn:feature_code":"PPL",
    "gn:name":"Meymand",
    "gn:population":0,
    "gn:timezone":"Asia/Tehran",
    "iso:country":"IR",
    "name:ara_x_preferred":[
        "\u0645\u064a\u0645\u0646\u062f"
    ],
    "name:aze_x_preferred":[
        "M\u0259ym\u0259nd"
    ],
    "name:bul_x_preferred":[
        "\u041c\u0435\u0439\u043c\u0430\u043d\u0434"
    ],
    "name:deu_x_preferred":[
        "Maymand"
    ],
    "name:eus_x_preferred":[
        "Maimand"
    ],
    "name:fas_x_preferred":[
        "\u0645\u06cc\u0645\u0646\u062f"
    ],
    "name:fin_x_preferred":[
        "Meymand"
    ],
    "name:fra_x_preferred":[
        "Maymand"
    ],
    "name:hrv_x_preferred":[
        "Majmand"
    ],
    "name:hun_x_preferred":[
        "Mejmand"
    ],
    "name:ita_x_preferred":[
        "Maymand"
    ],
    "name:jpn_x_preferred":[
        "\u30e1\u30a4\u30de\u30f3\u30c9"
    ],
    "name:kat_x_preferred":[
        "\u10db\u10d4\u10d8\u10db\u10d0\u10dc\u10d3\u10d8"
    ],
    "name:kir_x_preferred":[
        "\u041c\u0435\u0439\u043c\u0430\u043d\u0434 \u043a\u044b\u0448\u0442\u0430\u0433\u044b"
    ],
    "name:lit_x_preferred":[
        "Meimandas"
    ],
    "name:por_x_preferred":[
        "Maymand"
    ],
    "name:rus_x_preferred":[
        "\u041c\u0435\u0439\u043c\u0430\u043d\u0434"
    ],
    "name:swe_x_preferred":[
        "Meymand"
    ],
    "name:tur_x_preferred":[
        "Meymand"
    ],
    "name:vie_x_preferred":[
        "Meymand"
    ],
    "wof:name":"Meymand",
    "wof:placetype":"locality"
},
  "geometry": {"coordinates":[55.3756,30.2295],"type":"Point"}
}