{
  "type": "Feature",
  "properties": {
    "gn:admin1_code":"29",
    "gn:asciiname":"Meymand",
    "gn:country_code":"IR",
    "gn:dem":2209,
    "gn:feature_class":"P",
    "gn:feature_code":"PPL",
    "gn:name":"Meymand",
    "gn:population":0,
    "gn:timezone":"Asia/Tehran",
    "iso:country":"IR",
    "name:fas_x_preferred":[
        "\u0645\u06cc\u0645\u0646\u062f"
    ],
    "name:und_x_variant":[
        "Maimand",
        "Meymand"
    ],
    "wof:name":"Meymand",
    "wof:placetype":"locality"
},
  "geometry": {"coordinates":[55.3756,30.2295],"type":"Point"}
}