{
  "type": "Feature",
  "properties": {
    "gn:admin1_code":"4.0",
    "gn:asciiname":"Sabz Gaz-e Bala",
    "gn:country_code":"IR",
    "gn:dem":1306,
    "gn:feature_class":"P",
    "gn:feature_code":"PPL",
    "gn:name":"Sabz Gaz-e B\u0101l\u0101",
    "gn:population":0,
    "gn:timezone":"Asia/Tehran",
    "iso:country":"IR",
    "name:fas_x_preferred":[
        "\u0633\u0628\u0632 \u06af\u0632 \u0628\u0627\u0644\u0627"
    ],
    "name:fas_x_variant":[
        "Sabz Gaz-e M\u012b\u0101n\u012b",
        "\u0633\u0628\u0632 \u06af\u0632 \u0648\u0633\u0637\u06cc"
    ],
    "name:und_x_variant":[
        "Sabz Gaz-e B\u0101l\u0101",
        "Sabz Gaz-e Vost\u00e1",
        "Sabz Gaz"
    ],
    "wof:name":"Sabz Gaz-e Bala",
    "wof:placetype":"locality"
},
  "geometry": {"coordinates":[61.48322,28.35307],"type":"Point"}
}