{
  "type": "Feature",
  "properties": {
    "gn:admin1_code":"33",
    "gn:asciiname":"Khadzhi-Makhmudlu",
    "gn:country_code":"IR",
    "gn:dem":1567,
    "gn:feature_class":"P",
    "gn:feature_code":"PPL",
    "gn:name":"Khadzhi-Makhmudlu",
    "gn:population":0,
    "gn:timezone":"Asia/Tehran",
    "iso:country":"IR",
    "name:fas_x_preferred":[
        "\u062d\u0627\u062c\u06cc \u0645\u062d\u0645\u0648\u062f\u0644\u0648"
    ],
    "name:fas_x_variant":[
        "\u1e28\u0101jj\u012b Ma\u1e29m\u016bdl\u016b",
        "\u062d\u0627\u062c\u06cc\u200c\u0645\u062d\u0645\u0648\u062f\u0644\u0648"
    ],
    "name:msa_x_preferred":[
        "Hajji Mahmudlu"
    ],
    "name:und_x_variant":[
        "H\u0101ji Mahmudlu"
    ],
    "wof:name":"Khadzhi-Makhmudlu",
    "wof:placetype":"locality"
},
  "geometry": {"coordinates":[48.07042,37.20222],"type":"Point"}
}