{
  "type": "Feature",
  "properties": {
    "gn:admin1_code":"8.0",
    "gn:asciiname":"Divrash",
    "gn:country_code":"IR",
    "gn:dem":291,
    "gn:feature_class":"P",
    "gn:feature_code":"PPL",
    "gn:name":"D\u012bvrash",
    "gn:population":0,
    "gn:timezone":"Asia/Tehran",
    "iso:country":"IR",
    "name:ceb_x_preferred":[
        "D\u012bvrash"
    ],
    "name:fas_x_preferred":[
        "D\u012bvrash"
    ],
    "name:fas_x_variant":[
        "\u062f\u06cc\u0648\u0631\u0634"
    ],
    "name:msa_x_preferred":[
        "Divrash"
    ],
    "name:swe_x_preferred":[
        "D\u012bvrash"
    ],
    "name:ukr_x_preferred":[
        "\u0414\u0456\u0432\u0440\u0430\u0448"
    ],
    "wof:name":"Divrash",
    "wof:placetype":"locality"
},
  "geometry": {"coordinates":[49.57862,36.89896],"type":"Point"}
}