{
  "type": "Feature",
  "properties": {
    "gn:admin1_code":"37",
    "gn:asciiname":"Duz Olum Fadavi-ye Shomali",
    "gn:country_code":"IR",
    "gn:dem":19,
    "gn:feature_class":"P",
    "gn:feature_code":"PPL",
    "gn:name":"D\u016bz Ol\u016bm Fadav\u012b-ye Shom\u0101l\u012b",
    "gn:population":0,
    "gn:timezone":"Asia/Tehran",
    "iso:country":"IR",
    "name:fas_x_preferred":[
        "\u0641\u062f\u0648\u06cc"
    ],
    "name:fas_x_variant":[
        "Fadav\u012b",
        "\u062f\u0648\u0632 \u0627\u0644\u0648\u0645 \u0641\u062f\u0648\u06cc \u0634\u0645\u0627\u0644\u06cc",
        "\u062f\u0648\u0632 \u0627\u0644\u0648\u0645"
    ],
    "name:und_x_variant":[
        "D\u016bz Ol\u016bm Fadav\u012b-ye Shom\u0101l\u012b",
        "D\u016bz Ol\u016bm",
        "D\u016bz Olowm"
    ],
    "wof:name":"Duz Olum Fadavi-ye Shomali",
    "wof:placetype":"locality"
},
  "geometry": {"coordinates":[54.83406,37.56954],"type":"Point"}
}