{
  "type": "Feature",
  "properties": {
    "gn:admin1_code":"35.0",
    "gn:asciiname":"Duneh Sar",
    "gn:country_code":"IR",
    "gn:dem":21,
    "gn:feature_class":"P",
    "gn:feature_code":"PPL",
    "gn:name":"D\u016bneh Sar",
    "gn:population":0,
    "gn:timezone":"Asia/Tehran",
    "iso:country":"IR",
    "name:fas_x_preferred":[
        "\u062f\u0648\u0646\u0647 \u0633\u0631"
    ],
    "name:fas_x_variant":[
        "D\u016bneh Sar"
    ],
    "name:und_x_variant":[
        "\u062f\u0648\u0646\u0650\u0647 \u0633\u064e\u0631"
    ],
    "wof:name":"Duneh Sar",
    "wof:placetype":"locality"
},
  "geometry": {"coordinates":[52.63306,36.45789],"type":"Point"}
}