{
  "type": "Feature",
  "properties": {
    "gn:admin1_code":"23",
    "gn:asciiname":"Ziveh",
    "gn:country_code":"IR",
    "gn:dem":1650,
    "gn:feature_class":"P",
    "gn:feature_code":"PPL",
    "gn:name":"Z\u012bveh",
    "gn:population":0,
    "gn:timezone":"Asia/Tehran",
    "iso:country":"IR",
    "name:fas_x_preferred":[
        "\u0632\u064a\u0648\u0647"
    ],
    "name:fas_x_variant":[
        "Z\u012bveh"
    ],
    "name:und_x_variant":[
        "Zeybeh",
        "Z\u012bweh",
        "Z\u012bbeh"
    ],
    "wof:name":"Ziveh",
    "wof:placetype":"locality"
},
  "geometry": {"coordinates":[48.84967,33.80799],"type":"Point"}
}