{
  "type": "Feature",
  "properties": {
    "gn:admin1_code":"7",
    "gn:asciiname":"Maleki",
    "gn:country_code":"IR",
    "gn:dem":923,
    "gn:feature_class":"P",
    "gn:feature_code":"PPL",
    "gn:name":"M\u0101lek\u012b",
    "gn:population":0,
    "gn:timezone":"Asia/Tehran",
    "iso:country":"IR",
    "name:fas_x_preferred":[
        "M\u0101lek\u012b"
    ],
    "wof:name":"Maleki",
    "wof:placetype":"locality"
},
  "geometry": {"coordinates":[51.59778,29.84056],"type":"Point"}
}