{
  "type": "Feature",
  "properties": {
    "gn:admin1_code":"41",
    "gn:asciiname":"Mazra`eh-ye Tajarg",
    "gn:country_code":"IR",
    "gn:dem":1874,
    "gn:feature_class":"P",
    "gn:feature_code":"PPL",
    "gn:name":"Mazra\u2018eh-ye Tajarg",
    "gn:population":0,
    "gn:timezone":"Asia/Tehran",
    "iso:country":"IR",
    "name:fas_x_preferred":[
        "\u062a\u062c\u0631\u06a9"
    ],
    "name:fas_x_variant":[
        "\u0645\u0632\u0631\u0639\u0647 \u062a\u062c\u0631\u06af",
        "\u062a\u062c\u0631\u06af"
    ],
    "name:und_x_variant":[
        "Tajarg",
        "Tajerg",
        "Tajark",
        "\u062a\u062c\u0631\u06a9",
        "Mazra\u2018eh-ye Tajarg"
    ],
    "wof:name":"Mazra`eh-ye Tajarg",
    "wof:placetype":"locality"
},
  "geometry": {"coordinates":[58.99001,33.67374],"type":"Point"}
}