{
  "type": "Feature",
  "properties": {
    "gn:admin1_code":"4.0",
    "gn:asciiname":"Shur Mitak",
    "gn:country_code":"IR",
    "gn:dem":743,
    "gn:feature_class":"P",
    "gn:feature_code":"PPL",
    "gn:name":"Sh\u016br M\u012btak",
    "gn:population":0,
    "gn:timezone":"Asia/Tehran",
    "iso:country":"IR",
    "name:fas_x_preferred":[
        "Sh\u016brm\u012btag"
    ],
    "name:fas_x_variant":[
        "Sh\u016br M\u012btak",
        "\u0634\u0648\u0631 \u0645\u06cc\u062a\u06a9"
    ],
    "name:und_x_variant":[
        "Sh\u016br\u012b M\u012btak",
        "Shormet\u0101"
    ],
    "wof:name":"Shur Mitak",
    "wof:placetype":"locality"
},
  "geometry": {"coordinates":[61.19574,26.48564],"type":"Point"}
}