{
  "type": "Feature",
  "properties": {
    "gn:admin1_code":"5.0",
    "gn:asciiname":"Pasrish",
    "gn:country_code":"IR",
    "gn:dem":1561,
    "gn:feature_class":"P",
    "gn:feature_code":"PPL",
    "gn:name":"Pasr\u012bsh",
    "gn:population":0,
    "gn:timezone":"Asia/Tehran",
    "iso:country":"IR",
    "name:fas_x_preferred":[
        "\u067e\u064e\u0633\u0631\u064a\u0634"
    ],
    "name:fas_x_variant":[
        "Pasr\u012bsh"
    ],
    "wof:name":"Pasrish",
    "wof:placetype":"locality"
},
  "geometry": {"coordinates":[50.47667,31.23667],"type":"Point"}
}