{
  "type": "Feature",
  "properties": {
    "gn:admin1_code":"43",
    "gn:asciiname":"Now Deh Bam",
    "gn:country_code":"IR",
    "gn:dem":1715,
    "gn:feature_class":"P",
    "gn:feature_code":"PPL",
    "gn:name":"Now Deh B\u0101m",
    "gn:population":0,
    "gn:timezone":"Asia/Tehran",
    "iso:country":"IR",
    "name:ara_x_preferred":[
        "\u0646\u0648\u062f\u0629 \u0628\u0627\u0645"
    ],
    "name:ceb_x_preferred":[
        "Now Deh"
    ],
    "name:fas_x_preferred":[
        "Now Deh B\u0101m"
    ],
    "name:fas_x_variant":[
        "\u0646\u0648 \u062f\u0647",
        "\u0646\u0648 \u062f\u0647 \u0628\u0627\u0645",
        "\u0646\u0648\u062f\u0647 \u0628\u0627\u0645"
    ],
    "name:und_x_variant":[
        "Now Deh",
        "\u0646\u0648 \u062f\u0647"
    ],
    "wof:name":"Now Deh Bam",
    "wof:placetype":"locality"
},
  "geometry": {"coordinates":[57.9383,36.9584],"type":"Point"}
}