{
  "type": "Feature",
  "properties": {
    "gn:admin1_code":"23",
    "gn:asciiname":"Qanatabad",
    "gn:country_code":"IR",
    "gn:dem":1475,
    "gn:feature_class":"P",
    "gn:feature_code":"PPL",
    "gn:name":"Qan\u0101t\u0101b\u0101d",
    "gn:population":0,
    "gn:timezone":"Asia/Tehran",
    "iso:country":"IR",
    "name:fas_x_preferred":[
        "\u0642\u064e\u0646\u0627\u062a \u0622\u0628\u0627\u062f"
    ],
    "name:fas_x_variant":[
        "Qan\u0101t\u0101b\u0101d"
    ],
    "wof:name":"Qanatabad",
    "wof:placetype":"locality"
},
  "geometry": {"coordinates":[48.51667,33.45],"type":"Point"}
}