{
  "type": "Feature",
  "properties": {
    "gn:admin1_code":"42",
    "gn:asciiname":"Golestan",
    "gn:country_code":"IR",
    "gn:dem":1238,
    "gn:feature_class":"P",
    "gn:feature_code":"PPL",
    "gn:name":"Golest\u0101n",
    "gn:population":0,
    "gn:timezone":"Asia/Tehran",
    "iso:country":"IR",
    "name:fas_x_preferred":[
        "\u06af\u0644\u0633\u062a\u0627\u0646"
    ],
    "name:fas_x_variant":[
        "Golest\u0101n"
    ],
    "name:rus_x_preferred":[
        "\u0413\u043e\u043b\u0435\u0441\u0442\u0430\u043d"
    ],
    "wof:name":"Golestan",
    "wof:placetype":"locality"
},
  "geometry": {"coordinates":[59.407,36.3191],"type":"Point"}
}