{
  "type": "Feature",
  "properties": {
    "gn:admin1_code":"34",
    "gn:asciiname":"`Abbasabad",
    "gn:country_code":"IR",
    "gn:dem":1772,
    "gn:feature_class":"P",
    "gn:feature_code":"PPL",
    "gn:name":"\u2018Abb\u0101s\u0101b\u0101d",
    "gn:population":0,
    "gn:timezone":"Asia/Tehran",
    "iso:country":"IR",
    "name:fas_x_preferred":[
        "\u0642\u0644\u0639\u0647 \u0639\u0628\u0651\u0627\u0633 \u0622\u0628\u0627\u062f"
    ],
    "name:fas_x_variant":[
        "\u0639\u0628\u0651\u0627\u0633 \u0622\u0628\u0627\u062f",
        "\u2018Abb\u0101s\u0101b\u0101d"
    ],
    "name:und_x_variant":[
        "Qal\u2018eh \u2018Abb\u0101s\u0101b\u0101d"
    ],
    "wof:name":"`Abbasabad",
    "wof:placetype":"locality"
},
  "geometry": {"coordinates":[49.2401,34.287],"type":"Point"}
}