{
  "type": "Feature",
  "properties": {
    "gn:admin1_code":"28",
    "gn:asciiname":"Darakehabad",
    "gn:country_code":"IR",
    "gn:dem":2284,
    "gn:feature_class":"P",
    "gn:feature_code":"PPL",
    "gn:name":"Darakeh\u0101b\u0101d",
    "gn:population":0,
    "gn:timezone":"Asia/Tehran",
    "iso:country":"IR",
    "name:fas_x_preferred":[
        "Darakeh\u0101b\u0101d"
    ],
    "name:fas_x_variant":[
        "\u062f\u0631\u06a9\u0647 \u0622\u0628\u0627\u062f"
    ],
    "name:und_x_variant":[
        "Darak\u0101b\u0101d",
        "\u062f\u0631\u06a9\u0647 \u0622\u0628\u0627\u062f"
    ],
    "wof:name":"Darakehabad",
    "wof:placetype":"locality"
},
  "geometry": {"coordinates":[50.37692,32.6906],"type":"Point"}
}