{
  "type": "Feature",
  "properties": {
    "gn:admin1_code":"8",
    "gn:asciiname":"Darband",
    "gn:country_code":"IR",
    "gn:dem":-5,
    "gn:feature_class":"P",
    "gn:feature_code":"PPL",
    "gn:name":"Darband",
    "gn:population":0,
    "gn:timezone":"Asia/Tehran",
    "iso:country":"IR",
    "name:fas_x_preferred":[
        "\u062f\u0631\u0628\u0646\u062f"
    ],
    "wof:name":"Darband",
    "wof:placetype":"locality"
},
  "geometry": {"coordinates":[48.8413,38.3633],"type":"Point"}
}