{
  "type": "Feature",
  "properties": {
    "gn:admin1_code":"33.0",
    "gn:asciiname":"Boqriq",
    "gn:country_code":"IR",
    "gn:dem":1890,
    "gn:feature_class":"P",
    "gn:feature_code":"PPL",
    "gn:name":"Boqr\u012bq",
    "gn:population":0,
    "gn:timezone":"Asia/Tehran",
    "iso:country":"IR",
    "name:fas_x_preferred":[
        "\u0628\u0642\u0631\u06cc\u0642"
    ],
    "name:fas_x_variant":[
        "Boqr\u012bq"
    ],
    "wof:name":"Boqriq",
    "wof:placetype":"locality"
},
  "geometry": {"coordinates":[47.2796,37.8175],"type":"Point"}
}