{
  "type": "Feature",
  "properties": {
    "gn:admin1_code":"7",
    "gn:asciiname":"Ghuri",
    "gn:country_code":"IR",
    "gn:dem":1928,
    "gn:feature_class":"P",
    "gn:feature_code":"PPL",
    "gn:name":"Gh\u016br\u012b",
    "gn:population":0,
    "gn:timezone":"Asia/Tehran",
    "iso:country":"IR",
    "name:fas_x_preferred":[
        "Gh\u016br\u012b"
    ],
    "name:fas_x_variant":[
        "\u063a\u0648\u0631\u06cc"
    ],
    "name:msa_x_preferred":[
        "Ghuri"
    ],
    "name:und_x_variant":[
        "Q\u016br\u012b",
        "Ghowr\u012b"
    ],
    "wof:name":"Ghuri",
    "wof:placetype":"locality"
},
  "geometry": {"coordinates":[54.46941,29.51006],"type":"Point"}
}