{
  "type": "Feature",
  "properties": {
    "gn:admin1_code":"13",
    "gn:asciiname":"Marzelan",
    "gn:country_code":"IR",
    "gn:dem":1367,
    "gn:feature_class":"P",
    "gn:feature_code":"PPL",
    "gn:name":"Marzel\u0101n",
    "gn:population":0,
    "gn:timezone":"Asia/Tehran",
    "iso:country":"IR",
    "name:ceb_x_preferred":[
        "Marzel\u0101n"
    ],
    "name:fas_x_preferred":[
        "\u0645\u0631\u0632\u0644\u0627\u0646"
    ],
    "name:fas_x_variant":[
        "Marzel\u0101n-e Mo\u1e29ammad Mor\u0101d",
        "Marzel\u0101n",
        "\u0645\u0631\u0632\u0644\u0627\u0646\u200c\u0645\u062d\u0645\u062f\u0645\u0631\u0627\u062f"
    ],
    "name:swe_x_preferred":[
        "Marzel\u0101n"
    ],
    "wof:name":"Marzelan",
    "wof:placetype":"locality"
},
  "geometry": {"coordinates":[46.1292,34.6502],"type":"Point"}
}