{
  "type": "Feature",
  "properties": {
    "gn:admin1_code":"8.0",
    "gn:asciiname":"Simbar Khaleh-ye Pa'in",
    "gn:country_code":"IR",
    "gn:dem":-22,
    "gn:feature_class":"P",
    "gn:feature_code":"PPL",
    "gn:name":"S\u012bmbar Kh\u0101leh-ye P\u0101\u2019\u012bn",
    "gn:population":0,
    "gn:timezone":"Asia/Tehran",
    "iso:country":"IR",
    "name:fas_x_preferred":[
        "\u0633\u06cc\u0645\u0628\u0631 \u062e\u0627\u0644\u0647 \u067e\u0627\u06cc\u06cc\u0646"
    ],
    "name:und_x_variant":[
        "S\u012bmbar Kh\u0101leh-ye P\u0101\u2019\u012bn"
    ],
    "wof:name":"Simbar Khaleh-ye Pa'in",
    "wof:placetype":"locality"
},
  "geometry": {"coordinates":[49.07664000000001,37.65312],"type":"Point"}
}