{
  "type": "Feature",
  "properties": {
    "gn:admin1_code":"4.0",
    "gn:asciiname":"Radu",
    "gn:country_code":"IR",
    "gn:dem":42,
    "gn:feature_class":"P",
    "gn:feature_code":"PPL",
    "gn:name":"R\u0101d\u016b",
    "gn:population":0,
    "gn:timezone":"Asia/Tehran",
    "iso:country":"IR",
    "name:deu_x_preferred":[
        "Radu"
    ],
    "name:fas_x_preferred":[
        "R\u0101d\u016b"
    ],
    "name:heb_x_preferred":[
        "\u05e8\u05d0\u05d3\u05d5"
    ],
    "name:ita_x_preferred":[
        "Radu"
    ],
    "name:jpn_x_preferred":[
        "\u30e9\u30c9\u30a5"
    ],
    "name:ron_x_preferred":[
        "Radu"
    ],
    "name:rus_x_preferred":[
        "\u0420\u0430\u0434\u0443"
    ],
    "name:ukr_x_preferred":[
        "\u0420\u0430\u0434\u0443"
    ],
    "wof:name":"Radu",
    "wof:placetype":"locality"
},
  "geometry": {"coordinates":[60.9325,25.61861],"type":"Point"}
}