{
  "type": "Feature",
  "properties": {
    "gn:admin1_code":"13",
    "gn:asciiname":"Nim Dangi",
    "gn:country_code":"IR",
    "gn:dem":1254,
    "gn:feature_class":"P",
    "gn:feature_code":"PPL",
    "gn:name":"N\u012bm D\u0101ng\u012b",
    "gn:population":0,
    "gn:timezone":"Asia/Tehran",
    "iso:country":"IR",
    "name:fas_x_preferred":[
        "\u0646\u06cc\u0645 \u062f\u0627\u0646\u06af\u06cc"
    ],
    "name:fas_x_variant":[
        "N\u012bmd\u0101ng\u012b",
        "N\u012bm D\u0101ng\u012b",
        "\u0646\u06cc\u0645\u062f\u0627\u0646\u06af\u06cc"
    ],
    "wof:name":"Nim Dangi",
    "wof:placetype":"locality"
},
  "geometry": {"coordinates":[47.3279,34.1853],"type":"Point"}
}