{
  "type": "Feature",
  "properties": {
    "gn:admin1_code":"15",
    "gn:asciiname":"Zanat",
    "gn:country_code":"IR",
    "gn:dem":18,
    "gn:feature_class":"P",
    "gn:feature_code":"PPL",
    "gn:name":"Zan\u0101\u0163",
    "gn:population":0,
    "gn:timezone":"Asia/Tehran",
    "iso:country":"IR",
    "name:fas_x_preferred":[
        "\u0632\u0646\u0627\u062a"
    ],
    "name:fas_x_variant":[
        "Zan\u0101t",
        "\u0632\u0646\u0627\u0637"
    ],
    "name:und_x_variant":[
        "Bel\u0101d-e R\u0101\u1e95\u012b",
        "Bel\u0101darz\u012b",
        "Bel\u0101derz\u012b",
        "Zan\u0101\u0163"
    ],
    "wof:name":"Zanat",
    "wof:placetype":"locality"
},
  "geometry": {"coordinates":[49.33328,30.80196],"type":"Point"}
}