{
  "type": "Feature",
  "properties": {
    "gn:admin1_code":"42",
    "gn:asciiname":"Khij",
    "gn:country_code":"IR",
    "gn:dem":1332,
    "gn:feature_class":"P",
    "gn:feature_code":"PPL",
    "gn:name":"Kh\u012bj",
    "gn:population":0,
    "gn:timezone":"Asia/Tehran",
    "iso:country":"IR",
    "name:fas_x_preferred":[
        "\u062e\u06cc\u062c"
    ],
    "name:fas_x_variant":[
        "Kh\u012bj"
    ],
    "name:und_x_variant":[
        "Khej"
    ],
    "wof:name":"Khij",
    "wof:placetype":"locality"
},
  "geometry": {"coordinates":[59.10666,36.55535],"type":"Point"}
}