{
  "type": "Feature",
  "properties": {
    "gn:admin1_code":"8.0",
    "gn:asciiname":"Siah `Alam Mahalleh",
    "gn:country_code":"IR",
    "gn:dem":-10,
    "gn:feature_class":"P",
    "gn:feature_code":"PPL",
    "gn:name":"S\u012b\u0101h \u2018Alam Ma\u1e29alleh",
    "gn:population":0,
    "gn:timezone":"Asia/Tehran",
    "iso:country":"IR",
    "name:fas_x_preferred":[
        "\u0633\u06cc\u0627\u0647 \u0639\u0644\u0645 \u0645\u062d\u0644\u0647"
    ],
    "name:und_x_variant":[
        "S\u012b\u0101h \u2018Alam Ma\u1e29alleh"
    ],
    "wof:name":"Siah `Alam Mahalleh",
    "wof:placetype":"locality"
},
  "geometry": {"coordinates":[49.01438,37.69198],"type":"Point"}
}