{
  "type": "Feature",
  "properties": {
    "gn:admin1_code":"15",
    "gn:asciiname":"Shah Nabi",
    "gn:country_code":"IR",
    "gn:dem":32,
    "gn:feature_class":"P",
    "gn:feature_code":"PPL",
    "gn:name":"Sh\u0101h Nab\u012b",
    "gn:population":0,
    "gn:timezone":"Asia/Tehran",
    "iso:country":"IR",
    "name:fas_x_preferred":[
        "Sh\u0101h Nab\u012b-ye \u2018Oly\u0101"
    ],
    "name:fas_x_variant":[
        "\u0634\u0627\u0647 \u0646\u0628\u06cc",
        "\u0634\u0627\u0647 \u0646\u0628\u06cc \u0639\u0644\u06cc\u0627",
        "\u0634\u0627\u0647 \u0646\u0628\u06cc \u0628\u0627\u0644\u0627"
    ],
    "name:und_x_variant":[
        "Sh\u0101h Nab\u012b B\u0101l\u0101",
        "Sh\u0101h Nab\u012b",
        "Sh\u0101h Nab\u012b-ye B\u0101l\u0101"
    ],
    "wof:name":"Shah Nabi",
    "wof:placetype":"locality"
},
  "geometry": {"coordinates":[49.60826,30.86244000000001],"type":"Point"}
}