{
  "type": "Feature",
  "properties": {
    "gn:admin1_code":"42",
    "gn:asciiname":"Shah Rah",
    "gn:country_code":"IR",
    "gn:dem":1047,
    "gn:feature_class":"P",
    "gn:feature_code":"PPL",
    "gn:name":"Sh\u0101h R\u0101h",
    "gn:population":0,
    "gn:timezone":"Asia/Tehran",
    "iso:country":"IR",
    "name:fas_x_preferred":[
        "\u0634\u0627\u0647 \u0631\u0627\u0647"
    ],
    "name:fas_x_variant":[
        "Sh\u0101hr\u0101h",
        "Sh\u0101h R\u0101h"
    ],
    "wof:name":"Shah Rah",
    "wof:placetype":"locality"
},
  "geometry": {"coordinates":[59.4414,36.4884],"type":"Point"}
}