{
  "type": "Feature",
  "properties": {
    "gn:admin1_code":"8",
    "gn:asciiname":"Pa'in Pashaki",
    "gn:country_code":"IR",
    "gn:dem":23,
    "gn:feature_class":"P",
    "gn:feature_code":"PPL",
    "gn:name":"P\u0101\u2019\u012bn P\u0101sh\u0101k\u012b",
    "gn:population":0,
    "gn:timezone":"Asia/Tehran",
    "iso:country":"IR",
    "name:fas_x_preferred":[
        "P\u0101shk\u012b-ye P\u0101\u2019\u012bn"
    ],
    "name:fas_x_variant":[
        "P\u0101sh\u0101k\u012b P\u0101\u2019\u012bn Ma\u1e29alleh",
        "\u067e\u0627\u0634\u06a9\u06cc \u067e\u0627\u0626\u06cc\u0646",
        "\u067e\u0627\u06cc\u06cc\u0646 \u067e\u0627\u0634\u0627\u06a9\u06cc",
        "\u067e\u0627\u06cc\u06cc\u0646 \u0645\u062d\u0644\u0647 \u067e\u0627\u0634\u0627\u06a9\u06cc"
    ],
    "name:und_x_variant":[
        "P\u0101\u2019\u012bn Ma\u1e29alleh",
        "\u067e\u0627\u0634\u06a9\u06cc \u067e\u0627\u0626\u06cc\u0646",
        "P\u0101\u2019\u012bn P\u0101sh\u0101k\u012b",
        "P\u0101\u2019\u012bn Ma\u1e29alleh-ye P\u0101sh\u0101k\u012b"
    ],
    "wof:name":"Pa'in Pashaki",
    "wof:placetype":"locality"
},
  "geometry": {"coordinates":[49.79452,37.17307],"type":"Point"}
}