{
  "type": "Feature",
  "properties": {
    "gn:admin1_code":"15",
    "gn:asciiname":"Qal`eh-ye Sefid",
    "gn:country_code":"IR",
    "gn:dem":400,
    "gn:feature_class":"P",
    "gn:feature_code":"PPL",
    "gn:name":"Qal\u2018eh-ye Sef\u012bd",
    "gn:population":0,
    "gn:timezone":"Asia/Tehran",
    "iso:country":"IR",
    "name:fas_x_preferred":[
        "Qal\u2018eh Sef\u012bd"
    ],
    "name:fas_x_variant":[
        "Qal\u2018eh Sef\u012bd-e \u2018Oly\u0101",
        "\u0642\u0644\u0639\u0647 \u0633\u0641\u06cc\u062f",
        "\u0642\u0644\u0639\u0647 \u0633\u0641\u06cc\u062f \u0639\u0644\u06cc\u0627"
    ],
    "name:und_x_variant":[
        "Qal\u2018eh-ye Sef\u012bd",
        "Qal\u2018eh-ye Saf\u012bd",
        "Qal\u2018eh-ye Sef\u012bd-e \u2018Oly\u0101"
    ],
    "wof:name":"Qal`eh-ye Sefid",
    "wof:placetype":"locality"
},
  "geometry": {"coordinates":[49.58148,31.97216],"type":"Point"}
}