{
  "type": "Feature",
  "properties": {
    "gn:admin1_code":"5.0",
    "gn:asciiname":"Deh-e Eskandar",
    "gn:country_code":"IR",
    "gn:dem":1546,
    "gn:feature_class":"P",
    "gn:feature_code":"PPL",
    "gn:name":"Deh-e Eskandar",
    "gn:population":0,
    "gn:timezone":"Asia/Tehran",
    "iso:country":"IR",
    "name:fas_x_preferred":[
        "\u062f\u0647 \u0627\u0633\u06a9\u0646\u062f\u0631"
    ],
    "name:und_x_variant":[
        "\u062f\u0647 \u0627\u0633\u06a9\u0646\u062f\u0631"
    ],
    "wof:name":"Deh-e Eskandar",
    "wof:placetype":"locality"
},
  "geometry": {"coordinates":[50.78,30.886],"type":"Point"}
}