{
  "type": "Feature",
  "properties": {
    "gn:admin1_code":"29",
    "gn:asciiname":"Chahu",
    "gn:cc2":"IR",
    "gn:country_code":"IR",
    "gn:dem":1891,
    "gn:feature_class":"P",
    "gn:feature_code":"PPL",
    "gn:name":"Ch\u0101h\u016b",
    "gn:population":0,
    "gn:timezone":"Asia/Tehran",
    "iso:country":"IR",
    "name:ceb_x_preferred":[
        "Chahu"
    ],
    "name:fas_x_preferred":[
        "Ch\u0101h\u016b"
    ],
    "name:swe_x_preferred":[
        "Chahu"
    ],
    "name:und_x_variant":[
        "Chahoo\u2019eyeh Siloo\u2019eyeh"
    ],
    "wof:name":"Chahu",
    "wof:placetype":"locality"
},
  "geometry": {"coordinates":[56.35194,30.69611],"type":"Point"}
}