{
  "type": "Feature",
  "properties": {
    "gn:admin1_code":"32",
    "gn:asciiname":"Gol Tappeh",
    "gn:country_code":"IR",
    "gn:dem":1757,
    "gn:feature_class":"P",
    "gn:feature_code":"PPL",
    "gn:name":"Gol Tappeh",
    "gn:population":0,
    "gn:timezone":"Asia/Tehran",
    "iso:country":"IR",
    "name:ceb_x_preferred":[
        "Gol Tappeh"
    ],
    "name:fas_x_preferred":[
        "\u0100b-e Garm"
    ],
    "name:fas_x_variant":[
        "\u06af\u0644 \u062a\u067e\u0647"
    ],
    "name:swe_x_preferred":[
        "Gol Tappeh"
    ],
    "name:und_x_variant":[
        "Kal Tappeh"
    ],
    "wof:name":"Gol Tappeh",
    "wof:placetype":"locality"
},
  "geometry": {"coordinates":[48.4299,37.69072],"type":"Point"}
}