{
  "type": "Feature",
  "properties": {
    "gn:admin1_code":"7",
    "gn:asciiname":"Sardab",
    "gn:country_code":"IR",
    "gn:dem":1986,
    "gn:feature_class":"P",
    "gn:feature_code":"PPLF",
    "gn:name":"Sard\u0101b",
    "gn:population":0,
    "gn:timezone":"Asia/Tehran",
    "iso:country":"IR",
    "name:fas_x_preferred":[
        "\u0633\u0631\u062f\u0627\u0628"
    ],
    "name:fas_x_variant":[
        "Sard\u0101b"
    ],
    "name:msa_x_preferred":[
        "Sardab"
    ],
    "wof:name":"Sardab",
    "wof:placetype":"locality"
},
  "geometry": {"coordinates":[54.4484,29.459],"type":"Point"}
}