{
  "type": "Feature",
  "properties": {
    "gn:admin1_code":"7",
    "gn:asciiname":"Cheshmeh Shirin",
    "gn:country_code":"IR",
    "gn:dem":1585,
    "gn:feature_class":"P",
    "gn:feature_code":"PPL",
    "gn:name":"Cheshmeh Sh\u012br\u012bn",
    "gn:population":0,
    "gn:timezone":"Asia/Tehran",
    "iso:country":"IR",
    "name:fas_x_preferred":[
        "\u0686\u0634\u0645\u0647 \u0634\u06cc\u0631\u06cc\u0646"
    ],
    "name:fas_x_variant":[
        "Cheshmeh Sh\u012br\u012bn"
    ],
    "wof:name":"Cheshmeh Shirin",
    "wof:placetype":"locality"
},
  "geometry": {"coordinates":[53.1498,29.7382],"type":"Point"}
}