{
  "type": "Feature",
  "properties": {
    "gn:admin1_code":"11",
    "gn:asciiname":"Garu",
    "gn:country_code":"IR",
    "gn:dem":71,
    "gn:feature_class":"P",
    "gn:feature_code":"PPL",
    "gn:name":"Gar\u016b",
    "gn:population":0,
    "gn:timezone":"Asia/Tehran",
    "iso:country":"IR",
    "name:fas_x_preferred":[
        "\u06af\u0631\u0648"
    ],
    "name:fas_x_variant":[
        "Gar\u016b"
    ],
    "wof:name":"Garu",
    "wof:placetype":"locality"
},
  "geometry": {"coordinates":[57.27746,26.84607],"type":"Point"}
}