{
  "type": "Feature",
  "properties": {
    "gn:admin1_code":"15",
    "gn:asciiname":"Mamatin-e `Olya",
    "gn:country_code":"IR",
    "gn:dem":355,
    "gn:feature_class":"P",
    "gn:feature_code":"PPL",
    "gn:name":"M\u0101m\u0101t\u012bn-e \u2018Oly\u0101",
    "gn:population":0,
    "gn:timezone":"Asia/Tehran",
    "iso:country":"IR",
    "name:fas_x_preferred":[
        "M\u0101m\u0101t\u012bn-e B\u0101l\u0101"
    ],
    "name:fas_x_variant":[
        "M\u0101m\u0101t\u012bn-e \u2018Oly\u0101",
        "\u0645\u0627\u0645\u0627\u062a\u06cc\u0646 \u0639\u0644\u06cc\u0627"
    ],
    "name:und_x_variant":[
        "M\u0101m\u0101tayn-e B\u0101l\u0101",
        "M\u0101m\u0101tin"
    ],
    "wof:name":"Mamatin-e `Olya",
    "wof:placetype":"locality"
},
  "geometry": {"coordinates":[49.76697,31.30795],"type":"Point"}
}