{
  "type": "Feature",
  "properties": {
    "gn:admin1_code":"16.0",
    "gn:asciiname":"Tazehabad-e Doktor Vase`",
    "gn:country_code":"IR",
    "gn:dem":2082,
    "gn:feature_class":"P",
    "gn:feature_code":"PPL",
    "gn:name":"T\u0101zeh\u0101b\u0101d-e Doktor V\u0101se\u2018",
    "gn:population":0,
    "gn:timezone":"Asia/Tehran",
    "iso:country":"IR",
    "name:fas_x_preferred":[
        "\u062a\u0627\u0632\u0647 \u0622\u0628\u0627\u062f"
    ],
    "name:fas_x_variant":[
        "T\u0101zeh\u0101b\u0101d-e Doktor V\u0101se\u2018",
        "T\u0101zeh\u0101b\u0101d",
        "\u062a\u0627\u0632\u0647 \u0622\u0628\u0627\u062f \u062f\u06a9\u062a\u0631 \u0648\u0627\u0633\u0639"
    ],
    "wof:name":"Tazehabad-e Doktor Vase`",
    "wof:placetype":"locality"
},
  "geometry": {"coordinates":[47.1069,35.46181],"type":"Point"}
}