{
  "type": "Feature",
  "properties": {
    "gn:admin1_code":"7",
    "gn:asciiname":"Jabal-e Anaruyeh",
    "gn:country_code":"IR",
    "gn:dem":1622,
    "gn:feature_class":"P",
    "gn:feature_code":"PPL",
    "gn:name":"Jabal-e An\u0101r\u016byeh",
    "gn:population":0,
    "gn:timezone":"Asia/Tehran",
    "iso:country":"IR",
    "name:fas_x_preferred":[
        "\u062c\u0628\u0644 \u0627\u0646\u0627\u0631\u0648\u06cc\u0647"
    ],
    "name:fas_x_variant":[
        "Jabal-e An\u0101r\u016byeh"
    ],
    "wof:name":"Jabal-e Anaruyeh",
    "wof:placetype":"locality"
},
  "geometry": {"coordinates":[52.7126,28.7453],"type":"Point"}
}