{
  "type": "Feature",
  "properties": {
    "gn:admin1_code":"29",
    "gn:asciiname":"Kargah",
    "gn:country_code":"IR",
    "gn:dem":1558,
    "gn:feature_class":"P",
    "gn:feature_code":"PPL",
    "gn:name":"K\u0101rg\u0101h",
    "gn:population":0,
    "gn:timezone":"Asia/Tehran",
    "iso:country":"IR",
    "name:fas_x_preferred":[
        "\u06a9\u0627\u0631\u06af\u0627\u0647"
    ],
    "name:fas_x_variant":[
        "K\u0101rg\u0101h"
    ],
    "wof:name":"Kargah",
    "wof:placetype":"locality"
},
  "geometry": {"coordinates":[56.83604,28.35013],"type":"Point"}
}