{
  "type": "Feature",
  "properties": {
    "gn:admin1_code":"35.0",
    "gn:asciiname":"Babulat",
    "gn:country_code":"IR",
    "gn:dem":-11,
    "gn:feature_class":"P",
    "gn:feature_code":"PPL",
    "gn:name":"B\u0101b\u016bl\u0101t",
    "gn:population":0,
    "gn:timezone":"Asia/Tehran",
    "iso:country":"IR",
    "name:fas_x_preferred":[
        "\u0628\u0627\u0628\u0648\u0644\u0627\u062a"
    ],
    "name:und_x_variant":[
        "B\u0101b\u016bl\u0101t"
    ],
    "wof:name":"Babulat",
    "wof:placetype":"locality"
},
  "geometry": {"coordinates":[50.96285,36.75228],"type":"Point"}
}