{
  "type": "Feature",
  "properties": {
    "gn:admin1_code":"36",
    "gn:asciiname":"Hamzeh Khan",
    "gn:country_code":"IR",
    "gn:dem":1392,
    "gn:feature_class":"P",
    "gn:feature_code":"PPL",
    "gn:name":"\u1e28amzeh Kh\u0101n",
    "gn:population":0,
    "gn:timezone":"Asia/Tehran",
    "iso:country":"IR",
    "name:fas_x_preferred":[
        "\u062d\u0645\u0632\u0647 \u062e\u0627\u0646"
    ],
    "name:fas_x_variant":[
        "\u1e28amzeh\u0101b\u0101d",
        "\u1e28amzeh Kh\u0101n",
        "\u062d\u0645\u0632\u0647 \u0622\u0628\u0627\u062f"
    ],
    "wof:name":"Hamzeh Khan",
    "wof:placetype":"locality"
},
  "geometry": {"coordinates":[47.80397,36.53657000000001],"type":"Point"}
}