{
  "type": "Feature",
  "properties": {
    "gn:admin1_code":"4.0",
    "gn:asciiname":"Dalgan",
    "gn:country_code":"IR",
    "gn:dem":18,
    "gn:feature_class":"P",
    "gn:feature_code":"PPL",
    "gn:name":"Dalg\u0101n",
    "gn:population":0,
    "gn:timezone":"Asia/Tehran",
    "iso:country":"IR",
    "name:fas_x_preferred":[
        "Dalg\u0101n"
    ],
    "name:fas_x_variant":[
        "\u062f\u0644\u06af\u0627\u0646"
    ],
    "wof:name":"Dalgan",
    "wof:placetype":"locality"
},
  "geometry": {"coordinates":[61.26234,25.4846],"type":"Point"}
}