{
  "type": "Feature",
  "properties": {
    "gn:admin1_code":"11",
    "gn:asciiname":"Bandar-e Nakhilu",
    "gn:country_code":"IR",
    "gn:dem":0,
    "gn:feature_class":"P",
    "gn:feature_code":"PPL",
    "gn:name":"Bandar-e Nakh\u012bl\u016b",
    "gn:population":0,
    "gn:timezone":"Asia/Tehran",
    "iso:country":"IR",
    "name:ara_x_preferred":[
        "\u0646\u062e\u064a\u0644\u0648\u0629"
    ],
    "name:ceb_x_preferred":[
        "Bandar-e Nakh\u012bl\u016b"
    ],
    "name:fas_x_preferred":[
        "\u0628\u0646\u062f\u0631\u0650 \u0646\u062e\u064a\u0644\u0648"
    ],
    "name:fas_x_variant":[
        "\u0646\u062e\u064a\u0644\u0648",
        "Bandar-e Nakh\u012bl\u016b",
        "Nahk\u012bl\u016b",
        "\u0646\u062e\u06cc\u0644\u0648\u0647"
    ],
    "name:msa_x_preferred":[
        "Bandar-e Nakhilu"
    ],
    "name:swe_x_preferred":[
        "Bandar-e Nakh\u012bl\u016b"
    ],
    "name:und_x_variant":[
        "Nahk\u012blu",
        "Nakhilu"
    ],
    "wof:name":"Bandar-e Nakhilu",
    "wof:placetype":"locality"
},
  "geometry": {"coordinates":[53.4874,26.891],"type":"Point"}
}