{
  "type": "Feature",
  "properties": {
    "gn:admin1_code":"29",
    "gn:asciiname":"Bahrami",
    "gn:country_code":"IR",
    "gn:dem":594,
    "gn:feature_class":"P",
    "gn:feature_code":"PPL",
    "gn:name":"Bahr\u0101m\u012b",
    "gn:population":0,
    "gn:timezone":"Asia/Tehran",
    "iso:country":"IR",
    "name:deu_x_preferred":[
        "Bahrami"
    ],
    "name:fas_x_preferred":[
        "\u0628\u0647\u0631\u0627\u0645\u06cc"
    ],
    "name:fas_x_variant":[
        "Bahr\u0101m\u012b-ye P\u0101\u2019\u012bn",
        "Bahr\u0101m\u012b"
    ],
    "wof:name":"Bahrami",
    "wof:placetype":"locality"
},
  "geometry": {"coordinates":[57.8006,28.5307],"type":"Point"}
}