{
  "type": "Feature",
  "properties": {
    "gn:admin1_code":"1",
    "gn:asciiname":"Bakhtiaran",
    "gn:country_code":"IR",
    "gn:dem":1194,
    "gn:feature_class":"P",
    "gn:feature_code":"PPL",
    "gn:name":"Bakht\u012b\u0101r\u0101n",
    "gn:population":0,
    "gn:timezone":"Asia/Tehran",
    "iso:country":"IR",
    "name:fas_x_preferred":[
        "\u0628\u062e\u062a\u06cc\u0627\u0631\u0627\u0646"
    ],
    "name:fas_x_variant":[
        "Bakht\u012b\u0101r\u0101n"
    ],
    "wof:name":"Bakhtiaran",
    "wof:placetype":"locality"
},
  "geometry": {"coordinates":[44.8698,38.4364],"type":"Point"}
}