{
  "type": "Feature",
  "properties": {
    "gn:admin1_code":"29",
    "gn:asciiname":"Harinu",
    "gn:country_code":"IR",
    "gn:dem":2491,
    "gn:feature_class":"P",
    "gn:feature_code":"PPL",
    "gn:name":"H\u0101r\u012bn\u016b",
    "gn:population":0,
    "gn:timezone":"Asia/Tehran",
    "iso:country":"IR",
    "name:fas_x_preferred":[
        "\u0647\u0627\u0631\u06cc\u0646\u0648"
    ],
    "name:fas_x_variant":[
        "H\u0101r\u012bn\u016b"
    ],
    "wof:name":"Harinu",
    "wof:placetype":"locality"
},
  "geometry": {"coordinates":[56.1297,29.996],"type":"Point"}
}