{
  "type": "Feature",
  "properties": {
    "gn:admin1_code":"13",
    "gn:asciiname":"Deh Tut-e `Olya",
    "gn:country_code":"IR",
    "gn:dem":1242,
    "gn:feature_class":"P",
    "gn:feature_code":"PPL",
    "gn:name":"Deh T\u016bt-e \u2018Oly\u0101",
    "gn:population":0,
    "gn:timezone":"Asia/Tehran",
    "iso:country":"IR",
    "name:fas_x_preferred":[
        "\u062f\u0647 \u062a\u0648\u062a \u0639\u0644\u064a\u0627"
    ],
    "name:fas_x_variant":[
        "Deht\u016b-ye \u2018Oly\u0101",
        "Deh T\u016bt-e \u2018Oly\u0101"
    ],
    "name:und_x_variant":[
        "Deh T\u016bt",
        "Deht\u016b-ye B\u0101l\u0101"
    ],
    "wof:name":"Deh Tut-e `Olya",
    "wof:placetype":"locality"
},
  "geometry": {"coordinates":[46.3784,34.818],"type":"Point"}
}