{
  "type": "Feature",
  "properties": {
    "gn:admin1_code":"28",
    "gn:asciiname":"Darreh Alicheh",
    "gn:country_code":"IR",
    "gn:dem":2249,
    "gn:feature_class":"P",
    "gn:feature_code":"PPL",
    "gn:name":"Darreh \u0100l\u012bcheh",
    "gn:population":0,
    "gn:timezone":"Asia/Tehran",
    "iso:country":"IR",
    "name:fas_x_preferred":[
        "Darreh \u0100l\u012bcheh"
    ],
    "name:fas_x_variant":[
        "\u062f\u0631\u0647 \u0622\u0644\u06cc\u0686\u0647"
    ],
    "wof:name":"Darreh Alicheh",
    "wof:placetype":"locality"
},
  "geometry": {"coordinates":[50.28032,32.60781],"type":"Point"}
}