{
  "type": "Feature",
  "properties": {
    "gn:admin1_code":"5",
    "gn:asciiname":"Kamak",
    "gn:country_code":"IR",
    "gn:dem":1831,
    "gn:feature_class":"P",
    "gn:feature_code":"PPL",
    "gn:name":"Kamak",
    "gn:population":0,
    "gn:timezone":"Asia/Tehran",
    "iso:country":"IR",
    "name:fas_x_preferred":[
        "Kamak-e Sofl\u00e1"
    ],
    "name:fas_x_variant":[
        "\u0643\u0645\u06a9"
    ],
    "name:und_x_variant":[
        "Chamech",
        "Kamek",
        "Kamak",
        "Chamesh"
    ],
    "wof:name":"Kamak",
    "wof:placetype":"locality"
},
  "geometry": {"coordinates":[50.80682,31.01993],"type":"Point"}
}