{
  "type": "Feature",
  "properties": {
    "gn:admin1_code":"8.0",
    "gn:asciiname":"Chelunsar",
    "gn:country_code":"IR",
    "gn:dem":15,
    "gn:feature_class":"P",
    "gn:feature_code":"PPL",
    "gn:name":"Chel\u016bnsar",
    "gn:population":0,
    "gn:timezone":"Asia/Tehran",
    "iso:country":"IR",
    "name:fas_x_preferred":[
        "\u0686\u0644\u0646\u0647 \u0633\u0631"
    ],
    "name:fas_x_variant":[
        "Chal\u0101n\u0101 S\u0101r",
        "Chalmeh Sar\u0101",
        "Chateh Naz\u0327ar",
        "Chelowna\u015far",
        "Chal\u0101neh Sar",
        "\u0686\u0644\u0648\u0646\u0633\u0631",
        "\u0686\u0644\u0648\u0646\u0647 \u0633\u0631"
    ],
    "name:und_x_variant":[
        "Chelow Sar",
        "Chalakasar",
        "Chelneh Sar",
        "Chel\u016bnsar",
        "Chel\u016bneh Sar"
    ],
    "wof:name":"Chelunsar",
    "wof:placetype":"locality"
},
  "geometry": {"coordinates":[48.8937,37.8712],"type":"Point"}
}