{
  "type": "Feature",
  "properties": {
    "gn:admin1_code":"41",
    "gn:asciiname":"Deh-e Mir",
    "gn:country_code":"IR",
    "gn:dem":1492,
    "gn:feature_class":"P",
    "gn:feature_code":"PPL",
    "gn:name":"Deh-e M\u012br",
    "gn:population":0,
    "gn:timezone":"Asia/Tehran",
    "iso:country":"IR",
    "name:fas_x_preferred":[
        "Deh-e M\u012br"
    ],
    "name:fas_x_variant":[
        "\u062f\u0647 \u0645\u06cc\u0631"
    ],
    "wof:name":"Deh-e Mir",
    "wof:placetype":"locality"
},
  "geometry": {"coordinates":[59.23845,34.00463],"type":"Point"}
}