{
  "type": "Feature",
  "properties": {
    "gn:admin1_code":"35.0",
    "gn:asciiname":"Darabdin-e Bahnemir",
    "gn:country_code":"IR",
    "gn:dem":-16,
    "gn:feature_class":"P",
    "gn:feature_code":"PPL",
    "gn:name":"D\u0101r\u0101bd\u012bn-e Bahnem\u012br",
    "gn:population":0,
    "gn:timezone":"Asia/Tehran",
    "iso:country":"IR",
    "name:fas_x_preferred":[
        "\u062f\u0627\u0631\u0627\u0628\u062f\u064a\u0646 \u0628\u0647\u0646\u0645\u064a\u0631"
    ],
    "name:fas_x_variant":[
        "\u062f\u0627\u0631\u0627\u0628 \u062f\u064a\u0646 \u0628\u064e\u0647\u0646\u0650\u0645\u064a\u0631",
        "D\u0101r\u0101bd\u012bn-e Bahnem\u012br"
    ],
    "name:und_x_variant":[
        "D\u0101r\u0101b D\u012bn Bahnem\u012br"
    ],
    "wof:name":"Darabdin-e Bahnemir",
    "wof:placetype":"locality"
},
  "geometry": {"coordinates":[52.76495,36.6806],"type":"Point"}
}