{
  "type": "Feature",
  "properties": {
    "gn:admin1_code":"4",
    "gn:asciiname":"Ghafurabad",
    "gn:country_code":"IR",
    "gn:dem":1399,
    "gn:feature_class":"P",
    "gn:feature_code":"PPL",
    "gn:name":"Ghaf\u016br\u0101b\u0101d",
    "gn:population":0,
    "gn:timezone":"Asia/Tehran",
    "iso:country":"IR",
    "name:fas_x_preferred":[
        "\u063a\u0641\u0648\u0631 \u0622\u0628\u0627\u062f"
    ],
    "name:fas_x_variant":[
        "Ghaf\u016br\u0101b\u0101d"
    ],
    "wof:name":"Ghafurabad",
    "wof:placetype":"locality"
},
  "geometry": {"coordinates":[60.8354,28.0529],"type":"Point"}
}