{
  "type": "Feature",
  "properties": {
    "gn:admin1_code":"4.0",
    "gn:asciiname":"Chah-e Molla `Isa",
    "gn:country_code":"IR",
    "gn:dem":1165,
    "gn:feature_class":"P",
    "gn:feature_code":"PPL",
    "gn:name":"Ch\u0101h-e Moll\u0101 \u2018\u012as\u00e1",
    "gn:population":0,
    "gn:timezone":"Asia/Tehran",
    "iso:country":"IR",
    "name:fas_x_preferred":[
        "Ch\u0101h-e Moll\u0101 \u2018\u012as\u00e1"
    ],
    "name:fas_x_variant":[
        "\u0686\u0627\u0647 \u0645\u0644\u0627 \u0639\u064a\u0633\u06cc",
        "\u0686\u0627\u0647 \u06a9\u0631\u06cc\u0645\u06cc",
        "\u0686\u0627\u0647 \u0645\u0644\u0627 \u0639\u0644\u06cc"
    ],
    "name:und_x_variant":[
        "Ch\u0101h-e Kar\u012bm\u012b",
        "Ch\u0101h-e Moll\u0101 \u2018Al\u012b"
    ],
    "wof:name":"Chah-e Molla `Isa",
    "wof:placetype":"locality"
},
  "geometry": {"coordinates":[61.91597,27.36143],"type":"Point"}
}