{
  "type": "Feature",
  "properties": {
    "gn:admin1_code":"3",
    "gn:asciiname":"Karf-e Sofla",
    "gn:country_code":"IR",
    "gn:dem":1502,
    "gn:feature_class":"P",
    "gn:feature_code":"PPL",
    "gn:name":"Karf-e Sofl\u00e1",
    "gn:population":0,
    "gn:timezone":"Asia/Tehran",
    "iso:country":"IR",
    "name:ceb_x_preferred":[
        "Karf-e Sofl\u00e1"
    ],
    "name:fas_x_preferred":[
        "Karf-e Sofl\u00e1"
    ],
    "name:fas_x_variant":[
        "\u0643\u0631\u0641 \u0633\u0641\u0644\u0649",
        "\u06a9\u0631\u0641 \u0633\u0641\u0644\u06cc"
    ],
    "name:msa_x_preferred":[
        "Karf-e Sofla"
    ],
    "name:swe_x_preferred":[
        "Karf-e Sofl\u00e1"
    ],
    "wof:name":"Karf-e Sofla",
    "wof:placetype":"locality"
},
  "geometry": {"coordinates":[50.70708,31.52956],"type":"Point"}
}