{
  "type": "Feature",
  "properties": {
    "gn:admin1_code":"33",
    "gn:asciiname":"Goshayesh",
    "gn:country_code":"IR",
    "gn:dem":1577,
    "gn:feature_class":"P",
    "gn:feature_code":"PPL",
    "gn:name":"Gosh\u0101yesh",
    "gn:population":0,
    "gn:timezone":"Asia/Tehran",
    "iso:country":"IR",
    "name:fas_x_preferred":[
        "\u06af\u0634\u0627\u06cc\u0634"
    ],
    "name:fas_x_variant":[
        "Gosh\u0101yesh"
    ],
    "wof:name":"Goshayesh",
    "wof:placetype":"locality"
},
  "geometry": {"coordinates":[46.3456,37.3278],"type":"Point"}
}