{
  "type": "Feature",
  "properties": {
    "gn:admin1_code":"22",
    "gn:asciiname":"Jazireh-ye Jonubi",
    "gn:country_code":"IR",
    "gn:dem":6,
    "gn:feature_class":"P",
    "gn:feature_code":"PPL",
    "gn:name":"Jaz\u012breh-ye Jon\u016bb\u012b",
    "gn:population":0,
    "gn:timezone":"Asia/Tehran",
    "iso:country":"IR",
    "name:ceb_x_preferred":[
        "Jaz\u012breh-ye Jon\u016bb\u012b"
    ],
    "name:fas_x_preferred":[
        "\u062c\u0632\u064a\u0631\u0650\u06c1 \u062c\u0646\u0648\u0628\u06cc"
    ],
    "name:fas_x_variant":[
        "Jaz\u012breh-ye Jon\u016bb\u012b",
        "\u062c\u0632\u06cc\u0631\u0647 \u062c\u0646\u0648\u0628\u06cc"
    ],
    "name:msa_x_preferred":[
        "Jazireh-ye Jonubi"
    ],
    "name:swe_x_preferred":[
        "Jaz\u012breh-ye Jon\u016bb\u012b"
    ],
    "wof:name":"Jazireh-ye Jonubi",
    "wof:placetype":"locality"
},
  "geometry": {"coordinates":[50.666,29.4184],"type":"Point"}
}