{
  "type": "Feature",
  "properties": {
    "gn:admin1_code":"8",
    "gn:asciiname":"Lima",
    "gn:country_code":"IR",
    "gn:dem":1285,
    "gn:feature_class":"P",
    "gn:feature_code":"PPL",
    "gn:name":"L\u012bm\u0101",
    "gn:population":0,
    "gn:timezone":"Asia/Tehran",
    "iso:country":"IR",
    "name:fas_x_preferred":[
        "L\u012bm\u0101"
    ],
    "name:fas_x_variant":[
        "\u0644\u06cc\u0645\u0627",
        "\u0644\u06cc\u0645\u0627\u06af\u0648\u0627\u0628\u0631"
    ],
    "name:msa_x_preferred":[
        "Lima Gavabar"
    ],
    "name:ukr_x_preferred":[
        "\u041b\u0456\u043c\u0430-\u0490\u0430\u0432\u0430\u0431\u0430\u0440"
    ],
    "wof:name":"Lima",
    "wof:placetype":"locality"
},
  "geometry": {"coordinates":[50.25183,36.84293],"type":"Point"}
}