{
  "type": "Feature",
  "properties": {
    "gn:admin1_code":"7.0",
    "gn:asciiname":"Ab Bid",
    "gn:country_code":"IR",
    "gn:dem":2146,
    "gn:feature_class":"P",
    "gn:feature_code":"PPL",
    "gn:name":"\u0100b B\u012bd",
    "gn:population":0,
    "gn:timezone":"Asia/Tehran",
    "iso:country":"IR",
    "name:fas_x_preferred":[
        "\u0100b B\u012bd-e Bav\u0101n"
    ],
    "name:fas_x_variant":[
        "\u0100b B\u012bd",
        "\u0622\u0628 \u0628\u06cc\u062f",
        "\u0622\u0628\u200c\u0628\u06cc\u062f \u0628\u0648\u0627\u0646"
    ],
    "name:msa_x_preferred":[
        "Ab Bid-e Bavan"
    ],
    "name:und_x_variant":[
        "\u0100b B\u012bd-e Bov\u0101n"
    ],
    "name:urd_x_preferred":[
        "\u0622\u0628 \u0628\u06cc\u062f \u0628\u0648\u0627\u0646"
    ],
    "wof:name":"Ab Bid",
    "wof:placetype":"locality"
},
  "geometry": {"coordinates":[51.70472,29.98951],"type":"Point"}
}