{
  "type": "Feature",
  "properties": {
    "gn:admin1_code":"4",
    "gn:asciiname":"Gazzak",
    "gn:country_code":"IR",
    "gn:dem":1718,
    "gn:feature_class":"P",
    "gn:feature_code":"PPL",
    "gn:name":"Gazzak",
    "gn:population":0,
    "gn:timezone":"Asia/Tehran",
    "iso:country":"IR",
    "name:fas_x_preferred":[
        "\u06af\u0632\u0651\u06a9"
    ],
    "wof:name":"Gazzak",
    "wof:placetype":"locality"
},
  "geometry": {"coordinates":[61.30296,28.57851],"type":"Point"}
}