{
  "type": "Feature",
  "properties": {
    "gn:admin1_code":"4.0",
    "gn:asciiname":"Konari",
    "gn:country_code":"IR",
    "gn:dem":1090,
    "gn:feature_class":"P",
    "gn:feature_code":"PPL",
    "gn:name":"Kon\u0101r\u012b",
    "gn:population":0,
    "gn:timezone":"Asia/Tehran",
    "iso:country":"IR",
    "name:fas_x_preferred":[
        "\u06a9\u0646\u0627\u0631\u06cc"
    ],
    "name:fas_x_variant":[
        "Kon\u0101r\u012b",
        "Ken\u0101r\u012b"
    ],
    "name:und_x_variant":[
        "Ken\u0101r\u012b"
    ],
    "wof:name":"Konari",
    "wof:placetype":"locality"
},
  "geometry": {"coordinates":[60.6844,26.66228],"type":"Point"}
}