{
  "type": "Feature",
  "properties": {
    "gn:admin1_code":"9",
    "gn:asciiname":"Segavi",
    "gn:country_code":"IR",
    "gn:dem":1504,
    "gn:feature_class":"P",
    "gn:feature_code":"PPL",
    "gn:name":"Seg\u0101v\u012b",
    "gn:population":0,
    "gn:timezone":"Asia/Tehran",
    "iso:country":"IR",
    "name:ceb_x_preferred":[
        "Sek\u0101v\u012b"
    ],
    "name:fas_x_preferred":[
        "\u0633\u064e\u06af\u064e\u0648\u06cc"
    ],
    "name:fas_x_variant":[
        "\u0633\u0650\u06af\u0627\u0648\u06cc",
        "\u0633\u064e\u0643\u0627\u0648\u06cc",
        "Sek\u0101v\u012b",
        "Sagav\u012b",
        "\u0633\u06a9\u0627\u0648\u06cc",
        "\u0633\u06af\u0627\u0648\u06cc"
    ],
    "name:msa_x_preferred":[
        "Segavi"
    ],
    "name:swe_x_preferred":[
        "Sek\u0101v\u012b"
    ],
    "name:und_x_variant":[
        "Seg\u0101v\u012b",
        "Sak\u0101v\u012b"
    ],
    "wof:name":"Segavi",
    "wof:placetype":"locality"
},
  "geometry": {"coordinates":[48.10096,34.58531],"type":"Point"}
}