{
  "type": "Feature",
  "properties": {
    "gn:admin1_code":"13",
    "gn:asciiname":"Choqa Bala-ye Sofla",
    "gn:country_code":"IR",
    "gn:dem":1860,
    "gn:feature_class":"P",
    "gn:feature_code":"PPL",
    "gn:name":"Choq\u0101 B\u0101l\u0101-ye Sofl\u00e1",
    "gn:population":0,
    "gn:timezone":"Asia/Tehran",
    "iso:country":"IR",
    "name:fas_x_preferred":[
        "Choq\u0101 B\u0101l\u0101-ye Sofl\u00e1"
    ],
    "name:fas_x_variant":[
        "\u0686\u0642\u0627 \u0628\u0627\u0644\u0627 \u0633\u0641\u0644\u06cc"
    ],
    "wof:name":"Choqa Bala-ye Sofla",
    "wof:placetype":"locality"
},
  "geometry": {"coordinates":[47.77245,34.71628],"type":"Point"}
}