{
  "type": "Feature",
  "properties": {
    "gn:admin1_code":"41",
    "gn:asciiname":"Mazra`eh-ye Dahaneh-ye Afkesht",
    "gn:country_code":"IR",
    "gn:dem":1592,
    "gn:feature_class":"P",
    "gn:feature_code":"PPLF",
    "gn:name":"Mazra\u2018eh-ye Dahaneh-ye Afkesht",
    "gn:population":0,
    "gn:timezone":"Asia/Tehran",
    "iso:country":"IR",
    "name:fas_x_preferred":[
        "\u0645\u0632\u0631\u0639\u0647 \u062f\u0647\u0646\u0647 \u0627\u0641\u06a9\u0634\u062a"
    ],
    "name:fas_x_variant":[
        "\u062f\u0647\u0646\u0647"
    ],
    "name:und_x_variant":[
        "Kal\u0101teh Deh\u0101neh",
        "Dahaneh \u0100bkesh",
        "Dahaneh-ye \u0100b kesh",
        "Dahaneh",
        "Mazra\u2018eh-ye Dahaneh-ye Afkesht"
    ],
    "wof:name":"Mazra`eh-ye Dahaneh-ye Afkesht",
    "wof:placetype":"locality"
},
  "geometry": {"coordinates":[58.80841,33.11397],"type":"Point"}
}