{
  "type": "Feature",
  "properties": {
    "gn:admin1_code":"28",
    "gn:asciiname":"Dowlatabad-e Karim",
    "gn:country_code":"IR",
    "gn:dem":2283,
    "gn:feature_class":"P",
    "gn:feature_code":"PPL",
    "gn:name":"Dowlat\u0101b\u0101d-e Kar\u012bm",
    "gn:population":0,
    "gn:timezone":"Asia/Tehran",
    "iso:country":"IR",
    "name:ara_x_preferred":[
        "\u062f\u0648\u0644\u062a\u200c\u0622\u0628\u0627\u062f"
    ],
    "name:fas_x_preferred":[
        "Dowlat\u0101b\u0101d-e Sofl\u00e1"
    ],
    "name:fas_x_variant":[
        "Dowlat\u0101b\u0101d-e Kar\u012bm",
        "\u062f\u0648\u0644\u062a \u0622\u0628\u0627\u062f \u06a9\u0631\u06cc\u0645",
        "\u062f\u0648\u0644\u062a\u200c\u0622\u0628\u0627\u062f"
    ],
    "wof:name":"Dowlatabad-e Karim",
    "wof:placetype":"locality"
},
  "geometry": {"coordinates":[50.31095,32.59757],"type":"Point"}
}