{
  "type": "Feature",
  "properties": {
    "gn:admin1_code":"42",
    "gn:asciiname":"Kalateh-ye Pa'in Deh",
    "gn:country_code":"IR",
    "gn:dem":1463,
    "gn:feature_class":"P",
    "gn:feature_code":"PPL",
    "gn:name":"Kal\u0101teh-ye P\u0101\u2019\u012bn Deh",
    "gn:population":0,
    "gn:timezone":"Asia/Tehran",
    "iso:country":"IR",
    "name:fas_x_preferred":[
        "Kal\u0101teh-ye P\u0101\u2019\u012bn Deh"
    ],
    "name:fas_x_variant":[
        "Kal\u0101teh-ye P\u0101\u2019\u012bn Darreh",
        "\u06a9\u0644\u0627\u062a\u0647 \u067e\u0627\u0626\u064a\u0646 \u062f\u0631\u0647",
        "\u06a9\u0644\u0627\u062a\u0647 \u067e\u0627\u06cc\u06cc\u0646 \u062f\u0647",
        "\u06a9\u0644\u0627\u062a\u0647 \u067e\u0627\u06cc\u06cc\u0646\u200c\u062f\u0631\u0647"
    ],
    "name:und_x_variant":[
        "\u06a9\u0644\u0627\u062a\u0647 \u067e\u0627\u0626\u064a\u0646 \u062f\u0631\u0647"
    ],
    "wof:name":"Kalateh-ye Pa'in Deh",
    "wof:placetype":"locality"
},
  "geometry": {"coordinates":[58.33354,35.4744],"type":"Point"}
}