{
  "type": "Feature",
  "properties": {
    "gn:admin1_code":"34.0",
    "gn:asciiname":"`Omarabad",
    "gn:country_code":"IR",
    "gn:dem":1689,
    "gn:feature_class":"P",
    "gn:feature_code":"PPL",
    "gn:name":"\u2018Omar\u0101b\u0101d",
    "gn:population":0,
    "gn:timezone":"Asia/Tehran",
    "iso:country":"IR",
    "name:fas_x_preferred":[
        "\u0639\u064e\u0645\u0631\u064f\u0648 \u0622\u0628\u0627\u062f"
    ],
    "name:fas_x_variant":[
        "\u0639\u064e\u0645\u0631 \u0622\u0628\u0627\u062f",
        "\u2018Omar\u0101b\u0101d",
        "\u2018Amrow\u0101b\u0101d",
        "\u0639\u0645\u0631 \u0622\u0628\u0627\u062f"
    ],
    "name:und_x_variant":[
        "\u2018Amr\u0101b\u0101d"
    ],
    "wof:name":"`Omarabad",
    "wof:placetype":"locality"
},
  "geometry": {"coordinates":[50.06492,34.16976],"type":"Point"}
}