{
  "type": "Feature",
  "properties": {
    "gn:admin1_code":"34",
    "gn:asciiname":"Shurakabad",
    "gn:country_code":"IR",
    "gn:dem":1246,
    "gn:feature_class":"P",
    "gn:feature_code":"PPL",
    "gn:name":"Sh\u016brak\u0101b\u0101d",
    "gn:population":0,
    "gn:timezone":"Asia/Tehran",
    "iso:country":"IR",
    "name:fas_x_preferred":[
        "\u0634\u0648\u0631\u06a9 \u0622\u0628\u0627\u062f"
    ],
    "name:fas_x_variant":[
        "Sh\u016brak\u0101b\u0101d",
        "\u0634\u0648\u0631\u06a9\u200c\u0622\u0628\u0627\u062f"
    ],
    "name:fra_x_preferred":[
        "Chourakabad"
    ],
    "name:ukr_x_preferred":[
        "\u0428\u0443\u0440\u0430\u043a\u0430\u0431\u0430\u0434"
    ],
    "wof:name":"Shurakabad",
    "wof:placetype":"locality"
},
  "geometry": {"coordinates":[50.55991,35.36042],"type":"Point"}
}