{
  "type": "Feature",
  "properties": {
    "gn:admin1_code":"23",
    "gn:asciiname":"Dar Kul",
    "gn:country_code":"IR",
    "gn:dem":2150,
    "gn:feature_class":"P",
    "gn:feature_code":"PPL",
    "gn:name":"Dar K\u016bl",
    "gn:population":0,
    "gn:timezone":"Asia/Tehran",
    "iso:country":"IR",
    "name:fas_x_preferred":[
        "\u062f\u0631\u0651\u0647 \u0643\u0648\u0644"
    ],
    "name:fas_x_variant":[
        "Darreh K\u016bl",
        "\u062f\u0631 \u06a9\u0648\u0644"
    ],
    "name:und_x_variant":[
        "Dar K\u016bl"
    ],
    "wof:name":"Dar Kul",
    "wof:placetype":"locality"
},
  "geometry": {"coordinates":[49.59631,33.03167],"type":"Point"}
}