{
  "type": "Feature",
  "properties": {
    "gn:admin1_code":"4",
    "gn:asciiname":"Garban",
    "gn:country_code":"IR",
    "gn:dem":1250,
    "gn:feature_class":"P",
    "gn:feature_code":"PPL",
    "gn:name":"Garb\u0101n",
    "gn:population":0,
    "gn:timezone":"Asia/Tehran",
    "iso:country":"IR",
    "name:fas_x_preferred":[
        "\u06af\u0631\u0628\u0627\u0646"
    ],
    "name:fas_x_variant":[
        "Garb\u0101n"
    ],
    "wof:name":"Garban",
    "wof:placetype":"locality"
},
  "geometry": {"coordinates":[61.03876999999999,26.89167],"type":"Point"}
}