{
  "type": "Feature",
  "properties": {
    "gn:admin1_code":"7",
    "gn:asciiname":"Zir Ab",
    "gn:country_code":"IR",
    "gn:dem":1027,
    "gn:feature_class":"P",
    "gn:feature_code":"PPL",
    "gn:name":"Z\u012br \u0100b",
    "gn:population":0,
    "gn:timezone":"Asia/Tehran",
    "iso:country":"IR",
    "name:fas_x_preferred":[
        "Z\u012br \u0100b"
    ],
    "name:fas_x_variant":[
        "\u0632\u06cc\u0631 \u0622\u0628",
        "\u0632\u06cc\u0631\u0627\u0628"
    ],
    "name:msa_x_preferred":[
        "Zirab"
    ],
    "name:und_x_variant":[
        "Z\u012br\u0101b",
        "\u0632\u06cc\u0631 \u0622\u0628"
    ],
    "wof:name":"Zir Ab",
    "wof:placetype":"locality"
},
  "geometry": {"coordinates":[54.43399,28.47981],"type":"Point"}
}