{
  "type": "Feature",
  "properties": {
    "gn:admin1_code":"16.0",
    "gn:asciiname":"Aghol Sukhteh",
    "gn:country_code":"IR",
    "gn:dem":1675,
    "gn:feature_class":"P",
    "gn:feature_code":"PPL",
    "gn:name":"\u0100ghol S\u016bkhteh",
    "gn:population":0,
    "gn:timezone":"Asia/Tehran",
    "iso:country":"IR",
    "name:fas_x_preferred":[
        "\u0622\u063a\u0644 \u0633\u0648\u062e\u062a\u0647"
    ],
    "name:fas_x_variant":[
        "\u0100ghol S\u016bkhteh"
    ],
    "wof:name":"Aghol Sukhteh",
    "wof:placetype":"locality"
},
  "geometry": {"coordinates":[45.8097,36.09],"type":"Point"}
}