{
  "type": "Feature",
  "properties": {
    "gn:admin1_code":"11",
    "gn:asciiname":"Jaghard",
    "gn:country_code":"IR",
    "gn:dem":431,
    "gn:feature_class":"P",
    "gn:feature_code":"PPL",
    "gn:name":"Jaghard",
    "gn:population":0,
    "gn:timezone":"Asia/Tehran",
    "iso:country":"IR",
    "name:fas_x_preferred":[
        "\u062c\u063a\u0631\u062f"
    ],
    "wof:name":"Jaghard",
    "wof:placetype":"locality"
},
  "geometry": {"coordinates":[57.8261,26.245],"type":"Point"}
}