{
  "type": "Feature",
  "properties": {
    "gn:admin1_code":"7",
    "gn:asciiname":"Gozradun",
    "gn:country_code":"IR",
    "gn:dem":400,
    "gn:feature_class":"P",
    "gn:feature_code":"PPL",
    "gn:name":"Gozr\u0101d\u016bn",
    "gn:population":0,
    "gn:timezone":"Asia/Tehran",
    "iso:country":"IR",
    "name:ara_x_preferred":[
        "\u0643\u0631\u0627\u0632\u062f\u0627\u0646"
    ],
    "name:fas_x_preferred":[
        "\u06af\u0632\u0631\u0627\u062f\u0648\u0646"
    ],
    "name:fas_x_variant":[
        "Gor\u0101zd\u0101n",
        "Gozr\u0101d\u016bn",
        "\u06af\u0631\u0627\u0632\u062f\u0627\u0646"
    ],
    "name:msa_x_preferred":[
        "Gorazdan"
    ],
    "name:und_x_variant":[
        "Gor\u0101zd\u016bn"
    ],
    "wof:name":"Gozradun",
    "wof:placetype":"locality"
},
  "geometry": {"coordinates":[53.5493,27.2816],"type":"Point"}
}