{
  "type": "Feature",
  "properties": {
    "gn:admin1_code":"15",
    "gn:asciiname":"Chamtar Khan-e `Olya",
    "gn:country_code":"IR",
    "gn:dem":40,
    "gn:feature_class":"P",
    "gn:feature_code":"PPL",
    "gn:name":"Chamtar Kh\u0101n-e \u2018Oly\u0101",
    "gn:population":0,
    "gn:timezone":"Asia/Tehran",
    "iso:country":"IR",
    "name:fas_x_preferred":[
        "\u0686\u0645\u062a\u0631\u062e\u0627\u0646 \u0639\u0644\u06cc\u0627"
    ],
    "name:fas_x_variant":[
        "Chamtar Kh\u0101n-e B\u0101l\u0101",
        "Kab\u016bt\u0101r Kh\u0101n-e \u2018Oly\u0101",
        "Chamtar Kh\u0101n-e \u2018Oly\u0101"
    ],
    "name:und_x_variant":[
        "Asadullah",
        "Boneh-ye Moll\u0101 Mehd\u012b",
        "Asadoll\u0101h",
        "Cham Tarkh\u0101n",
        "Chamtar Kh\u0101n Asadoll\u0101h"
    ],
    "wof:name":"Chamtar Khan-e `Olya",
    "wof:placetype":"locality"
},
  "geometry": {"coordinates":[48.76736,31.97113],"type":"Point"}
}