{
  "type": "Feature",
  "properties": {
    "gn:admin1_code":"5.0",
    "gn:asciiname":"Nehzatabad",
    "gn:country_code":"IR",
    "gn:dem":694,
    "gn:feature_class":"P",
    "gn:feature_code":"PPL",
    "gn:name":"Neh\u1e95at\u0101b\u0101d",
    "gn:population":0,
    "gn:timezone":"Asia/Tehran",
    "iso:country":"IR",
    "name:fas_x_preferred":[
        "\u0646\u0647\u0636\u062a \u0622\u0628\u0627\u062f"
    ],
    "name:fas_x_variant":[
        "Neh\u1e95at\u0101b\u0101d"
    ],
    "wof:name":"Nehzatabad",
    "wof:placetype":"locality"
},
  "geometry": {"coordinates":[50.5409,30.69107],"type":"Point"}
}