{
  "type": "Feature",
  "properties": {
    "gn:admin1_code":"1",
    "gn:asciiname":"Shurbolagh-e Sofla",
    "gn:country_code":"IR",
    "gn:dem":847,
    "gn:feature_class":"P",
    "gn:feature_code":"PPL",
    "gn:name":"Sh\u016brbol\u0101gh-e Sofl\u00e1",
    "gn:population":0,
    "gn:timezone":"Asia/Tehran",
    "iso:country":"IR",
    "name:azb_x_preferred":[
        "\u0622\u0634\u0627\u063a\u0627 \u0634\u0648\u0631\u0628\u0648\u0644\u0627\u0642"
    ],
    "name:aze_x_preferred":[
        "A\u015fa\u011f\u0131 \u015eorbulaq"
    ],
    "name:ceb_x_preferred":[
        "Sh\u016brbol\u0101gh-e Sofl\u00e1"
    ],
    "name:fas_x_preferred":[
        "\u0634\u0648\u0631\u0628\u064f\u0644\u0627\u063a\u0650 \u0633\u064f\u0641\u0644\u064e\u0649"
    ],
    "name:fas_x_variant":[
        "\u0634\u0648\u0631\u0628\u0644\u0627\u063a \u0633\u0641\u0644\u06cc",
        "Sh\u016brbol\u0101gh-e Sofl\u00e1"
    ],
    "name:msa_x_preferred":[
        "Shurbolagh-e Sofla"
    ],
    "name:swe_x_preferred":[
        "Sh\u016brbol\u0101gh-e Sofl\u00e1"
    ],
    "wof:name":"Shurbolagh-e Sofla",
    "wof:placetype":"locality"
},
  "geometry": {"coordinates":[44.889,39.3764],"type":"Point"}
}