{
  "type": "Feature",
  "properties": {
    "gn:admin1_code":"34",
    "gn:asciiname":"Qatar Aghaj-e Bala",
    "gn:country_code":"IR",
    "gn:dem":1953,
    "gn:feature_class":"P",
    "gn:feature_code":"PPL",
    "gn:name":"Qa\u0163\u0101r \u0100gh\u0101j-e B\u0101l\u0101",
    "gn:population":0,
    "gn:timezone":"Asia/Tehran",
    "iso:country":"IR",
    "name:fas_x_preferred":[
        "\u0642\u0637\u0627\u0631 \u0622\u063a\u0627\u062c \u0639\u0644\u064a\u0627"
    ],
    "name:fas_x_variant":[
        "\u0642\u0637\u0627\u0631 \u0622\u063a\u0627\u062c \u0628\u0627\u0644\u0627"
    ],
    "name:und_x_variant":[
        "Qa\u0163\u0101r \u0100gh\u0101j-e \u2018Oly\u0101",
        "Qa\u0163\u0101r \u0100gh\u0101j-e B\u0101l\u0101"
    ],
    "wof:name":"Qatar Aghaj-e Bala",
    "wof:placetype":"locality"
},
  "geometry": {"coordinates":[49.4033,34.4203],"type":"Point"}
}