{
  "type": "Feature",
  "properties": {
    "gn:admin1_code":"13",
    "gn:asciiname":"Samereh-ye `Olya",
    "gn:country_code":"IR",
    "gn:dem":1379,
    "gn:feature_class":"P",
    "gn:feature_code":"PPL",
    "gn:name":"S\u0101mereh-ye \u2018Oly\u0101",
    "gn:population":0,
    "gn:timezone":"Asia/Tehran",
    "iso:country":"IR",
    "name:fas_x_preferred":[
        "\u0633\u0627\u0645\u0631\u0647 \u0639\u0644\u06cc\u0627"
    ],
    "name:fas_x_variant":[
        "S\u0101mereh-ye \u2018Oly\u0101"
    ],
    "name:und_x_variant":[
        "S\u0101mereh",
        "Samarrah"
    ],
    "wof:name":"Samereh-ye `Olya",
    "wof:placetype":"locality"
},
  "geometry": {"coordinates":[46.8866,34.234],"type":"Point"}
}