{
  "type": "Feature",
  "properties": {
    "gn:admin1_code":"7",
    "gn:asciiname":"Kikomdan",
    "gn:country_code":"IR",
    "gn:dem":1545,
    "gn:feature_class":"P",
    "gn:feature_code":"PPL",
    "gn:name":"K\u012bkomd\u0101n",
    "gn:population":0,
    "gn:timezone":"Asia/Tehran",
    "iso:country":"IR",
    "name:fas_x_preferred":[
        "K\u012bkomd\u0101n"
    ],
    "name:fas_x_variant":[
        "K\u012bkomd\u0101n-e P\u0101\u2019\u012bn",
        "\u06a9\u06cc\u06a9\u0645\u062f\u0627\u0646"
    ],
    "name:und_x_variant":[
        "\u06a9\u06cc\u06a9\u0645\u062f\u0627\u0646"
    ],
    "wof:name":"Kikomdan",
    "wof:placetype":"locality"
},
  "geometry": {"coordinates":[51.87653,30.00816],"type":"Point"}
}