{
  "type": "Feature",
  "properties": {
    "gn:admin1_code":"13.0",
    "gn:asciiname":"Amir ol Omara'",
    "gn:country_code":"IR",
    "gn:dem":1804,
    "gn:feature_class":"P",
    "gn:feature_code":"PPL",
    "gn:name":"Am\u012br ol Omar\u0101\u2019",
    "gn:population":0,
    "gn:timezone":"Asia/Tehran",
    "iso:country":"IR",
    "name:fas_x_preferred":[
        "\u0627\u0645\u06cc\u0631 \u0627\u0644\u0627\u0645\u0631\u0627\u0621"
    ],
    "name:fas_x_variant":[
        "M\u012br Mar\u0101n",
        "Am\u012br \u2018Omr\u0101n",
        "\u0645\u06cc\u0631 \u0645\u0631\u0627\u0646",
        "Am\u012br ol Omar\u0101\u2019"
    ],
    "name:und_x_variant":[
        "M\u012br Umr\u0101n",
        "Am\u012br ol \u2018Emr\u0101n",
        "M\u012br \u2018Om\u0101n",
        "Am\u012br \u2018Emr\u0101n"
    ],
    "wof:name":"Amir ol Omara'",
    "wof:placetype":"locality"
},
  "geometry": {"coordinates":[47.3282,34.9717],"type":"Point"}
}