{
  "type": "Feature",
  "properties": {
    "gn:admin1_code":"7",
    "gn:asciiname":"Qanat-e Malek",
    "gn:country_code":"IR",
    "gn:dem":2301,
    "gn:feature_class":"P",
    "gn:feature_code":"PPL",
    "gn:name":"Qan\u0101t-e Malek",
    "gn:population":0,
    "gn:timezone":"Asia/Tehran",
    "iso:country":"IR",
    "name:ara_x_preferred":[
        "\u0642\u0646\u0627\u062a \u0645\u0644\u0643"
    ],
    "name:fas_x_preferred":[
        "\u0642\u0646\u0627\u062a \u0645\u0644\u06a9"
    ],
    "name:fas_x_variant":[
        "Qan\u0101t-e Malek"
    ],
    "name:msa_x_preferred":[
        "Qanat-e Malek"
    ],
    "name:und_x_variant":[
        "Qan\u0101t-i-Malik"
    ],
    "wof:name":"Qanat-e Malek",
    "wof:placetype":"locality"
},
  "geometry": {"coordinates":[53.5398,30.5048],"type":"Point"}
}