{
  "type": "Feature",
  "properties": {
    "gn:admin1_code":"43",
    "gn:asciiname":"Qal`eh Haji Taqi",
    "gn:country_code":"IR",
    "gn:dem":1200,
    "gn:feature_class":"P",
    "gn:feature_code":"PPL",
    "gn:name":"Qal\u2018eh \u1e28\u0101j\u012b Taq\u012b",
    "gn:population":0,
    "gn:timezone":"Asia/Tehran",
    "iso:country":"IR",
    "name:ara_x_preferred":[
        "\u062d\u0627\u062c \u062a\u0642\u064a"
    ],
    "name:ceb_x_preferred":[
        "Qal\u2018eh \u1e28\u0101j\u012b Taq\u012b"
    ],
    "name:fas_x_preferred":[
        "Qal\u2018eh-ye \u1e28\u0101jj\u012b Taq\u012b"
    ],
    "name:fas_x_variant":[
        "Qal\u2018eh \u1e28\u0101j\u012b Taq\u012b",
        "\u0642\u0644\u0639\u0647 \u062d\u0627\u062c\u06cc \u062a\u0642\u06cc",
        "\u062d\u0627\u062c\u06cc \u062a\u0642\u06cc"
    ],
    "name:swe_x_preferred":[
        "Qal\u2018eh \u1e28\u0101j\u012b Taq\u012b"
    ],
    "name:und_x_variant":[
        "\u1e28\u0101jj\u012b Taq\u012b",
        "Qal\u2018eh-ye H\u0101j\u012btaq\u012b"
    ],
    "wof:name":"Qal`eh Haji Taqi",
    "wof:placetype":"locality"
},
  "geometry": {"coordinates":[58.29912,37.2607],"type":"Point"}
}