{
  "type": "Feature",
  "properties": {
    "gn:admin1_code":"8",
    "gn:asciiname":"Sar Cheshmeh",
    "gn:country_code":"IR",
    "gn:dem":365,
    "gn:feature_class":"P",
    "gn:feature_code":"PPL",
    "gn:name":"Sar Cheshmeh",
    "gn:population":0,
    "gn:timezone":"Asia/Tehran",
    "iso:country":"IR",
    "name:fas_x_preferred":[
        "\u0633\u0631 \u0686\u0634\u0645\u0647"
    ],
    "name:und_x_variant":[
        "Sar Chashmeh",
        "Sar Cheshmeh",
        "\u0633\u0631 \u0686\u0634\u0645\u0647"
    ],
    "wof:name":"Sar Cheshmeh",
    "wof:placetype":"locality"
},
  "geometry": {"coordinates":[50.08414000000001,37.15303],"type":"Point"}
}