{
  "type": "Feature",
  "properties": {
    "gn:admin1_code":"4",
    "gn:asciiname":"Rish Pish-e Pa'in",
    "gn:country_code":"IR",
    "gn:dem":1114,
    "gn:feature_class":"P",
    "gn:feature_code":"PPL",
    "gn:name":"R\u012bsh P\u012bsh-e P\u0101\u2019\u012bn",
    "gn:population":0,
    "gn:timezone":"Asia/Tehran",
    "iso:country":"IR",
    "name:fas_x_preferred":[
        "\u0631\u06cc\u0634 \u067e\u06cc\u0634 \u067e\u0627\u0626\u06cc\u0646"
    ],
    "name:fas_x_variant":[
        "R\u012bsh P\u012bsh-e P\u0101\u2019\u012bn"
    ],
    "wof:name":"Rish Pish-e Pa'in",
    "wof:placetype":"locality"
},
  "geometry": {"coordinates":[63.049,26.8513],"type":"Point"}
}