{
  "type": "Feature",
  "properties": {
    "gn:admin1_code":"29",
    "gn:asciiname":"Roq`eh",
    "gn:country_code":"IR",
    "gn:dem":2296,
    "gn:feature_class":"P",
    "gn:feature_code":"PPL",
    "gn:name":"Roq\u2018eh",
    "gn:population":0,
    "gn:timezone":"Asia/Tehran",
    "iso:country":"IR",
    "name:fas_x_preferred":[
        "\u0631\u0642\u0639\u0647"
    ],
    "name:fas_x_variant":[
        "Roq\u2018eh-ye \u015eoghr\u00e1",
        "Roq\u2018eh"
    ],
    "wof:name":"Roq`eh",
    "wof:placetype":"locality"
},
  "geometry": {"coordinates":[57.01308,30.687],"type":"Point"}
}