{
  "type": "Feature",
  "properties": {
    "gn:admin1_code":"7",
    "gn:asciiname":"Kupan",
    "gn:country_code":"IR",
    "gn:dem":2411,
    "gn:feature_class":"P",
    "gn:feature_code":"PPL",
    "gn:name":"K\u016bp\u0101n",
    "gn:population":0,
    "gn:timezone":"Asia/Tehran",
    "iso:country":"IR",
    "name:ara_x_preferred":[
        "\u06a9\u0648\u0628\u0627\u0646"
    ],
    "name:fas_x_preferred":[
        "\u06a9\u0648\u067e\u0627\u0646"
    ],
    "name:fas_x_variant":[
        "K\u016bp\u0101n"
    ],
    "name:msa_x_preferred":[
        "Kupan"
    ],
    "name:und_x_variant":[
        "K\u016by\u0101n"
    ],
    "wof:name":"Kupan",
    "wof:placetype":"locality"
},
  "geometry": {"coordinates":[53.5909,30.2866],"type":"Point"}
}