{
  "type": "Feature",
  "properties": {
    "gn:admin1_code":"29.0",
    "gn:asciiname":"Surgavan-e `Olya",
    "gn:country_code":"IR",
    "gn:dem":408,
    "gn:feature_class":"P",
    "gn:feature_code":"PPL",
    "gn:name":"S\u016brg\u0101v\u0101n-e \u2018Oly\u0101",
    "gn:population":0,
    "gn:timezone":"Asia/Tehran",
    "iso:country":"IR",
    "name:fas_x_preferred":[
        "\u0633\u0648\u0631\u06af\u0627\u0648\u0627\u0646 \u0639\u0644\u064a\u0627"
    ],
    "name:fas_x_variant":[
        "\u0633\u0648\u0631\u06af\u0627\u0646 \u0639\u0644\u064a\u0627"
    ],
    "name:und_x_variant":[
        "S\u016brg\u0101v\u0101n-e \u2018Oly\u0101",
        "S\u016brg\u0101n-e \u2018Oly\u0101"
    ],
    "wof:name":"Surgavan-e `Olya",
    "wof:placetype":"locality"
},
  "geometry": {"coordinates":[58.16111,27.67452],"type":"Point"}
}