{
  "type": "Feature",
  "properties": {
    "gn:admin1_code":"35",
    "gn:asciiname":"Musaabad",
    "gn:country_code":"IR",
    "gn:dem":15,
    "gn:feature_class":"P",
    "gn:feature_code":"PPL",
    "gn:name":"M\u016bs\u00e1\u0101b\u0101d",
    "gn:population":0,
    "gn:timezone":"Asia/Tehran",
    "iso:country":"IR",
    "name:fas_x_preferred":[
        "\u0645\u0648\u0633\u0649 \u0622\u0628\u0627\u062f"
    ],
    "name:fas_x_variant":[
        "M\u016bs\u00e1\u0101b\u0101d",
        "\u0645\u0648\u0633\u06cc\u200c\u0622\u0628\u0627\u062f"
    ],
    "name:und_x_variant":[
        "M\u016bs\u012b \u0100b\u0101d"
    ],
    "wof:name":"Musaabad",
    "wof:placetype":"locality"
},
  "geometry": {"coordinates":[51.51745,36.63487],"type":"Point"}
}