{
  "type": "Feature",
  "properties": {
    "gn:admin1_code":"13",
    "gn:asciiname":"Shuhan-e Sofla",
    "gn:country_code":"IR",
    "gn:dem":1357,
    "gn:feature_class":"P",
    "gn:feature_code":"PPL",
    "gn:name":"Sh\u016bh\u0101n-e Sofl\u00e1",
    "gn:population":0,
    "gn:timezone":"Asia/Tehran",
    "iso:country":"IR",
    "name:fas_x_preferred":[
        "\u0634\u0648\u0647\u0627\u0646 \u0633\u0641\u0644\u06cc"
    ],
    "name:fas_x_variant":[
        "Sh\u016bh\u0101n-e Sofl\u00e1"
    ],
    "name:und_x_variant":[
        "Sh\u016bf\u0101n",
        "Sh\u016b\u0101n",
        "Showh\u0101n-e Sofl\u00e1",
        "Shian",
        "Sh\u016bh\u0101n"
    ],
    "wof:name":"Shuhan-e Sofla",
    "wof:placetype":"locality"
},
  "geometry": {"coordinates":[46.7978,34.0251],"type":"Point"}
}