{
  "type": "Feature",
  "properties": {
    "gn:admin1_code":"11",
    "gn:asciiname":"Mazra`eh",
    "gn:country_code":"IR",
    "gn:dem":500,
    "gn:feature_class":"P",
    "gn:feature_code":"PPL",
    "gn:name":"Mazra\u2018eh",
    "gn:population":0,
    "gn:timezone":"Asia/Tehran",
    "iso:country":"IR",
    "name:fas_x_preferred":[
        "\u0645\u064e\u0632\u0631\u064e\u0639\u0650\u0647"
    ],
    "name:fas_x_variant":[
        "\u0645\u064e\u0632\u0631\u064e\u0639\u0650\u06c0 \u067e\u0627\u0626\u064a\u0646",
        "\u0645\u064e\u0632\u0631\u064e\u0639\u0650\u06c0 \u0628\u0627\u0644\u0627",
        "Mazra\u2018eh"
    ],
    "name:und_x_variant":[
        "Mazra\u2018eh-ye P\u0101\u2019\u012bn",
        "Mazra\u2018eh-ye B\u0101l\u0101"
    ],
    "wof:name":"Mazra`eh",
    "wof:placetype":"locality"
},
  "geometry": {"coordinates":[56.14611,27.62833],"type":"Point"}
}