{
  "type": "Feature",
  "properties": {
    "gn:admin1_code":"7",
    "gn:asciiname":"Forud",
    "gn:country_code":"IR",
    "gn:dem":1522,
    "gn:feature_class":"P",
    "gn:feature_code":"PPL",
    "gn:name":"For\u016bd",
    "gn:population":0,
    "gn:timezone":"Asia/Tehran",
    "iso:country":"IR",
    "name:fas_x_preferred":[
        "\u0641\u0631\u0648\u062f"
    ],
    "name:fas_x_variant":[
        "For\u016bd"
    ],
    "wof:name":"Forud",
    "wof:placetype":"locality"
},
  "geometry": {"coordinates":[52.736,29.2291],"type":"Point"}
}