{
  "type": "Feature",
  "properties": {
    "gn:admin1_code":"26",
    "gn:asciiname":"Khaledabad",
    "gn:country_code":"IR",
    "gn:dem":878,
    "gn:feature_class":"P",
    "gn:feature_code":"PPL",
    "gn:name":"Kh\u0101led\u0101b\u0101d",
    "gn:population":0,
    "gn:timezone":"Asia/Tehran",
    "iso:country":"IR",
    "name:fas_x_preferred":[
        "Kh\u0101led\u0101b\u0101d"
    ],
    "name:fas_x_variant":[
        "\u062e\u0627\u0644\u062f \u0622\u0628\u0627\u062f",
        "\u062e\u0627\u0644\u062f\u0622\u0628\u0627\u062f"
    ],
    "name:und_x_variant":[
        "\u062e\u0627\u0644\u062f \u0622\u0628\u0627\u062f"
    ],
    "wof:name":"Khaledabad",
    "wof:placetype":"locality"
},
  "geometry": {"coordinates":[51.60668,35.26739],"type":"Point"}
}