{
  "type": "Feature",
  "properties": {
    "gn:admin1_code":"41",
    "gn:asciiname":"Bozqonj",
    "gn:country_code":"IR",
    "gn:dem":1996,
    "gn:feature_class":"P",
    "gn:feature_code":"PPL",
    "gn:name":"Bozqonj",
    "gn:population":0,
    "gn:timezone":"Asia/Tehran",
    "iso:country":"IR",
    "name:ara_x_preferred":[
        "\u0628\u0632 \u0642\u0648\u0646\u064a"
    ],
    "name:ceb_x_preferred":[
        "Boz Qonj"
    ],
    "name:fas_x_preferred":[
        "\u0628\u0632\u0642\u0646\u062c"
    ],
    "name:fas_x_variant":[
        "Bozq\u016bnj"
    ],
    "name:swe_x_preferred":[
        "Boz Qonj"
    ],
    "name:und_x_variant":[
        "Bozq\u016bnj",
        "Buzghunj",
        "Bozqonj"
    ],
    "wof:name":"Bozqonj",
    "wof:placetype":"locality"
},
  "geometry": {"coordinates":[59.36755,33.08338],"type":"Point"}
}