{
  "type": "Feature",
  "properties": {
    "gn:admin1_code":"34",
    "gn:asciiname":"Lowzdar-e Vasat",
    "gn:country_code":"IR",
    "gn:dem":1974,
    "gn:feature_class":"P",
    "gn:feature_code":"PPL",
    "gn:name":"Lowzdar-e Vasa\u0163",
    "gn:population":0,
    "gn:timezone":"Asia/Tehran",
    "iso:country":"IR",
    "name:fas_x_preferred":[
        "\u0644\u0648\u0632\u062f\u0631\u0650 \u0648\u0633\u0637\u0649"
    ],
    "name:fas_x_variant":[
        "\u0644\u0648\u0632\u062f\u0631 \u0648\u0633\u0637",
        "L\u016bz-e Vos\u0163\u00e1",
        "Lowzdar-e Vasa\u0163\u012b",
        "Lowzdar-e Vasa\u0163"
    ],
    "name:und_x_variant":[
        "Lowzdar-e Vos\u0163\u00e1"
    ],
    "wof:name":"Lowzdar-e Vasat",
    "wof:placetype":"locality"
},
  "geometry": {"coordinates":[49.30145,33.69985],"type":"Point"}
}