{
  "type": "Feature",
  "properties": {
    "gn:admin1_code":"7",
    "gn:asciiname":"Qalunak",
    "gn:country_code":"IR",
    "gn:dem":1604,
    "gn:feature_class":"P",
    "gn:feature_code":"PPL",
    "gn:name":"Q\u0101l\u016bnak",
    "gn:population":0,
    "gn:timezone":"Asia/Tehran",
    "iso:country":"IR",
    "name:fas_x_preferred":[
        "Q\u0101l\u016bnak"
    ],
    "wof:name":"Qalunak",
    "wof:placetype":"locality"
},
  "geometry": {"coordinates":[52.65083000000001,30.00389],"type":"Point"}
}