{
  "type": "Feature",
  "properties": {
    "gn:admin1_code":"42.0",
    "gn:asciiname":"Disfan",
    "gn:country_code":"IR",
    "gn:dem":1669,
    "gn:feature_class":"P",
    "gn:feature_code":"PPL",
    "gn:name":"D\u012bsf\u0101n",
    "gn:population":0,
    "gn:timezone":"Asia/Tehran",
    "iso:country":"IR",
    "name:ara_x_preferred":[
        "\u062f\u064a\u0633\u0641\u0627\u0646"
    ],
    "name:ceb_x_preferred":[
        "D\u012bsf\u0101n"
    ],
    "name:fas_x_preferred":[
        "D\u012bsf\u0101n"
    ],
    "name:fas_x_variant":[
        "\u062f\u064a\u0633\u0641\u0627\u0646",
        "\u062f\u06cc\u0633\u0641\u0627\u0646"
    ],
    "name:swe_x_preferred":[
        "D\u012bsf\u0101n"
    ],
    "name:und_x_variant":[
        "\u062f\u064a\u0633\u0641\u0627\u0646"
    ],
    "wof:name":"Disfan",
    "wof:placetype":"locality"
},
  "geometry": {"coordinates":[58.57981,34.16144],"type":"Point"}
}