{
  "type": "Feature",
  "properties": {
    "gn:admin1_code":"5",
    "gn:asciiname":"Murderaz-e `Olya",
    "gn:country_code":"IR",
    "gn:dem":1797,
    "gn:feature_class":"P",
    "gn:feature_code":"PPL",
    "gn:name":"M\u016brder\u0101z-e \u2018Oly\u0101",
    "gn:population":0,
    "gn:timezone":"Asia/Tehran",
    "iso:country":"IR",
    "name:fas_x_preferred":[
        "\u0645\u0648\u0631\u062f\u0650\u0631\u0627\u0632\u0650 \u0628\u0627\u0644\u0627"
    ],
    "name:fas_x_variant":[
        "M\u016brder\u0101z-e \u2018Oly\u0101",
        "M\u016brder\u0101z-e B\u0101l\u0101",
        "\u0645\u0648\u0631\u062f\u0631\u0627\u0632 \u0639\u0644\u06cc\u0627"
    ],
    "wof:name":"Murderaz-e `Olya",
    "wof:placetype":"locality"
},
  "geometry": {"coordinates":[51.55378,30.60801],"type":"Point"}
}