{
  "type": "Feature",
  "properties": {
    "gn:admin1_code":"15",
    "gn:asciiname":"Kavian",
    "gn:country_code":"IR",
    "gn:dem":7,
    "gn:feature_class":"P",
    "gn:feature_code":"PPL",
    "gn:name":"K\u0101v\u012b\u0101n",
    "gn:population":0,
    "gn:timezone":"Asia/Tehran",
    "iso:country":"IR",
    "name:ara_x_preferred":[
        "\u0643\u0627\u0648\u064a\u0627\u0646"
    ],
    "name:fas_x_preferred":[
        "\u06a9\u0627\u0648\u06cc\u0627\u0646"
    ],
    "wof:name":"Kavian",
    "wof:placetype":"locality"
},
  "geometry": {"coordinates":[47.96667,31.66667],"type":"Point"}
}