{
  "type": "Feature",
  "properties": {
    "gn:admin1_code":"13",
    "gn:asciiname":"Talani",
    "gn:country_code":"IR",
    "gn:dem":1742,
    "gn:feature_class":"P",
    "gn:feature_code":"PPL",
    "gn:name":"T\u0101l\u0101n\u012b",
    "gn:population":0,
    "gn:timezone":"Asia/Tehran",
    "iso:country":"IR",
    "wof:name":"Talani",
    "wof:placetype":"locality"
},
  "geometry": {"coordinates":[46.53333,34.26667],"type":"Point"}
}