{
  "type": "Feature",
  "properties": {
    "gn:admin1_code":"8",
    "gn:asciiname":"Razi Nesa",
    "gn:country_code":"IR",
    "gn:dem":455,
    "gn:feature_class":"P",
    "gn:feature_code":"PPL",
    "gn:name":"Ra\u1e95\u012b Nes\u0101",
    "gn:population":0,
    "gn:timezone":"Asia/Tehran",
    "iso:country":"IR",
    "name:fas_x_preferred":[
        "Ra\u1e95\u012b Nes\u0101"
    ],
    "name:fas_x_variant":[
        "\u0631\u0636\u06cc \u0646\u0633\u0627"
    ],
    "name:und_x_variant":[
        "Raz\u012b Nes\u0101"
    ],
    "wof:name":"Razi Nesa",
    "wof:placetype":"locality"
},
  "geometry": {"coordinates":[49.10047,37.16501],"type":"Point"}
}