{
  "type": "Feature",
  "properties": {
    "gn:admin1_code":"8",
    "gn:asciiname":"Posht Masar",
    "gn:country_code":"IR",
    "gn:dem":3,
    "gn:feature_class":"P",
    "gn:feature_code":"PPL",
    "gn:name":"Posht Mas\u0101r",
    "gn:population":0,
    "gn:timezone":"Asia/Tehran",
    "iso:country":"IR",
    "name:fas_x_preferred":[
        "\u067e\u0634\u062a \u0645\u0633\u0627\u0631"
    ],
    "name:fas_x_variant":[
        "Posht Mas\u0101r"
    ],
    "wof:name":"Posht Masar",
    "wof:placetype":"locality"
},
  "geometry": {"coordinates":[49.2561,37.32482],"type":"Point"}
}