{
  "type": "Feature",
  "properties": {
    "gn:admin1_code":"42.0",
    "gn:asciiname":"Nezamand",
    "gn:country_code":"IR",
    "gn:dem":1948,
    "gn:feature_class":"P",
    "gn:feature_code":"PPL",
    "gn:name":"Nez\u0327\u0101mand",
    "gn:population":0,
    "gn:timezone":"Asia/Tehran",
    "iso:country":"IR",
    "name:fas_x_preferred":[
        "\u0646\u0638\u0627\u0645\u0646\u062f"
    ],
    "name:fas_x_variant":[
        "Nez\u0327\u0101mand",
        "\u0646\u0632\u0648\u0645\u0646\u062f"
    ],
    "name:und_x_variant":[
        "Nez\u016bmand"
    ],
    "wof:name":"Nezamand",
    "wof:placetype":"locality"
},
  "geometry": {"coordinates":[60.06907,33.30011],"type":"Point"}
}