{
  "type": "Feature",
  "properties": {
    "gn:admin1_code":"1.0",
    "gn:asciiname":"Gayanjeh",
    "gn:country_code":"IR",
    "gn:dem":1676,
    "gn:feature_class":"P",
    "gn:feature_code":"PPL",
    "gn:name":"G\u0101yanjeh",
    "gn:population":0,
    "gn:timezone":"Asia/Tehran",
    "iso:country":"IR",
    "name:ara_x_preferred":[
        "\u063a\u0627\u064a\u0646\u062c\u0629"
    ],
    "name:aze_x_preferred":[
        "Qayanca"
    ],
    "name:fas_x_preferred":[
        "\u06af\u0627\u06cc\u0646\u062c\u0647"
    ],
    "name:fas_x_variant":[
        "G\u0101yanjeh"
    ],
    "name:msa_x_preferred":[
        "Gayanjeh"
    ],
    "wof:name":"Gayanjeh",
    "wof:placetype":"locality"
},
  "geometry": {"coordinates":[46.4224,36.5628],"type":"Point"}
}