{
  "type": "Feature",
  "properties": {
    "gn:admin1_code":"28",
    "gn:asciiname":"Ovardeh Khalvat",
    "gn:country_code":"IR",
    "gn:dem":1026,
    "gn:feature_class":"P",
    "gn:feature_code":"PPL",
    "gn:name":"Ovardeh Khalvat",
    "gn:population":0,
    "gn:timezone":"Asia/Tehran",
    "iso:country":"IR",
    "name:fas_x_preferred":[
        "\u0627\u0648\u0631\u062f\u0647 \u062e\u0644\u0648\u062a"
    ],
    "wof:name":"Ovardeh Khalvat",
    "wof:placetype":"locality"
},
  "geometry": {"coordinates":[51.3757,33.9479],"type":"Point"}
}