{
  "type": "Feature",
  "properties": {
    "gn:admin1_code":"8.0",
    "gn:asciiname":"Kaftar Khani",
    "gn:country_code":"IR",
    "gn:dem":1729,
    "gn:feature_class":"P",
    "gn:feature_code":"PPL",
    "gn:name":"Kaftar Kh\u0101n\u012b",
    "gn:population":0,
    "gn:timezone":"Asia/Tehran",
    "iso:country":"IR",
    "name:fas_x_preferred":[
        "Kab\u016btar Kh\u0101n"
    ],
    "name:fas_x_variant":[
        "\u06a9\u0628\u0648\u062a\u0631 \u062e\u0627\u0646",
        "\u06a9\u0641\u062a\u0631 \u062e\u0627\u0646\u06cc"
    ],
    "name:und_x_variant":[
        "\u06a9\u0628\u0648\u062a\u0631 \u062e\u0627\u0646",
        "Kaftar Kh\u0101n\u012b"
    ],
    "wof:name":"Kaftar Khani",
    "wof:placetype":"locality"
},
  "geometry": {"coordinates":[49.72164,36.90798],"type":"Point"}
}