{
  "type": "Feature",
  "properties": {
    "gn:admin1_code":"7",
    "gn:asciiname":"Eslamabad-e Sedaqat",
    "gn:country_code":"IR",
    "gn:dem":1590,
    "gn:feature_class":"P",
    "gn:feature_code":"PPL",
    "gn:name":"Esl\u0101m\u0101b\u0101d-e \u015eed\u0101qat",
    "gn:population":0,
    "gn:timezone":"Asia/Tehran",
    "iso:country":"IR",
    "name:fas_x_preferred":[
        "\u0627\u0633\u0644\u0627\u0645 \u0622\u0628\u0627\u062f \u0635\u062f\u0627\u0642\u062a"
    ],
    "name:fas_x_variant":[
        "Esl\u0101m\u0101b\u0101d-e \u015eed\u0101qat"
    ],
    "wof:name":"Eslamabad-e Sedaqat",
    "wof:placetype":"locality"
},
  "geometry": {"coordinates":[54.8754,28.956],"type":"Point"}
}