{
  "type": "Feature",
  "properties": {
    "gn:admin1_code":"29",
    "gn:asciiname":"Behjatabad",
    "gn:country_code":"IR",
    "gn:dem":1435,
    "gn:feature_class":"P",
    "gn:feature_code":"PPL",
    "gn:name":"Behjat\u0101b\u0101d",
    "gn:population":0,
    "gn:timezone":"Asia/Tehran",
    "iso:country":"IR",
    "name:fas_x_preferred":[
        "Behjat\u0101b\u0101d"
    ],
    "name:fas_x_variant":[
        "\u0628\u0647\u062c\u062a \u0622\u0628\u0627\u062f"
    ],
    "name:und_x_variant":[
        "\u0628\u0647\u062c\u062a \u0622\u0628\u0627\u062f"
    ],
    "wof:name":"Behjatabad",
    "wof:placetype":"locality"
},
  "geometry": {"coordinates":[55.72054,30.54176],"type":"Point"}
}