{
  "type": "Feature",
  "properties": {
    "gn:admin1_code":"15",
    "gn:asciiname":"Bavaj-e Abu ol Fares",
    "gn:country_code":"IR",
    "gn:dem":533,
    "gn:feature_class":"P",
    "gn:feature_code":"PPL",
    "gn:name":"B\u0101vaj-e Ab\u016b ol F\u0101res",
    "gn:population":0,
    "gn:timezone":"Asia/Tehran",
    "iso:country":"IR",
    "name:fas_x_preferred":[
        "B\u0101vaj"
    ],
    "name:fas_x_variant":[
        "\u0628\u0627\u0648\u062c",
        "\u0628\u0627\u0648\u062c \u0627\u0628\u0648\u0627\u0644\u0641\u0627\u0631\u0633"
    ],
    "name:und_x_variant":[
        "\u0628\u0627\u0648\u062c",
        "B\u0101vaj-e Ab\u016b ol F\u0101res"
    ],
    "wof:name":"Bavaj-e Abu ol Fares",
    "wof:placetype":"locality"
},
  "geometry": {"coordinates":[49.91349,31.14718],"type":"Point"}
}