{
  "type": "Feature",
  "properties": {
    "gn:admin1_code":"22",
    "gn:asciiname":"Qal`eh-ye Chah Kutah",
    "gn:country_code":"IR",
    "gn:dem":18,
    "gn:feature_class":"P",
    "gn:feature_code":"PPL",
    "gn:name":"Qal\u2018eh-ye Ch\u0101h K\u016bt\u0101h",
    "gn:population":0,
    "gn:timezone":"Asia/Tehran",
    "iso:country":"IR",
    "name:fas_x_preferred":[
        "\u0642\u064e\u0644\u0639\u0650\u06c0 \u0627\u064e\u062d\u0645\u064e\u062f\u062e\u0627\u0646"
    ],
    "name:fas_x_variant":[
        "\u0642\u0644\u0639\u0647 \u0686\u0627\u0647 \u06a9\u0648\u062a\u0627\u0647",
        "Qal\u2018eh-ye A\u1e29madkh\u0101n",
        "Qal\u2018eh-ye Ch\u0101h K\u016bt\u0101h"
    ],
    "wof:name":"Qal`eh-ye Chah Kutah",
    "wof:placetype":"locality"
},
  "geometry": {"coordinates":[51.1225,29.0555],"type":"Point"}
}