{
  "type": "Feature",
  "properties": {
    "gn:admin1_code":"4.0",
    "gn:asciiname":"Paskuh",
    "gn:country_code":"IR",
    "gn:dem":1264,
    "gn:feature_class":"P",
    "gn:feature_code":"PPL",
    "gn:name":"Pask\u016bh",
    "gn:population":0,
    "gn:timezone":"Asia/Tehran",
    "iso:country":"IR",
    "name:fas_x_preferred":[
        "\u067e\u0633\u06a9\u0648\u0647"
    ],
    "name:fas_x_variant":[
        "Pask\u016bh"
    ],
    "name:und_x_variant":[
        "Paskooh"
    ],
    "wof:name":"Paskuh",
    "wof:placetype":"locality"
},
  "geometry": {"coordinates":[61.63223000000001,27.55613],"type":"Point"}
}