{
  "type": "Feature",
  "properties": {
    "gn:admin1_code":"15",
    "gn:asciiname":"Dasht-e Lati",
    "gn:country_code":"IR",
    "gn:dem":381,
    "gn:feature_class":"P",
    "gn:feature_code":"PPLA2",
    "gn:name":"Dasht-e Lati",
    "gn:population":0,
    "gn:timezone":"Asia/Tehran",
    "iso:country":"IR",
    "name:fas_x_preferred":[
        "\u062f\u0634\u062a \u0644\u0627\u0644\u06cc"
    ],
    "name:fas_x_variant":[
        "Dasht-e L\u0101l\u012b",
        "\u0644\u0627\u0644\u06cc"
    ],
    "name:und_x_variant":[
        "L\u0101l\u012b Pel\u0101yen",
        "Dasht-e Lati",
        "L\u0101l\u012b"
    ],
    "wof:name":"Dasht-e Lati",
    "wof:placetype":"locality"
},
  "geometry": {"coordinates":[49.09324,32.32980999999999],"type":"Point"}
}