{
  "type": "Feature",
  "properties": {
    "gn:admin1_code":"15",
    "gn:asciiname":"Dasht-e Lati",
    "gn:country_code":"IR",
    "gn:dem":381,
    "gn:feature_class":"P",
    "gn:feature_code":"PPLA2",
    "gn:name":"Dasht-e Lati",
    "gn:population":0,
    "gn:timezone":"Asia/Tehran",
    "iso:country":"IR",
    "name:ara_x_preferred":[
        "\u0644\u0627\u0644\u064a"
    ],
    "name:aze_x_preferred":[
        "Lali"
    ],
    "name:ceb_x_preferred":[
        "Dasht-e Lati"
    ],
    "name:deu_x_preferred":[
        "Lali"
    ],
    "name:fas_x_preferred":[
        "\u062f\u0634\u062a \u0644\u0627\u0644\u06cc"
    ],
    "name:fas_x_variant":[
        "Dasht-e L\u0101l\u012b",
        "\u0644\u0627\u0644\u06cc"
    ],
    "name:ita_x_preferred":[
        "Lali"
    ],
    "name:mlg_x_preferred":[
        "Lali"
    ],
    "name:rus_x_preferred":[
        "\u041b\u0430\u043b\u0438"
    ],
    "name:swe_x_preferred":[
        "Dasht-e Lati"
    ],
    "name:tur_x_preferred":[
        "Lali"
    ],
    "name:und_x_variant":[
        "L\u0101l\u012b Pel\u0101yen",
        "L\u0101l\u012b"
    ],
    "name:urd_x_preferred":[
        "\u0644\u0627\u0644\u06cc"
    ],
    "wof:name":"Dasht-e Lati",
    "wof:placetype":"locality"
},
  "geometry": {"coordinates":[49.09324,32.32980999999999],"type":"Point"}
}