{
  "type": "Feature",
  "properties": {
    "gn:admin1_code":"15",
    "gn:asciiname":"Cham Khan-e Sofla",
    "gn:country_code":"IR",
    "gn:dem":36,
    "gn:feature_class":"P",
    "gn:feature_code":"PPL",
    "gn:name":"Cham Kh\u0101n-e Sofl\u00e1",
    "gn:population":0,
    "gn:timezone":"Asia/Tehran",
    "iso:country":"IR",
    "name:ceb_x_preferred":[
        "Chamtar Kh\u0101n-e Sofl\u00e1"
    ],
    "name:fas_x_preferred":[
        "\u0686\u0645\u062a\u0631 \u062e\u0627\u0646 \u0633\u0641\u0644\u06cc"
    ],
    "name:fas_x_variant":[
        "Kab\u016bt\u0101r Kh\u0101n-e Sofl\u0101",
        "Chamtar Kh\u0101n-e P\u0101\u2019\u012bn",
        "Chamtar Kh\u0101n-e Sofl\u00e1",
        "\u0686\u0645 \u062e\u0627\u0646 \u0633\u0641\u0644\u06cc",
        "\u0686\u0645\u062a\u0631\u062e\u0627\u0646 \u0633\u0641\u0644\u06cc"
    ],
    "name:swe_x_preferred":[
        "Chamtar Kh\u0101n-e Sofl\u00e1"
    ],
    "name:und_x_variant":[
        "Khalaf-e Nab\u012b",
        "Cham Kh\u0101n-e Sofl\u00e1"
    ],
    "wof:name":"Cham Khan-e Sofla",
    "wof:placetype":"locality"
},
  "geometry": {"coordinates":[48.77912,31.95765],"type":"Point"}
}