{
  "type": "Feature",
  "properties": {
    "gn:admin1_code":"9",
    "gn:asciiname":"Khorramabad",
    "gn:country_code":"IR",
    "gn:dem":1725,
    "gn:feature_class":"P",
    "gn:feature_code":"PPL",
    "gn:name":"Khorram\u0101b\u0101d",
    "gn:population":0,
    "gn:timezone":"Asia/Tehran",
    "iso:country":"IR",
    "name:fas_x_preferred":[
        "\u0642\u0644\u0639\u0647 \u0641\u062a\u0627\u062d\u06cc\u0647"
    ],
    "name:fas_x_variant":[
        "Qal\u2018eh-ye Fatt\u0101\u1e29\u012byeh",
        "\u062e\u0631\u0645 \u0622\u0628\u0627\u062f",
        "\u0645\u06cc\u0631\u0641\u062a\u0651\u0627\u062d"
    ],
    "name:und_x_variant":[
        "Ghal\u2018eh Fattahiyeh",
        "Qal\u2018eh-ye Fatt\u0101\u1e29\u012b",
        "Qal\u2018eh Fatt\u0101\u1e29\u012byeh",
        "Qal\u2018eh-ye Fat\u0101\u1e29\u012b",
        "Khorram\u0101b\u0101d",
        "M\u012brfatt\u0101\u1e29"
    ],
    "wof:name":"Khorramabad",
    "wof:placetype":"locality"
},
  "geometry": {"coordinates":[48.7832,34.3083],"type":"Point"}
}