{
  "type": "Feature",
  "properties": {
    "gn:admin1_code":"26.0",
    "gn:asciiname":"Mahalleh-ye Lowran",
    "gn:country_code":"IR",
    "gn:dem":1717,
    "gn:feature_class":"P",
    "gn:feature_code":"PPL",
    "gn:name":"Ma\u1e29alleh-ye Lowr\u0101n",
    "gn:population":0,
    "gn:timezone":"Asia/Tehran",
    "iso:country":"IR",
    "name:fas_x_preferred":[
        "\u0644\u0648\u0631\u0627\u0646"
    ],
    "name:fas_x_variant":[
        "Lowr\u0101n",
        "\u0645\u062d\u0644\u0647 \u0644\u0648\u0631\u0627\u0646"
    ],
    "name:und_x_variant":[
        "Ma\u1e29alleh-ye Lowr\u0101n"
    ],
    "wof:name":"Mahalleh-ye Lowran",
    "wof:placetype":"locality"
},
  "geometry": {"coordinates":[51.87494,35.73348],"type":"Point"}
}