{
  "type": "Feature",
  "properties": {
    "gn:admin1_code":"29",
    "gn:asciiname":"Sabz Pushan",
    "gn:country_code":"IR",
    "gn:dem":525,
    "gn:feature_class":"P",
    "gn:feature_code":"PPL",
    "gn:name":"Sabz P\u016bsh\u0101n",
    "gn:population":0,
    "gn:timezone":"Asia/Tehran",
    "iso:country":"IR",
    "name:fas_x_preferred":[
        "\u0633\u0628\u0632 \u067e\u0648\u0634\u0627\u0646"
    ],
    "name:fas_x_variant":[
        "Sabz P\u016bsh\u0101n"
    ],
    "wof:name":"Sabz Pushan",
    "wof:placetype":"locality"
},
  "geometry": {"coordinates":[58.49968000000001,27.95901],"type":"Point"}
}