{
  "type": "Feature",
  "properties": {
    "gn:admin1_code":"40",
    "gn:asciiname":"Kuy-e Feyziyeh",
    "gn:country_code":"IR",
    "gn:dem":1237,
    "gn:feature_class":"P",
    "gn:feature_code":"PPL",
    "gn:name":"K\u016by-e Fey\u1e95\u012byeh",
    "gn:population":0,
    "gn:timezone":"Asia/Tehran",
    "iso:country":"IR",
    "name:fas_x_preferred":[
        "\u0628\u0627\u063a\u0650 \u0646\u0627\u0635\u0650\u0631"
    ],
    "name:fas_x_variant":[
        "B\u0101gh-e N\u0101\u015fer",
        "K\u016by-e Fey\u1e95\u012byeh",
        "\u06a9\u0648\u064a \u0641\u064a\u0636\u064a\u0647"
    ],
    "name:und_x_variant":[
        "B\u0101gh-i-N\u0101sir"
    ],
    "wof:name":"Kuy-e Feyziyeh",
    "wof:placetype":"locality"
},
  "geometry": {"coordinates":[54.36666999999999,31.85],"type":"Point"}
}