{
  "type": "Feature",
  "properties": {
    "gn:admin1_code":"8.0",
    "gn:asciiname":"Varam Heram",
    "gn:country_code":"IR",
    "gn:dem":1484,
    "gn:feature_class":"P",
    "gn:feature_code":"PPL",
    "gn:name":"Varam \u1e28eram",
    "gn:population":0,
    "gn:timezone":"Asia/Tehran",
    "iso:country":"IR",
    "name:fas_x_preferred":[
        "\u0648\u0631\u0645 \u062d\u0631\u0645"
    ],
    "name:und_x_variant":[
        "Varam \u1e28eram"
    ],
    "wof:name":"Varam Heram",
    "wof:placetype":"locality"
},
  "geometry": {"coordinates":[48.72602,37.78354],"type":"Point"}
}