{
  "type": "Feature",
  "properties": {
    "gn:admin1_code":"29",
    "gn:asciiname":"Ahuan-e Pa'in",
    "gn:country_code":"IR",
    "gn:dem":422,
    "gn:feature_class":"P",
    "gn:feature_code":"PPL",
    "gn:name":"\u0100h\u016b\u0101n-e P\u0101\u2019\u012bn",
    "gn:population":0,
    "gn:timezone":"Asia/Tehran",
    "iso:country":"IR",
    "name:fas_x_preferred":[
        "\u0622\u0647\u0648\u0627\u0646 \u067e\u0627\u0626\u06cc\u0646"
    ],
    "name:fas_x_variant":[
        "\u0100h\u016b\u0101n-e P\u0101\u2019\u012bn"
    ],
    "wof:name":"Ahuan-e Pa'in",
    "wof:placetype":"locality"
},
  "geometry": {"coordinates":[57.9304,27.6836],"type":"Point"}
}