{
  "type": "Feature",
  "properties": {
    "gn:admin1_code":"15",
    "gn:asciiname":"Gazkar",
    "gn:country_code":"IR",
    "gn:dem":28,
    "gn:feature_class":"P",
    "gn:feature_code":"PPL",
    "gn:name":"Gazk\u0101r",
    "gn:population":0,
    "gn:timezone":"Asia/Tehran",
    "iso:country":"IR",
    "name:fas_x_preferred":[
        "Gazk\u0101r"
    ],
    "wof:name":"Gazkar",
    "wof:placetype":"locality"
},
  "geometry": {"coordinates":[48.63111,31.56944],"type":"Point"}
}