{
  "type": "Feature",
  "properties": {
    "gn:admin1_code":"4.0",
    "gn:asciiname":"Sargezi",
    "gn:country_code":"IR",
    "gn:dem":481,
    "gn:feature_class":"P",
    "gn:feature_code":"PPL",
    "gn:name":"Sargez\u012b",
    "gn:population":0,
    "gn:timezone":"Asia/Tehran",
    "iso:country":"IR",
    "name:fas_x_preferred":[
        "\u0633\u0631\u06af\u0632\u06cc"
    ],
    "name:fas_x_variant":[
        "Sargez\u012b",
        "\u0633\u0631\u06af\u0644\u0632\u0627\u064a\u06cc"
    ],
    "name:und_x_variant":[
        "Sargolz\u0101\u2019\u012b"
    ],
    "wof:name":"Sargezi",
    "wof:placetype":"locality"
},
  "geometry": {"coordinates":[61.6716,31.1429],"type":"Point"}
}