{
  "type": "Feature",
  "properties": {
    "gn:admin1_code":"16",
    "gn:asciiname":"Sheybanju",
    "gn:country_code":"IR",
    "gn:dem":1579,
    "gn:feature_class":"P",
    "gn:feature_code":"PPL",
    "gn:name":"Sheyb\u0101nj\u016b",
    "gn:population":0,
    "gn:timezone":"Asia/Tehran",
    "iso:country":"IR",
    "name:fas_x_preferred":[
        "\u0634\u064a\u067e\u0627\u0646\u0650\u062c\u0648"
    ],
    "name:fas_x_variant":[
        "\u0634\u064a\u067e\u0627\u0646\u062c\u0648",
        "\u0634\u064a\u067e\u0627\u0646\u064e\u062c\u0627\u0648",
        "\u0634\u06cc\u0628\u0627\u0646\u062c\u0648",
        "Sh\u012bp\u0101nej\u016b",
        "Sheyb\u0101nj\u016b"
    ],
    "name:und_x_variant":[
        "Sh\u012bp\u0101naj\u0101v",
        "Shipanjoo",
        "Sh\u012bp\u0101nj\u016b"
    ],
    "wof:name":"Sheybanju",
    "wof:placetype":"locality"
},
  "geometry": {"coordinates":[46.2578,35.9569],"type":"Point"}
}