{
  "type": "Feature",
  "properties": {
    "gn:admin1_code":"42",
    "gn:asciiname":"Tarababad",
    "gn:country_code":"IR",
    "gn:dem":1200,
    "gn:feature_class":"P",
    "gn:feature_code":"PPL",
    "gn:name":"\u0162arab\u0101b\u0101d",
    "gn:population":0,
    "gn:timezone":"Asia/Tehran",
    "iso:country":"IR",
    "name:fas_x_preferred":[
        "\u0637\u0631\u0628 \u0622\u0628\u0627\u062f"
    ],
    "name:fas_x_variant":[
        "Torb\u0101b\u0101d",
        "\u0162arab\u0101b\u0101d"
    ],
    "wof:name":"Tarababad",
    "wof:placetype":"locality"
},
  "geometry": {"coordinates":[58.84988000000001,36.1759],"type":"Point"}
}