{
  "type": "Feature",
  "properties": {
    "gn:admin1_code":"33",
    "gn:asciiname":"Sovich-e Bala",
    "gn:country_code":"IR",
    "gn:dem":1534,
    "gn:feature_class":"P",
    "gn:feature_code":"PPL",
    "gn:name":"Sov\u012bch-e B\u0101l\u0101",
    "gn:population":0,
    "gn:timezone":"Asia/Tehran",
    "iso:country":"IR",
    "name:fas_x_preferred":[
        "\u0633\u0648\u06cc\u0686 \u0628\u0627\u0644\u0627"
    ],
    "name:fas_x_variant":[
        "Sov\u012bnj-e \u2018Oly\u0101",
        "Sov\u012bch-e B\u0101l\u0101",
        "\u0633\u0648\u0646\u062c \u0639\u0644\u06cc\u0627"
    ],
    "name:msa_x_preferred":[
        "Sovinj-e Olya"
    ],
    "wof:name":"Sovich-e Bala",
    "wof:placetype":"locality"
},
  "geometry": {"coordinates":[47.2881,37.5347],"type":"Point"}
}