{
  "type": "Feature",
  "properties": {
    "gn:admin1_code":"25",
    "gn:asciiname":"Biarjomand",
    "gn:country_code":"IR",
    "gn:dem":1091,
    "gn:feature_class":"P",
    "gn:feature_code":"PPL",
    "gn:name":"B\u012b\u0101rjomand",
    "gn:population":0,
    "gn:timezone":"Asia/Tehran",
    "iso:country":"IR",
    "name:fas_x_preferred":[
        "\u0628\u0650\u064a\u0627\u0631"
    ],
    "name:fas_x_variant":[
        "\u0628\u064a\u0651\u0627\u0631\u062c\u064f\u0645\u064e\u0646\u062f",
        "\u0628\u064a\u0627\u0631\u062c\u0645\u064e\u0646\u062f",
        "B\u012b\u0101rjomand",
        "Bey\u0101rjomand",
        "\u0628\u06cc\u0627\u0631\u062c\u0645\u0646\u062f",
        "B\u012b\u0101rjmand",
        "Bey\u0101r",
        "B\u012by\u0101rjomand"
    ],
    "name:und_x_variant":[
        "B\u012by\u0101rjomand",
        "B\u012b\u0101rjmand",
        "Bey\u0101r"
    ],
    "wof:name":"Biarjomand",
    "wof:placetype":"locality"
},
  "geometry": {"coordinates":[55.8097,36.08056],"type":"Point"}
}