{
  "type": "Feature",
  "properties": {
    "gn:admin1_code":"10.0",
    "gn:asciiname":"Qalibeh",
    "gn:country_code":"IR",
    "gn:dem":434,
    "gn:elevation":"0.0",
    "gn:feature_class":"P",
    "gn:feature_code":"PPL",
    "gn:name":"Q\u0101l\u012bbeh",
    "gn:population":0,
    "gn:timezone":"Asia/Tehran",
    "iso:country":"IR",
    "name:fas_x_preferred":[
        "\u0642\u0627\u0644\u064a\u0645\u0650\u0647"
    ],
    "name:fas_x_variant":[
        "\u0642\u0627\u0644\u06cc\u0628\u0647",
        "Q\u0101l\u012bmeh",
        "Q\u0101l\u012bbeh"
    ],
    "wof:name":"Qalibeh",
    "wof:placetype":"locality"
},
  "geometry": {"coordinates":[46.2771,33.3744],"type":"Point"}
}