{
  "type": "Feature",
  "properties": {
    "gn:admin1_code":"4",
    "gn:asciiname":"Kharestan-e Bala",
    "gn:country_code":"IR",
    "gn:dem":2190,
    "gn:feature_class":"P",
    "gn:feature_code":"PPL",
    "gn:name":"Kh\u0101rest\u0101n-e B\u0101l\u0101",
    "gn:population":0,
    "gn:timezone":"Asia/Tehran",
    "iso:country":"IR",
    "name:fas_x_preferred":[
        "\u062e\u0627\u0631\u0633\u062a\u0627\u0646 \u0628\u0627\u0644\u0627"
    ],
    "name:fas_x_variant":[
        "Kh\u0101rest\u0101n-e B\u0101l\u0101"
    ],
    "wof:name":"Kharestan-e Bala",
    "wof:placetype":"locality"
},
  "geometry": {"coordinates":[60.9363,28.6934],"type":"Point"}
}