{
  "type": "Feature",
  "properties": {
    "gn:admin1_code":"7",
    "gn:asciiname":"Gur-e Espid",
    "gn:cc2":"IR",
    "gn:country_code":"IR",
    "gn:dem":1078,
    "gn:feature_class":"P",
    "gn:feature_code":"PPL",
    "gn:name":"G\u016br-e Esp\u012bd",
    "gn:population":0,
    "gn:timezone":"Asia/Tehran",
    "iso:country":"IR",
    "name:fas_x_preferred":[
        "G\u016br-e Esp\u012bd"
    ],
    "name:fas_x_variant":[
        "\u06af\u0648\u0631 \u0627\u0633\u067e\u06cc\u062f"
    ],
    "name:msa_x_preferred":[
        "Gur-e Espid"
    ],
    "name:und_x_variant":[
        "G\u016br Esp\u012bd",
        "G\u016br-e Sef\u012bd"
    ],
    "wof:name":"Gur-e Espid",
    "wof:placetype":"locality"
},
  "geometry": {"coordinates":[51.33083,30.14917],"type":"Point"}
}