{
  "type": "Feature",
  "properties": {
    "gn:admin1_code":"7",
    "gn:asciiname":"Jow Karan",
    "gn:country_code":"IR",
    "gn:dem":1567,
    "gn:feature_class":"P",
    "gn:feature_code":"PPL",
    "gn:name":"Jow K\u0101r\u0101n",
    "gn:population":0,
    "gn:timezone":"Asia/Tehran",
    "iso:country":"IR",
    "name:fas_x_preferred":[
        "Jow K\u0101r\u0101n"
    ],
    "name:fas_x_variant":[
        "Tall-e Jow K\u0101r\u0101n",
        "\u062a\u0644 \u062c\u0648 \u06a9\u0627\u0631\u0627\u0646",
        "\u062c\u0648 \u06a9\u0627\u0631\u0627\u0646",
        "\u0628\u0646\u0647 \u062c\u0648 \u06a9\u0627\u0631\u0627\u0646"
    ],
    "name:und_x_variant":[
        "Boneh Jow K\u0101r\u0101n"
    ],
    "wof:name":"Jow Karan",
    "wof:placetype":"locality"
},
  "geometry": {"coordinates":[53.69675,29.647],"type":"Point"}
}