{
  "type": "Feature",
  "properties": {
    "gn:admin1_code":"23",
    "gn:asciiname":"Ayazabad",
    "gn:country_code":"IR",
    "gn:dem":1679,
    "gn:feature_class":"P",
    "gn:feature_code":"PPL",
    "gn:name":"Ay\u0101z\u0101b\u0101d",
    "gn:population":0,
    "gn:timezone":"Asia/Tehran",
    "iso:country":"IR",
    "name:fas_x_preferred":[
        "\u0627\u06cc\u0627\u0632 \u0622\u0628\u0627 \u06a9\u0627\u0633\u06cc\u0627\u0646"
    ],
    "name:fas_x_variant":[
        "\u0627\u06cc\u0627\u0632 \u0622\u0628\u0627\u062f",
        "\u0627\u06cc\u0627\u0632\u0622\u0628\u0627\u062f"
    ],
    "name:und_x_variant":[
        "Ay\u0101z\u0101b\u0101 K\u0101s\u012b\u0101n",
        "K\u0101s\u012b\u0101n-e Ay\u0101z\u0101b\u0101d",
        "Ay\u0101z\u0101b\u0101d"
    ],
    "wof:name":"Ayazabad",
    "wof:placetype":"locality"
},
  "geometry": {"coordinates":[48.6192,33.6468],"type":"Point"}
}