{
  "type": "Feature",
  "properties": {
    "gn:admin1_code":"8",
    "gn:asciiname":"Kiuleh Khuni",
    "gn:country_code":"IR",
    "gn:dem":1914,
    "gn:feature_class":"P",
    "gn:feature_code":"PPL",
    "gn:name":"K\u012b\u016bleh Kh\u016bn\u012b",
    "gn:population":0,
    "gn:timezone":"Asia/Tehran",
    "iso:country":"IR",
    "name:fas_x_preferred":[
        "\u06a9\u06cc\u0648\u0644\u0647 \u062e\u0648\u0646\u06cc"
    ],
    "name:fas_x_variant":[
        "K\u012b\u016bleh Kh\u016bn\u012b"
    ],
    "wof:name":"Kiuleh Khuni",
    "wof:placetype":"locality"
},
  "geometry": {"coordinates":[48.9245,37.2514],"type":"Point"}
}