{
  "type": "Feature",
  "properties": {
    "gn:admin1_code":"8",
    "gn:asciiname":"Haviq",
    "gn:country_code":"IR",
    "gn:dem":10,
    "gn:feature_class":"P",
    "gn:feature_code":"PPL",
    "gn:name":"\u1e28av\u012bq",
    "gn:population":0,
    "gn:timezone":"Asia/Tehran",
    "iso:country":"IR",
    "name:fas_x_preferred":[
        "\u062d\u0648\u06cc\u0642"
    ],
    "name:fas_x_variant":[
        "\u012ashak \u0100gh\u0101s\u012b-ye \u1e28av\u012bq",
        "\u1e28av\u012bq"
    ],
    "wof:name":"Haviq",
    "wof:placetype":"locality"
},
  "geometry": {"coordinates":[48.8831,38.1502],"type":"Point"}
}