{
  "type": "Feature",
  "properties": {
    "gn:admin1_code":"22",
    "gn:asciiname":"Bonud",
    "gn:country_code":"IR",
    "gn:dem":9,
    "gn:feature_class":"P",
    "gn:feature_code":"PPL",
    "gn:name":"Bon\u016bd",
    "gn:population":0,
    "gn:timezone":"Asia/Tehran",
    "iso:country":"IR",
    "name:ceb_x_preferred":[
        "Bon\u016bd"
    ],
    "name:fas_x_preferred":[
        "\u0628\u0646\u0648\u062f"
    ],
    "name:fas_x_variant":[
        "\u0628\u064e\u0646\u064f\u0651\u062f",
        "Bon\u016bd"
    ],
    "name:msa_x_preferred":[
        "Bonud"
    ],
    "name:swe_x_preferred":[
        "Bon\u016bd"
    ],
    "name:und_x_variant":[
        "Banood",
        "Bun\u016bt",
        "Ban\u016bd"
    ],
    "wof:name":"Bonud",
    "wof:placetype":"locality"
},
  "geometry": {"coordinates":[52.7263,27.3468],"type":"Point"}
}