{
  "type": "Feature",
  "properties": {
    "gn:admin1_code":"23",
    "gn:asciiname":"Dush Sorkh",
    "gn:country_code":"IR",
    "gn:dem":1219,
    "gn:feature_class":"P",
    "gn:feature_code":"PPL",
    "gn:name":"D\u016bsh Sorkh",
    "gn:population":0,
    "gn:timezone":"Asia/Tehran",
    "iso:country":"IR",
    "name:fas_x_preferred":[
        "\u062f\u0648\u0634 \u0633\u064f\u0631\u062e"
    ],
    "wof:name":"Dush Sorkh",
    "wof:placetype":"locality"
},
  "geometry": {"coordinates":[48.55,33.18333],"type":"Point"}
}