{
  "type": "Feature",
  "properties": {
    "gn:admin1_code":"32",
    "gn:asciiname":"Qeshlaq-e Hajji `Avaz",
    "gn:country_code":"IR",
    "gn:dem":38,
    "gn:feature_class":"P",
    "gn:feature_code":"PPL",
    "gn:name":"Qeshl\u0101q-e \u1e28\u0101jj\u012b \u2018Ava\u1e95",
    "gn:population":0,
    "gn:timezone":"Asia/Tehran",
    "iso:country":"IR",
    "name:fas_x_preferred":[
        "\u0642\u0634\u0644\u0627\u0642 \u062d\u0627\u062c\u06cc \u0639\u0648\u0636"
    ],
    "name:fas_x_variant":[
        "Qeshl\u0101q-e \u1e28\u0101jj\u012b \u2018Ava\u1e95"
    ],
    "wof:name":"Qeshlaq-e Hajji `Avaz",
    "wof:placetype":"locality"
},
  "geometry": {"coordinates":[48.1058,39.5749],"type":"Point"}
}