{
  "type": "Feature",
  "properties": {
    "gn:admin1_code":"35.0",
    "gn:asciiname":"`Abdollahabad",
    "gn:country_code":"IR",
    "gn:dem":65,
    "gn:feature_class":"P",
    "gn:feature_code":"PPL",
    "gn:name":"\u2018Abdoll\u0101h\u0101b\u0101d",
    "gn:population":0,
    "gn:timezone":"Asia/Tehran",
    "iso:country":"IR",
    "name:fas_x_preferred":[
        "\u0639\u0628\u062f\u0627\u0644\u0644\u0647 \u0622\u0628\u0627\u062f"
    ],
    "name:fas_x_variant":[
        "\u2018Abdoll\u0101h\u0101b\u0101d"
    ],
    "wof:name":"`Abdollahabad",
    "wof:placetype":"locality"
},
  "geometry": {"coordinates":[52.12746,36.502],"type":"Point"}
}