{
  "type": "Feature",
  "properties": {
    "gn:admin1_code":"25.0",
    "gn:asciiname":"Satveh",
    "gn:country_code":"IR",
    "gn:dem":926,
    "gn:feature_class":"P",
    "gn:feature_code":"PPL",
    "gn:name":"Sa\u0163veh",
    "gn:population":0,
    "gn:timezone":"Asia/Tehran",
    "iso:country":"IR",
    "name:fas_x_preferred":[
        "\u0633\u0627\u0646\u0650\u0647"
    ],
    "name:fas_x_variant":[
        "S\u0101neh",
        "\u0633\u0637\u0648\u0647",
        "\u0633\u064e\u062f\u0641\u0650\u0647",
        "\u0633\u064e\u062a\u0641\u064e\u0631",
        "\u0633\u064e\u062a\u0648\u064e"
    ],
    "name:und_x_variant":[
        "Sa\u0163veh",
        "Satva",
        "Satfar",
        "Sadfeh"
    ],
    "wof:name":"Satveh",
    "wof:placetype":"locality"
},
  "geometry": {"coordinates":[54.69071,35.27165],"type":"Point"}
}