{
  "type": "Feature",
  "properties": {
    "gn:admin1_code":"28.0",
    "gn:asciiname":"Mazra`eh-ye Gavart",
    "gn:country_code":"IR",
    "gn:dem":1544,
    "gn:feature_class":"P",
    "gn:feature_code":"PPL",
    "gn:name":"Mazra\u2018eh-ye Gavart",
    "gn:population":0,
    "gn:timezone":"Asia/Tehran",
    "iso:country":"IR",
    "name:fas_x_preferred":[
        "Mazra\u2018eh-ye Gavart"
    ],
    "name:fas_x_variant":[
        "\u0645\u0632\u0631\u0639\u0647 \u06af\u0648\u0631\u062a",
        "\u0627\u0633\u0644\u0627\u0645 \u0622\u0628\u0627\u062f \u0642\u0647\u0627\u0628"
    ],
    "name:und_x_variant":[
        "Esl\u0101m\u0101b\u0101d Qah\u0101b"
    ],
    "wof:name":"Mazra`eh-ye Gavart",
    "wof:placetype":"locality"
},
  "geometry": {"coordinates":[51.84679000000001,32.65569],"type":"Point"}
}