{
  "type": "Feature",
  "properties": {
    "gn:admin1_code":"7",
    "gn:asciiname":"Damcheh",
    "gn:country_code":"IR",
    "gn:dem":824,
    "gn:feature_class":"P",
    "gn:feature_code":"PPL",
    "gn:name":"D\u0101mcheh",
    "gn:population":0,
    "gn:timezone":"Asia/Tehran",
    "iso:country":"IR",
    "name:fas_x_preferred":[
        "\u062f\u0627\u0645\u0686\u0647"
    ],
    "name:fas_x_variant":[
        "D\u0101mcheh"
    ],
    "wof:name":"Damcheh",
    "wof:placetype":"locality"
},
  "geometry": {"coordinates":[53.94197,28.14947],"type":"Point"}
}