{
  "type": "Feature",
  "properties": {
    "gn:admin1_code":"35.0",
    "gn:asciiname":"Mohammad Sheykh ol Eslami",
    "gn:country_code":"IR",
    "gn:dem":107,
    "gn:feature_class":"P",
    "gn:feature_code":"PPL",
    "gn:name":"Mo\u1e29ammad Sheykh ol Esl\u0101m\u012b",
    "gn:population":0,
    "gn:timezone":"Asia/Tehran",
    "iso:country":"IR",
    "name:fas_x_preferred":[
        "Mo\u1e29ammad Sheykh ol Esl\u0101m\u012b"
    ],
    "wof:name":"Mohammad Sheykh ol Eslami",
    "wof:placetype":"locality"
},
  "geometry": {"coordinates":[51.41667,36.63333],"type":"Point"}
}