{
  "type": "Feature",
  "properties": {
    "gn:admin1_code":"4.0",
    "gn:asciiname":"Bazar-e `Omar",
    "gn:country_code":"IR",
    "gn:dem":16,
    "gn:feature_class":"P",
    "gn:feature_code":"PPL",
    "gn:name":"B\u0101z\u0101r-e \u2018Omar",
    "gn:population":0,
    "gn:timezone":"Asia/Tehran",
    "iso:country":"IR",
    "name:fas_x_preferred":[
        "B\u0101z\u0101r-e \u2018Omar"
    ],
    "name:fas_x_variant":[
        "\u0628\u0627\u0632\u0627\u0631 \u0639\u0645\u0631"
    ],
    "name:und_x_variant":[
        "\u0628\u0627\u0632\u0627\u0631 \u0639\u0645\u0631"
    ],
    "wof:name":"Bazar-e `Omar",
    "wof:placetype":"locality"
},
  "geometry": {"coordinates":[61.24921,25.41514],"type":"Point"}
}