{
  "type": "Feature",
  "properties": {
    "gn:admin1_code":"8",
    "gn:asciiname":"Tataf Rud",
    "gn:country_code":"IR",
    "gn:dem":96,
    "gn:feature_class":"P",
    "gn:feature_code":"PPLL",
    "gn:name":"Ta\u0163af R\u016bd",
    "gn:population":0,
    "gn:timezone":"Asia/Tehran",
    "iso:country":"IR",
    "name:fas_x_preferred":[
        "\u062a\u0637\u0641 \u0631\u0648\u062f"
    ],
    "name:fas_x_variant":[
        "Ta\u0163af R\u016bd-e \u0100l\u012b\u0101n",
        "Ta\u0163af R\u016bd"
    ],
    "name:und_x_variant":[
        "Tatavrut",
        "Ta\u0163af R\u016bd"
    ],
    "wof:name":"Tataf Rud",
    "wof:placetype":"locality"
},
  "geometry": {"coordinates":[49.1745,37.2467],"type":"Point"}
}