{
  "type": "Feature",
  "properties": {
    "gn:admin1_code":"7",
    "gn:asciiname":"Javaliqan",
    "gn:country_code":"IR",
    "gn:dem":837,
    "gn:feature_class":"P",
    "gn:feature_code":"PPL",
    "gn:name":"Jav\u0101l\u012bq\u0101n",
    "gn:population":0,
    "gn:timezone":"Asia/Tehran",
    "iso:country":"IR",
    "name:fas_x_preferred":[
        "Jav\u0101l\u012bq\u0101n"
    ],
    "name:fas_x_variant":[
        "\u062c\u0648\u0627\u0644\u06cc\u0642\u0627\u0646"
    ],
    "name:msa_x_preferred":[
        "Javaliqan"
    ],
    "name:und_x_variant":[
        "\u062c\u0648\u0627\u0644\u06cc\u0642\u0627\u0646"
    ],
    "name:urd_x_preferred":[
        "\u062c\u0648\u0627\u0644\u064a\u0642\u0627\u0646"
    ],
    "wof:name":"Javaliqan",
    "wof:placetype":"locality"
},
  "geometry": {"coordinates":[51.98867,29.27127],"type":"Point"}
}