{
  "type": "Feature",
  "properties": {
    "gn:admin1_code":"33",
    "gn:asciiname":"Gol Tappeh",
    "gn:country_code":"IR",
    "gn:dem":2053,
    "gn:feature_class":"P",
    "gn:feature_code":"PPL",
    "gn:name":"Gol Tappeh",
    "gn:population":0,
    "gn:timezone":"Asia/Tehran",
    "iso:country":"IR",
    "name:ceb_x_preferred":[
        "Gol Tappeh"
    ],
    "name:fas_x_preferred":[
        "\u06af\u0644 \u062a\u067e\u0651\u0647"
    ],
    "name:swe_x_preferred":[
        "Gol Tappeh"
    ],
    "wof:name":"Gol Tappeh",
    "wof:placetype":"locality"
},
  "geometry": {"coordinates":[46.7532,37.13800000000001],"type":"Point"}
}