{
  "type": "Feature",
  "properties": {
    "gn:admin1_code":"15",
    "gn:asciiname":"Mian Rag",
    "gn:country_code":"IR",
    "gn:dem":1042,
    "gn:feature_class":"P",
    "gn:feature_code":"PPL",
    "gn:name":"M\u012b\u0101n Rag",
    "gn:population":0,
    "gn:timezone":"Asia/Tehran",
    "iso:country":"IR",
    "name:fas_x_preferred":[
        "M\u012b\u0101n Rag"
    ],
    "wof:name":"Mian Rag",
    "wof:placetype":"locality"
},
  "geometry": {"coordinates":[50.035,31.88167],"type":"Point"}
}