{
  "type": "Feature",
  "properties": {
    "gn:admin1_code":"11",
    "gn:asciiname":"Kah Shuru",
    "gn:country_code":"IR",
    "gn:dem":1788,
    "gn:feature_class":"P",
    "gn:feature_code":"PPL",
    "gn:name":"K\u0101h Sh\u016br\u016b",
    "gn:population":0,
    "gn:timezone":"Asia/Tehran",
    "iso:country":"IR",
    "name:fas_x_preferred":[
        "\u06a9\u0627\u0647 \u0634\u0648\u0631\u0648"
    ],
    "name:fas_x_variant":[
        "K\u0101h Sh\u016br\u016b"
    ],
    "wof:name":"Kah Shuru",
    "wof:placetype":"locality"
},
  "geometry": {"coordinates":[56.8004,28.1057],"type":"Point"}
}