{
  "type": "Feature",
  "properties": {
    "gn:admin1_code":"11",
    "gn:asciiname":"Tomb-e Baluchi",
    "gn:country_code":"IR",
    "gn:dem":646,
    "gn:feature_class":"P",
    "gn:feature_code":"PPL",
    "gn:name":"Tomb-e Bal\u016bch\u012b",
    "gn:population":0,
    "gn:timezone":"Asia/Tehran",
    "iso:country":"IR",
    "name:fas_x_preferred":[
        "\u062a\u064f\u0645\u0628\u0650 \u0628\u064e\u0644\u0648\u0686\u06cc"
    ],
    "name:fas_x_variant":[
        "Tomb-e Bal\u016bch\u012b"
    ],
    "wof:name":"Tomb-e Baluchi",
    "wof:placetype":"locality"
},
  "geometry": {"coordinates":[56.33056,27.76361],"type":"Point"}
}