{
  "type": "Feature",
  "properties": {
    "gn:admin1_code":"29",
    "gn:asciiname":"Shahri",
    "gn:country_code":"IR",
    "gn:dem":928,
    "gn:feature_class":"P",
    "gn:feature_code":"PPL",
    "gn:name":"Shahr\u012b",
    "gn:population":0,
    "gn:timezone":"Asia/Tehran",
    "iso:country":"IR",
    "name:fas_x_preferred":[
        "\u0634\u0647\u0631\u06cc"
    ],
    "name:fas_x_variant":[
        "Shahr\u012b"
    ],
    "wof:name":"Shahri",
    "wof:placetype":"locality"
},
  "geometry": {"coordinates":[58.55824000000001,26.6221],"type":"Point"}
}