{
  "type": "Feature",
  "properties": {
    "gn:admin1_code":"8",
    "gn:asciiname":"Khanevaneh",
    "gn:country_code":"IR",
    "gn:dem":126,
    "gn:feature_class":"P",
    "gn:feature_code":"PPL",
    "gn:name":"Kh\u0101nev\u0101neh",
    "gn:population":0,
    "gn:timezone":"Asia/Tehran",
    "iso:country":"IR",
    "name:fas_x_preferred":[
        "\u062e\u0627\u0646\u0648\u0627\u0646\u0647"
    ],
    "name:fas_x_variant":[
        "Kh\u0101nev\u0101neh"
    ],
    "name:und_x_variant":[
        "Kh\u0101nev\u0101neh"
    ],
    "wof:name":"Khanevaneh",
    "wof:placetype":"locality"
},
  "geometry": {"coordinates":[49.20744000000001,37.20779],"type":"Point"}
}