{
  "type": "Feature",
  "properties": {
    "gn:admin1_code":"16.0",
    "gn:asciiname":"Savarian",
    "gn:country_code":"IR",
    "gn:dem":1309,
    "gn:elevation":"0.0",
    "gn:feature_class":"P",
    "gn:feature_code":"PPL",
    "gn:name":"Sav\u0101r\u012b\u0101n",
    "gn:population":0,
    "gn:timezone":"Asia/Tehran",
    "iso:country":"IR",
    "name:fas_x_preferred":[
        "\u0633\u0648\u0627\u0631\u06cc\u0627\u0646"
    ],
    "name:fas_x_variant":[
        "Sav\u0101r\u012b\u0101n"
    ],
    "name:und_x_variant":[
        "H\u0101n\u012b Qorb\u0101n\u012b",
        "K\u0101n\u012b Qorb\u0101n\u012b"
    ],
    "wof:name":"Savarian",
    "wof:placetype":"locality"
},
  "geometry": {"coordinates":[46.8905,35.1299],"type":"Point"}
}