{
  "type": "Feature",
  "properties": {
    "gn:admin1_code":"13",
    "gn:asciiname":"Nesar Direh",
    "gn:country_code":"IR",
    "gn:dem":681,
    "gn:feature_class":"P",
    "gn:feature_code":"PPL",
    "gn:name":"Nes\u0101r D\u012breh",
    "gn:population":0,
    "gn:timezone":"Asia/Tehran",
    "iso:country":"IR",
    "name:fas_x_preferred":[
        "\u0646\u0633\u0627\u0631 \u062f\u06cc\u0631\u0647"
    ],
    "name:fas_x_variant":[
        "Nes\u0101reh D\u012breh",
        "Nes\u0101r D\u012breh"
    ],
    "name:und_x_variant":[
        "D\u0113hra",
        "Nes\u0101r"
    ],
    "wof:name":"Nesar Direh",
    "wof:placetype":"locality"
},
  "geometry": {"coordinates":[45.86927,34.32337],"type":"Point"}
}