{
  "type": "Feature",
  "properties": {
    "gn:admin1_code":"5",
    "gn:asciiname":"Shitab",
    "gn:country_code":"IR",
    "gn:dem":1052,
    "gn:feature_class":"P",
    "gn:feature_code":"PPL",
    "gn:name":"Sh\u012bt\u0101b",
    "gn:population":0,
    "gn:timezone":"Asia/Tehran",
    "iso:country":"IR",
    "name:ceb_x_preferred":[
        "Shet\u0101b"
    ],
    "name:fas_x_preferred":[
        "\u0634\u06cc\u062a\u0627\u0628"
    ],
    "name:fas_x_variant":[
        "Sh\u012bt\u0101b"
    ],
    "name:swe_x_preferred":[
        "Shet\u0101b"
    ],
    "wof:name":"Shitab",
    "wof:placetype":"locality"
},
  "geometry": {"coordinates":[50.425,30.9986],"type":"Point"}
}