{
  "type": "Feature",
  "properties": {
    "gn:admin1_code":"28.0",
    "gn:asciiname":"Ormak",
    "gn:country_code":"IR",
    "gn:dem":1837,
    "gn:feature_class":"P",
    "gn:feature_code":"PPL",
    "gn:name":"Ormak",
    "gn:population":0,
    "gn:timezone":"Asia/Tehran",
    "iso:country":"IR",
    "name:fas_x_preferred":[
        "\u0622\u0631\u0645\u064e\u0643"
    ],
    "name:fas_x_variant":[
        "\u0627\u0631\u0645\u06a9",
        "\u0100rmak"
    ],
    "wof:name":"Ormak",
    "wof:placetype":"locality"
},
  "geometry": {"coordinates":[51.0607,34.1105],"type":"Point"}
}