{
  "type": "Feature",
  "properties": {
    "gn:admin1_code":"23",
    "gn:asciiname":"Sorkheh Lizeh",
    "gn:country_code":"IR",
    "gn:dem":1234,
    "gn:feature_class":"P",
    "gn:feature_code":"PPL",
    "gn:name":"Sorkheh L\u012bzeh",
    "gn:population":0,
    "gn:timezone":"Asia/Tehran",
    "iso:country":"IR",
    "name:fas_x_preferred":[
        "Sorkheh L\u012bzeh"
    ],
    "name:fas_x_variant":[
        "\u0633\u0631\u062e\u0647 \u0644\u06cc\u0632\u0647"
    ],
    "name:und_x_variant":[
        "\u0633\u0631\u062e\u0647 \u0644\u06cc\u0632\u0647",
        "Sorkheh Yazar",
        "Sorkheh Yez\u0101r",
        "Sorkheh L\u012bzeh Meleh Sh\u0101b\u0101n\u0101n",
        "Sorkheh Neyz\u0101r"
    ],
    "wof:name":"Sorkheh Lizeh",
    "wof:placetype":"locality"
},
  "geometry": {"coordinates":[48.20638,33.49722],"type":"Point"}
}