{
  "type": "Feature",
  "properties": {
    "gn:admin1_code":"5",
    "gn:asciiname":"Kandi Khowri",
    "gn:country_code":"IR",
    "gn:dem":1782,
    "gn:feature_class":"P",
    "gn:feature_code":"PPL",
    "gn:name":"Kand\u012b Khowr\u012b",
    "gn:population":0,
    "gn:timezone":"Asia/Tehran",
    "iso:country":"IR",
    "name:fas_x_preferred":[
        "\u0643\u064e\u0646\u062f\u06cc \u062e\u064f\u0648\u0631\u06cc"
    ],
    "name:und_x_variant":[
        "Kand\u012b Khowr\u012b"
    ],
    "wof:name":"Kandi Khowri",
    "wof:placetype":"locality"
},
  "geometry": {"coordinates":[51.35,30.88333],"type":"Point"}
}