{
  "type": "Feature",
  "properties": {
    "gn:admin1_code":"1",
    "gn:asciiname":"Hesar-e Soporghan",
    "gn:country_code":"IR",
    "gn:dem":1279,
    "gn:feature_class":"P",
    "gn:feature_code":"PPL",
    "gn:name":"\u1e28e\u015f\u0101r-e Soporgh\u0101n",
    "gn:population":0,
    "gn:timezone":"Asia/Tehran",
    "iso:country":"IR",
    "name:azb_x_preferred":[
        "\u062d\u06cc\u0635\u0627\u0631\u0633\u067e\u0648\u0631\u063a\u0627\u0646"
    ],
    "name:aze_x_preferred":[
        "Hisar-i S\u00fcp\u00fcrg\u0259n"
    ],
    "name:ceb_x_preferred":[
        "\u1e28e\u015f\u0101r-e Soporgh\u0101n"
    ],
    "name:fas_x_preferred":[
        "\u062d\u0635\u0627\u0631 \u0633\u067e\u0631\u063a\u0627\u0646"
    ],
    "name:fas_x_variant":[
        "\u062d\u0650\u0635\u0627\u0631\u0650 \u0633\u064f\u067e\u0648\u0631\u063a\u0627\u0646",
        "\u1e28e\u015f\u0101r-e Sop\u016brgh\u0101n",
        "\u1e28e\u015f\u0101r-e Soporgh\u0101n",
        "\u062d\u0635\u0627\u0631 \u0633\u067e\u0648\u0631\u063a\u0627\u0646"
    ],
    "name:msa_x_preferred":[
        "Hesar-e Sopurghan"
    ],
    "name:swe_x_preferred":[
        "\u1e28e\u015f\u0101r-e Soporgh\u0101n"
    ],
    "wof:name":"Hesar-e Soporghan",
    "wof:placetype":"locality"
},
  "geometry": {"coordinates":[45.1941,37.7407],"type":"Point"}
}