{
  "type": "Feature",
  "properties": {
    "gn:admin1_code":"1.0",
    "gn:asciiname":"Qarah Khezer",
    "gn:country_code":"IR",
    "gn:dem":1522,
    "gn:elevation":"0.0",
    "gn:feature_class":"P",
    "gn:feature_code":"PPL",
    "gn:name":"Qarah Khe\u1e95er",
    "gn:population":0,
    "gn:timezone":"Asia/Tehran",
    "iso:country":"IR",
    "name:fas_x_preferred":[
        "\u0642\u0631\u0647 \u062e\u0636\u0631"
    ],
    "name:fas_x_variant":[
        "Qareh Khe\u1e95r",
        "Qarah Khe\u1e95er"
    ],
    "name:und_x_variant":[
        "Qarah Qhezer"
    ],
    "wof:name":"Qarah Khezer",
    "wof:placetype":"locality"
},
  "geometry": {"coordinates":[45.2748,36.6458],"type":"Point"}
}