{
  "type": "Feature",
  "properties": {
    "gn:admin1_code":"11",
    "gn:asciiname":"Baba `Alem-e Pa'in",
    "gn:country_code":"IR",
    "gn:dem":10,
    "gn:feature_class":"P",
    "gn:feature_code":"PPL",
    "gn:name":"B\u0101b\u0101 \u2018\u0100lem-e P\u0101\u2019\u012bn",
    "gn:population":0,
    "gn:timezone":"Asia/Tehran",
    "iso:country":"IR",
    "name:fas_x_preferred":[
        "\u0628\u0627\u0628\u0627 \u0639\u0627\u0644\u0650\u0645\u0650 \u067e\u0627\u0626\u064a\u0646"
    ],
    "name:fas_x_variant":[
        "B\u0101b\u0101 \u2018\u0100lem-e P\u0101\u2019\u012bn"
    ],
    "wof:name":"Baba `Alem-e Pa'in",
    "wof:placetype":"locality"
},
  "geometry": {"coordinates":[56.62222,27.27389],"type":"Point"}
}