{
  "type": "Feature",
  "properties": {
    "gn:admin1_code":"37.0",
    "gn:asciiname":"Sib Chal",
    "gn:country_code":"IR",
    "gn:dem":1454,
    "gn:feature_class":"P",
    "gn:feature_code":"PPL",
    "gn:name":"S\u012bb Ch\u0101l",
    "gn:population":0,
    "gn:timezone":"Asia/Tehran",
    "iso:country":"IR",
    "name:ceb_x_preferred":[
        "S\u012bb Ch\u0101l"
    ],
    "name:fas_x_preferred":[
        "\u0633\u064a\u0628 \u0686\u0627\u0644"
    ],
    "name:fas_x_variant":[
        "S\u012bb Ch\u0101l",
        "\u0633\u06cc\u0628\u200c\u0686\u0627\u0644"
    ],
    "name:msa_x_preferred":[
        "Sib Chal"
    ],
    "name:swe_x_preferred":[
        "S\u012bb Ch\u0101l"
    ],
    "wof:name":"Sib Chal",
    "wof:placetype":"locality"
},
  "geometry": {"coordinates":[55.53485,37.00559000000001],"type":"Point"}
}