{
  "type": "Feature",
  "properties": {
    "gn:admin1_code":"29.0",
    "gn:asciiname":"Mazra`eh-ye Shir Aghuz",
    "gn:country_code":"IR",
    "gn:dem":2549,
    "gn:feature_class":"P",
    "gn:feature_code":"PPLF",
    "gn:name":"Mazra\u2018eh-ye Sh\u012br \u0100gh\u016bz",
    "gn:population":0,
    "gn:timezone":"Asia/Tehran",
    "iso:country":"IR",
    "name:fas_x_preferred":[
        "Gard\u012bn-e \u2018Oly\u0101"
    ],
    "name:fas_x_variant":[
        "\u06af\u0631\u062f\u06cc\u0646 \u0639\u0644\u06cc\u0627",
        "\u0645\u0632\u0631\u0639\u0647 \u0634\u064a\u0631 \u0622\u063a\u0648\u0632"
    ],
    "name:und_x_variant":[
        "Mazra\u2018eh-ye Sh\u012br \u0100gh\u016bz"
    ],
    "wof:name":"Mazra`eh-ye Shir Aghuz",
    "wof:placetype":"locality"
},
  "geometry": {"coordinates":[57.36128000000001,29.2351],"type":"Point"}
}