{
  "type": "Feature",
  "properties": {
    "gn:admin1_code":"41",
    "gn:asciiname":"Kalateh-ye Fulad-e Bala",
    "gn:country_code":"IR",
    "gn:dem":1957,
    "gn:feature_class":"P",
    "gn:feature_code":"PPL",
    "gn:name":"Kal\u0101teh-ye F\u016bl\u0101d-e B\u0101l\u0101",
    "gn:population":0,
    "gn:timezone":"Asia/Tehran",
    "iso:country":"IR",
    "name:fas_x_preferred":[
        "F\u016bl\u0101d\u0101b\u0101d-e B\u0101l\u0101"
    ],
    "name:fas_x_variant":[
        "\u06a9\u0644\u0627\u062a\u0647 \u0641\u0648\u0644\u0627\u062f \u0628\u0627\u0644\u0627",
        "\u0641\u0648\u0644\u0627\u062f \u0622\u0628\u0627\u062f \u0628\u0627\u0644\u0627",
        "\u0641\u0648\u0644\u0627\u062f \u0622\u0628\u0627\u062f"
    ],
    "name:und_x_variant":[
        "F\u016bl\u0101d",
        "F\u016bl\u0101d\u0101b\u0101d-e \u2018Oly\u0101",
        "Foolid Abad",
        "F\u016bl\u0101d\u0101b\u0101d",
        "F\u016bl\u0101d\u0101b\u0101d-e Sofl\u00e1",
        "Kal\u0101teh-ye F\u016bl\u0101d-e B\u0101l\u0101"
    ],
    "wof:name":"Kalateh-ye Fulad-e Bala",
    "wof:placetype":"locality"
},
  "geometry": {"coordinates":[59.39355,32.23477],"type":"Point"}
}