{
  "type": "Feature",
  "properties": {
    "gn:admin1_code":"23",
    "gn:asciiname":"Hayyeh",
    "gn:country_code":"IR",
    "gn:dem":1461,
    "gn:feature_class":"P",
    "gn:feature_code":"PPL",
    "gn:name":"\u1e28ayyeh",
    "gn:population":0,
    "gn:timezone":"Asia/Tehran",
    "iso:country":"IR",
    "name:ara_x_preferred":[
        "\u062d\u064a\u0629"
    ],
    "name:fas_x_preferred":[
        "\u0647\u064e\u064a\u0650\u0647"
    ],
    "name:fas_x_variant":[
        "\u0647\u064e\u064a\u064e\u0647",
        "\u062d\u06cc\u0647",
        "\u1e28ayyeh"
    ],
    "name:und_x_variant":[
        "Hayah",
        "Hayeh"
    ],
    "wof:name":"Hayyeh",
    "wof:placetype":"locality"
},
  "geometry": {"coordinates":[48.99158,33.24631],"type":"Point"}
}