{
  "type": "Feature",
  "properties": {
    "gn:admin1_code":"4",
    "gn:asciiname":"Sirin Kur",
    "gn:country_code":"IR",
    "gn:dem":301,
    "gn:feature_class":"P",
    "gn:feature_code":"PPL",
    "gn:name":"S\u012br\u012bn K\u016br",
    "gn:population":0,
    "gn:timezone":"Asia/Tehran",
    "iso:country":"IR",
    "name:fas_x_preferred":[
        "\u0633\u06cc\u0631\u06cc\u0646 \u06a9\u0648\u0631"
    ],
    "name:fas_x_variant":[
        "S\u012br\u012bn K\u016br"
    ],
    "wof:name":"Sirin Kur",
    "wof:placetype":"locality"
},
  "geometry": {"coordinates":[61.56358,26.16264],"type":"Point"}
}