{
  "type": "Feature",
  "properties": {
    "gn:admin1_code":"29.0",
    "gn:asciiname":"Kamachabad",
    "gn:country_code":"IR",
    "gn:dem":2281,
    "gn:feature_class":"P",
    "gn:feature_code":"PPLF",
    "gn:name":"Kam\u0101ch\u0101b\u0101d",
    "gn:population":0,
    "gn:timezone":"Asia/Tehran",
    "iso:country":"IR",
    "name:fas_x_preferred":[
        "\u06a9\u0645\u0627\u0686 \u0622\u0628\u0627\u062f"
    ],
    "name:und_x_variant":[
        "Kam\u0101ch\u0101b\u0101d"
    ],
    "wof:name":"Kamachabad",
    "wof:placetype":"locality"
},
  "geometry": {"coordinates":[56.85667,28.57583],"type":"Point"}
}