{
  "type": "Feature",
  "properties": {
    "gn:admin1_code":"41",
    "gn:asciiname":"Janabad",
    "gn:country_code":"IR",
    "gn:dem":1704,
    "gn:feature_class":"P",
    "gn:feature_code":"PPL",
    "gn:name":"Jan\u0101b\u0101d",
    "gn:population":0,
    "gn:timezone":"Asia/Tehran",
    "iso:country":"IR",
    "name:fas_x_preferred":[
        "Jannat\u0101b\u0101d"
    ],
    "name:fas_x_variant":[
        "\u062c\u0646 \u0622\u0628\u0627\u062f",
        "\u0627\u0633\u0644\u0627\u0645 \u0622\u0628\u0627\u062f",
        "\u062c\u0646\u062a \u0622\u0628\u0627\u062f"
    ],
    "name:und_x_variant":[
        "Jan\u0101b\u0101d",
        "Esl\u0101m\u0101b\u0101d"
    ],
    "wof:name":"Janabad",
    "wof:placetype":"locality"
},
  "geometry": {"coordinates":[59.9945,32.54931],"type":"Point"}
}