{
  "type": "Feature",
  "properties": {
    "gn:admin1_code":"4.0",
    "gn:asciiname":"Tagazuk",
    "gn:country_code":"IR",
    "gn:dem":1079,
    "gn:feature_class":"P",
    "gn:feature_code":"PPL",
    "gn:name":"\u0162\u0101gaz\u016bk",
    "gn:population":0,
    "gn:timezone":"Asia/Tehran",
    "iso:country":"IR",
    "name:fas_x_preferred":[
        "\u0162\u0101gaz\u016bk-e P\u0101\u2019\u012bn"
    ],
    "name:fas_x_variant":[
        "\u0637\u0627\u06af\u0632\u0648\u06a9"
    ],
    "name:und_x_variant":[
        "\u0162\u0101gaz\u016bk"
    ],
    "wof:name":"Tagazuk",
    "wof:placetype":"locality"
},
  "geometry": {"coordinates":[61.42859,28.88333],"type":"Point"}
}