{
  "type": "Feature",
  "properties": {
    "gn:admin1_code":"3",
    "gn:asciiname":"Mishan-e Pa'in",
    "gn:country_code":"IR",
    "gn:dem":1827,
    "gn:feature_class":"P",
    "gn:feature_code":"PPL",
    "gn:name":"M\u012bsh\u0101n-e P\u0101\u2019\u012bn",
    "gn:population":0,
    "gn:timezone":"Asia/Tehran",
    "iso:country":"IR",
    "name:fas_x_preferred":[
        "\u0645\u064a\u0634\u0627\u0646 \u0633\u064f\u0641\u0644\u064e\u0649"
    ],
    "name:fas_x_variant":[
        "M\u012bsh\u0101n-e P\u0101\u2019\u012bn",
        "\u0645\u064a\u0634\u0627\u0646\u0650 \u0633\u064f\u0641\u0644\u064e\u0649",
        "\u0645\u064a\u0634\u0627\u0646 \u067e\u0627\u0626\u064a\u0646",
        "\u0645\u064a\u0634\u0627\u0646"
    ],
    "name:und_x_variant":[
        "M\u012bsh\u0101n-e Sofl\u00e1",
        "M\u012bsh\u0101n Sofl\u00e1",
        "M\u012bsh\u0101n",
        "\u0645\u064a\u0634\u0627\u0646 \u067e\u0627\u0626\u064a\u0646",
        "\u0645\u064a\u0634\u0627\u0646"
    ],
    "wof:name":"Mishan-e Pa'in",
    "wof:placetype":"locality"
},
  "geometry": {"coordinates":[51.22143,31.3061],"type":"Point"}
}