{
  "type": "Feature",
  "properties": {
    "gn:admin1_code":"29",
    "gn:asciiname":"Chah-e Pudeh",
    "gn:country_code":"IR",
    "gn:dem":815,
    "gn:feature_class":"P",
    "gn:feature_code":"PPLL",
    "gn:name":"Ch\u0101h-e P\u016bdeh",
    "gn:population":0,
    "gn:timezone":"Asia/Tehran",
    "iso:country":"IR",
    "name:fas_x_preferred":[
        "D\u016bl\u0101b"
    ],
    "name:fas_x_variant":[
        "\u0686\u0627\u0647 \u067e\u0648\u062f\u0647"
    ],
    "name:und_x_variant":[
        "Ch\u0101h-e P\u016bdeh"
    ],
    "wof:name":"Chah-e Pudeh",
    "wof:placetype":"locality"
},
  "geometry": {"coordinates":[59.00887,28.3281],"type":"Point"}
}