{
  "type": "Feature",
  "properties": {
    "gn:admin1_code":"33",
    "gn:asciiname":"Vali Beyklu",
    "gn:country_code":"IR",
    "gn:dem":403,
    "gn:feature_class":"P",
    "gn:feature_code":"PPL",
    "gn:name":"Val\u012b Beykl\u016b",
    "gn:population":0,
    "gn:timezone":"Asia/Tehran",
    "iso:country":"IR",
    "name:fas_x_preferred":[
        "\u0648\u064e\u0644\u06cc \u0628\u0650\u064a\u06af\u0644\u0648"
    ],
    "name:fas_x_variant":[
        "\u0648\u0644\u06cc \u0628\u064a\u06a9\u0644\u0648",
        "Val\u012b Beygl\u016b",
        "Val\u012b Beykl\u016b"
    ],
    "wof:name":"Vali Beyklu",
    "wof:placetype":"locality"
},
  "geometry": {"coordinates":[47.5186,39.0268],"type":"Point"}
}