{
  "type": "Feature",
  "properties": {
    "gn:admin1_code":"33",
    "gn:asciiname":"Zaklik-e `Olya",
    "gn:country_code":"IR",
    "gn:dem":1781,
    "gn:elevation":"0.0",
    "gn:feature_class":"P",
    "gn:feature_code":"PPL",
    "gn:name":"Zakl\u012bk-e \u2018Oly\u0101",
    "gn:population":0,
    "gn:timezone":"Asia/Tehran",
    "iso:country":"IR",
    "name:fas_x_preferred":[
        "\u0632\u06a9\u0644\u06a9 \u0628\u0627\u0644\u0627"
    ],
    "name:fas_x_variant":[
        "Zagl\u012bk-e \u2018Oly\u0101",
        "Zakl\u012bk-e B\u0101l\u0101",
        "Zaklak-e B\u0101l\u0101",
        "\u0632\u06a9\u0644\u06cc\u06a9 \u0639\u0644\u06cc\u0627",
        "\u0632\u06af\u0644\u06cc\u06a9 \u0639\u0644\u06cc\u0627"
    ],
    "name:und_x_variant":[
        "Zakl\u012bk-e \u2018Oly\u0101"
    ],
    "wof:name":"Zaklik-e `Olya",
    "wof:placetype":"locality"
},
  "geometry": {"coordinates":[47.1132,38.5854],"type":"Point"}
}