{
  "type": "Feature",
  "properties": {
    "gn:admin1_code":"8",
    "gn:asciiname":"Bandbon-e Beneksar",
    "gn:country_code":"IR",
    "gn:dem":89,
    "gn:feature_class":"P",
    "gn:feature_code":"PPL",
    "gn:name":"Bandbon-e Beneksar",
    "gn:population":0,
    "gn:timezone":"Asia/Tehran",
    "iso:country":"IR",
    "name:fas_x_preferred":[
        "\u0628\u0646\u062f\u0628\u0646 \u0628\u0646\u06a9\u0633\u0631"
    ],
    "name:und_x_variant":[
        "\u0628\u0646\u062f\u0628\u0646 \u0628\u0646\u06a9\u0633\u0631"
    ],
    "wof:name":"Bandbon-e Beneksar",
    "wof:placetype":"locality"
},
  "geometry": {"coordinates":[50.30806,37.009],"type":"Point"}
}