{
  "type": "Feature",
  "properties": {
    "gn:admin1_code":"15",
    "gn:asciiname":"Bar Aftab-e Zafari",
    "gn:country_code":"IR",
    "gn:dem":1252,
    "gn:feature_class":"P",
    "gn:feature_code":"PPL",
    "gn:name":"Bar \u0100ft\u0101b-e Z\u0327afar\u012b",
    "gn:population":0,
    "gn:timezone":"Asia/Tehran",
    "iso:country":"IR",
    "name:azb_x_preferred":[
        "\u0628\u0631\u0627\u0641\u062a\u0627\u0628 \u0638\u0641\u0631\u06cc(\u0627\u06cc\u0630\u0647)"
    ],
    "name:ceb_x_preferred":[
        "Bar \u0100ft\u0101b-e Z\u0327afar\u012b"
    ],
    "name:fas_x_preferred":[
        "Bar \u0100ft\u0101b-e Z\u0327afar\u012b"
    ],
    "name:fas_x_variant":[
        "\u0628\u0631\u0622\u0641\u062a\u0627\u0628 \u0638\u0641\u0631\u06cc"
    ],
    "name:swe_x_preferred":[
        "Bar \u0100ft\u0101b-e Z\u0327afar\u012b"
    ],
    "wof:name":"Bar Aftab-e Zafari",
    "wof:placetype":"locality"
},
  "geometry": {"coordinates":[50.32028,31.56444],"type":"Point"}
}