{
  "type": "Feature",
  "properties": {
    "gn:admin1_code":"23",
    "gn:asciiname":"Jamshidabad",
    "gn:country_code":"IR",
    "gn:dem":1659,
    "gn:feature_class":"P",
    "gn:feature_code":"PPL",
    "gn:name":"Jamsh\u012bd\u0101b\u0101d",
    "gn:population":0,
    "gn:timezone":"Asia/Tehran",
    "iso:country":"IR",
    "name:fas_x_preferred":[
        "\u0639\u0628\u0651\u0627\u0633 \u0622\u0628\u0627\u062f"
    ],
    "name:fas_x_variant":[
        "\u2018Abb\u0101s\u0101b\u0101d",
        "\u062c\u0645\u0634\u06cc\u062f \u0622\u0628\u0627\u062f",
        "\u062c\u0645\u0634\u06cc\u062f\u0622\u0628\u0627\u062f"
    ],
    "name:und_x_variant":[
        "Jamsh\u012bd\u0101b\u0101d"
    ],
    "wof:name":"Jamshidabad",
    "wof:placetype":"locality"
},
  "geometry": {"coordinates":[48.3069,33.8645],"type":"Point"}
}