{
  "type": "Feature",
  "properties": {
    "gn:admin1_code":"29",
    "gn:asciiname":"Chah Qal`eh",
    "gn:country_code":"IR",
    "gn:dem":1717,
    "gn:feature_class":"P",
    "gn:feature_code":"PPLF",
    "gn:name":"Ch\u0101h Qal\u2018eh",
    "gn:population":0,
    "gn:timezone":"Asia/Tehran",
    "iso:country":"IR",
    "name:fas_x_preferred":[
        "\u0686\u0627\u0647 \u0642\u0644\u0639\u0647"
    ],
    "name:fas_x_variant":[
        "Ch\u0101h Qal\u2018eh"
    ],
    "wof:name":"Chah Qal`eh",
    "wof:placetype":"locality"
},
  "geometry": {"coordinates":[55.7401,29.1393],"type":"Point"}
}