{
  "type": "Feature",
  "properties": {
    "gn:admin1_code":"29",
    "gn:asciiname":"Darsinuyeh",
    "gn:country_code":"IR",
    "gn:dem":2129,
    "gn:feature_class":"P",
    "gn:feature_code":"PPL",
    "gn:name":"D\u0101rs\u012bn\u016byeh",
    "gn:population":0,
    "gn:timezone":"Asia/Tehran",
    "iso:country":"IR",
    "name:fas_x_preferred":[
        "Darsinoo\u2019iyeh"
    ],
    "name:fas_x_variant":[
        "\u062f\u0627\u0631\u0633\u06cc\u0646\u0648\u06cc\u0647",
        "D\u0101rs\u012bn\u016byeh",
        "Dars\u012bnu",
        "\u062f\u0627\u0631\u0633\u06cc\u0646\u0648\u06cc\u06cc\u0647"
    ],
    "name:und_x_variant":[
        "Dars\u012bnu"
    ],
    "wof:name":"Darsinuyeh",
    "wof:placetype":"locality"
},
  "geometry": {"coordinates":[57.23639,30.38307],"type":"Point"}
}