{
  "type": "Feature",
  "properties": {
    "gn:admin1_code":"8",
    "gn:asciiname":"Anladi",
    "gn:country_code":"IR",
    "gn:dem":1361,
    "gn:feature_class":"P",
    "gn:feature_code":"PPL",
    "gn:name":"Anlad\u012b",
    "gn:population":0,
    "gn:timezone":"Asia/Tehran",
    "iso:country":"IR",
    "name:fas_x_preferred":[
        "\u0627\u0644\u0644\u0651\u0647 \u062f\u0647"
    ],
    "name:fas_x_variant":[
        "All\u0101h Deh",
        "\u0627\u0646\u0644\u062f\u06cc"
    ],
    "name:und_x_variant":[
        "Allyady",
        "Alladi",
        "Anlad\u012b"
    ],
    "wof:name":"Anladi",
    "wof:placetype":"locality"
},
  "geometry": {"coordinates":[48.73341,37.58055],"type":"Point"}
}