{
  "type": "Feature",
  "properties": {
    "gn:admin1_code":"4.0",
    "gn:asciiname":"Malek Guri",
    "gn:country_code":"IR",
    "gn:dem":1268,
    "gn:feature_class":"P",
    "gn:feature_code":"PPL",
    "gn:name":"Malek G\u016br\u012b",
    "gn:population":0,
    "gn:timezone":"Asia/Tehran",
    "iso:country":"IR",
    "name:fas_x_preferred":[
        "Malek G\u016br\u012b"
    ],
    "wof:name":"Malek Guri",
    "wof:placetype":"locality"
},
  "geometry": {"coordinates":[60.67111,30.61556],"type":"Point"}
}