{
  "type": "Feature",
  "properties": {
    "gn:admin1_code":"11.0",
    "gn:asciiname":"Zank Zala",
    "gn:country_code":"IR",
    "gn:dem":1136,
    "gn:feature_class":"P",
    "gn:feature_code":"PPL",
    "gn:name":"Zank Zal\u0101",
    "gn:population":0,
    "gn:timezone":"Asia/Tehran",
    "iso:country":"IR",
    "name:fas_x_preferred":[
        "\u0632\u0646\u06a9 \u0632\u0644\u0627"
    ],
    "name:und_x_variant":[
        "Zank Zal\u0101"
    ],
    "wof:name":"Zank Zala",
    "wof:placetype":"locality"
},
  "geometry": {"coordinates":[56.29024,28.05788],"type":"Point"}
}