{
  "type": "Feature",
  "properties": {
    "gn:admin1_code":"39.0",
    "gn:asciiname":"Seyyedabad",
    "gn:country_code":"IR",
    "gn:dem":818,
    "gn:feature_class":"P",
    "gn:feature_code":"PPL",
    "gn:name":"Seyyed\u0101b\u0101d",
    "gn:population":0,
    "gn:timezone":"Asia/Tehran",
    "iso:country":"IR",
    "name:aze_x_preferred":[
        "Seyidabad"
    ],
    "name:fas_x_preferred":[
        "\u0633\u064a\u062f \u0622\u0628\u0627\u062f"
    ],
    "name:fas_x_variant":[
        "Seyyed\u0101b\u0101d",
        "\u0635\u064a\u062f \u0622\u0628\u0627\u062f",
        "\u0633\u06cc\u062f\u0622\u0628\u0627\u062f"
    ],
    "name:und_x_variant":[
        "\u015eeyd\u0101b\u0101d"
    ],
    "wof:name":"Seyyedabad",
    "wof:placetype":"locality"
},
  "geometry": {"coordinates":[51.2075,34.847],"type":"Point"}
}