{
  "type": "Feature",
  "properties": {
    "gn:admin1_code":"37.0",
    "gn:asciiname":"Fazeli",
    "gn:country_code":"IR",
    "gn:dem":26,
    "gn:feature_class":"P",
    "gn:feature_code":"PPL",
    "gn:name":"F\u0101\u1e95el\u012b",
    "gn:population":0,
    "gn:timezone":"Asia/Tehran",
    "iso:country":"IR",
    "name:fas_x_preferred":[
        "\u0641\u0627\u0636\u0644\u06cc"
    ],
    "name:und_x_variant":[
        "F\u0101\u1e95el\u012b"
    ],
    "wof:name":"Fazeli",
    "wof:placetype":"locality"
},
  "geometry": {"coordinates":[54.88686,37.07593],"type":"Point"}
}