{
  "type": "Feature",
  "properties": {
    "gn:admin1_code":"35.0",
    "gn:asciiname":"Pishkuh",
    "gn:country_code":"IR",
    "gn:dem":2333,
    "gn:feature_class":"P",
    "gn:feature_code":"PPLL",
    "gn:name":"P\u012bshk\u016bh",
    "gn:population":0,
    "gn:timezone":"Asia/Tehran",
    "iso:country":"IR",
    "name:fas_x_preferred":[
        "\u067e\u064a\u0634\u06a9\u0648\u0647"
    ],
    "name:und_x_variant":[
        "P\u012bshk\u016bh"
    ],
    "wof:name":"Pishkuh",
    "wof:placetype":"locality"
},
  "geometry": {"coordinates":[52.27396,35.90383],"type":"Point"}
}