{
  "type": "Feature",
  "properties": {
    "gn:admin1_code":"1",
    "gn:asciiname":"Duz Aghol",
    "gn:country_code":"IR",
    "gn:dem":1190,
    "gn:feature_class":"P",
    "gn:feature_code":"PPL",
    "gn:name":"D\u016bz \u0100ghol",
    "gn:population":0,
    "gn:timezone":"Asia/Tehran",
    "iso:country":"IR",
    "name:azb_x_preferred":[
        "\u062f\u0648\u0632\u0622\u063a\u0648\u0644"
    ],
    "name:aze_x_preferred":[
        "D\u00fcza\u011f\u0131l\u0131"
    ],
    "name:ceb_x_preferred":[
        "D\u016bz \u0100ghol"
    ],
    "name:fas_x_preferred":[
        "\u062f\u064f\u0651\u0632 \u0627\u064e\u063a\u0644\u06cc"
    ],
    "name:fas_x_variant":[
        "\u062f\u0648\u0632 \u0622\u063a\u0644",
        "\u062f\u0648\u0632 \u0622\u063a\u064f\u0644",
        "\u062f\u0648\u0632 \u0622\u063a\u0650\u0644",
        "D\u016bz \u0100ghol",
        "\u062f\u0648\u0632 \u0622\u063a\u0644\u06cc",
        "\u062f\u0648\u0632\u0622\u063a\u0644"
    ],
    "name:kur_x_preferred":[
        "Dozaqol"
    ],
    "name:msa_x_preferred":[
        "Duz Aghol"
    ],
    "name:swe_x_preferred":[
        "D\u016bz \u0100ghol"
    ],
    "name:und_x_variant":[
        "D\u016bz \u0100ghl\u012b",
        "D\u016bz \u0100ghel",
        "Duzagal",
        "Dooz Aghl\u012b"
    ],
    "wof:name":"Duz Aghol",
    "wof:placetype":"locality"
},
  "geometry": {"coordinates":[44.9407,39.0717],"type":"Point"}
}