{
  "type": "Feature",
  "properties": {
    "gn:admin1_code":"4",
    "gn:asciiname":"Afzalabad-e Bala",
    "gn:country_code":"IR",
    "gn:dem":1282,
    "gn:feature_class":"P",
    "gn:feature_code":"PPL",
    "gn:name":"Af\u1e95al\u0101b\u0101d-e B\u0101l\u0101",
    "gn:population":0,
    "gn:timezone":"Asia/Tehran",
    "iso:country":"IR",
    "name:fas_x_preferred":[
        "\u0627\u0641\u0636\u0644 \u0622\u0628\u0627\u062f \u0628\u0627\u0644\u0627"
    ],
    "name:fas_x_variant":[
        "Af\u1e95al\u0101b\u0101d-e B\u0101l\u0101"
    ],
    "wof:name":"Afzalabad-e Bala",
    "wof:placetype":"locality"
},
  "geometry": {"coordinates":[61.7372,27.0405],"type":"Point"}
}