{
  "type": "Feature",
  "properties": {
    "gn:admin1_code":"38",
    "gn:asciiname":"Shahidabad",
    "gn:country_code":"IR",
    "gn:dem":2059,
    "gn:feature_class":"P",
    "gn:feature_code":"PPL",
    "gn:name":"Shah\u012bd\u0101b\u0101d",
    "gn:population":0,
    "gn:timezone":"Asia/Tehran",
    "iso:country":"IR",
    "name:fas_x_preferred":[
        "\u0634\u0647\u064a\u062f \u0622\u0628\u0627\u062f"
    ],
    "name:fas_x_variant":[
        "\u06af\u064e\u0648\u064a\u064e\u0644",
        "\u06af\u0627\u0648\u064a\u0643",
        "\u06af\u064e\u0648\u0650\u064a\u0643",
        "Shah\u012bd\u0101b\u0101d",
        "\u06af\u0627\u0648\u06cc\u06a9",
        "\u0634\u0647\u06cc\u062f\u0622\u0628\u0627\u062f"
    ],
    "name:und_x_variant":[
        "Gaveyk",
        "Gavyal",
        "G\u0101v\u012bk"
    ],
    "wof:name":"Shahidabad",
    "wof:placetype":"locality"
},
  "geometry": {"coordinates":[49.28653,35.52397],"type":"Point"}
}