{
  "type": "Feature",
  "properties": {
    "gn:admin1_code":"33.0",
    "gn:asciiname":"Vargahan",
    "gn:country_code":"IR",
    "gn:dem":768,
    "gn:feature_class":"P",
    "gn:feature_code":"PPL",
    "gn:name":"Vargah\u0101n",
    "gn:population":0,
    "gn:timezone":"Asia/Tehran",
    "iso:country":"IR",
    "name:fas_x_preferred":[
        "\u0648\u0631\u06af\u0647\u0627\u0646"
    ],
    "name:fas_x_variant":[
        "Vargah\u0101n"
    ],
    "wof:name":"Vargahan",
    "wof:placetype":"locality"
},
  "geometry": {"coordinates":[47.49981,38.62154],"type":"Point"}
}