{
  "type": "Feature",
  "properties": {
    "gn:admin1_code":"13",
    "gn:asciiname":"Saruran",
    "gn:country_code":"IR",
    "gn:dem":1322,
    "gn:feature_class":"P",
    "gn:feature_code":"PPL",
    "gn:name":"Sar\u016br\u0101n",
    "gn:population":0,
    "gn:timezone":"Asia/Tehran",
    "iso:country":"IR",
    "name:ceb_x_preferred":[
        "Sar\u016br\u0101n"
    ],
    "name:fas_x_preferred":[
        "\u0633\u0631\u0648\u0631\u0627\u0646"
    ],
    "name:fas_x_variant":[
        "Sar\u016br\u0101n"
    ],
    "name:swe_x_preferred":[
        "Sar\u016br\u0101n"
    ],
    "wof:name":"Saruran",
    "wof:placetype":"locality"
},
  "geometry": {"coordinates":[46.9064,34.6017],"type":"Point"}
}