{
  "type": "Feature",
  "properties": {
    "gn:admin1_code":"15.0",
    "gn:asciiname":"Sar Qal`eh-ye Kenar Siah",
    "gn:country_code":"IR",
    "gn:dem":638,
    "gn:feature_class":"P",
    "gn:feature_code":"PPL",
    "gn:name":"Sar Qal\u2018eh-ye Ken\u0101r S\u012b\u0101h",
    "gn:population":0,
    "gn:timezone":"Asia/Tehran",
    "iso:country":"IR",
    "name:fas_x_preferred":[
        "Sar Qal\u2018eh-ye Ken\u0101r S\u012b\u0101h"
    ],
    "name:fas_x_variant":[
        "\u0633\u0631\u0642\u0644\u0639\u0647 \u06a9\u0646\u0627\u0631 \u0633\u06cc\u0627\u0647"
    ],
    "name:und_x_variant":[
        "S\u012b\u0101h",
        "Kon\u0101r Sey\u0101h",
        "Kon\u0101r S\u012b\u0101h"
    ],
    "wof:name":"Sar Qal`eh-ye Kenar Siah",
    "wof:placetype":"locality"
},
  "geometry": {"coordinates":[49.87413,32.0027],"type":"Point"}
}