{
  "type": "Feature",
  "properties": {
    "gn:admin1_code":"28",
    "gn:asciiname":"Rezvaniyeh",
    "gn:country_code":"IR",
    "gn:dem":723,
    "gn:feature_class":"P",
    "gn:feature_code":"PPLF",
    "gn:name":"Re\u1e95v\u0101n\u012byeh",
    "gn:population":0,
    "gn:timezone":"Asia/Tehran",
    "iso:country":"IR",
    "name:fas_x_preferred":[
        "Mazra\u2018eh-ye Deh Now"
    ],
    "name:fas_x_variant":[
        "Re\u1e95v\u0101n\u012byeh",
        "\u0631\u0636\u0648\u0627\u0646\u06cc\u0647",
        "\u0645\u0632\u0631\u0639\u0647 \u062f\u0647 \u0646\u0648"
    ],
    "wof:name":"Rezvaniyeh",
    "wof:placetype":"locality"
},
  "geometry": {"coordinates":[55.16789,33.45092],"type":"Point"}
}