{
  "type": "Feature",
  "properties": {
    "gn:admin1_code":"8.0",
    "gn:asciiname":"Yeylaq Chermeh",
    "gn:country_code":"IR",
    "gn:dem":1857,
    "gn:feature_class":"P",
    "gn:feature_code":"PPL",
    "gn:name":"Yeyl\u0101q Chermeh",
    "gn:population":0,
    "gn:timezone":"Asia/Tehran",
    "iso:country":"IR",
    "name:fas_x_preferred":[
        "\u0686\u0631\u0645\u0647"
    ],
    "name:fas_x_variant":[
        "\u06cc\u06cc\u0644\u0627\u0642 \u0686\u0631\u0645\u0647"
    ],
    "name:und_x_variant":[
        "Chermeh",
        "Yeyl\u0101q Chermeh"
    ],
    "wof:name":"Yeylaq Chermeh",
    "wof:placetype":"locality"
},
  "geometry": {"coordinates":[48.62327,37.67164],"type":"Point"}
}