{
  "type": "Feature",
  "properties": {
    "gn:admin1_code":"5.0",
    "gn:asciiname":"Ganduk",
    "gn:country_code":"IR",
    "gn:dem":1082,
    "gn:feature_class":"P",
    "gn:feature_code":"PPL",
    "gn:name":"Gand\u016bk",
    "gn:population":0,
    "gn:timezone":"Asia/Tehran",
    "iso:country":"IR",
    "name:fas_x_preferred":[
        "S\u0101d\u0101t-e Mashhad\u012b"
    ],
    "name:fas_x_variant":[
        "\u0633\u0627\u062f\u0627\u062a \u0645\u0634\u0647\u062f\u06cc",
        "\u06af\u0646\u062f\u0648\u06a9"
    ],
    "name:und_x_variant":[
        "\u0633\u0627\u062f\u0627\u062a \u0645\u0634\u0647\u062f\u06cc",
        "Gand\u016bk"
    ],
    "wof:name":"Ganduk",
    "wof:placetype":"locality"
},
  "geometry": {"coordinates":[50.56397,31.07011],"type":"Point"}
}