{
  "type": "Feature",
  "properties": {
    "gn:admin1_code":"8.0",
    "gn:asciiname":"Sineh Khalbeneh",
    "gn:country_code":"IR",
    "gn:dem":-22,
    "gn:feature_class":"P",
    "gn:feature_code":"PPL",
    "gn:name":"S\u012bneh Kh\u0101lbeneh",
    "gn:population":0,
    "gn:timezone":"Asia/Tehran",
    "iso:country":"IR",
    "name:fas_x_preferred":[
        "S\u012bneh Kh\u0101lbeneh"
    ],
    "name:fas_x_variant":[
        "\u0633\u06cc\u0646\u0647 \u062e\u0627\u0644\u0628\u0646\u0647"
    ],
    "name:und_x_variant":[
        "\u0633\u06cc\u0646\u0647 \u062e\u0627\u0644\u0628\u0646\u0647"
    ],
    "wof:name":"Sineh Khalbeneh",
    "wof:placetype":"locality"
},
  "geometry": {"coordinates":[50.15158,37.24307],"type":"Point"}
}