{
  "type": "Feature",
  "properties": {
    "gn:admin1_code":"28.0",
    "gn:asciiname":"Kafoshan",
    "gn:country_code":"IR",
    "gn:dem":1608,
    "gn:feature_class":"P",
    "gn:feature_code":"PPL",
    "gn:name":"K\u0101fosh\u0101n",
    "gn:population":0,
    "gn:timezone":"Asia/Tehran",
    "iso:country":"IR",
    "name:fas_x_preferred":[
        "\u06a9\u0627\u0647 \u0641\u0634\u0627\u0646"
    ],
    "name:fas_x_variant":[
        "K\u0101h Fash\u0101n",
        "\u06a9\u0627\u0641\u0634\u0627\u0646"
    ],
    "name:und_x_variant":[
        "G\u0101h Fash\u0101n",
        "K\u0101p\u0101s\u0101n",
        "G\u0101h Fosh\u0101n",
        "K\u0101fosh\u0101n"
    ],
    "wof:name":"Kafoshan",
    "wof:placetype":"locality"
},
  "geometry": {"coordinates":[51.49931,32.57444],"type":"Point"}
}