{
  "type": "Feature",
  "properties": {
    "gn:admin1_code":"15",
    "gn:asciiname":"Sarshatt",
    "gn:country_code":"IR",
    "gn:dem":1231,
    "gn:feature_class":"P",
    "gn:feature_code":"PPL",
    "gn:name":"Sarsha\u0163\u0163",
    "gn:population":0,
    "gn:timezone":"Asia/Tehran",
    "iso:country":"IR",
    "name:ara_x_preferred":[
        "\u0633\u0631\u0634\u062a"
    ],
    "name:ceb_x_preferred":[
        "Seresht"
    ],
    "name:fas_x_preferred":[
        "\u0633\u0631\u0634\u0637"
    ],
    "name:swe_x_preferred":[
        "Seresht"
    ],
    "name:und_x_variant":[
        "Sar-i-Shat",
        "Seresht",
        "Sarsha\u0163\u0163"
    ],
    "wof:name":"Sarshatt",
    "wof:placetype":"locality"
},
  "geometry": {"coordinates":[49.7156,32.36047],"type":"Point"}
}