{
  "type": "Feature",
  "properties": {
    "gn:admin1_code":"5",
    "gn:asciiname":"Garubaz",
    "gn:country_code":"IR",
    "gn:dem":986,
    "gn:feature_class":"P",
    "gn:feature_code":"PPL",
    "gn:name":"Gar\u016bb\u0101z",
    "gn:population":0,
    "gn:timezone":"Asia/Tehran",
    "iso:country":"IR",
    "name:fas_x_preferred":[
        "Gar\u016bb\u0101z"
    ],
    "name:fas_x_variant":[
        "\u06af\u0631\u0648\u0628\u0627\u0632"
    ],
    "wof:name":"Garubaz",
    "wof:placetype":"locality"
},
  "geometry": {"coordinates":[50.59232,30.89213],"type":"Point"}
}