{
  "type": "Feature",
  "properties": {
    "gn:admin1_code":"8.0",
    "gn:asciiname":"Jalow Dahaneh",
    "gn:country_code":"IR",
    "gn:dem":298,
    "gn:feature_class":"P",
    "gn:feature_code":"PPLL",
    "gn:name":"Jalow Dahaneh",
    "gn:population":0,
    "gn:timezone":"Asia/Tehran",
    "iso:country":"IR",
    "name:fas_x_preferred":[
        "\u062c\u0644\u0648 \u062f\u0647\u0646\u0647"
    ],
    "wof:name":"Jalow Dahaneh",
    "wof:placetype":"locality"
},
  "geometry": {"coordinates":[49.44842,36.98193],"type":"Point"}
}