{
  "type": "Feature",
  "properties": {
    "gn:admin1_code":"7",
    "gn:asciiname":"Kuh Sabz",
    "gn:country_code":"IR",
    "gn:dem":1600,
    "gn:feature_class":"P",
    "gn:feature_code":"PPL",
    "gn:name":"K\u016bh Sabz",
    "gn:population":0,
    "gn:timezone":"Asia/Tehran",
    "iso:country":"IR",
    "name:fas_x_preferred":[
        "\u06a9\u0648\u0647 \u0633\u0628\u0632"
    ],
    "name:fas_x_variant":[
        "K\u016bh Sabz"
    ],
    "name:msa_x_preferred":[
        "Kuh Sabz"
    ],
    "name:und_x_variant":[
        "Kooh Sabz",
        "K\u016bh-e Sabz"
    ],
    "wof:name":"Kuh Sabz",
    "wof:placetype":"locality"
},
  "geometry": {"coordinates":[52.7071,29.9137],"type":"Point"}
}