{
  "type": "Feature",
  "properties": {
    "gn:admin1_code":"40",
    "gn:asciiname":"Khastkuh",
    "gn:country_code":"IR",
    "gn:dem":1537,
    "gn:feature_class":"P",
    "gn:feature_code":"PPL",
    "gn:name":"Kh\u0101stk\u016bh",
    "gn:population":0,
    "gn:timezone":"Asia/Tehran",
    "iso:country":"IR",
    "name:fas_x_preferred":[
        "\u062e\u0627\u0633\u062a\u06a9\u0648\u0647"
    ],
    "name:fas_x_variant":[
        "Kh\u0101stk\u016bh"
    ],
    "wof:name":"Khastkuh",
    "wof:placetype":"locality"
},
  "geometry": {"coordinates":[53.6719,32.3151],"type":"Point"}
}