{
  "type": "Feature",
  "properties": {
    "gn:admin1_code":"13",
    "gn:asciiname":"Namivand-e Pa'in",
    "gn:country_code":"IR",
    "gn:dem":1345,
    "gn:feature_class":"P",
    "gn:feature_code":"PPL",
    "gn:name":"N\u0101m\u012bvand-e P\u0101\u2019\u012bn",
    "gn:population":0,
    "gn:timezone":"Asia/Tehran",
    "iso:country":"IR",
    "name:fas_x_preferred":[
        "\u0646\u0627\u0645\u06cc\u0648\u0646\u062f \u067e\u0627\u0626\u06cc\u0646"
    ],
    "name:und_x_variant":[
        "N\u0101m\u012bvand-e P\u0101\u2019\u012bn"
    ],
    "wof:name":"Namivand-e Pa'in",
    "wof:placetype":"locality"
},
  "geometry": {"coordinates":[46.7525,34.3705],"type":"Point"}
}