{
  "type": "Feature",
  "properties": {
    "gn:admin1_code":"37",
    "gn:asciiname":"Shafi`abad",
    "gn:country_code":"IR",
    "gn:dem":101,
    "gn:feature_class":"P",
    "gn:feature_code":"PPL",
    "gn:name":"Shaf\u012b\u2018\u0101b\u0101d",
    "gn:population":0,
    "gn:timezone":"Asia/Tehran",
    "iso:country":"IR",
    "name:fas_x_preferred":[
        "\u0634\u0641\u06cc\u0639 \u0622\u0628\u0627\u062f"
    ],
    "name:fas_x_variant":[
        "Shaf\u012b\u2018\u0101b\u0101d"
    ],
    "wof:name":"Shafi`abad",
    "wof:placetype":"locality"
},
  "geometry": {"coordinates":[54.97136,36.96235],"type":"Point"}
}