{
  "type": "Feature",
  "properties": {
    "gn:admin1_code":"8.0",
    "gn:asciiname":"Vilama Deh",
    "gn:country_code":"IR",
    "gn:dem":416,
    "gn:feature_class":"P",
    "gn:feature_code":"PPL",
    "gn:name":"V\u012bl\u0101m\u0101 Deh",
    "gn:population":0,
    "gn:timezone":"Asia/Tehran",
    "iso:country":"IR",
    "name:fas_x_preferred":[
        "V\u012bl\u0101m\u0101 Deh"
    ],
    "wof:name":"Vilama Deh",
    "wof:placetype":"locality"
},
  "geometry": {"coordinates":[49.71667,36.98333],"type":"Point"}
}