{
  "type": "Feature",
  "properties": {
    "gn:admin1_code":"43.0",
    "gn:asciiname":"Yomuq",
    "gn:country_code":"IR",
    "gn:dem":678,
    "gn:feature_class":"P",
    "gn:feature_code":"PPL",
    "gn:name":"Yom\u016bq",
    "gn:population":0,
    "gn:timezone":"Asia/Tehran",
    "iso:country":"IR",
    "name:ceb_x_preferred":[
        "Yom\u016bq"
    ],
    "name:fas_x_preferred":[
        "\u06cc\u0645\u0648\u0642"
    ],
    "name:fas_x_variant":[
        "Yom\u016bq"
    ],
    "name:por_x_preferred":[
        "Yomuq"
    ],
    "name:swe_x_preferred":[
        "Yom\u016bq"
    ],
    "name:urd_x_preferred":[
        "\u06cc\u0648\u0645\u0642"
    ],
    "wof:name":"Yomuq",
    "wof:placetype":"locality"
},
  "geometry": {"coordinates":[56.4787,37.9962],"type":"Point"}
}