{
  "type": "Feature",
  "properties": {
    "gn:admin1_code":"23",
    "gn:asciiname":"Ardudar",
    "gn:country_code":"IR",
    "gn:dem":2066,
    "gn:feature_class":"P",
    "gn:feature_code":"PPL",
    "gn:name":"Ard\u016bdar",
    "gn:population":0,
    "gn:timezone":"Asia/Tehran",
    "iso:country":"IR",
    "name:ara_x_preferred":[
        "\u0623\u0631\u062f\u0648\u062f\u0627\u0631"
    ],
    "name:ceb_x_preferred":[
        "Ard\u016bdar"
    ],
    "name:fas_x_preferred":[
        "\u0627\u064e\u0631\u062f\u0648\u062f\u0627\u0631"
    ],
    "name:fas_x_variant":[
        "\u0627\u064f\u0631\u062f\u0648\u062f\u0627\u0631",
        "Ard\u016bd\u0101r",
        "Ard\u016bdar",
        "\u0627\u0631\u062f\u0648\u062f\u0631"
    ],
    "name:swe_x_preferred":[
        "Ard\u016bdar"
    ],
    "name:und_x_variant":[
        "Ord\u016bd\u0101r",
        "\u0627\u0631\u062f\u0648\u062f\u0631"
    ],
    "wof:name":"Ardudar",
    "wof:placetype":"locality"
},
  "geometry": {"coordinates":[49.66005,33.36081],"type":"Point"}
}