{
  "type": "Feature",
  "properties": {
    "gn:admin1_code":"4.0",
    "gn:asciiname":"Gorgij",
    "gn:country_code":"IR",
    "gn:dem":1362,
    "gn:feature_class":"P",
    "gn:feature_code":"PPL",
    "gn:name":"Gorg\u012bj",
    "gn:population":0,
    "gn:timezone":"Asia/Tehran",
    "iso:country":"IR",
    "wof:name":"Gorgij",
    "wof:placetype":"locality"
},
  "geometry": {"coordinates":[60.88417,29.51111],"type":"Point"}
}