{
  "type": "Feature",
  "properties": {
    "gn:admin1_code":"4.0",
    "gn:asciiname":"Karimvar",
    "gn:country_code":"IR",
    "gn:dem":907,
    "gn:feature_class":"P",
    "gn:feature_code":"PPL",
    "gn:name":"Kar\u012bmv\u0101r",
    "gn:population":0,
    "gn:timezone":"Asia/Tehran",
    "iso:country":"IR",
    "name:fas_x_preferred":[
        "Kar\u012bmv\u0101r"
    ],
    "wof:name":"Karimvar",
    "wof:placetype":"locality"
},
  "geometry": {"coordinates":[60.55222,26.38861],"type":"Point"}
}