{
  "type": "Feature",
  "properties": {
    "gn:admin1_code":"25.0",
    "gn:asciiname":"Seyang",
    "gn:country_code":"IR",
    "gn:dem":876,
    "gn:feature_class":"P",
    "gn:feature_code":"PPL",
    "gn:name":"Seyang",
    "gn:population":0,
    "gn:timezone":"Asia/Tehran",
    "iso:country":"IR",
    "name:fas_x_preferred":[
        "\u0633\u064a\u0646\u06af"
    ],
    "name:fas_x_variant":[
        "\u0633\u06cc\u064a\u0646\u06af"
    ],
    "name:und_x_variant":[
        "Seyyang"
    ],
    "wof:name":"Seyang",
    "wof:placetype":"locality"
},
  "geometry": {"coordinates":[54.58234,35.22257000000001],"type":"Point"}
}