{
  "type": "Feature",
  "properties": {
    "gn:admin1_code":"33",
    "gn:asciiname":"Peygham",
    "gn:country_code":"IR",
    "gn:dem":1364,
    "gn:feature_class":"P",
    "gn:feature_code":"PPL",
    "gn:name":"Peygh\u0101m",
    "gn:population":0,
    "gn:timezone":"Asia/Tehran",
    "iso:country":"IR",
    "name:ceb_x_preferred":[
        "Peygh\u0101m"
    ],
    "name:fas_x_preferred":[
        "Peygh\u0101n Ch\u0101y"
    ],
    "name:fas_x_variant":[
        "\u067e\u06cc\u063a\u0627\u0645",
        "\u067e\u06cc\u063a\u0627\u0646"
    ],
    "name:msa_x_preferred":[
        "Peyghan"
    ],
    "name:swe_x_preferred":[
        "Peygh\u0101m"
    ],
    "name:und_x_variant":[
        "Peygh\u0101n",
        "Pighan",
        "Peygam"
    ],
    "wof:name":"Peygham",
    "wof:placetype":"locality"
},
  "geometry": {"coordinates":[47.06851,38.7707],"type":"Point"}
}