{
  "type": "Feature",
  "properties": {
    "gn:admin1_code":"38",
    "gn:asciiname":"Sabzak",
    "gn:country_code":"IR",
    "gn:dem":1891,
    "gn:feature_class":"P",
    "gn:feature_code":"PPL",
    "gn:name":"Sabzak",
    "gn:population":0,
    "gn:timezone":"Asia/Tehran",
    "iso:country":"IR",
    "name:ceb_x_preferred":[
        "Sabzak"
    ],
    "name:fas_x_preferred":[
        "\u0633\u0628\u0632\u0643"
    ],
    "name:fas_x_variant":[
        "\u0633\u0628\u0632\u06a9"
    ],
    "name:swe_x_preferred":[
        "Sabzak"
    ],
    "name:und_x_variant":[
        "\u012ashak Ch\u016bp\u0101n",
        "Sabzok",
        "Sabzeh"
    ],
    "name:urd_x_preferred":[
        "\u0633\u0628\u0632\u0627\u06a9"
    ],
    "wof:name":"Sabzak",
    "wof:placetype":"locality"
},
  "geometry": {"coordinates":[49.51053,35.61786],"type":"Point"}
}