{
  "type": "Feature",
  "properties": {
    "gn:admin1_code":"13",
    "gn:asciiname":"Gol Kheyrak",
    "gn:country_code":"IR",
    "gn:dem":760,
    "gn:feature_class":"P",
    "gn:feature_code":"PPL",
    "gn:name":"Gol Kheyrak",
    "gn:population":0,
    "gn:timezone":"Asia/Tehran",
    "iso:country":"IR",
    "name:fas_x_preferred":[
        "\u06af\u0644 \u062e\u06cc\u0631\u06a9"
    ],
    "wof:name":"Gol Kheyrak",
    "wof:placetype":"locality"
},
  "geometry": {"coordinates":[45.9482,34.0076],"type":"Point"}
}