{
  "type": "Feature",
  "properties": {
    "gn:admin1_code":"9.0",
    "gn:asciiname":"Ziaratgah-e Qasr-e Bolagh",
    "gn:country_code":"IR",
    "gn:dem":1845,
    "gn:feature_class":"P",
    "gn:feature_code":"PPL",
    "gn:name":"Z\u012b\u0101ratg\u0101h-e Qa\u015fr-e Bol\u0101gh",
    "gn:population":0,
    "gn:timezone":"Asia/Tehran",
    "iso:country":"IR",
    "name:fas_x_preferred":[
        "Z\u012b\u0101ratg\u0101h-e Qa\u015fr-e Bol\u0101gh"
    ],
    "name:fas_x_variant":[
        "\u0632\u06cc\u0627\u0631\u062a\u06af\u0627\u0647 \u0642\u0635\u0631 \u0628\u0644\u0627\u063a"
    ],
    "wof:name":"Ziaratgah-e Qasr-e Bolagh",
    "wof:placetype":"locality"
},
  "geometry": {"coordinates":[48.4192,34.86065],"type":"Point"}
}