{
  "type": "Feature",
  "properties": {
    "gn:admin1_code":"33.0",
    "gn:asciiname":"Azarshahr",
    "gn:country_code":"IR",
    "gn:dem":1386,
    "gn:feature_class":"P",
    "gn:feature_code":"PPLA2",
    "gn:name":"\u0100z\u0304arshahr",
    "gn:population":0,
    "gn:timezone":"Asia/Tehran",
    "iso:country":"IR",
    "name:fas_x_preferred":[
        "\u0622\u0630\u0631\u0634\u0647\u0631"
    ],
    "name:und_x_variant":[
        "\u0100z\u0304arshahr",
        "Dehkhv\u0101req\u0101n",
        "\u062f\u0650\u0647\u062e\u0648\u0627\u0631\u0650\u0642\u0627\u0646"
    ],
    "wof:name":"Azarshahr",
    "wof:placetype":"locality"
},
  "geometry": {"coordinates":[45.9783,37.759],"type":"Point"}
}