{
  "type": "Feature",
  "properties": {
    "gn:admin1_code":"33.0",
    "gn:asciiname":"Azarshahr",
    "gn:country_code":"IR",
    "gn:dem":1386,
    "gn:feature_class":"P",
    "gn:feature_code":"PPLA2",
    "gn:name":"\u0100z\u0304arshahr",
    "gn:population":0,
    "gn:timezone":"Asia/Tehran",
    "iso:country":"IR",
    "name:ara_x_preferred":[
        "\u0622\u0630\u0631\u0634\u0647\u0631"
    ],
    "name:azb_x_preferred":[
        "\u0622\u0630\u0631\u0634\u0647\u0631"
    ],
    "name:aze_x_preferred":[
        "Az\u0259r\u015f\u0259hr"
    ],
    "name:ceb_x_preferred":[
        "\u0100z\u0304arshahr"
    ],
    "name:deu_x_preferred":[
        "Azarschahr"
    ],
    "name:fas_x_preferred":[
        "\u0622\u0630\u0631\u0634\u0647\u0631"
    ],
    "name:hin_x_preferred":[
        "\u0905\u091c\u093c\u093e\u0930\u0936\u0939\u0930"
    ],
    "name:ita_x_preferred":[
        "Azar Shahr"
    ],
    "name:mlg_x_preferred":[
        "Azarshahr"
    ],
    "name:msa_x_preferred":[
        "Azarshahr"
    ],
    "name:pnb_x_preferred":[
        "\u0622\u0630\u0631\u0634\u06c1\u0631"
    ],
    "name:pol_x_preferred":[
        "Azarszahr"
    ],
    "name:rus_x_preferred":[
        "\u0410\u0437\u0435\u0440\u0448\u0435\u0445\u0440"
    ],
    "name:snd_x_preferred":[
        "\u0622\u0630\u0631\u0634\u0647\u0631"
    ],
    "name:tgk_x_preferred":[
        "\u041e\u0437\u0430\u0440\u0448\u0430\u04b3\u0440"
    ],
    "name:tur_x_preferred":[
        "Azer\u015fehr"
    ],
    "name:und_x_variant":[
        "Dehkhv\u0101req\u0101n",
        "\u062f\u0650\u0647\u062e\u0648\u0627\u0631\u0650\u0642\u0627\u0646"
    ],
    "name:urd_x_preferred":[
        "\u0622\u0630\u0631\u0634\u06c1\u0631"
    ],
    "wof:name":"Azarshahr",
    "wof:placetype":"locality"
},
  "geometry": {"coordinates":[45.9783,37.759],"type":"Point"}
}