{
  "type": "Feature",
  "properties": {
    "gn:admin1_code":"23.0",
    "gn:asciiname":"Chenarkareh",
    "gn:country_code":"IR",
    "gn:dem":1534,
    "gn:feature_class":"P",
    "gn:feature_code":"PPL",
    "gn:name":"Chen\u0101rkareh",
    "gn:population":0,
    "gn:timezone":"Asia/Tehran",
    "iso:country":"IR",
    "name:fas_x_preferred":[
        "\u0686\u0646\u0627\u0631\u06a9\u0631\u0647"
    ],
    "name:und_x_variant":[
        "Chen\u0101rkareh"
    ],
    "wof:name":"Chenarkareh",
    "wof:placetype":"locality"
},
  "geometry": {"coordinates":[47.31225,33.62565],"type":"Point"}
}