{
  "type": "Feature",
  "properties": {
    "gn:admin1_code":"4",
    "gn:asciiname":"Sharaf od Din",
    "gn:country_code":"IR",
    "gn:dem":1313,
    "gn:feature_class":"P",
    "gn:feature_code":"PPL",
    "gn:name":"Sharaf od D\u012bn",
    "gn:population":0,
    "gn:timezone":"Asia/Tehran",
    "iso:country":"IR",
    "name:fas_x_preferred":[
        "\u0634\u0631\u0641 \u0627\u0644\u062f\u064a\u0646"
    ],
    "name:fas_x_variant":[
        "Sharaf od D\u012bn"
    ],
    "wof:name":"Sharaf od Din",
    "wof:placetype":"locality"
},
  "geometry": {"coordinates":[61.07009,27.69856],"type":"Point"}
}