{
  "type": "Feature",
  "properties": {
    "gn:admin1_code":"22.0",
    "gn:asciiname":"Khor Al Zubair",
    "gn:country_code":"IR",
    "gn:dem":5,
    "gn:feature_class":"P",
    "gn:feature_code":"PPL",
    "gn:name":"Khor Al Zubair",
    "gn:population":0,
    "gn:timezone":"Asia/Tehran",
    "iso:country":"IR",
    "name:ara_x_preferred":[
        "\u062e\u0648\u0631 \u0627\u0644\u0632\u0628\u064a\u0631"
    ],
    "name:ind_x_preferred":[
        "Khur Al Zubair"
    ],
    "wof:name":"Khor Al Zubair",
    "wof:placetype":"locality"
},
  "geometry": {"coordinates":[47.985,30.19694],"type":"Point"}
}