{
  "type": "Feature",
  "properties": {
    "gn:admin1_code":"23",
    "gn:asciiname":"Garmabalah-ye `Olya",
    "gn:country_code":"IR",
    "gn:dem":1787,
    "gn:feature_class":"P",
    "gn:feature_code":"PPL",
    "gn:name":"Garm\u0101balah-ye \u2018Oly\u0101",
    "gn:population":0,
    "gn:timezone":"Asia/Tehran",
    "iso:country":"IR",
    "name:fas_x_preferred":[
        "\u06af\u0631\u0645 \u0622\u0628\u0644\u0647 \u0639\u0644\u064a\u0627"
    ],
    "name:fas_x_variant":[
        "\u06af\u0631\u0645\u0627\u0648\u0644\u0647 \u0639\u0644\u064a\u0627",
        "Garm\u0101balah-ye \u2018Oly\u0101",
        "Garm\u0101valeh-ye \u2018Oly\u0101"
    ],
    "wof:name":"Garmabalah-ye `Olya",
    "wof:placetype":"locality"
},
  "geometry": {"coordinates":[48.5561,33.524],"type":"Point"}
}