{
  "type": "Feature",
  "properties": {
    "gn:admin1_code":"29",
    "gn:asciiname":"Rahmatabad",
    "gn:country_code":"IR",
    "gn:dem":269,
    "gn:feature_class":"P",
    "gn:feature_code":"PPL",
    "gn:name":"Ra\u1e29mat\u0101b\u0101d",
    "gn:population":0,
    "gn:timezone":"Asia/Tehran",
    "iso:country":"IR",
    "name:fas_x_preferred":[
        "Ra\u1e29mat\u0101b\u0101d"
    ],
    "wof:name":"Rahmatabad",
    "wof:placetype":"locality"
},
  "geometry": {"coordinates":[57.98,30.34917],"type":"Point"}
}