{
  "type": "Feature",
  "properties": {
    "gn:admin1_code":"13",
    "gn:asciiname":"Quri Qal`eh",
    "gn:country_code":"IR",
    "gn:dem":1553,
    "gn:feature_class":"P",
    "gn:feature_code":"PPL",
    "gn:name":"Q\u016br\u012b Qal\u2018eh",
    "gn:population":0,
    "gn:timezone":"Asia/Tehran",
    "iso:country":"IR",
    "name:fas_x_preferred":[
        "\u0642\u0648\u0631\u06cc \u0642\u0644\u0639\u0647"
    ],
    "name:fas_x_variant":[
        "Q\u016br\u012b Qal\u2018eh"
    ],
    "wof:name":"Quri Qal`eh",
    "wof:placetype":"locality"
},
  "geometry": {"coordinates":[46.4963,34.892],"type":"Point"}
}