{
  "type": "Feature",
  "properties": {
    "gn:admin1_code":"25.0",
    "gn:asciiname":"Ravanabad",
    "gn:country_code":"IR",
    "gn:dem":1438,
    "gn:feature_class":"P",
    "gn:feature_code":"PPLL",
    "gn:name":"Rav\u0101n\u0101b\u0101d",
    "gn:population":0,
    "gn:timezone":"Asia/Tehran",
    "iso:country":"IR",
    "name:fas_x_preferred":[
        "Rav\u0101n\u0101b\u0101d"
    ],
    "name:fas_x_variant":[
        "\u0631\u0648\u0627\u0646 \u0622\u0628\u0627\u062f"
    ],
    "wof:name":"Ravanabad",
    "wof:placetype":"locality"
},
  "geometry": {"coordinates":[54.98546,36.52584],"type":"Point"}
}