{
  "type": "Feature",
  "properties": {
    "gn:admin1_code":"7.0",
    "gn:asciiname":"Kenareh",
    "gn:country_code":"IR",
    "gn:dem":1609,
    "gn:feature_class":"P",
    "gn:feature_code":"PPL",
    "gn:name":"Ken\u0101reh",
    "gn:population":0,
    "gn:timezone":"Asia/Tehran",
    "iso:country":"IR",
    "name:fas_x_preferred":[
        "\u06a9\u0646\u0627\u0631\u0647"
    ],
    "name:fas_x_variant":[
        "Ken\u0101reh"
    ],
    "wof:name":"Kenareh",
    "wof:placetype":"locality"
},
  "geometry": {"coordinates":[52.8585,29.9036],"type":"Point"}
}