{
  "type": "Feature",
  "properties": {
    "gn:admin1_code":"32",
    "gn:asciiname":"Kanchubeh",
    "gn:country_code":"IR",
    "gn:dem":894,
    "gn:feature_class":"P",
    "gn:feature_code":"PPL",
    "gn:name":"Kanch\u016bbeh",
    "gn:population":0,
    "gn:timezone":"Asia/Tehran",
    "iso:country":"IR",
    "name:ceb_x_preferred":[
        "Gonch\u016bbeh"
    ],
    "name:fas_x_preferred":[
        "Kanch\u016bbeh"
    ],
    "name:fas_x_variant":[
        "\u06af\u0646\u0686\u0648\u0628\u0647",
        "\u06a9\u0646\u0686\u0648\u0628\u0647"
    ],
    "name:msa_x_preferred":[
        "Kanchubeh"
    ],
    "name:mzn_x_preferred":[
        "\u06a9\u0646\u0686\u0648\u0628\u0647"
    ],
    "name:swe_x_preferred":[
        "Gonch\u016bbeh"
    ],
    "name:und_x_variant":[
        "Ganch\u016bbeh"
    ],
    "wof:name":"Kanchubeh",
    "wof:placetype":"locality"
},
  "geometry": {"coordinates":[47.5634,38.7505],"type":"Point"}
}