{
  "type": "Feature",
  "properties": {
    "gn:admin1_code":"8",
    "gn:asciiname":"Kacha",
    "gn:country_code":"IR",
    "gn:dem":124,
    "gn:feature_class":"P",
    "gn:feature_code":"PPL",
    "gn:name":"Kach\u0101",
    "gn:population":0,
    "gn:timezone":"Asia/Tehran",
    "iso:country":"IR",
    "name:fas_x_preferred":[
        "Kach\u0101 P\u0101\u2019\u012bn Ma\u1e29alleh"
    ],
    "name:fas_x_variant":[
        "Kach\u0101",
        "\u06a9\u0686\u0627",
        "\u0628\u0627\u0644\u0627 \u0645\u062d\u0644\u0647",
        "\u0628\u0627\u0644\u0627 \u0645\u062d\u0644\u0647 \u06a9\u0686\u0627"
    ],
    "name:und_x_variant":[
        "Kechakh",
        "Kacheh",
        "Kach\u0101",
        "K\u0101ch\u0101",
        "\u06a9\u0686\u0627",
        "B\u0101l\u0101 Ma\u1e29alleh",
        "B\u0101l\u0101 Ma\u1e29alleh-ye Kach\u0101"
    ],
    "wof:name":"Kacha",
    "wof:placetype":"locality"
},
  "geometry": {"coordinates":[49.60196,37.08346],"type":"Point"}
}