{
  "type": "Feature",
  "properties": {
    "gn:admin1_code":"42",
    "gn:asciiname":"Payeh",
    "gn:country_code":"IR",
    "gn:dem":1672,
    "gn:feature_class":"P",
    "gn:feature_code":"PPL",
    "gn:name":"P\u0101yeh",
    "gn:population":0,
    "gn:timezone":"Asia/Tehran",
    "iso:country":"IR",
    "name:ara_x_preferred":[
        "\u0643\u0644\u0627\u062a\u0647 \u0628\u0627\u064a\u0647"
    ],
    "name:fas_x_preferred":[
        "\u067e\u0627\u06cc\u0647"
    ],
    "name:fas_x_variant":[
        "Kal\u0101teh-ye P\u0101yeh",
        "P\u0101yeh",
        "\u06a9\u0644\u0627\u062a\u0647 \u067e\u0627\u06cc\u0647"
    ],
    "wof:name":"Payeh",
    "wof:placetype":"locality"
},
  "geometry": {"coordinates":[59.02016999999999,36.45754],"type":"Point"}
}