{
  "type": "Feature",
  "properties": {
    "gn:admin1_code":"4.0",
    "gn:asciiname":"Moridvaru",
    "gn:country_code":"IR",
    "gn:dem":35,
    "gn:feature_class":"P",
    "gn:feature_code":"PPL",
    "gn:name":"Mor\u012bdv\u0101r\u016b",
    "gn:population":0,
    "gn:timezone":"Asia/Tehran",
    "iso:country":"IR",
    "name:fas_x_preferred":[
        "Mor\u012bdv\u0101r\u016b B\u0101l\u0101"
    ],
    "name:fas_x_variant":[
        "Mor\u012bdv\u0101r\u016b",
        "\u0645\u0631\u06cc\u062f\u0648\u0627\u0631\u0648"
    ],
    "name:und_x_variant":[
        "Mor\u012bd D\u0101r\u016b",
        "Mor\u012bd B\u0101r\u016b",
        "\u0645\u0631\u06cc\u062f\u0648\u0627\u0631\u0648"
    ],
    "wof:name":"Moridvaru",
    "wof:placetype":"locality"
},
  "geometry": {"coordinates":[61.04751,25.65841],"type":"Point"}
}