{
  "type": "Feature",
  "properties": {
    "gn:admin1_code":"23",
    "gn:asciiname":"Nasirabad",
    "gn:country_code":"IR",
    "gn:dem":1990,
    "gn:feature_class":"P",
    "gn:feature_code":"PPL",
    "gn:name":"Na\u015f\u012br\u0101b\u0101d",
    "gn:population":0,
    "gn:timezone":"Asia/Tehran",
    "iso:country":"IR",
    "name:ceb_x_preferred":[
        "Nasirabad"
    ],
    "name:fas_x_preferred":[
        "Na\u015f\u012br\u0101b\u0101d"
    ],
    "name:fas_x_variant":[
        "\u0646\u0635\u06cc\u0631\u0622\u0628\u0627\u062f"
    ],
    "name:mzn_x_preferred":[
        "\u0646\u0635\u06cc\u0631\u0622\u0628\u0627\u062f"
    ],
    "name:swe_x_preferred":[
        "Nasirabad"
    ],
    "wof:name":"Nasirabad",
    "wof:placetype":"locality"
},
  "geometry": {"coordinates":[49.46667,33.33333],"type":"Point"}
}