{
  "type": "Feature",
  "properties": {
    "gn:admin1_code":"32",
    "gn:asciiname":"Bayram Badan",
    "gn:country_code":"IR",
    "gn:dem":1436,
    "gn:feature_class":"P",
    "gn:feature_code":"PPL",
    "gn:name":"B\u0101yr\u0101m Badan",
    "gn:population":0,
    "gn:timezone":"Asia/Tehran",
    "iso:country":"IR",
    "name:fas_x_preferred":[
        "\u0628\u0627\u064a\u0631\u0627\u0645 \u0628\u062f\u0646"
    ],
    "name:fas_x_variant":[
        "B\u0101yr\u0101m Badan"
    ],
    "wof:name":"Bayram Badan",
    "wof:placetype":"locality"
},
  "geometry": {"coordinates":[48.2489,38.4748],"type":"Point"}
}