{
  "type": "Feature",
  "properties": {
    "gn:admin1_code":"42",
    "gn:asciiname":"Padeh",
    "gn:country_code":"IR",
    "gn:dem":1634,
    "gn:feature_class":"P",
    "gn:feature_code":"PPL",
    "gn:name":"Padeh",
    "gn:population":0,
    "gn:timezone":"Asia/Tehran",
    "iso:country":"IR",
    "name:fas_x_preferred":[
        "\u067e\u062f\u0647"
    ],
    "wof:name":"Padeh",
    "wof:placetype":"locality"
},
  "geometry": {"coordinates":[59.2806,35.44563],"type":"Point"}
}