{
  "type": "Feature",
  "properties": {
    "gn:admin1_code":"41.0",
    "gn:asciiname":"Dehel Kuh",
    "gn:country_code":"IR",
    "gn:dem":1517,
    "gn:feature_class":"P",
    "gn:feature_code":"PPL",
    "gn:name":"Dehel K\u016bh",
    "gn:population":0,
    "gn:timezone":"Asia/Tehran",
    "iso:country":"IR",
    "name:fas_x_preferred":[
        "\u062f\u0647\u0644 \u06a9\u0648\u0647"
    ],
    "name:und_x_variant":[
        "Dehel K\u016bh"
    ],
    "wof:name":"Dehel Kuh",
    "wof:placetype":"locality"
},
  "geometry": {"coordinates":[59.24781,32.91164000000001],"type":"Point"}
}