{
  "type": "Feature",
  "properties": {
    "gn:admin1_code":"8",
    "gn:asciiname":"Dash Deybi",
    "gn:country_code":"IR",
    "gn:dem":1715,
    "gn:feature_class":"P",
    "gn:feature_code":"PPL",
    "gn:name":"D\u0101sh Deyb\u012b",
    "gn:population":0,
    "gn:timezone":"Asia/Tehran",
    "iso:country":"IR",
    "name:fas_x_preferred":[
        "\u062f\u0627\u0634 \u062f\u06cc\u0628\u06cc"
    ],
    "name:fas_x_variant":[
        "D\u0101sh Deyb\u012b"
    ],
    "name:und_x_variant":[
        "T\u0101sh D\u012bb"
    ],
    "wof:name":"Dash Deybi",
    "wof:placetype":"locality"
},
  "geometry": {"coordinates":[48.60072,37.8412],"type":"Point"}
}