{
  "type": "Feature",
  "properties": {
    "gn:admin1_code":"37",
    "gn:asciiname":"Hoseyn Farid",
    "gn:country_code":"IR",
    "gn:dem":132,
    "gn:feature_class":"P",
    "gn:feature_code":"PPL",
    "gn:name":"\u1e28oseyn Far\u012bd",
    "gn:population":0,
    "gn:timezone":"Asia/Tehran",
    "iso:country":"IR",
    "name:fas_x_preferred":[
        "S\u0101zem\u0101n-e Far\u012bd"
    ],
    "name:fas_x_variant":[
        "\u062d\u0633\u06cc\u0646 \u0641\u0631\u06cc\u062f",
        "\u0645\u0632\u0631\u0639\u0647 \u062d\u0633\u06cc\u0646 \u0641\u0631\u06cc\u062f"
    ],
    "name:und_x_variant":[
        "\u1e28oseyn Far\u012bd",
        "Mazra\u2018eh-ye \u1e28oseyn Far\u012bd"
    ],
    "wof:name":"Hoseyn Farid",
    "wof:placetype":"locality"
},
  "geometry": {"coordinates":[55.46144,37.36915],"type":"Point"}
}