{
  "type": "Feature",
  "properties": {
    "gn:admin1_code":"40",
    "gn:asciiname":"Manshad",
    "gn:country_code":"IR",
    "gn:dem":2253,
    "gn:feature_class":"P",
    "gn:feature_code":"PPL",
    "gn:name":"Mansh\u0101d",
    "gn:population":0,
    "gn:timezone":"Asia/Tehran",
    "iso:country":"IR",
    "name:ceb_x_preferred":[
        "Mansh\u0101d"
    ],
    "name:fas_x_preferred":[
        "\u0645\u0646\u0634\u0627\u062f"
    ],
    "name:fas_x_variant":[
        "\u062f\u064e\u0631\u0650\u0651\u0647",
        "Mansh\u0101d"
    ],
    "name:ita_x_preferred":[
        "Manshad"
    ],
    "name:swe_x_preferred":[
        "Mansh\u0101d"
    ],
    "name:und_x_variant":[
        "Darreh"
    ],
    "wof:name":"Manshad",
    "wof:placetype":"locality"
},
  "geometry": {"coordinates":[54.21977,31.5291],"type":"Point"}
}