{
  "type": "Feature",
  "properties": {
    "gn:admin1_code":"7",
    "gn:asciiname":"Bir",
    "gn:country_code":"IR",
    "gn:dem":1251,
    "gn:feature_class":"P",
    "gn:feature_code":"PPL",
    "gn:name":"B\u012br",
    "gn:population":0,
    "gn:timezone":"Asia/Tehran",
    "iso:country":"IR",
    "name:fas_x_preferred":[
        "\u0628\u06cc\u0631"
    ],
    "name:fas_x_variant":[
        "B\u012br"
    ],
    "name:msa_x_preferred":[
        "Bir"
    ],
    "wof:name":"Bir",
    "wof:placetype":"locality"
},
  "geometry": {"coordinates":[53.2247,28.9319],"type":"Point"}
}