{
  "type": "Feature",
  "properties": {
    "gn:admin1_code":"15",
    "gn:asciiname":"Dehlaviyeh",
    "gn:country_code":"IR",
    "gn:dem":12,
    "gn:feature_class":"P",
    "gn:feature_code":"PPL",
    "gn:name":"Dehl\u0101v\u012byeh",
    "gn:population":0,
    "gn:timezone":"Asia/Tehran",
    "iso:country":"IR",
    "name:ceb_x_preferred":[
        "Dehl\u0101v\u012byeh"
    ],
    "name:fas_x_preferred":[
        "\u062f\u0647\u0644\u0627\u0648\u06cc\u0647"
    ],
    "name:fas_x_variant":[
        "Dehl\u0101v\u012byeh"
    ],
    "name:fra_x_preferred":[
        "Dehlaviyeh"
    ],
    "name:swe_x_preferred":[
        "Dehl\u0101v\u012byeh"
    ],
    "name:und_x_variant":[
        "Dehl\u0101yeh"
    ],
    "wof:name":"Dehlaviyeh",
    "wof:placetype":"locality"
},
  "geometry": {"coordinates":[48.0847,31.6351],"type":"Point"}
}