{
  "type": "Feature",
  "properties": {
    "gn:admin1_code":"8",
    "gn:asciiname":"Tabar Kalayeh",
    "gn:country_code":"IR",
    "gn:dem":1,
    "gn:feature_class":"P",
    "gn:feature_code":"PPL",
    "gn:name":"Tabar Kal\u0101yeh",
    "gn:population":0,
    "gn:timezone":"Asia/Tehran",
    "iso:country":"IR",
    "name:ceb_x_preferred":[
        "Tabar Kal\u0101-ye Gelr\u016bdb\u0101r"
    ],
    "name:fas_x_preferred":[
        "Tabar Kal\u0101yeh"
    ],
    "name:fas_x_variant":[
        "\u062a\u0628\u0631\u06a9\u0644\u0627\u06cc\u0647"
    ],
    "name:msa_x_preferred":[
        "Tabar Kalayeh"
    ],
    "name:swe_x_preferred":[
        "Tabar Kal\u0101-ye Gelr\u016bdb\u0101r"
    ],
    "name:ukr_x_preferred":[
        "\u0422\u0430\u0431\u0430\u0440-\u041a\u0430\u043b\u0430\u0454"
    ],
    "wof:name":"Tabar Kalayeh",
    "wof:placetype":"locality"
},
  "geometry": {"coordinates":[49.91611,37.20583],"type":"Point"}
}