{
  "type": "Feature",
  "properties": {
    "gn:admin1_code":"8",
    "gn:asciiname":"Tabar Kalayeh",
    "gn:country_code":"IR",
    "gn:dem":1,
    "gn:feature_class":"P",
    "gn:feature_code":"PPL",
    "gn:name":"Tabar Kal\u0101yeh",
    "gn:population":0,
    "gn:timezone":"Asia/Tehran",
    "iso:country":"IR",
    "name:fas_x_preferred":[
        "Tabar Kal\u0101yeh"
    ],
    "wof:name":"Tabar Kalayeh",
    "wof:placetype":"locality"
},
  "geometry": {"coordinates":[49.91611,37.20583],"type":"Point"}
}