{
  "type": "Feature",
  "properties": {
    "gn:admin1_code":"15.0",
    "gn:asciiname":"Babol-e Seyyed Gatush",
    "gn:country_code":"IR",
    "gn:dem":116,
    "gn:feature_class":"P",
    "gn:feature_code":"PPL",
    "gn:name":"B\u0101bol-e Seyyed Gat\u016bsh",
    "gn:population":0,
    "gn:timezone":"Asia/Tehran",
    "iso:country":"IR",
    "name:fas_x_preferred":[
        "\u0633\u06cc\u0651\u062f \u06af\u0634\u0651\u06cc\u0634"
    ],
    "name:fas_x_variant":[
        "\u0628\u0627\u0628\u0644 \u0633\u06cc\u062f \u06af\u062a\u0648\u0634",
        "\u0633\u06cc\u062f \u06af\u062a\u0648\u0634"
    ],
    "name:und_x_variant":[
        "Seyyed Goshsheysh",
        "B\u0101bol-e Seyyed Gat\u016bsh",
        "Seyyed Gat\u016bsh"
    ],
    "wof:name":"Babol-e Seyyed Gatush",
    "wof:placetype":"locality"
},
  "geometry": {"coordinates":[49.61025,31.16569],"type":"Point"}
}