{
  "type": "Feature",
  "properties": {
    "gn:admin1_code":"26.0",
    "gn:asciiname":"Javadiyeh",
    "gn:country_code":"IR",
    "gn:dem":1105,
    "gn:feature_class":"P",
    "gn:feature_code":"PPL",
    "gn:name":"Jav\u0101d\u012byeh",
    "gn:population":0,
    "gn:timezone":"Asia/Tehran",
    "iso:country":"IR",
    "name:fas_x_preferred":[
        "\u062c\u0648\u0627\u062f\u064a\u0647"
    ],
    "name:fas_x_variant":[
        "\u062c\u064e\u0648\u0627\u062f\u064a\u0651\u064a\u0650\u0647",
        "Jav\u0101d\u012byeh"
    ],
    "name:und_x_variant":[
        "Jav\u0101d\u012byyeh"
    ],
    "wof:name":"Javadiyeh",
    "wof:placetype":"locality"
},
  "geometry": {"coordinates":[51.3869,35.6493],"type":"Point"}
}