{
  "type": "Feature",
  "properties": {
    "gn:admin1_code":"26.0",
    "gn:asciiname":"Chal Tarkhan",
    "gn:country_code":"IR",
    "gn:dem":991,
    "gn:feature_class":"P",
    "gn:feature_code":"PPL",
    "gn:name":"Ch\u0101l Tarkh\u0101n",
    "gn:population":0,
    "gn:timezone":"Asia/Tehran",
    "iso:country":"IR",
    "name:ceb_x_preferred":[
        "Ch\u0101l \u0162arkh\u0101n"
    ],
    "name:fas_x_preferred":[
        "\u0686\u0627\u0644 \u062a\u064e\u0631\u062e\u0627\u0646"
    ],
    "name:fas_x_variant":[
        "Ch\u0101leh \u0162arkh\u0101n",
        "Ch\u0101l \u0162arkh\u0101n",
        "\u0686\u0627\u0644\u0647 \u0637\u0631\u062e\u0627\u0646"
    ],
    "name:swe_x_preferred":[
        "Ch\u0101l \u0162arkh\u0101n"
    ],
    "name:und_x_variant":[
        "Ch\u0101h \u0162arkh\u0101n"
    ],
    "wof:name":"Chal Tarkhan",
    "wof:placetype":"locality"
},
  "geometry": {"coordinates":[51.47778,35.50028],"type":"Point"}
}