{
  "type": "Feature",
  "properties": {
    "gn:admin1_code":"15",
    "gn:asciiname":"Bahar",
    "gn:country_code":"IR",
    "gn:dem":14,
    "gn:feature_class":"P",
    "gn:feature_code":"PPL",
    "gn:name":"Ba\u1e29ar",
    "gn:population":0,
    "gn:timezone":"Asia/Tehran",
    "iso:country":"IR",
    "name:aze_x_preferred":[
        "Bahar"
    ],
    "name:bel_x_preferred":[
        "\u0411\u0430\u0445\u0430\u0440"
    ],
    "name:cat_x_preferred":[
        "Bahar"
    ],
    "name:ceb_x_preferred":[
        "Bahar"
    ],
    "name:deu_x_preferred":[
        "Bahar"
    ],
    "name:fas_x_preferred":[
        "Ba\u1e29ar"
    ],
    "name:fas_x_variant":[
        "\u0628\u062d\u0631",
        "\u0628\u0647\u0631",
        "\u0628\u0647\u0627\u0631"
    ],
    "name:fra_x_preferred":[
        "Bahar"
    ],
    "name:kat_x_preferred":[
        "\u10d1\u10d0\u10f0\u10d0\u10e0\u10d8"
    ],
    "name:pnb_x_preferred":[
        "\u0628\u06c1\u0627\u0631"
    ],
    "name:rus_x_preferred":[
        "\u0411\u0430\u0445\u0430\u0440"
    ],
    "name:swe_x_preferred":[
        "Bahar"
    ],
    "name:tur_x_preferred":[
        "Bahar"
    ],
    "name:und_x_variant":[
        "\u0628\u062d\u0631",
        "Bahar"
    ],
    "wof:name":"Bahar",
    "wof:placetype":"locality"
},
  "geometry": {"coordinates":[48.54838,31.17951],"type":"Point"}
}