{
  "type": "Feature",
  "properties": {
    "gn:admin1_code":"7",
    "gn:asciiname":"Rubahqan",
    "gn:country_code":"IR",
    "gn:dem":1570,
    "gn:feature_class":"P",
    "gn:feature_code":"PPL",
    "gn:name":"R\u016bbahq\u0101n",
    "gn:population":0,
    "gn:timezone":"Asia/Tehran",
    "iso:country":"IR",
    "name:fas_x_preferred":[
        "\u0631\u0648\u0628\u0647\u0642\u0627\u0646"
    ],
    "name:fas_x_variant":[
        "R\u016bbahq\u0101n"
    ],
    "name:msa_x_preferred":[
        "Rubahqan"
    ],
    "name:und_x_variant":[
        "Roobahghan",
        "R\u016bbehq\u0101n"
    ],
    "wof:name":"Rubahqan",
    "wof:placetype":"locality"
},
  "geometry": {"coordinates":[53.1553,29.6239],"type":"Point"}
}