{
  "type": "Feature",
  "properties": {
    "gn:admin1_code":"41.0",
    "gn:asciiname":"Shumeh",
    "gn:country_code":"IR",
    "gn:dem":1680,
    "gn:feature_class":"P",
    "gn:feature_code":"PPL",
    "gn:name":"Sh\u016bmeh",
    "gn:population":0,
    "gn:timezone":"Asia/Tehran",
    "iso:country":"IR",
    "name:ara_x_preferred":[
        "\u0634\u0648\u0645\u0629"
    ],
    "name:fas_x_preferred":[
        "\u0634\u0648\u0645\u0647"
    ],
    "name:fas_x_variant":[
        "Sh\u016bmeh",
        "Sh\u0101meh"
    ],
    "name:und_x_variant":[
        "Shommeh",
        "Sh\u0101meh",
        "Showmen",
        "Shameh"
    ],
    "wof:name":"Shumeh",
    "wof:placetype":"locality"
},
  "geometry": {"coordinates":[60.02558000000001,32.73183],"type":"Point"}
}