{
  "type": "Feature",
  "properties": {
    "gn:admin1_code":"29",
    "gn:asciiname":"Eslamabad",
    "gn:country_code":"IR",
    "gn:dem":1772,
    "gn:feature_class":"P",
    "gn:feature_code":"PPL",
    "gn:name":"Esl\u0101m\u0101b\u0101d",
    "gn:population":0,
    "gn:timezone":"Asia/Tehran",
    "iso:country":"IR",
    "name:ara_x_preferred":[
        "\u0625\u0633\u0644\u0627\u0645 \u0622\u0628\u0627\u062f"
    ],
    "name:fas_x_preferred":[
        "\u0627\u0633\u0644\u0627\u0645 \u0634\u0647\u0631 \u062a\u0646\u0628\u0648\u0631"
    ],
    "name:fas_x_variant":[
        "Esl\u0101m Shahr-e Tanb\u016br",
        "\u0627\u0633\u0644\u0627\u0645 \u0622\u0628\u0627\u062f",
        "\u0627\u0633\u0644\u0627\u0645\u200c\u0622\u0628\u0627\u062f"
    ],
    "name:und_x_variant":[
        "Esl\u0101m\u0101b\u0101d"
    ],
    "wof:name":"Eslamabad",
    "wof:placetype":"locality"
},
  "geometry": {"coordinates":[55.8307,29.4285],"type":"Point"}
}