{
  "type": "Feature",
  "properties": {
    "gn:admin1_code":"9",
    "gn:asciiname":"Kamangaran",
    "gn:country_code":"IR",
    "gn:dem":1701,
    "gn:feature_class":"P",
    "gn:feature_code":"PPL",
    "gn:name":"Kam\u0101ngar\u0101n",
    "gn:population":0,
    "gn:timezone":"Asia/Tehran",
    "iso:country":"IR",
    "name:fas_x_preferred":[
        "Kam\u0101ngar\u0101n"
    ],
    "name:fas_x_variant":[
        "\u06a9\u0645\u0627\u0646\u06af\u0631\u0627\u0646",
        "\u06a9\u0645\u0627\u0646 \u06af\u0631\u0627\u0646"
    ],
    "name:msa_x_preferred":[
        "Kamangaran"
    ],
    "wof:name":"Kamangaran",
    "wof:placetype":"locality"
},
  "geometry": {"coordinates":[48.14427,34.44883],"type":"Point"}
}