{
  "type": "Feature",
  "properties": {
    "gn:admin1_code":"35.0",
    "gn:asciiname":"Kashar Kheyl",
    "gn:country_code":"IR",
    "gn:dem":192,
    "gn:feature_class":"P",
    "gn:feature_code":"PPL",
    "gn:name":"Kashar Kheyl",
    "gn:population":0,
    "gn:timezone":"Asia/Tehran",
    "iso:country":"IR",
    "name:fas_x_preferred":[
        "\u0643\u064e\u0634\u064e\u0631 \u062e\u0650\u064a\u0644"
    ],
    "wof:name":"Kashar Kheyl",
    "wof:placetype":"locality"
},
  "geometry": {"coordinates":[53.63333000000001,36.68333],"type":"Point"}
}