{
  "type": "Feature",
  "properties": {
    "gn:admin1_code":"37",
    "gn:asciiname":"Shamushak-e Sofla",
    "gn:country_code":"IR",
    "gn:dem":156,
    "gn:feature_class":"P",
    "gn:feature_code":"PPL",
    "gn:name":"Sham\u016bshak-e Sofl\u00e1",
    "gn:population":0,
    "gn:timezone":"Asia/Tehran",
    "iso:country":"IR",
    "name:ara_x_preferred":[
        "\u0634\u0645\u0648\u0634\u0643 \u0633\u0641\u0644\u064a"
    ],
    "name:fas_x_preferred":[
        "Sham\u016bshak-e P\u0101\u2019\u012bn"
    ],
    "name:fas_x_variant":[
        "\u0634\u0645\u0648\u0634\u0643 \u067e\u0627\u0626\u064a\u0646",
        "\u0634\u0645\u0648\u0634\u06a9 \u0633\u0641\u0644\u06cc"
    ],
    "name:msa_x_preferred":[
        "Shamushak-e Sofla"
    ],
    "name:und_x_variant":[
        "Sham\u016bshak-e Sofl\u00e1"
    ],
    "wof:name":"Shamushak-e Sofla",
    "wof:placetype":"locality"
},
  "geometry": {"coordinates":[54.27231,36.77694],"type":"Point"}
}