{
  "type": "Feature",
  "properties": {
    "gn:admin1_code":"15.0",
    "gn:asciiname":"Boneh-ye `Alvan",
    "gn:country_code":"IR",
    "gn:dem":54,
    "gn:elevation":"0.0",
    "gn:feature_class":"P",
    "gn:feature_code":"PPL",
    "gn:name":"Boneh-ye \u2018Alv\u0101n",
    "gn:population":0,
    "gn:timezone":"Asia/Tehran",
    "iso:country":"IR",
    "name:ara_x_preferred":[
        "\u0639\u0644\u0648\u0627\u0646"
    ],
    "name:aze_x_preferred":[
        "\u018flvan"
    ],
    "name:ceb_x_preferred":[
        "Alv\u0101n"
    ],
    "name:fas_x_preferred":[
        "\u0627\u0644\u0648\u0627\u0646"
    ],
    "name:fas_x_variant":[
        "\u2018Alv\u0101n",
        "Alv\u0101n",
        "\u0628\u0646\u0647 \u0639\u0644\u0648\u0627\u0646"
    ],
    "name:ita_x_preferred":[
        "Alvan"
    ],
    "name:mlg_x_preferred":[
        "Alvan"
    ],
    "name:rus_x_preferred":[
        "\u0410\u043b\u0432\u0430\u043d"
    ],
    "name:swe_x_preferred":[
        "Alv\u0101n"
    ],
    "name:und_x_variant":[
        "Boneh-ye \u2018Alv\u0101n",
        "Boneh Alv\u0101n",
        "Boneh Alavan"
    ],
    "name:zho_x_preferred":[
        "\u963f\u723e\u842c"
    ],
    "wof:name":"Boneh-ye `Alvan",
    "wof:placetype":"locality"
},
  "geometry": {"coordinates":[48.45877,32.11171],"type":"Point"}
}