{
  "type": "Feature",
  "properties": {
    "gn:admin1_code":"8",
    "gn:asciiname":"Khomeyran",
    "gn:country_code":"IR",
    "gn:dem":-17,
    "gn:feature_class":"P",
    "gn:feature_code":"PPL",
    "gn:name":"Khomeyr\u0101n",
    "gn:population":0,
    "gn:timezone":"Asia/Tehran",
    "iso:country":"IR",
    "name:fas_x_preferred":[
        "\u0645\u0627\u0641\u0627\u0646"
    ],
    "name:fas_x_variant":[
        "Ma\u2018\u0101f",
        "M\u0101f\u0101n",
        "\u062e\u0645\u064a\u0631\u0627\u0646"
    ],
    "name:und_x_variant":[
        "Mafan",
        "Khomeyr\u0101n"
    ],
    "wof:name":"Khomeyran",
    "wof:placetype":"locality"
},
  "geometry": {"coordinates":[49.26818,37.49073],"type":"Point"}
}