{
  "type": "Feature",
  "properties": {
    "gn:admin1_code":"35.0",
    "gn:asciiname":"Jamard",
    "gn:country_code":"IR",
    "gn:dem":2119,
    "gn:feature_class":"P",
    "gn:feature_code":"PPL",
    "gn:name":"Jamard",
    "gn:population":0,
    "gn:timezone":"Asia/Tehran",
    "iso:country":"IR",
    "name:fas_x_preferred":[
        "\u062c\u0645\u0631\u062f"
    ],
    "name:und_x_variant":[
        "\u062c\u0645\u0631\u062f"
    ],
    "wof:name":"Jamard",
    "wof:placetype":"locality"
},
  "geometry": {"coordinates":[50.96045,36.58089],"type":"Point"}
}