{
  "type": "Feature",
  "properties": {
    "gn:admin1_code":"28",
    "gn:asciiname":"Mazra`eh-ye Hajji Baqer",
    "gn:country_code":"IR",
    "gn:dem":1352,
    "gn:feature_class":"P",
    "gn:feature_code":"PPL",
    "gn:name":"Mazra\u2018eh-ye \u1e28\u0101jj\u012b B\u0101qer",
    "gn:population":0,
    "gn:timezone":"Asia/Tehran",
    "iso:country":"IR",
    "name:fas_x_preferred":[
        "Mazra\u2018eh-ye \u1e28\u0101jj\u012b B\u0101qer"
    ],
    "name:fas_x_variant":[
        "\u0645\u0632\u0631\u0639\u0647 \u062d\u0627\u062c\u06cc \u0628\u0627\u0642\u0631",
        "Mazra\u2018eh-ye \u1e28\u0101j\u012b B\u0101qer"
    ],
    "wof:name":"Mazra`eh-ye Hajji Baqer",
    "wof:placetype":"locality"
},
  "geometry": {"coordinates":[53.64744,33.42703],"type":"Point"}
}