{
  "type": "Feature",
  "properties": {
    "gn:admin1_code":"29",
    "gn:asciiname":"Kalutan",
    "gn:country_code":"IR",
    "gn:dem":735,
    "gn:feature_class":"P",
    "gn:feature_code":"PPL",
    "gn:name":"Kal\u016bt\u0101n",
    "gn:population":0,
    "gn:timezone":"Asia/Tehran",
    "iso:country":"IR",
    "name:fas_x_preferred":[
        "\u06a9\u0644\u0648\u062a\u0627\u0646"
    ],
    "name:fas_x_variant":[
        "Kal\u016bt\u0101n"
    ],
    "wof:name":"Kalutan",
    "wof:placetype":"locality"
},
  "geometry": {"coordinates":[57.7021,27.6649],"type":"Point"}
}