{
  "type": "Feature",
  "properties": {
    "gn:admin1_code":"32",
    "gn:asciiname":"Ojaq",
    "gn:country_code":"IR",
    "gn:dem":567,
    "gn:feature_class":"P",
    "gn:feature_code":"PPL",
    "gn:name":"Oj\u0101q",
    "gn:population":0,
    "gn:timezone":"Asia/Tehran",
    "iso:country":"IR",
    "name:ara_x_preferred":[
        "\u0623\u0648\u062c\u0627\u0642 \u0623\u0644\u0632\u0627\u0631"
    ],
    "name:azb_x_preferred":[
        "\u0622\u0644 \u0642\u0627\u0646\u0648"
    ],
    "name:ceb_x_preferred":[
        "Oj\u0101q"
    ],
    "name:fas_x_preferred":[
        "\u0627\u062c\u0627\u0642"
    ],
    "name:fas_x_variant":[
        "Oj\u0101q \u0100l\u0101z\u0101r",
        "Oj\u0101q",
        "\u0627\u0648\u062c\u0627\u0642 \u0622\u0644\u0627\u0632\u0627\u0631"
    ],
    "name:msa_x_preferred":[
        "Ojaq Alazar"
    ],
    "name:und_x_variant":[
        "Alazar",
        "\u0100lz\u0304ar"
    ],
    "wof:name":"Ojaq",
    "wof:placetype":"locality"
},
  "geometry": {"coordinates":[48.1689,39.07],"type":"Point"}
}