{
  "type": "Feature",
  "properties": {
    "gn:admin1_code":"9",
    "gn:asciiname":"Taveh",
    "gn:country_code":"IR",
    "gn:dem":1637,
    "gn:feature_class":"P",
    "gn:feature_code":"PPL",
    "gn:name":"\u0162\u0101veh",
    "gn:population":0,
    "gn:timezone":"Asia/Tehran",
    "iso:country":"IR",
    "name:ara_x_preferred":[
        "\u062a\u0627\u0648\u0629"
    ],
    "name:fas_x_preferred":[
        "\u0637\u0627\u0648\u0647"
    ],
    "name:fas_x_variant":[
        "\u0162\u0101veh",
        "\u062a\u0627\u0648\u0647"
    ],
    "name:msa_x_preferred":[
        "Taveh"
    ],
    "name:und_x_variant":[
        "T\u0101weh",
        "T\u0101veh"
    ],
    "wof:name":"Taveh",
    "wof:placetype":"locality"
},
  "geometry": {"coordinates":[49.02784000000001,35.1169],"type":"Point"}
}