{
  "type": "Feature",
  "properties": {
    "gn:admin1_code":"35.0",
    "gn:asciiname":"Banulu",
    "gn:country_code":"IR",
    "gn:dem":2590,
    "gn:feature_class":"P",
    "gn:feature_code":"PPL",
    "gn:name":"B\u0101n\u016bl\u016b",
    "gn:population":0,
    "gn:timezone":"Asia/Tehran",
    "iso:country":"IR",
    "name:fas_x_preferred":[
        "\u0628\u0627\u0646\u0648\u0644\u0648"
    ],
    "name:fas_x_variant":[
        "B\u0101n\u016bl\u016b"
    ],
    "wof:name":"Banulu",
    "wof:placetype":"locality"
},
  "geometry": {"coordinates":[52.06546,36.26785],"type":"Point"}
}