{
  "type": "Feature",
  "properties": {
    "gn:admin1_code":"42",
    "gn:asciiname":"Farimaneh",
    "gn:country_code":"IR",
    "gn:dem":1512,
    "gn:feature_class":"P",
    "gn:feature_code":"PPL",
    "gn:name":"Far\u012bm\u0101neh",
    "gn:population":0,
    "gn:timezone":"Asia/Tehran",
    "iso:country":"IR",
    "name:fas_x_preferred":[
        "Far\u012bm\u0101neh"
    ],
    "name:fas_x_variant":[
        "\u0641\u0631\u06cc\u0645\u0627\u0646\u0647",
        "Far\u012bm\u0101n"
    ],
    "wof:name":"Farimaneh",
    "wof:placetype":"locality"
},
  "geometry": {"coordinates":[57.11179,36.56816],"type":"Point"}
}