{
  "type": "Feature",
  "properties": {
    "gn:admin1_code":"7",
    "gn:asciiname":"Shokrabad",
    "gn:country_code":"IR",
    "gn:dem":1609,
    "gn:feature_class":"P",
    "gn:feature_code":"PPL",
    "gn:name":"Shokr\u0101b\u0101d",
    "gn:population":0,
    "gn:timezone":"Asia/Tehran",
    "iso:country":"IR",
    "name:fas_x_preferred":[
        "\u0634\u06a9\u0631 \u0622\u0628\u0627\u062f"
    ],
    "name:fas_x_variant":[
        "Shokr\u0101b\u0101d"
    ],
    "wof:name":"Shokrabad",
    "wof:placetype":"locality"
},
  "geometry": {"coordinates":[55.3067,28.5281],"type":"Point"}
}