{
  "type": "Feature",
  "properties": {
    "gn:admin1_code":"4.0",
    "gn:asciiname":"Zaboli",
    "gn:country_code":"IR",
    "gn:dem":1274,
    "gn:feature_class":"P",
    "gn:feature_code":"PPLA2",
    "gn:name":"Z\u0101bol\u012b",
    "gn:population":0,
    "gn:timezone":"Asia/Tehran",
    "iso:country":"IR",
    "name:fas_x_preferred":[
        "\u0632\u0627\u0628\u0644\u06cc"
    ],
    "name:fas_x_variant":[
        "Z\u0101bol\u012b",
        "\u0645\u0647\u0631\u0633\u062a\u0627\u0646"
    ],
    "name:und_x_variant":[
        "Qal\u2018eh-ye Z\u0101bol\u012b",
        "Magas",
        "Mehrest\u0101n"
    ],
    "wof:name":"Zaboli",
    "wof:placetype":"locality"
},
  "geometry": {"coordinates":[61.67445,27.131],"type":"Point"}
}