{
  "type": "Feature",
  "properties": {
    "gn:admin1_code":"5",
    "gn:asciiname":"Mirabad",
    "gn:country_code":"IR",
    "gn:dem":2187,
    "gn:feature_class":"P",
    "gn:feature_code":"PPL",
    "gn:name":"M\u012br\u0101b\u0101d",
    "gn:population":0,
    "gn:timezone":"Asia/Tehran",
    "iso:country":"IR",
    "name:aze_x_preferred":[
        "Mirabad"
    ],
    "name:ceb_x_preferred":[
        "Mirabad"
    ],
    "name:fas_x_preferred":[
        "M\u012br\u0101b\u0101d"
    ],
    "name:fas_x_variant":[
        "\u0645\u06cc\u0631 \u0622\u0628\u0627\u062f",
        "\u0645\u06cc\u0631\u0622\u0628\u0627\u062f"
    ],
    "name:swe_x_preferred":[
        "Mirabad"
    ],
    "name:und_x_variant":[
        "\u0645\u06cc\u0631 \u0622\u0628\u0627\u062f"
    ],
    "wof:name":"Mirabad",
    "wof:placetype":"locality"
},
  "geometry": {"coordinates":[51.70172,30.46804],"type":"Point"}
}