{
  "type": "Feature",
  "properties": {
    "gn:admin1_code":"29.0",
    "gn:asciiname":"Ab Panguyeh",
    "gn:country_code":"IR",
    "gn:dem":1928,
    "gn:feature_class":"P",
    "gn:feature_code":"PPL",
    "gn:name":"\u0100b Pang\u016byeh",
    "gn:population":0,
    "gn:timezone":"Asia/Tehran",
    "iso:country":"IR",
    "name:fas_x_preferred":[
        "\u0100bpang\u016b\u2019\u012byeh"
    ],
    "name:fas_x_variant":[
        "\u0100b Pang\u016byeh",
        "\u0622\u0628 \u067e\u0646\u06af\u0648\u06cc\u0647",
        "Op\u0101ng"
    ],
    "name:und_x_variant":[
        "Op\u0101ng",
        "Ab Pangooeyeh",
        "\u0622\u0628 \u067e\u0646\u06af\u0648\u06cc\u0647"
    ],
    "wof:name":"Ab Panguyeh",
    "wof:placetype":"locality"
},
  "geometry": {"coordinates":[56.65753,30.83609],"type":"Point"}
}