{
  "type": "Feature",
  "properties": {
    "gn:admin1_code":"15.0",
    "gn:asciiname":"Abu Tabareh-ye Yek",
    "gn:country_code":"IR",
    "gn:dem":88,
    "gn:feature_class":"P",
    "gn:feature_code":"PPL",
    "gn:name":"Ab\u016b \u0162ab\u0101reh-ye Yek",
    "gn:population":0,
    "gn:timezone":"Asia/Tehran",
    "iso:country":"IR",
    "name:aze_x_preferred":[
        "\u018fbu T\u0259bar\u0259-yi yek"
    ],
    "name:fas_x_preferred":[
        "\u0627\u0628\u0648 \u062a\u0628\u0627\u0631\u0647"
    ],
    "name:fas_x_variant":[
        "Ab\u016b Tab\u0101reh",
        "\u0627\u0628\u0648 \u0637\u0628\u0627\u0631\u0647 \u06cc\u06a9",
        "\u0627\u0628\u0648\u0637\u0628\u0627\u0631\u0647 \u06cc\u06a9"
    ],
    "name:und_x_variant":[
        "Abootabareh",
        "Ab\u016b \u0162ab\u0101reh-ye Yek"
    ],
    "wof:name":"Abu Tabareh-ye Yek",
    "wof:placetype":"locality"
},
  "geometry": {"coordinates":[49.23907,31.59983],"type":"Point"}
}