{
  "type": "Feature",
  "properties": {
    "gn:admin1_code":"42.0",
    "gn:asciiname":"Sar Cheshmeh Berashk",
    "gn:country_code":"IR",
    "gn:dem":1386,
    "gn:feature_class":"P",
    "gn:feature_code":"PPL",
    "gn:name":"Sar Cheshmeh Ber\u0101shk",
    "gn:population":0,
    "gn:timezone":"Asia/Tehran",
    "iso:country":"IR",
    "name:fas_x_preferred":[
        "\u0633\u0631\u0686\u0634\u0645\u0647 \u0628\u0631\u0627\u0634\u06a9"
    ],
    "name:fas_x_variant":[
        "Mo\u1e29ammad\u0101b\u0101d-e Sar Cheshmeh",
        "Sar Cheshmeh Ber\u0101shk"
    ],
    "name:und_x_variant":[
        "Mohammad \u0100b\u0101d",
        "Sar-i-Chashmeh",
        "Sar Chashmeh",
        "Sar Cheshmeh"
    ],
    "wof:name":"Sar Cheshmeh Berashk",
    "wof:placetype":"locality"
},
  "geometry": {"coordinates":[60.38011,35.70121],"type":"Point"}
}