{
  "type": "Feature",
  "properties": {
    "gn:admin1_code":"16",
    "gn:asciiname":"Jahad-e Sazandegi",
    "gn:country_code":"IR",
    "gn:dem":1474,
    "gn:feature_class":"P",
    "gn:feature_code":"PPL",
    "gn:name":"Jah\u0101d-e S\u0101zandeg\u012b",
    "gn:population":0,
    "gn:timezone":"Asia/Tehran",
    "iso:country":"IR",
    "name:fas_x_preferred":[
        "\u062c\u064e\u0647\u0627\u062f\u0650 \u0633\u0627\u0632\u064e\u0646\u062f\u0650\u06af\u06cc"
    ],
    "name:fas_x_variant":[
        "Jah\u0101d-e S\u0101zandeg\u012b"
    ],
    "wof:name":"Jahad-e Sazandegi",
    "wof:placetype":"locality"
},
  "geometry": {"coordinates":[46.95,34.76667],"type":"Point"}
}