{
  "type": "Feature",
  "properties": {
    "gn:admin1_code":"13",
    "gn:asciiname":"Sufiyehvand",
    "gn:country_code":"IR",
    "gn:dem":1355,
    "gn:feature_class":"P",
    "gn:feature_code":"PPL",
    "gn:name":"\u015e\u016bf\u012byehvand",
    "gn:population":0,
    "gn:timezone":"Asia/Tehran",
    "iso:country":"IR",
    "name:fas_x_preferred":[
        "\u0635\u0648\u0641\u06cc\u0647 \u0648\u0646\u062f"
    ],
    "name:fas_x_variant":[
        "\u015e\u016bf\u012bvand",
        "\u015e\u016bf\u012byehvand"
    ],
    "wof:name":"Sufiyehvand",
    "wof:placetype":"locality"
},
  "geometry": {"coordinates":[47.4537,34.2592],"type":"Point"}
}