{
  "type": "Feature",
  "properties": {
    "gn:admin1_code":"10",
    "gn:asciiname":"Gonbad Pir Mohammad",
    "gn:country_code":"IR",
    "gn:dem":886,
    "gn:feature_class":"P",
    "gn:feature_code":"PPL",
    "gn:name":"Gonbad P\u012br Mo\u1e29ammad",
    "gn:population":0,
    "gn:timezone":"Asia/Tehran",
    "iso:country":"IR",
    "name:fas_x_preferred":[
        "\u06af\u0646\u0628\u062f \u067e\u06cc\u0631 \u0645\u062d\u0645\u0651\u062f"
    ],
    "name:fas_x_variant":[
        "\u06af\u0646\u0628\u062f \u067e\u06cc\u0631\u0645\u062d\u0645\u062f"
    ],
    "name:msa_x_preferred":[
        "Gonbad-e Pir Mohammad"
    ],
    "name:und_x_variant":[
        "Em\u0101mz\u0101deh P\u012br Mo\u1e29ad",
        "\u012amamzade P\u012br Mohan",
        "Em\u0101mz\u0101deh P\u012br Mo\u1e29ammad",
        "\u012am\u0101mz\u0101deh P\u012br Mohad",
        "P\u012br Mo\u1e29ammad",
        "Gonbad P\u012br Mo\u1e29ammad"
    ],
    "wof:name":"Gonbad Pir Mohammad",
    "wof:placetype":"locality"
},
  "geometry": {"coordinates":[46.5406,33.25104],"type":"Point"}
}