{
  "type": "Feature",
  "properties": {
    "gn:admin1_code":"13",
    "gn:asciiname":"Zeynalan-e Sofla",
    "gn:country_code":"IR",
    "gn:dem":1352,
    "gn:feature_class":"P",
    "gn:feature_code":"PPL",
    "gn:name":"Zeynal\u0101n-e Sofl\u00e1",
    "gn:population":0,
    "gn:timezone":"Asia/Tehran",
    "iso:country":"IR",
    "name:fas_x_preferred":[
        "\u0632\u06cc\u0646\u0644\u0627\u0646 \u0633\u0641\u0644\u06cc"
    ],
    "name:und_x_variant":[
        "Zeynal\u0101n-e Sofl\u00e1"
    ],
    "wof:name":"Zeynalan-e Sofla",
    "wof:placetype":"locality"
},
  "geometry": {"coordinates":[47.0729,33.9489],"type":"Point"}
}