{
  "type": "Feature",
  "properties": {
    "iso:country":"IR",
    "name:ara_x_preferred":[
        "\u0628\u0627\u0628\u0644\u0633\u0631"
    ],
    "name:azb_x_preferred":[
        "\u0628\u0627\u0628\u0648\u0644\u0633\u0631"
    ],
    "name:aze_x_preferred":[
        "Babols\u0259r"
    ],
    "name:aze_x_variant":[
        "Bab\u00fcls\u0259r"
    ],
    "name:ceb_x_preferred":[
        "B\u0101bolsar"
    ],
    "name:ces_x_preferred":[
        "Babolsar"
    ],
    "name:deu_x_preferred":[
        "Babolsar"
    ],
    "name:eng_x_preferred":[
        "Babolsar"
    ],
    "name:epo_x_preferred":[
        "Babolsar"
    ],
    "name:fas_x_preferred":[
        "\u0628\u0627\u0628\u0644\u0633\u0631"
    ],
    "name:fas_x_variant":[
        "\u0645\u064e\u0634\u0647\u064e\u062f\u0633\u064e\u0631",
        "B\u0101bolsar"
    ],
    "name:fra_x_preferred":[
        "Babolsar"
    ],
    "name:gle_x_preferred":[
        "Babolsar"
    ],
    "name:glk_x_preferred":[
        "\u0628\u0627\u0628\u0644\u0633\u0631"
    ],
    "name:hin_x_preferred":[
        "\u092c\u093e\u092c\u094b\u0932\u0938\u0930"
    ],
    "name:hun_x_preferred":[
        "B\u00e1bolszar"
    ],
    "name:hye_x_preferred":[
        "\u0532\u0561\u0562\u0578\u056c\u057d\u0561\u0580"
    ],
    "name:ita_x_preferred":[
        "Babolsar"
    ],
    "name:kaz_x_preferred":[
        "\u0411\u0430\u0431\u043e\u043b\u044c\u0441\u0435\u0440"
    ],
    "name:mal_x_preferred":[
        "\u0d2c\u0d3e\u0d2c\u0d4b\u0d7d\u0d38\u0d7c"
    ],
    "name:mlg_x_preferred":[
        "Babolsar"
    ],
    "name:mzn_x_preferred":[
        "\u0628\u0627\u0628\u0644\u0633\u0631"
    ],
    "name:nan_x_preferred":[
        "Babolsar"
    ],
    "name:nld_x_preferred":[
        "Babolsar"
    ],
    "name:oss_x_preferred":[
        "\u0411\u0430\u0431\u043e\u043b\u044c\u0441\u0435\u0440"
    ],
    "name:pnb_x_preferred":[
        "\u0628\u0627\u0628\u0644\u0633\u0631"
    ],
    "name:pol_x_preferred":[
        "Babolsar"
    ],
    "name:ron_x_preferred":[
        "Babolsar"
    ],
    "name:rus_x_preferred":[
        "\u0411\u0430\u0431\u043e\u043b\u044c\u0441\u0435\u0440"
    ],
    "name:swe_x_preferred":[
        "B\u0101bolsar"
    ],
    "name:swe_x_variant":[
        "Babolsar"
    ],
    "name:tgk_x_preferred":[
        "\u0411\u043e\u0431\u0443\u043b\u0441\u0430\u0440"
    ],
    "name:tur_x_preferred":[
        "Babolser"
    ],
    "name:ukr_x_preferred":[
        "\u0411\u0430\u0431\u043e\u043b\u0441\u0430\u0440"
    ],
    "name:und_x_variant":[
        "Meshed-i-Sar"
    ],
    "name:zho_x_preferred":[
        "\u5df4\u535a\u52d2\u85a9\u723e"
    ],
    "qs:gn_country":"IR",
    "qs:gn_fcode":"PPL",
    "qs:gn_pop":48051,
    "qs:name":"Mashhad-i-Sar",
    "qs:name_adm0":"Iran",
    "qs:name_adm1":"Mazandaran",
    "qs:photos":10,
    "qs:photos_1k":2,
    "qs:photos_9k":1,
    "qs:photos_9r":1,
    "qs:photos_all":10,
    "qs:photos_sr":1,
    "qs:placetype":"Town",
    "qs:pop_sr":"7",
    "qs:woe_adm0":23424851,
    "wof:name":"Mashhad-i-Sar",
    "wof:placetype":"locality",
    "wof:population":48051
},
  "geometry": {"coordinates":[52.6576,36.70251],"type":"Point"}
}