{
  "type": "Feature",
  "properties": {
    "gn:admin1_code":"1",
    "gn:asciiname":"Satelmish-e Tupkhaneh",
    "gn:country_code":"IR",
    "gn:dem":1287,
    "gn:feature_class":"P",
    "gn:feature_code":"PPL",
    "gn:name":"S\u0101telm\u012bsh-e T\u016bpkh\u0101neh",
    "gn:population":0,
    "gn:timezone":"Asia/Tehran",
    "iso:country":"IR",
    "name:azb_x_preferred":[
        "\u0633\u0627\u062a\u06cc\u0644\u0645\u06cc\u0634\u200c\u062a\u0648\u0652\u067e\u062e\u0627\u0646\u0627(\u0642\u0648\u0634\u0627\u0686\u0627\u06cc)"
    ],
    "name:aze_x_preferred":[
        "Sat\u0131lm\u0131\u015f-i Topxana"
    ],
    "name:ceb_x_preferred":[
        "S\u0101telm\u012bsh-e T\u016bpkh\u0101neh"
    ],
    "name:fas_x_preferred":[
        "\u0633\u0627\u062a\u0644\u0645\u06cc\u0634 \u062a\u0648\u067e\u062e\u0627\u0646\u0647"
    ],
    "name:fas_x_variant":[
        "S\u0101telm\u012bsh-e T\u016bpkh\u0101neh",
        "\u0633\u0627\u062a\u0644\u0645\u06cc\u0634\u200c\u062a\u0648\u067e\u062e\u0627\u0646\u0647"
    ],
    "name:msa_x_preferred":[
        "Satelmish-e Tupkhaneh"
    ],
    "name:swe_x_preferred":[
        "S\u0101telm\u012bsh-e T\u016bpkh\u0101neh"
    ],
    "wof:name":"Satelmish-e Tupkhaneh",
    "wof:placetype":"locality"
},
  "geometry": {"coordinates":[46.03235,37.04838],"type":"Point"}
}