{
  "type": "Feature",
  "properties": {
    "gn:admin1_code":"1",
    "gn:asciiname":"Hasanabad-e `Olya",
    "gn:country_code":"IR",
    "gn:dem":1897,
    "gn:feature_class":"P",
    "gn:feature_code":"PPL",
    "gn:name":"\u1e28asan\u0101b\u0101d-e \u2018Oly\u0101",
    "gn:population":0,
    "gn:timezone":"Asia/Tehran",
    "iso:country":"IR",
    "name:fas_x_preferred":[
        "\u062d\u0633\u0646 \u0622\u0628\u0627\u062f \u0639\u0644\u06cc\u0627"
    ],
    "name:fas_x_variant":[
        "\u1e28asan\u0101b\u0101d",
        "\u1e28asan\u0101b\u0101d-e \u2018Oly\u0101"
    ],
    "wof:name":"Hasanabad-e `Olya",
    "wof:placetype":"locality"
},
  "geometry": {"coordinates":[44.8236,38.0163],"type":"Point"}
}