{
  "type": "Feature",
  "properties": {
    "gn:admin1_code":"4.0",
    "gn:asciiname":"Gonbad",
    "gn:country_code":"IR",
    "gn:dem":779,
    "gn:feature_class":"P",
    "gn:feature_code":"PPL",
    "gn:name":"Gonbad",
    "gn:population":0,
    "gn:timezone":"Asia/Tehran",
    "iso:country":"IR",
    "name:deu_x_preferred":[
        "Gonbad"
    ],
    "name:fas_x_preferred":[
        "\u06af\u0646\u0628\u062f"
    ],
    "name:tur_x_preferred":[
        "K\u00fcmbet"
    ],
    "wof:name":"Gonbad",
    "wof:placetype":"locality"
},
  "geometry": {"coordinates":[59.53813,26.45608],"type":"Point"}
}