{
  "type": "Feature",
  "properties": {
    "gn:admin1_code":"15.0",
    "gn:asciiname":"Chehel Derakht",
    "gn:country_code":"IR",
    "gn:dem":239,
    "gn:feature_class":"P",
    "gn:feature_code":"PPL",
    "gn:name":"Chehel Derakht",
    "gn:population":0,
    "gn:timezone":"Asia/Tehran",
    "iso:country":"IR",
    "name:fas_x_preferred":[
        "\u0622\u0628 \u0627\u0646\u062c\u06cc\u0631\u06a9"
    ],
    "name:fas_x_variant":[
        "\u0100b Anj\u012brak",
        "\u0686\u0647\u0644 \u062f\u0631\u062e\u062a",
        "\u0627\u0646\u062c\u06cc\u0631\u06a9"
    ],
    "name:und_x_variant":[
        "\u0100b-e Anj\u012brak-e \u2018Oly\u0101",
        "\u0100b-e Anj\u012brak",
        "Chehel Derakht",
        "Anj\u012brak",
        "\u015eafar\u0101b\u0101d",
        "\u0635\u0641\u0631 \u0622\u0628\u0627\u062f"
    ],
    "wof:name":"Chehel Derakht",
    "wof:placetype":"locality"
},
  "geometry": {"coordinates":[49.20531,32.0347],"type":"Point"}
}