{
  "type": "Feature",
  "properties": {
    "gn:admin1_code":"32",
    "gn:asciiname":"Darreh Nasiri",
    "gn:country_code":"IR",
    "gn:dem":580,
    "gn:feature_class":"P",
    "gn:feature_code":"PPL",
    "gn:name":"Darreh Na\u015f\u012br\u012b",
    "gn:population":0,
    "gn:timezone":"Asia/Tehran",
    "iso:country":"IR",
    "name:fas_x_preferred":[
        "Darreh Na\u015f\u012br\u012b"
    ],
    "name:fas_x_variant":[
        "\u062f\u064e\u0631\u0650\u0651\u0647 \u0646\u064e\u0635\u064a\u0631\u06cc"
    ],
    "wof:name":"Darreh Nasiri",
    "wof:placetype":"locality"
},
  "geometry": {"coordinates":[48.33333,39.03333],"type":"Point"}
}