{
  "type": "Feature",
  "properties": {
    "gn:admin1_code":"37",
    "gn:asciiname":"Shaftalu Bagh-e `Olya",
    "gn:country_code":"IR",
    "gn:dem":17,
    "gn:feature_class":"P",
    "gn:feature_code":"PPL",
    "gn:name":"Shaft\u0101l\u016b B\u0101gh-e \u2018Oly\u0101",
    "gn:population":0,
    "gn:timezone":"Asia/Tehran",
    "iso:country":"IR",
    "name:ara_x_preferred":[
        "\u0634\u0641\u062a\u0627\u0644\u0648\u0628\u0627\u063a \u0627\u0644\u0639\u0644\u064a\u0627"
    ],
    "name:fas_x_preferred":[
        "Shaft\u0101l\u016b B\u0101gh-e B\u0101l\u0101"
    ],
    "name:fas_x_variant":[
        "\u0634\u0641\u062a\u0627\u0644\u0648 \u0628\u0627\u063a \u0628\u0627\u0644\u0627",
        "\u0634\u0641\u062a\u0627\u0644\u0648 \u0628\u0627\u063a \u0639\u0644\u064a\u0627",
        "\u0634\u0641\u062a\u0627\u0644\u0648\u0628\u0627\u063a \u0639\u0644\u06cc\u0627"
    ],
    "name:msa_x_preferred":[
        "Shaftalu Bagh-e Olya"
    ],
    "name:und_x_variant":[
        "Shaft\u0101l\u016b B\u0101gh-e \u2018Oly\u0101"
    ],
    "wof:name":"Shaftalu Bagh-e `Olya",
    "wof:placetype":"locality"
},
  "geometry": {"coordinates":[54.66978,37.00963],"type":"Point"}
}