{
  "type": "Feature",
  "properties": {
    "gn:admin1_code":"16.0",
    "gn:asciiname":"Bagh-e Mir",
    "gn:country_code":"IR",
    "gn:dem":1888,
    "gn:feature_class":"P",
    "gn:feature_code":"PPL",
    "gn:name":"B\u0101gh-e M\u012br",
    "gn:population":0,
    "gn:timezone":"Asia/Tehran",
    "iso:country":"IR",
    "name:fas_x_preferred":[
        "\u0628\u0627\u063a \u0645\u06cc\u0631"
    ],
    "name:und_x_variant":[
        "B\u0101gh-e M\u012br"
    ],
    "wof:name":"Bagh-e Mir",
    "wof:placetype":"locality"
},
  "geometry": {"coordinates":[47.52971,35.76337],"type":"Point"}
}