{
  "type": "Feature",
  "properties": {
    "gn:admin1_code":"23",
    "gn:asciiname":"Bontang",
    "gn:country_code":"IR",
    "gn:dem":1155,
    "gn:feature_class":"P",
    "gn:feature_code":"PPL",
    "gn:name":"Bontang",
    "gn:population":0,
    "gn:timezone":"Asia/Tehran",
    "iso:country":"IR",
    "name:afr_x_preferred":[
        "Bontang"
    ],
    "name:ara_x_preferred":[
        "\u0628\u0648\u0646\u062a\u0627\u0646\u063a"
    ],
    "name:bug_x_preferred":[
        "Bontang"
    ],
    "name:ceb_x_preferred":[
        "Bontang"
    ],
    "name:fas_x_preferred":[
        "\u0628\u064f\u0646\u062a\u064e\u0646\u06af"
    ],
    "name:fas_x_variant":[
        "\u0628\u0648\u0646\u062a\u0627\u0646\u06af"
    ],
    "name:fra_x_preferred":[
        "Bontang"
    ],
    "name:ind_x_preferred":[
        "Kota Bontang"
    ],
    "name:ita_x_preferred":[
        "Bontang"
    ],
    "name:jav_x_preferred":[
        "Kutha Bontang"
    ],
    "name:jpn_x_preferred":[
        "\u30dc\u30f3\u30bf\u30f3"
    ],
    "name:mal_x_preferred":[
        "\u0d2c\u0d4b\u0d23\u0d4d\u0d1f\u0d3e\u0d19\u0d4d"
    ],
    "name:mlg_x_preferred":[
        "Kota Bontang"
    ],
    "name:msa_x_preferred":[
        "Kota Bontang"
    ],
    "name:nor_x_preferred":[
        "Bontang"
    ],
    "name:pol_x_preferred":[
        "Bontang"
    ],
    "name:rus_x_preferred":[
        "\u0411\u043e\u043d\u0442\u0430\u043d\u0433"
    ],
    "name:swe_x_preferred":[
        "Bontang"
    ],
    "name:tur_x_preferred":[
        "Bontang"
    ],
    "wof:name":"Bontang",
    "wof:placetype":"locality"
},
  "geometry": {"coordinates":[48.05,33.23333],"type":"Point"}
}