{
  "type": "Feature",
  "properties": {
    "gn:admin1_code":"23",
    "gn:asciiname":"Bontang",
    "gn:country_code":"IR",
    "gn:dem":1155,
    "gn:feature_class":"P",
    "gn:feature_code":"PPL",
    "gn:name":"Bontang",
    "gn:population":0,
    "gn:timezone":"Asia/Tehran",
    "iso:country":"IR",
    "name:fas_x_preferred":[
        "\u0628\u064f\u0646\u062a\u064e\u0646\u06af"
    ],
    "wof:name":"Bontang",
    "wof:placetype":"locality"
},
  "geometry": {"coordinates":[48.05,33.23333],"type":"Point"}
}