{
  "type": "Feature",
  "properties": {
    "gn:admin1_code":"4.0",
    "gn:asciiname":"Rudkhaneh-ye Fasli-ye Ab Anbar",
    "gn:country_code":"IR",
    "gn:dem":631,
    "gn:feature_class":"P",
    "gn:feature_code":"PPL",
    "gn:name":"R\u016bdkh\u0101neh-ye Fa\u015fl\u012b-ye \u0100b Anb\u0101r",
    "gn:population":0,
    "gn:timezone":"Asia/Tehran",
    "iso:country":"IR",
    "name:fas_x_preferred":[
        "\u0631\u0648\u062f\u062e\u0627\u0646\u0647 \u0641\u0635\u0644\u06cc \u0622\u0628 \u0627\u0646\u0628\u0627\u0631"
    ],
    "name:und_x_variant":[
        "R\u016bdkh\u0101neh-ye Fa\u015fl\u012b-ye \u0100b Anb\u0101r"
    ],
    "wof:name":"Rudkhaneh-ye Fasli-ye Ab Anbar",
    "wof:placetype":"locality"
},
  "geometry": {"coordinates":[59.06998000000001,26.73994],"type":"Point"}
}