{
  "type": "Feature",
  "properties": {
    "gn:admin1_code":"5",
    "gn:asciiname":"Kheyrabad-e Sofla",
    "gn:country_code":"IR",
    "gn:dem":371,
    "gn:feature_class":"P",
    "gn:feature_code":"PPL",
    "gn:name":"Kheyr\u0101b\u0101d-e Sofl\u00e1",
    "gn:population":0,
    "gn:timezone":"Asia/Tehran",
    "iso:country":"IR",
    "name:fas_x_preferred":[
        "\u062e\u064a\u0631\u0627\u0628\u0627\u062f \u067e\u0627\u0626\u064a\u0646"
    ],
    "name:fas_x_variant":[
        "Kheyr\u0101b\u0101d-e Sofl\u00e1",
        "Kheyr\u0101b\u0101d-e P\u0101\u2019\u012bn",
        "\u062e\u06cc\u0631 \u0622\u0628\u0627\u062f \u0633\u0641\u0644\u06cc"
    ],
    "name:und_x_variant":[
        "Khair\u0101b\u0101d",
        "Kheyr\u0101b\u0101d"
    ],
    "wof:name":"Kheyrabad-e Sofla",
    "wof:placetype":"locality"
},
  "geometry": {"coordinates":[50.43976,30.52714000000001],"type":"Point"}
}