{
  "type": "Feature",
  "properties": {
    "gn:admin1_code":"7",
    "gn:asciiname":"Berkeh-ye Sefid",
    "gn:country_code":"IR",
    "gn:dem":446,
    "gn:feature_class":"P",
    "gn:feature_code":"PPL",
    "gn:name":"Berkeh-ye Sef\u012bd",
    "gn:population":0,
    "gn:timezone":"Asia/Tehran",
    "iso:country":"IR",
    "name:fas_x_preferred":[
        "\u0628\u0631\u06a9\u0647 \u0633\u0641\u06cc\u062f"
    ],
    "name:fas_x_variant":[
        "Berkeh-ye Sef\u012bd"
    ],
    "name:msa_x_preferred":[
        "Berkeh-ye Sefid"
    ],
    "wof:name":"Berkeh-ye Sefid",
    "wof:placetype":"locality"
},
  "geometry": {"coordinates":[52.9299,27.7114],"type":"Point"}
}