{
  "type": "Feature",
  "properties": {
    "gn:admin1_code":"1",
    "gn:asciiname":"Chamanlu",
    "gn:country_code":"IR",
    "gn:dem":2230,
    "gn:feature_class":"P",
    "gn:feature_code":"PPL",
    "gn:name":"Chamanl\u016b",
    "gn:population":0,
    "gn:timezone":"Asia/Tehran",
    "iso:country":"IR",
    "name:fas_x_preferred":[
        "\u0686\u0645\u0646\u0644\u0648"
    ],
    "name:fas_x_variant":[
        "\u0686\u064e\u0645\u064e\u0646\u0644\u0648",
        "Chamanl\u016b"
    ],
    "wof:name":"Chamanlu",
    "wof:placetype":"locality"
},
  "geometry": {"coordinates":[44.5978,39.1723],"type":"Point"}
}