{
  "type": "Feature",
  "properties": {
    "gn:admin1_code":"35.0",
    "gn:asciiname":"Harabdeh",
    "gn:country_code":"IR",
    "gn:dem":-20,
    "gn:feature_class":"P",
    "gn:feature_code":"PPL",
    "gn:name":"\u1e28arabdeh",
    "gn:population":0,
    "gn:timezone":"Asia/Tehran",
    "iso:country":"IR",
    "name:ceb_x_preferred":[
        "\u1e28arabdeh"
    ],
    "name:fas_x_preferred":[
        "\u062d\u0631\u0628\u062f\u0647"
    ],
    "name:fas_x_variant":[
        "\u1e28arabdeh",
        "\u062d\u0631\u0628\u200c\u062f\u0647"
    ],
    "name:swe_x_preferred":[
        "\u1e28arabdeh"
    ],
    "wof:name":"Harabdeh",
    "wof:placetype":"locality"
},
  "geometry": {"coordinates":[52.29574,36.62428],"type":"Point"}
}