{
  "type": "Feature",
  "properties": {
    "gn:admin1_code":"7.0",
    "gn:asciiname":"Sabzu",
    "gn:country_code":"IR",
    "gn:dem":2004,
    "gn:feature_class":"P",
    "gn:feature_code":"PPL",
    "gn:name":"Sabz\u016b",
    "gn:population":0,
    "gn:timezone":"Asia/Tehran",
    "iso:country":"IR",
    "name:fas_x_preferred":[
        "Sabz\u016b"
    ],
    "wof:name":"Sabzu",
    "wof:placetype":"locality"
},
  "geometry": {"coordinates":[54.5975,29.05667],"type":"Point"}
}