{
  "type": "Feature",
  "properties": {
    "gn:admin1_code":"25",
    "gn:asciiname":"Hoseynabad-e Kordha",
    "gn:country_code":"IR",
    "gn:dem":846,
    "gn:feature_class":"P",
    "gn:feature_code":"PPL",
    "gn:name":"\u1e28oseyn\u0101b\u0101d-e Kordh\u0101",
    "gn:population":0,
    "gn:timezone":"Asia/Tehran",
    "iso:country":"IR",
    "name:fas_x_preferred":[
        "\u062d\u0633\u06cc\u0646 \u0622\u0628\u0627\u062f"
    ],
    "name:fas_x_variant":[
        "\u1e28oseyn\u0101b\u0101d",
        "\u062d\u0633\u06cc\u0646 \u0622\u0628\u0627\u062f \u06a9\u0631\u062f\u0647\u0627",
        "\u0631\u0633\u062a\u0645 \u0622\u0628\u0627\u062f"
    ],
    "name:und_x_variant":[
        "\u1e28oseyn\u0101b\u0101d-e Kordh\u0101",
        "Rostam\u0101b\u0101d"
    ],
    "wof:name":"Hoseynabad-e Kordha",
    "wof:placetype":"locality"
},
  "geometry": {"coordinates":[52.49944,35.20305],"type":"Point"}
}