{
  "type": "Feature",
  "properties": {
    "gn:admin1_code":"35.0",
    "gn:asciiname":"Sia Sar",
    "gn:country_code":"IR",
    "gn:dem":1874,
    "gn:feature_class":"P",
    "gn:feature_code":"PPL",
    "gn:name":"S\u012b\u0101 Sar",
    "gn:population":0,
    "gn:timezone":"Asia/Tehran",
    "iso:country":"IR",
    "name:fas_x_preferred":[
        "S\u012b\u0101 Sar"
    ],
    "name:fas_x_variant":[
        "S\u012b\u0101hsar",
        "\u0633\u064a\u0627 \u0633\u0631"
    ],
    "name:und_x_variant":[
        "\u0633\u064a\u0627 \u0633\u0631"
    ],
    "wof:name":"Sia Sar",
    "wof:placetype":"locality"
},
  "geometry": {"coordinates":[50.57356,36.79886],"type":"Point"}
}