{
  "type": "Feature",
  "properties": {
    "gn:admin1_code":"7",
    "gn:asciiname":"Kareh",
    "gn:cc2":"IR",
    "gn:country_code":"IR",
    "gn:dem":1404,
    "gn:feature_class":"P",
    "gn:feature_code":"PPL",
    "gn:name":"Kareh",
    "gn:population":0,
    "gn:timezone":"Asia/Tehran",
    "iso:country":"IR",
    "name:und_x_variant":[
        "Kereh",
        "Kareh"
    ],
    "wof:name":"Kareh",
    "wof:placetype":"locality"
},
  "geometry": {"coordinates":[54.08333,28.95],"type":"Point"}
}