{
  "type": "Feature",
  "properties": {
    "gn:admin1_code":"29",
    "gn:asciiname":"Kaviz-e `Olya",
    "gn:country_code":"IR",
    "gn:dem":1020,
    "gn:feature_class":"P",
    "gn:feature_code":"PPL",
    "gn:name":"Kav\u012bz-e \u2018Oly\u0101",
    "gn:population":0,
    "gn:timezone":"Asia/Tehran",
    "iso:country":"IR",
    "name:fas_x_preferred":[
        "\u06a9\u0648\u06cc\u0632 \u0639\u0644\u06cc\u0627"
    ],
    "name:fas_x_variant":[
        "Kav\u012bz-e \u2018Oly\u0101"
    ],
    "wof:name":"Kaviz-e `Olya",
    "wof:placetype":"locality"
},
  "geometry": {"coordinates":[58.2325,28.3313],"type":"Point"}
}