{
  "type": "Feature",
  "properties": {
    "gn:admin1_code":"7.0",
    "gn:asciiname":"Chahu",
    "gn:country_code":"IR",
    "gn:dem":1930,
    "gn:feature_class":"P",
    "gn:feature_code":"PPLF",
    "gn:name":"Ch\u0101h\u016b",
    "gn:population":0,
    "gn:timezone":"Asia/Tehran",
    "iso:country":"IR",
    "name:ceb_x_preferred":[
        "Chahu"
    ],
    "name:fas_x_preferred":[
        "\u0686\u0627\u0647\u0648"
    ],
    "name:swe_x_preferred":[
        "Chahu"
    ],
    "name:und_x_variant":[
        "Ch\u0101h\u016b"
    ],
    "wof:name":"Chahu",
    "wof:placetype":"locality"
},
  "geometry": {"coordinates":[52.36691,30.33916],"type":"Point"}
}