{
  "type": "Feature",
  "properties": {
    "gn:admin1_code":"28",
    "gn:asciiname":"Nasrabad",
    "gn:country_code":"IR",
    "gn:dem":867,
    "gn:feature_class":"P",
    "gn:feature_code":"PPL",
    "gn:name":"Na\u015fr\u0101b\u0101d",
    "gn:population":0,
    "gn:timezone":"Asia/Tehran",
    "iso:country":"IR",
    "name:fas_x_preferred":[
        "\u0646\u0635\u0631 \u0622\u0628\u0627\u062f"
    ],
    "name:fas_x_variant":[
        "Na\u015fr\u0101b\u0101d"
    ],
    "name:und_x_variant":[
        "Na\u015fr\u0101b\u0101d-e Kharb\u016bzeh"
    ],
    "wof:name":"Nasrabad",
    "wof:placetype":"locality"
},
  "geometry": {"coordinates":[51.3518,34.1265],"type":"Point"}
}