{
  "type": "Feature",
  "properties": {
    "gn:admin1_code":"35",
    "gn:asciiname":"Estarem",
    "gn:country_code":"IR",
    "gn:dem":1377,
    "gn:feature_class":"P",
    "gn:feature_code":"PPL",
    "gn:name":"Est\u0101rem",
    "gn:population":0,
    "gn:timezone":"Asia/Tehran",
    "iso:country":"IR",
    "name:fas_x_preferred":[
        "\u0627\u0650\u0633\u062a\u0627\u0631\u064e\u0645"
    ],
    "name:fas_x_variant":[
        "Est\u0101rem",
        "\u0627\u0633\u062a\u0627\u0631\u0645"
    ],
    "name:und_x_variant":[
        "Est\u0101ram"
    ],
    "wof:name":"Estarem",
    "wof:placetype":"locality"
},
  "geometry": {"coordinates":[53.90286,36.5619],"type":"Point"}
}