{
  "type": "Feature",
  "properties": {
    "gn:admin1_code":"35.0",
    "gn:asciiname":"Mahalleh-ye Larusar",
    "gn:country_code":"IR",
    "gn:dem":3,
    "gn:feature_class":"P",
    "gn:feature_code":"PPL",
    "gn:name":"Ma\u1e29alleh-ye L\u0101r\u016bsar",
    "gn:population":0,
    "gn:timezone":"Asia/Tehran",
    "iso:country":"IR",
    "name:fas_x_preferred":[
        "\u0645\u062d\u0644\u0647 \u0644\u0627\u0631\u0648\u0633\u0631"
    ],
    "name:und_x_variant":[
        "Ma\u1e29alleh-ye L\u0101r\u016bsar"
    ],
    "wof:name":"Mahalleh-ye Larusar",
    "wof:placetype":"locality"
},
  "geometry": {"coordinates":[51.25773,36.68088],"type":"Point"}
}