{
  "type": "Feature",
  "properties": {
    "gn:admin1_code":"35.0",
    "gn:asciiname":"Tazehabad",
    "gn:country_code":"IR",
    "gn:dem":332,
    "gn:feature_class":"P",
    "gn:feature_code":"PPL",
    "gn:name":"T\u0101zeh\u0101b\u0101d",
    "gn:population":0,
    "gn:timezone":"Asia/Tehran",
    "iso:country":"IR",
    "name:fas_x_preferred":[
        "T\u0101zeh\u0101b\u0101d"
    ],
    "name:fas_x_variant":[
        "\u062a\u0627\u0632\u0647 \u0622\u0628\u0627\u062f",
        "\u0646\u0639\u064a\u0645 \u0622\u0628\u0627\u062f"
    ],
    "name:und_x_variant":[
        "\u062a\u0627\u0632\u0647 \u0622\u0628\u0627\u062f",
        "Na\u2018\u012bm\u0101b\u0101d"
    ],
    "wof:name":"Tazehabad",
    "wof:placetype":"locality"
},
  "geometry": {"coordinates":[50.87074000000001,36.69085],"type":"Point"}
}