{
  "type": "Feature",
  "properties": {
    "gn:admin1_code":"35.0",
    "gn:asciiname":"Tazehabad",
    "gn:country_code":"IR",
    "gn:dem":332,
    "gn:feature_class":"P",
    "gn:feature_code":"PPL",
    "gn:name":"T\u0101zeh\u0101b\u0101d",
    "gn:population":0,
    "gn:timezone":"Asia/Tehran",
    "iso:country":"IR",
    "name:ara_x_preferred":[
        "\u062a\u0627\u0632\u0647 \u0623\u0628\u0627\u062f"
    ],
    "name:aze_x_preferred":[
        "T\u0259z\u0259abad"
    ],
    "name:ckb_x_preferred":[
        "\u062a\u0627\u0632\u0627\u0648\u0627\u06cc \u0633\u06d5\u0644\u0627\u0633"
    ],
    "name:fas_x_preferred":[
        "T\u0101zeh\u0101b\u0101d"
    ],
    "name:fas_x_variant":[
        "\u062a\u0627\u0632\u0647 \u0622\u0628\u0627\u062f",
        "\u0646\u0639\u064a\u0645 \u0622\u0628\u0627\u062f",
        "\u062a\u0627\u0632\u0647\u200c\u0622\u0628\u0627\u062f"
    ],
    "name:ita_x_preferred":[
        "Tazehabad"
    ],
    "name:mlg_x_preferred":[
        "Tazehabad"
    ],
    "name:mzn_x_preferred":[
        "\u062a\u0627\u0632\u0647\u200c\u0622\u0628\u0627\u062f"
    ],
    "name:rus_x_preferred":[
        "\u0422\u0430\u0437\u0435\u0445\u0430\u0431\u0430\u0434"
    ],
    "name:tur_x_preferred":[
        "Tazeabad"
    ],
    "name:und_x_variant":[
        "Na\u2018\u012bm\u0101b\u0101d"
    ],
    "name:zho_x_preferred":[
        "\u5854\u6fa4\u54c8\u5df4\u5fb7"
    ],
    "wof:name":"Tazehabad",
    "wof:placetype":"locality"
},
  "geometry": {"coordinates":[50.87074000000001,36.69085],"type":"Point"}
}