{
  "type": "Feature",
  "properties": {
    "gn:admin1_code":"9",
    "gn:asciiname":"Behkandan",
    "gn:country_code":"IR",
    "gn:dem":1752,
    "gn:feature_class":"P",
    "gn:feature_code":"PPL",
    "gn:name":"Behkand\u0101n",
    "gn:population":0,
    "gn:timezone":"Asia/Tehran",
    "iso:country":"IR",
    "name:fas_x_preferred":[
        "\u0628\u064f\u062d\u0643\u064e\u0646\u062f\u0627\u0646"
    ],
    "name:fas_x_variant":[
        "\u0628\u0648\u0643\u064e\u0646\u062f\u0627\u0646",
        "\u0628\u0647\u06a9\u0646\u062f\u0627\u0646",
        "Bo\u1e29kand\u0101n",
        "Behkand\u0101n"
    ],
    "name:msa_x_preferred":[
        "Behkandan"
    ],
    "name:und_x_variant":[
        "B\u016bkand\u0101n"
    ],
    "wof:name":"Behkandan",
    "wof:placetype":"locality"
},
  "geometry": {"coordinates":[49.09919,35.2727],"type":"Point"}
}