{
  "type": "Feature",
  "properties": {
    "gn:admin1_code":"29",
    "gn:asciiname":"Tam Gaz",
    "gn:country_code":"IR",
    "gn:dem":406,
    "gn:feature_class":"P",
    "gn:feature_code":"PPL",
    "gn:name":"Tam Gaz",
    "gn:population":0,
    "gn:timezone":"Asia/Tehran",
    "iso:country":"IR",
    "name:fas_x_preferred":[
        "\u062a\u0645 \u06af\u0632"
    ],
    "wof:name":"Tam Gaz",
    "wof:placetype":"locality"
},
  "geometry": {"coordinates":[57.8989,27.4529],"type":"Point"}
}