{
  "type": "Feature",
  "properties": {
    "gn:admin1_code":"23",
    "gn:asciiname":"Karfaleh",
    "gn:country_code":"IR",
    "gn:dem":1070,
    "gn:feature_class":"P",
    "gn:feature_code":"PPL",
    "gn:name":"Karfaleh",
    "gn:population":0,
    "gn:timezone":"Asia/Tehran",
    "iso:country":"IR",
    "name:fas_x_preferred":[
        "Karfaleh-ye \u2018Oly\u0101"
    ],
    "name:fas_x_variant":[
        "\u06a9\u0631\u0641\u0644\u0647 \u06cc\u06a9",
        "\u06a9\u0631\u0641\u0644\u0647"
    ],
    "name:und_x_variant":[
        "Karfaleh-ye Yek",
        "Kerfeleh-ye \u2018Oly\u0101",
        "Karfaleh"
    ],
    "wof:name":"Karfaleh",
    "wof:placetype":"locality"
},
  "geometry": {"coordinates":[48.1094,33.4906],"type":"Point"}
}