{
  "type": "Feature",
  "properties": {
    "gn:admin1_code":"15",
    "gn:asciiname":"Posht Kuh-e Roch",
    "gn:country_code":"IR",
    "gn:dem":606,
    "gn:feature_class":"P",
    "gn:feature_code":"PPL",
    "gn:name":"Posht K\u016bh-e Roch",
    "gn:population":0,
    "gn:timezone":"Asia/Tehran",
    "iso:country":"IR",
    "name:fas_x_preferred":[
        "\u0645\u0634\u0647\u062f\u06cc \u0639\u0628\u0627\u0633"
    ],
    "name:fas_x_variant":[
        "Mashhad\u012b \u2018Abb\u0101s",
        "\u067e\u0634\u062a \u06a9\u0648\u0647 \u0631\u0686",
        "\u062f\u0647 \u0645\u0634\u0647\u062f\u06cc \u0639\u0628\u0627\u0633"
    ],
    "name:und_x_variant":[
        "Posht K\u016bh-e Roch",
        "Deh-e Mashhad\u012b \u2018Abb\u0101s"
    ],
    "wof:name":"Posht Kuh-e Roch",
    "wof:placetype":"locality"
},
  "geometry": {"coordinates":[50.2571,30.7718],"type":"Point"}
}