{
  "type": "Feature",
  "properties": {
    "gn:admin1_code":"35.0",
    "gn:asciiname":"Sarfaqihabad",
    "gn:country_code":"IR",
    "gn:dem":16,
    "gn:feature_class":"P",
    "gn:feature_code":"PPL",
    "gn:name":"Sarfaq\u012bh\u0101b\u0101d",
    "gn:population":0,
    "gn:timezone":"Asia/Tehran",
    "iso:country":"IR",
    "name:ceb_x_preferred":[
        "Sarfaq\u012bh\u0101b\u0101d"
    ],
    "name:fas_x_preferred":[
        "Bandbon-e Qol\u012b"
    ],
    "name:fas_x_variant":[
        "\u0628\u0646\u062f\u0628\u0646 \u0642\u0644\u06cc",
        "\u0633\u0631\u0641\u0642\u06cc\u0647 \u0622\u0628\u0627\u062f",
        "\u0633\u0631\u0641\u0642\u06cc\u0647\u200c\u0622\u0628\u0627\u062f"
    ],
    "name:swe_x_preferred":[
        "Sarfaq\u012bh\u0101b\u0101d"
    ],
    "wof:name":"Sarfaqihabad",
    "wof:placetype":"locality"
},
  "geometry": {"coordinates":[51.03406,36.70181],"type":"Point"}
}