{
  "type": "Feature",
  "properties": {
    "gn:admin1_code":"8",
    "gn:asciiname":"Seh Tarabad",
    "gn:country_code":"IR",
    "gn:dem":102,
    "gn:feature_class":"P",
    "gn:feature_code":"PPL",
    "gn:name":"Seh T\u0101r\u0101b\u0101d",
    "gn:population":0,
    "gn:timezone":"Asia/Tehran",
    "iso:country":"IR",
    "name:fas_x_preferred":[
        "Satt\u0101r\u0101b\u0101d"
    ],
    "name:fas_x_variant":[
        "\u0633\u062a\u0627\u0631 \u0622\u0628\u0627\u062f",
        "\u0633\u0647 \u062a\u0627\u0631 \u0622\u0628\u0627\u062f"
    ],
    "name:und_x_variant":[
        "\u0633\u062a\u0627\u0631 \u0622\u0628\u0627\u062f",
        "Seh T\u0101r\u0101b\u0101d"
    ],
    "wof:name":"Seh Tarabad",
    "wof:placetype":"locality"
},
  "geometry": {"coordinates":[50.07935,37.14027],"type":"Point"}
}