{
  "type": "Feature",
  "properties": {
    "gn:admin1_code":"10",
    "gn:asciiname":"Nesar Karzan-e Sofla",
    "gn:cc2":"IR",
    "gn:country_code":"IR",
    "gn:dem":1326,
    "gn:feature_class":"P",
    "gn:feature_code":"PPL",
    "gn:name":"Nes\u0101r K\u0101rz\u0101n-e Sofl\u00e1",
    "gn:population":0,
    "gn:timezone":"Asia/Tehran",
    "iso:country":"IR",
    "name:fas_x_preferred":[
        "\u0643\u0627\u0646\u0626 \u0643\u0627\u0631\u064e\u0632\u0627\u0646"
    ],
    "name:fas_x_variant":[
        "Nes\u0101r K\u0101rz\u0101n-e Sofl\u00e1",
        "\u0646\u0650\u0633\u0627\u0631 \u0643\u0627\u0631\u0632\u0627\u0646\u0650 \u0633\u064f\u0641\u0644\u064e\u0649",
        "\u062a\u0627\u0631\u0632\u0627\u0646\u0650 \u0633\u064f\u0641\u0644\u064e\u0649"
    ],
    "name:und_x_variant":[
        "K\u0101n\u012b-ye K\u0101raz\u0101n",
        "T\u0101rz\u0101n-e Sofl\u00e1",
        "Kani Karazan"
    ],
    "wof:name":"Nesar Karzan-e Sofla",
    "wof:placetype":"locality"
},
  "geometry": {"coordinates":[46.48333,33.73333],"type":"Point"}
}