{
  "type": "Feature",
  "properties": {
    "gn:admin1_code":"35.0",
    "gn:asciiname":"Surbin-e Shomali",
    "gn:country_code":"IR",
    "gn:dem":53,
    "gn:feature_class":"P",
    "gn:feature_code":"PPL",
    "gn:name":"S\u016brb\u012bn-e Shom\u0101l\u012b",
    "gn:population":0,
    "gn:timezone":"Asia/Tehran",
    "iso:country":"IR",
    "name:fas_x_preferred":[
        "\u0633\u0648\u0631\u0628\u06cc\u0646 \u0634\u0645\u0627\u0644\u06cc"
    ],
    "name:und_x_variant":[
        "S\u016brb\u012bn-e Shom\u0101l\u012b"
    ],
    "wof:name":"Surbin-e Shomali",
    "wof:placetype":"locality"
},
  "geometry": {"coordinates":[52.2332,36.47113],"type":"Point"}
}