{
  "type": "Feature",
  "properties": {
    "gn:admin1_code":"15.0",
    "gn:asciiname":"`Ali Akbar",
    "gn:country_code":"IR",
    "gn:dem":61,
    "gn:elevation":"0.0",
    "gn:feature_class":"P",
    "gn:feature_code":"PPL",
    "gn:name":"\u2018Al\u012b Akbar",
    "gn:population":0,
    "gn:timezone":"Asia/Tehran",
    "iso:country":"IR",
    "name:fas_x_preferred":[
        "\u0634\u06cc\u062e \u0627\u062d\u0645\u062f"
    ],
    "name:fas_x_variant":[
        "A\u1e29mad Mowl\u0101",
        "Sheykh A\u1e29mad",
        "\u0639\u0644\u06cc \u0627\u06a9\u0628\u0631",
        "\u0627\u062d\u0645\u062f \u0645\u0648\u0644\u0627"
    ],
    "name:und_x_variant":[
        "\u2018Al\u012b Akbar"
    ],
    "wof:name":"`Ali Akbar",
    "wof:placetype":"locality"
},
  "geometry": {"coordinates":[48.25756,32.08427],"type":"Point"}
}