{
  "type": "Feature",
  "properties": {
    "gn:admin1_code":"29",
    "gn:asciiname":"Bon-e `Ur",
    "gn:country_code":"IR",
    "gn:dem":384,
    "gn:feature_class":"P",
    "gn:feature_code":"PPL",
    "gn:name":"Bon-e \u2018\u016ar",
    "gn:population":0,
    "gn:timezone":"Asia/Tehran",
    "iso:country":"IR",
    "name:fas_x_preferred":[
        "Bon-e \u2018\u016ar"
    ],
    "wof:name":"Bon-e `Ur",
    "wof:placetype":"locality"
},
  "geometry": {"coordinates":[57.56583000000001,27.30722],"type":"Point"}
}