{
  "type": "Feature",
  "properties": {
    "gn:admin1_code":"7",
    "gn:asciiname":"Kandar-e Kolah Boland",
    "gn:country_code":"IR",
    "gn:dem":408,
    "gn:feature_class":"P",
    "gn:feature_code":"PPL",
    "gn:name":"Kandar-e Kol\u0101h Boland",
    "gn:population":0,
    "gn:timezone":"Asia/Tehran",
    "iso:country":"IR",
    "name:fas_x_preferred":[
        "\u06a9\u0646\u062f\u0631 \u06a9\u0644\u0627\u0647 \u0628\u0644\u0646\u062f"
    ],
    "name:fas_x_variant":[
        "Kandar-e Kol\u0101h Boland"
    ],
    "name:und_x_variant":[
        "Kondor Kolah Boland"
    ],
    "wof:name":"Kandar-e Kolah Boland",
    "wof:placetype":"locality"
},
  "geometry": {"coordinates":[53.3712,27.2602],"type":"Point"}
}