{
  "type": "Feature",
  "properties": {
    "gn:admin1_code":"41",
    "gn:asciiname":"Rowshanavand",
    "gn:country_code":"IR",
    "gn:dem":1635,
    "gn:feature_class":"P",
    "gn:feature_code":"PPL",
    "gn:name":"Rowshan\u0101vand",
    "gn:population":0,
    "gn:timezone":"Asia/Tehran",
    "iso:country":"IR",
    "name:fas_x_preferred":[
        "Rowshn\u0101vand"
    ],
    "name:fas_x_variant":[
        "\u0631\u0648\u0634\u0646\u0627\u0648\u0646\u062f",
        "Rushan\u0101wand"
    ],
    "name:und_x_variant":[
        "Rushan\u0101wand",
        "Rowshan\u0101vand",
        "\u0631\u0648\u0634\u0646\u0627\u0648\u0646\u062f"
    ],
    "wof:name":"Rowshanavand",
    "wof:placetype":"locality"
},
  "geometry": {"coordinates":[59.15136,32.29947],"type":"Point"}
}