{
  "type": "Feature",
  "properties": {
    "gn:admin1_code":"8",
    "gn:asciiname":"Sotun",
    "gn:country_code":"IR",
    "gn:dem":1102,
    "gn:feature_class":"P",
    "gn:feature_code":"PPL",
    "gn:name":"Sot\u016bn",
    "gn:population":0,
    "gn:timezone":"Asia/Tehran",
    "iso:country":"IR",
    "name:fas_x_preferred":[
        "Sot\u016bn"
    ],
    "wof:name":"Sotun",
    "wof:placetype":"locality"
},
  "geometry": {"coordinates":[48.90139,37.37278],"type":"Point"}
}