{
  "type": "Feature",
  "properties": {
    "gn:admin1_code":"4.0",
    "gn:asciiname":"Shahrak-e Taqiabad",
    "gn:country_code":"IR",
    "gn:dem":434,
    "gn:feature_class":"P",
    "gn:feature_code":"PPL",
    "gn:name":"Shahrak-e Taq\u012b\u0101b\u0101d",
    "gn:population":0,
    "gn:timezone":"Asia/Tehran",
    "iso:country":"IR",
    "name:fas_x_preferred":[
        "\u0634\u0647\u0631\u06a9 \u062a\u0642\u06cc \u0622\u0628\u0627\u062f"
    ],
    "name:und_x_variant":[
        "Shahrak-e Taq\u012b\u0101b\u0101d"
    ],
    "wof:name":"Shahrak-e Taqiabad",
    "wof:placetype":"locality"
},
  "geometry": {"coordinates":[59.14037,26.9943],"type":"Point"}
}