{
  "type": "Feature",
  "properties": {
    "gn:admin1_code":"29",
    "gn:asciiname":"`Anbarabad",
    "gn:country_code":"IR",
    "gn:dem":1536,
    "gn:feature_class":"P",
    "gn:feature_code":"PPL",
    "gn:name":"\u2018Anbar\u0101b\u0101d",
    "gn:population":0,
    "gn:timezone":"Asia/Tehran",
    "iso:country":"IR",
    "name:fas_x_preferred":[
        "Tolombeh-ye Mo\u1e29ammad Shaf\u012b\u2018 Deh\u0101n"
    ],
    "name:fas_x_variant":[
        "\u0639\u0646\u0628\u0631 \u0622\u0628\u0627\u062f",
        "\u0645\u0648\u062a\u0648\u0631 \u0663\u0667",
        "\u062a\u0644\u0645\u0628\u0647 \u0645\u062d\u0645\u062f \u0634\u0641\u06cc\u0639"
    ],
    "name:und_x_variant":[
        "\u2018Anbar\u0101b\u0101d",
        "M\u016bt\u016br-e 37",
        "Tolombeh-ye Mo\u1e29ammad Shaf\u012b\u2018"
    ],
    "wof:name":"`Anbarabad",
    "wof:placetype":"locality"
},
  "geometry": {"coordinates":[56.9074,28.3796],"type":"Point"}
}