{
  "type": "Feature",
  "properties": {
    "gn:admin1_code":"11",
    "gn:asciiname":"Sir Dotuj",
    "gn:country_code":"IR",
    "gn:dem":17,
    "gn:feature_class":"P",
    "gn:feature_code":"PPL",
    "gn:name":"S\u012br Dot\u016bj",
    "gn:population":0,
    "gn:timezone":"Asia/Tehran",
    "iso:country":"IR",
    "name:fas_x_preferred":[
        "\u0633\u064a\u0631 \u062f\u064f\u062a\u0648\u062c"
    ],
    "name:fas_x_variant":[
        "S\u012br Dot\u016bj"
    ],
    "wof:name":"Sir Dotuj",
    "wof:placetype":"locality"
},
  "geometry": {"coordinates":[56.65194,27.34861],"type":"Point"}
}