{
  "type": "Feature",
  "properties": {
    "gn:admin1_code":"33",
    "gn:asciiname":"Sha`ban",
    "gn:country_code":"IR",
    "gn:dem":2071,
    "gn:feature_class":"P",
    "gn:feature_code":"PPL",
    "gn:name":"Sha\u2018b\u0101n",
    "gn:population":0,
    "gn:timezone":"Asia/Tehran",
    "iso:country":"IR",
    "name:fas_x_preferred":[
        "\u0634\u0639\u0628\u0627\u0646"
    ],
    "name:fas_x_variant":[
        "Sha\u2018b\u0101n"
    ],
    "wof:name":"Sha`ban",
    "wof:placetype":"locality"
},
  "geometry": {"coordinates":[46.95224,36.95362],"type":"Point"}
}