{
  "type": "Feature",
  "properties": {
    "gn:admin1_code":"23.0",
    "gn:asciiname":"Cheshmeh Kuzan",
    "gn:country_code":"IR",
    "gn:dem":1619,
    "gn:feature_class":"P",
    "gn:feature_code":"PPL",
    "gn:name":"Cheshmeh K\u016bz\u0101n",
    "gn:population":0,
    "gn:timezone":"Asia/Tehran",
    "iso:country":"IR",
    "name:fas_x_preferred":[
        "\u0686\u0650\u0634\u0645\u0650\u0647 \u0643\u0648\u0632\u0627\u0646"
    ],
    "wof:name":"Cheshmeh Kuzan",
    "wof:placetype":"locality"
},
  "geometry": {"coordinates":[47.56667,34.11667],"type":"Point"}
}