{
  "type": "Feature",
  "properties": {
    "gn:admin1_code":"8",
    "gn:asciiname":"Mobarakabad",
    "gn:country_code":"IR",
    "gn:dem":-23,
    "gn:feature_class":"P",
    "gn:feature_code":"PPL",
    "gn:name":"Mob\u0101rak\u0101b\u0101d",
    "gn:population":0,
    "gn:timezone":"Asia/Tehran",
    "iso:country":"IR",
    "name:fas_x_preferred":[
        "Mob\u0101rak\u0101b\u0101d"
    ],
    "name:fas_x_variant":[
        "\u0645\u0628\u0627\u0631\u06a9 \u0622\u0628\u0627\u062f",
        "\u0627\u0633\u0644\u0627\u0645 \u0622\u0628\u0627\u062f",
        "\u0645\u0628\u0627\u0631\u06a9\u200c\u0622\u0628\u0627\u062f"
    ],
    "name:msa_x_preferred":[
        "Mobarakabad"
    ],
    "name:ukr_x_preferred":[
        "\u041c\u043e\u0431\u0430\u0440\u0430\u043a\u0430\u0431\u0430\u0434"
    ],
    "name:und_x_variant":[
        "Mubarykabad",
        "Mobark Abade Hoomeh",
        "M\u016bb\u0101rak\u0101b\u0101d",
        "\u0645\u0628\u0627\u0631\u06a9 \u0622\u0628\u0627\u062f",
        "Esl\u0101m\u0101b\u0101d"
    ],
    "wof:name":"Mobarakabad",
    "wof:placetype":"locality"
},
  "geometry": {"coordinates":[49.54248,37.37604],"type":"Point"}
}