{
  "type": "Feature",
  "properties": {
    "gn:admin1_code":"3",
    "gn:asciiname":"Talineh",
    "gn:country_code":"IR",
    "gn:dem":1416,
    "gn:feature_class":"P",
    "gn:feature_code":"PPL",
    "gn:name":"\u0162al\u012bneh",
    "gn:population":0,
    "gn:timezone":"Asia/Tehran",
    "iso:country":"IR",
    "name:fas_x_preferred":[
        "\u0162al\u012bneh-ye D\u016bder\u0101\u2019"
    ],
    "name:fas_x_variant":[
        "\u0637\u0644\u06cc\u0646\u0647",
        "\u062a\u0644\u06cc\u0646\u0647",
        "\u0637\u0644\u06cc\u0646\u0647 \u062f\u0648\u062f\u0631\u0627"
    ],
    "name:und_x_variant":[
        "\u0162al\u012bneh",
        "Tal\u0101yeh",
        "Tal\u012bneh",
        "\u0162al\u012bneh-ye D\u016bder\u0101"
    ],
    "wof:name":"Talineh",
    "wof:placetype":"locality"
},
  "geometry": {"coordinates":[50.8517,31.31489],"type":"Point"}
}