{
  "type": "Feature",
  "properties": {
    "gn:admin1_code":"11",
    "gn:asciiname":"Chukhun",
    "gn:country_code":"IR",
    "gn:dem":459,
    "gn:feature_class":"P",
    "gn:feature_code":"PPL",
    "gn:name":"Ch\u016bkh\u016bn",
    "gn:population":0,
    "gn:timezone":"Asia/Tehran",
    "iso:country":"IR",
    "name:fas_x_preferred":[
        "\u0686\u0648\u062e\u0648\u0646"
    ],
    "name:fas_x_variant":[
        "Ch\u016bkh\u016bn"
    ],
    "wof:name":"Chukhun",
    "wof:placetype":"locality"
},
  "geometry": {"coordinates":[57.6786,26.3062],"type":"Point"}
}