{
  "type": "Feature",
  "properties": {
    "gn:admin1_code":"1.0",
    "gn:asciiname":"Mirabad",
    "gn:country_code":"IR",
    "gn:dem":1322,
    "gn:elevation":"0.0",
    "gn:feature_class":"P",
    "gn:feature_code":"PPL",
    "gn:name":"M\u012br\u0101b\u0101d",
    "gn:population":0,
    "gn:timezone":"Asia/Tehran",
    "iso:country":"IR",
    "name:fas_x_preferred":[
        "\u0645\u06cc\u0631 \u0622\u0628\u0627\u062f"
    ],
    "name:fas_x_variant":[
        "M\u012br\u0101b\u0101d"
    ],
    "wof:name":"Mirabad",
    "wof:placetype":"locality"
},
  "geometry": {"coordinates":[45.3135,36.9864],"type":"Point"}
}