{
  "type": "Feature",
  "properties": {
    "gn:admin1_code":"33",
    "gn:asciiname":"Amir Khan-e Karim",
    "gn:country_code":"IR",
    "gn:dem":394,
    "gn:feature_class":"P",
    "gn:feature_code":"PPL",
    "gn:name":"Am\u012br Kh\u0101n-e Kar\u012bm",
    "gn:population":0,
    "gn:timezone":"Asia/Tehran",
    "iso:country":"IR",
    "name:fas_x_preferred":[
        "\u0627\u064e\u0645\u064a\u0631 \u062e\u0627\u0646\u0650 \u0643\u064e\u0631\u064a\u0645"
    ],
    "name:fas_x_variant":[
        "Am\u012br Kh\u0101n-e Kar\u012bm"
    ],
    "wof:name":"Amir Khan-e Karim",
    "wof:placetype":"locality"
},
  "geometry": {"coordinates":[47.43333,39.21667],"type":"Point"}
}