{
  "type": "Feature",
  "properties": {
    "gn:admin1_code":"33",
    "gn:asciiname":"Hafez",
    "gn:country_code":"IR",
    "gn:dem":1568,
    "gn:feature_class":"P",
    "gn:feature_code":"PPL",
    "gn:name":"\u1e28\u0101fez\u0327",
    "gn:population":0,
    "gn:timezone":"Asia/Tehran",
    "iso:country":"IR",
    "name:fas_x_preferred":[
        "\u062d\u0627\u0641\u0638"
    ],
    "name:fas_x_variant":[
        "\u1e28\u0101fez\u0327"
    ],
    "wof:name":"Hafez",
    "wof:placetype":"locality"
},
  "geometry": {"coordinates":[47.2242,37.5723],"type":"Point"}
}