{
  "type": "Feature",
  "properties": {
    "gn:admin1_code":"1",
    "gn:asciiname":"Deldar",
    "gn:country_code":"IR",
    "gn:dem":1982,
    "gn:feature_class":"P",
    "gn:feature_code":"PPL",
    "gn:name":"Deldar",
    "gn:population":0,
    "gn:timezone":"Asia/Tehran",
    "iso:country":"IR",
    "name:fas_x_preferred":[
        "\u062f\u0650\u0644\u0627\u062f\u064e\u0631"
    ],
    "name:fas_x_variant":[
        "\u062f\u0644\u062f\u0631",
        "Del\u0101dar",
        "\u062f\u064f\u0644\u062f\u064f\u0631"
    ],
    "name:und_x_variant":[
        "Doldor",
        "Deldar"
    ],
    "wof:name":"Deldar",
    "wof:placetype":"locality"
},
  "geometry": {"coordinates":[44.8451,37.8494],"type":"Point"}
}