{
  "type": "Feature",
  "properties": {
    "gn:admin1_code":"32",
    "gn:asciiname":"Kenab",
    "gn:country_code":"IR",
    "gn:dem":989,
    "gn:feature_class":"P",
    "gn:feature_code":"PPL",
    "gn:name":"Ken\u0101b",
    "gn:population":0,
    "gn:timezone":"Asia/Tehran",
    "iso:country":"IR",
    "name:fas_x_preferred":[
        "\u0643\u0646\u0627\u0628"
    ],
    "name:fas_x_variant":[
        "Ken\u0101b"
    ],
    "wof:name":"Kenab",
    "wof:placetype":"locality"
},
  "geometry": {"coordinates":[47.6199,38.9434],"type":"Point"}
}