{
  "type": "Feature",
  "properties": {
    "gn:admin1_code":"15",
    "gn:asciiname":"Cherkin-e Bala",
    "gn:country_code":"IR",
    "gn:dem":925,
    "gn:feature_class":"P",
    "gn:feature_code":"PPL",
    "gn:name":"Cherk\u012bn-e B\u0101l\u0101",
    "gn:population":0,
    "gn:timezone":"Asia/Tehran",
    "iso:country":"IR",
    "name:fas_x_preferred":[
        "Cherk\u012bn-e B\u0101l\u0101"
    ],
    "name:fas_x_variant":[
        "\u0686\u0631\u0643\u064a\u0646 \u0628\u0627\u0644\u0627"
    ],
    "name:und_x_variant":[
        "\u0686\u0631\u0643\u064a\u0646 \u0628\u0627\u0644\u0627"
    ],
    "wof:name":"Cherkin-e Bala",
    "wof:placetype":"locality"
},
  "geometry": {"coordinates":[50.47077,31.61675],"type":"Point"}
}