{
  "type": "Feature",
  "properties": {
    "gn:admin1_code":"35.0",
    "gn:asciiname":"Livsu",
    "gn:country_code":"IR",
    "gn:dem":1097,
    "gn:feature_class":"P",
    "gn:feature_code":"PPL",
    "gn:name":"L\u012bvs\u016b",
    "gn:population":0,
    "gn:timezone":"Asia/Tehran",
    "iso:country":"IR",
    "name:fas_x_preferred":[
        "L\u012bvs\u016b"
    ],
    "name:fas_x_variant":[
        "\u0644\u06cc\u0648\u0633\u0648"
    ],
    "wof:name":"Livsu",
    "wof:placetype":"locality"
},
  "geometry": {"coordinates":[51.39314,36.38978],"type":"Point"}
}