{
  "type": "Feature",
  "properties": {
    "gn:admin1_code":"43",
    "gn:asciiname":"Qal`eh-ye Hoseyn Khan",
    "gn:country_code":"IR",
    "gn:dem":678,
    "gn:feature_class":"P",
    "gn:feature_code":"PPL",
    "gn:name":"Qal\u2018eh-ye \u1e28oseyn Kh\u0101n",
    "gn:population":0,
    "gn:timezone":"Asia/Tehran",
    "iso:country":"IR",
    "name:fas_x_preferred":[
        "Qal\u2018eh-ye \u1e28oseyn Kh\u0101n"
    ],
    "name:fas_x_variant":[
        "\u0642\u0644\u0639\u0647 \u062d\u0633\u06cc\u0646 \u062e\u0627\u0646"
    ],
    "wof:name":"Qal`eh-ye Hoseyn Khan",
    "wof:placetype":"locality"
},
  "geometry": {"coordinates":[57.14669,37.65474],"type":"Point"}
}