{
  "type": "Feature",
  "properties": {
    "gn:admin1_code":"33",
    "gn:asciiname":"Shahnavaz-e `Olya",
    "gn:country_code":"IR",
    "gn:dem":2089,
    "gn:feature_class":"P",
    "gn:feature_code":"PPL",
    "gn:name":"Shahnav\u0101z-e \u2018Oly\u0101",
    "gn:population":0,
    "gn:timezone":"Asia/Tehran",
    "iso:country":"IR",
    "name:fas_x_preferred":[
        "Shahnav\u0101z-e \u2018Oly\u0101"
    ],
    "name:fas_x_variant":[
        "\u0634\u0647\u0646\u0648\u0627\u0632 \u0639\u0644\u06cc\u0627"
    ],
    "name:und_x_variant":[
        "Shahnav\u0101z",
        "\u0634\u0647\u0646\u0648\u0627\u0632 \u0639\u0644\u06cc\u0627"
    ],
    "wof:name":"Shahnavaz-e `Olya",
    "wof:placetype":"locality"
},
  "geometry": {"coordinates":[46.7521,37.1171],"type":"Point"}
}