{
  "type": "Feature",
  "properties": {
    "gn:admin1_code":"33",
    "gn:asciiname":"Vareh Gol",
    "gn:country_code":"IR",
    "gn:dem":1873,
    "gn:feature_class":"P",
    "gn:feature_code":"PPL",
    "gn:name":"Vareh Gol",
    "gn:population":0,
    "gn:timezone":"Asia/Tehran",
    "iso:country":"IR",
    "name:fas_x_preferred":[
        "\u0648\u0631\u06af\u0644"
    ],
    "name:fas_x_variant":[
        "\u0648\u0631\u0647 \u06af\u0644"
    ],
    "name:und_x_variant":[
        "Varagol",
        "Vareh Gol"
    ],
    "wof:name":"Vareh Gol",
    "wof:placetype":"locality"
},
  "geometry": {"coordinates":[46.7369,37.5556],"type":"Point"}
}