{
  "type": "Feature",
  "properties": {
    "gn:admin1_code":"42",
    "gn:asciiname":"Nuq",
    "gn:country_code":"IR",
    "gn:dem":1304,
    "gn:feature_class":"P",
    "gn:feature_code":"PPL",
    "gn:name":"N\u016bq",
    "gn:population":0,
    "gn:timezone":"Asia/Tehran",
    "iso:country":"IR",
    "name:fas_x_preferred":[
        "\u0646\u0648\u0642"
    ],
    "name:fas_x_variant":[
        "N\u016bq"
    ],
    "name:und_x_variant":[
        "N\u016bk",
        "N\u016bgh"
    ],
    "wof:name":"Nuq",
    "wof:placetype":"locality"
},
  "geometry": {"coordinates":[59.60123000000001,35.08285],"type":"Point"}
}