{
  "type": "Feature",
  "properties": {
    "gn:admin1_code":"8.0",
    "gn:asciiname":"Diamunsar",
    "gn:country_code":"IR",
    "gn:dem":1181,
    "gn:feature_class":"P",
    "gn:feature_code":"PPLF",
    "gn:name":"D\u012b\u0101m\u016bnsar",
    "gn:population":0,
    "gn:timezone":"Asia/Tehran",
    "iso:country":"IR",
    "name:fas_x_preferred":[
        "\u062f\u06cc\u0627\u0645\u0648\u0646\u0633\u0631"
    ],
    "name:fas_x_variant":[
        "V\u012b\u0101nsar",
        "D\u012b\u0101m\u016bnsar"
    ],
    "wof:name":"Diamunsar",
    "wof:placetype":"locality"
},
  "geometry": {"coordinates":[48.8872,37.5541],"type":"Point"}
}