{
  "type": "Feature",
  "properties": {
    "gn:admin1_code":"42",
    "gn:asciiname":"Kariz Sabz-e Now",
    "gn:country_code":"IR",
    "gn:dem":1766,
    "gn:feature_class":"P",
    "gn:feature_code":"PPL",
    "gn:name":"K\u0101r\u012bz Sabz-e Now",
    "gn:population":0,
    "gn:timezone":"Asia/Tehran",
    "iso:country":"IR",
    "name:fas_x_preferred":[
        "\u06a9\u0627\u0631\u06cc\u0632 \u0633\u0628\u0632 \u0646\u0648"
    ],
    "name:fas_x_variant":[
        "K\u0101r\u012bz Sabz",
        "K\u0101r\u012bz Sabz-e Now"
    ],
    "wof:name":"Kariz Sabz-e Now",
    "wof:placetype":"locality"
},
  "geometry": {"coordinates":[59.45891,35.5501],"type":"Point"}
}