{
  "type": "Feature",
  "properties": {
    "gn:admin1_code":"4.0",
    "gn:asciiname":"Tasian",
    "gn:country_code":"IR",
    "gn:dem":1298,
    "gn:feature_class":"P",
    "gn:feature_code":"PPLF",
    "gn:name":"T\u0101s\u012b\u0101n",
    "gn:population":0,
    "gn:timezone":"Asia/Tehran",
    "iso:country":"IR",
    "name:fas_x_preferred":[
        "\u062a\u0627\u0633\u064a\u0627\u0646"
    ],
    "name:fas_x_variant":[
        "\u062a\u0627\u0633\u06cc\u0627\u0646"
    ],
    "name:und_x_variant":[
        "T\u0101s\u012b\u0101n"
    ],
    "wof:name":"Tasian",
    "wof:placetype":"locality"
},
  "geometry": {"coordinates":[61.71373000000001,27.2496],"type":"Point"}
}