{
  "type": "Feature",
  "properties": {
    "gn:admin1_code":"8",
    "gn:asciiname":"Ahmad Sara",
    "gn:country_code":"IR",
    "gn:dem":70,
    "gn:feature_class":"P",
    "gn:feature_code":"PPL",
    "gn:name":"A\u1e29mad Sar\u0101",
    "gn:population":0,
    "gn:timezone":"Asia/Tehran",
    "iso:country":"IR",
    "name:fas_x_preferred":[
        "A\u1e29mad Sar\u0101"
    ],
    "wof:name":"Ahmad Sara",
    "wof:placetype":"locality"
},
  "geometry": {"coordinates":[49.66278,37.07139],"type":"Point"}
}