{
  "type": "Feature",
  "properties": {
    "gn:admin1_code":"28.0",
    "gn:asciiname":"Jeznabad",
    "gn:country_code":"IR",
    "gn:dem":2289,
    "gn:feature_class":"P",
    "gn:feature_code":"PPL",
    "gn:name":"Jezn\u0101b\u0101d",
    "gn:population":0,
    "gn:timezone":"Asia/Tehran",
    "iso:country":"IR",
    "name:fas_x_preferred":[
        "\u062c\u0632\u0646 \u0622\u0628\u0627\u062f"
    ],
    "name:fas_x_variant":[
        "Jezn\u0101b\u0101d",
        "\u062c\u0632\u0646\u200c\u0622\u0628\u0627\u062f"
    ],
    "name:und_x_variant":[
        "Jazan\u0101b\u0101d"
    ],
    "wof:name":"Jeznabad",
    "wof:placetype":"locality"
},
  "geometry": {"coordinates":[52.8803,32.7164],"type":"Point"}
}