{
  "type": "Feature",
  "properties": {
    "gn:admin1_code":"33",
    "gn:asciiname":"Lowtejan",
    "gn:country_code":"IR",
    "gn:dem":709,
    "gn:feature_class":"P",
    "gn:feature_code":"PPL",
    "gn:name":"Lowtej\u0101n",
    "gn:population":0,
    "gn:timezone":"Asia/Tehran",
    "iso:country":"IR",
    "name:ceb_x_preferred":[
        "Lowtej\u0101n"
    ],
    "name:fas_x_preferred":[
        "\u0644\u0648\u062a\u062c\u0627\u0646"
    ],
    "name:fas_x_variant":[
        "Lotehj\u0101n",
        "Lowtej\u0101n"
    ],
    "name:msa_x_preferred":[
        "Lowtejan"
    ],
    "name:swe_x_preferred":[
        "Lowtej\u0101n"
    ],
    "wof:name":"Lowtejan",
    "wof:placetype":"locality"
},
  "geometry": {"coordinates":[47.0689,39.0873],"type":"Point"}
}