{
  "type": "Feature",
  "properties": {
    "gn:admin1_code":"4.0",
    "gn:asciiname":"Hoseyn Zehi",
    "gn:country_code":"IR",
    "gn:dem":43,
    "gn:feature_class":"P",
    "gn:feature_code":"PPL",
    "gn:name":"\u1e28oseyn Zeh\u012b",
    "gn:population":0,
    "gn:timezone":"Asia/Tehran",
    "iso:country":"IR",
    "name:fas_x_preferred":[
        "\u1e28oseyn Zeh\u012b"
    ],
    "name:fas_x_variant":[
        "\u062d\u0633\u06cc\u0646 \u0632\u0647\u06cc"
    ],
    "name:und_x_variant":[
        "Husanzai",
        "\u1e28oseyn-e Z\u0101y",
        "\u1e28oseyn Z\u0101h\u012b",
        "\u1e28oseyn-e Zeh\u012b",
        "\u1e28oseyn Z\u0101\u2019\u012b",
        "\u062d\u0633\u06cc\u0646 \u0632\u0647\u06cc"
    ],
    "wof:name":"Hoseyn Zehi",
    "wof:placetype":"locality"
},
  "geometry": {"coordinates":[60.9678,25.66767],"type":"Point"}
}