{
  "type": "Feature",
  "properties": {
    "gn:admin1_code":"7.0",
    "gn:asciiname":"Malicheh",
    "gn:country_code":"IR",
    "gn:dem":1647,
    "gn:feature_class":"P",
    "gn:feature_code":"PPL",
    "gn:name":"M\u0101l\u012bcheh",
    "gn:population":0,
    "gn:timezone":"Asia/Tehran",
    "iso:country":"IR",
    "name:fas_x_preferred":[
        "\u0645\u0627\u0644\u06cc\u0686\u0647"
    ],
    "name:fas_x_variant":[
        "M\u0101l\u012bcheh-ye B\u0101l\u0101",
        "M\u0101l\u012bcheh"
    ],
    "wof:name":"Malicheh",
    "wof:placetype":"locality"
},
  "geometry": {"coordinates":[52.6862,30.2028],"type":"Point"}
}