{
  "type": "Feature",
  "properties": {
    "gn:admin1_code":"4.0",
    "gn:asciiname":"Darduk",
    "gn:country_code":"IR",
    "gn:dem":1238,
    "gn:feature_class":"P",
    "gn:feature_code":"PPL",
    "gn:name":"D\u0101rd\u016bk",
    "gn:population":0,
    "gn:timezone":"Asia/Tehran",
    "iso:country":"IR",
    "name:fas_x_preferred":[
        "D\u0101rd\u016bk"
    ],
    "wof:name":"Darduk",
    "wof:placetype":"locality"
},
  "geometry": {"coordinates":[62.31667,27.26667],"type":"Point"}
}