{
  "type": "Feature",
  "properties": {
    "gn:admin1_code":"8",
    "gn:asciiname":"Alesh Dasht",
    "gn:country_code":"IR",
    "gn:dem":480,
    "gn:feature_class":"P",
    "gn:feature_code":"PPL",
    "gn:name":"\u0100lesh Dasht",
    "gn:population":0,
    "gn:timezone":"Asia/Tehran",
    "iso:country":"IR",
    "name:fas_x_preferred":[
        "\u0100lesh Dasht"
    ],
    "name:fas_x_variant":[
        "\u0622\u0644\u0634 \u062f\u0634\u062a"
    ],
    "wof:name":"Alesh Dasht",
    "wof:placetype":"locality"
},
  "geometry": {"coordinates":[49.5134,36.84117],"type":"Point"}
}