{
  "type": "Feature",
  "properties": {
    "gn:admin1_code":"5.0",
    "gn:asciiname":"Mazra`eh-ye Delitangu",
    "gn:country_code":"IR",
    "gn:dem":2251,
    "gn:feature_class":"P",
    "gn:feature_code":"PPL",
    "gn:name":"Mazra\u2018eh-ye Del\u012btang\u016b",
    "gn:population":0,
    "gn:timezone":"Asia/Tehran",
    "iso:country":"IR",
    "name:fas_x_preferred":[
        "T\u0101gas\u012bseh"
    ],
    "name:fas_x_variant":[
        "\u062a\u0627\u06af\u0633\u06cc\u0633\u0647",
        "\u0645\u0632\u0631\u0639\u0647 \u062f\u0644\u06cc\u062a\u0646\u06af\u0648"
    ],
    "name:und_x_variant":[
        "Mazra\u2018eh-ye Del\u012btang\u016b"
    ],
    "wof:name":"Mazra`eh-ye Delitangu",
    "wof:placetype":"locality"
},
  "geometry": {"coordinates":[50.95177,31.1179],"type":"Point"}
}