{
  "type": "Feature",
  "properties": {
    "gn:admin1_code":"42.0",
    "gn:asciiname":"Kalateh-ye Now Bahar",
    "gn:country_code":"IR",
    "gn:dem":1302,
    "gn:feature_class":"P",
    "gn:feature_code":"PPL",
    "gn:name":"Kal\u0101teh-ye Now Bah\u0101r",
    "gn:population":0,
    "gn:timezone":"Asia/Tehran",
    "iso:country":"IR",
    "name:fas_x_preferred":[
        "Kal\u0101teh-ye Now Bah\u0101r"
    ],
    "wof:name":"Kalateh-ye Now Bahar",
    "wof:placetype":"locality"
},
  "geometry": {"coordinates":[58.19306,36.3725],"type":"Point"}
}