{
  "type": "Feature",
  "properties": {
    "gn:admin1_code":"29",
    "gn:asciiname":"Ne`matabad",
    "gn:country_code":"IR",
    "gn:dem":1704,
    "gn:feature_class":"P",
    "gn:feature_code":"PPL",
    "gn:name":"Ne\u2018mat\u0101b\u0101d",
    "gn:population":0,
    "gn:timezone":"Asia/Tehran",
    "iso:country":"IR",
    "name:fas_x_preferred":[
        "Ne\u2018mat\u0101b\u0101d"
    ],
    "name:fas_x_variant":[
        "Ne\u2018mat\u0101b\u0101d-e Farrokh",
        "\u0646\u0639\u0645\u062a \u0622\u0628\u0627\u062f"
    ],
    "name:und_x_variant":[
        "\u0646\u0639\u0645\u062a \u0622\u0628\u0627\u062f",
        "Tolombeh-ye Ne\u2018mat\u0101b\u0101d"
    ],
    "wof:name":"Ne`matabad",
    "wof:placetype":"locality"
},
  "geometry": {"coordinates":[55.49391,29.50701],"type":"Point"}
}