{
  "type": "Feature",
  "properties": {
    "gn:admin1_code":"5.0",
    "gn:asciiname":"Molla `Abadi",
    "gn:country_code":"IR",
    "gn:dem":1137,
    "gn:feature_class":"P",
    "gn:feature_code":"PPL",
    "gn:name":"Moll\u0101 \u2018Ab\u0101d\u012b",
    "gn:population":0,
    "gn:timezone":"Asia/Tehran",
    "iso:country":"IR",
    "name:fas_x_preferred":[
        "\u0645\u0644\u0627 \u0639\u0628\u0627\u062f\u06cc"
    ],
    "name:und_x_variant":[
        "Moll\u0101 \u2018Ab\u0101d\u012b"
    ],
    "wof:name":"Molla `Abadi",
    "wof:placetype":"locality"
},
  "geometry": {"coordinates":[50.07601,31.14851],"type":"Point"}
}