{
  "type": "Feature",
  "properties": {
    "gn:admin1_code":"23",
    "gn:asciiname":"Cheshmeh Kareh",
    "gn:country_code":"IR",
    "gn:dem":1850,
    "gn:feature_class":"P",
    "gn:feature_code":"PPL",
    "gn:name":"Cheshmeh Kareh",
    "gn:population":0,
    "gn:timezone":"Asia/Tehran",
    "iso:country":"IR",
    "name:fas_x_preferred":[
        "\u0686\u0634\u0645\u0647 \u0643\u0631\u0647"
    ],
    "name:fas_x_variant":[
        "\u0686\u0634\u0645\u0647\u200c\u06a9\u0631\u0647"
    ],
    "wof:name":"Cheshmeh Kareh",
    "wof:placetype":"locality"
},
  "geometry": {"coordinates":[48.718,33.3253],"type":"Point"}
}