{
  "type": "Feature",
  "properties": {
    "gn:admin1_code":"41",
    "gn:asciiname":"Karbala Aqa `Ali",
    "gn:country_code":"IR",
    "gn:dem":1416,
    "gn:feature_class":"P",
    "gn:feature_code":"PPL",
    "gn:name":"Karbal\u0101 \u0100q\u0101 \u2018Al\u012b",
    "gn:population":0,
    "gn:timezone":"Asia/Tehran",
    "iso:country":"IR",
    "name:fas_x_preferred":[
        "Karbal\u0101 \u0100q\u0101 \u2018Al\u012b"
    ],
    "name:und_x_variant":[
        "Karbal\u0101\u2019\u012b \u0100q\u0101 \u2018Al\u012b",
        "Karbal\u0101-ye Agh\u0101 \u2018Al\u012b",
        "Karbala yi \u0100gha \u2018Ali"
    ],
    "wof:name":"Karbala Aqa `Ali",
    "wof:placetype":"locality"
},
  "geometry": {"coordinates":[57.48917,33.27139],"type":"Point"}
}