{
  "type": "Feature",
  "properties": {
    "gn:admin1_code":"13",
    "gn:asciiname":"Gardi Vazn",
    "gn:country_code":"IR",
    "gn:dem":1168,
    "gn:feature_class":"P",
    "gn:feature_code":"PPL",
    "gn:name":"Gard\u012b Vazn",
    "gn:population":0,
    "gn:timezone":"Asia/Tehran",
    "iso:country":"IR",
    "name:fas_x_preferred":[
        "\u06af\u0631\u062f\u06cc \u0648\u0632\u0646"
    ],
    "name:fas_x_variant":[
        "Gard\u012bvzan",
        "Gard\u012b Vazn"
    ],
    "wof:name":"Gardi Vazn",
    "wof:placetype":"locality"
},
  "geometry": {"coordinates":[46.1454,34.8672],"type":"Point"}
}