{
  "type": "Feature",
  "properties": {
    "gn:admin1_code":"7",
    "gn:asciiname":"Zarabad",
    "gn:country_code":"IR",
    "gn:dem":788,
    "gn:feature_class":"P",
    "gn:feature_code":"PPL",
    "gn:name":"Zar\u0101b\u0101d",
    "gn:population":0,
    "gn:timezone":"Asia/Tehran",
    "iso:country":"IR",
    "name:fas_x_preferred":[
        "Zar\u0101b\u0101d"
    ],
    "wof:name":"Zarabad",
    "wof:placetype":"locality"
},
  "geometry": {"coordinates":[51.57667,29.75472],"type":"Point"}
}