{
  "type": "Feature",
  "properties": {
    "gn:admin1_code":"35",
    "gn:asciiname":"Lasem",
    "gn:country_code":"IR",
    "gn:dem":2601,
    "gn:feature_class":"P",
    "gn:feature_code":"PPL",
    "gn:name":"L\u0101sem",
    "gn:population":0,
    "gn:timezone":"Asia/Tehran",
    "iso:country":"IR",
    "name:ara_x_preferred":[
        "\u0644\u0627\u0633\u0645"
    ],
    "name:fas_x_preferred":[
        "\u0644\u0627\u0633\u0645"
    ],
    "name:fas_x_variant":[
        "\u0644\u064e\u0633\u0645",
        "L\u0101sem"
    ],
    "name:mlg_x_preferred":[
        "Lasem"
    ],
    "name:ukr_x_preferred":[
        "\u041b\u0430\u0441\u0435\u043c"
    ],
    "name:und_x_variant":[
        "Lishan",
        "Lasm"
    ],
    "name:urd_x_preferred":[
        "\u0644\u0627\u0633\u06cc\u0645"
    ],
    "wof:name":"Lasem",
    "wof:placetype":"locality"
},
  "geometry": {"coordinates":[52.20895,35.80996],"type":"Point"}
}