{
  "type": "Feature",
  "properties": {
    "gn:admin1_code":"16",
    "gn:asciiname":"Gomeh Darreh",
    "gn:country_code":"IR",
    "gn:dem":1941,
    "gn:feature_class":"P",
    "gn:feature_code":"PPL",
    "gn:name":"Gomeh Darreh",
    "gn:population":0,
    "gn:timezone":"Asia/Tehran",
    "iso:country":"IR",
    "name:fas_x_preferred":[
        "\u06af\u0645\u0647 \u062f\u0631\u0651\u0647"
    ],
    "name:fas_x_variant":[
        "\u06af\u0645 \u062f\u0631\u0647"
    ],
    "name:und_x_variant":[
        "Gum Darreh",
        "Gom Darreh",
        "Gommeh Darreh",
        "Gomeh Darreh"
    ],
    "wof:name":"Gomeh Darreh",
    "wof:placetype":"locality"
},
  "geometry": {"coordinates":[47.26149,35.4778],"type":"Point"}
}