{
  "type": "Feature",
  "properties": {
    "gn:admin1_code":"23",
    "gn:asciiname":"Dah Baradar",
    "gn:country_code":"IR",
    "gn:dem":880,
    "gn:feature_class":"P",
    "gn:feature_code":"PPL",
    "gn:name":"Dah Bar\u0101dar",
    "gn:population":0,
    "gn:timezone":"Asia/Tehran",
    "iso:country":"IR",
    "name:fas_x_preferred":[
        "\u062f\u0647 \u0628\u0631\u0627\u062f\u0631"
    ],
    "name:fas_x_variant":[
        "Dah Bar\u0101dar"
    ],
    "wof:name":"Dah Baradar",
    "wof:placetype":"locality"
},
  "geometry": {"coordinates":[47.20364,33.3883],"type":"Point"}
}