{
  "type": "Feature",
  "properties": {
    "gn:admin1_code":"38",
    "gn:asciiname":"Dodeh",
    "gn:country_code":"IR",
    "gn:dem":1501,
    "gn:feature_class":"P",
    "gn:feature_code":"PPL",
    "gn:name":"Dodeh",
    "gn:population":0,
    "gn:timezone":"Asia/Tehran",
    "iso:country":"IR",
    "name:fas_x_preferred":[
        "Deheh-ye B\u0101l\u0101"
    ],
    "name:fas_x_variant":[
        "D\u016bdaheh",
        "\u062f\u0647\u0647 \u0628\u0644\u0627",
        "\u062f\u0648\u062f\u0647",
        "\u062f\u0648\u062f\u0647\u0647",
        "\u062f\u0648\u062f\u0647 \u0642\u062f\u06cc\u0645"
    ],
    "name:und_x_variant":[
        "Dudakh",
        "D\u016bdeh-ye B\u0101l\u0101",
        "D\u016bdah",
        "Dodeh",
        "Dodeheh",
        "Dodeh-ye Qadim"
    ],
    "wof:name":"Dodeh",
    "wof:placetype":"locality"
},
  "geometry": {"coordinates":[49.68562,36.37207],"type":"Point"}
}