{
  "type": "Feature",
  "properties": {
    "gn:admin1_code":"28",
    "gn:asciiname":"Razabad",
    "gn:country_code":"IR",
    "gn:dem":2137,
    "gn:feature_class":"P",
    "gn:feature_code":"PPL",
    "gn:name":"R\u0101z\u0101b\u0101d",
    "gn:population":0,
    "gn:timezone":"Asia/Tehran",
    "iso:country":"IR",
    "name:fas_x_preferred":[
        "\u0631\u0627\u0632 \u0622\u0628\u0627\u062f"
    ],
    "name:fas_x_variant":[
        "R\u0101z\u0101b\u0101d"
    ],
    "wof:name":"Razabad",
    "wof:placetype":"locality"
},
  "geometry": {"coordinates":[52.8984,32.7567],"type":"Point"}
}