{
  "type": "Feature",
  "properties": {
    "gn:admin1_code":"23",
    "gn:asciiname":"Hasanabad",
    "gn:country_code":"IR",
    "gn:dem":1710,
    "gn:feature_class":"P",
    "gn:feature_code":"PPL",
    "gn:name":"\u1e28asan\u0101b\u0101d",
    "gn:population":0,
    "gn:timezone":"Asia/Tehran",
    "iso:country":"IR",
    "name:aze_x_preferred":[
        "H\u0259s\u0259nabad"
    ],
    "name:ceb_x_preferred":[
        "Hasanabad"
    ],
    "name:fas_x_preferred":[
        "\u0686\u0627\u0644 \u0622\u0628 \u0633\u0641\u0644\u06cc"
    ],
    "name:fas_x_variant":[
        "Ch\u0101l \u0100b-e Sofl\u00e1",
        "\u062d\u0633\u0646 \u0622\u0628\u0627\u062f",
        "\u062d\u0633\u0646\u200c\u0622\u0628\u0627\u062f"
    ],
    "name:ita_x_preferred":[
        "Hasanabad"
    ],
    "name:swe_x_preferred":[
        "Hasanabad"
    ],
    "name:und_x_variant":[
        "\u1e28asan\u0101b\u0101d"
    ],
    "wof:name":"Hasanabad",
    "wof:placetype":"locality"
},
  "geometry": {"coordinates":[47.7024,33.9422],"type":"Point"}
}