{
  "type": "Feature",
  "properties": {
    "gn:admin1_code":"29",
    "gn:asciiname":"Khoshk Avari",
    "gn:country_code":"IR",
    "gn:dem":654,
    "gn:feature_class":"P",
    "gn:feature_code":"PPLF",
    "gn:name":"Khoshk \u0100var\u012b",
    "gn:population":0,
    "gn:timezone":"Asia/Tehran",
    "iso:country":"IR",
    "name:fas_x_preferred":[
        "Ch\u0101h-e Khoshk\u0101vor\u012b"
    ],
    "name:fas_x_variant":[
        "\u062e\u0634\u06a9 \u0622\u0648\u0631\u06cc",
        "\u0645\u0648\u062a\u0648\u0631\u0647\u0627\u06cc \u062e\u0634\u06a9 \u0622\u0648\u0631\u06cc \u062d\u0648\u0631"
    ],
    "name:und_x_variant":[
        "Khoshk \u0100var\u012b",
        "Mowtowrh\u0101-ye Khowshk \u0100var\u012b \u1e28owr"
    ],
    "wof:name":"Khoshk Avari",
    "wof:placetype":"locality"
},
  "geometry": {"coordinates":[57.27081,28.1583],"type":"Point"}
}