{
  "type": "Feature",
  "properties": {
    "gn:admin1_code":"8",
    "gn:asciiname":"Ma`af Mahalleh",
    "gn:country_code":"IR",
    "gn:dem":-22,
    "gn:feature_class":"P",
    "gn:feature_code":"PPL",
    "gn:name":"Ma\u2018\u0101f Ma\u1e29alleh",
    "gn:population":0,
    "gn:timezone":"Asia/Tehran",
    "iso:country":"IR",
    "name:fas_x_preferred":[
        "Ma\u2018\u0101f Ma\u1e29alleh"
    ],
    "wof:name":"Ma`af Mahalleh",
    "wof:placetype":"locality"
},
  "geometry": {"coordinates":[49.66639,37.40806],"type":"Point"}
}