{
  "type": "Feature",
  "properties": {
    "gn:admin1_code":"13",
    "gn:asciiname":"Davar Dar Mian",
    "gn:country_code":"IR",
    "gn:dem":1363,
    "gn:feature_class":"P",
    "gn:feature_code":"PPL",
    "gn:name":"D\u0101var Dar M\u012b\u0101n",
    "gn:population":0,
    "gn:timezone":"Asia/Tehran",
    "iso:country":"IR",
    "name:fas_x_preferred":[
        "\u062f\u0627\u0648\u0631 \u062f\u0631 \u0645\u06cc\u0627\u0646"
    ],
    "name:fas_x_variant":[
        "Dav\u0101r Dar M\u012b\u0101n",
        "D\u0101var Dar M\u012b\u0101n"
    ],
    "name:und_x_variant":[
        "Dav\u0101r Bam\u012b\u0101n"
    ],
    "wof:name":"Davar Dar Mian",
    "wof:placetype":"locality"
},
  "geometry": {"coordinates":[46.7529,33.7964],"type":"Point"}
}