{
  "type": "Feature",
  "properties": {
    "gn:admin1_code":"29",
    "gn:asciiname":"Rasulabad",
    "gn:country_code":"IR",
    "gn:dem":1402,
    "gn:feature_class":"P",
    "gn:feature_code":"PPL",
    "gn:name":"Ras\u016bl\u0101b\u0101d",
    "gn:population":0,
    "gn:timezone":"Asia/Tehran",
    "iso:country":"IR",
    "name:fas_x_preferred":[
        "Ras\u016bl\u0101b\u0101d"
    ],
    "name:fas_x_variant":[
        "\u0631\u0633\u0648\u0644 \u0622\u0628\u0627\u062f",
        "\u0631\u0633\u0648\u0644 \u0622\u0628\u0627\u062f \u0634\u0631\u06a9\u0627\u0621"
    ],
    "name:und_x_variant":[
        "Ras\u016bl\u0101b\u0101d-e Shorak\u0101\u2019"
    ],
    "wof:name":"Rasulabad",
    "wof:placetype":"locality"
},
  "geometry": {"coordinates":[55.37367,30.80439],"type":"Point"}
}