{
  "type": "Feature",
  "properties": {
    "gn:admin1_code":"29.0",
    "gn:asciiname":"Bagh Fatk",
    "gn:cc2":"IR",
    "gn:country_code":"IR",
    "gn:dem":2467,
    "gn:feature_class":"P",
    "gn:feature_code":"PPL",
    "gn:name":"B\u0101gh Fatk",
    "gn:population":0,
    "gn:timezone":"Asia/Tehran",
    "iso:country":"IR",
    "name:fas_x_preferred":[
        "B\u0101gh Fatk"
    ],
    "name:und_x_variant":[
        "B\u0101gh-e Fatak"
    ],
    "wof:name":"Bagh Fatk",
    "wof:placetype":"locality"
},
  "geometry": {"coordinates":[56.65611,29.27833],"type":"Point"}
}