{
  "type": "Feature",
  "properties": {
    "gn:admin1_code":"11",
    "gn:asciiname":"Qalaman-e Guran",
    "gn:country_code":"IR",
    "gn:dem":685,
    "gn:feature_class":"P",
    "gn:feature_code":"PPL",
    "gn:name":"Qalam\u0101n-e G\u016br\u0101n",
    "gn:population":0,
    "gn:timezone":"Asia/Tehran",
    "iso:country":"IR",
    "name:fas_x_preferred":[
        "\u0642\u064e\u0644\u064e\u0645\u0627\u0646\u0650 \u06af\u0648\u0631\u0627\u0646"
    ],
    "name:fas_x_variant":[
        "Qalam\u0101n-e G\u016br\u0101n"
    ],
    "wof:name":"Qalaman-e Guran",
    "wof:placetype":"locality"
},
  "geometry": {"coordinates":[57.28139,27.68611],"type":"Point"}
}