{
  "type": "Feature",
  "properties": {
    "gn:admin1_code":"26.0",
    "gn:asciiname":"Khorram Deh",
    "gn:country_code":"IR",
    "gn:dem":1712,
    "gn:feature_class":"P",
    "gn:feature_code":"PPL",
    "gn:name":"Khorram Deh",
    "gn:population":0,
    "gn:timezone":"Asia/Tehran",
    "iso:country":"IR",
    "name:fas_x_preferred":[
        "\u062e\u0631\u0645 \u062f\u0647"
    ],
    "wof:name":"Khorram Deh",
    "wof:placetype":"locality"
},
  "geometry": {"coordinates":[52.00602,35.63825999999999],"type":"Point"}
}