{
  "type": "Feature",
  "properties": {
    "gn:admin1_code":"39.0",
    "gn:asciiname":"Dulay Gharqi",
    "gn:country_code":"IR",
    "gn:dem":1250,
    "gn:feature_class":"P",
    "gn:feature_code":"PPL",
    "gn:name":"D\u016bl\u0101y Gh\u0101rq\u012b",
    "gn:population":0,
    "gn:timezone":"Asia/Tehran",
    "iso:country":"IR",
    "name:fas_x_preferred":[
        "\u062f\u0648\u0644\u0627\u06cc \u0642\u0627\u0631\u06cc"
    ],
    "name:fas_x_variant":[
        "D\u016bl\u0101y Q\u0101rq\u012b",
        "D\u016bl\u0101y Q\u0101r\u012b",
        "\u062f\u0648\u0644\u0627\u06cc \u063a\u0627\u0631\u0642\u06cc",
        "\u062f\u0648\u0644\u0627\u06cc \u0642\u0627\u0631\u0642\u06cc"
    ],
    "name:und_x_variant":[
        "D\u016bl\u0101-ye Q\u0101rq\u012b",
        "D\u016bl\u0101y Gh\u0101rq\u012b"
    ],
    "wof:name":"Dulay Gharqi",
    "wof:placetype":"locality"
},
  "geometry": {"coordinates":[50.88229000000001,35.14001],"type":"Point"}
}