{
  "type": "Feature",
  "properties": {
    "gn:admin1_code":"7",
    "gn:asciiname":"Sang Bid",
    "gn:country_code":"IR",
    "gn:dem":1591,
    "gn:feature_class":"P",
    "gn:feature_code":"PPLF",
    "gn:name":"Sang B\u012bd",
    "gn:population":0,
    "gn:timezone":"Asia/Tehran",
    "iso:country":"IR",
    "name:fas_x_preferred":[
        "\u0633\u0646\u06af \u0628\u06cc\u062f"
    ],
    "name:fas_x_variant":[
        "Sang B\u012bd",
        "\u0686\u0634\u0645\u0647 \u0633\u0646\u06af \u0628\u0646\u062f",
        "\u0633\u0646\u06af \u0628\u0646\u062f"
    ],
    "name:und_x_variant":[
        "Cheshmeh Sang Band",
        "Sang Band"
    ],
    "wof:name":"Sang Bid",
    "wof:placetype":"locality"
},
  "geometry": {"coordinates":[53.0091,29.8277],"type":"Point"}
}