{
  "type": "Feature",
  "properties": {
    "gn:admin1_code":"32",
    "gn:asciiname":"`Ata' od Din",
    "gn:country_code":"IR",
    "gn:dem":1386,
    "gn:feature_class":"P",
    "gn:feature_code":"PPL",
    "gn:name":"\u2018A\u0163\u0101\u2019 od D\u012bn",
    "gn:population":0,
    "gn:timezone":"Asia/Tehran",
    "iso:country":"IR",
    "name:fas_x_preferred":[
        "\u0639\u0644\u0627\u0621 \u0627\u0644\u062f\u064a\u0646"
    ],
    "name:fas_x_variant":[
        "A\u2018l\u0101 od D\u012bn",
        "\u0639\u0637\u0627\u0621 \u0627\u0644\u062f\u06cc\u0646",
        "\u0639\u0644\u0627 \u0627\u0644\u062f\u064a\u0646"
    ],
    "name:und_x_variant":[
        "\u0100l\u0101d\u012bn",
        "\u2018Al\u0101\u2019 od D\u012bn",
        "\u2018A\u0163\u0101\u2019 od D\u012bn",
        "\u2018Al\u0101 od D\u012bn"
    ],
    "wof:name":"`Ata' od Din",
    "wof:placetype":"locality"
},
  "geometry": {"coordinates":[48.21514000000001,37.53685],"type":"Point"}
}