{
  "type": "Feature",
  "properties": {
    "gn:admin1_code":"34",
    "gn:asciiname":"Band-e Chay",
    "gn:country_code":"IR",
    "gn:dem":1082,
    "gn:feature_class":"P",
    "gn:feature_code":"PPL",
    "gn:name":"Band-e Ch\u0101y",
    "gn:population":0,
    "gn:timezone":"Asia/Tehran",
    "iso:country":"IR",
    "name:fas_x_preferred":[
        "\u0628\u064e\u0646\u062f\u0686\u0627\u0644"
    ],
    "name:fas_x_variant":[
        "\u0628\u064e\u0646\u062f \u0686\u0627\u0626\u06cc",
        "Band-e Ch\u0101y",
        "\u0628\u0646\u062f \u0686\u0627\u06cc"
    ],
    "name:und_x_variant":[
        "Band Ch\u0101\u2019\u012b",
        "Bandch\u0101l",
        "\u0628\u0646\u062f \u0686\u0627\u06cc"
    ],
    "wof:name":"Band-e Chay",
    "wof:placetype":"locality"
},
  "geometry": {"coordinates":[50.18411,34.9241],"type":"Point"}
}