{
  "type": "Feature",
  "properties": {
    "gn:admin1_code":"42",
    "gn:asciiname":"Kalateh-ye Lukhi",
    "gn:country_code":"IR",
    "gn:dem":1317,
    "gn:feature_class":"P",
    "gn:feature_code":"PPL",
    "gn:name":"Kal\u0101teh-ye L\u016bkh\u012b",
    "gn:population":0,
    "gn:timezone":"Asia/Tehran",
    "iso:country":"IR",
    "name:fas_x_preferred":[
        "\u06a9\u0644\u0627\u062a\u0647 \u0644\u0648\u062e\u06cc"
    ],
    "name:fas_x_variant":[
        "Kal\u0101teh-ye L\u016bkh\u012b"
    ],
    "wof:name":"Kalateh-ye Lukhi",
    "wof:placetype":"locality"
},
  "geometry": {"coordinates":[59.19917,35.23732000000001],"type":"Point"}
}