{
  "type": "Feature",
  "properties": {
    "gn:admin1_code":"15",
    "gn:asciiname":"Shalheh-ye Romeyleh",
    "gn:country_code":"IR",
    "gn:dem":2,
    "gn:feature_class":"P",
    "gn:feature_code":"PPL",
    "gn:name":"Shalheh-ye Romeyleh",
    "gn:population":0,
    "gn:timezone":"Asia/Tehran",
    "iso:country":"IR",
    "wof:name":"Shalheh-ye Romeyleh",
    "wof:placetype":"locality"
},
  "geometry": {"coordinates":[48.35,30.28333],"type":"Point"}
}