{
  "type": "Feature",
  "properties": {
    "gn:admin1_code":"32",
    "gn:asciiname":"Sadeqlu",
    "gn:country_code":"IR",
    "gn:dem":1902,
    "gn:feature_class":"P",
    "gn:feature_code":"PPL",
    "gn:name":"\u015e\u0101deql\u016b",
    "gn:population":0,
    "gn:timezone":"Asia/Tehran",
    "iso:country":"IR",
    "name:fas_x_preferred":[
        "\u0635\u0627\u062f\u0642 \u0644\u0648"
    ],
    "name:fas_x_variant":[
        "\u015e\u0101deql\u016b"
    ],
    "wof:name":"Sadeqlu",
    "wof:placetype":"locality"
},
  "geometry": {"coordinates":[48.26636,37.88647],"type":"Point"}
}