{
  "type": "Feature",
  "properties": {
    "gn:admin1_code":"4.0",
    "gn:asciiname":"Buleh",
    "gn:country_code":"IR",
    "gn:dem":484,
    "gn:feature_class":"P",
    "gn:feature_code":"PPL",
    "gn:name":"B\u016bleh",
    "gn:population":0,
    "gn:timezone":"Asia/Tehran",
    "iso:country":"IR",
    "name:fas_x_preferred":[
        "\u0628\u0648\u0644\u0647"
    ],
    "name:fas_x_variant":[
        "B\u016bleh",
        "\u062f\u0647 \u0628\u0648\u0644\u0647"
    ],
    "name:und_x_variant":[
        "Deh-e B\u016bleh"
    ],
    "wof:name":"Buleh",
    "wof:placetype":"locality"
},
  "geometry": {"coordinates":[61.5943,31.1126],"type":"Point"}
}