{
  "type": "Feature",
  "properties": {
    "gn:admin1_code":"4.0",
    "gn:asciiname":"Kavari",
    "gn:country_code":"IR",
    "gn:dem":1347,
    "gn:feature_class":"P",
    "gn:feature_code":"PPL",
    "gn:name":"K\u0101v\u0101r\u012b",
    "gn:population":0,
    "gn:timezone":"Asia/Tehran",
    "iso:country":"IR",
    "name:fas_x_preferred":[
        "\u06a9\u0627\u0648\u0627\u0631\u06cc"
    ],
    "name:fas_x_variant":[
        "K\u0101v\u0101r\u012b"
    ],
    "wof:name":"Kavari",
    "wof:placetype":"locality"
},
  "geometry": {"coordinates":[60.40971999999999,28.30551],"type":"Point"}
}