{
  "type": "Feature",
  "properties": {
    "gn:admin1_code":"1.0",
    "gn:asciiname":"Qalatukh",
    "gn:country_code":"IR",
    "gn:dem":1627,
    "gn:feature_class":"P",
    "gn:feature_code":"PPL",
    "gn:name":"Q\u0101l\u0101t\u016bkh",
    "gn:population":0,
    "gn:timezone":"Asia/Tehran",
    "iso:country":"IR",
    "name:fas_x_preferred":[
        "\u0642\u0627\u0644\u0627\u062a\u0648\u062e"
    ],
    "name:fas_x_variant":[
        "Q\u0101l\u0101t\u016bkh"
    ],
    "wof:name":"Qalatukh",
    "wof:placetype":"locality"
},
  "geometry": {"coordinates":[45.0831,37.0487],"type":"Point"}
}