{
  "type": "Feature",
  "properties": {
    "gn:admin1_code":"33",
    "gn:asciiname":"Shurjeh-ye Qasem",
    "gn:country_code":"IR",
    "gn:dem":1423,
    "gn:feature_class":"P",
    "gn:feature_code":"PPL",
    "gn:name":"Sh\u016brjeh-ye Q\u0101sem",
    "gn:population":0,
    "gn:timezone":"Asia/Tehran",
    "iso:country":"IR",
    "name:fas_x_preferred":[
        "\u0634\u0648\u0631\u062c\u0647 \u0642\u0627\u0633\u0645"
    ],
    "name:fas_x_variant":[
        "Sh\u016brjeh-ye Q\u0101sem"
    ],
    "name:msa_x_preferred":[
        "Shurjeh-ye Qasem"
    ],
    "wof:name":"Shurjeh-ye Qasem",
    "wof:placetype":"locality"
},
  "geometry": {"coordinates":[47.5561,37.429],"type":"Point"}
}