{
  "type": "Feature",
  "properties": {
    "gn:admin1_code":"29",
    "gn:asciiname":"Chah-e Nowruz",
    "gn:country_code":"IR",
    "gn:dem":455,
    "gn:feature_class":"P",
    "gn:feature_code":"PPL",
    "gn:name":"Ch\u0101h-e Nowr\u016bz",
    "gn:population":0,
    "gn:timezone":"Asia/Tehran",
    "iso:country":"IR",
    "name:ceb_x_preferred":[
        "Ch\u0101h-e Nowr\u016bz"
    ],
    "name:fas_x_preferred":[
        "\u0686\u0627\u0647 \u0646\u0648\u0631\u0648\u0632"
    ],
    "name:fas_x_variant":[
        "Ch\u0101h-e Nowr\u016bz"
    ],
    "name:swe_x_preferred":[
        "Ch\u0101h-e Nowr\u016bz"
    ],
    "wof:name":"Chah-e Nowruz",
    "wof:placetype":"locality"
},
  "geometry": {"coordinates":[57.8458,27.4031],"type":"Point"}
}