{
  "type": "Feature",
  "properties": {
    "gn:admin1_code":"42",
    "gn:asciiname":"Kameh",
    "gn:country_code":"IR",
    "gn:dem":1435,
    "gn:feature_class":"P",
    "gn:feature_code":"PPL",
    "gn:name":"K\u0101meh",
    "gn:population":0,
    "gn:timezone":"Asia/Tehran",
    "iso:country":"IR",
    "name:ara_x_preferred":[
        "\u06a9\u0627\u0645\u0629"
    ],
    "name:fas_x_preferred":[
        "K\u0101meh"
    ],
    "name:fas_x_variant":[
        "\u06a9\u0627\u0645\u0647",
        "Kam\u012b"
    ],
    "name:und_x_variant":[
        "Kam\u012b",
        "\u06a9\u0627\u0645\u0647"
    ],
    "wof:name":"Kameh",
    "wof:placetype":"locality"
},
  "geometry": {"coordinates":[58.34413000000001,34.44459000000001],"type":"Point"}
}