{
  "type": "Feature",
  "properties": {
    "gn:admin1_code":"7",
    "gn:asciiname":"Gerd Bisheh",
    "gn:country_code":"IR",
    "gn:dem":887,
    "gn:feature_class":"P",
    "gn:feature_code":"PPL",
    "gn:name":"Gerd B\u012bsheh",
    "gn:population":0,
    "gn:timezone":"Asia/Tehran",
    "iso:country":"IR",
    "name:fas_x_preferred":[
        "\u06af\u0650\u0631\u062f \u0628\u064a\u0634\u0650\u0647"
    ],
    "name:fas_x_variant":[
        "Gerd B\u012bsheh"
    ],
    "name:und_x_variant":[
        "Gird B\u012bsheh"
    ],
    "wof:name":"Gerd Bisheh",
    "wof:placetype":"locality"
},
  "geometry": {"coordinates":[52.93333000000001,28.06667],"type":"Point"}
}