{
  "type": "Feature",
  "properties": {
    "gn:admin1_code":"8.0",
    "gn:asciiname":"Mahalleh-ye Khalavarjan",
    "gn:country_code":"IR",
    "gn:dem":51,
    "gn:feature_class":"P",
    "gn:feature_code":"PPL",
    "gn:name":"Ma\u1e29alleh-ye Khalavarj\u0101n",
    "gn:population":0,
    "gn:timezone":"Asia/Tehran",
    "iso:country":"IR",
    "name:fas_x_preferred":[
        "\u062e\u0644\u0647 \u0648\u0631\u062c\u0627\u0646"
    ],
    "name:fas_x_variant":[
        "Khalavarj\u0101n",
        "\u0645\u062d\u0644\u0647 \u062e\u0644\u0648\u0631\u062c\u0627\u0646",
        "\u062e\u0644\u0648\u0631\u062c\u0627\u0646"
    ],
    "name:und_x_variant":[
        "Khaleh Varj\u0101n",
        "Ma\u1e29alleh-ye Khalavarj\u0101n"
    ],
    "wof:name":"Mahalleh-ye Khalavarjan",
    "wof:placetype":"locality"
},
  "geometry": {"coordinates":[49.11304000000001,37.44241],"type":"Point"}
}