{
  "type": "Feature",
  "properties": {
    "gn:admin1_code":"15",
    "gn:asciiname":"Pashgar",
    "gn:country_code":"IR",
    "gn:dem":408,
    "gn:feature_class":"P",
    "gn:feature_code":"PPL",
    "gn:name":"Pashgar",
    "gn:population":0,
    "gn:timezone":"Asia/Tehran",
    "iso:country":"IR",
    "name:azb_x_preferred":[
        "\u067e\u0634\u06af\u0631(\u0628\u0647\u0628\u0647\u0627\u0646)"
    ],
    "name:fas_x_preferred":[
        "\u067e\u0634\u06a9\u0631"
    ],
    "name:fas_x_variant":[
        "\u067e\u0634\u06af\u0631"
    ],
    "name:und_x_variant":[
        "Pashkar"
    ],
    "wof:name":"Pashgar",
    "wof:placetype":"locality"
},
  "geometry": {"coordinates":[50.34474,30.69422],"type":"Point"}
}