{
  "type": "Feature",
  "properties": {
    "gn:admin1_code":"37.0",
    "gn:asciiname":"Qarah Davang",
    "gn:country_code":"IR",
    "gn:dem":84,
    "gn:feature_class":"P",
    "gn:feature_code":"PPL",
    "gn:name":"Qarah Davang",
    "gn:population":0,
    "gn:timezone":"Asia/Tehran",
    "iso:country":"IR",
    "name:fas_x_preferred":[
        "\u0642\u0631\u0647 \u062f\u0648\u0646\u06af"
    ],
    "wof:name":"Qarah Davang",
    "wof:placetype":"locality"
},
  "geometry": {"coordinates":[54.95786,37.65202],"type":"Point"}
}