{
  "type": "Feature",
  "properties": {
    "gn:admin1_code":"32",
    "gn:asciiname":"Teymur",
    "gn:country_code":"IR",
    "gn:dem":147,
    "gn:feature_class":"P",
    "gn:feature_code":"PPL",
    "gn:name":"Teym\u016br",
    "gn:population":0,
    "gn:timezone":"Asia/Tehran",
    "iso:country":"IR",
    "name:fas_x_preferred":[
        "\u062a\u064a\u0645\u0648\u0631"
    ],
    "name:fas_x_variant":[
        "T\u012bm\u016br",
        "Teym\u016br"
    ],
    "wof:name":"Teymur",
    "wof:placetype":"locality"
},
  "geometry": {"coordinates":[47.5658,39.481],"type":"Point"}
}