{
  "type": "Feature",
  "properties": {
    "gn:admin1_code":"29",
    "gn:asciiname":"Vakar Chiska",
    "gn:cc2":"IR",
    "gn:country_code":"IR",
    "gn:dem":1589,
    "gn:feature_class":"P",
    "gn:feature_code":"PPL",
    "gn:name":"Vakar Ch\u012bsk\u0101",
    "gn:population":0,
    "gn:timezone":"Asia/Tehran",
    "iso:country":"IR",
    "name:fas_x_preferred":[
        "Vakar Ch\u012bsk\u0101"
    ],
    "name:und_x_variant":[
        "Vagar Ch\u012bsk\u0101"
    ],
    "wof:name":"Vakar Chiska",
    "wof:placetype":"locality"
},
  "geometry": {"coordinates":[57.85,28.87806],"type":"Point"}
}