{
  "type": "Feature",
  "properties": {
    "gn:admin1_code":"22",
    "gn:asciiname":"Mohammad Taheri",
    "gn:country_code":"IR",
    "gn:dem":49,
    "gn:feature_class":"P",
    "gn:feature_code":"PPL",
    "gn:name":"Mo\u1e29ammad \u0162\u0101her\u012b",
    "gn:population":0,
    "gn:timezone":"Asia/Tehran",
    "iso:country":"IR",
    "name:fas_x_preferred":[
        "\u0645\u062d\u0645\u062f \u0637\u0627\u0647\u0631\u06cc"
    ],
    "name:fas_x_variant":[
        "Mo\u1e29ammad \u0162\u0101her\u012b",
        "\u0645\u062d\u0645\u062f\u0637\u0627\u0647\u0631\u06cc"
    ],
    "name:msa_x_preferred":[
        "Mohammad Taheri"
    ],
    "wof:name":"Mohammad Taheri",
    "wof:placetype":"locality"
},
  "geometry": {"coordinates":[51.2099,28.8164],"type":"Point"}
}