{
  "type": "Feature",
  "properties": {
    "gn:admin1_code":"1",
    "gn:asciiname":"Darbarud",
    "gn:country_code":"IR",
    "gn:dem":1285,
    "gn:feature_class":"P",
    "gn:feature_code":"PPL",
    "gn:name":"D\u0101rb\u0101r\u016bd",
    "gn:population":0,
    "gn:timezone":"Asia/Tehran",
    "iso:country":"IR",
    "name:aze_x_preferred":[
        "D\u0259rb\u0259rud"
    ],
    "name:ceb_x_preferred":[
        "D\u0101rb\u0101r\u016bd"
    ],
    "name:fas_x_preferred":[
        "\u062f\u0627\u0631\u0628\u0627\u0631\u0648\u062f"
    ],
    "name:fas_x_variant":[
        "\u062f\u0631\u0628\u0627\u0631\u0648\u062f",
        "D\u0101rb\u0101r\u016bd"
    ],
    "name:msa_x_preferred":[
        "Darbarud"
    ],
    "name:swe_x_preferred":[
        "D\u0101rb\u0101r\u016bd"
    ],
    "name:ukr_x_preferred":[
        "\u0414\u0430\u0440\u0431\u0430\u0440\u0443\u0434"
    ],
    "wof:name":"Darbarud",
    "wof:placetype":"locality"
},
  "geometry": {"coordinates":[45.2226,37.4059],"type":"Point"}
}