{
  "type": "Feature",
  "properties": {
    "gn:admin1_code":"4.0",
    "gn:asciiname":"Hit",
    "gn:country_code":"IR",
    "gn:dem":432,
    "gn:feature_class":"P",
    "gn:feature_code":"PPL",
    "gn:name":"H\u012bt",
    "gn:population":0,
    "gn:timezone":"Asia/Tehran",
    "iso:country":"IR",
    "name:aze_x_preferred":[
        "Hit"
    ],
    "name:dan_x_preferred":[
        "Hit"
    ],
    "name:deu_x_preferred":[
        "Hit"
    ],
    "name:fas_x_preferred":[
        "\u0647\u06cc\u062a"
    ],
    "name:fas_x_variant":[
        "H\u012bt"
    ],
    "name:fry_x_preferred":[
        "Hit"
    ],
    "name:hun_x_preferred":[
        "Hit"
    ],
    "name:nld_x_preferred":[
        "Hit"
    ],
    "name:pol_x_preferred":[
        "Hit"
    ],
    "name:por_x_preferred":[
        "Hit"
    ],
    "name:rus_x_preferred":[
        "\u0425\u0438\u0442"
    ],
    "name:slk_x_preferred":[
        "Hit"
    ],
    "name:spa_x_preferred":[
        "Hit"
    ],
    "name:srp_x_preferred":[
        "\u0425\u0438\u0442"
    ],
    "name:swe_x_preferred":[
        "Hit"
    ],
    "name:tur_x_preferred":[
        "Hit"
    ],
    "name:ukr_x_preferred":[
        "\u0425\u0456\u0442"
    ],
    "name:und_x_variant":[
        "Heyyat",
        "Hait",
        "Heyt"
    ],
    "wof:name":"Hit",
    "wof:placetype":"locality"
},
  "geometry": {"coordinates":[60.6797,26.1953],"type":"Point"}
}