{
  "type": "Feature",
  "properties": {
    "gn:admin1_code":"4.0",
    "gn:asciiname":"Hit",
    "gn:country_code":"IR",
    "gn:dem":432,
    "gn:feature_class":"P",
    "gn:feature_code":"PPL",
    "gn:name":"H\u012bt",
    "gn:population":0,
    "gn:timezone":"Asia/Tehran",
    "iso:country":"IR",
    "name:fas_x_preferred":[
        "\u0647\u06cc\u062a"
    ],
    "name:fas_x_variant":[
        "H\u012bt"
    ],
    "name:und_x_variant":[
        "Heyyat",
        "Hait",
        "Heyt"
    ],
    "wof:name":"Hit",
    "wof:placetype":"locality"
},
  "geometry": {"coordinates":[60.6797,26.1953],"type":"Point"}
}