{
  "type": "Feature",
  "properties": {
    "gn:admin1_code":"35",
    "gn:asciiname":"Duk-e Bala",
    "gn:country_code":"IR",
    "gn:dem":8,
    "gn:feature_class":"P",
    "gn:feature_code":"PPL",
    "gn:name":"D\u016bk-e B\u0101l\u0101",
    "gn:population":0,
    "gn:timezone":"Asia/Tehran",
    "iso:country":"IR",
    "name:fas_x_preferred":[
        "\u062f\u0648\u0643"
    ],
    "name:fas_x_variant":[
        "D\u016bk",
        "D\u016bk-e B\u0101l\u0101",
        "\u062f\u0648\u0643 \u0628\u0627\u0644\u0627"
    ],
    "wof:name":"Duk-e Bala",
    "wof:placetype":"locality"
},
  "geometry": {"coordinates":[52.85193,36.53123],"type":"Point"}
}