{
  "type": "Feature",
  "properties": {
    "gn:admin1_code":"23",
    "gn:asciiname":"Zangolvar",
    "gn:country_code":"IR",
    "gn:dem":1881,
    "gn:feature_class":"P",
    "gn:feature_code":"PPL",
    "gn:name":"Zangolv\u0101r",
    "gn:population":0,
    "gn:timezone":"Asia/Tehran",
    "iso:country":"IR",
    "name:fas_x_preferred":[
        "\u0632\u064e\u0646\u06af\u0648\u0644 \u062f\u064e\u0631"
    ],
    "name:fas_x_variant":[
        "\u0632\u0646\u06af\u0648\u0644\u0648\u0627\u0631",
        "Zang\u016bl Dar",
        "Zang\u016blv\u0101r",
        "\u0632\u0646\u06af\u0644\u0648\u0627\u0631"
    ],
    "name:und_x_variant":[
        "Zangolv\u0101r"
    ],
    "wof:name":"Zangolvar",
    "wof:placetype":"locality"
},
  "geometry": {"coordinates":[48.76798,33.26054],"type":"Point"}
}