{
  "type": "Feature",
  "properties": {
    "gn:admin1_code":"13",
    "gn:asciiname":"Pir Mozd",
    "gn:country_code":"IR",
    "gn:dem":1332,
    "gn:feature_class":"P",
    "gn:feature_code":"PPL",
    "gn:name":"P\u012br Mozd",
    "gn:population":0,
    "gn:timezone":"Asia/Tehran",
    "iso:country":"IR",
    "name:fas_x_preferred":[
        "\u067e\u06cc\u0631 \u0645\u0632\u062f"
    ],
    "name:fas_x_variant":[
        "P\u012br Mozd",
        "\u067e\u06cc\u0631\u0645\u0632\u062f"
    ],
    "wof:name":"Pir Mozd",
    "wof:placetype":"locality"
},
  "geometry": {"coordinates":[46.8878,34.6611],"type":"Point"}
}