{
  "type": "Feature",
  "properties": {
    "gn:admin1_code":"4",
    "gn:asciiname":"Kaluki",
    "gn:country_code":"IR",
    "gn:dem":1264,
    "gn:feature_class":"P",
    "gn:feature_code":"PPL",
    "gn:name":"Kal\u016bk\u012b",
    "gn:population":0,
    "gn:timezone":"Asia/Tehran",
    "iso:country":"IR",
    "name:fas_x_preferred":[
        "\u06a9\u0644\u0648\u06a9\u06cc"
    ],
    "name:fas_x_variant":[
        "Kal\u016bk\u012b"
    ],
    "wof:name":"Kaluki",
    "wof:placetype":"locality"
},
  "geometry": {"coordinates":[62.3211,26.8516],"type":"Point"}
}