{
  "type": "Feature",
  "properties": {
    "gn:admin1_code":"13",
    "gn:asciiname":"Karvaneh-ye Sofla",
    "gn:country_code":"IR",
    "gn:dem":1473,
    "gn:feature_class":"P",
    "gn:feature_code":"PPL",
    "gn:name":"K\u0101rv\u0101neh-ye Sofl\u00e1",
    "gn:population":0,
    "gn:timezone":"Asia/Tehran",
    "iso:country":"IR",
    "name:ceb_x_preferred":[
        "K\u0101rv\u0101neh-ye Sofl\u00e1"
    ],
    "name:fas_x_preferred":[
        "\u06a9\u0627\u0631\u0648\u0627\u0646\u0647 \u0633\u0641\u0644\u06cc"
    ],
    "name:fas_x_variant":[
        "K\u0101rv\u0101neh-ye Sofl\u00e1"
    ],
    "name:swe_x_preferred":[
        "K\u0101rv\u0101neh-ye Sofl\u00e1"
    ],
    "wof:name":"Karvaneh-ye Sofla",
    "wof:placetype":"locality"
},
  "geometry": {"coordinates":[47.093,34.1159],"type":"Point"}
}