{
  "type": "Feature",
  "properties": {
    "gn:admin1_code":"28",
    "gn:asciiname":"Tokhmaghlu",
    "gn:country_code":"IR",
    "gn:dem":2294,
    "gn:feature_class":"P",
    "gn:feature_code":"PPL",
    "gn:name":"Tokhm\u0101ghl\u016b",
    "gn:population":0,
    "gn:timezone":"Asia/Tehran",
    "iso:country":"IR",
    "name:ara_x_preferred":[
        "\u062a\u062e\u0645\u0627\u0642\u0644\u0648"
    ],
    "name:fas_x_preferred":[
        "Tokhm\u0101ql\u016b"
    ],
    "name:fas_x_variant":[
        "Tokhm\u0101ghl\u016b",
        "\u062a\u062e\u0645\u0627\u063a\u0644\u0648",
        "\u062a\u062e\u0645\u0627\u0642\u0644\u0648"
    ],
    "name:und_x_variant":[
        "Tukhm \u0100qlu",
        "\u062a\u062e\u0645\u0627\u063a\u0644\u0648"
    ],
    "wof:name":"Tokhmaghlu",
    "wof:placetype":"locality"
},
  "geometry": {"coordinates":[50.13171,33.19538],"type":"Point"}
}