{
  "type": "Feature",
  "properties": {
    "gn:admin1_code":"8.0",
    "gn:asciiname":"Gisum-e Pa'in",
    "gn:country_code":"IR",
    "gn:dem":-19,
    "gn:feature_class":"P",
    "gn:feature_code":"PPL",
    "gn:name":"G\u012bs\u016bm-e P\u0101\u2019\u012bn",
    "gn:population":0,
    "gn:timezone":"Asia/Tehran",
    "iso:country":"IR",
    "name:fas_x_preferred":[
        "\u06af\u06cc\u0633\u0648\u0645 \u067e\u0627\u0626\u06cc\u0646"
    ],
    "name:fas_x_variant":[
        "G\u012bs\u016bm-e P\u0101\u2019\u012bn"
    ],
    "wof:name":"Gisum-e Pa'in",
    "wof:placetype":"locality"
},
  "geometry": {"coordinates":[49.02964,37.67428],"type":"Point"}
}