{
  "type": "Feature",
  "properties": {
    "gn:admin1_code":"8.0",
    "gn:asciiname":"Suleh Sara",
    "gn:country_code":"IR",
    "gn:dem":1488,
    "gn:feature_class":"P",
    "gn:feature_code":"PPL",
    "gn:name":"S\u016bleh Sar\u0101",
    "gn:population":0,
    "gn:timezone":"Asia/Tehran",
    "iso:country":"IR",
    "name:fas_x_preferred":[
        "S\u016bleh Sar\u0101"
    ],
    "name:fas_x_variant":[
        "\u0633\u0648\u0644\u0647 \u0633\u0631\u0627"
    ],
    "wof:name":"Suleh Sara",
    "wof:placetype":"locality"
},
  "geometry": {"coordinates":[50.52161,36.89014],"type":"Point"}
}