{
  "type": "Feature",
  "properties": {
    "gn:admin1_code":"4",
    "gn:asciiname":"Juri",
    "gn:country_code":"IR",
    "gn:dem":1063,
    "gn:feature_class":"P",
    "gn:feature_code":"PPL",
    "gn:name":"J\u016br\u012b",
    "gn:population":0,
    "gn:timezone":"Asia/Tehran",
    "iso:country":"IR",
    "name:ceb_x_preferred":[
        "Juri"
    ],
    "name:deu_x_preferred":[
        "Juri"
    ],
    "name:fas_x_preferred":[
        "J\u016br\u012b"
    ],
    "name:fas_x_variant":[
        "\u062c\u0648\u0631\u06cc"
    ],
    "name:hun_x_preferred":[
        "Juri"
    ],
    "name:ita_x_preferred":[
        "Juri"
    ],
    "name:por_x_preferred":[
        "Juri"
    ],
    "name:rus_x_preferred":[
        "\u0414\u0436\u0443\u0440\u0438"
    ],
    "name:slk_x_preferred":[
        "Juri"
    ],
    "name:swe_x_preferred":[
        "Juri"
    ],
    "name:und_x_variant":[
        "\u062c\u0648\u0631\u06cc"
    ],
    "name:vie_x_preferred":[
        "Juri"
    ],
    "wof:name":"Juri",
    "wof:placetype":"locality"
},
  "geometry": {"coordinates":[61.00159,26.49124],"type":"Point"}
}