{
  "type": "Feature",
  "properties": {
    "gn:admin1_code":"16.0",
    "gn:asciiname":"Shilan",
    "gn:country_code":"IR",
    "gn:dem":1378,
    "gn:elevation":"0.0",
    "gn:feature_class":"P",
    "gn:feature_code":"PPL",
    "gn:name":"Sh\u012bl\u0101n",
    "gn:population":0,
    "gn:timezone":"Asia/Tehran",
    "iso:country":"IR",
    "name:fas_x_preferred":[
        "\u0634\u06cc\u0644\u0627\u0646"
    ],
    "name:fas_x_variant":[
        "Sh\u012bl\u0101n"
    ],
    "wof:name":"Shilan",
    "wof:placetype":"locality"
},
  "geometry": {"coordinates":[46.9411,35.0967],"type":"Point"}
}