{
  "type": "Feature",
  "properties": {
    "gn:admin1_code":"44",
    "gn:asciiname":"Ahmadabad",
    "gn:country_code":"IR",
    "gn:dem":1179,
    "gn:feature_class":"P",
    "gn:feature_code":"PPL",
    "gn:name":"A\u1e29mad\u0101b\u0101d",
    "gn:population":0,
    "gn:timezone":"Asia/Tehran",
    "iso:country":"IR",
    "name:ara_x_preferred":[
        "\u0627\u062d\u0645\u062f\u0627\u0628\u0627\u062f\u0645\u0635\u062f\u0642"
    ],
    "name:fas_x_preferred":[
        "\u0627\u062d\u0645\u062f\u0622\u0628\u0627\u062f \u0645\u0635\u062f\u0642"
    ],
    "name:fas_x_variant":[
        "A\u1e29mad\u0101b\u0101d-e K\u0101sh\u0101n\u012b",
        "A\u1e29mad\u0101b\u0101d-e Mo\u015faddeq",
        "\u0627\u062d\u0645\u062f \u0622\u0628\u0627\u062f",
        "\u0642\u0644\u0639\u0647 \u0627\u062d\u0645\u062f\u0622\u0628\u0627\u062f"
    ],
    "name:fra_x_preferred":[
        "Ahmadabad"
    ],
    "name:ita_x_preferred":[
        "Ahmadabad"
    ],
    "name:msa_x_preferred":[
        "Ahmadabad-e Mosaddeq"
    ],
    "name:pol_x_preferred":[
        "Ahmadabad-e Mosaddegh"
    ],
    "name:rus_x_preferred":[
        "\u0410\u0445\u043c\u0435\u0434\u0430\u0431\u0430\u0434\u0435-\u041c\u043e\u0441\u0430\u0434\u0434\u0435\u043a"
    ],
    "name:und_x_variant":[
        "A\u1e29mad\u0101b\u0101d"
    ],
    "wof:name":"Ahmadabad",
    "wof:placetype":"locality"
},
  "geometry": {"coordinates":[50.4752,35.9938],"type":"Point"}
}