{
  "type": "Feature",
  "properties": {
    "gn:admin1_code":"42.0",
    "gn:asciiname":"Javadiyeh",
    "gn:country_code":"IR",
    "gn:dem":1305,
    "gn:feature_class":"P",
    "gn:feature_code":"PPL",
    "gn:name":"Jav\u0101d\u012byeh",
    "gn:population":0,
    "gn:timezone":"Asia/Tehran",
    "iso:country":"IR",
    "name:fas_x_preferred":[
        "\u0646\u0648 \u0628\u0646\u06cc\u0627\u062f"
    ],
    "name:fas_x_variant":[
        "Now Bony\u0101d",
        "\u062c\u0648\u0627\u062f\u06cc\u0647",
        "\u062d\u0633\u06cc\u0646 \u0622\u0628\u0627\u062f \u0686\u0646\u06af\u0647 \u0639\u0628\u0627\u0633\u06cc"
    ],
    "name:und_x_variant":[
        "Jav\u0101d\u012byeh",
        "\u1e28oseyn\u0101b\u0101d-e Chang \u2018Abb\u0101s\u012b",
        "\u1e28oseyn\u0101b\u0101d-e Changeh \u2018Abb\u0101s\u012b"
    ],
    "wof:name":"Javadiyeh",
    "wof:placetype":"locality"
},
  "geometry": {"coordinates":[59.1457,36.0399],"type":"Point"}
}