{
  "type": "Feature",
  "properties": {
    "gn:admin1_code":"41",
    "gn:asciiname":"Kaseh Sangi",
    "gn:country_code":"IR",
    "gn:dem":1664,
    "gn:feature_class":"P",
    "gn:feature_code":"PPL",
    "gn:name":"K\u0101seh Sang\u012b",
    "gn:population":0,
    "gn:timezone":"Asia/Tehran",
    "iso:country":"IR",
    "name:ara_x_preferred":[
        "\u0643\u0627\u0633\u0629 \u0633\u0646\u063a\u064a"
    ],
    "name:ceb_x_preferred":[
        "K\u0101seh Sang\u012b"
    ],
    "name:fas_x_preferred":[
        "K\u0101seh Sang\u012b"
    ],
    "name:fas_x_variant":[
        "\u06a9\u0627\u0633\u0647 \u0633\u0646\u06af\u06cc",
        "K\u0101seh Sang"
    ],
    "name:swe_x_preferred":[
        "K\u0101seh Sang\u012b"
    ],
    "wof:name":"Kaseh Sangi",
    "wof:placetype":"locality"
},
  "geometry": {"coordinates":[59.18411,32.82725],"type":"Point"}
}