{
  "type": "Feature",
  "properties": {
    "gn:admin1_code":"8",
    "gn:asciiname":"Wermani",
    "gn:country_code":"IR",
    "gn:dem":-17,
    "gn:feature_class":"P",
    "gn:feature_code":"PPL",
    "gn:name":"Wermani",
    "gn:population":0,
    "gn:timezone":"Asia/Tehran",
    "iso:country":"IR",
    "name:fas_x_preferred":[
        "\u0648\u06cc\u0631\u0645\u0648\u0646\u06cc"
    ],
    "name:fas_x_variant":[
        "V\u012brm\u016bn\u012b"
    ],
    "name:msa_x_preferred":[
        "Virmuni"
    ],
    "name:ukr_x_preferred":[
        "\u0412\u0456\u0440\u043c\u0443\u043d\u0456"
    ],
    "wof:name":"Wermani",
    "wof:placetype":"locality"
},
  "geometry": {"coordinates":[48.8338,38.4163],"type":"Point"}
}