{
  "type": "Feature",
  "properties": {
    "gn:admin1_code":"26.0",
    "gn:asciiname":"Hajjiabad",
    "gn:cc2":"IR",
    "gn:country_code":"IR",
    "gn:dem":989,
    "gn:feature_class":"P",
    "gn:feature_code":"PPL",
    "gn:name":"H\u0101jj\u012b\u0101b\u0101d",
    "gn:population":0,
    "gn:timezone":"Asia/Tehran",
    "iso:country":"IR",
    "name:fas_x_preferred":[
        "\u0647\u0627\u062c\u0651\u06cc \u0622\u0628\u0627\u062f"
    ],
    "name:fas_x_variant":[
        "\u0647\u0627\u062c\u06cc \u0622\u0628\u0627\u062f",
        "H\u0101jj\u012b\u0101b\u0101d"
    ],
    "name:und_x_variant":[
        "H\u0101j\u012b\u0101b\u0101d"
    ],
    "wof:name":"Hajjiabad",
    "wof:placetype":"locality"
},
  "geometry": {"coordinates":[51.16917,35.39889],"type":"Point"}
}