{
  "type": "Feature",
  "properties": {
    "gn:admin1_code":"8.0",
    "gn:asciiname":"Pulustan",
    "gn:country_code":"IR",
    "gn:dem":1946,
    "gn:feature_class":"P",
    "gn:feature_code":"PPL",
    "gn:name":"P\u016bl\u016bst\u0101n",
    "gn:population":0,
    "gn:timezone":"Asia/Tehran",
    "iso:country":"IR",
    "name:fas_x_preferred":[
        "\u067e\u0648\u0644\u0648\u0633\u062a\u0627\u0646"
    ],
    "name:fas_x_variant":[
        "\u067e\u0644\u0633\u062a\u0627\u0646"
    ],
    "name:und_x_variant":[
        "P\u016bl\u016bst\u0101n",
        "Polest\u0101n"
    ],
    "wof:name":"Pulustan",
    "wof:placetype":"locality"
},
  "geometry": {"coordinates":[50.31545,36.69326],"type":"Point"}
}