{
  "type": "Feature",
  "properties": {
    "gn:admin1_code":"23",
    "gn:asciiname":"Jahadabad",
    "gn:country_code":"IR",
    "gn:dem":1773,
    "gn:feature_class":"P",
    "gn:feature_code":"PPL",
    "gn:name":"Jah\u0101d\u0101b\u0101d",
    "gn:population":0,
    "gn:timezone":"Asia/Tehran",
    "iso:country":"IR",
    "name:fas_x_preferred":[
        "Jah\u0101d\u0101b\u0101d"
    ],
    "wof:name":"Jahadabad",
    "wof:placetype":"locality"
},
  "geometry": {"coordinates":[48.70806,33.53389],"type":"Point"}
}