{
  "type": "Feature",
  "properties": {
    "gn:admin1_code":"15",
    "gn:asciiname":"Seyyed Anjiri",
    "gn:country_code":"IR",
    "gn:dem":958,
    "gn:feature_class":"P",
    "gn:feature_code":"PPL",
    "gn:name":"Seyyed Anj\u012br\u012b",
    "gn:population":0,
    "gn:timezone":"Asia/Tehran",
    "iso:country":"IR",
    "name:fas_x_preferred":[
        "Seyyed Anj\u012br\u012b"
    ],
    "wof:name":"Seyyed Anjiri",
    "wof:placetype":"locality"
},
  "geometry": {"coordinates":[50.11667,31.72972],"type":"Point"}
}