{
  "type": "Feature",
  "properties": {
    "gn:admin1_code":"40.0",
    "gn:asciiname":"Mahalleh-ye Mir Seyyed Mohammad",
    "gn:country_code":"IR",
    "gn:dem":1624,
    "gn:feature_class":"P",
    "gn:feature_code":"PPL",
    "gn:name":"Ma\u1e29alleh-ye M\u012br Seyyed Mo\u1e29ammad",
    "gn:population":0,
    "gn:timezone":"Asia/Tehran",
    "iso:country":"IR",
    "name:fas_x_preferred":[
        "\u0645\u062d\u0644\u0647 \u0645\u06cc\u0631 \u0633\u06cc\u062f \u0645\u062d\u0645\u062f"
    ],
    "name:und_x_variant":[
        "Ma\u1e29alleh-ye M\u012br Seyyed Mo\u1e29ammad"
    ],
    "wof:name":"Mahalleh-ye Mir Seyyed Mohammad",
    "wof:placetype":"locality"
},
  "geometry": {"coordinates":[54.16664,31.73094],"type":"Point"}
}