{
  "type": "Feature",
  "properties": {
    "gn:admin1_code":"34",
    "gn:asciiname":"Khana Darreh-ye Sofla",
    "gn:country_code":"IR",
    "gn:dem":2072,
    "gn:feature_class":"P",
    "gn:feature_code":"PPL",
    "gn:name":"Khan\u0101 Darreh-ye Sofl\u00e1",
    "gn:population":0,
    "gn:timezone":"Asia/Tehran",
    "iso:country":"IR",
    "name:ceb_x_preferred":[
        "Khan\u0101 Darreh-ye Sofl\u00e1"
    ],
    "name:fas_x_preferred":[
        "\u062e\u0646\u0627 \u062f\u0631\u0647 \u0633\u0641\u0644\u06cc"
    ],
    "name:fas_x_variant":[
        "Khan\u0101 Darreh-ye Sofl\u00e1",
        "\u062e\u0646\u0627\u0631 \u062f\u0631\u0647 \u0633\u0641\u0644\u06cc"
    ],
    "name:swe_x_preferred":[
        "Khan\u0101 Darreh-ye Sofl\u00e1"
    ],
    "name:ukr_x_preferred":[
        "\u0425\u0430\u043d\u0430-\u0414\u0430\u0440\u0440\u0435-\u0454 \u0421\u043e\u0444\u043b\u0430"
    ],
    "name:und_x_variant":[
        "Khen\u0101 Darreh-ye P\u0101\u2019\u012bn",
        "Khen\u0101 Darreh-ye Sofl\u00e1",
        "Khen\u0101 Darreh P\u0101\u2019\u012bn",
        "Khenadarah",
        "Khan\u0101r Darreh-ye Sofl\u00e1"
    ],
    "wof:name":"Khana Darreh-ye Sofla",
    "wof:placetype":"locality"
},
  "geometry": {"coordinates":[49.20954,33.75414],"type":"Point"}
}