{
  "type": "Feature",
  "properties": {
    "gn:admin1_code":"1",
    "gn:asciiname":"Qermez Bolagh",
    "gn:country_code":"IR",
    "gn:dem":1428,
    "gn:feature_class":"P",
    "gn:feature_code":"PPL",
    "gn:name":"Qermez Bol\u0101gh",
    "gn:population":0,
    "gn:timezone":"Asia/Tehran",
    "iso:country":"IR",
    "name:aze_x_preferred":[
        "Q\u0131rm\u0131z\u0131 Bulaq"
    ],
    "name:fas_x_preferred":[
        "\u0642\u0631\u0645\u0632 \u0628\u0644\u0627\u063a"
    ],
    "name:fas_x_variant":[
        "Qermez Bol\u0101gh",
        "\u0642\u0631\u0645\u0632\u06cc \u0628\u0644\u0627\u063a",
        "\u0642\u0631\u0645\u0632\u06cc\u200c\u0628\u0644\u0627\u063a"
    ],
    "name:msa_x_preferred":[
        "Qermezi Bolagh"
    ],
    "name:und_x_variant":[
        "Qermez\u012b Bol\u0101gh"
    ],
    "wof:name":"Qermez Bolagh",
    "wof:placetype":"locality"
},
  "geometry": {"coordinates":[46.4194,37.0413],"type":"Point"}
}