{
  "type": "Feature",
  "properties": {
    "gn:admin1_code":"23",
    "gn:asciiname":"Aftabaran",
    "gn:country_code":"IR",
    "gn:dem":1769,
    "gn:feature_class":"P",
    "gn:feature_code":"PPL",
    "gn:name":"\u0100ft\u0101bar\u0101n",
    "gn:population":0,
    "gn:timezone":"Asia/Tehran",
    "iso:country":"IR",
    "name:fas_x_preferred":[
        "\u0622\u0641\u062a\u0627\u0628\u0631\u0627\u0646"
    ],
    "name:fas_x_variant":[
        "\u0100ft\u0101bar\u0101n"
    ],
    "wof:name":"Aftabaran",
    "wof:placetype":"locality"
},
  "geometry": {"coordinates":[47.7657,34.1245],"type":"Point"}
}