{
  "type": "Feature",
  "properties": {
    "gn:admin1_code":"8.0",
    "gn:asciiname":"Kandeh Bunak",
    "gn:country_code":"IR",
    "gn:dem":129,
    "gn:feature_class":"P",
    "gn:feature_code":"PPL",
    "gn:name":"Kandeh B\u016bnak",
    "gn:population":0,
    "gn:timezone":"Asia/Tehran",
    "iso:country":"IR",
    "name:fas_x_preferred":[
        "Kandeh B\u016bnak"
    ],
    "name:fas_x_variant":[
        "\u06a9\u0646\u062f\u0647 \u0628\u0648\u0646\u06a9"
    ],
    "wof:name":"Kandeh Bunak",
    "wof:placetype":"locality"
},
  "geometry": {"coordinates":[50.29649000000001,36.99249],"type":"Point"}
}