{
  "type": "Feature",
  "properties": {
    "gn:admin1_code":"15.0",
    "gn:asciiname":"Machasebeh",
    "gn:country_code":"IR",
    "gn:dem":6,
    "gn:feature_class":"P",
    "gn:feature_code":"PPL",
    "gn:name":"Mach\u0101sebeh",
    "gn:population":0,
    "gn:timezone":"Asia/Tehran",
    "iso:country":"IR",
    "name:fas_x_preferred":[
        "\u0645\u0686\u0627\u0633\u0628\u0647"
    ],
    "name:fas_x_variant":[
        "\u0645\u0633\u06cc\u0651\u0631"
    ],
    "name:und_x_variant":[
        "Mach\u0101sebeh",
        "Mosayyer"
    ],
    "wof:name":"Machasebeh",
    "wof:placetype":"locality"
},
  "geometry": {"coordinates":[48.70577,30.67826],"type":"Point"}
}