{
  "type": "Feature",
  "properties": {
    "gn:admin1_code":"15",
    "gn:asciiname":"Morvarid",
    "gn:country_code":"IR",
    "gn:dem":1745,
    "gn:feature_class":"P",
    "gn:feature_code":"PPL",
    "gn:name":"Morv\u0101r\u012bd",
    "gn:population":0,
    "gn:timezone":"Asia/Tehran",
    "iso:country":"IR",
    "name:fas_x_preferred":[
        "Morv\u0101r\u012bd"
    ],
    "name:fas_x_variant":[
        "\u0645\u0631\u0648\u0627\u0631\u06cc\u062f"
    ],
    "name:und_x_variant":[
        "Mawari",
        "Morvar\u012bd",
        "Marvar\u012b",
        "Mavar\u012b"
    ],
    "wof:name":"Morvarid",
    "wof:placetype":"locality"
},
  "geometry": {"coordinates":[50.38246,31.73112],"type":"Point"}
}