{
  "type": "Feature",
  "properties": {
    "gn:admin1_code":"33",
    "gn:asciiname":"Kahjuq",
    "gn:country_code":"IR",
    "gn:dem":1630,
    "gn:feature_class":"P",
    "gn:feature_code":"PPL",
    "gn:name":"Kahj\u016bq",
    "gn:population":0,
    "gn:timezone":"Asia/Tehran",
    "iso:country":"IR",
    "name:azb_x_preferred":[
        "\u06a9\u0647\u062c\u0648\u0642"
    ],
    "name:fas_x_preferred":[
        "\u06a9\u0647\u062c\u0648\u0642"
    ],
    "name:fas_x_variant":[
        "Kahj\u016bq"
    ],
    "name:msa_x_preferred":[
        "Kahjuq"
    ],
    "wof:name":"Kahjuq",
    "wof:placetype":"locality"
},
  "geometry": {"coordinates":[46.4042,37.3246],"type":"Point"}
}