{
  "type": "Feature",
  "properties": {
    "gn:admin1_code":"35.0",
    "gn:asciiname":"`Ur Dasht",
    "gn:country_code":"IR",
    "gn:dem":2,
    "gn:feature_class":"P",
    "gn:feature_code":"PPL",
    "gn:name":"\u2018\u016ar Dasht",
    "gn:population":0,
    "gn:timezone":"Asia/Tehran",
    "iso:country":"IR",
    "name:fas_x_preferred":[
        "\u0639\u0648\u0631\u0637\u064e\u0634\u062a"
    ],
    "name:fas_x_variant":[
        "\u0639\u0648\u0631\u0637",
        "\u2018\u016ar\u0163asht",
        "\u2018\u016ar Dasht",
        "\u0639\u0648\u0631 \u062f\u0634\u062a"
    ],
    "name:und_x_variant":[
        "\u2018\u016ar\u0163"
    ],
    "wof:name":"`Ur Dasht",
    "wof:placetype":"locality"
},
  "geometry": {"coordinates":[52.37268,36.57007],"type":"Point"}
}