{
  "type": "Feature",
  "properties": {
    "gn:admin1_code":"37",
    "gn:asciiname":"Owdarreh",
    "gn:country_code":"IR",
    "gn:dem":1766,
    "gn:feature_class":"P",
    "gn:feature_code":"PPL",
    "gn:name":"Owdarreh",
    "gn:population":0,
    "gn:timezone":"Asia/Tehran",
    "iso:country":"IR",
    "name:fas_x_preferred":[
        "\u067e\u0627\u0626\u064a\u0646 \u0622\u0628 \u062f\u0631\u0647"
    ],
    "name:fas_x_variant":[
        "P\u0101\u2019\u012bn \u0100b Darreh",
        "\u0627\u0648\u062f\u0631\u0647"
    ],
    "wof:name":"Owdarreh",
    "wof:placetype":"locality"
},
  "geometry": {"coordinates":[54.28929,36.67932],"type":"Point"}
}