{
  "type": "Feature",
  "properties": {
    "gn:admin1_code":"25",
    "gn:asciiname":"Rameh-ye Bala",
    "gn:country_code":"IR",
    "gn:dem":2081,
    "gn:feature_class":"P",
    "gn:feature_code":"PPL",
    "gn:name":"R\u0101meh-ye B\u0101l\u0101",
    "gn:population":0,
    "gn:timezone":"Asia/Tehran",
    "iso:country":"IR",
    "name:fas_x_preferred":[
        "\u0631\u0627\u0645\u0647 \u0628\u0627\u0644\u0627"
    ],
    "name:fas_x_variant":[
        "R\u0101meh-ye B\u0101l\u0101"
    ],
    "name:und_x_variant":[
        "R\u0101meh-ye B\u0101l\u0101"
    ],
    "wof:name":"Rameh-ye Bala",
    "wof:placetype":"locality"
},
  "geometry": {"coordinates":[52.7252,35.47667],"type":"Point"}
}