{
  "type": "Feature",
  "properties": {
    "gn:admin1_code":"4",
    "gn:asciiname":"Gazdar",
    "gn:country_code":"IR",
    "gn:dem":1071,
    "gn:feature_class":"P",
    "gn:feature_code":"PPL",
    "gn:name":"Gazdar",
    "gn:population":0,
    "gn:timezone":"Asia/Tehran",
    "iso:country":"IR",
    "name:fas_x_preferred":[
        "\u06af\u0632\u062f\u0631"
    ],
    "wof:name":"Gazdar",
    "wof:placetype":"locality"
},
  "geometry": {"coordinates":[62.6498,26.7395],"type":"Point"}
}