{
  "type": "Feature",
  "properties": {
    "gn:admin1_code":"26.0",
    "gn:asciiname":"Ab Sard",
    "gn:country_code":"IR",
    "gn:dem":1931,
    "gn:feature_class":"P",
    "gn:feature_code":"PPL",
    "gn:name":"\u0100b Sard",
    "gn:population":0,
    "gn:timezone":"Asia/Tehran",
    "iso:country":"IR",
    "name:ara_x_preferred":[
        "\u0622\u0628\u0633\u0631\u062f"
    ],
    "name:azb_x_preferred":[
        "\u0622\u0628\u0633\u0631\u062f"
    ],
    "name:fas_x_preferred":[
        "\u0622\u0628\u0633\u0631\u062f"
    ],
    "name:fas_x_variant":[
        "\u0100b Sard"
    ],
    "name:ita_x_preferred":[
        "Absard"
    ],
    "name:mlg_x_preferred":[
        "Absard"
    ],
    "name:mzn_x_preferred":[
        "\u0622\u0628\u0633\u0631\u062f"
    ],
    "name:tur_x_preferred":[
        "Abserd"
    ],
    "wof:name":"Ab Sard",
    "wof:placetype":"locality"
},
  "geometry": {"coordinates":[52.15323,35.62293],"type":"Point"}
}