{
  "type": "Feature",
  "properties": {
    "gn:admin1_code":"23",
    "gn:asciiname":"Gur Mohammad Tizab",
    "gn:country_code":"IR",
    "gn:dem":1794,
    "gn:feature_class":"P",
    "gn:feature_code":"PPL",
    "gn:name":"G\u016br Mo\u1e29ammad T\u012bz\u0101b",
    "gn:population":0,
    "gn:timezone":"Asia/Tehran",
    "iso:country":"IR",
    "name:ara_x_preferred":[
        "\u063a\u0648\u0631\u0645\u062d\u0645\u062f"
    ],
    "name:ceb_x_preferred":[
        "G\u016br Mo\u1e29ammad T\u012bz\u0101b"
    ],
    "name:fas_x_preferred":[
        "\u06af\u0648\u0631 \u0645\u062d\u0645\u0651\u062f"
    ],
    "name:fas_x_variant":[
        "G\u016br Mo\u1e29ammad",
        "\u06af\u0648\u0631 \u0645\u062d\u0645\u062f \u062a\u06cc\u0632\u0627\u0628",
        "\u06af\u0648\u0631\u0645\u062d\u0645\u062f"
    ],
    "name:swe_x_preferred":[
        "G\u016br Mo\u1e29ammad T\u012bz\u0101b"
    ],
    "name:und_x_variant":[
        "G\u016br Mo\u1e29ammad T\u012bz\u0101b"
    ],
    "wof:name":"Gur Mohammad Tizab",
    "wof:placetype":"locality"
},
  "geometry": {"coordinates":[47.8157,33.94564],"type":"Point"}
}