{
  "type": "Feature",
  "properties": {
    "gn:admin1_code":"16.0",
    "gn:asciiname":"Gonab",
    "gn:country_code":"IR",
    "gn:dem":1813,
    "gn:feature_class":"P",
    "gn:feature_code":"PPL",
    "gn:name":"Gon\u0101b",
    "gn:population":0,
    "gn:timezone":"Asia/Tehran",
    "iso:country":"IR",
    "name:fas_x_preferred":[
        "\u06af\u0646\u0627\u0628"
    ],
    "name:fas_x_variant":[
        "Gon\u0101b"
    ],
    "wof:name":"Gonab",
    "wof:placetype":"locality"
},
  "geometry": {"coordinates":[46.218,35.28],"type":"Point"}
}