{
  "type": "Feature",
  "properties": {
    "gn:admin1_code":"29",
    "gn:asciiname":"Chah-e Dar Khoda",
    "gn:country_code":"IR",
    "gn:dem":492,
    "gn:feature_class":"P",
    "gn:feature_code":"PPLL",
    "gn:name":"Ch\u0101h-e D\u0101r Khod\u0101",
    "gn:population":0,
    "gn:timezone":"Asia/Tehran",
    "iso:country":"IR",
    "name:fas_x_preferred":[
        "\u0686\u0627\u0647 \u062f\u0627\u0631 \u062e\u062f\u0627"
    ],
    "name:fas_x_variant":[
        "Ch\u0101h-e D\u0101r Khod\u0101"
    ],
    "wof:name":"Chah-e Dar Khoda",
    "wof:placetype":"locality"
},
  "geometry": {"coordinates":[58.56451,27.92219],"type":"Point"}
}