{
  "type": "Feature",
  "properties": {
    "gn:admin1_code":"8.0",
    "gn:asciiname":"Hashkova",
    "gn:country_code":"IR",
    "gn:dem":8,
    "gn:feature_class":"P",
    "gn:feature_code":"PPL",
    "gn:name":"\u1e28ashkov\u0101",
    "gn:population":0,
    "gn:timezone":"Asia/Tehran",
    "iso:country":"IR",
    "name:fas_x_preferred":[
        "\u062e\u0634\u06af\u0648\u0627"
    ],
    "name:fas_x_variant":[
        "\u062d\u0634\u06a9\u0648\u0627"
    ],
    "name:msa_x_preferred":[
        "Hashkova"
    ],
    "name:ukr_x_preferred":[
        "\u0425\u0430\u0448\u043a\u043e\u0432\u0430"
    ],
    "name:und_x_variant":[
        "Khoshgov\u0101",
        "\u1e28ashkov\u0101"
    ],
    "wof:name":"Hashkova",
    "wof:placetype":"locality"
},
  "geometry": {"coordinates":[49.75813,37.25426],"type":"Point"}
}