{
  "type": "Feature",
  "properties": {
    "gn:admin1_code":"15",
    "gn:asciiname":"Ja`far Qoli",
    "gn:country_code":"IR",
    "gn:dem":1027,
    "gn:feature_class":"P",
    "gn:feature_code":"PPL",
    "gn:name":"Ja\u2018far Qol\u012b",
    "gn:population":0,
    "gn:timezone":"Asia/Tehran",
    "iso:country":"IR",
    "name:fas_x_preferred":[
        "Ja\u2018far Qol\u012b"
    ],
    "wof:name":"Ja`far Qoli",
    "wof:placetype":"locality"
},
  "geometry": {"coordinates":[49.6975,32.04722],"type":"Point"}
}