{
  "type": "Feature",
  "properties": {
    "gn:admin1_code":"28",
    "gn:asciiname":"Yahyaabad",
    "gn:country_code":"IR",
    "gn:dem":2057,
    "gn:feature_class":"P",
    "gn:feature_code":"PPL",
    "gn:name":"Ya\u1e29y\u00e1\u0101b\u0101d",
    "gn:population":0,
    "gn:timezone":"Asia/Tehran",
    "iso:country":"IR",
    "name:fas_x_preferred":[
        "Ya\u1e29y\u00e1\u0101b\u0101d"
    ],
    "name:fas_x_variant":[
        "\u06cc\u062d\u06cc\u06cc \u0622\u0628\u0627\u062f"
    ],
    "name:und_x_variant":[
        "\u06cc\u062d\u06cc\u06cc \u0622\u0628\u0627\u062f"
    ],
    "wof:name":"Yahyaabad",
    "wof:placetype":"locality"
},
  "geometry": {"coordinates":[51.77386,33.34096],"type":"Point"}
}