{
  "type": "Feature",
  "properties": {
    "gn:admin1_code":"15.0",
    "gn:asciiname":"Farsiyeh-ye Do",
    "gn:country_code":"IR",
    "gn:dem":32,
    "gn:feature_class":"P",
    "gn:feature_code":"PPL",
    "gn:name":"F\u0101rs\u012byeh-ye Do",
    "gn:population":0,
    "gn:timezone":"Asia/Tehran",
    "iso:country":"IR",
    "name:ceb_x_preferred":[
        "F\u0101rs\u012byeh-ye Do"
    ],
    "name:fas_x_preferred":[
        "\u0641\u0627\u0631\u0633\u06cc\u0647 \u062f\u0648"
    ],
    "name:fas_x_variant":[
        "F\u0101rs\u012byeh-ye Do"
    ],
    "name:swe_x_preferred":[
        "F\u0101rs\u012byeh-ye Do"
    ],
    "wof:name":"Farsiyeh-ye Do",
    "wof:placetype":"locality"
},
  "geometry": {"coordinates":[48.6956,31.7493],"type":"Point"}
}