{
  "type": "Feature",
  "properties": {
    "gn:admin1_code":"15",
    "gn:asciiname":"Shamariyeh",
    "gn:country_code":"IR",
    "gn:dem":12,
    "gn:feature_class":"P",
    "gn:feature_code":"PPL",
    "gn:name":"Shamar\u012byeh",
    "gn:population":0,
    "gn:timezone":"Asia/Tehran",
    "iso:country":"IR",
    "name:ara_x_preferred":[
        "\u0634\u0645\u0631\u064a\u0629"
    ],
    "name:azb_x_preferred":[
        "\u0634\u0645\u0631\u06cc\u0647(\u0627\u0647\u0648\u0627\u0632)"
    ],
    "name:ceb_x_preferred":[
        "Shamar\u012byeh"
    ],
    "name:fas_x_preferred":[
        "\u0634\u0645\u0631\u06cc\u0647"
    ],
    "name:fas_x_variant":[
        "Shomeyr\u012byeh",
        "Shamar\u012byeh"
    ],
    "name:swe_x_preferred":[
        "Shamar\u012byeh"
    ],
    "name:und_x_variant":[
        "Shemiriyeh",
        "Tall Asvad-e Yek"
    ],
    "wof:name":"Shamariyeh",
    "wof:placetype":"locality"
},
  "geometry": {"coordinates":[48.36373,31.09914],"type":"Point"}
}