{
  "type": "Feature",
  "properties": {
    "gn:admin1_code":"15",
    "gn:asciiname":"Boneh-ye Yabareh",
    "gn:country_code":"IR",
    "gn:dem":36,
    "gn:feature_class":"P",
    "gn:feature_code":"PPL",
    "gn:name":"Boneh-ye Yab\u0101reh",
    "gn:population":0,
    "gn:timezone":"Asia/Tehran",
    "iso:country":"IR",
    "name:fas_x_preferred":[
        "\u0628\u0646\u0647 \u06cc\u0628\u0627\u0631\u0647"
    ],
    "name:fas_x_variant":[
        "Boneh-ye Yab\u0101reh"
    ],
    "name:und_x_variant":[
        "Yebareh",
        "Boneh-ye Y\u016bb\u0101r\u0101",
        "Yob\u0101reh",
        "\u06cc\u0628\u0627\u0631\u0647"
    ],
    "wof:name":"Boneh-ye Yabareh",
    "wof:placetype":"locality"
},
  "geometry": {"coordinates":[48.97654,31.89953],"type":"Point"}
}