{
  "type": "Feature",
  "properties": {
    "gn:admin1_code":"32",
    "gn:asciiname":"Mehmandust-e Pa'in",
    "gn:country_code":"IR",
    "gn:dem":1438,
    "gn:feature_class":"P",
    "gn:feature_code":"PPL",
    "gn:name":"Mehm\u0101nd\u016bst-e P\u0101\u2019\u012bn",
    "gn:population":0,
    "gn:timezone":"Asia/Tehran",
    "iso:country":"IR",
    "name:fas_x_preferred":[
        "\u0645\u0647\u0645\u0627\u0646\u062f\u0648\u0633\u062a \u067e\u0627\u0626\u064a\u0646"
    ],
    "name:fas_x_variant":[
        "\u0645\u064a\u0647\u0645\u0627\u0646\u062f\u0648\u0633\u062a\u0650 \u067e\u0627\u0626\u064a\u0646",
        "Mehm\u0101nd\u016bst",
        "Mehm\u0101nd\u016bst-e P\u0101\u2019\u012bn"
    ],
    "name:und_x_variant":[
        "M\u012bhm\u0101nd\u016bst-e P\u0101\u2019\u012bn"
    ],
    "wof:name":"Mehmandust-e Pa'in",
    "wof:placetype":"locality"
},
  "geometry": {"coordinates":[48.3229,38.0551],"type":"Point"}
}