{
  "type": "Feature",
  "properties": {
    "gn:admin1_code":"32",
    "gn:asciiname":"Kanzaq",
    "gn:country_code":"IR",
    "gn:dem":1560,
    "gn:feature_class":"P",
    "gn:feature_code":"PPL",
    "gn:name":"Kanzaq",
    "gn:population":0,
    "gn:timezone":"Asia/Tehran",
    "iso:country":"IR",
    "name:ceb_x_preferred":[
        "Kanzaq"
    ],
    "name:fas_x_preferred":[
        "\u0643\u0646\u0632\u0642"
    ],
    "name:fas_x_variant":[
        "\u0643\u064e\u062a\u064a\u0631\u064e\u0642",
        "\u06af\u064e\u0646\u0632\u064e\u0642",
        "\u0643\u064e\u0646\u0632\u064e\u06af",
        "\u06af\u0650\u0646\u0632\u0650\u0643",
        "\u06af\u064e\u0646\u0632\u0650\u063a",
        "\u06a9\u0646\u0632\u0642"
    ],
    "name:msa_x_preferred":[
        "Kanzaq"
    ],
    "name:mzn_x_preferred":[
        "\u06a9\u0646\u0632\u0642"
    ],
    "name:und_x_variant":[
        "Ganzaq",
        "Kanzag",
        "Ganzegh",
        "Kat\u012braq",
        "Genzek",
        "Kanzaq"
    ],
    "wof:name":"Kanzaq",
    "wof:placetype":"locality"
},
  "geometry": {"coordinates":[48.1119,38.1473],"type":"Point"}
}