{
  "type": "Feature",
  "properties": {
    "gn:admin1_code":"32.0",
    "gn:asciiname":"Urta Chay",
    "gn:country_code":"IR",
    "gn:dem":2923,
    "gn:feature_class":"P",
    "gn:feature_code":"PPLL",
    "gn:name":"\u016art\u0101 Ch\u0101y",
    "gn:population":0,
    "gn:timezone":"Asia/Tehran",
    "iso:country":"IR",
    "name:fas_x_preferred":[
        "\u0627\u0648\u0631\u062a\u0627 \u0686\u0627\u06cc"
    ],
    "name:und_x_variant":[
        "\u016art\u0101 Ch\u0101y"
    ],
    "wof:name":"Urta Chay",
    "wof:placetype":"locality"
},
  "geometry": {"coordinates":[48.61224,37.96825],"type":"Point"}
}