{
  "type": "Feature",
  "properties": {
    "gn:admin1_code":"13",
    "gn:asciiname":"Qilan",
    "gn:country_code":"IR",
    "gn:dem":824,
    "gn:feature_class":"P",
    "gn:feature_code":"PPL",
    "gn:name":"Q\u012bl\u0101n",
    "gn:population":0,
    "gn:timezone":"Asia/Tehran",
    "iso:country":"IR",
    "name:ara_x_preferred":[
        "\u0642\u064a\u0644\u0627\u0646"
    ],
    "name:ceb_x_preferred":[
        "Q\u012bl\u0101n"
    ],
    "name:fas_x_preferred":[
        "\u0642\u06cc\u0644\u0627\u0646"
    ],
    "name:fas_x_variant":[
        "Q\u012bl\u0101n"
    ],
    "name:swe_x_preferred":[
        "Q\u012bl\u0101n"
    ],
    "wof:name":"Qilan",
    "wof:placetype":"locality"
},
  "geometry": {"coordinates":[45.9506,34.0313],"type":"Point"}
}