{
  "type": "Feature",
  "properties": {
    "gn:admin1_code":"36",
    "gn:asciiname":"Pari",
    "gn:country_code":"IR",
    "gn:dem":1708,
    "gn:feature_class":"P",
    "gn:feature_code":"PPL",
    "gn:name":"Par\u012b",
    "gn:population":0,
    "gn:timezone":"Asia/Tehran",
    "iso:country":"IR",
    "name:azb_x_preferred":[
        "\u067e\u0631\u06cc"
    ],
    "name:fas_x_preferred":[
        "\u067e\u0631\u06cc"
    ],
    "name:fas_x_variant":[
        "Par\u012b"
    ],
    "wof:name":"Pari",
    "wof:placetype":"locality"
},
  "geometry": {"coordinates":[47.4186,36.87771],"type":"Point"}
}