{
  "type": "Feature",
  "properties": {
    "gn:admin1_code":"15",
    "gn:asciiname":"Charat",
    "gn:country_code":"IR",
    "gn:dem":48,
    "gn:feature_class":"P",
    "gn:feature_code":"PPL",
    "gn:name":"Ch\u0101r\u0101t",
    "gn:population":0,
    "gn:timezone":"Asia/Tehran",
    "iso:country":"IR",
    "name:ceb_x_preferred":[
        "Ch\u0101r\u0101t-e \u2018Oly\u0101"
    ],
    "name:fas_x_preferred":[
        "\u0686\u0627\u0631\u0627\u062a \u0639\u0644\u06cc\u0627"
    ],
    "name:fas_x_variant":[
        "Ch\u0101r\u0101t",
        "Ch\u0101r\u0101t-e \u2018Oly\u0101",
        "\u0686\u0627\u0631\u0627\u062a"
    ],
    "name:swe_x_preferred":[
        "Ch\u0101r\u0101t-e \u2018Oly\u0101"
    ],
    "wof:name":"Charat",
    "wof:placetype":"locality"
},
  "geometry": {"coordinates":[49.3827,31.04608],"type":"Point"}
}