{
  "type": "Feature",
  "properties": {
    "gn:admin1_code":"4.0",
    "gn:asciiname":"Darsan",
    "gn:country_code":"IR",
    "gn:dem":1181,
    "gn:feature_class":"P",
    "gn:feature_code":"PPL",
    "gn:name":"D\u0101rs\u0101n",
    "gn:population":0,
    "gn:timezone":"Asia/Tehran",
    "iso:country":"IR",
    "name:fas_x_preferred":[
        "\u062f\u0627\u0631\u0633\u0627\u0646"
    ],
    "name:fas_x_variant":[
        "D\u0101rs\u0101n"
    ],
    "wof:name":"Darsan",
    "wof:placetype":"locality"
},
  "geometry": {"coordinates":[61.02602,27.55696],"type":"Point"}
}