{
  "type": "Feature",
  "properties": {
    "gn:admin1_code":"23",
    "gn:asciiname":"Tumaleh-ye Sofla",
    "gn:country_code":"IR",
    "gn:dem":1750,
    "gn:feature_class":"P",
    "gn:feature_code":"PPL",
    "gn:name":"T\u016bm\u0101leh-ye Sofl\u00e1",
    "gn:population":0,
    "gn:timezone":"Asia/Tehran",
    "iso:country":"IR",
    "name:fas_x_preferred":[
        "T\u016bm\u0101leh-ye Sofl\u00e1"
    ],
    "wof:name":"Tumaleh-ye Sofla",
    "wof:placetype":"locality"
},
  "geometry": {"coordinates":[48.75,33.53333],"type":"Point"}
}