{
  "type": "Feature",
  "properties": {
    "gn:admin1_code":"34",
    "gn:asciiname":"Deh-e Asghar",
    "gn:country_code":"IR",
    "gn:dem":2105,
    "gn:feature_class":"P",
    "gn:feature_code":"PPL",
    "gn:name":"Deh-e A\u015fghar",
    "gn:population":0,
    "gn:timezone":"Asia/Tehran",
    "iso:country":"IR",
    "name:fas_x_preferred":[
        "\u062f\u0647 \u0639\u0633\u06af\u0631"
    ],
    "name:fas_x_variant":[
        "Deh-e A\u015fghar",
        "Deh-e \u2018Asgar",
        "\u062f\u0647 \u0627\u0635\u063a\u0631"
    ],
    "name:und_x_variant":[
        "Deh \u2018Askar",
        "Deh \u2018Askur",
        "Deh-e \u2018Askar",
        "Deh \u2018Asgar"
    ],
    "wof:name":"Deh-e Asghar",
    "wof:placetype":"locality"
},
  "geometry": {"coordinates":[49.15653,33.81491],"type":"Point"}
}