{
  "type": "Feature",
  "properties": {
    "gn:admin1_code":"37.0",
    "gn:asciiname":"Shurjah-e Pa'in",
    "gn:country_code":"IR",
    "gn:dem":157,
    "gn:feature_class":"P",
    "gn:feature_code":"PPL",
    "gn:name":"Sh\u016brjah-e P\u0101\u2019\u012bn",
    "gn:population":0,
    "gn:timezone":"Asia/Tehran",
    "iso:country":"IR",
    "name:fas_x_preferred":[
        "\u0634\u0648\u0631\u062c\u0647 \u067e\u0627\u0626\u06cc\u0646"
    ],
    "name:fas_x_variant":[
        "Sh\u016brjah",
        "Sh\u016brjah-e P\u0101\u2019\u012bn"
    ],
    "wof:name":"Shurjah-e Pa'in",
    "wof:placetype":"locality"
},
  "geometry": {"coordinates":[55.82657,37.88126],"type":"Point"}
}