{
  "type": "Feature",
  "properties": {
    "gn:admin1_code":"8.0",
    "gn:asciiname":"Mahalleh Alan",
    "gn:country_code":"IR",
    "gn:dem":55,
    "gn:feature_class":"P",
    "gn:feature_code":"PPL",
    "gn:name":"Ma\u1e29alleh Al\u0101n",
    "gn:population":0,
    "gn:timezone":"Asia/Tehran",
    "iso:country":"IR",
    "name:fas_x_preferred":[
        "\u0627\u0644\u0627\u0646"
    ],
    "name:fas_x_variant":[
        "Al\u0101n",
        "\u0645\u062d\u0644\u0647 \u0627\u0644\u0627\u0646"
    ],
    "name:und_x_variant":[
        "Ma\u1e29alleh Al\u0101n"
    ],
    "wof:name":"Mahalleh Alan",
    "wof:placetype":"locality"
},
  "geometry": {"coordinates":[49.13643,37.5063],"type":"Point"}
}