{
  "type": "Feature",
  "properties": {
    "gn:admin1_code":"11.0",
    "gn:asciiname":"Mehragan-e Sofla",
    "gn:country_code":"IR",
    "gn:dem":27,
    "gn:feature_class":"P",
    "gn:feature_code":"PPL",
    "gn:name":"Mehrag\u0101n-e Sofl\u00e1",
    "gn:population":0,
    "gn:timezone":"Asia/Tehran",
    "iso:country":"IR",
    "name:fas_x_preferred":[
        "\u0645\u0647\u0631\u06a9\u0627\u0646 \u067e\u0627\u0626\u06cc\u0646"
    ],
    "name:fas_x_variant":[
        "\u0645\u0647\u0631\u06af\u0627\u0646 \u0633\u0641\u0644\u06cc",
        "\u0645\u0647\u0631\u06af\u0627\u0646 \u067e\u0627\u06cc\u06cc\u0646"
    ],
    "name:und_x_variant":[
        "Mehrak\u0101n-e P\u0101\u2019\u012bn",
        "Mehrag\u0101n-e Sofl\u00e1",
        "Mehrag\u0101n-e P\u0101\u2019\u012bn"
    ],
    "wof:name":"Mehragan-e Sofla",
    "wof:placetype":"locality"
},
  "geometry": {"coordinates":[54.84511,26.75309],"type":"Point"}
}