{
  "type": "Feature",
  "properties": {
    "gn:admin1_code":"8.0",
    "gn:asciiname":"Bataksar",
    "gn:country_code":"IR",
    "gn:dem":97,
    "gn:feature_class":"P",
    "gn:feature_code":"PPL",
    "gn:name":"Bataksar",
    "gn:population":0,
    "gn:timezone":"Asia/Tehran",
    "iso:country":"IR",
    "name:fas_x_preferred":[
        "\u0628\u062a\u06a9\u0633\u0631"
    ],
    "wof:name":"Bataksar",
    "wof:placetype":"locality"
},
  "geometry": {"coordinates":[50.2969,37.00618],"type":"Point"}
}