{
  "type": "Feature",
  "properties": {
    "gn:admin1_code":"35.0",
    "gn:asciiname":"Jalikan-e Sofla",
    "gn:country_code":"IR",
    "gn:dem":27,
    "gn:feature_class":"P",
    "gn:feature_code":"PPL",
    "gn:name":"Jal\u012bk\u0101n-e Sofl\u00e1",
    "gn:population":0,
    "gn:timezone":"Asia/Tehran",
    "iso:country":"IR",
    "name:fas_x_preferred":[
        "\u062c\u0644\u064a\u0643\u0627\u0646 \u067e\u0627\u0626\u064a\u0646"
    ],
    "name:fas_x_variant":[
        "Jal\u012bk\u0101n-e P\u0101\u2019\u012bn",
        "\u062c\u0644\u06cc\u06a9\u0627\u0646 \u0633\u0641\u0644\u06cc"
    ],
    "name:und_x_variant":[
        "Jal\u012bk\u0101n-e Sofl\u00e1"
    ],
    "wof:name":"Jalikan-e Sofla",
    "wof:placetype":"locality"
},
  "geometry": {"coordinates":[52.19018,36.49351],"type":"Point"}
}