{
  "type": "Feature",
  "properties": {
    "gn:admin1_code":"42.0",
    "gn:asciiname":"Sangan",
    "gn:country_code":"IR",
    "gn:dem":867,
    "gn:feature_class":"P",
    "gn:feature_code":"PPL",
    "gn:name":"Sang\u0101n",
    "gn:population":0,
    "gn:timezone":"Asia/Tehran",
    "iso:country":"IR",
    "name:ara_x_preferred":[
        "\u0633\u0646\u063a\u0627\u0646"
    ],
    "name:aze_x_preferred":[
        "S\u0259ngan"
    ],
    "name:ceb_x_preferred":[
        "Sang\u0101n"
    ],
    "name:fas_x_preferred":[
        "Sang\u016bn-e P\u0101\u2019\u012bn"
    ],
    "name:fas_x_variant":[
        "Sang\u0101n P\u0101\u2019\u012bn",
        "\u0633\u0646\u06af\u0627\u0646",
        "Sang\u0101n-e P\u0101\u2019\u012bn",
        "Sang\u0101n",
        "Sang\u016bn-i-P\u0101\u012bn"
    ],
    "name:ita_x_preferred":[
        "Sangan"
    ],
    "name:mlg_x_preferred":[
        "Sangan"
    ],
    "name:swe_x_preferred":[
        "Sang\u0101n"
    ],
    "name:tur_x_preferred":[
        "Sengan"
    ],
    "name:und_x_variant":[
        "Sang\u016bn-i-P\u0101\u012bn"
    ],
    "wof:name":"Sangan",
    "wof:placetype":"locality"
},
  "geometry": {"coordinates":[60.25798,34.39850999999999],"type":"Point"}
}