{
  "type": "Feature",
  "properties": {
    "gn:admin1_code":"13",
    "gn:asciiname":"Bandarabad",
    "gn:country_code":"IR",
    "gn:dem":1353,
    "gn:feature_class":"P",
    "gn:feature_code":"PPL",
    "gn:name":"Bandar\u0101b\u0101d",
    "gn:population":0,
    "gn:timezone":"Asia/Tehran",
    "iso:country":"IR",
    "name:fas_x_preferred":[
        "\u0628\u0646\u062f\u0631 \u0622\u0628\u0627\u062f"
    ],
    "name:fas_x_variant":[
        "Bandar\u0101b\u0101d",
        "\u0628\u0646\u062f\u0631\u0622\u0628\u0627\u062f"
    ],
    "wof:name":"Bandarabad",
    "wof:placetype":"locality"
},
  "geometry": {"coordinates":[46.7517,34.3069],"type":"Point"}
}