{
  "type": "Feature",
  "properties": {
    "gn:admin1_code":"7",
    "gn:asciiname":"Mazra`eh-ye Palangun",
    "gn:country_code":"IR",
    "gn:dem":1849,
    "gn:feature_class":"P",
    "gn:feature_code":"PPLF",
    "gn:name":"Mazra\u2018eh-ye Palang\u016bn",
    "gn:population":0,
    "gn:timezone":"Asia/Tehran",
    "iso:country":"IR",
    "name:fas_x_preferred":[
        "\u067e\u0644\u0646\u06af\u0627\u0646"
    ],
    "name:fas_x_variant":[
        "Palang\u0101n",
        "\u0645\u0632\u0631\u0639\u0647 \u067e\u0644\u0646\u06af\u0648\u0646"
    ],
    "name:und_x_variant":[
        "Mazra\u2018eh-ye Palang\u016bn"
    ],
    "wof:name":"Mazra`eh-ye Palangun",
    "wof:placetype":"locality"
},
  "geometry": {"coordinates":[54.35741,29.11126],"type":"Point"}
}