{
  "type": "Feature",
  "properties": {
    "gn:admin1_code":"15",
    "gn:asciiname":"Kalleh Pir",
    "gn:country_code":"IR",
    "gn:dem":739,
    "gn:feature_class":"P",
    "gn:feature_code":"PPL",
    "gn:name":"Kalleh P\u012br",
    "gn:population":0,
    "gn:timezone":"Asia/Tehran",
    "iso:country":"IR",
    "name:fas_x_preferred":[
        "Kaleh-ye P\u012br"
    ],
    "name:fas_x_variant":[
        "Kalleh P\u012br",
        "\u06a9\u0644\u0647 \u067e\u06cc\u0631"
    ],
    "name:und_x_variant":[
        "Qal\u2018eh Pir",
        "Gal-e P\u012br"
    ],
    "wof:name":"Kalleh Pir",
    "wof:placetype":"locality"
},
  "geometry": {"coordinates":[50.00089000000001,31.42369],"type":"Point"}
}