{
  "type": "Feature",
  "properties": {
    "gn:admin1_code":"29",
    "gn:asciiname":"Seyyed Ne`matollah",
    "gn:country_code":"IR",
    "gn:dem":2368,
    "gn:feature_class":"P",
    "gn:feature_code":"PPL",
    "gn:name":"Seyyed Ne\u2018matoll\u0101h",
    "gn:population":0,
    "gn:timezone":"Asia/Tehran",
    "iso:country":"IR",
    "name:fas_x_preferred":[
        "Seyyed Ne\u2018matoll\u0101h"
    ],
    "name:und_x_variant":[
        "Seyyed Ne\u2018mattoll\u0101h"
    ],
    "wof:name":"Seyyed Ne`matollah",
    "wof:placetype":"locality"
},
  "geometry": {"coordinates":[56.715,30.33528],"type":"Point"}
}