{
  "type": "Feature",
  "properties": {
    "gn:admin1_code":"40",
    "gn:asciiname":"Hushangabad",
    "gn:country_code":"IR",
    "gn:dem":1861,
    "gn:feature_class":"P",
    "gn:feature_code":"PPLF",
    "gn:name":"H\u016bshang\u0101b\u0101d",
    "gn:population":0,
    "gn:timezone":"Asia/Tehran",
    "iso:country":"IR",
    "name:fas_x_preferred":[
        "\u0647\u0648\u0634\u064e\u0646\u06af \u0622\u0628\u0627\u062f"
    ],
    "name:fas_x_variant":[
        "H\u016bshang\u0101b\u0101d",
        "\u0647\u0648\u0634\u0646\u06af \u0622\u0628\u0627\u062f"
    ],
    "wof:name":"Hushangabad",
    "wof:placetype":"locality"
},
  "geometry": {"coordinates":[53.9752,31.23651],"type":"Point"}
}