{
  "type": "Feature",
  "properties": {
    "gn:admin1_code":"41",
    "gn:asciiname":"Golian",
    "gn:country_code":"IR",
    "gn:dem":1813,
    "gn:feature_class":"P",
    "gn:feature_code":"PPL",
    "gn:name":"Gol\u012b\u0101n",
    "gn:population":0,
    "gn:timezone":"Asia/Tehran",
    "iso:country":"IR",
    "name:deu_x_preferred":[
        "Golian"
    ],
    "name:fas_x_preferred":[
        "Gol\u012b\u0101n"
    ],
    "name:fas_x_variant":[
        "\u06a9\u0644\u0627\u062a \u06af\u0644\u064a\u0627\u0646",
        "\u06af\u0644\u064a\u0627\u0646"
    ],
    "name:und_x_variant":[
        "Guli\u0101n"
    ],
    "wof:name":"Golian",
    "wof:placetype":"locality"
},
  "geometry": {"coordinates":[59.09316,32.79556],"type":"Point"}
}