{
  "type": "Feature",
  "properties": {
    "gn:admin1_code":"40",
    "gn:asciiname":"Dashtok-e Pa'in",
    "gn:country_code":"IR",
    "gn:dem":2297,
    "gn:feature_class":"P",
    "gn:feature_code":"PPL",
    "gn:name":"Dashtok-e P\u0101\u2019\u012bn",
    "gn:population":0,
    "gn:timezone":"Asia/Tehran",
    "iso:country":"IR",
    "name:fas_x_preferred":[
        "\u062f\u0634\u062a\u06a9 \u067e\u0627\u0626\u064a\u0646"
    ],
    "name:fas_x_variant":[
        "\u062f\u064e\u0634\u062a\u064e\u0643 \u0633\u064f\u0641\u0644\u064e",
        "Dashtok-e P\u0101\u2019\u012bn",
        "\u062f\u0634\u062a\u06a9 \u0633\u0641\u0644\u06cc"
    ],
    "name:und_x_variant":[
        "Dashtak Sofla",
        "Dashtok-e Sofl\u00e1"
    ],
    "wof:name":"Dashtok-e Pa'in",
    "wof:placetype":"locality"
},
  "geometry": {"coordinates":[54.01971999999999,31.65916],"type":"Point"}
}