{
  "type": "Feature",
  "properties": {
    "gn:admin1_code":"13",
    "gn:asciiname":"Zandhar",
    "gn:country_code":"IR",
    "gn:dem":1396,
    "gn:feature_class":"P",
    "gn:feature_code":"PPL",
    "gn:name":"Zandhar",
    "gn:population":0,
    "gn:timezone":"Asia/Tehran",
    "iso:country":"IR",
    "name:fas_x_preferred":[
        "\u0632\u0646\u062f\u0647\u0631"
    ],
    "wof:name":"Zandhar",
    "wof:placetype":"locality"
},
  "geometry": {"coordinates":[46.6603,34.3395],"type":"Point"}
}