{
  "type": "Feature",
  "properties": {
    "gn:admin1_code":"35.0",
    "gn:asciiname":"Lash Kenar",
    "gn:country_code":"IR",
    "gn:dem":1571,
    "gn:feature_class":"P",
    "gn:feature_code":"PPL",
    "gn:name":"Lash Ken\u0101r",
    "gn:population":0,
    "gn:timezone":"Asia/Tehran",
    "iso:country":"IR",
    "name:fas_x_preferred":[
        "Lashken\u0101r"
    ],
    "name:fas_x_variant":[
        "\u0644\u0634\u0643\u0646\u0627\u0631",
        "\u0644\u0634 \u06a9\u0646\u0627\u0631"
    ],
    "name:und_x_variant":[
        "Lash Ken\u0101r"
    ],
    "wof:name":"Lash Kenar",
    "wof:placetype":"locality"
},
  "geometry": {"coordinates":[51.47221,36.47486],"type":"Point"}
}