{
  "type": "Feature",
  "properties": {
    "gn:admin1_code":"35.0",
    "gn:asciiname":"Tajarak",
    "gn:country_code":"IR",
    "gn:dem":2959,
    "gn:feature_class":"P",
    "gn:feature_code":"PPL",
    "gn:name":"Tajarak",
    "gn:population":0,
    "gn:timezone":"Asia/Tehran",
    "iso:country":"IR",
    "name:fas_x_preferred":[
        "\u062a\u062c\u0631\u06a9"
    ],
    "name:fas_x_variant":[
        "\u062a\u062c\u064a\u0631\u06a9"
    ],
    "name:und_x_variant":[
        "Taj\u012brak"
    ],
    "wof:name":"Tajarak",
    "wof:placetype":"locality"
},
  "geometry": {"coordinates":[52.40766,35.86591],"type":"Point"}
}