{
  "type": "Feature",
  "properties": {
    "gn:admin1_code":"7",
    "gn:asciiname":"Mal Henkun",
    "gn:country_code":"IR",
    "gn:dem":1626,
    "gn:feature_class":"P",
    "gn:feature_code":"PPL",
    "gn:name":"M\u0101l Henk\u016bn",
    "gn:population":0,
    "gn:timezone":"Asia/Tehran",
    "iso:country":"IR",
    "name:fas_x_preferred":[
        "M\u0101l Henk\u016bn"
    ],
    "wof:name":"Mal Henkun",
    "wof:placetype":"locality"
},
  "geometry": {"coordinates":[51.80833,30.045],"type":"Point"}
}