{
  "type": "Feature",
  "properties": {
    "gn:admin1_code":"1",
    "gn:asciiname":"Aversi",
    "gn:country_code":"IR",
    "gn:dem":1708,
    "gn:feature_class":"P",
    "gn:feature_code":"PPL",
    "gn:name":"Avers\u012b",
    "gn:population":0,
    "gn:timezone":"Asia/Tehran",
    "iso:country":"IR",
    "name:fas_x_preferred":[
        "\u0622\u0648\u0650\u0631\u0633\u06cc"
    ],
    "name:fas_x_variant":[
        "Avers\u012b",
        "\u0627\u0648\u0631\u0633\u06cc",
        "\u0100vers\u012b"
    ],
    "wof:name":"Aversi",
    "wof:placetype":"locality"
},
  "geometry": {"coordinates":[44.8632,37.3193],"type":"Point"}
}