{
  "type": "Feature",
  "properties": {
    "gn:admin1_code":"42.0",
    "gn:asciiname":"Asafabad",
    "gn:country_code":"IR",
    "gn:dem":291,
    "gn:feature_class":"P",
    "gn:feature_code":"PPL",
    "gn:name":"Asafabad",
    "gn:population":0,
    "gn:timezone":"Asia/Tehran",
    "iso:country":"IR",
    "name:fas_x_preferred":[
        "\u0100\u015fef\u0101b\u0101d"
    ],
    "name:fas_x_variant":[
        "\u0622\u0635\u0641 \u0622\u0628\u0627\u062f",
        "\u0622\u0635\u0641\u200c\u0622\u0628\u0627\u062f"
    ],
    "name:und_x_variant":[
        "\u0100\u015faf\u0101b\u0101d",
        "\u0622\u0635\u0641 \u0622\u0628\u0627\u062f",
        "Asafabad"
    ],
    "wof:name":"Asafabad",
    "wof:placetype":"locality"
},
  "geometry": {"coordinates":[61.14901999999999,36.44069],"type":"Point"}
}