{
  "type": "Feature",
  "properties": {
    "gn:admin1_code":"29",
    "gn:asciiname":"Moosa Abad",
    "gn:country_code":"IR",
    "gn:dem":1497,
    "gn:feature_class":"P",
    "gn:feature_code":"PPLF",
    "gn:name":"Moosa Abad",
    "gn:population":0,
    "gn:timezone":"Asia/Tehran",
    "iso:country":"IR",
    "name:fas_x_preferred":[
        "Shar\u0101fat"
    ],
    "name:fas_x_variant":[
        "\u0645\u0648\u0633\u06cc \u0622\u0628\u0627\u062f",
        "\u0645\u0644\u06a9 \u0622\u0628\u0627\u062f"
    ],
    "name:und_x_variant":[
        "Tolombeh-ye Shar\u0101fat",
        "M\u016bs\u00e1\u0101b\u0101d",
        "Moosa Abad",
        "Malek\u0101b\u0101d"
    ],
    "wof:name":"Moosa Abad",
    "wof:placetype":"locality"
},
  "geometry": {"coordinates":[55.99665,30.47134],"type":"Point"}
}