{
  "type": "Feature",
  "properties": {
    "gn:admin1_code":"4.0",
    "gn:asciiname":"Mohammadabad-e Harati",
    "gn:country_code":"IR",
    "gn:dem":483,
    "gn:feature_class":"P",
    "gn:feature_code":"PPL",
    "gn:name":"Mo\u1e29ammad\u0101b\u0101d-e Har\u0101t\u012b",
    "gn:population":0,
    "gn:timezone":"Asia/Tehran",
    "iso:country":"IR",
    "name:fas_x_preferred":[
        "\u0645\u062d\u0645\u062f \u0622\u0628\u0627\u062f \u0647\u0631\u0627\u062a\u06cc"
    ],
    "name:fas_x_variant":[
        "Deh-e Har\u0101t\u012b",
        "\u0647\u0631\u0627\u062a\u06cc"
    ],
    "name:und_x_variant":[
        "Mo\u1e29ammad\u0101b\u0101d-e Har\u0101t\u012b",
        "Har\u0101t\u012b"
    ],
    "wof:name":"Mohammadabad-e Harati",
    "wof:placetype":"locality"
},
  "geometry": {"coordinates":[61.5078,30.9653],"type":"Point"}
}