{
  "type": "Feature",
  "properties": {
    "gn:admin1_code":"42",
    "gn:asciiname":"Khunshah",
    "gn:country_code":"IR",
    "gn:dem":1180,
    "gn:feature_class":"P",
    "gn:feature_code":"PPL",
    "gn:name":"Kh\u016bnsh\u0101h",
    "gn:population":0,
    "gn:timezone":"Asia/Tehran",
    "iso:country":"IR",
    "name:fas_x_preferred":[
        "\u062e\u0648\u0646\u0634\u0627"
    ],
    "name:fas_x_variant":[
        "Kh\u0101nsh\u0101h",
        "Kh\u016bnsh\u0101",
        "\u062e\u0648\u0646\u0634\u0627\u0647",
        "\u062e\u0627\u0646\u0634\u0627\u0647"
    ],
    "name:und_x_variant":[
        "Kh\u016bnsh\u0101h"
    ],
    "wof:name":"Khunshah",
    "wof:placetype":"locality"
},
  "geometry": {"coordinates":[58.89204,36.10485],"type":"Point"}
}