{
  "type": "Feature",
  "properties": {
    "gn:admin1_code":"35.0",
    "gn:asciiname":"Gowhar Kola",
    "gn:country_code":"IR",
    "gn:dem":1276,
    "gn:feature_class":"P",
    "gn:feature_code":"PPL",
    "gn:name":"Gowhar Kol\u0101",
    "gn:population":0,
    "gn:timezone":"Asia/Tehran",
    "iso:country":"IR",
    "name:ara_x_preferred":[
        "\u063a\u0648\u0647\u0631\u0643\u0644\u0627"
    ],
    "name:ceb_x_preferred":[
        "Gowhar Kol\u0101"
    ],
    "name:fas_x_preferred":[
        "\u06af\u064e\u0631 \u0643\u064f\u0644\u0627"
    ],
    "name:fas_x_variant":[
        "Gowhar Kol\u0101",
        "\u06af\u0648\u0647\u0631 \u0643\u0644\u0627",
        "\u06af\u0648\u0647\u0631\u06a9\u0644\u0627"
    ],
    "name:swe_x_preferred":[
        "Gowhar Kol\u0101"
    ],
    "name:und_x_variant":[
        "Gar Kol\u0101",
        "\u06af\u0648\u0647\u0631 \u0643\u0644\u0627"
    ],
    "wof:name":"Gowhar Kola",
    "wof:placetype":"locality"
},
  "geometry": {"coordinates":[51.24986,36.48224],"type":"Point"}
}