{
  "type": "Feature",
  "properties": {
    "gn:admin1_code":"8",
    "gn:asciiname":"Alamu",
    "gn:country_code":"IR",
    "gn:dem":598,
    "gn:feature_class":"P",
    "gn:feature_code":"PPL",
    "gn:name":"\u0100l\u0101m\u016b",
    "gn:population":0,
    "gn:timezone":"Asia/Tehran",
    "iso:country":"IR",
    "name:fas_x_preferred":[
        "\u0100l\u0101m\u016b"
    ],
    "name:fas_x_variant":[
        "\u0622\u0644\u0627\u0645\u0648"
    ],
    "wof:name":"Alamu",
    "wof:placetype":"locality"
},
  "geometry": {"coordinates":[49.80759000000001,36.92984000000001],"type":"Point"}
}