{
  "type": "Feature",
  "properties": {
    "gn:admin1_code":"41.0",
    "gn:asciiname":"Chah-e Kazeh",
    "gn:country_code":"IR",
    "gn:dem":1272,
    "gn:feature_class":"P",
    "gn:feature_code":"PPLL",
    "gn:name":"Ch\u0101h-e K\u0101zeh",
    "gn:population":0,
    "gn:timezone":"Asia/Tehran",
    "iso:country":"IR",
    "name:fas_x_preferred":[
        "\u0686\u0627\u0647 \u06a9\u0627\u0632\u0647"
    ],
    "name:fas_x_variant":[
        "\u0686\u0627\u0647\u200c\u06a9\u0627\u0632\u0647"
    ],
    "name:und_x_variant":[
        "Ch\u0101h-e K\u0101zeh"
    ],
    "wof:name":"Chah-e Kazeh",
    "wof:placetype":"locality"
},
  "geometry": {"coordinates":[58.28422,33.5312],"type":"Point"}
}