{
  "type": "Feature",
  "properties": {
    "gn:admin1_code":"9.0",
    "gn:asciiname":"Akhtehchi",
    "gn:country_code":"IR",
    "gn:dem":2067,
    "gn:feature_class":"P",
    "gn:feature_code":"PPL",
    "gn:name":"Akhtehch\u012b",
    "gn:population":0,
    "gn:timezone":"Asia/Tehran",
    "iso:country":"IR",
    "name:ara_x_preferred":[
        "\u0623\u062e\u062a\u0627\u062a\u0634\u064a"
    ],
    "name:azb_x_preferred":[
        "\u0622\u062e\u062a\u0627\u0686\u06cc\u060c\u0628\u0627\u0647\u0627\u0631"
    ],
    "name:fas_x_preferred":[
        "\u0627\u064e\u062e\u062a\u0627\u0686\u06cc"
    ],
    "name:fas_x_variant":[
        "\u0627\u064e\u062e\u062a\u0650\u0647\u0686\u06cc",
        "Akht\u0101ch\u012b",
        "\u0627\u062e\u062a\u0627\u0686\u06cc",
        "\u0627\u062e\u062a\u0647 \u0686\u06cc"
    ],
    "name:msa_x_preferred":[
        "Akhtachi"
    ],
    "name:und_x_variant":[
        "Akhtarchi",
        "Akhtehch\u012b",
        "Akhtaji"
    ],
    "wof:name":"Akhtehchi",
    "wof:placetype":"locality"
},
  "geometry": {"coordinates":[48.20956,34.90665],"type":"Point"}
}