{
  "type": "Feature",
  "properties": {
    "gn:admin1_code":"9",
    "gn:asciiname":"Moslemabad",
    "gn:country_code":"IR",
    "gn:dem":1755,
    "gn:feature_class":"P",
    "gn:feature_code":"PPL",
    "gn:name":"Moslem\u0101b\u0101d",
    "gn:population":0,
    "gn:timezone":"Asia/Tehran",
    "iso:country":"IR",
    "name:fas_x_preferred":[
        "Moslem\u0101b\u0101d"
    ],
    "name:fas_x_variant":[
        "\u0645\u0633\u0644\u0645 \u0622\u0628\u0627\u062f",
        "\u06af\u0627\u0648\u062e\u0627\u0646\u0647"
    ],
    "name:und_x_variant":[
        "G\u0101vkh\u0101neh",
        "Gau Kh\u0101neh",
        "G\u0101v Kh\u0101neh"
    ],
    "wof:name":"Moslemabad",
    "wof:placetype":"locality"
},
  "geometry": {"coordinates":[48.91196,34.67236],"type":"Point"}
}