{
  "type": "Feature",
  "properties": {
    "gn:admin1_code":"15",
    "gn:asciiname":"Qal`eh-ye Sahar",
    "gn:country_code":"IR",
    "gn:dem":34,
    "gn:feature_class":"P",
    "gn:feature_code":"PPL",
    "gn:name":"Qal\u2018eh-ye Sa\u1e29ar",
    "gn:population":0,
    "gn:timezone":"Asia/Tehran",
    "iso:country":"IR",
    "name:fas_x_preferred":[
        "\u0642\u0644\u0639\u0647 \u0633\u062d\u0631"
    ],
    "name:fas_x_variant":[
        "Qal\u2018eh-ye Sa\u1e29ar"
    ],
    "name:und_x_variant":[
        "Qal\u2018eh Sahar",
        "Qal\u2018eh-ye Sa\u1e29ar Alh\u0101\u2019\u012b"
    ],
    "wof:name":"Qal`eh-ye Sahar",
    "wof:placetype":"locality"
},
  "geometry": {"coordinates":[48.5682,31.67704],"type":"Point"}
}