{
  "type": "Feature",
  "properties": {
    "gn:admin1_code":"29",
    "gn:asciiname":"Chah Dasht",
    "gn:country_code":"IR",
    "gn:dem":394,
    "gn:feature_class":"P",
    "gn:feature_code":"PPL",
    "gn:name":"Ch\u0101h Dasht",
    "gn:population":0,
    "gn:timezone":"Asia/Tehran",
    "iso:country":"IR",
    "name:fas_x_preferred":[
        "\u0686\u0627\u0647 \u062f\u0634\u062a"
    ],
    "name:fas_x_variant":[
        "Ch\u0101h Dasht"
    ],
    "wof:name":"Chah Dasht",
    "wof:placetype":"locality"
},
  "geometry": {"coordinates":[58.4377,27.77495],"type":"Point"}
}