{
  "type": "Feature",
  "properties": {
    "gn:admin1_code":"29",
    "gn:asciiname":"Hoseynabad",
    "gn:country_code":"IR",
    "gn:dem":644,
    "gn:feature_class":"P",
    "gn:feature_code":"PPL",
    "gn:name":"\u1e28oseyn\u0101b\u0101d",
    "gn:population":0,
    "gn:timezone":"Asia/Tehran",
    "iso:country":"IR",
    "name:fas_x_preferred":[
        "\u062f\u0647\u0646\u0648"
    ],
    "name:fas_x_variant":[
        "\u062d\u0633\u06cc\u0646 \u0622\u0628\u0627\u062f"
    ],
    "name:und_x_variant":[
        "Dehnow",
        "\u1e28oseyn\u0101b\u0101d"
    ],
    "wof:name":"Hoseynabad",
    "wof:placetype":"locality"
},
  "geometry": {"coordinates":[58.9754,28.717],"type":"Point"}
}