{
  "type": "Feature",
  "properties": {
    "gn:admin1_code":"23.0",
    "gn:asciiname":"Borj Kabud",
    "gn:country_code":"IR",
    "gn:dem":464,
    "gn:feature_class":"P",
    "gn:feature_code":"PPL",
    "gn:name":"Borj Kab\u016bd",
    "gn:population":0,
    "gn:timezone":"Asia/Tehran",
    "iso:country":"IR",
    "name:fas_x_preferred":[
        "\u0628\u0631\u062c \u06a9\u0628\u0648\u062f"
    ],
    "name:und_x_variant":[
        "Borj Kab\u016bd"
    ],
    "wof:name":"Borj Kabud",
    "wof:placetype":"locality"
},
  "geometry": {"coordinates":[47.80474,33.00075],"type":"Point"}
}