{
  "type": "Feature",
  "properties": {
    "gn:admin1_code":"33",
    "gn:asciiname":"Nehriq",
    "gn:country_code":"IR",
    "gn:dem":1957,
    "gn:feature_class":"P",
    "gn:feature_code":"PPL",
    "gn:name":"Nehr\u012bq",
    "gn:population":0,
    "gn:timezone":"Asia/Tehran",
    "iso:country":"IR",
    "name:fas_x_preferred":[
        "\u0646\u0647\u0631\u06cc\u0642"
    ],
    "name:fas_x_variant":[
        "Nehr\u012bq",
        "\u0646\u0650\u0647\u0631\u064a\u0642",
        "\u0646\u0650\u0647\u0631\u0644\u064a\u0642",
        "\u0646\u064a\u0631\u064a\u062e"
    ],
    "name:und_x_variant":[
        "Nahrigh",
        "Nehrl\u012bq",
        "N\u012br\u012bkh",
        "Nyrykh",
        "\u0646\u064a\u0631\u064a\u062e"
    ],
    "wof:name":"Nehriq",
    "wof:placetype":"locality"
},
  "geometry": {"coordinates":[46.8043,38.6052],"type":"Point"}
}