{
  "type": "Feature",
  "properties": {
    "gn:admin1_code":"5.0",
    "gn:asciiname":"Baghcheh-ye Jalil",
    "gn:country_code":"IR",
    "gn:dem":2050,
    "gn:feature_class":"P",
    "gn:feature_code":"PPL",
    "gn:name":"B\u0101ghcheh-ye Jal\u012bl",
    "gn:population":0,
    "gn:timezone":"Asia/Tehran",
    "iso:country":"IR",
    "name:fas_x_preferred":[
        "B\u0101ghcheh-ye Jal\u012bl"
    ],
    "name:fas_x_variant":[
        "\u0628\u0627\u063a\u0686\u0647 \u062c\u0644\u06cc\u0644"
    ],
    "name:und_x_variant":[
        "\u0628\u0627\u063a\u0686\u0647 \u062c\u0644\u06cc\u0644"
    ],
    "wof:name":"Baghcheh-ye Jalil",
    "wof:placetype":"locality"
},
  "geometry": {"coordinates":[51.26387,30.6498],"type":"Point"}
}