{
  "type": "Feature",
  "properties": {
    "gn:admin1_code":"4.0",
    "gn:asciiname":"Shurag",
    "gn:country_code":"IR",
    "gn:dem":1268,
    "gn:feature_class":"P",
    "gn:feature_code":"PPL",
    "gn:name":"Sh\u016brag",
    "gn:population":0,
    "gn:timezone":"Asia/Tehran",
    "iso:country":"IR",
    "name:fas_x_preferred":[
        "\u0634\u0648\u0631\u06af"
    ],
    "name:fas_x_variant":[
        "Sh\u016brag",
        "Sh\u016br\u0101z",
        "\u0634\u0648\u0631\u06a9"
    ],
    "name:und_x_variant":[
        "Sh\u016br\u0101z",
        "Sh\u016brak"
    ],
    "wof:name":"Shurag",
    "wof:placetype":"locality"
},
  "geometry": {"coordinates":[61.01079,27.67062],"type":"Point"}
}