{
  "type": "Feature",
  "properties": {
    "gn:admin1_code":"23",
    "gn:asciiname":"Venna'i",
    "gn:country_code":"IR",
    "gn:dem":1977,
    "gn:feature_class":"P",
    "gn:feature_code":"PPL",
    "gn:name":"Venn\u0101\u2019\u012b",
    "gn:population":0,
    "gn:timezone":"Asia/Tehran",
    "iso:country":"IR",
    "name:fas_x_preferred":[
        "\u062a\u0648\u0626\u064a\u0634\u06a9\u0647"
    ],
    "name:fas_x_variant":[
        "Venn\u0101\u2019\u012b"
    ],
    "name:und_x_variant":[
        "Vann\u0101\u2019\u012b",
        "Van\u0101\u2019\u012b"
    ],
    "wof:name":"Venna'i",
    "wof:placetype":"locality"
},
  "geometry": {"coordinates":[48.5913,33.9153],"type":"Point"}
}