{
  "type": "Feature",
  "properties": {
    "gn:admin1_code":"40",
    "gn:asciiname":"Qavamabad",
    "gn:country_code":"IR",
    "gn:dem":1644,
    "gn:feature_class":"P",
    "gn:feature_code":"PPL",
    "gn:name":"Qav\u0101m\u0101b\u0101d",
    "gn:population":0,
    "gn:timezone":"Asia/Tehran",
    "iso:country":"IR",
    "name:fas_x_preferred":[
        "\u063a\u064e\u0648\u064e\u0645 \u0627\u064e\u0628\u064e\u062f"
    ],
    "name:fas_x_variant":[
        "Qav\u0101m\u0101b\u0101d",
        "\u0642\u0648\u0627\u0645 \u0622\u0628\u0627\u062f"
    ],
    "name:und_x_variant":[
        "Ghavam Abad"
    ],
    "wof:name":"Qavamabad",
    "wof:placetype":"locality"
},
  "geometry": {"coordinates":[54.07876,31.81821],"type":"Point"}
}