{
  "type": "Feature",
  "properties": {
    "gn:admin1_code":"4",
    "gn:asciiname":"Mowd-e Geli",
    "gn:country_code":"IR",
    "gn:dem":1283,
    "gn:feature_class":"P",
    "gn:feature_code":"PPL",
    "gn:name":"Mowd-e Gel\u012b",
    "gn:population":0,
    "gn:timezone":"Asia/Tehran",
    "iso:country":"IR",
    "name:fas_x_preferred":[
        "\u0645\u0648\u062f \u06af\u0644\u06cc"
    ],
    "name:fas_x_variant":[
        "Mowd-e Gel\u012b"
    ],
    "wof:name":"Mowd-e Geli",
    "wof:placetype":"locality"
},
  "geometry": {"coordinates":[62.79704,26.8216],"type":"Point"}
}