{
  "type": "Feature",
  "properties": {
    "gn:admin1_code":"1",
    "gn:asciiname":"Hajj'ali Kand",
    "gn:country_code":"IR",
    "gn:dem":1682,
    "gn:feature_class":"P",
    "gn:feature_code":"PPL",
    "gn:name":"\u1e28\u0101jj\u2019al\u012b Kand",
    "gn:population":0,
    "gn:timezone":"Asia/Tehran",
    "iso:country":"IR",
    "name:fas_x_preferred":[
        "\u062d\u0627\u062c\u0651\u06cc \u0639\u064e\u0644\u06cc \u0643\u064e\u0646\u062f\u06cc"
    ],
    "name:fas_x_variant":[
        "\u0647\u0627\u062c\u0639\u064e\u0644\u06cc \u0643\u064e\u0646\u062f",
        "\u1e28\u0101jj\u2019al\u012b Kand",
        "\u062d\u0627\u062c\u0639\u0644\u06cc \u06a9\u0646\u062f",
        "\u1e28\u0101jj\u012b \u2018Al\u012b Kand\u012b",
        "\u062d\u0627\u062c\u0651\u06cc \u0639\u064e\u0644\u06cc \u0643\u064e\u0646\u062f"
    ],
    "name:und_x_variant":[
        "H\u0101j\u2018al\u012b Kand",
        "\u1e28\u0101jj\u012b \u2018Al\u012b Kand",
        "H\u0101ji \u2018Ali Kh\u0101n"
    ],
    "wof:name":"Hajj'ali Kand",
    "wof:placetype":"locality"
},
  "geometry": {"coordinates":[45.9268,36.7565],"type":"Point"}
}