{
  "type": "Feature",
  "properties": {
    "gn:admin1_code":"8.0",
    "gn:asciiname":"Aliabad Cham",
    "gn:country_code":"IR",
    "gn:dem":226,
    "gn:feature_class":"P",
    "gn:feature_code":"PPL",
    "gn:name":"Aliabad Cham",
    "gn:population":0,
    "gn:timezone":"Asia/Tehran",
    "iso:country":"IR",
    "name:fas_x_preferred":[
        "\u0639\u0644\u06cc \u0622\u0628\u0627\u062f"
    ],
    "name:fas_x_variant":[
        "\u2018Al\u012b\u0101b\u0101d-e P\u0101\u2019\u012bn",
        "\u2018Al\u012b\u0101b\u0101d",
        "\u0639\u0644\u06cc \u0622\u0628\u0627\u062f \u067e\u0627\u0626\u06cc\u0646",
        "\u0633\u067e\u06cc\u062f \u0631\u0648\u062f",
        "\u0633\u0641\u06cc\u062f \u0631\u0648\u062f"
    ],
    "name:und_x_variant":[
        "Sep\u012bd R\u016bd",
        "Sef\u012bd R\u016bd"
    ],
    "wof:name":"Aliabad Cham",
    "wof:placetype":"locality"
},
  "geometry": {"coordinates":[49.3893,36.76508],"type":"Point"}
}