{
  "type": "Feature",
  "properties": {
    "gn:admin1_code":"11.0",
    "gn:asciiname":"Mohammad `Ali Shahi",
    "gn:country_code":"IR",
    "gn:dem":371,
    "gn:feature_class":"P",
    "gn:feature_code":"PPL",
    "gn:name":"Mo\u1e29ammad \u2018Al\u012b Sh\u0101h\u012b",
    "gn:population":0,
    "gn:timezone":"Asia/Tehran",
    "iso:country":"IR",
    "name:fas_x_preferred":[
        "\u0645\u062d\u0645\u062f \u0639\u0644\u06cc \u0634\u0627\u0647\u06cc"
    ],
    "name:fas_x_variant":[
        "Mo\u1e29ammad \u2018Al\u012b Sh\u0101h\u012b"
    ],
    "wof:name":"Mohammad `Ali Shahi",
    "wof:placetype":"locality"
},
  "geometry": {"coordinates":[57.2797,27.0794],"type":"Point"}
}