{
  "type": "Feature",
  "properties": {
    "gn:admin1_code":"35.0",
    "gn:asciiname":"Saf Sar",
    "gn:country_code":"IR",
    "gn:dem":1719,
    "gn:feature_class":"P",
    "gn:feature_code":"PPL",
    "gn:name":"\u015e\u0101f Sar",
    "gn:population":0,
    "gn:timezone":"Asia/Tehran",
    "iso:country":"IR",
    "name:fas_x_preferred":[
        "\u0635\u0627\u0641 \u0633\u0631"
    ],
    "name:und_x_variant":[
        "\u015e\u0101f Sar"
    ],
    "wof:name":"Saf Sar",
    "wof:placetype":"locality"
},
  "geometry": {"coordinates":[51.1976,36.35021],"type":"Point"}
}