{
  "type": "Feature",
  "properties": {
    "gn:admin1_code":"32",
    "gn:asciiname":"Ilanjegh",
    "gn:country_code":"IR",
    "gn:dem":1691,
    "gn:feature_class":"P",
    "gn:feature_code":"PPL",
    "gn:name":"Ilanjegh",
    "gn:population":0,
    "gn:timezone":"Asia/Tehran",
    "iso:country":"IR",
    "name:fas_x_preferred":[
        "Val\u012b-ye \u2018A\u015fr"
    ],
    "name:fas_x_variant":[
        "\u0627\u06cc\u0644\u0627\u0646\u062c\u0648\u0642",
        "\u0648\u0644\u06cc\u0639\u0635\u0631"
    ],
    "name:und_x_variant":[
        "\u012al\u0101nj\u016bq",
        "Yel\u0101nj\u016bq",
        "Ilanjegh",
        "Val\u012b\u2018a\u015fr"
    ],
    "wof:name":"Ilanjegh",
    "wof:placetype":"locality"
},
  "geometry": {"coordinates":[47.92459,38.00045],"type":"Point"}
}