{
  "type": "Feature",
  "properties": {
    "gn:admin1_code":"16.0",
    "gn:asciiname":"`Alijan",
    "gn:country_code":"IR",
    "gn:dem":1918,
    "gn:elevation":"0.0",
    "gn:feature_class":"P",
    "gn:feature_code":"PPL",
    "gn:name":"\u2018Al\u012bj\u0101n",
    "gn:population":0,
    "gn:timezone":"Asia/Tehran",
    "iso:country":"IR",
    "name:fas_x_preferred":[
        "\u2018Al\u012bj\u0101n"
    ],
    "name:fas_x_variant":[
        "\u0100l\u012bj\u0101n",
        "\u0622\u0644\u064a\u062c\u0627\u0646",
        "\u0639\u0644\u06cc\u062c\u0627\u0646"
    ],
    "wof:name":"`Alijan",
    "wof:placetype":"locality"
},
  "geometry": {"coordinates":[46.6827,35.9215],"type":"Point"}
}