{
  "type": "Feature",
  "properties": {
    "gn:admin1_code":"9",
    "gn:asciiname":"Qilab",
    "gn:country_code":"IR",
    "gn:dem":1465,
    "gn:feature_class":"P",
    "gn:feature_code":"PPL",
    "gn:name":"Q\u012bl\u0101b",
    "gn:population":0,
    "gn:timezone":"Asia/Tehran",
    "iso:country":"IR",
    "name:ckb_x_preferred":[
        "\u0642\u06cc\u0644\u0627\u0648"
    ],
    "name:fas_x_preferred":[
        "Q\u012bl\u0101b"
    ],
    "name:fas_x_variant":[
        "\u0642\u06cc\u0644\u0627\u0628"
    ],
    "name:msa_x_preferred":[
        "Qilab"
    ],
    "name:und_x_variant":[
        "\u0642\u06cc\u0644\u0627\u0628"
    ],
    "wof:name":"Qilab",
    "wof:placetype":"locality"
},
  "geometry": {"coordinates":[48.06073,34.30466],"type":"Point"}
}