{
  "type": "Feature",
  "properties": {
    "gn:admin1_code":"28",
    "gn:asciiname":"Savaran",
    "gn:country_code":"IR",
    "gn:dem":2190,
    "gn:feature_class":"P",
    "gn:feature_code":"PPL",
    "gn:name":"Sav\u0101r\u0101n",
    "gn:population":0,
    "gn:timezone":"Asia/Tehran",
    "iso:country":"IR",
    "name:ara_x_preferred":[
        "\u0633\u0648\u0627\u0631\u0627\u0646"
    ],
    "name:fas_x_preferred":[
        "Sav\u0101r\u0101n"
    ],
    "name:fas_x_variant":[
        "\u0633\u0648\u0627\u0631\u0627\u0646"
    ],
    "name:hye_x_preferred":[
        "\u054d\u057e\u0561\u0580\u0561\u0576"
    ],
    "name:und_x_variant":[
        "Saw\u0101r\u0101n"
    ],
    "wof:name":"Savaran",
    "wof:placetype":"locality"
},
  "geometry": {"coordinates":[50.36937,32.8788],"type":"Point"}
}