{
  "type": "Feature",
  "properties": {
    "gn:admin1_code":"29.0",
    "gn:asciiname":"Bab Tangol",
    "gn:country_code":"IR",
    "gn:dem":1894,
    "gn:feature_class":"P",
    "gn:feature_code":"PPL",
    "gn:name":"B\u0101b Tangol",
    "gn:population":0,
    "gn:timezone":"Asia/Tehran",
    "iso:country":"IR",
    "name:fas_x_preferred":[
        "B\u0101b Tangal"
    ],
    "name:fas_x_variant":[
        "B\u0101b Tangol",
        "\u0628\u0627\u0628 \u062a\u0646\u06af\u0644"
    ],
    "name:und_x_variant":[
        "Dungal",
        "Bab Tankal",
        "Bab-Tanqal",
        "\u0628\u0627\u0628 \u062a\u0646\u06af\u0644"
    ],
    "wof:name":"Bab Tangol",
    "wof:placetype":"locality"
},
  "geometry": {"coordinates":[56.56902,30.91035],"type":"Point"}
}