{
  "type": "Feature",
  "properties": {
    "gn:admin1_code":"7",
    "gn:asciiname":"`Ali Resideh",
    "gn:country_code":"IR",
    "gn:dem":1783,
    "gn:feature_class":"P",
    "gn:feature_code":"PPL",
    "gn:name":"\u2018Al\u012b Res\u012bdeh",
    "gn:population":0,
    "gn:timezone":"Asia/Tehran",
    "iso:country":"IR",
    "name:fas_x_preferred":[
        "\u0639\u0644\u06cc \u0631\u0633\u06cc\u062f\u0647"
    ],
    "name:fas_x_variant":[
        "\u2018Al\u012b Res\u012bdeh"
    ],
    "name:und_x_variant":[
        "\u2018Al\u012b Sor\u012bdeh"
    ],
    "wof:name":"`Ali Resideh",
    "wof:placetype":"locality"
},
  "geometry": {"coordinates":[53.1197,30.0307],"type":"Point"}
}