{
  "type": "Feature",
  "properties": {
    "gn:admin1_code":"42",
    "gn:asciiname":"Golbu-ye Sofla",
    "gn:country_code":"IR",
    "gn:dem":1389,
    "gn:feature_class":"P",
    "gn:feature_code":"PPL",
    "gn:name":"Golb\u016b-ye Sofl\u00e1",
    "gn:population":0,
    "gn:timezone":"Asia/Tehran",
    "iso:country":"IR",
    "name:fas_x_preferred":[
        "\u06af\u0644\u0628\u0648\u06cc \u067e\u0627\u0626\u06cc\u0646"
    ],
    "name:fas_x_variant":[
        "Golb\u016b-ye P\u0101\u2019\u012bn",
        "\u06af\u0644\u0628\u0648 \u0633\u0641\u0644\u06cc"
    ],
    "name:und_x_variant":[
        "Golb\u016b-ye Sofl\u00e1"
    ],
    "wof:name":"Golbu-ye Sofla",
    "wof:placetype":"locality"
},
  "geometry": {"coordinates":[58.85972,35.78315],"type":"Point"}
}