{
  "type": "Feature",
  "properties": {
    "gn:admin1_code":"42",
    "gn:asciiname":"Gandom Khvab",
    "gn:country_code":"IR",
    "gn:dem":1045,
    "gn:feature_class":"P",
    "gn:feature_code":"PPL",
    "gn:name":"Gandom Khv\u0101b",
    "gn:population":0,
    "gn:timezone":"Asia/Tehran",
    "iso:country":"IR",
    "name:fas_x_preferred":[
        "\u06af\u0646\u062f\u0645 \u062e\u0648\u0627\u0628"
    ],
    "name:fas_x_variant":[
        "Gandom Khv\u0101b"
    ],
    "name:und_x_variant":[
        "Gandom Khav\u0101b"
    ],
    "wof:name":"Gandom Khvab",
    "wof:placetype":"locality"
},
  "geometry": {"coordinates":[59.50303,36.53883],"type":"Point"}
}