{
  "type": "Feature",
  "properties": {
    "gn:admin1_code":"1",
    "gn:asciiname":"`Aleyh",
    "gn:country_code":"IR",
    "gn:dem":1551,
    "gn:feature_class":"P",
    "gn:feature_code":"PPL",
    "gn:name":"\u2018Aleyh",
    "gn:population":0,
    "gn:timezone":"Asia/Tehran",
    "iso:country":"IR",
    "name:fas_x_preferred":[
        "\u0639\u064e\u0644\u0650\u064a\u0647"
    ],
    "name:fas_x_variant":[
        "\u2018Aleyh",
        "\u0639\u0644\u06cc\u0647"
    ],
    "wof:name":"`Aleyh",
    "wof:placetype":"locality"
},
  "geometry": {"coordinates":[44.8969,37.2123],"type":"Point"}
}