{
  "type": "Feature",
  "properties": {
    "gn:admin1_code":"7",
    "gn:asciiname":"Dareh",
    "gn:country_code":"IR",
    "gn:dem":1764,
    "gn:feature_class":"P",
    "gn:feature_code":"PPL",
    "gn:name":"Dareh",
    "gn:population":0,
    "gn:timezone":"Asia/Tehran",
    "iso:country":"IR",
    "name:fas_x_preferred":[
        "\u062f\u0631\u0647"
    ],
    "name:und_x_variant":[
        "Derreh",
        "Darreh",
        "Dareh"
    ],
    "wof:name":"Dareh",
    "wof:placetype":"locality"
},
  "geometry": {"coordinates":[52.3777,29.4476],"type":"Point"}
}