{
  "type": "Feature",
  "properties": {
    "gn:admin1_code":"35.0",
    "gn:asciiname":"Afra Koti",
    "gn:country_code":"IR",
    "gn:dem":27,
    "gn:feature_class":"P",
    "gn:feature_code":"PPL",
    "gn:name":"Afr\u0101 Kot\u012b",
    "gn:population":0,
    "gn:timezone":"Asia/Tehran",
    "iso:country":"IR",
    "name:fas_x_preferred":[
        "\u0627\u0641\u0631\u0627 \u0643\u062a\u06cc"
    ],
    "name:fas_x_variant":[
        "Afr\u0101 Kot\u012b"
    ],
    "wof:name":"Afra Koti",
    "wof:placetype":"locality"
},
  "geometry": {"coordinates":[52.80833000000001,36.48964],"type":"Point"}
}