{
  "type": "Feature",
  "properties": {
    "gn:admin1_code":"15",
    "gn:asciiname":"Sheykh Kazem",
    "gn:cc2":"IR",
    "gn:country_code":"IR",
    "gn:dem":25,
    "gn:feature_class":"P",
    "gn:feature_code":"PPL",
    "gn:name":"Sheykh K\u0101z\u0327em",
    "gn:population":0,
    "gn:timezone":"Asia/Tehran",
    "iso:country":"IR",
    "name:fas_x_preferred":[
        "Sheykh K\u0101z\u0327em"
    ],
    "name:und_x_variant":[
        "Shaikh K\u0101zim"
    ],
    "wof:name":"Sheykh Kazem",
    "wof:placetype":"locality"
},
  "geometry": {"coordinates":[48.86667,31.56667],"type":"Point"}
}