{
  "type": "Feature",
  "properties": {
    "gn:admin1_code":"11",
    "gn:asciiname":"Garsur",
    "gn:country_code":"IR",
    "gn:dem":125,
    "gn:feature_class":"P",
    "gn:feature_code":"PPL",
    "gn:name":"Gars\u016br",
    "gn:population":0,
    "gn:timezone":"Asia/Tehran",
    "iso:country":"IR",
    "name:fas_x_preferred":[
        "\u062a\u0627\u0648\u0650\u0647"
    ],
    "name:fas_x_variant":[
        "T\u0101veh",
        "\u06af\u0631\u0633\u0648\u0631"
    ],
    "name:und_x_variant":[
        "Gars\u016br"
    ],
    "wof:name":"Garsur",
    "wof:placetype":"locality"
},
  "geometry": {"coordinates":[55.06166999999999,26.92167],"type":"Point"}
}