{
  "type": "Feature",
  "properties": {
    "gn:admin1_code":"43",
    "gn:asciiname":"Yengi Qal`eh",
    "gn:country_code":"IR",
    "gn:dem":956,
    "gn:feature_class":"P",
    "gn:feature_code":"PPL",
    "gn:name":"Yeng\u012b Qal\u2018eh",
    "gn:population":0,
    "gn:timezone":"Asia/Tehran",
    "iso:country":"IR",
    "name:fas_x_preferred":[
        "Yeng\u012b Qal\u2018eh"
    ],
    "name:fas_x_variant":[
        "\u06cc\u0646\u06af\u06cc \u0642\u0644\u0639\u0647"
    ],
    "name:und_x_variant":[
        "\u06cc\u0646\u06af\u06cc \u0642\u0644\u0639\u0647"
    ],
    "wof:name":"Yengi Qal`eh",
    "wof:placetype":"locality"
},
  "geometry": {"coordinates":[57.12391,37.58476],"type":"Point"}
}