{
  "type": "Feature",
  "properties": {
    "gn:admin1_code":"29",
    "gn:asciiname":"Tolombeh-ye Rowshan",
    "gn:country_code":"IR",
    "gn:dem":1711,
    "gn:feature_class":"P",
    "gn:feature_code":"PPL",
    "gn:name":"Tolombeh-ye Rowshan",
    "gn:population":0,
    "gn:timezone":"Asia/Tehran",
    "iso:country":"IR",
    "wof:name":"Tolombeh-ye Rowshan",
    "wof:placetype":"locality"
},
  "geometry": {"coordinates":[55.74916999999999,29.11389],"type":"Point"}
}