{
  "type": "Feature",
  "properties": {
    "gn:admin1_code":"11",
    "gn:asciiname":"Qahveh Khaneh-ye Abmah",
    "gn:country_code":"IR",
    "gn:dem":862,
    "gn:feature_class":"P",
    "gn:feature_code":"PPL",
    "gn:name":"Qahveh Kh\u0101neh-ye \u0100bm\u0101h",
    "gn:population":0,
    "gn:timezone":"Asia/Tehran",
    "iso:country":"IR",
    "name:fas_x_preferred":[
        "\u0642\u064e\u0647\u0648\u0650\u0647 \u062e\u0627\u0646\u0650\u06c0 \u0622\u0628\u0645\u0627\u0647"
    ],
    "name:fas_x_variant":[
        "Qahveh Kh\u0101neh-ye \u0100bm\u0101h"
    ],
    "wof:name":"Qahveh Khaneh-ye Abmah",
    "wof:placetype":"locality"
},
  "geometry": {"coordinates":[55.99333000000001,27.83333],"type":"Point"}
}