{
  "type": "Feature",
  "properties": {
    "gn:admin1_code":"7",
    "gn:asciiname":"Chahar Deh",
    "gn:country_code":"IR",
    "gn:dem":1373,
    "gn:feature_class":"P",
    "gn:feature_code":"PPL",
    "gn:name":"Chah\u0101r Deh",
    "gn:population":0,
    "gn:timezone":"Asia/Tehran",
    "iso:country":"IR",
    "name:ara_x_preferred":[
        "\u062a\u0634\u0647\u0627\u0631\u062f\u0629"
    ],
    "name:fas_x_preferred":[
        "\u0686\u0647\u0627\u0631 \u062f\u0647"
    ],
    "name:fas_x_variant":[
        "Chah\u0101r Deh",
        "\u0686\u0647\u0627\u0631\u062f\u0647"
    ],
    "name:msa_x_preferred":[
        "Chahar Deh"
    ],
    "name:und_x_variant":[
        "Chahar D\u0101ng",
        "Cheh\u0101rdeh"
    ],
    "wof:name":"Chahar Deh",
    "wof:placetype":"locality"
},
  "geometry": {"coordinates":[55.0408,28.4758],"type":"Point"}
}