{
  "type": "Feature",
  "properties": {
    "gn:admin1_code":"37",
    "gn:asciiname":"Yarem Tappeh",
    "gn:country_code":"IR",
    "gn:dem":121,
    "gn:feature_class":"P",
    "gn:feature_code":"PPL",
    "gn:name":"Y\u0101rem Tappeh",
    "gn:population":0,
    "gn:timezone":"Asia/Tehran",
    "iso:country":"IR",
    "name:ceb_x_preferred":[
        "Y\u0101rem Tappeh"
    ],
    "name:fas_x_preferred":[
        "Y\u0101rem Tappeh"
    ],
    "name:fas_x_variant":[
        "\u064a\u0627\u0631\u0645 \u062a\u067e\u0647",
        "\u06cc\u0627\u0631\u0645\u200c\u062a\u067e\u0647"
    ],
    "name:msa_x_preferred":[
        "Yarem Tappeh"
    ],
    "name:swe_x_preferred":[
        "Y\u0101rem Tappeh"
    ],
    "name:urd_x_preferred":[
        "\u06cc\u0631\u0645 \u062a\u067e\u067e\u06cc\u06c1"
    ],
    "wof:name":"Yarem Tappeh",
    "wof:placetype":"locality"
},
  "geometry": {"coordinates":[55.39247,37.45343],"type":"Point"}
}