{
  "type": "Feature",
  "properties": {
    "gn:admin1_code":"25",
    "gn:asciiname":"Dasht-e Shad",
    "gn:country_code":"IR",
    "gn:dem":1572,
    "gn:feature_class":"P",
    "gn:feature_code":"PPL",
    "gn:name":"Dasht-e Sh\u0101d",
    "gn:population":0,
    "gn:timezone":"Asia/Tehran",
    "iso:country":"IR",
    "name:fas_x_preferred":[
        "\u062f\u0634\u062a \u0634\u0627\u062f"
    ],
    "name:fas_x_variant":[
        "\u062f\u064e\u0633\u062a \u0634\u0627\u0647",
        "\u062f\u064e\u0633\u062a\u0650 \u0634\u0627",
        "\u062f\u0633\u062a \u0634\u0627\u0647",
        "Dasht-e Sh\u0101d",
        "Dast-e Sh\u0101h"
    ],
    "name:und_x_variant":[
        "Destisha",
        "Dast Sh\u0101h",
        "Dast-e Sh\u0101"
    ],
    "wof:name":"Dasht-e Shad",
    "wof:placetype":"locality"
},
  "geometry": {"coordinates":[55.7651,37.27479],"type":"Point"}
}