{
  "type": "Feature",
  "properties": {
    "gn:admin1_code":"35",
    "gn:asciiname":"Anarestan",
    "gn:country_code":"IR",
    "gn:dem":43,
    "gn:feature_class":"P",
    "gn:feature_code":"PPL",
    "gn:name":"An\u0101rest\u0101n",
    "gn:population":0,
    "gn:timezone":"Asia/Tehran",
    "iso:country":"IR",
    "name:fas_x_preferred":[
        "\u0627\u0646\u0627\u0631\u0633\u062a\u0627\u0646"
    ],
    "name:fas_x_variant":[
        "An\u0101rest\u0101n"
    ],
    "name:und_x_variant":[
        "\u0627\u064e\u0646\u0627\u0631\u0650\u0633\u062a\u0627\u0646"
    ],
    "wof:name":"Anarestan",
    "wof:placetype":"locality"
},
  "geometry": {"coordinates":[52.71064000000001,36.41119000000001],"type":"Point"}
}