{
  "type": "Feature",
  "properties": {
    "gn:admin1_code":"7",
    "gn:asciiname":"Qal`eh Now",
    "gn:country_code":"IR",
    "gn:dem":1084,
    "gn:feature_class":"P",
    "gn:feature_code":"PPL",
    "gn:name":"Qal\u2018eh Now",
    "gn:population":0,
    "gn:timezone":"Asia/Tehran",
    "iso:country":"IR",
    "name:fas_x_preferred":[
        "\u0642\u0644\u0639\u0647 \u0646\u0648"
    ],
    "name:fas_x_variant":[
        "Qal\u2018eh Now"
    ],
    "name:und_x_variant":[
        "Qal\u2018eh-i-Nau",
        "Qal\u2018eh-ye Now"
    ],
    "wof:name":"Qal`eh Now",
    "wof:placetype":"locality"
},
  "geometry": {"coordinates":[54.4737,28.666],"type":"Point"}
}