{
  "type": "Feature",
  "properties": {
    "gn:admin1_code":"29",
    "gn:asciiname":"Joldar",
    "gn:country_code":"IR",
    "gn:dem":674,
    "gn:feature_class":"P",
    "gn:feature_code":"PPL",
    "gn:name":"Joldar",
    "gn:population":0,
    "gn:timezone":"Asia/Tehran",
    "iso:country":"IR",
    "wof:name":"Joldar",
    "wof:placetype":"locality"
},
  "geometry": {"coordinates":[57.83389,27.26389],"type":"Point"}
}