{
  "type": "Feature",
  "properties": {
    "gn:admin1_code":"42",
    "gn:asciiname":"Borqeban",
    "gn:country_code":"IR",
    "gn:dem":1313,
    "gn:feature_class":"P",
    "gn:feature_code":"PPL",
    "gn:name":"Borqeb\u0101n",
    "gn:population":0,
    "gn:timezone":"Asia/Tehran",
    "iso:country":"IR",
    "name:fas_x_preferred":[
        "Borgheb\u0101n"
    ],
    "name:fas_x_variant":[
        "Borqeb\u0101n",
        "\u0628\u0631\u0642\u0628\u0627\u0646",
        "Borqb\u0101n",
        "Barqeb\u0101n",
        "Bargh\u012b\u0101n",
        "Barghey\u0101n"
    ],
    "name:und_x_variant":[
        "Varqabeh",
        "Boroghbeh",
        "Tabailak",
        "Barqabeh"
    ],
    "wof:name":"Borqeban",
    "wof:placetype":"locality"
},
  "geometry": {"coordinates":[57.89256,36.39791],"type":"Point"}
}