{
  "type": "Feature",
  "properties": {
    "gn:admin1_code":"34.0",
    "gn:asciiname":"Shulak",
    "gn:country_code":"IR",
    "gn:dem":1762,
    "gn:feature_class":"P",
    "gn:feature_code":"PPL",
    "gn:name":"Sh\u016blak",
    "gn:population":0,
    "gn:timezone":"Asia/Tehran",
    "iso:country":"IR",
    "name:fas_x_preferred":[
        "\u0634\u0648\u0644\u06a9"
    ],
    "name:fas_x_variant":[
        "Sh\u016blak"
    ],
    "wof:name":"Shulak",
    "wof:placetype":"locality"
},
  "geometry": {"coordinates":[49.79892,34.96805999999999],"type":"Point"}
}