{
  "type": "Feature",
  "properties": {
    "gn:admin1_code":"35.0",
    "gn:asciiname":"Shamansara",
    "gn:country_code":"IR",
    "gn:dem":14,
    "gn:feature_class":"P",
    "gn:feature_code":"PPL",
    "gn:name":"Sham\u0101nsar\u0101",
    "gn:population":0,
    "gn:timezone":"Asia/Tehran",
    "iso:country":"IR",
    "name:fas_x_preferred":[
        "\u0634\u0645\u0627\u0646\u0633\u0631\u0627"
    ],
    "name:und_x_variant":[
        "Sham\u0101nsar\u0101"
    ],
    "wof:name":"Shamansara",
    "wof:placetype":"locality"
},
  "geometry": {"coordinates":[51.13765,36.67963],"type":"Point"}
}