{
  "type": "Feature",
  "properties": {
    "gn:admin1_code":"32.0",
    "gn:asciiname":"Gollu",
    "gn:country_code":"IR",
    "gn:dem":1783,
    "gn:feature_class":"P",
    "gn:feature_code":"PPL",
    "gn:name":"Goll\u016b",
    "gn:population":0,
    "gn:timezone":"Asia/Tehran",
    "iso:country":"IR",
    "name:fas_x_preferred":[
        "\u06af\u0644\u0648"
    ],
    "name:fas_x_variant":[
        "Goll\u016b"
    ],
    "wof:name":"Gollu",
    "wof:placetype":"locality"
},
  "geometry": {"coordinates":[48.2063,37.8312],"type":"Point"}
}