{
  "type": "Feature",
  "properties": {
    "gn:admin1_code":"44",
    "gn:asciiname":"Sirah",
    "gn:country_code":"IR",
    "gn:dem":1840,
    "gn:feature_class":"P",
    "gn:feature_code":"PPL",
    "gn:name":"Sirah",
    "gn:population":0,
    "gn:timezone":"Asia/Tehran",
    "iso:country":"IR",
    "name:ceb_x_preferred":[
        "Sirah"
    ],
    "name:deu_x_preferred":[
        "Sirah"
    ],
    "name:fas_x_preferred":[
        "\u0633\u064a\u0631\u0627"
    ],
    "name:fas_x_variant":[
        "\u0633\u064e\u0631\u0627\u0628",
        "S\u012br\u0101"
    ],
    "name:swe_x_preferred":[
        "Sirah"
    ],
    "name:und_x_variant":[
        "Sar\u0101b",
        "Sirah"
    ],
    "wof:name":"Sirah",
    "wof:placetype":"locality"
},
  "geometry": {"coordinates":[51.15491,36.02865999999999],"type":"Point"}
}