{
  "type": "Feature",
  "properties": {
    "gn:admin1_code":"37.0",
    "gn:asciiname":"Deruk",
    "gn:country_code":"IR",
    "gn:dem":732,
    "gn:feature_class":"P",
    "gn:feature_code":"PPL",
    "gn:name":"Der\u016bk",
    "gn:population":0,
    "gn:timezone":"Asia/Tehran",
    "iso:country":"IR",
    "name:fas_x_preferred":[
        "Der\u016bk"
    ],
    "name:fas_x_variant":[
        "\u062f\u0631\u0648\u06a9"
    ],
    "wof:name":"Deruk",
    "wof:placetype":"locality"
},
  "geometry": {"coordinates":[55.49786,37.11599],"type":"Point"}
}