{
  "type": "Feature",
  "properties": {
    "gn:admin1_code":"36",
    "gn:asciiname":"Hirabad",
    "gn:country_code":"IR",
    "gn:dem":1800,
    "gn:feature_class":"P",
    "gn:feature_code":"PPL",
    "gn:name":"H\u012br\u0101b\u0101d",
    "gn:population":0,
    "gn:timezone":"Asia/Tehran",
    "iso:country":"IR",
    "name:fas_x_preferred":[
        "\u0647\u06cc\u0631 \u0622\u0628\u0627\u062f"
    ],
    "name:fas_x_variant":[
        "H\u012br\u0101b\u0101d"
    ],
    "wof:name":"Hirabad",
    "wof:placetype":"locality"
},
  "geometry": {"coordinates":[48.67345,35.88079000000001],"type":"Point"}
}