{
  "type": "Feature",
  "properties": {
    "gn:admin1_code":"41",
    "gn:asciiname":"Samak",
    "gn:country_code":"IR",
    "gn:dem":1803,
    "gn:feature_class":"P",
    "gn:feature_code":"PPL",
    "gn:name":"Samak",
    "gn:population":0,
    "gn:timezone":"Asia/Tehran",
    "iso:country":"IR",
    "name:ceb_x_preferred":[
        "Samak"
    ],
    "name:fas_x_preferred":[
        "\u0633\u0646\u0645\u06a9"
    ],
    "name:fas_x_variant":[
        "\u0633\u0645\u06a9"
    ],
    "name:fra_x_preferred":[
        "Samak"
    ],
    "name:swe_x_preferred":[
        "Samak"
    ],
    "name:ukr_x_preferred":[
        "\u0421\u0430\u043c\u0430\u043a"
    ],
    "name:und_x_variant":[
        "S\u012bmak",
        "Samk",
        "Simorgh",
        "Samak",
        "Sanmak"
    ],
    "wof:name":"Samak",
    "wof:placetype":"locality"
},
  "geometry": {"coordinates":[59.5215,32.0582],"type":"Point"}
}