{
  "type": "Feature",
  "properties": {
    "gn:admin1_code":"41",
    "gn:asciiname":"Chahkanduk",
    "gn:country_code":"IR",
    "gn:dem":1893,
    "gn:feature_class":"P",
    "gn:feature_code":"PPL",
    "gn:name":"Ch\u0101hkand\u016bk",
    "gn:population":0,
    "gn:timezone":"Asia/Tehran",
    "iso:country":"IR",
    "name:fas_x_preferred":[
        "Ch\u0101hkand\u016bk"
    ],
    "name:fas_x_variant":[
        "\u0686\u0627\u0647 \u06a9\u0646\u062f\u0648\u06a9",
        "Ch\u0101h Kand\u016bk"
    ],
    "name:und_x_variant":[
        "Chah Kandook Nahar Khan"
    ],
    "wof:name":"Chahkanduk",
    "wof:placetype":"locality"
},
  "geometry": {"coordinates":[59.46338000000001,32.55374],"type":"Point"}
}