{
  "type": "Feature",
  "properties": {
    "gn:country":"IR",
    "gn:fcode":"PPL",
    "gn:population":251834,
    "iso:country":"IR",
    "name:ara_x_preferred":[
        "\u0642\u0631\u062a\u0634\u0643"
    ],
    "name:aze_x_preferred":[
        "\u0642\u0631\u0686\u06a9"
    ],
    "name:ceb_x_preferred":[
        "Qarchak"
    ],
    "name:deu_x_preferred":[
        "Ghartschak"
    ],
    "name:eng_x_preferred":[
        "Qarchak"
    ],
    "name:fas_x_preferred":[
        "\u0642\u0631\u0686\u0643"
    ],
    "name:fas_x_variant":[
        "\u0642\u0631\u0686\u06a9"
    ],
    "name:fin_x_preferred":[
        "Qarchak"
    ],
    "name:fra_x_preferred":[
        "Qarchak"
    ],
    "name:hin_x_preferred":[
        "\u0915\u093e\u0930\u094d\u091a\u093e\u0915"
    ],
    "name:hun_x_preferred":[
        "Karcsak"
    ],
    "name:ita_x_preferred":[
        "Qarchak"
    ],
    "name:mlg_x_preferred":[
        "Qarchak"
    ],
    "name:nld_x_preferred":[
        "Qarchak"
    ],
    "name:pol_x_preferred":[
        "Gharczak"
    ],
    "name:ron_x_preferred":[
        "Qarchak"
    ],
    "name:rus_x_preferred":[
        "\u0413\u0430\u0440\u0447\u0430\u043a"
    ],
    "name:swe_x_preferred":[
        "Qarchak"
    ],
    "name:tur_x_preferred":[
        "Kar\u00e7ak"
    ],
    "name:war_x_preferred":[
        "Qarchak"
    ],
    "qs_pg:aaroncc":"IR",
    "qs_pg:gn_country":"IR",
    "qs_pg:gn_fcode":"PPL",
    "qs_pg:gn_pop":251834,
    "qs_pg:name":"Qarchak",
    "qs_pg:photos_9r":0,
    "qs_pg:photos_sr":0,
    "qs_pg:pop_sr":10,
    "qs_pg:qs_pg_placetype":"locality",
    "wof:name":"Qarchak",
    "wof:placetype":"locality",
    "wof:population":251834
},
  "geometry": {"coordinates":[51.57544,35.42867],"type":"Point"}
}