{
  "type": "Feature",
  "properties": {
    "gn:admin1_code":"7.0",
    "gn:asciiname":"Dezhabad",
    "gn:country_code":"IR",
    "gn:dem":1580,
    "gn:feature_class":"P",
    "gn:feature_code":"PPL",
    "gn:name":"Dezh\u0101b\u0101d",
    "gn:population":0,
    "gn:timezone":"Asia/Tehran",
    "iso:country":"IR",
    "name:fas_x_preferred":[
        "\u062f\u0698 \u0622\u0628\u0627\u062f"
    ],
    "name:fas_x_variant":[
        "Dez\u0101b\u0101d",
        "Dezh\u0101b\u0101d"
    ],
    "wof:name":"Dezhabad",
    "wof:placetype":"locality"
},
  "geometry": {"coordinates":[52.9033,29.7445],"type":"Point"}
}