{
  "type": "Feature",
  "properties": {
    "gn:admin1_code":"0",
    "gn:asciiname":"Tafbaq",
    "gn:country_code":"IR",
    "gn:dem":964,
    "gn:feature_class":"P",
    "gn:feature_code":"PPL",
    "gn:name":"Tafbaq",
    "gn:population":0,
    "gn:timezone":"Asia/Tehran",
    "iso:country":"IR",
    "wof:name":"Tafbaq",
    "wof:placetype":"locality"
},
  "geometry": {"coordinates":[47.56667,38.48333],"type":"Point"}
}