{
  "type": "Feature",
  "properties": {
    "gn:admin1_code":"8",
    "gn:asciiname":"Shah Sara",
    "gn:country_code":"IR",
    "gn:dem":-8,
    "gn:feature_class":"P",
    "gn:feature_code":"PPL",
    "gn:name":"Sh\u0101h Sar\u0101",
    "gn:population":0,
    "gn:timezone":"Asia/Tehran",
    "iso:country":"IR",
    "name:fas_x_preferred":[
        "Khomeyn\u012b Sar\u0101"
    ],
    "name:fas_x_variant":[
        "Sh\u0101h\u012b Sar\u0101",
        "Sh\u0101h Sar\u0101",
        "\u0634\u0627\u0647 \u0633\u0631\u0627"
    ],
    "name:und_x_variant":[
        "Sh\u0101h Sar\u0101",
        "\u0634\u0627\u0647 \u0633\u0631\u0627"
    ],
    "wof:name":"Shah Sara",
    "wof:placetype":"locality"
},
  "geometry": {"coordinates":[50.24283,37.11536],"type":"Point"}
}