{
  "type": "Feature",
  "properties": {
    "gn:admin1_code":"35",
    "gn:asciiname":"Saram",
    "gn:country_code":"IR",
    "gn:dem":786,
    "gn:feature_class":"P",
    "gn:feature_code":"PPLF",
    "gn:name":"S\u0101ram",
    "gn:population":0,
    "gn:timezone":"Asia/Tehran",
    "iso:country":"IR",
    "name:fas_x_preferred":[
        "\u0633\u0627\u0631\u064e\u0645"
    ],
    "name:fas_x_variant":[
        "S\u0101ram",
        "\u0633\u0631\u0645"
    ],
    "name:und_x_variant":[
        "\u0633\u0631\u0645"
    ],
    "wof:name":"Saram",
    "wof:placetype":"locality"
},
  "geometry": {"coordinates":[53.4838,36.47445],"type":"Point"}
}