{
  "type": "Feature",
  "properties": {
    "gn:admin1_code":"33",
    "gn:asciiname":"Qal`eh Jiq-e `Olya",
    "gn:country_code":"IR",
    "gn:dem":1930,
    "gn:feature_class":"P",
    "gn:feature_code":"PPL",
    "gn:name":"Qal\u2018eh J\u012bq-e \u2018Oly\u0101",
    "gn:population":0,
    "gn:timezone":"Asia/Tehran",
    "iso:country":"IR",
    "name:fas_x_preferred":[
        "\u0642\u0644\u0639\u0647 \u062c\u0648\u0642 \u0628\u0627\u0644\u0627"
    ],
    "name:fas_x_variant":[
        "Qal\u2018eh J\u016bq-e \u2018Oly\u0101",
        "Qal\u2018eh J\u016bq-e B\u0101l\u0101",
        "\u0642\u0644\u0639\u0647 \u062c\u06cc\u0642 \u0639\u0644\u06cc\u0627",
        "\u0642\u0644\u0639\u0647 \u062c\u0648\u0642 \u0639\u0644\u06cc\u0627"
    ],
    "name:und_x_variant":[
        "Qal\u2018eh J\u012bq-e \u2018Oly\u0101"
    ],
    "wof:name":"Qal`eh Jiq-e `Olya",
    "wof:placetype":"locality"
},
  "geometry": {"coordinates":[46.7125,37.5483],"type":"Point"}
}