{
  "type": "Feature",
  "properties": {
    "gn:admin1_code":"42",
    "gn:asciiname":"Ebrahim Bay",
    "gn:country_code":"IR",
    "gn:dem":591,
    "gn:feature_class":"P",
    "gn:feature_code":"PPL",
    "gn:name":"Ebr\u0101h\u012bm B\u0101y",
    "gn:population":0,
    "gn:timezone":"Asia/Tehran",
    "iso:country":"IR",
    "name:fas_x_preferred":[
        "Ebr\u0101h\u012bm B\u0101y"
    ],
    "name:fas_x_variant":[
        "\u0627\u0628\u0631\u0627\u0647\u06cc\u0645 \u0628\u0627\u06cc"
    ],
    "name:und_x_variant":[
        "\u0627\u0628\u0631\u0627\u0647\u06cc\u0645 \u0628\u0627\u06cc"
    ],
    "wof:name":"Ebrahim Bay",
    "wof:placetype":"locality"
},
  "geometry": {"coordinates":[61.20894000000001,35.59624],"type":"Point"}
}