{
  "type": "Feature",
  "properties": {
    "gn:admin1_code":"43",
    "gn:asciiname":"Rezqaneh",
    "gn:country_code":"IR",
    "gn:dem":1277,
    "gn:feature_class":"P",
    "gn:feature_code":"PPL",
    "gn:name":"Rezq\u0101neh",
    "gn:population":0,
    "gn:timezone":"Asia/Tehran",
    "iso:country":"IR",
    "name:ara_x_preferred":[
        "\u0631\u0632\u0642\u0627\u0646\u0629"
    ],
    "name:ceb_x_preferred":[
        "Rezq\u0101neh"
    ],
    "name:fas_x_preferred":[
        "Rezq\u0101neh"
    ],
    "name:fas_x_variant":[
        "\u0631\u0632\u0642\u0627\u0646\u0647"
    ],
    "name:swe_x_preferred":[
        "Rezq\u0101neh"
    ],
    "name:und_x_variant":[
        "Razq\u0101neh"
    ],
    "wof:name":"Rezqaneh",
    "wof:placetype":"locality"
},
  "geometry": {"coordinates":[57.42672,37.86592],"type":"Point"}
}