{
  "type": "Feature",
  "properties": {
    "gn:admin1_code":"15",
    "gn:asciiname":"Shari`ati",
    "gn:country_code":"IR",
    "gn:dem":23,
    "gn:feature_class":"P",
    "gn:feature_code":"PPL",
    "gn:name":"Shar\u012b\u2018at\u012b",
    "gn:population":0,
    "gn:timezone":"Asia/Tehran",
    "iso:country":"IR",
    "name:fas_x_preferred":[
        "\u0633\u06cc\u0651\u062f \u0639\u0628\u0627\u0633"
    ],
    "name:fas_x_variant":[
        "Seyyed \u2018Abb\u0101s-e \u0162\u0101leq\u0101n\u012b",
        "Seyyed \u2018Abb\u0101s",
        "\u0634\u0631\u06cc\u0639\u062a\u06cc"
    ],
    "name:und_x_variant":[
        "Shar\u012b\u2018at\u012b"
    ],
    "wof:name":"Shari`ati",
    "wof:placetype":"locality"
},
  "geometry": {"coordinates":[48.4251,31.4863],"type":"Point"}
}