{
  "type": "Feature",
  "properties": {
    "gn:admin1_code":"34",
    "gn:asciiname":"Qal`eh Babu",
    "gn:country_code":"IR",
    "gn:dem":2011,
    "gn:feature_class":"P",
    "gn:feature_code":"PPL",
    "gn:name":"Qal\u2018eh B\u0101b\u016b",
    "gn:population":0,
    "gn:timezone":"Asia/Tehran",
    "iso:country":"IR",
    "name:fas_x_preferred":[
        "\u0642\u064e\u0644\u0639\u0650\u06c0 \u0628\u0627\u0628\u0648"
    ],
    "name:fas_x_variant":[
        "\u0642\u0644\u0639\u0647 \u0628\u0627\u0628\u0648",
        "Qal\u2018eh-ye B\u0101b\u016b",
        "Qal\u2018eh B\u0101n\u016b",
        "\u0642\u0644\u0639\u0647 \u0628\u0627\u0646\u0648"
    ],
    "name:und_x_variant":[
        "Qal\u2018eh B\u0101b\u016b",
        "Ghal\u2019eh Baboo",
        "\u0642\u0644\u0639\u0647 \u0628\u0627\u0646\u0648"
    ],
    "wof:name":"Qal`eh Babu",
    "wof:placetype":"locality"
},
  "geometry": {"coordinates":[49.64987,33.61646],"type":"Point"}
}