{
  "type": "Feature",
  "properties": {
    "gn:admin1_code":"8",
    "gn:asciiname":"Kiaban",
    "gn:country_code":"IR",
    "gn:dem":16,
    "gn:feature_class":"P",
    "gn:feature_code":"PPL",
    "gn:name":"K\u012b\u0101b\u0101n",
    "gn:population":0,
    "gn:timezone":"Asia/Tehran",
    "iso:country":"IR",
    "name:fas_x_preferred":[
        "\u06a9\u06cc\u0627\u0628\u0627\u0646"
    ],
    "name:fas_x_variant":[
        "K\u012b\u0101b\u0101n"
    ],
    "wof:name":"Kiaban",
    "wof:placetype":"locality"
},
  "geometry": {"coordinates":[49.36935,37.23452],"type":"Point"}
}