{
  "type": "Feature",
  "properties": {
    "gn:admin1_code":"29",
    "gn:asciiname":"Esma`iliyeh-ye `Olya",
    "gn:country_code":"IR",
    "gn:dem":673,
    "gn:feature_class":"P",
    "gn:feature_code":"PPL",
    "gn:name":"Esm\u0101\u2018\u012bl\u012byeh-ye \u2018Oly\u0101",
    "gn:population":0,
    "gn:timezone":"Asia/Tehran",
    "iso:country":"IR",
    "name:fas_x_preferred":[
        "\u0627\u0633\u0645\u0627\u0639\u06cc\u0644\u06cc\u0647 \u0639\u0644\u06cc\u0627"
    ],
    "name:fas_x_variant":[
        "Esm\u0101\u2018\u012bl\u012byeh-ye \u2018Oly\u0101"
    ],
    "name:und_x_variant":[
        "Esma\u2018ili \u2018Olya",
        "Esm\u0101\u2018\u012bl\u012b -ye B\u0101l\u0101",
        "Esm\u0101\u2018\u012bl\u012b B\u0101l\u0101"
    ],
    "wof:name":"Esma`iliyeh-ye `Olya",
    "wof:placetype":"locality"
},
  "geometry": {"coordinates":[57.555,28.2847],"type":"Point"}
}