{
  "type": "Feature",
  "properties": {
    "gn:admin1_code":"32",
    "gn:asciiname":"Qeshlaq-e Hasan`ali Aq Bash",
    "gn:country_code":"IR",
    "gn:dem":278,
    "gn:feature_class":"P",
    "gn:feature_code":"PPL",
    "gn:name":"Qeshl\u0101q-e \u1e28asan\u2018al\u012b \u0100q B\u0101sh",
    "gn:population":0,
    "gn:timezone":"Asia/Tehran",
    "iso:country":"IR",
    "name:fas_x_preferred":[
        "\u0642\u0650\u0634\u0644\u0627\u0642\u0650 \u062d\u064e\u0633\u064e\u0646\u0639\u064e\u0644\u06cc \u0622\u0642 \u0628\u0627\u0634"
    ],
    "name:fas_x_variant":[
        "Qeshl\u0101q-e \u1e28asan\u2018al\u012b \u0100q B\u0101sh"
    ],
    "wof:name":"Qeshlaq-e Hasan`ali Aq Bash",
    "wof:placetype":"locality"
},
  "geometry": {"coordinates":[47.71667,39.38333],"type":"Point"}
}