{
  "type": "Feature",
  "properties": {
    "gn:admin1_code":"3",
    "gn:asciiname":"Chahgah",
    "gn:country_code":"IR",
    "gn:dem":1853,
    "gn:feature_class":"P",
    "gn:feature_code":"PPL",
    "gn:name":"Ch\u0101hg\u0101h",
    "gn:population":0,
    "gn:timezone":"Asia/Tehran",
    "iso:country":"IR",
    "name:fas_x_preferred":[
        "\u0686\u0627\u0647 \u06af\u0627\u0648"
    ],
    "name:fas_x_variant":[
        "\u0686\u0627\u0647\u06af\u0627\u0647"
    ],
    "name:und_x_variant":[
        "Ch\u0101h G\u0101v",
        "Ch\u0101hg\u0101h"
    ],
    "wof:name":"Chahgah",
    "wof:placetype":"locality"
},
  "geometry": {"coordinates":[50.93024000000001,31.56817],"type":"Point"}
}