{
  "type": "Feature",
  "properties": {
    "gn:admin1_code":"39.0",
    "gn:asciiname":"Seydabad",
    "gn:country_code":"IR",
    "gn:dem":932,
    "gn:feature_class":"P",
    "gn:feature_code":"PPL",
    "gn:name":"\u015eeyd\u0101b\u0101d",
    "gn:population":0,
    "gn:timezone":"Asia/Tehran",
    "iso:country":"IR",
    "name:fas_x_preferred":[
        "\u0635\u06cc\u062f \u0622\u0628\u0627\u062f"
    ],
    "name:fas_x_variant":[
        "\u015eeyd\u0101b\u0101d",
        "\u0635\u06cc\u062f\u0622\u0628\u0627\u062f"
    ],
    "wof:name":"Seydabad",
    "wof:placetype":"locality"
},
  "geometry": {"coordinates":[50.5591,34.8196],"type":"Point"}
}