{
  "type": "Feature",
  "properties": {
    "gn:admin1_code":"4.0",
    "gn:asciiname":"Khati Khoshk",
    "gn:country_code":"IR",
    "gn:dem":846,
    "gn:feature_class":"P",
    "gn:feature_code":"PPL",
    "gn:name":"Kha\u0163\u012b Khoshk",
    "gn:population":0,
    "gn:timezone":"Asia/Tehran",
    "iso:country":"IR",
    "name:fas_x_preferred":[
        "Kha\u0163\u012b Khoshk"
    ],
    "wof:name":"Khati Khoshk",
    "wof:placetype":"locality"
},
  "geometry": {"coordinates":[60.53028000000001,26.9325],"type":"Point"}
}