{
  "type": "Feature",
  "properties": {
    "gn:admin1_code":"5",
    "gn:asciiname":"Rowshanabad",
    "gn:country_code":"IR",
    "gn:dem":708,
    "gn:feature_class":"P",
    "gn:feature_code":"PPL",
    "gn:name":"Rowshan\u0101b\u0101d",
    "gn:population":0,
    "gn:timezone":"Asia/Tehran",
    "iso:country":"IR",
    "name:fas_x_preferred":[
        "Rowshan\u0101b\u0101d"
    ],
    "name:fas_x_variant":[
        "\u0631\u0648\u0634\u0646 \u0622\u0628\u0627\u062f",
        "\u0631\u0648\u0634\u0646\u200c\u0622\u0628\u0627\u062f"
    ],
    "name:rus_x_preferred":[
        "\u0420\u0430\u0432\u0448\u0430\u043d\u0430\u0431\u0430\u0434"
    ],
    "name:und_x_variant":[
        "Roshan\u0101b\u0101d",
        "Rashan\u0101b\u0101d"
    ],
    "wof:name":"Rowshanabad",
    "wof:placetype":"locality"
},
  "geometry": {"coordinates":[50.52425,30.71108],"type":"Point"}
}