{
  "type": "Feature",
  "properties": {
    "gn:admin1_code":"26.0",
    "gn:asciiname":"Peyghambar",
    "gn:country_code":"IR",
    "gn:dem":1078,
    "gn:feature_class":"P",
    "gn:feature_code":"PPL",
    "gn:name":"Peyghambar",
    "gn:population":0,
    "gn:timezone":"Asia/Tehran",
    "iso:country":"IR",
    "name:fas_x_preferred":[
        "\u067e\u064a\u063a\u0645\u0628\u0631"
    ],
    "name:fas_x_variant":[
        "\u0645\u064f\u062d\u064e\u0645\u064e\u0651\u062f \u0622\u0628\u0627\u062f",
        "\u0645\u062d\u0645\u0651\u062f \u0622\u0628\u0627\u062f \u067e\u064a\u063a\u0645\u0628\u0631",
        "Mo\u1e29ammad\u0101b\u0101d-e Peyghambar",
        "\u067e\u06cc\u063a\u0645\u0628\u0631"
    ],
    "name:und_x_variant":[
        "Mo\u1e29ammad\u0101b\u0101d",
        "Peyghambar"
    ],
    "wof:name":"Peyghambar",
    "wof:placetype":"locality"
},
  "geometry": {"coordinates":[51.0441,35.5407],"type":"Point"}
}