{
  "type": "Feature",
  "properties": {
    "gn:admin1_code":"23",
    "gn:asciiname":"Anbarteh",
    "gn:country_code":"IR",
    "gn:dem":1634,
    "gn:feature_class":"P",
    "gn:feature_code":"PPL",
    "gn:name":"Anb\u0101rteh",
    "gn:population":0,
    "gn:timezone":"Asia/Tehran",
    "iso:country":"IR",
    "name:fas_x_preferred":[
        "\u0627\u064e\u0646\u0628\u0627\u0631\u062a\u0650\u0647"
    ],
    "name:fas_x_variant":[
        "\u0639\u0646\u0628\u0631\u062a\u0647"
    ],
    "name:ukr_x_preferred":[
        "\u0410\u043d\u0431\u0430\u0440\u0442\u0435"
    ],
    "wof:name":"Anbarteh",
    "wof:placetype":"locality"
},
  "geometry": {"coordinates":[47.81889,33.93778],"type":"Point"}
}