{
  "type": "Feature",
  "properties": {
    "gn:admin1_code":"42",
    "gn:asciiname":"Kuhabad",
    "gn:country_code":"IR",
    "gn:dem":1174,
    "gn:feature_class":"P",
    "gn:feature_code":"PPL",
    "gn:name":"K\u016bh\u0101b\u0101d",
    "gn:population":0,
    "gn:timezone":"Asia/Tehran",
    "iso:country":"IR",
    "name:ara_x_preferred":[
        "\u0643\u0648\u0647\u200c\u0623\u0628\u0627\u062f"
    ],
    "name:ceb_x_preferred":[
        "K\u016bh\u0101b\u0101d"
    ],
    "name:fas_x_preferred":[
        "\u06a9\u0648\u0647 \u0622\u0628\u0627\u062f"
    ],
    "name:fas_x_variant":[
        "K\u016bh\u0101b\u0101d",
        "\u06a9\u0648\u0647\u200c\u0622\u0628\u0627\u062f"
    ],
    "name:swe_x_preferred":[
        "K\u016bh\u0101b\u0101d"
    ],
    "wof:name":"Kuhabad",
    "wof:placetype":"locality"
},
  "geometry": {"coordinates":[60.50219,34.60267],"type":"Point"}
}