{
  "type": "Feature",
  "properties": {
    "gn:admin1_code":"37.0",
    "gn:asciiname":"Valfara",
    "gn:country_code":"IR",
    "gn:dem":18,
    "gn:feature_class":"P",
    "gn:feature_code":"PPL",
    "gn:name":"Valfar\u0101",
    "gn:population":0,
    "gn:timezone":"Asia/Tehran",
    "iso:country":"IR",
    "name:ara_x_preferred":[
        "\u0648\u0644\u0641\u0631\u0627"
    ],
    "name:ceb_x_preferred":[
        "Valfar\u0101"
    ],
    "name:fas_x_preferred":[
        "\u0648\u0644\u0641\u0631\u0627"
    ],
    "name:msa_x_preferred":[
        "Valfara"
    ],
    "name:swe_x_preferred":[
        "Valfar\u0101"
    ],
    "name:und_x_variant":[
        "Valfar\u0101"
    ],
    "wof:name":"Valfara",
    "wof:placetype":"locality"
},
  "geometry": {"coordinates":[53.98897,36.74858],"type":"Point"}
}