{
  "type": "Feature",
  "properties": {
    "gn:admin1_code":"10.0",
    "gn:asciiname":"Lashekan",
    "gn:country_code":"IR",
    "gn:dem":1050,
    "gn:feature_class":"P",
    "gn:feature_code":"PPL",
    "gn:name":"L\u0101shekan",
    "gn:population":0,
    "gn:timezone":"Asia/Tehran",
    "iso:country":"IR",
    "name:fas_x_preferred":[
        "\u0644\u0627\u0634\u06a9\u0646"
    ],
    "name:fas_x_variant":[
        "L\u0101shekan"
    ],
    "wof:name":"Lashekan",
    "wof:placetype":"locality"
},
  "geometry": {"coordinates":[46.3008,33.706],"type":"Point"}
}