{
  "type": "Feature",
  "properties": {
    "gn:admin1_code":"42",
    "gn:asciiname":"Roshtkhvar",
    "gn:country_code":"IR",
    "gn:dem":1149,
    "gn:feature_class":"P",
    "gn:feature_code":"PPLA2",
    "gn:name":"Roshtkhv\u0101r",
    "gn:population":0,
    "gn:timezone":"Asia/Tehran",
    "iso:country":"IR",
    "name:fas_x_preferred":[
        "Rashtkhv\u0101r"
    ],
    "name:fas_x_variant":[
        "Roshtkhv\u0101r",
        "\u0631\u0634\u062a\u062e\u0648\u0627\u0631",
        "R\u016bshk\u0101r",
        "Roshtehkhv\u0101r",
        "Roshkhv\u0101r",
        "Rashkhv\u0101n",
        "Roshtkh\u0101r"
    ],
    "name:und_x_variant":[
        "R\u016bshk\u0101r",
        "Rash Khar",
        "Roshtkh\u0101r",
        "Roshtehkhv\u0101r",
        "Roshkhv\u0101r",
        "Rashkhv\u0101n",
        "\u0631\u0634\u062a\u062e\u0648\u0627\u0631"
    ],
    "wof:name":"Roshtkhvar",
    "wof:placetype":"locality"
},
  "geometry": {"coordinates":[59.62481999999999,34.97512],"type":"Point"}
}