{
  "type": "Feature",
  "properties": {
    "gn:admin1_code":"29",
    "gn:asciiname":"Sebotk",
    "gn:country_code":"IR",
    "gn:dem":2062,
    "gn:feature_class":"P",
    "gn:feature_code":"PPL",
    "gn:name":"Sebotk",
    "gn:population":0,
    "gn:timezone":"Asia/Tehran",
    "iso:country":"IR",
    "name:ceb_x_preferred":[
        "Sebotk"
    ],
    "name:fas_x_preferred":[
        "\u0633\u0647 \u0628\u062a\u06a9"
    ],
    "name:fas_x_variant":[
        "\u0633\u0628\u062a\u06a9"
    ],
    "name:swe_x_preferred":[
        "Sebotk"
    ],
    "name:und_x_variant":[
        "Seh Botk"
    ],
    "wof:name":"Sebotk",
    "wof:placetype":"locality"
},
  "geometry": {"coordinates":[56.43834,31.09566],"type":"Point"}
}