{
  "type": "Feature",
  "properties": {
    "gn:admin1_code":"32",
    "gn:asciiname":"Qarah Tappeh",
    "gn:country_code":"IR",
    "gn:dem":1671,
    "gn:feature_class":"P",
    "gn:feature_code":"PPL",
    "gn:name":"Qarah Tappeh",
    "gn:population":0,
    "gn:timezone":"Asia/Tehran",
    "iso:country":"IR",
    "name:fas_x_preferred":[
        "\u0642\u0631\u0647 \u062a\u067e\u0647"
    ],
    "name:msa_x_preferred":[
        "Qarah Tappeh"
    ],
    "name:und_x_variant":[
        "Qareh Tappeh"
    ],
    "wof:name":"Qarah Tappeh",
    "wof:placetype":"locality"
},
  "geometry": {"coordinates":[47.9579,38.0428],"type":"Point"}
}