{
  "type": "Feature",
  "properties": {
    "gn:admin1_code":"42",
    "gn:asciiname":"Masihabad",
    "gn:country_code":"IR",
    "gn:dem":1142,
    "gn:feature_class":"P",
    "gn:feature_code":"PPL",
    "gn:name":"Mas\u012b\u1e29\u0101b\u0101d",
    "gn:population":0,
    "gn:timezone":"Asia/Tehran",
    "iso:country":"IR",
    "name:fas_x_preferred":[
        "\u0645\u0633\u06cc\u062d \u0622\u0628\u0627\u062f"
    ],
    "name:fas_x_variant":[
        "Mas\u012b\u1e29\u0101b\u0101d"
    ],
    "wof:name":"Masihabad",
    "wof:placetype":"locality"
},
  "geometry": {"coordinates":[58.75182,36.15517],"type":"Point"}
}