{
  "type": "Feature",
  "properties": {
    "gn:admin1_code":"4.0",
    "gn:asciiname":"Kulivnak",
    "gn:country_code":"IR",
    "gn:dem":546,
    "gn:feature_class":"P",
    "gn:feature_code":"PPL",
    "gn:name":"K\u016bl\u012bvn\u0101k",
    "gn:population":0,
    "gn:timezone":"Asia/Tehran",
    "iso:country":"IR",
    "name:fas_x_preferred":[
        "K\u016bl\u012bvn\u0101k"
    ],
    "wof:name":"Kulivnak",
    "wof:placetype":"locality"
},
  "geometry": {"coordinates":[60.70083,26.1475],"type":"Point"}
}