{
  "type": "Feature",
  "properties": {
    "iso:country":"IR",
    "name:als_x_preferred":[
        "Abhar"
    ],
    "name:ara_x_preferred":[
        "\u0623\u0628\u0647\u0631"
    ],
    "name:arz_x_preferred":[
        "\u0627\u0628\u0647\u0631"
    ],
    "name:azb_x_preferred":[
        "\u0627\u0628\u0647\u0631"
    ],
    "name:aze_x_preferred":[
        "\u018fbh\u0259r"
    ],
    "name:cat_x_preferred":[
        "Abhar"
    ],
    "name:ceb_x_preferred":[
        "Abhar"
    ],
    "name:ell_x_preferred":[
        "\u0391\u03bc\u03c0\u03c7\u03ac\u03c1"
    ],
    "name:eng_x_preferred":[
        "Abhar"
    ],
    "name:fas_x_preferred":[
        "\u0627\u0628\u0647\u0631"
    ],
    "name:fas_x_variant":[
        "\u0627\u0628\u0631",
        "\u0627\u064e\u0628\u062e\u064e\u0631"
    ],
    "name:fra_x_preferred":[
        "Abhar"
    ],
    "name:gsw_x_preferred":[
        "Abhar"
    ],
    "name:heb_x_preferred":[
        "\u05d0\u05d1\u05d4\u05e8"
    ],
    "name:hin_x_preferred":[
        "\u0905\u092c\u0939\u093e\u0930"
    ],
    "name:ind_x_preferred":[
        "Abhar"
    ],
    "name:ita_x_preferred":[
        "Abhar"
    ],
    "name:jpn_x_preferred":[
        "\u30a2\u30d6\u30cf\u30eb"
    ],
    "name:kaz_x_preferred":[
        "\u0410\u0431\u0445\u0430\u0440"
    ],
    "name:mlg_x_preferred":[
        "Abhar"
    ],
    "name:nld_x_preferred":[
        "Abhar"
    ],
    "name:pnb_x_preferred":[
        "\u0627\u0628\u06c1\u0627\u0631"
    ],
    "name:pol_x_preferred":[
        "Abhar"
    ],
    "name:ron_x_preferred":[
        "Abhar"
    ],
    "name:rup_x_preferred":[
        "Abhar"
    ],
    "name:rus_x_preferred":[
        "\u0410\u0431\u0445\u0430\u0440"
    ],
    "name:swe_x_preferred":[
        "Abhar"
    ],
    "name:tgk_x_preferred":[
        "\u0410\u0431\u04b3\u0430\u0440"
    ],
    "name:tur_x_preferred":[
        "Ebher"
    ],
    "name:tur_x_variant":[
        "Abher"
    ],
    "name:ukr_x_preferred":[
        "\u0410\u0431\u0445\u0430\u0440"
    ],
    "name:unk_x_variant":[
        "Abhar"
    ],
    "name:urd_x_preferred":[
        "\u0627\u0628\u06c1\u0631"
    ],
    "name:urd_x_variant":[
        "\u0627\u0628\u0647\u0631"
    ],
    "name:zho_x_preferred":[
        "\u963f\u535c\u54c8\u723e"
    ],
    "qs:gn_country":"IR",
    "qs:gn_fcode":"PPL",
    "qs:gn_pop":69889,
    "qs:name":"Abkhar",
    "qs:name_adm0":"Iran",
    "qs:name_adm1":"Zanjan",
    "qs:photos":0,
    "qs:photos_1k":0,
    "qs:photos_9k":1,
    "qs:photos_9r":1,
    "qs:photos_all":3,
    "qs:photos_sr":0,
    "qs:placetype":"Town",
    "qs:pop_sr":"8",
    "qs:woe_adm0":23424851,
    "wd:wordcount":59,
    "wof:name":"Abkhar",
    "wof:placetype":"locality",
    "wof:population":69889
},
  "geometry": {"coordinates":[49.218,36.1468],"type":"Point"}
}