{
  "type": "Feature",
  "properties": {
    "gn:admin1_code":"4.0",
    "gn:asciiname":"Deh-e Deh-e Hajji Hoseyn",
    "gn:country_code":"IR",
    "gn:dem":487,
    "gn:feature_class":"P",
    "gn:feature_code":"PPL",
    "gn:name":"Deh-e Deh-e \u1e28\u0101jj\u012b \u1e28oseyn",
    "gn:population":0,
    "gn:timezone":"Asia/Tehran",
    "iso:country":"IR",
    "name:fas_x_preferred":[
        "Deh-e Deh-e \u1e28\u0101jj\u012b \u1e28oseyn"
    ],
    "wof:name":"Deh-e Deh-e Hajji Hoseyn",
    "wof:placetype":"locality"
},
  "geometry": {"coordinates":[61.56667,30.85],"type":"Point"}
}