{
  "type": "Feature",
  "properties": {
    "gn:admin1_code":"5.0",
    "gn:asciiname":"Sadat",
    "gn:country_code":"IR",
    "gn:dem":1087,
    "gn:feature_class":"P",
    "gn:feature_code":"PPL",
    "gn:name":"S\u0101d\u0101t",
    "gn:population":0,
    "gn:timezone":"Asia/Tehran",
    "iso:country":"IR",
    "name:fas_x_preferred":[
        "S\u0101d\u0101t"
    ],
    "name:fas_x_variant":[
        "\u0633\u0627\u062f\u0627\u062a"
    ],
    "name:fra_x_preferred":[
        "Sadat"
    ],
    "name:und_x_variant":[
        "\u0633\u0627\u062f\u0627\u062a"
    ],
    "wof:name":"Sadat",
    "wof:placetype":"locality"
},
  "geometry": {"coordinates":[51.00556,30.44506],"type":"Point"}
}