{
  "type": "Feature",
  "properties": {
    "gn:admin1_code":"8.0",
    "gn:asciiname":"Luchak",
    "gn:country_code":"IR",
    "gn:dem":1121,
    "gn:feature_class":"P",
    "gn:feature_code":"PPL",
    "gn:name":"L\u016bch\u0101k",
    "gn:population":0,
    "gn:timezone":"Asia/Tehran",
    "iso:country":"IR",
    "name:fas_x_preferred":[
        "L\u016bch\u0101k"
    ],
    "name:fas_x_variant":[
        "\u0644\u0648\u0686\u0627\u06a9"
    ],
    "name:und_x_variant":[
        "\u0644\u0648\u0686\u0627\u06a9"
    ],
    "wof:name":"Luchak",
    "wof:placetype":"locality"
},
  "geometry": {"coordinates":[49.6981,36.8398],"type":"Point"}
}