{
  "type": "Feature",
  "properties": {
    "gn:admin1_code":"37",
    "gn:asciiname":"Nowdijeh",
    "gn:country_code":"IR",
    "gn:dem":13,
    "gn:feature_class":"P",
    "gn:feature_code":"PPL",
    "gn:name":"Nowd\u012bjeh",
    "gn:population":0,
    "gn:timezone":"Asia/Tehran",
    "iso:country":"IR",
    "name:ara_x_preferred":[
        "\u0646\u0648\u062f\u064a\u062c\u0647"
    ],
    "name:fas_x_preferred":[
        "Nowd\u012bjeh"
    ],
    "name:fas_x_variant":[
        "\u0646\u0648\u062f\u064a\u062c\u0647",
        "\u0646\u0648\u062f\u06cc\u062c\u0647"
    ],
    "name:msa_x_preferred":[
        "Nowdijeh"
    ],
    "name:und_x_variant":[
        "\u0646\u0648\u062f\u064a\u062c\u0647"
    ],
    "wof:name":"Nowdijeh",
    "wof:placetype":"locality"
},
  "geometry": {"coordinates":[54.27398,36.83772],"type":"Point"}
}