{
  "type": "Feature",
  "properties": {
    "gn:admin1_code":"1",
    "gn:asciiname":"Kharmanyeri",
    "gn:country_code":"IR",
    "gn:dem":1407,
    "gn:feature_class":"P",
    "gn:feature_code":"PPL",
    "gn:name":"Kharmanyer\u012b",
    "gn:population":0,
    "gn:timezone":"Asia/Tehran",
    "iso:country":"IR",
    "name:azb_x_preferred":[
        "\u062e\u0627\u0631\u0645\u0627\u0646 \u06cc\u0626\u0631\u06cc"
    ],
    "name:aze_x_preferred":[
        "Xarmanyeri"
    ],
    "name:ceb_x_preferred":[
        "Kharmanyer\u012b"
    ],
    "name:fas_x_preferred":[
        "\u062e\u064e\u0631\u0645\u064e\u0646\u064a\u0650\u0631\u06cc"
    ],
    "name:fas_x_variant":[
        "\u062e\u0631\u0645\u0646 \u064a\u0631\u06cc",
        "Kharmanyer\u012b",
        "\u062e\u0631\u0645\u0646\u200c\u06cc\u0631\u06cc"
    ],
    "name:msa_x_preferred":[
        "Kharmanyeri"
    ],
    "name:swe_x_preferred":[
        "Kharmanyer\u012b"
    ],
    "wof:name":"Kharmanyeri",
    "wof:placetype":"locality"
},
  "geometry": {"coordinates":[44.4516,39.4057],"type":"Point"}
}