{
  "type": "Feature",
  "properties": {
    "gn:admin1_code":"23",
    "gn:asciiname":"Chah Zowlfaqar",
    "gn:country_code":"IR",
    "gn:dem":1159,
    "gn:feature_class":"P",
    "gn:feature_code":"PPL",
    "gn:name":"Ch\u0101h Z\u0304owlfaq\u0101r",
    "gn:population":0,
    "gn:timezone":"Asia/Tehran",
    "iso:country":"IR",
    "name:fas_x_preferred":[
        "\u0686\u0627\u0647 \u0630\u0648\u0627\u0644\u0641\u0642\u0627\u0631"
    ],
    "name:und_x_variant":[
        "Ch\u0101h Z\u0304owlfaq\u0101r"
    ],
    "wof:name":"Chah Zowlfaqar",
    "wof:placetype":"locality"
},
  "geometry": {"coordinates":[47.889,33.6209],"type":"Point"}
}