{
  "type": "Feature",
  "properties": {
    "gn:admin1_code":"42",
    "gn:asciiname":"Malekabad",
    "gn:country_code":"IR",
    "gn:dem":1372,
    "gn:feature_class":"P",
    "gn:feature_code":"PPL",
    "gn:name":"Malek\u0101b\u0101d",
    "gn:population":0,
    "gn:timezone":"Asia/Tehran",
    "iso:country":"IR",
    "name:fas_x_preferred":[
        "Malek\u0101b\u0101d"
    ],
    "name:fas_x_variant":[
        "\u0645\u0644\u06a9 \u0622\u0628\u0627\u062f"
    ],
    "name:und_x_variant":[
        "\u0645\u0644\u06a9 \u0622\u0628\u0627\u062f"
    ],
    "wof:name":"Malekabad",
    "wof:placetype":"locality"
},
  "geometry": {"coordinates":[59.27412,35.29078],"type":"Point"}
}