{
  "type": "Feature",
  "properties": {
    "gn:admin1_code":"4",
    "gn:asciiname":"Hajjiabad-e Bala",
    "gn:country_code":"IR",
    "gn:dem":1611,
    "gn:feature_class":"P",
    "gn:feature_code":"PPL",
    "gn:name":"\u1e28\u0101jj\u012b\u0101b\u0101d-e B\u0101l\u0101",
    "gn:population":0,
    "gn:timezone":"Asia/Tehran",
    "iso:country":"IR",
    "name:fas_x_preferred":[
        "\u062d\u0627\u062c\u06cc \u0622\u0628\u0627\u062f \u0628\u0627\u0644\u0627"
    ],
    "name:fas_x_variant":[
        "\u1e28\u0101jj\u012b\u0101b\u0101d-e B\u0101l\u0101",
        "\u062d\u0627\u062c\u06cc\u200c\u0622\u0628\u0627\u062f \u0628\u0627\u0644\u0627"
    ],
    "wof:name":"Hajjiabad-e Bala",
    "wof:placetype":"locality"
},
  "geometry": {"coordinates":[60.53447,28.78839],"type":"Point"}
}