{
  "type": "Feature",
  "properties": {
    "gn:admin1_code":"13",
    "gn:asciiname":"Qal`eh Badri",
    "gn:country_code":"IR",
    "gn:dem":569,
    "gn:feature_class":"P",
    "gn:feature_code":"PPL",
    "gn:name":"Qal\u2018eh Badr\u012b",
    "gn:population":0,
    "gn:timezone":"Asia/Tehran",
    "iso:country":"IR",
    "name:fas_x_preferred":[
        "\u0642\u0644\u0639\u0647 \u0628\u062f\u0631\u06cc"
    ],
    "name:fas_x_variant":[
        "Qal\u2018eh Badr\u012b"
    ],
    "wof:name":"Qal`eh Badri",
    "wof:placetype":"locality"
},
  "geometry": {"coordinates":[45.84899,34.58415],"type":"Point"}
}