{
  "type": "Feature",
  "properties": {
    "gn:admin1_code":"29.0",
    "gn:asciiname":"`Aliabad",
    "gn:country_code":"IR",
    "gn:dem":1690,
    "gn:feature_class":"P",
    "gn:feature_code":"PPL",
    "gn:name":"\u2018Al\u012b\u0101b\u0101d",
    "gn:population":0,
    "gn:timezone":"Asia/Tehran",
    "iso:country":"IR",
    "name:fas_x_preferred":[
        "\u2018Al\u012b\u0101b\u0101d-e B\u0101l\u0101"
    ],
    "name:fas_x_variant":[
        "\u2018Al\u012b\u0101b\u0101d",
        "\u0639\u0644\u06cc \u0622\u0628\u0627\u062f",
        "\u2018Al\u012b\u0101b\u0101d-e \u2018Oly\u0101"
    ],
    "name:und_x_variant":[
        "\u2018Al\u012b\u0101b\u0101d",
        "\u2018Al\u012b\u0101b\u0101d-e \u2018Oly\u0101",
        "\u0639\u0644\u06cc \u0622\u0628\u0627\u062f"
    ],
    "wof:name":"`Aliabad",
    "wof:placetype":"locality"
},
  "geometry": {"coordinates":[56.64506,30.68593],"type":"Point"}
}