{
  "type": "Feature",
  "properties": {
    "gn:admin1_code":"5.0",
    "gn:asciiname":"Gardekan",
    "gn:country_code":"IR",
    "gn:dem":1577,
    "gn:feature_class":"P",
    "gn:feature_code":"PPL",
    "gn:name":"Gardek\u0101n",
    "gn:population":0,
    "gn:timezone":"Asia/Tehran",
    "iso:country":"IR",
    "name:ara_x_preferred":[
        "\u063a\u0631\u062f\u06a9\u0627\u0646"
    ],
    "name:ceb_x_preferred":[
        "Gardek\u0101n"
    ],
    "name:fas_x_preferred":[
        "Gardek\u0101n"
    ],
    "name:fas_x_variant":[
        "\u06af\u0631\u062f\u06a9\u0627\u0646"
    ],
    "name:swe_x_preferred":[
        "Gardek\u0101n"
    ],
    "wof:name":"Gardekan",
    "wof:placetype":"locality"
},
  "geometry": {"coordinates":[50.89569,30.91803],"type":"Point"}
}