{
  "type": "Feature",
  "properties": {
    "gn:admin1_code":"29.0",
    "gn:asciiname":"Shaltukabad",
    "gn:country_code":"IR",
    "gn:dem":710,
    "gn:feature_class":"P",
    "gn:feature_code":"PPL",
    "gn:name":"Shalt\u016bk\u0101b\u0101d",
    "gn:population":0,
    "gn:timezone":"Asia/Tehran",
    "iso:country":"IR",
    "name:ceb_x_preferred":[
        "Shalt\u016bk\u0101b\u0101d"
    ],
    "name:fas_x_preferred":[
        "\u0634\u0644\u062a\u0648\u06a9 \u0622\u0628\u0627\u062f \u06af\u0646\u0628\u06af\u06cc"
    ],
    "name:fas_x_variant":[
        "Shalt\u016bk\u0101b\u0101d",
        "Shalt\u016bk\u0101b\u0101d-e Gonbag\u012b",
        "\u0634\u0644\u062a\u0648\u06a9 \u0622\u0628\u0627\u062f",
        "\u0634\u0644\u062a\u0648\u06a9\u200c\u0622\u0628\u0627\u062f"
    ],
    "name:swe_x_preferred":[
        "Shalt\u016bk\u0101b\u0101d"
    ],
    "wof:name":"Shaltukabad",
    "wof:placetype":"locality"
},
  "geometry": {"coordinates":[58.86,28.7476],"type":"Point"}
}