{
  "type": "Feature",
  "properties": {
    "gn:admin1_code":"40",
    "gn:asciiname":"Jalaliyeh",
    "gn:country_code":"IR",
    "gn:dem":1470,
    "gn:feature_class":"P",
    "gn:feature_code":"PPL",
    "gn:name":"Jal\u0101l\u012byeh",
    "gn:population":0,
    "gn:timezone":"Asia/Tehran",
    "iso:country":"IR",
    "name:fas_x_preferred":[
        "\u062c\u064e\u0644\u0627\u0644\u064a\u0650\u0651\u0647"
    ],
    "name:fas_x_variant":[
        "Jal\u0101l\u012byeh"
    ],
    "wof:name":"Jalaliyeh",
    "wof:placetype":"locality"
},
  "geometry": {"coordinates":[53.64361,31.27861],"type":"Point"}
}