{
  "type": "Feature",
  "properties": {
    "gn:admin1_code":"13",
    "gn:asciiname":"Vazmeleh",
    "gn:country_code":"IR",
    "gn:dem":1327,
    "gn:feature_class":"P",
    "gn:feature_code":"PPL",
    "gn:name":"Vazmeleh",
    "gn:population":0,
    "gn:timezone":"Asia/Tehran",
    "iso:country":"IR",
    "name:fas_x_preferred":[
        "\u0648\u0632\u0645\u0644\u0647"
    ],
    "wof:name":"Vazmeleh",
    "wof:placetype":"locality"
},
  "geometry": {"coordinates":[46.8747,34.6195],"type":"Point"}
}