{
  "type": "Feature",
  "properties": {
    "gn:admin1_code":"42.0",
    "gn:asciiname":"Kondeh Sukhteh",
    "gn:country_code":"IR",
    "gn:dem":569,
    "gn:feature_class":"P",
    "gn:feature_code":"PPL",
    "gn:name":"Kondeh S\u016bkhteh",
    "gn:population":0,
    "gn:timezone":"Asia/Tehran",
    "iso:country":"IR",
    "name:fas_x_preferred":[
        "\u06a9\u0646\u062f\u0647 \u0633\u0648\u062e\u062a\u0647"
    ],
    "name:fas_x_variant":[
        "Kondeh S\u016bkhteh"
    ],
    "wof:name":"Kondeh Sukhteh",
    "wof:placetype":"locality"
},
  "geometry": {"coordinates":[61.18594,35.38156],"type":"Point"}
}