{
  "type": "Feature",
  "properties": {
    "gn:admin1_code":"5.0",
    "gn:asciiname":"Chah Maqer",
    "gn:country_code":"IR",
    "gn:dem":1956,
    "gn:feature_class":"P",
    "gn:feature_code":"PPL",
    "gn:name":"Ch\u0101h M\u0101qer",
    "gn:population":0,
    "gn:timezone":"Asia/Tehran",
    "iso:country":"IR",
    "name:fas_x_preferred":[
        "\u0686\u0627\u0647 \u0645\u0627\u0642\u0631"
    ],
    "name:und_x_variant":[
        "Ch\u0101h M\u0101qer"
    ],
    "wof:name":"Chah Maqer",
    "wof:placetype":"locality"
},
  "geometry": {"coordinates":[50.09949,31.05092],"type":"Point"}
}