{
  "type": "Feature",
  "properties": {
    "gn:admin1_code":"23",
    "gn:asciiname":"Cham-e Latur",
    "gn:country_code":"IR",
    "gn:dem":716,
    "gn:feature_class":"P",
    "gn:feature_code":"PPL",
    "gn:name":"Cham-e La\u0163\u016br",
    "gn:population":0,
    "gn:timezone":"Asia/Tehran",
    "iso:country":"IR",
    "name:ceb_x_preferred":[
        "Cham-e La\u0163\u016br"
    ],
    "name:fas_x_preferred":[
        "\u0686\u0645 \u0644\u0637\u0648\u0631"
    ],
    "name:fas_x_variant":[
        "Cham-e La\u0163\u016br",
        "\u0686\u0645 \u0644\u062a\u0648\u0631"
    ],
    "name:swe_x_preferred":[
        "Cham-e La\u0163\u016br"
    ],
    "name:und_x_variant":[
        "Cham Lat\u016br",
        "Cham-e La\u0163\u016br"
    ],
    "wof:name":"Cham-e Latur",
    "wof:placetype":"locality"
},
  "geometry": {"coordinates":[46.9486,33.4648],"type":"Point"}
}