{
  "type": "Feature",
  "properties": {
    "gn:admin1_code":"26.0",
    "gn:asciiname":"Fararat",
    "gn:country_code":"IR",
    "gn:dem":1101,
    "gn:feature_class":"P",
    "gn:feature_code":"PPL",
    "gn:name":"Far\u0101rat",
    "gn:population":0,
    "gn:timezone":"Asia/Tehran",
    "iso:country":"IR",
    "name:fas_x_preferred":[
        "\u0641\u0631\u0627\u0631\u062a"
    ],
    "name:fas_x_variant":[
        "Far\u0101rat"
    ],
    "wof:name":"Fararat",
    "wof:placetype":"locality"
},
  "geometry": {"coordinates":[51.0261,35.5758],"type":"Point"}
}