{
  "type": "Feature",
  "properties": {
    "gn:admin1_code":"42.0",
    "gn:asciiname":"Chah Hajji Hoseyn",
    "gn:country_code":"IR",
    "gn:dem":1451,
    "gn:feature_class":"P",
    "gn:feature_code":"PPL",
    "gn:name":"Ch\u0101h \u1e28\u0101jj\u012b \u1e28oseyn",
    "gn:population":0,
    "gn:timezone":"Asia/Tehran",
    "iso:country":"IR",
    "name:fas_x_preferred":[
        "\u0686\u0627\u0647 \u062d\u0627\u062c\u06cc \u062d\u0633\u06cc\u0646"
    ],
    "name:und_x_variant":[
        "Ch\u0101h \u1e28\u0101jj\u012b \u1e28oseyn"
    ],
    "wof:name":"Chah Hajji Hoseyn",
    "wof:placetype":"locality"
},
  "geometry": {"coordinates":[59.70776,35.24736],"type":"Point"}
}