{
  "type": "Feature",
  "properties": {
    "gn:admin1_code":"16",
    "gn:asciiname":"Kuaneh",
    "gn:country_code":"IR",
    "gn:dem":1442,
    "gn:feature_class":"P",
    "gn:feature_code":"PPL",
    "gn:name":"K\u016b\u0101neh",
    "gn:population":0,
    "gn:timezone":"Asia/Tehran",
    "iso:country":"IR",
    "name:fas_x_preferred":[
        "\u0643\u0648\u0627\u0646\u0650\u0647"
    ],
    "name:fas_x_variant":[
        "\u06a9\u0648\u0627\u0646\u0647",
        "K\u016b\u0101neh"
    ],
    "wof:name":"Kuaneh",
    "wof:placetype":"locality"
},
  "geometry": {"coordinates":[46.9837,34.9723],"type":"Point"}
}