{
  "type": "Feature",
  "properties": {
    "gn:admin1_code":"33",
    "gn:asciiname":"Sir-e `Olya",
    "gn:country_code":"IR",
    "gn:dem":1923,
    "gn:feature_class":"P",
    "gn:feature_code":"PPL",
    "gn:name":"S\u012br-e \u2018Oly\u0101",
    "gn:population":0,
    "gn:timezone":"Asia/Tehran",
    "iso:country":"IR",
    "name:fas_x_preferred":[
        "\u0633\u06cc\u0631 \u0628\u0627\u0644\u0627"
    ],
    "name:fas_x_variant":[
        "\u0633\u06cc\u0631 \u0639\u0644\u06cc\u0627"
    ],
    "name:und_x_variant":[
        "S\u012br-e \u2018Oly\u0101",
        "S\u012br-e B\u0101l\u0101"
    ],
    "wof:name":"Sir-e `Olya",
    "wof:placetype":"locality"
},
  "geometry": {"coordinates":[46.70305,37.60898],"type":"Point"}
}