{
  "type": "Feature",
  "properties": {
    "gn:admin1_code":"33",
    "gn:asciiname":"Tabaqlu",
    "gn:country_code":"IR",
    "gn:dem":1874,
    "gn:feature_class":"P",
    "gn:feature_code":"PPL",
    "gn:name":"Tabaql\u016b",
    "gn:population":0,
    "gn:timezone":"Asia/Tehran",
    "iso:country":"IR",
    "name:fas_x_preferred":[
        "\u0637\u0628\u0642\u0644\u0648"
    ],
    "name:fas_x_variant":[
        "\u0162abaql\u016b",
        "\u062a\u0628\u0642\u0644\u0648"
    ],
    "name:und_x_variant":[
        "Tabaql\u016b"
    ],
    "wof:name":"Tabaqlu",
    "wof:placetype":"locality"
},
  "geometry": {"coordinates":[46.88056,37.64781],"type":"Point"}
}