{
  "type": "Feature",
  "properties": {
    "gn:admin1_code":"42.0",
    "gn:asciiname":"Jannatabad",
    "gn:country_code":"IR",
    "gn:dem":692,
    "gn:feature_class":"P",
    "gn:feature_code":"PPL",
    "gn:name":"Jannat\u0101b\u0101d",
    "gn:population":0,
    "gn:timezone":"Asia/Tehran",
    "iso:country":"IR",
    "name:fas_x_preferred":[
        "Jannat\u0101b\u0101d"
    ],
    "name:fas_x_variant":[
        "\u062c\u0646\u062a \u0622\u0628\u0627\u062f"
    ],
    "name:und_x_variant":[
        "\u062c\u0646\u062a \u0622\u0628\u0627\u062f"
    ],
    "wof:name":"Jannatabad",
    "wof:placetype":"locality"
},
  "geometry": {"coordinates":[61.14104,35.59827999999999],"type":"Point"}
}