{
  "type": "Feature",
  "properties": {
    "gn:admin1_code":"15",
    "gn:asciiname":"Morghak",
    "gn:country_code":"IR",
    "gn:dem":889,
    "gn:feature_class":"P",
    "gn:feature_code":"PPL",
    "gn:name":"Morghak",
    "gn:population":0,
    "gn:timezone":"Asia/Tehran",
    "iso:country":"IR",
    "name:fas_x_preferred":[
        "\u0645\u0631\u063a\u06a9"
    ],
    "wof:name":"Morghak",
    "wof:placetype":"locality"
},
  "geometry": {"coordinates":[50.45904,31.65607],"type":"Point"}
}