{
  "type": "Feature",
  "properties": {
    "gn:admin1_code":"4.0",
    "gn:asciiname":"Kafarzeh",
    "gn:country_code":"IR",
    "gn:dem":1339,
    "gn:feature_class":"P",
    "gn:feature_code":"PPL",
    "gn:name":"Kaf\u0101rzeh",
    "gn:population":0,
    "gn:timezone":"Asia/Tehran",
    "iso:country":"IR",
    "name:fas_x_preferred":[
        "Kaf\u0101rzeh"
    ],
    "wof:name":"Kafarzeh",
    "wof:placetype":"locality"
},
  "geometry": {"coordinates":[60.38333000000001,28.31667],"type":"Point"}
}