{
  "type": "Feature",
  "properties": {
    "gn:admin1_code":"9",
    "gn:asciiname":"Emamzadeh Qasem",
    "gn:country_code":"IR",
    "gn:dem":1761,
    "gn:feature_class":"P",
    "gn:feature_code":"PPL",
    "gn:name":"Em\u0101mz\u0101deh Q\u0101sem",
    "gn:population":0,
    "gn:timezone":"Asia/Tehran",
    "iso:country":"IR",
    "name:fas_x_preferred":[
        "\u0627\u0645\u0627\u0645\u0632\u0627\u062f\u0647 \u0642\u0627\u0633\u0645"
    ],
    "name:fas_x_variant":[
        "Em\u0101mz\u0101deh Q\u0101sem"
    ],
    "wof:name":"Emamzadeh Qasem",
    "wof:placetype":"locality"
},
  "geometry": {"coordinates":[49.04054,35.30767],"type":"Point"}
}