{
  "type": "Feature",
  "properties": {
    "gn:admin1_code":"16",
    "gn:asciiname":"Tazehabad",
    "gn:country_code":"IR",
    "gn:dem":1569,
    "gn:feature_class":"P",
    "gn:feature_code":"PPL",
    "gn:name":"T\u0101zeh\u0101b\u0101d",
    "gn:population":0,
    "gn:timezone":"Asia/Tehran",
    "iso:country":"IR",
    "name:fas_x_preferred":[
        "\u062a\u0627\u0632\u0650\u0647\u0627\u0628\u0627\u062f\u0650 \u0642\u064e\u0644\u0639\u0650\u0647 \u062c\u064f\u0642"
    ],
    "name:fas_x_variant":[
        "\u062a\u0627\u0632\u0650\u0647 \u062f\u0650\u0647",
        "T\u0101zeh\u0101b\u0101d-e Qal\u2018eh Joq",
        "T\u0101zeh\u0101b\u0101d",
        "\u062a\u0627\u0632\u0647 \u0622\u0628\u0627\u062f",
        "\u062a\u0627\u0632\u0647 \u0622\u0628\u0627\u062f \u0642\u0644\u0639\u0647 \u062c\u0648\u0642"
    ],
    "name:und_x_variant":[
        "T\u0101zeh Deh",
        "\u062a\u0627\u0632\u0647 \u0622\u0628\u0627\u062f",
        "T\u0101zeh\u0101b\u0101d Qal\u2018eh J\u016bq"
    ],
    "wof:name":"Tazehabad",
    "wof:placetype":"locality"
},
  "geometry": {"coordinates":[46.62,35.4289],"type":"Point"}
}