{
  "type": "Feature",
  "properties": {
    "gn:admin1_code":"37.0",
    "gn:asciiname":"Shahid Raja'i",
    "gn:country_code":"IR",
    "gn:dem":41,
    "gn:feature_class":"P",
    "gn:feature_code":"PPLL",
    "gn:name":"Shah\u012bd Raj\u0101\u2019\u012b",
    "gn:population":0,
    "gn:timezone":"Asia/Tehran",
    "iso:country":"IR",
    "name:fas_x_preferred":[
        "\u0634\u0647\u06cc\u062f \u0631\u062c\u0627\u0626\u06cc"
    ],
    "name:fas_x_variant":[
        "\u0627\u0632\u062f\u0627\u0631\u06cc"
    ],
    "name:und_x_variant":[
        "Shah\u012bd Raj\u0101\u2019\u012b",
        "Azd\u0101r\u012b"
    ],
    "wof:name":"Shahid Raja'i",
    "wof:placetype":"locality"
},
  "geometry": {"coordinates":[55.0136,37.0189],"type":"Point"}
}