{
  "type": "Feature",
  "properties": {
    "gn:admin1_code":"13",
    "gn:asciiname":"Dar Derafsh-e Seyyed Karim",
    "gn:country_code":"IR",
    "gn:dem":1333,
    "gn:feature_class":"P",
    "gn:feature_code":"PPL",
    "gn:name":"D\u0101r Derafsh-e Seyyed Kar\u012bm",
    "gn:population":0,
    "gn:timezone":"Asia/Tehran",
    "iso:country":"IR",
    "name:fas_x_preferred":[
        "D\u0101r Derafsh-e Seyyed Kar\u012bm"
    ],
    "wof:name":"Dar Derafsh-e Seyyed Karim",
    "wof:placetype":"locality"
},
  "geometry": {"coordinates":[46.75,34.51667],"type":"Point"}
}