{
  "type": "Feature",
  "properties": {
    "gn:admin1_code":"3",
    "gn:asciiname":"Kalvari",
    "gn:country_code":"IR",
    "gn:dem":1467,
    "gn:feature_class":"P",
    "gn:feature_code":"PPL",
    "gn:name":"Kalv\u0101r\u012b",
    "gn:population":0,
    "gn:timezone":"Asia/Tehran",
    "iso:country":"IR",
    "name:fas_x_preferred":[
        "Kalv\u0101r\u012b"
    ],
    "name:fas_x_variant":[
        "\u0643\u0644\u0648\u0627\u0631\u06cc"
    ],
    "name:und_x_variant":[
        "\u0643\u0644\u0648\u0627\u0631\u06cc"
    ],
    "wof:name":"Kalvari",
    "wof:placetype":"locality"
},
  "geometry": {"coordinates":[50.57771,31.59403],"type":"Point"}
}