{
  "type": "Feature",
  "properties": {
    "gn:admin1_code":"35.0",
    "gn:asciiname":"Lat Kumeh",
    "gn:country_code":"IR",
    "gn:dem":1225,
    "gn:feature_class":"P",
    "gn:feature_code":"PPL",
    "gn:name":"Lat K\u016bmeh",
    "gn:population":0,
    "gn:timezone":"Asia/Tehran",
    "iso:country":"IR",
    "name:ceb_x_preferred":[
        "Lat K\u016bmeh"
    ],
    "name:fas_x_preferred":[
        "\u0644\u062a \u06a9\u0648\u0645\u0647"
    ],
    "name:fas_x_variant":[
        "Lat K\u016bmeh",
        "\u0644\u062a\u200c\u06a9\u0648\u0645\u0647"
    ],
    "name:swe_x_preferred":[
        "Lat K\u016bmeh"
    ],
    "name:und_x_variant":[
        "Lat Kohneh"
    ],
    "name:urd_x_preferred":[
        "\u0644\u062a \u06a9\u0648\u0645\u06c1"
    ],
    "wof:name":"Lat Kumeh",
    "wof:placetype":"locality"
},
  "geometry": {"coordinates":[54.01455,36.63019],"type":"Point"}
}