{
  "type": "Feature",
  "properties": {
    "gn:admin1_code":"15",
    "gn:asciiname":"Kowsar",
    "gn:country_code":"IR",
    "gn:dem":440,
    "gn:feature_class":"P",
    "gn:feature_code":"PPL",
    "gn:name":"Kows\u0304ar",
    "gn:population":0,
    "gn:timezone":"Asia/Tehran",
    "iso:country":"IR",
    "name:ces_x_preferred":[
        "Kosar"
    ],
    "name:fas_x_preferred":[
        "\u06a9\u0648\u062b\u0631"
    ],
    "name:fas_x_variant":[
        "Kows\u0304ar"
    ],
    "name:fra_x_preferred":[
        "Kowsar"
    ],
    "name:pnb_x_preferred":[
        "\u06a9\u0648\u062b\u0631"
    ],
    "name:sco_x_preferred":[
        "Kowsar"
    ],
    "wof:name":"Kowsar",
    "wof:placetype":"locality"
},
  "geometry": {"coordinates":[48.5102,32.7336],"type":"Point"}
}