{
  "type": "Feature",
  "properties": {
    "gn:admin1_code":"11",
    "gn:asciiname":"Siru'iyeh",
    "gn:country_code":"IR",
    "gn:dem":845,
    "gn:feature_class":"P",
    "gn:feature_code":"PPL",
    "gn:name":"S\u012br\u016b\u2019\u012byeh",
    "gn:population":0,
    "gn:timezone":"Asia/Tehran",
    "iso:country":"IR",
    "name:fas_x_preferred":[
        "\u0633\u064a\u0631\u0648\u0626\u064a\u0651\u0647"
    ],
    "name:fas_x_variant":[
        "\u0633\u064a\u0631\u064a\u0626\u064a\u0650\u0651\u0647",
        "S\u012br\u016b\u2019\u012byeh"
    ],
    "name:und_x_variant":[
        "Siroo\u2019eyeh",
        "S\u012bry\u2019\u012byeh"
    ],
    "wof:name":"Siru'iyeh",
    "wof:placetype":"locality"
},
  "geometry": {"coordinates":[55.9808,28.1737],"type":"Point"}
}