{
  "type": "Feature",
  "properties": {
    "gn:admin1_code":"5",
    "gn:asciiname":"Gol Zeyni",
    "gn:country_code":"IR",
    "gn:dem":1025,
    "gn:feature_class":"P",
    "gn:feature_code":"PPL",
    "gn:name":"Gol Zeyn\u012b",
    "gn:population":0,
    "gn:timezone":"Asia/Tehran",
    "iso:country":"IR",
    "name:fas_x_preferred":[
        "Gol Zadan\u012b"
    ],
    "name:fas_x_variant":[
        "\u06af\u0644 \u0632\u062f\u0646\u06cc",
        "\u06af\u0644 \u0632\u06cc\u0646\u06cc"
    ],
    "name:und_x_variant":[
        "Gol Zeyn\u012b"
    ],
    "wof:name":"Gol Zeyni",
    "wof:placetype":"locality"
},
  "geometry": {"coordinates":[50.54147,31.08047],"type":"Point"}
}