{
  "type": "Feature",
  "properties": {
    "gn:admin1_code":"23",
    "gn:asciiname":"Pashmaleh",
    "gn:country_code":"IR",
    "gn:dem":1509,
    "gn:feature_class":"P",
    "gn:feature_code":"PPL",
    "gn:name":"Pashmaleh",
    "gn:population":0,
    "gn:timezone":"Asia/Tehran",
    "iso:country":"IR",
    "name:fas_x_preferred":[
        "\u067e\u064e\u0634\u0645\u064e\u0644\u0650\u0647"
    ],
    "wof:name":"Pashmaleh",
    "wof:placetype":"locality"
},
  "geometry": {"coordinates":[47.53333,34.13333],"type":"Point"}
}