{
  "type": "Feature",
  "properties": {
    "gn:admin1_code":"40",
    "gn:asciiname":"Dorond-e `Olya",
    "gn:country_code":"IR",
    "gn:dem":2421,
    "gn:feature_class":"P",
    "gn:feature_code":"PPL",
    "gn:name":"Dorond-e \u2018Oly\u0101",
    "gn:population":0,
    "gn:timezone":"Asia/Tehran",
    "iso:country":"IR",
    "name:ara_x_preferred":[
        "\u062f\u0631\u0646\u062f \u0627\u0644\u0639\u0644\u064a\u0627"
    ],
    "name:fas_x_preferred":[
        "\u062f\u064f\u0631\u064f\u0646\u062f"
    ],
    "name:fas_x_variant":[
        "Dorond-e \u2018Oly\u0101",
        "\u062f\u0631\u0646\u062f \u0639\u0644\u06cc\u0627"
    ],
    "name:und_x_variant":[
        "Dorond"
    ],
    "wof:name":"Dorond-e `Olya",
    "wof:placetype":"locality"
},
  "geometry": {"coordinates":[55.89222,31.80937],"type":"Point"}
}