{
  "type": "Feature",
  "properties": {
    "gn:admin1_code":"8",
    "gn:asciiname":"Pir Poshteh",
    "gn:country_code":"IR",
    "gn:dem":-21,
    "gn:feature_class":"P",
    "gn:feature_code":"PPL",
    "gn:name":"P\u012br Poshteh",
    "gn:population":0,
    "gn:timezone":"Asia/Tehran",
    "iso:country":"IR",
    "name:ceb_x_preferred":[
        "P\u012br Poshteh"
    ],
    "name:fas_x_preferred":[
        "P\u012br Poshteh"
    ],
    "name:fas_x_variant":[
        "\u067e\u06cc\u0631 \u067e\u0634\u062a\u0647",
        "\u067e\u06cc\u0631\u067e\u0634\u062a\u0647"
    ],
    "name:msa_x_preferred":[
        "Pir Poshteh"
    ],
    "name:swe_x_preferred":[
        "P\u012br Poshteh"
    ],
    "name:ukr_x_preferred":[
        "\u041f\u0456\u0440-\u041f\u043e\u0448\u0442\u0435"
    ],
    "wof:name":"Pir Poshteh",
    "wof:placetype":"locality"
},
  "geometry": {"coordinates":[50.23606,37.19978],"type":"Point"}
}