{
  "type": "Feature",
  "properties": {
    "gn:admin1_code":"8.0",
    "gn:asciiname":"Mazu Kalleh Poshteh",
    "gn:country_code":"IR",
    "gn:dem":631,
    "gn:feature_class":"P",
    "gn:feature_code":"PPL",
    "gn:name":"M\u0101z\u016b Kalleh Poshteh",
    "gn:population":0,
    "gn:timezone":"Asia/Tehran",
    "iso:country":"IR",
    "name:fas_x_preferred":[
        "M\u0101z\u016bkal\u0101 Poshteh"
    ],
    "name:fas_x_variant":[
        "\u0645\u0627\u0632\u0648 \u06a9\u0644\u0647 \u067e\u0634\u062a\u0647",
        "\u0645\u0627\u0632\u06cc \u06a9\u0644\u0647 \u067e\u0634\u062a\u0647",
        "\u0645\u0627\u0632\u06cc \u06a9\u0644\u0647"
    ],
    "name:msa_x_preferred":[
        "Mazi Kalleh"
    ],
    "name:ukr_x_preferred":[
        "\u041c\u0430\u0437\u0456-\u041a\u0430\u043b\u0435"
    ],
    "name:und_x_variant":[
        "M\u0101z\u016b Kalleh Poshteh",
        "M\u0101z\u012b Kalleh Poshteh"
    ],
    "wof:name":"Mazu Kalleh Poshteh",
    "wof:placetype":"locality"
},
  "geometry": {"coordinates":[50.56609,36.9352],"type":"Point"}
}