{
  "type": "Feature",
  "properties": {
    "gn:admin1_code":"32",
    "gn:asciiname":"Qeshlaq-e Amir A`lam",
    "gn:country_code":"IR",
    "gn:dem":470,
    "gn:feature_class":"P",
    "gn:feature_code":"PPL",
    "gn:name":"Qeshl\u0101q-e Am\u012br A\u2018lam",
    "gn:population":0,
    "gn:timezone":"Asia/Tehran",
    "iso:country":"IR",
    "name:fas_x_preferred":[
        "Qeshl\u0101q-e Am\u012br A\u2018lam"
    ],
    "name:fas_x_variant":[
        "\u0642\u0650\u0634\u0644\u0627\u0642\u0650 \u0627\u064e\u0645\u064a\u0631 \u0627\u064e\u0639\u0644\u064e\u0645",
        "\u0648\u062f\u0644\u0648 \u0642\u0650\u0634\u0644\u0627\u0642"
    ],
    "name:und_x_variant":[
        "\u016adl\u016b Qeshl\u0101q"
    ],
    "wof:name":"Qeshlaq-e Amir A`lam",
    "wof:placetype":"locality"
},
  "geometry": {"coordinates":[48.03333,39.33333],"type":"Point"}
}