{
  "type": "Feature",
  "properties": {
    "gn:admin1_code":"8.0",
    "gn:asciiname":"Marsarud",
    "gn:country_code":"IR",
    "gn:dem":-8,
    "gn:feature_class":"P",
    "gn:feature_code":"PPLF",
    "gn:name":"Mars\u0101r\u016bd",
    "gn:population":0,
    "gn:timezone":"Asia/Tehran",
    "iso:country":"IR",
    "name:fas_x_preferred":[
        "Mars\u0101r\u016bd"
    ],
    "name:fas_x_variant":[
        "\u0645\u0631\u0633\u0627\u0631\u0648\u062f"
    ],
    "wof:name":"Marsarud",
    "wof:placetype":"locality"
},
  "geometry": {"coordinates":[49.37067,37.31583],"type":"Point"}
}