{
  "type": "Feature",
  "properties": {
    "gn:admin1_code":"42",
    "gn:asciiname":"Chah Howz",
    "gn:country_code":"IR",
    "gn:dem":875,
    "gn:feature_class":"P",
    "gn:feature_code":"PPL",
    "gn:name":"Ch\u0101h \u1e28ow\u1e95",
    "gn:population":0,
    "gn:timezone":"Asia/Tehran",
    "iso:country":"IR",
    "name:ara_x_preferred":[
        "\u0631\u0628\u0627\u0637 \u062a\u0634\u0627\u0647 \u062d\u0648\u0636"
    ],
    "name:fas_x_preferred":[
        "Ch\u0101h \u1e28ow\u1e95"
    ],
    "name:fas_x_variant":[
        "\u0631\u0628\u0627\u0637 \u0686\u0627\u0647 \u062d\u0648\u0636"
    ],
    "wof:name":"Chah Howz",
    "wof:placetype":"locality"
},
  "geometry": {"coordinates":[59.56222,34.16889],"type":"Point"}
}