{
  "type": "Feature",
  "properties": {
    "gn:admin1_code":"7",
    "gn:asciiname":"Chahaki",
    "gn:country_code":"IR",
    "gn:dem":887,
    "gn:feature_class":"P",
    "gn:feature_code":"PPL",
    "gn:name":"Chahak\u012b",
    "gn:population":0,
    "gn:timezone":"Asia/Tehran",
    "iso:country":"IR",
    "name:fas_x_preferred":[
        "Chahak\u012b"
    ],
    "name:fas_x_variant":[
        "Ch\u0101hak\u012b",
        "\u0686\u0647\u06a9\u06cc",
        "\u0686\u0627\u0647\u06a9\u06cc"
    ],
    "name:msa_x_preferred":[
        "Chahaki"
    ],
    "name:und_x_variant":[
        "\u0686\u0647\u06a9\u06cc"
    ],
    "wof:name":"Chahaki",
    "wof:placetype":"locality"
},
  "geometry": {"coordinates":[51.47976,30.19767],"type":"Point"}
}