{
  "type": "Feature",
  "properties": {
    "gn:admin1_code":"42",
    "gn:asciiname":"Dashbolagh",
    "gn:country_code":"IR",
    "gn:dem":1849,
    "gn:feature_class":"P",
    "gn:feature_code":"PPLL",
    "gn:name":"D\u0101shbol\u0101gh",
    "gn:population":0,
    "gn:timezone":"Asia/Tehran",
    "iso:country":"IR",
    "name:fas_x_preferred":[
        "\u062f\u0627\u0634\u0628\u0644\u0627\u063a"
    ],
    "name:fas_x_variant":[
        "D\u0101shbol\u0101gh"
    ],
    "wof:name":"Dashbolagh",
    "wof:placetype":"locality"
},
  "geometry": {"coordinates":[58.79023000000001,36.67732],"type":"Point"}
}