{
  "type": "Feature",
  "properties": {
    "gn:admin1_code":"10.0",
    "gn:asciiname":"Bargeh",
    "gn:country_code":"IR",
    "gn:dem":1114,
    "gn:feature_class":"P",
    "gn:feature_code":"PPL",
    "gn:name":"B\u0101rgeh",
    "gn:population":0,
    "gn:timezone":"Asia/Tehran",
    "iso:country":"IR",
    "name:fas_x_preferred":[
        "\u0628\u0627\u0631\u06af\u0647"
    ],
    "name:fas_x_variant":[
        "\u0628\u0631\u06af\u0647"
    ],
    "name:und_x_variant":[
        "B\u0101rgeh"
    ],
    "wof:name":"Bargeh",
    "wof:placetype":"locality"
},
  "geometry": {"coordinates":[47.28199,33.77549],"type":"Point"}
}