{
  "type": "Feature",
  "properties": {
    "gn:admin1_code":"32",
    "gn:asciiname":"Marzand",
    "gn:country_code":"IR",
    "gn:dem":975,
    "gn:feature_class":"P",
    "gn:feature_code":"PPL",
    "gn:name":"Marzand",
    "gn:population":0,
    "gn:timezone":"Asia/Tehran",
    "iso:country":"IR",
    "name:fas_x_preferred":[
        "\u0645\u064e\u0631\u0632\u064e\u0646\u062f"
    ],
    "wof:name":"Marzand",
    "wof:placetype":"locality"
},
  "geometry": {"coordinates":[47.9275,39.00444],"type":"Point"}
}