{
  "type": "Feature",
  "properties": {
    "gn:admin1_code":"7.0",
    "gn:asciiname":"Bagh-e Bozorg",
    "gn:country_code":"IR",
    "gn:dem":774,
    "gn:feature_class":"P",
    "gn:feature_code":"PPL",
    "gn:name":"B\u0101gh-e Bozorg",
    "gn:population":0,
    "gn:timezone":"Asia/Tehran",
    "iso:country":"IR",
    "name:fas_x_preferred":[
        "B\u0101gh-e Bozorg"
    ],
    "name:fas_x_variant":[
        "\u0628\u0627\u063a \u0628\u0632\u0631\u06af"
    ],
    "wof:name":"Bagh-e Bozorg",
    "wof:placetype":"locality"
},
  "geometry": {"coordinates":[51.57391,29.74618],"type":"Point"}
}