{
  "type": "Feature",
  "properties": {
    "gn:admin1_code":"42",
    "gn:asciiname":"Taherabad",
    "gn:country_code":"IR",
    "gn:dem":1251,
    "gn:feature_class":"P",
    "gn:feature_code":"PPLF",
    "gn:name":"\u0162\u0101her\u0101b\u0101d",
    "gn:population":0,
    "gn:timezone":"Asia/Tehran",
    "iso:country":"IR",
    "name:fas_x_preferred":[
        "\u0637\u0627\u0647\u0631 \u0622\u0628\u0627\u062f"
    ],
    "name:fas_x_variant":[
        "\u0162\u0101her\u0101b\u0101d",
        "\u0637\u0627\u0647\u0631\u0622\u0628\u0627\u062f"
    ],
    "wof:name":"Taherabad",
    "wof:placetype":"locality"
},
  "geometry": {"coordinates":[58.74221,35.26559],"type":"Point"}
}