{
  "type": "Feature",
  "properties": {
    "gn:admin1_code":"15.0",
    "gn:asciiname":"Deh Yur",
    "gn:country_code":"IR",
    "gn:dem":203,
    "gn:feature_class":"P",
    "gn:feature_code":"PPL",
    "gn:name":"Deh Y\u016br",
    "gn:population":0,
    "gn:timezone":"Asia/Tehran",
    "iso:country":"IR",
    "name:ara_x_preferred":[
        "\u062f\u0647\u064a\u0648\u0631"
    ],
    "name:ceb_x_preferred":[
        "Dehy\u016br"
    ],
    "name:fas_x_preferred":[
        "Dehy\u016br"
    ],
    "name:fas_x_variant":[
        "\u062f\u0647\u06cc\u0648\u0631",
        "\u062f\u0647 \u06cc\u0648\u0631"
    ],
    "name:swe_x_preferred":[
        "Dehy\u016br"
    ],
    "name:und_x_variant":[
        "Deh Y\u016br"
    ],
    "wof:name":"Deh Yur",
    "wof:placetype":"locality"
},
  "geometry": {"coordinates":[49.6512,31.24866],"type":"Point"}
}