{
  "type": "Feature",
  "properties": {
    "gn:admin1_code":"3",
    "gn:asciiname":"Kalgeh-ye Sar Dasht",
    "gn:country_code":"IR",
    "gn:dem":2036,
    "gn:feature_class":"P",
    "gn:feature_code":"PPL",
    "gn:name":"Kalgeh-ye Sar Dasht",
    "gn:population":0,
    "gn:timezone":"Asia/Tehran",
    "iso:country":"IR",
    "name:fas_x_preferred":[
        "\u06a9\u0644\u06af\u0647 \u0633\u0631\u062f\u0634\u062a"
    ],
    "name:fas_x_variant":[
        "\u0643\u0644 \u06af\u0647"
    ],
    "name:und_x_variant":[
        "Kal Gah"
    ],
    "wof:name":"Kalgeh-ye Sar Dasht",
    "wof:placetype":"locality"
},
  "geometry": {"coordinates":[50.8361,31.39615],"type":"Point"}
}