{
  "type": "Feature",
  "properties": {
    "gn:admin1_code":"7",
    "gn:asciiname":"Tolombeh-ye Ebrahimabad",
    "gn:country_code":"IR",
    "gn:dem":2267,
    "gn:feature_class":"P",
    "gn:feature_code":"PPL",
    "gn:name":"Tolombeh-ye Ebr\u0101h\u012bm\u0101b\u0101d",
    "gn:population":0,
    "gn:timezone":"Asia/Tehran",
    "iso:country":"IR",
    "name:fas_x_preferred":[
        "Ebr\u0101h\u012bm Kh\u0101n"
    ],
    "name:fas_x_variant":[
        "\u062a\u0644\u0645\u0628\u0647 \u0627\u0628\u0631\u0627\u0647\u064a\u0645 \u0622\u0628\u0627\u062f"
    ],
    "name:und_x_variant":[
        "Tolombeh-ye Ebr\u0101h\u012bm\u0101b\u0101d"
    ],
    "wof:name":"Tolombeh-ye Ebrahimabad",
    "wof:placetype":"locality"
},
  "geometry": {"coordinates":[52.7736,30.36662],"type":"Point"}
}