{
  "type": "Feature",
  "properties": {
    "gn:admin1_code":"9",
    "gn:asciiname":"Laminabad",
    "gn:country_code":"IR",
    "gn:dem":1787,
    "gn:feature_class":"P",
    "gn:feature_code":"PPL",
    "gn:name":"Lam\u012bn\u0101b\u0101d",
    "gn:population":0,
    "gn:timezone":"Asia/Tehran",
    "iso:country":"IR",
    "name:fas_x_preferred":[
        "\u0627\u0645\u06cc\u0646 \u0622\u0628\u0627\u062f"
    ],
    "name:fas_x_variant":[
        "Am\u012bn\u0101b\u0101d",
        "\u0644\u0645\u06cc\u0646 \u0622\u0628\u0627\u062f",
        "\u0642\u0646\u0628\u0631 \u0622\u0628\u0627\u062f"
    ],
    "name:und_x_variant":[
        "Lam\u012bn\u0101b\u0101d",
        "Qanbar\u0101b\u0101d"
    ],
    "wof:name":"Laminabad",
    "wof:placetype":"locality"
},
  "geometry": {"coordinates":[47.96264,34.791],"type":"Point"}
}