{
  "type": "Feature",
  "properties": {
    "gn:admin1_code":"28",
    "gn:asciiname":"Busunar",
    "gn:country_code":"IR",
    "gn:dem":1200,
    "gn:feature_class":"P",
    "gn:feature_code":"PPL",
    "gn:name":"B\u016bs\u016bnar",
    "gn:population":0,
    "gn:timezone":"Asia/Tehran",
    "iso:country":"IR",
    "name:fas_x_preferred":[
        "B\u016bs\u016bnar"
    ],
    "wof:name":"Busunar",
    "wof:placetype":"locality"
},
  "geometry": {"coordinates":[53.35,33.63333],"type":"Point"}
}