{
  "type": "Feature",
  "properties": {
    "gn:admin1_code":"43",
    "gn:asciiname":"Korf",
    "gn:country_code":"IR",
    "gn:dem":1129,
    "gn:feature_class":"P",
    "gn:feature_code":"PPL",
    "gn:name":"Korf",
    "gn:population":0,
    "gn:timezone":"Asia/Tehran",
    "iso:country":"IR",
    "name:deu_x_preferred":[
        "Korf"
    ],
    "name:fas_x_preferred":[
        "\u06a9\u0631\u0641"
    ],
    "name:fas_x_variant":[
        "K\u016brf"
    ],
    "name:fra_x_preferred":[
        "Korf"
    ],
    "name:ita_x_preferred":[
        "Korf"
    ],
    "name:lav_x_preferred":[
        "Korff"
    ],
    "name:pol_x_preferred":[
        "Korf"
    ],
    "name:rus_x_preferred":[
        "\u041a\u043e\u0440\u0444"
    ],
    "name:ukr_x_preferred":[
        "\u041a\u043e\u0440\u0444"
    ],
    "name:und_x_variant":[
        "Kafar",
        "K\u016brf",
        "Korf",
        "\u06a9\u0631\u0641"
    ],
    "wof:name":"Korf",
    "wof:placetype":"locality"
},
  "geometry": {"coordinates":[56.83406,37.18844],"type":"Point"}
}