{
  "type": "Feature",
  "properties": {
    "gn:admin1_code":"15",
    "gn:asciiname":"Tovijiyeh-ye `Olya",
    "gn:country_code":"IR",
    "gn:dem":16,
    "gn:elevation":"0.0",
    "gn:feature_class":"P",
    "gn:feature_code":"PPL",
    "gn:name":"Tov\u012bj\u012byeh-ye \u2018Oly\u0101",
    "gn:population":0,
    "gn:timezone":"Asia/Tehran",
    "iso:country":"IR",
    "name:fas_x_preferred":[
        "Toveyj\u012byeh-ye B\u0101l\u0101"
    ],
    "name:fas_x_variant":[
        "\u0162owj\u012byeh",
        "\u062a\u0648\u06cc\u062c\u06cc\u0647 \u0639\u0644\u06cc\u0627",
        "\u0637\u0648\u062c\u064a\u0647",
        "\u062a\u0648\u06cc\u062c\u06cc\u0647 \u067e\u0627\u06cc\u06cc\u0646"
    ],
    "name:und_x_variant":[
        "Tov\u012bj\u012byeh-ye \u2018Oly\u0101",
        "Toveyj\u012byeh-ye P\u0101\u2019\u012bn",
        "\u0162ovj\u012byeh",
        "\u062a\u0648\u06cc\u062c\u06cc\u0647 \u0628\u0627\u0644\u0627"
    ],
    "wof:name":"Tovijiyeh-ye `Olya",
    "wof:placetype":"locality"
},
  "geometry": {"coordinates":[49.00959,30.75073],"type":"Point"}
}