{
  "type": "Feature",
  "properties": {
    "gn:admin1_code":"26",
    "gn:asciiname":"Kuy-e Shamsabad",
    "gn:country_code":"IR",
    "gn:dem":1638,
    "gn:feature_class":"P",
    "gn:feature_code":"PPL",
    "gn:name":"K\u016by-e Shams\u0101b\u0101d",
    "gn:population":0,
    "gn:timezone":"Asia/Tehran",
    "iso:country":"IR",
    "name:fas_x_preferred":[
        "\u0634\u0645\u0633 \u0622\u0628\u0627\u062f"
    ],
    "name:fas_x_variant":[
        "Shams\u0101b\u0101d",
        "\u06a9\u0648\u06cc \u0634\u0645\u0633 \u0622\u0628\u0627\u062f"
    ],
    "name:und_x_variant":[
        "K\u016by-e Shams\u0101b\u0101d"
    ],
    "wof:name":"Kuy-e Shamsabad",
    "wof:placetype":"locality"
},
  "geometry": {"coordinates":[51.73468,35.751],"type":"Point"}
}