{
  "type": "Feature",
  "properties": {
    "gn:admin1_code":"29",
    "gn:asciiname":"Zeydabad Chehel Tokhm",
    "gn:country_code":"IR",
    "gn:dem":1085,
    "gn:feature_class":"P",
    "gn:feature_code":"PPL",
    "gn:name":"Zeyd\u0101b\u0101d Chehel Tokhm",
    "gn:population":0,
    "gn:timezone":"Asia/Tehran",
    "iso:country":"IR",
    "name:fas_x_preferred":[
        "\u0686\u0647\u0644 \u062a\u062e\u0645"
    ],
    "name:fas_x_variant":[
        "\u0632\u064a\u062f \u0622\u0628\u0627\u062f \u0686\u0647\u0644 \u062a\u062e\u0645"
    ],
    "name:und_x_variant":[
        "Chil T\u016bkh",
        "Chehel Tokhm-e Bam",
        "Chehel Tokhm",
        "Zeyd\u0101b\u0101d Chehel Tokhm",
        "Seyyed\u0101b\u0101d"
    ],
    "wof:name":"Zeydabad Chehel Tokhm",
    "wof:placetype":"locality"
},
  "geometry": {"coordinates":[58.3294,29.1262],"type":"Point"}
}