{
  "type": "Feature",
  "properties": {
    "gn:admin1_code":"4.0",
    "gn:asciiname":"Chutani",
    "gn:country_code":"IR",
    "gn:dem":43,
    "gn:feature_class":"P",
    "gn:feature_code":"PPL",
    "gn:name":"Ch\u016bt\u0101n\u012b",
    "gn:population":0,
    "gn:timezone":"Asia/Tehran",
    "iso:country":"IR",
    "name:ara_x_preferred":[
        "\u062a\u0634\u0648\u062a\u0627\u0646\u064a"
    ],
    "name:fas_x_preferred":[
        "Ch\u016bt\u0101n\u012b"
    ],
    "name:fas_x_variant":[
        "\u0686\u0648\u062a\u0627\u0646\u06cc"
    ],
    "wof:name":"Chutani",
    "wof:placetype":"locality"
},
  "geometry": {"coordinates":[60.96739,25.64908],"type":"Point"}
}