{
  "type": "Feature",
  "properties": {
    "gn:admin1_code":"37",
    "gn:asciiname":"Maliar-e Bala",
    "gn:country_code":"IR",
    "gn:dem":1038,
    "gn:feature_class":"P",
    "gn:feature_code":"PPL",
    "gn:name":"Mal\u012b\u0101r-e B\u0101l\u0101",
    "gn:population":0,
    "gn:timezone":"Asia/Tehran",
    "iso:country":"IR",
    "name:fas_x_preferred":[
        "Mal\u012b\u0101r-e B\u0101l\u0101"
    ],
    "wof:name":"Maliar-e Bala",
    "wof:placetype":"locality"
},
  "geometry": {"coordinates":[54.81667,36.76667],"type":"Point"}
}