{
  "type": "Feature",
  "properties": {
    "gn:admin1_code":"37.0",
    "gn:asciiname":"Digcheh",
    "gn:country_code":"IR",
    "gn:dem":21,
    "gn:feature_class":"P",
    "gn:feature_code":"PPL",
    "gn:name":"D\u012bgcheh",
    "gn:population":0,
    "gn:timezone":"Asia/Tehran",
    "iso:country":"IR",
    "name:ara_x_preferred":[
        "\u062f\u064a\u063a\u062a\u0634\u0647"
    ],
    "name:fas_x_preferred":[
        "\u062f\u064a\u06af\u0686\u0647"
    ],
    "name:fas_x_variant":[
        "D\u012bkcheh",
        "\u062f\u064a\u0643\u0686\u0647",
        "\u062f\u06cc\u06af\u0686\u0647"
    ],
    "name:msa_x_preferred":[
        "Dikcheh"
    ],
    "name:und_x_variant":[
        "D\u012bgcheh"
    ],
    "wof:name":"Digcheh",
    "wof:placetype":"locality"
},
  "geometry": {"coordinates":[54.95137,37.2572],"type":"Point"}
}