{
  "type": "Feature",
  "properties": {
    "gn:admin1_code":"4.0",
    "gn:asciiname":"Deh-e Gholam`ali",
    "gn:country_code":"IR",
    "gn:dem":477,
    "gn:feature_class":"P",
    "gn:feature_code":"PPL",
    "gn:name":"Deh-e Ghol\u0101m\u2018al\u012b",
    "gn:population":0,
    "gn:timezone":"Asia/Tehran",
    "iso:country":"IR",
    "name:fas_x_preferred":[
        "Ghol\u0101m \u2018Al\u012b"
    ],
    "name:fas_x_variant":[
        "\u062f\u0647 \u063a\u0644\u0627\u0645\u0639\u0644\u06cc"
    ],
    "name:und_x_variant":[
        "Deh Ghul\u0101m Ali",
        "Deh-e Ghol\u0101m\u2018al\u012b",
        "\u062f\u0647 \u063a\u0644\u0627\u0645\u0639\u0644\u06cc"
    ],
    "wof:name":"Deh-e Gholam`ali",
    "wof:placetype":"locality"
},
  "geometry": {"coordinates":[61.4416,31.1258],"type":"Point"}
}