{
  "type": "Feature",
  "properties": {
    "gn:admin1_code":"35.0",
    "gn:asciiname":"Ab Dang Sar",
    "gn:country_code":"IR",
    "gn:dem":197,
    "gn:feature_class":"P",
    "gn:feature_code":"PPL",
    "gn:name":"\u0100b Dang Sar",
    "gn:population":0,
    "gn:timezone":"Asia/Tehran",
    "iso:country":"IR",
    "name:fas_x_preferred":[
        "\u0622\u0628 \u062f\u0646\u06af \u0633\u0631"
    ],
    "name:fas_x_variant":[
        "\u0100b Dang Sar"
    ],
    "wof:name":"Ab Dang Sar",
    "wof:placetype":"locality"
},
  "geometry": {"coordinates":[52.8695,36.32551],"type":"Point"}
}