{
  "type": "Feature",
  "properties": {
    "gn:admin1_code":"36",
    "gn:asciiname":"Emam",
    "gn:country_code":"IR",
    "gn:dem":2022,
    "gn:feature_class":"P",
    "gn:feature_code":"PPL",
    "gn:name":"Em\u0101m",
    "gn:population":0,
    "gn:timezone":"Asia/Tehran",
    "iso:country":"IR",
    "name:azb_x_preferred":[
        "\u0627\u0645\u0627\u0645"
    ],
    "name:fas_x_preferred":[
        "\u0627\u0645\u0627\u0645"
    ],
    "name:fas_x_variant":[
        "Em\u0101m"
    ],
    "name:und_x_variant":[
        "Imam"
    ],
    "wof:name":"Emam",
    "wof:placetype":"locality"
},
  "geometry": {"coordinates":[48.80676,36.70236],"type":"Point"}
}