{
  "type": "Feature",
  "properties": {
    "gn:admin1_code":"42",
    "gn:asciiname":"Lotfabad",
    "gn:country_code":"IR",
    "gn:dem":1145,
    "gn:feature_class":"P",
    "gn:feature_code":"PPL",
    "gn:name":"Lo\u0163f\u0101b\u0101d",
    "gn:population":0,
    "gn:timezone":"Asia/Tehran",
    "iso:country":"IR",
    "name:fas_x_preferred":[
        "\u0644\u0637\u0641 \u0622\u0628\u0627\u062f"
    ],
    "name:fas_x_variant":[
        "Lo\u0163f\u0101b\u0101d",
        "\u0644\u0637\u0641\u200c\u0622\u0628\u0627\u062f"
    ],
    "wof:name":"Lotfabad",
    "wof:placetype":"locality"
},
  "geometry": {"coordinates":[58.7352,36.1794],"type":"Point"}
}