{
  "type": "Feature",
  "properties": {
    "gn:admin1_code":"11",
    "gn:asciiname":"Gezir-e Sofla",
    "gn:country_code":"IR",
    "gn:dem":43,
    "gn:feature_class":"P",
    "gn:feature_code":"PPL",
    "gn:name":"Gez\u012br-e Sofl\u00e1",
    "gn:population":0,
    "gn:timezone":"Asia/Tehran",
    "iso:country":"IR",
    "name:fas_x_preferred":[
        "Gez\u012br"
    ],
    "name:fas_x_variant":[
        "\u06af\u0632\u064a\u0631",
        "\u06af\u0632\u064a\u0631 \u0633\u0641\u0644\u06cc"
    ],
    "name:und_x_variant":[
        "\u06af\u0632\u064a\u0631",
        "Gez\u012br-e Sofl\u00e1"
    ],
    "wof:name":"Gezir-e Sofla",
    "wof:placetype":"locality"
},
  "geometry": {"coordinates":[54.94766,26.72672],"type":"Point"}
}