{
  "type": "Feature",
  "properties": {
    "gn:admin1_code":"4",
    "gn:asciiname":"Sayyadan-e Yek",
    "gn:country_code":"IR",
    "gn:dem":533,
    "gn:feature_class":"P",
    "gn:feature_code":"PPL",
    "gn:name":"\u015eayy\u0101d\u0101n-e Yek",
    "gn:population":0,
    "gn:timezone":"Asia/Tehran",
    "iso:country":"IR",
    "name:fas_x_preferred":[
        "\u0635\u06cc\u0627\u062f\u0627\u0646 \u06cc\u06a9"
    ],
    "name:fas_x_variant":[
        "\u015eayy\u0101d\u0101n-e Yek",
        "\u0633\u0631\u062f\u06a9"
    ],
    "name:und_x_variant":[
        "Sardak"
    ],
    "wof:name":"Sayyadan-e Yek",
    "wof:placetype":"locality"
},
  "geometry": {"coordinates":[62.7261,28.0021],"type":"Point"}
}