{
  "type": "Feature",
  "properties": {
    "gn:admin1_code":"42.0",
    "gn:asciiname":"Hasanak",
    "gn:country_code":"IR",
    "gn:dem":1346,
    "gn:feature_class":"P",
    "gn:feature_code":"PPL",
    "gn:name":"\u1e28asanak",
    "gn:population":0,
    "gn:timezone":"Asia/Tehran",
    "iso:country":"IR",
    "name:fas_x_preferred":[
        "\u062d\u0633\u0646\u06a9"
    ],
    "name:fas_x_variant":[
        "\u1e28asanak"
    ],
    "wof:name":"Hasanak",
    "wof:placetype":"locality"
},
  "geometry": {"coordinates":[60.16636999999999,35.40779000000001],"type":"Point"}
}