{
  "type": "Feature",
  "properties": {
    "gn:admin1_code":"37.0",
    "gn:asciiname":"Qarah Quzi-ye Pa'in",
    "gn:country_code":"IR",
    "gn:dem":174,
    "gn:feature_class":"P",
    "gn:feature_code":"PPL",
    "gn:name":"Qarah Q\u016bz\u012b-ye P\u0101\u2019\u012bn",
    "gn:population":0,
    "gn:timezone":"Asia/Tehran",
    "iso:country":"IR",
    "name:fas_x_preferred":[
        "\u0642\u0631\u0647 \u0642\u0648\u0632\u06cc \u067e\u0627\u0626\u06cc\u0646"
    ],
    "name:und_x_variant":[
        "Qarah Q\u016bz\u012b-ye P\u0101\u2019\u012bn"
    ],
    "wof:name":"Qarah Quzi-ye Pa'in",
    "wof:placetype":"locality"
},
  "geometry": {"coordinates":[55.5013,37.4996],"type":"Point"}
}