{
  "type": "Feature",
  "properties": {
    "gn:admin1_code":"42",
    "gn:asciiname":"Samandar",
    "gn:country_code":"IR",
    "gn:dem":1158,
    "gn:feature_class":"P",
    "gn:feature_code":"PPL",
    "gn:name":"Samandar",
    "gn:population":0,
    "gn:timezone":"Asia/Tehran",
    "iso:country":"IR",
    "name:ara_x_preferred":[
        "\u0633\u0645\u0646\u062f\u0631"
    ],
    "name:fas_x_preferred":[
        "\u0633\u0645\u0646\u062f\u0631"
    ],
    "wof:name":"Samandar",
    "wof:placetype":"locality"
},
  "geometry": {"coordinates":[59.08745,36.68409000000001],"type":"Point"}
}