{
  "type": "Feature",
  "properties": {
    "gn:admin1_code":"15",
    "gn:asciiname":"Shobeysheh Buzi",
    "gn:country_code":"IR",
    "gn:dem":9,
    "gn:feature_class":"P",
    "gn:feature_code":"PPL",
    "gn:name":"Shobeysheh B\u016bz\u012b",
    "gn:population":0,
    "gn:timezone":"Asia/Tehran",
    "iso:country":"IR",
    "name:fas_x_preferred":[
        "\u0634\u0628\u06cc\u0634\u0647"
    ],
    "name:fas_x_variant":[
        "\u0634\u0628\u06cc\u0634\u0647 \u0628\u0648\u0632\u06cc"
    ],
    "name:und_x_variant":[
        "Shobeysheh",
        "Shobeysheh B\u016bz\u012b"
    ],
    "wof:name":"Shobeysheh Buzi",
    "wof:placetype":"locality"
},
  "geometry": {"coordinates":[48.71816,30.68965],"type":"Point"}
}