{
  "type": "Feature",
  "properties": {
    "gn:admin1_code":"0",
    "gn:asciiname":"`Alamdan-e Pa'in",
    "gn:country_code":"IR",
    "gn:dem":180,
    "gn:feature_class":"P",
    "gn:feature_code":"PPL",
    "gn:name":"\u2018Alamd\u0101n-e P\u0101\u2019\u012bn",
    "gn:population":0,
    "gn:timezone":"Asia/Tehran",
    "iso:country":"IR",
    "name:fas_x_preferred":[
        "\u0639\u0644\u0645\u062f\u0627\u0646 \u067e\u0627\u06cc\u06cc\u0646"
    ],
    "name:fas_x_variant":[
        "\u2018Alamd\u0101n-e P\u0101\u2019\u012bn"
    ],
    "wof:name":"`Alamdan-e Pa'in",
    "wof:placetype":"locality"
},
  "geometry": {"coordinates":[52.2369,28.1508],"type":"Point"}
}