{
  "type": "Feature",
  "properties": {
    "gn:admin1_code":"42",
    "gn:asciiname":"`Abbasiabad-e Khuk Ab",
    "gn:country_code":"IR",
    "gn:dem":737,
    "gn:feature_class":"P",
    "gn:feature_code":"PPL",
    "gn:name":"\u2018Abb\u0101s\u012b\u0101b\u0101d-e Kh\u016bk \u0100b",
    "gn:population":0,
    "gn:timezone":"Asia/Tehran",
    "iso:country":"IR",
    "name:fas_x_preferred":[
        "\u2018Abb\u0101s\u012b\u0101b\u0101d-e Kh\u016bk \u0100b"
    ],
    "name:fas_x_variant":[
        "\u0639\u0628\u0651\u0627\u0633\u06cc \u0622\u0628\u0627\u062f \u062e\u0648\u06a9 \u0622\u0628"
    ],
    "wof:name":"`Abbasiabad-e Khuk Ab",
    "wof:placetype":"locality"
},
  "geometry": {"coordinates":[61.07264,35.91311],"type":"Point"}
}