{
  "type": "Feature",
  "properties": {
    "gn:admin1_code":"7",
    "gn:asciiname":"Ekrad",
    "gn:country_code":"IR",
    "gn:dem":1582,
    "gn:feature_class":"P",
    "gn:feature_code":"PPL",
    "gn:name":"Ekr\u0101d",
    "gn:population":0,
    "gn:timezone":"Asia/Tehran",
    "iso:country":"IR",
    "name:fas_x_preferred":[
        "\u0627\u06a9\u0631\u0627\u062f"
    ],
    "name:fas_x_variant":[
        "Ekr\u0101d"
    ],
    "name:und_x_variant":[
        "Ikr\u0101d"
    ],
    "wof:name":"Ekrad",
    "wof:placetype":"locality"
},
  "geometry": {"coordinates":[52.9197,29.7311],"type":"Point"}
}