{
  "type": "Feature",
  "properties": {
    "gn:admin1_code":"33",
    "gn:asciiname":"Qushqovan-e Vosta",
    "gn:country_code":"IR",
    "gn:dem":1804,
    "gn:feature_class":"P",
    "gn:feature_code":"PPL",
    "gn:name":"Q\u016bshqov\u0101n-e Vos\u0163\u00e1",
    "gn:population":0,
    "gn:timezone":"Asia/Tehran",
    "iso:country":"IR",
    "name:ara_x_preferred":[
        "\u0642\u0648\u0634\u0642\u0648\u0627\u0646 \u0648\u0633\u0637\u064a"
    ],
    "name:fas_x_preferred":[
        "\u0642\u0648\u0634\u0642\u0648\u0627\u0646 \u0648\u0633\u0637\u06cc"
    ],
    "name:fas_x_variant":[
        "Q\u016bshqov\u0101n-e Vos\u0163\u00e1"
    ],
    "name:msa_x_preferred":[
        "Qushqovan-e Vosta"
    ],
    "wof:name":"Qushqovan-e Vosta",
    "wof:placetype":"locality"
},
  "geometry": {"coordinates":[47.0406,37.1468],"type":"Point"}
}