{
  "type": "Feature",
  "properties": {
    "gn:admin1_code":"1",
    "gn:asciiname":"Sureh Dukal",
    "gn:country_code":"IR",
    "gn:dem":1892,
    "gn:feature_class":"P",
    "gn:feature_code":"PPL",
    "gn:name":"S\u016breh D\u016bkal",
    "gn:population":0,
    "gn:timezone":"Asia/Tehran",
    "iso:country":"IR",
    "name:fas_x_preferred":[
        "\u0633\u0648\u0644\u0650\u0647 \u062f\u064f\u06af\u064e\u0644"
    ],
    "name:fas_x_variant":[
        "\u0633\u0648\u0631\u0647 \u062f\u0648\u06a9\u0644",
        "S\u016bleh Dogal",
        "S\u016breh D\u016bkal"
    ],
    "wof:name":"Sureh Dukal",
    "wof:placetype":"locality"
},
  "geometry": {"coordinates":[44.875,37.1783],"type":"Point"}
}