{
  "type": "Feature",
  "properties": {
    "gn:admin1_code":"15",
    "gn:asciiname":"Gargah",
    "gn:country_code":"IR",
    "gn:dem":64,
    "gn:feature_class":"P",
    "gn:feature_code":"PPL",
    "gn:name":"G\u0101rgah",
    "gn:population":0,
    "gn:timezone":"Asia/Tehran",
    "iso:country":"IR",
    "name:fas_x_preferred":[
        "\u06a9\u0627\u0631\u06af\u062f"
    ],
    "name:fas_x_variant":[
        "K\u0101rged",
        "\u06af\u0627\u0631\u06af\u0647"
    ],
    "name:und_x_variant":[
        "Garga",
        "G\u0101rgah"
    ],
    "wof:name":"Gargah",
    "wof:placetype":"locality"
},
  "geometry": {"coordinates":[49.12097,31.61528],"type":"Point"}
}