{
  "type": "Feature",
  "properties": {
    "gn:admin1_code":"10",
    "gn:asciiname":"Cheshmeh Chahi-ye Vosta",
    "gn:country_code":"IR",
    "gn:dem":1316,
    "gn:feature_class":"P",
    "gn:feature_code":"PPL",
    "gn:name":"Cheshmeh Ch\u0101h\u012b-ye Vos\u0163\u00e1",
    "gn:population":0,
    "gn:timezone":"Asia/Tehran",
    "iso:country":"IR",
    "name:fas_x_preferred":[
        "\u0686\u0634\u0645\u0647 \u0686\u0627\u0647\u06cc \u0648\u0633\u0637\u06cc"
    ],
    "name:fas_x_variant":[
        "Cheshmeh Ch\u0101h\u012b-ye Vos\u0163\u00e1"
    ],
    "wof:name":"Cheshmeh Chahi-ye Vosta",
    "wof:placetype":"locality"
},
  "geometry": {"coordinates":[46.558,33.6803],"type":"Point"}
}