{
  "type": "Feature",
  "properties": {
    "gn:admin1_code":"15.0",
    "gn:asciiname":"Abu Garveh-ye Yek",
    "gn:country_code":"IR",
    "gn:dem":27,
    "gn:feature_class":"P",
    "gn:feature_code":"PPL",
    "gn:name":"Ab\u016b Garveh-ye Yek",
    "gn:population":0,
    "gn:timezone":"Asia/Tehran",
    "iso:country":"IR",
    "name:ceb_x_preferred":[
        "Ab\u016b Garv\u0101-e Yek"
    ],
    "name:fas_x_preferred":[
        "\u0627\u0628\u0648 \u06af\u0631\u0648\u0627 \u06cc\u06a9"
    ],
    "name:fas_x_variant":[
        "Ab\u016b Garv\u0101",
        "Ab\u016b Garv\u0101-e Yek",
        "\u0627\u0628\u0648 \u06af\u0631\u0648\u0647 \u06cc\u06a9",
        "\u0627\u0628\u0648\u06af\u0631\u0648\u0627\u06cc\u06a9"
    ],
    "name:swe_x_preferred":[
        "Ab\u016b Garv\u0101-e Yek"
    ],
    "name:und_x_variant":[
        "Ab\u016b Gorv\u0101",
        "Ab\u016b Gerv\u0101",
        "Ab\u016b Gorveh",
        "Ab\u016b Garveh-ye Yek"
    ],
    "wof:name":"Abu Garveh-ye Yek",
    "wof:placetype":"locality"
},
  "geometry": {"coordinates":[48.75911,31.63416],"type":"Point"}
}