{
  "type": "Feature",
  "properties": {
    "gn:admin1_code":"28.0",
    "gn:asciiname":"Kahriz Sang",
    "gn:country_code":"IR",
    "gn:dem":1610,
    "gn:feature_class":"P",
    "gn:feature_code":"PPL",
    "gn:name":"Kahr\u012bz Sang",
    "gn:population":0,
    "gn:timezone":"Asia/Tehran",
    "iso:country":"IR",
    "name:fas_x_preferred":[
        "\u06a9\u0647\u0631\u06cc\u0632 \u0633\u0646\u06af"
    ],
    "name:fas_x_variant":[
        "Kahr\u012bz Sang"
    ],
    "name:und_x_variant":[
        "\u2018Al\u012b\u0101b\u0101d-e Kahr\u012bz Sang"
    ],
    "wof:name":"Kahriz Sang",
    "wof:placetype":"locality"
},
  "geometry": {"coordinates":[51.4811,32.6267],"type":"Point"}
}