{
  "type": "Feature",
  "properties": {
    "gn:admin1_code":"15",
    "gn:asciiname":"Shahrak-e Motahhari-ye Varzard",
    "gn:country_code":"IR",
    "gn:dem":477,
    "gn:feature_class":"P",
    "gn:feature_code":"PPL",
    "gn:name":"Shahrak-e Mo\u0163ahhar\u012b-ye Varzard",
    "gn:population":0,
    "gn:timezone":"Asia/Tehran",
    "iso:country":"IR",
    "name:azb_x_preferred":[
        "\u0634\u0647\u0631\u0643 \u0645\u0637\u0647\u0631\u06cc(\u0628\u0647\u0628\u0647\u0627\u0646)"
    ],
    "name:ceb_x_preferred":[
        "Shahrak-e Mo\u0163ahhar\u012b-ye Varzard"
    ],
    "name:fas_x_preferred":[
        "\u0634\u0647\u0631\u06a9 \u0645\u0637\u0647\u0631\u06cc \u0648\u0631\u0632\u0631\u062f"
    ],
    "name:fas_x_variant":[
        "Shahrak-e Mo\u0163ahhar\u012b",
        "Shahrak-e Mo\u0163ahhar\u012b-ye Varzard",
        "\u0634\u0647\u0631\u06a9 \u0645\u0637\u0647\u0631\u06cc"
    ],
    "name:swe_x_preferred":[
        "Shahrak-e Mo\u0163ahhar\u012b-ye Varzard"
    ],
    "name:und_x_variant":[
        "Var-e Zard"
    ],
    "wof:name":"Shahrak-e Motahhari-ye Varzard",
    "wof:placetype":"locality"
},
  "geometry": {"coordinates":[50.1573,30.8098],"type":"Point"}
}