{
  "type": "Feature",
  "properties": {
    "gn:admin1_code":"28.0",
    "gn:asciiname":"Shah Sara",
    "gn:country_code":"IR",
    "gn:dem":1518,
    "gn:feature_class":"P",
    "gn:feature_code":"PPL",
    "gn:name":"Sh\u0101h Sar\u0101",
    "gn:population":0,
    "gn:timezone":"Asia/Tehran",
    "iso:country":"IR",
    "name:fas_x_preferred":[
        "Sh\u0101h Sar\u0101"
    ],
    "wof:name":"Shah Sara",
    "wof:placetype":"locality"
},
  "geometry": {"coordinates":[52.03028,32.52111],"type":"Point"}
}