{
  "type": "Feature",
  "properties": {
    "gn:admin1_code":"10",
    "gn:asciiname":"Bahramabad",
    "gn:cc2":"IR",
    "gn:country_code":"IR",
    "gn:dem":118,
    "gn:feature_class":"P",
    "gn:feature_code":"PPL",
    "gn:name":"Bahr\u0101m\u0101b\u0101d",
    "gn:population":0,
    "gn:timezone":"Asia/Tehran",
    "iso:country":"IR",
    "name:fas_x_preferred":[
        "\u0628\u0650\u0647\u0631\u0627\u0645 \u0622\u0628\u0627\u062f"
    ],
    "name:fas_x_variant":[
        "Bahr\u0101m\u0101b\u0101d",
        "\u0628\u064e\u0647\u0631\u0627\u0645 \u0622\u0628\u0627\u062f",
        "\u0628\u0647\u0631\u0627\u0645\u200c\u0622\u0628\u0627\u062f"
    ],
    "name:und_x_variant":[
        "Behr\u0101m\u0101b\u0101d"
    ],
    "wof:name":"Bahramabad",
    "wof:placetype":"locality"
},
  "geometry": {"coordinates":[46.08333,33.11667],"type":"Point"}
}