{
  "type": "Feature",
  "properties": {
    "gn:admin1_code":"37",
    "gn:asciiname":"Qaranjil",
    "gn:country_code":"IR",
    "gn:dem":178,
    "gn:feature_class":"P",
    "gn:feature_code":"PPL",
    "gn:name":"Qaranj\u012bl",
    "gn:population":0,
    "gn:timezone":"Asia/Tehran",
    "iso:country":"IR",
    "name:fas_x_preferred":[
        "Qareh Anj\u012bl"
    ],
    "name:fas_x_variant":[
        "\u0642\u0631\u0646\u062c\u06cc\u0644"
    ],
    "name:und_x_variant":[
        "Qaranj\u012bl"
    ],
    "wof:name":"Qaranjil",
    "wof:placetype":"locality"
},
  "geometry": {"coordinates":[55.39771,37.23045],"type":"Point"}
}