{
  "type": "Feature",
  "properties": {
    "gn:admin1_code":"15.0",
    "gn:asciiname":"`Oteysh",
    "gn:country_code":"IR",
    "gn:dem":8,
    "gn:feature_class":"P",
    "gn:feature_code":"PPL",
    "gn:name":"\u2018O\u0163eysh",
    "gn:population":0,
    "gn:timezone":"Asia/Tehran",
    "iso:country":"IR",
    "name:fas_x_preferred":[
        "\u2018A\u0163ash"
    ],
    "name:fas_x_variant":[
        "\u2018O\u0163eysh",
        "\u0639\u0637\u0634",
        "\u0639\u0637\u06cc\u0634"
    ],
    "name:und_x_variant":[
        "\u0639\u0637\u0634"
    ],
    "wof:name":"`Oteysh",
    "wof:placetype":"locality"
},
  "geometry": {"coordinates":[48.66931,30.90982],"type":"Point"}
}