{
  "type": "Feature",
  "properties": {
    "gn:admin1_code":"36",
    "gn:asciiname":"Qarah Mohammad",
    "gn:country_code":"IR",
    "gn:dem":1970,
    "gn:feature_class":"P",
    "gn:feature_code":"PPL",
    "gn:name":"Qarah Mo\u1e29ammad",
    "gn:population":0,
    "gn:timezone":"Asia/Tehran",
    "iso:country":"IR",
    "name:fas_x_preferred":[
        "\u0642\u0631\u0647 \u0645\u062d\u0645\u062f"
    ],
    "name:fas_x_variant":[
        "Qareh Mo\u1e29ammad",
        "Qarah Mo\u1e29ammad"
    ],
    "name:und_x_variant":[
        "Kara-Mukhammed",
        "Qar\u0101 Mo\u1e29ammad"
    ],
    "wof:name":"Qarah Mohammad",
    "wof:placetype":"locality"
},
  "geometry": {"coordinates":[48.55481,36.06543],"type":"Point"}
}