{
  "type": "Feature",
  "properties": {
    "gn:admin1_code":"8.0",
    "gn:asciiname":"Mavardian",
    "gn:country_code":"IR",
    "gn:dem":19,
    "gn:feature_class":"P",
    "gn:feature_code":"PPL",
    "gn:name":"M\u0101vard\u012b\u0101n",
    "gn:population":0,
    "gn:timezone":"Asia/Tehran",
    "iso:country":"IR",
    "name:ara_x_preferred":[
        "\u0645\u0627\u0648\u0631\u062f\u064a\u0627\u0646"
    ],
    "name:ceb_x_preferred":[
        "M\u0101vard\u012b\u0101n"
    ],
    "name:fas_x_preferred":[
        "\u0645\u0627\u0648\u0631\u062f\u06cc\u0627\u0646"
    ],
    "name:fas_x_variant":[
        "M\u0101vard\u012b\u0101n"
    ],
    "name:msa_x_preferred":[
        "Mavardian"
    ],
    "name:swe_x_preferred":[
        "M\u0101vard\u012b\u0101n"
    ],
    "name:ukr_x_preferred":[
        "\u041c\u0430\u0432\u0430\u0440\u0434\u0456\u044f\u043d"
    ],
    "name:und_x_variant":[
        "M\u0101vard\u012b\u0101n"
    ],
    "wof:name":"Mavardian",
    "wof:placetype":"locality"
},
  "geometry": {"coordinates":[49.31065,37.25703],"type":"Point"}
}