{
  "type": "Feature",
  "properties": {
    "gn:admin1_code":"7",
    "gn:asciiname":"Kar Siah-e `Olya",
    "gn:country_code":"IR",
    "gn:dem":1094,
    "gn:feature_class":"P",
    "gn:feature_code":"PPL",
    "gn:name":"Kar S\u012b\u0101h-e \u2018Oly\u0101",
    "gn:population":0,
    "gn:timezone":"Asia/Tehran",
    "iso:country":"IR",
    "name:fas_x_preferred":[
        "\u06a9\u0631 \u0633\u06cc\u0627\u0647 \u0639\u0644\u06cc\u0627"
    ],
    "name:fas_x_variant":[
        "Kar S\u012b\u0101h-e \u2018Oly\u0101"
    ],
    "wof:name":"Kar Siah-e `Olya",
    "wof:placetype":"locality"
},
  "geometry": {"coordinates":[54.4152,28.7745],"type":"Point"}
}