{
  "type": "Feature",
  "properties": {
    "gn:admin1_code":"11.0",
    "gn:asciiname":"Mirzaabad",
    "gn:country_code":"IR",
    "gn:dem":420,
    "gn:feature_class":"P",
    "gn:feature_code":"PPL",
    "gn:name":"M\u012brz\u0101\u0101b\u0101d",
    "gn:population":0,
    "gn:timezone":"Asia/Tehran",
    "iso:country":"IR",
    "name:fas_x_preferred":[
        "M\u012brz\u0101\u0101b\u0101d"
    ],
    "name:fas_x_variant":[
        "\u0645\u064a\u0631\u0632\u0627 \u0622\u0628\u0627\u062f",
        "\u0645\u06cc\u0631\u0632\u0627\u0622\u0628\u0627\u062f"
    ],
    "wof:name":"Mirzaabad",
    "wof:placetype":"locality"
},
  "geometry": {"coordinates":[54.36419,27.18291],"type":"Point"}
}