{
  "type": "Feature",
  "properties": {
    "gn:admin1_code":"29.0",
    "gn:asciiname":"Baghbaghu'iyeh",
    "gn:country_code":"IR",
    "gn:dem":620,
    "gn:feature_class":"P",
    "gn:feature_code":"PPL",
    "gn:name":"B\u0101ghb\u0101gh\u016b\u2019\u012byeh",
    "gn:population":0,
    "gn:timezone":"Asia/Tehran",
    "iso:country":"IR",
    "name:fas_x_preferred":[
        "\u0628\u0627\u063a\u0628\u0627\u063a\u0648\u0626\u06cc\u0647"
    ],
    "name:fas_x_variant":[
        "B\u0101gh-e B\u0101b\u016b\u2019\u012byeh",
        "B\u0101ghb\u0101gh\u016b\u2019\u012byeh"
    ],
    "name:und_x_variant":[
        "B\u0101gh-e B\u0101b\u016b\u2019\u012byeh-ye Oly\u0101",
        "Sofla Baghbanloo\u2019iyeh Olya",
        "B\u0101gh-e B\u0101b\u016b\u2019\u012byeh Sofl\u0101"
    ],
    "wof:name":"Baghbaghu'iyeh",
    "wof:placetype":"locality"
},
  "geometry": {"coordinates":[57.7248,28.5601],"type":"Point"}
}