{
  "type": "Feature",
  "properties": {
    "gn:admin1_code":"3",
    "gn:asciiname":"Parvaz",
    "gn:country_code":"IR",
    "gn:dem":1559,
    "gn:feature_class":"P",
    "gn:feature_code":"PPL",
    "gn:name":"Parvaz",
    "gn:population":0,
    "gn:timezone":"Asia/Tehran",
    "iso:country":"IR",
    "name:fas_x_preferred":[
        "\u067e\u0650\u0631\u0648\u064e\u0632"
    ],
    "name:fas_x_variant":[
        "\u067e\u0631\u0648\u0632"
    ],
    "name:und_x_variant":[
        "Pervaz",
        "Parvaz",
        "\u067e\u0631\u0648\u0632"
    ],
    "wof:name":"Parvaz",
    "wof:placetype":"locality"
},
  "geometry": {"coordinates":[51.15575,31.22287],"type":"Point"}
}