{
  "type": "Feature",
  "properties": {
    "gn:admin1_code":"13",
    "gn:asciiname":"Qal`eh-ye Darab Khan",
    "gn:country_code":"IR",
    "gn:dem":1337,
    "gn:feature_class":"P",
    "gn:feature_code":"PPL",
    "gn:name":"Qal\u2018eh-ye D\u0101r\u0101b Kh\u0101n",
    "gn:population":0,
    "gn:timezone":"Asia/Tehran",
    "iso:country":"IR",
    "name:fas_x_preferred":[
        "\u0642\u0644\u0639\u0647 \u062f\u0627\u0631\u0627\u0628 \u062e\u0627\u0646"
    ],
    "name:fas_x_variant":[
        "Qal\u2018eh-ye D\u0101r\u0101b Kh\u0101n"
    ],
    "wof:name":"Qal`eh-ye Darab Khan",
    "wof:placetype":"locality"
},
  "geometry": {"coordinates":[46.7306,34.4315],"type":"Point"}
}