{
  "type": "Feature",
  "properties": {
    "gn:admin1_code":"7",
    "gn:asciiname":"Posht-e Par",
    "gn:country_code":"IR",
    "gn:dem":1483,
    "gn:feature_class":"P",
    "gn:feature_code":"PPL",
    "gn:name":"Posht-e Par",
    "gn:population":0,
    "gn:timezone":"Asia/Tehran",
    "iso:country":"IR",
    "name:fas_x_preferred":[
        "\u067e\u0634\u062a \u067e\u0631"
    ],
    "name:fas_x_variant":[
        "\u067e\u0634\u062a\u200c\u067e\u0631"
    ],
    "name:msa_x_preferred":[
        "Posht-e Par"
    ],
    "name:und_x_variant":[
        "Posht Bar",
        "Posht Par"
    ],
    "wof:name":"Posht-e Par",
    "wof:placetype":"locality"
},
  "geometry": {"coordinates":[52.8509,29.3168],"type":"Point"}
}