{
  "type": "Feature",
  "properties": {
    "gn:admin1_code":"7",
    "gn:asciiname":"Shahrak-e Vali-ye `Asr",
    "gn:country_code":"IR",
    "gn:dem":1437,
    "gn:feature_class":"P",
    "gn:feature_code":"PPL",
    "gn:name":"Shahrak-e Val\u012b-ye \u2018A\u015fr",
    "gn:population":0,
    "gn:timezone":"Asia/Tehran",
    "iso:country":"IR",
    "name:ara_x_preferred":[
        "\u0634\u0647\u0631\u0643 \u0648\u0644\u064a\u0639\u0635\u0631"
    ],
    "name:fas_x_preferred":[
        "\u0634\u0647\u0631\u0643 \u0648\u0644\u06cc\u0639\u0635\u0631"
    ],
    "name:fas_x_variant":[
        "Shahrak-e Val\u012b-ye \u2018A\u015fr",
        "\u0634\u0647\u0631\u06a9 \u0648\u0644\u06cc\u0639\u0635\u0631"
    ],
    "name:msa_x_preferred":[
        "Shahrak-e Vali-ye Asr"
    ],
    "wof:name":"Shahrak-e Vali-ye `Asr",
    "wof:placetype":"locality"
},
  "geometry": {"coordinates":[54.9849,28.4998],"type":"Point"}
}