{
  "type": "Feature",
  "properties": {
    "gn:admin1_code":"37",
    "gn:asciiname":"Chalaki",
    "gn:country_code":"IR",
    "gn:dem":47,
    "gn:feature_class":"P",
    "gn:feature_code":"PPL",
    "gn:name":"Ch\u0101lak\u012b",
    "gn:population":0,
    "gn:timezone":"Asia/Tehran",
    "iso:country":"IR",
    "name:ara_x_preferred":[
        "\u062a\u0634\u0627\u0644\u0643\u064a"
    ],
    "name:fas_x_preferred":[
        "\u0686\u0627\u0644\u0650\u0643\u06cc"
    ],
    "name:fas_x_variant":[
        "Ch\u0101lak\u012b",
        "\u0686\u0627\u0644\u0643\u06cc",
        "\u0686\u0627\u0644\u06a9\u06cc"
    ],
    "name:msa_x_preferred":[
        "Chalaki"
    ],
    "name:und_x_variant":[
        "Ch\u0101lek\u012b",
        "Chalki"
    ],
    "wof:name":"Chalaki",
    "wof:placetype":"locality"
},
  "geometry": {"coordinates":[54.3019,36.83772],"type":"Point"}
}