{
  "type": "Feature",
  "properties": {
    "gn:admin1_code":"38.0",
    "gn:asciiname":"Moghul",
    "gn:country_code":"IR",
    "gn:dem":1374,
    "gn:feature_class":"P",
    "gn:feature_code":"PPL",
    "gn:name":"Mogh\u016bl",
    "gn:population":0,
    "gn:timezone":"Asia/Tehran",
    "iso:country":"IR",
    "name:fas_x_preferred":[
        "\u0645\u063a\u0648\u0644"
    ],
    "name:und_x_variant":[
        "Mogh\u016bl"
    ],
    "wof:name":"Moghul",
    "wof:placetype":"locality"
},
  "geometry": {"coordinates":[50.48021,36.09352],"type":"Point"}
}