{
  "type": "Feature",
  "properties": {
    "gn:admin1_code":"5",
    "gn:asciiname":"Sar Peri",
    "gn:country_code":"IR",
    "gn:dem":733,
    "gn:feature_class":"P",
    "gn:feature_code":"PPL",
    "gn:name":"Sar Per\u012b",
    "gn:population":0,
    "gn:timezone":"Asia/Tehran",
    "iso:country":"IR",
    "name:ceb_x_preferred":[
        "Sar Per\u012b"
    ],
    "name:fas_x_preferred":[
        "\u0633\u064e\u0631 \u067e\u064e\u0631\u06cc"
    ],
    "name:fas_x_variant":[
        "Sar Per\u012b",
        "\u0633\u0631 \u067e\u0631\u06cc",
        "\u0633\u0631\u067e\u0631\u06cc"
    ],
    "name:swe_x_preferred":[
        "Sar Per\u012b"
    ],
    "name:und_x_variant":[
        "Sar Par\u012b"
    ],
    "wof:name":"Sar Peri",
    "wof:placetype":"locality"
},
  "geometry": {"coordinates":[50.54301,30.76094],"type":"Point"}
}