{
  "type": "Feature",
  "properties": {
    "gn:admin1_code":"8",
    "gn:asciiname":"Now Kandeh",
    "gn:country_code":"IR",
    "gn:dem":-15,
    "gn:feature_class":"P",
    "gn:feature_code":"PPL",
    "gn:name":"Now Kandeh",
    "gn:population":0,
    "gn:timezone":"Asia/Tehran",
    "iso:country":"IR",
    "name:fas_x_preferred":[
        "\u0646\u0648 \u06a9\u0646\u062f\u0647"
    ],
    "name:fas_x_variant":[
        "\u0646\u0648\u06a9\u0646\u062f\u0647"
    ],
    "name:fra_x_preferred":[
        "Now Kandeh"
    ],
    "name:msa_x_preferred":[
        "Now Kandeh"
    ],
    "name:ukr_x_preferred":[
        "\u041d\u043e\u0432\u043a\u0430\u043d\u0434\u0435"
    ],
    "wof:name":"Now Kandeh",
    "wof:placetype":"locality"
},
  "geometry": {"coordinates":[49.1082,37.6044],"type":"Point"}
}