{
  "type": "Feature",
  "properties": {
    "gn:admin1_code":"22",
    "gn:asciiname":"Zard",
    "gn:country_code":"IR",
    "gn:dem":4,
    "gn:feature_class":"P",
    "gn:feature_code":"PPL",
    "gn:name":"Z\u0101rd",
    "gn:population":0,
    "gn:timezone":"Asia/Tehran",
    "iso:country":"IR",
    "name:cat_x_preferred":[
        "Zard"
    ],
    "name:deu_x_preferred":[
        "Zard"
    ],
    "name:fas_x_preferred":[
        "\u0632\u0627\u0631\u062f"
    ],
    "name:fas_x_variant":[
        "Z\u0101rd"
    ],
    "name:ita_x_preferred":[
        "Zard"
    ],
    "name:pol_x_preferred":[
        "Zard"
    ],
    "name:por_x_preferred":[
        "Zard"
    ],
    "name:rus_x_preferred":[
        "Zard"
    ],
    "name:spa_x_preferred":[
        "Zard"
    ],
    "name:tha_x_preferred":[
        "\u0e0b\u0e32\u0e23\u0e4c\u0e14"
    ],
    "wof:name":"Zard",
    "wof:placetype":"locality"
},
  "geometry": {"coordinates":[52.72667,27.37194],"type":"Point"}
}