{
  "type": "Feature",
  "properties": {
    "gn:admin1_code":"5.0",
    "gn:asciiname":"Jadval-e Now",
    "gn:country_code":"IR",
    "gn:dem":1789,
    "gn:feature_class":"P",
    "gn:feature_code":"PPL",
    "gn:name":"Jadval-e Now",
    "gn:population":0,
    "gn:timezone":"Asia/Tehran",
    "iso:country":"IR",
    "name:fas_x_preferred":[
        "S\u0101d\u0101t\u0101b\u0101d"
    ],
    "name:fas_x_variant":[
        "\u0633\u0627\u062f\u0627\u062a \u0622\u0628\u0627\u062f",
        "\u062c\u062f\u0648\u0644 \u0646\u0648"
    ],
    "name:und_x_variant":[
        "\u0633\u0627\u062f\u0627\u062a \u0622\u0628\u0627\u062f",
        "Jadval-e Now"
    ],
    "wof:name":"Jadval-e Now",
    "wof:placetype":"locality"
},
  "geometry": {"coordinates":[51.4934,30.47493],"type":"Point"}
}