{
  "type": "Feature",
  "properties": {
    "gn:admin1_code":"5",
    "gn:asciiname":"Vazgestan",
    "gn:country_code":"IR",
    "gn:dem":2073,
    "gn:feature_class":"P",
    "gn:feature_code":"PPL",
    "gn:name":"Vazgest\u0101n",
    "gn:population":0,
    "gn:timezone":"Asia/Tehran",
    "iso:country":"IR",
    "name:ara_x_preferred":[
        "\u0648\u0632\u063a\u0633\u062a\u0627\u0646"
    ],
    "name:fas_x_preferred":[
        "Vazgest\u0101n"
    ],
    "name:fas_x_variant":[
        "\u0648\u0632\u06af\u0633\u062a\u0627\u0646"
    ],
    "name:und_x_variant":[
        "\u0648\u0632\u06af\u0633\u062a\u0627\u0646"
    ],
    "wof:name":"Vazgestan",
    "wof:placetype":"locality"
},
  "geometry": {"coordinates":[51.35036,30.61473],"type":"Point"}
}