{
  "type": "Feature",
  "properties": {
    "gn:admin1_code":"10",
    "gn:asciiname":"Burbur",
    "gn:country_code":"IR",
    "gn:dem":881,
    "gn:feature_class":"P",
    "gn:feature_code":"PPL",
    "gn:name":"B\u016brb\u016br",
    "gn:population":0,
    "gn:timezone":"Asia/Tehran",
    "iso:country":"IR",
    "name:fas_x_preferred":[
        "B\u016brb\u016br"
    ],
    "name:fas_x_variant":[
        "\u0628\u0648\u0631\u0628\u0648\u0631"
    ],
    "name:und_x_variant":[
        "\u0628\u0648\u0631\u0628\u0648\u0631"
    ],
    "wof:name":"Burbur",
    "wof:placetype":"locality"
},
  "geometry": {"coordinates":[46.769,33.5662],"type":"Point"}
}