{
  "type": "Feature",
  "properties": {
    "gn:admin1_code":"29",
    "gn:asciiname":"Hoseyn Lulu",
    "gn:country_code":"IR",
    "gn:dem":2540,
    "gn:feature_class":"P",
    "gn:feature_code":"PPL",
    "gn:name":"\u1e28oseyn L\u016bl\u016b",
    "gn:population":0,
    "gn:timezone":"Asia/Tehran",
    "iso:country":"IR",
    "name:fas_x_preferred":[
        "\u062d\u0633\u06cc\u0646 \u0644\u0648\u0644\u0648"
    ],
    "name:fas_x_variant":[
        "\u1e28oseyn L\u016bl\u016b"
    ],
    "wof:name":"Hoseyn Lulu",
    "wof:placetype":"locality"
},
  "geometry": {"coordinates":[57.6192,29.0405],"type":"Point"}
}