{
  "type": "Feature",
  "properties": {
    "gn:admin1_code":"35.0",
    "gn:asciiname":"Sarus",
    "gn:country_code":"IR",
    "gn:dem":1279,
    "gn:feature_class":"P",
    "gn:feature_code":"PPL",
    "gn:name":"S\u0101r\u016bs",
    "gn:population":0,
    "gn:timezone":"Asia/Tehran",
    "iso:country":"IR",
    "name:deu_x_preferred":[
        "Sarus"
    ],
    "name:fas_x_preferred":[
        "\u0633\u0627\u0631\u0648\u0633"
    ],
    "name:fas_x_variant":[
        "S\u0101r\u016bs"
    ],
    "name:lat_x_preferred":[
        "Sarus"
    ],
    "wof:name":"Sarus",
    "wof:placetype":"locality"
},
  "geometry": {"coordinates":[51.38333,36.50728],"type":"Point"}
}