{
  "type": "Feature",
  "properties": {
    "gn:admin1_code":"23",
    "gn:asciiname":"Deh-e Aqa",
    "gn:country_code":"IR",
    "gn:dem":1584,
    "gn:feature_class":"P",
    "gn:feature_code":"PPL",
    "gn:name":"Deh-e \u0100q\u0101",
    "gn:population":0,
    "gn:timezone":"Asia/Tehran",
    "iso:country":"IR",
    "name:fas_x_preferred":[
        "\u0622\u0642\u0627"
    ],
    "name:fas_x_variant":[
        "\u0622\u063a\u064e",
        "\u062f\u0647 \u0622\u0642\u0627",
        "Deh-e \u0100q\u0101"
    ],
    "name:und_x_variant":[
        "\u0100q\u0101",
        "\u0100gha"
    ],
    "wof:name":"Deh-e Aqa",
    "wof:placetype":"locality"
},
  "geometry": {"coordinates":[48.1794,33.8725],"type":"Point"}
}