{
  "type": "Feature",
  "properties": {
    "gn:admin1_code":"44",
    "gn:asciiname":"Gajereh",
    "gn:country_code":"IR",
    "gn:dem":2516,
    "gn:feature_class":"P",
    "gn:feature_code":"PPL",
    "gn:name":"G\u0101jereh",
    "gn:population":0,
    "gn:timezone":"Asia/Tehran",
    "iso:country":"IR",
    "name:fas_x_preferred":[
        "G\u0101jereh"
    ],
    "name:fas_x_variant":[
        "\u06af\u0627\u062c\u0631\u0647"
    ],
    "wof:name":"Gajereh",
    "wof:placetype":"locality"
},
  "geometry": {"coordinates":[51.39166,36.06179],"type":"Point"}
}