{
  "type": "Feature",
  "properties": {
    "gn:admin1_code":"11",
    "gn:asciiname":"Fatuyeh",
    "gn:country_code":"IR",
    "gn:dem":479,
    "gn:feature_class":"P",
    "gn:feature_code":"PPL",
    "gn:name":"Fat\u016byeh",
    "gn:population":0,
    "gn:timezone":"Asia/Tehran",
    "iso:country":"IR",
    "name:fas_x_preferred":[
        "\u0641\u064e\u062a\u064f\u0651\u064a\u0650\u0647"
    ],
    "name:fas_x_variant":[
        "Fat\u016byeh",
        "\u0641\u062a\u0648\u06cc\u0647"
    ],
    "name:und_x_variant":[
        "Fatooyeh",
        "\u0641\u062a\u0648\u06cc\u0647"
    ],
    "wof:name":"Fatuyeh",
    "wof:placetype":"locality"
},
  "geometry": {"coordinates":[54.40998,27.33084],"type":"Point"}
}