{
  "type": "Feature",
  "properties": {
    "gn:admin1_code":"15.0",
    "gn:asciiname":"Darreh Khoshk",
    "gn:country_code":"IR",
    "gn:dem":600,
    "gn:feature_class":"P",
    "gn:feature_code":"PPL",
    "gn:name":"Darreh Khoshk",
    "gn:population":0,
    "gn:timezone":"Asia/Tehran",
    "iso:country":"IR",
    "name:fas_x_preferred":[
        "\u062f\u0631\u0651\u0647 \u062e\u0634\u06a9"
    ],
    "name:fas_x_variant":[
        "\u062f\u0631\u0647 \u062e\u0634\u06a9"
    ],
    "wof:name":"Darreh Khoshk",
    "wof:placetype":"locality"
},
  "geometry": {"coordinates":[49.9132,31.17181],"type":"Point"}
}