{
  "type": "Feature",
  "properties": {
    "gn:admin1_code":"15",
    "gn:asciiname":"Ab Sorkh",
    "gn:country_code":"IR",
    "gn:dem":1118,
    "gn:feature_class":"P",
    "gn:feature_code":"PPL",
    "gn:name":"\u0100b Sorkh",
    "gn:population":0,
    "gn:timezone":"Asia/Tehran",
    "iso:country":"IR",
    "name:fas_x_preferred":[
        "\u0100b Sorkh"
    ],
    "wof:name":"Ab Sorkh",
    "wof:placetype":"locality"
},
  "geometry": {"coordinates":[50.13306,31.81583],"type":"Point"}
}