{
  "type": "Feature",
  "properties": {
    "gn:admin1_code":"1",
    "gn:asciiname":"Qarah Aghaj",
    "gn:country_code":"IR",
    "gn:dem":1303,
    "gn:feature_class":"P",
    "gn:feature_code":"PPL",
    "gn:name":"Qarah \u0100gh\u0101j",
    "gn:population":0,
    "gn:timezone":"Asia/Tehran",
    "iso:country":"IR",
    "name:fas_x_preferred":[
        "\u0642\u0631\u0647 \u0622\u063a\u0627\u062c"
    ],
    "name:fas_x_variant":[
        "\u0642\u064e\u0631\u0650\u0647 \u0622\u063a\u0627\u062c",
        "Qareh \u0100gh\u0101j",
        "Qarah \u0100gh\u0101j"
    ],
    "wof:name":"Qarah Aghaj",
    "wof:placetype":"locality"
},
  "geometry": {"coordinates":[45.1495,37.538],"type":"Point"}
}