{
  "type": "Feature",
  "properties": {
    "gn:admin1_code":"1",
    "gn:asciiname":"Qarah Aghaj",
    "gn:country_code":"IR",
    "gn:dem":1303,
    "gn:feature_class":"P",
    "gn:feature_code":"PPL",
    "gn:name":"Qarah \u0100gh\u0101j",
    "gn:population":0,
    "gn:timezone":"Asia/Tehran",
    "iso:country":"IR",
    "name:ara_x_preferred":[
        "\u0642\u0631\u0629 \u0622\u063a\u0627\u062c"
    ],
    "name:azb_x_preferred":[
        "\u0642\u0631\u0647\u200c\u0622\u063a\u0627\u062c"
    ],
    "name:aze_x_preferred":[
        "Qaraa\u011fac"
    ],
    "name:fas_x_preferred":[
        "\u0642\u0631\u0647 \u0622\u063a\u0627\u062c"
    ],
    "name:fas_x_variant":[
        "\u0642\u064e\u0631\u0650\u0647 \u0622\u063a\u0627\u062c",
        "Qareh \u0100gh\u0101j",
        "Qarah \u0100gh\u0101j",
        "\u0642\u0631\u0647\u200c\u0622\u063a\u0627\u062c"
    ],
    "name:ita_x_preferred":[
        "Qarah Aghaj"
    ],
    "name:mlg_x_preferred":[
        "Qarah Aghaj"
    ],
    "name:msa_x_preferred":[
        "Qarah Aghaj"
    ],
    "name:mzn_x_preferred":[
        "\u0642\u0631\u0647\u200c\u0622\u063a\u0627\u062c"
    ],
    "name:tur_x_preferred":[
        "Karaa\u011fa\u00e7"
    ],
    "wof:name":"Qarah Aghaj",
    "wof:placetype":"locality"
},
  "geometry": {"coordinates":[45.1495,37.538],"type":"Point"}
}