{
  "type": "Feature",
  "properties": {
    "gn:admin1_code":"28.0",
    "gn:asciiname":"Changarzeh",
    "gn:country_code":"IR",
    "gn:dem":2295,
    "gn:feature_class":"P",
    "gn:feature_code":"PPL",
    "gn:name":"Changarzeh",
    "gn:population":0,
    "gn:timezone":"Asia/Tehran",
    "iso:country":"IR",
    "name:fas_x_preferred":[
        "Ma\u2018dan-e Cham Darreh"
    ],
    "name:fas_x_variant":[
        "\u0686\u0646\u06af\u0631\u0632\u0647"
    ],
    "name:und_x_variant":[
        "Cham Darreh"
    ],
    "wof:name":"Changarzeh",
    "wof:placetype":"locality"
},
  "geometry": {"coordinates":[51.94143,33.26339],"type":"Point"}
}