{
  "type": "Feature",
  "properties": {
    "gn:admin1_code":"39.0",
    "gn:asciiname":"Edrisabad",
    "gn:country_code":"IR",
    "gn:dem":926,
    "gn:feature_class":"P",
    "gn:feature_code":"PPL",
    "gn:name":"Edr\u012bs\u0101b\u0101d",
    "gn:population":0,
    "gn:timezone":"Asia/Tehran",
    "iso:country":"IR",
    "name:fas_x_preferred":[
        "\u0627\u062f\u0631\u064a\u0633 \u0622\u0628\u0627\u062f"
    ],
    "name:fas_x_variant":[
        "\u0627\u0650\u062f\u0631\u0650\u0633 \u0622\u0628\u0627\u062f",
        "Edr\u012bs\u0101b\u0101d",
        "\u0627\u062f\u0631\u06cc\u0633\u200c\u0622\u0628\u0627\u062f"
    ],
    "name:und_x_variant":[
        "Edres\u0101b\u0101d"
    ],
    "wof:name":"Edrisabad",
    "wof:placetype":"locality"
},
  "geometry": {"coordinates":[50.5324,34.8449],"type":"Point"}
}