{
  "type": "Feature",
  "properties": {
    "gn:admin1_code":"5.0",
    "gn:asciiname":"Esper",
    "gn:country_code":"IR",
    "gn:dem":957,
    "gn:feature_class":"P",
    "gn:feature_code":"PPL",
    "gn:name":"Esper",
    "gn:population":0,
    "gn:timezone":"Asia/Tehran",
    "iso:country":"IR",
    "name:fas_x_preferred":[
        "\u0627\u0633\u067e\u0631"
    ],
    "name:und_x_variant":[
        "\u0627\u0633\u067e\u0631"
    ],
    "wof:name":"Esper",
    "wof:placetype":"locality"
},
  "geometry": {"coordinates":[50.74705,30.60024],"type":"Point"}
}