{
  "type": "Feature",
  "properties": {
    "gn:admin1_code":"5.0",
    "gn:asciiname":"Esper",
    "gn:country_code":"IR",
    "gn:dem":957,
    "gn:feature_class":"P",
    "gn:feature_code":"PPL",
    "gn:name":"Esper",
    "gn:population":0,
    "gn:timezone":"Asia/Tehran",
    "iso:country":"IR",
    "name:deu_x_preferred":[
        "Esper"
    ],
    "name:fas_x_preferred":[
        "\u0627\u0633\u067e\u0631"
    ],
    "name:fra_x_preferred":[
        "Esper"
    ],
    "name:ita_x_preferred":[
        "Esper"
    ],
    "name:jpn_x_preferred":[
        "\u30a8\u30b9\u30d1\u30fc"
    ],
    "name:nld_x_preferred":[
        "Esper"
    ],
    "name:rus_x_preferred":[
        "\u042d\u0441\u043f\u0435\u0440"
    ],
    "name:swe_x_preferred":[
        "Esper"
    ],
    "name:ukr_x_preferred":[
        "\u0415\u0441\u043f\u0435\u0440"
    ],
    "name:vie_x_preferred":[
        "Esper"
    ],
    "wof:name":"Esper",
    "wof:placetype":"locality"
},
  "geometry": {"coordinates":[50.74705,30.60024],"type":"Point"}
}