{
  "type": "Feature",
  "properties": {
    "gn:admin1_code":"37",
    "gn:asciiname":"Anbar Alum",
    "gn:country_code":"IR",
    "gn:dem":3,
    "gn:feature_class":"P",
    "gn:feature_code":"PPL",
    "gn:name":"Anb\u0101r \u0100l\u016bm",
    "gn:population":0,
    "gn:timezone":"Asia/Tehran",
    "iso:country":"IR",
    "name:ara_x_preferred":[
        "\u0627\u0646\u0628\u0627\u0631\u0623\u0644\u0648\u0645"
    ],
    "name:aze_x_preferred":[
        "Anbar Alum"
    ],
    "name:fas_x_preferred":[
        "\u0634\u0627\u0647 \u0645\u0632\u0631\u0639\u0647"
    ],
    "name:fas_x_variant":[
        "Sh\u0101h Mazra\u2018eh",
        "\u0627\u0646\u0628\u0627\u0631 \u0622\u0644\u0648\u0645",
        "\u0627\u0646\u0628\u0627\u0631 \u0627\u0644\u0648\u0645",
        "\u0627\u0646\u0628\u0627\u0631\u0622\u0644\u0648\u0645"
    ],
    "name:ita_x_preferred":[
        "Anbar Alum"
    ],
    "name:mlg_x_preferred":[
        "Anbar Olum"
    ],
    "name:msa_x_preferred":[
        "Anbar Olum"
    ],
    "name:tuk_x_preferred":[
        "Ambarolum"
    ],
    "name:tur_x_preferred":[
        "Anbar Alum"
    ],
    "name:und_x_variant":[
        "Anb\u0101r \u0100l\u016bm",
        "Anb\u0101r Ol\u016bm",
        "Anb\u0101r Olom"
    ],
    "wof:name":"Anbar Alum",
    "wof:placetype":"locality"
},
  "geometry": {"coordinates":[54.61968,37.1331],"type":"Point"}
}