{
  "type": "Feature",
  "properties": {
    "gn:admin1_code":"35.0",
    "gn:asciiname":"Khares",
    "gn:country_code":"IR",
    "gn:dem":1839,
    "gn:feature_class":"P",
    "gn:feature_code":"PPL",
    "gn:name":"Kh\u0101res",
    "gn:population":0,
    "gn:timezone":"Asia/Tehran",
    "iso:country":"IR",
    "name:fas_x_preferred":[
        "\u062e\u0627\u0631\u0633"
    ],
    "name:und_x_variant":[
        "Kh\u0101res",
        "\u062e\u0627\u0631\u0633"
    ],
    "wof:name":"Khares",
    "wof:placetype":"locality"
},
  "geometry": {"coordinates":[51.19136,36.35566],"type":"Point"}
}