{
  "type": "Feature",
  "properties": {
    "gn:admin1_code":"1",
    "gn:asciiname":"Arbat-e `Olya",
    "gn:country_code":"IR",
    "gn:dem":2031,
    "gn:feature_class":"P",
    "gn:feature_code":"PPL",
    "gn:name":"Arba\u0163-e \u2018Oly\u0101",
    "gn:population":0,
    "gn:timezone":"Asia/Tehran",
    "iso:country":"IR",
    "name:fas_x_preferred":[
        "\u0627\u0631\u0628\u0637 \u0639\u0644\u06cc\u0627"
    ],
    "name:fas_x_variant":[
        "Arba\u0163 \u2018Oly\u0101",
        "Arba\u0163-e \u2018Oly\u0101"
    ],
    "wof:name":"Arbat-e `Olya",
    "wof:placetype":"locality"
},
  "geometry": {"coordinates":[46.7082,37.0666],"type":"Point"}
}