{
  "type": "Feature",
  "properties": {
    "gn:admin1_code":"33",
    "gn:asciiname":"Lam`eh Eslam-e Pa'in",
    "gn:country_code":"IR",
    "gn:dem":816,
    "gn:feature_class":"P",
    "gn:feature_code":"PPL",
    "gn:name":"Lam\u2018eh Esl\u0101m-e P\u0101\u2019\u012bn",
    "gn:population":0,
    "gn:timezone":"Asia/Tehran",
    "iso:country":"IR",
    "name:fas_x_preferred":[
        "\u0644\u0645\u0639\u0647 \u0627\u0633\u0644\u0627\u0645 \u067e\u0627\u0626\u06cc\u0646"
    ],
    "name:und_x_variant":[
        "Lam\u2018eh Esl\u0101m-e P\u0101\u2019\u012bn"
    ],
    "wof:name":"Lam`eh Eslam-e Pa'in",
    "wof:placetype":"locality"
},
  "geometry": {"coordinates":[46.6841,38.9099],"type":"Point"}
}