{
  "type": "Feature",
  "properties": {
    "gn:admin1_code":"15",
    "gn:asciiname":"Hureh",
    "gn:country_code":"IR",
    "gn:dem":602,
    "gn:feature_class":"P",
    "gn:feature_code":"PPL",
    "gn:name":"H\u016breh",
    "gn:population":0,
    "gn:timezone":"Asia/Tehran",
    "iso:country":"IR",
    "name:fas_x_preferred":[
        "H\u016breh"
    ],
    "wof:name":"Hureh",
    "wof:placetype":"locality"
},
  "geometry": {"coordinates":[49.66667,31.53333],"type":"Point"}
}