{
  "type": "Feature",
  "properties": {
    "gn:admin1_code":"41.0",
    "gn:asciiname":"Semani-ye Bala",
    "gn:country_code":"IR",
    "gn:dem":1903,
    "gn:feature_class":"P",
    "gn:feature_code":"PPL",
    "gn:name":"Seman\u012b-ye B\u0101l\u0101",
    "gn:population":0,
    "gn:timezone":"Asia/Tehran",
    "iso:country":"IR",
    "name:fas_x_preferred":[
        "\u0633\u0645\u0646\u06cc \u0628\u0627\u0644\u0627"
    ],
    "name:und_x_variant":[
        "Seman\u012b-ye B\u0101l\u0101"
    ],
    "wof:name":"Semani-ye Bala",
    "wof:placetype":"locality"
},
  "geometry": {"coordinates":[59.4213,32.05194],"type":"Point"}
}