{
  "type": "Feature",
  "properties": {
    "gn:admin1_code":"13",
    "gn:asciiname":"Kashanbeh-ye Chahardangi",
    "gn:country_code":"IR",
    "gn:dem":1454,
    "gn:feature_class":"P",
    "gn:feature_code":"PPL",
    "gn:name":"K\u0101shanbeh-ye Chah\u0101rd\u0101ng\u012b",
    "gn:population":0,
    "gn:timezone":"Asia/Tehran",
    "iso:country":"IR",
    "name:fas_x_preferred":[
        "\u06a9\u0627\u0634\u0646\u0628\u0647 \u0686\u0647\u0627\u0631\u062f\u0627\u0646\u06af\u06cc"
    ],
    "name:fas_x_variant":[
        "K\u0101shanbeh-ye Chah\u0101r D\u0101ng\u012b",
        "K\u0101shanbeh-ye Chah\u0101rd\u0101ng\u012b"
    ],
    "wof:name":"Kashanbeh-ye Chahardangi",
    "wof:placetype":"locality"
},
  "geometry": {"coordinates":[46.6556,34.2983],"type":"Point"}
}