{
  "type": "Feature",
  "properties": {
    "gn:admin1_code":"22",
    "gn:asciiname":"Mazare`i",
    "gn:country_code":"IR",
    "gn:dem":95,
    "gn:feature_class":"P",
    "gn:feature_code":"PPL",
    "gn:name":"Maz\u0101re\u2018\u012b",
    "gn:population":0,
    "gn:timezone":"Asia/Tehran",
    "iso:country":"IR",
    "name:fas_x_preferred":[
        "\u0645\u0632\u0627\u0631\u0639\u06cc"
    ],
    "name:fas_x_variant":[
        "\u0645\u064e\u0632\u0627\u0631\u06cc",
        "Maz\u0101re\u2018\u012b"
    ],
    "name:und_x_variant":[
        "Mazarai",
        "Maz\u0101r\u012b"
    ],
    "wof:name":"Mazare`i",
    "wof:placetype":"locality"
},
  "geometry": {"coordinates":[51.23195,29.48459],"type":"Point"}
}