{
  "type": "Feature",
  "properties": {
    "gn:admin1_code":"23",
    "gn:asciiname":"Darreh Kabud",
    "gn:country_code":"IR",
    "gn:dem":1881,
    "gn:feature_class":"P",
    "gn:feature_code":"PPL",
    "gn:name":"Darreh Kab\u016bd",
    "gn:population":0,
    "gn:timezone":"Asia/Tehran",
    "iso:country":"IR",
    "name:ara_x_preferred":[
        "\u062f\u0631\u0629 \u06a9\u0628\u0648\u062f"
    ],
    "name:ceb_x_preferred":[
        "Darreh Kab\u016bd"
    ],
    "name:fas_x_preferred":[
        "\u062f\u0631\u0651\u0647 \u06a9\u0628\u0648\u062f"
    ],
    "name:fas_x_variant":[
        "Darreh Kab\u016bd \u2018Oly\u0101",
        "Darreh Kab\u016bd",
        "\u062f\u0631\u0647 \u06a9\u0628\u0648\u062f"
    ],
    "name:swe_x_preferred":[
        "Darreh Kab\u016bd"
    ],
    "name:und_x_variant":[
        "Darreh \u1e28oseyn\u012b"
    ],
    "wof:name":"Darreh Kabud",
    "wof:placetype":"locality"
},
  "geometry": {"coordinates":[48.73945,33.66813],"type":"Point"}
}