{
  "type": "Feature",
  "properties": {
    "gn:admin1_code":"15",
    "gn:asciiname":"Tavileh-ye Kuchak",
    "gn:country_code":"IR",
    "gn:dem":31,
    "gn:feature_class":"P",
    "gn:feature_code":"PPL",
    "gn:name":"\u0162av\u012bleh-ye K\u016bchak",
    "gn:population":0,
    "gn:timezone":"Asia/Tehran",
    "iso:country":"IR",
    "name:ara_x_preferred":[
        "\u0637\u0648\u064a\u0644\u0629 \u0627\u0644\u0635\u063a\u0631\u0649"
    ],
    "name:azb_x_preferred":[
        "\u0637\u0648\u06cc\u0644\u0647 \u0643\u0648\u0686\u0643(\u0627\u0647\u0648\u0627\u0632)"
    ],
    "name:ceb_x_preferred":[
        "\u0162oveyleh-ye K\u016bchak"
    ],
    "name:fas_x_preferred":[
        "\u0637\u0648\u06cc\u0644\u0647 \u06a9\u0648\u0686\u06a9"
    ],
    "name:fas_x_variant":[
        "\u0162oveyleh-ye K\u016bchek",
        "\u0162oveyleh-ye K\u016bchak"
    ],
    "name:swe_x_preferred":[
        "\u0162oveyleh-ye K\u016bchak"
    ],
    "name:und_x_variant":[
        "Loveyleh-ye K\u016bchek",
        "\u0162av\u012bleh K\u016bchek",
        "Tavileh\u00e9 Koochak",
        "\u0162av\u012bleh-ye K\u016bchak",
        "\u0162av\u012bleh-ye K\u016bchek",
        "\u0162av\u012bleh-ye Ma\u2018\u0101rej"
    ],
    "wof:name":"Tavileh-ye Kuchak",
    "wof:placetype":"locality"
},
  "geometry": {"coordinates":[49.11522,31.33361],"type":"Point"}
}