{
  "type": "Feature",
  "properties": {
    "gn:admin1_code":"8.0",
    "gn:asciiname":"Siah Chal",
    "gn:country_code":"IR",
    "gn:dem":-14,
    "gn:feature_class":"P",
    "gn:feature_code":"PPL",
    "gn:name":"S\u012b\u0101h Ch\u0101l",
    "gn:population":0,
    "gn:timezone":"Asia/Tehran",
    "iso:country":"IR",
    "name:fas_x_preferred":[
        "\u062e\u0648\u0646\u0647 \u067e\u0627 \u062e\u0627\u0644\u0647"
    ],
    "name:fas_x_variant":[
        "Kh\u016bneh P\u0101 Kh\u0101leh",
        "\u0633\u06cc\u0627\u0647 \u0686\u0627\u0644"
    ],
    "name:und_x_variant":[
        "S\u012b\u0101h Ch\u0101l"
    ],
    "wof:name":"Siah Chal",
    "wof:placetype":"locality"
},
  "geometry": {"coordinates":[48.98809,37.75157],"type":"Point"}
}