{
  "type": "Feature",
  "properties": {
    "gn:admin1_code":"26",
    "gn:asciiname":"Yabarak",
    "gn:country_code":"IR",
    "gn:dem":1130,
    "gn:feature_class":"P",
    "gn:feature_code":"PPL",
    "gn:name":"Yab\u0101rak",
    "gn:population":0,
    "gn:timezone":"Asia/Tehran",
    "iso:country":"IR",
    "name:fas_x_preferred":[
        "\u06cc\u0628\u0627\u0631\u06a9"
    ],
    "name:fas_x_variant":[
        "Yab\u0101rak"
    ],
    "name:urd_x_preferred":[
        "\u06cc\u0628\u0627\u0631\u06a9"
    ],
    "wof:name":"Yabarak",
    "wof:placetype":"locality"
},
  "geometry": {"coordinates":[50.9941,35.619],"type":"Point"}
}