{
  "type": "Feature",
  "properties": {
    "gn:admin1_code":"22",
    "gn:asciiname":"Hammalabad",
    "gn:country_code":"IR",
    "gn:dem":432,
    "gn:feature_class":"P",
    "gn:feature_code":"PPL",
    "gn:name":"\u1e28amm\u0101l\u0101b\u0101d",
    "gn:population":0,
    "gn:timezone":"Asia/Tehran",
    "iso:country":"IR",
    "name:fas_x_preferred":[
        "\u062c\u064e\u0645\u0627\u0644 \u0622\u0628\u0627\u062f"
    ],
    "name:fas_x_variant":[
        "Jam\u0101l\u0101b\u0101d",
        "\u062d\u0645\u0627\u0644 \u0622\u0628\u0627\u062f"
    ],
    "name:und_x_variant":[
        "\u1e28amm\u0101l\u0101b\u0101d"
    ],
    "wof:name":"Hammalabad",
    "wof:placetype":"locality"
},
  "geometry": {"coordinates":[52.14528,27.98116],"type":"Point"}
}