{
  "type": "Feature",
  "properties": {
    "gn:admin1_code":"23",
    "gn:asciiname":"Safarabad",
    "gn:country_code":"IR",
    "gn:dem":1965,
    "gn:feature_class":"P",
    "gn:feature_code":"PPL",
    "gn:name":"\u015eafar\u0101b\u0101d",
    "gn:population":0,
    "gn:timezone":"Asia/Tehran",
    "iso:country":"IR",
    "name:fas_x_preferred":[
        "\u0635\u0641\u0631 \u0622\u0628\u0627\u062f"
    ],
    "name:fas_x_variant":[
        "\u015eafar\u0101b\u0101d"
    ],
    "wof:name":"Safarabad",
    "wof:placetype":"locality"
},
  "geometry": {"coordinates":[48.8263,33.5424],"type":"Point"}
}