{
  "type": "Feature",
  "properties": {
    "gn:admin1_code":"42",
    "gn:asciiname":"Sana'i",
    "gn:country_code":"IR",
    "gn:dem":1692,
    "gn:feature_class":"P",
    "gn:feature_code":"PPL",
    "gn:name":"San\u0101\u2019\u012b",
    "gn:population":0,
    "gn:timezone":"Asia/Tehran",
    "iso:country":"IR",
    "name:fas_x_preferred":[
        "\u0633\u0646\u0627\u0626\u06cc"
    ],
    "name:fas_x_variant":[
        "San\u0101\u2019\u012b"
    ],
    "wof:name":"Sana'i",
    "wof:placetype":"locality"
},
  "geometry": {"coordinates":[59.56092,35.42585],"type":"Point"}
}