{
  "type": "Feature",
  "properties": {
    "gn:admin1_code":"42",
    "gn:asciiname":"Kalateh-ye Kamal",
    "gn:country_code":"IR",
    "gn:dem":499,
    "gn:feature_class":"P",
    "gn:feature_code":"PPL",
    "gn:name":"Kal\u0101teh-ye Kam\u0101l",
    "gn:population":0,
    "gn:timezone":"Asia/Tehran",
    "iso:country":"IR",
    "name:fas_x_preferred":[
        "Kal\u0101teh-ye Kam\u0101l"
    ],
    "name:fas_x_variant":[
        "\u06a9\u0644\u0627\u062a\u0647 \u06a9\u0645\u0627\u0644"
    ],
    "wof:name":"Kalateh-ye Kamal",
    "wof:placetype":"locality"
},
  "geometry": {"coordinates":[60.95997,36.02321],"type":"Point"}
}