{
  "type": "Feature",
  "properties": {
    "gn:admin1_code":"32",
    "gn:asciiname":"Kildin",
    "gn:country_code":"IR",
    "gn:dem":2217,
    "gn:feature_class":"P",
    "gn:feature_code":"PPL",
    "gn:name":"Kildin",
    "gn:population":0,
    "gn:timezone":"Asia/Tehran",
    "iso:country":"IR",
    "wof:name":"Kildin",
    "wof:placetype":"locality"
},
  "geometry": {"coordinates":[48.66667,37.28333],"type":"Point"}
}