{
  "type": "Feature",
  "properties": {
    "gn:admin1_code":"8.0",
    "gn:asciiname":"Darsanak",
    "gn:country_code":"IR",
    "gn:dem":1618,
    "gn:feature_class":"P",
    "gn:feature_code":"PPL",
    "gn:name":"Darsanak",
    "gn:population":0,
    "gn:timezone":"Asia/Tehran",
    "iso:country":"IR",
    "name:fas_x_preferred":[
        "\u062f\u0631\u0633\u0646\u06a9"
    ],
    "name:und_x_variant":[
        "\u062f\u0631\u0633\u0646\u06a9"
    ],
    "wof:name":"Darsanak",
    "wof:placetype":"locality"
},
  "geometry": {"coordinates":[50.33709,36.71389],"type":"Point"}
}