{
  "type": "Feature",
  "properties": {
    "gn:admin1_code":"42",
    "gn:asciiname":"Sharifabad",
    "gn:country_code":"IR",
    "gn:dem":1456,
    "gn:feature_class":"P",
    "gn:feature_code":"PPL",
    "gn:name":"Shar\u012bf\u0101b\u0101d",
    "gn:population":0,
    "gn:timezone":"Asia/Tehran",
    "iso:country":"IR",
    "name:fas_x_preferred":[
        "\u0634\u0631\u06cc\u0641 \u0622\u0628\u0627\u062f"
    ],
    "name:fas_x_variant":[
        "Shar\u012bf\u0101b\u0101d",
        "\u0634\u0631\u06cc\u0641\u200c\u0622\u0628\u0627\u062f"
    ],
    "wof:name":"Sharifabad",
    "wof:placetype":"locality"
},
  "geometry": {"coordinates":[59.5064,36.0272],"type":"Point"}
}