{
  "type": "Feature",
  "properties": {
    "gn:admin1_code":"4.0",
    "gn:asciiname":"Vashnam-e Ashaq",
    "gn:country_code":"IR",
    "gn:dem":24,
    "gn:feature_class":"P",
    "gn:feature_code":"PPL",
    "gn:name":"Vashn\u0101m-e As\u1e29\u0101q",
    "gn:population":0,
    "gn:timezone":"Asia/Tehran",
    "iso:country":"IR",
    "name:fas_x_preferred":[
        "\u0648\u0634\u0646\u0627\u0645 \u0627\u0633\u062d\u0627\u0642"
    ],
    "name:und_x_variant":[
        "Vashn\u0101m-e As\u1e29\u0101q"
    ],
    "wof:name":"Vashnam-e Ashaq",
    "wof:placetype":"locality"
},
  "geometry": {"coordinates":[60.85868000000001,25.4444],"type":"Point"}
}