{
  "type": "Feature",
  "properties": {
    "gn:admin1_code":"35.0",
    "gn:asciiname":"Hajji Kola-ye Bala",
    "gn:country_code":"IR",
    "gn:dem":-18,
    "gn:feature_class":"P",
    "gn:feature_code":"PPL",
    "gn:name":"\u1e28\u0101jj\u012b Kol\u0101-ye B\u0101l\u0101",
    "gn:population":0,
    "gn:timezone":"Asia/Tehran",
    "iso:country":"IR",
    "name:fas_x_preferred":[
        "\u062d\u0627\u062c\u0651\u06cc \u0643\u064f\u0644\u0627\u06cc \u0639\u064f\u0644\u064a\u0627"
    ],
    "name:fas_x_variant":[
        "\u1e28\u0101jj\u012b Kol\u0101-ye \u2018Oly\u0101",
        "\u1e28\u0101jj\u012b Kol\u0101-ye B\u0101l\u0101",
        "\u062d\u0627\u062c\u06cc \u0643\u0644\u0627\u06cc \u0628\u0627\u0644\u0627"
    ],
    "wof:name":"Hajji Kola-ye Bala",
    "wof:placetype":"locality"
},
  "geometry": {"coordinates":[52.4188,36.65079],"type":"Point"}
}