{
  "type": "Feature",
  "properties": {
    "gn:admin1_code":"26.0",
    "gn:asciiname":"Yaftabad",
    "gn:country_code":"IR",
    "gn:dem":1123,
    "gn:feature_class":"P",
    "gn:feature_code":"PPL",
    "gn:name":"Y\u0101ft\u0101b\u0101d",
    "gn:population":0,
    "gn:timezone":"Asia/Tehran",
    "iso:country":"IR",
    "name:ara_x_preferred":[
        "\u064a\u0627\u0641\u062a \u0623\u0628\u0627\u062f"
    ],
    "name:fas_x_preferred":[
        "\u064a\u0627\u0641\u062a \u0622\u0628\u0627\u062f"
    ],
    "name:fas_x_variant":[
        "Y\u0101ft\u0101b\u0101d",
        "\u064a\u0627\u0641\u062a \u0622\u0628\u0627\u062f \u062c\u0646\u0648\u0628\u06cc",
        "\u06cc\u0627\u0641\u062a\u200c\u0622\u0628\u0627\u062f"
    ],
    "name:und_x_variant":[
        "Y\u0101ft\u0101b\u0101d-e Jon\u016bb\u012b"
    ],
    "name:urd_x_preferred":[
        "\u06cc\u0641\u062a \u0622\u0628\u0627\u062f"
    ],
    "wof:name":"Yaftabad",
    "wof:placetype":"locality"
},
  "geometry": {"coordinates":[51.30499,35.64354],"type":"Point"}
}