{
  "type": "Feature",
  "properties": {
    "gn:admin1_code":"28.0",
    "gn:asciiname":"Emamzadeh",
    "gn:country_code":"IR",
    "gn:dem":1636,
    "gn:feature_class":"P",
    "gn:feature_code":"PPL",
    "gn:name":"Em\u0101mz\u0101deh",
    "gn:population":0,
    "gn:timezone":"Asia/Tehran",
    "iso:country":"IR",
    "name:fas_x_preferred":[
        "\u0627\u0645\u0627\u0645\u0632\u0627\u062f\u0647"
    ],
    "name:fas_x_variant":[
        "Em\u0101mz\u0101deh"
    ],
    "wof:name":"Emamzadeh",
    "wof:placetype":"locality"
},
  "geometry": {"coordinates":[51.3637,32.5678],"type":"Point"}
}