{
  "type": "Feature",
  "properties": {
    "gn:admin1_code":"8",
    "gn:asciiname":"Vasat Mahalleh-ye Kacha",
    "gn:cc2":"IR",
    "gn:country_code":"IR",
    "gn:dem":131,
    "gn:feature_class":"P",
    "gn:feature_code":"PPL",
    "gn:name":"Vasa\u0163 Ma\u1e29alleh-ye Kach\u0101",
    "gn:population":0,
    "gn:timezone":"Asia/Tehran",
    "iso:country":"IR",
    "name:fas_x_preferred":[
        "Vasa\u0163 Ma\u1e29alleh-ye Kach\u0101"
    ],
    "name:und_x_variant":[
        "Vas\u0163 Ma\u1e29alleh-ye Kach\u0101"
    ],
    "wof:name":"Vasat Mahalleh-ye Kacha",
    "wof:placetype":"locality"
},
  "geometry": {"coordinates":[49.62194,37.0975],"type":"Point"}
}