{
  "type": "Feature",
  "properties": {
    "gn:admin1_code":"28",
    "gn:asciiname":"Pir Goli",
    "gn:country_code":"IR",
    "gn:dem":2692,
    "gn:feature_class":"P",
    "gn:feature_code":"PPL",
    "gn:name":"P\u012br Gol\u012b",
    "gn:population":0,
    "gn:timezone":"Asia/Tehran",
    "iso:country":"IR",
    "name:fas_x_preferred":[
        "P\u012br Gol\u012b"
    ],
    "name:fas_x_variant":[
        "\u067e\u06cc\u0631\u06af\u0644\u06cc"
    ],
    "name:und_x_variant":[
        "\u067e\u06cc\u0631\u06af\u0644\u06cc"
    ],
    "wof:name":"Pir Goli",
    "wof:placetype":"locality"
},
  "geometry": {"coordinates":[50.26901,32.77265],"type":"Point"}
}