{
  "type": "Feature",
  "properties": {
    "gn:admin1_code":"35.0",
    "gn:asciiname":"Bandpey",
    "gn:country_code":"IR",
    "gn:dem":300,
    "gn:feature_class":"P",
    "gn:feature_code":"PPL",
    "gn:name":"Bandpey",
    "gn:population":0,
    "gn:timezone":"Asia/Tehran",
    "iso:country":"IR",
    "name:fas_x_preferred":[
        "\u0628\u064e\u0646\u062f\u067e\u0650\u06cc"
    ],
    "name:fas_x_variant":[
        "\u0628\u0646\u062f\u067e\u06cc"
    ],
    "wof:name":"Bandpey",
    "wof:placetype":"locality"
},
  "geometry": {"coordinates":[52.48333,36.35],"type":"Point"}
}