{
  "type": "Feature",
  "properties": {
    "gn:admin1_code":"15",
    "gn:asciiname":"Sheykh Sa`dun",
    "gn:country_code":"IR",
    "gn:dem":13,
    "gn:feature_class":"P",
    "gn:feature_code":"PPL",
    "gn:name":"Sheykh Sa\u2018d\u016bn",
    "gn:population":0,
    "gn:timezone":"Asia/Tehran",
    "iso:country":"IR",
    "name:fas_x_preferred":[
        "Sheykh Sa\u2018d\u016bn"
    ],
    "name:und_x_variant":[
        "Sheykh So\u2018d\u016bn"
    ],
    "wof:name":"Sheykh Sa`dun",
    "wof:placetype":"locality"
},
  "geometry": {"coordinates":[48.05972,31.51333],"type":"Point"}
}