{
  "type": "Feature",
  "properties": {
    "gn:admin1_code":"1.0",
    "gn:asciiname":"Salus",
    "gn:country_code":"IR",
    "gn:dem":1548,
    "gn:feature_class":"P",
    "gn:feature_code":"PPL",
    "gn:name":"S\u0101l\u016bs",
    "gn:population":0,
    "gn:timezone":"Asia/Tehran",
    "iso:country":"IR",
    "name:cat_x_preferred":[
        "Salus"
    ],
    "name:deu_x_preferred":[
        "Salus"
    ],
    "name:fas_x_preferred":[
        "\u0633\u0627\u0644\u0648\u0633"
    ],
    "name:fas_x_variant":[
        "S\u0101l\u016bs"
    ],
    "name:ind_x_preferred":[
        "Salus"
    ],
    "name:ita_x_preferred":[
        "Salus"
    ],
    "name:kor_x_preferred":[
        "\uc0b4\ub8e8\uc2a4"
    ],
    "name:nld_x_preferred":[
        "Salus"
    ],
    "name:pol_x_preferred":[
        "Salus"
    ],
    "name:ron_x_preferred":[
        "Salus"
    ],
    "name:rus_x_preferred":[
        "\u0421\u0430\u043b\u044e\u0441"
    ],
    "name:swe_x_preferred":[
        "Salus"
    ],
    "name:ukr_x_preferred":[
        "\u0421\u0430\u043b\u044e\u0441"
    ],
    "name:zho_x_preferred":[
        "\u8428\u5362\u65af"
    ],
    "wof:name":"Salus",
    "wof:placetype":"locality"
},
  "geometry": {"coordinates":[45.3919,36.4765],"type":"Point"}
}