{
  "type": "Feature",
  "properties": {
    "gn:admin1_code":"13",
    "gn:asciiname":"Barzeh",
    "gn:country_code":"IR",
    "gn:dem":1727,
    "gn:feature_class":"P",
    "gn:feature_code":"PPL",
    "gn:name":"Barzeh",
    "gn:population":0,
    "gn:timezone":"Asia/Tehran",
    "iso:country":"IR",
    "name:fas_x_preferred":[
        "\u0628\u0631\u0632\u0647"
    ],
    "wof:name":"Barzeh",
    "wof:placetype":"locality"
},
  "geometry": {"coordinates":[46.5308,34.2635],"type":"Point"}
}