{
  "type": "Feature",
  "properties": {
    "gn:admin1_code":"16.0",
    "gn:asciiname":"Piran Kohneh",
    "gn:country_code":"IR",
    "gn:dem":1507,
    "gn:feature_class":"P",
    "gn:feature_code":"PPL",
    "gn:name":"P\u012br\u0101n Kohneh",
    "gn:population":0,
    "gn:timezone":"Asia/Tehran",
    "iso:country":"IR",
    "name:fas_x_preferred":[
        "\u067e\u064a\u0631\u0627\u0646\u0634\u0627\u0647"
    ],
    "name:fas_x_variant":[
        "\u067e\u06cc\u0631\u0627\u0646 \u06a9\u0647\u0646\u0647",
        "P\u012br\u0101n Kohneh"
    ],
    "name:und_x_variant":[
        "P\u012br\u0101nsh\u0101h",
        "Piran"
    ],
    "wof:name":"Piran Kohneh",
    "wof:placetype":"locality"
},
  "geometry": {"coordinates":[46.03168,35.49302],"type":"Point"}
}