{
  "type": "Feature",
  "properties": {
    "gn:admin1_code":"11",
    "gn:asciiname":"Zakin",
    "gn:country_code":"IR",
    "gn:dem":1093,
    "gn:feature_class":"P",
    "gn:feature_code":"PPL",
    "gn:name":"Z\u0101k\u012bn",
    "gn:population":0,
    "gn:timezone":"Asia/Tehran",
    "iso:country":"IR",
    "name:ara_x_preferred":[
        "\u0632\u0627\u06a9\u064a\u0646"
    ],
    "name:ceb_x_preferred":[
        "Z\u0101k\u012bn"
    ],
    "name:fas_x_preferred":[
        "\u0632\u0627\u0643\u064a\u0646"
    ],
    "name:fas_x_variant":[
        "Z\u0101k\u012bn",
        "\u0632\u0627\u06a9\u06cc\u0646"
    ],
    "name:msa_x_preferred":[
        "Zakin"
    ],
    "name:swe_x_preferred":[
        "Z\u0101k\u012bn"
    ],
    "wof:name":"Zakin",
    "wof:placetype":"locality"
},
  "geometry": {"coordinates":[56.3064,27.8311],"type":"Point"}
}