{
  "type": "Feature",
  "properties": {
    "gn:admin1_code":"28.0",
    "gn:asciiname":"Sharkat-e Ta`avoni",
    "gn:country_code":"IR",
    "gn:dem":1919,
    "gn:feature_class":"P",
    "gn:feature_code":"PPL",
    "gn:name":"Sharkat-e Ta\u2018\u0101von\u012b",
    "gn:population":0,
    "gn:timezone":"Asia/Tehran",
    "iso:country":"IR",
    "name:fas_x_preferred":[
        "\u0633\u0631\u06a9\u062a \u062a\u0639\u0627\u0648\u0646\u064a"
    ],
    "name:fas_x_variant":[
        "Sharkat-e Ta\u2018\u0101von\u012b"
    ],
    "wof:name":"Sharkat-e Ta`avoni",
    "wof:placetype":"locality"
},
  "geometry": {"coordinates":[51.0755,32.7487],"type":"Point"}
}