{
  "type": "Feature",
  "properties": {
    "gn:admin1_code":"42",
    "gn:asciiname":"Robat-e Pasakuh",
    "gn:country_code":"IR",
    "gn:dem":813,
    "gn:feature_class":"P",
    "gn:feature_code":"PPL",
    "gn:name":"Rob\u0101\u0163-e Pas\u0101k\u016bh",
    "gn:population":0,
    "gn:timezone":"Asia/Tehran",
    "iso:country":"IR",
    "name:fas_x_preferred":[
        "\u0631\u0628\u0627\u0637 \u067e\u0633\u0627\u06a9\u0648\u0647"
    ],
    "name:fas_x_variant":[
        "Rob\u0101\u0163-e Pas\u0101k\u016bh"
    ],
    "wof:name":"Robat-e Pasakuh",
    "wof:placetype":"locality"
},
  "geometry": {"coordinates":[60.0841,36.646],"type":"Point"}
}