{
  "type": "Feature",
  "properties": {
    "gn:admin1_code":"5.0",
    "gn:asciiname":"Boneh-ye Gerd",
    "gn:country_code":"IR",
    "gn:dem":2083,
    "gn:feature_class":"P",
    "gn:feature_code":"PPL",
    "gn:name":"Boneh-ye Gerd",
    "gn:population":0,
    "gn:timezone":"Asia/Tehran",
    "iso:country":"IR",
    "name:fas_x_preferred":[
        "\u0628\u0646\u0647 \u06af\u0631\u062f"
    ],
    "name:und_x_variant":[
        "\u0628\u0646\u0647 \u06af\u0631\u062f"
    ],
    "wof:name":"Boneh-ye Gerd",
    "wof:placetype":"locality"
},
  "geometry": {"coordinates":[50.8967,31.10878],"type":"Point"}
}