{
  "type": "Feature",
  "properties": {
    "gn:admin1_code":"7",
    "gn:asciiname":"Fotuhabad",
    "gn:country_code":"IR",
    "gn:dem":1626,
    "gn:feature_class":"P",
    "gn:feature_code":"PPL",
    "gn:name":"Fot\u016b\u1e29\u0101b\u0101d",
    "gn:population":0,
    "gn:timezone":"Asia/Tehran",
    "iso:country":"IR",
    "name:fas_x_preferred":[
        "\u0641\u062a\u0648\u062d \u0622\u0628\u0627\u062f"
    ],
    "name:fas_x_variant":[
        "Fot\u016b\u1e29\u0101b\u0101d",
        "\u0641\u062a\u0648\u062d\u200c\u0622\u0628\u0627\u062f"
    ],
    "name:msa_x_preferred":[
        "Fotuhabad"
    ],
    "wof:name":"Fotuhabad",
    "wof:placetype":"locality"
},
  "geometry": {"coordinates":[52.5639,30.1317],"type":"Point"}
}