{
  "type": "Feature",
  "properties": {
    "gn:admin1_code":"11",
    "gn:asciiname":"Tambu",
    "gn:country_code":"IR",
    "gn:dem":392,
    "gn:feature_class":"P",
    "gn:feature_code":"PPL",
    "gn:name":"Tamb\u016b",
    "gn:population":0,
    "gn:timezone":"Asia/Tehran",
    "iso:country":"IR",
    "name:ceb_x_preferred":[
        "Tambu"
    ],
    "name:fas_x_preferred":[
        "\u062a\u0645\u0628\u0648"
    ],
    "name:fas_x_variant":[
        "Tamb\u016b"
    ],
    "name:fin_x_preferred":[
        "Tambu"
    ],
    "name:nld_x_preferred":[
        "Tambu"
    ],
    "name:slk_x_preferred":[
        "Tambu"
    ],
    "name:slv_x_preferred":[
        "Tambu"
    ],
    "name:swe_x_preferred":[
        "Tambu"
    ],
    "wof:name":"Tambu",
    "wof:placetype":"locality"
},
  "geometry": {"coordinates":[57.5176,26.6761],"type":"Point"}
}