{
  "type": "Feature",
  "properties": {
    "gn:admin1_code":"5.0",
    "gn:asciiname":"Dashtak",
    "gn:country_code":"IR",
    "gn:dem":1935,
    "gn:feature_class":"P",
    "gn:feature_code":"PPL",
    "gn:name":"Dashtak",
    "gn:population":0,
    "gn:timezone":"Asia/Tehran",
    "iso:country":"IR",
    "name:fas_x_preferred":[
        "\u062f\u0634\u062a\u06a9"
    ],
    "name:und_x_variant":[
        "\u062f\u0634\u062a\u06a9"
    ],
    "wof:name":"Dashtak",
    "wof:placetype":"locality"
},
  "geometry": {"coordinates":[51.19444,30.65959],"type":"Point"}
}