{
  "type": "Feature",
  "properties": {
    "gn:admin1_code":"15",
    "gn:asciiname":"Kharestan-e Sofla",
    "gn:cc2":"IR",
    "gn:country_code":"IR",
    "gn:dem":301,
    "gn:feature_class":"P",
    "gn:feature_code":"PPL",
    "gn:name":"Kh\u0101rest\u0101n-e Sofl\u00e1",
    "gn:population":0,
    "gn:timezone":"Asia/Tehran",
    "iso:country":"IR",
    "name:fas_x_preferred":[
        "Kh\u0101rest\u0101n-e Sofl\u00e1"
    ],
    "name:fas_x_variant":[
        "\u062e\u0627\u0631\u0650\u0633\u062a\u0627\u0646 \u0633\u0641\u0644\u06cc",
        "\u062e\u0627\u0631\u0650\u0633\u062a\u0627\u0646 \u0648\u0633\u0637\u06cc",
        "\u062e\u0627\u0631\u0633\u062a\u0627\u0646 \u0633\u0641\u0644\u06cc"
    ],
    "name:und_x_variant":[
        "Kh\u0101r s\u016bn Sofl\u00e1",
        "Kh\u0101rest\u0101n-e Vos\u0163\u00e1"
    ],
    "wof:name":"Kharestan-e Sofla",
    "wof:placetype":"locality"
},
  "geometry": {"coordinates":[50.21361,30.65306],"type":"Point"}
}