{
  "type": "Feature",
  "properties": {
    "gn:admin1_code":"38",
    "gn:asciiname":"Dakan",
    "gn:country_code":"IR",
    "gn:dem":1316,
    "gn:feature_class":"P",
    "gn:feature_code":"PPL",
    "gn:name":"D\u0101k\u0101n",
    "gn:population":0,
    "gn:timezone":"Asia/Tehran",
    "iso:country":"IR",
    "name:fas_x_preferred":[
        "\u062f\u0627\u0643\u0627\u0646"
    ],
    "name:fas_x_variant":[
        "D\u0101k\u0101n",
        "\u062f\u0627\u06a9\u0627\u0646"
    ],
    "name:und_x_variant":[
        "Dukk\u0101n",
        "D\u0101dk\u0101n"
    ],
    "wof:name":"Dakan",
    "wof:placetype":"locality"
},
  "geometry": {"coordinates":[49.5836,35.9868],"type":"Point"}
}