{
  "type": "Feature",
  "properties": {
    "gn:admin1_code":"1",
    "gn:asciiname":"Yekhelqan",
    "gn:country_code":"IR",
    "gn:dem":1143,
    "gn:feature_class":"P",
    "gn:feature_code":"PPL",
    "gn:name":"Yekhelq\u0101n",
    "gn:population":0,
    "gn:timezone":"Asia/Tehran",
    "iso:country":"IR",
    "name:azb_x_preferred":[
        "\u06cc\u062e\u0644\u0642\u0627\u0646"
    ],
    "name:aze_x_preferred":[
        "Y\u0131x\u0131lqan"
    ],
    "name:ceb_x_preferred":[
        "Yekhelq\u0101n"
    ],
    "name:fas_x_preferred":[
        "\u064a\u0650\u062e\u0650\u0644\u0642\u0627\u0646"
    ],
    "name:fas_x_variant":[
        "\u06cc\u062e\u0644\u0642\u0627\u0646",
        "Yekhelq\u0101n"
    ],
    "name:msa_x_preferred":[
        "Yekhelqan"
    ],
    "name:swe_x_preferred":[
        "Yekhelq\u0101n"
    ],
    "name:urd_x_preferred":[
        "\u06cc\u062e\u0644\u0642\u0627\u0646"
    ],
    "wof:name":"Yekhelqan",
    "wof:placetype":"locality"
},
  "geometry": {"coordinates":[44.6229,39.5737],"type":"Point"}
}