{
  "type": "Feature",
  "properties": {
    "gn:admin1_code":"36.0",
    "gn:asciiname":"Sharbulakh",
    "gn:country_code":"IR",
    "gn:dem":1757,
    "gn:feature_class":"P",
    "gn:feature_code":"PPL",
    "gn:name":"Sharb\u016bl\u0101kh",
    "gn:population":0,
    "gn:timezone":"Asia/Tehran",
    "iso:country":"IR",
    "name:fas_x_preferred":[
        "\u0634\u0631\u0628\u0648\u0644\u0627\u062e"
    ],
    "name:und_x_variant":[
        "Sharb\u016bl\u0101kh"
    ],
    "wof:name":"Sharbulakh",
    "wof:placetype":"locality"
},
  "geometry": {"coordinates":[48.75517,36.50468],"type":"Point"}
}