{
  "type": "Feature",
  "properties": {
    "gn:admin1_code":"32.0",
    "gn:asciiname":"Qareh Qabaq-e Sofla",
    "gn:country_code":"IR",
    "gn:dem":125,
    "gn:feature_class":"P",
    "gn:feature_code":"PPL",
    "gn:name":"Qareh Q\u0101b\u0101q-e Sofl\u0101",
    "gn:population":0,
    "gn:timezone":"Asia/Tehran",
    "iso:country":"IR",
    "name:azb_x_preferred":[
        "\u0622\u0634\u0627\u063a\u0627 \u0642\u0627\u0631\u0627 \u0642\u0627\u0628\u0627\u0642"
    ],
    "name:ceb_x_preferred":[
        "Qareh Q\u0101b\u0101q-e Sofl\u0101"
    ],
    "name:fas_x_preferred":[
        "\u0642\u0631\u0647\u200c\u0642\u0628\u0627\u0642 \u0633\u0641\u0644\u06cc"
    ],
    "name:msa_x_preferred":[
        "Qareh Qabaq-e Sofla"
    ],
    "name:mzn_x_preferred":[
        "\u0642\u0631\u0647\u200c\u0642\u0628\u0627\u0642 \u0633\u0641\u0644\u06cc"
    ],
    "name:swe_x_preferred":[
        "Qareh Q\u0101b\u0101q-e Sofl\u0101"
    ],
    "wof:name":"Qareh Qabaq-e Sofla",
    "wof:placetype":"locality"
},
  "geometry": {"coordinates":[47.5325,39.49306],"type":"Point"}
}