{
  "type": "Feature",
  "properties": {
    "gn:admin1_code":"35.0",
    "gn:asciiname":"Amir Deh",
    "gn:country_code":"IR",
    "gn:dem":112,
    "gn:feature_class":"P",
    "gn:feature_code":"PPL",
    "gn:name":"Am\u012br Deh",
    "gn:population":0,
    "gn:timezone":"Asia/Tehran",
    "iso:country":"IR",
    "name:fas_x_preferred":[
        "\u0627\u0645\u064a\u0631 \u062f\u0647"
    ],
    "name:fas_x_variant":[
        "Am\u012br Deh"
    ],
    "name:und_x_variant":[
        "\u064e\u0627\u0645\u064a\u0631 \u062f\u0650\u0647"
    ],
    "wof:name":"Amir Deh",
    "wof:placetype":"locality"
},
  "geometry": {"coordinates":[52.67105,36.34871],"type":"Point"}
}