{
  "type": "Feature",
  "properties": {
    "gn:admin1_code":"15",
    "gn:asciiname":"Borj-e Molla Valikhan",
    "gn:cc2":"IR",
    "gn:country_code":"IR",
    "gn:dem":483,
    "gn:feature_class":"P",
    "gn:feature_code":"PPL",
    "gn:name":"Borj-e Moll\u0101 Val\u012bkh\u0101n",
    "gn:population":0,
    "gn:timezone":"Asia/Tehran",
    "iso:country":"IR",
    "name:fas_x_preferred":[
        "Borj-e Moll\u0101 Val\u012bkh\u0101n"
    ],
    "name:und_x_variant":[
        "Burj-i- \u2018Abb\u0101s",
        "Borj-e \u2018Abb\u0101s",
        "Borj Molla Vali Khan"
    ],
    "wof:name":"Borj-e Molla Valikhan",
    "wof:placetype":"locality"
},
  "geometry": {"coordinates":[50.15,30.78333],"type":"Point"}
}