{
  "type": "Feature",
  "properties": {
    "gn:admin1_code":"4.0",
    "gn:asciiname":"`Omar",
    "gn:country_code":"IR",
    "gn:dem":1286,
    "gn:feature_class":"P",
    "gn:feature_code":"PPL",
    "gn:name":"\u2018Omar",
    "gn:population":0,
    "gn:timezone":"Asia/Tehran",
    "iso:country":"IR",
    "name:fas_x_preferred":[
        "\u2018Omar"
    ],
    "wof:name":"`Omar",
    "wof:placetype":"locality"
},
  "geometry": {"coordinates":[60.5325,30.76889000000001],"type":"Point"}
}