{
  "type": "Feature",
  "properties": {
    "gn:admin1_code":"43.0",
    "gn:asciiname":"Kalateh-ye Nowruz `Ali Khan",
    "gn:country_code":"IR",
    "gn:dem":496,
    "gn:feature_class":"P",
    "gn:feature_code":"PPLF",
    "gn:name":"Kal\u0101teh-ye Nowr\u016bz \u2018Al\u012b Kh\u0101n",
    "gn:population":0,
    "gn:timezone":"Asia/Tehran",
    "iso:country":"IR",
    "name:fas_x_preferred":[
        "Kal\u0101teh-ye Nowr\u016bz \u2018Al\u012b Kh\u0101n"
    ],
    "name:fas_x_variant":[
        "\u06a9\u0644\u0627\u062a\u0647 \u0646\u0648\u0631\u0648\u0632 \u0639\u0644\u06cc \u062e\u0627\u0646"
    ],
    "name:und_x_variant":[
        "\u06a9\u0644\u0627\u062a\u0647 \u0646\u0648\u0631\u0648\u0632 \u0639\u0644\u06cc \u062e\u0627\u0646"
    ],
    "wof:name":"Kalateh-ye Nowruz `Ali Khan",
    "wof:placetype":"locality"
},
  "geometry": {"coordinates":[56.52802,37.81092],"type":"Point"}
}