{
  "type": "Feature",
  "properties": {
    "gn:admin1_code":"29.0",
    "gn:asciiname":"Madin",
    "gn:country_code":"IR",
    "gn:dem":2544,
    "gn:feature_class":"P",
    "gn:feature_code":"PPL",
    "gn:name":"Mad\u012bn",
    "gn:population":0,
    "gn:timezone":"Asia/Tehran",
    "iso:country":"IR",
    "name:deu_x_preferred":[
        "Madin"
    ],
    "name:fas_x_preferred":[
        "Mad\u012bn"
    ],
    "wof:name":"Madin",
    "wof:placetype":"locality"
},
  "geometry": {"coordinates":[57.68472,29.01278],"type":"Point"}
}