{
  "type": "Feature",
  "properties": {
    "gn:admin1_code":"9",
    "gn:asciiname":"Qal`eh-ye `Alimoradkha'",
    "gn:country_code":"IR",
    "gn:dem":2041,
    "gn:feature_class":"P",
    "gn:feature_code":"PPL",
    "gn:name":"Qal\u2018eh-ye \u2018Al\u012bmor\u0101dkh\u0101\u2019",
    "gn:population":0,
    "gn:timezone":"Asia/Tehran",
    "iso:country":"IR",
    "name:fas_x_preferred":[
        "\u0639\u0644\u06cc \u0645\u0631\u0627\u062f \u062e\u0648\u0627\u0647"
    ],
    "name:fas_x_variant":[
        "\u0642\u064e\u0644\u0639\u0650\u0647 \u0639\u064e\u0644\u06cc \u0645\u064f\u0631\u0627\u062f",
        "\u0642\u064e\u0644\u0639\u0650\u06c0 \u0639\u064e\u0644\u06cc \u0645\u064f\u0631\u0627\u062f",
        "\u0642\u0644\u0639\u0647 \u0639\u0644\u06cc \u0645\u0631\u0627\u062f \u062e\u0627",
        "\u2018Al\u012b Mor\u0101d Khv\u0101h",
        "\u0642\u0644\u0639\u0647 \u0639\u0644\u06cc\u0645\u0631\u0627\u062f\u062e\u0627\u0621"
    ],
    "name:und_x_variant":[
        "Qal\u2018eh \u2018Al\u012b Mor\u0101d",
        "Qal\u2018eh-ye \u2018Al\u012b Mor\u0101d",
        "Qal\u2018eh-ye \u2018Al\u012b Mor\u0101d Kh\u0101",
        "Qal\u2018eh-ye \u2018Al\u012bmor\u0101dkh\u0101\u2019"
    ],
    "wof:name":"Qal`eh-ye `Alimoradkha'",
    "wof:placetype":"locality"
},
  "geometry": {"coordinates":[48.55237,34.19783],"type":"Point"}
}