{
  "type": "Feature",
  "properties": {
    "gn:admin1_code":"29",
    "gn:asciiname":"Dureh'i",
    "gn:country_code":"IR",
    "gn:dem":1139,
    "gn:feature_class":"P",
    "gn:feature_code":"PPL",
    "gn:name":"D\u016breh\u2019\u012b",
    "gn:population":0,
    "gn:timezone":"Asia/Tehran",
    "iso:country":"IR",
    "name:fas_x_preferred":[
        "\u062f\u0648\u0631\u0647 \u0627\u06cc"
    ],
    "name:fas_x_variant":[
        "Dowreh\u2019\u012b"
    ],
    "name:und_x_variant":[
        "D\u016breh\u2019\u012b"
    ],
    "wof:name":"Dureh'i",
    "wof:placetype":"locality"
},
  "geometry": {"coordinates":[57.7171,28.8749],"type":"Point"}
}