{
  "type": "Feature",
  "properties": {
    "gn:admin1_code":"29.0",
    "gn:asciiname":"Do Rudi",
    "gn:country_code":"IR",
    "gn:dem":2307,
    "gn:feature_class":"P",
    "gn:feature_code":"PPL",
    "gn:name":"Do R\u016bd\u012b",
    "gn:population":0,
    "gn:timezone":"Asia/Tehran",
    "iso:country":"IR",
    "name:fas_x_preferred":[
        "\u062f\u0648\u0631\u0648\u062f\u06cc"
    ],
    "wof:name":"Do Rudi",
    "wof:placetype":"locality"
},
  "geometry": {"coordinates":[56.91194,29.23194],"type":"Point"}
}