{
  "type": "Feature",
  "properties": {
    "gn:admin1_code":"23",
    "gn:asciiname":"Homu Kuh",
    "gn:country_code":"IR",
    "gn:dem":1857,
    "gn:feature_class":"P",
    "gn:feature_code":"PPL",
    "gn:name":"Hom\u016b K\u016bh",
    "gn:population":0,
    "gn:timezone":"Asia/Tehran",
    "iso:country":"IR",
    "name:fas_x_preferred":[
        "Ham\u0101n K\u016bh"
    ],
    "name:fas_x_variant":[
        "\u0647\u0645\u0648 \u06a9\u0648\u0647"
    ],
    "name:und_x_variant":[
        "Hom\u016b K\u016bh"
    ],
    "wof:name":"Homu Kuh",
    "wof:placetype":"locality"
},
  "geometry": {"coordinates":[49.35079,33.13411],"type":"Point"}
}