{
  "type": "Feature",
  "properties": {
    "gn:admin1_code":"8.0",
    "gn:asciiname":"Talash Mahalleh",
    "gn:country_code":"IR",
    "gn:dem":-14,
    "gn:feature_class":"P",
    "gn:feature_code":"PPL",
    "gn:name":"T\u0101lash Ma\u1e29alleh",
    "gn:population":0,
    "gn:timezone":"Asia/Tehran",
    "iso:country":"IR",
    "name:fas_x_preferred":[
        "\u062a\u0627\u0644\u0634 \u0645\u062d\u0644\u0647"
    ],
    "name:und_x_variant":[
        "T\u0101lash Ma\u1e29alleh"
    ],
    "wof:name":"Talash Mahalleh",
    "wof:placetype":"locality"
},
  "geometry": {"coordinates":[49.24206,37.50097],"type":"Point"}
}