{
  "type": "Feature",
  "properties": {
    "gn:admin1_code":"7",
    "gn:asciiname":"Tang-e Sofla",
    "gn:country_code":"IR",
    "gn:dem":680,
    "gn:feature_class":"P",
    "gn:feature_code":"PPL",
    "gn:name":"Tang-e Sofl\u00e1",
    "gn:population":0,
    "gn:timezone":"Asia/Tehran",
    "iso:country":"IR",
    "name:fas_x_preferred":[
        "\u062a\u0646\u06af \u0633\u0641\u0644\u06cc"
    ],
    "name:fas_x_variant":[
        "Tang-e Sofl\u00e1"
    ],
    "wof:name":"Tang-e Sofla",
    "wof:placetype":"locality"
},
  "geometry": {"coordinates":[52.8429,28.2393],"type":"Point"}
}