{
  "type": "Feature",
  "properties": {
    "iso:country":"IR",
    "name:aze_x_preferred":[
        "Astara"
    ],
    "name:cat_x_preferred":[
        "Astara"
    ],
    "name:ces_x_preferred":[
        "Astara"
    ],
    "name:deu_x_preferred":[
        "Astara"
    ],
    "name:epo_x_preferred":[
        "Astara"
    ],
    "name:fas_x_preferred":[
        "\u0622\u0633\u062a\u0627\u0631\u0627"
    ],
    "name:fas_x_variant":[
        "\u0100st\u0101r\u0101"
    ],
    "name:fin_x_preferred":[
        "Astara"
    ],
    "name:fra_x_preferred":[
        "Astara"
    ],
    "name:ind_x_preferred":[
        "Astara"
    ],
    "name:kor_x_preferred":[
        "\uc544\uc2a4\ud0c0\ub77c"
    ],
    "name:kur_x_preferred":[
        "Astara"
    ],
    "name:lit_x_preferred":[
        "Astara"
    ],
    "name:nld_x_preferred":[
        "Astara"
    ],
    "name:pnb_x_preferred":[
        "\u0627\u0633\u062a\u0627\u0631\u0627"
    ],
    "name:pol_x_preferred":[
        "Astara"
    ],
    "name:rus_x_preferred":[
        "\u0410\u0441\u0442\u0430\u0440\u0430"
    ],
    "name:sco_x_preferred":[
        "Astara"
    ],
    "name:tur_x_preferred":[
        "Astara"
    ],
    "name:unk_x_variant":[
        "\u0622\u0633\u062a\u0627\u0631\u0627"
    ],
    "qs:gn_country":"IR",
    "qs:gn_fcode":"PPL",
    "qs:gn_pop":39065,
    "qs:name":"Astara",
    "qs:name_adm0":"Iran",
    "qs:name_adm1":"Gilan",
    "qs:photos":39,
    "qs:photos_1k":8,
    "qs:photos_9k":1,
    "qs:photos_9r":2,
    "qs:photos_all":39,
    "qs:photos_sr":2,
    "qs:placetype":"Town",
    "qs:pop_sr":"7",
    "qs:woe_adm0":23424851,
    "wd:wordcount":36,
    "wof:name":"Astara",
    "wof:placetype":"locality",
    "wof:population":39065
},
  "geometry": {"coordinates":[48.872,38.4291],"type":"Point"}
}