{
  "type": "Feature",
  "properties": {
    "gn:admin1_code":"8.0",
    "gn:asciiname":"Amir Gavabor",
    "gn:country_code":"IR",
    "gn:dem":171,
    "gn:feature_class":"P",
    "gn:feature_code":"PPL",
    "gn:name":"Am\u012br Gav\u0101bor",
    "gn:population":0,
    "gn:timezone":"Asia/Tehran",
    "iso:country":"IR",
    "name:fas_x_preferred":[
        "Am\u012br Gav\u0101bor"
    ],
    "name:fas_x_variant":[
        "\u0627\u0645\u06cc\u0631 \u06af\u0648\u0627\u0628\u0631"
    ],
    "name:und_x_variant":[
        "\u0627\u0645\u06cc\u0631 \u06af\u0648\u0627\u0628\u0631"
    ],
    "wof:name":"Amir Gavabor",
    "wof:placetype":"locality"
},
  "geometry": {"coordinates":[50.3077,36.98014000000001],"type":"Point"}
}