{
  "type": "Feature",
  "properties": {
    "gn:admin1_code":"32",
    "gn:asciiname":"Mansurlu",
    "gn:country_code":"IR",
    "gn:dem":900,
    "gn:feature_class":"P",
    "gn:feature_code":"PPL",
    "gn:name":"Man\u015f\u016brl\u016b",
    "gn:population":0,
    "gn:timezone":"Asia/Tehran",
    "iso:country":"IR",
    "name:fas_x_preferred":[
        "\u0645\u0646\u0635\u0648\u0631\u0644\u0648"
    ],
    "name:fas_x_variant":[
        "Tappeh-ye Man\u015f\u016brl\u016b",
        "\u062a\u064e\u067e\u0650\u0651\u06c0 \u0645\u064e\u0646\u0635\u0648\u0631\u0644\u0648",
        "Man\u015f\u016brl\u016b"
    ],
    "wof:name":"Mansurlu",
    "wof:placetype":"locality"
},
  "geometry": {"coordinates":[47.842,39.0199],"type":"Point"}
}