{
  "type": "Feature",
  "properties": {
    "gn:admin1_code":"41",
    "gn:asciiname":"Mazra`eh-ye Rudkhaneh",
    "gn:country_code":"IR",
    "gn:dem":1714,
    "gn:feature_class":"P",
    "gn:feature_code":"PPL",
    "gn:name":"Mazra\u2018eh-ye R\u016bdkh\u0101neh",
    "gn:population":0,
    "gn:timezone":"Asia/Tehran",
    "iso:country":"IR",
    "name:fas_x_preferred":[
        "\u0631\u0648\u062f\u062e\u0627\u0646\u0647"
    ],
    "name:fas_x_variant":[
        "R\u016bdkh\u0101neh",
        "\u0645\u0632\u0631\u0639\u0647 \u0631\u0648\u062f\u062e\u0627\u0646\u0647"
    ],
    "name:und_x_variant":[
        "Mazra\u2018eh-ye R\u016bdkh\u0101neh"
    ],
    "wof:name":"Mazra`eh-ye Rudkhaneh",
    "wof:placetype":"locality"
},
  "geometry": {"coordinates":[59.02757,33.68107],"type":"Point"}
}