{
  "type": "Feature",
  "properties": {
    "gn:admin1_code":"29",
    "gn:asciiname":"Dalilabad",
    "gn:country_code":"IR",
    "gn:dem":649,
    "gn:feature_class":"P",
    "gn:feature_code":"PPLF",
    "gn:name":"Dal\u012bl\u0101b\u0101d",
    "gn:population":0,
    "gn:timezone":"Asia/Tehran",
    "iso:country":"IR",
    "name:fas_x_preferred":[
        "\u0639\u0644\u06cc \u0622\u0628\u0627\u062f"
    ],
    "name:fas_x_variant":[
        "Ch\u0101h-e \u2018Al\u012b\u0101b\u0101d",
        "\u2018Al\u012b\u0101b\u0101d",
        "\u062f\u0644\u064a\u0644 \u0622\u0628\u0627\u062f"
    ],
    "name:und_x_variant":[
        "Ch\u0101h-e Khod\u0101 Mor\u0101d",
        "Dal\u012bl\u0101b\u0101d",
        "Ch\u0101h-e Deymehk\u0101r",
        "Ch\u0101h-e Dal\u012bl\u0101b\u0101d"
    ],
    "wof:name":"Dalilabad",
    "wof:placetype":"locality"
},
  "geometry": {"coordinates":[57.299,28.155],"type":"Point"}
}