{
  "type": "Feature",
  "properties": {
    "gn:admin1_code":"8.0",
    "gn:asciiname":"Suti Sara",
    "gn:country_code":"IR",
    "gn:dem":1617,
    "gn:feature_class":"P",
    "gn:feature_code":"PPL",
    "gn:name":"S\u016bt\u012b Sar\u0101",
    "gn:population":0,
    "gn:timezone":"Asia/Tehran",
    "iso:country":"IR",
    "name:fas_x_preferred":[
        "S\u016bt\u012b Sar\u0101"
    ],
    "name:fas_x_variant":[
        "\u0633\u0648\u062a\u06cc \u0633\u0631\u0627"
    ],
    "wof:name":"Suti Sara",
    "wof:placetype":"locality"
},
  "geometry": {"coordinates":[50.05191,36.96343],"type":"Point"}
}