{
  "type": "Feature",
  "properties": {
    "gn:admin1_code":"1",
    "gn:asciiname":"Margan-e `Azizabad",
    "gn:country_code":"IR",
    "gn:dem":989,
    "gn:feature_class":"P",
    "gn:feature_code":"PPL",
    "gn:name":"Margan-e \u2018Az\u012bz\u0101b\u0101d",
    "gn:population":0,
    "gn:timezone":"Asia/Tehran",
    "iso:country":"IR",
    "name:fas_x_preferred":[
        "\u0645\u064e\u0631\u06af\u064e\u0646\u0650 \u0639\u064e\u0632\u064a\u0632 \u0622\u0628\u0627\u062f"
    ],
    "name:fas_x_variant":[
        "\u0645\u0631\u06af\u0646 \u0639\u0632\u06cc\u0632 \u0622\u0628\u0627\u062f",
        "Margan-e \u2018Az\u012bz\u0101b\u0101d"
    ],
    "wof:name":"Margan-e `Azizabad",
    "wof:placetype":"locality"
},
  "geometry": {"coordinates":[44.9504,39.1567],"type":"Point"}
}