{
  "type": "Feature",
  "properties": {
    "gn:admin1_code":"29",
    "gn:asciiname":"Feyzabad",
    "gn:country_code":"IR",
    "gn:dem":1540,
    "gn:feature_class":"P",
    "gn:feature_code":"PPL",
    "gn:name":"Fey\u1e95\u0101b\u0101d",
    "gn:population":0,
    "gn:timezone":"Asia/Tehran",
    "iso:country":"IR",
    "name:fas_x_preferred":[
        "\u0641\u06cc\u0636 \u0622\u0628\u0627\u062f"
    ],
    "name:fas_x_variant":[
        "Feyz\u0101b\u0101d",
        "Fey\u1e95\u0101b\u0101d"
    ],
    "name:und_x_variant":[
        "Faiz\u0101b\u0101d"
    ],
    "wof:name":"Feyzabad",
    "wof:placetype":"locality"
},
  "geometry": {"coordinates":[56.0252,30.3731],"type":"Point"}
}