{
  "type": "Feature",
  "properties": {
    "gn:admin1_code":"29.0",
    "gn:asciiname":"Esker",
    "gn:country_code":"IR",
    "gn:dem":2626,
    "gn:feature_class":"P",
    "gn:feature_code":"PPL",
    "gn:name":"Esker",
    "gn:population":0,
    "gn:timezone":"Asia/Tehran",
    "iso:country":"IR",
    "name:fas_x_preferred":[
        "\u0627\u0633\u06a9\u0631"
    ],
    "name:und_x_variant":[
        "\u2018Asgar",
        "\u2018Askar",
        "Esker"
    ],
    "wof:name":"Esker",
    "wof:placetype":"locality"
},
  "geometry": {"coordinates":[56.8383,29.3114],"type":"Point"}
}