{
  "type": "Feature",
  "properties": {
    "gn:admin1_code":"29.0",
    "gn:asciiname":"Esker",
    "gn:country_code":"IR",
    "gn:dem":2626,
    "gn:feature_class":"P",
    "gn:feature_code":"PPL",
    "gn:name":"Esker",
    "gn:population":0,
    "gn:timezone":"Asia/Tehran",
    "iso:country":"IR",
    "name:ast_x_preferred":[
        "Esker"
    ],
    "name:aze_x_preferred":[
        "Ozlar"
    ],
    "name:bel_x_preferred":[
        "\u041e\u0437\u044b"
    ],
    "name:ces_x_preferred":[
        "Esker"
    ],
    "name:cym_x_preferred":[
        "Esgair"
    ],
    "name:dan_x_preferred":[
        "\u00c5s"
    ],
    "name:deu_x_preferred":[
        "Os"
    ],
    "name:est_x_preferred":[
        "Oos"
    ],
    "name:fas_x_preferred":[
        "\u0627\u0633\u06a9\u0631"
    ],
    "name:fin_x_preferred":[
        "Harju"
    ],
    "name:fra_x_preferred":[
        "Esker"
    ],
    "name:gle_x_preferred":[
        "Eiscir"
    ],
    "name:glg_x_preferred":[
        "Esker"
    ],
    "name:heb_x_preferred":[
        "\u05d0\u05e1\u05e7\u05e8"
    ],
    "name:hin_x_preferred":[
        "\u090f\u0938\u094d\u0915\u0930"
    ],
    "name:hun_x_preferred":[
        "\u00d3z"
    ],
    "name:isl_x_preferred":[
        "Malar\u00e1s"
    ],
    "name:ita_x_preferred":[
        "Esker"
    ],
    "name:jpn_x_preferred":[
        "\u30a8\u30b9\u30ab\u30fc"
    ],
    "name:kat_x_preferred":[
        "\u10dd\u10d6\u10d4\u10d1\u10d8"
    ],
    "name:kaz_x_preferred":[
        "\u042d\u0441\u043a\u0435\u0440\u043b\u0435\u0440"
    ],
    "name:kor_x_preferred":[
        "\uc5d0\uc2a4\ucee4"
    ],
    "name:lat_x_preferred":[
        "Dorsum montis"
    ],
    "name:lav_x_preferred":[
        "Oss"
    ],
    "name:lit_x_preferred":[
        "Ozas"
    ],
    "name:nld_x_preferred":[
        "Esker"
    ],
    "name:nor_x_preferred":[
        "Esker"
    ],
    "name:pol_x_preferred":[
        "Oz"
    ],
    "name:por_x_preferred":[
        "Esker"
    ],
    "name:rus_x_preferred":[
        "\u041e\u0437\u044b"
    ],
    "name:spa_x_preferred":[
        "Esker"
    ],
    "name:swe_x_preferred":[
        "Rullstens\u00e5s"
    ],
    "name:tur_x_preferred":[
        "Esker"
    ],
    "name:ukr_x_preferred":[
        "\u041e\u0437\u0438"
    ],
    "name:und_x_variant":[
        "\u2018Asgar",
        "\u2018Askar"
    ],
    "name:zho_x_preferred":[
        "\u86c7\u5f62\u4e18"
    ],
    "wof:name":"Esker",
    "wof:placetype":"locality"
},
  "geometry": {"coordinates":[56.8383,29.3114],"type":"Point"}
}