{
  "type": "Feature",
  "properties": {
    "gn:admin1_code":"7.0",
    "gn:asciiname":"Dowlatabad-e Yek",
    "gn:country_code":"IR",
    "gn:dem":1575,
    "gn:feature_class":"P",
    "gn:feature_code":"PPL",
    "gn:name":"Dowlat\u0101b\u0101d-e Yek",
    "gn:population":0,
    "gn:timezone":"Asia/Tehran",
    "iso:country":"IR",
    "name:fas_x_preferred":[
        "\u062f\u0648\u0644\u062a \u0622\u0628\u0627\u062f \u06cc\u06a9"
    ],
    "name:und_x_variant":[
        "Dowlat\u0101b\u0101d-e Yek"
    ],
    "wof:name":"Dowlatabad-e Yek",
    "wof:placetype":"locality"
},
  "geometry": {"coordinates":[54.23758,29.28618],"type":"Point"}
}