{
  "type": "Feature",
  "properties": {
    "gn:admin1_code":"23.0",
    "gn:asciiname":"Ashurabad",
    "gn:country_code":"IR",
    "gn:dem":2015,
    "gn:feature_class":"P",
    "gn:feature_code":"PPL",
    "gn:name":"\u0100sh\u016br\u0101b\u0101d",
    "gn:population":0,
    "gn:timezone":"Asia/Tehran",
    "iso:country":"IR",
    "name:fas_x_preferred":[
        "\u0622\u0634\u0648\u0631 \u0622\u0628\u0627\u062f"
    ],
    "name:fas_x_variant":[
        "\u0100sh\u016br\u0101b\u0101d"
    ],
    "name:und_x_variant":[
        "\u2018Ash\u012br\u0101b\u0101d",
        "Ashorab\u0101d"
    ],
    "wof:name":"Ashurabad",
    "wof:placetype":"locality"
},
  "geometry": {"coordinates":[49.40871,33.64364],"type":"Point"}
}