{
  "type": "Feature",
  "properties": {
    "gn:admin1_code":"23.0",
    "gn:asciiname":"Mian Mahalleh `Abbasabad-e Owlad Qobad",
    "gn:country_code":"IR",
    "gn:dem":1241,
    "gn:feature_class":"P",
    "gn:feature_code":"PPL",
    "gn:name":"M\u012b\u0101n Ma\u1e29alleh \u2018Abbas\u0101b\u0101d-e Owl\u0101d Qob\u0101d",
    "gn:population":0,
    "gn:timezone":"Asia/Tehran",
    "iso:country":"IR",
    "name:fas_x_preferred":[
        "\u0645\u06cc\u0627\u0646 \u0645\u062d\u0644\u0647 \u0639\u0628\u0627\u0633 \u0622\u0628\u0627\u062f \u0627\u0648\u0644\u0627\u062f \u0642\u0628\u0627\u062f"
    ],
    "name:und_x_variant":[
        "M\u012b\u0101n Ma\u1e29alleh \u2018Abbas\u0101b\u0101d-e Owl\u0101d Qob\u0101d"
    ],
    "wof:name":"Mian Mahalleh `Abbasabad-e Owlad Qobad",
    "wof:placetype":"locality"
},
  "geometry": {"coordinates":[47.45775,33.70399],"type":"Point"}
}