{
  "type": "Feature",
  "properties": {
    "gn:admin1_code":"41",
    "gn:asciiname":"Sar Khong",
    "gn:country_code":"IR",
    "gn:dem":2087,
    "gn:feature_class":"P",
    "gn:feature_code":"PPL",
    "gn:name":"Sar Khong",
    "gn:population":0,
    "gn:timezone":"Asia/Tehran",
    "iso:country":"IR",
    "name:fas_x_preferred":[
        "\u0633\u0631\u062e\u0646\u06af"
    ],
    "name:und_x_variant":[
        "B\u0101gh-e Sar Khonak",
        "Sar Khank",
        "Sar Khonak",
        "Sar-i-Khung",
        "Sar-e Khong",
        "Sar Khong"
    ],
    "wof:name":"Sar Khong",
    "wof:placetype":"locality"
},
  "geometry": {"coordinates":[59.70236,33.18584],"type":"Point"}
}