{
  "type": "Feature",
  "properties": {
    "gn:admin1_code":"35.0",
    "gn:asciiname":"Namusdeh",
    "gn:country_code":"IR",
    "gn:dem":13,
    "gn:feature_class":"P",
    "gn:feature_code":"PPL",
    "gn:name":"N\u0101m\u016bsdeh",
    "gn:population":0,
    "gn:timezone":"Asia/Tehran",
    "iso:country":"IR",
    "name:fas_x_preferred":[
        "\u0646\u0627\u0645\u0648\u0633\u062f\u0647"
    ],
    "name:fas_x_variant":[
        "N\u0101m\u016bsdeh"
    ],
    "wof:name":"Namusdeh",
    "wof:placetype":"locality"
},
  "geometry": {"coordinates":[52.31325,36.54322],"type":"Point"}
}