{
  "type": "Feature",
  "properties": {
    "gn:admin1_code":"28.0",
    "gn:asciiname":"Shahrak-e Shahid Raja'i",
    "gn:country_code":"IR",
    "gn:dem":1867,
    "gn:feature_class":"P",
    "gn:feature_code":"PPL",
    "gn:name":"Shahrak-e Shah\u012bd Raj\u0101\u2019\u012b",
    "gn:population":0,
    "gn:timezone":"Asia/Tehran",
    "iso:country":"IR",
    "name:fas_x_preferred":[
        "Shahrak-e Shah\u012bd Raj\u0101\u2019\u012b"
    ],
    "name:fas_x_variant":[
        "\u0634\u0647\u0631\u0643 \u0634\u0647\u06cc\u062f \u0631\u062c\u0627\u0626\u06cc"
    ],
    "name:und_x_variant":[
        "\u0634\u0647\u0631\u0643 \u0634\u0647\u06cc\u062f \u0631\u062c\u0627\u0626\u06cc"
    ],
    "wof:name":"Shahrak-e Shahid Raja'i",
    "wof:placetype":"locality"
},
  "geometry": {"coordinates":[50.25301,33.47147],"type":"Point"}
}