{
  "type": "Feature",
  "properties": {
    "gn:admin1_code":"34",
    "gn:asciiname":"Rakin",
    "gn:country_code":"IR",
    "gn:dem":1986,
    "gn:feature_class":"P",
    "gn:feature_code":"PPL",
    "gn:name":"Rak\u012bn",
    "gn:population":0,
    "gn:timezone":"Asia/Tehran",
    "iso:country":"IR",
    "name:fas_x_preferred":[
        "Rak\u012bn"
    ],
    "name:fas_x_variant":[
        "\u0631\u0643\u064a\u0646"
    ],
    "name:und_x_variant":[
        "Rok\u012bn",
        "Raikhin",
        "\u0631\u0643\u064a\u0646"
    ],
    "wof:name":"Rakin",
    "wof:placetype":"locality"
},
  "geometry": {"coordinates":[49.58952,34.76586],"type":"Point"}
}