{
  "type": "Feature",
  "properties": {
    "gn:admin1_code":"33",
    "gn:asciiname":"Bajushin",
    "gn:country_code":"IR",
    "gn:dem":1666,
    "gn:feature_class":"P",
    "gn:feature_code":"PPL",
    "gn:name":"Baj\u016bsh\u012bn",
    "gn:population":0,
    "gn:timezone":"Asia/Tehran",
    "iso:country":"IR",
    "name:fas_x_preferred":[
        "\u0628\u062c\u0648\u0634\u06cc\u0646"
    ],
    "name:fas_x_variant":[
        "Baj\u016bsh\u012bn",
        "Bejowsh\u012bn",
        "Bejowsh\u0101n",
        "Bej\u016bshan",
        "Bej\u016bsh\u012bn"
    ],
    "name:und_x_variant":[
        "Bejushan",
        "Bedzheushan",
        "Bajooshin"
    ],
    "wof:name":"Bajushin",
    "wof:placetype":"locality"
},
  "geometry": {"coordinates":[46.7546,38.5396],"type":"Point"}
}