{
  "type": "Feature",
  "properties": {
    "gn:admin1_code":"42",
    "gn:asciiname":"Senjedak",
    "gn:country_code":"IR",
    "gn:dem":1669,
    "gn:feature_class":"P",
    "gn:feature_code":"PPL",
    "gn:name":"Senjedak",
    "gn:population":0,
    "gn:timezone":"Asia/Tehran",
    "iso:country":"IR",
    "name:fas_x_preferred":[
        "\u0633\u0646\u062c\u062f\u06a9"
    ],
    "wof:name":"Senjedak",
    "wof:placetype":"locality"
},
  "geometry": {"coordinates":[58.17252,35.59836],"type":"Point"}
}