{
  "type": "Feature",
  "properties": {
    "gn:admin1_code":"8",
    "gn:asciiname":"Kord Mahalleh",
    "gn:country_code":"IR",
    "gn:dem":101,
    "gn:feature_class":"P",
    "gn:feature_code":"PPL",
    "gn:name":"Kord Ma\u1e29alleh",
    "gn:population":0,
    "gn:timezone":"Asia/Tehran",
    "iso:country":"IR",
    "name:fas_x_preferred":[
        "\u06a9\u0631\u062f \u0645\u062d\u0644\u0647"
    ],
    "name:fas_x_variant":[
        "Kord Ma\u1e29alleh"
    ],
    "wof:name":"Kord Mahalleh",
    "wof:placetype":"locality"
},
  "geometry": {"coordinates":[49.2599,37.1674],"type":"Point"}
}