{
  "type": "Feature",
  "properties": {
    "gn:admin1_code":"42",
    "gn:asciiname":"Shuy-e Vasati",
    "gn:country_code":"IR",
    "gn:dem":998,
    "gn:feature_class":"P",
    "gn:feature_code":"PPL",
    "gn:name":"Sh\u016by-e Vasa\u0163\u012b",
    "gn:population":0,
    "gn:timezone":"Asia/Tehran",
    "iso:country":"IR",
    "name:fas_x_preferred":[
        "Sh\u016by-e Vasa\u0163\u012b"
    ],
    "wof:name":"Shuy-e Vasati",
    "wof:placetype":"locality"
},
  "geometry": {"coordinates":[58.78333000000001,37.56667],"type":"Point"}
}