{
  "type": "Feature",
  "properties": {
    "gn:admin1_code":"37.0",
    "gn:asciiname":"Bastam Darreh",
    "gn:country_code":"IR",
    "gn:dem":485,
    "gn:feature_class":"P",
    "gn:feature_code":"PPL",
    "gn:name":"Bas\u0163\u0101m Darreh",
    "gn:population":0,
    "gn:timezone":"Asia/Tehran",
    "iso:country":"IR",
    "name:ceb_x_preferred":[
        "Bas\u0163\u0101m Darreh"
    ],
    "name:fas_x_preferred":[
        "\u0628\u0633\u0637\u0627\u0645 \u062f\u0631\u0651\u0647"
    ],
    "name:fas_x_variant":[
        "Bas\u0163\u0101m Darreh",
        "\u0628\u0633\u0637\u0627\u0645\u200c\u062f\u0631\u0647"
    ],
    "name:msa_x_preferred":[
        "Bastam Darreh"
    ],
    "name:swe_x_preferred":[
        "Bas\u0163\u0101m Darreh"
    ],
    "wof:name":"Bastam Darreh",
    "wof:placetype":"locality"
},
  "geometry": {"coordinates":[56.09976999999999,37.98688],"type":"Point"}
}