{
  "type": "Feature",
  "properties": {
    "gn:admin1_code":"35.0",
    "gn:asciiname":"Shahrak-e Saheli-ye Fulad Iran",
    "gn:country_code":"IR",
    "gn:dem":-22,
    "gn:feature_class":"P",
    "gn:feature_code":"PPL",
    "gn:name":"Shahrak-e S\u0101\u1e29el\u012b-ye F\u016bl\u0101d \u012ar\u0101n",
    "gn:population":0,
    "gn:timezone":"Asia/Tehran",
    "iso:country":"IR",
    "name:fas_x_preferred":[
        "\u0634\u0647\u0631\u0643 \u0633\u0627\u062d\u0644\u06cc \u0641\u0648\u0644\u0627\u062f \u0627\u06cc\u0631\u0627\u0646"
    ],
    "name:fas_x_variant":[
        "Shahrak-e S\u0101\u1e29el\u012b-ye F\u016bl\u0101d \u012ar\u0101n"
    ],
    "name:und_x_variant":[
        "Shahrak-e S\u0101\u1e29el\u012b-ye F\u016bl\u0101d \u012ar\u0101n"
    ],
    "wof:name":"Shahrak-e Saheli-ye Fulad Iran",
    "wof:placetype":"locality"
},
  "geometry": {"coordinates":[52.9731,36.7728],"type":"Point"}
}