{
  "type": "Feature",
  "properties": {
    "gn:admin1_code":"33",
    "gn:asciiname":"Shahnavaz-e Vosta",
    "gn:country_code":"IR",
    "gn:dem":2049,
    "gn:feature_class":"P",
    "gn:feature_code":"PPL",
    "gn:name":"Shahnav\u0101z-e Vos\u0163\u00e1",
    "gn:population":0,
    "gn:timezone":"Asia/Tehran",
    "iso:country":"IR",
    "name:ara_x_preferred":[
        "\u0634\u0647\u0646\u0648\u0627\u0632 \u0648\u0633\u0637\u064a"
    ],
    "name:ceb_x_preferred":[
        "Shahnav\u0101z-e Vos\u0163\u00e1"
    ],
    "name:fas_x_preferred":[
        "\u0634\u0647\u0646\u0648\u0627\u0632 \u0648\u0633\u0637\u06cc"
    ],
    "name:fas_x_variant":[
        "Shahnav\u0101z-e Vos\u0163\u00e1"
    ],
    "name:msa_x_preferred":[
        "Shahnavaz-e Vosta"
    ],
    "name:swe_x_preferred":[
        "Shahnav\u0101z-e Vos\u0163\u00e1"
    ],
    "wof:name":"Shahnavaz-e Vosta",
    "wof:placetype":"locality"
},
  "geometry": {"coordinates":[46.7377,37.1172],"type":"Point"}
}