{
  "type": "Feature",
  "properties": {
    "gn:admin1_code":"29",
    "gn:asciiname":"Nakhlestan",
    "gn:country_code":"IR",
    "gn:dem":1453,
    "gn:feature_class":"P",
    "gn:feature_code":"PPL",
    "gn:name":"Nakhlest\u0101n",
    "gn:population":0,
    "gn:timezone":"Asia/Tehran",
    "iso:country":"IR",
    "name:fas_x_preferred":[
        "Nakhlest\u0101n"
    ],
    "wof:name":"Nakhlestan",
    "wof:placetype":"locality"
},
  "geometry": {"coordinates":[57.03333000000001,28.31667],"type":"Point"}
}