{
  "type": "Feature",
  "properties": {
    "gn:admin1_code":"4",
    "gn:asciiname":"Gazchar",
    "gn:country_code":"IR",
    "gn:dem":1292,
    "gn:feature_class":"P",
    "gn:feature_code":"PPL",
    "gn:name":"Gazch\u0101r",
    "gn:population":0,
    "gn:timezone":"Asia/Tehran",
    "iso:country":"IR",
    "name:fas_x_preferred":[
        "\u06af\u0632\u0686\u0627\u0631"
    ],
    "name:fas_x_variant":[
        "Gazch\u0101r"
    ],
    "wof:name":"Gazchar",
    "wof:placetype":"locality"
},
  "geometry": {"coordinates":[62.1771,26.9126],"type":"Point"}
}