{
  "type": "Feature",
  "properties": {
    "gn:admin1_code":"22",
    "gn:asciiname":"Kaki",
    "gn:country_code":"IR",
    "gn:dem":22,
    "gn:feature_class":"P",
    "gn:feature_code":"PPL",
    "gn:name":"K\u0101k\u012b",
    "gn:population":0,
    "gn:timezone":"Asia/Tehran",
    "iso:country":"IR",
    "name:ara_x_preferred":[
        "\u0643\u0627\u0643\u064a"
    ],
    "name:aze_x_preferred":[
        "Kaki"
    ],
    "name:ceb_x_preferred":[
        "K\u0101k\u012b"
    ],
    "name:deu_x_preferred":[
        "Kaki"
    ],
    "name:fas_x_preferred":[
        "\u0643\u0627\u0643\u06cc"
    ],
    "name:fas_x_variant":[
        "K\u0101k\u012b",
        "\u06a9\u0627\u06a9\u06cc"
    ],
    "name:fra_x_preferred":[
        "Kaki"
    ],
    "name:hun_x_preferred":[
        "Kaki"
    ],
    "name:ita_x_preferred":[
        "Kaki"
    ],
    "name:mlg_x_preferred":[
        "Kaki"
    ],
    "name:msa_x_preferred":[
        "Kaki"
    ],
    "name:rus_x_preferred":[
        "\u041a\u0430\u043a\u0438"
    ],
    "name:tur_x_preferred":[
        "Kaki"
    ],
    "name:urd_x_preferred":[
        "\u06a9\u0627\u06a9\u06cc"
    ],
    "wof:name":"Kaki",
    "wof:placetype":"locality"
},
  "geometry": {"coordinates":[51.52361,28.33861],"type":"Point"}
}