{
  "type": "Feature",
  "properties": {
    "gn:admin1_code":"22",
    "gn:asciiname":"Kaki",
    "gn:country_code":"IR",
    "gn:dem":22,
    "gn:feature_class":"P",
    "gn:feature_code":"PPL",
    "gn:name":"K\u0101k\u012b",
    "gn:population":0,
    "gn:timezone":"Asia/Tehran",
    "iso:country":"IR",
    "name:fas_x_preferred":[
        "\u0643\u0627\u0643\u06cc"
    ],
    "name:fas_x_variant":[
        "K\u0101k\u012b"
    ],
    "wof:name":"Kaki",
    "wof:placetype":"locality"
},
  "geometry": {"coordinates":[51.52361,28.33861],"type":"Point"}
}