{
  "type": "Feature",
  "properties": {
    "gn:admin1_code":"1",
    "gn:asciiname":"Sheykh Shamzin",
    "gn:country_code":"IR",
    "gn:dem":1652,
    "gn:feature_class":"P",
    "gn:feature_code":"PPL",
    "gn:name":"Sheykh Shamz\u012bn",
    "gn:population":0,
    "gn:timezone":"Asia/Tehran",
    "iso:country":"IR",
    "name:azb_x_preferred":[
        "\u0634\u06cc\u062e \u0634\u0645\u0632\u06cc\u0646"
    ],
    "name:aze_x_preferred":[
        "\u015eeyx\u015f\u0259mzin"
    ],
    "name:ceb_x_preferred":[
        "Sheykh Shamz\u012bn"
    ],
    "name:fas_x_preferred":[
        "\u0634\u0650\u064a\u062e \u0634\u064e\u0645\u0632\u064a\u0646"
    ],
    "name:fas_x_variant":[
        "\u0634\u06cc\u062e \u0634\u0645\u0632\u06cc\u0646",
        "Sheykh Shamz\u012bn"
    ],
    "name:msa_x_preferred":[
        "Sheykh Shamzin"
    ],
    "name:swe_x_preferred":[
        "Sheykh Shamz\u012bn"
    ],
    "wof:name":"Sheykh Shamzin",
    "wof:placetype":"locality"
},
  "geometry": {"coordinates":[44.832,37.5283],"type":"Point"}
}