{
  "type": "Feature",
  "properties": {
    "gn:admin1_code":"36",
    "gn:asciiname":"Nazar Qoli",
    "gn:country_code":"IR",
    "gn:dem":1819,
    "gn:feature_class":"P",
    "gn:feature_code":"PPL",
    "gn:name":"Naz\u0327ar Qol\u012b",
    "gn:population":0,
    "gn:timezone":"Asia/Tehran",
    "iso:country":"IR",
    "name:azb_x_preferred":[
        "\u0646\u0638\u0631\u0642\u0644\u06cc"
    ],
    "name:fas_x_preferred":[
        "\u0646\u0638\u0631 \u0642\u0644\u06cc"
    ],
    "name:fas_x_variant":[
        "Naz\u0327ar Qol\u012b",
        "\u0646\u0638\u0631\u0642\u0644\u06cc"
    ],
    "name:und_x_variant":[
        "Nazar-Kalekh",
        "Nazar Qal\u2018eh"
    ],
    "wof:name":"Nazar Qoli",
    "wof:placetype":"locality"
},
  "geometry": {"coordinates":[48.67151,36.16025],"type":"Point"}
}