{
  "type": "Feature",
  "properties": {
    "gn:admin1_code":"13",
    "gn:asciiname":"Mahmudabad",
    "gn:country_code":"IR",
    "gn:dem":1786,
    "gn:feature_class":"P",
    "gn:feature_code":"PPL",
    "gn:name":"Ma\u1e29m\u016bd\u0101b\u0101d",
    "gn:population":0,
    "gn:timezone":"Asia/Tehran",
    "iso:country":"IR",
    "name:aze_x_preferred":[
        "Mahmudabad"
    ],
    "name:bpy_x_preferred":[
        "\u09ae\u09be\u09b9\u09ae\u09c1\u09a6\u09be\u09ac\u09be\u09a6"
    ],
    "name:ceb_x_preferred":[
        "Mahmudabad"
    ],
    "name:fas_x_preferred":[
        "Ma\u1e29m\u016bd\u0101b\u0101d"
    ],
    "name:fas_x_variant":[
        "\u0645\u062d\u0645\u0648\u062f\u0622\u0628\u0627\u062f"
    ],
    "name:pol_x_preferred":[
        "Mahmudabad"
    ],
    "name:rus_x_preferred":[
        "\u041c\u0430\u0445\u043c\u0443\u0434\u0430\u0431\u0430\u0434"
    ],
    "name:swe_x_preferred":[
        "Mahmudabad"
    ],
    "wof:name":"Mahmudabad",
    "wof:placetype":"locality"
},
  "geometry": {"coordinates":[47.56667,34.63333],"type":"Point"}
}