{
  "type": "Feature",
  "properties": {
    "gn:admin1_code":"29",
    "gn:asciiname":"`Abdolabad",
    "gn:country_code":"IR",
    "gn:dem":490,
    "gn:feature_class":"P",
    "gn:feature_code":"PPL",
    "gn:name":"\u2018Abdol\u0101b\u0101d",
    "gn:population":0,
    "gn:timezone":"Asia/Tehran",
    "iso:country":"IR",
    "name:fas_x_preferred":[
        "\u2018Abdol\u0101b\u0101d"
    ],
    "wof:name":"`Abdolabad",
    "wof:placetype":"locality"
},
  "geometry": {"coordinates":[57.72444,27.98333],"type":"Point"}
}