{
  "type": "Feature",
  "properties": {
    "gn:admin1_code":"15",
    "gn:asciiname":"Meshlashiyeh-ye Sofla",
    "gn:country_code":"IR",
    "gn:dem":22,
    "gn:feature_class":"P",
    "gn:feature_code":"PPL",
    "gn:name":"Meshlash\u012byeh-ye Sofl\u00e1",
    "gn:population":0,
    "gn:timezone":"Asia/Tehran",
    "iso:country":"IR",
    "name:fas_x_preferred":[
        "\u0645\u0634\u06cc\u0644\u0634\u06cc\u0647 \u0633\u0641\u0644\u06cc"
    ],
    "name:fas_x_variant":[
        "M\u012bshelsh\u012byeh-ye Sofl\u00e1",
        "Mesheylsh\u012byeh-ye P\u0101\u2019\u012bn",
        "Mesheylsh\u012byeh-ye Sofl\u00e1",
        "\u0645\u0634\u0644\u0634\u06cc\u0647 \u0633\u0641\u0644\u06cc",
        "\u0645\u0634\u0644\u0634\u0647 \u0633\u0641\u0644\u06cc"
    ],
    "name:und_x_variant":[
        "Mowsher Sheyeh",
        "Mowsher Sh\u012byeh",
        "Meshlash\u012byeh-ye Sofl\u00e1",
        "Meshlasheh-ye Sofl\u00e1"
    ],
    "wof:name":"Meshlashiyeh-ye Sofla",
    "wof:placetype":"locality"
},
  "geometry": {"coordinates":[49.39209,30.85993],"type":"Point"}
}