{
  "type": "Feature",
  "properties": {
    "gn:admin1_code":"34",
    "gn:asciiname":"Susan Naqin",
    "gn:country_code":"IR",
    "gn:dem":1345,
    "gn:feature_class":"P",
    "gn:feature_code":"PPL",
    "gn:name":"S\u016bsan Naq\u012bn",
    "gn:population":0,
    "gn:timezone":"Asia/Tehran",
    "iso:country":"IR",
    "name:ceb_x_preferred":[
        "S\u016bsan Naq\u012bn"
    ],
    "name:fas_x_preferred":[
        "\u0633\u0648\u0633\u0646 \u0646\u0642\u064a\u0646"
    ],
    "name:fas_x_variant":[
        "\u0633\u0648\u0633\u0647 \u0646\u0642\u06cc",
        "S\u016bsan Naq\u012bn",
        "S\u016bseh Naq\u012b",
        "\u0633\u0648\u0633\u0646 \u0646\u0642\u06cc\u0646"
    ],
    "name:swe_x_preferred":[
        "S\u016bsan Naq\u012bn"
    ],
    "name:ukr_x_preferred":[
        "\u0421\u0443\u0441\u0430\u043d-\u041d\u0430\u043a\u0456\u043d"
    ],
    "name:und_x_variant":[
        "Susnaq\u012bn",
        "S\u016bsan Naq\u012b",
        "S\u016bsan Q\u012bn"
    ],
    "wof:name":"Susan Naqin",
    "wof:placetype":"locality"
},
  "geometry": {"coordinates":[50.0122,35.036],"type":"Point"}
}