{
  "type": "Feature",
  "properties": {
    "gn:admin1_code":"29",
    "gn:asciiname":"Deh Chenar",
    "gn:country_code":"IR",
    "gn:dem":1976,
    "gn:feature_class":"P",
    "gn:feature_code":"PPL",
    "gn:name":"Deh Chen\u0101r",
    "gn:population":0,
    "gn:timezone":"Asia/Tehran",
    "iso:country":"IR",
    "name:fas_x_preferred":[
        "\u062f\u0647 \u0686\u0646\u0627\u0631"
    ],
    "name:fas_x_variant":[
        "Deh Chen\u0101r"
    ],
    "wof:name":"Deh Chenar",
    "wof:placetype":"locality"
},
  "geometry": {"coordinates":[57.9809,29.0547],"type":"Point"}
}