{
  "type": "Feature",
  "properties": {
    "gn:admin1_code":"5",
    "gn:asciiname":"Dashtak",
    "gn:country_code":"IR",
    "gn:dem":1867,
    "gn:feature_class":"P",
    "gn:feature_code":"PPL",
    "gn:name":"Dashtak",
    "gn:population":0,
    "gn:timezone":"Asia/Tehran",
    "iso:country":"IR",
    "name:ceb_x_preferred":[
        "Dashtak"
    ],
    "name:fas_x_preferred":[
        "Dashtak-e Sofl\u00e1"
    ],
    "name:fas_x_variant":[
        "\u062f\u0634\u062a\u06a9 \u0633\u0641\u0644\u06cc",
        "\u062f\u0634\u062a\u06a9"
    ],
    "name:swe_x_preferred":[
        "Dashtak"
    ],
    "name:und_x_variant":[
        "\u062f\u0634\u062a\u06a9 \u0633\u0641\u0644\u06cc",
        "Dashtak"
    ],
    "wof:name":"Dashtak",
    "wof:placetype":"locality"
},
  "geometry": {"coordinates":[50.38857,31.34234],"type":"Point"}
}