{
  "type": "Feature",
  "properties": {
    "gn:admin1_code":"33",
    "gn:asciiname":"Chay Darsi",
    "gn:country_code":"IR",
    "gn:dem":2100,
    "gn:feature_class":"P",
    "gn:feature_code":"PPL",
    "gn:name":"Ch\u0101y Dars\u012b",
    "gn:population":0,
    "gn:timezone":"Asia/Tehran",
    "iso:country":"IR",
    "name:fas_x_preferred":[
        "Ch\u0101y Dars\u012b"
    ],
    "wof:name":"Chay Darsi",
    "wof:placetype":"locality"
},
  "geometry": {"coordinates":[47.26667,36.98333],"type":"Point"}
}