{
  "type": "Feature",
  "properties": {
    "gn:admin1_code":"11",
    "gn:asciiname":"Dast Kherd",
    "gn:country_code":"IR",
    "gn:dem":421,
    "gn:feature_class":"P",
    "gn:feature_code":"PPL",
    "gn:name":"Dast Kherd",
    "gn:population":0,
    "gn:timezone":"Asia/Tehran",
    "iso:country":"IR",
    "name:fas_x_preferred":[
        "\u062f\u0633\u062a \u062e\u0631\u062f"
    ],
    "name:und_x_variant":[
        "Dast Kherd"
    ],
    "wof:name":"Dast Kherd",
    "wof:placetype":"locality"
},
  "geometry": {"coordinates":[54.90214,27.19071],"type":"Point"}
}