{
  "type": "Feature",
  "properties": {
    "gn:admin1_code":"5.0",
    "gn:asciiname":"`Aliabad",
    "gn:country_code":"IR",
    "gn:dem":1774,
    "gn:feature_class":"P",
    "gn:feature_code":"PPL",
    "gn:name":"\u2018Al\u012b\u0101b\u0101d",
    "gn:population":0,
    "gn:timezone":"Asia/Tehran",
    "iso:country":"IR",
    "name:fas_x_preferred":[
        "\u0639\u0644\u06cc \u0622\u0628\u0627\u062f"
    ],
    "name:fas_x_variant":[
        "\u0639\u064e\u0644\u064a\u0627\u0628\u0627\u062f\u0650 \u0633\u064e\u0631\u062a\u064f\u0644",
        "\u2018Al\u012b\u0101b\u0101d"
    ],
    "name:und_x_variant":[
        "\u2018Al\u012b\u0101b\u0101d-e Sartol"
    ],
    "wof:name":"`Aliabad",
    "wof:placetype":"locality"
},
  "geometry": {"coordinates":[51.52315,30.67118],"type":"Point"}
}