{
  "type": "Feature",
  "properties": {
    "gn:admin1_code":"8",
    "gn:asciiname":"Veshal",
    "gn:cc2":"IR",
    "gn:country_code":"IR",
    "gn:dem":-16,
    "gn:feature_class":"P",
    "gn:feature_code":"PPL",
    "gn:name":"Vesh\u0101l",
    "gn:population":0,
    "gn:timezone":"Asia/Tehran",
    "iso:country":"IR",
    "name:fas_x_preferred":[
        "Vesh\u0101l"
    ],
    "name:und_x_variant":[
        "P\u016bsh\u0101l",
        "P\u016bshal"
    ],
    "wof:name":"Veshal",
    "wof:placetype":"locality"
},
  "geometry": {"coordinates":[49.99944,37.32556],"type":"Point"}
}