{
  "type": "Feature",
  "properties": {
    "gn:admin1_code":"36.0",
    "gn:asciiname":"Aqcheh Qal`eh",
    "gn:country_code":"IR",
    "gn:dem":1747,
    "gn:feature_class":"P",
    "gn:feature_code":"PPL",
    "gn:name":"\u0100qcheh Qal\u2018eh",
    "gn:population":0,
    "gn:timezone":"Asia/Tehran",
    "iso:country":"IR",
    "name:azb_x_preferred":[
        "\u0622\u0642\u062c\u0647 \u0642\u0644\u0639\u0647"
    ],
    "name:aze_x_preferred":[
        "A\u011fcaqala"
    ],
    "name:fas_x_preferred":[
        "\u0627\u0642\u062c\u0647 \u0642\u0644\u0639\u0647"
    ],
    "name:fas_x_variant":[
        "\u0100qjeh Qal\u2018eh",
        "Aqjeh Qal\u2018eh",
        "\u0622\u0642\u0686\u0647 \u0642\u0644\u0639\u0647"
    ],
    "name:und_x_variant":[
        "\u0100ghjeh Qal\u2018eh",
        "Akcha-Kalekh",
        "\u0100qcheh Qal\u2018eh",
        "Aqcha Qal\u2018eh"
    ],
    "wof:name":"Aqcheh Qal`eh",
    "wof:placetype":"locality"
},
  "geometry": {"coordinates":[48.18342,37.11266],"type":"Point"}
}