{
  "type": "Feature",
  "properties": {
    "gn:admin1_code":"33",
    "gn:asciiname":"Dash Bolagh-e Kharabeh Kalak",
    "gn:country_code":"IR",
    "gn:dem":2111,
    "gn:feature_class":"P",
    "gn:feature_code":"PPL",
    "gn:name":"D\u0101sh Bol\u0101gh-e Khar\u0101beh Kalak",
    "gn:population":0,
    "gn:timezone":"Asia/Tehran",
    "iso:country":"IR",
    "name:fas_x_preferred":[
        "\u062f\u0627\u0634 \u0628\u0644\u0627\u063a \u062e\u0631\u0627\u0628\u0647 \u06a9\u0644\u06a9"
    ],
    "name:fas_x_variant":[
        "D\u0101sh Bol\u0101gh-e Khar\u0101beh Kalak",
        "\u062f\u0627\u0634 \u0628\u0644\u0627\u063a \u062e\u0631\u0627\u0628\u0647 \u06af\u0644\u06a9"
    ],
    "name:und_x_variant":[
        "D\u0101sh Bol\u0101gh-e Khar\u0101beh Galak"
    ],
    "wof:name":"Dash Bolagh-e Kharabeh Kalak",
    "wof:placetype":"locality"
},
  "geometry": {"coordinates":[46.7657,37.1764],"type":"Point"}
}