{
  "type": "Feature",
  "properties": {
    "gn:admin1_code":"25.0",
    "gn:asciiname":"Zagheh",
    "gn:country_code":"IR",
    "gn:dem":1437,
    "gn:feature_class":"P",
    "gn:feature_code":"PPL",
    "gn:name":"Z\u0101gheh",
    "gn:population":0,
    "gn:timezone":"Asia/Tehran",
    "iso:country":"IR",
    "name:ara_x_preferred":[
        "\u0632\u0627\u063a\u0647"
    ],
    "name:aze_x_preferred":[
        "Za\u011f\u0259"
    ],
    "name:ceb_x_preferred":[
        "Z\u0101gheh-ye \u2018Oly\u0101"
    ],
    "name:fas_x_preferred":[
        "Z\u0101gheh"
    ],
    "name:fas_x_variant":[
        "\u0632\u0627\u063a\u0647"
    ],
    "name:ita_x_preferred":[
        "Zagheh"
    ],
    "name:mlg_x_preferred":[
        "Zagheh"
    ],
    "name:swe_x_preferred":[
        "Z\u0101gheh-ye \u2018Oly\u0101"
    ],
    "name:tur_x_preferred":[
        "Za\u011fe"
    ],
    "name:urd_x_preferred":[
        "\u0632\u0627\u063a\u06c1"
    ],
    "wof:name":"Zagheh",
    "wof:placetype":"locality"
},
  "geometry": {"coordinates":[54.88333000000001,36.38333],"type":"Point"}
}