{
  "type": "Feature",
  "properties": {
    "gn:admin1_code":"29",
    "gn:asciiname":"Chahar Chahi",
    "gn:country_code":"IR",
    "gn:dem":390,
    "gn:feature_class":"P",
    "gn:feature_code":"PPL",
    "gn:name":"Chah\u0101r Ch\u0101h\u012b",
    "gn:population":0,
    "gn:timezone":"Asia/Tehran",
    "iso:country":"IR",
    "name:fas_x_preferred":[
        "\u0686\u0647\u0627\u0631 \u0686\u0627\u0647\u06cc"
    ],
    "name:fas_x_variant":[
        "Chah\u0101r Ch\u0101h\u012b"
    ],
    "wof:name":"Chahar Chahi",
    "wof:placetype":"locality"
},
  "geometry": {"coordinates":[58.54499000000001,27.76958],"type":"Point"}
}