{
  "type": "Feature",
  "properties": {
    "gn:admin1_code":"7",
    "gn:asciiname":"Robatak",
    "gn:country_code":"IR",
    "gn:dem":754,
    "gn:feature_class":"P",
    "gn:feature_code":"PPL",
    "gn:name":"Rob\u0101\u0163ak",
    "gn:population":0,
    "gn:timezone":"Asia/Tehran",
    "iso:country":"IR",
    "name:fas_x_preferred":[
        "Rob\u0101\u0163ak"
    ],
    "name:fas_x_variant":[
        "\u0631\u0628\u0627\u0637\u0643"
    ],
    "name:und_x_variant":[
        "Rab\u0101tak",
        "\u0631\u0628\u0627\u0637\u0643"
    ],
    "wof:name":"Robatak",
    "wof:placetype":"locality"
},
  "geometry": {"coordinates":[51.85137,29.38523],"type":"Point"}
}