{
  "type": "Feature",
  "properties": {
    "gn:admin1_code":"40",
    "gn:asciiname":"Mazra`eh-ye Gol Gashtu",
    "gn:country_code":"IR",
    "gn:dem":1664,
    "gn:feature_class":"P",
    "gn:feature_code":"PPLF",
    "gn:name":"Mazra\u2018eh-ye Gol Gasht\u016b",
    "gn:population":0,
    "gn:timezone":"Asia/Tehran",
    "iso:country":"IR",
    "name:fas_x_preferred":[
        "Gol Kashk\u016b\u2019\u012byeh"
    ],
    "name:fas_x_variant":[
        "Gol Gasht\u0101n",
        "\u06af\u0644 \u06af\u0634\u062a\u0627\u0646",
        "\u0645\u0632\u0631\u0639\u0647 \u06af\u0644 \u06af\u0634\u062a\u0648",
        "\u06af\u0644\u06af\u0634\u062a\u0648\u06cc\u06cc\u0647"
    ],
    "name:und_x_variant":[
        "Gul-i-Gashmu",
        "Golkashm\u016b\u2019\u012byeh",
        "Gol Kashm\u016b",
        "Gol Gasht\u016b",
        "Golgasht\u0101n",
        "Mazra\u2018eh-ye Gol Gasht\u016b",
        "Golgasht\u016b\u2019\u012byeh"
    ],
    "wof:name":"Mazra`eh-ye Gol Gashtu",
    "wof:placetype":"locality"
},
  "geometry": {"coordinates":[54.4061,29.95373],"type":"Point"}
}