{
  "type": "Feature",
  "properties": {
    "gn:admin1_code":"37.0",
    "gn:asciiname":"Qarah Qashli",
    "gn:country_code":"IR",
    "gn:dem":159,
    "gn:feature_class":"P",
    "gn:feature_code":"PPL",
    "gn:name":"Qarah Q\u0101shl\u012b",
    "gn:population":0,
    "gn:timezone":"Asia/Tehran",
    "iso:country":"IR",
    "name:ceb_x_preferred":[
        "Qarah Q\u0101shl\u012b"
    ],
    "name:fas_x_preferred":[
        "\u0642\u0631\u0647 \u0622\u0642\u0627\u0686\u0644\u06cc"
    ],
    "name:fas_x_variant":[
        "\u0642\u0631\u0647 \u0642\u0627\u0634\u0644\u06cc",
        "Qarah \u0100q\u0101chl\u012b",
        "Qarah Q\u0101shl\u012b",
        "\u0642\u0631\u0647\u200c\u0622\u0642\u0627 \u0686\u0644\u06cc"
    ],
    "name:msa_x_preferred":[
        "Qarah Aqachli"
    ],
    "name:swe_x_preferred":[
        "Qarah Q\u0101shl\u012b"
    ],
    "wof:name":"Qarah Qashli",
    "wof:placetype":"locality"
},
  "geometry": {"coordinates":[55.80732,37.87726],"type":"Point"}
}