{
  "type": "Feature",
  "properties": {
    "gn:admin1_code":"13.0",
    "gn:asciiname":"Soltanabad",
    "gn:country_code":"IR",
    "gn:dem":1818,
    "gn:feature_class":"P",
    "gn:feature_code":"PPL",
    "gn:name":"Sol\u0163\u0101n\u0101b\u0101d",
    "gn:population":0,
    "gn:timezone":"Asia/Tehran",
    "iso:country":"IR",
    "name:ara_x_preferred":[
        "\u0633\u0644\u0637\u0627\u0646 \u0623\u0628\u0627\u062f"
    ],
    "name:aze_x_preferred":[
        "Soltanabad"
    ],
    "name:cat_x_preferred":[
        "Soltanabad"
    ],
    "name:ceb_x_preferred":[
        "Soltanabad"
    ],
    "name:fas_x_preferred":[
        "\u0633\u0644\u0637\u0627\u0646 \u0622\u0628\u0627\u062f"
    ],
    "name:fas_x_variant":[
        "Sol\u0163\u0101n\u0101b\u0101d",
        "\u0633\u0644\u0637\u0627\u0646\u06cc\u0647 \u062d\u0627\u062c\u06cc \u0622\u0628\u0627\u062f",
        "\u0633\u0644\u0637\u0627\u0646\u200c\u0622\u0628\u0627\u062f"
    ],
    "name:mzn_x_preferred":[
        "\u0633\u0644\u0637\u0627\u0646\u200c\u0622\u0628\u0627\u062f"
    ],
    "name:swe_x_preferred":[
        "Soltanabad"
    ],
    "name:und_x_variant":[
        "Sol\u0163\u0101n\u012byeh \u1e28\u0101jj\u012b\u0101b\u0101d"
    ],
    "wof:name":"Soltanabad",
    "wof:placetype":"locality"
},
  "geometry": {"coordinates":[47.3685,35.01612],"type":"Point"}
}