{
  "type": "Feature",
  "properties": {
    "gn:admin1_code":"5.0",
    "gn:asciiname":"Pornur-e Mohammadi",
    "gn:country_code":"IR",
    "gn:dem":1063,
    "gn:feature_class":"P",
    "gn:feature_code":"PPL",
    "gn:name":"Porn\u016br-e Mo\u1e29ammad\u012b",
    "gn:population":0,
    "gn:timezone":"Asia/Tehran",
    "iso:country":"IR",
    "name:fas_x_preferred":[
        "\u0633\u0631 \u067e\u0631 \u0646\u0648\u0631 \u0645\u062d\u0645\u0651\u062f\u06cc"
    ],
    "name:fas_x_variant":[
        "Sar Por-e N\u016br Mo\u1e29ammad\u012b",
        "\u067e\u0631\u0646\u0648\u0631 \u0645\u062d\u0645\u062f\u06cc",
        "\u0627\u062d\u0645\u062f \u0633\u0627\u0644\u0627\u0631"
    ],
    "name:und_x_variant":[
        "Porn\u016br-e Mo\u1e29ammad\u012b",
        "A\u1e29mad S\u0101l\u0101r"
    ],
    "wof:name":"Pornur-e Mohammadi",
    "wof:placetype":"locality"
},
  "geometry": {"coordinates":[50.55394,31.08178],"type":"Point"}
}