{
  "type": "Feature",
  "properties": {
    "gn:admin1_code":"32",
    "gn:asciiname":"Goljeh",
    "gn:country_code":"IR",
    "gn:dem":1915,
    "gn:feature_class":"P",
    "gn:feature_code":"PPL",
    "gn:name":"Goljeh",
    "gn:population":0,
    "gn:timezone":"Asia/Tehran",
    "iso:country":"IR",
    "name:fas_x_preferred":[
        "\u0643\u0644\u062c\u0647"
    ],
    "name:fas_x_variant":[
        "Kol\u016bjeh",
        "\u06af\u0644\u062c\u0647",
        "\u06af\u0644\u0648\u062c\u0647"
    ],
    "name:und_x_variant":[
        "Koljeh",
        "Goljeh",
        "Gol\u016bjeh"
    ],
    "wof:name":"Goljeh",
    "wof:placetype":"locality"
},
  "geometry": {"coordinates":[47.9544,38.1051],"type":"Point"}
}