{
  "type": "Feature",
  "properties": {
    "gn:admin1_code":"4.0",
    "gn:asciiname":"Bashu",
    "gn:country_code":"IR",
    "gn:dem":23,
    "gn:feature_class":"P",
    "gn:feature_code":"PPL",
    "gn:name":"B\u0101sh\u016b",
    "gn:population":0,
    "gn:timezone":"Asia/Tehran",
    "iso:country":"IR",
    "name:fas_x_preferred":[
        "\u0628\u0627\u0634\u0648"
    ],
    "name:fas_x_variant":[
        "B\u0101sh\u016b"
    ],
    "name:und_x_variant":[
        "Bachu"
    ],
    "wof:name":"Bashu",
    "wof:placetype":"locality"
},
  "geometry": {"coordinates":[61.13333000000001,25.65],"type":"Point"}
}