{
  "type": "Feature",
  "properties": {
    "gn:admin1_code":"11.0",
    "gn:asciiname":"Baghan",
    "gn:country_code":"IR",
    "gn:dem":9,
    "gn:feature_class":"P",
    "gn:feature_code":"PPL",
    "gn:name":"B\u0101gh\u0101n",
    "gn:population":0,
    "gn:timezone":"Asia/Tehran",
    "iso:country":"IR",
    "name:fas_x_preferred":[
        "\u0628\u0627\u063a\u0627\u0646"
    ],
    "name:fas_x_variant":[
        "\u0628\u0627\u063a\u064a\u0646",
        "\u0628\u0627\u063a\u0650\u064a\u0646",
        "B\u0101gh\u0101n"
    ],
    "name:und_x_variant":[
        "B\u0101gheyn",
        "B\u0101gh\u012bn"
    ],
    "wof:name":"Baghan",
    "wof:placetype":"locality"
},
  "geometry": {"coordinates":[57.63377,25.7996],"type":"Point"}
}