{
  "type": "Feature",
  "properties": {
    "gn:admin1_code":"1",
    "gn:asciiname":"Eslamlu",
    "gn:country_code":"IR",
    "gn:dem":1894,
    "gn:feature_class":"P",
    "gn:feature_code":"PPL",
    "gn:name":"Esl\u0101ml\u016b",
    "gn:population":0,
    "gn:timezone":"Asia/Tehran",
    "iso:country":"IR",
    "name:fas_x_preferred":[
        "\u0627\u0633\u0644\u0627\u0645\u0644\u0648"
    ],
    "name:fas_x_variant":[
        "Esl\u0101ml\u016b"
    ],
    "name:und_x_variant":[
        "Esl\u0101mb\u016b"
    ],
    "wof:name":"Eslamlu",
    "wof:placetype":"locality"
},
  "geometry": {"coordinates":[45.1684,37.1426],"type":"Point"}
}