{
  "type": "Feature",
  "properties": {
    "gn:admin1_code":"4.0",
    "gn:asciiname":"Deh-e Ahmad `Ali Khan",
    "gn:country_code":"IR",
    "gn:dem":493,
    "gn:feature_class":"P",
    "gn:feature_code":"PPL",
    "gn:name":"Deh-e A\u1e29mad \u2018Al\u012b Kh\u0101n",
    "gn:population":0,
    "gn:timezone":"Asia/Tehran",
    "iso:country":"IR",
    "name:fas_x_preferred":[
        "\u062f\u0647 \u0627\u062d\u0645\u062f \u0639\u0644\u06cc \u062e\u0627\u0646"
    ],
    "name:fas_x_variant":[
        "Deh-e A\u1e29mad \u2018Al\u012b Kh\u0101n"
    ],
    "wof:name":"Deh-e Ahmad `Ali Khan",
    "wof:placetype":"locality"
},
  "geometry": {"coordinates":[61.7292,30.8797],"type":"Point"}
}