{
  "type": "Feature",
  "properties": {
    "gn:admin1_code":"29",
    "gn:asciiname":"Nimrudi",
    "gn:country_code":"IR",
    "gn:dem":1623,
    "gn:feature_class":"P",
    "gn:feature_code":"PPL",
    "gn:name":"N\u012bmr\u016bd\u012b",
    "gn:population":0,
    "gn:timezone":"Asia/Tehran",
    "iso:country":"IR",
    "name:fas_x_preferred":[
        "\u0646\u06cc\u0645\u0631\u0648\u062f\u06cc"
    ],
    "name:fas_x_variant":[
        "N\u012bmr\u016bd\u012b"
    ],
    "wof:name":"Nimrudi",
    "wof:placetype":"locality"
},
  "geometry": {"coordinates":[57.065,28.9671],"type":"Point"}
}