{
  "type": "Feature",
  "properties": {
    "gn:admin1_code":"33",
    "gn:asciiname":"Qichaq",
    "gn:country_code":"IR",
    "gn:dem":1737,
    "gn:feature_class":"P",
    "gn:feature_code":"PPL",
    "gn:name":"Q\u012bch\u0101q",
    "gn:population":0,
    "gn:timezone":"Asia/Tehran",
    "iso:country":"IR",
    "name:fas_x_preferred":[
        "\u0642\u06cc\u0686\u0627\u0642"
    ],
    "name:fas_x_variant":[
        "Q\u012bpch\u0101q",
        "Q\u012bch\u0101q"
    ],
    "wof:name":"Qichaq",
    "wof:placetype":"locality"
},
  "geometry": {"coordinates":[47.0298,37.6686],"type":"Point"}
}