{
  "type": "Feature",
  "properties": {
    "gn:admin1_code":"29",
    "gn:asciiname":"Qa'emiyeh",
    "gn:country_code":"IR",
    "gn:dem":1364,
    "gn:feature_class":"P",
    "gn:feature_code":"PPL",
    "gn:name":"Q\u0101\u2019em\u012byeh",
    "gn:population":0,
    "gn:timezone":"Asia/Tehran",
    "iso:country":"IR",
    "name:fas_x_preferred":[
        "Q\u0101\u2019em\u012byeh"
    ],
    "name:fas_x_variant":[
        "\u0642\u0627\u0626\u064a\u0645\u0647"
    ],
    "name:und_x_variant":[
        "\u0642\u0627\u0626\u064a\u0645\u0647"
    ],
    "wof:name":"Qa'emiyeh",
    "wof:placetype":"locality"
},
  "geometry": {"coordinates":[55.82076,30.78487],"type":"Point"}
}