{
  "type": "Feature",
  "properties": {
    "gn:admin1_code":"35.0",
    "gn:asciiname":"Rajar Sarak",
    "gn:country_code":"IR",
    "gn:dem":1280,
    "gn:feature_class":"P",
    "gn:feature_code":"PPL",
    "gn:name":"Rajar Sarak",
    "gn:population":0,
    "gn:timezone":"Asia/Tehran",
    "iso:country":"IR",
    "name:fas_x_preferred":[
        "\u0631\u062c\u0631\u0633\u0631\u06a9"
    ],
    "wof:name":"Rajar Sarak",
    "wof:placetype":"locality"
},
  "geometry": {"coordinates":[53.43214,36.28361],"type":"Point"}
}