{
  "type": "Feature",
  "properties": {
    "gn:admin1_code":"29",
    "gn:asciiname":"Senjed Khoshk",
    "gn:country_code":"IR",
    "gn:dem":2331,
    "gn:feature_class":"P",
    "gn:feature_code":"PPL",
    "gn:name":"Senjed Khoshk",
    "gn:population":0,
    "gn:timezone":"Asia/Tehran",
    "iso:country":"IR",
    "name:fas_x_preferred":[
        "\u0633\u0646\u062c\u062f \u062e\u0634\u06a9"
    ],
    "name:und_x_variant":[
        "Shesht\u0101 Khoshk",
        "Senjed Khoshk"
    ],
    "wof:name":"Senjed Khoshk",
    "wof:placetype":"locality"
},
  "geometry": {"coordinates":[57.8846,29.0747],"type":"Point"}
}