{
  "type": "Feature",
  "properties": {
    "gn:admin1_code":"35.0",
    "gn:asciiname":"Shahrak-e Afshan",
    "gn:country_code":"IR",
    "gn:dem":25,
    "gn:feature_class":"P",
    "gn:feature_code":"PPL",
    "gn:name":"Shahrak-e Afsh\u0101n",
    "gn:population":0,
    "gn:timezone":"Asia/Tehran",
    "iso:country":"IR",
    "name:fas_x_preferred":[
        "\u0634\u0647\u0631\u06a9 \u0627\u0641\u0634\u0627\u0646"
    ],
    "name:und_x_variant":[
        "Shahrak-e Afsh\u0101n"
    ],
    "wof:name":"Shahrak-e Afshan",
    "wof:placetype":"locality"
},
  "geometry": {"coordinates":[51.93589,36.54303],"type":"Point"}
}