{
  "type": "Feature",
  "properties": {
    "gn:admin1_code":"9",
    "gn:asciiname":"Lilas",
    "gn:country_code":"IR",
    "gn:dem":1489,
    "gn:feature_class":"P",
    "gn:feature_code":"PPL",
    "gn:name":"L\u012bl\u0101s",
    "gn:population":0,
    "gn:timezone":"Asia/Tehran",
    "iso:country":"IR",
    "name:ceb_x_preferred":[
        "L\u012bl\u0101s"
    ],
    "name:fas_x_preferred":[
        "L\u012bl\u0101s"
    ],
    "name:fas_x_variant":[
        "L\u012bl\u0101n",
        "\u0644\u06cc\u0644\u0627\u0633"
    ],
    "name:msa_x_preferred":[
        "Lilas"
    ],
    "name:swe_x_preferred":[
        "L\u012bl\u0101s"
    ],
    "name:und_x_variant":[
        "Leyl\u0101n",
        "\u0644\u06cc\u0644\u0627\u0633",
        "Lail\u0101s",
        "Leyl\u0101s"
    ],
    "wof:name":"Lilas",
    "wof:placetype":"locality"
},
  "geometry": {"coordinates":[48.18755,34.26811],"type":"Point"}
}