{
  "type": "Feature",
  "properties": {
    "iso:country":"IR",
    "name:fas_x_preferred":[
        "\u0622\u0628\u064a\u0650\u0643\u0650 \u0648\u064e\u0633\u064e\u0637\u06cc"
    ],
    "name:fas_x_variant":[
        "\u0622\u0628\u064a\u0650\u0643\u0650 \u0633\u064f\u0641\u0644\u064e\u0649"
    ],
    "name:unk_x_variant":[
        "\u0100byek-e Vasa\u0163\u012b"
    ],
    "qs:gn_country":"IR",
    "qs:gn_fcode":"PPLX",
    "qs:gn_pop":0,
    "qs:name":"\u0100byek-e Vasat\u012b",
    "qs:name_adm0":"Iran",
    "qs:name_adm1":"Qazvin",
    "qs:photos":5,
    "qs:photos_1k":1,
    "qs:photos_9k":1,
    "qs:photos_9r":1,
    "qs:photos_all":5,
    "qs:photos_sr":1,
    "qs:placetype":"Suburb",
    "qs:pop_sr":"0",
    "qs:woe_adm0":23424851,
    "wof:name":"\u0100byek-e Vasat\u012b",
    "wof:placetype":"neighbourhood"
},
  "geometry": {"coordinates":[50.55,36.05],"type":"Point"}
}