{
  "type": "Feature",
  "properties": {
    "gn:admin1_code":"22.0",
    "gn:asciiname":"Delaras",
    "gn:country_code":"IR",
    "gn:dem":23,
    "gn:feature_class":"P",
    "gn:feature_code":"PPL",
    "gn:name":"Del\u0101ras",
    "gn:population":0,
    "gn:timezone":"Asia/Tehran",
    "iso:country":"IR",
    "name:fas_x_preferred":[
        "\u062f\u0644\u0627\u0631\u0633"
    ],
    "name:fas_x_variant":[
        "Del\u0101ras"
    ],
    "wof:name":"Delaras",
    "wof:placetype":"locality"
},
  "geometry": {"coordinates":[51.0769,28.8088],"type":"Point"}
}