{
  "type": "Feature",
  "properties": {
    "gn:admin1_code":"8.0",
    "gn:asciiname":"Garjansu",
    "gn:country_code":"IR",
    "gn:dem":1631,
    "gn:feature_class":"P",
    "gn:feature_code":"PPL",
    "gn:name":"Garj\u0101ns\u016b",
    "gn:population":0,
    "gn:timezone":"Asia/Tehran",
    "iso:country":"IR",
    "name:fas_x_preferred":[
        "Garj\u0101ns\u016b"
    ],
    "name:fas_x_variant":[
        "\u06af\u0631\u062c\u0627\u0646\u0633\u0648"
    ],
    "wof:name":"Garjansu",
    "wof:placetype":"locality"
},
  "geometry": {"coordinates":[50.32953,36.75728],"type":"Point"}
}