{
  "type": "Feature",
  "properties": {
    "gn:admin1_code":"7",
    "gn:asciiname":"Kangarestan",
    "gn:country_code":"IR",
    "gn:dem":2050,
    "gn:feature_class":"P",
    "gn:feature_code":"PPL",
    "gn:name":"Kangarest\u0101n",
    "gn:population":0,
    "gn:timezone":"Asia/Tehran",
    "iso:country":"IR",
    "name:fas_x_preferred":[
        "Kangarest\u0101n"
    ],
    "wof:name":"Kangarestan",
    "wof:placetype":"locality"
},
  "geometry": {"coordinates":[51.28389,30.5675],"type":"Point"}
}