{
  "type": "Feature",
  "properties": {
    "gn:admin1_code":"10",
    "gn:asciiname":"Cham Zhab",
    "gn:country_code":"IR",
    "gn:dem":574,
    "gn:feature_class":"P",
    "gn:feature_code":"PPL",
    "gn:name":"Cham Zh\u0101b",
    "gn:population":0,
    "gn:timezone":"Asia/Tehran",
    "iso:country":"IR",
    "name:ara_x_preferred":[
        "\u062a\u0634\u0645 \u062c\u0627\u0628"
    ],
    "name:ceb_x_preferred":[
        "Cham Zh\u0101b"
    ],
    "name:fas_x_preferred":[
        "\u0686\u0645 \u0698\u0627\u0628"
    ],
    "name:fas_x_variant":[
        "Cham Zh\u0101b"
    ],
    "name:msa_x_preferred":[
        "Cham Zhab"
    ],
    "name:swe_x_preferred":[
        "Cham Zh\u0101b"
    ],
    "wof:name":"Cham Zhab",
    "wof:placetype":"locality"
},
  "geometry": {"coordinates":[47.45179,33.14497],"type":"Point"}
}