{
  "type": "Feature",
  "properties": {
    "gn:admin1_code":"23",
    "gn:asciiname":"Gol Badam",
    "gn:country_code":"IR",
    "gn:dem":1022,
    "gn:feature_class":"P",
    "gn:feature_code":"PPL",
    "gn:name":"Gol B\u0101d\u0101m",
    "gn:population":0,
    "gn:timezone":"Asia/Tehran",
    "iso:country":"IR",
    "name:fas_x_preferred":[
        "\u0643\u0648\u0644 \u0628\u0627\u062f\u0627\u0645\u0650 \u0646\u0648\u0631\u0645\u064f\u0631\u0627\u062f"
    ],
    "name:fas_x_variant":[
        "\u06a9\u0648\u0644 \u0628\u0627\u062f\u0627\u0645",
        "K\u016bl B\u0101d\u0101m-e N\u016brmor\u0101d",
        "K\u016bl B\u0101d\u0101m",
        "\u06af\u0644 \u0628\u0627\u062f\u0627\u0645"
    ],
    "name:und_x_variant":[
        "K\u016bl B\u0101d\u0101m-e Y\u0101var",
        "\u0643\u0648\u0644 \u0628\u0627\u062f\u0627\u0645\u0650 \u064a\u0627\u0648\u064e\u0631",
        "Gol B\u0101d\u0101m"
    ],
    "wof:name":"Gol Badam",
    "wof:placetype":"locality"
},
  "geometry": {"coordinates":[47.00683,33.58164],"type":"Point"}
}