{
  "type": "Feature",
  "properties": {
    "gn:admin1_code":"7",
    "gn:asciiname":"Chah-e Sheshom",
    "gn:country_code":"IR",
    "gn:dem":1633,
    "gn:feature_class":"P",
    "gn:feature_code":"PPL",
    "gn:name":"Ch\u0101h-e Sheshom",
    "gn:population":0,
    "gn:timezone":"Asia/Tehran",
    "iso:country":"IR",
    "name:fas_x_preferred":[
        "\u0686\u0627\u0647 \u0634\u0634\u0645"
    ],
    "name:fas_x_variant":[
        "Ch\u0101h-e Sheshom"
    ],
    "wof:name":"Chah-e Sheshom",
    "wof:placetype":"locality"
},
  "geometry": {"coordinates":[55.07951,28.79334],"type":"Point"}
}