{
  "type": "Feature",
  "properties": {
    "gn:admin1_code":"25",
    "gn:asciiname":"Kabud Darreh",
    "gn:country_code":"IR",
    "gn:dem":2180,
    "gn:feature_class":"P",
    "gn:feature_code":"PPL",
    "gn:name":"Kab\u016bd Darreh",
    "gn:population":0,
    "gn:timezone":"Asia/Tehran",
    "iso:country":"IR",
    "name:fas_x_preferred":[
        "\u06a9\u0628\u0648\u062f \u062f\u0631\u0647"
    ],
    "name:fas_x_variant":[
        "Kab\u016bd Darreh",
        "\u06a9\u0628\u0648\u062f \u062f\u0631\u0647 \u0628\u0627\u0644\u0627",
        "\u06a9\u0628\u0648\u062f\u062f\u0631\u0647"
    ],
    "name:und_x_variant":[
        "Kab\u016bd Darreh-ye B\u0101l\u0101"
    ],
    "wof:name":"Kabud Darreh",
    "wof:placetype":"locality"
},
  "geometry": {"coordinates":[53.27788,35.82557],"type":"Point"}
}