{
  "type": "Feature",
  "properties": {
    "gn:admin1_code":"35",
    "gn:asciiname":"Kangalak Gardan",
    "gn:country_code":"IR",
    "gn:dem":1903,
    "gn:feature_class":"P",
    "gn:feature_code":"PPL",
    "gn:name":"Kang\u0101lak Gardan",
    "gn:population":0,
    "gn:timezone":"Asia/Tehran",
    "iso:country":"IR",
    "name:fas_x_preferred":[
        "\u0643\u064e\u0646\u06af\u0627\u0644\u064e\u0643 \u06af\u064e\u0631\u062f\u064e\u0646"
    ],
    "wof:name":"Kangalak Gardan",
    "wof:placetype":"locality"
},
  "geometry": {"coordinates":[50.66667,36.68333],"type":"Point"}
}