{
  "type": "Feature",
  "properties": {
    "gn:admin1_code":"13",
    "gn:asciiname":"Choqa Maran",
    "gn:country_code":"IR",
    "gn:dem":1336,
    "gn:feature_class":"P",
    "gn:feature_code":"PPL",
    "gn:name":"Choq\u0101 M\u0101r\u0101n",
    "gn:population":0,
    "gn:timezone":"Asia/Tehran",
    "iso:country":"IR",
    "name:fas_x_preferred":[
        "\u0686\u0642\u0627 \u0645\u0627\u0631\u0627\u0646"
    ],
    "name:fas_x_variant":[
        "Choq\u0101 M\u0101r\u0101n"
    ],
    "wof:name":"Choqa Maran",
    "wof:placetype":"locality"
},
  "geometry": {"coordinates":[46.8642,34.6473],"type":"Point"}
}