{
  "type": "Feature",
  "properties": {
    "gn:admin1_code":"11",
    "gn:asciiname":"Bid Ra'is",
    "gn:country_code":"IR",
    "gn:dem":231,
    "gn:feature_class":"P",
    "gn:feature_code":"PPL",
    "gn:name":"B\u012bd Ra\u2019\u012bs",
    "gn:population":0,
    "gn:timezone":"Asia/Tehran",
    "iso:country":"IR",
    "name:fas_x_preferred":[
        "\u0628\u06cc\u062f \u0631\u0626\u06cc\u0633"
    ],
    "name:fas_x_variant":[
        "B\u012bd Ra\u2019\u012bs"
    ],
    "wof:name":"Bid Ra'is",
    "wof:placetype":"locality"
},
  "geometry": {"coordinates":[57.3752,27.04717],"type":"Point"}
}