{
  "type": "Feature",
  "properties": {
    "gn:admin1_code":"32",
    "gn:asciiname":"Giluneh",
    "gn:country_code":"IR",
    "gn:dem":1562,
    "gn:feature_class":"P",
    "gn:feature_code":"PPL",
    "gn:name":"G\u012bl\u016bneh",
    "gn:population":0,
    "gn:timezone":"Asia/Tehran",
    "iso:country":"IR",
    "name:fas_x_preferred":[
        "\u06af\u06cc\u0644\u0648\u0646\u0647"
    ],
    "name:fas_x_variant":[
        "G\u012bl\u016bneh"
    ],
    "wof:name":"Giluneh",
    "wof:placetype":"locality"
},
  "geometry": {"coordinates":[48.93642,37.286],"type":"Point"}
}