{
  "type": "Feature",
  "properties": {
    "gn:admin1_code":"33",
    "gn:asciiname":"Alharod",
    "gn:country_code":"IR",
    "gn:dem":2017,
    "gn:feature_class":"P",
    "gn:feature_code":"PPL",
    "gn:name":"Alharod",
    "gn:population":0,
    "gn:timezone":"Asia/Tehran",
    "iso:country":"IR",
    "name:ara_x_preferred":[
        "\u0627\u0644\u0647\u0631\u062f"
    ],
    "name:azb_x_preferred":[
        "\u0627\u0644\u0647\u0631\u062f"
    ],
    "name:fas_x_preferred":[
        "\u0627\u0644\u0647\u0631\u062f"
    ],
    "name:msa_x_preferred":[
        "Alharod"
    ],
    "name:und_x_variant":[
        "Elehred",
        "Alirt",
        "Eleherd",
        "Alard",
        "Al\u012br\u012b",
        "Alhard",
        "Al\u012brd",
        "Alert"
    ],
    "wof:name":"Alharod",
    "wof:placetype":"locality"
},
  "geometry": {"coordinates":[46.4802,38.479],"type":"Point"}
}