{
  "type": "Feature",
  "properties": {
    "gn:admin1_code":"35.0",
    "gn:asciiname":"Pa'in Takish",
    "gn:country_code":"IR",
    "gn:dem":193,
    "gn:feature_class":"P",
    "gn:feature_code":"PPL",
    "gn:name":"Pa\u2019\u012bn Tak\u012bsh",
    "gn:population":0,
    "gn:timezone":"Asia/Tehran",
    "iso:country":"IR",
    "name:fas_x_preferred":[
        "T\u012bk\u012bsh"
    ],
    "name:fas_x_variant":[
        "Pa\u2019\u012bn Tak\u012bsh",
        "\u067e\u0627\u0626\u06cc\u0646 \u062a\u06a9\u06cc\u0634"
    ],
    "wof:name":"Pa'in Takish",
    "wof:placetype":"locality"
},
  "geometry": {"coordinates":[50.78684000000001,36.77632],"type":"Point"}
}