{
  "type": "Feature",
  "properties": {
    "gn:admin1_code":"28",
    "gn:asciiname":"Sakhteman-e Qobad",
    "gn:country_code":"IR",
    "gn:dem":2676,
    "gn:feature_class":"P",
    "gn:feature_code":"PPL",
    "gn:name":"S\u0101khtem\u0101n-e Qob\u0101d",
    "gn:population":0,
    "gn:timezone":"Asia/Tehran",
    "iso:country":"IR",
    "name:fas_x_preferred":[
        "S\u0101khtem\u0101n-e Qob\u0101d"
    ],
    "name:fas_x_variant":[
        "S\u0101kht-e Qob\u0101d",
        "\u0633\u0627\u062e\u062a\u0645\u0627\u0646 \u0642\u0628\u0627\u062f"
    ],
    "name:und_x_variant":[
        "\u0633\u0627\u062e\u062a\u0645\u0627\u0646 \u0642\u0628\u0627\u062f"
    ],
    "wof:name":"Sakhteman-e Qobad",
    "wof:placetype":"locality"
},
  "geometry": {"coordinates":[51.61148,31.51662],"type":"Point"}
}