{
  "type": "Feature",
  "properties": {
    "gn:admin1_code":"28",
    "gn:asciiname":"Safajerd",
    "gn:country_code":"IR",
    "gn:dem":1758,
    "gn:feature_class":"P",
    "gn:feature_code":"PPL",
    "gn:name":"Saf\u0101jerd",
    "gn:population":0,
    "gn:timezone":"Asia/Tehran",
    "iso:country":"IR",
    "name:fas_x_preferred":[
        "Esf\u0101jerd"
    ],
    "name:fas_x_variant":[
        "Saf\u0101jerd",
        "\u0633\u0641\u0627\u062c\u0631\u062f"
    ],
    "name:und_x_variant":[
        "Isfajird",
        "\u0633\u0641\u0627\u062c\u0631\u062f"
    ],
    "wof:name":"Safajerd",
    "wof:placetype":"locality"
},
  "geometry": {"coordinates":[50.34749,33.56193],"type":"Point"}
}