{
  "type": "Feature",
  "properties": {
    "gn:admin1_code":"7",
    "gn:asciiname":"Mohammad `Abbasi",
    "gn:country_code":"IR",
    "gn:dem":489,
    "gn:feature_class":"P",
    "gn:feature_code":"PPL",
    "gn:name":"Mo\u1e29ammad \u2018Abb\u0101s\u012b",
    "gn:population":0,
    "gn:timezone":"Asia/Tehran",
    "iso:country":"IR",
    "name:fas_x_preferred":[
        "\u0645\u062d\u0645\u062f \u0639\u0628\u0627\u0633\u06cc"
    ],
    "name:fas_x_variant":[
        "Mo\u1e29ammad \u2018Abb\u0101s\u012b",
        "\u0645\u0632\u0631\u0639\u0647 \u0645\u062d\u0645\u062f \u0639\u0628\u0627\u0633\u06cc"
    ],
    "name:und_x_variant":[
        "Mazra\u2018eh-ye Mo\u1e29ammad \u2018Abb\u0101s\u012b"
    ],
    "wof:name":"Mohammad `Abbasi",
    "wof:placetype":"locality"
},
  "geometry": {"coordinates":[53.37166,27.57536],"type":"Point"}
}