{
  "type": "Feature",
  "properties": {
    "gn:admin1_code":"4.0",
    "gn:asciiname":"Gar Kandi",
    "gn:country_code":"IR",
    "gn:dem":33,
    "gn:feature_class":"P",
    "gn:feature_code":"PPL",
    "gn:name":"Gar Kand\u012b",
    "gn:population":0,
    "gn:timezone":"Asia/Tehran",
    "iso:country":"IR",
    "name:ara_x_preferred":[
        "\u063a\u0627\u0631 \u0643\u0646\u062f\u064a"
    ],
    "name:fas_x_preferred":[
        "G\u0101r Kand\u012b"
    ],
    "name:fas_x_variant":[
        "Gar Kand\u012b",
        "\u06af\u0631 \u06a9\u0646\u062f\u06cc",
        "\u06af\u0627\u0631 \u06a9\u0646\u062f\u06cc"
    ],
    "name:und_x_variant":[
        "K\u0101r Gand\u012b",
        "\u06af\u0631 \u06a9\u0646\u062f\u06cc"
    ],
    "wof:name":"Gar Kandi",
    "wof:placetype":"locality"
},
  "geometry": {"coordinates":[61.06100000000001,25.61784],"type":"Point"}
}