{
  "type": "Feature",
  "properties": {
    "gn:admin1_code":"16",
    "gn:asciiname":"Gavkaj-e Sofla",
    "gn:country_code":"IR",
    "gn:dem":1921,
    "gn:feature_class":"P",
    "gn:feature_code":"PPL",
    "gn:name":"G\u0101vkaj-e Sofl\u00e1",
    "gn:population":0,
    "gn:timezone":"Asia/Tehran",
    "iso:country":"IR",
    "name:fas_x_preferred":[
        "\u06af\u0627\u0648\u06a9\u062c \u067e\u0627\u0626\u06cc\u0646"
    ],
    "name:fas_x_variant":[
        "G\u0101vkaj-e Sofl\u00e1",
        "\u06af\u0627\u0648\u0643\u064e\u062c\u0650 \u0633\u064f\u0641\u0644\u064e\u0649",
        "G\u0101vkaj-e P\u0101\u2019\u012bn",
        "\u06af\u0627\u0648 \u06a9\u062c \u0633\u0641\u0644\u06cc"
    ],
    "wof:name":"Gavkaj-e Sofla",
    "wof:placetype":"locality"
},
  "geometry": {"coordinates":[46.65834,36.01872],"type":"Point"}
}