{
  "type": "Feature",
  "properties": {
    "gn:admin1_code":"35.0",
    "gn:asciiname":"Likar",
    "gn:country_code":"IR",
    "gn:dem":1743,
    "gn:feature_class":"P",
    "gn:feature_code":"PPL",
    "gn:name":"L\u012bkar",
    "gn:population":0,
    "gn:timezone":"Asia/Tehran",
    "iso:country":"IR",
    "name:ara_x_preferred":[
        "\u0644\u064a\u0643\u0631"
    ],
    "name:ceb_x_preferred":[
        "L\u012bkar"
    ],
    "name:fas_x_preferred":[
        "\u0644\u06cc\u06a9\u0631"
    ],
    "name:fas_x_variant":[
        "L\u012bkar",
        "L\u012bkar Kol\u0101",
        "\u0644\u06cc\u06a9\u0631\u0647"
    ],
    "name:swe_x_preferred":[
        "L\u012bkar"
    ],
    "name:und_x_variant":[
        "L\u012bkareh"
    ],
    "wof:name":"Likar",
    "wof:placetype":"locality"
},
  "geometry": {"coordinates":[51.2397,36.40261],"type":"Point"}
}