{
  "type": "Feature",
  "properties": {
    "gn:admin1_code":"33",
    "gn:asciiname":"Baftan",
    "gn:country_code":"IR",
    "gn:dem":1659,
    "gn:feature_class":"P",
    "gn:feature_code":"PPL",
    "gn:name":"B\u0101ft\u0101n",
    "gn:population":0,
    "gn:timezone":"Asia/Tehran",
    "iso:country":"IR",
    "name:fas_x_preferred":[
        "\u0628\u0627\u0641\u062a\u0627\u0646"
    ],
    "name:fas_x_variant":[
        "B\u0101ft\u0101n"
    ],
    "wof:name":"Baftan",
    "wof:placetype":"locality"
},
  "geometry": {"coordinates":[47.334,37.891],"type":"Point"}
}