{
  "type": "Feature",
  "properties": {
    "gn:admin1_code":"33",
    "gn:asciiname":"Nani Qayah",
    "gn:country_code":"IR",
    "gn:dem":1547,
    "gn:feature_class":"P",
    "gn:feature_code":"PPL",
    "gn:name":"N\u0101n\u012b Qayah",
    "gn:population":0,
    "gn:timezone":"Asia/Tehran",
    "iso:country":"IR",
    "wof:name":"Nani Qayah",
    "wof:placetype":"locality"
},
  "geometry": {"coordinates":[45.03333,38.71667],"type":"Point"}
}