{
  "type": "Feature",
  "properties": {
    "gn:admin1_code":"7",
    "gn:asciiname":"Now Dad",
    "gn:country_code":"IR",
    "gn:dem":1147,
    "gn:feature_class":"P",
    "gn:feature_code":"PPL",
    "gn:name":"Now D\u0101d",
    "gn:population":0,
    "gn:timezone":"Asia/Tehran",
    "iso:country":"IR",
    "name:fas_x_preferred":[
        "\u0646\u0648 \u062f\u0627\u062f"
    ],
    "name:fas_x_variant":[
        "Now D\u0101d",
        "\u0646\u0648\u062f\u0627\u062f"
    ],
    "name:msa_x_preferred":[
        "Now Dad"
    ],
    "wof:name":"Now Dad",
    "wof:placetype":"locality"
},
  "geometry": {"coordinates":[52.9698,28.6962],"type":"Point"}
}