{
  "type": "Feature",
  "properties": {
    "gn:admin1_code":"5.0",
    "gn:asciiname":"`Aliabad-e Sadat",
    "gn:country_code":"IR",
    "gn:dem":1949,
    "gn:feature_class":"P",
    "gn:feature_code":"PPL",
    "gn:name":"\u2018Al\u012b\u0101b\u0101d-e S\u0101d\u0101t",
    "gn:population":0,
    "gn:timezone":"Asia/Tehran",
    "iso:country":"IR",
    "name:fas_x_preferred":[
        "\u2018Al\u012b\u0101b\u0101d-e S\u0101d\u0101t"
    ],
    "name:fas_x_variant":[
        "\u0639\u0644\u06cc \u0622\u0628\u0627\u062f \u0633\u0627\u062f\u0627\u062a"
    ],
    "name:und_x_variant":[
        "\u0639\u0644\u06cc \u0622\u0628\u0627\u062f \u0633\u0627\u062f\u0627\u062a"
    ],
    "wof:name":"`Aliabad-e Sadat",
    "wof:placetype":"locality"
},
  "geometry": {"coordinates":[51.60645,30.67809],"type":"Point"}
}