{
  "type": "Feature",
  "properties": {
    "gn:admin1_code":"35",
    "gn:asciiname":"Zahed Kola",
    "gn:country_code":"IR",
    "gn:dem":29,
    "gn:feature_class":"P",
    "gn:feature_code":"PPL",
    "gn:name":"Z\u0101hed Kol\u0101",
    "gn:population":0,
    "gn:timezone":"Asia/Tehran",
    "iso:country":"IR",
    "name:fas_x_preferred":[
        "\u0632\u0627\u0647\u062f \u0643\u0644\u0627"
    ],
    "name:fas_x_variant":[
        "Z\u0101hed Kol\u0101"
    ],
    "name:und_x_variant":[
        "\u0632\u0627\u0647\u0650\u062f \u0643\u064f\u0644\u0627"
    ],
    "wof:name":"Zahed Kola",
    "wof:placetype":"locality"
},
  "geometry": {"coordinates":[52.52324,36.44408],"type":"Point"}
}