{
  "type": "Feature",
  "properties": {
    "gn:admin1_code":"36",
    "gn:asciiname":"Khanjin",
    "gn:country_code":"IR",
    "gn:dem":1689,
    "gn:feature_class":"P",
    "gn:feature_code":"PPL",
    "gn:name":"Kh\u0101nj\u012bn",
    "gn:population":0,
    "gn:timezone":"Asia/Tehran",
    "iso:country":"IR",
    "name:azb_x_preferred":[
        "\u062e\u0627\u0646\u062c\u06cc\u0646"
    ],
    "name:ceb_x_preferred":[
        "Kh\u0101nj\u012bn"
    ],
    "name:fas_x_preferred":[
        "\u062e\u0627\u0646 \u062c\u064a\u0646"
    ],
    "name:fas_x_variant":[
        "\u062e\u0627\u0646\u0650\u062c\u064a\u0646",
        "\u062e\u0627\u0646\u062c\u06cc\u0646",
        "Kh\u0101n J\u012bn",
        "Kh\u0101nj\u012bn"
    ],
    "name:swe_x_preferred":[
        "Kh\u0101nj\u012bn"
    ],
    "name:und_x_variant":[
        "Kh\u0101nej\u012bn",
        "Khanjin",
        "Khakadzhin",
        "Kh\u0101naji"
    ],
    "wof:name":"Khanjin",
    "wof:placetype":"locality"
},
  "geometry": {"coordinates":[48.24615,36.41616],"type":"Point"}
}