{
  "type": "Feature",
  "properties": {
    "gn:admin1_code":"40.0",
    "gn:asciiname":"Amirabad",
    "gn:country_code":"IR",
    "gn:dem":1142,
    "gn:feature_class":"P",
    "gn:feature_code":"PPL",
    "gn:name":"Am\u012br\u0101b\u0101d",
    "gn:population":0,
    "gn:timezone":"Asia/Tehran",
    "iso:country":"IR",
    "name:fas_x_preferred":[
        "Am\u012br\u0101b\u0101d"
    ],
    "name:fas_x_variant":[
        "\u0627\u0645\u064a\u0631 \u0622\u0628\u0627\u062f",
        "\u0627\u0645\u064a\u0646 \u0622\u0628\u0627\u062f",
        "\u0627\u0645\u06cc\u0631\u0622\u0628\u0627\u062f"
    ],
    "name:und_x_variant":[
        "Khord Narv\u0101n",
        "Khvord N\u0101rv\u0101n",
        "Kh\u016brd N\u0101rv\u0101n",
        "Am\u012bn\u0101b\u0101d"
    ],
    "wof:name":"Amirabad",
    "wof:placetype":"locality"
},
  "geometry": {"coordinates":[56.98638,34.01579],"type":"Point"}
}