{
  "type": "Feature",
  "properties": {
    "gn:admin1_code":"8",
    "gn:asciiname":"Katekul-e Dafchah",
    "gn:country_code":"IR",
    "gn:dem":-8,
    "gn:feature_class":"P",
    "gn:feature_code":"PPL",
    "gn:name":"Katek\u016bl-e D\u0101fch\u0101h",
    "gn:population":0,
    "gn:timezone":"Asia/Tehran",
    "iso:country":"IR",
    "name:fas_x_preferred":[
        "Katek\u016bl-e D\u0101fch\u0101h"
    ],
    "wof:name":"Katekul-e Dafchah",
    "wof:placetype":"locality"
},
  "geometry": {"coordinates":[49.7025,37.34722],"type":"Point"}
}