{
  "type": "Feature",
  "properties": {
    "gn:admin1_code":"8.0",
    "gn:asciiname":"Sasansara",
    "gn:country_code":"IR",
    "gn:dem":3,
    "gn:feature_class":"P",
    "gn:feature_code":"PPL",
    "gn:name":"S\u0101s\u0101nsar\u0101",
    "gn:population":0,
    "gn:timezone":"Asia/Tehran",
    "iso:country":"IR",
    "name:ceb_x_preferred":[
        "S\u0101s\u0101n Sar\u0101"
    ],
    "name:fas_x_preferred":[
        "\u0633\u0627\u0633\u0627\u0646 \u0633\u0631\u0627"
    ],
    "name:fas_x_variant":[
        "S\u0101s\u0101n Sar\u0101",
        "\u0633\u0627\u0633\u0627\u0646\u0633\u0631\u0627"
    ],
    "name:msa_x_preferred":[
        "Sasan Sara"
    ],
    "name:swe_x_preferred":[
        "S\u0101s\u0101n Sar\u0101"
    ],
    "name:ukr_x_preferred":[
        "\u0421\u0430\u0441\u0430\u043d\u0441\u0430\u0440\u0430"
    ],
    "name:und_x_variant":[
        "S\u0101s\u0101nsar\u0101"
    ],
    "wof:name":"Sasansara",
    "wof:placetype":"locality"
},
  "geometry": {"coordinates":[49.16407,37.54612],"type":"Point"}
}