{
  "type": "Feature",
  "properties": {
    "gn:admin1_code":"29",
    "gn:asciiname":"Sineh Kuh",
    "gn:country_code":"IR",
    "gn:dem":2173,
    "gn:feature_class":"P",
    "gn:feature_code":"PPL",
    "gn:name":"S\u012bneh K\u016bh",
    "gn:population":0,
    "gn:timezone":"Asia/Tehran",
    "iso:country":"IR",
    "name:fas_x_preferred":[
        "\u0633\u064a\u0646\u0647 \u0643\u0648\u0626\u064a\u0647"
    ],
    "name:fas_x_variant":[
        "\u0633\u06cc\u0646\u0647 \u06a9\u0648\u0647",
        "S\u012bneh K\u016b\u2019\u012byeh"
    ],
    "name:und_x_variant":[
        "S\u012bneh K\u016bh"
    ],
    "wof:name":"Sineh Kuh",
    "wof:placetype":"locality"
},
  "geometry": {"coordinates":[56.48698,31.34012],"type":"Point"}
}