{
  "type": "Feature",
  "properties": {
    "gn:admin1_code":"1",
    "gn:asciiname":"Shirin Bolagh",
    "gn:country_code":"IR",
    "gn:dem":1327,
    "gn:feature_class":"P",
    "gn:feature_code":"PPL",
    "gn:name":"Sh\u012br\u012bn Bol\u0101gh",
    "gn:population":0,
    "gn:timezone":"Asia/Tehran",
    "iso:country":"IR",
    "name:fas_x_preferred":[
        "\u0634\u06cc\u0631\u06cc\u0646 \u0628\u0644\u0627\u063a"
    ],
    "name:fas_x_variant":[
        "Sh\u012br\u012bn Bol\u0101gh"
    ],
    "wof:name":"Shirin Bolagh",
    "wof:placetype":"locality"
},
  "geometry": {"coordinates":[45.4307,37.1369],"type":"Point"}
}