{
  "type": "Feature",
  "properties": {
    "gn:admin1_code":"16",
    "gn:asciiname":"Choqur Qeshlaq",
    "gn:country_code":"IR",
    "gn:dem":1639,
    "gn:feature_class":"P",
    "gn:feature_code":"PPL",
    "gn:name":"Choq\u016br Qeshl\u0101q",
    "gn:population":0,
    "gn:timezone":"Asia/Tehran",
    "iso:country":"IR",
    "name:ara_x_preferred":[
        "\u062a\u0634\u063a\u0648\u0631 \u0642\u0634\u0644\u0627\u0642"
    ],
    "name:ceb_x_preferred":[
        "Chogh\u016br Qeshl\u0101q"
    ],
    "name:fas_x_preferred":[
        "\u0686\u063a\u0648\u0631 \u0642\u0634\u0644\u0627\u0642"
    ],
    "name:fas_x_variant":[
        "Choq\u016br Qeshl\u0101q",
        "Chogh\u016br Qeshl\u0101q",
        "\u0686\u0642\u0648\u0631 \u0642\u0634\u0644\u0627\u0642",
        "\u0686\u063a\u0648\u0631\u0642\u0634\u0644\u0627\u0642"
    ],
    "name:swe_x_preferred":[
        "Chogh\u016br Qeshl\u0101q"
    ],
    "wof:name":"Choqur Qeshlaq",
    "wof:placetype":"locality"
},
  "geometry": {"coordinates":[47.85986,36.1146],"type":"Point"}
}