{
  "type": "Feature",
  "properties": {
    "gn:admin1_code":"8",
    "gn:asciiname":"Nafar Bijar",
    "gn:country_code":"IR",
    "gn:dem":-5,
    "gn:feature_class":"P",
    "gn:feature_code":"PPL",
    "gn:name":"Nafar B\u012bj\u0101r",
    "gn:population":0,
    "gn:timezone":"Asia/Tehran",
    "iso:country":"IR",
    "name:ceb_x_preferred":[
        "Nowb\u012bj\u0101r"
    ],
    "name:fas_x_preferred":[
        "Nowb\u012bj\u0101r"
    ],
    "name:fas_x_variant":[
        "\u0646\u0648\u0628\u06cc\u062c\u0627\u0631",
        "\u0646\u0641\u0631 \u0628\u06cc\u062c\u0627\u0631"
    ],
    "name:msa_x_preferred":[
        "Nowbijar"
    ],
    "name:swe_x_preferred":[
        "Nowb\u012bj\u0101r"
    ],
    "name:ukr_x_preferred":[
        "\u041d\u043e\u0432\u0431\u0456\u0434\u0436\u0430\u0440"
    ],
    "name:und_x_variant":[
        "\u0646\u0648\u0628\u06cc\u062c\u0627\u0631",
        "Nafar B\u012bj\u0101r"
    ],
    "wof:name":"Nafar Bijar",
    "wof:placetype":"locality"
},
  "geometry": {"coordinates":[50.02788,37.23749],"type":"Point"}
}