{
  "type": "Feature",
  "properties": {
    "gn:admin1_code":"36",
    "gn:asciiname":"Qarah Tappeh",
    "gn:country_code":"IR",
    "gn:dem":1801,
    "gn:feature_class":"P",
    "gn:feature_code":"PPL",
    "gn:name":"Qarah Tappeh",
    "gn:population":0,
    "gn:timezone":"Asia/Tehran",
    "iso:country":"IR",
    "name:azb_x_preferred":[
        "\u0642\u0631\u0647 \u062a\u067e\u0647"
    ],
    "name:fas_x_preferred":[
        "\u0642\u0631\u0647 \u062a\u067e\u0647"
    ],
    "name:fas_x_variant":[
        "\u0642\u0631\u0647\u200c\u062a\u067e\u0647"
    ],
    "name:und_x_variant":[
        "Qaratepe",
        "Kara-Tappekh",
        "Qareh Tappeh",
        "Qarah Tappeh"
    ],
    "wof:name":"Qarah Tappeh",
    "wof:placetype":"locality"
},
  "geometry": {"coordinates":[48.5184,36.58887],"type":"Point"}
}