{
  "type": "Feature",
  "properties": {
    "gn:admin1_code":"23",
    "gn:asciiname":"Qal`eh Tazeh",
    "gn:country_code":"IR",
    "gn:dem":1531,
    "gn:feature_class":"P",
    "gn:feature_code":"PPL",
    "gn:name":"Qal\u2018eh T\u0101zeh",
    "gn:population":0,
    "gn:timezone":"Asia/Tehran",
    "iso:country":"IR",
    "name:fas_x_preferred":[
        "\u0642\u0644\u0639\u0647 \u062a\u0627\u0632\u0647"
    ],
    "name:fas_x_variant":[
        "Qal\u2018eh T\u0101zeh"
    ],
    "wof:name":"Qal`eh Tazeh",
    "wof:placetype":"locality"
},
  "geometry": {"coordinates":[48.72877,33.86519000000001],"type":"Point"}
}