{
  "type": "Feature",
  "properties": {
    "gn:admin1_code":"8",
    "gn:asciiname":"Langaraj Mahalleh",
    "gn:country_code":"IR",
    "gn:dem":13,
    "gn:feature_class":"P",
    "gn:feature_code":"PPL",
    "gn:name":"Langar\u0101j Ma\u1e29alleh",
    "gn:population":0,
    "gn:timezone":"Asia/Tehran",
    "iso:country":"IR",
    "name:fas_x_preferred":[
        "\u0644\u0646\u06af\u0631\u0627\u062c \u0645\u062d\u0644\u0647"
    ],
    "name:fas_x_variant":[
        "Langar\u0101j Ma\u1e29alleh"
    ],
    "wof:name":"Langaraj Mahalleh",
    "wof:placetype":"locality"
},
  "geometry": {"coordinates":[48.9747,37.6949],"type":"Point"}
}