{
  "type": "Feature",
  "properties": {
    "gn:admin1_code":"13",
    "gn:asciiname":"Gowharabad",
    "gn:country_code":"IR",
    "gn:dem":1444,
    "gn:feature_class":"P",
    "gn:feature_code":"PPL",
    "gn:name":"Gowhar\u0101b\u0101d",
    "gn:population":0,
    "gn:timezone":"Asia/Tehran",
    "iso:country":"IR",
    "name:fas_x_preferred":[
        "\u06af\u0648\u0647\u0631 \u0622\u0628\u0627\u062f"
    ],
    "name:fas_x_variant":[
        "Gowhar\u0101b\u0101d"
    ],
    "wof:name":"Gowharabad",
    "wof:placetype":"locality"
},
  "geometry": {"coordinates":[46.6855,34.2689],"type":"Point"}
}