{
  "type": "Feature",
  "properties": {
    "gn:admin1_code":"41",
    "gn:asciiname":"Kalateh-ye Hoseyn",
    "gn:country_code":"IR",
    "gn:dem":1824,
    "gn:feature_class":"P",
    "gn:feature_code":"PPL",
    "gn:name":"Kal\u0101teh-ye \u1e28oseyn",
    "gn:population":0,
    "gn:timezone":"Asia/Tehran",
    "iso:country":"IR",
    "name:ara_x_preferred":[
        "\u0643\u0644\u0627\u062a\u0629 \u062d\u0633\u064a\u0646"
    ],
    "name:fas_x_preferred":[
        "Kal\u0101teh-ye \u1e28oseyn"
    ],
    "name:fas_x_variant":[
        "\u06a9\u0644\u0627\u062a\u0647 \u062d\u0633\u064a\u0646",
        "Kal\u0101teh Husain",
        "Kal\u0101t-e \u1e28oseyn",
        "\u06a9\u0644\u0627\u062a\u0647 \u062d\u0633\u06cc\u0646"
    ],
    "name:und_x_variant":[
        "Kalateh Hosein"
    ],
    "wof:name":"Kalateh-ye Hoseyn",
    "wof:placetype":"locality"
},
  "geometry": {"coordinates":[59.48656999999999,32.73443],"type":"Point"}
}