{
  "type": "Feature",
  "properties": {
    "gn:admin1_code":"29.0",
    "gn:asciiname":"Gozar",
    "gn:country_code":"IR",
    "gn:dem":1167,
    "gn:feature_class":"P",
    "gn:feature_code":"PPL",
    "gn:name":"Gozar",
    "gn:population":0,
    "gn:timezone":"Asia/Tehran",
    "iso:country":"IR",
    "name:fas_x_preferred":[
        "\u06af\u0632\u0631"
    ],
    "name:und_x_variant":[
        "Gazdar",
        "Gozar"
    ],
    "wof:name":"Gozar",
    "wof:placetype":"locality"
},
  "geometry": {"coordinates":[58.2532,29.1269],"type":"Point"}
}