{
  "type": "Feature",
  "properties": {
    "gn:admin1_code":"16",
    "gn:asciiname":"Khan Agah",
    "gn:country_code":"IR",
    "gn:dem":1139,
    "gn:feature_class":"P",
    "gn:feature_code":"PPL",
    "gn:name":"Kh\u0101n \u0100g\u0101h",
    "gn:population":0,
    "gn:timezone":"Asia/Tehran",
    "iso:country":"IR",
    "name:fas_x_preferred":[
        "\u062e\u0627\u0646 \u0622\u06af\u0627\u0647"
    ],
    "name:fas_x_variant":[
        "Kh\u0101naq\u0101h",
        "Kh\u0101n \u0100g\u0101h",
        "\u062e\u0627\u0646\u0642\u0627\u0647 \u0631\u0632\u0627\u0628"
    ],
    "name:und_x_variant":[
        "Kh\u0101n \u0100q\u0101h",
        "Kh\u0101n\u0101gah",
        "Kh\u0101neq\u0101h-e Zar \u0100b",
        "Kh\u0101neq\u0101h",
        "Kh\u0101neq\u0101h-e Raz\u0101b"
    ],
    "wof:name":"Khan Agah",
    "wof:placetype":"locality"
},
  "geometry": {"coordinates":[46.3974,35.2694],"type":"Point"}
}