{
  "type": "Feature",
  "properties": {
    "gn:admin1_code":"7",
    "gn:asciiname":"Mansuri-ye Pa'in",
    "gn:country_code":"IR",
    "gn:dem":1062,
    "gn:feature_class":"P",
    "gn:feature_code":"PPL",
    "gn:name":"Man\u015f\u016br\u012b-ye P\u0101\u2019\u012bn",
    "gn:population":0,
    "gn:timezone":"Asia/Tehran",
    "iso:country":"IR",
    "name:fas_x_preferred":[
        "\u0645\u0646\u0635\u0648\u0631\u06cc \u067e\u0627\u0626\u06cc\u0646"
    ],
    "name:fas_x_variant":[
        "Man\u015f\u016br\u012b-ye P\u0101\u2019\u012bn"
    ],
    "wof:name":"Mansuri-ye Pa'in",
    "wof:placetype":"locality"
},
  "geometry": {"coordinates":[54.3437,28.7585],"type":"Point"}
}