{
  "type": "Feature",
  "properties": {
    "gn:admin1_code":"33",
    "gn:asciiname":"Sorkheh Karan",
    "gn:country_code":"IR",
    "gn:dem":956,
    "gn:feature_class":"P",
    "gn:feature_code":"PPL",
    "gn:name":"Sorkheh Kar\u0101n",
    "gn:population":0,
    "gn:timezone":"Asia/Tehran",
    "iso:country":"IR",
    "name:fas_x_preferred":[
        "\u0633\u0631\u062e\u0647 \u06a9\u0631\u0627\u0646"
    ],
    "name:fas_x_variant":[
        "Sorkheh Kamr\u0101n",
        "Sorkheh Kar\u0101n"
    ],
    "wof:name":"Sorkheh Karan",
    "wof:placetype":"locality"
},
  "geometry": {"coordinates":[46.9654,38.9696],"type":"Point"}
}