{
  "type": "Feature",
  "properties": {
    "gn:admin1_code":"32",
    "gn:asciiname":"Makup Yanhasi",
    "gn:cc2":"IR",
    "gn:country_code":"IR",
    "gn:dem":1291,
    "gn:feature_class":"P",
    "gn:feature_code":"PPL",
    "gn:name":"Mak\u016bp Yanhas\u012b",
    "gn:population":0,
    "gn:timezone":"Asia/Tehran",
    "iso:country":"IR",
    "name:fas_x_preferred":[
        "\u0645\u064e\u0643\u0648\u067e \u064a\u064e\u0646\u0647\u064e\u0633\u06cc"
    ],
    "name:fas_x_variant":[
        "Mak\u016bp Yanhas\u012b"
    ],
    "name:und_x_variant":[
        "Magup Behehsi"
    ],
    "wof:name":"Makup Yanhasi",
    "wof:placetype":"locality"
},
  "geometry": {"coordinates":[48.11306,38.98389],"type":"Point"}
}