{
  "type": "Feature",
  "properties": {
    "gn:admin1_code":"42",
    "gn:asciiname":"Gavareshkan",
    "gn:country_code":"IR",
    "gn:dem":1280,
    "gn:feature_class":"P",
    "gn:feature_code":"PPL",
    "gn:name":"Gav\u0101reshk\u0101n",
    "gn:population":0,
    "gn:timezone":"Asia/Tehran",
    "iso:country":"IR",
    "name:ara_x_preferred":[
        "\u063a\u0648\u0627\u0631\u0634\u0643\u0627\u0646"
    ],
    "name:ceb_x_preferred":[
        "Gav\u0101reshg\u0101n"
    ],
    "name:fas_x_preferred":[
        "\u06af\u0648\u0627\u0631\u0634\u06af\u0627\u0646"
    ],
    "name:fas_x_variant":[
        "Gav\u0101reshkan",
        "Gav\u0101reshg\u0101n",
        "\u06af\u0648\u0627\u0631\u0634\u06a9\u0627\u0646"
    ],
    "name:swe_x_preferred":[
        "Gav\u0101reshg\u0101n"
    ],
    "name:und_x_variant":[
        "Gav\u0101reshk\u0101n"
    ],
    "wof:name":"Gavareshkan",
    "wof:placetype":"locality"
},
  "geometry": {"coordinates":[58.94259,36.88453],"type":"Point"}
}