{
  "type": "Feature",
  "properties": {
    "gn:admin1_code":"32",
    "gn:asciiname":"Tazeh Qeshlaq",
    "gn:country_code":"IR",
    "gn:dem":1500,
    "gn:feature_class":"P",
    "gn:feature_code":"PPL",
    "gn:name":"T\u0101zeh Qeshl\u0101q",
    "gn:population":0,
    "gn:timezone":"Asia/Tehran",
    "iso:country":"IR",
    "name:fas_x_preferred":[
        "\u062a\u0627\u0632\u0647 \u0642\u0634\u0644\u0627\u0642"
    ],
    "name:fas_x_variant":[
        "T\u0101zeh Qeshl\u0101q"
    ],
    "wof:name":"Tazeh Qeshlaq",
    "wof:placetype":"locality"
},
  "geometry": {"coordinates":[48.25489,37.98685],"type":"Point"}
}