{
  "type": "Feature",
  "properties": {
    "gn:admin1_code":"5.0",
    "gn:asciiname":"Gorgid-e Sarqaryab",
    "gn:country_code":"IR",
    "gn:dem":1231,
    "gn:feature_class":"P",
    "gn:feature_code":"PPL",
    "gn:name":"Gorg\u012bd-e Sarq\u0101ry\u0101b",
    "gn:population":0,
    "gn:timezone":"Asia/Tehran",
    "iso:country":"IR",
    "name:fas_x_preferred":[
        "Gorg\u012bd-e Sarq\u0101ry\u0101b"
    ],
    "name:fas_x_variant":[
        "\u06af\u0631\u06af\u06cc\u062f \u0633\u0631\u0642\u0627\u0631\u06cc\u0627\u0628"
    ],
    "wof:name":"Gorgid-e Sarqaryab",
    "wof:placetype":"locality"
},
  "geometry": {"coordinates":[50.85065,30.79561],"type":"Point"}
}