{
  "type": "Feature",
  "properties": {
    "gn:admin1_code":"4.0",
    "gn:asciiname":"Jaruk Mosafer",
    "gn:country_code":"IR",
    "gn:dem":496,
    "gn:feature_class":"P",
    "gn:feature_code":"PPL",
    "gn:name":"Jar\u016bk Mos\u0101fer",
    "gn:population":0,
    "gn:timezone":"Asia/Tehran",
    "iso:country":"IR",
    "name:fas_x_preferred":[
        "\u062c\u0631\u0648\u06a9 \u0645\u0633\u0627\u0641\u0631"
    ],
    "name:fas_x_variant":[
        "Jar\u016bk Mos\u0101fer"
    ],
    "wof:name":"Jaruk Mosafer",
    "wof:placetype":"locality"
},
  "geometry": {"coordinates":[61.7694,30.8113],"type":"Point"}
}