{
  "type": "Feature",
  "properties": {
    "gn:admin1_code":"35.0",
    "gn:asciiname":"Kuk Deh",
    "gn:country_code":"IR",
    "gn:dem":31,
    "gn:feature_class":"P",
    "gn:feature_code":"PPL",
    "gn:name":"K\u016bk Deh",
    "gn:population":0,
    "gn:timezone":"Asia/Tehran",
    "iso:country":"IR",
    "name:ara_x_preferred":[
        "\u0643\u0648\u0643\u062f\u0629"
    ],
    "name:ceb_x_preferred":[
        "K\u016bk Deh"
    ],
    "name:fas_x_preferred":[
        "\u0643\u0648\u06a9 \u062f\u0647"
    ],
    "name:fas_x_variant":[
        "K\u016bk Deh",
        "\u06a9\u0648\u06a9\u062f\u0647"
    ],
    "name:mzn_x_preferred":[
        "\u06a9\u0648\u06a9\u062f\u0647"
    ],
    "name:swe_x_preferred":[
        "K\u016bk Deh"
    ],
    "name:ukr_x_preferred":[
        "\u041a\u0443\u043a-\u0414\u0435\u0445"
    ],
    "wof:name":"Kuk Deh",
    "wof:placetype":"locality"
},
  "geometry": {"coordinates":[52.25258,36.49124000000001],"type":"Point"}
}