{
  "type": "Feature",
  "properties": {
    "gn:admin1_code":"13",
    "gn:asciiname":"Rostamabad",
    "gn:country_code":"IR",
    "gn:dem":1456,
    "gn:feature_class":"P",
    "gn:feature_code":"PPL",
    "gn:name":"Rostam\u0101b\u0101d",
    "gn:population":0,
    "gn:timezone":"Asia/Tehran",
    "iso:country":"IR",
    "name:fas_x_preferred":[
        "\u0631\u0633\u062a\u0645 \u0622\u0628\u0627\u062f"
    ],
    "name:fas_x_variant":[
        "Rostam\u0101b\u0101d",
        "\u0631\u0633\u062a\u0645\u200c\u0622\u0628\u0627\u062f"
    ],
    "wof:name":"Rostamabad",
    "wof:placetype":"locality"
},
  "geometry": {"coordinates":[47.9567,34.4811],"type":"Point"}
}