{
  "type": "Feature",
  "properties": {
    "gn:admin1_code":"35.0",
    "gn:asciiname":"Nafar",
    "gn:country_code":"IR",
    "gn:dem":1336,
    "gn:feature_class":"P",
    "gn:feature_code":"PPL",
    "gn:name":"Nafar",
    "gn:population":0,
    "gn:timezone":"Asia/Tehran",
    "iso:country":"IR",
    "name:fas_x_preferred":[
        "\u0646\u064e\u067e\u064e\u0631"
    ],
    "name:fas_x_variant":[
        "\u0646\u0641\u0631",
        "\u0646\u067e\u0631"
    ],
    "name:und_x_variant":[
        "\u0646\u0641\u0631",
        "Napar"
    ],
    "wof:name":"Nafar",
    "wof:placetype":"locality"
},
  "geometry": {"coordinates":[51.39428,36.41223],"type":"Point"}
}