{
  "type": "Feature",
  "properties": {
    "gn:admin1_code":"29.0",
    "gn:asciiname":"Tidu",
    "gn:country_code":"IR",
    "gn:dem":1883,
    "gn:feature_class":"P",
    "gn:feature_code":"PPL",
    "gn:name":"T\u012bd\u016b",
    "gn:population":0,
    "gn:timezone":"Asia/Tehran",
    "iso:country":"IR",
    "name:fas_x_preferred":[
        "T\u012bd\u016b"
    ],
    "wof:name":"Tidu",
    "wof:placetype":"locality"
},
  "geometry": {"coordinates":[58.20444000000001,28.86167],"type":"Point"}
}