{
  "type": "Feature",
  "properties": {
    "gn:admin1_code":"15",
    "gn:asciiname":"Chaga Sorkhak",
    "gn:country_code":"IR",
    "gn:dem":867,
    "gn:feature_class":"P",
    "gn:feature_code":"PPL",
    "gn:name":"Chag\u0101 Sorkhak",
    "gn:population":0,
    "gn:timezone":"Asia/Tehran",
    "iso:country":"IR",
    "name:ceb_x_preferred":[
        "Chag\u0101 Sorkhak"
    ],
    "name:fas_x_preferred":[
        "Chagh\u0101 Sorkhak"
    ],
    "name:fas_x_variant":[
        "Chagh\u0101 Sorkheh",
        "\u0686\u063a\u0627 \u0633\u0631\u062e\u0647",
        "\u0686\u06af\u0627 \u0633\u0631\u062e\u06a9",
        "\u0686\u063a\u0627\u0633\u0631\u062e\u06a9"
    ],
    "name:swe_x_preferred":[
        "Chag\u0101 Sorkhak"
    ],
    "wof:name":"Chaga Sorkhak",
    "wof:placetype":"locality"
},
  "geometry": {"coordinates":[50.00313,31.45333],"type":"Point"}
}