{
  "type": "Feature",
  "properties": {
    "gn:admin1_code":"5",
    "gn:asciiname":"Talishen",
    "gn:country_code":"IR",
    "gn:dem":2297,
    "gn:feature_class":"P",
    "gn:feature_code":"PPL",
    "gn:name":"T\u0101l\u012bshen",
    "gn:population":0,
    "gn:timezone":"Asia/Tehran",
    "iso:country":"IR",
    "name:fas_x_preferred":[
        "T\u0101l\u012bshen"
    ],
    "wof:name":"Talishen",
    "wof:placetype":"locality"
},
  "geometry": {"coordinates":[51.4825,30.52583],"type":"Point"}
}