{
  "type": "Feature",
  "properties": {
    "gn:admin1_code":"15",
    "gn:asciiname":"Do Dangeh-ye Bozorg",
    "gn:country_code":"IR",
    "gn:dem":312,
    "gn:feature_class":"P",
    "gn:feature_code":"PPL",
    "gn:name":"Do D\u0101ngeh-ye Bozorg",
    "gn:population":0,
    "gn:timezone":"Asia/Tehran",
    "iso:country":"IR",
    "name:fas_x_preferred":[
        "\u062f\u0648 \u062f\u0627\u0646\u06af\u0647 \u0628\u0632\u0631\u06af"
    ],
    "name:fas_x_variant":[
        "Do D\u0101ngeh-ye Bozorg"
    ],
    "name:und_x_variant":[
        "Do D\u0101ngeh Bozorg",
        "Dow D\u0101ngeh-ye Bozorg"
    ],
    "wof:name":"Do Dangeh-ye Bozorg",
    "wof:placetype":"locality"
},
  "geometry": {"coordinates":[50.1855,30.7124],"type":"Point"}
}