{
  "type": "Feature",
  "properties": {
    "gn:admin1_code":"29",
    "gn:asciiname":"Shadian",
    "gn:country_code":"IR",
    "gn:dem":2129,
    "gn:feature_class":"P",
    "gn:feature_code":"PPL",
    "gn:name":"Sh\u0101d\u012b\u0101n",
    "gn:population":0,
    "gn:timezone":"Asia/Tehran",
    "iso:country":"IR",
    "name:ara_x_preferred":[
        "\u0634\u0627\u062f\u064a\u0627\u0646"
    ],
    "name:fas_x_preferred":[
        "\u0634\u0627\u062f\u06cc\u0627\u0646"
    ],
    "name:fas_x_variant":[
        "Sh\u0101d\u012b\u0101n"
    ],
    "wof:name":"Shadian",
    "wof:placetype":"locality"
},
  "geometry": {"coordinates":[56.79848000000001,28.81215],"type":"Point"}
}