{
  "type": "Feature",
  "properties": {
    "gn:admin1_code":"7.0",
    "gn:asciiname":"Qal`eh-ye Parian",
    "gn:country_code":"IR",
    "gn:dem":721,
    "gn:feature_class":"P",
    "gn:feature_code":"PPL",
    "gn:name":"Qal\u2018eh-ye Par\u012b\u0101n",
    "gn:population":0,
    "gn:timezone":"Asia/Tehran",
    "iso:country":"IR",
    "name:fas_x_preferred":[
        "Qal\u2018eh-ye Par\u012b\u0101n"
    ],
    "wof:name":"Qal`eh-ye Parian",
    "wof:placetype":"locality"
},
  "geometry": {"coordinates":[53.04528000000001,28.46056],"type":"Point"}
}