{
  "type": "Feature",
  "properties": {
    "gn:admin1_code":"15",
    "gn:asciiname":"Chowvab",
    "gn:country_code":"IR",
    "gn:dem":794,
    "gn:feature_class":"P",
    "gn:feature_code":"PPL",
    "gn:name":"Chowv\u0101b",
    "gn:population":0,
    "gn:timezone":"Asia/Tehran",
    "iso:country":"IR",
    "name:fas_x_preferred":[
        "Chov\u0101b"
    ],
    "name:fas_x_variant":[
        "\u0686\u0648\u0648\u0627\u0628",
        "\u0631\u0627\u062f\u0632"
    ],
    "name:und_x_variant":[
        "Chowv\u0101b",
        "R\u0101dez"
    ],
    "wof:name":"Chowvab",
    "wof:placetype":"locality"
},
  "geometry": {"coordinates":[49.0929,32.8857],"type":"Point"}
}