{
  "type": "Feature",
  "properties": {
    "gn:admin1_code":"8",
    "gn:asciiname":"Sandian",
    "gn:country_code":"IR",
    "gn:dem":-5,
    "gn:feature_class":"P",
    "gn:feature_code":"PPL",
    "gn:name":"Sand\u012b\u0101n",
    "gn:population":0,
    "gn:timezone":"Asia/Tehran",
    "iso:country":"IR",
    "name:ceb_x_preferred":[
        "Sand\u012b\u0101n"
    ],
    "name:fas_x_preferred":[
        "\u0633\u0646\u062f\u06cc\u0627\u0646"
    ],
    "name:fas_x_variant":[
        "Sand\u012b\u0101n"
    ],
    "name:msa_x_preferred":[
        "Sandian"
    ],
    "name:swe_x_preferred":[
        "Sand\u012b\u0101n"
    ],
    "name:ukr_x_preferred":[
        "\u0421\u0430\u043d\u0434\u0456\u0430\u043d"
    ],
    "name:und_x_variant":[
        "Sand\u012bs\u0101n B\u0101z\u0101r"
    ],
    "wof:name":"Sandian",
    "wof:placetype":"locality"
},
  "geometry": {"coordinates":[49.12641,37.57342],"type":"Point"}
}