{
  "type": "Feature",
  "properties": {
    "gn:admin1_code":"41.0",
    "gn:asciiname":"Kalateh-ye `Aliabad",
    "gn:country_code":"IR",
    "gn:dem":1403,
    "gn:feature_class":"P",
    "gn:feature_code":"PPL",
    "gn:name":"Kal\u0101teh-ye \u2018Al\u012b\u0101b\u0101d",
    "gn:population":0,
    "gn:timezone":"Asia/Tehran",
    "iso:country":"IR",
    "name:fas_x_preferred":[
        "Kal\u0101teh-ye \u2018Al\u012b\u0101b\u0101d"
    ],
    "name:und_x_variant":[
        "\u2018Al\u012b\u0101b\u0101d",
        "Kal\u0101teh \u2018Al\u012b\u0101b\u0101d"
    ],
    "wof:name":"Kalateh-ye `Aliabad",
    "wof:placetype":"locality"
},
  "geometry": {"coordinates":[58.96694,32.60528],"type":"Point"}
}