{
  "type": "Feature",
  "properties": {
    "gn:admin1_code":"11",
    "gn:asciiname":"Shambiran",
    "gn:country_code":"IR",
    "gn:dem":16,
    "gn:feature_class":"P",
    "gn:feature_code":"PPL",
    "gn:name":"Shamb\u012br\u0101n",
    "gn:population":0,
    "gn:timezone":"Asia/Tehran",
    "iso:country":"IR",
    "name:ceb_x_preferred":[
        "Shamb\u012br\u0101n"
    ],
    "name:fas_x_preferred":[
        "\u0634\u0645\u0628\u064a\u0631\u0627\u0646"
    ],
    "name:fas_x_variant":[
        "Shamb\u012br\u0101n",
        "\u0634\u0645\u064a\u0631\u0627\u0646",
        "\u0634\u0645\u0628\u06cc\u0631\u0627\u0646"
    ],
    "name:msa_x_preferred":[
        "Shambiran"
    ],
    "name:swe_x_preferred":[
        "Shamb\u012br\u0101n"
    ],
    "name:und_x_variant":[
        "Sham\u012br\u0101n"
    ],
    "wof:name":"Shambiran",
    "wof:placetype":"locality"
},
  "geometry": {"coordinates":[57.2462,26.0565],"type":"Point"}
}