{
  "type": "Feature",
  "properties": {
    "gn:admin1_code":"5",
    "gn:asciiname":"Khiar Kaleh",
    "gn:country_code":"IR",
    "gn:dem":886,
    "gn:feature_class":"P",
    "gn:feature_code":"PPL",
    "gn:name":"Kh\u012b\u0101r K\u0101leh",
    "gn:population":0,
    "gn:timezone":"Asia/Tehran",
    "iso:country":"IR",
    "name:fas_x_preferred":[
        "Kh\u012b\u0101r K\u0101leh"
    ],
    "name:fas_x_variant":[
        "\u062e\u064a\u0627\u0631 \u0643\u0627\u0644\u0647"
    ],
    "wof:name":"Khiar Kaleh",
    "wof:placetype":"locality"
},
  "geometry": {"coordinates":[50.62013,30.85604],"type":"Point"}
}