{
  "type": "Feature",
  "properties": {
    "gn:admin1_code":"8",
    "gn:asciiname":"Gilvana",
    "gn:country_code":"IR",
    "gn:dem":536,
    "gn:feature_class":"P",
    "gn:feature_code":"PPL",
    "gn:name":"G\u012blv\u0101n\u0101",
    "gn:population":0,
    "gn:timezone":"Asia/Tehran",
    "iso:country":"IR",
    "name:fas_x_preferred":[
        "G\u012blv\u0101n\u0101"
    ],
    "wof:name":"Gilvana",
    "wof:placetype":"locality"
},
  "geometry": {"coordinates":[48.95972,37.37194],"type":"Point"}
}