{
  "type": "Feature",
  "properties": {
    "gn:admin1_code":"41",
    "gn:asciiname":"Kalateh-ye Qasem",
    "gn:country_code":"IR",
    "gn:dem":1909,
    "gn:feature_class":"P",
    "gn:feature_code":"PPL",
    "gn:name":"Kal\u0101teh-ye Q\u0101sem",
    "gn:population":0,
    "gn:timezone":"Asia/Tehran",
    "iso:country":"IR",
    "wof:name":"Kalateh-ye Qasem",
    "wof:placetype":"locality"
},
  "geometry": {"coordinates":[59.66056,31.90861],"type":"Point"}
}