{
  "type": "Feature",
  "properties": {
    "gn:admin1_code":"43.0",
    "gn:asciiname":"Mazra`eh-ye Khowjehlar",
    "gn:country_code":"IR",
    "gn:dem":892,
    "gn:feature_class":"P",
    "gn:feature_code":"PPL",
    "gn:name":"Mazra\u2018eh-ye Khowjehlar",
    "gn:population":0,
    "gn:timezone":"Asia/Tehran",
    "iso:country":"IR",
    "name:fas_x_preferred":[
        "\u0645\u0632\u0631\u0639\u0647 \u062e\u0648\u062c\u0647 \u0644\u0631"
    ],
    "name:und_x_variant":[
        "Mazra\u2018eh-ye Khowjehlar",
        "Khojakaleh"
    ],
    "wof:name":"Mazra`eh-ye Khowjehlar",
    "wof:placetype":"locality"
},
  "geometry": {"coordinates":[56.77206999999999,38.24293],"type":"Point"}
}