{
  "type": "Feature",
  "properties": {
    "gn:admin1_code":"37",
    "gn:asciiname":"Zendan Chal",
    "gn:country_code":"IR",
    "gn:dem":815,
    "gn:feature_class":"P",
    "gn:feature_code":"PPL",
    "gn:name":"Zend\u0101n Ch\u0101l",
    "gn:population":0,
    "gn:timezone":"Asia/Tehran",
    "iso:country":"IR",
    "name:ceb_x_preferred":[
        "Zend\u0101n Ch\u0101l"
    ],
    "name:fas_x_preferred":[
        "Zend\u0101n Ch\u0101l"
    ],
    "name:fas_x_variant":[
        "\u0632\u0646\u062f\u0627\u0646 \u0686\u0627\u0644",
        "\u0632\u0646\u062f\u0627\u0646\u200c\u0686\u0627\u0644"
    ],
    "name:msa_x_preferred":[
        "Zendan Chal"
    ],
    "name:swe_x_preferred":[
        "Zend\u0101n Ch\u0101l"
    ],
    "name:und_x_variant":[
        "\u0632\u0646\u062f\u0627\u0646 \u0686\u0627\u0644"
    ],
    "wof:name":"Zendan Chal",
    "wof:placetype":"locality"
},
  "geometry": {"coordinates":[55.47774,37.09341],"type":"Point"}
}