{
  "type": "Feature",
  "properties": {
    "gn:admin1_code":"23",
    "gn:asciiname":"Kapargah",
    "gn:country_code":"IR",
    "gn:dem":1238,
    "gn:feature_class":"P",
    "gn:feature_code":"PPL",
    "gn:name":"Kapargah",
    "gn:population":0,
    "gn:timezone":"Asia/Tehran",
    "iso:country":"IR",
    "name:fas_x_preferred":[
        "\u0643\u064e\u067e\u064e\u0631\u06af\u0627\u0647\u0650 \u0622\u0642\u0627 \u062d\u064f\u0633\u0650\u064a\u0646"
    ],
    "name:fas_x_variant":[
        "\u06a9\u067e\u0631\u06af\u0647",
        "\u0634\u0647\u06cc\u062f \u0686\u0645\u0631\u0627\u0646 \u06cc\u06a9",
        "\u06a9\u067e\u0631\u06af\u0647 \u0627\u0642\u0627 \u062d\u0633\u064a\u0646",
        "\u06a9\u067e\u0631\u06af\u0647 \u0622\u0642\u0627\u062d\u0633\u06cc\u0646"
    ],
    "name:und_x_variant":[
        "Kapargah-e Aq\u0101 \u1e28oseyn",
        "Kapargah",
        "Shah\u012bd Chamr\u0101n-e Yek"
    ],
    "wof:name":"Kapargah",
    "wof:placetype":"locality"
},
  "geometry": {"coordinates":[48.08577,33.21426],"type":"Point"}
}