{
  "type": "Feature",
  "properties": {
    "gn:admin1_code":"38",
    "gn:asciiname":"Bayeh",
    "gn:country_code":"IR",
    "gn:dem":1206,
    "gn:feature_class":"P",
    "gn:feature_code":"PPL",
    "gn:name":"B\u0101yeh",
    "gn:population":0,
    "gn:timezone":"Asia/Tehran",
    "iso:country":"IR",
    "name:ceb_x_preferred":[
        "No\u015frat\u0101b\u0101d-e B\u0101yeh"
    ],
    "name:fas_x_preferred":[
        "No\u015frat\u0101b\u0101d-e B\u0101yeh"
    ],
    "name:fas_x_variant":[
        "\u0646\u0635\u0631\u062a \u0622\u0628\u0627\u062f \u0628\u0627\u064a\u0647",
        "\u0646\u0635\u0631\u062a \u0622\u0628\u0627\u062f \u0628\u0627\u0628\u0647",
        "No\u015frat\u0101b\u0101d-e B\u0101beh",
        "\u0628\u0627\u0628\u0647",
        "\u0646\u0635\u0631\u062a\u200c\u0622\u0628\u0627\u062f \u0628\u0627\u06cc\u0647"
    ],
    "name:swe_x_preferred":[
        "No\u015frat\u0101b\u0101d-e B\u0101yeh"
    ],
    "name:und_x_variant":[
        "B\u0101yeh",
        "B\u0101ya"
    ],
    "wof:name":"Bayeh",
    "wof:placetype":"locality"
},
  "geometry": {"coordinates":[49.9994,36.0954],"type":"Point"}
}