{
  "type": "Feature",
  "properties": {
    "gn:admin1_code":"26.0",
    "gn:asciiname":"Yaqeh",
    "gn:country_code":"IR",
    "gn:dem":1088,
    "gn:feature_class":"P",
    "gn:feature_code":"PPL",
    "gn:name":"Yaqeh",
    "gn:population":0,
    "gn:timezone":"Asia/Tehran",
    "iso:country":"IR",
    "name:fas_x_preferred":[
        "\u064a\u0642\u0647"
    ],
    "name:fas_x_variant":[
        "\u0644\u0642\u0647"
    ],
    "name:und_x_variant":[
        "Laqeh",
        "\u0644\u0642\u0647"
    ],
    "wof:name":"Yaqeh",
    "wof:placetype":"locality"
},
  "geometry": {"coordinates":[51.0381,35.5556],"type":"Point"}
}