{
  "type": "Feature",
  "properties": {
    "gn:admin1_code":"9",
    "gn:asciiname":"Qarah Day",
    "gn:country_code":"IR",
    "gn:dem":1600,
    "gn:feature_class":"P",
    "gn:feature_code":"PPL",
    "gn:name":"Qarah D\u0101y",
    "gn:population":0,
    "gn:timezone":"Asia/Tehran",
    "iso:country":"IR",
    "name:fas_x_preferred":[
        "\u0642\u0631\u0647 \u062f\u0627\u06cc"
    ],
    "name:fas_x_variant":[
        "Qareh D\u0101y",
        "Qarah D\u0101y"
    ],
    "name:und_x_variant":[
        "Qara Deh",
        "Qar\u0101 D\u0101y"
    ],
    "wof:name":"Qarah Day",
    "wof:placetype":"locality"
},
  "geometry": {"coordinates":[49.28233,35.12522],"type":"Point"}
}