{
  "type": "Feature",
  "properties": {
    "gn:admin1_code":"37.0",
    "gn:asciiname":"Aqa Mohammad",
    "gn:country_code":"IR",
    "gn:dem":18,
    "gn:feature_class":"P",
    "gn:feature_code":"PPL",
    "gn:name":"\u0100q\u0101 Mo\u1e29ammad",
    "gn:population":0,
    "gn:timezone":"Asia/Tehran",
    "iso:country":"IR",
    "name:fas_x_preferred":[
        "\u0100q\u0101 Mo\u1e29ammad"
    ],
    "wof:name":"Aqa Mohammad",
    "wof:placetype":"locality"
},
  "geometry": {"coordinates":[54.81667,37.61667],"type":"Point"}
}