{
  "type": "Feature",
  "properties": {
    "gn:admin1_code":"28.0",
    "gn:asciiname":"Khowrchan",
    "gn:country_code":"IR",
    "gn:dem":1508,
    "gn:feature_class":"P",
    "gn:feature_code":"PPL",
    "gn:name":"Khowrch\u0101n",
    "gn:population":0,
    "gn:timezone":"Asia/Tehran",
    "iso:country":"IR",
    "name:fas_x_preferred":[
        "\u062e\u0648\u0631\u0686\u0627\u0646"
    ],
    "name:fas_x_variant":[
        "Kh\u016brch\u0101n"
    ],
    "name:und_x_variant":[
        "Kharch\u016bn",
        "Khorch\u016bn",
        "Khorech\u016bn",
        "Khowrch\u0101n"
    ],
    "wof:name":"Khowrchan",
    "wof:placetype":"locality"
},
  "geometry": {"coordinates":[52.1937,32.4732],"type":"Point"}
}