{
  "type": "Feature",
  "properties": {
    "gn:admin1_code":"42",
    "gn:asciiname":"Almeh Juq",
    "gn:country_code":"IR",
    "gn:dem":1698,
    "gn:feature_class":"P",
    "gn:feature_code":"PPL",
    "gn:name":"\u0100lmeh J\u016bq",
    "gn:population":0,
    "gn:timezone":"Asia/Tehran",
    "iso:country":"IR",
    "name:fas_x_preferred":[
        "\u0622\u0644\u0645\u0647 \u062c\u0648\u0642"
    ],
    "name:fas_x_variant":[
        "Kam J\u016bq",
        "\u0100lmeh J\u016bq"
    ],
    "name:und_x_variant":[
        "Almeh J\u016bq"
    ],
    "wof:name":"Almeh Juq",
    "wof:placetype":"locality"
},
  "geometry": {"coordinates":[59.59103,35.77803],"type":"Point"}
}