{
  "type": "Feature",
  "properties": {
    "gn:admin1_code":"35.0",
    "gn:asciiname":"Padizan",
    "gn:country_code":"IR",
    "gn:dem":1850,
    "gn:feature_class":"P",
    "gn:feature_code":"PPL",
    "gn:name":"Pad\u012bzan",
    "gn:population":0,
    "gn:timezone":"Asia/Tehran",
    "iso:country":"IR",
    "name:fas_x_preferred":[
        "\u067e\u062f\u06cc\u0632\u0646"
    ],
    "name:und_x_variant":[
        "Pad\u012bzan"
    ],
    "wof:name":"Padizan",
    "wof:placetype":"locality"
},
  "geometry": {"coordinates":[51.96513,36.19803],"type":"Point"}
}