{
  "type": "Feature",
  "properties": {
    "gn:admin1_code":"32",
    "gn:asciiname":"Ravinduzaq",
    "gn:country_code":"IR",
    "gn:dem":1310,
    "gn:feature_class":"P",
    "gn:feature_code":"PPL",
    "gn:name":"Rav\u012bnd\u016bzaq",
    "gn:population":0,
    "gn:timezone":"Asia/Tehran",
    "iso:country":"IR",
    "name:fas_x_preferred":[
        "\u0642\u0648\u0646\u0627\u0642 \u0642\u0650\u0631\u0627\u0646"
    ],
    "name:fas_x_variant":[
        "\u0631\u0648\u064a\u0646\u062f\u0648\u0632\u0642",
        "Q\u016bn\u0101q Qer\u0101n",
        "Rav\u012bnd\u016bzaq"
    ],
    "wof:name":"Ravinduzaq",
    "wof:placetype":"locality"
},
  "geometry": {"coordinates":[48.08,38.4398],"type":"Point"}
}