{
  "type": "Feature",
  "properties": {
    "gn:admin1_code":"23",
    "gn:asciiname":"Yar `Ali",
    "gn:country_code":"IR",
    "gn:dem":2036,
    "gn:feature_class":"P",
    "gn:feature_code":"PPL",
    "gn:name":"Y\u0101r \u2018Al\u012b",
    "gn:population":0,
    "gn:timezone":"Asia/Tehran",
    "iso:country":"IR",
    "name:fas_x_preferred":[
        "\u064a\u0627\u0631 \u0639\u0644\u06cc"
    ],
    "name:fas_x_variant":[
        "Y\u0101r \u2018Al\u012b"
    ],
    "wof:name":"Yar `Ali",
    "wof:placetype":"locality"
},
  "geometry": {"coordinates":[48.8642,33.5228],"type":"Point"}
}