{
  "type": "Feature",
  "properties": {
    "gn:admin1_code":"11",
    "gn:asciiname":"Hashemabad",
    "gn:country_code":"IR",
    "gn:dem":725,
    "gn:feature_class":"P",
    "gn:feature_code":"PPL",
    "gn:name":"H\u0101shem\u0101b\u0101d",
    "gn:population":0,
    "gn:timezone":"Asia/Tehran",
    "iso:country":"IR",
    "name:fas_x_preferred":[
        "\u0647\u0627\u0634\u0645 \u0622\u0628\u0627\u062f \u067e\u062a\u06a9\u0648\u0626\u06cc\u0651\u0647"
    ],
    "name:fas_x_variant":[
        "H\u0101shem\u0101b\u0101d-e Patk\u016b\u2019\u012byeh",
        "\u0647\u0627\u0634\u0645 \u0622\u0628\u0627\u062f",
        "\u0647\u0627\u0634\u0645\u200c\u0622\u0628\u0627\u062f"
    ],
    "name:msa_x_preferred":[
        "Hashemabad"
    ],
    "name:und_x_variant":[
        "H\u0101shem\u0101b\u0101d"
    ],
    "wof:name":"Hashemabad",
    "wof:placetype":"locality"
},
  "geometry": {"coordinates":[55.7635,28.1795],"type":"Point"}
}