{
  "type": "Feature",
  "properties": {
    "gn:admin1_code":"8",
    "gn:asciiname":"Daramsiah Bil",
    "gn:country_code":"IR",
    "gn:dem":802,
    "gn:feature_class":"P",
    "gn:feature_code":"PPL",
    "gn:name":"Darams\u012b\u0101h B\u012bl",
    "gn:population":0,
    "gn:timezone":"Asia/Tehran",
    "iso:country":"IR",
    "name:fas_x_preferred":[
        "\u0633\u06cc\u0627\u0647 \u0628\u06cc\u0644"
    ],
    "name:fas_x_variant":[
        "S\u012b\u0101hb\u012bl",
        "S\u012b\u0101h B\u012bl",
        "\u062f\u0631\u0645\u0633\u06cc\u0627\u0647 \u0628\u06cc\u0644"
    ],
    "name:und_x_variant":[
        "Darams\u012b\u0101h B\u012bl"
    ],
    "wof:name":"Daramsiah Bil",
    "wof:placetype":"locality"
},
  "geometry": {"coordinates":[48.95662,37.49952],"type":"Point"}
}