{
  "type": "Feature",
  "properties": {
    "gn:admin1_code":"8.0",
    "gn:asciiname":"Elateh Zamin",
    "gn:country_code":"IR",
    "gn:dem":2777,
    "gn:feature_class":"P",
    "gn:feature_code":"PPL",
    "gn:name":"El\u0101teh Zam\u012bn",
    "gn:population":0,
    "gn:timezone":"Asia/Tehran",
    "iso:country":"IR",
    "name:fas_x_preferred":[
        "El\u0101teh Zam\u012bn"
    ],
    "wof:name":"Elateh Zamin",
    "wof:placetype":"locality"
},
  "geometry": {"coordinates":[48.98333,37.10806],"type":"Point"}
}