{
  "type": "Feature",
  "properties": {
    "gn:admin1_code":"16",
    "gn:asciiname":"Kowleh",
    "gn:country_code":"IR",
    "gn:dem":1805,
    "gn:feature_class":"P",
    "gn:feature_code":"PPL",
    "gn:name":"Kowleh",
    "gn:population":0,
    "gn:timezone":"Asia/Tehran",
    "iso:country":"IR",
    "name:fas_x_preferred":[
        "\u06a9\u0648\u0644\u0647"
    ],
    "name:und_x_variant":[
        "Qaula",
        "Ka\u016bleh",
        "K\u016bleh",
        "Kooleh",
        "Kowleh"
    ],
    "wof:name":"Kowleh",
    "wof:placetype":"locality"
},
  "geometry": {"coordinates":[47.0533,35.79039],"type":"Point"}
}