{
  "type": "Feature",
  "properties": {
    "gn:admin1_code":"4",
    "gn:asciiname":"Gazuki",
    "gn:country_code":"IR",
    "gn:dem":654,
    "gn:feature_class":"P",
    "gn:feature_code":"PPL",
    "gn:name":"Gaz\u016bk\u012b",
    "gn:population":0,
    "gn:timezone":"Asia/Tehran",
    "iso:country":"IR",
    "name:fas_x_preferred":[
        "\u06af\u0632\u0648\u06a9\u06cc"
    ],
    "name:fas_x_variant":[
        "Gaz\u016bk\u012b"
    ],
    "wof:name":"Gazuki",
    "wof:placetype":"locality"
},
  "geometry": {"coordinates":[60.57083000000001,27.28631],"type":"Point"}
}