{
  "type": "Feature",
  "properties": {
    "gn:admin1_code":"28",
    "gn:asciiname":"Iragh",
    "gn:country_code":"IR",
    "gn:dem":1248,
    "gn:feature_class":"P",
    "gn:feature_code":"PPL",
    "gn:name":"Iragh",
    "gn:population":0,
    "gn:timezone":"Asia/Tehran",
    "iso:country":"IR",
    "name:fas_x_preferred":[
        "\u012ar\u0101j"
    ],
    "name:fas_x_variant":[
        "\u0627\u064a\u0631\u0627\u062c",
        "\u0627\u06cc\u0631\u0627\u062c"
    ],
    "name:und_x_variant":[
        "\u2018Ir\u0101q",
        "Iragh"
    ],
    "wof:name":"Iragh",
    "wof:placetype":"locality"
},
  "geometry": {"coordinates":[54.86866,33.45762],"type":"Point"}
}