{
  "type": "Feature",
  "properties": {
    "gn:admin1_code":"22",
    "gn:asciiname":"Chah Pir",
    "gn:country_code":"IR",
    "gn:dem":38,
    "gn:feature_class":"P",
    "gn:feature_code":"PPL",
    "gn:name":"Ch\u0101h P\u012br",
    "gn:population":0,
    "gn:timezone":"Asia/Tehran",
    "iso:country":"IR",
    "name:ceb_x_preferred":[
        "Ch\u0101h P\u012br"
    ],
    "name:fas_x_preferred":[
        "\u0686\u0627\u0647 \u067e\u064a\u0631"
    ],
    "name:fas_x_variant":[
        "Ch\u0101h P\u012br",
        "\u0634\u0627\u0647 \u067e\u064a\u0631",
        "\u0686\u0627\u0647\u200c\u067e\u06cc\u0631"
    ],
    "name:msa_x_preferred":[
        "Chah Pir"
    ],
    "name:swe_x_preferred":[
        "Ch\u0101h P\u012br"
    ],
    "name:und_x_variant":[
        "Sh\u0101h P\u012br",
        "Ch\u0101h-i-P\u012br",
        "Ch\u0101h-e P\u012br"
    ],
    "wof:name":"Chah Pir",
    "wof:placetype":"locality"
},
  "geometry": {"coordinates":[51.22058,28.99939],"type":"Point"}
}