{
  "type": "Feature",
  "properties": {
    "gn:admin1_code":"23",
    "gn:asciiname":"Tudar-e Shah Karami",
    "gn:country_code":"IR",
    "gn:dem":1133,
    "gn:feature_class":"P",
    "gn:feature_code":"PPL",
    "gn:name":"T\u016bd\u0101r-e Sh\u0101h Karam\u012b",
    "gn:population":0,
    "gn:timezone":"Asia/Tehran",
    "iso:country":"IR",
    "name:fas_x_preferred":[
        "T\u016bd\u0101r-e Sh\u0101h Karam\u012b"
    ],
    "name:fas_x_variant":[
        "T\u016bdar-e Sh\u0101ker\u012b",
        "\u062a\u0648\u062f\u0627\u0631 \u0634\u0627\u0647 \u06a9\u0631\u0645\u06cc",
        "\u062a\u0648\u062f\u0627\u0631\u0634\u0627\u0647 \u06a9\u0631\u0645\u06cc"
    ],
    "wof:name":"Tudar-e Shah Karami",
    "wof:placetype":"locality"
},
  "geometry": {"coordinates":[48.0063,33.4205],"type":"Point"}
}