{
  "type": "Feature",
  "properties": {
    "gn:admin1_code":"7",
    "gn:asciiname":"Sharqi",
    "gn:country_code":"IR",
    "gn:dem":1243,
    "gn:feature_class":"P",
    "gn:feature_code":"PPL",
    "gn:name":"Sharq\u012b",
    "gn:population":0,
    "gn:timezone":"Asia/Tehran",
    "iso:country":"IR",
    "name:fas_x_preferred":[
        "\u0634\u0631\u0642\u06cc"
    ],
    "name:fas_x_variant":[
        "Sharq\u012b"
    ],
    "name:msa_x_preferred":[
        "Sharqi"
    ],
    "name:und_x_variant":[
        "Mazra\u2018eh-ye M\u016brd",
        "Shahraki",
        "Sharq\u012b-ye Mazra\u2018eh-ye M\u016brd"
    ],
    "wof:name":"Sharqi",
    "wof:placetype":"locality"
},
  "geometry": {"coordinates":[53.2611,28.9333],"type":"Point"}
}