{
  "type": "Feature",
  "properties": {
    "gn:admin1_code":"35",
    "gn:asciiname":"Khalkhal Mahalleh-ye Jadid",
    "gn:country_code":"IR",
    "gn:dem":13,
    "gn:feature_class":"P",
    "gn:feature_code":"PPL",
    "gn:name":"Khalkh\u0101l Ma\u1e29alleh-ye Jad\u012bd",
    "gn:population":0,
    "gn:timezone":"Asia/Tehran",
    "iso:country":"IR",
    "name:fas_x_preferred":[
        "Khalkh\u0101l\u012b Ma\u1e29alleh"
    ],
    "name:fas_x_variant":[
        "\u062e\u0644\u062e\u0627\u0644\u06cc \u0645\u062d\u0644\u0647",
        "\u062e\u0644\u062e\u0627\u0644 \u0645\u062d\u0644\u0647 \u062c\u062f\u064a\u062f",
        "\u062e\u0644\u062e\u0627\u0644\u200c\u0645\u062d\u0644\u0647 \u062c\u062f\u06cc\u062f"
    ],
    "name:und_x_variant":[
        "Khalkh\u0101l Ma\u1e29alleh",
        "Khalkh\u0101l Ma\u1e29alleh-ye Jad\u012bd"
    ],
    "wof:name":"Khalkhal Mahalleh-ye Jadid",
    "wof:placetype":"locality"
},
  "geometry": {"coordinates":[50.83037,36.81311],"type":"Point"}
}