{
  "type": "Feature",
  "properties": {
    "gn:admin1_code":"7.0",
    "gn:asciiname":"Najafabad",
    "gn:country_code":"IR",
    "gn:dem":1748,
    "gn:feature_class":"P",
    "gn:feature_code":"PPL",
    "gn:name":"Najaf\u0101b\u0101d",
    "gn:population":0,
    "gn:timezone":"Asia/Tehran",
    "iso:country":"IR",
    "name:fas_x_preferred":[
        "\u0646\u062c\u0641 \u0622\u0628\u0627\u062f"
    ],
    "name:fas_x_variant":[
        "Najaf\u0101b\u0101d"
    ],
    "wof:name":"Najafabad",
    "wof:placetype":"locality"
},
  "geometry": {"coordinates":[52.4827,29.2093],"type":"Point"}
}