{
  "type": "Feature",
  "properties": {
    "gn:admin1_code":"7",
    "gn:asciiname":"Chekak",
    "gn:country_code":"IR",
    "gn:dem":1046,
    "gn:feature_class":"P",
    "gn:feature_code":"PPL",
    "gn:name":"Chekak",
    "gn:population":0,
    "gn:timezone":"Asia/Tehran",
    "iso:country":"IR",
    "name:fas_x_preferred":[
        "\u0686\u06a9\u06a9"
    ],
    "name:msa_x_preferred":[
        "Chekak"
    ],
    "name:und_x_variant":[
        "Jakak",
        "Chegak"
    ],
    "wof:name":"Chekak",
    "wof:placetype":"locality"
},
  "geometry": {"coordinates":[51.68834,29.8128],"type":"Point"}
}