{
  "type": "Feature",
  "properties": {
    "gn:admin1_code":"7",
    "gn:asciiname":"Tavileh Band",
    "gn:country_code":"IR",
    "gn:dem":2057,
    "gn:feature_class":"P",
    "gn:feature_code":"PPL",
    "gn:name":"\u0162av\u012bleh Band",
    "gn:population":0,
    "gn:timezone":"Asia/Tehran",
    "iso:country":"IR",
    "name:fas_x_preferred":[
        "\u0637\u0648\u06cc\u0644\u0647 \u0628\u0646\u062f"
    ],
    "name:fas_x_variant":[
        "\u0162av\u012bleh Band",
        "\u0646\u0648\u0631 \u0622\u0628\u0627\u062f"
    ],
    "name:und_x_variant":[
        "N\u016br\u0101b\u0101d"
    ],
    "wof:name":"Tavileh Band",
    "wof:placetype":"locality"
},
  "geometry": {"coordinates":[52.0564,30.6603],"type":"Point"}
}