{
  "type": "Feature",
  "properties": {
    "gn:admin1_code":"9",
    "gn:asciiname":"Raziabad",
    "gn:country_code":"IR",
    "gn:dem":1656,
    "gn:feature_class":"P",
    "gn:feature_code":"PPL",
    "gn:name":"Ra\u1e95\u012b\u0101b\u0101d",
    "gn:population":0,
    "gn:timezone":"Asia/Tehran",
    "iso:country":"IR",
    "name:fas_x_preferred":[
        "\u0631\u0636\u06cc \u0622\u0628\u0627\u062f"
    ],
    "name:fas_x_variant":[
        "Ra\u1e95\u012b\u0101b\u0101d",
        "\u0639\u0644\u06cc \u0622\u0628\u0627\u062f"
    ],
    "name:und_x_variant":[
        "Ra\u1e95\u012b\u0101b\u0101d",
        "Raz\u012b\u0101b\u0101d",
        "Raj\u012b\u0101b\u0101d",
        "Al\u012b\u0101b\u0101d"
    ],
    "wof:name":"Raziabad",
    "wof:placetype":"locality"
},
  "geometry": {"coordinates":[48.38457,34.1671],"type":"Point"}
}