{
  "type": "Feature",
  "properties": {
    "gn:admin1_code":"7",
    "gn:asciiname":"Chah Ab Siri",
    "gn:country_code":"IR",
    "gn:dem":1604,
    "gn:feature_class":"P",
    "gn:feature_code":"PPL",
    "gn:name":"Ch\u0101h \u0100b S\u012br\u012b",
    "gn:population":0,
    "gn:timezone":"Asia/Tehran",
    "iso:country":"IR",
    "name:fas_x_preferred":[
        "\u0645\u0632\u0631\u0639\u0647 \u0633\u06cc\u062f\u06cc"
    ],
    "name:fas_x_variant":[
        "Ch\u0101h-e Seyyed\u012b",
        "Mazra\u2018eh Seyyed\u012b",
        "\u0686\u0627\u0647 \u0622\u0628 \u0633\u06cc\u0631\u06cc"
    ],
    "name:und_x_variant":[
        "Ch\u0101h \u0100b S\u012br\u012b"
    ],
    "wof:name":"Chah Ab Siri",
    "wof:placetype":"locality"
},
  "geometry": {"coordinates":[52.7919,30.0037],"type":"Point"}
}