{
  "type": "Feature",
  "properties": {
    "gn:country":"IR",
    "gn:fcode":"PPL",
    "gn:population":4500,
    "iso:country":"IR",
    "name:bul_x_preferred":[
        "\u0417\u0438\u0430\u0431\u0430\u0440"
    ],
    "name:ceb_x_preferred":[
        "Ziabar"
    ],
    "name:eng_x_preferred":[
        "Ziabar"
    ],
    "name:fas_x_preferred":[
        "\u0636\u06cc\u0627\u0628\u0631"
    ],
    "name:fas_x_variant":[
        "\u1e94\u012b\u0101\u2019 Bar",
        "\u1e94\u012b\u0101bar"
    ],
    "name:msa_x_preferred":[
        "Ziabar"
    ],
    "name:nld_x_preferred":[
        "Ziabar"
    ],
    "name:swe_x_preferred":[
        "Ziabar"
    ],
    "name:ukr_x_preferred":[
        "\u0417\u0456\u044f\u0431\u0430\u0440"
    ],
    "name:und_x_variant":[
        "Z\u012by\u0101\u2019 Bar"
    ],
    "qs_pg:aaroncc":"IR",
    "qs_pg:gn_country":"IR",
    "qs_pg:gn_fcode":"PPL",
    "qs_pg:gn_pop":4500,
    "qs_pg:name":"Ziabar",
    "qs_pg:photos_9r":0,
    "qs_pg:photos_sr":0,
    "qs_pg:pop_sr":4,
    "qs_pg:qs_pg_placetype":"locality",
    "wof:name":"Ziabar",
    "wof:placetype":"locality",
    "wof:population":4500
},
  "geometry": {"coordinates":[49.2459,37.4261],"type":"Point"}
}