{
  "type": "Feature",
  "properties": {
    "gn:admin1_code":"8.0",
    "gn:asciiname":"Bala Mahalleh-ye Lafmejan",
    "gn:country_code":"IR",
    "gn:dem":-3,
    "gn:feature_class":"P",
    "gn:feature_code":"PPL",
    "gn:name":"B\u0101l\u0101 Ma\u1e29alleh-ye Lafmej\u0101n",
    "gn:population":0,
    "gn:timezone":"Asia/Tehran",
    "iso:country":"IR",
    "name:ceb_x_preferred":[
        "Lafmej\u0101n"
    ],
    "name:fas_x_preferred":[
        "B\u0101l\u0101 Ma\u1e29alleh-ye Lafmej\u0101n"
    ],
    "name:fas_x_variant":[
        "\u0628\u0627\u0644\u0627\u0645\u062d\u0644\u0647 \u0644\u0641\u0645\u062c\u0627\u0646"
    ],
    "name:msa_x_preferred":[
        "Bala Mahalleh-ye Lafmejan"
    ],
    "name:swe_x_preferred":[
        "Lafmej\u0101n"
    ],
    "name:ukr_x_preferred":[
        "\u0411\u0430\u043b\u0430-\u041c\u0430\u0445\u0430\u043b\u0435-\u041b\u0430\u0444\u043c\u0435\u0434\u0436\u0430\u043d"
    ],
    "wof:name":"Bala Mahalleh-ye Lafmejan",
    "wof:placetype":"locality"
},
  "geometry": {"coordinates":[49.88111,37.21611],"type":"Point"}
}