{
  "type": "Feature",
  "properties": {
    "gn:admin1_code":"8.0",
    "gn:asciiname":"Bala Mahalleh-ye Lafmejan",
    "gn:country_code":"IR",
    "gn:dem":-3,
    "gn:feature_class":"P",
    "gn:feature_code":"PPL",
    "gn:name":"B\u0101l\u0101 Ma\u1e29alleh-ye Lafmej\u0101n",
    "gn:population":0,
    "gn:timezone":"Asia/Tehran",
    "iso:country":"IR",
    "name:fas_x_preferred":[
        "B\u0101l\u0101 Ma\u1e29alleh-ye Lafmej\u0101n"
    ],
    "wof:name":"Bala Mahalleh-ye Lafmejan",
    "wof:placetype":"locality"
},
  "geometry": {"coordinates":[49.88111,37.21611],"type":"Point"}
}