{
  "type": "Feature",
  "properties": {
    "gn:admin1_code":"35.0",
    "gn:asciiname":"Shahrak-e Setayesh",
    "gn:country_code":"IR",
    "gn:dem":-17,
    "gn:feature_class":"P",
    "gn:feature_code":"PPL",
    "gn:name":"Shahrak-e Set\u0101yesh",
    "gn:population":0,
    "gn:timezone":"Asia/Tehran",
    "iso:country":"IR",
    "name:fas_x_preferred":[
        "\u0634\u0647\u0631\u06a9 \u0633\u062a\u0627\u06cc\u0634"
    ],
    "name:und_x_variant":[
        "Shahrak-e Set\u0101yesh"
    ],
    "wof:name":"Shahrak-e Setayesh",
    "wof:placetype":"locality"
},
  "geometry": {"coordinates":[51.09437,36.72017],"type":"Point"}
}