{
  "type": "Feature",
  "properties": {
    "gn:admin1_code":"15",
    "gn:asciiname":"Seyyed Majid",
    "gn:cc2":"IR",
    "gn:country_code":"IR",
    "gn:dem":51,
    "gn:feature_class":"P",
    "gn:feature_code":"PPL",
    "gn:name":"Seyyed Maj\u012bd",
    "gn:population":0,
    "gn:timezone":"Asia/Tehran",
    "iso:country":"IR",
    "name:fas_x_preferred":[
        "Seyyed Maj\u012bd"
    ],
    "name:und_x_variant":[
        "Boneh Seyyed Maj\u012bd"
    ],
    "wof:name":"Seyyed Majid",
    "wof:placetype":"locality"
},
  "geometry": {"coordinates":[48.49889,32.11056],"type":"Point"}
}