{
  "type": "Feature",
  "properties": {
    "gn:admin1_code":"7",
    "gn:asciiname":"Abadeh-ye Tashk",
    "gn:country_code":"IR",
    "gn:dem":1598,
    "gn:feature_class":"P",
    "gn:feature_code":"PPL",
    "gn:name":"\u0100b\u0101deh-ye \u0162ashk",
    "gn:population":0,
    "gn:timezone":"Asia/Tehran",
    "iso:country":"IR",
    "name:ara_x_preferred":[
        "\u0622\u0628\u0627\u062f\u0629 \u062a\u0634\u0643"
    ],
    "name:aze_x_preferred":[
        "Abad\u0259 T\u0259\u015fk"
    ],
    "name:ceb_x_preferred":[
        "\u0100b\u0101deh-ye \u0162ashk"
    ],
    "name:fas_x_preferred":[
        "\u0100b\u0101deh-ye \u0162ashk"
    ],
    "name:fas_x_variant":[
        "\u0622\u0628\u0627\u062f\u0647 \u0637\u0634\u06a9",
        "\u0162ashk",
        "\u0100b\u0101d\u012b-ye Tashk",
        "\u0100b\u0101deh-i-Tashk"
    ],
    "name:ita_x_preferred":[
        "Abadeh Toshk"
    ],
    "name:mlg_x_preferred":[
        "Abadeh Tashk"
    ],
    "name:msa_x_preferred":[
        "Abadeh Tashk"
    ],
    "name:mzn_x_preferred":[
        "\u0622\u0628\u0627\u062f\u0647 \u0637\u0634\u06a9"
    ],
    "name:rus_x_preferred":[
        "\u0410\u0431\u0430\u0434\u0435-\u0422\u0430\u0448\u043a"
    ],
    "name:snd_x_preferred":[
        "\u0622\u0628\u0627\u062f\u0647 \u0637\u0634\u06aa"
    ],
    "name:swe_x_preferred":[
        "\u0100b\u0101deh-ye \u0162ashk"
    ],
    "name:tur_x_preferred":[
        "Abadete\u015fk"
    ],
    "name:tur_x_variant":[
        "Abadeta\u015fk"
    ],
    "name:ukr_x_preferred":[
        "\u0410\u0431\u0430\u0434\u0435-\u0422\u0435\u0448\u043a"
    ],
    "name:ukr_x_variant":[
        "\u0410\u0431\u0430\u0434\u0435\u0301-\u0439\u0435-\u0422\u0430\u0448\u043a",
        "\u0410\u0431\u0430\u0434\u0456-\u0422\u043e\u0448\u043a",
        "\u0410\u0431\u0430\u0434\u0435\u0301-\u0456-\u0422\u0430\u0448\u043a",
        "\u0422\u0430\u0448\u043a",
        "\u0410\u0431\u0430\u0434\u0435-\u0422\u0430\u0448\u043a"
    ],
    "name:und_x_variant":[
        "\u0100b\u0101deh Toshk"
    ],
    "name:urd_x_preferred":[
        "\u0622\u0628\u0627\u062f\u06c1 \u0637\u0634\u06a9"
    ],
    "name:zho_x_preferred":[
        "\u963f\u5df4\u4ee3\u8d6b\u5854\u4ec0\u514b"
    ],
    "wof:name":"Abadeh-ye Tashk",
    "wof:placetype":"locality"
},
  "geometry": {"coordinates":[53.7275,29.81083],"type":"Point"}
}