{
  "type": "Feature",
  "properties": {
    "gn:admin1_code":"29",
    "gn:asciiname":"Baravat",
    "gn:country_code":"IR",
    "gn:dem":1003,
    "gn:feature_class":"P",
    "gn:feature_code":"PPL",
    "gn:name":"Barav\u0101t",
    "gn:population":0,
    "gn:timezone":"Asia/Tehran",
    "iso:country":"IR",
    "name:ara_x_preferred":[
        "\u0628\u0631\u0648\u0627\u062a"
    ],
    "name:aze_x_preferred":[
        "B\u0259r\u0259vat"
    ],
    "name:ceb_x_preferred":[
        "Barav\u0101t"
    ],
    "name:fas_x_preferred":[
        "\u0628\u0631\u0648\u0627\u062a"
    ],
    "name:fas_x_variant":[
        "Barav\u0101t"
    ],
    "name:ita_x_preferred":[
        "Baravat"
    ],
    "name:mlg_x_preferred":[
        "Baravat"
    ],
    "name:swe_x_preferred":[
        "Barav\u0101t"
    ],
    "name:tur_x_preferred":[
        "Berevat"
    ],
    "name:und_x_variant":[
        "Bur\u0101b\u0101d",
        "Barvat",
        "Bor\u016bn\u0101b\u0101d"
    ],
    "wof:name":"Baravat",
    "wof:placetype":"locality"
},
  "geometry": {"coordinates":[58.4046,29.0663],"type":"Point"}
}