{
  "type": "Feature",
  "properties": {
    "gn:admin1_code":"11.0",
    "gn:asciiname":"Dahandar-e Mir `Omar",
    "gn:country_code":"IR",
    "gn:dem":1007,
    "gn:feature_class":"P",
    "gn:feature_code":"PPLL",
    "gn:name":"Dahandar-e M\u012br \u2018Omar",
    "gn:population":0,
    "gn:timezone":"Asia/Tehran",
    "iso:country":"IR",
    "name:fas_x_preferred":[
        "\u062f\u0647\u0646\u062f\u0631 \u0645\u06cc\u0631 \u0639\u0645\u0631"
    ],
    "name:und_x_variant":[
        "Dahandar-e M\u012br \u2018Omar"
    ],
    "wof:name":"Dahandar-e Mir `Omar",
    "wof:placetype":"locality"
},
  "geometry": {"coordinates":[58.24571,26.40366],"type":"Point"}
}