{
  "type": "Feature",
  "properties": {
    "gn:admin1_code":"4",
    "gn:asciiname":"Derangu",
    "gn:country_code":"IR",
    "gn:dem":8,
    "gn:feature_class":"P",
    "gn:feature_code":"PPL",
    "gn:name":"Derang\u016b",
    "gn:population":0,
    "gn:timezone":"Asia/Tehran",
    "iso:country":"IR",
    "name:fas_x_preferred":[
        "Derang\u016b"
    ],
    "name:fas_x_variant":[
        "\u062f\u0631\u0646\u06af\u0648",
        "\u062f\u0631\u0627\u0646\u06af\u0648"
    ],
    "name:und_x_variant":[
        "Dr\u0101ngow",
        "Drango",
        "\u062f\u0631\u0646\u06af\u0648"
    ],
    "wof:name":"Derangu",
    "wof:placetype":"locality"
},
  "geometry": {"coordinates":[59.69669,25.41221],"type":"Point"}
}