{
  "type": "Feature",
  "properties": {
    "gn:admin1_code":"15.0",
    "gn:asciiname":"Beyt-e Shukayeh",
    "gn:country_code":"IR",
    "gn:dem":30,
    "gn:feature_class":"P",
    "gn:feature_code":"PPL",
    "gn:name":"Beyt-e Sh\u016bk\u0101yeh",
    "gn:population":0,
    "gn:timezone":"Asia/Tehran",
    "iso:country":"IR",
    "name:fas_x_preferred":[
        "\u0634\u0648\u06a9\u0627\u06cc\u0647"
    ],
    "name:fas_x_variant":[
        "Shok\u0101yeh",
        "\u0628\u06cc\u062a \u0634\u0648\u06a9\u0627\u06cc\u0647"
    ],
    "name:und_x_variant":[
        "Beyt-e Sh\u016bk\u0101yeh"
    ],
    "wof:name":"Beyt-e Shukayeh",
    "wof:placetype":"locality"
},
  "geometry": {"coordinates":[48.55167,31.63368],"type":"Point"}
}