{
  "type": "Feature",
  "properties": {
    "gn:admin1_code":"13",
    "gn:asciiname":"Darli Sar",
    "gn:country_code":"IR",
    "gn:dem":1273,
    "gn:feature_class":"P",
    "gn:feature_code":"PPL",
    "gn:name":"D\u0101rl\u012b Sar",
    "gn:population":0,
    "gn:timezone":"Asia/Tehran",
    "iso:country":"IR",
    "name:ceb_x_preferred":[
        "D\u0101rl\u012b Sar"
    ],
    "name:fas_x_preferred":[
        "\u062f\u0627\u0631\u0644\u06cc \u0633\u0631"
    ],
    "name:fas_x_variant":[
        "V\u0101n\u012b Sar",
        "D\u0101rl\u012b Sar",
        "\u0648\u0627\u0646\u06cc\u200c\u0633\u0631"
    ],
    "name:swe_x_preferred":[
        "D\u0101rl\u012b Sar"
    ],
    "wof:name":"Darli Sar",
    "wof:placetype":"locality"
},
  "geometry": {"coordinates":[46.0963,34.8066],"type":"Point"}
}