{
  "type": "Feature",
  "properties": {
    "gn:admin1_code":"28.0",
    "gn:asciiname":"Mangi-ye Bala",
    "gn:cc2":"IR",
    "gn:country_code":"IR",
    "gn:dem":2168,
    "gn:feature_class":"P",
    "gn:feature_code":"PPL",
    "gn:name":"M\u0101ng\u012b-ye B\u0101l\u0101",
    "gn:population":0,
    "gn:timezone":"Asia/Tehran",
    "iso:country":"IR",
    "name:fas_x_preferred":[
        "M\u0101ng\u012b-ye B\u0101l\u0101"
    ],
    "name:und_x_variant":[
        "M\u0101ndeg\u012b-ye B\u0101l\u0101"
    ],
    "wof:name":"Mangi-ye Bala",
    "wof:placetype":"locality"
},
  "geometry": {"coordinates":[52.91667,32.70111],"type":"Point"}
}