{
  "type": "Feature",
  "properties": {
    "gn:admin1_code":"33.0",
    "gn:asciiname":"Aseh Magheh",
    "gn:cc2":"IR",
    "gn:country_code":"IR",
    "gn:dem":1048,
    "gn:feature_class":"P",
    "gn:feature_code":"PPL",
    "gn:name":"\u0100seh M\u0101gheh",
    "gn:population":0,
    "gn:timezone":"Asia/Tehran",
    "iso:country":"IR",
    "name:fas_x_preferred":[
        "\u0100seh M\u0101gheh"
    ],
    "name:und_x_variant":[
        "\u0100id\u0101gheh"
    ],
    "wof:name":"Aseh Magheh",
    "wof:placetype":"locality"
},
  "geometry": {"coordinates":[45.46972,38.53417],"type":"Point"}
}