{
  "type": "Feature",
  "properties": {
    "gn:admin1_code":"16",
    "gn:asciiname":"Shuyesheh",
    "gn:country_code":"IR",
    "gn:dem":1533,
    "gn:feature_class":"P",
    "gn:feature_code":"PPL",
    "gn:name":"Sh\u016byesheh",
    "gn:population":0,
    "gn:timezone":"Asia/Tehran",
    "iso:country":"IR",
    "name:fas_x_preferred":[
        "\u0634\u0648\u06cc\u0634\u0647"
    ],
    "name:fas_x_variant":[
        "Sh\u016byesheh"
    ],
    "name:und_x_variant":[
        "Shav\u012bsheh",
        "Shev\u012bsheh"
    ],
    "wof:name":"Shuyesheh",
    "wof:placetype":"locality"
},
  "geometry": {"coordinates":[46.6777,35.3567],"type":"Point"}
}