{
  "type": "Feature",
  "properties": {
    "gn:admin1_code":"43",
    "gn:asciiname":"Kalateh-ye Hajji Qajar",
    "gn:country_code":"IR",
    "gn:dem":1279,
    "gn:feature_class":"P",
    "gn:feature_code":"PPLF",
    "gn:name":"Kal\u0101teh-ye \u1e28\u0101jj\u012b Qajar",
    "gn:population":0,
    "gn:timezone":"Asia/Tehran",
    "iso:country":"IR",
    "name:fas_x_preferred":[
        "\u06a9\u0644\u0627\u062a\u0647 \u062d\u0627\u062c \u0642\u062c\u0631"
    ],
    "name:fas_x_variant":[
        "\u06a9\u0644\u0627\u062a\u0647 \u062d\u0627\u062c\u06cc \u0642\u062c\u0631"
    ],
    "name:und_x_variant":[
        "Kal\u0101teh-ye \u1e28\u0101jj Qajar",
        "Kal\u0101teh-ye \u1e28\u0101jj\u012b Qajar"
    ],
    "wof:name":"Kalateh-ye Hajji Qajar",
    "wof:placetype":"locality"
},
  "geometry": {"coordinates":[57.0626,38.05885],"type":"Point"}
}