{
  "type": "Feature",
  "properties": {
    "gn:admin1_code":"7",
    "gn:asciiname":"Zavali",
    "gn:country_code":"IR",
    "gn:dem":840,
    "gn:feature_class":"P",
    "gn:feature_code":"PPL",
    "gn:name":"Zav\u0101l\u012b",
    "gn:population":0,
    "gn:timezone":"Asia/Tehran",
    "iso:country":"IR",
    "name:fas_x_preferred":[
        "Zav\u0101l\u012b"
    ],
    "name:fas_x_variant":[
        "\u0632\u0648\u0627\u0644\u06cc"
    ],
    "name:msa_x_preferred":[
        "Zavali"
    ],
    "wof:name":"Zavali",
    "wof:placetype":"locality"
},
  "geometry": {"coordinates":[51.77884,29.55284],"type":"Point"}
}