{
  "type": "Feature",
  "properties": {
    "gn:admin1_code":"16",
    "gn:asciiname":"Gavileh",
    "gn:country_code":"IR",
    "gn:dem":1559,
    "gn:feature_class":"P",
    "gn:feature_code":"PPL",
    "gn:name":"Gav\u012bleh",
    "gn:population":0,
    "gn:timezone":"Asia/Tehran",
    "iso:country":"IR",
    "name:fas_x_preferred":[
        "\u06af\u064e\u0648\u064a\u0644\u0650\u0647"
    ],
    "name:fas_x_variant":[
        "\u06af\u064f\u0648\u064a\u0644\u0650\u0647",
        "\u06af\u0648\u06cc\u0644\u0647",
        "Gav\u012bleh"
    ],
    "name:und_x_variant":[
        "Gov\u012bleh"
    ],
    "wof:name":"Gavileh",
    "wof:placetype":"locality"
},
  "geometry": {"coordinates":[46.3286,35.6849],"type":"Point"}
}