{
  "type": "Feature",
  "properties": {
    "gn:admin1_code":"1",
    "gn:asciiname":"Owkhchilar",
    "gn:country_code":"IR",
    "gn:dem":1285,
    "gn:feature_class":"P",
    "gn:feature_code":"PPL",
    "gn:name":"Owkhch\u012bl\u0101r",
    "gn:population":0,
    "gn:timezone":"Asia/Tehran",
    "iso:country":"IR",
    "name:azb_x_preferred":[
        "\u0627\u0648\u062e\u0686\u0648\u0644\u0627\u0631"
    ],
    "name:aze_x_preferred":[
        "Ox\u00e7ular"
    ],
    "name:fas_x_preferred":[
        "\u0648\u062e\u0686\u0650\u0644\u064e\u0631"
    ],
    "name:fas_x_variant":[
        "\u0627\u0648\u062e\u0686\u06cc\u0644\u0627\u0631",
        "\u016akhchelar",
        "Owkhch\u012bl\u0101r"
    ],
    "name:msa_x_preferred":[
        "Owkhchilar"
    ],
    "wof:name":"Owkhchilar",
    "wof:placetype":"locality"
},
  "geometry": {"coordinates":[45.1231,37.7511],"type":"Point"}
}