{
  "type": "Feature",
  "properties": {
    "gn:admin1_code":"29",
    "gn:asciiname":"Kejik",
    "gn:country_code":"IR",
    "gn:dem":2398,
    "gn:feature_class":"P",
    "gn:feature_code":"PPL",
    "gn:name":"Kej\u012bk",
    "gn:population":0,
    "gn:timezone":"Asia/Tehran",
    "iso:country":"IR",
    "name:fas_x_preferred":[
        "\u06a9\u062c\u06cc\u06a9"
    ],
    "name:fas_x_variant":[
        "Kej\u012bk"
    ],
    "wof:name":"Kejik",
    "wof:placetype":"locality"
},
  "geometry": {"coordinates":[57.6157,29.0282],"type":"Point"}
}