{
  "type": "Feature",
  "properties": {
    "gn:admin1_code":"8",
    "gn:asciiname":"Chakur",
    "gn:country_code":"IR",
    "gn:dem":-23,
    "gn:feature_class":"P",
    "gn:feature_code":"PPL",
    "gn:name":"Chak\u016br",
    "gn:population":0,
    "gn:timezone":"Asia/Tehran",
    "iso:country":"IR",
    "name:ceb_x_preferred":[
        "Chekover"
    ],
    "name:fas_x_preferred":[
        "\u0686\u06a9\u0648\u0631"
    ],
    "name:fas_x_variant":[
        "Chek\u016bver",
        "\u0686\u06a9\u0648\u0648\u0631"
    ],
    "name:msa_x_preferred":[
        "Chakuvar"
    ],
    "name:swe_x_preferred":[
        "Chekover"
    ],
    "name:ukr_x_preferred":[
        "\u0427\u0430\u043a\u0443\u0432\u0430\u0440"
    ],
    "name:und_x_variant":[
        "Chak\u016bvar",
        "Chekuper",
        "Chekover",
        "Chak\u016br"
    ],
    "wof:name":"Chakur",
    "wof:placetype":"locality"
},
  "geometry": {"coordinates":[49.29474,37.41028],"type":"Point"}
}