{
  "type": "Feature",
  "properties": {
    "gn:admin1_code":"7",
    "gn:asciiname":"Tall Quchi",
    "gn:country_code":"IR",
    "gn:dem":972,
    "gn:feature_class":"P",
    "gn:feature_code":"PPL",
    "gn:name":"Tall Q\u016bch\u012b",
    "gn:population":0,
    "gn:timezone":"Asia/Tehran",
    "iso:country":"IR",
    "name:fas_x_preferred":[
        "Tall Q\u016bch\u012b"
    ],
    "wof:name":"Tall Quchi",
    "wof:placetype":"locality"
},
  "geometry": {"coordinates":[51.32,29.91167],"type":"Point"}
}