{
  "type": "Feature",
  "properties": {
    "gn:admin1_code":"15",
    "gn:asciiname":"Qasemiabad",
    "gn:country_code":"IR",
    "gn:dem":749,
    "gn:feature_class":"P",
    "gn:feature_code":"PPL",
    "gn:name":"Q\u0101sem\u012b\u0101b\u0101d",
    "gn:population":0,
    "gn:timezone":"Asia/Tehran",
    "iso:country":"IR",
    "name:fas_x_preferred":[
        "Q\u0101sem\u0101b\u0101d-e D\u012bneh R\u0101k"
    ],
    "name:fas_x_variant":[
        "Q\u0101sem\u012b\u0101b\u0101d",
        "\u0642\u0627\u0633\u0645\u06cc \u0622\u0628\u0627\u062f",
        "\u0639\u0644\u06cc \u0646\u0638\u0631"
    ],
    "name:und_x_variant":[
        "Q\u0101sem\u0101b\u0101d",
        "\u0642\u0627\u0633\u0645\u06cc \u0622\u0628\u0627\u062f",
        "\u2018Al\u012b Naz\u0327ar"
    ],
    "wof:name":"Qasemiabad",
    "wof:placetype":"locality"
},
  "geometry": {"coordinates":[49.51781,32.19903],"type":"Point"}
}