{
  "type": "Feature",
  "properties": {
    "gn:admin1_code":"23",
    "gn:asciiname":"Saranbar-e Tashkan",
    "gn:country_code":"IR",
    "gn:dem":1173,
    "gn:feature_class":"P",
    "gn:feature_code":"PPL",
    "gn:name":"Saranb\u0101r-e Tashkan",
    "gn:population":0,
    "gn:timezone":"Asia/Tehran",
    "iso:country":"IR",
    "name:fas_x_preferred":[
        "\u0633\u064e\u0631\u064e\u0646\u0628\u0627\u0631\u0650 \u062a\u064e\u0634\u0643\u064e\u0646"
    ],
    "name:fas_x_variant":[
        "Saranb\u0101r-e Tashkan"
    ],
    "wof:name":"Saranbar-e Tashkan",
    "wof:placetype":"locality"
},
  "geometry": {"coordinates":[47.85,33.66667],"type":"Point"}
}