{
  "type": "Feature",
  "properties": {
    "gn:admin1_code":"28",
    "gn:asciiname":"Meydanak-e Dovvom",
    "gn:country_code":"IR",
    "gn:dem":2566,
    "gn:feature_class":"P",
    "gn:feature_code":"PPL",
    "gn:name":"Meyd\u0101nak-e Dovvom",
    "gn:population":0,
    "gn:timezone":"Asia/Tehran",
    "iso:country":"IR",
    "name:fas_x_preferred":[
        "Meyd\u0101nak-e Dovvom"
    ],
    "wof:name":"Meydanak-e Dovvom",
    "wof:placetype":"locality"
},
  "geometry": {"coordinates":[50.23278,32.73444],"type":"Point"}
}