{
  "type": "Feature",
  "properties": {
    "gn:admin1_code":"29",
    "gn:asciiname":"Allahabad-e Seyyed",
    "gn:country_code":"IR",
    "gn:dem":610,
    "gn:feature_class":"P",
    "gn:feature_code":"PPL",
    "gn:name":"All\u0101h\u0101b\u0101d-e Seyyed",
    "gn:population":0,
    "gn:timezone":"Asia/Tehran",
    "iso:country":"IR",
    "name:fas_x_preferred":[
        "\u0627\u0644\u0644\u0651\u0647 \u0622\u0628\u0627\u062f \u0633\u06cc\u062f"
    ],
    "name:fas_x_variant":[
        "All\u0101h\u0101b\u0101d-e Seyyed"
    ],
    "wof:name":"Allahabad-e Seyyed",
    "wof:placetype":"locality"
},
  "geometry": {"coordinates":[57.7348,28.5188],"type":"Point"}
}