{
  "type": "Feature",
  "properties": {
    "gn:admin1_code":"34",
    "gn:asciiname":"Gheshlagh Salehi",
    "gn:country_code":"IR",
    "gn:dem":1956,
    "gn:feature_class":"P",
    "gn:feature_code":"PPL",
    "gn:name":"Gheshlagh Salehi",
    "gn:population":0,
    "gn:timezone":"Asia/Tehran",
    "iso:country":"IR",
    "name:fas_x_preferred":[
        "\u0635\u0627\u0644\u062d\u06cc"
    ],
    "name:fas_x_variant":[
        "\u015e\u0101le\u1e29\u012b"
    ],
    "name:und_x_variant":[
        "Qeshl\u0101q-e \u015e\u0101le\u1e29\u012b"
    ],
    "wof:name":"Gheshlagh Salehi",
    "wof:placetype":"locality"
},
  "geometry": {"coordinates":[49.19107,34.22384],"type":"Point"}
}