{
  "type": "Feature",
  "properties": {
    "gn:admin1_code":"32",
    "gn:asciiname":"Qeshlaq-e Chenar",
    "gn:country_code":"IR",
    "gn:dem":728,
    "gn:feature_class":"P",
    "gn:feature_code":"PPL",
    "gn:name":"Qeshl\u0101q-e Chen\u0101r",
    "gn:population":0,
    "gn:timezone":"Asia/Tehran",
    "iso:country":"IR",
    "name:fas_x_preferred":[
        "\u0642\u0634\u0644\u0627\u0642 \u0686\u0646\u0627\u0631"
    ],
    "name:fas_x_variant":[
        "Qeshl\u0101q-e Chen\u0101r"
    ],
    "wof:name":"Qeshlaq-e Chenar",
    "wof:placetype":"locality"
},
  "geometry": {"coordinates":[47.675,39.198],"type":"Point"}
}