{
  "type": "Feature",
  "properties": {
    "gn:admin1_code":"40",
    "gn:asciiname":"Marvast",
    "gn:cc2":"IR",
    "gn:country_code":"IR",
    "gn:dem":1540,
    "gn:feature_class":"P",
    "gn:feature_code":"PPL",
    "gn:name":"Marvast",
    "gn:population":0,
    "gn:timezone":"Asia/Tehran",
    "iso:country":"IR",
    "name:fas_x_preferred":[
        "\u0645\u0631\u0648\u0633\u062a"
    ],
    "name:und_x_variant":[
        "Marvas",
        "Marvast",
        "Dabest\u0101n-e Khv\u0101jeh Marvast"
    ],
    "wof:name":"Marvast",
    "wof:placetype":"locality"
},
  "geometry": {"coordinates":[54.21167,30.47833],"type":"Point"}
}