{
  "type": "Feature",
  "properties": {
    "gn:admin1_code":"42.0",
    "gn:asciiname":"Kuh Darreh",
    "gn:country_code":"IR",
    "gn:dem":1577,
    "gn:feature_class":"P",
    "gn:feature_code":"PPL",
    "gn:name":"K\u016bh Darreh",
    "gn:population":0,
    "gn:timezone":"Asia/Tehran",
    "iso:country":"IR",
    "name:ceb_x_preferred":[
        "K\u016bh Darreh"
    ],
    "name:fas_x_preferred":[
        "K\u016bh Darreh"
    ],
    "name:fas_x_variant":[
        "\u06a9\u0648\u0647 \u062f\u0631\u0651\u0647",
        "\u06a9\u0648\u0647\u200c\u062f\u0631\u0647"
    ],
    "name:swe_x_preferred":[
        "K\u016bh Darreh"
    ],
    "wof:name":"Kuh Darreh",
    "wof:placetype":"locality"
},
  "geometry": {"coordinates":[58.19212,36.76572],"type":"Point"}
}