{
  "type": "Feature",
  "properties": {
    "gn:admin1_code":"16",
    "gn:asciiname":"Sharif Kandi",
    "gn:country_code":"IR",
    "gn:dem":1997,
    "gn:feature_class":"P",
    "gn:feature_code":"PPL",
    "gn:name":"Shar\u012bf Kand\u012b",
    "gn:population":0,
    "gn:timezone":"Asia/Tehran",
    "iso:country":"IR",
    "name:fas_x_preferred":[
        "\u0634\u0631\u06cc\u0641 \u06a9\u0646\u062f\u06cc"
    ],
    "name:fas_x_variant":[
        "Shar\u012bf Kand\u012b"
    ],
    "wof:name":"Sharif Kandi",
    "wof:placetype":"locality"
},
  "geometry": {"coordinates":[47.42699,36.30461],"type":"Point"}
}