{
  "type": "Feature",
  "properties": {
    "gn:admin1_code":"7",
    "gn:asciiname":"Mashil-e Bondar",
    "gn:country_code":"IR",
    "gn:dem":1340,
    "gn:feature_class":"P",
    "gn:feature_code":"PPL",
    "gn:name":"Mash\u012bl-e Bondar",
    "gn:population":0,
    "gn:timezone":"Asia/Tehran",
    "iso:country":"IR",
    "name:fas_x_preferred":[
        "Mash\u012bl-e Bondar"
    ],
    "name:fas_x_variant":[
        "Mash\u012bl-e Bond\u0101r",
        "\u0645\u0634\u06cc\u0644 \u0628\u0646\u062f\u0631"
    ],
    "name:und_x_variant":[
        "\u0645\u0634\u06cc\u0644 \u0628\u0646\u062f\u0631"
    ],
    "wof:name":"Mashil-e Bondar",
    "wof:placetype":"locality"
},
  "geometry": {"coordinates":[51.347,30.002],"type":"Point"}
}