{
  "type": "Feature",
  "properties": {
    "gn:admin1_code":"15",
    "gn:asciiname":"Begesi",
    "gn:country_code":"IR",
    "gn:dem":595,
    "gn:feature_class":"P",
    "gn:feature_code":"PPL",
    "gn:name":"Beges\u012b",
    "gn:population":0,
    "gn:timezone":"Asia/Tehran",
    "iso:country":"IR",
    "name:ara_x_preferred":[
        "\u0628\u064a\u063a\u064a\u0633\u064a"
    ],
    "name:fas_x_preferred":[
        "\u0628\u06af\u0633\u06cc"
    ],
    "name:fas_x_variant":[
        "Beges\u012b"
    ],
    "wof:name":"Begesi",
    "wof:placetype":"locality"
},
  "geometry": {"coordinates":[49.39485,32.11889],"type":"Point"}
}