{
  "type": "Feature",
  "properties": {
    "gn:admin1_code":"7.0",
    "gn:asciiname":"Ab Zangi",
    "gn:country_code":"IR",
    "gn:dem":1655,
    "gn:feature_class":"P",
    "gn:feature_code":"PPL",
    "gn:name":"\u0100b Zang\u012b",
    "gn:population":0,
    "gn:timezone":"Asia/Tehran",
    "iso:country":"IR",
    "name:fas_x_preferred":[
        "\u0622\u0628 \u0632\u0646\u06af\u06cc"
    ],
    "name:fas_x_variant":[
        "\u0100b Zang\u012b",
        "\u0622\u0628\u200c\u0632\u0646\u06af\u06cc"
    ],
    "name:msa_x_preferred":[
        "Ab Zangi"
    ],
    "wof:name":"Ab Zangi",
    "wof:placetype":"locality"
},
  "geometry": {"coordinates":[52.5735,29.6459],"type":"Point"}
}