{
  "type": "Feature",
  "properties": {
    "gn:admin1_code":"37.0",
    "gn:asciiname":"`Arab Laleh Gun",
    "gn:country_code":"IR",
    "gn:dem":837,
    "gn:feature_class":"P",
    "gn:feature_code":"PPL",
    "gn:name":"\u2018Arab L\u0101leh G\u016bn",
    "gn:population":0,
    "gn:timezone":"Asia/Tehran",
    "iso:country":"IR",
    "name:fas_x_preferred":[
        "\u0639\u0631\u0628 \u0644\u0627\u0644\u0647 \u06af\u0648\u0646"
    ],
    "name:fas_x_variant":[
        "\u2018Arab L\u0101leh G\u016bn",
        "\u0639\u0631\u0628 \u0644\u0627\u0644\u0647\u200c\u06af\u0648\u0646"
    ],
    "name:msa_x_preferred":[
        "Arab Laleh Gun"
    ],
    "wof:name":"`Arab Laleh Gun",
    "wof:placetype":"locality"
},
  "geometry": {"coordinates":[55.90069,37.65736],"type":"Point"}
}