{
  "type": "Feature",
  "properties": {
    "gn:admin1_code":"28",
    "gn:asciiname":"Tarqan",
    "gn:country_code":"IR",
    "gn:dem":2241,
    "gn:feature_class":"P",
    "gn:feature_code":"PPL",
    "gn:name":"Tarq\u0101n",
    "gn:population":0,
    "gn:timezone":"Asia/Tehran",
    "iso:country":"IR",
    "name:fas_x_preferred":[
        "\u062a\u064e\u0631\u0642\u0627\u0646"
    ],
    "name:fas_x_variant":[
        "\u062a\u064e\u0631\u063a\u064e\u0646",
        "Tarq\u0101n"
    ],
    "name:und_x_variant":[
        "Targhan",
        "Takun"
    ],
    "wof:name":"Tarqan",
    "wof:placetype":"locality"
},
  "geometry": {"coordinates":[51.71806,31.81861],"type":"Point"}
}