{
  "type": "Feature",
  "properties": {
    "gn:admin1_code":"8.0",
    "gn:asciiname":"Simbareh Chal",
    "gn:country_code":"IR",
    "gn:dem":2112,
    "gn:feature_class":"P",
    "gn:feature_code":"PPL",
    "gn:name":"S\u012bmbareh Ch\u0101l",
    "gn:population":0,
    "gn:timezone":"Asia/Tehran",
    "iso:country":"IR",
    "name:fas_x_preferred":[
        "\u0633\u06cc\u0645\u0628\u0631\u0647 \u0686\u0627\u0644"
    ],
    "name:und_x_variant":[
        "S\u012bmbareh Ch\u0101l"
    ],
    "wof:name":"Simbareh Chal",
    "wof:placetype":"locality"
},
  "geometry": {"coordinates":[48.75273,37.46547],"type":"Point"}
}