{
  "type": "Feature",
  "properties": {
    "gn:admin1_code":"15.0",
    "gn:asciiname":"Saleh Zobari",
    "gn:country_code":"IR",
    "gn:dem":34,
    "gn:feature_class":"P",
    "gn:feature_code":"PPL",
    "gn:name":"\u015e\u0101le\u1e29 Zob\u0101r\u012b",
    "gn:population":0,
    "gn:timezone":"Asia/Tehran",
    "iso:country":"IR",
    "name:ara_x_preferred":[
        "\u0635\u0627\u0644\u062d \u0632\u0628\u064a\u0631\u064a"
    ],
    "name:azb_x_preferred":[
        "\u0635\u0627\u0644\u062d \u0632\u0628\u0627\u0631\u06cc(\u0627\u0647\u0648\u0627\u0632)"
    ],
    "name:fas_x_preferred":[
        "\u0635\u0627\u0644\u062d \u0632\u0628\u06cc\u0631\u06cc"
    ],
    "name:fas_x_variant":[
        "\u015e\u0101le\u1e29 Zobeyr\u012b",
        "\u0635\u0627\u0644\u062d \u0632\u0628\u0627\u0631\u06cc"
    ],
    "name:und_x_variant":[
        "\u015e\u0101le\u1e29 Zob\u0101r\u012b"
    ],
    "wof:name":"Saleh Zobari",
    "wof:placetype":"locality"
},
  "geometry": {"coordinates":[48.52128,31.72918],"type":"Point"}
}