{
  "type": "Feature",
  "properties": {
    "gn:admin1_code":"29.0",
    "gn:asciiname":"Dasht-e Kazeh Zirboreh",
    "gn:country_code":"IR",
    "gn:dem":1602,
    "gn:feature_class":"P",
    "gn:feature_code":"PPL",
    "gn:name":"Dasht-e K\u0101zeh Z\u012brboreh",
    "gn:population":0,
    "gn:timezone":"Asia/Tehran",
    "iso:country":"IR",
    "name:fas_x_preferred":[
        "\u062f\u0634\u062a \u06a9\u0627\u0632\u0647 \u0632\u064a\u0631\u0628\u0631\u0647"
    ],
    "name:und_x_variant":[
        "Dasht-e K\u0101zeh Z\u012brboreh"
    ],
    "wof:name":"Dasht-e Kazeh Zirboreh",
    "wof:placetype":"locality"
},
  "geometry": {"coordinates":[55.76915,30.34681],"type":"Point"}
}