{
  "type": "Feature",
  "properties": {
    "gn:admin1_code":"15",
    "gn:asciiname":"Posht Par",
    "gn:country_code":"IR",
    "gn:dem":888,
    "gn:feature_class":"P",
    "gn:feature_code":"PPL",
    "gn:name":"Posht Par",
    "gn:population":0,
    "gn:timezone":"Asia/Tehran",
    "iso:country":"IR",
    "name:fas_x_preferred":[
        "\u067e\u0634\u062a \u067e\u0631"
    ],
    "wof:name":"Posht Par",
    "wof:placetype":"locality"
},
  "geometry": {"coordinates":[50.04244,31.38993],"type":"Point"}
}