{
  "type": "Feature",
  "properties": {
    "gn:admin1_code":"44",
    "gn:asciiname":"Bi Sim-e Halq Darreh",
    "gn:country_code":"IR",
    "gn:dem":1236,
    "gn:feature_class":"P",
    "gn:feature_code":"PPL",
    "gn:name":"B\u012b S\u012bm-e \u1e28alq Darreh",
    "gn:population":0,
    "gn:timezone":"Asia/Tehran",
    "iso:country":"IR",
    "name:fas_x_preferred":[
        "\u0628\u06cc \u0633\u064a\u0645\u0650 \u062d\u064e\u0644\u0642 \u062f\u064e\u0631\u0650\u0651\u0647"
    ],
    "name:fas_x_variant":[
        "B\u012b S\u012bm-e \u1e28alq Darreh"
    ],
    "wof:name":"Bi Sim-e Halq Darreh",
    "wof:placetype":"locality"
},
  "geometry": {"coordinates":[50.86972,35.77917],"type":"Point"}
}