{
  "type": "Feature",
  "properties": {
    "gn:admin1_code":"11",
    "gn:asciiname":"Jowzan",
    "gn:country_code":"IR",
    "gn:dem":16,
    "gn:feature_class":"P",
    "gn:feature_code":"PPL",
    "gn:name":"Jowz\u0101n",
    "gn:population":0,
    "gn:timezone":"Asia/Tehran",
    "iso:country":"IR",
    "name:fas_x_preferred":[
        "\u062c\u0648\u0632\u0627\u0646"
    ],
    "name:fas_x_variant":[
        "Jowz\u0101n"
    ],
    "name:msa_x_preferred":[
        "Jowzan"
    ],
    "wof:name":"Jowzan",
    "wof:placetype":"locality"
},
  "geometry": {"coordinates":[56.9514,27.2028],"type":"Point"}
}