{
  "type": "Feature",
  "properties": {
    "gn:admin1_code":"11.0",
    "gn:asciiname":"Mirabad",
    "gn:country_code":"IR",
    "gn:dem":27,
    "gn:feature_class":"P",
    "gn:feature_code":"PPL",
    "gn:name":"M\u012br\u0101b\u0101d",
    "gn:population":0,
    "gn:timezone":"Asia/Tehran",
    "iso:country":"IR",
    "name:fas_x_preferred":[
        "\u0645\u0644\u0627 \u062c\u0645\u0627\u062a\u06cc"
    ],
    "name:fas_x_variant":[
        "Moll\u0101 Jam\u0101t\u012b",
        "\u0645\u06cc\u0631 \u0622\u0628\u0627\u062f"
    ],
    "name:und_x_variant":[
        "M\u012br\u0101b\u0101d"
    ],
    "wof:name":"Mirabad",
    "wof:placetype":"locality"
},
  "geometry": {"coordinates":[57.0291,27.1379],"type":"Point"}
}