{
  "type": "Feature",
  "properties": {
    "gn:admin1_code":"11.0",
    "gn:asciiname":"Shahbaz-e Qadim",
    "gn:country_code":"IR",
    "gn:dem":32,
    "gn:feature_class":"P",
    "gn:feature_code":"PPL",
    "gn:name":"Shahb\u0101z-e Qad\u012bm",
    "gn:population":0,
    "gn:timezone":"Asia/Tehran",
    "iso:country":"IR",
    "name:fas_x_preferred":[
        "\u0634\u064e\u0647\u0648\u0627\u0631"
    ],
    "name:fas_x_variant":[
        "Shahv\u0101r",
        "\u0634\u0647\u0628\u0627\u0632 \u0642\u062f\u06cc\u0645",
        "\u0634\u0647\u0648\u0627\u0631 \u067e\u0627\u0644\u0648\u0631"
    ],
    "name:und_x_variant":[
        "Shahb\u0101z-e Qad\u012bm",
        "Shahv\u0101r Pal\u016br"
    ],
    "wof:name":"Shahbaz-e Qadim",
    "wof:placetype":"locality"
},
  "geometry": {"coordinates":[57.05075,27.19449],"type":"Point"}
}