{
  "type": "Feature",
  "properties": {
    "gn:admin1_code":"34",
    "gn:asciiname":"Kamarak",
    "gn:country_code":"IR",
    "gn:dem":1835,
    "gn:feature_class":"P",
    "gn:feature_code":"PPL",
    "gn:name":"Kamarak",
    "gn:population":0,
    "gn:timezone":"Asia/Tehran",
    "iso:country":"IR",
    "name:ceb_x_preferred":[
        "Kamarak"
    ],
    "name:fas_x_preferred":[
        "\u0643\u0645\u0631\u0643"
    ],
    "name:swe_x_preferred":[
        "Kamarak"
    ],
    "name:und_x_variant":[
        "Kamareh",
        "Kamrak",
        "\u0643\u0645\u0631\u0643",
        "Kamarak"
    ],
    "wof:name":"Kamarak",
    "wof:placetype":"locality"
},
  "geometry": {"coordinates":[49.58675,34.58692],"type":"Point"}
}