{
  "type": "Feature",
  "properties": {
    "gn:admin1_code":"29",
    "gn:asciiname":"Dehnow-ye `Abbasabad",
    "gn:country_code":"IR",
    "gn:dem":708,
    "gn:feature_class":"P",
    "gn:feature_code":"PPL",
    "gn:name":"Dehnow-ye \u2018Abb\u0101s\u0101b\u0101d",
    "gn:population":0,
    "gn:timezone":"Asia/Tehran",
    "iso:country":"IR",
    "name:fas_x_preferred":[
        "\u062f\u0647\u0646\u0648 \u0639\u0628\u0627\u0633 \u0622\u0628\u0627\u062f"
    ],
    "name:fas_x_variant":[
        "\u2018Abb\u0101s\u0101b\u0101d",
        "Dehnow-ye \u2018Abb\u0101s\u0101b\u0101d",
        "\u0639\u0628\u0627\u0633 \u0622\u0628\u0627\u062f"
    ],
    "wof:name":"Dehnow-ye `Abbasabad",
    "wof:placetype":"locality"
},
  "geometry": {"coordinates":[58.79919,28.99466],"type":"Point"}
}