{
  "type": "Feature",
  "properties": {
    "gn:admin1_code":"10",
    "gn:asciiname":"Mian Tang-e Mansuri",
    "gn:country_code":"IR",
    "gn:dem":1179,
    "gn:feature_class":"P",
    "gn:feature_code":"PPL",
    "gn:name":"M\u012b\u0101n Tang-e Man\u015f\u016br\u012b",
    "gn:population":0,
    "gn:timezone":"Asia/Tehran",
    "iso:country":"IR",
    "name:fas_x_preferred":[
        "\u0645\u06cc\u0627\u0646 \u062a\u0646\u06af \u0645\u0646\u0635\u0648\u0631\u06cc"
    ],
    "name:fas_x_variant":[
        "M\u012b\u0101n Tang-e Man\u015f\u016br\u012b"
    ],
    "wof:name":"Mian Tang-e Mansuri",
    "wof:placetype":"locality"
},
  "geometry": {"coordinates":[46.6593,33.8247],"type":"Point"}
}