{
  "type": "Feature",
  "properties": {
    "gn:admin1_code":"34",
    "gn:asciiname":"Chehelraz",
    "gn:country_code":"IR",
    "gn:dem":1732,
    "gn:feature_class":"P",
    "gn:feature_code":"PPL",
    "gn:name":"Chehelraz",
    "gn:population":0,
    "gn:timezone":"Asia/Tehran",
    "iso:country":"IR",
    "name:und_x_variant":[
        "Chehraz",
        "Chehelraz"
    ],
    "wof:name":"Chehelraz",
    "wof:placetype":"locality"
},
  "geometry": {"coordinates":[50.51194,33.69583],"type":"Point"}
}