{
  "type": "Feature",
  "properties": {
    "gn:admin1_code":"29",
    "gn:asciiname":"Farhangabad",
    "gn:country_code":"IR",
    "gn:dem":1375,
    "gn:feature_class":"P",
    "gn:feature_code":"PPLF",
    "gn:name":"Farhang\u0101b\u0101d",
    "gn:population":0,
    "gn:timezone":"Asia/Tehran",
    "iso:country":"IR",
    "name:fas_x_preferred":[
        "Farhang\u0101b\u0101d"
    ],
    "name:fas_x_variant":[
        "\u0641\u0631\u0647\u0646\u06af \u0622\u0628\u0627\u062f"
    ],
    "wof:name":"Farhangabad",
    "wof:placetype":"locality"
},
  "geometry": {"coordinates":[55.26447,30.95029000000001],"type":"Point"}
}