{
  "type": "Feature",
  "properties": {
    "gn:admin1_code":"34",
    "gn:asciiname":"Qeshlaq-e Qarah Baba",
    "gn:country_code":"IR",
    "gn:dem":1622,
    "gn:feature_class":"P",
    "gn:feature_code":"PPL",
    "gn:name":"Qeshl\u0101q-e Qarah B\u0101b\u0101",
    "gn:population":0,
    "gn:timezone":"Asia/Tehran",
    "iso:country":"IR",
    "name:fas_x_preferred":[
        "\u0642\u0650\u0634\u0644\u0627\u0642\u0650 \u0642\u064e\u0631\u064e\u0647 \u0628\u0627\u0628\u0627"
    ],
    "name:fas_x_variant":[
        "Qeshl\u0101q-e Qarah B\u0101b\u0101"
    ],
    "wof:name":"Qeshlaq-e Qarah Baba",
    "wof:placetype":"locality"
},
  "geometry": {"coordinates":[49.46667,35.05],"type":"Point"}
}