{
  "type": "Feature",
  "properties": {
    "gn:admin1_code":"28",
    "gn:asciiname":"Tutekan",
    "gn:country_code":"IR",
    "gn:dem":1831,
    "gn:feature_class":"P",
    "gn:feature_code":"PPL",
    "gn:name":"T\u016btek\u0101n",
    "gn:population":0,
    "gn:timezone":"Asia/Tehran",
    "iso:country":"IR",
    "name:fas_x_preferred":[
        "\u062a\u0648\u062a\u06a9\u0627\u0646"
    ],
    "name:fas_x_variant":[
        "T\u016bt Tag\u0101n",
        "T\u016btek\u0101n"
    ],
    "name:und_x_variant":[
        "T\u016btg\u0101n"
    ],
    "wof:name":"Tutekan",
    "wof:placetype":"locality"
},
  "geometry": {"coordinates":[52.3034,33.2013],"type":"Point"}
}