{
  "type": "Feature",
  "properties": {
    "gn:admin1_code":"7",
    "gn:asciiname":"Qanat",
    "gn:country_code":"IR",
    "gn:dem":2087,
    "gn:feature_class":"P",
    "gn:feature_code":"PPL",
    "gn:name":"Qan\u0101t",
    "gn:population":0,
    "gn:timezone":"Asia/Tehran",
    "iso:country":"IR",
    "wof:name":"Qanat",
    "wof:placetype":"locality"
},
  "geometry": {"coordinates":[51.93333,30.11667000000001],"type":"Point"}
}