{
  "type": "Feature",
  "properties": {
    "gn:admin1_code":"8.0",
    "gn:asciiname":"Sarash",
    "gn:country_code":"IR",
    "gn:dem":436,
    "gn:feature_class":"P",
    "gn:feature_code":"PPL",
    "gn:name":"Sar\u0101sh",
    "gn:population":0,
    "gn:timezone":"Asia/Tehran",
    "iso:country":"IR",
    "name:fas_x_preferred":[
        "Sar\u0101sh"
    ],
    "name:fas_x_variant":[
        "\u0633\u0631\u0627\u0634"
    ],
    "wof:name":"Sarash",
    "wof:placetype":"locality"
},
  "geometry": {"coordinates":[50.03713,37.10409],"type":"Point"}
}