{
  "type": "Feature",
  "properties": {
    "gn:admin1_code":"3",
    "gn:asciiname":"Qal`eh-ye Bandestaki",
    "gn:country_code":"IR",
    "gn:dem":2317,
    "gn:feature_class":"P",
    "gn:feature_code":"PPL",
    "gn:name":"Qal\u2018eh-ye Bandestak\u012b",
    "gn:population":0,
    "gn:timezone":"Asia/Tehran",
    "iso:country":"IR",
    "name:fas_x_preferred":[
        "Bahr\u0101m\u0101b\u0101d-e Benow Estak\u012b"
    ],
    "name:fas_x_variant":[
        "\u0628\u064e\u0647\u0631\u0627\u0645\u0627\u0628\u0627\u062f\u0650 \u0628\u0650\u0646\u064f\u0648 \u0627\u0650\u0633\u062a\u064e\u06a9\u06cc",
        "Qal\u2018eh-ye Bandestak\u012b",
        "\u0642\u0644\u0639\u0647 \u0628\u0646\u062f\u0627\u0633\u062a\u06a9\u06cc"
    ],
    "name:und_x_variant":[
        "\u0642\u0644\u0639\u0647 \u0628\u0646\u062f\u0627\u0633\u062a\u06a9\u06cc"
    ],
    "wof:name":"Qal`eh-ye Bandestaki",
    "wof:placetype":"locality"
},
  "geometry": {"coordinates":[50.20567,32.57276],"type":"Point"}
}