{
  "type": "Feature",
  "properties": {
    "gn:admin1_code":"5.0",
    "gn:asciiname":"Tahlehzar",
    "gn:country_code":"IR",
    "gn:dem":2021,
    "gn:feature_class":"P",
    "gn:feature_code":"PPL",
    "gn:name":"Tahlehz\u0101r",
    "gn:population":0,
    "gn:timezone":"Asia/Tehran",
    "iso:country":"IR",
    "name:fas_x_preferred":[
        "\u0100b Qan\u0101t"
    ],
    "name:fas_x_variant":[
        "\u0622\u0628 \u0642\u0646\u0627\u062a",
        "\u062a\u0647\u0644\u0647 \u0632\u0627\u0631"
    ],
    "name:und_x_variant":[
        "\u0622\u0628 \u0642\u0646\u0627\u062a",
        "Tahlehz\u0101r"
    ],
    "wof:name":"Tahlehzar",
    "wof:placetype":"locality"
},
  "geometry": {"coordinates":[50.69387,31.25892],"type":"Point"}
}