{
  "type": "Feature",
  "properties": {
    "gn:admin1_code":"15",
    "gn:asciiname":"Darkhovin",
    "gn:country_code":"IR",
    "gn:dem":5,
    "gn:feature_class":"P",
    "gn:feature_code":"PPL",
    "gn:name":"D\u0101rkhov\u012bn",
    "gn:population":0,
    "gn:timezone":"Asia/Tehran",
    "iso:country":"IR",
    "name:ara_x_preferred":[
        "\u0642\u0631\u064a\u0629 \u062f\u0627\u0631\u062e\u0648\u064a\u0646"
    ],
    "name:fas_x_preferred":[
        "\u062f\u0627\u0631\u062e\u0648\u06cc\u0646"
    ],
    "name:fas_x_variant":[
        "D\u0101rkhoveyn"
    ],
    "name:und_x_variant":[
        "K\u016bt ol \u2018Ab\u012bd",
        "Darkhwin",
        "Daurat al Qaiwain",
        "Dorquain",
        "D\u0101r Kh\u016byeh",
        "D\u0101rkhov\u012bn"
    ],
    "wof:name":"Darkhovin",
    "wof:placetype":"locality"
},
  "geometry": {"coordinates":[48.42282,30.7445],"type":"Point"}
}