{
  "type": "Feature",
  "properties": {
    "gn:admin1_code":"11",
    "gn:asciiname":"Bandzak",
    "gn:country_code":"IR",
    "gn:dem":24,
    "gn:feature_class":"P",
    "gn:feature_code":"PPL",
    "gn:name":"Bandzak",
    "gn:population":0,
    "gn:timezone":"Asia/Tehran",
    "iso:country":"IR",
    "name:fas_x_preferred":[
        "\u0628\u0646\u062f\u0631\u0643"
    ],
    "name:fas_x_variant":[
        "\u0628\u0646\u062f\u0632\u06a9",
        "\u0628\u0646\u062f\u0632\u0631\u06a9"
    ],
    "name:msa_x_preferred":[
        "Band-e Zarak"
    ],
    "name:und_x_variant":[
        "Banz\u0304ark Kohneh",
        "Banz\u0304ark-e Kohneh",
        "Banz\u0304ark Now",
        "Bandark-e Kohneh",
        "Band-e-Zarak",
        "Bandarak",
        "Bandzak",
        "Bandzarak"
    ],
    "wof:name":"Bandzak",
    "wof:placetype":"locality"
},
  "geometry": {"coordinates":[56.9762,27.0666],"type":"Point"}
}