{
  "type": "Feature",
  "properties": {
    "gn:admin1_code":"16",
    "gn:asciiname":"Konamar",
    "gn:country_code":"IR",
    "gn:dem":1643,
    "gn:feature_class":"P",
    "gn:feature_code":"PPL",
    "gn:name":"Kon\u0101m\u0101r",
    "gn:population":0,
    "gn:timezone":"Asia/Tehran",
    "iso:country":"IR",
    "name:fas_x_preferred":[
        "\u06a9\u0646\u0627\u0645\u0627\u0631"
    ],
    "name:fas_x_variant":[
        "\u0643\u0648\u0646\u064e \u0645\u0627\u0631",
        "Kon\u0101m\u0101r"
    ],
    "name:und_x_variant":[
        "K\u016bna M\u0101r"
    ],
    "wof:name":"Konamar",
    "wof:placetype":"locality"
},
  "geometry": {"coordinates":[47.81694,35.63942],"type":"Point"}
}