{
  "type": "Feature",
  "properties": {
    "gn:admin1_code":"32",
    "gn:asciiname":"Kervi",
    "gn:country_code":"IR",
    "gn:dem":1382,
    "gn:feature_class":"P",
    "gn:feature_code":"PPL",
    "gn:name":"Kerv\u012b",
    "gn:population":0,
    "gn:timezone":"Asia/Tehran",
    "iso:country":"IR",
    "name:fas_x_preferred":[
        "\u0643\u0650\u0631\u0648\u06cc"
    ],
    "name:fas_x_variant":[
        "Kerv\u012b"
    ],
    "wof:name":"Kervi",
    "wof:placetype":"locality"
},
  "geometry": {"coordinates":[48.36667,38.13333],"type":"Point"}
}