{
  "type": "Feature",
  "properties": {
    "gn:admin1_code":"23",
    "gn:asciiname":"Shahzadeh Mohammad",
    "gn:country_code":"IR",
    "gn:dem":987,
    "gn:feature_class":"P",
    "gn:feature_code":"PPL",
    "gn:name":"Sh\u0101hz\u0101deh Mo\u1e29ammad",
    "gn:population":0,
    "gn:timezone":"Asia/Tehran",
    "iso:country":"IR",
    "name:ara_x_preferred":[
        "\u062f\u0631\u0628 \u063a\u0646\u0628\u062f"
    ],
    "name:aze_x_preferred":[
        "D\u0259rb G\u00fcnb\u0259d"
    ],
    "name:ceb_x_preferred":[
        "Sh\u0101hz\u0101deh Mo\u1e29ammad"
    ],
    "name:fas_x_preferred":[
        "\u062f\u064e\u0631\u0628\u0650 \u06af\u064f\u0646\u0628\u064e\u062f"
    ],
    "name:fas_x_variant":[
        "\u062f\u0631\u0628 \u06af\u0646\u0628\u062f",
        "\u0634\u0627\u0647\u0632\u0627\u062f\u0647 \u0645\u062d\u0645\u062f"
    ],
    "name:mlg_x_preferred":[
        "Darb-e Gonbad"
    ],
    "name:pol_x_preferred":[
        "Darb-e Gonbad"
    ],
    "name:swe_x_preferred":[
        "Sh\u0101hz\u0101deh Mo\u1e29ammad"
    ],
    "name:tur_x_preferred":[
        "Derb G\u00fcnbed"
    ],
    "name:und_x_variant":[
        "Darb-e Gonbad",
        "Sh\u0101hz\u0101deh Mo\u1e29ammad"
    ],
    "wof:name":"Shahzadeh Mohammad",
    "wof:placetype":"locality"
},
  "geometry": {"coordinates":[47.1514,33.6894],"type":"Point"}
}