{
  "type": "Feature",
  "properties": {
    "gn:admin1_code":"7",
    "gn:asciiname":"Kuzarag",
    "gn:country_code":"IR",
    "gn:dem":1652,
    "gn:feature_class":"P",
    "gn:feature_code":"PPL",
    "gn:name":"K\u016bzarag",
    "gn:population":0,
    "gn:timezone":"Asia/Tehran",
    "iso:country":"IR",
    "name:fas_x_preferred":[
        "\u06a9\u0648\u0632\u0631\u06af"
    ],
    "name:fas_x_variant":[
        "K\u016bzarak",
        "K\u016bzarag"
    ],
    "wof:name":"Kuzarag",
    "wof:placetype":"locality"
},
  "geometry": {"coordinates":[52.182,29.4974],"type":"Point"}
}