{
  "type": "Feature",
  "properties": {
    "gn:admin1_code":"8.0",
    "gn:asciiname":"Vali Marz",
    "gn:country_code":"IR",
    "gn:dem":604,
    "gn:feature_class":"P",
    "gn:feature_code":"PPLL",
    "gn:name":"Val\u012b Marz",
    "gn:population":0,
    "gn:timezone":"Asia/Tehran",
    "iso:country":"IR",
    "name:fas_x_preferred":[
        "\u0648\u0644\u06cc \u0645\u0631\u0632"
    ],
    "name:und_x_variant":[
        "Val\u012b Marz"
    ],
    "wof:name":"Vali Marz",
    "wof:placetype":"locality"
},
  "geometry": {"coordinates":[49.04171,37.44638],"type":"Point"}
}