{
  "type": "Feature",
  "properties": {
    "gn:admin1_code":"7",
    "gn:asciiname":"Tolombeh-ye Sarhaddi",
    "gn:country_code":"IR",
    "gn:dem":1594,
    "gn:feature_class":"P",
    "gn:feature_code":"PPL",
    "gn:name":"Tolombeh-ye Sar\u1e29add\u012b",
    "gn:population":0,
    "gn:timezone":"Asia/Tehran",
    "iso:country":"IR",
    "name:fas_x_preferred":[
        "\u062a\u0644\u0645\u0628\u0647 \u0633\u0631\u062d\u062f\u06cc"
    ],
    "name:fas_x_variant":[
        "Tolombeh-ye Sar\u1e29add\u012b"
    ],
    "wof:name":"Tolombeh-ye Sarhaddi",
    "wof:placetype":"locality"
},
  "geometry": {"coordinates":[54.894,28.9453],"type":"Point"}
}