{
  "type": "Feature",
  "properties": {
    "gn:admin1_code":"32",
    "gn:asciiname":"Qazi Kandi",
    "gn:country_code":"IR",
    "gn:dem":1675,
    "gn:feature_class":"P",
    "gn:feature_code":"PPL",
    "gn:name":"Q\u0101\u1e95\u012b Kand\u012b",
    "gn:population":0,
    "gn:timezone":"Asia/Tehran",
    "iso:country":"IR",
    "name:fas_x_preferred":[
        "\u0642\u0627\u0636\u06cc \u0643\u0646\u062f\u06cc"
    ],
    "name:fas_x_variant":[
        "Q\u0101\u1e95\u012b Kand\u012b"
    ],
    "wof:name":"Qazi Kandi",
    "wof:placetype":"locality"
},
  "geometry": {"coordinates":[48.3467,38.5618],"type":"Point"}
}