{
  "type": "Feature",
  "properties": {
    "gn:admin1_code":"42",
    "gn:asciiname":"Khomar Taj",
    "gn:country_code":"IR",
    "gn:dem":1418,
    "gn:feature_class":"P",
    "gn:feature_code":"PPL",
    "gn:name":"Khom\u0101r T\u0101j",
    "gn:population":0,
    "gn:timezone":"Asia/Tehran",
    "iso:country":"IR",
    "name:fas_x_preferred":[
        "Khom\u0101r T\u0101j"
    ],
    "name:fas_x_variant":[
        "Khom\u0101rt\u0101sh",
        "\u062e\u0645\u0627\u0631 \u062a\u0627\u062c"
    ],
    "name:und_x_variant":[
        "Khom\u0101rt\u0101j",
        "\u062e\u0645\u0627\u0631 \u062a\u0627\u062c"
    ],
    "wof:name":"Khomar Taj",
    "wof:placetype":"locality"
},
  "geometry": {"coordinates":[58.4348,37.2155],"type":"Point"}
}