{
  "type": "Feature",
  "properties": {
    "gn:admin1_code":"8.0",
    "gn:asciiname":"Tiulay",
    "gn:country_code":"IR",
    "gn:dem":1060,
    "gn:feature_class":"P",
    "gn:feature_code":"PPL",
    "gn:name":"\u0162\u012b\u016bl\u0101y",
    "gn:population":0,
    "gn:timezone":"Asia/Tehran",
    "iso:country":"IR",
    "name:fas_x_preferred":[
        "\u0162\u012b\u016bl\u0101-ye P\u0101\u2019\u012bn"
    ],
    "name:fas_x_variant":[
        "\u0637\u06cc\u0648\u0644\u0627\u06cc \u067e\u0627\u0626\u06cc\u0646",
        "\u0637\u06cc\u0648\u0644\u0627\u06cc",
        "\u0637\u0648\u0644\u0627\u06cc \u067e\u0627\u0626\u06cc\u0646"
    ],
    "name:und_x_variant":[
        "\u0637\u06cc\u0648\u0644\u0627\u06cc \u067e\u0627\u0626\u06cc\u0646",
        "\u0162\u012b\u016bl\u0101y",
        "\u0162\u016bl\u0101-ye P\u0101\u2019\u012bn"
    ],
    "wof:name":"Tiulay",
    "wof:placetype":"locality"
},
  "geometry": {"coordinates":[50.20252,36.84793],"type":"Point"}
}