{
  "type": "Feature",
  "properties": {
    "gn:admin1_code":"7",
    "gn:asciiname":"Anjirak-e `Olya",
    "gn:country_code":"IR",
    "gn:dem":1463,
    "gn:feature_class":"P",
    "gn:feature_code":"PPL",
    "gn:name":"Anj\u012brak-e \u2018Oly\u0101",
    "gn:population":0,
    "gn:timezone":"Asia/Tehran",
    "iso:country":"IR",
    "name:fas_x_preferred":[
        "\u0627\u0646\u062c\u06cc\u0631\u0643 \u0639\u0644\u06cc\u0627"
    ],
    "name:fas_x_variant":[
        "Anj\u012brak-e \u2018Oly\u0101"
    ],
    "wof:name":"Anjirak-e `Olya",
    "wof:placetype":"locality"
},
  "geometry": {"coordinates":[54.3426,28.9644],"type":"Point"}
}