{
  "type": "Feature",
  "properties": {
    "gn:admin1_code":"15",
    "gn:asciiname":"Beyt-e Moqattaf",
    "gn:cc2":"IR",
    "gn:country_code":"IR",
    "gn:dem":24,
    "gn:feature_class":"P",
    "gn:feature_code":"PPL",
    "gn:name":"Beyt-e Moq\u0101\u0163\u0163af",
    "gn:population":0,
    "gn:timezone":"Asia/Tehran",
    "iso:country":"IR",
    "name:fas_x_preferred":[
        "Beyt-e Moq\u0101\u0163\u0163af"
    ],
    "name:und_x_variant":[
        "Bait Muqattaf",
        "Beyt"
    ],
    "wof:name":"Beyt-e Moqattaf",
    "wof:placetype":"locality"
},
  "geometry": {"coordinates":[48.63333,31.55],"type":"Point"}
}