{
  "type": "Feature",
  "properties": {
    "gn:admin1_code":"28",
    "gn:asciiname":"Parmeh-ye Bala",
    "gn:country_code":"IR",
    "gn:dem":2485,
    "gn:feature_class":"P",
    "gn:feature_code":"PPL",
    "gn:name":"Parmeh-ye B\u0101l\u0101",
    "gn:population":0,
    "gn:timezone":"Asia/Tehran",
    "iso:country":"IR",
    "name:ara_x_preferred":[
        "\u0628\u0631\u0645\u0629 \u0639\u0644\u064a\u0627"
    ],
    "name:fas_x_preferred":[
        "Parmeh-ye B\u0101l\u0101"
    ],
    "name:fas_x_variant":[
        "Parmeh-ye \u2018Oly\u0101",
        "\u067e\u0631\u0645\u0647 \u0628\u0627\u0644\u0627",
        "\u067e\u0631\u0645\u0647 \u0639\u0644\u06cc\u0627"
    ],
    "name:und_x_variant":[
        "Parmeh \u2018Oly\u0101",
        "\u067e\u0631\u0645\u0647 \u0628\u0627\u0644\u0627"
    ],
    "wof:name":"Parmeh-ye Bala",
    "wof:placetype":"locality"
},
  "geometry": {"coordinates":[50.3353,32.73674],"type":"Point"}
}