{
  "type": "Feature",
  "properties": {
    "gn:admin1_code":"15",
    "gn:asciiname":"Shahrak-e Shohada",
    "gn:country_code":"IR",
    "gn:dem":88,
    "gn:feature_class":"P",
    "gn:feature_code":"PPL",
    "gn:name":"Shahrak-e Shohad\u0101",
    "gn:population":0,
    "gn:timezone":"Asia/Tehran",
    "iso:country":"IR",
    "name:fas_x_preferred":[
        "\u062d\u0645\u06cc\u062f\u0622\u0628\u0627\u062f"
    ],
    "name:fas_x_variant":[
        "Mam\u012bd\u0101b\u0101d",
        "Shahrak-e Shohad\u0101",
        "\u1e28am\u012bd\u0101b\u0101d",
        "\u0634\u0647\u0631\u06a9 \u0634\u0647\u062f\u0627"
    ],
    "wof:name":"Shahrak-e Shohada",
    "wof:placetype":"locality"
},
  "geometry": {"coordinates":[48.33064,32.24111],"type":"Point"}
}