{
  "type": "Feature",
  "properties": {
    "gn:admin1_code":"1",
    "gn:asciiname":"Bardehsur",
    "gn:country_code":"IR",
    "gn:dem":1594,
    "gn:feature_class":"P",
    "gn:feature_code":"PPL",
    "gn:name":"Bardehs\u016br",
    "gn:population":0,
    "gn:timezone":"Asia/Tehran",
    "iso:country":"IR",
    "name:fas_x_preferred":[
        "\u0628\u064e\u0631\u062f\u0650\u0647\u0633\u0648\u0631"
    ],
    "name:fas_x_variant":[
        "Bardehs\u016br",
        "\u0628\u0631\u062f\u0647 \u0633\u0648\u0631"
    ],
    "name:und_x_variant":[
        "\u0628\u0631\u062f\u0647 \u0633\u0648\u0631"
    ],
    "wof:name":"Bardehsur",
    "wof:placetype":"locality"
},
  "geometry": {"coordinates":[44.8276,37.4381],"type":"Point"}
}