{
  "type": "Feature",
  "properties": {
    "gn:admin1_code":"42",
    "gn:asciiname":"Shilgan",
    "gn:country_code":"IR",
    "gn:dem":251,
    "gn:feature_class":"P",
    "gn:feature_code":"PPL",
    "gn:name":"Sh\u012blg\u0101n",
    "gn:population":0,
    "gn:timezone":"Asia/Tehran",
    "iso:country":"IR",
    "name:fas_x_preferred":[
        "Sh\u012blg\u0101n"
    ],
    "name:fas_x_variant":[
        "\u0634\u06cc\u0644\u06af\u0627\u0646"
    ],
    "name:und_x_variant":[
        "\u0634\u06cc\u0644\u06af\u0627\u0646"
    ],
    "wof:name":"Shilgan",
    "wof:placetype":"locality"
},
  "geometry": {"coordinates":[59.37644,37.48184000000001],"type":"Point"}
}