{
  "type": "Feature",
  "properties": {
    "gn:admin1_code":"15.0",
    "gn:asciiname":"Sedreh",
    "gn:country_code":"IR",
    "gn:dem":25,
    "gn:feature_class":"P",
    "gn:feature_code":"PPL",
    "gn:name":"Sedreh",
    "gn:population":0,
    "gn:timezone":"Asia/Tehran",
    "iso:country":"IR",
    "name:diq_x_preferred":[
        "Sedre"
    ],
    "name:fas_x_preferred":[
        "\u0633\u062f\u0631\u0647"
    ],
    "name:rus_x_preferred":[
        "\u0421\u0435\u0434\u0440\u0435"
    ],
    "wof:name":"Sedreh",
    "wof:placetype":"locality"
},
  "geometry": {"coordinates":[48.4452,31.55885],"type":"Point"}
}