{
  "type": "Feature",
  "properties": {
    "gn:admin1_code":"40",
    "gn:asciiname":"Mazra`eh-ye Qanatu",
    "gn:country_code":"IR",
    "gn:dem":1967,
    "gn:feature_class":"P",
    "gn:feature_code":"PPL",
    "gn:name":"Mazra\u2018eh-ye Qan\u0101t\u016b",
    "gn:population":0,
    "gn:timezone":"Asia/Tehran",
    "iso:country":"IR",
    "name:fas_x_preferred":[
        "\u0642\u0646\u0627\u062a\u0648"
    ],
    "name:fas_x_variant":[
        "Qan\u0101t\u016b",
        "\u0645\u0632\u0631\u0639\u0647 \u0642\u0646\u0627\u062a\u0648"
    ],
    "name:und_x_variant":[
        "Mazra\u2018eh-ye Qan\u0101t\u016b"
    ],
    "wof:name":"Mazra`eh-ye Qanatu",
    "wof:placetype":"locality"
},
  "geometry": {"coordinates":[54.1815,29.7574],"type":"Point"}
}