{
  "type": "Feature",
  "properties": {
    "gn:admin1_code":"40.0",
    "gn:asciiname":"`Aliabad",
    "gn:country_code":"IR",
    "gn:dem":2353,
    "gn:feature_class":"P",
    "gn:feature_code":"PPL",
    "gn:name":"\u2018Al\u012b\u0101b\u0101d",
    "gn:population":0,
    "gn:timezone":"Asia/Tehran",
    "iso:country":"IR",
    "name:fas_x_preferred":[
        "\u0639\u064e\u0644\u064a\u0627\u0628\u0627\u062f\u0650 \u0628\u064e\u0646\u0627\u062f \u0643\u0648\u0643"
    ],
    "name:fas_x_variant":[
        "\u0639\u0644\u06cc \u0622\u0628\u0627\u062f",
        "\u2018Al\u012b\u0101b\u0101d-e Ban\u0101d K\u016bk",
        "\u2018Al\u012b\u0101b\u0101d"
    ],
    "wof:name":"`Aliabad",
    "wof:placetype":"locality"
},
  "geometry": {"coordinates":[53.9593,31.4868],"type":"Point"}
}