{
  "type": "Feature",
  "properties": {
    "gn:admin1_code":"4.0",
    "gn:asciiname":"Padgan",
    "gn:country_code":"IR",
    "gn:dem":1283,
    "gn:feature_class":"P",
    "gn:feature_code":"PPL",
    "gn:name":"Padg\u0101n",
    "gn:population":0,
    "gn:timezone":"Asia/Tehran",
    "iso:country":"IR",
    "name:fas_x_preferred":[
        "\u067e\u062f\u06af\u0627\u0646"
    ],
    "name:fas_x_variant":[
        "Padg\u0101n-e Golz\u0101r",
        "Padg\u0101n"
    ],
    "wof:name":"Padgan",
    "wof:placetype":"locality"
},
  "geometry": {"coordinates":[60.74197,27.90482],"type":"Point"}
}