{
  "type": "Feature",
  "properties": {
    "gn:admin1_code":"4.0",
    "gn:asciiname":"Burvi",
    "gn:country_code":"IR",
    "gn:dem":1362,
    "gn:feature_class":"P",
    "gn:feature_code":"PPL",
    "gn:name":"B\u016brv\u012b",
    "gn:population":0,
    "gn:timezone":"Asia/Tehran",
    "iso:country":"IR",
    "name:fas_x_preferred":[
        "\u0628\u0648\u0631\u0648\u06cc"
    ],
    "name:fas_x_variant":[
        "B\u016brv\u012b"
    ],
    "name:und_x_variant":[
        "B\u016br\u016b\u2019\u012b"
    ],
    "wof:name":"Burvi",
    "wof:placetype":"locality"
},
  "geometry": {"coordinates":[62.6886,26.8112],"type":"Point"}
}