{
  "type": "Feature",
  "properties": {
    "gn:admin1_code":"29",
    "gn:asciiname":"Beshuran",
    "gn:country_code":"IR",
    "gn:dem":1201,
    "gn:feature_class":"P",
    "gn:feature_code":"PPL",
    "gn:name":"Besh\u016br\u0101n",
    "gn:population":0,
    "gn:timezone":"Asia/Tehran",
    "iso:country":"IR",
    "name:fas_x_preferred":[
        "\u0628\u0634\u0648\u0631\u0627\u0646"
    ],
    "name:fas_x_variant":[
        "Besh\u016br\u0101n"
    ],
    "wof:name":"Beshuran",
    "wof:placetype":"locality"
},
  "geometry": {"coordinates":[57.5543,28.8416],"type":"Point"}
}