{
  "type": "Feature",
  "properties": {
    "gn:admin1_code":"28.0",
    "gn:asciiname":"Sonuchi",
    "gn:country_code":"IR",
    "gn:dem":1509,
    "gn:feature_class":"P",
    "gn:feature_code":"PPL",
    "gn:name":"Son\u016bch\u012b",
    "gn:population":0,
    "gn:timezone":"Asia/Tehran",
    "iso:country":"IR",
    "name:fas_x_preferred":[
        "\u0633\u0648\u0646\u0686\u06cc"
    ],
    "name:fas_x_variant":[
        "Son\u016bch\u012b",
        "S\u016bnoch\u012b",
        "\u0633\u0646\u0648\u0686\u06cc"
    ],
    "name:und_x_variant":[
        "Sownoch\u012b",
        "S\u016bn\u016bch\u012b",
        "S\u016bn\u012bch\u012b"
    ],
    "wof:name":"Sonuchi",
    "wof:placetype":"locality"
},
  "geometry": {"coordinates":[52.1984,32.52],"type":"Point"}
}