{
  "type": "Feature",
  "properties": {
    "gn:admin1_code":"42",
    "gn:asciiname":"Chah-e Nasr",
    "gn:country_code":"IR",
    "gn:dem":1346,
    "gn:feature_class":"P",
    "gn:feature_code":"PPL",
    "gn:name":"Ch\u0101h-e Nasr",
    "gn:population":0,
    "gn:timezone":"Asia/Tehran",
    "iso:country":"IR",
    "name:ceb_x_preferred":[
        "Ch\u0101h Nasar"
    ],
    "name:fas_x_preferred":[
        "\u0686\u0627\u0647 \u0646\u0633\u0631"
    ],
    "name:fas_x_variant":[
        "Ch\u0101h Nasar"
    ],
    "name:swe_x_preferred":[
        "Ch\u0101h Nasar"
    ],
    "name:und_x_variant":[
        "Ch\u0101h-e Nasr"
    ],
    "wof:name":"Chah-e Nasr",
    "wof:placetype":"locality"
},
  "geometry": {"coordinates":[58.5297,35.82545],"type":"Point"}
}