{
  "type": "Feature",
  "properties": {
    "gn:admin1_code":"35.0",
    "gn:asciiname":"Larusar",
    "gn:country_code":"IR",
    "gn:dem":1590,
    "gn:feature_class":"P",
    "gn:feature_code":"PPL",
    "gn:name":"L\u0101r\u016bsar",
    "gn:population":0,
    "gn:timezone":"Asia/Tehran",
    "iso:country":"IR",
    "name:fas_x_preferred":[
        "\u0644\u0627\u0631\u0648\u0633\u0631"
    ],
    "name:und_x_variant":[
        "L\u0101r\u016bsar"
    ],
    "wof:name":"Larusar",
    "wof:placetype":"locality"
},
  "geometry": {"coordinates":[51.08694000000001,36.46582],"type":"Point"}
}