{
  "type": "Feature",
  "properties": {
    "gn:admin1_code":"1",
    "gn:asciiname":"Khaneh-ye Behdasht",
    "gn:country_code":"IR",
    "gn:dem":794,
    "gn:feature_class":"P",
    "gn:feature_code":"PPL",
    "gn:name":"Kh\u0101neh-ye Behd\u0101sht",
    "gn:population":0,
    "gn:timezone":"Asia/Tehran",
    "iso:country":"IR",
    "name:fas_x_preferred":[
        "Kh\u0101neh-ye Behd\u0101sht"
    ],
    "name:fas_x_variant":[
        "\u062e\u0627\u0646\u0650\u06c0 \u0628\u0650\u0647\u062f\u0627\u0634\u062a"
    ],
    "wof:name":"Khaneh-ye Behdasht",
    "wof:placetype":"locality"
},
  "geometry": {"coordinates":[45.08333,39.28333],"type":"Point"}
}