{
  "type": "Feature",
  "properties": {
    "gn:admin1_code":"23",
    "gn:asciiname":"Kahriz-e Sorkh",
    "gn:country_code":"IR",
    "gn:dem":2111,
    "gn:feature_class":"P",
    "gn:feature_code":"PPL",
    "gn:name":"Kahr\u012bz-e Sorkh",
    "gn:population":0,
    "gn:timezone":"Asia/Tehran",
    "iso:country":"IR",
    "name:fas_x_preferred":[
        "\u06a9\u0647\u0631\u06cc\u0632 \u0633\u0631\u062e"
    ],
    "name:fas_x_variant":[
        "\u0643\u064e\u0647\u0631\u064a\u0632 \u0633\u064f\u0631\u062e",
        "Kahr\u012bz-e Sorkh"
    ],
    "name:und_x_variant":[
        "Kahr\u012bz Sorkh"
    ],
    "wof:name":"Kahriz-e Sorkh",
    "wof:placetype":"locality"
},
  "geometry": {"coordinates":[49.72505,33.33274],"type":"Point"}
}