{
  "type": "Feature",
  "properties": {
    "gn:admin1_code":"35",
    "gn:asciiname":"Jalikan-e `Olya",
    "gn:country_code":"IR",
    "gn:dem":21,
    "gn:feature_class":"P",
    "gn:feature_code":"PPL",
    "gn:name":"Jal\u012bk\u0101n-e \u2018Oly\u0101",
    "gn:population":0,
    "gn:timezone":"Asia/Tehran",
    "iso:country":"IR",
    "name:fas_x_preferred":[
        "\u062c\u0644\u064a\u0643\u0627\u0646 \u0628\u0627\u0644\u0627"
    ],
    "name:fas_x_variant":[
        "\u062c\u064e\u0644\u064a\u0643\u0627\u0646",
        "Jal\u012bk\u0101n-e B\u0101l\u0101",
        "\u062c\u0644\u06cc\u06a9\u0627\u0646 \u0639\u0644\u06cc\u0627"
    ],
    "name:und_x_variant":[
        "Jal\u012bk\u0101n",
        "Jal\u012bk\u0101n-e \u2018Oly\u0101"
    ],
    "wof:name":"Jalikan-e `Olya",
    "wof:placetype":"locality"
},
  "geometry": {"coordinates":[52.18019,36.49933],"type":"Point"}
}