{
  "type": "Feature",
  "properties": {
    "gn:admin1_code":"26.0",
    "gn:asciiname":"Kamaliyeh",
    "gn:country_code":"IR",
    "gn:dem":1016,
    "gn:feature_class":"P",
    "gn:feature_code":"PPL",
    "gn:name":"Kam\u0101l\u012byeh",
    "gn:population":0,
    "gn:timezone":"Asia/Tehran",
    "iso:country":"IR",
    "name:fas_x_preferred":[
        "Kam\u0101l\u0101b\u0101d"
    ],
    "name:fas_x_variant":[
        "Kam\u0101l\u012byeh",
        "\u0643\u0645\u0627\u0644 \u0622\u0628\u0627\u062f",
        "\u06a9\u0645\u0627\u0644\u06cc\u0647"
    ],
    "wof:name":"Kamaliyeh",
    "wof:placetype":"locality"
},
  "geometry": {"coordinates":[51.23629,35.47542],"type":"Point"}
}