{
  "type": "Feature",
  "properties": {
    "gn:admin1_code":"29",
    "gn:asciiname":"Cheshmeh",
    "gn:country_code":"IR",
    "gn:dem":342,
    "gn:feature_class":"P",
    "gn:feature_code":"PPL",
    "gn:name":"Cheshmeh",
    "gn:population":0,
    "gn:timezone":"Asia/Tehran",
    "iso:country":"IR",
    "name:ceb_x_preferred":[
        "Cheshmeh"
    ],
    "name:fas_x_preferred":[
        "\u0686\u0634\u0645\u0647"
    ],
    "name:swe_x_preferred":[
        "Cheshmeh"
    ],
    "wof:name":"Cheshmeh",
    "wof:placetype":"locality"
},
  "geometry": {"coordinates":[57.50119,27.38791],"type":"Point"}
}