{
  "type": "Feature",
  "properties": {
    "gn:admin1_code":"5.0",
    "gn:asciiname":"Nahliun",
    "gn:country_code":"IR",
    "gn:dem":1791,
    "gn:feature_class":"P",
    "gn:feature_code":"PPL",
    "gn:name":"Nahl\u012b\u016bn",
    "gn:population":0,
    "gn:timezone":"Asia/Tehran",
    "iso:country":"IR",
    "name:fas_x_preferred":[
        "Nahl\u012b\u016bn"
    ],
    "name:fas_x_variant":[
        "\u0646\u0647\u0644\u06cc\u0648\u0646",
        "\u062f\u0647 \u067e\u0627\u06cc \u062a\u0648\u0641",
        "\u062a\u0647\u0644\u06cc\u0648\u0646"
    ],
    "name:und_x_variant":[
        "\u0646\u0647\u0644\u06cc\u0648\u0646",
        "Deh-e P\u0101y T\u016bf",
        "Tahl\u012b\u016bn"
    ],
    "wof:name":"Nahliun",
    "wof:placetype":"locality"
},
  "geometry": {"coordinates":[50.86151,31.05905],"type":"Point"}
}