{
  "type": "Feature",
  "properties": {
    "gn:admin1_code":"13",
    "gn:asciiname":"Khalilan-e Sofla",
    "gn:country_code":"IR",
    "gn:dem":1507,
    "gn:feature_class":"P",
    "gn:feature_code":"PPL",
    "gn:name":"Khal\u012bl\u0101n-e Sofl\u00e1",
    "gn:population":0,
    "gn:timezone":"Asia/Tehran",
    "iso:country":"IR",
    "name:fas_x_preferred":[
        "\u062e\u0644\u06cc\u0644\u0627\u0646 \u0633\u0641\u0644\u06cc"
    ],
    "name:fas_x_variant":[
        "Khal\u012bl\u0101n-e Sofl\u00e1"
    ],
    "wof:name":"Khalilan-e Sofla",
    "wof:placetype":"locality"
},
  "geometry": {"coordinates":[47.0514,34.0856],"type":"Point"}
}