{
  "type": "Feature",
  "properties": {
    "gn:admin1_code":"8",
    "gn:asciiname":"Rudkol",
    "gn:country_code":"IR",
    "gn:dem":4,
    "gn:feature_class":"P",
    "gn:feature_code":"PPL",
    "gn:name":"R\u016bdkol",
    "gn:population":0,
    "gn:timezone":"Asia/Tehran",
    "iso:country":"IR",
    "name:fas_x_preferred":[
        "R\u016bdkol"
    ],
    "name:fas_x_variant":[
        "\u0631\u0648\u062f \u06a9\u0644"
    ],
    "name:und_x_variant":[
        "Rood Kal",
        "Rud-Gul",
        "R\u016bd Kad"
    ],
    "wof:name":"Rudkol",
    "wof:placetype":"locality"
},
  "geometry": {"coordinates":[49.76503,37.26733],"type":"Point"}
}