{
  "type": "Feature",
  "properties": {
    "gn:admin1_code":"41",
    "gn:asciiname":"Doghal",
    "gn:country_code":"IR",
    "gn:dem":1444,
    "gn:feature_class":"P",
    "gn:feature_code":"PPL",
    "gn:name":"Dogh\u0101l",
    "gn:population":0,
    "gn:timezone":"Asia/Tehran",
    "iso:country":"IR",
    "name:fas_x_preferred":[
        "\u062f\u063a\u0627\u0644"
    ],
    "name:fas_x_variant":[
        "Dogh\u0101l"
    ],
    "wof:name":"Doghal",
    "wof:placetype":"locality"
},
  "geometry": {"coordinates":[60.3047,31.8719],"type":"Point"}
}