{
  "type": "Feature",
  "properties": {
    "gn:admin1_code":"28",
    "gn:asciiname":"Kuy-e Shahid Beheshti",
    "gn:country_code":"IR",
    "gn:dem":2008,
    "gn:feature_class":"P",
    "gn:feature_code":"PPL",
    "gn:name":"K\u016by-e Shah\u012bd Behesht\u012b",
    "gn:population":0,
    "gn:timezone":"Asia/Tehran",
    "iso:country":"IR",
    "name:fas_x_preferred":[
        "K\u016by-e Shah\u012bd Behesht\u012b"
    ],
    "name:fas_x_variant":[
        "\u06a9\u0648\u06cc \u0634\u0647\u06cc\u062f \u0628\u0647\u0634\u062a\u06cc"
    ],
    "name:und_x_variant":[
        "\u06a9\u0648\u06cc \u0634\u0647\u06cc\u062f \u0628\u0647\u0634\u062a\u06cc"
    ],
    "wof:name":"Kuy-e Shahid Beheshti",
    "wof:placetype":"locality"
},
  "geometry": {"coordinates":[50.75809,32.73301],"type":"Point"}
}