{
  "type": "Feature",
  "properties": {
    "gn:admin1_code":"25.0",
    "gn:asciiname":"Gandalabad",
    "gn:country_code":"IR",
    "gn:dem":1877,
    "gn:feature_class":"P",
    "gn:feature_code":"PPL",
    "gn:name":"Gandal\u0101b\u0101d",
    "gn:population":0,
    "gn:timezone":"Asia/Tehran",
    "iso:country":"IR",
    "name:fas_x_preferred":[
        "\u06af\u064e\u0646\u062f\u064e\u0644 \u0622\u0628\u0627\u062f"
    ],
    "name:fas_x_variant":[
        "Gandal\u0101b\u0101d"
    ],
    "wof:name":"Gandalabad",
    "wof:placetype":"locality"
},
  "geometry": {"coordinates":[53.73333,36.08333],"type":"Point"}
}