{
  "type": "Feature",
  "properties": {
    "gn:admin1_code":"28",
    "gn:asciiname":"Guged",
    "gn:country_code":"IR",
    "gn:dem":1793,
    "gn:feature_class":"P",
    "gn:feature_code":"PPL",
    "gn:name":"G\u016bged",
    "gn:population":0,
    "gn:timezone":"Asia/Tehran",
    "iso:country":"IR",
    "name:ara_x_preferred":[
        "\u063a\u0648\u063a\u062f"
    ],
    "name:aze_x_preferred":[
        "Gug\u0259d"
    ],
    "name:ceb_x_preferred":[
        "G\u016bged"
    ],
    "name:fas_x_preferred":[
        "G\u016bgad"
    ],
    "name:fas_x_variant":[
        "G\u016bged",
        "\u06af\u0648\u06af\u062f"
    ],
    "name:fra_x_preferred":[
        "Gougued"
    ],
    "name:ita_x_preferred":[
        "Guged"
    ],
    "name:mlg_x_preferred":[
        "Guged"
    ],
    "name:rus_x_preferred":[
        "\u0413\u0443\u0433\u0435\u0434"
    ],
    "name:swe_x_preferred":[
        "G\u016bged"
    ],
    "name:tur_x_preferred":[
        "Guged"
    ],
    "name:und_x_variant":[
        "Googad"
    ],
    "wof:name":"Guged",
    "wof:placetype":"locality"
},
  "geometry": {"coordinates":[50.35249,33.47558],"type":"Point"}
}