{
  "type": "Feature",
  "properties": {
    "gn:admin1_code":"42.0",
    "gn:asciiname":"Orduluk",
    "gn:country_code":"IR",
    "gn:dem":1091,
    "gn:feature_class":"P",
    "gn:feature_code":"PPL",
    "gn:name":"Ord\u016bl\u016bk",
    "gn:population":0,
    "gn:timezone":"Asia/Tehran",
    "iso:country":"IR",
    "name:ceb_x_preferred":[
        "Ord\u016bl\u016bk"
    ],
    "name:fas_x_preferred":[
        "\u0627\u0631\u062f\u0648\u0644\u0648\u06a9"
    ],
    "name:fas_x_variant":[
        "Ordol\u016bk",
        "Ord\u016bl\u016bk",
        "Ard\u016blak",
        "Ardal\u016bk"
    ],
    "name:swe_x_preferred":[
        "Ord\u016bl\u016bk"
    ],
    "name:und_x_variant":[
        "Urduluk",
        "Ardalook"
    ],
    "wof:name":"Orduluk",
    "wof:placetype":"locality"
},
  "geometry": {"coordinates":[60.0953,36.2676],"type":"Point"}
}