{
  "type": "Feature",
  "properties": {
    "gn:admin1_code":"7",
    "gn:asciiname":"Deh Bava",
    "gn:country_code":"IR",
    "gn:dem":1753,
    "gn:feature_class":"P",
    "gn:feature_code":"PPL",
    "gn:name":"Deh Bav\u0101",
    "gn:population":0,
    "gn:timezone":"Asia/Tehran",
    "iso:country":"IR",
    "name:fas_x_preferred":[
        "\u062f\u0650\u0647 \u0628\u064e\u0648\u0627"
    ],
    "name:fas_x_variant":[
        "Deh Bav\u0101"
    ],
    "wof:name":"Deh Bava",
    "wof:placetype":"locality"
},
  "geometry": {"coordinates":[51.93333,29.95],"type":"Point"}
}