{
  "type": "Feature",
  "properties": {
    "gn:admin1_code":"35.0",
    "gn:asciiname":"Kamarbon",
    "gn:country_code":"IR",
    "gn:dem":2602,
    "gn:feature_class":"P",
    "gn:feature_code":"PPL",
    "gn:name":"Kamarbon",
    "gn:population":0,
    "gn:timezone":"Asia/Tehran",
    "iso:country":"IR",
    "name:fas_x_preferred":[
        "\u06a9\u0645\u0631\u0628\u0646"
    ],
    "wof:name":"Kamarbon",
    "wof:placetype":"locality"
},
  "geometry": {"coordinates":[51.39801,36.22815],"type":"Point"}
}