{
  "type": "Feature",
  "properties": {
    "gn:admin1_code":"29",
    "gn:asciiname":"Rahu'i",
    "gn:country_code":"IR",
    "gn:dem":588,
    "gn:feature_class":"P",
    "gn:feature_code":"PPL",
    "gn:name":"R\u0101h\u016b\u2019\u012b",
    "gn:population":0,
    "gn:timezone":"Asia/Tehran",
    "iso:country":"IR",
    "name:fas_x_preferred":[
        "\u0631\u0627\u0647\u0648\u0626\u06cc"
    ],
    "name:fas_x_variant":[
        "R\u0101h\u016b\u2019\u012b"
    ],
    "wof:name":"Rahu'i",
    "wof:placetype":"locality"
},
  "geometry": {"coordinates":[57.4726,27.7463],"type":"Point"}
}