{
  "type": "Feature",
  "properties": {
    "gn:admin1_code":"28",
    "gn:asciiname":"Dengezi",
    "gn:country_code":"IR",
    "gn:dem":2225,
    "gn:feature_class":"P",
    "gn:feature_code":"PPL",
    "gn:name":"Dengez\u012b",
    "gn:population":0,
    "gn:timezone":"Asia/Tehran",
    "iso:country":"IR",
    "name:fas_x_preferred":[
        "Dengezl\u016b"
    ],
    "name:fas_x_variant":[
        "\u062f\u0646\u06af\u0632\u0644\u0648",
        "\u062f\u0646\u06af\u0632\u06cc"
    ],
    "name:und_x_variant":[
        "Dahgezl\u012b",
        "Dangazl\u016b-ye \u2018Oly\u0101",
        "Dangazl\u016b",
        "Dengez\u012b",
        "Deng-e Zol\u012b"
    ],
    "wof:name":"Dengezi",
    "wof:placetype":"locality"
},
  "geometry": {"coordinates":[51.64838,30.86865],"type":"Point"}
}