{
  "type": "Feature",
  "properties": {
    "gn:admin1_code":"35.0",
    "gn:asciiname":"Mij",
    "gn:country_code":"IR",
    "gn:dem":2272,
    "gn:feature_class":"P",
    "gn:feature_code":"PPL",
    "gn:name":"M\u012bj",
    "gn:population":0,
    "gn:timezone":"Asia/Tehran",
    "iso:country":"IR",
    "name:fas_x_preferred":[
        "\u0645\u064a\u062c"
    ],
    "name:fas_x_variant":[
        "M\u012bj"
    ],
    "wof:name":"Mij",
    "wof:placetype":"locality"
},
  "geometry": {"coordinates":[50.4812,36.6118],"type":"Point"}
}