{
  "type": "Feature",
  "properties": {
    "gn:admin1_code":"35.0",
    "gn:asciiname":"Gandyab-e Sofla",
    "gn:country_code":"IR",
    "gn:dem":3,
    "gn:feature_class":"P",
    "gn:feature_code":"PPL",
    "gn:name":"Gandy\u0101b-e Sofl\u00e1",
    "gn:population":0,
    "gn:timezone":"Asia/Tehran",
    "iso:country":"IR",
    "name:fas_x_preferred":[
        "\u06af\u0646\u062f\u064a\u0627\u0628 \u067e\u0627\u0626\u064a\u0646"
    ],
    "name:fas_x_variant":[
        "Gandy\u0101b-e P\u0101\u2019\u012bn",
        "\u06af\u0646\u062f\u06cc\u0627\u0628 \u0633\u0641\u0644\u06cc"
    ],
    "name:und_x_variant":[
        "Gandy\u0101b-e Sofl\u00e1"
    ],
    "wof:name":"Gandyab-e Sofla",
    "wof:placetype":"locality"
},
  "geometry": {"coordinates":[52.03604,36.5397],"type":"Point"}
}