{
  "type": "Feature",
  "properties": {
    "gn:admin1_code":"41",
    "gn:asciiname":"Mahmu'i",
    "gn:country_code":"IR",
    "gn:dem":1444,
    "gn:feature_class":"P",
    "gn:feature_code":"PPL",
    "gn:name":"Mahm\u016b\u2019\u012b",
    "gn:population":0,
    "gn:timezone":"Asia/Tehran",
    "iso:country":"IR",
    "name:fas_x_preferred":[
        "Mahm\u016b\u2019\u012b"
    ],
    "name:fas_x_variant":[
        "\u0645\u0647\u0645\u0648\u064a\u06cc",
        "\u0645\u0647\u0645\u0648\u0626\u06cc"
    ],
    "wof:name":"Mahmu'i",
    "wof:placetype":"locality"
},
  "geometry": {"coordinates":[59.23781,33.73661],"type":"Point"}
}