{
  "type": "Feature",
  "properties": {
    "gn:admin1_code":"34",
    "gn:asciiname":"Yardel Aghaj",
    "gn:country_code":"IR",
    "gn:dem":1728,
    "gn:feature_class":"P",
    "gn:feature_code":"PPL",
    "gn:name":"Y\u0101rdel \u0100gh\u0101j",
    "gn:population":0,
    "gn:timezone":"Asia/Tehran",
    "iso:country":"IR",
    "name:fas_x_preferred":[
        "\u064a\u0627\u0631\u062f\u0650\u0644 \u0622\u063a\u0627\u062c"
    ],
    "name:fas_x_variant":[
        "Y\u0101rdel \u0100gh\u0101j"
    ],
    "wof:name":"Yardel Aghaj",
    "wof:placetype":"locality"
},
  "geometry": {"coordinates":[50.21667,33.71667],"type":"Point"}
}