{
  "type": "Feature",
  "properties": {
    "gn:admin1_code":"7",
    "gn:asciiname":"Gowd Rizi",
    "gn:country_code":"IR",
    "gn:dem":2014,
    "gn:feature_class":"P",
    "gn:feature_code":"PPL",
    "gn:name":"Gowd R\u012bz\u012b",
    "gn:population":0,
    "gn:timezone":"Asia/Tehran",
    "iso:country":"IR",
    "name:fas_x_preferred":[
        "Gowd R\u012bz\u012b"
    ],
    "wof:name":"Gowd Rizi",
    "wof:placetype":"locality"
},
  "geometry": {"coordinates":[51.93417,29.90222],"type":"Point"}
}