{
  "type": "Feature",
  "properties": {
    "gn:admin1_code":"29.0",
    "gn:asciiname":"Yazdan Panah",
    "gn:country_code":"IR",
    "gn:dem":596,
    "gn:feature_class":"P",
    "gn:feature_code":"PPL",
    "gn:name":"Yazd\u0101n Pan\u0101h",
    "gn:population":0,
    "gn:timezone":"Asia/Tehran",
    "iso:country":"IR",
    "name:ceb_x_preferred":[
        "Yazd\u0101n Pan\u0101h"
    ],
    "name:fas_x_preferred":[
        "\u06cc\u0632\u062f\u0627\u0646 \u067e\u0646\u0627\u0647"
    ],
    "name:fas_x_variant":[
        "Yazd\u0101n Pan\u0101h",
        "\u06cc\u0632\u062f\u0627\u0646\u200c\u067e\u0646\u0627\u0647"
    ],
    "name:swe_x_preferred":[
        "Yazd\u0101n Pan\u0101h"
    ],
    "name:urd_x_preferred":[
        "\u06cc\u0632\u062f\u0627\u06ba \u067e\u0646\u0627\u06c1"
    ],
    "wof:name":"Yazdan Panah",
    "wof:placetype":"locality"
},
  "geometry": {"coordinates":[59.08292,28.6467],"type":"Point"}
}