{
  "type": "Feature",
  "properties": {
    "gn:admin1_code":"42",
    "gn:asciiname":"Filian-e Qa'em Maqam",
    "gn:country_code":"IR",
    "gn:dem":1031,
    "gn:feature_class":"P",
    "gn:feature_code":"PPL",
    "gn:name":"F\u012bl\u012b\u0101n-e Q\u0101\u2019em Maq\u0101m",
    "gn:population":0,
    "gn:timezone":"Asia/Tehran",
    "iso:country":"IR",
    "name:fas_x_preferred":[
        "\u0641\u06cc\u0644\u06cc\u0627\u0646 \u0642\u0627\u0626\u0645 \u0645\u0642\u0627\u0645"
    ],
    "name:fas_x_variant":[
        "Fel\u012b\u0101n-e Qa\u2019em Maq\u0101m\u012b",
        "F\u012bl\u012b\u0101n-e Q\u0101\u2019em Maq\u0101m"
    ],
    "name:und_x_variant":[
        "Fel\u012b\u0101n-e Qa\u2019em Maq\u0101m"
    ],
    "wof:name":"Filian-e Qa'em Maqam",
    "wof:placetype":"locality"
},
  "geometry": {"coordinates":[59.42315,36.52576],"type":"Point"}
}