{
  "type": "Feature",
  "properties": {
    "gn:admin1_code":"35",
    "gn:asciiname":"Chalek Deh",
    "gn:country_code":"IR",
    "gn:dem":823,
    "gn:feature_class":"P",
    "gn:feature_code":"PPL",
    "gn:name":"Ch\u0101lek Deh",
    "gn:population":0,
    "gn:timezone":"Asia/Tehran",
    "iso:country":"IR",
    "name:fas_x_preferred":[
        "Ch\u0101lek Deh"
    ],
    "name:fas_x_variant":[
        "\u0686\u0627\u0644\u0643 \u062f\u0647"
    ],
    "name:und_x_variant":[
        "\u0686\u0627\u0644\u0643 \u062f\u0647"
    ],
    "wof:name":"Chalek Deh",
    "wof:placetype":"locality"
},
  "geometry": {"coordinates":[53.65669000000001,36.57484],"type":"Point"}
}