{
  "type": "Feature",
  "properties": {
    "gn:admin1_code":"35.0",
    "gn:asciiname":"Jisa",
    "gn:country_code":"IR",
    "gn:dem":35,
    "gn:feature_class":"P",
    "gn:feature_code":"PPL",
    "gn:name":"J\u012bs\u0101",
    "gn:population":0,
    "gn:timezone":"Asia/Tehran",
    "iso:country":"IR",
    "name:fas_x_preferred":[
        "\u062c\u064a\u0633\u0627"
    ],
    "name:fas_x_variant":[
        "J\u012bs\u0101",
        "\u062c\u06cc\u0633\u0627 \u06a9\u0644\u0627\u0631\u0622\u0628\u0627\u062f"
    ],
    "name:und_x_variant":[
        "J\u012bs\u0101 Kal\u0101r\u0101b\u0101d"
    ],
    "wof:name":"Jisa",
    "wof:placetype":"locality"
},
  "geometry": {"coordinates":[51.24488,36.66622],"type":"Point"}
}