{
  "type": "Feature",
  "properties": {
    "gn:admin1_code":"8",
    "gn:asciiname":"Madar Sara",
    "gn:country_code":"IR",
    "gn:dem":264,
    "gn:feature_class":"P",
    "gn:feature_code":"PPL",
    "gn:name":"M\u0101dar Sar\u0101",
    "gn:population":0,
    "gn:timezone":"Asia/Tehran",
    "iso:country":"IR",
    "name:fas_x_preferred":[
        "M\u0101dar Sar\u0101"
    ],
    "name:fas_x_variant":[
        "\u0645\u0627\u062f\u0631\u0633\u0631\u0627"
    ],
    "name:msa_x_preferred":[
        "Madar Sara"
    ],
    "name:ukr_x_preferred":[
        "\u041c\u0430\u0434\u0430\u0440-\u0421\u0430\u0440\u0430"
    ],
    "name:urd_x_preferred":[
        "\u0645\u06cc\u0688\u0627\u0631 \u0633\u0627\u0631\u0627"
    ],
    "wof:name":"Madar Sara",
    "wof:placetype":"locality"
},
  "geometry": {"coordinates":[49.76833,37.03778],"type":"Point"}
}