{
  "type": "Feature",
  "properties": {
    "gn:admin1_code":"15.0",
    "gn:asciiname":"Deh-e Bahrami",
    "gn:country_code":"IR",
    "gn:dem":843,
    "gn:feature_class":"P",
    "gn:feature_code":"PPL",
    "gn:name":"Deh-e Bahr\u0101m\u012b",
    "gn:population":0,
    "gn:timezone":"Asia/Tehran",
    "iso:country":"IR",
    "name:fas_x_preferred":[
        "Deh-e Bahr\u0101m\u012b"
    ],
    "name:fas_x_variant":[
        "\u062f\u0647 \u0628\u0647\u0631\u0627\u0645\u06cc"
    ],
    "name:und_x_variant":[
        "\u062f\u0647 \u0628\u0647\u0631\u0627\u0645\u06cc"
    ],
    "wof:name":"Deh-e Bahrami",
    "wof:placetype":"locality"
},
  "geometry": {"coordinates":[49.76572,31.61939000000001],"type":"Point"}
}