{
  "type": "Feature",
  "properties": {
    "gn:admin1_code":"7",
    "gn:asciiname":"Roknabad",
    "gn:country_code":"IR",
    "gn:dem":414,
    "gn:feature_class":"P",
    "gn:feature_code":"PPL",
    "gn:name":"Rokn\u0101b\u0101d",
    "gn:population":0,
    "gn:timezone":"Asia/Tehran",
    "iso:country":"IR",
    "name:fas_x_preferred":[
        "\u0632\u06a9\u0646 \u0622\u0628\u0627\u062f"
    ],
    "name:fas_x_variant":[
        "Rokn\u0101b\u0101d",
        "Zekn\u0101b\u0101d",
        "\u0631\u06a9\u0646 \u0622\u0628\u0627\u062f"
    ],
    "name:und_x_variant":[
        "Rukn\u0101b\u0101d"
    ],
    "wof:name":"Roknabad",
    "wof:placetype":"locality"
},
  "geometry": {"coordinates":[53.42646,27.23517],"type":"Point"}
}