{
  "type": "Feature",
  "properties": {
    "gn:admin1_code":"11.0",
    "gn:asciiname":"Sarchaghan Gorazi",
    "gn:country_code":"IR",
    "gn:dem":209,
    "gn:feature_class":"P",
    "gn:feature_code":"PPL",
    "gn:name":"Sarch\u0101gh\u0101n Gor\u0101z\u012b",
    "gn:population":0,
    "gn:timezone":"Asia/Tehran",
    "iso:country":"IR",
    "name:fas_x_preferred":[
        "\u0633\u0631\u0686\u0627\u063a\u0627\u0646 \u06af\u0631\u0627\u0632\u06cc"
    ],
    "name:fas_x_variant":[
        "Sarch\u0101gh\u0101n Gor\u0101z\u012b"
    ],
    "wof:name":"Sarchaghan Gorazi",
    "wof:placetype":"locality"
},
  "geometry": {"coordinates":[57.33462,27.18695],"type":"Point"}
}