{
  "type": "Feature",
  "properties": {
    "gn:admin1_code":"37",
    "gn:asciiname":"Emamabad",
    "gn:country_code":"IR",
    "gn:dem":64,
    "gn:feature_class":"P",
    "gn:feature_code":"PPL",
    "gn:name":"Em\u0101m\u0101b\u0101d",
    "gn:population":0,
    "gn:timezone":"Asia/Tehran",
    "iso:country":"IR",
    "name:fas_x_preferred":[
        "Em\u0101m\u0101b\u0101d"
    ],
    "name:fas_x_variant":[
        "\u0100v\u0101ns\u012byeh",
        "\u0627\u0645\u0627\u0645 \u0622\u0628\u0627\u062f",
        "\u0627\u0645\u0627\u0645 \u0622\u0628\u0627\u062f \u0633\u064a\u0633\u062a\u0627\u0646\u064a\u0647\u0627"
    ],
    "name:und_x_variant":[
        "Em\u0101m\u0101b\u0101d-e S\u012bst\u0101n\u012bh\u0101",
        "\u0627\u0645\u0627\u0645 \u0622\u0628\u0627\u062f"
    ],
    "wof:name":"Emamabad",
    "wof:placetype":"locality"
},
  "geometry": {"coordinates":[54.81106,36.98295],"type":"Point"}
}