{
  "type": "Feature",
  "properties": {
    "gn:admin1_code":"4.0",
    "gn:asciiname":"Mahban",
    "gn:cc2":"IR",
    "gn:country_code":"IR",
    "gn:dem":984,
    "gn:feature_class":"P",
    "gn:feature_code":"PPL",
    "gn:name":"M\u0101hb\u0101n",
    "gn:population":0,
    "gn:timezone":"Asia/Tehran",
    "iso:country":"IR",
    "name:fas_x_preferred":[
        "M\u0101hb\u0101n"
    ],
    "name:und_x_variant":[
        "M\u0101h\u0101b\u0101n",
        "Moheb\u0101n",
        "M\u0101h\u0101n"
    ],
    "wof:name":"Mahban",
    "wof:placetype":"locality"
},
  "geometry": {"coordinates":[60.55222,26.43556],"type":"Point"}
}