{
  "type": "Feature",
  "properties": {
    "gn:admin1_code":"4.0",
    "gn:asciiname":"Falizan",
    "gn:country_code":"IR",
    "gn:dem":1518,
    "gn:feature_class":"P",
    "gn:feature_code":"PPL",
    "gn:name":"F\u0101l\u012bz\u0101n",
    "gn:population":0,
    "gn:timezone":"Asia/Tehran",
    "iso:country":"IR",
    "name:ara_x_preferred":[
        "\u0641\u0627\u0644\u064a\u0632\u0627\u0646"
    ],
    "name:ceb_x_preferred":[
        "F\u0101l\u012bz\u0101n"
    ],
    "name:fas_x_preferred":[
        "\u0641\u0627\u0644\u06cc\u0632\u0627\u0646"
    ],
    "name:swe_x_preferred":[
        "F\u0101l\u012bz\u0101n"
    ],
    "name:urd_x_preferred":[
        "\u0641\u0627\u0644\u06cc\u0632\u0627\u0646"
    ],
    "wof:name":"Falizan",
    "wof:placetype":"locality"
},
  "geometry": {"coordinates":[61.19111,27.81667],"type":"Point"}
}