{
  "type": "Feature",
  "properties": {
    "gn:admin1_code":"25.0",
    "gn:asciiname":"Sarkheh-ye Bala",
    "gn:country_code":"IR",
    "gn:dem":1360,
    "gn:feature_class":"P",
    "gn:feature_code":"PPL",
    "gn:name":"Sarkheh-ye B\u0101l\u0101",
    "gn:population":0,
    "gn:timezone":"Asia/Tehran",
    "iso:country":"IR",
    "name:fas_x_preferred":[
        "\u0633\u0631\u062e\u0647 \u0628\u0627\u0644\u0627"
    ],
    "name:fas_x_variant":[
        "\u0633\u0631\u062a\u062e\u062a",
        "\u0633\u0631\u062a\u062e\u062a \u0628\u0627\u0644\u0627"
    ],
    "name:und_x_variant":[
        "Sarkheh-ye B\u0101l\u0101",
        "Sartakht",
        "Sartakht-e B\u0101l\u0101"
    ],
    "wof:name":"Sarkheh-ye Bala",
    "wof:placetype":"locality"
},
  "geometry": {"coordinates":[54.7824,35.41447],"type":"Point"}
}