{
  "type": "Feature",
  "properties": {
    "gn:admin1_code":"34",
    "gn:asciiname":"Famarin",
    "gn:country_code":"IR",
    "gn:dem":1683,
    "gn:feature_class":"P",
    "gn:feature_code":"PPL",
    "gn:name":"F\u0101mar\u012bn",
    "gn:population":0,
    "gn:timezone":"Asia/Tehran",
    "iso:country":"IR",
    "name:fas_x_preferred":[
        "\u0641\u0627\u0645\u0631\u064a\u0646"
    ],
    "name:fas_x_variant":[
        "F\u0101mar\u012bn"
    ],
    "name:und_x_variant":[
        "F\u0101mer\u012bn",
        "Fam\u0101r\u012bn"
    ],
    "wof:name":"Famarin",
    "wof:placetype":"locality"
},
  "geometry": {"coordinates":[49.2587,34.6706],"type":"Point"}
}