{
  "type": "Feature",
  "properties": {
    "gn:admin1_code":"29.0",
    "gn:asciiname":"Khandan",
    "gn:country_code":"IR",
    "gn:dem":2334,
    "gn:feature_class":"P",
    "gn:feature_code":"PPL",
    "gn:name":"Khand\u0101n",
    "gn:population":0,
    "gn:timezone":"Asia/Tehran",
    "iso:country":"IR",
    "wof:name":"Khandan",
    "wof:placetype":"locality"
},
  "geometry": {"coordinates":[57.88361,29.08278],"type":"Point"}
}