{
  "type": "Feature",
  "properties": {
    "gn:admin1_code":"42",
    "gn:asciiname":"Bazeh `Asheqan",
    "gn:country_code":"IR",
    "gn:dem":1109,
    "gn:feature_class":"P",
    "gn:feature_code":"PPL",
    "gn:name":"B\u0101zeh \u2018\u0100sheq\u0101n",
    "gn:population":0,
    "gn:timezone":"Asia/Tehran",
    "iso:country":"IR",
    "name:fas_x_preferred":[
        "B\u0101zeh \u2018\u0100sheq\u0101n"
    ],
    "name:fas_x_variant":[
        "\u2018\u0100sheq\u0101n",
        "B\u0101zeh-ye \u2018\u0100sheq\u0101n",
        "\u0639\u0627\u0634\u0642\u0627\u0646",
        "B\u0101shq\u016bn",
        "B\u0101sheq\u016bn",
        "B\u0101shek\u016bn",
        "\u0628\u0627\u0632\u0647 \u0639\u0627\u0634\u0642\u0627\u0646"
    ],
    "wof:name":"Bazeh `Asheqan",
    "wof:placetype":"locality"
},
  "geometry": {"coordinates":[59.55239,34.96761],"type":"Point"}
}