{
  "type": "Feature",
  "properties": {
    "gn:admin1_code":"4",
    "gn:asciiname":"Hiyan",
    "gn:country_code":"IR",
    "gn:dem":21,
    "gn:feature_class":"P",
    "gn:feature_code":"PPL",
    "gn:name":"Hiyan",
    "gn:population":0,
    "gn:timezone":"Asia/Tehran",
    "iso:country":"IR",
    "name:fas_x_preferred":[
        "H\u012b\u0101n"
    ],
    "name:fas_x_variant":[
        "\u0647\u06cc\u0627\u0646"
    ],
    "name:und_x_variant":[
        "Hey\u0101n",
        "Hiyan",
        "\u0647\u06cc\u0627\u0646"
    ],
    "wof:name":"Hiyan",
    "wof:placetype":"locality"
},
  "geometry": {"coordinates":[59.33859,25.71262],"type":"Point"}
}