{
  "type": "Feature",
  "properties": {
    "gn:admin1_code":"15",
    "gn:asciiname":"Chehshur",
    "gn:country_code":"IR",
    "gn:dem":599,
    "gn:feature_class":"P",
    "gn:feature_code":"PPL",
    "gn:name":"Chehsh\u016br",
    "gn:population":0,
    "gn:timezone":"Asia/Tehran",
    "iso:country":"IR",
    "wof:name":"Chehshur",
    "wof:placetype":"locality"
},
  "geometry": {"coordinates":[49.41667,32.08333],"type":"Point"}
}