{
  "type": "Feature",
  "properties": {
    "gn:admin1_code":"23",
    "gn:asciiname":"Rusta-ye Fasli-ye Khalaj-e Sofla",
    "gn:country_code":"IR",
    "gn:dem":2021,
    "gn:feature_class":"P",
    "gn:feature_code":"PPL",
    "gn:name":"R\u016bst\u0101-ye Fa\u015fl\u012b-ye Khalaj-e Sofl\u00e1",
    "gn:population":0,
    "gn:timezone":"Asia/Tehran",
    "iso:country":"IR",
    "name:fas_x_preferred":[
        "\u062e\u0644\u062c \u0633\u0641\u0644\u0649"
    ],
    "name:fas_x_variant":[
        "\u062e\u0644\u062c \u067e\u0627\u0626\u064a\u0646",
        "Khalaj-e Sofl\u00e1",
        "Khalaj-e P\u0101\u2019\u012bn",
        "\u0631\u0648\u0633\u062a\u0627\u06cc \u0641\u0635\u0644\u06cc \u062e\u0644\u062c \u0633\u0641\u0644\u06cc"
    ],
    "name:und_x_variant":[
        "Kalaj",
        "Khalach",
        "Khalaj",
        "R\u016bst\u0101-ye Fa\u015fl\u012b-ye Khalaj-e Sofl\u00e1"
    ],
    "wof:name":"Rusta-ye Fasli-ye Khalaj-e Sofla",
    "wof:placetype":"locality"
},
  "geometry": {"coordinates":[49.35005,33.68486],"type":"Point"}
}