{
  "type": "Feature",
  "properties": {
    "gn:admin1_code":"13",
    "gn:asciiname":"Menderek",
    "gn:country_code":"IR",
    "gn:dem":1585,
    "gn:feature_class":"P",
    "gn:feature_code":"PPL",
    "gn:name":"Menderek",
    "gn:population":0,
    "gn:timezone":"Asia/Tehran",
    "iso:country":"IR",
    "name:fas_x_preferred":[
        "\u0645\u0646\u062f\u0631\u06a9"
    ],
    "name:und_x_variant":[
        "Manderek",
        "Mandrak",
        "Menderek"
    ],
    "wof:name":"Menderek",
    "wof:placetype":"locality"
},
  "geometry": {"coordinates":[46.9112,34.0124],"type":"Point"}
}