{
  "type": "Feature",
  "properties": {
    "gn:admin1_code":"16",
    "gn:asciiname":"Darreh Nakhi",
    "gn:country_code":"IR",
    "gn:dem":1271,
    "gn:feature_class":"P",
    "gn:feature_code":"PPL",
    "gn:name":"Darreh Nakh\u012b",
    "gn:population":0,
    "gn:timezone":"Asia/Tehran",
    "iso:country":"IR",
    "name:ceb_x_preferred":[
        "Darreh Nakh\u012b"
    ],
    "name:ckb_x_preferred":[
        "\u062f\u06d5\u0631\u06d5\u0646\u0627\u062e\u06ce"
    ],
    "name:fas_x_preferred":[
        "\u062f\u0631\u0647 \u0646\u0627\u062e\u06cc"
    ],
    "name:fas_x_variant":[
        "\u062f\u0631\u0651\u0647 \u0646\u062e\u06cc",
        "Darreh N\u0101kh\u012b",
        "Darreh Nakh\u012b"
    ],
    "name:swe_x_preferred":[
        "Darreh Nakh\u012b"
    ],
    "name:und_x_variant":[
        "Darreh N\u0101kheh",
        "Darreh-ye N\u0101kh\u012b"
    ],
    "wof:name":"Darreh Nakhi",
    "wof:placetype":"locality"
},
  "geometry": {"coordinates":[46.2355,35.3919],"type":"Point"}
}