{
  "type": "Feature",
  "properties": {
    "gn:admin1_code":"37.0",
    "gn:asciiname":"Gugol-e Bozorg",
    "gn:country_code":"IR",
    "gn:dem":361,
    "gn:feature_class":"P",
    "gn:feature_code":"PPL",
    "gn:name":"G\u016bgol-e Bozorg",
    "gn:population":0,
    "gn:timezone":"Asia/Tehran",
    "iso:country":"IR",
    "name:ceb_x_preferred":[
        "G\u016bgol-e Bozorg"
    ],
    "name:fas_x_preferred":[
        "G\u016bgol-e Bozorg"
    ],
    "name:fas_x_variant":[
        "\u06af\u06af\u0644 \u0628\u0632\u0631\u06af",
        "\u06af\u0648\u06af\u0644 \u0628\u0632\u0631\u06af"
    ],
    "name:msa_x_preferred":[
        "Gugol-e Bozorg"
    ],
    "name:swe_x_preferred":[
        "G\u016bgol-e Bozorg"
    ],
    "name:und_x_variant":[
        "Gogol-e Bozorg"
    ],
    "wof:name":"Gugol-e Bozorg",
    "wof:placetype":"locality"
},
  "geometry": {"coordinates":[55.70606,37.38721],"type":"Point"}
}