{
  "type": "Feature",
  "properties": {
    "gn:admin1_code":"8.0",
    "gn:asciiname":"Nokhowd Cheshmeh",
    "gn:country_code":"IR",
    "gn:dem":88,
    "gn:feature_class":"P",
    "gn:feature_code":"PPL",
    "gn:name":"Nokhowd Cheshmeh",
    "gn:population":0,
    "gn:timezone":"Asia/Tehran",
    "iso:country":"IR",
    "name:fas_x_preferred":[
        "\u0646\u062e\u0648\u062f \u0686\u0634\u0645\u0647"
    ],
    "wof:name":"Nokhowd Cheshmeh",
    "wof:placetype":"locality"
},
  "geometry": {"coordinates":[49.64267,37.06566],"type":"Point"}
}