{
  "type": "Feature",
  "properties": {
    "gn:admin1_code":"42",
    "gn:asciiname":"Akhangun",
    "gn:country_code":"IR",
    "gn:dem":1097,
    "gn:feature_class":"P",
    "gn:feature_code":"PPL",
    "gn:name":"Akhang\u016bn",
    "gn:population":0,
    "gn:timezone":"Asia/Tehran",
    "iso:country":"IR",
    "name:ceb_x_preferred":[
        "Akhang\u016bn"
    ],
    "name:fas_x_preferred":[
        "\u0627\u062e\u0646\u06af\u0648\u0646"
    ],
    "name:fas_x_variant":[
        "Akhang\u0101n",
        "Akhang\u016bn",
        "\u0627\u062e\u0646\u06af\u0627\u0646"
    ],
    "name:swe_x_preferred":[
        "Akhang\u016bn"
    ],
    "name:und_x_variant":[
        "Akhang\u016bl"
    ],
    "name:urd_x_preferred":[
        "\u0627\u062e\u0646\u06af\u0627\u0646"
    ],
    "wof:name":"Akhangun",
    "wof:placetype":"locality"
},
  "geometry": {"coordinates":[59.61819000000001,36.52117],"type":"Point"}
}