{
  "type": "Feature",
  "properties": {
    "gn:admin1_code":"35.0",
    "gn:asciiname":"Dunchal",
    "gn:country_code":"IR",
    "gn:dem":-17,
    "gn:feature_class":"P",
    "gn:feature_code":"PPL",
    "gn:name":"D\u016bnch\u0101l",
    "gn:population":0,
    "gn:timezone":"Asia/Tehran",
    "iso:country":"IR",
    "name:fas_x_preferred":[
        "\u062f\u0648\u0646\u0686\u0627\u0644"
    ],
    "name:fas_x_variant":[
        "D\u016bnch\u0101l",
        "\u062f\u0648\u0646\u200c\u0686\u0627\u0644"
    ],
    "wof:name":"Dunchal",
    "wof:placetype":"locality"
},
  "geometry": {"coordinates":[52.86268000000001,36.68449],"type":"Point"}
}