{
  "type": "Feature",
  "properties": {
    "gn:admin1_code":"36",
    "gn:asciiname":"Gilvan",
    "gn:country_code":"IR",
    "gn:dem":323,
    "gn:feature_class":"P",
    "gn:feature_code":"PPL",
    "gn:name":"G\u012blv\u0101n",
    "gn:population":0,
    "gn:timezone":"Asia/Tehran",
    "iso:country":"IR",
    "name:azb_x_preferred":[
        "\u06af\u06cc\u0644\u0648\u0627\u0646"
    ],
    "name:fas_x_preferred":[
        "\u0634\u064a\u0631 \u062f\u0634\u062a"
    ],
    "name:fas_x_variant":[
        "Sh\u012br Dasht",
        "\u06af\u06cc\u0644\u0648\u0627\u0646"
    ],
    "name:und_x_variant":[
        "G\u012blv\u0101n"
    ],
    "wof:name":"Gilvan",
    "wof:placetype":"locality"
},
  "geometry": {"coordinates":[49.13169,36.78431],"type":"Point"}
}