{
  "type": "Feature",
  "properties": {
    "gn:admin1_code":"35.0",
    "gn:asciiname":"Pordsar",
    "gn:country_code":"IR",
    "gn:dem":451,
    "gn:feature_class":"P",
    "gn:feature_code":"PPL",
    "gn:name":"Pordsar",
    "gn:population":0,
    "gn:timezone":"Asia/Tehran",
    "iso:country":"IR",
    "name:fas_x_preferred":[
        "\u067e\u0631\u062f\u0633\u0631"
    ],
    "name:und_x_variant":[
        "\u067e\u0631\u062f\u0633\u0631",
        "Pordsar"
    ],
    "wof:name":"Pordsar",
    "wof:placetype":"locality"
},
  "geometry": {"coordinates":[50.82816,36.6825],"type":"Point"}
}