{
  "type": "Feature",
  "properties": {
    "gn:admin1_code":"33",
    "gn:asciiname":"Qezeljeh",
    "gn:country_code":"IR",
    "gn:dem":1264,
    "gn:feature_class":"P",
    "gn:feature_code":"PPL",
    "gn:name":"Qezeljeh",
    "gn:population":0,
    "gn:timezone":"Asia/Tehran",
    "iso:country":"IR",
    "name:ceb_x_preferred":[
        "Qezeljeh"
    ],
    "name:fas_x_preferred":[
        "\u0642\u0632\u0644\u062c\u0647"
    ],
    "name:swe_x_preferred":[
        "Qezeljeh"
    ],
    "wof:name":"Qezeljeh",
    "wof:placetype":"locality"
},
  "geometry": {"coordinates":[47.9568,37.1758],"type":"Point"}
}