{
  "type": "Feature",
  "properties": {
    "gn:admin1_code":"29",
    "gn:asciiname":"Darb Asiab",
    "gn:country_code":"IR",
    "gn:dem":2368,
    "gn:feature_class":"P",
    "gn:feature_code":"PPL",
    "gn:name":"Darb \u0100s\u012b\u0101b",
    "gn:population":0,
    "gn:timezone":"Asia/Tehran",
    "iso:country":"IR",
    "name:fas_x_preferred":[
        "\u062f\u0631\u0628 \u0622\u0633\u06cc\u0627\u0628"
    ],
    "name:fas_x_variant":[
        "Darb \u0100s\u012b\u0101b",
        "Darb \u0100s\u012by\u0101b"
    ],
    "name:und_x_variant":[
        "Darb \u0100s\u012by\u0101b"
    ],
    "wof:name":"Darb Asiab",
    "wof:placetype":"locality"
},
  "geometry": {"coordinates":[57.18199,30.50174],"type":"Point"}
}