{
  "type": "Feature",
  "properties": {
    "gn:admin1_code":"35.0",
    "gn:asciiname":"Kowsar Deh",
    "gn:country_code":"IR",
    "gn:dem":1,
    "gn:feature_class":"P",
    "gn:feature_code":"PPL",
    "gn:name":"Kows\u0304ar Deh",
    "gn:population":0,
    "gn:timezone":"Asia/Tehran",
    "iso:country":"IR",
    "name:fas_x_preferred":[
        "\u0643\u064f\u0648\u062b\u064e\u0631 \u062f\u0650\u0647"
    ],
    "name:fas_x_variant":[
        "Kows\u0304ar Deh"
    ],
    "wof:name":"Kowsar Deh",
    "wof:placetype":"locality"
},
  "geometry": {"coordinates":[52.21667,36.53333],"type":"Point"}
}