{
  "type": "Feature",
  "properties": {
    "gn:admin1_code":"7",
    "gn:asciiname":"Abgarm",
    "gn:country_code":"IR",
    "gn:dem":1607,
    "gn:feature_class":"P",
    "gn:feature_code":"PPL",
    "gn:name":"\u0100bgarm",
    "gn:population":0,
    "gn:timezone":"Asia/Tehran",
    "iso:country":"IR",
    "name:fas_x_preferred":[
        "\u0100b Garm-e Bozorg"
    ],
    "name:fas_x_variant":[
        "\u0100bgarm",
        "\u0622\u0628\u06af\u0631\u0645"
    ],
    "name:und_x_variant":[
        "\u0622\u0628\u06af\u0631\u0645"
    ],
    "wof:name":"Abgarm",
    "wof:placetype":"locality"
},
  "geometry": {"coordinates":[52.68808000000001,29.99955],"type":"Point"}
}