{
  "type": "Feature",
  "properties": {
    "gn:admin1_code":"7",
    "gn:asciiname":"Abgarm",
    "gn:country_code":"IR",
    "gn:dem":1607,
    "gn:feature_class":"P",
    "gn:feature_code":"PPL",
    "gn:name":"\u0100bgarm",
    "gn:population":0,
    "gn:timezone":"Asia/Tehran",
    "iso:country":"IR",
    "name:ara_x_preferred":[
        "\u0623\u0628\u063a\u0631\u0645"
    ],
    "name:azb_x_preferred":[
        "\u0622\u0628\u06af\u0631\u0645"
    ],
    "name:aze_x_preferred":[
        "Abg\u0259rm"
    ],
    "name:ceb_x_preferred":[
        "\u0100bgarm"
    ],
    "name:fas_x_preferred":[
        "\u0100b Garm-e Bozorg"
    ],
    "name:fas_x_variant":[
        "\u0100bgarm",
        "\u0622\u0628\u06af\u0631\u0645"
    ],
    "name:ita_x_preferred":[
        "Ab Garm"
    ],
    "name:mlg_x_preferred":[
        "Abgarm"
    ],
    "name:pol_x_preferred":[
        "Abgarm"
    ],
    "name:tur_x_preferred":[
        "Abgerm"
    ],
    "name:und_x_variant":[
        "\u0622\u0628\u06af\u0631\u0645"
    ],
    "name:urd_x_preferred":[
        "\u0622\u0628\u06af\u0631\u0645"
    ],
    "wof:name":"Abgarm",
    "wof:placetype":"locality"
},
  "geometry": {"coordinates":[52.68808000000001,29.99955],"type":"Point"}
}