{
  "type": "Feature",
  "properties": {
    "gn:admin1_code":"33",
    "gn:asciiname":"Molk",
    "gn:country_code":"IR",
    "gn:dem":1607,
    "gn:feature_class":"P",
    "gn:feature_code":"PPL",
    "gn:name":"Molk",
    "gn:population":0,
    "gn:timezone":"Asia/Tehran",
    "iso:country":"IR",
    "name:ceb_x_preferred":[
        "Molk"
    ],
    "name:fas_x_preferred":[
        "\u0645\u0644\u06a9"
    ],
    "name:msa_x_preferred":[
        "Molk"
    ],
    "wof:name":"Molk",
    "wof:placetype":"locality"
},
  "geometry": {"coordinates":[47.9533,37.7449],"type":"Point"}
}