{
  "type": "Feature",
  "properties": {
    "gn:admin1_code":"23",
    "gn:asciiname":"Bahram Ju",
    "gn:country_code":"IR",
    "gn:dem":1250,
    "gn:feature_class":"P",
    "gn:feature_code":"PPL",
    "gn:name":"Bahr\u0101m J\u016b",
    "gn:population":0,
    "gn:timezone":"Asia/Tehran",
    "iso:country":"IR",
    "name:fas_x_preferred":[
        "\u0628\u0647\u0631\u0627\u0645 \u062d\u0648"
    ],
    "name:fas_x_variant":[
        "Bahr\u0101mj\u016b",
        "Bahr\u0101m \u1e28ow",
        "\u0628\u0647\u0631\u0627\u0645 \u062c\u0648"
    ],
    "name:und_x_variant":[
        "Bahr\u0101m \u1e28ow",
        "Bahr\u0101m J\u016b"
    ],
    "wof:name":"Bahram Ju",
    "wof:placetype":"locality"
},
  "geometry": {"coordinates":[48.2998,33.5691],"type":"Point"}
}