{
  "type": "Feature",
  "properties": {
    "gn:admin1_code":"5.0",
    "gn:asciiname":"Ben Tu",
    "gn:country_code":"IR",
    "gn:dem":1258,
    "gn:feature_class":"P",
    "gn:feature_code":"PPL",
    "gn:name":"Ben T\u016b",
    "gn:population":0,
    "gn:timezone":"Asia/Tehran",
    "iso:country":"IR",
    "name:fas_x_preferred":[
        "Ben T\u016b"
    ],
    "name:fas_x_variant":[
        "\u0628\u0646 \u062a\u0648"
    ],
    "name:und_x_variant":[
        "\u0628\u0646 \u062a\u0648"
    ],
    "wof:name":"Ben Tu",
    "wof:placetype":"locality"
},
  "geometry": {"coordinates":[50.53957,31.17331],"type":"Point"}
}