{
  "type": "Feature",
  "properties": {
    "gn:admin1_code":"4.0",
    "gn:asciiname":"Jangal-e Mukan",
    "gn:country_code":"IR",
    "gn:dem":1154,
    "gn:feature_class":"P",
    "gn:feature_code":"PPL",
    "gn:name":"Jangal-e M\u016bk\u0101n",
    "gn:population":0,
    "gn:timezone":"Asia/Tehran",
    "iso:country":"IR",
    "name:fas_x_preferred":[
        "\u062c\u0646\u06af\u0644 \u0645\u0648\u06a9\u0627\u0646"
    ],
    "name:fas_x_variant":[
        "Jangal-e M\u016bk\u0101n"
    ],
    "name:urd_x_preferred":[
        "\u062c\u0646\u06af\u0644 \u0645\u0648\u06a9\u0627\u0646"
    ],
    "wof:name":"Jangal-e Mukan",
    "wof:placetype":"locality"
},
  "geometry": {"coordinates":[61.00128,27.57352],"type":"Point"}
}