{
  "type": "Feature",
  "properties": {
    "gn:admin1_code":"34",
    "gn:asciiname":"Hajjiabad",
    "gn:country_code":"IR",
    "gn:dem":1811,
    "gn:feature_class":"P",
    "gn:feature_code":"PPL",
    "gn:name":"\u1e28\u0101jj\u012b\u0101b\u0101d",
    "gn:population":0,
    "gn:timezone":"Asia/Tehran",
    "iso:country":"IR",
    "name:aze_x_preferred":[
        "Hac\u0131abad"
    ],
    "name:ceb_x_preferred":[
        "Hajjiabad"
    ],
    "name:fas_x_preferred":[
        "\u1e28\u0101jj\u012b\u0101b\u0101d"
    ],
    "name:fas_x_variant":[
        "\u1e28aq Verd\u012b",
        "\u062d\u0627\u062c\u06cc \u0622\u0628\u0627\u062f",
        "\u062d\u0642 \u0648\u0631\u062f\u06cc",
        "\u062d\u0627\u062c\u06cc\u200c\u0622\u0628\u0627\u062f"
    ],
    "name:mzn_x_preferred":[
        "\u062d\u0627\u062c\u06cc\u200c\u0622\u0628\u0627\u062f"
    ],
    "name:rus_x_preferred":[
        "\u0425\u0430\u0434\u0436\u0438\u0430\u0431\u0430\u0434"
    ],
    "name:swe_x_preferred":[
        "Hajjiabad"
    ],
    "wof:name":"Hajjiabad",
    "wof:placetype":"locality"
},
  "geometry": {"coordinates":[50.06086,33.65154],"type":"Point"}
}