{
  "type": "Feature",
  "properties": {
    "gn:admin1_code":"41",
    "gn:asciiname":"Kharu-ye Sofla",
    "gn:country_code":"IR",
    "gn:dem":1338,
    "gn:feature_class":"P",
    "gn:feature_code":"PPLF",
    "gn:name":"Khar\u016b-ye Sofl\u00e1",
    "gn:population":0,
    "gn:timezone":"Asia/Tehran",
    "iso:country":"IR",
    "name:fas_x_preferred":[
        "Kharv-e P\u0101\u2019\u012bn"
    ],
    "name:fas_x_variant":[
        "\u062e\u0631\u0648 \u0633\u0641\u0644\u06cc"
    ],
    "name:und_x_variant":[
        "Khar\u016b-ye Sofl\u00e1"
    ],
    "wof:name":"Kharu-ye Sofla",
    "wof:placetype":"locality"
},
  "geometry": {"coordinates":[57.15534,33.63936],"type":"Point"}
}