{
  "type": "Feature",
  "properties": {
    "gn:admin1_code":"1",
    "gn:asciiname":"Julfa",
    "gn:cc2":"IR",
    "gn:country_code":"IR",
    "gn:dem":704,
    "gn:feature_class":"P",
    "gn:feature_code":"PPL",
    "gn:name":"Julfa",
    "gn:population":0,
    "gn:timezone":"Asia/Tehran",
    "iso:country":"IR",
    "name:aze_x_historical":[
        "Culfa"
    ],
    "name:aze_x_preferred":[
        "Culfa"
    ],
    "name:eng_x_preferred":[
        "Julfa"
    ],
    "name:fas_x_preferred":[
        "Jolf\u0101"
    ],
    "name:fas_x_variant":[
        "\u062c\u064f\u0644\u0641\u0627"
    ],
    "name:und_x_variant":[
        "Dzhulfi"
    ],
    "wof:name":"Julfa",
    "wof:placetype":"locality"
},
  "geometry": {"coordinates":[45.63329,38.93788],"type":"Point"}
}