{
  "type": "Feature",
  "properties": {
    "gn:admin1_code":"13",
    "gn:asciiname":"Kamicheh",
    "gn:country_code":"IR",
    "gn:dem":1325,
    "gn:feature_class":"P",
    "gn:feature_code":"PPL",
    "gn:name":"Kam\u012bcheh",
    "gn:population":0,
    "gn:timezone":"Asia/Tehran",
    "iso:country":"IR",
    "name:fas_x_preferred":[
        "\u06a9\u0645\u06cc\u0686\u0647"
    ],
    "name:fas_x_variant":[
        "Kam\u012bjeh",
        "Kam\u012bcheh"
    ],
    "wof:name":"Kamicheh",
    "wof:placetype":"locality"
},
  "geometry": {"coordinates":[47.368,34.5194],"type":"Point"}
}