{
  "type": "Feature",
  "properties": {
    "gn:admin1_code":"8",
    "gn:asciiname":"Feshtam",
    "gn:country_code":"IR",
    "gn:dem":44,
    "gn:feature_class":"P",
    "gn:feature_code":"PPL",
    "gn:name":"Fesht\u0101m",
    "gn:population":0,
    "gn:timezone":"Asia/Tehran",
    "iso:country":"IR",
    "name:fas_x_preferred":[
        "Fesht\u0101m-e P\u0101\u2019\u012bn Ma\u1e29alleh"
    ],
    "name:fas_x_variant":[
        "\u0641\u0634\u062a\u0627\u0645",
        "\u0641\u06cc\u0634\u062f\u0627\u0645",
        "\u0641\u062e\u0631\u0622\u0628\u0627\u062f"
    ],
    "name:msa_x_preferred":[
        "Fakhrabad"
    ],
    "name:ukr_x_preferred":[
        "\u0424\u0430\u0445\u0440\u0430\u0431\u0430\u0434"
    ],
    "name:und_x_variant":[
        "Fesht\u0101m",
        "F\u012bshd\u0101m"
    ],
    "wof:name":"Feshtam",
    "wof:placetype":"locality"
},
  "geometry": {"coordinates":[49.65503,37.15879],"type":"Point"}
}