{
  "type": "Feature",
  "properties": {
    "gn:admin1_code":"42",
    "gn:asciiname":"Kalateh-ye Chah Bahrami",
    "gn:country_code":"IR",
    "gn:dem":934,
    "gn:feature_class":"P",
    "gn:feature_code":"PPL",
    "gn:name":"Kal\u0101teh-ye Ch\u0101h Bahr\u0101m\u012b",
    "gn:population":0,
    "gn:timezone":"Asia/Tehran",
    "iso:country":"IR",
    "name:fas_x_preferred":[
        "Bahr\u0101m\u012b"
    ],
    "name:fas_x_variant":[
        "\u06a9\u0644\u0627\u062a\u0647 \u0686\u0627\u0647 \u0628\u0647\u0631\u0627\u0645\u06cc"
    ],
    "name:und_x_variant":[
        "Kal\u0101teh-ye Ch\u0101h Bahr\u0101m\u012b"
    ],
    "wof:name":"Kalateh-ye Chah Bahrami",
    "wof:placetype":"locality"
},
  "geometry": {"coordinates":[57.97841999999999,34.61383],"type":"Point"}
}