{
  "type": "Feature",
  "properties": {
    "gn:admin1_code":"7",
    "gn:asciiname":"Charmur",
    "gn:country_code":"IR",
    "gn:dem":1945,
    "gn:feature_class":"P",
    "gn:feature_code":"PPL",
    "gn:name":"Ch\u0101rm\u016br",
    "gn:population":0,
    "gn:timezone":"Asia/Tehran",
    "iso:country":"IR",
    "name:fas_x_preferred":[
        "\u0686\u0647\u0627\u0631 \u0645\u0631"
    ],
    "name:fas_x_variant":[
        "Chah\u0101r M\u016br",
        "Chah\u0101r Mor",
        "\u0686\u0627\u0631\u0645\u0648\u0631",
        "\u0686\u0647\u0627\u0631 \u0645\u0648\u0631",
        "\u0686\u0647\u0627\u0631\u0645\u0648\u0631"
    ],
    "name:msa_x_preferred":[
        "Chahar Mur"
    ],
    "name:und_x_variant":[
        "\u1e28\u0101jj\u012b B\u0101n\u012b",
        "Ch\u0101rm\u016br"
    ],
    "wof:name":"Charmur",
    "wof:placetype":"locality"
},
  "geometry": {"coordinates":[52.0879,30.0646],"type":"Point"}
}