{
  "type": "Feature",
  "properties": {
    "gn:admin1_code":"7",
    "gn:asciiname":"Khowrdeh Darreh",
    "gn:country_code":"IR",
    "gn:dem":808,
    "gn:feature_class":"P",
    "gn:feature_code":"PPL",
    "gn:name":"Khowrdeh Darreh",
    "gn:population":0,
    "gn:timezone":"Asia/Tehran",
    "iso:country":"IR",
    "name:fas_x_preferred":[
        "\u0628\u0631\u06a9\u0647 \u0633\u0641\u06cc\u062f"
    ],
    "name:fas_x_variant":[
        "Berkeh-ye Sef\u012bd",
        "\u062e\u0648\u0631\u062f\u0647 \u062f\u0631\u0647"
    ],
    "wof:name":"Khowrdeh Darreh",
    "wof:placetype":"locality"
},
  "geometry": {"coordinates":[53.4052,28.2674],"type":"Point"}
}