{
  "type": "Feature",
  "properties": {
    "gn:admin1_code":"4.0",
    "gn:asciiname":"Khan Mohammad",
    "gn:country_code":"IR",
    "gn:dem":482,
    "gn:feature_class":"P",
    "gn:feature_code":"PPL",
    "gn:name":"Kh\u0101n Mo\u1e29ammad",
    "gn:population":0,
    "gn:timezone":"Asia/Tehran",
    "iso:country":"IR",
    "name:fas_x_preferred":[
        "\u062e\u0627\u0646 \u0645\u062d\u0645\u0651\u062f"
    ],
    "name:fas_x_variant":[
        "Kh\u0101n Mo\u1e29ammad",
        "\u062e\u0627\u0646 \u0645\u062d\u0645\u062f"
    ],
    "wof:name":"Khan Mohammad",
    "wof:placetype":"locality"
},
  "geometry": {"coordinates":[61.74698000000001,31.14369000000001],"type":"Point"}
}