{
  "type": "Feature",
  "properties": {
    "gn:admin1_code":"5",
    "gn:asciiname":"Deli Pir Mahmud",
    "gn:country_code":"IR",
    "gn:dem":834,
    "gn:feature_class":"P",
    "gn:feature_code":"PPL",
    "gn:name":"Del\u012b P\u012br Ma\u1e29m\u016bd",
    "gn:population":0,
    "gn:timezone":"Asia/Tehran",
    "iso:country":"IR",
    "name:fas_x_preferred":[
        "\u062f\u0650\u0644\u06cc \u067e\u064a\u0631 \u0645\u064e\u062d\u0645\u0648\u062f\u0650 \u0633\u064f\u0641\u0644\u064e\u0649"
    ],
    "name:fas_x_variant":[
        "\u062f\u064e\u0644\u06cc \u067e\u064a\u0631 \u0645\u064e\u062d\u0645\u0648\u062f",
        "Del\u012b P\u012br Ma\u1e29m\u016bd",
        "Del\u012b P\u012br Ma\u1e29m\u016bd-e Sofl\u00e1",
        "\u062f\u0644\u06cc \u067e\u064a\u0631 \u0645\u062d\u0645\u0648\u062f"
    ],
    "name:und_x_variant":[
        "Dal\u012b P\u012br Ma\u1e29m\u016bd",
        "Deli Pir Ma\u1e29mud",
        "\u062f\u0644\u06cc \u067e\u064a\u0631 \u0645\u062d\u0645\u0648\u062f"
    ],
    "wof:name":"Deli Pir Mahmud",
    "wof:placetype":"locality"
},
  "geometry": {"coordinates":[50.70201,30.84314],"type":"Point"}
}