{
  "type": "Feature",
  "properties": {
    "gn:admin1_code":"42",
    "gn:asciiname":"Rasan",
    "gn:country_code":"IR",
    "gn:dem":893,
    "gn:feature_class":"P",
    "gn:feature_code":"PPL",
    "gn:name":"Rasan",
    "gn:population":0,
    "gn:timezone":"Asia/Tehran",
    "iso:country":"IR",
    "name:fas_x_preferred":[
        "\u0631\u0633\u0646"
    ],
    "name:und_x_variant":[
        "\u0631\u0633\u0646"
    ],
    "wof:name":"Rasan",
    "wof:placetype":"locality"
},
  "geometry": {"coordinates":[57.24361999999999,35.15999],"type":"Point"}
}