{
  "type": "Feature",
  "properties": {
    "gn:admin1_code":"23",
    "gn:asciiname":"Papol",
    "gn:country_code":"IR",
    "gn:dem":1011,
    "gn:feature_class":"P",
    "gn:feature_code":"PPL",
    "gn:name":"P\u0101pol",
    "gn:population":0,
    "gn:timezone":"Asia/Tehran",
    "iso:country":"IR",
    "name:fas_x_preferred":[
        "\u067e\u0627\u067e\u0644"
    ],
    "name:fas_x_variant":[
        "P\u0101pol"
    ],
    "wof:name":"Papol",
    "wof:placetype":"locality"
},
  "geometry": {"coordinates":[47.88028,33.58835],"type":"Point"}
}