{
  "type": "Feature",
  "properties": {
    "gn:admin1_code":"34",
    "gn:asciiname":"Siah Soltan",
    "gn:country_code":"IR",
    "gn:dem":2252,
    "gn:feature_class":"P",
    "gn:feature_code":"PPL",
    "gn:name":"S\u012b\u0101h Sol\u0163\u0101n",
    "gn:population":0,
    "gn:timezone":"Asia/Tehran",
    "iso:country":"IR",
    "name:fas_x_preferred":[
        "\u0633\u06cc\u0627\u0647 \u0633\u0644\u0637\u0627\u0646"
    ],
    "name:fas_x_variant":[
        "S\u012b\u0101h Sol\u0163\u0101n"
    ],
    "name:und_x_variant":[
        "Sey\u0101h Sol\u0163\u0101n",
        "S\u012b\u0101 Sol\u0163\u0101n",
        "Mia Sult\u0101n",
        "M\u012b\u0101 Sol\u0163\u0101n"
    ],
    "wof:name":"Siah Soltan",
    "wof:placetype":"locality"
},
  "geometry": {"coordinates":[49.34362,33.74086],"type":"Point"}
}