{
  "type": "Feature",
  "properties": {
    "gn:admin1_code":"41",
    "gn:asciiname":"Yekkeh Chah",
    "gn:country_code":"IR",
    "gn:dem":1913,
    "gn:feature_class":"P",
    "gn:feature_code":"PPL",
    "gn:name":"Yekkeh Ch\u0101h",
    "gn:population":0,
    "gn:timezone":"Asia/Tehran",
    "iso:country":"IR",
    "name:fas_x_preferred":[
        "\u0633\u0631\u062e \u06a9\u0648\u0647"
    ],
    "name:fas_x_variant":[
        "Sorkh K\u016bh",
        "\u06cc\u06a9\u0647 \u0686\u0627\u0647"
    ],
    "name:und_x_variant":[
        "Yekkeh Ch\u0101h"
    ],
    "wof:name":"Yekkeh Chah",
    "wof:placetype":"locality"
},
  "geometry": {"coordinates":[59.70686,31.87457],"type":"Point"}
}