{
  "type": "Feature",
  "properties": {
    "gn:admin1_code":"29",
    "gn:asciiname":"Sekonj",
    "gn:country_code":"IR",
    "gn:dem":2298,
    "gn:feature_class":"P",
    "gn:feature_code":"PPL",
    "gn:name":"Sekonj",
    "gn:population":0,
    "gn:timezone":"Asia/Tehran",
    "iso:country":"IR",
    "name:fas_x_preferred":[
        "\u0633\u06a9\u0646\u062c"
    ],
    "name:fas_x_variant":[
        "\u0633\u0647\u200c\u06a9\u0646\u062c"
    ],
    "name:und_x_variant":[
        "Tawakkul\u0101b\u0101d",
        "Sekonj",
        "Sheykh \u2018Al\u012b B\u0101b\u0101",
        "Seh Konj",
        "Seh G\u016bsh",
        "Segach",
        "Sag\u016bch",
        "\u1e28ojjat\u0101b\u0101d"
    ],
    "wof:name":"Sekonj",
    "wof:placetype":"locality"
},
  "geometry": {"coordinates":[57.4222,29.99523],"type":"Point"}
}