{
  "type": "Feature",
  "properties": {
    "gn:admin1_code":"4.0",
    "gn:asciiname":"Jama Zehi",
    "gn:country_code":"IR",
    "gn:dem":26,
    "gn:feature_class":"P",
    "gn:feature_code":"PPL",
    "gn:name":"Jam\u0101 Zeh\u012b",
    "gn:population":0,
    "gn:timezone":"Asia/Tehran",
    "iso:country":"IR",
    "name:ara_x_preferred":[
        "\u062c\u0645\u0627 \u0632\u0647\u064a"
    ],
    "name:fas_x_preferred":[
        "Jamm\u0101z\u012b"
    ],
    "name:fas_x_variant":[
        "Jam\u0101 Zeh\u012b",
        "\u062c\u0645\u0627 \u0632\u0647\u06cc"
    ],
    "name:und_x_variant":[
        "Jam\u0101\u2018at Z\u0101\u2019\u012b",
        "Jomm\u0101z\u012b",
        "Jam\u0101\u2018at Zeh\u012b"
    ],
    "name:urd_x_preferred":[
        "\u062c\u0645\u0627 \u0632\u06c1\u06cc"
    ],
    "wof:name":"Jama Zehi",
    "wof:placetype":"locality"
},
  "geometry": {"coordinates":[61.15635,25.62619],"type":"Point"}
}