{
  "type": "Feature",
  "properties": {
    "gn:admin1_code":"4",
    "gn:asciiname":"Bandar-e Tang",
    "gn:country_code":"IR",
    "gn:dem":6,
    "gn:feature_class":"P",
    "gn:feature_code":"PPL",
    "gn:name":"Bandar-e Tang",
    "gn:population":0,
    "gn:timezone":"Asia/Tehran",
    "iso:country":"IR",
    "name:fas_x_preferred":[
        "\u0628\u0646\u062f\u0631 \u062a\u0646\u06af"
    ],
    "name:fas_x_variant":[
        "\u0628\u0646\u062f\u0631\u062a\u0646\u06af"
    ],
    "name:und_x_variant":[
        "Tang",
        "Bandar Tang",
        "T\u0101nk",
        "Bandar-e Tank",
        "Bandar T\u0101nk",
        "Bandar-e Tang",
        "\u0628\u0646\u062f\u0631 \u062a\u0646\u06af"
    ],
    "wof:name":"Bandar-e Tang",
    "wof:placetype":"locality"
},
  "geometry": {"coordinates":[59.89044000000001,25.36056],"type":"Point"}
}