{
  "type": "Feature",
  "properties": {
    "gn:admin1_code":"5",
    "gn:asciiname":"Delibaj-e Bala",
    "gn:country_code":"IR",
    "gn:dem":1972,
    "gn:feature_class":"P",
    "gn:feature_code":"PPL",
    "gn:name":"Del\u012bbaj-e B\u0101l\u0101",
    "gn:population":0,
    "gn:timezone":"Asia/Tehran",
    "iso:country":"IR",
    "name:fas_x_preferred":[
        "\u062f\u0650\u0644\u064a\u0628\u064e\u062c\u0650 \u0628\u0627\u0644\u0627"
    ],
    "name:fas_x_variant":[
        "Del\u012bbaj-e B\u0101l\u0101"
    ],
    "wof:name":"Delibaj-e Bala",
    "wof:placetype":"locality"
},
  "geometry": {"coordinates":[51.19306,30.96306],"type":"Point"}
}