{
  "type": "Feature",
  "properties": {
    "gn:admin1_code":"33",
    "gn:asciiname":"Mizanu",
    "gn:country_code":"IR",
    "gn:dem":707,
    "gn:feature_class":"P",
    "gn:feature_code":"PPL",
    "gn:name":"M\u012bz\u0101n\u016b",
    "gn:population":0,
    "gn:timezone":"Asia/Tehran",
    "iso:country":"IR",
    "name:ara_x_preferred":[
        "\u0648\u064a\u0632\u0627\u0646\u0627\u0628"
    ],
    "name:azb_x_preferred":[
        "\u0648\u06cc\u0632\u0646\u0627\u0628"
    ],
    "name:ceb_x_preferred":[
        "M\u012bz\u0101n\u016b"
    ],
    "name:fas_x_preferred":[
        "\u0645\u06cc\u0632\u0627\u0646\u0648"
    ],
    "name:fas_x_variant":[
        "M\u012bz\u0101n\u016b"
    ],
    "name:msa_x_preferred":[
        "Vizanab"
    ],
    "name:swe_x_preferred":[
        "M\u012bz\u0101n\u016b"
    ],
    "wof:name":"Mizanu",
    "wof:placetype":"locality"
},
  "geometry": {"coordinates":[47.5094,38.815],"type":"Point"}
}