{
  "type": "Feature",
  "properties": {
    "gn:admin1_code":"3.0",
    "gn:asciiname":"Badam Shirindan",
    "gn:country_code":"IR",
    "gn:dem":1500,
    "gn:feature_class":"P",
    "gn:feature_code":"PPL",
    "gn:name":"B\u0101d\u0101m Sh\u012br\u012bnd\u0101n",
    "gn:population":0,
    "gn:timezone":"Asia/Tehran",
    "iso:country":"IR",
    "name:fas_x_preferred":[
        "\u0628\u0627\u062f\u0627\u0645 \u0634\u064a\u0631\u064a\u0646"
    ],
    "name:fas_x_variant":[
        "B\u0101d\u0101m Sh\u012br\u012bnd\u0101n",
        "\u0628\u0627\u062f\u0627\u0645 \u0634\u064a\u0631\u064a\u0646\u062f\u0627\u0646"
    ],
    "name:und_x_variant":[
        "B\u0101d\u0101m Sh\u012br\u012bn",
        "\u0628\u0627\u062f\u0627\u0645 \u0634\u064a\u0631\u064a\u0646\u062f\u0627\u0646"
    ],
    "wof:name":"Badam Shirindan",
    "wof:placetype":"locality"
},
  "geometry": {"coordinates":[50.15472000000001,32.0525],"type":"Point"}
}