{
  "type": "Feature",
  "properties": {
    "gn:admin1_code":"32",
    "gn:asciiname":"Qal`eh Juq",
    "gn:country_code":"IR",
    "gn:dem":1736,
    "gn:feature_class":"P",
    "gn:feature_code":"PPL",
    "gn:name":"Qal\u2018eh J\u016bq",
    "gn:population":0,
    "gn:timezone":"Asia/Tehran",
    "iso:country":"IR",
    "name:fas_x_preferred":[
        "\u0642\u0644\u0639\u0647 \u062c\u0648\u0642"
    ],
    "name:fas_x_variant":[
        "Qal\u2018eh Jaq",
        "Qal\u2018eh J\u016bq"
    ],
    "name:und_x_variant":[
        "Kalandzhik",
        "Qal\u2018eh J\u012bk",
        "Kalanjik"
    ],
    "wof:name":"Qal`eh Juq",
    "wof:placetype":"locality"
},
  "geometry": {"coordinates":[48.28526,37.91986],"type":"Point"}
}