{
  "type": "Feature",
  "properties": {
    "gn:admin1_code":"13",
    "gn:asciiname":"Bansulab-e Shirzad",
    "gn:country_code":"IR",
    "gn:dem":1302,
    "gn:feature_class":"P",
    "gn:feature_code":"PPL",
    "gn:name":"B\u0101ns\u016bl\u0101b-e Sh\u012brz\u0101d",
    "gn:population":0,
    "gn:timezone":"Asia/Tehran",
    "iso:country":"IR",
    "name:ara_x_preferred":[
        "\u0628\u0627\u0646\u200c\u0633\u0648\u0644\u0627\u0628 \u0634\u064a\u0631\u0632\u0627\u062f"
    ],
    "name:fas_x_preferred":[
        "\u0628\u0627\u0646\u0633\u0648\u0644\u0627\u0628 \u0634\u064a\u0631\u0632\u0627\u062f"
    ],
    "name:fas_x_variant":[
        "B\u0101n S\u016bleh-ye Sh\u012brz\u0101d",
        "B\u0101ns\u016bl\u0101b-e Sh\u012brz\u0101d",
        "\u0628\u0627\u0646\u200c\u0633\u0648\u0644\u0627\u0628 \u0634\u06cc\u0631\u0632\u0627\u062f"
    ],
    "name:und_x_variant":[
        "Kotak Bozorg"
    ],
    "wof:name":"Bansulab-e Shirzad",
    "wof:placetype":"locality"
},
  "geometry": {"coordinates":[46.3779,34.5178],"type":"Point"}
}