{
  "type": "Feature",
  "properties": {
    "gn:admin1_code":"42",
    "gn:asciiname":"Khanik",
    "gn:country_code":"IR",
    "gn:dem":1309,
    "gn:feature_class":"P",
    "gn:feature_code":"PPL",
    "gn:name":"Kh\u0101n\u012bk",
    "gn:population":0,
    "gn:timezone":"Asia/Tehran",
    "iso:country":"IR",
    "name:ara_x_preferred":[
        "\u064a\u063a\u064a"
    ],
    "name:ceb_x_preferred":[
        "Kh\u0101n\u012bk"
    ],
    "name:fas_x_preferred":[
        "Yeg\u012b"
    ],
    "name:fas_x_variant":[
        "\u06cc\u06af\u06cc",
        "\u062e\u0627\u0646\u06cc\u06a9"
    ],
    "name:swe_x_preferred":[
        "Kh\u0101n\u012bk"
    ],
    "name:und_x_variant":[
        "\u06cc\u06af\u06cc",
        "Kh\u0101n\u012bk"
    ],
    "name:urd_x_preferred":[
        "\u06cc\u06af\u06cc"
    ],
    "wof:name":"Khanik",
    "wof:placetype":"locality"
},
  "geometry": {"coordinates":[57.24179,33.80106],"type":"Point"}
}