{
  "type": "Feature",
  "properties": {
    "gn:admin1_code":"36",
    "gn:asciiname":"Qorqan `Olya",
    "gn:country_code":"IR",
    "gn:dem":1905,
    "gn:feature_class":"P",
    "gn:feature_code":"PPL",
    "gn:name":"Qorq\u0101n \u2018Oly\u0101",
    "gn:population":0,
    "gn:timezone":"Asia/Tehran",
    "iso:country":"IR",
    "name:azb_x_preferred":[
        "\u0642\u0631\u0642\u0627\u0646 \u0639\u0644\u06cc\u0627"
    ],
    "name:fas_x_preferred":[
        "\u0642\u0648\u0631\u0642\u0627\u0646 \u0639\u0644\u064a\u0627"
    ],
    "name:fas_x_variant":[
        "Qarq\u0101n-e \u2018Oly\u0101",
        "Q\u016brq\u0101n-e \u2018Oly\u0101",
        "\u0642\u0631\u0642\u0627\u0646 \u0639\u0644\u06cc\u0627"
    ],
    "name:und_x_variant":[
        "Qorq\u0101n \u2018Oly\u0101"
    ],
    "wof:name":"Qorqan `Olya",
    "wof:placetype":"locality"
},
  "geometry": {"coordinates":[47.6374,36.39962],"type":"Point"}
}