{
  "type": "Feature",
  "properties": {
    "gn:admin1_code":"9",
    "gn:asciiname":"Mokarrabi",
    "gn:country_code":"IR",
    "gn:dem":2174,
    "gn:feature_class":"P",
    "gn:feature_code":"PPL",
    "gn:name":"Mokarrab\u012b",
    "gn:population":0,
    "gn:timezone":"Asia/Tehran",
    "iso:country":"IR",
    "name:fas_x_preferred":[
        "Mokarrab\u012b"
    ],
    "name:fas_x_variant":[
        "\u0645\u06a9\u0631\u0628\u06cc"
    ],
    "name:msa_x_preferred":[
        "Mokarrabi"
    ],
    "name:und_x_variant":[
        "Makrebi Asdollah Khan",
        "Mokarreb\u012b"
    ],
    "wof:name":"Mokarrabi",
    "wof:placetype":"locality"
},
  "geometry": {"coordinates":[48.69784,34.6253],"type":"Point"}
}