{
  "type": "Feature",
  "properties": {
    "gn:admin1_code":"29",
    "gn:asciiname":"Bidu'iyeh",
    "gn:country_code":"IR",
    "gn:dem":2580,
    "gn:feature_class":"P",
    "gn:feature_code":"PPL",
    "gn:name":"B\u012bd\u016b\u2019\u012byeh",
    "gn:population":0,
    "gn:timezone":"Asia/Tehran",
    "iso:country":"IR",
    "name:fas_x_preferred":[
        "\u0628\u06cc\u062f\u0648\u0626\u06cc\u0647"
    ],
    "name:fas_x_variant":[
        "B\u012bd\u016b\u2019\u012byeh"
    ],
    "wof:name":"Bidu'iyeh",
    "wof:placetype":"locality"
},
  "geometry": {"coordinates":[57.18524,30.51483],"type":"Point"}
}