{
  "type": "Feature",
  "properties": {
    "gn:admin1_code":"1",
    "gn:asciiname":"Mirdavud",
    "gn:country_code":"IR",
    "gn:dem":1434,
    "gn:feature_class":"P",
    "gn:feature_code":"PPL",
    "gn:name":"M\u012brd\u0101v\u016bd",
    "gn:population":0,
    "gn:timezone":"Asia/Tehran",
    "iso:country":"IR",
    "name:aze_x_preferred":[
        "Mirdavud"
    ],
    "name:fas_x_preferred":[
        "\u0645\u06cc\u0631\u062f\u0627\u0648\u0648\u062f"
    ],
    "name:fas_x_variant":[
        "M\u012brd\u0101v\u016bd",
        "\u0645\u06cc\u0631\u062f\u0627\u0648\u062f"
    ],
    "name:msa_x_preferred":[
        "Mirdavud"
    ],
    "wof:name":"Mirdavud",
    "wof:placetype":"locality"
},
  "geometry": {"coordinates":[44.8228,37.6723],"type":"Point"}
}