{
  "type": "Feature",
  "properties": {
    "gn:admin1_code":"32.0",
    "gn:asciiname":"Lajayer",
    "gn:country_code":"IR",
    "gn:dem":1021,
    "gn:feature_class":"P",
    "gn:feature_code":"PPL",
    "gn:name":"Laj\u0101yer",
    "gn:population":0,
    "gn:timezone":"Asia/Tehran",
    "iso:country":"IR",
    "name:ara_x_preferred":[
        "\u0644\u062c\u0627\u064a\u0631"
    ],
    "name:azb_x_preferred":[
        "\u0644\u062c\u0627\u06cc\u06cc\u0631"
    ],
    "name:fas_x_preferred":[
        "\u0644\u064e\u062c\u0627\u064a\u0650\u0631"
    ],
    "name:fas_x_variant":[
        "Laj\u0101yer",
        "\u0644\u062c\u0627\u06cc\u0631"
    ],
    "name:msa_x_preferred":[
        "Lajayer"
    ],
    "name:urd_x_preferred":[
        "\u0644\u0627\u062e\u0627\u0626\u0631"
    ],
    "wof:name":"Lajayer",
    "wof:placetype":"locality"
},
  "geometry": {"coordinates":[48.23889000000001,38.96694],"type":"Point"}
}