{
  "type": "Feature",
  "properties": {
    "gn:admin1_code":"33",
    "gn:asciiname":"Marjanlu",
    "gn:country_code":"IR",
    "gn:dem":1287,
    "gn:feature_class":"P",
    "gn:feature_code":"PPL",
    "gn:name":"Marj\u0101nl\u016b",
    "gn:population":0,
    "gn:timezone":"Asia/Tehran",
    "iso:country":"IR",
    "name:ceb_x_preferred":[
        "Marj\u0101nl\u016b"
    ],
    "name:fas_x_preferred":[
        "\u0645\u0631\u062c\u0627\u0646\u0644\u0648"
    ],
    "name:fas_x_variant":[
        "M\u012brj\u0101nl\u016b",
        "Marj\u0101nl\u016b"
    ],
    "name:msa_x_preferred":[
        "Marjanlu"
    ],
    "name:swe_x_preferred":[
        "Marj\u0101nl\u016b"
    ],
    "wof:name":"Marjanlu",
    "wof:placetype":"locality"
},
  "geometry": {"coordinates":[45.913,37.9423],"type":"Point"}
}