{
  "type": "Feature",
  "properties": {
    "gn:admin1_code":"4.0",
    "gn:asciiname":"Anjereh",
    "gn:country_code":"IR",
    "gn:dem":1415,
    "gn:feature_class":"P",
    "gn:feature_code":"PPL",
    "gn:name":"Anjereh",
    "gn:population":0,
    "gn:timezone":"Asia/Tehran",
    "iso:country":"IR",
    "name:fas_x_preferred":[
        "\u0627\u0646\u062c\u0631\u0647"
    ],
    "name:fas_x_variant":[
        "Anj\u012breh"
    ],
    "name:und_x_variant":[
        "Anjareh",
        "Anjerah",
        "Anjereh"
    ],
    "wof:name":"Anjereh",
    "wof:placetype":"locality"
},
  "geometry": {"coordinates":[61.24465,28.82961],"type":"Point"}
}