{
  "type": "Feature",
  "properties": {
    "gn:admin1_code":"40",
    "gn:asciiname":"Chah Kuh Birin",
    "gn:country_code":"IR",
    "gn:dem":1786,
    "gn:feature_class":"P",
    "gn:feature_code":"PPL",
    "gn:name":"Ch\u0101h K\u016bh B\u012br\u012bn",
    "gn:population":0,
    "gn:timezone":"Asia/Tehran",
    "iso:country":"IR",
    "name:fas_x_preferred":[
        "\u0686\u0627\u0647 \u0643\u0648\u0647 \u0628\u064a\u0631\u064a\u0646"
    ],
    "name:fas_x_variant":[
        "Ch\u0101h K\u016bh B\u012br\u012bn"
    ],
    "wof:name":"Chah Kuh Birin",
    "wof:placetype":"locality"
},
  "geometry": {"coordinates":[53.47833000000001,31.64278],"type":"Point"}
}