{
  "type": "Feature",
  "properties": {
    "gn:admin1_code":"35",
    "gn:asciiname":"Bala Bandar Kheyl",
    "gn:country_code":"IR",
    "gn:dem":21,
    "gn:feature_class":"P",
    "gn:feature_code":"PPL",
    "gn:name":"B\u0101l\u0101 Band\u0101r Kheyl",
    "gn:population":0,
    "gn:timezone":"Asia/Tehran",
    "iso:country":"IR",
    "name:fas_x_preferred":[
        "\u0628\u064e\u0646\u062f\u0627\u0631 \u062e\u0650\u064a\u0644"
    ],
    "name:fas_x_variant":[
        "B\u0101l\u0101 Band\u0101r Kheyl",
        "Band\u0101r Kheyl",
        "Pend\u0101r Kheyl",
        "\u067e\u0650\u0646\u062f\u0627\u0631 \u062e\u0650\u064a\u0644",
        "\u0628\u0627\u0644\u0627 \u0628\u0646\u062f\u0627\u0631 \u062e\u064a\u0644",
        "\u0628\u0646\u062f\u0627\u0631\u062e\u06cc\u0644"
    ],
    "name:mzn_x_preferred":[
        "\u0628\u0646\u062f\u0627\u0631\u062e\u06cc\u0644"
    ],
    "name:und_x_variant":[
        "\u0628\u0627\u0644\u0627 \u0628\u0646\u062f\u0627\u0631 \u062e\u064a\u0644"
    ],
    "wof:name":"Bala Bandar Kheyl",
    "wof:placetype":"locality"
},
  "geometry": {"coordinates":[53.03504,36.58433],"type":"Point"}
}