{
  "type": "Feature",
  "properties": {
    "gn:admin1_code":"9",
    "gn:asciiname":"Belartu",
    "gn:country_code":"IR",
    "gn:dem":1653,
    "gn:feature_class":"P",
    "gn:feature_code":"PPL",
    "gn:name":"Belart\u016b",
    "gn:population":0,
    "gn:timezone":"Asia/Tehran",
    "iso:country":"IR",
    "name:fas_x_preferred":[
        "Belart\u016b"
    ],
    "name:fas_x_variant":[
        "\u0628\u0644\u0631\u062a\u0648"
    ],
    "name:und_x_variant":[
        "\u0628\u0644\u0631\u062a\u0648"
    ],
    "wof:name":"Belartu",
    "wof:placetype":"locality"
},
  "geometry": {"coordinates":[48.51614,34.33546],"type":"Point"}
}