{
  "type": "Feature",
  "properties": {
    "gn:admin1_code":"22",
    "gn:asciiname":"Sarkavirdan",
    "gn:cc2":"IR",
    "gn:country_code":"IR",
    "gn:dem":70,
    "gn:feature_class":"P",
    "gn:feature_code":"PPL",
    "gn:name":"Sarkav\u012brd\u0101n",
    "gn:population":0,
    "gn:timezone":"Asia/Tehran",
    "iso:country":"IR",
    "name:fas_x_preferred":[
        "\u0633\u064e\u0631\u0643\u064e\u0648\u064a\u0631\u062f\u0627\u0646"
    ],
    "name:fas_x_variant":[
        "\u0633\u064e\u0631\u0643\u0650\u0648\u0650\u0631\u062f\u0627\u0646",
        "Sarkav\u012brd\u0101n"
    ],
    "name:und_x_variant":[
        "Sarkuvard\u0101n",
        "Sarkeverd\u0101n"
    ],
    "wof:name":"Sarkavirdan",
    "wof:placetype":"locality"
},
  "geometry": {"coordinates":[51.26028,29.4075],"type":"Point"}
}