{
  "type": "Feature",
  "properties": {
    "gn:admin1_code":"15",
    "gn:asciiname":"Hoseyniyeh-ye Mashkur",
    "gn:country_code":"IR",
    "gn:dem":31,
    "gn:feature_class":"P",
    "gn:feature_code":"PPL",
    "gn:name":"\u1e28oseyn\u012byeh-ye Mashk\u016br",
    "gn:population":0,
    "gn:timezone":"Asia/Tehran",
    "iso:country":"IR",
    "name:fas_x_preferred":[
        "\u062d\u0633\u06cc\u0646\u06cc\u0647 \u0645\u0634\u06a9\u0648\u0631"
    ],
    "name:fas_x_variant":[
        "\u1e28oseyn\u012byeh-ye Mashk\u016br"
    ],
    "wof:name":"Hoseyniyeh-ye Mashkur",
    "wof:placetype":"locality"
},
  "geometry": {"coordinates":[49.42332,30.94681],"type":"Point"}
}