{
  "type": "Feature",
  "properties": {
    "gn:admin1_code":"7",
    "gn:asciiname":"Rashk-e Bala",
    "gn:country_code":"IR",
    "gn:dem":1814,
    "gn:feature_class":"P",
    "gn:feature_code":"PPL",
    "gn:name":"R\u0101shk-e B\u0101l\u0101",
    "gn:population":0,
    "gn:timezone":"Asia/Tehran",
    "iso:country":"IR",
    "name:fas_x_preferred":[
        "R\u0101shk-e B\u0101l\u0101"
    ],
    "name:fas_x_variant":[
        "R\u0101shk-e \u2018Oly\u0101",
        "\u0631\u0627\u0634\u0643 \u0628\u0627\u0644\u0627"
    ],
    "name:und_x_variant":[
        "Jah\u0101neh",
        "R\u0101shk \u2018Olya",
        "R\u0101shk-e Bal\u016b\u0163-e",
        "\u0631\u0627\u0634\u0643 \u0628\u0627\u0644\u0627"
    ],
    "wof:name":"Rashk-e Bala",
    "wof:placetype":"locality"
},
  "geometry": {"coordinates":[51.81412,30.09498],"type":"Point"}
}