{
  "type": "Feature",
  "properties": {
    "gn:admin1_code":"11",
    "gn:asciiname":"Podol",
    "gn:country_code":"IR",
    "gn:dem":142,
    "gn:feature_class":"P",
    "gn:feature_code":"PPL",
    "gn:name":"Podol",
    "gn:population":0,
    "gn:timezone":"Asia/Tehran",
    "iso:country":"IR",
    "name:deu_x_preferred":[
        "Podol"
    ],
    "name:fas_x_preferred":[
        "\u067e\u062f\u0644"
    ],
    "name:msa_x_preferred":[
        "Podol"
    ],
    "name:und_x_variant":[
        "\u067e\u062f\u0644",
        "Podol"
    ],
    "wof:name":"Podol",
    "wof:placetype":"locality"
},
  "geometry": {"coordinates":[54.96575,27.00604],"type":"Point"}
}