{
  "type": "Feature",
  "properties": {
    "gn:admin1_code":"35",
    "gn:asciiname":"Sarta",
    "gn:country_code":"IR",
    "gn:dem":557,
    "gn:feature_class":"P",
    "gn:feature_code":"PPLF",
    "gn:name":"Sart\u0101",
    "gn:population":0,
    "gn:timezone":"Asia/Tehran",
    "iso:country":"IR",
    "name:ara_x_preferred":[
        "\u0633\u0631\u0637\u0629"
    ],
    "name:cat_x_preferred":[
        "Sarta"
    ],
    "name:ceb_x_preferred":[
        "\u015ear\u0163ah"
    ],
    "name:fas_x_preferred":[
        "Sart\u0101"
    ],
    "name:fas_x_variant":[
        "\u0633\u0631\u062a\u0627"
    ],
    "name:heb_x_preferred":[
        "\u05e1\u05e8\u05d8\u05d0"
    ],
    "name:nno_x_preferred":[
        "Sarta"
    ],
    "name:pol_x_preferred":[
        "Sarta"
    ],
    "name:und_x_variant":[
        "\u0633\u0631\u062a\u0627"
    ],
    "wof:name":"Sarta",
    "wof:placetype":"locality"
},
  "geometry": {"coordinates":[53.32342,36.44909000000001],"type":"Point"}
}