{
  "type": "Feature",
  "properties": {
    "gn:admin1_code":"42",
    "gn:asciiname":"Das",
    "gn:country_code":"IR",
    "gn:dem":1764,
    "gn:feature_class":"P",
    "gn:feature_code":"PPL",
    "gn:name":"D\u0101s",
    "gn:population":0,
    "gn:timezone":"Asia/Tehran",
    "iso:country":"IR",
    "name:fas_x_preferred":[
        "\u062f\u0627\u0633"
    ],
    "name:fas_x_variant":[
        "D\u0101s"
    ],
    "wof:name":"Das",
    "wof:placetype":"locality"
},
  "geometry": {"coordinates":[59.08821999999999,36.16712],"type":"Point"}
}