{
  "type": "Feature",
  "properties": {
    "gn:admin1_code":"35.0",
    "gn:asciiname":"Tangeh-ye Lavij",
    "gn:country_code":"IR",
    "gn:dem":323,
    "gn:feature_class":"P",
    "gn:feature_code":"PPL",
    "gn:name":"Tangeh-ye L\u0101v\u012bj",
    "gn:population":0,
    "gn:timezone":"Asia/Tehran",
    "iso:country":"IR",
    "name:fas_x_preferred":[
        "\u062a\u0646\u06af\u0647 \u0644\u0627\u0648\u06cc\u062c"
    ],
    "name:fas_x_variant":[
        "Tangeh-ye L\u0101v\u012bj",
        "\u062a\u0646\u06af\u0647",
        "\u0633\u0631 \u062a\u0646\u06af\u0647 \u0644\u0627\u0648\u06cc\u062c"
    ],
    "name:und_x_variant":[
        "Tangeh",
        "Sar Tangeh-ye L\u0101v\u012bj"
    ],
    "wof:name":"Tangeh-ye Lavij",
    "wof:placetype":"locality"
},
  "geometry": {"coordinates":[52.06548,36.42258],"type":"Point"}
}