{
  "type": "Feature",
  "properties": {
    "gn:admin1_code":"32",
    "gn:asciiname":"Shakar Ab",
    "gn:country_code":"IR",
    "gn:dem":811,
    "gn:feature_class":"P",
    "gn:feature_code":"PPL",
    "gn:name":"Shakar \u0100b",
    "gn:population":0,
    "gn:timezone":"Asia/Tehran",
    "iso:country":"IR",
    "name:ara_x_preferred":[
        "\u0634\u0643\u0631\u0622\u0628"
    ],
    "name:azb_x_preferred":[
        "\u0634\u06a9\u0631\u0648\u0648"
    ],
    "name:fas_x_preferred":[
        "\u0634\u0643\u0631 \u0622\u0628"
    ],
    "name:fas_x_variant":[
        "Shakar \u0100b",
        "\u0634\u06a9\u0631\u0622\u0628"
    ],
    "name:msa_x_preferred":[
        "Shakar Ab"
    ],
    "name:mzn_x_preferred":[
        "\u0634\u06a9\u0631\u0622\u0628"
    ],
    "wof:name":"Shakar Ab",
    "wof:placetype":"locality"
},
  "geometry": {"coordinates":[48.096,39.0775],"type":"Point"}
}