{
  "type": "Feature",
  "properties": {
    "gn:admin1_code":"8",
    "gn:asciiname":"Dar Sara",
    "gn:country_code":"IR",
    "gn:dem":-2,
    "gn:feature_class":"P",
    "gn:feature_code":"PPL",
    "gn:name":"D\u0101r Sar\u0101",
    "gn:population":0,
    "gn:timezone":"Asia/Tehran",
    "iso:country":"IR",
    "name:ceb_x_preferred":[
        "D\u0101r Sar\u0101"
    ],
    "name:fas_x_preferred":[
        "\u062f\u0627\u0631 \u0633\u0631\u0627"
    ],
    "name:fas_x_variant":[
        "D\u0101r Sar\u0101",
        "\u062a\u0631\u0628\u0647 \u0628\u0631",
        "\u062f\u0627\u0631\u0633\u0631\u0627"
    ],
    "name:msa_x_preferred":[
        "Dar Sara"
    ],
    "name:swe_x_preferred":[
        "D\u0101r Sar\u0101"
    ],
    "name:ukr_x_preferred":[
        "\u0414\u0430\u0440-\u0421\u0430\u0440\u0430"
    ],
    "name:und_x_variant":[
        "Torasara",
        "Darisara",
        "Torbeh Bar"
    ],
    "wof:name":"Dar Sara",
    "wof:placetype":"locality"
},
  "geometry": {"coordinates":[49.18655,37.52665],"type":"Point"}
}