{
  "type": "Feature",
  "properties": {
    "gn:admin1_code":"11",
    "gn:asciiname":"Bonab",
    "gn:country_code":"IR",
    "gn:dem":1230,
    "gn:feature_class":"P",
    "gn:feature_code":"PPL",
    "gn:name":"Bon\u0101b",
    "gn:population":0,
    "gn:timezone":"Asia/Tehran",
    "iso:country":"IR",
    "name:ara_x_preferred":[
        "\u0628\u0646\u0627\u0628"
    ],
    "name:azb_x_preferred":[
        "\u0628\u0646\u0627\u0628"
    ],
    "name:aze_x_preferred":[
        "B\u00fcnab"
    ],
    "name:ceb_x_preferred":[
        "Bon\u0101b"
    ],
    "name:deu_x_preferred":[
        "Bonab"
    ],
    "name:fas_x_preferred":[
        "\u0628\u0646\u0627\u0628"
    ],
    "name:fas_x_variant":[
        "Bon\u0101b"
    ],
    "name:hin_x_preferred":[
        "\u092c\u0947\u0928\u093e\u092c"
    ],
    "name:hye_x_preferred":[
        "\u0532\u0578\u0576\u0561\u0562"
    ],
    "name:ita_x_preferred":[
        "Bonab"
    ],
    "name:mlg_x_preferred":[
        "Bonab"
    ],
    "name:msa_x_preferred":[
        "Bonab"
    ],
    "name:pnb_x_preferred":[
        "\u0628\u0646\u0627\u0628"
    ],
    "name:pol_x_preferred":[
        "Bonab"
    ],
    "name:ron_x_preferred":[
        "Benab"
    ],
    "name:rus_x_preferred":[
        "\u0411\u0435\u043d\u0430\u0431"
    ],
    "name:tgk_x_preferred":[
        "\u0411\u0443\u043d\u043e\u0431"
    ],
    "name:tur_x_preferred":[
        "Bunab"
    ],
    "name:urd_x_preferred":[
        "\u0628\u0646\u0627\u0628"
    ],
    "name:zho_x_preferred":[
        "\u535a\u7d0d\u535c"
    ],
    "wof:name":"Bonab",
    "wof:placetype":"locality"
},
  "geometry": {"coordinates":[56.0958,27.9948],"type":"Point"}
}