{
  "type": "Feature",
  "properties": {
    "gn:admin1_code":"29",
    "gn:asciiname":"Godar Sabz",
    "gn:country_code":"IR",
    "gn:dem":2109,
    "gn:feature_class":"P",
    "gn:feature_code":"PPL",
    "gn:name":"God\u0101r Sabz",
    "gn:population":0,
    "gn:timezone":"Asia/Tehran",
    "iso:country":"IR",
    "name:fas_x_preferred":[
        "\u06af\u062f\u0627\u0631 \u0633\u0628\u0632"
    ],
    "name:fas_x_variant":[
        "God\u0101r Sabz"
    ],
    "wof:name":"Godar Sabz",
    "wof:placetype":"locality"
},
  "geometry": {"coordinates":[56.8474,28.8799],"type":"Point"}
}