{
  "type": "Feature",
  "properties": {
    "gn:admin1_code":"8",
    "gn:asciiname":"Bareh Dasht",
    "gn:country_code":"IR",
    "gn:dem":1617,
    "gn:feature_class":"P",
    "gn:feature_code":"PPL",
    "gn:name":"Bareh Dasht",
    "gn:population":0,
    "gn:timezone":"Asia/Tehran",
    "iso:country":"IR",
    "name:fas_x_preferred":[
        "\u0628\u0631\u0647 \u062f\u0634\u062a"
    ],
    "wof:name":"Bareh Dasht",
    "wof:placetype":"locality"
},
  "geometry": {"coordinates":[49.0953,37.0597],"type":"Point"}
}