{
  "type": "Feature",
  "properties": {
    "gn:admin1_code":"5",
    "gn:asciiname":"Dunun",
    "gn:country_code":"IR",
    "gn:dem":1328,
    "gn:feature_class":"P",
    "gn:feature_code":"PPL",
    "gn:name":"D\u016bn\u016bn",
    "gn:population":0,
    "gn:timezone":"Asia/Tehran",
    "iso:country":"IR",
    "name:bul_x_preferred":[
        "\u0414\u0436\u0443\u043d-\u0434\u0436\u0443\u043d"
    ],
    "name:deu_x_preferred":[
        "Djemb\u00e9#Die Bass-Trommeln"
    ],
    "name:fas_x_preferred":[
        "D\u016bn\u016bn"
    ],
    "name:fin_x_preferred":[
        "Dundun"
    ],
    "name:fra_x_preferred":[
        "Dum dum"
    ],
    "name:nld_x_preferred":[
        "Doundoun"
    ],
    "name:pol_x_preferred":[
        "Dundun"
    ],
    "name:por_x_preferred":[
        "Dundun"
    ],
    "name:spa_x_preferred":[
        "Dunun"
    ],
    "name:yor_x_preferred":[
        "Dundun"
    ],
    "wof:name":"Dunun",
    "wof:placetype":"locality"
},
  "geometry": {"coordinates":[51.00306,30.62583],"type":"Point"}
}