{
  "type": "Feature",
  "properties": {
    "gn:admin1_code":"28.0",
    "gn:asciiname":"Amiran",
    "gn:country_code":"IR",
    "gn:dem":1008,
    "gn:feature_class":"P",
    "gn:feature_code":"PPL",
    "gn:name":"Am\u012br\u0101n",
    "gn:population":0,
    "gn:timezone":"Asia/Tehran",
    "iso:country":"IR",
    "name:ara_x_preferred":[
        "\u0627\u0645\u064a\u0631\u0627\u0646"
    ],
    "name:fas_x_preferred":[
        "\u0627\u0645\u06cc\u0631\u0627\u0646"
    ],
    "name:fas_x_variant":[
        "Am\u012br\u0101n"
    ],
    "name:und_x_variant":[
        "Omehr\u0101n"
    ],
    "wof:name":"Amiran",
    "wof:placetype":"locality"
},
  "geometry": {"coordinates":[52.4039,33.4631],"type":"Point"}
}