{
  "type": "Feature",
  "properties": {
    "gn:admin1_code":"5",
    "gn:asciiname":"Mansur Khani",
    "gn:country_code":"IR",
    "gn:dem":2293,
    "gn:feature_class":"P",
    "gn:feature_code":"PPL",
    "gn:name":"Man\u015f\u016br Kh\u0101n\u012b",
    "gn:population":0,
    "gn:timezone":"Asia/Tehran",
    "iso:country":"IR",
    "name:fas_x_preferred":[
        "Man\u015f\u016br Kh\u0101n\u012b"
    ],
    "name:fas_x_variant":[
        "\u0645\u0646\u0635\u0648\u0631\u062e\u0627\u0646\u06cc",
        "\u067e\u0627\u0633\u062f\u0627\u0631\u0627\u0646"
    ],
    "name:und_x_variant":[
        "P\u0101sd\u0101r\u0101n"
    ],
    "wof:name":"Mansur Khani",
    "wof:placetype":"locality"
},
  "geometry": {"coordinates":[51.80514,30.63496],"type":"Point"}
}