{
  "type": "Feature",
  "properties": {
    "gn:admin1_code":"11",
    "gn:asciiname":"Kontakan Shahbar",
    "gn:country_code":"IR",
    "gn:dem":42,
    "gn:feature_class":"P",
    "gn:feature_code":"PPL",
    "gn:name":"Kontak\u0101n Shahb\u0101r",
    "gn:population":0,
    "gn:timezone":"Asia/Tehran",
    "iso:country":"IR",
    "name:fas_x_preferred":[
        "\u0643\u0646\u062a\u0643\u0627\u0646"
    ],
    "name:fas_x_variant":[
        "\u0643\u064f\u0646\u062a\u0650\u06af\u0627\u0646",
        "\u0643\u0650\u0646\u062a\u0650\u06af\u0627\u0646",
        "\u0643\u064e\u0646\u0643\u064e\u0646",
        "\u06a9\u0646\u062a\u06a9\u0627\u0646 \u0634\u0647\u0628\u0627\u0631",
        "Kontak\u0101n"
    ],
    "name:und_x_variant":[
        "Kankan",
        "Kenteg\u0101n",
        "Konteg\u0101n",
        "Kontak\u0101n Shahb\u0101r"
    ],
    "wof:name":"Kontakan Shahbar",
    "wof:placetype":"locality"
},
  "geometry": {"coordinates":[57.063,27.1889],"type":"Point"}
}