{
  "type": "Feature",
  "properties": {
    "gn:admin1_code":"15",
    "gn:asciiname":"Haddameh-ye Vosta",
    "gn:country_code":"IR",
    "gn:dem":17,
    "gn:feature_class":"P",
    "gn:feature_code":"PPL",
    "gn:name":"\u1e28add\u0101meh-ye Vos\u0163\u00e1",
    "gn:population":0,
    "gn:timezone":"Asia/Tehran",
    "iso:country":"IR",
    "name:fas_x_preferred":[
        "\u062d\u062f\u0627\u0645\u0647 \u0648\u0633\u0637\u06cc"
    ],
    "name:fas_x_variant":[
        "Had\u0101meh-ye M\u012b\u0101n\u012b",
        "Had\u0101meh-ye Vos\u0163\u00e1",
        "\u0647\u062f\u0627\u0645\u0647 \u0648\u0633\u0637\u06cc"
    ],
    "name:und_x_variant":[
        "\u1e28add\u0101meh-ye Sofl\u00e1",
        "Hadd\u0101meh-ye Dovom",
        "\u1e28add\u0101meh-ye Vos\u0163\u00e1",
        "Hadd\u0101meh-ye Yakom",
        "\u1e28add\u0101meh",
        "Hadd\u0101meh-ye Vos\u0163\u00e1"
    ],
    "wof:name":"Haddameh-ye Vosta",
    "wof:placetype":"locality"
},
  "geometry": {"coordinates":[49.2026,30.7413],"type":"Point"}
}