{
  "type": "Feature",
  "properties": {
    "gn:admin1_code":"4.0",
    "gn:asciiname":"Golchah",
    "gn:country_code":"IR",
    "gn:dem":1427,
    "gn:feature_class":"P",
    "gn:feature_code":"PPL",
    "gn:name":"Golch\u0101h",
    "gn:population":0,
    "gn:timezone":"Asia/Tehran",
    "iso:country":"IR",
    "name:fas_x_preferred":[
        "\u06af\u0644\u0686\u0627\u0647"
    ],
    "name:fas_x_variant":[
        "Golch\u0101h",
        "Kalch\u0101",
        "Golcheh-ye K\u016bren"
    ],
    "wof:name":"Golchah",
    "wof:placetype":"locality"
},
  "geometry": {"coordinates":[60.31462,28.95876],"type":"Point"}
}