{
  "type": "Feature",
  "properties": {
    "gn:admin1_code":"3.0",
    "gn:asciiname":"Amiri-ye Bala",
    "gn:country_code":"IR",
    "gn:dem":2020,
    "gn:feature_class":"P",
    "gn:feature_code":"PPL",
    "gn:name":"Am\u012br\u012b-ye B\u0101l\u0101",
    "gn:population":0,
    "gn:timezone":"Asia/Tehran",
    "iso:country":"IR",
    "name:fas_x_preferred":[
        "Am\u012br\u012b-ye B\u0101l\u0101"
    ],
    "name:fas_x_variant":[
        "\u0627\u064e\u0645\u064a\u0631\u06cc \u0628\u0627\u0644\u0627",
        "\u0627\u064e\u0645\u064a\u0631\u0626 \u0639\u064f\u0644\u064a\u0627",
        "Am\u012br\u012b \u2018Oly\u0101",
        "\u0627\u064e\u0645\u064a\u0631\u0626 \u0628\u0627\u0644\u0627",
        "\u0627\u064e\u0645\u064a\u0631\u06cc \u0639\u064f\u0644\u064a\u0627",
        "\u0627\u0645\u064a\u0631\u06cc \u0628\u0627\u0644\u0627"
    ],
    "name:und_x_variant":[
        "Am\u012br\u012b B\u0101l\u0101",
        "Am\u012br\u012b-ye \u2018Oly\u0101",
        "\u0627\u0645\u064a\u0631\u06cc \u0628\u0627\u0644\u0627"
    ],
    "wof:name":"Amiri-ye Bala",
    "wof:placetype":"locality"
},
  "geometry": {"coordinates":[51.00652,31.40983],"type":"Point"}
}