{
  "type": "Feature",
  "properties": {
    "gn:admin1_code":"1.0",
    "gn:asciiname":"Gaz Gesak",
    "gn:country_code":"IR",
    "gn:dem":1431,
    "gn:feature_class":"P",
    "gn:feature_code":"PPL",
    "gn:name":"Gaz Gesak",
    "gn:population":0,
    "gn:timezone":"Asia/Tehran",
    "iso:country":"IR",
    "name:fas_x_preferred":[
        "\u06af\u0632 \u06af\u0633\u06a9"
    ],
    "wof:name":"Gaz Gesak",
    "wof:placetype":"locality"
},
  "geometry": {"coordinates":[45.2802,36.5009],"type":"Point"}
}