{
  "type": "Feature",
  "properties": {
    "gn:admin1_code":"3",
    "gn:asciiname":"Qal`eh-ye Ab-e Kaseh",
    "gn:country_code":"IR",
    "gn:dem":2311,
    "gn:feature_class":"P",
    "gn:feature_code":"PPL",
    "gn:name":"Qal\u2018eh-ye \u0100b-e K\u0101seh",
    "gn:population":0,
    "gn:timezone":"Asia/Tehran",
    "iso:country":"IR",
    "name:fas_x_preferred":[
        "\u0100b K\u0101seh"
    ],
    "name:fas_x_variant":[
        "Qal\u2018eh-ye \u0100b-e K\u0101seh",
        "\u0642\u0644\u0639\u0647 \u0622\u0628 \u06a9\u0627\u0633\u0647"
    ],
    "wof:name":"Qal`eh-ye Ab-e Kaseh",
    "wof:placetype":"locality"
},
  "geometry": {"coordinates":[50.24774,32.5338],"type":"Point"}
}