{
  "type": "Feature",
  "properties": {
    "gn:admin1_code":"7.0",
    "gn:asciiname":"Mahmudabad",
    "gn:country_code":"IR",
    "gn:dem":1487,
    "gn:feature_class":"P",
    "gn:feature_code":"PPL",
    "gn:name":"Ma\u1e29m\u016bd\u0101b\u0101d",
    "gn:population":0,
    "gn:timezone":"Asia/Tehran",
    "iso:country":"IR",
    "name:fas_x_preferred":[
        "Ma\u1e29m\u016bd\u0101b\u0101d"
    ],
    "name:und_x_variant":[
        "S\u0101khtem\u0101n"
    ],
    "wof:name":"Mahmudabad",
    "wof:placetype":"locality"
},
  "geometry": {"coordinates":[52.80234,29.38079],"type":"Point"}
}