{
  "type": "Feature",
  "properties": {
    "gn:admin1_code":"8.0",
    "gn:asciiname":"Palang Posht",
    "gn:country_code":"IR",
    "gn:dem":84,
    "gn:feature_class":"P",
    "gn:feature_code":"PPL",
    "gn:name":"Palang Posht",
    "gn:population":0,
    "gn:timezone":"Asia/Tehran",
    "iso:country":"IR",
    "name:fas_x_preferred":[
        "\u067e\u0644\u0646\u06af \u067e\u0634\u062a"
    ],
    "name:und_x_variant":[
        "Zardk\u0101m",
        "Palang Posht"
    ],
    "wof:name":"Palang Posht",
    "wof:placetype":"locality"
},
  "geometry": {"coordinates":[49.39768,37.09862],"type":"Point"}
}