{
  "type": "Feature",
  "properties": {
    "gn:admin1_code":"11.0",
    "gn:asciiname":"Kam Kart",
    "gn:country_code":"IR",
    "gn:dem":204,
    "gn:feature_class":"P",
    "gn:feature_code":"PPL",
    "gn:name":"Kam Kart",
    "gn:population":0,
    "gn:timezone":"Asia/Tehran",
    "iso:country":"IR",
    "name:ceb_x_preferred":[
        "Kam Kart"
    ],
    "name:fas_x_preferred":[
        "\u06a9\u0645 \u06a9\u0631\u062a"
    ],
    "name:msa_x_preferred":[
        "Kam Kart"
    ],
    "name:swe_x_preferred":[
        "Kam Kart"
    ],
    "wof:name":"Kam Kart",
    "wof:placetype":"locality"
},
  "geometry": {"coordinates":[57.328,27.1918],"type":"Point"}
}