{
  "type": "Feature",
  "properties": {
    "gn:admin1_code":"42",
    "gn:asciiname":"Mazra`eh-ye Kalateh Fulad",
    "gn:country_code":"IR",
    "gn:dem":1340,
    "gn:feature_class":"P",
    "gn:feature_code":"PPL",
    "gn:name":"Mazra\u2018eh-ye Kal\u0101teh F\u016bl\u0101d",
    "gn:population":0,
    "gn:timezone":"Asia/Tehran",
    "iso:country":"IR",
    "name:fas_x_preferred":[
        "Kal\u0101teh-ye F\u016bl\u0101d"
    ],
    "name:fas_x_variant":[
        "\u0645\u0632\u0631\u0639\u0647 \u06a9\u0644\u0627\u062a\u0647 \u0641\u0648\u0644\u0627\u062f",
        "\u06a9\u0644\u0627\u062a\u0647 \u0641\u0648\u0644\u0627\u062f"
    ],
    "name:und_x_variant":[
        "F\u016bl\u0101d",
        "Mazra\u2018eh-ye Kal\u0101teh F\u016bl\u0101d"
    ],
    "wof:name":"Mazra`eh-ye Kalateh Fulad",
    "wof:placetype":"locality"
},
  "geometry": {"coordinates":[58.15124,35.36594],"type":"Point"}
}