{
  "type": "Feature",
  "properties": {
    "gn:admin1_code":"26.0",
    "gn:asciiname":"Chal Tarkhan",
    "gn:country_code":"IR",
    "gn:dem":988,
    "gn:feature_class":"P",
    "gn:feature_code":"PPL",
    "gn:name":"Ch\u0101l \u0162arkh\u0101n",
    "gn:population":0,
    "gn:timezone":"Asia/Tehran",
    "iso:country":"IR",
    "name:fas_x_preferred":[
        "\u0686\u0627\u0644 \u0637\u0631\u062e\u0627\u0646"
    ],
    "name:fas_x_variant":[
        "Ch\u0101leh \u0162arkh\u0101n",
        "Ch\u0101l \u0162arkh\u0101n",
        "\u0686\u0627\u0644\u0647 \u0637\u0631\u062e\u0627\u0646"
    ],
    "name:und_x_variant":[
        "Ch\u0101h \u0162arkh\u0101n"
    ],
    "wof:name":"Chal Tarkhan",
    "wof:placetype":"locality"
},
  "geometry": {"coordinates":[51.4773,35.4986],"type":"Point"}
}