{
  "type": "Feature",
  "properties": {
    "gn:admin1_code":"29",
    "gn:asciiname":"Mehru'iyeh-ye Bala",
    "gn:country_code":"IR",
    "gn:dem":652,
    "gn:feature_class":"P",
    "gn:feature_code":"PPL",
    "gn:name":"Mehr\u016b\u2019\u012byeh-ye B\u0101l\u0101",
    "gn:population":0,
    "gn:timezone":"Asia/Tehran",
    "iso:country":"IR",
    "name:fas_x_preferred":[
        "\u0645\u0647\u0631\u0648\u06cc\u0647"
    ],
    "name:fas_x_variant":[
        "Mehr\u016byeh",
        "\u0645\u0647\u0631\u0648\u0626\u064a\u0647 \u0628\u0627\u0644\u0627"
    ],
    "name:und_x_variant":[
        "Mehr\u016b\u2019\u012byeh-ye B\u0101l\u0101"
    ],
    "wof:name":"Mehru'iyeh-ye Bala",
    "wof:placetype":"locality"
},
  "geometry": {"coordinates":[57.4207,28.0979],"type":"Point"}
}