{
  "type": "Feature",
  "properties": {
    "gn:admin1_code":"42.0",
    "gn:asciiname":"Baranqarib",
    "gn:country_code":"IR",
    "gn:dem":1393,
    "gn:feature_class":"P",
    "gn:feature_code":"PPL",
    "gn:name":"Bar\u0101nqar\u012bb",
    "gn:population":0,
    "gn:timezone":"Asia/Tehran",
    "iso:country":"IR",
    "name:fas_x_preferred":[
        "\u0628\u0631\u0627\u0646\u0642\u0631\u06cc\u0628"
    ],
    "name:fas_x_variant":[
        "Baranqar\u012byeh",
        "Bar\u0101nqar\u012bb"
    ],
    "wof:name":"Baranqarib",
    "wof:placetype":"locality"
},
  "geometry": {"coordinates":[60.831,35.43170999999999],"type":"Point"}
}