{
  "type": "Feature",
  "properties": {
    "gn:admin1_code":"34",
    "gn:asciiname":"Sa`dabad",
    "gn:country_code":"IR",
    "gn:dem":1949,
    "gn:feature_class":"P",
    "gn:feature_code":"PPL",
    "gn:name":"Sa\u2018d\u0101b\u0101d",
    "gn:population":0,
    "gn:timezone":"Asia/Tehran",
    "iso:country":"IR",
    "name:fas_x_preferred":[
        "\u0633\u0639\u062f \u0622\u0628\u0627\u062f"
    ],
    "name:fas_x_variant":[
        "Sa\u2018d\u0101b\u0101d"
    ],
    "wof:name":"Sa`dabad",
    "wof:placetype":"locality"
},
  "geometry": {"coordinates":[49.885,34.53],"type":"Point"}
}