{
  "type": "Feature",
  "properties": {
    "gn:admin1_code":"28.0",
    "gn:asciiname":"Qal`eh Mir",
    "gn:country_code":"IR",
    "gn:dem":1616,
    "gn:feature_class":"P",
    "gn:feature_code":"PPL",
    "gn:name":"Qal\u2018eh M\u012br",
    "gn:population":0,
    "gn:timezone":"Asia/Tehran",
    "iso:country":"IR",
    "name:fas_x_preferred":[
        "\u0642\u0644\u0639\u0647 \u0645\u06cc\u0631"
    ],
    "name:fas_x_variant":[
        "Qal\u2018eh-e M\u012br",
        "Qal\u2018eh M\u012br"
    ],
    "name:und_x_variant":[
        "Qal\u2018eh-ye Am\u012br",
        "Qal\u2018eh-ye M\u012br",
        "Qal\u2018eh Am\u012br\u012byeh"
    ],
    "wof:name":"Qal`eh Mir",
    "wof:placetype":"locality"
},
  "geometry": {"coordinates":[51.4593,32.5264],"type":"Point"}
}