{
  "type": "Feature",
  "properties": {
    "gn:admin1_code":"4.0",
    "gn:asciiname":"Mur Mohammad",
    "gn:country_code":"IR",
    "gn:dem":1380,
    "gn:feature_class":"P",
    "gn:feature_code":"PPL",
    "gn:name":"M\u016br Mo\u1e29ammad",
    "gn:population":0,
    "gn:timezone":"Asia/Tehran",
    "iso:country":"IR",
    "name:fas_x_preferred":[
        "\u0645\u0648\u0631 \u0645\u064f\u062d\u064e\u0645\u064e\u0651\u062f"
    ],
    "name:fas_x_variant":[
        "\u0646\u0648\u0631 \u0645\u064f\u062d\u064e\u0645\u064e\u0651\u062f",
        "M\u016br Mo\u1e29ammad"
    ],
    "name:und_x_variant":[
        "N\u016br Mo\u1e29ammad"
    ],
    "wof:name":"Mur Mohammad",
    "wof:placetype":"locality"
},
  "geometry": {"coordinates":[60.51667,28.33333],"type":"Point"}
}