{
  "type": "Feature",
  "properties": {
    "gn:admin1_code":"13",
    "gn:asciiname":"Tarazu Bareh",
    "gn:country_code":"IR",
    "gn:dem":1563,
    "gn:feature_class":"P",
    "gn:feature_code":"PPL",
    "gn:name":"Tar\u0101z\u016b Bareh",
    "gn:population":0,
    "gn:timezone":"Asia/Tehran",
    "iso:country":"IR",
    "name:fas_x_preferred":[
        "\u062a\u0631\u0627\u0632\u0648\u0628\u0631\u0647"
    ],
    "name:fas_x_variant":[
        "Tar\u0101z\u016b Barreh",
        "Tar\u0101z\u016b Bareh"
    ],
    "wof:name":"Tarazu Bareh",
    "wof:placetype":"locality"
},
  "geometry": {"coordinates":[47.2281,34.6294],"type":"Point"}
}