{
  "type": "Feature",
  "properties": {
    "gn:admin1_code":"42",
    "gn:asciiname":"Shurok-e Tupkanlu",
    "gn:country_code":"IR",
    "gn:dem":1393,
    "gn:feature_class":"P",
    "gn:feature_code":"PPL",
    "gn:name":"Sh\u016brok-e T\u016bpk\u0101nl\u016b",
    "gn:population":0,
    "gn:timezone":"Asia/Tehran",
    "iso:country":"IR",
    "name:fas_x_preferred":[
        "Sh\u016brok-e T\u016bpk\u0101nl\u016b"
    ],
    "name:fas_x_variant":[
        "\u0634\u0648\u0631\u06a9 \u062a\u0648\u067e\u06a9\u0627\u0646\u0644\u0648"
    ],
    "name:und_x_variant":[
        "Sh\u016brak-e T\u016bpk\u0101nl\u016b",
        "\u0634\u0648\u0631\u06a9 \u062a\u0648\u067e\u06a9\u0627\u0646\u0644\u0648"
    ],
    "wof:name":"Shurok-e Tupkanlu",
    "wof:placetype":"locality"
},
  "geometry": {"coordinates":[58.50516,37.1647],"type":"Point"}
}