{
  "type": "Feature",
  "properties": {
    "gn:admin1_code":"13",
    "gn:asciiname":"Khowrneh-ye `Olya",
    "gn:country_code":"IR",
    "gn:dem":1335,
    "gn:feature_class":"P",
    "gn:feature_code":"PPL",
    "gn:name":"Khowrneh-ye \u2018Oly\u0101",
    "gn:population":0,
    "gn:timezone":"Asia/Tehran",
    "iso:country":"IR",
    "name:fas_x_preferred":[
        "\u062e\u0648\u0631\u0646\u0647 \u0639\u0644\u06cc\u0627"
    ],
    "name:fas_x_variant":[
        "Kh\u016brneh-ye \u2018Oly\u0101"
    ],
    "name:und_x_variant":[
        "Khowrneh-ye \u2018Oly\u0101"
    ],
    "wof:name":"Khowrneh-ye `Olya",
    "wof:placetype":"locality"
},
  "geometry": {"coordinates":[46.632,34.5176],"type":"Point"}
}