{
  "type": "Feature",
  "properties": {
    "gn:admin1_code":"5",
    "gn:asciiname":"Pataveh",
    "gn:country_code":"IR",
    "gn:dem":2067,
    "gn:feature_class":"P",
    "gn:feature_code":"PPL",
    "gn:name":"P\u0101t\u0101veh",
    "gn:population":0,
    "gn:timezone":"Asia/Tehran",
    "iso:country":"IR",
    "name:fas_x_preferred":[
        "P\u0101t\u0101veh"
    ],
    "name:fas_x_variant":[
        "\u067e\u0627\u062a\u0627\u0648\u0647"
    ],
    "name:und_x_variant":[
        "\u067e\u0627\u062a\u0627\u0648\u0647"
    ],
    "wof:name":"Pataveh",
    "wof:placetype":"locality"
},
  "geometry": {"coordinates":[51.35801,30.60918],"type":"Point"}
}