{
  "type": "Feature",
  "properties": {
    "gn:admin1_code":"35.0",
    "gn:asciiname":"Chalsiu",
    "gn:country_code":"IR",
    "gn:dem":869,
    "gn:feature_class":"P",
    "gn:feature_code":"PPL",
    "gn:name":"Ch\u0101ls\u012b\u016b",
    "gn:population":0,
    "gn:timezone":"Asia/Tehran",
    "iso:country":"IR",
    "name:fas_x_preferred":[
        "\u0686\u0627\u0644 \u0633\u064a\u0627\u0647"
    ],
    "name:fas_x_variant":[
        "Ch\u0101l S\u012b\u0101h",
        "\u0686\u0627\u0644\u0633\u06cc\u0648",
        "\u0686\u0627\u0644\u0647 \u0633\u064a\u0627\u0647"
    ],
    "name:und_x_variant":[
        "Ch\u0101ls\u012b\u016b",
        "Ch\u0101leh S\u012b\u0101h"
    ],
    "wof:name":"Chalsiu",
    "wof:placetype":"locality"
},
  "geometry": {"coordinates":[51.9216,36.4088],"type":"Point"}
}