{
  "type": "Feature",
  "properties": {
    "gn:admin1_code":"34",
    "gn:asciiname":"Kahak-e Bala",
    "gn:country_code":"IR",
    "gn:dem":1499,
    "gn:feature_class":"P",
    "gn:feature_code":"PPL",
    "gn:name":"Kahak-e B\u0101l\u0101",
    "gn:population":0,
    "gn:timezone":"Asia/Tehran",
    "iso:country":"IR",
    "name:fas_x_preferred":[
        "Kahak-e B\u0101l\u0101"
    ],
    "name:fas_x_variant":[
        "\u0643\u0647\u0643 \u0628\u0627\u0644\u0627",
        "\u0643\u0647\u0643 \u0633\u0641\u0644\u06cc"
    ],
    "name:und_x_variant":[
        "Kahak",
        "\u0643\u0647\u0643 \u0628\u0627\u0644\u0627",
        "Kahak-e Sofl\u00e1"
    ],
    "wof:name":"Kahak-e Bala",
    "wof:placetype":"locality"
},
  "geometry": {"coordinates":[49.81517,35.08456],"type":"Point"}
}