{
  "type": "Feature",
  "properties": {
    "gn:admin1_code":"32",
    "gn:asciiname":"Qeshlaq-e Qashqa Hashem",
    "gn:country_code":"IR",
    "gn:dem":473,
    "gn:feature_class":"P",
    "gn:feature_code":"PPL",
    "gn:name":"Qeshl\u0101q-e Q\u0101shq\u0101 H\u0101shem",
    "gn:population":0,
    "gn:timezone":"Asia/Tehran",
    "iso:country":"IR",
    "name:fas_x_preferred":[
        "\u0642\u0650\u0634\u0644\u0627\u0642\u0650 \u0642\u0627\u0634\u0642\u0627 \u0647\u0627\u0634\u0650\u0645"
    ],
    "name:fas_x_variant":[
        "Qeshl\u0101q-e Q\u0101shq\u0101 H\u0101shem"
    ],
    "wof:name":"Qeshlaq-e Qashqa Hashem",
    "wof:placetype":"locality"
},
  "geometry": {"coordinates":[47.76667,39.25],"type":"Point"}
}