{
  "type": "Feature",
  "properties": {
    "gn:admin1_code":"7",
    "gn:asciiname":"Khoffeh Bideh",
    "gn:country_code":"IR",
    "gn:dem":1523,
    "gn:feature_class":"P",
    "gn:feature_code":"PPL",
    "gn:name":"Khoffeh B\u012bdeh",
    "gn:population":0,
    "gn:timezone":"Asia/Tehran",
    "iso:country":"IR",
    "name:fas_x_preferred":[
        "\u06af\u0648\u062f \u06a9\u0648\u0631\u06a9\u06cc"
    ],
    "name:fas_x_variant":[
        "Gowd-e K\u016brak\u012b",
        "\u062e\u0641\u0647 \u0628\u06cc\u062f\u0647",
        "\u062e\u0641\u0631 \u0628\u06cc\u062f\u0647"
    ],
    "name:und_x_variant":[
        "Khoffeh B\u012bdeh",
        "Khoffar B\u012bdeh"
    ],
    "wof:name":"Khoffeh Bideh",
    "wof:placetype":"locality"
},
  "geometry": {"coordinates":[53.7105,28.3701],"type":"Point"}
}