{
  "type": "Feature",
  "properties": {
    "gn:admin1_code":"1.0",
    "gn:asciiname":"Masjed",
    "gn:country_code":"IR",
    "gn:dem":1402,
    "gn:feature_class":"P",
    "gn:feature_code":"PPL",
    "gn:name":"Masjed",
    "gn:population":0,
    "gn:timezone":"Asia/Tehran",
    "iso:country":"IR",
    "name:fas_x_preferred":[
        "\u0645\u064e\u0633\u062c\u0650\u062f"
    ],
    "name:fas_x_variant":[
        "\u0645\u0633\u062c\u062f"
    ],
    "wof:name":"Masjed",
    "wof:placetype":"locality"
},
  "geometry": {"coordinates":[46.4568,36.8987],"type":"Point"}
}