{
  "type": "Feature",
  "properties": {
    "gn:admin1_code":"23",
    "gn:asciiname":"Posht-e Tang-e Chenar",
    "gn:country_code":"IR",
    "gn:dem":1097,
    "gn:feature_class":"P",
    "gn:feature_code":"PPL",
    "gn:name":"Posht-e Tang-e Chen\u0101r",
    "gn:population":0,
    "gn:timezone":"Asia/Tehran",
    "iso:country":"IR",
    "name:fas_x_preferred":[
        "\u067e\u064f\u0634\u062a\u0650 \u062a\u064e\u0646\u06af\u0650 \u0686\u0650\u0646\u0627\u0631"
    ],
    "name:fas_x_variant":[
        "\u067e\u064f\u0634\u062a \u062a\u064e\u0646\u06af",
        "\u067e\u064f\u0634\u062a \u062a\u064e\u0646\u06af\u0650 \u0686\u0650\u0646\u0627\u0631",
        "Posht-e Tang-e Chen\u0101r",
        "\u067e\u0634\u062a \u062a\u0646\u06af \u0686\u0646\u0627\u0631"
    ],
    "name:und_x_variant":[
        "Posht-e Tang",
        "Posht Tang-e Chen\u0101r",
        "Posht Tang",
        "\u067e\u0634\u062a \u062a\u0646\u06af \u0686\u0646\u0627\u0631"
    ],
    "wof:name":"Posht-e Tang-e Chenar",
    "wof:placetype":"locality"
},
  "geometry": {"coordinates":[48.1106,33.4702],"type":"Point"}
}