{
  "type": "Feature",
  "properties": {
    "gn:admin1_code":"8.0",
    "gn:asciiname":"Abrud",
    "gn:country_code":"IR",
    "gn:dem":193,
    "gn:feature_class":"P",
    "gn:feature_code":"PPLL",
    "gn:name":"\u0100br\u016bd",
    "gn:population":0,
    "gn:timezone":"Asia/Tehran",
    "iso:country":"IR",
    "name:fas_x_preferred":[
        "\u0622\u0628\u0631\u0648\u062f"
    ],
    "name:fas_x_variant":[
        "\u0100br\u016bd"
    ],
    "name:und_x_variant":[
        "\u0100br\u016bd"
    ],
    "wof:name":"Abrud",
    "wof:placetype":"locality"
},
  "geometry": {"coordinates":[49.17974,37.17691],"type":"Point"}
}