{
  "type": "Feature",
  "properties": {
    "gn:admin1_code":"8.0",
    "gn:asciiname":"Abrud",
    "gn:country_code":"IR",
    "gn:dem":193,
    "gn:feature_class":"P",
    "gn:feature_code":"PPLL",
    "gn:name":"\u0100br\u016bd",
    "gn:population":0,
    "gn:timezone":"Asia/Tehran",
    "iso:country":"IR",
    "name:arg_x_preferred":[
        "Abrud"
    ],
    "name:ceb_x_preferred":[
        "Ora\u0219 Abrud"
    ],
    "name:ces_x_preferred":[
        "Abrud"
    ],
    "name:deu_x_preferred":[
        "Abrud"
    ],
    "name:epo_x_preferred":[
        "Abrud"
    ],
    "name:fas_x_preferred":[
        "\u0622\u0628\u0631\u0648\u062f"
    ],
    "name:fas_x_variant":[
        "\u0100br\u016bd",
        "\u0627\u0628\u0631\u0648"
    ],
    "name:fin_x_preferred":[
        "Abrud"
    ],
    "name:fra_x_preferred":[
        "Abrud"
    ],
    "name:glg_x_preferred":[
        "Abrud"
    ],
    "name:hun_x_preferred":[
        "Abrudb\u00e1nya"
    ],
    "name:ita_x_preferred":[
        "Abrud"
    ],
    "name:lat_x_preferred":[
        "Abruttus"
    ],
    "name:min_x_preferred":[
        "Abrud"
    ],
    "name:msa_x_preferred":[
        "Abrud"
    ],
    "name:nld_x_preferred":[
        "Abrud"
    ],
    "name:oci_x_preferred":[
        "Abrud"
    ],
    "name:pol_x_preferred":[
        "Abrud"
    ],
    "name:por_x_preferred":[
        "Abrud"
    ],
    "name:ron_x_preferred":[
        "Abrud"
    ],
    "name:rus_x_preferred":[
        "\u0410\u0431\u0440\u0443\u0434"
    ],
    "name:spa_x_preferred":[
        "Abrud"
    ],
    "name:srp_x_preferred":[
        "\u041e\u043f\u0448\u0442\u0438\u043d\u0430 \u0410\u0431\u0440\u0443\u0434"
    ],
    "name:swe_x_preferred":[
        "Abrud"
    ],
    "name:tgk_x_preferred":[
        "\u0410\u0431\u0440\u0443\u0434"
    ],
    "name:ukr_x_preferred":[
        "\u0410\u0431\u0440\u0443\u0434"
    ],
    "name:vie_x_preferred":[
        "Abrud"
    ],
    "name:zho_x_preferred":[
        "\u963f\u5e03\u9c81\u5fb7"
    ],
    "wof:name":"Abrud",
    "wof:placetype":"locality"
},
  "geometry": {"coordinates":[49.17974,37.17691],"type":"Point"}
}