{
  "type": "Feature",
  "properties": {
    "gn:admin1_code":"28.0",
    "gn:asciiname":"Salehabad",
    "gn:country_code":"IR",
    "gn:dem":1676,
    "gn:feature_class":"P",
    "gn:feature_code":"PPL",
    "gn:name":"\u015e\u0101le\u1e29\u0101b\u0101d",
    "gn:population":0,
    "gn:timezone":"Asia/Tehran",
    "iso:country":"IR",
    "name:aze_x_preferred":[
        "Salehabad"
    ],
    "name:ceb_x_preferred":[
        "Salehabad"
    ],
    "name:fas_x_preferred":[
        "\u0635\u0627\u0644\u062d \u0622\u0628\u0627\u062f"
    ],
    "name:fas_x_variant":[
        "\u015e\u0101le\u1e29\u0101b\u0101d",
        "\u0635\u0627\u0644\u062d\u200c\u0622\u0628\u0627\u062f"
    ],
    "name:ita_x_preferred":[
        "Salehabad"
    ],
    "name:swe_x_preferred":[
        "Salehabad"
    ],
    "wof:name":"Salehabad",
    "wof:placetype":"locality"
},
  "geometry": {"coordinates":[51.3143,32.6461],"type":"Point"}
}