{
  "type": "Feature",
  "properties": {
    "gn:admin1_code":"23.0",
    "gn:asciiname":"Zalali Keykamdar",
    "gn:country_code":"IR",
    "gn:dem":1803,
    "gn:feature_class":"P",
    "gn:feature_code":"PPL",
    "gn:name":"Zal\u0101l\u012b Keykamdar",
    "gn:population":0,
    "gn:timezone":"Asia/Tehran",
    "iso:country":"IR",
    "name:fas_x_preferred":[
        "\u0632\u0644\u0627\u0644\u06cc \u06a9\u06cc\u06a9\u0645\u062f\u0631"
    ],
    "name:fas_x_variant":[
        "\u0632\u0644\u0627\u0644\u06cc"
    ],
    "name:und_x_variant":[
        "Zal\u0101l\u012b Keykamdar",
        "Zal\u0101l\u012b"
    ],
    "wof:name":"Zalali Keykamdar",
    "wof:placetype":"locality"
},
  "geometry": {"coordinates":[48.80655,33.47964],"type":"Point"}
}