{
  "type": "Feature",
  "properties": {
    "gn:admin1_code":"34.0",
    "gn:asciiname":"Qeshlaq-e Soltani",
    "gn:country_code":"IR",
    "gn:dem":1242,
    "gn:feature_class":"P",
    "gn:feature_code":"PPLL",
    "gn:name":"Qeshl\u0101q-e Sol\u0163\u0101n\u012b",
    "gn:population":0,
    "gn:timezone":"Asia/Tehran",
    "iso:country":"IR",
    "name:fas_x_preferred":[
        "\u0642\u0634\u0644\u0627\u0642 \u0633\u0644\u0637\u0627\u0646\u06cc"
    ],
    "name:und_x_variant":[
        "Qeshl\u0101q-e Sol\u0163\u0101n\u012b"
    ],
    "wof:name":"Qeshlaq-e Soltani",
    "wof:placetype":"locality"
},
  "geometry": {"coordinates":[50.74736,35.47591],"type":"Point"}
}