{
  "type": "Feature",
  "properties": {
    "gn:admin1_code":"38.0",
    "gn:asciiname":"Miankuh",
    "gn:country_code":"IR",
    "gn:dem":1387,
    "gn:feature_class":"P",
    "gn:feature_code":"PPL",
    "gn:name":"M\u012b\u0101nk\u016bh",
    "gn:population":0,
    "gn:timezone":"Asia/Tehran",
    "iso:country":"IR",
    "name:fas_x_preferred":[
        "\u0645\u06cc\u0627\u0646\u06a9\u0648\u0647"
    ],
    "name:fas_x_variant":[
        "M\u012b\u0101nk\u016bh"
    ],
    "wof:name":"Miankuh",
    "wof:placetype":"locality"
},
  "geometry": {"coordinates":[50.4963,36.08308],"type":"Point"}
}