{
  "type": "Feature",
  "properties": {
    "gn:admin1_code":"29",
    "gn:asciiname":"Kahdan-e Bala",
    "gn:cc2":"IR",
    "gn:country_code":"IR",
    "gn:dem":1635,
    "gn:feature_class":"P",
    "gn:feature_code":"PPL",
    "gn:name":"K\u0101hd\u0101n-e B\u0101l\u0101",
    "gn:population":0,
    "gn:timezone":"Asia/Tehran",
    "iso:country":"IR",
    "name:ara_x_preferred":[
        "\u0643\u0627\u0647 \u062f\u0627\u0646"
    ],
    "name:fas_x_preferred":[
        "K\u0101hd\u0101n-e B\u0101l\u0101"
    ],
    "name:fas_x_variant":[
        "\u06a9\u0627\u0647 \u062f\u0627\u0646"
    ],
    "name:und_x_variant":[
        "K\u0101hd\u0101n",
        "K\u0101hd\u0101n-e A\u1e29mad Kh\u0101n\u012b"
    ],
    "wof:name":"Kahdan-e Bala",
    "wof:placetype":"locality"
},
  "geometry": {"coordinates":[56.15944,28.78139],"type":"Point"}
}