{
  "type": "Feature",
  "properties": {
    "gn:admin1_code":"32",
    "gn:asciiname":"Kuzah Topraqi",
    "gn:country_code":"IR",
    "gn:dem":1392,
    "gn:feature_class":"P",
    "gn:feature_code":"PPL",
    "gn:name":"K\u016bzah Topr\u0101q\u012b",
    "gn:population":0,
    "gn:timezone":"Asia/Tehran",
    "iso:country":"IR",
    "name:ara_x_preferred":[
        "\u0643\u0648\u0632\u0629 \u062a\u0628\u0631\u0627\u0642\u064a"
    ],
    "name:ceb_x_preferred":[
        "K\u016bzah Topr\u0101q\u012b"
    ],
    "name:fas_x_preferred":[
        "\u0643\u0648\u0632\u064e\u0647 \u062a\u064f\u0631\u067e\u0627\u0642\u06cc"
    ],
    "name:fas_x_variant":[
        "\u0643\u0648\u0632\u0647 \u062a\u067e\u0631\u0627\u0642\u06cc",
        "K\u016bzah Torp\u0101q\u012b",
        "K\u016bzah Topr\u0101q\u012b",
        "\u06a9\u0648\u0632\u0647 \u062a\u067e\u0631\u0627\u0642\u06cc"
    ],
    "name:msa_x_preferred":[
        "Kuzah Topraqi"
    ],
    "name:swe_x_preferred":[
        "K\u016bzah Topr\u0101q\u012b"
    ],
    "wof:name":"Kuzah Topraqi",
    "wof:placetype":"locality"
},
  "geometry": {"coordinates":[48.3679,38.1211],"type":"Point"}
}