{
  "type": "Feature",
  "properties": {
    "gn:admin1_code":"4.0",
    "gn:asciiname":"Deh-e `Ali Sarani",
    "gn:country_code":"IR",
    "gn:dem":481,
    "gn:feature_class":"P",
    "gn:feature_code":"PPL",
    "gn:name":"Deh-e \u2018Al\u012b S\u0101r\u0101n\u012b",
    "gn:population":0,
    "gn:timezone":"Asia/Tehran",
    "iso:country":"IR",
    "name:fas_x_preferred":[
        "\u062f\u0647 \u0639\u0644\u06cc \u0633\u0627\u0631\u0627\u0646\u06cc"
    ],
    "name:fas_x_variant":[
        "Deh-e \u2018Al\u012b S\u0101r\u0101n\u012b"
    ],
    "wof:name":"Deh-e `Ali Sarani",
    "wof:placetype":"locality"
},
  "geometry": {"coordinates":[61.658,31.1124],"type":"Point"}
}