{
  "type": "Feature",
  "properties": {
    "gn:admin1_code":"8",
    "gn:asciiname":"Varzan",
    "gn:country_code":"IR",
    "gn:dem":2010,
    "gn:feature_class":"P",
    "gn:feature_code":"PPL",
    "gn:name":"Varzan",
    "gn:population":0,
    "gn:timezone":"Asia/Tehran",
    "iso:country":"IR",
    "name:ceb_x_preferred":[
        "Varzan"
    ],
    "name:fas_x_preferred":[
        "\u0634\u062a\u0647 \u0698\u06cc"
    ],
    "name:fas_x_variant":[
        "Shateh Zh\u012b",
        "\u0648\u0631\u0632\u0646"
    ],
    "name:msa_x_preferred":[
        "Varzan"
    ],
    "name:rus_x_preferred":[
        "\u0412\u0435\u0440\u0437\u0435\u043d"
    ],
    "name:swe_x_preferred":[
        "Varzan"
    ],
    "wof:name":"Varzan",
    "wof:placetype":"locality"
},
  "geometry": {"coordinates":[48.68393,37.96567],"type":"Point"}
}