{
  "type": "Feature",
  "properties": {
    "gn:admin1_code":"1",
    "gn:asciiname":"Bazargan",
    "gn:country_code":"IR",
    "gn:dem":1409,
    "gn:feature_class":"P",
    "gn:feature_code":"PPL",
    "gn:name":"B\u0101zarg\u0101n",
    "gn:population":0,
    "gn:timezone":"Asia/Tehran",
    "iso:country":"IR",
    "name:fas_x_preferred":[
        "\u0628\u0627\u0632\u064e\u0631\u06af\u0627\u0646"
    ],
    "name:fas_x_variant":[
        "\u0628\u0627\u0632\u0650\u0631\u06af\u0627\u0646",
        "B\u0101zarg\u0101n",
        "\u0628\u0627\u0632\u0631\u06af\u0627\u0646"
    ],
    "name:und_x_variant":[
        "B\u0101zerg\u0101n",
        "\u0628\u0627\u0632\u0631\u06af\u0627\u0646"
    ],
    "wof:name":"Bazargan",
    "wof:placetype":"locality"
},
  "geometry": {"coordinates":[44.3875,39.3915],"type":"Point"}
}