{
  "type": "Feature",
  "properties": {
    "gn:admin1_code":"1",
    "gn:asciiname":"Bazargan",
    "gn:country_code":"IR",
    "gn:dem":1409,
    "gn:feature_class":"P",
    "gn:feature_code":"PPL",
    "gn:name":"B\u0101zarg\u0101n",
    "gn:population":0,
    "gn:timezone":"Asia/Tehran",
    "iso:country":"IR",
    "name:ara_x_preferred":[
        "\u0628\u0627\u0632\u0631\u063a\u0627\u0646"
    ],
    "name:azb_x_preferred":[
        "\u0628\u0627\u0632\u0631\u06af\u0627\u0646"
    ],
    "name:aze_x_preferred":[
        "Baz\u0259rgan"
    ],
    "name:ceb_x_preferred":[
        "B\u0101zarg\u0101n"
    ],
    "name:ckb_x_preferred":[
        "\u0628\u0627\u0632\u06d5\u0631\u06af\u0627\u0646"
    ],
    "name:fas_x_preferred":[
        "\u0628\u0627\u0632\u064e\u0631\u06af\u0627\u0646"
    ],
    "name:fas_x_variant":[
        "\u0628\u0627\u0632\u0650\u0631\u06af\u0627\u0646",
        "B\u0101zarg\u0101n",
        "\u0628\u0627\u0632\u0631\u06af\u0627\u0646"
    ],
    "name:fra_x_preferred":[
        "Bazargan"
    ],
    "name:hye_x_preferred":[
        "\u0532\u0561\u0566\u0561\u0580\u0563\u0561\u0576"
    ],
    "name:ita_x_preferred":[
        "Bazargan"
    ],
    "name:kur_x_preferred":[
        "Bazirgan"
    ],
    "name:mlg_x_preferred":[
        "Bazargan"
    ],
    "name:msa_x_preferred":[
        "Bazargan"
    ],
    "name:pol_x_preferred":[
        "Bazargan"
    ],
    "name:rus_x_preferred":[
        "\u0411\u0430\u0437\u0435\u0440\u0433\u0430\u043d"
    ],
    "name:spa_x_preferred":[
        "Bazarg\u00e1n"
    ],
    "name:swe_x_preferred":[
        "B\u0101zarg\u0101n"
    ],
    "name:tur_x_preferred":[
        "Bazergan"
    ],
    "name:und_x_variant":[
        "B\u0101zerg\u0101n"
    ],
    "name:urd_x_preferred":[
        "\u0628\u0627\u0632\u0631\u06af\u0627\u0646"
    ],
    "name:uzb_x_preferred":[
        "Bozarqon"
    ],
    "name:zho_x_preferred":[
        "\u5df4\u585e\u7518"
    ],
    "wof:name":"Bazargan",
    "wof:placetype":"locality"
},
  "geometry": {"coordinates":[44.3875,39.3915],"type":"Point"}
}