{
  "type": "Feature",
  "properties": {
    "gn:admin1_code":"15.0",
    "gn:asciiname":"Dehliz-e Yek",
    "gn:country_code":"IR",
    "gn:dem":16,
    "gn:feature_class":"P",
    "gn:feature_code":"PPL",
    "gn:name":"Dehl\u012bz-e Yek",
    "gn:population":0,
    "gn:timezone":"Asia/Tehran",
    "iso:country":"IR",
    "name:fas_x_preferred":[
        "\u062f\u0647\u0644\u06cc\u0632 \u06cc\u06a9"
    ],
    "name:fas_x_variant":[
        "Dehl\u012bz-e Yek"
    ],
    "wof:name":"Dehliz-e Yek",
    "wof:placetype":"locality"
},
  "geometry": {"coordinates":[48.49529,31.35934],"type":"Point"}
}