{
  "type": "Feature",
  "properties": {
    "gn:admin1_code":"4.0",
    "gn:asciiname":"Parud",
    "gn:country_code":"IR",
    "gn:dem":609,
    "gn:feature_class":"P",
    "gn:feature_code":"PPL",
    "gn:name":"P\u0101r\u016bd",
    "gn:population":0,
    "gn:timezone":"Asia/Tehran",
    "iso:country":"IR",
    "name:fas_x_preferred":[
        "P\u0101r\u016bd"
    ],
    "name:und_x_variant":[
        "Sardok\u0101n-e P\u0101r\u016bd",
        "\u067e\u0627\u0631\u0648\u062f"
    ],
    "wof:name":"Parud",
    "wof:placetype":"locality"
},
  "geometry": {"coordinates":[61.2902,26.3698],"type":"Point"}
}