{
  "type": "Feature",
  "properties": {
    "gn:admin1_code":"8",
    "gn:asciiname":"Laleh Dasht",
    "gn:country_code":"IR",
    "gn:dem":1,
    "gn:feature_class":"P",
    "gn:feature_code":"PPL",
    "gn:name":"L\u0101leh Dasht",
    "gn:population":0,
    "gn:timezone":"Asia/Tehran",
    "iso:country":"IR",
    "name:ceb_x_preferred":[
        "L\u0101leh Dasht"
    ],
    "name:fas_x_preferred":[
        "L\u0101leh Dasht"
    ],
    "name:fas_x_variant":[
        "\u0644\u0627\u0644\u0647 \u062f\u0634\u062a",
        "\u0644\u0627\u0644\u0647\u200c\u062f\u0634\u062a"
    ],
    "name:msa_x_preferred":[
        "Laleh Dasht"
    ],
    "name:swe_x_preferred":[
        "L\u0101leh Dasht"
    ],
    "name:ukr_x_preferred":[
        "\u041b\u044f\u043b\u0435-\u0414\u0435\u0448\u0442"
    ],
    "name:und_x_variant":[
        "Laldash"
    ],
    "name:urd_x_preferred":[
        "\u0644\u0627\u0644\u06c1 \u062f\u0634\u062a"
    ],
    "wof:name":"Laleh Dasht",
    "wof:placetype":"locality"
},
  "geometry": {"coordinates":[49.75862,37.28384000000001],"type":"Point"}
}