{
  "type": "Feature",
  "properties": {
    "gn:admin1_code":"4.0",
    "gn:asciiname":"Kuseychi",
    "gn:country_code":"IR",
    "gn:dem":738,
    "gn:feature_class":"P",
    "gn:feature_code":"PPL",
    "gn:name":"K\u016bseych\u012b",
    "gn:population":0,
    "gn:timezone":"Asia/Tehran",
    "iso:country":"IR",
    "name:fas_x_preferred":[
        "\u06a9\u0648\u0633\u06cc\u0686\u06cc"
    ],
    "name:fas_x_variant":[
        "\u06a9\u0648\u0633\u06cc\u0686\u06cc \u0628\u0627\u0644\u0627",
        "\u06a9\u0648\u0633\u06cc\u0686\u06cc \u067e\u0627\u0626\u06cc\u0646"
    ],
    "name:und_x_variant":[
        "K\u016bseych\u012b",
        "K\u016bseych\u012b-ye B\u0101l\u0101",
        "K\u016bseych\u012b-ye P\u0101\u2019\u012bn"
    ],
    "wof:name":"Kuseychi",
    "wof:placetype":"locality"
},
  "geometry": {"coordinates":[59.18415,26.71118],"type":"Point"}
}