{
  "type": "Feature",
  "properties": {
    "gn:admin1_code":"5.0",
    "gn:asciiname":"Tall-e Siah",
    "gn:country_code":"IR",
    "gn:dem":2003,
    "gn:feature_class":"P",
    "gn:feature_code":"PPL",
    "gn:name":"Tall-e S\u012b\u0101h",
    "gn:population":0,
    "gn:timezone":"Asia/Tehran",
    "iso:country":"IR",
    "name:fas_x_preferred":[
        "Tall-e S\u012b\u0101h"
    ],
    "name:fas_x_variant":[
        "\u062a\u0644 \u0633\u06cc\u0627\u0647"
    ],
    "wof:name":"Tall-e Siah",
    "wof:placetype":"locality"
},
  "geometry": {"coordinates":[51.46252,30.64673],"type":"Point"}
}