{
  "type": "Feature",
  "properties": {
    "gn:admin1_code":"7",
    "gn:asciiname":"`Aliabad-e Sofla",
    "gn:country_code":"IR",
    "gn:dem":1741,
    "gn:feature_class":"P",
    "gn:feature_code":"PPL",
    "gn:name":"\u2018Al\u012b\u0101b\u0101d-e Sofl\u00e1",
    "gn:population":0,
    "gn:timezone":"Asia/Tehran",
    "iso:country":"IR",
    "name:fas_x_preferred":[
        "\u0639\u0644\u06cc \u0622\u0628\u0627\u062f \u06a9\u0627\u0645\u0641\u06cc\u0631\u0648\u0632 \u0633\u0641\u0644\u06cc"
    ],
    "name:fas_x_variant":[
        "\u2018Al\u012b\u0101b\u0101d-e P\u0101\u2019\u012bn",
        "\u2018Al\u012b\u0101b\u0101d-e K\u0101mf\u012br\u016bz-e Sofl\u00e1",
        "\u0639\u0644\u06cc \u0622\u0628\u0627\u062f \u0633\u0641\u0644\u06cc",
        "\u0639\u0644\u06cc\u200c\u0622\u0628\u0627\u062f \u0633\u0641\u0644\u06cc"
    ],
    "name:msa_x_preferred":[
        "Aliabad-e Sofla"
    ],
    "name:und_x_variant":[
        "\u2018Al\u012b\u0101b\u0101d-e Sofl\u00e1"
    ],
    "wof:name":"`Aliabad-e Sofla",
    "wof:placetype":"locality"
},
  "geometry": {"coordinates":[52.1964,30.3541],"type":"Point"}
}