{
  "type": "Feature",
  "properties": {
    "gn:admin1_code":"9",
    "gn:asciiname":"Kaka `Abbas",
    "gn:country_code":"IR",
    "gn:dem":1768,
    "gn:feature_class":"P",
    "gn:feature_code":"PPL",
    "gn:name":"K\u0101k\u0101 \u2018Abb\u0101s",
    "gn:population":0,
    "gn:timezone":"Asia/Tehran",
    "iso:country":"IR",
    "name:fas_x_preferred":[
        "\u06a9\u0627\u06a9\u0627 \u0639\u0628\u0627\u0633"
    ],
    "name:fas_x_variant":[
        "\u0643\u064e\u0643 \u0639\u064e\u0628\u0651\u0627\u0633",
        "K\u0101k\u0101 \u2018Abb\u0101s"
    ],
    "name:und_x_variant":[
        "Kak \u2018Abb\u0101s"
    ],
    "wof:name":"Kaka `Abbas",
    "wof:placetype":"locality"
},
  "geometry": {"coordinates":[48.04102,35.65652],"type":"Point"}
}