{
  "type": "Feature",
  "properties": {
    "gn:admin1_code":"38",
    "gn:asciiname":"Parchkuh",
    "gn:country_code":"IR",
    "gn:dem":1725,
    "gn:feature_class":"P",
    "gn:feature_code":"PPL",
    "gn:name":"Parchk\u016bh",
    "gn:population":0,
    "gn:timezone":"Asia/Tehran",
    "iso:country":"IR",
    "name:ceb_x_preferred":[
        "Parchk\u016bh"
    ],
    "name:fas_x_preferred":[
        "\u067e\u064e\u0631\u0686\u064e\u0647\u0643\u0648\u0647"
    ],
    "name:fas_x_variant":[
        "Parchk\u016bh",
        "\u067e\u0631\u0686\u0643\u0648\u0647",
        "\u067e\u0631\u0686\u06a9\u0648\u0647"
    ],
    "name:swe_x_preferred":[
        "Parchk\u016bh"
    ],
    "name:und_x_variant":[
        "Parchahk\u016bh",
        "\u067e\u0631\u0686\u0643\u0648\u0647"
    ],
    "wof:name":"Parchkuh",
    "wof:placetype":"locality"
},
  "geometry": {"coordinates":[50.1727,36.63233],"type":"Point"}
}