{
  "type": "Feature",
  "properties": {
    "gn:admin1_code":"8",
    "gn:asciiname":"Aseyyed Mohammad",
    "gn:country_code":"IR",
    "gn:dem":-11,
    "gn:feature_class":"P",
    "gn:feature_code":"PPL",
    "gn:name":"\u0100seyyed Mo\u1e29ammad",
    "gn:population":0,
    "gn:timezone":"Asia/Tehran",
    "iso:country":"IR",
    "name:fas_x_preferred":[
        "\u0622\u0633\u06cc\u062f \u0645\u062d\u0645\u062f"
    ],
    "name:fas_x_variant":[
        "\u0100s\u012bd Mo\u1e29ammad"
    ],
    "name:und_x_variant":[
        "\u0100seyyed Mo\u1e29ammad"
    ],
    "wof:name":"Aseyyed Mohammad",
    "wof:placetype":"locality"
},
  "geometry": {"coordinates":[49.26017,37.37152],"type":"Point"}
}