{
  "type": "Feature",
  "properties": {
    "gn:admin1_code":"42",
    "gn:asciiname":"Sadrabad",
    "gn:country_code":"IR",
    "gn:dem":1143,
    "gn:feature_class":"P",
    "gn:feature_code":"PPL",
    "gn:name":"\u015eadr\u0101b\u0101d",
    "gn:population":0,
    "gn:timezone":"Asia/Tehran",
    "iso:country":"IR",
    "name:fas_x_preferred":[
        "\u0635\u062f\u0631 \u0622\u0628\u0627\u062f"
    ],
    "name:fas_x_variant":[
        "\u015eadr\u0101b\u0101d"
    ],
    "wof:name":"Sadrabad",
    "wof:placetype":"locality"
},
  "geometry": {"coordinates":[58.81476,36.11059],"type":"Point"}
}