{
  "type": "Feature",
  "properties": {
    "gn:admin1_code":"7",
    "gn:asciiname":"Mashtakan",
    "gn:country_code":"IR",
    "gn:dem":1731,
    "gn:feature_class":"P",
    "gn:feature_code":"PPL",
    "gn:name":"Mashtak\u0101n",
    "gn:population":0,
    "gn:timezone":"Asia/Tehran",
    "iso:country":"IR",
    "name:fas_x_preferred":[
        "Mashtak\u0101n"
    ],
    "name:fas_x_variant":[
        "\u0645\u0634\u062a\u06a9\u0627\u0646",
        "\u0627\u0633\u0644\u0627\u0645 \u0622\u0628\u0627\u062f"
    ],
    "name:und_x_variant":[
        "Esl\u0101m\u0101b\u0101d"
    ],
    "wof:name":"Mashtakan",
    "wof:placetype":"locality"
},
  "geometry": {"coordinates":[52.3216,30.0286],"type":"Point"}
}