{
  "type": "Feature",
  "properties": {
    "gn:admin1_code":"25.0",
    "gn:asciiname":"Salmabad",
    "gn:country_code":"IR",
    "gn:dem":1618,
    "gn:feature_class":"P",
    "gn:feature_code":"PPLF",
    "gn:name":"Salm\u0101b\u0101d",
    "gn:population":0,
    "gn:timezone":"Asia/Tehran",
    "iso:country":"IR",
    "name:fas_x_preferred":[
        "Salm\u0101b\u0101d"
    ],
    "name:fas_x_variant":[
        "\u0633\u0644\u0645 \u0622\u0628\u0627\u062f"
    ],
    "name:nld_x_preferred":[
        "Salmbad"
    ],
    "name:nno_x_preferred":[
        "Salmabad"
    ],
    "wof:name":"Salmabad",
    "wof:placetype":"locality"
},
  "geometry": {"coordinates":[54.57825,35.43552000000001],"type":"Point"}
}