{
  "type": "Feature",
  "properties": {
    "iso:country":"IR",
    "name:ara_x_preferred":[
        "\u0628\u0646\u0627\u0628"
    ],
    "name:azb_x_preferred":[
        "\u0628\u0646\u0627\u0628"
    ],
    "name:aze_x_preferred":[
        "Bunab"
    ],
    "name:aze_x_variant":[
        "\u0628\u06cc\u0646\u0626\u0648"
    ],
    "name:ceb_x_preferred":[
        "Bon\u0101b"
    ],
    "name:deu_x_preferred":[
        "Bonab"
    ],
    "name:eng_x_preferred":[
        "Bonab"
    ],
    "name:fas_x_preferred":[
        "\u0628\u0646\u0627\u0628"
    ],
    "name:fas_x_variant":[
        "Bon\u0101b"
    ],
    "name:fra_x_preferred":[
        "Bonab"
    ],
    "name:hin_x_preferred":[
        "\u092c\u0947\u0928\u093e\u092c"
    ],
    "name:hye_x_preferred":[
        "\u0532\u0578\u0576\u0561\u0562"
    ],
    "name:ita_x_preferred":[
        "Bonab"
    ],
    "name:mlg_x_preferred":[
        "Bonab"
    ],
    "name:msa_x_preferred":[
        "Bonab"
    ],
    "name:nld_x_preferred":[
        "Bonab"
    ],
    "name:pnb_x_preferred":[
        "\u0628\u0646\u0627\u0628"
    ],
    "name:pol_x_preferred":[
        "Bonab"
    ],
    "name:ron_x_preferred":[
        "Benab"
    ],
    "name:rus_x_preferred":[
        "\u0411\u043e\u043d\u0430\u0431"
    ],
    "name:rus_x_variant":[
        "\u0411\u0435\u043d\u0430\u0431"
    ],
    "name:swe_x_preferred":[
        "Bon\u0101b"
    ],
    "name:tgk_x_preferred":[
        "\u0411\u0443\u043d\u043e\u0431"
    ],
    "name:tur_x_preferred":[
        "Bunab"
    ],
    "name:unk_x_variant":[
        "Bin\u0101b"
    ],
    "name:urd_x_preferred":[
        "\u0628\u0646\u0627\u0628"
    ],
    "name:zho_x_preferred":[
        "\u535a\u7d0d\u535c"
    ],
    "qs:gn_country":"IR",
    "qs:gn_fcode":"PPL",
    "qs:gn_pop":80359,
    "qs:name":"Binab",
    "qs:name_adm0":"Iran",
    "qs:name_adm1":"Azarbayjan-e Sharqi",
    "qs:photos":0,
    "qs:photos_1k":0,
    "qs:photos_9k":0,
    "qs:photos_9r":0,
    "qs:photos_all":0,
    "qs:photos_sr":0,
    "qs:placetype":"Town",
    "qs:pop_sr":"8",
    "qs:woe_adm0":23424851,
    "wd:wordcount":201,
    "wof:name":"Binab",
    "wof:placetype":"locality",
    "wof:population":80359
},
  "geometry": {"coordinates":[46.0561,37.3404],"type":"Point"}
}