{
  "type": "Feature",
  "properties": {
    "gn:admin1_code":"35.0",
    "gn:asciiname":"Baslkuh",
    "gn:country_code":"IR",
    "gn:dem":-7,
    "gn:feature_class":"P",
    "gn:feature_code":"PPL",
    "gn:name":"Baslk\u016bh",
    "gn:population":0,
    "gn:timezone":"Asia/Tehran",
    "iso:country":"IR",
    "name:fas_x_preferred":[
        "Ba\u015fl K\u016bh"
    ],
    "name:fas_x_variant":[
        "\u0628\u0635\u0644 \u06a9\u0648\u0647",
        "\u0628\u0633\u0644\u06a9\u0648\u0647",
        "\u0628\u0635\u0644\u200c\u06a9\u0648\u0647"
    ],
    "name:und_x_variant":[
        "Baslk\u016bh"
    ],
    "wof:name":"Baslkuh",
    "wof:placetype":"locality"
},
  "geometry": {"coordinates":[50.76091,36.86708],"type":"Point"}
}