{
  "type": "Feature",
  "properties": {
    "gn:admin1_code":"35.0",
    "gn:asciiname":"Pa'in Baziar",
    "gn:country_code":"IR",
    "gn:dem":34,
    "gn:feature_class":"P",
    "gn:feature_code":"PPL",
    "gn:name":"P\u0101\u2019\u012bn B\u0101z\u012b\u0101r",
    "gn:population":0,
    "gn:timezone":"Asia/Tehran",
    "iso:country":"IR",
    "name:fas_x_preferred":[
        "\u067e\u0627\u0626\u064a\u0646 \u0628\u0627\u0632\u064a\u0627\u0631"
    ],
    "name:fas_x_variant":[
        "\u067e\u0627\u0626\u064a\u0646 \u0628\u064e\u0632\u0650\u064a\u0627\u0631",
        "\u067e\u0627\u0626\u064a\u0646 \u0628\u064e\u0632\u064a\u0627\u0631",
        "P\u0101\u2019\u012bn B\u0101z\u012b\u0101r"
    ],
    "name:und_x_variant":[
        "P\u0101\u2019\u012bn Bazey\u0101r",
        "P\u0101\u2019\u012bn Baz\u012b\u0101r",
        "P\u0101\u2019\u012bn B\u0101z\u012b\u0101r",
        "B\u0101zy\u0101r-e P\u0101\u2019\u012bn",
        "\u0628\u0627\u0632\u064a\u0627\u0631\u0650 \u067e\u0627\u0626\u064a\u0646"
    ],
    "wof:name":"Pa'in Baziar",
    "wof:placetype":"locality"
},
  "geometry": {"coordinates":[52.53199,36.42161],"type":"Point"}
}