{
  "type": "Feature",
  "properties": {
    "gn:admin1_code":"36",
    "gn:asciiname":"Tuzlu",
    "gn:country_code":"IR",
    "gn:dem":1867,
    "gn:feature_class":"P",
    "gn:feature_code":"PPL",
    "gn:name":"T\u016bzl\u016b",
    "gn:population":0,
    "gn:timezone":"Asia/Tehran",
    "iso:country":"IR",
    "name:azb_x_preferred":[
        "\u062a\u0648\u0632\u0644\u0648"
    ],
    "name:fas_x_preferred":[
        "\u062a\u0648\u0632\u0644\u0648"
    ],
    "name:fas_x_variant":[
        "Towzl\u016b"
    ],
    "name:und_x_variant":[
        "Toozloo",
        "T\u016bzl\u016b",
        "Tozl\u016b"
    ],
    "wof:name":"Tuzlu",
    "wof:placetype":"locality"
},
  "geometry": {"coordinates":[48.58083,35.6551],"type":"Point"}
}