{
  "type": "Feature",
  "properties": {
    "gn:admin1_code":"32",
    "gn:asciiname":"Hoseyn Hajjilu",
    "gn:country_code":"IR",
    "gn:dem":816,
    "gn:feature_class":"P",
    "gn:feature_code":"PPL",
    "gn:name":"\u1e28oseyn \u1e28\u0101jj\u012bl\u016b",
    "gn:population":0,
    "gn:timezone":"Asia/Tehran",
    "iso:country":"IR",
    "name:fas_x_preferred":[
        "\u062d\u0633\u064a\u0646 \u062d\u0627\u062c\u06cc \u0644\u0648"
    ],
    "name:fas_x_variant":[
        "\u1e28oseyn \u1e28\u0101jj\u012bl\u016b"
    ],
    "wof:name":"Hoseyn Hajjilu",
    "wof:placetype":"locality"
},
  "geometry": {"coordinates":[47.6536,39.2167],"type":"Point"}
}