{
  "type": "Feature",
  "properties": {
    "gn:admin1_code":"15",
    "gn:asciiname":"Keykavus-e Aghajari",
    "gn:country_code":"IR",
    "gn:dem":328,
    "gn:feature_class":"P",
    "gn:feature_code":"PPL",
    "gn:name":"Keyk\u0101v\u016bs-e \u0100gh\u0101j\u0101r\u012b",
    "gn:population":0,
    "gn:timezone":"Asia/Tehran",
    "iso:country":"IR",
    "name:fas_x_preferred":[
        "\u06a9\u06cc\u06a9\u0627\u0648\u0633 \u0622\u063a\u0627\u062c\u0627\u0631\u06cc"
    ],
    "name:fas_x_variant":[
        "Mo\u1e29ammad \u0100q\u0101jar\u012b",
        "Keyk\u0101v\u016bs-e \u0100gh\u0101j\u0101r\u012b",
        "\u0622\u063a\u0627\u062c\u0631\u06cc",
        "\u0645\u062d\u0645\u062f \u0622\u0642\u0627 \u0622\u0642\u0627\u062a\u062c\u0627\u0631\u06cc"
    ],
    "name:und_x_variant":[
        "\u0100gh\u0101jar\u012b",
        "Mo\u1e29ammad \u0100q\u0101 \u0100q\u0101jar\u012b"
    ],
    "wof:name":"Keykavus-e Aghajari",
    "wof:placetype":"locality"
},
  "geometry": {"coordinates":[50.1641,30.7331],"type":"Point"}
}