{
  "type": "Feature",
  "properties": {
    "gn:admin1_code":"33",
    "gn:asciiname":"Qurchi Kandi",
    "gn:country_code":"IR",
    "gn:dem":1874,
    "gn:feature_class":"P",
    "gn:feature_code":"PPL",
    "gn:name":"Q\u016brch\u012b Kand\u012b",
    "gn:population":0,
    "gn:timezone":"Asia/Tehran",
    "iso:country":"IR",
    "name:fas_x_preferred":[
        "Q\u016brch\u012b Kand\u012b"
    ],
    "wof:name":"Qurchi Kandi",
    "wof:placetype":"locality"
},
  "geometry": {"coordinates":[47.08333,38.38333],"type":"Point"}
}