{
  "type": "Feature",
  "properties": {
    "gn:admin1_code":"15",
    "gn:asciiname":"Keft-e Geleh",
    "gn:country_code":"IR",
    "gn:dem":878,
    "gn:feature_class":"P",
    "gn:feature_code":"PPL",
    "gn:name":"Keft-e Geleh",
    "gn:population":0,
    "gn:timezone":"Asia/Tehran",
    "iso:country":"IR",
    "name:fas_x_preferred":[
        "\u06a9\u0641\u062a \u06af\u0644\u0647"
    ],
    "wof:name":"Keft-e Geleh",
    "wof:placetype":"locality"
},
  "geometry": {"coordinates":[49.94694000000001,31.9867],"type":"Point"}
}