{
  "type": "Feature",
  "properties": {
    "gn:admin1_code":"16.0",
    "gn:asciiname":"Miraki",
    "gn:country_code":"IR",
    "gn:dem":1885,
    "gn:feature_class":"P",
    "gn:feature_code":"PPL",
    "gn:name":"M\u012brak\u012b",
    "gn:population":0,
    "gn:timezone":"Asia/Tehran",
    "iso:country":"IR",
    "name:fas_x_preferred":[
        "\u0645\u06cc\u0631\u06a9\u06cc"
    ],
    "name:fas_x_variant":[
        "M\u012brak\u012b"
    ],
    "wof:name":"Miraki",
    "wof:placetype":"locality"
},
  "geometry": {"coordinates":[47.29156,35.43584],"type":"Point"}
}