{
  "type": "Feature",
  "properties": {
    "gn:admin1_code":"15",
    "gn:asciiname":"Sardat",
    "gn:country_code":"IR",
    "gn:dem":1164,
    "gn:feature_class":"P",
    "gn:feature_code":"PPL",
    "gn:name":"Sardat",
    "gn:population":0,
    "gn:timezone":"Asia/Tehran",
    "iso:country":"IR",
    "name:fas_x_preferred":[
        "\u0633\u064e\u0631\u062f\u064e\u062a"
    ],
    "wof:name":"Sardat",
    "wof:placetype":"locality"
},
  "geometry": {"coordinates":[50.31667,31.56667],"type":"Point"}
}