{
  "type": "Feature",
  "properties": {
    "gn:admin1_code":"33",
    "gn:asciiname":"Kazi-Kandi",
    "gn:country_code":"IR",
    "gn:dem":1719,
    "gn:feature_class":"P",
    "gn:feature_code":"PPL",
    "gn:name":"Kazi-Kandi",
    "gn:population":0,
    "gn:timezone":"Asia/Tehran",
    "iso:country":"IR",
    "name:fas_x_preferred":[
        "\u0642\u0627\u0636\u06cc \u0643\u0646\u062f"
    ],
    "name:fas_x_variant":[
        "Q\u0101\u1e95\u012bkand\u012b",
        "Q\u0101\u1e95\u012b Kand",
        "\u0642\u0627\u0636\u06cc \u06a9\u0646\u062f\u06cc"
    ],
    "wof:name":"Kazi-Kandi",
    "wof:placetype":"locality"
},
  "geometry": {"coordinates":[48.02751,37.30314],"type":"Point"}
}