{
  "type": "Feature",
  "properties": {
    "gn:admin1_code":"26.0",
    "gn:asciiname":"Pakdasht",
    "gn:country_code":"IR",
    "gn:dem":1030,
    "gn:feature_class":"P",
    "gn:feature_code":"PPLA2",
    "gn:name":"P\u0101kdasht",
    "gn:population":0,
    "gn:timezone":"Asia/Tehran",
    "iso:country":"IR",
    "name:ara_x_preferred":[
        "\u0628\u0627\u0643\u062f\u0634\u062a"
    ],
    "name:aze_x_preferred":[
        "Pakd\u0259\u015ft"
    ],
    "name:epo_x_preferred":[
        "Pakda\u015dt"
    ],
    "name:fas_x_preferred":[
        "\u067e\u0627\u06a9\u062f\u0634\u062a"
    ],
    "name:fas_x_variant":[
        "\u0645\u0627\u0645\u0627\u0632\u0627\u0646"
    ],
    "name:fin_x_preferred":[
        "Pakdasht"
    ],
    "name:fra_x_preferred":[
        "Pakdacht"
    ],
    "name:hin_x_preferred":[
        "\u092a\u093e\u0915\u0926\u0936\u094d\u0924"
    ],
    "name:ita_x_preferred":[
        "Pakdasht"
    ],
    "name:mlg_x_preferred":[
        "Pakdasht"
    ],
    "name:pnb_x_preferred":[
        "\u067e\u0627\u06a9 \u062f\u0634\u062a"
    ],
    "name:pol_x_preferred":[
        "Pakdaszt"
    ],
    "name:rus_x_preferred":[
        "\u041f\u0430\u043a\u0434\u0435\u0448\u0442"
    ],
    "name:swe_x_preferred":[
        "Pakdasht"
    ],
    "name:tur_x_preferred":[
        "Pakde\u015ft"
    ],
    "name:und_x_variant":[
        "P\u0101kdasht",
        "M\u0101m\u0101z\u0101n"
    ],
    "name:urd_x_preferred":[
        "\u067e\u0627\u06a9\u062f\u0634\u062a"
    ],
    "name:zho_x_preferred":[
        "\u5e15\u514b\u9054\u4ec0\u7279"
    ],
    "wof:name":"Pakdasht",
    "wof:placetype":"locality"
},
  "geometry": {"coordinates":[51.6834,35.47854],"type":"Point"}
}