{
  "type": "Feature",
  "properties": {
    "gn:admin1_code":"32",
    "gn:asciiname":"Qeshlaq-e Moradlu",
    "gn:country_code":"IR",
    "gn:dem":354,
    "gn:feature_class":"P",
    "gn:feature_code":"PPL",
    "gn:name":"Qeshl\u0101q-e Mor\u0101dl\u016b",
    "gn:population":0,
    "gn:timezone":"Asia/Tehran",
    "iso:country":"IR",
    "name:fas_x_preferred":[
        "\u0645\u064f\u0631\u0627\u062f\u0644\u0648 \u0622\u0642 \u0628\u064f\u0631\u0648\u0646"
    ],
    "name:fas_x_variant":[
        "Qeshl\u0101q-e Mor\u0101dl\u016b",
        "\u0642\u0650\u0634\u0644\u0627\u0642\u0650 \u0645\u064f\u0631\u0627\u062f\u0644\u0648"
    ],
    "name:und_x_variant":[
        "Mor\u0101dl\u016b \u0100q Bor\u016bn"
    ],
    "wof:name":"Qeshlaq-e Moradlu",
    "wof:placetype":"locality"
},
  "geometry": {"coordinates":[48.08333,39.26667],"type":"Point"}
}