{
  "type": "Feature",
  "properties": {
    "gn:admin1_code":"23",
    "gn:asciiname":"Asiabaleh",
    "gn:country_code":"IR",
    "gn:dem":1032,
    "gn:feature_class":"P",
    "gn:feature_code":"PPL",
    "gn:name":"\u0100s\u012b\u0101baleh",
    "gn:population":0,
    "gn:timezone":"Asia/Tehran",
    "iso:country":"IR",
    "name:fas_x_preferred":[
        "\u0622\u0633\u064a\u0627\u0648\u064e\u0644\u0650\u0647"
    ],
    "name:fas_x_variant":[
        "\u0622\u0633\u06cc\u0627\u0628\u0644\u0647",
        "\u0100s\u012b\u0101valeh",
        "\u0100s\u012b\u0101baleh"
    ],
    "wof:name":"Asiabaleh",
    "wof:placetype":"locality"
},
  "geometry": {"coordinates":[47.1362,33.6765],"type":"Point"}
}