{
  "type": "Feature",
  "properties": {
    "gn:admin1_code":"23",
    "gn:asciiname":"Ja`farbagi-ye Sofla",
    "gn:country_code":"IR",
    "gn:dem":1964,
    "gn:feature_class":"P",
    "gn:feature_code":"PPL",
    "gn:name":"Ja\u2018farbag\u012b-ye Sofl\u00e1",
    "gn:population":0,
    "gn:timezone":"Asia/Tehran",
    "iso:country":"IR",
    "name:fas_x_preferred":[
        "Ja\u2018farbag\u012b-ye Sofl\u00e1"
    ],
    "name:fas_x_variant":[
        "\u062c\u0639\u0641\u0631\u0628\u06af\u06cc \u0633\u0641\u0644\u06cc",
        "\u062c\u0639\u0641\u0631\u0628\u06a9 \u0633\u0641\u0644\u06cc",
        "\u062c\u0627\u0641\u0631 \u0628\u06cc\u06af\u06cc \u0633\u0641\u0644\u06cc"
    ],
    "name:und_x_variant":[
        "Ja\u2018farbek-e Sofl\u00e1",
        "J\u0101far Beyg\u012b-ye Sofl\u00e1"
    ],
    "wof:name":"Ja`farbagi-ye Sofla",
    "wof:placetype":"locality"
},
  "geometry": {"coordinates":[48.20017,34.02959],"type":"Point"}
}