{
  "type": "Feature",
  "properties": {
    "gn:admin1_code":"5.0",
    "gn:asciiname":"Deh-e Bar Aftab",
    "gn:country_code":"IR",
    "gn:dem":1908,
    "gn:feature_class":"P",
    "gn:feature_code":"PPL",
    "gn:name":"Deh-e Bar \u0100ft\u0101b",
    "gn:population":0,
    "gn:timezone":"Asia/Tehran",
    "iso:country":"IR",
    "name:fas_x_preferred":[
        "Deh-e Bar \u0100ft\u0101b"
    ],
    "name:fas_x_variant":[
        "\u062f\u0647 \u0628\u0631 \u0622\u0641\u062a\u0627\u0628"
    ],
    "wof:name":"Deh-e Bar Aftab",
    "wof:placetype":"locality"
},
  "geometry": {"coordinates":[51.23552,30.84192],"type":"Point"}
}