{
  "type": "Feature",
  "properties": {
    "gn:admin1_code":"1",
    "gn:asciiname":"`Eyn ol Rrum",
    "gn:country_code":"IR",
    "gn:dem":1734,
    "gn:feature_class":"P",
    "gn:feature_code":"PPL",
    "gn:name":"\u2018Eyn ol Rr\u016bm",
    "gn:population":0,
    "gn:timezone":"Asia/Tehran",
    "iso:country":"IR",
    "name:fas_x_preferred":[
        "\u0639\u06cc\u0646 \u0627\u0644\u0631\u0651\u0648\u0645"
    ],
    "name:fas_x_variant":[
        "\u2018Eyn or R\u016bm",
        "\u2018Eyn ol Rr\u016bm"
    ],
    "wof:name":"`Eyn ol Rrum",
    "wof:placetype":"locality"
},
  "geometry": {"coordinates":[45.13399999999999,37.1767],"type":"Point"}
}