{
  "type": "Feature",
  "properties": {
    "gn:admin1_code":"41",
    "gn:asciiname":"Kalateh-ye Tak-e Samad",
    "gn:country_code":"IR",
    "gn:dem":1730,
    "gn:feature_class":"P",
    "gn:feature_code":"PPL",
    "gn:name":"Kal\u0101teh-ye Tak-e \u015eamad",
    "gn:population":0,
    "gn:timezone":"Asia/Tehran",
    "iso:country":"IR",
    "name:fas_x_preferred":[
        "Kal\u0101teh-ye Tak-e \u015eamad"
    ],
    "name:fas_x_variant":[
        "Tak-e \u015eamad",
        "\u06a9\u0644\u0627\u062a\u0647 \u062a\u06a9 \u0635\u0645\u062f",
        "\u062a\u06a9 \u0635\u0645\u062f"
    ],
    "name:und_x_variant":[
        "\u06a9\u0644\u0627\u062a\u0647 \u062a\u06a9 \u0635\u0645\u062f"
    ],
    "wof:name":"Kalateh-ye Tak-e Samad",
    "wof:placetype":"locality"
},
  "geometry": {"coordinates":[59.23392,32.81174],"type":"Point"}
}