{
  "type": "Feature",
  "properties": {
    "gn:admin1_code":"32",
    "gn:asciiname":"Khan Beyli",
    "gn:country_code":"IR",
    "gn:dem":1178,
    "gn:feature_class":"P",
    "gn:feature_code":"PPL",
    "gn:name":"Kh\u0101n Beyl\u012b",
    "gn:population":0,
    "gn:timezone":"Asia/Tehran",
    "iso:country":"IR",
    "name:fas_x_preferred":[
        "\u062e\u0627\u0646\u06cc \u0628\u064e\u0628\u064e\u0647\u0644\u0648"
    ],
    "name:fas_x_variant":[
        "Kh\u0101n\u012b Babahl\u016b",
        "\u062e\u0627\u0646 \u0628\u06cc\u0644\u06cc",
        "\u062e\u0627\u0646 \u0628\u0628\u0644\u06cc",
        "\u062e\u0627\u0646 \u0628\u06cc\u0644\u062f\u06cc"
    ],
    "name:und_x_variant":[
        "Kh\u0101n Beyl\u012b",
        "Kh\u0101n Babl\u012b",
        "Kh\u0101n Beyld\u012b"
    ],
    "wof:name":"Khan Beyli",
    "wof:placetype":"locality"
},
  "geometry": {"coordinates":[47.88262,38.70907],"type":"Point"}
}