{
  "type": "Feature",
  "properties": {
    "gn:admin1_code":"1",
    "gn:asciiname":"Kord Kandi",
    "gn:country_code":"IR",
    "gn:dem":896,
    "gn:feature_class":"P",
    "gn:feature_code":"PPL",
    "gn:name":"Kord Kand\u012b",
    "gn:population":0,
    "gn:timezone":"Asia/Tehran",
    "iso:country":"IR",
    "name:fas_x_preferred":[
        "\u06a9\u0631\u062f \u06a9\u0646\u062f\u06cc"
    ],
    "name:fas_x_variant":[
        "\u062d\u064f\u0633\u0650\u064a\u0646\u0639\u064e\u0644\u0626 \u0643\u064e\u0646\u062f\u06cc \u0643\u064f\u0631\u062f",
        "\u1e28oseyn\u2018al\u012b-ye Kand\u012b Kord",
        "Kord Kand\u012b",
        "\u06a9\u0631\u062f\u06a9\u0646\u062f\u06cc"
    ],
    "wof:name":"Kord Kandi",
    "wof:placetype":"locality"
},
  "geometry": {"coordinates":[44.8644,39.276],"type":"Point"}
}