{
  "type": "Feature",
  "properties": {
    "gn:admin1_code":"15",
    "gn:asciiname":"Omm ol Emamid",
    "gn:country_code":"IR",
    "gn:dem":116,
    "gn:feature_class":"P",
    "gn:feature_code":"PPL",
    "gn:name":"Omm ol Em\u0101m\u012bd",
    "gn:population":0,
    "gn:timezone":"Asia/Tehran",
    "iso:country":"IR",
    "name:ara_x_preferred":[
        "\u062a\u0644 \u0632\u0631\u0646\u064a"
    ],
    "name:fas_x_preferred":[
        "\u0627\u0645 \u0627\u0644\u0627\u0645\u0627\u0645\u06cc"
    ],
    "name:fas_x_variant":[
        "\u062a\u0644 \u0632\u0631\u0651\u06cc\u0646\u06cc",
        "Omm ol Em\u0101m\u012b",
        "Tall-e Zarr\u012bn\u012b",
        "\u0627\u0645 \u0627\u0644\u0627\u0645\u0627\u0645\u06cc\u062f",
        "\u062a\u0644\u200c\u0632\u0631\u06cc\u0646\u06cc"
    ],
    "name:und_x_variant":[
        "Omm ol Em\u0101m\u012bd"
    ],
    "wof:name":"Omm ol Emamid",
    "wof:placetype":"locality"
},
  "geometry": {"coordinates":[49.47049000000001,31.24038],"type":"Point"}
}