{
  "type": "Feature",
  "properties": {
    "gn:admin1_code":"41",
    "gn:asciiname":"Chah-e Mian Chengu",
    "gn:country_code":"IR",
    "gn:dem":1616,
    "gn:feature_class":"P",
    "gn:feature_code":"PPLL",
    "gn:name":"Ch\u0101h-e M\u012b\u0101n Cheng\u016b",
    "gn:population":0,
    "gn:timezone":"Asia/Tehran",
    "iso:country":"IR",
    "name:fas_x_preferred":[
        "Ch\u0101h Cheng\u016b"
    ],
    "name:fas_x_variant":[
        "\u0686\u0627\u0647 \u0645\u064a\u0627\u0646 \u0686\u0646\u06af\u0648",
        "\u06a9\u0644\u0627\u062a\u0647 \u06a9\u0627\u0648\u0647"
    ],
    "name:und_x_variant":[
        "Ch\u0101r Chungu",
        "Chah\u0101r Cheng\u016b",
        "Ch\u0101h-e M\u012b\u0101n Cheng\u016b",
        "Kal\u0101teh-ye K\u0101veh"
    ],
    "wof:name":"Chah-e Mian Chengu",
    "wof:placetype":"locality"
},
  "geometry": {"coordinates":[59.26793000000001,33.59709],"type":"Point"}
}