{
  "type": "Feature",
  "properties": {
    "gn:admin1_code":"28",
    "gn:asciiname":"Hasan Hafez",
    "gn:country_code":"IR",
    "gn:dem":1838,
    "gn:feature_class":"P",
    "gn:feature_code":"PPL",
    "gn:name":"\u1e28asan \u1e28\u0101fez\u0327",
    "gn:population":0,
    "gn:timezone":"Asia/Tehran",
    "iso:country":"IR",
    "name:fas_x_preferred":[
        "\u1e28asan \u1e28\u0101fez\u0327"
    ],
    "name:fas_x_variant":[
        "\u062d\u0633\u0646 \u062d\u0627\u0641\u0638",
        "\u0645\u062d\u0644\u0647 \u062d\u0633\u0646 \u062d\u0627\u0641\u0638"
    ],
    "name:und_x_variant":[
        "Rob\u0101\u0163-e \u1e28asan \u1e28\u0101fez",
        "Hasan H\u0101fiz",
        "\u062d\u0633\u0646 \u062d\u0627\u0641\u0638",
        "Ma\u1e29alleh-ye \u1e28asan \u1e28\u0101fez\u0327"
    ],
    "wof:name":"Hasan Hafez",
    "wof:placetype":"locality"
},
  "geometry": {"coordinates":[50.25386,33.44205],"type":"Point"}
}