{
  "type": "Feature",
  "properties": {
    "gn:admin1_code":"8",
    "gn:asciiname":"Lapuneh Kesh",
    "gn:country_code":"IR",
    "gn:dem":1746,
    "gn:feature_class":"P",
    "gn:feature_code":"PPL",
    "gn:name":"L\u0101p\u016bneh Kesh",
    "gn:population":0,
    "gn:timezone":"Asia/Tehran",
    "iso:country":"IR",
    "name:fas_x_preferred":[
        "\u0644\u0627\u067e\u0648\u0646\u0647 \u06a9\u0634"
    ],
    "name:fas_x_variant":[
        "L\u0101p\u016bneh Kesh"
    ],
    "wof:name":"Lapuneh Kesh",
    "wof:placetype":"locality"
},
  "geometry": {"coordinates":[48.715,37.8892],"type":"Point"}
}