{
  "type": "Feature",
  "properties": {
    "gn:admin1_code":"29",
    "gn:asciiname":"Karimabad-e Ansari",
    "gn:country_code":"IR",
    "gn:dem":705,
    "gn:feature_class":"P",
    "gn:feature_code":"PPL",
    "gn:name":"Kar\u012bm\u0101b\u0101d-e An\u015f\u0101r\u012b",
    "gn:population":0,
    "gn:timezone":"Asia/Tehran",
    "iso:country":"IR",
    "name:ara_x_preferred":[
        "\u0643\u0631\u064a\u0645\u200c\u0622\u0628\u0627\u062f \u0627\u0646\u0635\u0627\u0631\u064a"
    ],
    "name:ceb_x_preferred":[
        "Kar\u012bm\u0101b\u0101d-e An\u015f\u0101r\u012b"
    ],
    "name:fas_x_preferred":[
        "\u06a9\u0631\u06cc\u0645 \u0622\u0628\u0627\u062f \u0627\u0646\u0635\u0627\u0631\u06cc"
    ],
    "name:fas_x_variant":[
        "Kar\u012bm\u0101b\u0101d",
        "Kar\u012bm\u0101b\u0101d-e An\u015f\u0101r\u012b",
        "\u06a9\u0631\u06cc\u0645\u200c\u0622\u0628\u0627\u062f \u0627\u0646\u0635\u0627\u0631\u06cc"
    ],
    "name:swe_x_preferred":[
        "Kar\u012bm\u0101b\u0101d-e An\u015f\u0101r\u012b"
    ],
    "name:und_x_variant":[
        "Kar\u012bm\u0101b\u0101d An\u015f\u0101r\u012b"
    ],
    "wof:name":"Karimabad-e Ansari",
    "wof:placetype":"locality"
},
  "geometry": {"coordinates":[58.85162,28.90912],"type":"Point"}
}