{
  "type": "Feature",
  "properties": {
    "gn:admin1_code":"40",
    "gn:asciiname":"Bowz",
    "gn:country_code":"IR",
    "gn:dem":2257,
    "gn:feature_class":"P",
    "gn:feature_code":"PPL",
    "gn:name":"Bowz",
    "gn:population":0,
    "gn:timezone":"Asia/Tehran",
    "iso:country":"IR",
    "name:fas_x_preferred":[
        "\u0628\u064f\u0648\u0632"
    ],
    "wof:name":"Bowz",
    "wof:placetype":"locality"
},
  "geometry": {"coordinates":[53.92306,31.83944],"type":"Point"}
}