{
  "type": "Feature",
  "properties": {
    "gn:admin1_code":"41.0",
    "gn:asciiname":"Mojulestan",
    "gn:country_code":"IR",
    "gn:dem":1074,
    "gn:feature_class":"P",
    "gn:feature_code":"PPLL",
    "gn:name":"Moj\u016blest\u0101n",
    "gn:population":0,
    "gn:timezone":"Asia/Tehran",
    "iso:country":"IR",
    "name:fas_x_preferred":[
        "Moj\u016blest\u0101n"
    ],
    "name:fas_x_variant":[
        "\u0645\u062c\u0648\u0644\u0633\u062a\u0627\u0646"
    ],
    "wof:name":"Mojulestan",
    "wof:placetype":"locality"
},
  "geometry": {"coordinates":[56.14303,33.52829000000001],"type":"Point"}
}