{
  "type": "Feature",
  "properties": {
    "gn:admin1_code":"7",
    "gn:asciiname":"Banesh",
    "gn:country_code":"IR",
    "gn:dem":1617,
    "gn:feature_class":"P",
    "gn:feature_code":"PPL",
    "gn:name":"B\u0101nesh",
    "gn:population":0,
    "gn:timezone":"Asia/Tehran",
    "iso:country":"IR",
    "name:fas_x_preferred":[
        "\u0628\u0627\u0646\u0634"
    ],
    "name:fas_x_variant":[
        "B\u0101nesh"
    ],
    "name:und_x_variant":[
        "B\u0101nish"
    ],
    "wof:name":"Banesh",
    "wof:placetype":"locality"
},
  "geometry": {"coordinates":[52.42825,30.09797],"type":"Point"}
}