{
  "type": "Feature",
  "properties": {
    "gn:admin1_code":"23",
    "gn:asciiname":"Rahimabad-e Yek",
    "gn:cc2":"IR",
    "gn:country_code":"IR",
    "gn:dem":1118,
    "gn:feature_class":"P",
    "gn:feature_code":"PPL",
    "gn:name":"Ra\u1e29\u012bm\u0101b\u0101d-e Yek",
    "gn:population":0,
    "gn:timezone":"Asia/Tehran",
    "iso:country":"IR",
    "name:ara_x_preferred":[
        "\u0631\u062d\u064a\u0645\u200c\u0622\u0628\u0627\u062f \u064a\u0643"
    ],
    "name:ceb_x_preferred":[
        "Ra\u1e29\u012bm\u0101b\u0101d-e Yek"
    ],
    "name:fas_x_preferred":[
        "\u0631\u064e\u062d\u064a\u0645\u0627\u0628\u0627\u062f\u0650 \u064a\u0650\u0643"
    ],
    "name:fas_x_variant":[
        "\u0686\u0650\u0646\u0627\u0631 \u062e\u064f\u0633\u0631\u064f\u0648",
        "Ra\u1e29\u012bm\u0101b\u0101d-e Yek",
        "\u0631\u062d\u06cc\u0645\u200c\u0622\u0628\u0627\u062f \u06cc\u06a9"
    ],
    "name:swe_x_preferred":[
        "Ra\u1e29\u012bm\u0101b\u0101d-e Yek"
    ],
    "name:und_x_variant":[
        "Chen\u0101r Khosrow"
    ],
    "wof:name":"Rahimabad-e Yek",
    "wof:placetype":"locality"
},
  "geometry": {"coordinates":[48.11556,33.51361],"type":"Point"}
}