{
  "type": "Feature",
  "properties": {
    "gn:admin1_code":"33.0",
    "gn:asciiname":"`Alaviq",
    "gn:country_code":"IR",
    "gn:dem":1799,
    "gn:feature_class":"P",
    "gn:feature_code":"PPL",
    "gn:name":"\u2018Alav\u012bq",
    "gn:population":0,
    "gn:timezone":"Asia/Tehran",
    "iso:country":"IR",
    "name:fas_x_preferred":[
        "\u0639\u0644\u0648\u06cc\u0642"
    ],
    "name:fas_x_variant":[
        "\u2018Alav\u012bq"
    ],
    "name:und_x_variant":[
        "Alyavi"
    ],
    "wof:name":"`Alaviq",
    "wof:placetype":"locality"
},
  "geometry": {"coordinates":[46.9848,38.7213],"type":"Point"}
}