{
  "type": "Feature",
  "properties": {
    "gn:admin1_code":"43.0",
    "gn:asciiname":"Seyu Khosavi Hajj `Ali",
    "gn:country_code":"IR",
    "gn:dem":1256,
    "gn:feature_class":"P",
    "gn:feature_code":"PPL",
    "gn:name":"Sey\u016b Khosav\u012b \u1e28\u0101jj \u2018Al\u012b",
    "gn:population":0,
    "gn:timezone":"Asia/Tehran",
    "iso:country":"IR",
    "name:fas_x_preferred":[
        "Sey\u016b Khosav\u012b \u1e28\u0101jj \u2018Al\u012b"
    ],
    "name:fas_x_variant":[
        "\u0633\u06cc\u0648\u062e\u0633\u0648\u06cc \u062d\u0627\u062c \u0639\u0644\u06cc"
    ],
    "wof:name":"Seyu Khosavi Hajj `Ali",
    "wof:placetype":"locality"
},
  "geometry": {"coordinates":[57.1471,38.15054],"type":"Point"}
}