{
  "type": "Feature",
  "properties": {
    "gn:admin1_code":"4.0",
    "gn:asciiname":"Seyyedabad",
    "gn:country_code":"IR",
    "gn:dem":1828,
    "gn:feature_class":"P",
    "gn:feature_code":"PPL",
    "gn:name":"Seyyed\u0101b\u0101d",
    "gn:population":0,
    "gn:timezone":"Asia/Tehran",
    "iso:country":"IR",
    "name:aze_x_preferred":[
        "Seyidabad"
    ],
    "name:fas_x_preferred":[
        "\u0633\u06cc\u0651\u062f \u0622\u0628\u0627\u062f"
    ],
    "name:fas_x_variant":[
        "Seyyed\u0101b\u0101d",
        "\u0633\u06cc\u062f\u0622\u0628\u0627\u062f"
    ],
    "wof:name":"Seyyedabad",
    "wof:placetype":"locality"
},
  "geometry": {"coordinates":[60.9276,28.9429],"type":"Point"}
}