{
  "type": "Feature",
  "properties": {
    "gn:admin1_code":"33.0",
    "gn:asciiname":"Kuy-e Golmohammad",
    "gn:country_code":"IR",
    "gn:dem":1285,
    "gn:feature_class":"P",
    "gn:feature_code":"PPL",
    "gn:name":"K\u016by-e Golmo\u1e29ammad",
    "gn:population":0,
    "gn:timezone":"Asia/Tehran",
    "iso:country":"IR",
    "name:fas_x_preferred":[
        "\u06a9\u0648\u06cc \u06af\u0644\u0645\u062d\u0645\u0651\u062f"
    ],
    "name:und_x_variant":[
        "K\u016by-e Golmo\u1e29ammad"
    ],
    "wof:name":"Kuy-e Golmohammad",
    "wof:placetype":"locality"
},
  "geometry": {"coordinates":[45.8099,38.4446],"type":"Point"}
}