{
  "type": "Feature",
  "properties": {
    "gn:admin1_code":"7",
    "gn:asciiname":"Sabuk",
    "gn:country_code":"IR",
    "gn:dem":1540,
    "gn:feature_class":"P",
    "gn:feature_code":"PPL",
    "gn:name":"Sab\u016bk",
    "gn:population":0,
    "gn:timezone":"Asia/Tehran",
    "iso:country":"IR",
    "name:fas_x_preferred":[
        "\u0633\u0628\u0648\u06a9"
    ],
    "name:fas_x_variant":[
        "Sab\u016bk"
    ],
    "wof:name":"Sabuk",
    "wof:placetype":"locality"
},
  "geometry": {"coordinates":[52.1432,29.3931],"type":"Point"}
}