{
  "type": "Feature",
  "properties": {
    "gn:admin1_code":"13.0",
    "gn:asciiname":"Deh-e Sanan",
    "gn:country_code":"IR",
    "gn:dem":1614,
    "gn:feature_class":"P",
    "gn:feature_code":"PPL",
    "gn:name":"Deh-e San\u0101n",
    "gn:population":0,
    "gn:timezone":"Asia/Tehran",
    "iso:country":"IR",
    "name:ceb_x_preferred":[
        "Deh-e San\u0101n"
    ],
    "name:fas_x_preferred":[
        "\u062f\u0647 \u0633\u0646\u0627\u0646"
    ],
    "name:fas_x_variant":[
        "Deh-e San\u0101n",
        "\u062f\u0647\u0633\u0646\u0627\u0646"
    ],
    "name:swe_x_preferred":[
        "Deh-e San\u0101n"
    ],
    "wof:name":"Deh-e Sanan",
    "wof:placetype":"locality"
},
  "geometry": {"coordinates":[47.5646,34.2058],"type":"Point"}
}