{
  "type": "Feature",
  "properties": {
    "gn:admin1_code":"28",
    "gn:asciiname":"Hamunabad",
    "gn:country_code":"IR",
    "gn:dem":2283,
    "gn:feature_class":"P",
    "gn:feature_code":"PPL",
    "gn:name":"H\u0101m\u016bn\u0101b\u0101d",
    "gn:population":0,
    "gn:timezone":"Asia/Tehran",
    "iso:country":"IR",
    "name:fas_x_preferred":[
        "\u0647\u0627\u0645\u0648\u0646 \u0622\u0628\u0627\u062f"
    ],
    "name:fas_x_variant":[
        "H\u0101m\u016bn\u0101b\u0101d"
    ],
    "wof:name":"Hamunabad",
    "wof:placetype":"locality"
},
  "geometry": {"coordinates":[52.7443,32.8384],"type":"Point"}
}