{
  "type": "Feature",
  "properties": {
    "gn:admin1_code":"7",
    "gn:asciiname":"Rugir-e Taj Amiri",
    "gn:country_code":"IR",
    "gn:dem":456,
    "gn:feature_class":"P",
    "gn:feature_code":"PPL",
    "gn:name":"R\u016bg\u012br-e T\u0101j Am\u012br\u012b",
    "gn:population":0,
    "gn:timezone":"Asia/Tehran",
    "iso:country":"IR",
    "name:fas_x_preferred":[
        "\u0631\u0648\u06af\u06cc\u0631 \u062a\u0627\u062c \u0627\u0645\u06cc\u0631\u06cc"
    ],
    "name:fas_x_variant":[
        "R\u016bg\u012br-e T\u0101j Am\u012br\u012b"
    ],
    "wof:name":"Rugir-e Taj Amiri",
    "wof:placetype":"locality"
},
  "geometry": {"coordinates":[53.1443,27.5569],"type":"Point"}
}