{
  "type": "Feature",
  "properties": {
    "gn:admin1_code":"38.0",
    "gn:asciiname":"Keshabad-e Bala",
    "gn:country_code":"IR",
    "gn:dem":1653,
    "gn:feature_class":"P",
    "gn:feature_code":"PPL",
    "gn:name":"Kesh\u0101b\u0101d-e B\u0101l\u0101",
    "gn:population":0,
    "gn:timezone":"Asia/Tehran",
    "iso:country":"IR",
    "name:fas_x_preferred":[
        "\u06a9\u0634 \u0622\u0628\u0627\u062f \u0639\u0644\u06cc\u0627"
    ],
    "name:fas_x_variant":[
        "Kesh\u0101b\u0101d-e \u2018Oly\u0101",
        "\u06a9\u0634 \u0622\u0628\u0627\u062f \u0628\u0627\u0644\u0627",
        "\u06a9\u0634\u200c\u0622\u0628\u0627\u062f \u0639\u0644\u06cc\u0627"
    ],
    "name:und_x_variant":[
        "Kesh\u0101b\u0101d-e B\u0101l\u0101"
    ],
    "wof:name":"Keshabad-e Bala",
    "wof:placetype":"locality"
},
  "geometry": {"coordinates":[50.0526,36.496],"type":"Point"}
}