{
  "type": "Feature",
  "properties": {
    "gn:admin1_code":"26",
    "gn:asciiname":"Akhtarabad",
    "gn:country_code":"IR",
    "gn:dem":1273,
    "gn:feature_class":"P",
    "gn:feature_code":"PPL",
    "gn:name":"Akhtar\u0101b\u0101d",
    "gn:population":0,
    "gn:timezone":"Asia/Tehran",
    "iso:country":"IR",
    "name:ceb_x_preferred":[
        "Akhtar\u0101b\u0101d"
    ],
    "name:fas_x_preferred":[
        "\u0627\u062e\u062a\u0631 \u0622\u0628\u0627\u062f"
    ],
    "name:fas_x_variant":[
        "\u0638\u064f\u0644\u0645 \u0622\u0628\u0627\u062f",
        "Akhtar\u0101b\u0101d",
        "\u0627\u062e\u062a\u0631\u0622\u0628\u0627\u062f"
    ],
    "name:swe_x_preferred":[
        "Akhtar\u0101b\u0101d"
    ],
    "name:und_x_variant":[
        "Z\u0327olm\u0101b\u0101d"
    ],
    "wof:name":"Akhtarabad",
    "wof:placetype":"locality"
},
  "geometry": {"coordinates":[50.5977,35.5917],"type":"Point"}
}