{
  "type": "Feature",
  "properties": {
    "gn:admin1_code":"40",
    "gn:asciiname":"Deh-e Mohammad",
    "gn:country_code":"IR",
    "gn:dem":1170,
    "gn:feature_class":"P",
    "gn:feature_code":"PPL",
    "gn:name":"Deh-e Mo\u1e29ammad",
    "gn:population":0,
    "gn:timezone":"Asia/Tehran",
    "iso:country":"IR",
    "name:ceb_x_preferred":[
        "Deh-e Mo\u1e29ammad"
    ],
    "name:fas_x_preferred":[
        "\u062f\u0647 \u0645\u062d\u0645\u062f"
    ],
    "name:fas_x_variant":[
        "Deh-e Mo\u1e29ammad"
    ],
    "name:swe_x_preferred":[
        "Deh-e Mo\u1e29ammad"
    ],
    "name:und_x_variant":[
        "Deh Mohammad",
        "Deh-i-Muhammad"
    ],
    "wof:name":"Deh-e Mohammad",
    "wof:placetype":"locality"
},
  "geometry": {"coordinates":[56.97998000000001,33.99044],"type":"Point"}
}