{
  "type": "Feature",
  "properties": {
    "gn:admin1_code":"8.0",
    "gn:asciiname":"Seyyedan",
    "gn:country_code":"IR",
    "gn:dem":22,
    "gn:feature_class":"P",
    "gn:feature_code":"PPL",
    "gn:name":"Seyyed\u0101n",
    "gn:population":0,
    "gn:timezone":"Asia/Tehran",
    "iso:country":"IR",
    "name:ara_x_preferred":[
        "\u0633\u064a\u062f\u0627\u0646"
    ],
    "name:aze_x_preferred":[
        "Seyidan"
    ],
    "name:ceb_x_preferred":[
        "Seyyed\u0101n"
    ],
    "name:fas_x_preferred":[
        "\u0633\u06cc\u062f\u0627\u0646"
    ],
    "name:ita_x_preferred":[
        "Seydan"
    ],
    "name:mlg_x_preferred":[
        "Seyyedan"
    ],
    "name:msa_x_preferred":[
        "Seyyedan"
    ],
    "name:rus_x_preferred":[
        "\u0421\u0435\u0439\u0435\u0434\u0430\u043d"
    ],
    "name:tur_x_preferred":[
        "Seyyidan"
    ],
    "name:urd_x_preferred":[
        "\u0633\u06cc\u062f\u0627\u0646"
    ],
    "wof:name":"Seyyedan",
    "wof:placetype":"locality"
},
  "geometry": {"coordinates":[49.69895,37.19505],"type":"Point"}
}