{
  "type": "Feature",
  "properties": {
    "gn:admin1_code":"7",
    "gn:asciiname":"Zaval",
    "gn:country_code":"IR",
    "gn:dem":1074,
    "gn:feature_class":"P",
    "gn:feature_code":"PPL",
    "gn:name":"Zav\u0101l",
    "gn:population":0,
    "gn:timezone":"Asia/Tehran",
    "iso:country":"IR",
    "name:fas_x_preferred":[
        "Zav\u0101l"
    ],
    "name:fas_x_variant":[
        "Zav\u0101l-e B\u0101l\u0101",
        "\u0632\u0648\u0627\u0644",
        "\u062e\u062f\u0627\u0628\u062e\u0634 \u0632\u0648\u0627\u0644"
    ],
    "name:msa_x_preferred":[
        "Zaval"
    ],
    "name:und_x_variant":[
        "Tang-e Zav\u0101l",
        "Sh\u012bb Zav\u0101l",
        "Zav\u0101l-e Khod\u0101 Bakhsh",
        "Khod\u0101 Bakhsh Zav\u0101l"
    ],
    "wof:name":"Zaval",
    "wof:placetype":"locality"
},
  "geometry": {"coordinates":[51.48779,30.33681],"type":"Point"}
}