{
  "type": "Feature",
  "properties": {
    "gn:admin1_code":"7",
    "gn:asciiname":"Tayun",
    "gn:country_code":"IR",
    "gn:dem":1487,
    "gn:feature_class":"P",
    "gn:feature_code":"PPL",
    "gn:name":"Tay\u016bn",
    "gn:population":0,
    "gn:timezone":"Asia/Tehran",
    "iso:country":"IR",
    "name:fas_x_preferred":[
        "\u062a\u06cc\u0648\u0646"
    ],
    "name:fas_x_variant":[
        "Taf\u012bh\u0101n",
        "Tay\u016bn"
    ],
    "name:und_x_variant":[
        "Taf\u012bum",
        "Tafy\u016bn"
    ],
    "wof:name":"Tayun",
    "wof:placetype":"locality"
},
  "geometry": {"coordinates":[52.6569,29.4187],"type":"Point"}
}