{
  "type": "Feature",
  "properties": {
    "gn:admin1_code":"35.0",
    "gn:asciiname":"Hotel-e Javaher",
    "gn:country_code":"IR",
    "gn:dem":1774,
    "gn:feature_class":"P",
    "gn:feature_code":"PPL",
    "gn:name":"Hotel-e Jav\u0101her",
    "gn:population":0,
    "gn:timezone":"Asia/Tehran",
    "iso:country":"IR",
    "name:fas_x_preferred":[
        "\u0647\u062a\u0644 \u062c\u0648\u0627\u0647\u0631"
    ],
    "name:und_x_variant":[
        "Hotel-e Jav\u0101her"
    ],
    "wof:name":"Hotel-e Javaher",
    "wof:placetype":"locality"
},
  "geometry": {"coordinates":[50.47346,36.85562],"type":"Point"}
}