{
  "type": "Feature",
  "properties": {
    "gn:admin1_code":"29",
    "gn:asciiname":"Shahrak-e Azadegan",
    "gn:country_code":"IR",
    "gn:dem":645,
    "gn:feature_class":"P",
    "gn:feature_code":"PPL",
    "gn:name":"Shahrak-e \u0100z\u0101deg\u0101n",
    "gn:population":0,
    "gn:timezone":"Asia/Tehran",
    "iso:country":"IR",
    "name:fas_x_preferred":[
        "\u0634\u0647\u0631\u0643 \u0622\u0632\u0627\u062f\u06af\u0627\u0646"
    ],
    "name:fas_x_variant":[
        "Shahrak-e \u0100z\u0101deg\u0101n"
    ],
    "wof:name":"Shahrak-e Azadegan",
    "wof:placetype":"locality"
},
  "geometry": {"coordinates":[57.8827,28.5372],"type":"Point"}
}