{
  "type": "Feature",
  "properties": {
    "gn:admin1_code":"7.0",
    "gn:asciiname":"Kohneh Darz",
    "gn:country_code":"IR",
    "gn:dem":716,
    "gn:feature_class":"P",
    "gn:feature_code":"PPL",
    "gn:name":"Kohneh Darz",
    "gn:population":0,
    "gn:timezone":"Asia/Tehran",
    "iso:country":"IR",
    "name:fas_x_preferred":[
        "\u06a9\u0647\u0646\u0647 \u062f\u0631\u0632"
    ],
    "wof:name":"Kohneh Darz",
    "wof:placetype":"locality"
},
  "geometry": {"coordinates":[55.39475,27.86419],"type":"Point"}
}