{
  "type": "Feature",
  "properties": {
    "gn:admin1_code":"23.0",
    "gn:asciiname":"Shabasi",
    "gn:country_code":"IR",
    "gn:dem":1644,
    "gn:feature_class":"P",
    "gn:feature_code":"PPL",
    "gn:name":"Shabas\u012b",
    "gn:population":0,
    "gn:timezone":"Asia/Tehran",
    "iso:country":"IR",
    "name:fas_x_preferred":[
        "\u0634\u064e\u0628\u064e\u0633\u06cc"
    ],
    "name:fas_x_variant":[
        "Shabas\u012b"
    ],
    "wof:name":"Shabasi",
    "wof:placetype":"locality"
},
  "geometry": {"coordinates":[48.22389,33.74778],"type":"Point"}
}