{
  "type": "Feature",
  "properties": {
    "gn:admin1_code":"35.0",
    "gn:asciiname":"Shahrak-e Kushan Sara",
    "gn:country_code":"IR",
    "gn:dem":219,
    "gn:feature_class":"P",
    "gn:feature_code":"PPL",
    "gn:name":"Shahrak-e K\u016bsh\u0101n Sar\u0101",
    "gn:population":0,
    "gn:timezone":"Asia/Tehran",
    "iso:country":"IR",
    "name:und_x_variant":[
        "Shahrak-e K\u016bsh\u0101n Sar\u0101",
        "\u0634\u0647\u0631\u06a9 \u06a9\u0648\u0634\u0627\u0646 \u0633\u0631\u0627"
    ],
    "wof:name":"Shahrak-e Kushan Sara",
    "wof:placetype":"locality"
},
  "geometry": {"coordinates":[50.98351,36.6929],"type":"Point"}
}