{
  "type": "Feature",
  "properties": {
    "gn:admin1_code":"29.0",
    "gn:asciiname":"Tang Lu",
    "gn:country_code":"IR",
    "gn:dem":2036,
    "gn:feature_class":"P",
    "gn:feature_code":"PPL",
    "gn:name":"Tang L\u016b",
    "gn:population":0,
    "gn:timezone":"Asia/Tehran",
    "iso:country":"IR",
    "name:fas_x_preferred":[
        "\u062a\u0646\u06af \u0644\u0648"
    ],
    "name:und_x_variant":[
        "Tang L\u016b"
    ],
    "wof:name":"Tang Lu",
    "wof:placetype":"locality"
},
  "geometry": {"coordinates":[56.45983,31.06932],"type":"Point"}
}