{
  "type": "Feature",
  "properties": {
    "gn:admin1_code":"10",
    "gn:asciiname":"Sarab-e Noql",
    "gn:country_code":"IR",
    "gn:dem":605,
    "gn:feature_class":"P",
    "gn:feature_code":"PPL",
    "gn:name":"Sar\u0101b-e Noql",
    "gn:population":0,
    "gn:timezone":"Asia/Tehran",
    "iso:country":"IR",
    "name:fas_x_preferred":[
        "\u0633\u0631\u0627\u0628 \u0646\u0642\u0644"
    ],
    "name:fas_x_variant":[
        "Sar\u0101b-e Noql",
        "\u0633\u0631\u0627\u0628\u0646\u0642\u0644"
    ],
    "name:msa_x_preferred":[
        "Sarab-e Noql"
    ],
    "wof:name":"Sarab-e Noql",
    "wof:placetype":"locality"
},
  "geometry": {"coordinates":[47.7229,32.8448],"type":"Point"}
}