{
  "type": "Feature",
  "properties": {
    "gn:admin1_code":"32",
    "gn:asciiname":"Kalfar",
    "gn:country_code":"IR",
    "gn:dem":1181,
    "gn:elevation":"0.0",
    "gn:feature_class":"P",
    "gn:feature_code":"PPL",
    "gn:name":"Kalfar",
    "gn:population":0,
    "gn:timezone":"Asia/Tehran",
    "iso:country":"IR",
    "name:fas_x_preferred":[
        "\u0643\u064e\u0644\u0647\u0648\u0631"
    ],
    "name:fas_x_variant":[
        "\u06a9\u0644\u0641\u06cc\u0631",
        "Kalh\u016br",
        "Kalf\u012br",
        "\u06a9\u0644\u0641\u0631",
        "\u06a9\u0644\u0647\u0631"
    ],
    "name:und_x_variant":[
        "Kalhor"
    ],
    "wof:name":"Kalfar",
    "wof:placetype":"locality"
},
  "geometry": {"coordinates":[47.49800000000001,38.3695],"type":"Point"}
}