{
  "type": "Feature",
  "properties": {
    "gn:admin1_code":"42.0",
    "gn:asciiname":"Talkhak",
    "gn:country_code":"IR",
    "gn:dem":1524,
    "gn:feature_class":"P",
    "gn:feature_code":"PPL",
    "gn:name":"Talkhak",
    "gn:population":0,
    "gn:timezone":"Asia/Tehran",
    "iso:country":"IR",
    "wof:name":"Talkhak",
    "wof:placetype":"locality"
},
  "geometry": {"coordinates":[60.68778,35.54667],"type":"Point"}
}