{
  "type": "Feature",
  "properties": {
    "gn:admin1_code":"28.0",
    "gn:asciiname":"Mahalleh-ye Koli Cheh",
    "gn:country_code":"IR",
    "gn:dem":1585,
    "gn:feature_class":"P",
    "gn:feature_code":"PPL",
    "gn:name":"Ma\u1e29alleh-ye Kol\u012b Cheh",
    "gn:population":0,
    "gn:timezone":"Asia/Tehran",
    "iso:country":"IR",
    "name:fas_x_preferred":[
        "\u0645\u062d\u0644\u0647 \u06a9\u0644\u06cc \u0686\u0647"
    ],
    "name:und_x_variant":[
        "Ma\u1e29alleh-ye Kol\u012b Cheh"
    ],
    "wof:name":"Mahalleh-ye Koli Cheh",
    "wof:placetype":"locality"
},
  "geometry": {"coordinates":[51.6016,32.66084],"type":"Point"}
}