{
  "type": "Feature",
  "properties": {
    "gn:admin1_code":"8.0",
    "gn:asciiname":"Birin",
    "gn:country_code":"IR",
    "gn:dem":1905,
    "gn:feature_class":"P",
    "gn:feature_code":"PPL",
    "gn:name":"B\u012br\u012bn",
    "gn:population":0,
    "gn:timezone":"Asia/Tehran",
    "iso:country":"IR",
    "name:fas_x_preferred":[
        "\u0628\u06cc\u0631\u06cc\u0646"
    ],
    "name:und_x_variant":[
        "B\u012br\u012bn"
    ],
    "wof:name":"Birin",
    "wof:placetype":"locality"
},
  "geometry": {"coordinates":[48.62086,37.88148],"type":"Point"}
}