{
  "type": "Feature",
  "properties": {
    "gn:admin1_code":"23",
    "gn:asciiname":"Jamshidabad",
    "gn:country_code":"IR",
    "gn:dem":1730,
    "gn:feature_class":"P",
    "gn:feature_code":"PPL",
    "gn:name":"Jamsh\u012bd\u0101b\u0101d",
    "gn:population":0,
    "gn:timezone":"Asia/Tehran",
    "iso:country":"IR",
    "name:fas_x_preferred":[
        "\u062c\u064e\u0645\u0634\u064a\u062f \u0622\u0628\u0627\u062f"
    ],
    "name:fas_x_variant":[
        "\u062c\u0645\u0634\u06cc\u062f \u0622\u0628\u0627\u062f",
        "Jamsh\u012bd\u0101b\u0101d",
        "\u062c\u0645\u0634\u06cc\u062f\u0622\u0628\u0627\u062f"
    ],
    "wof:name":"Jamshidabad",
    "wof:placetype":"locality"
},
  "geometry": {"coordinates":[47.6781,34.1428],"type":"Point"}
}