{
  "type": "Feature",
  "properties": {
    "gn:admin1_code":"15",
    "gn:asciiname":"Talkhab-e Kalat",
    "gn:country_code":"IR",
    "gn:dem":397,
    "gn:feature_class":"P",
    "gn:feature_code":"PPL",
    "gn:name":"Talkh\u0101b-e Kal\u0101t",
    "gn:population":0,
    "gn:timezone":"Asia/Tehran",
    "iso:country":"IR",
    "name:fas_x_preferred":[
        "\u062a\u0644\u062e\u0627\u0628 \u06a9\u0644\u0627\u062a"
    ],
    "name:fas_x_variant":[
        "Talkh\u0101b-e Kal\u0101t"
    ],
    "wof:name":"Talkhab-e Kalat",
    "wof:placetype":"locality"
},
  "geometry": {"coordinates":[49.0605,32.14852],"type":"Point"}
}