{
  "type": "Feature",
  "properties": {
    "gn:admin1_code":"13",
    "gn:asciiname":"Gomeshtar-e `Olya",
    "gn:country_code":"IR",
    "gn:dem":1340,
    "gn:feature_class":"P",
    "gn:feature_code":"PPL",
    "gn:name":"Gomeshtar-e \u2018Oly\u0101",
    "gn:population":0,
    "gn:timezone":"Asia/Tehran",
    "iso:country":"IR",
    "name:fas_x_preferred":[
        "\u06af\u0645\u0634\u062a\u0631 \u0639\u0644\u06cc\u0627"
    ],
    "name:fas_x_variant":[
        "Gomeshtar-e \u2018Oly\u0101"
    ],
    "wof:name":"Gomeshtar-e `Olya",
    "wof:placetype":"locality"
},
  "geometry": {"coordinates":[46.589,34.6667],"type":"Point"}
}