{
  "type": "Feature",
  "properties": {
    "gn:admin1_code":"4",
    "gn:asciiname":"Deh-e Hajj `Alikhan-e Bala",
    "gn:country_code":"IR",
    "gn:dem":1375,
    "gn:feature_class":"P",
    "gn:feature_code":"PPL",
    "gn:name":"Deh-e \u1e28\u0101jj \u2018Al\u012bkh\u0101n-e B\u0101l\u0101",
    "gn:population":0,
    "gn:timezone":"Asia/Tehran",
    "iso:country":"IR",
    "name:fas_x_preferred":[
        "\u062f\u0647 \u062d\u0627\u062c \u0639\u0644\u06cc\u062e\u0627\u0646 \u0628\u0627\u0644\u0627"
    ],
    "name:fas_x_variant":[
        "Deh-e \u1e28\u0101jj \u2018Al\u012bkh\u0101n-e B\u0101l\u0101"
    ],
    "wof:name":"Deh-e Hajj `Alikhan-e Bala",
    "wof:placetype":"locality"
},
  "geometry": {"coordinates":[60.27186,29.12803],"type":"Point"}
}