{
  "type": "Feature",
  "properties": {
    "gn:admin1_code":"42",
    "gn:asciiname":"Salan Guch",
    "gn:country_code":"IR",
    "gn:dem":1544,
    "gn:feature_class":"P",
    "gn:feature_code":"PPL",
    "gn:name":"S\u0101l\u0101n G\u016bch",
    "gn:population":0,
    "gn:timezone":"Asia/Tehran",
    "iso:country":"IR",
    "name:ceb_x_preferred":[
        "S\u0101l\u0101n G\u016bch"
    ],
    "name:fas_x_preferred":[
        "S\u0101l\u0101n G\u016bch"
    ],
    "name:fas_x_variant":[
        "S\u0101l\u0101nf\u016bj",
        "\u0633\u0627\u0644\u0627\u0646 \u06af\u0648\u0686",
        "S\u0101l\u0101nq\u016bch",
        "\u0633\u0627\u0644\u0627\u0646 \u0642\u0648\u0686"
    ],
    "name:swe_x_preferred":[
        "S\u0101l\u0101n G\u016bch"
    ],
    "name:und_x_variant":[
        "S\u0101l\u0101nq\u016bch",
        "\u0633\u0627\u0644\u0627\u0646 \u06af\u0648\u0686"
    ],
    "wof:name":"Salan Guch",
    "wof:placetype":"locality"
},
  "geometry": {"coordinates":[58.42797,37.24314],"type":"Point"}
}