{
  "type": "Feature",
  "properties": {
    "gn:admin1_code":"33",
    "gn:asciiname":"Dizaj `Azim",
    "gn:country_code":"IR",
    "gn:dem":1711,
    "gn:feature_class":"P",
    "gn:feature_code":"PPL",
    "gn:name":"D\u012bzaj \u2018Az\u0327\u012bm",
    "gn:population":0,
    "gn:timezone":"Asia/Tehran",
    "iso:country":"IR",
    "name:fas_x_preferred":[
        "\u062f\u06cc\u0632\u062c \u0639\u0638\u06cc\u0645"
    ],
    "name:fas_x_variant":[
        "D\u012bzaj \u2018Az\u0327\u012bm"
    ],
    "wof:name":"Dizaj `Azim",
    "wof:placetype":"locality"
},
  "geometry": {"coordinates":[47.5231,37.9698],"type":"Point"}
}