{
  "type": "Feature",
  "properties": {
    "gn:admin1_code":"4.0",
    "gn:asciiname":"Nukabad",
    "gn:country_code":"IR",
    "gn:dem":1222,
    "gn:feature_class":"P",
    "gn:feature_code":"PPL",
    "gn:name":"N\u016bk\u0101b\u0101d",
    "gn:population":0,
    "gn:timezone":"Asia/Tehran",
    "iso:country":"IR",
    "name:fas_x_preferred":[
        "\u0646\u0648\u06a9 \u0622\u0628\u0627\u062f"
    ],
    "name:fas_x_variant":[
        "Gol Sh\u016bd\u0101n",
        "N\u016bk\u0101b\u0101d"
    ],
    "wof:name":"Nukabad",
    "wof:placetype":"locality"
},
  "geometry": {"coordinates":[61.03971,26.68327],"type":"Point"}
}