{
  "type": "Feature",
  "properties": {
    "gn:admin1_code":"4",
    "gn:asciiname":"Shahd-e Ashiru",
    "gn:country_code":"IR",
    "gn:dem":1542,
    "gn:feature_class":"P",
    "gn:feature_code":"PPL",
    "gn:name":"Shahd-e Ash\u012br\u016b",
    "gn:population":0,
    "gn:timezone":"Asia/Tehran",
    "iso:country":"IR",
    "name:fas_x_preferred":[
        "\u0634\u0647\u062f \u0627\u0634\u06cc\u0631\u0648"
    ],
    "name:fas_x_variant":[
        "Shahd-e Ash\u012br\u016b"
    ],
    "wof:name":"Shahd-e Ashiru",
    "wof:placetype":"locality"
},
  "geometry": {"coordinates":[60.6681,28.5034],"type":"Point"}
}