{
  "type": "Feature",
  "properties": {
    "gn:admin1_code":"1",
    "gn:asciiname":"Jol",
    "gn:country_code":"IR",
    "gn:dem":1458,
    "gn:feature_class":"P",
    "gn:feature_code":"PPL",
    "gn:name":"Jol",
    "gn:population":0,
    "gn:timezone":"Asia/Tehran",
    "iso:country":"IR",
    "name:deu_x_preferred":[
        "Jol"
    ],
    "name:fas_x_preferred":[
        "\u062c\u064f\u0644"
    ],
    "name:fas_x_variant":[
        "\u062c\u0644"
    ],
    "name:fra_x_preferred":[
        "Jol"
    ],
    "name:nld_x_preferred":[
        "Jol"
    ],
    "name:nno_x_preferred":[
        "Jol"
    ],
    "name:nor_x_preferred":[
        "Jol"
    ],
    "wof:name":"Jol",
    "wof:placetype":"locality"
},
  "geometry": {"coordinates":[44.7009,39.4491],"type":"Point"}
}