{
  "type": "Feature",
  "properties": {
    "gn:admin1_code":"42.0",
    "gn:asciiname":"Esfak",
    "gn:country_code":"IR",
    "gn:dem":1028,
    "gn:feature_class":"P",
    "gn:feature_code":"PPL",
    "gn:name":"E\u015ff\u0101k",
    "gn:population":0,
    "gn:timezone":"Asia/Tehran",
    "iso:country":"IR",
    "name:ara_x_preferred":[
        "\u0623\u0633\u0641\u0643"
    ],
    "name:ceb_x_preferred":[
        "E\u015ff\u0101k"
    ],
    "name:fas_x_preferred":[
        "E\u015ff\u0101k"
    ],
    "name:fas_x_variant":[
        "\u0627\u0635\u0641\u0627\u06a9",
        "Asp\u0101k",
        "A\u015ff\u0101k"
    ],
    "name:swe_x_preferred":[
        "E\u015ff\u0101k"
    ],
    "name:und_x_variant":[
        "Asp\u0101k",
        "A\u015ff\u0101k",
        "Asopak",
        "\u0627\u0635\u0641\u0627\u06a9"
    ],
    "wof:name":"Esfak",
    "wof:placetype":"locality"
},
  "geometry": {"coordinates":[57.21321,34.0334],"type":"Point"}
}