{
  "type": "Feature",
  "properties": {
    "gn:admin1_code":"1",
    "gn:asciiname":"Zoor Abad",
    "gn:country_code":"IR",
    "gn:dem":1706,
    "gn:feature_class":"P",
    "gn:feature_code":"PPL",
    "gn:name":"Zoor Abad",
    "gn:population":0,
    "gn:timezone":"Asia/Tehran",
    "iso:country":"IR",
    "name:fas_x_preferred":[
        "Z\u016br\u0101b\u0101d"
    ],
    "name:und_x_variant":[
        "Zuhr\u0101b\u0101d"
    ],
    "wof:name":"Zoor Abad",
    "wof:placetype":"locality"
},
  "geometry": {"coordinates":[44.58361,38.80389],"type":"Point"}
}