{
  "type": "Feature",
  "properties": {
    "gn:admin1_code":"15",
    "gn:asciiname":"Takht-e Golzar",
    "gn:country_code":"IR",
    "gn:dem":879,
    "gn:feature_class":"P",
    "gn:feature_code":"PPL",
    "gn:name":"Takht-e Golz\u0101r",
    "gn:population":0,
    "gn:timezone":"Asia/Tehran",
    "iso:country":"IR",
    "name:fas_x_preferred":[
        "\u062a\u062e\u062a \u06af\u0644\u0632\u0627\u0631"
    ],
    "name:fas_x_variant":[
        "P\u0101-ye Takht-e Golz\u0101r",
        "Takht-e Golz\u0101r"
    ],
    "wof:name":"Takht-e Golzar",
    "wof:placetype":"locality"
},
  "geometry": {"coordinates":[48.3829,32.8469],"type":"Point"}
}