{
  "type": "Feature",
  "properties": {
    "gn:admin1_code":"7",
    "gn:asciiname":"Zighan",
    "gn:country_code":"IR",
    "gn:dem":462,
    "gn:feature_class":"P",
    "gn:feature_code":"PPL",
    "gn:name":"Z\u012bgh\u0101n",
    "gn:population":0,
    "gn:timezone":"Asia/Tehran",
    "iso:country":"IR",
    "name:fas_x_preferred":[
        "\u0632\u06cc\u063a\u0627\u0646"
    ],
    "name:fas_x_variant":[
        "Z\u012bgh\u0101n",
        "\u0632\u06cc\u0642\u0627\u0646"
    ],
    "name:msa_x_preferred":[
        "Zighan"
    ],
    "name:und_x_variant":[
        "Z\u012bq\u0101n"
    ],
    "wof:name":"Zighan",
    "wof:placetype":"locality"
},
  "geometry": {"coordinates":[52.7407,27.5953],"type":"Point"}
}