{
  "type": "Feature",
  "properties": {
    "gn:admin1_code":"13",
    "gn:asciiname":"Sarab-e Karian",
    "gn:country_code":"IR",
    "gn:dem":1268,
    "gn:feature_class":"P",
    "gn:feature_code":"PPL",
    "gn:name":"Sar\u0101b-e Kar\u012b\u0101n",
    "gn:population":0,
    "gn:timezone":"Asia/Tehran",
    "iso:country":"IR",
    "name:ceb_x_preferred":[
        "Kar\u012b\u0101n"
    ],
    "name:fas_x_preferred":[
        "\u0633\u0631\u0622\u0628\u06a9\u0631\u06cc\u0627\u0646"
    ],
    "name:swe_x_preferred":[
        "Kar\u012b\u0101n"
    ],
    "wof:name":"Sarab-e Karian",
    "wof:placetype":"locality"
},
  "geometry": {"coordinates":[47.02778,33.88833],"type":"Point"}
}