{
  "type": "Feature",
  "properties": {
    "gn:admin1_code":"13",
    "gn:asciiname":"Sarab-e Karian",
    "gn:country_code":"IR",
    "gn:dem":1268,
    "gn:feature_class":"P",
    "gn:feature_code":"PPL",
    "gn:name":"Sar\u0101b-e Kar\u012b\u0101n",
    "gn:population":0,
    "gn:timezone":"Asia/Tehran",
    "iso:country":"IR",
    "wof:name":"Sarab-e Karian",
    "wof:placetype":"locality"
},
  "geometry": {"coordinates":[47.02778,33.88833],"type":"Point"}
}