{
  "type": "Feature",
  "properties": {
    "gn:admin1_code":"9",
    "gn:asciiname":"Kand Tappeh",
    "gn:country_code":"IR",
    "gn:dem":2140,
    "gn:feature_class":"P",
    "gn:feature_code":"PPL",
    "gn:name":"Kand Tappeh",
    "gn:population":0,
    "gn:timezone":"Asia/Tehran",
    "iso:country":"IR",
    "name:ceb_x_preferred":[
        "Kand Tappeh"
    ],
    "name:fas_x_preferred":[
        "\u0643\u0646\u062f \u062a\u067e\u0647"
    ],
    "name:fas_x_variant":[
        "\u06a9\u0646\u062f\u062a\u067e\u0647"
    ],
    "name:msa_x_preferred":[
        "Kand Tappeh"
    ],
    "name:swe_x_preferred":[
        "Kand Tappeh"
    ],
    "name:und_x_variant":[
        "Kand Tepe",
        "Kand Tappeh"
    ],
    "wof:name":"Kand Tappeh",
    "wof:placetype":"locality"
},
  "geometry": {"coordinates":[48.30522,35.20134],"type":"Point"}
}