{
  "type": "Feature",
  "properties": {
    "gn:admin1_code":"34",
    "gn:asciiname":"Khanabad",
    "gn:country_code":"IR",
    "gn:dem":1723,
    "gn:feature_class":"P",
    "gn:feature_code":"PPL",
    "gn:name":"Kh\u0101n\u0101b\u0101d",
    "gn:population":0,
    "gn:timezone":"Asia/Tehran",
    "iso:country":"IR",
    "name:fas_x_preferred":[
        "\u062e\u0627\u0646 \u0622\u0628\u0627\u062f"
    ],
    "name:fas_x_variant":[
        "Kh\u0101n\u0101b\u0101d"
    ],
    "wof:name":"Khanabad",
    "wof:placetype":"locality"
},
  "geometry": {"coordinates":[49.292,34.61199999999999],"type":"Point"}
}