{
  "type": "Feature",
  "properties": {
    "gn:admin1_code":"34",
    "gn:asciiname":"Khanabad",
    "gn:country_code":"IR",
    "gn:dem":1723,
    "gn:feature_class":"P",
    "gn:feature_code":"PPL",
    "gn:name":"Kh\u0101n\u0101b\u0101d",
    "gn:population":0,
    "gn:timezone":"Asia/Tehran",
    "iso:country":"IR",
    "name:aze_x_preferred":[
        "Xanabad"
    ],
    "name:ceb_x_preferred":[
        "Khanabad"
    ],
    "name:deu_x_preferred":[
        "Chanabad"
    ],
    "name:fas_x_preferred":[
        "\u062e\u0627\u0646 \u0622\u0628\u0627\u062f"
    ],
    "name:fas_x_variant":[
        "Kh\u0101n\u0101b\u0101d",
        "\u062e\u0627\u0646\u200c\u0622\u0628\u0627\u062f"
    ],
    "name:fra_x_preferred":[
        "Khanabad"
    ],
    "name:ita_x_preferred":[
        "Xanabad"
    ],
    "name:kat_x_preferred":[
        "\u10ee\u10d0\u10dc\u10d0\u10d1\u10d0\u10d3\u10d8"
    ],
    "name:rus_x_preferred":[
        "\u0425\u0430\u043d\u0430\u0431\u0430\u0434"
    ],
    "name:swe_x_preferred":[
        "Khanabad"
    ],
    "name:ukr_x_preferred":[
        "\u0425\u0430\u043d\u0430\u0431\u0430\u0434"
    ],
    "name:uzb_x_preferred":[
        "Xonobod"
    ],
    "wof:name":"Khanabad",
    "wof:placetype":"locality"
},
  "geometry": {"coordinates":[49.292,34.61199999999999],"type":"Point"}
}