{
  "type": "Feature",
  "properties": {
    "gn:admin1_code":"44",
    "gn:asciiname":"Ardakan",
    "gn:country_code":"IR",
    "gn:dem":1853,
    "gn:feature_class":"P",
    "gn:feature_code":"PPL",
    "gn:name":"\u0100rdak\u0101n",
    "gn:population":0,
    "gn:timezone":"Asia/Tehran",
    "iso:country":"IR",
    "name:fas_x_preferred":[
        "Ardak\u0101n"
    ],
    "name:fas_x_variant":[
        "\u0100rdak\u0101n",
        "\u0622\u0631\u062f\u0643\u0627\u0646",
        "\u0627\u0631\u062f\u0643\u0627\u0646",
        "\u0622\u0631\u062f\u06a9\u0627\u0646"
    ],
    "name:msa_x_preferred":[
        "Ardakan"
    ],
    "name:pol_x_preferred":[
        "Ardakan"
    ],
    "name:und_x_variant":[
        "\u0627\u0631\u062f\u0643\u0627\u0646",
        "\u0622\u0631\u062f\u0643\u0627\u0646"
    ],
    "name:urd_x_preferred":[
        "\u0627\u0631\u062f\u06a9\u0627\u0646"
    ],
    "wof:name":"Ardakan",
    "wof:placetype":"locality"
},
  "geometry": {"coordinates":[50.70806,36.18648],"type":"Point"}
}