{
  "type": "Feature",
  "properties": {
    "gn:admin1_code":"29",
    "gn:asciiname":"Dehnow",
    "gn:country_code":"IR",
    "gn:dem":1949,
    "gn:feature_class":"P",
    "gn:feature_code":"PPLL",
    "gn:name":"Dehnow",
    "gn:population":0,
    "gn:timezone":"Asia/Tehran",
    "iso:country":"IR",
    "name:azb_x_preferred":[
        "\u062f\u0647 \u0646\u0648"
    ],
    "name:ceb_x_preferred":[
        "Dehnow"
    ],
    "name:fas_x_preferred":[
        "\u062f\u0647\u0646\u0648"
    ],
    "name:fas_x_variant":[
        "\u062f\u0647\u200c\u0646\u0648"
    ],
    "name:sco_x_preferred":[
        "Dehnow"
    ],
    "name:swe_x_preferred":[
        "Dehnow"
    ],
    "wof:name":"Dehnow",
    "wof:placetype":"locality"
},
  "geometry": {"coordinates":[58.16412,28.89115],"type":"Point"}
}