{
  "type": "Feature",
  "properties": {
    "gn:admin1_code":"5",
    "gn:asciiname":"Torab-e Vosta",
    "gn:country_code":"IR",
    "gn:dem":664,
    "gn:feature_class":"P",
    "gn:feature_code":"PPL",
    "gn:name":"Tor\u0101b-e Vos\u0163\u00e1",
    "gn:population":0,
    "gn:timezone":"Asia/Tehran",
    "iso:country":"IR",
    "name:fas_x_preferred":[
        "\u062a\u0631\u0627\u0628 \u0648\u0633\u0637\u06cc"
    ],
    "name:fas_x_variant":[
        "Tor\u0101b-e Vos\u0163\u00e1"
    ],
    "wof:name":"Torab-e Vosta",
    "wof:placetype":"locality"
},
  "geometry": {"coordinates":[50.49457,30.94738],"type":"Point"}
}