{
  "type": "Feature",
  "properties": {
    "gn:admin1_code":"7",
    "gn:asciiname":"Porzi",
    "gn:country_code":"IR",
    "gn:dem":446,
    "gn:feature_class":"P",
    "gn:feature_code":"PPL",
    "gn:name":"Porz\u012b",
    "gn:population":0,
    "gn:timezone":"Asia/Tehran",
    "iso:country":"IR",
    "name:fas_x_preferred":[
        "\u067e\u0631\u0632\u06cc"
    ],
    "name:fas_x_variant":[
        "Pord\u012b",
        "Porz\u012b"
    ],
    "name:msa_x_preferred":[
        "Porzi"
    ],
    "name:und_x_variant":[
        "Y\u016bz\u012b"
    ],
    "wof:name":"Porzi",
    "wof:placetype":"locality"
},
  "geometry": {"coordinates":[53.0176,27.6883],"type":"Point"}
}