{
  "type": "Feature",
  "properties": {
    "gn:admin1_code":"11",
    "gn:asciiname":"Dozak",
    "gn:country_code":"IR",
    "gn:dem":372,
    "gn:feature_class":"P",
    "gn:feature_code":"PPL",
    "gn:name":"Dozak",
    "gn:population":0,
    "gn:timezone":"Asia/Tehran",
    "iso:country":"IR",
    "name:fas_x_preferred":[
        "\u062f\u0632\u06a9"
    ],
    "name:fas_x_variant":[
        "\u062f\u064f\u0632\u064e\u06af",
        "\u062f\u0650\u0632\u0650\u0643\u0650\u0647"
    ],
    "name:und_x_variant":[
        "Dezekeh",
        "Dozag",
        "Dozak"
    ],
    "wof:name":"Dozak",
    "wof:placetype":"locality"
},
  "geometry": {"coordinates":[56.26912,27.39202],"type":"Point"}
}