{
  "type": "Feature",
  "properties": {
    "gn:admin1_code":"34.0",
    "gn:asciiname":"Khorram Dasht",
    "gn:country_code":"IR",
    "gn:dem":1951,
    "gn:feature_class":"P",
    "gn:feature_code":"PPL",
    "gn:name":"Khorram Dasht",
    "gn:population":0,
    "gn:timezone":"Asia/Tehran",
    "iso:country":"IR",
    "name:fas_x_preferred":[
        "\u062e\u0631\u0645 \u062f\u0634\u062a"
    ],
    "name:und_x_variant":[
        "\u062e\u0631\u0645 \u062f\u0634\u062a"
    ],
    "wof:name":"Khorram Dasht",
    "wof:placetype":"locality"
},
  "geometry": {"coordinates":[49.87763,33.67547],"type":"Point"}
}