{
  "type": "Feature",
  "properties": {
    "gn:admin1_code":"10.0",
    "gn:asciiname":"Nowcheh Galan",
    "gn:country_code":"IR",
    "gn:dem":916,
    "gn:feature_class":"P",
    "gn:feature_code":"PPL",
    "gn:name":"Nowcheh G\u0101l\u0101n",
    "gn:population":0,
    "gn:timezone":"Asia/Tehran",
    "iso:country":"IR",
    "name:fas_x_preferred":[
        "\u0646\u0648\u0686\u0647 \u06af\u0627\u0644\u0627\u0646"
    ],
    "name:und_x_variant":[
        "Nowcheh G\u0101l\u0101n"
    ],
    "wof:name":"Nowcheh Galan",
    "wof:placetype":"locality"
},
  "geometry": {"coordinates":[46.91941,33.36466],"type":"Point"}
}