{
  "type": "Feature",
  "properties": {
    "gn:admin1_code":"4.0",
    "gn:asciiname":"Mohammadabad",
    "gn:country_code":"IR",
    "gn:dem":481,
    "gn:feature_class":"P",
    "gn:feature_code":"PPL",
    "gn:name":"Mo\u1e29ammad\u0101b\u0101d",
    "gn:population":0,
    "gn:timezone":"Asia/Tehran",
    "iso:country":"IR",
    "name:aze_x_preferred":[
        "M\u0259h\u0259mm\u0259dabad"
    ],
    "name:bpy_x_preferred":[
        "\u09ae\u09cb\u09b9\u09be\u09ae\u09cd\u09ae\u09a6\u09be\u09ac\u09be\u09a6"
    ],
    "name:ceb_x_preferred":[
        "Mohammadabad"
    ],
    "name:fas_x_preferred":[
        "\u0645\u062d\u0645\u0651\u062f \u0622\u0628\u0627\u062f"
    ],
    "name:fas_x_variant":[
        "Mo\u1e29ammad\u0101b\u0101d"
    ],
    "name:new_x_preferred":[
        "\u092e\u094b\u0939\u092e\u094d\u092e\u0926\u093e\u092c\u093e\u0926"
    ],
    "name:nld_x_preferred":[
        "Mohammadabad"
    ],
    "name:pol_x_preferred":[
        "Mohammadabad"
    ],
    "name:swe_x_preferred":[
        "Mohammadabad"
    ],
    "wof:name":"Mohammadabad",
    "wof:placetype":"locality"
},
  "geometry": {"coordinates":[61.50179,31.00802],"type":"Point"}
}