{
  "type": "Feature",
  "properties": {
    "gn:admin1_code":"33",
    "gn:asciiname":"Kaljan",
    "gn:country_code":"IR",
    "gn:dem":1948,
    "gn:feature_class":"P",
    "gn:feature_code":"PPL",
    "gn:name":"K\u0101lj\u0101n",
    "gn:population":0,
    "gn:timezone":"Asia/Tehran",
    "iso:country":"IR",
    "name:fas_x_preferred":[
        "\u06a9\u0627\u0644\u062c\u0627\u0646"
    ],
    "name:fas_x_variant":[
        "K\u0101lj\u0101n"
    ],
    "name:und_x_variant":[
        "Oh\u0101lja",
        "\u016ah\u0101ljeh",
        "Kal\u012bj\u0101n",
        "Kaladzha"
    ],
    "wof:name":"Kaljan",
    "wof:placetype":"locality"
},
  "geometry": {"coordinates":[46.4904,38.6432],"type":"Point"}
}