{
  "type": "Feature",
  "properties": {
    "gn:admin1_code":"41",
    "gn:asciiname":"Gelerg",
    "gn:country_code":"IR",
    "gn:dem":2044,
    "gn:feature_class":"P",
    "gn:feature_code":"PPLL",
    "gn:name":"Gelerg",
    "gn:population":0,
    "gn:timezone":"Asia/Tehran",
    "iso:country":"IR",
    "name:fas_x_preferred":[
        "\u06af\u0644\u0631\u06af"
    ],
    "name:und_x_variant":[
        "Golrag",
        "Gilirg",
        "Gelerg",
        "\u06af\u0644\u0631\u06af"
    ],
    "wof:name":"Gelerg",
    "wof:placetype":"locality"
},
  "geometry": {"coordinates":[59.42787,32.28692],"type":"Point"}
}