{
  "type": "Feature",
  "properties": {
    "gn:admin1_code":"7.0",
    "gn:asciiname":"Gowd-e Baqeri",
    "gn:country_code":"IR",
    "gn:dem":1312,
    "gn:feature_class":"P",
    "gn:feature_code":"PPL",
    "gn:name":"Gowd-e B\u0101qer\u012b",
    "gn:population":0,
    "gn:timezone":"Asia/Tehran",
    "iso:country":"IR",
    "name:fas_x_preferred":[
        "\u06af\u0648\u062f \u0628\u0627\u0642\u0631\u06cc"
    ],
    "name:und_x_variant":[
        "Gowd-e B\u0101qer\u012b"
    ],
    "wof:name":"Gowd-e Baqeri",
    "wof:placetype":"locality"
},
  "geometry": {"coordinates":[53.79119,28.318],"type":"Point"}
}