{
  "type": "Feature",
  "properties": {
    "gn:admin1_code":"33",
    "gn:asciiname":"Qorban Kandi",
    "gn:country_code":"IR",
    "gn:dem":2068,
    "gn:feature_class":"P",
    "gn:feature_code":"PPL",
    "gn:name":"Qorb\u0101n Kand\u012b",
    "gn:population":0,
    "gn:timezone":"Asia/Tehran",
    "iso:country":"IR",
    "name:fas_x_preferred":[
        "\u0642\u0631\u0628\u0627\u0646 \u06a9\u0646\u062f\u06cc"
    ],
    "name:fas_x_variant":[
        "Qorb\u0101n Kand\u012b"
    ],
    "wof:name":"Qorban Kandi",
    "wof:placetype":"locality"
},
  "geometry": {"coordinates":[46.5976,37.5405],"type":"Point"}
}