{
  "type": "Feature",
  "properties": {
    "gn:admin1_code":"15.0",
    "gn:asciiname":"Ab Gonjeshkan",
    "gn:country_code":"IR",
    "gn:dem":864,
    "gn:feature_class":"P",
    "gn:feature_code":"PPL",
    "gn:name":"\u0100b Gonjeshk\u0101n",
    "gn:population":0,
    "gn:timezone":"Asia/Tehran",
    "iso:country":"IR",
    "name:azb_x_preferred":[
        "\u0627\u0628 \u06af\u0646\u062c\u0634\u0643\u06cc(\u0627\u06cc\u0630\u0647)"
    ],
    "name:fas_x_preferred":[
        "\u0100b Gonjeshk\u012b"
    ],
    "name:fas_x_variant":[
        "\u0100b Gonjeshk\u0101n",
        "\u0622\u0628 \u06af\u0646\u062c\u0634\u06a9\u0627\u0646",
        "\u0622\u0628\u06af\u0646\u062c\u0634\u06a9\u06cc"
    ],
    "name:und_x_variant":[
        "\u0100b Gonjeshg\u0101n",
        "\u0622\u0628 \u06af\u0646\u062c\u0634\u06a9\u0627\u0646"
    ],
    "name:urd_x_preferred":[
        "\u0627\u0628 \u06af\u0646\u062c\u0634\u0643\u06cc"
    ],
    "wof:name":"Ab Gonjeshkan",
    "wof:placetype":"locality"
},
  "geometry": {"coordinates":[50.15653,31.69499],"type":"Point"}
}