{
  "type": "Feature",
  "properties": {
    "gn:admin1_code":"38",
    "gn:asciiname":"Mayan",
    "gn:country_code":"IR",
    "gn:dem":1695,
    "gn:feature_class":"P",
    "gn:feature_code":"PPL",
    "gn:name":"M\u0101y\u0101n",
    "gn:population":0,
    "gn:timezone":"Asia/Tehran",
    "iso:country":"IR",
    "name:fas_x_preferred":[
        "\u0645\u0627\u064a\u0627\u0646"
    ],
    "name:fas_x_variant":[
        "M\u0101y\u0101n",
        "\u0645\u0627\u06cc\u0627\u0646"
    ],
    "name:und_x_variant":[
        "Makas\u0101n"
    ],
    "wof:name":"Mayan",
    "wof:placetype":"locality"
},
  "geometry": {"coordinates":[49.4578,36.2307],"type":"Point"}
}