{
  "type": "Feature",
  "properties": {
    "gn:admin1_code":"25",
    "gn:asciiname":"Molla Ahmad Tangeh",
    "gn:country_code":"IR",
    "gn:dem":2254,
    "gn:feature_class":"P",
    "gn:feature_code":"PPL",
    "gn:name":"Moll\u0101 A\u1e29mad Tangeh",
    "gn:population":0,
    "gn:timezone":"Asia/Tehran",
    "iso:country":"IR",
    "name:fas_x_preferred":[
        "\u0645\u0644\u0627 \u0627\u062d\u0645\u062f \u062a\u0646\u06af\u0647"
    ],
    "name:fas_x_variant":[
        "Moll\u0101 A\u1e29mad Tangeh"
    ],
    "wof:name":"Molla Ahmad Tangeh",
    "wof:placetype":"locality"
},
  "geometry": {"coordinates":[53.2315,35.81763],"type":"Point"}
}