{
  "type": "Feature",
  "properties": {
    "gn:admin1_code":"5",
    "gn:asciiname":"Shotor Khan",
    "gn:country_code":"IR",
    "gn:dem":1459,
    "gn:feature_class":"P",
    "gn:feature_code":"PPL",
    "gn:name":"Shotor Kh\u0101n",
    "gn:population":0,
    "gn:timezone":"Asia/Tehran",
    "iso:country":"IR",
    "name:fas_x_preferred":[
        "\u0634\u064f\u062a\u064f\u0631 \u062e\u0648\u0646"
    ],
    "name:fas_x_variant":[
        "Shotor Kh\u016bn",
        "Shotor Kh\u0101n",
        "\u0634\u062a\u0631 \u062e\u0627\u0646"
    ],
    "name:und_x_variant":[
        "\u0634\u062a\u0631 \u062e\u0627\u0646"
    ],
    "wof:name":"Shotor Khan",
    "wof:placetype":"locality"
},
  "geometry": {"coordinates":[51.23298,31.00424000000001],"type":"Point"}
}