{
  "type": "Feature",
  "properties": {
    "gn:admin1_code":"41",
    "gn:asciiname":"Rahimabad",
    "gn:country_code":"IR",
    "gn:dem":1244,
    "gn:feature_class":"P",
    "gn:feature_code":"PPL",
    "gn:name":"Ra\u1e29\u012bm\u0101b\u0101d",
    "gn:population":0,
    "gn:timezone":"Asia/Tehran",
    "iso:country":"IR",
    "name:aze_x_preferred":[
        "R\u0259himabad"
    ],
    "name:fas_x_preferred":[
        "\u0631\u062d\u06cc\u0645 \u0622\u0628\u0627\u062f"
    ],
    "name:fas_x_variant":[
        "Ra\u1e29\u012bm\u0101b\u0101d",
        "\u0631\u062d\u06cc\u0645\u200c\u0622\u0628\u0627\u062f"
    ],
    "wof:name":"Rahimabad",
    "wof:placetype":"locality"
},
  "geometry": {"coordinates":[60.51491,32.53214000000001],"type":"Point"}
}