{
  "type": "Feature",
  "properties": {
    "gn:admin1_code":"35.0",
    "gn:asciiname":"Tashkuh-e Sofla",
    "gn:country_code":"IR",
    "gn:dem":-10,
    "gn:feature_class":"P",
    "gn:feature_code":"PPL",
    "gn:name":"T\u0101shk\u016bh-e Sofl\u00e1",
    "gn:population":0,
    "gn:timezone":"Asia/Tehran",
    "iso:country":"IR",
    "name:ceb_x_preferred":[
        "Tashk\u016bh-e Sofl\u00e1"
    ],
    "name:fas_x_preferred":[
        "\u062a\u0627\u0634\u0643\u0648\u0647 \u067e\u0627\u0626\u064a\u0646"
    ],
    "name:fas_x_variant":[
        "T\u0101shk\u016bh-e P\u0101\u2019\u012bn",
        "\u062a\u0627\u0634\u0643\u0648\u0647 \u0633\u0641\u0644\u06cc",
        "\u062a\u0627\u0634\u06a9\u0648\u0647 \u0633\u0641\u0644\u06cc"
    ],
    "name:swe_x_preferred":[
        "Tashk\u016bh-e Sofl\u00e1"
    ],
    "name:und_x_variant":[
        "T\u0101shk\u016bh-e Sofl\u00e1"
    ],
    "wof:name":"Tashkuh-e Sofla",
    "wof:placetype":"locality"
},
  "geometry": {"coordinates":[51.95656,36.55586],"type":"Point"}
}