{
  "type": "Feature",
  "properties": {
    "gn:admin1_code":"15",
    "gn:asciiname":"Seyyed Mohammad Baqer-e Sadr",
    "gn:country_code":"IR",
    "gn:dem":73,
    "gn:feature_class":"P",
    "gn:feature_code":"PPL",
    "gn:name":"Seyyed Mo\u1e29ammad B\u0101qer-e \u015eadr",
    "gn:population":0,
    "gn:timezone":"Asia/Tehran",
    "iso:country":"IR",
    "name:fas_x_preferred":[
        "\u0634\u0647\u06cc\u062f \u0645\u062d\u0645\u0651\u062f \u0628\u0627\u0642\u0631 \u0635\u062f\u0631"
    ],
    "name:fas_x_variant":[
        "Ma\u1e29m\u012bd",
        "\u0645\u062d\u0645\u06cc\u062f",
        "Shah\u012bd Mo\u1e29ammad B\u0101qer-e \u015eadr",
        "\u0633\u06cc\u062f \u0645\u062d\u0645\u062f \u0628\u0627\u0642\u0631 \u0635\u062f\u0631",
        "\u0628\u06cc\u062a \u0645\u062c\u06cc\u062f"
    ],
    "name:und_x_variant":[
        "Ma\u1e29m\u016bd",
        "Seyyed Mo\u1e29ammad B\u0101qer-e \u015eadr",
        "Beyt-e Maj\u012bd"
    ],
    "wof:name":"Seyyed Mohammad Baqer-e Sadr",
    "wof:placetype":"locality"
},
  "geometry": {"coordinates":[48.30907,32.10638],"type":"Point"}
}