{
  "type": "Feature",
  "properties": {
    "gn:admin1_code":"23",
    "gn:asciiname":"Sar Gul Namak",
    "gn:country_code":"IR",
    "gn:dem":1769,
    "gn:feature_class":"P",
    "gn:feature_code":"PPL",
    "gn:name":"Sar G\u016bl Namak",
    "gn:population":0,
    "gn:timezone":"Asia/Tehran",
    "iso:country":"IR",
    "name:fas_x_preferred":[
        "\u062f\u0644\u0641\u0627\u0646"
    ],
    "name:fas_x_variant":[
        "Delf\u0101n",
        "\u0633\u0631 \u06af\u0648\u0644 \u0646\u0645\u06a9"
    ],
    "name:und_x_variant":[
        "Sar G\u016bl Namak"
    ],
    "wof:name":"Sar Gul Namak",
    "wof:placetype":"locality"
},
  "geometry": {"coordinates":[48.5268,33.5494],"type":"Point"}
}