{
  "type": "Feature",
  "properties": {
    "gn:admin1_code":"29",
    "gn:asciiname":"Bandar Sarasiab-e Shesh",
    "gn:country_code":"IR",
    "gn:dem":2457,
    "gn:feature_class":"P",
    "gn:feature_code":"PPL",
    "gn:name":"Bandar Sar\u0101s\u012b\u0101b-e Shesh",
    "gn:population":0,
    "gn:timezone":"Asia/Tehran",
    "iso:country":"IR",
    "name:fas_x_preferred":[
        "\u0628\u0646\u062f\u0631 \u0633\u0631 \u0622\u0633\u06cc\u0627\u0628 \u0634\u0634"
    ],
    "name:fas_x_variant":[
        "Bandar Sar\u0101s\u012b\u0101b-e Shesh"
    ],
    "wof:name":"Bandar Sarasiab-e Shesh",
    "wof:placetype":"locality"
},
  "geometry": {"coordinates":[57.02478000000001,30.53819],"type":"Point"}
}