{
  "type": "Feature",
  "properties": {
    "gn:admin1_code":"28.0",
    "gn:asciiname":"Kowhan",
    "gn:country_code":"IR",
    "gn:dem":1798,
    "gn:feature_class":"P",
    "gn:feature_code":"PPL",
    "gn:name":"Kowh\u0101n",
    "gn:population":0,
    "gn:timezone":"Asia/Tehran",
    "iso:country":"IR",
    "name:fas_x_preferred":[
        "\u06a9\u0648\u0647\u0627\u0646"
    ],
    "name:fas_x_variant":[
        "Kowh\u0101n",
        "Golshan\u0101b\u0101d",
        "G\u016bh\u0101n"
    ],
    "name:und_x_variant":[
        "Kah\u0101n",
        "K\u016bh\u0101n"
    ],
    "wof:name":"Kowhan",
    "wof:placetype":"locality"
},
  "geometry": {"coordinates":[51.1645,32.6804],"type":"Point"}
}