{
  "type": "Feature",
  "properties": {
    "gn:admin1_code":"35",
    "gn:asciiname":"Boneh Kenar",
    "gn:country_code":"IR",
    "gn:dem":-20,
    "gn:feature_class":"P",
    "gn:feature_code":"PPL",
    "gn:name":"Boneh Ken\u0101r",
    "gn:population":0,
    "gn:timezone":"Asia/Tehran",
    "iso:country":"IR",
    "name:fas_x_preferred":[
        "\u0628\u0646\u0647 \u06a9\u0646\u0627\u0631"
    ],
    "name:fas_x_variant":[
        "Boneh Ken\u0101r"
    ],
    "wof:name":"Boneh Kenar",
    "wof:placetype":"locality"
},
  "geometry": {"coordinates":[52.50431999999999,36.65177],"type":"Point"}
}