{
  "type": "Feature",
  "properties": {
    "gn:admin1_code":"1.0",
    "gn:asciiname":"Shiveh Sal",
    "gn:country_code":"IR",
    "gn:dem":1110,
    "gn:feature_class":"P",
    "gn:feature_code":"PPL",
    "gn:name":"Sh\u012bveh \u015eal",
    "gn:population":0,
    "gn:timezone":"Asia/Tehran",
    "iso:country":"IR",
    "name:azb_x_preferred":[
        "\u0634\u064a\u0648\u0647 \u0635\u0644"
    ],
    "name:ceb_x_preferred":[
        "Sh\u012bveh \u015eal"
    ],
    "name:ckb_x_preferred":[
        "\u0634\u06cc\u0648\u06d5\u0633\u06d5\u06b5"
    ],
    "name:fas_x_preferred":[
        "\u0634\u06cc\u0648\u0647 \u0635\u0644"
    ],
    "name:fas_x_variant":[
        "Sh\u012bveh \u015eal",
        "\u0634\u06cc\u0648\u0647\u200c\u0635\u0644"
    ],
    "name:kur_x_preferred":[
        "\u015e\u00eewesell"
    ],
    "name:msa_x_preferred":[
        "Shiveh Sal"
    ],
    "name:swe_x_preferred":[
        "Sh\u012bveh \u015eal"
    ],
    "wof:name":"Shiveh Sal",
    "wof:placetype":"locality"
},
  "geometry": {"coordinates":[45.4868,36.2514],"type":"Point"}
}