{
  "type": "Feature",
  "properties": {
    "gn:admin1_code":"11",
    "gn:asciiname":"Nelukan",
    "gn:country_code":"IR",
    "gn:dem":911,
    "gn:feature_class":"P",
    "gn:feature_code":"PPL",
    "gn:name":"Nel\u016bkan",
    "gn:population":0,
    "gn:timezone":"Asia/Tehran",
    "iso:country":"IR",
    "name:fas_x_preferred":[
        "\u0646\u0644\u0648\u06a9\u0646"
    ],
    "name:fas_x_variant":[
        "Nel\u016bkan"
    ],
    "wof:name":"Nelukan",
    "wof:placetype":"locality"
},
  "geometry": {"coordinates":[57.8929,26.5387],"type":"Point"}
}