{
  "type": "Feature",
  "properties": {
    "gn:admin1_code":"1",
    "gn:asciiname":"Hesar-e Bahram Khan",
    "gn:country_code":"IR",
    "gn:dem":1340,
    "gn:feature_class":"P",
    "gn:feature_code":"PPL",
    "gn:name":"\u1e28e\u015f\u0101r-e Bahr\u0101m Kh\u0101n",
    "gn:population":0,
    "gn:timezone":"Asia/Tehran",
    "iso:country":"IR",
    "name:azb_x_preferred":[
        "\u062d\u06cc\u0635\u0627\u0631\u0628\u0647\u0631\u0627\u0645 \u062e\u0627\u0646"
    ],
    "name:aze_x_preferred":[
        "Hisar-i B\u0259hramxan"
    ],
    "name:ceb_x_preferred":[
        "\u1e28e\u015f\u0101r-e Bahr\u0101m Kh\u0101n"
    ],
    "name:fas_x_preferred":[
        "\u062d\u0650\u0635\u0627\u0631\u0650 \u0628\u064e\u0647\u0631\u0627\u0645\u062e\u0627\u0646"
    ],
    "name:fas_x_variant":[
        "\u062d\u0635\u0627\u0631 \u0628\u0647\u0631\u0627\u0645 \u062e\u0627\u0646",
        "\u1e28e\u015f\u0101r-e Bahr\u0101mkh\u0101n",
        "\u1e28e\u015f\u0101r-e Bahr\u0101m Kh\u0101n",
        "\u062d\u0635\u0627\u0631 \u0628\u0647\u0631\u0627\u0645\u200c\u062e\u0627\u0646"
    ],
    "name:msa_x_preferred":[
        "Hesar-e Bahram Khan"
    ],
    "name:swe_x_preferred":[
        "\u1e28e\u015f\u0101r-e Bahr\u0101m Kh\u0101n"
    ],
    "wof:name":"Hesar-e Bahram Khan",
    "wof:placetype":"locality"
},
  "geometry": {"coordinates":[45.0149,37.7043],"type":"Point"}
}