{
  "type": "Feature",
  "properties": {
    "gn:admin1_code":"34.0",
    "gn:asciiname":"Zarrineh",
    "gn:country_code":"IR",
    "gn:dem":1679,
    "gn:feature_class":"P",
    "gn:feature_code":"PPL",
    "gn:name":"Zarr\u012bneh",
    "gn:population":0,
    "gn:timezone":"Asia/Tehran",
    "iso:country":"IR",
    "name:fas_x_preferred":[
        "Zarr\u012bneh"
    ],
    "name:fas_x_variant":[
        "\u0632\u0631\u06cc\u0646\u0647"
    ],
    "name:und_x_variant":[
        "\u0632\u0631\u06cc\u0646\u0647"
    ],
    "wof:name":"Zarrineh",
    "wof:placetype":"locality"
},
  "geometry": {"coordinates":[49.89287,34.26551],"type":"Point"}
}