{
  "type": "Feature",
  "properties": {
    "gn:admin1_code":"34.0",
    "gn:asciiname":"Zarrineh",
    "gn:country_code":"IR",
    "gn:dem":1679,
    "gn:feature_class":"P",
    "gn:feature_code":"PPL",
    "gn:name":"Zarr\u012bneh",
    "gn:population":0,
    "gn:timezone":"Asia/Tehran",
    "iso:country":"IR",
    "name:ara_x_preferred":[
        "\u0632\u0631\u064a\u0646\u0647"
    ],
    "name:aze_x_preferred":[
        "Z\u0259rrin\u0259"
    ],
    "name:ckb_x_preferred":[
        "\u0632\u06d5\u0695\u06cc\u0646\u06d5"
    ],
    "name:fas_x_preferred":[
        "Zarr\u012bneh"
    ],
    "name:fas_x_variant":[
        "\u0632\u0631\u06cc\u0646\u0647"
    ],
    "name:glk_x_preferred":[
        "\u0632\u0631\u06cc\u0646\u0647 \u06a9\u0648"
    ],
    "name:kur_x_preferred":[
        "Zer\u00eene"
    ],
    "name:mlg_x_preferred":[
        "Zarrineh"
    ],
    "name:tur_x_preferred":[
        "Zerrine"
    ],
    "wof:name":"Zarrineh",
    "wof:placetype":"locality"
},
  "geometry": {"coordinates":[49.89287,34.26551],"type":"Point"}
}