{
  "type": "Feature",
  "properties": {
    "gn:admin1_code":"29",
    "gn:asciiname":"Madun",
    "gn:country_code":"IR",
    "gn:dem":2701,
    "gn:feature_class":"P",
    "gn:feature_code":"PPL",
    "gn:name":"M\u0101d\u016bn",
    "gn:population":0,
    "gn:timezone":"Asia/Tehran",
    "iso:country":"IR",
    "name:ara_x_preferred":[
        "\u0645\u0627\u062f\u0648\u0646"
    ],
    "name:fas_x_preferred":[
        "\u0645\u0627\u062f\u0648\u0646"
    ],
    "name:fas_x_variant":[
        "M\u0101d\u016bn"
    ],
    "name:und_x_variant":[
        "M\u0101doon",
        "M\u0101d\u016bn-e Gowd B\u0101gh"
    ],
    "name:urd_x_preferred":[
        "\u0645\u06cc\u0688\u0648\u0646"
    ],
    "wof:name":"Madun",
    "wof:placetype":"locality"
},
  "geometry": {"coordinates":[56.6015,29.5503],"type":"Point"}
}