{
  "type": "Feature",
  "properties": {
    "gn:admin1_code":"43",
    "gn:asciiname":"Qarah Aghaj-e Mohammad Nafas",
    "gn:country_code":"IR",
    "gn:dem":973,
    "gn:feature_class":"P",
    "gn:feature_code":"PPL",
    "gn:name":"Qarah \u0100gh\u0101j-e Mo\u1e29ammad Nafas",
    "gn:population":0,
    "gn:timezone":"Asia/Tehran",
    "iso:country":"IR",
    "name:fas_x_preferred":[
        "Mo\u1e29ammad Nafas"
    ],
    "name:fas_x_variant":[
        "Qarah \u0100q\u0101j-e Mo\u1e29ammad Nafas",
        "\u0642\u0631\u0647 \u0622\u0642\u0627\u062c \u0645\u062d\u0645\u062f \u0646\u0641\u0633",
        "\u0642\u0631\u0647 \u0622\u063a\u0627\u062c \u0645\u062d\u0645\u062f \u0646\u0641\u0633",
        "\u0642\u0631\u0647 \u0622\u0642\u0627\u062c"
    ],
    "name:und_x_variant":[
        "Mumad-Napas",
        "Mohamad Napas",
        "Qarah \u0100gh\u0101j-e Mo\u1e29ammad Nafas",
        "Qarah \u0100gh\u0101j-e Mo\u1e29ammad Taq\u012b",
        "Qarah \u0100q\u0101j"
    ],
    "wof:name":"Qarah Aghaj-e Mohammad Nafas",
    "wof:placetype":"locality"
},
  "geometry": {"coordinates":[56.58712,38.12076],"type":"Point"}
}