{
  "type": "Feature",
  "properties": {
    "gn:admin1_code":"3",
    "gn:asciiname":"Eshkaftak",
    "gn:country_code":"IR",
    "gn:dem":2088,
    "gn:feature_class":"P",
    "gn:feature_code":"PPL",
    "gn:name":"Eshkaftak",
    "gn:population":0,
    "gn:timezone":"Asia/Tehran",
    "iso:country":"IR",
    "name:fas_x_preferred":[
        "\u0627\u0634\u0643\u0641\u062a\u0643"
    ],
    "name:und_x_variant":[
        "Eshkaftak"
    ],
    "wof:name":"Eshkaftak",
    "wof:placetype":"locality"
},
  "geometry": {"coordinates":[50.7998,32.36709],"type":"Point"}
}