{
  "type": "Feature",
  "properties": {
    "gn:admin1_code":"15.0",
    "gn:asciiname":"Sar Kuseh",
    "gn:country_code":"IR",
    "gn:dem":904,
    "gn:feature_class":"P",
    "gn:feature_code":"PPL",
    "gn:name":"Sar K\u016bseh",
    "gn:population":0,
    "gn:timezone":"Asia/Tehran",
    "iso:country":"IR",
    "name:fas_x_preferred":[
        "\u0633\u0631\u0622\u0645\u062f"
    ],
    "name:fas_x_variant":[
        "Sar\u0101mad",
        "\u0633\u0631 \u06a9\u0648\u0633\u0647"
    ],
    "name:und_x_variant":[
        "Sar K\u016bseh"
    ],
    "wof:name":"Sar Kuseh",
    "wof:placetype":"locality"
},
  "geometry": {"coordinates":[48.19314,32.97337],"type":"Point"}
}