{
  "type": "Feature",
  "properties": {
    "gn:admin1_code":"15",
    "gn:asciiname":"Butari",
    "gn:country_code":"IR",
    "gn:dem":9,
    "gn:feature_class":"P",
    "gn:feature_code":"PPL",
    "gn:name":"Butari",
    "gn:population":0,
    "gn:timezone":"Asia/Tehran",
    "iso:country":"IR",
    "name:fas_x_preferred":[
        "\u0628\u0648 \u0637\u0627\u0647\u0631\u06cc"
    ],
    "name:fas_x_variant":[
        "B\u016b \u0162\u0101her\u012b",
        "\u0628\u0648\u0637\u0627\u0647\u0631\u06cc"
    ],
    "wof:name":"Butari",
    "wof:placetype":"locality"
},
  "geometry": {"coordinates":[49.9944,30.2426],"type":"Point"}
}