{
  "type": "Feature",
  "properties": {
    "gn:admin1_code":"35.0",
    "gn:asciiname":"Shir Khvar Kola",
    "gn:country_code":"IR",
    "gn:dem":-2,
    "gn:feature_class":"P",
    "gn:feature_code":"PPL",
    "gn:name":"Sh\u012br Khv\u0101r Kol\u0101",
    "gn:population":0,
    "gn:timezone":"Asia/Tehran",
    "iso:country":"IR",
    "name:fas_x_preferred":[
        "\u0634\u064a\u0631 \u062e\u0648\u0627\u0631 \u0643\u0644\u0627"
    ],
    "name:fas_x_variant":[
        "\u0634\u064a\u0631 \u062e\u0648\u064e\u0631 \u0643\u064f\u0644\u0627",
        "\u0634\u064a\u0631 \u062e\u0648\u064e\u0631 \u0643\u064e\u0644\u0627",
        "Sh\u012br Khv\u0101r Kol\u0101"
    ],
    "name:und_x_variant":[
        "Sh\u012br Khvar Kal\u0101",
        "Sh\u012br Khvar Kol\u0101"
    ],
    "wof:name":"Shir Khvar Kola",
    "wof:placetype":"locality"
},
  "geometry": {"coordinates":[52.85738000000001,36.55577],"type":"Point"}
}