{
  "type": "Feature",
  "properties": {
    "gn:admin1_code":"33",
    "gn:asciiname":"Biraneh",
    "gn:country_code":"IR",
    "gn:dem":2235,
    "gn:feature_class":"P",
    "gn:feature_code":"PPL",
    "gn:name":"B\u012br\u0101neh",
    "gn:population":0,
    "gn:timezone":"Asia/Tehran",
    "iso:country":"IR",
    "name:fas_x_preferred":[
        "B\u012br\u0101neh"
    ],
    "name:fas_x_variant":[
        "\u0628\u06cc\u0631\u0627\u0646\u0647"
    ],
    "wof:name":"Biraneh",
    "wof:placetype":"locality"
},
  "geometry": {"coordinates":[46.81667,38.71667],"type":"Point"}
}