{
  "type": "Feature",
  "properties": {
    "gn:admin1_code":"29",
    "gn:asciiname":"Bagh Malek",
    "gn:country_code":"IR",
    "gn:dem":2619,
    "gn:feature_class":"P",
    "gn:feature_code":"PPL",
    "gn:name":"B\u0101gh Malek",
    "gn:population":0,
    "gn:timezone":"Asia/Tehran",
    "iso:country":"IR",
    "name:ara_x_preferred":[
        "\u0628\u0627\u063a \u0645\u0644\u0643"
    ],
    "name:fas_x_preferred":[
        "\u0628\u0627\u063a \u0645\u0644\u06a9"
    ],
    "name:fas_x_variant":[
        "B\u0101gh Malek",
        "\u0628\u0627\u063a\u200c\u0645\u0644\u06a9"
    ],
    "name:und_x_variant":[
        "B\u0101gh-e Malek"
    ],
    "wof:name":"Bagh Malek",
    "wof:placetype":"locality"
},
  "geometry": {"coordinates":[56.6263,29.3831],"type":"Point"}
}