{
  "type": "Feature",
  "properties": {
    "gn:admin1_code":"4.0",
    "gn:asciiname":"Tasht-e Maksan",
    "gn:country_code":"IR",
    "gn:dem":712,
    "gn:feature_class":"P",
    "gn:feature_code":"PPL",
    "gn:name":"Tasht-e Maks\u0101n",
    "gn:population":0,
    "gn:timezone":"Asia/Tehran",
    "iso:country":"IR",
    "name:fas_x_preferred":[
        "Tasht-e Maks\u0101n"
    ],
    "wof:name":"Tasht-e Maksan",
    "wof:placetype":"locality"
},
  "geometry": {"coordinates":[59.95639,27.65917],"type":"Point"}
}