{
  "type": "Feature",
  "properties": {
    "gn:admin1_code":"7",
    "gn:asciiname":"Vazireh",
    "gn:country_code":"IR",
    "gn:dem":1588,
    "gn:feature_class":"P",
    "gn:feature_code":"PPL",
    "gn:name":"Vaz\u012breh",
    "gn:population":0,
    "gn:timezone":"Asia/Tehran",
    "iso:country":"IR",
    "name:fas_x_preferred":[
        "\u0648\u0632\u06cc\u0631\u0647"
    ],
    "name:fas_x_variant":[
        "Vaz\u012breh"
    ],
    "name:msa_x_preferred":[
        "Vazireh"
    ],
    "name:und_x_variant":[
        "Vaz\u012brch"
    ],
    "wof:name":"Vazireh",
    "wof:placetype":"locality"
},
  "geometry": {"coordinates":[54.8611,28.9687],"type":"Point"}
}