{
  "type": "Feature",
  "properties": {
    "gn:admin1_code":"7",
    "gn:asciiname":"Kahow",
    "gn:cc2":"IR",
    "gn:country_code":"IR",
    "gn:dem":1096,
    "gn:feature_class":"P",
    "gn:feature_code":"PPL",
    "gn:name":"Kahow",
    "gn:population":0,
    "gn:timezone":"Asia/Tehran",
    "iso:country":"IR",
    "name:und_x_variant":[
        "Tah Tow",
        "Kahow"
    ],
    "wof:name":"Kahow",
    "wof:placetype":"locality"
},
  "geometry": {"coordinates":[51.33333,30.43333],"type":"Point"}
}