{
  "type": "Feature",
  "properties": {
    "gn:admin1_code":"3",
    "gn:asciiname":"Shalamzar",
    "gn:country_code":"IR",
    "gn:dem":2025,
    "gn:feature_class":"P",
    "gn:feature_code":"PPLA2",
    "gn:name":"Shalamz\u0101r",
    "gn:population":0,
    "gn:timezone":"Asia/Tehran",
    "iso:country":"IR",
    "name:fas_x_preferred":[
        "Shalamz\u0101r"
    ],
    "name:fas_x_variant":[
        "\u0634\u0644\u0645\u0632\u0627\u0631"
    ],
    "name:und_x_variant":[
        "\u0634\u0644\u0645\u0632\u0627\u0631"
    ],
    "wof:name":"Shalamzar",
    "wof:placetype":"locality"
},
  "geometry": {"coordinates":[50.81714,32.04539],"type":"Point"}
}