{
  "type": "Feature",
  "properties": {
    "gn:admin1_code":"3",
    "gn:asciiname":"Shalamzar",
    "gn:country_code":"IR",
    "gn:dem":2025,
    "gn:feature_class":"P",
    "gn:feature_code":"PPLA2",
    "gn:name":"Shalamz\u0101r",
    "gn:population":0,
    "gn:timezone":"Asia/Tehran",
    "iso:country":"IR",
    "name:ara_x_preferred":[
        "\u0634\u0644\u0645\u0632\u0627\u0631"
    ],
    "name:aze_x_preferred":[
        "\u015e\u0259l\u0259mzar"
    ],
    "name:ceb_x_preferred":[
        "Shalamz\u0101r"
    ],
    "name:fas_x_preferred":[
        "Shalamz\u0101r"
    ],
    "name:fas_x_variant":[
        "\u0634\u0644\u0645\u0632\u0627\u0631"
    ],
    "name:ita_x_preferred":[
        "Shalamzar"
    ],
    "name:mlg_x_preferred":[
        "Shalamzar"
    ],
    "name:msa_x_preferred":[
        "Shalamzar"
    ],
    "name:rus_x_preferred":[
        "\u0428\u0435\u043b\u0435\u043c\u0437\u0430\u0440"
    ],
    "name:swe_x_preferred":[
        "Shalamz\u0101r"
    ],
    "name:tur_x_preferred":[
        "\u015eelemzar"
    ],
    "name:urd_x_preferred":[
        "\u0634\u0644\u0645\u0632\u0627\u0631"
    ],
    "name:zho_x_preferred":[
        "\u6c99\u62c9\u59c6\u624e\u723e"
    ],
    "wof:name":"Shalamzar",
    "wof:placetype":"locality"
},
  "geometry": {"coordinates":[50.81714,32.04539],"type":"Point"}
}