{
  "type": "Feature",
  "properties": {
    "gn:admin1_code":"1",
    "gn:asciiname":"Qilehliq",
    "gn:country_code":"IR",
    "gn:dem":1562,
    "gn:feature_class":"P",
    "gn:feature_code":"PPL",
    "gn:name":"Q\u012blehl\u012bq",
    "gn:population":0,
    "gn:timezone":"Asia/Tehran",
    "iso:country":"IR",
    "name:aze_x_preferred":[
        "Gil\u0259hlik"
    ],
    "name:ceb_x_preferred":[
        "Q\u012blehl\u012bq"
    ],
    "name:fas_x_preferred":[
        "Q\u012blehl\u012bq"
    ],
    "name:fas_x_variant":[
        "\u0642\u06cc\u0644\u0647\u200c\u0644\u06cc\u0642"
    ],
    "name:msa_x_preferred":[
        "Qilehliq"
    ],
    "name:swe_x_preferred":[
        "Q\u012blehl\u012bq"
    ],
    "wof:name":"Qilehliq",
    "wof:placetype":"locality"
},
  "geometry": {"coordinates":[44.71667,38.46667],"type":"Point"}
}