{
  "type": "Feature",
  "properties": {
    "gn:admin1_code":"4.0",
    "gn:asciiname":"Deh-e Ghafur",
    "gn:country_code":"IR",
    "gn:dem":493,
    "gn:feature_class":"P",
    "gn:feature_code":"PPL",
    "gn:name":"Deh-e Ghaf\u016br",
    "gn:population":0,
    "gn:timezone":"Asia/Tehran",
    "iso:country":"IR",
    "name:fas_x_preferred":[
        "Deh-e Ghaf\u016br"
    ],
    "wof:name":"Deh-e Ghafur",
    "wof:placetype":"locality"
},
  "geometry": {"coordinates":[61.76667,30.88333],"type":"Point"}
}