{
  "type": "Feature",
  "properties": {
    "gn:admin1_code":"11",
    "gn:asciiname":"Valichi",
    "gn:country_code":"IR",
    "gn:dem":60,
    "gn:feature_class":"P",
    "gn:feature_code":"PPL",
    "gn:name":"Val\u012bch\u012b",
    "gn:population":0,
    "gn:timezone":"Asia/Tehran",
    "iso:country":"IR",
    "name:fas_x_preferred":[
        "\u0648\u0644\u06cc\u0686\u06cc"
    ],
    "name:fas_x_variant":[
        "\u0633\u064e\u062f\u0650\u0651 \u0645\u064a\u0646\u0627\u0628",
        "Val\u012bch\u012b"
    ],
    "name:und_x_variant":[
        "Sadd-e M\u012bn\u0101b"
    ],
    "wof:name":"Valichi",
    "wof:placetype":"locality"
},
  "geometry": {"coordinates":[57.20919,27.05317],"type":"Point"}
}