{
  "type": "Feature",
  "properties": {
    "gn:admin1_code":"16",
    "gn:asciiname":"Qal`eh-ye Fulad",
    "gn:country_code":"IR",
    "gn:dem":1895,
    "gn:feature_class":"P",
    "gn:feature_code":"PPL",
    "gn:name":"Qal\u2018eh-ye F\u016bl\u0101d",
    "gn:population":0,
    "gn:timezone":"Asia/Tehran",
    "iso:country":"IR",
    "name:fas_x_preferred":[
        "\u0642\u0644\u0639\u0647 \u0641\u0648\u0644\u0627\u062f"
    ],
    "name:fas_x_variant":[
        "Qal\u2018eh F\u016bl\u0101d"
    ],
    "name:und_x_variant":[
        "Qalla Pola",
        "Qal\u2018eh-ye F\u016bl\u0101d",
        "Qal\u2018eh-ye P\u016bl\u0101"
    ],
    "wof:name":"Qal`eh-ye Fulad",
    "wof:placetype":"locality"
},
  "geometry": {"coordinates":[47.34018,35.49299],"type":"Point"}
}