{
  "type": "Feature",
  "properties": {
    "gn:admin1_code":"0",
    "gn:asciiname":"Bahmanzad",
    "gn:country_code":"IR",
    "gn:dem":2347,
    "gn:feature_class":"P",
    "gn:feature_code":"PPL",
    "gn:name":"Bahmanz\u0101d",
    "gn:population":0,
    "gn:timezone":"Asia/Tehran",
    "iso:country":"IR",
    "name:fas_x_preferred":[
        "\u0628\u064e\u0647\u0645\u064e\u0646\u0632\u0627\u062f"
    ],
    "name:fas_x_variant":[
        "Bahmanz\u0101d"
    ],
    "wof:name":"Bahmanzad",
    "wof:placetype":"locality"
},
  "geometry": {"coordinates":[51.78889,31.25417],"type":"Point"}
}