{
  "type": "Feature",
  "properties": {
    "gn:admin1_code":"41",
    "gn:asciiname":"Mangu",
    "gn:country_code":"IR",
    "gn:dem":2064,
    "gn:feature_class":"P",
    "gn:feature_code":"PPL",
    "gn:name":"Mangu",
    "gn:population":0,
    "gn:timezone":"Asia/Tehran",
    "iso:country":"IR",
    "name:ceb_x_preferred":[
        "Mangu"
    ],
    "name:ita_x_preferred":[
        "Mangu"
    ],
    "name:swe_x_preferred":[
        "Mangu"
    ],
    "wof:name":"Mangu",
    "wof:placetype":"locality"
},
  "geometry": {"coordinates":[59.58333,32.25],"type":"Point"}
}