{
  "type": "Feature",
  "properties": {
    "gn:admin1_code":"7",
    "gn:asciiname":"Nur ed Dini",
    "gn:country_code":"IR",
    "gn:dem":461,
    "gn:feature_class":"P",
    "gn:feature_code":"PPL",
    "gn:name":"N\u016br ed D\u012bn\u012b",
    "gn:population":0,
    "gn:timezone":"Asia/Tehran",
    "iso:country":"IR",
    "name:fas_x_preferred":[
        "\u0646\u0648\u0631 \u0627\u0644\u062f\u06cc\u0646\u06cc"
    ],
    "name:fas_x_variant":[
        "N\u016br ed D\u012bn\u012b"
    ],
    "wof:name":"Nur ed Dini",
    "wof:placetype":"locality"
},
  "geometry": {"coordinates":[53.2146,27.5313],"type":"Point"}
}