{
  "type": "Feature",
  "properties": {
    "gn:admin1_code":"34",
    "gn:asciiname":"Varakabad",
    "gn:country_code":"IR",
    "gn:dem":1367,
    "gn:feature_class":"P",
    "gn:feature_code":"PPL",
    "gn:name":"Varak\u0101b\u0101d",
    "gn:population":0,
    "gn:timezone":"Asia/Tehran",
    "iso:country":"IR",
    "name:fas_x_preferred":[
        "\u0648\u0631\u06a9\u0628\u0627\u0631"
    ],
    "name:fas_x_variant":[
        "Varak B\u0101r-e P\u0101\u2019\u012bn",
        "Varakb\u0101r",
        "\u0648\u0631\u06a9 \u0622\u0628\u0627\u062f",
        "\u0648\u0631\u06a9\u0628\u0627\u0631 \u0633\u0641\u0644\u06cc"
    ],
    "name:und_x_variant":[
        "Varak B\u0101r",
        "Varak\u0101b\u0101d",
        "Varakb\u0101r-e Sofl\u00e1"
    ],
    "wof:name":"Varakabad",
    "wof:placetype":"locality"
},
  "geometry": {"coordinates":[49.98537,35.04214],"type":"Point"}
}