{
  "type": "Feature",
  "properties": {
    "gn:admin1_code":"29",
    "gn:asciiname":"Neyestanak",
    "gn:country_code":"IR",
    "gn:dem":2063,
    "gn:feature_class":"P",
    "gn:feature_code":"PPL",
    "gn:name":"Neyest\u0101nak",
    "gn:population":0,
    "gn:timezone":"Asia/Tehran",
    "iso:country":"IR",
    "name:fas_x_preferred":[
        "Neyest\u0101nak"
    ],
    "name:fas_x_variant":[
        "\u0646\u06cc\u0633\u062a\u0627\u0646\u06a9"
    ],
    "name:und_x_variant":[
        "Neyest\u0101n"
    ],
    "wof:name":"Neyestanak",
    "wof:placetype":"locality"
},
  "geometry": {"coordinates":[55.10154,30.52908],"type":"Point"}
}