{
  "type": "Feature",
  "properties": {
    "gn:admin1_code":"43",
    "gn:asciiname":"Dar Parchin-e Pa'in",
    "gn:country_code":"IR",
    "gn:dem":1823,
    "gn:feature_class":"P",
    "gn:feature_code":"PPL",
    "gn:name":"Dar Parch\u012bn-e P\u0101\u2019\u012bn",
    "gn:population":0,
    "gn:timezone":"Asia/Tehran",
    "iso:country":"IR",
    "name:ara_x_preferred":[
        "\u062f\u0631\u0628\u0631\u062a\u0634\u064a\u0646 \u0633\u0641\u0644\u064a"
    ],
    "name:ceb_x_preferred":[
        "Dar Parch\u012bn-e P\u0101'\u012bn"
    ],
    "name:fas_x_preferred":[
        "Dar Parch\u012bn-e P\u0101\u2019\u012bn"
    ],
    "name:fas_x_variant":[
        "\u062f\u0631 \u067e\u0631\u0686\u06cc\u0646 \u067e\u0627\u0626\u06cc\u0646",
        "\u062f\u0631\u067e\u0631\u0686\u06cc\u0646 \u0633\u0641\u0644\u06cc"
    ],
    "name:swe_x_preferred":[
        "Dar Parch\u012bn-e P\u0101'\u012bn"
    ],
    "name:und_x_variant":[
        "Dar Parch\u012bn",
        "Dar Parch\u012bn-e Sofl\u00e1",
        "Dar Parch\u012bn P\u0101\u2019\u012bn"
    ],
    "wof:name":"Dar Parchin-e Pa'in",
    "wof:placetype":"locality"
},
  "geometry": {"coordinates":[57.83276,37.14029],"type":"Point"}
}