{
  "type": "Feature",
  "properties": {
    "gn:admin1_code":"40.0",
    "gn:asciiname":"Charkhab-e Kohneh",
    "gn:country_code":"IR",
    "gn:dem":1188,
    "gn:feature_class":"P",
    "gn:feature_code":"PPLF",
    "gn:name":"Charkh\u0101b-e Kohneh",
    "gn:population":0,
    "gn:timezone":"Asia/Tehran",
    "iso:country":"IR",
    "name:fas_x_preferred":[
        "\u0686\u0631\u062e\u0627\u0628 \u06a9\u0647\u0646\u0647"
    ],
    "name:und_x_variant":[
        "Charkh\u0101b-e Kohneh"
    ],
    "wof:name":"Charkhab-e Kohneh",
    "wof:placetype":"locality"
},
  "geometry": {"coordinates":[54.19493000000001,31.94775],"type":"Point"}
}