{
  "type": "Feature",
  "properties": {
    "gn:admin1_code":"42.0",
    "gn:asciiname":"Feshanjerd",
    "gn:country_code":"IR",
    "gn:dem":1038,
    "gn:feature_class":"P",
    "gn:feature_code":"PPL",
    "gn:name":"Fesh\u0101njerd",
    "gn:population":0,
    "gn:timezone":"Asia/Tehran",
    "iso:country":"IR",
    "name:ceb_x_preferred":[
        "Fesh\u0101njerd"
    ],
    "name:fas_x_preferred":[
        "G\u016br\u012b Fesh\u0101njerd"
    ],
    "name:fas_x_variant":[
        "Fesh\u0101njerd",
        "\u0641\u0634\u0627\u0646\u062c\u0631\u062f"
    ],
    "name:swe_x_preferred":[
        "Fesh\u0101njerd"
    ],
    "wof:name":"Feshanjerd",
    "wof:placetype":"locality"
},
  "geometry": {"coordinates":[57.13869,36.79283],"type":"Point"}
}