{
  "type": "Feature",
  "properties": {
    "gn:admin1_code":"25",
    "gn:asciiname":"Haskuh",
    "gn:country_code":"IR",
    "gn:dem":2426,
    "gn:feature_class":"P",
    "gn:feature_code":"PPL",
    "gn:name":"Hask\u016bh",
    "gn:population":0,
    "gn:timezone":"Asia/Tehran",
    "iso:country":"IR",
    "name:fas_x_preferred":[
        "\u0647\u064e\u0643\u0648\u0650\u0647"
    ],
    "name:fas_x_variant":[
        "\u0647\u0633\u0643\u0648\u0647",
        "Hask\u016bh"
    ],
    "name:und_x_variant":[
        "Hakveh"
    ],
    "wof:name":"Haskuh",
    "wof:placetype":"locality"
},
  "geometry": {"coordinates":[53.45231999999999,35.94868],"type":"Point"}
}