{
  "type": "Feature",
  "properties": {
    "gn:admin1_code":"41",
    "gn:asciiname":"Cheshmeh Zangi",
    "gn:country_code":"IR",
    "gn:dem":1742,
    "gn:feature_class":"P",
    "gn:feature_code":"PPL",
    "gn:name":"Cheshmeh Zang\u012b",
    "gn:population":0,
    "gn:timezone":"Asia/Tehran",
    "iso:country":"IR",
    "name:fas_x_preferred":[
        "\u0632\u0646\u06af\u06cc \u0622\u0628\u0627\u062f"
    ],
    "name:fas_x_variant":[
        "Cheshmeh Zang\u012b",
        "Zang\u012b\u0101b\u0101d",
        "\u0686\u0634\u0645\u0647 \u0632\u0646\u06af\u06cc"
    ],
    "name:und_x_variant":[
        "Chashmeh Zang\u012b",
        "Chashmeh Rang\u012b",
        "Chashmeh-i-Zangi"
    ],
    "wof:name":"Cheshmeh Zangi",
    "wof:placetype":"locality"
},
  "geometry": {"coordinates":[59.9859,32.4514],"type":"Point"}
}