{
  "type": "Feature",
  "properties": {
    "gn:admin1_code":"32.0",
    "gn:asciiname":"Zarnas",
    "gn:country_code":"IR",
    "gn:dem":1339,
    "gn:feature_class":"P",
    "gn:feature_code":"PPL",
    "gn:name":"Zarn\u0101s",
    "gn:population":0,
    "gn:timezone":"Asia/Tehran",
    "iso:country":"IR",
    "name:fas_x_preferred":[
        "\u0632\u0631\u0646\u0627\u0633"
    ],
    "name:fas_x_variant":[
        "Zarn\u0101s"
    ],
    "wof:name":"Zarnas",
    "wof:placetype":"locality"
},
  "geometry": {"coordinates":[48.3212,38.256],"type":"Point"}
}