{
  "type": "Feature",
  "properties": {
    "gn:admin1_code":"32",
    "gn:asciiname":"Qeshlaq-e Hajj `Ali Barat",
    "gn:country_code":"IR",
    "gn:dem":499,
    "gn:feature_class":"P",
    "gn:feature_code":"PPL",
    "gn:name":"Qeshl\u0101q-e \u1e28\u0101jj \u2018Al\u012b Bar\u0101t",
    "gn:population":0,
    "gn:timezone":"Asia/Tehran",
    "iso:country":"IR",
    "name:fas_x_preferred":[
        "\u0642\u0650\u0634\u0644\u0627\u0642\u0650 \u062d\u0627\u062c\u0651 \u0639\u064e\u0644\u06cc \u0628\u064e\u0631\u0627\u062a"
    ],
    "name:fas_x_variant":[
        "Qeshl\u0101q-e \u1e28\u0101jj \u2018Al\u012b Bar\u0101t"
    ],
    "wof:name":"Qeshlaq-e Hajj `Ali Barat",
    "wof:placetype":"locality"
},
  "geometry": {"coordinates":[47.83333,39.25],"type":"Point"}
}