{
  "type": "Feature",
  "properties": {
    "gn:admin1_code":"15.0",
    "gn:asciiname":"Kolam od Din",
    "gn:country_code":"IR",
    "gn:dem":505,
    "gn:feature_class":"P",
    "gn:feature_code":"PPL",
    "gn:name":"Kol\u0101m od D\u012bn",
    "gn:population":0,
    "gn:timezone":"Asia/Tehran",
    "iso:country":"IR",
    "wof:name":"Kolam od Din",
    "wof:placetype":"locality"
},
  "geometry": {"coordinates":[49.76056,31.49222],"type":"Point"}
}