{
  "type": "Feature",
  "properties": {
    "gn:admin1_code":"7",
    "gn:asciiname":"Chenar Zahedan",
    "gn:country_code":"IR",
    "gn:dem":2333,
    "gn:feature_class":"P",
    "gn:feature_code":"PPL",
    "gn:name":"Chen\u0101r Z\u0101hed\u0101n",
    "gn:population":0,
    "gn:timezone":"Asia/Tehran",
    "iso:country":"IR",
    "name:ara_x_preferred":[
        "\u062a\u0634\u0646\u0627\u0631 \u0632\u0627\u0647\u062f\u0627\u0646"
    ],
    "name:fas_x_preferred":[
        "\u0686\u0646\u0627\u0631 \u0632\u0627\u0647\u062f\u0627\u0646"
    ],
    "name:fas_x_variant":[
        "Chen\u0101r Z\u0101hed\u0101n"
    ],
    "name:msa_x_preferred":[
        "Chenar Zahedan"
    ],
    "name:und_x_variant":[
        "Chen\u0101r Dozd"
    ],
    "wof:name":"Chenar Zahedan",
    "wof:placetype":"locality"
},
  "geometry": {"coordinates":[53.8308,30.0897],"type":"Point"}
}