{
  "type": "Feature",
  "properties": {
    "gn:admin1_code":"42",
    "gn:asciiname":"Kajeh",
    "gn:country_code":"IR",
    "gn:dem":947,
    "gn:feature_class":"P",
    "gn:feature_code":"PPL",
    "gn:name":"Kajeh",
    "gn:population":0,
    "gn:timezone":"Asia/Tehran",
    "iso:country":"IR",
    "name:fas_x_preferred":[
        "\u06a9\u062c\u0647"
    ],
    "wof:name":"Kajeh",
    "wof:placetype":"locality"
},
  "geometry": {"coordinates":[57.76633,34.2167],"type":"Point"}
}