{
  "type": "Feature",
  "properties": {
    "gn:admin1_code":"4",
    "gn:asciiname":"Belingini",
    "gn:country_code":"IR",
    "gn:dem":1264,
    "gn:feature_class":"P",
    "gn:feature_code":"PPL",
    "gn:name":"Bel\u012bng\u012bn\u012b",
    "gn:population":0,
    "gn:timezone":"Asia/Tehran",
    "iso:country":"IR",
    "name:fas_x_preferred":[
        "\u0628\u0644\u06cc\u0646\u06af\u06cc\u0646\u06cc"
    ],
    "name:fas_x_variant":[
        "Bel\u012bng\u012bn\u012b"
    ],
    "wof:name":"Belingini",
    "wof:placetype":"locality"
},
  "geometry": {"coordinates":[62.3038,26.8853],"type":"Point"}
}