{
  "type": "Feature",
  "properties": {
    "gn:admin1_code":"36",
    "gn:asciiname":"Nik Pey",
    "gn:country_code":"IR",
    "gn:dem":1399,
    "gn:feature_class":"P",
    "gn:feature_code":"PPL",
    "gn:name":"N\u012bk Pey",
    "gn:population":0,
    "gn:timezone":"Asia/Tehran",
    "iso:country":"IR",
    "name:ara_x_preferred":[
        "\u0646\u064a\u0643 \u0628\u064a"
    ],
    "name:azb_x_preferred":[
        "\u0646\u06cc\u06a9 \u067e\u06cc"
    ],
    "name:aze_x_preferred":[
        "Nikpey"
    ],
    "name:ceb_x_preferred":[
        "N\u012bk Pey"
    ],
    "name:fas_x_preferred":[
        "\u0646\u06cc\u06a9 \u067e\u06cc"
    ],
    "name:fas_x_variant":[
        "N\u012bk Pey",
        "\u0646\u06cc\u06a9\u200c\u067e\u06cc"
    ],
    "name:swe_x_preferred":[
        "N\u012bk Pey"
    ],
    "name:und_x_variant":[
        "N\u012bk Pay",
        "N\u012bkpei"
    ],
    "wof:name":"Nik Pey",
    "wof:placetype":"locality"
},
  "geometry": {"coordinates":[48.17826,36.8505],"type":"Point"}
}