{
  "type": "Feature",
  "properties": {
    "gn:admin1_code":"35",
    "gn:asciiname":"Shabanqol",
    "gn:country_code":"IR",
    "gn:dem":1588,
    "gn:feature_class":"P",
    "gn:feature_code":"PPL",
    "gn:name":"Shab\u0101nqol",
    "gn:population":0,
    "gn:timezone":"Asia/Tehran",
    "iso:country":"IR",
    "name:fas_x_preferred":[
        "\u0634\u0627\u0639\u0628\u0627\u0646 \u062e\u0650\u064a\u0644"
    ],
    "name:fas_x_variant":[
        "\u0634\u0628\u0627\u0646\u0642\u0644",
        "Sh\u0101\u2018b\u0101n Kheyl",
        "Shab\u0101nqol"
    ],
    "wof:name":"Shabanqol",
    "wof:placetype":"locality"
},
  "geometry": {"coordinates":[53.65229,36.24146],"type":"Point"}
}