{
  "type": "Feature",
  "properties": {
    "gn:admin1_code":"34",
    "gn:asciiname":"Vapileh",
    "gn:country_code":"IR",
    "gn:dem":1770,
    "gn:feature_class":"P",
    "gn:feature_code":"PPL",
    "gn:name":"V\u0101p\u012bleh",
    "gn:population":0,
    "gn:timezone":"Asia/Tehran",
    "iso:country":"IR",
    "name:fas_x_preferred":[
        "V\u0101p\u012bleh"
    ],
    "name:fas_x_variant":[
        "\u0648\u0627\u067e\u064a\u0644\u0647",
        "\u0648\u0627\u067e\u06cc\u0644\u0647"
    ],
    "name:ukr_x_preferred":[
        "\u0412\u0430\u043f\u0456\u043b\u0435"
    ],
    "name:und_x_variant":[
        "\u0648\u0627\u067e\u064a\u0644\u0647"
    ],
    "wof:name":"Vapileh",
    "wof:placetype":"locality"
},
  "geometry": {"coordinates":[50.21728,33.73791],"type":"Point"}
}