{
  "type": "Feature",
  "properties": {
    "gn:admin1_code":"11.0",
    "gn:asciiname":"Azadegan",
    "gn:country_code":"IR",
    "gn:dem":49,
    "gn:feature_class":"P",
    "gn:feature_code":"PPL",
    "gn:name":"\u0100z\u0101deg\u0101n",
    "gn:population":0,
    "gn:timezone":"Asia/Tehran",
    "iso:country":"IR",
    "name:fas_x_preferred":[
        "\u0622\u0632\u0627\u062f\u06af\u0627\u0646"
    ],
    "name:fas_x_variant":[
        "\u0100z\u0101deg\u0101n",
        "\u067e\u0634\u062a\u0647 \u0622\u0632\u0627\u062f\u06af\u0627\u0646"
    ],
    "name:und_x_variant":[
        "Poshteh \u0100z\u0101deg\u0101n"
    ],
    "wof:name":"Azadegan",
    "wof:placetype":"locality"
},
  "geometry": {"coordinates":[57.0567,27.2206],"type":"Point"}
}