{
  "type": "Feature",
  "properties": {
    "gn:admin1_code":"4.0",
    "gn:asciiname":"Katukan Shib",
    "gn:country_code":"IR",
    "gn:dem":1202,
    "gn:feature_class":"P",
    "gn:feature_code":"PPL",
    "gn:name":"Kat\u016bk\u0101n Sh\u012bb",
    "gn:population":0,
    "gn:timezone":"Asia/Tehran",
    "iso:country":"IR",
    "name:fas_x_preferred":[
        "Kat\u016bk\u0101n Sh\u012bb"
    ],
    "wof:name":"Katukan Shib",
    "wof:placetype":"locality"
},
  "geometry": {"coordinates":[60.425,26.67083],"type":"Point"}
}