{
  "type": "Feature",
  "properties": {
    "gn:admin1_code":"8",
    "gn:asciiname":"Khajkeh",
    "gn:country_code":"IR",
    "gn:dem":108,
    "gn:feature_class":"P",
    "gn:feature_code":"PPL",
    "gn:name":"Khajkeh",
    "gn:population":0,
    "gn:timezone":"Asia/Tehran",
    "iso:country":"IR",
    "name:ara_x_preferred":[
        "\u062e\u062c\u0643\u0647"
    ],
    "name:ceb_x_preferred":[
        "Khajkeh"
    ],
    "name:fas_x_preferred":[
        "\u062e\u062c\u06a9\u0647"
    ],
    "name:glk_x_preferred":[
        "\u062e\u062c\u06a9\u0647"
    ],
    "name:msa_x_preferred":[
        "Khajkeh"
    ],
    "name:swe_x_preferred":[
        "Khajkeh"
    ],
    "name:ukr_x_preferred":[
        "\u0425\u0430\u0434\u0436\u043a\u0435"
    ],
    "name:und_x_variant":[
        "Khejakeh",
        "Khajkeh"
    ],
    "wof:name":"Khajkeh",
    "wof:placetype":"locality"
},
  "geometry": {"coordinates":[49.18296,37.24492],"type":"Point"}
}