{
  "type": "Feature",
  "properties": {
    "gn:admin1_code":"4.0",
    "gn:asciiname":"Hajji `Alimardan",
    "gn:country_code":"IR",
    "gn:dem":490,
    "gn:feature_class":"P",
    "gn:feature_code":"PPL",
    "gn:name":"\u1e28\u0101jj\u012b \u2018Al\u012bmard\u0101n",
    "gn:population":0,
    "gn:timezone":"Asia/Tehran",
    "iso:country":"IR",
    "name:fas_x_preferred":[
        "\u062d\u0627\u062c\u06cc \u0639\u0644\u06cc\u0645\u0631\u062f\u0627\u0646"
    ],
    "name:fas_x_variant":[
        "\u1e28\u0101jj\u012b \u2018Al\u012bmard\u0101n",
        "\u0639\u0644\u06cc \u0645\u0631\u062f\u0627\u0646"
    ],
    "name:und_x_variant":[
        "\u2018Al\u012b Mard\u0101n"
    ],
    "wof:name":"Hajji `Alimardan",
    "wof:placetype":"locality"
},
  "geometry": {"coordinates":[61.648,30.8772],"type":"Point"}
}