{
  "type": "Feature",
  "properties": {
    "gn:admin1_code":"13",
    "gn:asciiname":"Qez Qebri-ye Yek",
    "gn:country_code":"IR",
    "gn:dem":1331,
    "gn:feature_class":"P",
    "gn:feature_code":"PPL",
    "gn:name":"Qez Qebr\u012b-ye Yek",
    "gn:population":0,
    "gn:timezone":"Asia/Tehran",
    "iso:country":"IR",
    "name:fas_x_preferred":[
        "\u0642\u0632 \u0642\u0628\u0631\u06cc \u06cc\u06a9"
    ],
    "name:fas_x_variant":[
        "Qez Qebr\u012b-ye Ebr\u0101h\u012bm",
        "Qez Qebr\u012b-ye Yek"
    ],
    "name:und_x_variant":[
        "Qez Qabr\u012b-ye Ebr\u0101h\u012bm"
    ],
    "wof:name":"Qez Qebri-ye Yek",
    "wof:placetype":"locality"
},
  "geometry": {"coordinates":[46.7365,34.457],"type":"Point"}
}