{
  "type": "Feature",
  "properties": {
    "gn:admin1_code":"13",
    "gn:asciiname":"Sarab-e Sar Firuzabad",
    "gn:country_code":"IR",
    "gn:dem":1639,
    "gn:feature_class":"P",
    "gn:feature_code":"PPL",
    "gn:name":"Sar\u0101b-e Sar F\u012br\u016bz\u0101b\u0101d",
    "gn:population":0,
    "gn:timezone":"Asia/Tehran",
    "iso:country":"IR",
    "name:fas_x_preferred":[
        "\u0633\u0631\u0627\u0628 \u0633\u0631 \u0641\u06cc\u0631\u0648\u0632 \u0622\u0628\u0627\u062f"
    ],
    "name:fas_x_variant":[
        "Sar\u0101b",
        "Sar\u0101b-e Sar F\u012br\u016bz\u0101b\u0101d"
    ],
    "name:und_x_variant":[
        "Sar\u0101b-e Sofl\u00e1",
        "Sar-e F\u012br\u016bz\u0101b\u0101d",
        "Sar\u0101b-e F\u012br\u016bz\u0101b\u0101d",
        "Sar-i-\u0100b-i-F\u012br\u016bz\u0101b\u0101d"
    ],
    "wof:name":"Sarab-e Sar Firuzabad",
    "wof:placetype":"locality"
},
  "geometry": {"coordinates":[47.2792,34.06],"type":"Point"}
}