{
  "type": "Feature",
  "properties": {
    "gn:admin1_code":"41.0",
    "gn:asciiname":"Ateshkadeh-ye Sofla",
    "gn:country_code":"IR",
    "gn:dem":1443,
    "gn:feature_class":"P",
    "gn:feature_code":"PPL",
    "gn:name":"\u0100teshkadeh-ye Sofl\u00e1",
    "gn:population":0,
    "gn:timezone":"Asia/Tehran",
    "iso:country":"IR",
    "name:fas_x_preferred":[
        "\u0100teshkadeh-ye P\u0101\u2019\u012bn"
    ],
    "name:fas_x_variant":[
        "\u0622\u062a\u0634\u06a9\u062f\u0647 \u0633\u0641\u0644\u06cc"
    ],
    "name:und_x_variant":[
        "\u0100tashkadeh",
        "\u0100teshkadeh",
        "\u0100teshkadeh-ye Sofl\u00e1"
    ],
    "wof:name":"Ateshkadeh-ye Sofla",
    "wof:placetype":"locality"
},
  "geometry": {"coordinates":[59.45134,31.6349],"type":"Point"}
}