{
  "type": "Feature",
  "properties": {
    "gn:admin1_code":"29",
    "gn:asciiname":"Shurabad",
    "gn:country_code":"IR",
    "gn:dem":697,
    "gn:feature_class":"P",
    "gn:feature_code":"PPL",
    "gn:name":"Sh\u016br\u0101b\u0101d",
    "gn:population":0,
    "gn:timezone":"Asia/Tehran",
    "iso:country":"IR",
    "name:aze_x_preferred":[
        "\u015euraabad"
    ],
    "name:ceb_x_preferred":[
        "Shurabad"
    ],
    "name:fas_x_preferred":[
        "\u0634\u0648\u0631 \u0622\u0628\u0627\u062f \u0646\u0648\u0631"
    ],
    "name:fas_x_variant":[
        "Sh\u016br\u0101b\u0101d-e N\u016br",
        "\u0634\u0648\u0631 \u0622\u0628\u0627\u062f"
    ],
    "name:kat_x_preferred":[
        "\u10e8\u10e3\u10e0\u10d0\u10d0\u10d1\u10d0\u10d3\u10d8"
    ],
    "name:msa_x_preferred":[
        "\u015euraabad"
    ],
    "name:swe_x_preferred":[
        "Shurabad"
    ],
    "name:und_x_variant":[
        "Sh\u016br\u0101b\u0101d"
    ],
    "wof:name":"Shurabad",
    "wof:placetype":"locality"
},
  "geometry": {"coordinates":[58.8359,28.99468],"type":"Point"}
}