{
  "type": "Feature",
  "properties": {
    "gn:admin1_code":"23",
    "gn:asciiname":"Valian",
    "gn:country_code":"IR",
    "gn:dem":1490,
    "gn:feature_class":"P",
    "gn:feature_code":"PPL",
    "gn:name":"Val\u012b\u0101n",
    "gn:population":0,
    "gn:timezone":"Asia/Tehran",
    "iso:country":"IR",
    "name:ara_x_preferred":[
        "\u0648\u0644\u064a\u0627\u0646"
    ],
    "name:ceb_x_preferred":[
        "Val\u012b\u0101n"
    ],
    "name:fas_x_preferred":[
        "\u0648\u0644\u064a\u0627\u0646"
    ],
    "name:fas_x_variant":[
        "Val\u012b\u0101n",
        "\u0648\u0644\u06cc\u0627\u0646"
    ],
    "name:swe_x_preferred":[
        "Val\u012b\u0101n"
    ],
    "name:und_x_variant":[
        "W\u0101li\u0101n",
        "Vely\u0101n",
        "Valy\u0101n"
    ],
    "wof:name":"Valian",
    "wof:placetype":"locality"
},
  "geometry": {"coordinates":[48.8848,33.7212],"type":"Point"}
}