{
  "type": "Feature",
  "properties": {
    "gn:admin1_code":"11",
    "gn:asciiname":"Gattan-e Pakuhi",
    "gn:country_code":"IR",
    "gn:dem":14,
    "gn:feature_class":"P",
    "gn:feature_code":"PPL",
    "gn:name":"Gatt\u0101n-e P\u0101k\u016bh\u012b",
    "gn:population":0,
    "gn:timezone":"Asia/Tehran",
    "iso:country":"IR",
    "name:fas_x_preferred":[
        "\u06af\u062a\u0627\u0646 \u067e\u0627\u0626\u064a\u0646"
    ],
    "name:fas_x_variant":[
        "\u06af\u062a\u0627\u0646 \u067e\u0627\u0643\u0648\u0647\u06cc",
        "Gatt\u0101n-e P\u0101\u2019\u012bn",
        "Gatt\u0101n-e P\u0101k\u016bh\u012b"
    ],
    "wof:name":"Gattan-e Pakuhi",
    "wof:placetype":"locality"
},
  "geometry": {"coordinates":[57.2905,25.9847],"type":"Point"}
}