{
  "type": "Feature",
  "properties": {
    "gn:admin1_code":"37.0",
    "gn:asciiname":"Milani",
    "gn:country_code":"IR",
    "gn:dem":182,
    "gn:feature_class":"P",
    "gn:feature_code":"PPL",
    "gn:name":"M\u012bl\u0101n\u012b",
    "gn:population":0,
    "gn:timezone":"Asia/Tehran",
    "iso:country":"IR",
    "name:fas_x_preferred":[
        "\u0645\u06cc\u0644\u0627\u0646\u06cc"
    ],
    "name:und_x_variant":[
        "M\u012bl\u0101n\u012b"
    ],
    "wof:name":"Milani",
    "wof:placetype":"locality"
},
  "geometry": {"coordinates":[55.49704000000001,37.31586],"type":"Point"}
}