{
  "type": "Feature",
  "properties": {
    "gn:admin1_code":"41",
    "gn:asciiname":"Chahar Qach",
    "gn:country_code":"IR",
    "gn:dem":1507,
    "gn:feature_class":"P",
    "gn:feature_code":"PPLL",
    "gn:name":"Chah\u0101r Q\u0101ch",
    "gn:population":0,
    "gn:timezone":"Asia/Tehran",
    "iso:country":"IR",
    "name:fas_x_preferred":[
        "Chah\u0101r Q\u0101rch"
    ],
    "name:fas_x_variant":[
        "\u0686\u0647\u0627\u0631 \u0642\u0627\u0631\u0686",
        "\u0686\u0647\u0627\u0631 \u0642\u0627\u0686"
    ],
    "name:und_x_variant":[
        "Chah\u0101r Q\u0101ch"
    ],
    "wof:name":"Chahar Qach",
    "wof:placetype":"locality"
},
  "geometry": {"coordinates":[56.40064,33.55944],"type":"Point"}
}