{
  "type": "Feature",
  "properties": {
    "gn:admin1_code":"23.0",
    "gn:asciiname":"Abrizak",
    "gn:country_code":"IR",
    "gn:dem":1391,
    "gn:feature_class":"P",
    "gn:feature_code":"PPL",
    "gn:name":"\u0100br\u012bzak",
    "gn:population":0,
    "gn:timezone":"Asia/Tehran",
    "iso:country":"IR",
    "name:fas_x_preferred":[
        "\u0622\u0628\u0631\u064a\u0632\u06a9"
    ],
    "name:und_x_variant":[
        "\u0100br\u012bzak"
    ],
    "wof:name":"Abrizak",
    "wof:placetype":"locality"
},
  "geometry": {"coordinates":[48.83037,33.12406],"type":"Point"}
}