{
  "type": "Feature",
  "properties": {
    "gn:admin1_code":"28.0",
    "gn:asciiname":"Ghadirabad",
    "gn:country_code":"IR",
    "gn:dem":1839,
    "gn:feature_class":"P",
    "gn:feature_code":"PPL",
    "gn:name":"Ghad\u012br\u0101b\u0101d",
    "gn:population":0,
    "gn:timezone":"Asia/Tehran",
    "iso:country":"IR",
    "name:fas_x_preferred":[
        "Ghad\u012br\u0101b\u0101d"
    ],
    "wof:name":"Ghadirabad",
    "wof:placetype":"locality"
},
  "geometry": {"coordinates":[51.13111,32.68167],"type":"Point"}
}