{
  "type": "Feature",
  "properties": {
    "gn:admin1_code":"32",
    "gn:asciiname":"Andazaq",
    "gn:country_code":"IR",
    "gn:dem":1523,
    "gn:feature_class":"P",
    "gn:feature_code":"PPL",
    "gn:name":"Andazaq",
    "gn:population":0,
    "gn:timezone":"Asia/Tehran",
    "iso:country":"IR",
    "name:ceb_x_preferred":[
        "Andazaq"
    ],
    "name:fas_x_preferred":[
        "\u0627\u0646\u062f\u0632\u0642"
    ],
    "name:msa_x_preferred":[
        "Andazaq"
    ],
    "name:mzn_x_preferred":[
        "\u0627\u0646\u062f\u0632\u0642"
    ],
    "name:swe_x_preferred":[
        "Andazaq"
    ],
    "wof:name":"Andazaq",
    "wof:placetype":"locality"
},
  "geometry": {"coordinates":[47.6095,38.3427],"type":"Point"}
}