{
  "type": "Feature",
  "properties": {
    "gn:admin1_code":"15",
    "gn:asciiname":"Beneshti",
    "gn:country_code":"IR",
    "gn:dem":773,
    "gn:feature_class":"P",
    "gn:feature_code":"PPL",
    "gn:name":"Benesht\u012b",
    "gn:population":0,
    "gn:timezone":"Asia/Tehran",
    "iso:country":"IR",
    "name:azb_x_preferred":[
        "\u0628\u0646\u0634\u062a\u06cc(\u0627\u06cc\u0630\u0647)"
    ],
    "name:fas_x_preferred":[
        "Benesht\u012b"
    ],
    "name:fas_x_variant":[
        "\u0628\u0646\u0634\u062a\u06cc"
    ],
    "wof:name":"Beneshti",
    "wof:placetype":"locality"
},
  "geometry": {"coordinates":[49.98333,31.98333],"type":"Point"}
}