{
  "type": "Feature",
  "properties": {
    "gn:admin1_code":"15",
    "gn:asciiname":"Beneshti",
    "gn:country_code":"IR",
    "gn:dem":773,
    "gn:feature_class":"P",
    "gn:feature_code":"PPL",
    "gn:name":"Benesht\u012b",
    "gn:population":0,
    "gn:timezone":"Asia/Tehran",
    "iso:country":"IR",
    "name:fas_x_preferred":[
        "Benesht\u012b"
    ],
    "wof:name":"Beneshti",
    "wof:placetype":"locality"
},
  "geometry": {"coordinates":[49.98333,31.98333],"type":"Point"}
}