{
  "type": "Feature",
  "properties": {
    "gn:admin1_code":"23",
    "gn:asciiname":"Chah Qazi",
    "gn:country_code":"IR",
    "gn:dem":1157,
    "gn:feature_class":"P",
    "gn:feature_code":"PPL",
    "gn:name":"Ch\u0101h Q\u0101\u1e95\u012b",
    "gn:population":0,
    "gn:timezone":"Asia/Tehran",
    "iso:country":"IR",
    "name:fas_x_preferred":[
        "\u0686\u0627\u0647 \u0642\u0627\u0633\u06cc"
    ],
    "name:fas_x_variant":[
        "Ch\u0101h Q\u0101sem\u012b",
        "Ch\u0101h Q\u0101s\u012b",
        "\u0686\u0627\u0647 \u0642\u0627\u0636\u06cc"
    ],
    "name:und_x_variant":[
        "Ch\u0101h Q\u0101\u1e95\u012b"
    ],
    "wof:name":"Chah Qazi",
    "wof:placetype":"locality"
},
  "geometry": {"coordinates":[46.9367,33.5457],"type":"Point"}
}