{
  "type": "Feature",
  "properties": {
    "gn:admin1_code":"11.0",
    "gn:asciiname":"Sorkh Bar",
    "gn:country_code":"IR",
    "gn:dem":62,
    "gn:feature_class":"P",
    "gn:feature_code":"PPL",
    "gn:name":"Sorkh B\u0101r",
    "gn:population":0,
    "gn:timezone":"Asia/Tehran",
    "iso:country":"IR",
    "name:fas_x_preferred":[
        "\u0633\u0631\u062e \u0628\u0627\u0631"
    ],
    "name:fas_x_variant":[
        "Sorkh B\u0101r"
    ],
    "wof:name":"Sorkh Bar",
    "wof:placetype":"locality"
},
  "geometry": {"coordinates":[57.1957,27.06557],"type":"Point"}
}