{
  "type": "Feature",
  "properties": {
    "gn:admin1_code":"44",
    "gn:asciiname":"Artun",
    "gn:country_code":"IR",
    "gn:dem":2249,
    "gn:feature_class":"P",
    "gn:feature_code":"PPL",
    "gn:name":"\u0100rt\u016bn",
    "gn:population":0,
    "gn:timezone":"Asia/Tehran",
    "iso:country":"IR",
    "name:ceb_x_preferred":[
        "\u0100rt\u016bn"
    ],
    "name:fas_x_preferred":[
        "\u0622\u0631\u062a\u0648\u0646"
    ],
    "name:fas_x_variant":[
        "\u0100rt\u016bn"
    ],
    "name:msa_x_preferred":[
        "Artun"
    ],
    "name:rus_x_preferred":[
        "\u0410\u0440\u0442\u0443\u043d"
    ],
    "name:swe_x_preferred":[
        "\u0100rt\u016bn"
    ],
    "wof:name":"Artun",
    "wof:placetype":"locality"
},
  "geometry": {"coordinates":[50.72539,36.2161],"type":"Point"}
}