{
  "type": "Feature",
  "properties": {
    "gn:admin1_code":"22.0",
    "gn:asciiname":"Ahsham-e Mohammad Heydar",
    "gn:country_code":"IR",
    "gn:dem":27,
    "gn:feature_class":"P",
    "gn:feature_code":"PPL",
    "gn:name":"A\u1e29sh\u0101m-e Mo\u1e29ammad \u1e28eydar",
    "gn:population":0,
    "gn:timezone":"Asia/Tehran",
    "iso:country":"IR",
    "name:fas_x_preferred":[
        "\u0627\u062d\u0634\u0627\u0645 \u0645\u062d\u0645\u0651\u062f \u062d\u06cc\u062f\u0631"
    ],
    "name:fas_x_variant":[
        "A\u1e29sh\u0101m-e Mo\u1e29ammad \u1e28eydar"
    ],
    "wof:name":"Ahsham-e Mohammad Heydar",
    "wof:placetype":"locality"
},
  "geometry": {"coordinates":[51.1468,28.9377],"type":"Point"}
}