{
  "type": "Feature",
  "properties": {
    "gn:admin1_code":"44",
    "gn:asciiname":"Meydanak",
    "gn:country_code":"IR",
    "gn:dem":2052,
    "gn:feature_class":"P",
    "gn:feature_code":"PPL",
    "gn:name":"Meyd\u0101nak",
    "gn:population":0,
    "gn:timezone":"Asia/Tehran",
    "iso:country":"IR",
    "name:fas_x_preferred":[
        "Meyd\u0101nak"
    ],
    "name:fas_x_variant":[
        "\u0645\u06cc\u062f\u0627\u0646\u06a9"
    ],
    "name:und_x_variant":[
        "Maidanak",
        "\u0645\u06cc\u062f\u0627\u0646\u06a9"
    ],
    "wof:name":"Meydanak",
    "wof:placetype":"locality"
},
  "geometry": {"coordinates":[51.31175,36.03687],"type":"Point"}
}