{
  "type": "Feature",
  "properties": {
    "gn:admin1_code":"11",
    "gn:asciiname":"Meyestan Gereh Kuh",
    "gn:cc2":"IR",
    "gn:country_code":"IR",
    "gn:dem":532,
    "gn:feature_class":"P",
    "gn:feature_code":"PPL",
    "gn:name":"Meyest\u0101n Gereh K\u016bh",
    "gn:population":0,
    "gn:timezone":"Asia/Tehran",
    "iso:country":"IR",
    "name:ara_x_preferred":[
        "\u0643\u0631\u0647 \u06a9\u0648\u0647"
    ],
    "name:fas_x_preferred":[
        "\u0645\u0650\u064a\u0650\u0633\u062a\u0627\u0646 \u06af\u0650\u0631\u0650\u0647 \u0643\u0648\u0647"
    ],
    "name:fas_x_variant":[
        "\u0645\u064a\u0633\u062a\u0627\u0646 \u06af\u0650\u0631\u0650\u0647 \u0643\u0648\u0647",
        "Meyest\u0101n Gereh K\u016bh",
        "\u06af\u0631\u0647 \u06a9\u0648\u0647"
    ],
    "name:msa_x_preferred":[
        "Gereh Kuh"
    ],
    "name:und_x_variant":[
        "M\u012bst\u0101n Gereh K\u016bh",
        "M\u012bst\u0101n-e-Gereh K\u016bh"
    ],
    "wof:name":"Meyestan Gereh Kuh",
    "wof:placetype":"locality"
},
  "geometry": {"coordinates":[54.09278000000001,27.18361],"type":"Point"}
}