{
  "type": "Feature",
  "properties": {
    "gn:admin1_code":"9",
    "gn:asciiname":"Sangdeh",
    "gn:country_code":"IR",
    "gn:dem":2157,
    "gn:feature_class":"P",
    "gn:feature_code":"PPL",
    "gn:name":"Sangdeh",
    "gn:population":0,
    "gn:timezone":"Asia/Tehran",
    "iso:country":"IR",
    "name:fas_x_preferred":[
        "\u0633\u0646\u06af\u062f\u0647"
    ],
    "wof:name":"Sangdeh",
    "wof:placetype":"locality"
},
  "geometry": {"coordinates":[49.03527,34.07155],"type":"Point"}
}