{
  "type": "Feature",
  "properties": {
    "gn:admin1_code":"1.0",
    "gn:asciiname":"Sanjuh",
    "gn:country_code":"IR",
    "gn:dem":942,
    "gn:feature_class":"P",
    "gn:feature_code":"PPL",
    "gn:name":"Sanj\u016bh",
    "gn:population":0,
    "gn:timezone":"Asia/Tehran",
    "iso:country":"IR",
    "name:fas_x_preferred":[
        "\u0633\u0646\u062c\u0648\u0647"
    ],
    "name:fas_x_variant":[
        "Sanj\u016bh"
    ],
    "wof:name":"Sanjuh",
    "wof:placetype":"locality"
},
  "geometry": {"coordinates":[45.4896,36.0144],"type":"Point"}
}