{
  "type": "Feature",
  "properties": {
    "gn:admin1_code":"4",
    "gn:asciiname":"Kohnak Ladi",
    "gn:country_code":"IR",
    "gn:dem":384,
    "gn:feature_class":"P",
    "gn:feature_code":"PPL",
    "gn:name":"Kohnak Lad\u012b",
    "gn:population":0,
    "gn:timezone":"Asia/Tehran",
    "iso:country":"IR",
    "name:fas_x_preferred":[
        "\u06a9\u0647\u0646\u06a9 \u0644\u062f\u06cc"
    ],
    "name:fas_x_variant":[
        "Kohnak Lad\u012b"
    ],
    "wof:name":"Kohnak Ladi",
    "wof:placetype":"locality"
},
  "geometry": {"coordinates":[59.41389,27.52453],"type":"Point"}
}