{
  "type": "Feature",
  "properties": {
    "gn:admin1_code":"8",
    "gn:asciiname":"Lasheh",
    "gn:country_code":"IR",
    "gn:dem":-11,
    "gn:feature_class":"P",
    "gn:feature_code":"PPL",
    "gn:name":"L\u0101sheh",
    "gn:population":0,
    "gn:timezone":"Asia/Tehran",
    "iso:country":"IR",
    "name:fas_x_preferred":[
        "L\u0101sheh"
    ],
    "name:fas_x_variant":[
        "\u0644\u0627\u0634\u0647"
    ],
    "name:msa_x_preferred":[
        "Lasheh"
    ],
    "name:ukr_x_preferred":[
        "\u041b\u0430\u0448\u0435"
    ],
    "name:und_x_variant":[
        "\u0644\u0627\u0634\u0647"
    ],
    "name:urd_x_preferred":[
        "\u0644\u0627\u0634\u06cc\u06c1"
    ],
    "wof:name":"Lasheh",
    "wof:placetype":"locality"
},
  "geometry": {"coordinates":[49.88225,37.33308],"type":"Point"}
}