{
  "type": "Feature",
  "properties": {
    "gn:admin1_code":"11",
    "gn:asciiname":"Gishan",
    "gn:country_code":"IR",
    "gn:dem":466,
    "gn:feature_class":"P",
    "gn:feature_code":"PPL",
    "gn:name":"G\u012bsh\u0101n",
    "gn:population":0,
    "gn:timezone":"Asia/Tehran",
    "iso:country":"IR",
    "name:fas_x_preferred":[
        "\u06af\u064a\u0634\u0627\u0646"
    ],
    "name:fas_x_variant":[
        "G\u012bsh\u0101n",
        "\u06af\u06cc\u0634\u0627\u0646"
    ],
    "wof:name":"Gishan",
    "wof:placetype":"locality"
},
  "geometry": {"coordinates":[57.22667,27.49861],"type":"Point"}
}