{
  "type": "Feature",
  "properties": {
    "gn:admin1_code":"1.0",
    "gn:asciiname":"Garmandar",
    "gn:country_code":"IR",
    "gn:dem":1607,
    "gn:feature_class":"P",
    "gn:feature_code":"PPL",
    "gn:name":"Garmand\u0101r",
    "gn:population":0,
    "gn:timezone":"Asia/Tehran",
    "iso:country":"IR",
    "name:fas_x_preferred":[
        "\u06af\u0631\u0645\u0646\u062f\u0627\u0631"
    ],
    "name:fas_x_variant":[
        "Garmand\u0101r"
    ],
    "wof:name":"Garmandar",
    "wof:placetype":"locality"
},
  "geometry": {"coordinates":[45.3792,36.5296],"type":"Point"}
}