{
  "type": "Feature",
  "properties": {
    "gn:admin1_code":"15.0",
    "gn:asciiname":"Cham Chakhal",
    "gn:country_code":"IR",
    "gn:dem":272,
    "gn:feature_class":"P",
    "gn:feature_code":"PPLL",
    "gn:name":"Cham Chakhal",
    "gn:population":0,
    "gn:timezone":"Asia/Tehran",
    "iso:country":"IR",
    "name:fas_x_preferred":[
        "\u0686\u0645 \u0686\u062e\u0644"
    ],
    "wof:name":"Cham Chakhal",
    "wof:placetype":"locality"
},
  "geometry": {"coordinates":[48.22399,32.58146],"type":"Point"}
}