{
  "type": "Feature",
  "properties": {
    "gn:admin1_code":"29",
    "gn:asciiname":"Rud Azhdar",
    "gn:country_code":"IR",
    "gn:dem":2705,
    "gn:feature_class":"P",
    "gn:feature_code":"PPL",
    "gn:name":"R\u016bd Azhdar",
    "gn:population":0,
    "gn:timezone":"Asia/Tehran",
    "iso:country":"IR",
    "name:fas_x_preferred":[
        "\u0631\u0648\u062f \u0627\u0698\u062f\u0631"
    ],
    "name:fas_x_variant":[
        "R\u016bd Azhdar"
    ],
    "wof:name":"Rud Azhdar",
    "wof:placetype":"locality"
},
  "geometry": {"coordinates":[56.069,29.868],"type":"Point"}
}