{
  "type": "Feature",
  "properties": {
    "gn:admin1_code":"13",
    "gn:asciiname":"Gahvareh",
    "gn:country_code":"IR",
    "gn:dem":1470,
    "gn:feature_class":"P",
    "gn:feature_code":"PPL",
    "gn:name":"Gahv\u0101reh",
    "gn:population":0,
    "gn:timezone":"Asia/Tehran",
    "iso:country":"IR",
    "name:fas_x_preferred":[
        "\u06af\u0647\u0648\u0627\u0631\u0647"
    ],
    "name:fas_x_variant":[
        "Gahv\u0101reh"
    ],
    "name:und_x_variant":[
        "Gav\u0101ra",
        "Gawareh"
    ],
    "wof:name":"Gahvareh",
    "wof:placetype":"locality"
},
  "geometry": {"coordinates":[46.41718,34.34412],"type":"Point"}
}