{
  "type": "Feature",
  "properties": {
    "gn:admin1_code":"8",
    "gn:asciiname":"Chulab",
    "gn:country_code":"IR",
    "gn:dem":-6,
    "gn:feature_class":"P",
    "gn:feature_code":"PPL",
    "gn:name":"Ch\u016bl\u0101b",
    "gn:population":0,
    "gn:timezone":"Asia/Tehran",
    "iso:country":"IR",
    "name:ceb_x_preferred":[
        "Ch\u016bl\u0101b"
    ],
    "name:fas_x_preferred":[
        "Ch\u016bl\u0101b"
    ],
    "name:fas_x_variant":[
        "\u0686\u0648\u0644\u0627\u0628"
    ],
    "name:msa_x_preferred":[
        "Chulab"
    ],
    "name:swe_x_preferred":[
        "Ch\u016bl\u0101b"
    ],
    "name:ukr_x_preferred":[
        "\u0427\u0443\u043b\u0430\u0431"
    ],
    "name:und_x_variant":[
        "Choolab",
        "\u0686\u0648\u0644\u0627\u0628"
    ],
    "wof:name":"Chulab",
    "wof:placetype":"locality"
},
  "geometry": {"coordinates":[49.88018,37.26229],"type":"Point"}
}