{
  "type": "Feature",
  "properties": {
    "gn:admin1_code":"23",
    "gn:asciiname":"Darreh Khowrshid",
    "gn:country_code":"IR",
    "gn:dem":1369,
    "gn:feature_class":"P",
    "gn:feature_code":"PPL",
    "gn:name":"Darreh Khowrsh\u012bd",
    "gn:population":0,
    "gn:timezone":"Asia/Tehran",
    "iso:country":"IR",
    "name:fas_x_preferred":[
        "\u062f\u0631\u0651\u0647 \u062e\u0648\u0634\u06cc"
    ],
    "name:fas_x_variant":[
        "\u062f\u0631\u0647 \u062e\u0648\u0631\u0634\u06cc\u062f"
    ],
    "name:und_x_variant":[
        "Darreh Khowsh\u012b",
        "Darreh Khowrsh\u012bd"
    ],
    "wof:name":"Darreh Khowrshid",
    "wof:placetype":"locality"
},
  "geometry": {"coordinates":[47.57317000000001,33.69772],"type":"Point"}
}