{
  "type": "Feature",
  "properties": {
    "gn:admin1_code":"29",
    "gn:asciiname":"Tavakkolabad",
    "gn:country_code":"IR",
    "gn:dem":1981,
    "gn:feature_class":"P",
    "gn:feature_code":"PPL",
    "gn:name":"Tavakkol\u0101b\u0101d",
    "gn:population":0,
    "gn:timezone":"Asia/Tehran",
    "iso:country":"IR",
    "name:fas_x_preferred":[
        "\u0686\u0627\u0647 \u062a\u0648\u06a9\u0644 \u0622\u0628\u0627\u062f"
    ],
    "name:fas_x_variant":[
        "Ch\u0101h-e Tavakkol\u0101b\u0101d",
        "\u062a\u0648\u06a9\u0644 \u0622\u0628\u0627\u062f",
        "\u062a\u0648\u06a9\u0644\u200c\u0622\u0628\u0627\u062f"
    ],
    "name:und_x_variant":[
        "Tavakkol\u0101b\u0101d"
    ],
    "wof:name":"Tavakkolabad",
    "wof:placetype":"locality"
},
  "geometry": {"coordinates":[55.005,30.2748],"type":"Point"}
}