{
  "type": "Feature",
  "properties": {
    "gn:admin1_code":"32",
    "gn:asciiname":"Qarah Khanlu",
    "gn:country_code":"IR",
    "gn:dem":1825,
    "gn:feature_class":"P",
    "gn:feature_code":"PPL",
    "gn:name":"Qarah Kh\u0101nl\u016b",
    "gn:population":0,
    "gn:timezone":"Asia/Tehran",
    "iso:country":"IR",
    "name:fas_x_preferred":[
        "\u0642\u0631\u0647 \u062e\u0627\u0646\u0644\u0648"
    ],
    "name:fas_x_variant":[
        "Qarah Kh\u0101nl\u016b"
    ],
    "name:msa_x_preferred":[
        "Qarah Khanlu"
    ],
    "wof:name":"Qarah Khanlu",
    "wof:placetype":"locality"
},
  "geometry": {"coordinates":[48.1795,38.7083],"type":"Point"}
}