{
  "type": "Feature",
  "properties": {
    "gn:admin1_code":"0",
    "gn:asciiname":"Begi",
    "gn:country_code":"IR",
    "gn:dem":780,
    "gn:feature_class":"P",
    "gn:feature_code":"PPL",
    "gn:name":"Beg\u012b",
    "gn:population":0,
    "gn:timezone":"Asia/Tehran",
    "iso:country":"IR",
    "name:fas_x_preferred":[
        "\u0628\u06af\u06cc"
    ],
    "name:fas_x_variant":[
        "Beg\u012b"
    ],
    "wof:name":"Begi",
    "wof:placetype":"locality"
},
  "geometry": {"coordinates":[57.539,27.7052],"type":"Point"}
}