{
  "type": "Feature",
  "properties": {
    "gn:admin1_code":"35.0",
    "gn:asciiname":"Halu'i",
    "gn:country_code":"IR",
    "gn:dem":14,
    "gn:feature_class":"P",
    "gn:feature_code":"PPL",
    "gn:name":"H\u0101l\u016b\u2019\u012b",
    "gn:population":0,
    "gn:timezone":"Asia/Tehran",
    "iso:country":"IR",
    "name:fas_x_preferred":[
        "H\u0101l\u016b\u2019\u012b"
    ],
    "name:fas_x_variant":[
        "\u0647\u0627\u0644\u0648\u0626\u06cc"
    ],
    "name:und_x_variant":[
        "\u0647\u0627\u0644\u0648\u0626\u06cc"
    ],
    "wof:name":"Halu'i",
    "wof:placetype":"locality"
},
  "geometry": {"coordinates":[50.89272,36.74512],"type":"Point"}
}