{
  "type": "Feature",
  "properties": {
    "gn:admin1_code":"26",
    "gn:asciiname":"Shahrak-e Deh-e Maviz",
    "gn:country_code":"IR",
    "gn:dem":1122,
    "gn:feature_class":"P",
    "gn:feature_code":"PPL",
    "gn:name":"Shahrak-e Deh-e Mav\u012bz",
    "gn:population":0,
    "gn:timezone":"Asia/Tehran",
    "iso:country":"IR",
    "name:fas_x_preferred":[
        "\u0634\u0647\u0631\u06a9 \u062f\u0647 \u0645\u0648\u064a\u0632"
    ],
    "name:und_x_variant":[
        "Deh Mav\u012bz",
        "Shahrak-e Deh-e Mav\u012bz"
    ],
    "wof:name":"Shahrak-e Deh-e Maviz",
    "wof:placetype":"locality"
},
  "geometry": {"coordinates":[51.1418,35.6477],"type":"Point"}
}