{
  "type": "Feature",
  "properties": {
    "gn:admin1_code":"7",
    "gn:asciiname":"Deh Namak",
    "gn:country_code":"IR",
    "gn:dem":1439,
    "gn:feature_class":"P",
    "gn:feature_code":"PPL",
    "gn:name":"Deh Namak",
    "gn:population":0,
    "gn:timezone":"Asia/Tehran",
    "iso:country":"IR",
    "name:fas_x_preferred":[
        "\u062f\u0647 \u0646\u0645\u06a9"
    ],
    "name:und_x_variant":[
        "Deh-e Namak",
        "Deh Namak"
    ],
    "wof:name":"Deh Namak",
    "wof:placetype":"locality"
},
  "geometry": {"coordinates":[52.1554,29.4204],"type":"Point"}
}