{
  "type": "Feature",
  "properties": {
    "gn:admin1_code":"11.0",
    "gn:asciiname":"Tam Gowhar",
    "gn:country_code":"IR",
    "gn:dem":17,
    "gn:feature_class":"P",
    "gn:feature_code":"PPL",
    "gn:name":"Tam Gowhar",
    "gn:population":0,
    "gn:timezone":"Asia/Tehran",
    "iso:country":"IR",
    "name:fas_x_preferred":[
        "\u062a\u0645 \u06af\u0648\u0647\u0631"
    ],
    "wof:name":"Tam Gowhar",
    "wof:placetype":"locality"
},
  "geometry": {"coordinates":[56.9998,27.1146],"type":"Point"}
}