{
  "type": "Feature",
  "properties": {
    "gn:admin1_code":"29.0",
    "gn:asciiname":"Bagh Kamal",
    "gn:country_code":"IR",
    "gn:dem":2269,
    "gn:feature_class":"P",
    "gn:feature_code":"PPL",
    "gn:name":"B\u0101gh Kam\u0101l",
    "gn:population":0,
    "gn:timezone":"Asia/Tehran",
    "iso:country":"IR",
    "name:fas_x_preferred":[
        "\u0628\u0627\u063a \u06a9\u0645\u0627\u0644"
    ],
    "name:und_x_variant":[
        "B\u0101gh Kam\u0101l"
    ],
    "wof:name":"Bagh Kamal",
    "wof:placetype":"locality"
},
  "geometry": {"coordinates":[57.61361,29.015],"type":"Point"}
}