{
  "type": "Feature",
  "properties": {
    "gn:admin1_code":"23",
    "gn:asciiname":"Chaqabol",
    "gn:country_code":"IR",
    "gn:dem":1903,
    "gn:feature_class":"P",
    "gn:feature_code":"PPL",
    "gn:name":"Chaq\u0101bol",
    "gn:population":0,
    "gn:timezone":"Asia/Tehran",
    "iso:country":"IR",
    "name:fas_x_preferred":[
        "\u0686\u064e\u0642\u0627\u0648\u064f\u0644"
    ],
    "name:fas_x_variant":[
        "\u0686\u064e\u0642\u0627\u0628\u064e\u0644",
        "\u0686\u064e\u063a\u0627\u0628\u064e\u0644",
        "\u0686\u064f\u0642\u0627 \u0628\u064f\u0644",
        "\u0686\u064f\u063a\u0627\u0628\u064e\u0644",
        "\u0686\u064f\u063a\u064e\u0648\u064e\u0644",
        "\u0686\u064f\u0642\u0627\u0628\u064e\u0644",
        "Chaq\u0101bol",
        "Chaq\u0101vol",
        "\u0686\u0642\u0627\u0628\u0644"
    ],
    "name:und_x_variant":[
        "Choghaval",
        "Chagawal",
        "Choq\u0101bal",
        "Chaq\u0101wal",
        "Choq\u0101 Bol",
        "Chagh\u0101bal",
        "Chogh\u0101bal",
        "Chaq\u0101bal",
        "\u0686\u0642\u0627\u0628\u0644"
    ],
    "wof:name":"Chaqabol",
    "wof:placetype":"locality"
},
  "geometry": {"coordinates":[48.50872,34.01445],"type":"Point"}
}