{
  "type": "Feature",
  "properties": {
    "gn:admin1_code":"15",
    "gn:asciiname":"Bazabad",
    "gn:country_code":"IR",
    "gn:dem":1458,
    "gn:feature_class":"P",
    "gn:feature_code":"PPL",
    "gn:name":"B\u0101z\u0101b\u0101d",
    "gn:population":0,
    "gn:timezone":"Asia/Tehran",
    "iso:country":"IR",
    "name:fas_x_preferred":[
        "\u0628\u0627\u0632\u0622\u0628\u0627\u062f"
    ],
    "wof:name":"Bazabad",
    "wof:placetype":"locality"
},
  "geometry": {"coordinates":[49.66694,32.41611],"type":"Point"}
}