{
  "type": "Feature",
  "properties": {
    "gn:admin1_code":"8.0",
    "gn:asciiname":"Pil Darreh",
    "gn:country_code":"IR",
    "gn:dem":182,
    "gn:feature_class":"P",
    "gn:feature_code":"PPL",
    "gn:name":"P\u012bl Darreh",
    "gn:population":0,
    "gn:timezone":"Asia/Tehran",
    "iso:country":"IR",
    "name:fas_x_preferred":[
        "P\u012bl Darreh"
    ],
    "wof:name":"Pil Darreh",
    "wof:placetype":"locality"
},
  "geometry": {"coordinates":[50.19667000000001,37.06361],"type":"Point"}
}