{
  "type": "Feature",
  "properties": {
    "gn:admin1_code":"8.0",
    "gn:asciiname":"Pil Darreh",
    "gn:country_code":"IR",
    "gn:dem":182,
    "gn:feature_class":"P",
    "gn:feature_code":"PPL",
    "gn:name":"P\u012bl Darreh",
    "gn:population":0,
    "gn:timezone":"Asia/Tehran",
    "iso:country":"IR",
    "name:ara_x_preferred":[
        "\u0628\u064a\u0644\u062f\u0631\u0629"
    ],
    "name:ceb_x_preferred":[
        "P\u012bl Darreh"
    ],
    "name:fas_x_preferred":[
        "P\u012bl Darreh"
    ],
    "name:fas_x_variant":[
        "\u067e\u06cc\u0644\u062f\u0631\u0647"
    ],
    "name:msa_x_preferred":[
        "Pil Darreh"
    ],
    "name:swe_x_preferred":[
        "P\u012bl Darreh"
    ],
    "name:ukr_x_preferred":[
        "\u041f\u0456\u043b\u0434\u0430\u0440\u0435"
    ],
    "wof:name":"Pil Darreh",
    "wof:placetype":"locality"
},
  "geometry": {"coordinates":[50.19667000000001,37.06361],"type":"Point"}
}