{
  "type": "Feature",
  "properties": {
    "gn:admin1_code":"34",
    "gn:asciiname":"Qal`eh-ye Mohammad Beyk",
    "gn:country_code":"IR",
    "gn:dem":1670,
    "gn:feature_class":"P",
    "gn:feature_code":"PPL",
    "gn:name":"Qal\u2018eh-ye Mo\u1e29ammad Beyk",
    "gn:population":0,
    "gn:timezone":"Asia/Tehran",
    "iso:country":"IR",
    "name:fas_x_preferred":[
        "Qal\u2018eh-ye Mo\u1e29ammad Beyk"
    ],
    "name:fas_x_variant":[
        "\u0642\u0644\u0639\u0647 \u0645\u062d\u0645\u062f \u0628\u064a\u0643"
    ],
    "name:und_x_variant":[
        "\u0642\u0644\u0639\u0647 \u0645\u062d\u0645\u062f \u0628\u064a\u0643"
    ],
    "wof:name":"Qal`eh-ye Mohammad Beyk",
    "wof:placetype":"locality"
},
  "geometry": {"coordinates":[50.30472,33.67965],"type":"Point"}
}