{
  "type": "Feature",
  "properties": {
    "gn:admin1_code":"34",
    "gn:asciiname":"Aq Bolagh",
    "gn:country_code":"IR",
    "gn:dem":2471,
    "gn:feature_class":"P",
    "gn:feature_code":"PPL",
    "gn:name":"\u0100q Bol\u0101gh",
    "gn:population":0,
    "gn:timezone":"Asia/Tehran",
    "iso:country":"IR",
    "name:fas_x_preferred":[
        "\u0622\u0642\u0628\u0644\u0627\u063a"
    ],
    "name:fas_x_variant":[
        "\u0622\u0642 \u0628\u0644\u0627\u0642",
        "\u0100q Bol\u0101gh",
        "\u0100q Bol\u0101q"
    ],
    "wof:name":"Aq Bolagh",
    "wof:placetype":"locality"
},
  "geometry": {"coordinates":[49.57632,35.37977],"type":"Point"}
}