{
  "type": "Feature",
  "properties": {
    "gn:admin1_code":"42.0",
    "gn:asciiname":"Darz Ab",
    "gn:country_code":"IR",
    "gn:dem":811,
    "gn:feature_class":"P",
    "gn:feature_code":"PPL",
    "gn:name":"Darz \u0100b",
    "gn:population":0,
    "gn:timezone":"Asia/Tehran",
    "iso:country":"IR",
    "name:fas_x_preferred":[
        "Darz \u0100b"
    ],
    "wof:name":"Darz Ab",
    "wof:placetype":"locality"
},
  "geometry": {"coordinates":[60.95889,35.85472],"type":"Point"}
}