{
  "type": "Feature",
  "properties": {
    "gn:admin1_code":"5",
    "gn:asciiname":"Zangi Va",
    "gn:country_code":"IR",
    "gn:dem":2156,
    "gn:feature_class":"P",
    "gn:feature_code":"PPL",
    "gn:name":"Zang\u012b V\u0101",
    "gn:population":0,
    "gn:timezone":"Asia/Tehran",
    "iso:country":"IR",
    "name:fas_x_preferred":[
        "\u0632\u064e\u0646\u06af\u064e\u0648\u0627"
    ],
    "name:fas_x_variant":[
        "Zang\u012b V\u0101",
        "Zangav\u0101",
        "\u0632\u0646\u06af\u06cc \u0648\u0627"
    ],
    "name:und_x_variant":[
        "\u0632\u0646\u06af\u06cc \u0648\u0627"
    ],
    "wof:name":"Zangi Va",
    "wof:placetype":"locality"
},
  "geometry": {"coordinates":[51.07842,30.8973],"type":"Point"}
}