{
  "type": "Feature",
  "properties": {
    "gn:admin1_code":"42",
    "gn:asciiname":"Tangal-e Shur-e Bala",
    "gn:country_code":"IR",
    "gn:dem":960,
    "gn:feature_class":"P",
    "gn:feature_code":"PPL",
    "gn:name":"Tangal-e Sh\u016br-e B\u0101l\u0101",
    "gn:population":0,
    "gn:timezone":"Asia/Tehran",
    "iso:country":"IR",
    "name:fas_x_preferred":[
        "\u062a\u0646\u06af\u0644 \u0634\u0648\u0631 \u0628\u0627\u0644\u0627"
    ],
    "name:fas_x_variant":[
        "Tangal-e Sh\u016br",
        "Tangal-e Sh\u016br-e B\u0101l\u0101"
    ],
    "wof:name":"Tangal-e Shur-e Bala",
    "wof:placetype":"locality"
},
  "geometry": {"coordinates":[59.8365,36.1368],"type":"Point"}
}