{
  "type": "Feature",
  "properties": {
    "gn:admin1_code":"13",
    "gn:asciiname":"Dom Badam",
    "gn:country_code":"IR",
    "gn:dem":1534,
    "gn:feature_class":"P",
    "gn:feature_code":"PPL",
    "gn:name":"Dom B\u0101d\u0101m",
    "gn:population":0,
    "gn:timezone":"Asia/Tehran",
    "iso:country":"IR",
    "name:fas_x_preferred":[
        "\u062f\u0645 \u0628\u0627\u062f\u0627\u0645"
    ],
    "name:fas_x_variant":[
        "Dom B\u0101d\u0101m"
    ],
    "wof:name":"Dom Badam",
    "wof:placetype":"locality"
},
  "geometry": {"coordinates":[47.9441,34.5377],"type":"Point"}
}