{
  "type": "Feature",
  "properties": {
    "gn:admin1_code":"10.0",
    "gn:asciiname":"Vachakbud-e `Olya",
    "gn:country_code":"IR",
    "gn:dem":856,
    "gn:feature_class":"P",
    "gn:feature_code":"PPL",
    "gn:name":"Vachakb\u016bd-e \u2018Oly\u0101",
    "gn:population":0,
    "gn:timezone":"Asia/Tehran",
    "iso:country":"IR",
    "name:fas_x_preferred":[
        "\u0648\u0686\u0643\u0628\u0648\u062f \u0639\u0644\u064a\u0627"
    ],
    "name:fas_x_variant":[
        "\u0648\u062c\u0647 \u06a9\u0628\u0648\u062f \u0628\u0627\u0644\u0627",
        "Vachakb\u016bd-e \u2018Oly\u0101",
        "Vajah Kab\u016bd-e B\u0101l\u0101",
        "\u0648\u064e\u062c\u0647\u0650 \u0643\u064e\u0628\u0648\u062f",
        "\u0648\u0686\u06a9\u0628\u0648\u062f \u0639\u0644\u06cc\u0627"
    ],
    "name:und_x_variant":[
        "Vajh-e Kab\u016bd"
    ],
    "wof:name":"Vachakbud-e `Olya",
    "wof:placetype":"locality"
},
  "geometry": {"coordinates":[47.57779,32.9255],"type":"Point"}
}