{
  "type": "Feature",
  "properties": {
    "gn:admin1_code":"33",
    "gn:asciiname":"Zir Kan",
    "gn:country_code":"IR",
    "gn:dem":1890,
    "gn:feature_class":"P",
    "gn:feature_code":"PPL",
    "gn:name":"Z\u012br K\u0101n",
    "gn:population":0,
    "gn:timezone":"Asia/Tehran",
    "iso:country":"IR",
    "name:ara_x_preferred":[
        "\u0632\u064a\u0631\u06a9\u0627\u0646"
    ],
    "name:fas_x_preferred":[
        "\u0632\u06cc\u0631 \u06a9\u0627\u0646"
    ],
    "name:fas_x_variant":[
        "Z\u012brk\u0101n",
        "Z\u012br K\u0101n",
        "\u0632\u06cc\u0631\u06a9\u0627\u0646"
    ],
    "name:msa_x_preferred":[
        "Zirkan"
    ],
    "wof:name":"Zir Kan",
    "wof:placetype":"locality"
},
  "geometry": {"coordinates":[47.0086,37.8832],"type":"Point"}
}