{
  "type": "Feature",
  "properties": {
    "gn:admin1_code":"0",
    "gn:asciiname":"Deylagarda",
    "gn:country_code":"IR",
    "gn:dem":100,
    "gn:feature_class":"P",
    "gn:feature_code":"PPL",
    "gn:name":"Deyl\u0101g\u0101rd\u0101",
    "gn:population":0,
    "gn:timezone":"Asia/Tehran",
    "iso:country":"IR",
    "name:fas_x_preferred":[
        "\u062f\u0650\u064a\u0644\u0627\u06af\u0627\u0631\u062f\u0627"
    ],
    "name:fas_x_variant":[
        "Deyl\u0101g\u0101rd\u0101"
    ],
    "wof:name":"Deylagarda",
    "wof:placetype":"locality"
},
  "geometry": {"coordinates":[47.63333,39.53333],"type":"Point"}
}