{
  "type": "Feature",
  "properties": {
    "gn:admin1_code":"15",
    "gn:asciiname":"Qarbiyeh",
    "gn:cc2":"IR",
    "gn:country_code":"IR",
    "gn:dem":30,
    "gn:feature_class":"P",
    "gn:feature_code":"PPL",
    "gn:name":"Qarb\u012byeh",
    "gn:population":0,
    "gn:timezone":"Asia/Tehran",
    "iso:country":"IR",
    "name:fas_x_preferred":[
        "Qarb\u012byeh"
    ],
    "name:und_x_variant":[
        "Ghareybeh"
    ],
    "wof:name":"Qarbiyeh",
    "wof:placetype":"locality"
},
  "geometry": {"coordinates":[48.56361,31.58972],"type":"Point"}
}