{
  "type": "Feature",
  "properties": {
    "gn:admin1_code":"33",
    "gn:asciiname":"Guravan",
    "gn:country_code":"IR",
    "gn:dem":1381,
    "gn:feature_class":"P",
    "gn:feature_code":"PPL",
    "gn:name":"G\u016br\u0101v\u0101n",
    "gn:population":0,
    "gn:timezone":"Asia/Tehran",
    "iso:country":"IR",
    "name:ara_x_preferred":[
        "\u063a\u0648\u0631\u0648\u0627\u0646 \u0628\u0632\u0631\u063a"
    ],
    "name:fas_x_preferred":[
        "G\u016bzv\u0101n-e Bozorg"
    ],
    "name:fas_x_variant":[
        "\u06af\u0648\u0631\u0627\u0648\u0627\u0646",
        "\u06af\u0648\u0631\u0627\u0646",
        "\u06af\u0648\u0631\u0648\u0627\u0646 \u0628\u0632\u0631\u06af"
    ],
    "name:msa_x_preferred":[
        "Gurvan-e Bozorg"
    ],
    "name:und_x_variant":[
        "G\u016br\u0101v\u0101n",
        "G\u016br\u0101n",
        "G\u016brv\u0101n-e Bozorg"
    ],
    "wof:name":"Guravan",
    "wof:placetype":"locality"
},
  "geometry": {"coordinates":[47.368,38.35797],"type":"Point"}
}