{
  "type": "Feature",
  "properties": {
    "gn:admin1_code":"29",
    "gn:asciiname":"Dar Patkan",
    "gn:country_code":"IR",
    "gn:dem":508,
    "gn:feature_class":"P",
    "gn:feature_code":"PPL",
    "gn:name":"Dar Pa\u0163k\u0101n",
    "gn:population":0,
    "gn:timezone":"Asia/Tehran",
    "iso:country":"IR",
    "name:fas_x_preferred":[
        "\u062f\u0631 \u067e\u0637\u06a9\u0627\u0646"
    ],
    "name:fas_x_variant":[
        "Dar Patg\u0101n",
        "Dar Pa\u0163k\u0101n"
    ],
    "wof:name":"Dar Patkan",
    "wof:placetype":"locality"
},
  "geometry": {"coordinates":[57.8577,27.8412],"type":"Point"}
}