{
  "type": "Feature",
  "properties": {
    "gn:admin1_code":"41.0",
    "gn:asciiname":"Dahaneh-ye Nasfandeh",
    "gn:country_code":"IR",
    "gn:dem":1211,
    "gn:feature_class":"P",
    "gn:feature_code":"PPL",
    "gn:name":"Dahaneh-ye N\u0101sfandeh",
    "gn:population":0,
    "gn:timezone":"Asia/Tehran",
    "iso:country":"IR",
    "name:fas_x_preferred":[
        "Dahaneh-ye N\u0101sfandeh"
    ],
    "name:fas_x_variant":[
        "\u062f\u0647\u0646\u0647 \u0646\u0627\u0633\u0641\u0646\u062f\u0647"
    ],
    "name:und_x_variant":[
        "N\u0101spandeh"
    ],
    "wof:name":"Dahaneh-ye Nasfandeh",
    "wof:placetype":"locality"
},
  "geometry": {"coordinates":[60.22044,31.6142],"type":"Point"}
}