{
  "type": "Feature",
  "properties": {
    "gn:admin1_code":"5",
    "gn:asciiname":"Chahab",
    "gn:country_code":"IR",
    "gn:dem":819,
    "gn:feature_class":"P",
    "gn:feature_code":"PPL",
    "gn:name":"Chah\u0101b",
    "gn:population":0,
    "gn:timezone":"Asia/Tehran",
    "iso:country":"IR",
    "name:fas_x_preferred":[
        "\u0686\u0647\u0627\u0628"
    ],
    "name:fas_x_variant":[
        "Chah\u0101b"
    ],
    "wof:name":"Chahab",
    "wof:placetype":"locality"
},
  "geometry": {"coordinates":[50.4867,30.67757000000001],"type":"Point"}
}