{
  "type": "Feature",
  "properties": {
    "gn:admin1_code":"8.0",
    "gn:asciiname":"Sadat Mahalleh-ye Nalkiashar",
    "gn:country_code":"IR",
    "gn:dem":-6,
    "gn:feature_class":"P",
    "gn:feature_code":"PPL",
    "gn:name":"S\u0101d\u0101t Ma\u1e29alleh-ye N\u0101lk\u012b\u0101shar",
    "gn:population":0,
    "gn:timezone":"Asia/Tehran",
    "iso:country":"IR",
    "name:fas_x_preferred":[
        "S\u0101d\u0101t Ma\u1e29alleh"
    ],
    "name:fas_x_variant":[
        "\u0633\u0627\u062f\u0627\u062a \u0645\u062d\u0644\u0647",
        "\u0633\u0627\u062f\u0627\u062a \u0645\u062d\u0644\u0647 \u0646\u0627\u0644\u06a9\u06cc\u0627\u0634\u0631",
        "\u0633\u0627\u062f\u0627\u062a \u0645\u062d\u0644\u0647 \u0646\u0627\u0644\u06a9\u06cc\u0627\u0634\u0647\u0631"
    ],
    "name:und_x_variant":[
        "S\u0101d\u0101t Ma\u1e29alleh-ye N\u0101lk\u012b\u0101shar",
        "S\u0101d\u0101t Ma\u1e29alleh-ye N\u0101lk\u012b\u0101shahr"
    ],
    "wof:name":"Sadat Mahalleh-ye Nalkiashar",
    "wof:placetype":"locality"
},
  "geometry": {"coordinates":[50.0842,37.21587],"type":"Point"}
}