{
  "type": "Feature",
  "properties": {
    "gn:admin1_code":"13",
    "gn:asciiname":"Qal`eh Jabre'il",
    "gn:country_code":"IR",
    "gn:dem":1883,
    "gn:feature_class":"P",
    "gn:feature_code":"PPL",
    "gn:name":"Qal\u2018eh Jabre\u2019\u012bl",
    "gn:population":0,
    "gn:timezone":"Asia/Tehran",
    "iso:country":"IR",
    "name:fas_x_preferred":[
        "\u0642\u0644\u0639\u0647 \u062c\u0628\u0631\u0626\u06cc\u0644"
    ],
    "name:fas_x_variant":[
        "Qal\u2018eh Jabre\u2019\u012bl"
    ],
    "name:und_x_variant":[
        "Deh Zh\u016br\u0101",
        "Qal\u2018eh-ye Jabr\u0101\u2019\u012bl",
        "Deh B\u0101l\u0101",
        "Deh-i-Jurail"
    ],
    "wof:name":"Qal`eh Jabre'il",
    "wof:placetype":"locality"
},
  "geometry": {"coordinates":[47.38259,35.01761],"type":"Point"}
}