{
  "type": "Feature",
  "properties": {
    "gn:admin1_code":"34",
    "gn:asciiname":"Qeshlaq Sharaflu",
    "gn:country_code":"IR",
    "gn:dem":1057,
    "gn:feature_class":"P",
    "gn:feature_code":"PPL",
    "gn:name":"Qeshl\u0101q Sharafl\u016b",
    "gn:population":0,
    "gn:timezone":"Asia/Tehran",
    "iso:country":"IR",
    "name:fas_x_preferred":[
        "Mazra\u2018eh-ye Sharafl\u016b"
    ],
    "name:fas_x_variant":[
        "\u0642\u0634\u0644\u0627\u0642 \u0634\u0631\u0641\u0644\u0648"
    ],
    "name:und_x_variant":[
        "Qeshl\u0101q Sharafl\u016b",
        "\u0642\u0634\u0644\u0627\u0642 \u0634\u0631\u0641\u0644\u0648"
    ],
    "wof:name":"Qeshlaq Sharaflu",
    "wof:placetype":"locality"
},
  "geometry": {"coordinates":[50.27735,34.9815],"type":"Point"}
}