{
  "type": "Feature",
  "properties": {
    "gn:admin1_code":"11",
    "gn:asciiname":"Kalengi",
    "gn:country_code":"IR",
    "gn:dem":29,
    "gn:feature_class":"P",
    "gn:feature_code":"PPL",
    "gn:name":"K\u0101leng\u012b",
    "gn:population":0,
    "gn:timezone":"Asia/Tehran",
    "iso:country":"IR",
    "name:fas_x_preferred":[
        "\u0643\u0627\u0644\u0646\u06af\u06cc"
    ],
    "name:fas_x_variant":[
        "K\u0101leng\u012b"
    ],
    "wof:name":"Kalengi",
    "wof:placetype":"locality"
},
  "geometry": {"coordinates":[57.0329,27.22641],"type":"Point"}
}