{
  "type": "Feature",
  "properties": {
    "gn:admin1_code":"1",
    "gn:asciiname":"Sheykh Salu-ye Sofla",
    "gn:country_code":"IR",
    "gn:dem":2365,
    "gn:feature_class":"P",
    "gn:feature_code":"PPL",
    "gn:name":"Sheykh Sal\u016b-ye Sofl\u00e1",
    "gn:population":0,
    "gn:timezone":"Asia/Tehran",
    "iso:country":"IR",
    "name:fas_x_preferred":[
        "Sheykh Sal\u016b-ye Sofl\u00e1"
    ],
    "name:fas_x_variant":[
        "\u0634\u06cc\u062e \u0633\u0644\u0648\u06cc \u0633\u0641\u0644\u06cc"
    ],
    "name:und_x_variant":[
        "Shaikh Silu Ash\u0101ghi",
        "Sheykh Sol\u016b",
        "Sheikh Salooy Sofla",
        "Sheykh Sol\u016b-ye Sofl\u00e1",
        "Sheykh Sal\u016b-ye P\u0101\u2019\u012bn",
        "Sheykh Sol\u016b-ye P\u0101\u2019\u012bn",
        "Sheykh Sel\u016b-ye P\u0101\u2019\u012bn"
    ],
    "wof:name":"Sheykh Salu-ye Sofla",
    "wof:placetype":"locality"
},
  "geometry": {"coordinates":[44.2091,38.9655],"type":"Point"}
}