{
  "type": "Feature",
  "properties": {
    "gn:admin1_code":"1.0",
    "gn:asciiname":"Yaghian",
    "gn:country_code":"IR",
    "gn:dem":1559,
    "gn:feature_class":"P",
    "gn:feature_code":"PPL",
    "gn:name":"Y\u0101gh\u012b\u0101n",
    "gn:population":0,
    "gn:timezone":"Asia/Tehran",
    "iso:country":"IR",
    "name:ara_x_preferred":[
        "\u064a\u0627\u063a\u064a\u0627\u0646"
    ],
    "name:aze_x_preferred":[
        "Ya\u011fiyan"
    ],
    "name:ceb_x_preferred":[
        "Y\u0101gh\u012b\u0101n"
    ],
    "name:fas_x_preferred":[
        "\u06cc\u0627\u063a\u06cc\u0627\u0646"
    ],
    "name:fas_x_variant":[
        "Y\u0101gh\u012b\u0101n"
    ],
    "name:msa_x_preferred":[
        "Yaghian"
    ],
    "name:swe_x_preferred":[
        "Y\u0101gh\u012b\u0101n"
    ],
    "name:urd_x_preferred":[
        "\u06cc\u06af\u06be\u06cc\u0627\u06ba"
    ],
    "wof:name":"Yaghian",
    "wof:placetype":"locality"
},
  "geometry": {"coordinates":[45.87,36.2516],"type":"Point"}
}