{
  "type": "Feature",
  "properties": {
    "gn:admin1_code":"16.0",
    "gn:asciiname":"Kowqher",
    "gn:country_code":"IR",
    "gn:dem":1638,
    "gn:feature_class":"P",
    "gn:feature_code":"PPL",
    "gn:name":"Kowqher",
    "gn:population":0,
    "gn:timezone":"Asia/Tehran",
    "iso:country":"IR",
    "name:fas_x_preferred":[
        "\u0643\u064f\u0648\u0642\u0647\u0650\u0631"
    ],
    "wof:name":"Kowqher",
    "wof:placetype":"locality"
},
  "geometry": {"coordinates":[45.83333,35.93333],"type":"Point"}
}