{
  "type": "Feature",
  "properties": {
    "gn:admin1_code":"35",
    "gn:asciiname":"Muzi Goti-ye Pa'in",
    "gn:country_code":"IR",
    "gn:dem":-3,
    "gn:feature_class":"P",
    "gn:feature_code":"PPL",
    "gn:name":"M\u016bz\u012b Got\u012b-ye P\u0101\u2019\u012bn",
    "gn:population":0,
    "gn:timezone":"Asia/Tehran",
    "iso:country":"IR",
    "name:fas_x_preferred":[
        "M\u016bz\u012bk\u016bt\u012b-ye P\u0101\u2019\u012bn"
    ],
    "name:fas_x_variant":[
        "M\u016bz\u012b Got\u012b-ye P\u0101\u2019\u012bn",
        "\u0645\u0648\u0632\u06cc \u06af\u062a\u06cc \u067e\u0627\u0626\u06cc\u0646"
    ],
    "wof:name":"Muzi Goti-ye Pa'in",
    "wof:placetype":"locality"
},
  "geometry": {"coordinates":[52.51481999999999,36.55117],"type":"Point"}
}