{
  "type": "Feature",
  "properties": {
    "gn:admin1_code":"11",
    "gn:asciiname":"Bandar-e Tahuneh",
    "gn:country_code":"IR",
    "gn:dem":4,
    "gn:feature_class":"P",
    "gn:feature_code":"PPL",
    "gn:name":"Bandar-e \u0162\u0101\u1e29\u016bneh",
    "gn:population":0,
    "gn:timezone":"Asia/Tehran",
    "iso:country":"IR",
    "name:fas_x_preferred":[
        "\u0637\u0627\u0639\u0648\u0646\u0650\u0647"
    ],
    "name:fas_x_variant":[
        "\u062a\u0627\u0648\u0648\u0646\u0650\u0647",
        "\u0637\u0627\u062d\u0648\u0646\u0650\u0647",
        "\u0628\u0646\u062f\u0631\u0650 \u0637\u0627\u0639\u0648\u0646\u0647",
        "\u0628\u064e\u0646\u062f\u064e\u0631 \u062a\u064e\u0647\u064f\u0651\u0646\u0650\u0647",
        "\u0162\u0101\u2018\u016bneh",
        "Bandar-e \u0162\u0101\u1e29\u016bneh",
        "\u0628\u0646\u062f\u0631 \u0637\u0627\u062d\u0648\u0646\u0647"
    ],
    "name:und_x_variant":[
        "Bandar-e \u0162\u0101\u1e29\u016bneh",
        "\u0162\u0101\u1e29\u016bneh",
        "Bandar-e \u0162\u0101\u2018\u016bneh",
        "T\u0101v\u016bneh",
        "Bandar Tahooneh",
        "\u0628\u0646\u062f\u0631 \u0637\u0627\u062d\u0648\u0646\u0647"
    ],
    "wof:name":"Bandar-e Tahuneh",
    "wof:placetype":"locality"
},
  "geometry": {"coordinates":[54.20394,26.70767],"type":"Point"}
}