{
  "type": "Feature",
  "properties": {
    "gn:admin1_code":"42",
    "gn:asciiname":"Farhadgerd",
    "gn:country_code":"IR",
    "gn:dem":1498,
    "gn:feature_class":"P",
    "gn:feature_code":"PPL",
    "gn:name":"Farh\u0101dgerd",
    "gn:population":0,
    "gn:timezone":"Asia/Tehran",
    "iso:country":"IR",
    "name:ara_x_preferred":[
        "\u0641\u0631\u0647\u0627\u062f\u063a\u0631\u062f"
    ],
    "name:aze_x_preferred":[
        "F\u0259rhadg\u0259rd"
    ],
    "name:ceb_x_preferred":[
        "Farh\u0101dgerd"
    ],
    "name:fas_x_preferred":[
        "\u0641\u0631\u0647\u0627\u062f\u06af\u0631\u062f"
    ],
    "name:fas_x_variant":[
        "Farh\u0101dgerd"
    ],
    "name:ita_x_preferred":[
        "Farhad Gerd"
    ],
    "name:mlg_x_preferred":[
        "Farhadgerd"
    ],
    "name:swe_x_preferred":[
        "Farh\u0101dgerd"
    ],
    "name:tur_x_preferred":[
        "Ferhadgerd"
    ],
    "name:und_x_variant":[
        "Far\u0101h Gird",
        "Far\u0101gerd",
        "Far\u0101jerd"
    ],
    "wof:name":"Farhadgerd",
    "wof:placetype":"locality"
},
  "geometry": {"coordinates":[59.73356,35.76579],"type":"Point"}
}