{
  "type": "Feature",
  "properties": {
    "gn:admin1_code":"8",
    "gn:asciiname":"Jahangiryeh",
    "gn:country_code":"IR",
    "gn:dem":1911,
    "gn:feature_class":"P",
    "gn:feature_code":"PPL",
    "gn:name":"Jah\u0101ng\u012bryeh",
    "gn:population":0,
    "gn:timezone":"Asia/Tehran",
    "iso:country":"IR",
    "name:fas_x_preferred":[
        "\u062c\u0647\u0627\u0646\u06af\u06cc\u0631\u06cc\u0647"
    ],
    "name:und_x_variant":[
        "Jah\u0101ng\u012bryeh"
    ],
    "wof:name":"Jahangiryeh",
    "wof:placetype":"locality"
},
  "geometry": {"coordinates":[48.73537,37.55664],"type":"Point"}
}