{
  "type": "Feature",
  "properties": {
    "gn:admin1_code":"34",
    "gn:asciiname":"Panjeh `Ali",
    "gn:country_code":"IR",
    "gn:dem":1868,
    "gn:feature_class":"P",
    "gn:feature_code":"PPL",
    "gn:name":"Panjeh \u2018Al\u012b",
    "gn:population":0,
    "gn:timezone":"Asia/Tehran",
    "iso:country":"IR",
    "name:fas_x_preferred":[
        "\u067e\u0646\u062c\u0647 \u0639\u0644\u06cc"
    ],
    "name:fas_x_variant":[
        "Panjeh \u2018Al\u012b"
    ],
    "wof:name":"Panjeh `Ali",
    "wof:placetype":"locality"
},
  "geometry": {"coordinates":[49.2977,34.0449],"type":"Point"}
}