{
  "type": "Feature",
  "properties": {
    "gn:admin1_code":"13",
    "gn:asciiname":"Qarah Benas",
    "gn:country_code":"IR",
    "gn:dem":1511,
    "gn:feature_class":"P",
    "gn:feature_code":"PPL",
    "gn:name":"Qarah Ben\u0101s",
    "gn:population":0,
    "gn:timezone":"Asia/Tehran",
    "iso:country":"IR",
    "name:ceb_x_preferred":[
        "Qarah Ben\u0101s"
    ],
    "name:fas_x_preferred":[
        "\u0642\u064e\u0631\u0650\u0647 \u0628\u064e\u0646\u0627\u0633"
    ],
    "name:fas_x_variant":[
        "\u0642\u064e\u0631\u0650\u0647 \u0628\u0650\u0646\u0627\u0633",
        "\u06af\u064e\u0631\u0650\u0647 \u0628\u064e\u0646\u0627\u0633",
        "\u0642\u0631\u0647 \u0628\u0646\u0627\u0633",
        "Qareh Ban\u0101s",
        "Qarah Ben\u0101s",
        "\u0642\u0631\u0647\u200c\u0628\u0646\u0627\u0633"
    ],
    "name:swe_x_preferred":[
        "Qarah Ben\u0101s"
    ],
    "name:und_x_variant":[
        "Gareh Ban\u0101s",
        "Qareh Ben\u0101s",
        "Qaraha Bughaz"
    ],
    "wof:name":"Qarah Benas",
    "wof:placetype":"locality"
},
  "geometry": {"coordinates":[47.9533,34.3978],"type":"Point"}
}