{
  "type": "Feature",
  "properties": {
    "gn:admin1_code":"1.0",
    "gn:asciiname":"Qaralar-e Mir Hoseynqoli",
    "gn:country_code":"IR",
    "gn:dem":1306,
    "gn:feature_class":"P",
    "gn:feature_code":"PPL",
    "gn:name":"Qar\u0101lar-e M\u012br \u1e28oseynqol\u012b",
    "gn:population":0,
    "gn:timezone":"Asia/Tehran",
    "iso:country":"IR",
    "name:fas_x_preferred":[
        "\u0642\u0631\u0627\u0644\u0631 \u0645\u06cc\u0631 \u062d\u0633\u06cc\u0646\u0642\u0644\u06cc"
    ],
    "name:fas_x_variant":[
        "Qar\u0101lar-e M\u012br \u1e28oseynqol\u012b"
    ],
    "wof:name":"Qaralar-e Mir Hoseynqoli",
    "wof:placetype":"locality"
},
  "geometry": {"coordinates":[45.0653,37.6823],"type":"Point"}
}