{
  "type": "Feature",
  "properties": {
    "gn:admin1_code":"33",
    "gn:asciiname":"Dabardan-e Sofla",
    "gn:country_code":"IR",
    "gn:dem":1901,
    "gn:feature_class":"P",
    "gn:feature_code":"PPL",
    "gn:name":"Dabard\u0101n-e Sofl\u00e1",
    "gn:population":0,
    "gn:timezone":"Asia/Tehran",
    "iso:country":"IR",
    "name:ara_x_preferred":[
        "\u062f\u0628\u0631\u062f\u0627\u0646 \u0633\u0641\u0644\u064a"
    ],
    "name:ceb_x_preferred":[
        "Dabard\u0101n-e Sofl\u00e1"
    ],
    "name:fas_x_preferred":[
        "\u062f\u0628\u0631\u062f\u0627\u0646 \u0633\u0641\u0644\u06cc"
    ],
    "name:fas_x_variant":[
        "Dabard\u0101n-e Sofl\u00e1"
    ],
    "name:msa_x_preferred":[
        "Dabardan-e Sofla"
    ],
    "name:swe_x_preferred":[
        "Dabard\u0101n-e Sofl\u00e1"
    ],
    "wof:name":"Dabardan-e Sofla",
    "wof:placetype":"locality"
},
  "geometry": {"coordinates":[46.9854,37.1229],"type":"Point"}
}