{
  "type": "Feature",
  "properties": {
    "gn:admin1_code":"11",
    "gn:asciiname":"Faryab-e Gohreh",
    "gn:country_code":"IR",
    "gn:dem":631,
    "gn:elevation":"630.0",
    "gn:feature_class":"P",
    "gn:feature_code":"PPL",
    "gn:name":"F\u0101ry\u0101b-e Gohreh",
    "gn:population":0,
    "gn:timezone":"Asia/Tehran",
    "iso:country":"IR",
    "name:fas_x_preferred":[
        "\u0641\u064e\u0631\u064a\u0627\u0628\u0650 \u06af\u064f\u0647\u0631\u0650\u0647"
    ],
    "name:fas_x_variant":[
        "\u0641\u0627\u0631\u064a\u0627\u0628 \u06af\u0647\u0631\u0647",
        "F\u0101ry\u0101b",
        "\u0641\u0627\u0631\u064a\u0627\u0628",
        "F\u0101ry\u0101b-e Gohreh"
    ],
    "name:und_x_variant":[
        "F\u0101r\u012b\u0101b",
        "Far\u012b\u0101b-e Gohreh"
    ],
    "wof:name":"Faryab-e Gohreh",
    "wof:placetype":"locality"
},
  "geometry": {"coordinates":[56.0696,27.7326],"type":"Point"}
}