{
  "type": "Feature",
  "properties": {
    "gn:admin1_code":"10.0",
    "gn:asciiname":"Dorregah",
    "gn:country_code":"IR",
    "gn:dem":1469,
    "gn:feature_class":"P",
    "gn:feature_code":"PPL",
    "gn:name":"Dorregah",
    "gn:population":0,
    "gn:timezone":"Asia/Tehran",
    "iso:country":"IR",
    "name:fas_x_preferred":[
        "\u062f\u064f\u0631\u0650\u0651\u06af\u064e\u0647"
    ],
    "wof:name":"Dorregah",
    "wof:placetype":"locality"
},
  "geometry": {"coordinates":[46.34545,33.90069],"type":"Point"}
}