{
  "type": "Feature",
  "properties": {
    "gn:admin1_code":"29",
    "gn:asciiname":"Chah-e Khoshkar-e Faryab",
    "gn:country_code":"IR",
    "gn:dem":638,
    "gn:feature_class":"P",
    "gn:feature_code":"PPL",
    "gn:name":"Ch\u0101h-e Khoshk\u0101r-e Fary\u0101b",
    "gn:population":0,
    "gn:timezone":"Asia/Tehran",
    "iso:country":"IR",
    "name:fas_x_preferred":[
        "Ch\u0101h-e Khoshk\u0101r-e Fary\u0101b"
    ],
    "wof:name":"Chah-e Khoshkar-e Faryab",
    "wof:placetype":"locality"
},
  "geometry": {"coordinates":[57.28333000000001,28.08333],"type":"Point"}
}