{
  "type": "Feature",
  "properties": {
    "gn:admin1_code":"8",
    "gn:asciiname":"Parush",
    "gn:country_code":"IR",
    "gn:dem":75,
    "gn:feature_class":"P",
    "gn:feature_code":"PPL",
    "gn:name":"Par\u016bsh",
    "gn:population":0,
    "gn:timezone":"Asia/Tehran",
    "iso:country":"IR",
    "name:ceb_x_preferred":[
        "Par\u016bsh"
    ],
    "name:fas_x_preferred":[
        "Por\u016bsh-e B\u0101l\u0101"
    ],
    "name:fas_x_variant":[
        "Par\u016bsh",
        "\u067e\u0631\u0648\u0634",
        "\u067e\u0631\u0648\u0634 \u0628\u0627\u0644\u0627"
    ],
    "name:msa_x_preferred":[
        "Porush-e Bala"
    ],
    "name:swe_x_preferred":[
        "Par\u016bsh"
    ],
    "name:ukr_x_preferred":[
        "\u041f\u043e\u0440\u0443\u0448-\u0435-\u0411\u0430\u043b\u0430"
    ],
    "name:und_x_variant":[
        "Par\u016bsh",
        "Poroosh",
        "\u067e\u0631\u0648\u0634",
        "Por\u016bsh-e P\u0101\u2019\u012bn",
        "Por\u016bsh",
        "\u067e\u0631\u0648\u0634 \u067e\u0627\u0626\u06cc\u0646"
    ],
    "wof:name":"Parush",
    "wof:placetype":"locality"
},
  "geometry": {"coordinates":[50.11136,37.12617],"type":"Point"}
}