{
  "type": "Feature",
  "properties": {
    "gn:admin1_code":"11",
    "gn:asciiname":"Zarru Kan",
    "gn:country_code":"IR",
    "gn:dem":926,
    "gn:feature_class":"P",
    "gn:feature_code":"PPL",
    "gn:name":"Zarr\u016b K\u0101n",
    "gn:population":0,
    "gn:timezone":"Asia/Tehran",
    "iso:country":"IR",
    "name:ara_x_preferred":[
        "\u0632\u0631\u0648\u06a9\u0627\u0646"
    ],
    "name:ceb_x_preferred":[
        "Zarr\u016b K\u0101n"
    ],
    "name:fas_x_preferred":[
        "\u0632\u0631\u0648 \u06a9\u0627\u0646"
    ],
    "name:fas_x_variant":[
        "Zarr\u016b K\u0101n",
        "\u0632\u0631\u0648\u06a9\u0627\u0646"
    ],
    "name:msa_x_preferred":[
        "Zarru Kan"
    ],
    "name:swe_x_preferred":[
        "Zarr\u016b K\u0101n"
    ],
    "wof:name":"Zarru Kan",
    "wof:placetype":"locality"
},
  "geometry": {"coordinates":[56.5359,27.8276],"type":"Point"}
}