{
  "type": "Feature",
  "properties": {
    "gn:admin1_code":"1",
    "gn:asciiname":"`Isa Khan",
    "gn:country_code":"IR",
    "gn:dem":1634,
    "gn:feature_class":"P",
    "gn:feature_code":"PPL",
    "gn:name":"\u2018\u012as\u00e1 Kh\u0101n",
    "gn:population":0,
    "gn:timezone":"Asia/Tehran",
    "iso:country":"IR",
    "name:fas_x_preferred":[
        "\u0639\u064a\u0633\u0627\u062e\u0627\u0646"
    ],
    "name:fas_x_variant":[
        "\u0639\u06cc\u0633\u06cc \u062e\u0627\u0646",
        "\u2018\u012as\u0101kh\u0101n",
        "\u2018\u012as\u00e1 Kh\u0101n"
    ],
    "wof:name":"`Isa Khan",
    "wof:placetype":"locality"
},
  "geometry": {"coordinates":[44.5919,39.4783],"type":"Point"}
}