{
  "type": "Feature",
  "properties": {
    "gn:admin1_code":"33",
    "gn:asciiname":"Aqeshlu",
    "gn:country_code":"IR",
    "gn:dem":1064,
    "gn:feature_class":"P",
    "gn:feature_code":"PPL",
    "gn:name":"\u0100qeshl\u016b",
    "gn:population":0,
    "gn:timezone":"Asia/Tehran",
    "iso:country":"IR",
    "wof:name":"Aqeshlu",
    "wof:placetype":"locality"
},
  "geometry": {"coordinates":[45.01667,38.61667],"type":"Point"}
}