{
  "type": "Feature",
  "properties": {
    "gn:admin1_code":"29",
    "gn:asciiname":"Hutak",
    "gn:country_code":"IR",
    "gn:dem":1814,
    "gn:feature_class":"P",
    "gn:feature_code":"PPL",
    "gn:name":"H\u016btak",
    "gn:population":0,
    "gn:timezone":"Asia/Tehran",
    "iso:country":"IR",
    "name:fas_x_preferred":[
        "H\u016btak"
    ],
    "name:fas_x_variant":[
        "\u0647\u0648\u062a\u06a9",
        "L\u016btak"
    ],
    "name:und_x_variant":[
        "Hutk",
        "Huth"
    ],
    "wof:name":"Hutak",
    "wof:placetype":"locality"
},
  "geometry": {"coordinates":[56.92988,30.57815],"type":"Point"}
}