{
  "type": "Feature",
  "properties": {
    "gn:admin1_code":"1",
    "gn:asciiname":"Yowla Galdi",
    "gn:country_code":"IR",
    "gn:dem":906,
    "gn:feature_class":"P",
    "gn:feature_code":"PPL",
    "gn:name":"Yowl\u0101 Gald\u012b",
    "gn:population":0,
    "gn:timezone":"Asia/Tehran",
    "iso:country":"IR",
    "name:fas_x_preferred":[
        "\u064a\u064f\u0648\u0644\u0627 \u06af\u064e\u0644\u062f\u06cc"
    ],
    "name:fas_x_variant":[
        "\u064a\u0648\u0644\u0627 \u06af\u0644\u062f\u06cc",
        "Yowl\u0101 Gald\u012b"
    ],
    "wof:name":"Yowla Galdi",
    "wof:placetype":"locality"
},
  "geometry": {"coordinates":[44.81800000000001,39.2848],"type":"Point"}
}