{
  "type": "Feature",
  "properties": {
    "gn:admin1_code":"11",
    "gn:asciiname":"Chah Gharbal",
    "gn:country_code":"IR",
    "gn:dem":242,
    "gn:feature_class":"P",
    "gn:feature_code":"PPL",
    "gn:name":"Ch\u0101h Gharb\u0101l",
    "gn:population":0,
    "gn:timezone":"Asia/Tehran",
    "iso:country":"IR",
    "name:fas_x_preferred":[
        "\u0686\u0627\u0647 \u063a\u0631\u0628\u0627\u0644"
    ],
    "name:fas_x_variant":[
        "Ch\u0101h Gharb\u0101l"
    ],
    "wof:name":"Chah Gharbal",
    "wof:placetype":"locality"
},
  "geometry": {"coordinates":[57.34713000000001,27.10947],"type":"Point"}
}