{
  "type": "Feature",
  "properties": {
    "gn:admin1_code":"15.0",
    "gn:asciiname":"Macheh Shavar",
    "gn:country_code":"IR",
    "gn:dem":2,
    "gn:feature_class":"P",
    "gn:feature_code":"PPL",
    "gn:name":"M\u0101cheh Shav\u0101r",
    "gn:population":0,
    "gn:timezone":"Asia/Tehran",
    "iso:country":"IR",
    "name:fas_x_preferred":[
        "M\u0101cheh Shav\u0101r"
    ],
    "wof:name":"Macheh Shavar",
    "wof:placetype":"locality"
},
  "geometry": {"coordinates":[48.45667,30.24472],"type":"Point"}
}