{
  "type": "Feature",
  "properties": {
    "gn:admin1_code":"23",
    "gn:asciiname":"Qal`eh Asa",
    "gn:country_code":"IR",
    "gn:dem":1704,
    "gn:feature_class":"P",
    "gn:feature_code":"PPL",
    "gn:name":"Qal\u2018eh \u0100s\u0101",
    "gn:population":0,
    "gn:timezone":"Asia/Tehran",
    "iso:country":"IR",
    "name:fas_x_preferred":[
        "\u0642\u0644\u0639\u0647 \u0622\u0633\u0627"
    ],
    "name:fas_x_variant":[
        "Qal\u2018eh \u0100s\u0101"
    ],
    "wof:name":"Qal`eh Asa",
    "wof:placetype":"locality"
},
  "geometry": {"coordinates":[48.67603,33.59639],"type":"Point"}
}