{
  "type": "Feature",
  "properties": {
    "gn:admin1_code":"42.0",
    "gn:asciiname":"Chahar Deh",
    "gn:country_code":"IR",
    "gn:dem":1035,
    "gn:feature_class":"P",
    "gn:feature_code":"PPL",
    "gn:name":"Chah\u0101r Deh",
    "gn:population":0,
    "gn:timezone":"Asia/Tehran",
    "iso:country":"IR",
    "name:fas_x_preferred":[
        "\u0686\u0647\u0627\u0631 \u062f\u0647"
    ],
    "name:fas_x_variant":[
        "Chah\u0101r Deh"
    ],
    "wof:name":"Chahar Deh",
    "wof:placetype":"locality"
},
  "geometry": {"coordinates":[60.03413000000001,34.69415],"type":"Point"}
}