{
  "type": "Feature",
  "properties": {
    "gn:admin1_code":"15",
    "gn:asciiname":"Shahab",
    "gn:country_code":"IR",
    "gn:dem":9,
    "gn:feature_class":"P",
    "gn:feature_code":"PPL",
    "gn:name":"Shah\u0101b",
    "gn:population":0,
    "gn:timezone":"Asia/Tehran",
    "iso:country":"IR",
    "name:ara_x_preferred":[
        "\u0646\u0647\u0631 \u0634\u0647\u0627\u0628"
    ],
    "name:fas_x_preferred":[
        "Nahr-e Shah\u0101b"
    ],
    "name:fas_x_variant":[
        "Shah\u0101b",
        "\u0646\u0647\u0631 \u0634\u0647\u0627\u0628",
        "\u0634\u0647\u0627\u0628",
        "\u0646\u0647\u0631\u0634\u0647\u0627\u0628"
    ],
    "name:und_x_variant":[
        "\u0646\u0647\u0631 \u0634\u0647\u0627\u0628"
    ],
    "wof:name":"Shahab",
    "wof:placetype":"locality"
},
  "geometry": {"coordinates":[48.74375,30.68584],"type":"Point"}
}