{
  "type": "Feature",
  "properties": {
    "gn:admin1_code":"0",
    "gn:asciiname":"Dan Sar",
    "gn:country_code":"IR",
    "gn:dem":193,
    "gn:feature_class":"P",
    "gn:feature_code":"PPL",
    "gn:name":"Dan Sar",
    "gn:population":0,
    "gn:timezone":"Asia/Tehran",
    "iso:country":"IR",
    "name:fas_x_preferred":[
        "\u062f\u0646 \u0633\u0631"
    ],
    "wof:name":"Dan Sar",
    "wof:placetype":"locality"
},
  "geometry": {"coordinates":[61.7525,25.9353],"type":"Point"}
}