{
  "type": "Feature",
  "properties": {
    "gn:admin1_code":"15.0",
    "gn:asciiname":"Beyt-e Shaye`",
    "gn:country_code":"IR",
    "gn:dem":72,
    "gn:feature_class":"P",
    "gn:feature_code":"PPL",
    "gn:name":"Beyt-e Sh\u0101ye\u2018",
    "gn:population":0,
    "gn:timezone":"Asia/Tehran",
    "iso:country":"IR",
    "name:fas_x_preferred":[
        "\u0634\u0647\u0631\u06a9 \u0641\u062e\u0631\u0627\u0644\u062f\u06cc\u0646 \u062d\u062c\u0627\u0632\u06cc"
    ],
    "name:fas_x_variant":[
        "\u0628\u06cc\u062a \u0634\u0627\u06cc\u0639",
        "Sharak-e Fakhr od D\u012bn \u1e28ej\u0101z\u012b"
    ],
    "name:und_x_variant":[
        "Beyt-e Sh\u0101ye\u2018"
    ],
    "wof:name":"Beyt-e Shaye`",
    "wof:placetype":"locality"
},
  "geometry": {"coordinates":[48.14981,31.9599],"type":"Point"}
}