{
  "type": "Feature",
  "properties": {
    "gn:admin1_code":"11",
    "gn:asciiname":"Buchir",
    "gn:country_code":"IR",
    "gn:dem":222,
    "gn:feature_class":"P",
    "gn:feature_code":"PPL",
    "gn:name":"B\u016bch\u012br",
    "gn:population":0,
    "gn:timezone":"Asia/Tehran",
    "iso:country":"IR",
    "name:fas_x_preferred":[
        "\u0628\u0648\u0686\u064a\u0631"
    ],
    "name:fas_x_variant":[
        "B\u016bch\u012br"
    ],
    "name:msa_x_preferred":[
        "Buchir"
    ],
    "name:und_x_variant":[
        "Boochir",
        "B\u016bsh\u012br"
    ],
    "wof:name":"Buchir",
    "wof:placetype":"locality"
},
  "geometry": {"coordinates":[53.6173,27.0633],"type":"Point"}
}