{
  "type": "Feature",
  "properties": {
    "gn:admin1_code":"26",
    "gn:asciiname":"Nasirabad",
    "gn:country_code":"IR",
    "gn:dem":1041,
    "gn:feature_class":"P",
    "gn:feature_code":"PPL",
    "gn:name":"Na\u015f\u012br\u0101b\u0101d",
    "gn:population":0,
    "gn:timezone":"Asia/Tehran",
    "iso:country":"IR",
    "name:fas_x_preferred":[
        "\u0646\u0635\u06cc\u0631 \u0622\u0628\u0627\u062f"
    ],
    "name:fas_x_variant":[
        "Na\u015f\u012br\u0101b\u0101d",
        "\u0646\u0635\u06cc\u0631 \u0622\u0628\u0627\u062f \u0642\u0627\u062c\u0627\u0631"
    ],
    "name:und_x_variant":[
        "Na\u015f\u012br\u0101b\u0101d-e Q\u0101j\u0101r"
    ],
    "wof:name":"Nasirabad",
    "wof:placetype":"locality"
},
  "geometry": {"coordinates":[51.13836,35.49209000000001],"type":"Point"}
}