{
  "type": "Feature",
  "properties": {
    "gn:admin1_code":"42.0",
    "gn:asciiname":"Koruzhadeh",
    "gn:country_code":"IR",
    "gn:dem":1074,
    "gn:feature_class":"P",
    "gn:feature_code":"PPL",
    "gn:name":"Kor\u016bzhadeh",
    "gn:population":0,
    "gn:timezone":"Asia/Tehran",
    "iso:country":"IR",
    "name:fas_x_preferred":[
        "Kor\u016bzhadeh"
    ],
    "name:fas_x_variant":[
        "\u06a9\u0631\u0648\u0698\u062f\u0647"
    ],
    "name:und_x_variant":[
        "\u06a9\u0631\u0648\u0698\u062f\u0647"
    ],
    "wof:name":"Koruzhadeh",
    "wof:placetype":"locality"
},
  "geometry": {"coordinates":[57.44973,36.69748],"type":"Point"}
}