{
  "type": "Feature",
  "properties": {
    "gn:admin1_code":"4",
    "gn:asciiname":"Marz-e Molk",
    "gn:country_code":"IR",
    "gn:dem":1618,
    "gn:feature_class":"P",
    "gn:feature_code":"PPL",
    "gn:name":"Marz-e Molk",
    "gn:population":0,
    "gn:timezone":"Asia/Tehran",
    "iso:country":"IR",
    "name:fas_x_preferred":[
        "\u0645\u0631\u0632 \u0645\u0644\u06a9"
    ],
    "wof:name":"Marz-e Molk",
    "wof:placetype":"locality"
},
  "geometry": {"coordinates":[60.3064,29.3595],"type":"Point"}
}