{
  "type": "Feature",
  "properties": {
    "gn:admin1_code":"1.0",
    "gn:asciiname":"Badaki",
    "gn:country_code":"IR",
    "gn:dem":1112,
    "gn:feature_class":"P",
    "gn:feature_code":"PPL",
    "gn:name":"B\u0101dak\u012b",
    "gn:population":0,
    "gn:timezone":"Asia/Tehran",
    "iso:country":"IR",
    "name:fas_x_preferred":[
        "\u0628\u0627\u062f\u06a9\u06cc"
    ],
    "name:fas_x_variant":[
        "B\u0101dak\u012b"
    ],
    "wof:name":"Badaki",
    "wof:placetype":"locality"
},
  "geometry": {"coordinates":[44.9931,38.8815],"type":"Point"}
}