{
  "type": "Feature",
  "properties": {
    "gn:admin1_code":"26",
    "gn:asciiname":"Kahrizak",
    "gn:country_code":"IR",
    "gn:dem":1004,
    "gn:feature_class":"P",
    "gn:feature_code":"PPL",
    "gn:name":"Kahr\u012bzak",
    "gn:population":0,
    "gn:timezone":"Asia/Tehran",
    "iso:country":"IR",
    "name:fas_x_preferred":[
        "\u0643\u0647\u0631\u064a\u0632\u0643"
    ],
    "name:fas_x_variant":[
        "\u0643\u064e\u0647\u0631\u064a\u0632\u064e\u0643\u0650 \u063a\u0627\u0631",
        "Kahr\u012bzak"
    ],
    "name:und_x_variant":[
        "Kahr\u012bzak-e Gh\u0101r"
    ],
    "wof:name":"Kahrizak",
    "wof:placetype":"locality"
},
  "geometry": {"coordinates":[51.36484,35.51595],"type":"Point"}
}