{
  "type": "Feature",
  "properties": {
    "gn:admin1_code":"5.0",
    "gn:asciiname":"Murtut",
    "gn:country_code":"IR",
    "gn:dem":1703,
    "gn:feature_class":"P",
    "gn:feature_code":"PPL",
    "gn:name":"M\u016brt\u016bt",
    "gn:population":0,
    "gn:timezone":"Asia/Tehran",
    "iso:country":"IR",
    "name:fas_x_preferred":[
        "M\u016brt\u016bt"
    ],
    "name:fas_x_variant":[
        "\u0645\u0648\u0631\u062a\u0648\u062a"
    ],
    "wof:name":"Murtut",
    "wof:placetype":"locality"
},
  "geometry": {"coordinates":[50.88571,30.93522],"type":"Point"}
}