{
  "type": "Feature",
  "properties": {
    "gn:admin1_code":"13",
    "gn:asciiname":"Karian",
    "gn:country_code":"IR",
    "gn:dem":1265,
    "gn:feature_class":"P",
    "gn:feature_code":"PPL",
    "gn:name":"Kar\u012b\u0101n",
    "gn:population":0,
    "gn:timezone":"Asia/Tehran",
    "iso:country":"IR",
    "name:ceb_x_preferred":[
        "Kar\u012b\u0101n"
    ],
    "name:fas_x_preferred":[
        "\u06a9\u0631\u06cc\u0627\u0646"
    ],
    "name:fas_x_variant":[
        "Kar\u012b\u0101n",
        "\u0633\u0631\u0622\u0628\u06a9\u0631\u06cc\u0627\u0646"
    ],
    "name:swe_x_preferred":[
        "Kar\u012b\u0101n"
    ],
    "name:und_x_variant":[
        "Karay\u0101n",
        "Karey\u0101n",
        "Sar\u0101b-e Kar\u012b\u0101n"
    ],
    "wof:name":"Karian",
    "wof:placetype":"locality"
},
  "geometry": {"coordinates":[47.0282,33.8866],"type":"Point"}
}