{
  "type": "Feature",
  "properties": {
    "gn:admin1_code":"33",
    "gn:asciiname":"Raj",
    "gn:country_code":"IR",
    "gn:dem":2342,
    "gn:feature_class":"P",
    "gn:feature_code":"PPL",
    "gn:name":"Raj",
    "gn:population":0,
    "gn:timezone":"Asia/Tehran",
    "iso:country":"IR",
    "name:fas_x_preferred":[
        "\u0631\u062c"
    ],
    "wof:name":"Raj",
    "wof:placetype":"locality"
},
  "geometry": {"coordinates":[47.8223,37.8376],"type":"Point"}
}