{
  "type": "Feature",
  "properties": {
    "gn:admin1_code":"1.0",
    "gn:asciiname":"Margaseh-ye Pa'in",
    "gn:country_code":"IR",
    "gn:dem":1465,
    "gn:feature_class":"P",
    "gn:feature_code":"PPL",
    "gn:name":"Marg\u0101seh-ye P\u0101\u2019\u012bn",
    "gn:population":0,
    "gn:timezone":"Asia/Tehran",
    "iso:country":"IR",
    "name:fas_x_preferred":[
        "\u0645\u0631\u06af\u0627\u0633\u0647 \u067e\u0627\u0626\u06cc\u0646"
    ],
    "name:und_x_variant":[
        "Marg\u0101seh-ye P\u0101\u2019\u012bn"
    ],
    "wof:name":"Margaseh-ye Pa'in",
    "wof:placetype":"locality"
},
  "geometry": {"coordinates":[45.4071,36.0497],"type":"Point"}
}