{
  "type": "Feature",
  "properties": {
    "gn:country":"IR",
    "gn:fcode":"PPL",
    "gn:population":49993,
    "iso:country":"IR",
    "name:ara_x_preferred":[
        "\u0637\u0628\u0633"
    ],
    "name:aze_x_preferred":[
        "T\u0259b\u0259s"
    ],
    "name:cat_x_preferred":[
        "Tabas Gilaki"
    ],
    "name:deu_x_preferred":[
        "Tabas"
    ],
    "name:eng_x_preferred":[
        "Tabas"
    ],
    "name:eng_x_variant":[
        "Golshan",
        "Gulshan",
        "\u0162abas"
    ],
    "name:epo_x_preferred":[
        "Tabas"
    ],
    "name:fas_x_preferred":[
        "\u0162abas"
    ],
    "name:fas_x_variant":[
        "\u0637\u0628\u0633"
    ],
    "name:fra_x_preferred":[
        "Tabas"
    ],
    "name:hun_x_preferred":[
        "Tabasz"
    ],
    "name:ita_x_preferred":[
        "Tabas"
    ],
    "name:mal_x_preferred":[
        "\u0d24\u0d2c\u0d38\u0d4d"
    ],
    "name:mlg_x_preferred":[
        "Tabas"
    ],
    "name:nld_x_preferred":[
        "Tabas"
    ],
    "name:pnb_x_preferred":[
        "\u0634\u06c1\u0631\u0633\u062a\u0627\u0646 \u0637\u0628\u0633"
    ],
    "name:pnb_x_variant":[
        "\u0637\u0628\u0633"
    ],
    "name:pol_x_preferred":[
        "Tabas"
    ],
    "name:ron_x_preferred":[
        "Tabas"
    ],
    "name:rus_x_preferred":[
        "\u0422\u0430\u0431\u0430\u0441"
    ],
    "name:rus_x_variant":[
        "\u0422\u0435\u0431\u0435\u0441"
    ],
    "name:tur_x_preferred":[
        "Tebes"
    ],
    "name:tur_x_variant":[
        "Tabas"
    ],
    "name:urd_x_preferred":[
        "\u0637\u0628\u0633"
    ],
    "name:zho_x_preferred":[
        "\u5854\u5df4\u65af"
    ],
    "qs_pg:aaroncc":"IR",
    "qs_pg:gn_country":"IR",
    "qs_pg:gn_fcode":"PPL",
    "qs_pg:gn_pop":49993,
    "qs_pg:name":"\u0162abas",
    "qs_pg:photos_9r":0,
    "qs_pg:photos_sr":0,
    "qs_pg:pop_sr":7,
    "qs_pg:qs_pg_placetype":"locality",
    "wof:name":"\u0162abas",
    "wof:placetype":"locality",
    "wof:population":49993
},
  "geometry": {"coordinates":[56.92437,33.59586],"type":"Point"}
}