{
  "type": "Feature",
  "properties": {
    "gn:admin1_code":"38",
    "gn:asciiname":"Qeshlaq-e Zaj Kan-e Pa'in",
    "gn:country_code":"IR",
    "gn:dem":1730,
    "gn:feature_class":"P",
    "gn:feature_code":"PPL",
    "gn:name":"Qeshl\u0101q-e Z\u0101j K\u0101n-e P\u0101\u2019\u012bn",
    "gn:population":0,
    "gn:timezone":"Asia/Tehran",
    "iso:country":"IR",
    "name:fas_x_preferred":[
        "Qeshl\u0101q-e Z\u0101chk\u0101n-e Sofl\u00e1"
    ],
    "name:fas_x_variant":[
        "\u0642\u0634\u0644\u0627\u0642 \u0632\u0627\u062c \u0643\u0627\u0646 \u067e\u0627\u0626\u064a\u0646"
    ],
    "name:und_x_variant":[
        "Qeshl\u0101q-e Z\u0101j K\u0101n-e P\u0101\u2019\u012bn",
        "Z\u0101jk\u0101n-e P\u0101\u2019\u012bn Qeshl\u0101q"
    ],
    "wof:name":"Qeshlaq-e Zaj Kan-e Pa'in",
    "wof:placetype":"locality"
},
  "geometry": {"coordinates":[49.4573,36.3339],"type":"Point"}
}