{
  "type": "Feature",
  "properties": {
    "gn:admin1_code":"7",
    "gn:asciiname":"`Aliabad-e Abkeshi",
    "gn:country_code":"IR",
    "gn:dem":496,
    "gn:feature_class":"P",
    "gn:feature_code":"PPL",
    "gn:name":"\u2018\u0100l\u012b\u0101b\u0101d-e \u0100bkesh\u012b",
    "gn:population":0,
    "gn:timezone":"Asia/Tehran",
    "iso:country":"IR",
    "name:fas_x_preferred":[
        "\u0639\u0644\u06cc \u0622\u0628\u0627\u062f"
    ],
    "name:fas_x_variant":[
        "\u2018Al\u012b\u0101b\u0101d",
        "\u0639\u0627\u0644\u06cc \u0622\u0628\u0627\u062f \u0622\u0628\u06a9\u0634\u06cc",
        "\u0639\u0644\u06cc \u0622\u0628\u0627\u062f \u0627\u0648\u06a9\u0634\u06cc"
    ],
    "name:und_x_variant":[
        "\u2018\u0100l\u012b\u0101b\u0101d-e \u0100bkesh\u012b",
        "\u2018Al\u012b\u0101b\u0101d-e Owkesh\u012b"
    ],
    "wof:name":"`Aliabad-e Abkeshi",
    "wof:placetype":"locality"
},
  "geometry": {"coordinates":[53.41441999999999,27.56853],"type":"Point"}
}