{
  "type": "Feature",
  "properties": {
    "gn:admin1_code":"28.0",
    "gn:asciiname":"Ja`farabad",
    "gn:country_code":"IR",
    "gn:dem":1610,
    "gn:feature_class":"P",
    "gn:feature_code":"PPL",
    "gn:name":"Ja`far\u0101b\u0101d",
    "gn:population":0,
    "gn:timezone":"Asia/Tehran",
    "iso:country":"IR",
    "wof:name":"Ja`farabad",
    "wof:placetype":"locality"
},
  "geometry": {"coordinates":[51.52583,32.55083],"type":"Point"}
}