{
  "type": "Feature",
  "properties": {
    "gn:admin1_code":"26.0",
    "gn:asciiname":"Alu'ak",
    "gn:country_code":"IR",
    "gn:dem":1070,
    "gn:feature_class":"P",
    "gn:feature_code":"PPL",
    "gn:name":"\u0100l\u016b\u2019ak",
    "gn:population":0,
    "gn:timezone":"Asia/Tehran",
    "iso:country":"IR",
    "name:fas_x_preferred":[
        "\u0100l\u016btak"
    ],
    "name:fas_x_variant":[
        "\u0100l\u016b\u2019ak",
        "\u0622\u0644\u0648\u0626\u06a9",
        "\u0627\u0644\u0648\u06cc\u06a9"
    ],
    "name:und_x_variant":[
        "Al\u016byak"
    ],
    "wof:name":"Alu'ak",
    "wof:placetype":"locality"
},
  "geometry": {"coordinates":[51.7296,35.4548],"type":"Point"}
}