{
  "type": "Feature",
  "properties": {
    "gn:admin1_code":"16",
    "gn:asciiname":"Seyf",
    "gn:country_code":"IR",
    "gn:dem":1822,
    "gn:feature_class":"P",
    "gn:feature_code":"PPL",
    "gn:name":"Seyf",
    "gn:population":0,
    "gn:timezone":"Asia/Tehran",
    "iso:country":"IR",
    "name:ceb_x_preferred":[
        "Seyf"
    ],
    "name:fas_x_preferred":[
        "\u0633\u0650\u064a\u0641"
    ],
    "name:fas_x_variant":[
        "\u0633\u064e\u0641",
        "\u062f\u0650\u06af\u0627\u06af\u0627\u0647",
        "\u0633\u06cc\u0641"
    ],
    "name:swe_x_preferred":[
        "Seyf"
    ],
    "name:und_x_variant":[
        "Saf",
        "Seyf"
    ],
    "wof:name":"Seyf",
    "wof:placetype":"locality"
},
  "geometry": {"coordinates":[46.3226,35.8382],"type":"Point"}
}