{
  "type": "Feature",
  "properties": {
    "gn:admin1_code":"29",
    "gn:asciiname":"Sar Godar",
    "gn:country_code":"IR",
    "gn:dem":1729,
    "gn:feature_class":"P",
    "gn:feature_code":"PPL",
    "gn:name":"Sar God\u0101r",
    "gn:population":0,
    "gn:timezone":"Asia/Tehran",
    "iso:country":"IR",
    "name:fas_x_preferred":[
        "\u0633\u0631 \u06af\u062f\u0627\u0631"
    ],
    "name:fas_x_variant":[
        "Sar God\u0101r"
    ],
    "wof:name":"Sar Godar",
    "wof:placetype":"locality"
},
  "geometry": {"coordinates":[57.6831,28.9521],"type":"Point"}
}