{
  "type": "Feature",
  "properties": {
    "gn:admin1_code":"35.0",
    "gn:asciiname":"Bilsekareh",
    "gn:country_code":"IR",
    "gn:dem":343,
    "gn:feature_class":"P",
    "gn:feature_code":"PPL",
    "gn:name":"B\u012blsekareh",
    "gn:population":0,
    "gn:timezone":"Asia/Tehran",
    "iso:country":"IR",
    "name:fas_x_preferred":[
        "B\u012blseg\u0101r"
    ],
    "name:fas_x_variant":[
        "\u0628\u06cc\u0644\u0633\u06af\u0627\u0631",
        "\u0628\u06cc\u0644\u0633\u06a9\u0631\u0647",
        "\u0628\u064a\u0644\u06a9 \u0633\u0631"
    ],
    "name:und_x_variant":[
        "B\u012blsekareh",
        "B\u012blak Sar"
    ],
    "wof:name":"Bilsekareh",
    "wof:placetype":"locality"
},
  "geometry": {"coordinates":[50.68613,36.80647],"type":"Point"}
}