{
  "type": "Feature",
  "properties": {
    "gn:admin1_code":"8.0",
    "gn:asciiname":"Taleh Lavati",
    "gn:country_code":"IR",
    "gn:dem":1705,
    "gn:feature_class":"P",
    "gn:feature_code":"PPL",
    "gn:name":"Taleh Lav\u0101t\u012b",
    "gn:population":0,
    "gn:timezone":"Asia/Tehran",
    "iso:country":"IR",
    "name:fas_x_preferred":[
        "L\u016b\u0101\u2019\u012b"
    ],
    "name:fas_x_variant":[
        "Lav\u0101l\u012b",
        "\u0644\u0648\u0627\u0644\u06cc",
        "\u062a\u0644\u0647 \u0644\u0648\u0627\u062a\u06cc"
    ],
    "name:msa_x_preferred":[
        "Lavali"
    ],
    "name:ukr_x_preferred":[
        "\u041b\u0430\u0432\u0430\u043b\u0456"
    ],
    "name:und_x_variant":[
        "Taleh Lav\u0101t\u012b"
    ],
    "wof:name":"Taleh Lavati",
    "wof:placetype":"locality"
},
  "geometry": {"coordinates":[50.07746,36.79682],"type":"Point"}
}