{
  "type": "Feature",
  "properties": {
    "gn:admin1_code":"26.0",
    "gn:asciiname":"Tappeh Hezar Cham",
    "gn:country_code":"IR",
    "gn:dem":1264,
    "gn:feature_class":"P",
    "gn:feature_code":"PPL",
    "gn:name":"Tappeh Hez\u0101r Cham",
    "gn:population":0,
    "gn:timezone":"Asia/Tehran",
    "iso:country":"IR",
    "name:fas_x_preferred":[
        "\u062a\u067e\u0647 \u0647\u0632\u0627\u0631 \u0686\u0645"
    ],
    "name:und_x_variant":[
        "Tappeh Hez\u0101r Cham"
    ],
    "wof:name":"Tappeh Hezar Cham",
    "wof:placetype":"locality"
},
  "geometry": {"coordinates":[51.51791,35.62864000000001],"type":"Point"}
}