{
  "type": "Feature",
  "properties": {
    "gn:admin1_code":"28",
    "gn:asciiname":"Sar Bisheh",
    "gn:country_code":"IR",
    "gn:dem":2261,
    "gn:feature_class":"P",
    "gn:feature_code":"PPL",
    "gn:name":"Sar B\u012bsheh",
    "gn:population":0,
    "gn:timezone":"Asia/Tehran",
    "iso:country":"IR",
    "name:ara_x_preferred":[
        "\u0633\u0631\u0628\u064a\u0634\u0647"
    ],
    "name:fas_x_preferred":[
        "\u0633\u0631 \u0628\u06cc\u0634\u0647 \u06a9\u0644\u0647\u0631\u0648\u062f"
    ],
    "name:fas_x_variant":[
        "Sar B\u012bsheh Kalahr\u016bd",
        "\u0633\u0631 \u0628\u06cc\u0634\u0647",
        "\u0633\u0631\u0628\u06cc\u0634\u0647"
    ],
    "name:und_x_variant":[
        "Sar B\u012bsheh"
    ],
    "wof:name":"Sar Bisheh",
    "wof:placetype":"locality"
},
  "geometry": {"coordinates":[51.5648,33.3624],"type":"Point"}
}