{
  "type": "Feature",
  "properties": {
    "gn:admin1_code":"13",
    "gn:asciiname":"La`labad-e Seyyed Ja`far",
    "gn:country_code":"IR",
    "gn:dem":1516,
    "gn:feature_class":"P",
    "gn:feature_code":"PPL",
    "gn:name":"La\u2018l\u0101b\u0101d-e Seyyed Ja\u2018far",
    "gn:population":0,
    "gn:timezone":"Asia/Tehran",
    "iso:country":"IR",
    "name:fas_x_preferred":[
        "La\u2018l\u0101b\u0101d-e Seyyed Ja\u2018far"
    ],
    "wof:name":"La`labad-e Seyyed Ja`far",
    "wof:placetype":"locality"
},
  "geometry": {"coordinates":[46.68611,34.23333],"type":"Point"}
}