{
  "type": "Feature",
  "properties": {
    "gn:admin1_code":"33",
    "gn:asciiname":"Owrta Qarah Darreh",
    "gn:country_code":"IR",
    "gn:dem":458,
    "gn:feature_class":"P",
    "gn:feature_code":"PPL",
    "gn:name":"Owrt\u0101 Qarah Darreh",
    "gn:population":0,
    "gn:timezone":"Asia/Tehran",
    "iso:country":"IR",
    "name:fas_x_preferred":[
        "\u0642\u064e\u0631\u064e\u0647 \u062f\u064e\u0631\u064e\u0642\u0650 \u0648\u064f\u0633\u0637\u064e\u0649"
    ],
    "name:fas_x_variant":[
        "\u0627\u0648\u0631\u062a\u0627 \u0642\u0631\u0647 \u062f\u0631\u0647",
        "Qarah Daraq-e Vos\u0163\u00e1",
        "Owrt\u0101 Qarah Darreh"
    ],
    "wof:name":"Owrta Qarah Darreh",
    "wof:placetype":"locality"
},
  "geometry": {"coordinates":[47.4473,39.1699],"type":"Point"}
}