{
  "type": "Feature",
  "properties": {
    "gn:admin1_code":"3",
    "gn:asciiname":"Varkab",
    "gn:country_code":"IR",
    "gn:dem":1416,
    "gn:feature_class":"P",
    "gn:feature_code":"PPL",
    "gn:name":"Vark\u0101b",
    "gn:population":0,
    "gn:timezone":"Asia/Tehran",
    "iso:country":"IR",
    "name:fas_x_preferred":[
        "\u0648\u064e\u0631\u0643\u064f\u0648"
    ],
    "name:fas_x_variant":[
        "Vark\u0101b",
        "\u0648\u0631\u06a9\u0627\u0628"
    ],
    "name:msa_x_preferred":[
        "Varkab"
    ],
    "name:und_x_variant":[
        "Varkow",
        "\u0648\u0631\u06a9\u0627\u0628"
    ],
    "wof:name":"Varkab",
    "wof:placetype":"locality"
},
  "geometry": {"coordinates":[51.02927,31.21068],"type":"Point"}
}