{
  "type": "Feature",
  "properties": {
    "gn:admin1_code":"43",
    "gn:asciiname":"Guy Nik",
    "gn:country_code":"IR",
    "gn:dem":1234,
    "gn:feature_class":"P",
    "gn:feature_code":"PPL",
    "gn:name":"G\u016by N\u012bk",
    "gn:population":0,
    "gn:timezone":"Asia/Tehran",
    "iso:country":"IR",
    "name:fas_x_preferred":[
        "G\u016bynak"
    ],
    "name:fas_x_variant":[
        "G\u016by N\u012bk",
        "\u06af\u0648\u06cc\u0646\u06a9",
        "\u06af\u0648\u06cc\u0646\u06cc\u06a9"
    ],
    "name:und_x_variant":[
        "\u06af\u0648\u06cc\u0646\u06a9"
    ],
    "wof:name":"Guy Nik",
    "wof:placetype":"locality"
},
  "geometry": {"coordinates":[57.01508000000001,37.99886],"type":"Point"}
}