{
  "type": "Feature",
  "properties": {
    "gn:admin1_code":"7",
    "gn:asciiname":"Bid-e A`lam",
    "gn:country_code":"IR",
    "gn:dem":2175,
    "gn:feature_class":"P",
    "gn:feature_code":"PPL",
    "gn:name":"B\u012bd-e A\u2018lam",
    "gn:population":0,
    "gn:timezone":"Asia/Tehran",
    "iso:country":"IR",
    "name:fas_x_preferred":[
        "B\u012bd-e A\u2018lam"
    ],
    "wof:name":"Bid-e A`lam",
    "wof:placetype":"locality"
},
  "geometry": {"coordinates":[52.47556,31.28556],"type":"Point"}
}