{
  "type": "Feature",
  "properties": {
    "gn:admin1_code":"5",
    "gn:asciiname":"Eshgaft",
    "gn:country_code":"IR",
    "gn:dem":1665,
    "gn:feature_class":"P",
    "gn:feature_code":"PPL",
    "gn:name":"Eshgaft",
    "gn:population":0,
    "gn:timezone":"Asia/Tehran",
    "iso:country":"IR",
    "name:fas_x_preferred":[
        "\u0627\u0650\u0634\u0643\u064e\u0641\u062a"
    ],
    "name:fas_x_variant":[
        "\u0627\u0634\u06af\u0641\u062a"
    ],
    "name:und_x_variant":[
        "Eshkaft"
    ],
    "wof:name":"Eshgaft",
    "wof:placetype":"locality"
},
  "geometry": {"coordinates":[50.84015,30.84849],"type":"Point"}
}