{
  "type": "Feature",
  "properties": {
    "gn:admin1_code":"4.0",
    "gn:asciiname":"Kajgurin",
    "gn:country_code":"IR",
    "gn:dem":793,
    "gn:feature_class":"P",
    "gn:feature_code":"PPL",
    "gn:name":"Kajg\u016br\u012bn",
    "gn:population":0,
    "gn:timezone":"Asia/Tehran",
    "iso:country":"IR",
    "name:fas_x_preferred":[
        "\u06a9\u062c\u06af\u0648\u0631\u064a\u0646"
    ],
    "name:fas_x_variant":[
        "Qal\u2018eh-ye Tar\u0101n",
        "Kajg\u016br\u012bn"
    ],
    "wof:name":"Kajgurin",
    "wof:placetype":"locality"
},
  "geometry": {"coordinates":[60.81674,27.44738],"type":"Point"}
}