{
  "type": "Feature",
  "properties": {
    "gn:admin1_code":"33",
    "gn:asciiname":"Lallehlu",
    "gn:country_code":"IR",
    "gn:dem":1742,
    "gn:feature_class":"P",
    "gn:feature_code":"PPL",
    "gn:name":"Lallehl\u016b",
    "gn:population":0,
    "gn:timezone":"Asia/Tehran",
    "iso:country":"IR",
    "name:fas_x_preferred":[
        "\u0644\u0644\u0647 \u0644\u0648"
    ],
    "name:fas_x_variant":[
        "Lalahl\u016b",
        "Lallahl\u016b"
    ],
    "name:und_x_variant":[
        "Lalakhlu",
        "Lalehl\u016b",
        "Lallehl\u016b"
    ],
    "wof:name":"Lallehlu",
    "wof:placetype":"locality"
},
  "geometry": {"coordinates":[48.01336,37.31348],"type":"Point"}
}