{
  "type": "Feature",
  "properties": {
    "gn:admin1_code":"4.0",
    "gn:asciiname":"Esma`il Kalak",
    "gn:country_code":"IR",
    "gn:dem":924,
    "gn:feature_class":"P",
    "gn:feature_code":"PPL",
    "gn:name":"Esm\u0101\u2018\u012bl Kalak",
    "gn:population":0,
    "gn:timezone":"Asia/Tehran",
    "iso:country":"IR",
    "name:fas_x_preferred":[
        "Esm\u0101\u2018\u012bl Kalak"
    ],
    "name:fas_x_variant":[
        "Esm\u0101\u2018\u012bl Kallag",
        "\u0627\u0633\u0645\u0627\u0639\u06cc\u0644 \u06a9\u0644\u06a9"
    ],
    "name:und_x_variant":[
        "\u0627\u0633\u0645\u0627\u0639\u06cc\u0644 \u06a9\u0644\u06a9"
    ],
    "wof:name":"Esma`il Kalak",
    "wof:placetype":"locality"
},
  "geometry": {"coordinates":[61.07643,26.49476],"type":"Point"}
}