{
  "type": "Feature",
  "properties": {
    "gn:admin1_code":"38",
    "gn:asciiname":"Kahvan",
    "gn:country_code":"IR",
    "gn:dem":1866,
    "gn:elevation":"0.0",
    "gn:feature_class":"P",
    "gn:feature_code":"PPL",
    "gn:name":"Kahv\u0101n",
    "gn:population":0,
    "gn:timezone":"Asia/Tehran",
    "iso:country":"IR",
    "name:ara_x_preferred":[
        "\u0643\u0647\u0648\u0627\u0646"
    ],
    "name:fas_x_preferred":[
        "\u0643\u0647\u0648\u0627\u0646"
    ],
    "name:fas_x_variant":[
        "Kahv\u0101n",
        "\u06a9\u0647\u0648\u0627\u0646"
    ],
    "wof:name":"Kahvan",
    "wof:placetype":"locality"
},
  "geometry": {"coordinates":[50.4951,36.1806],"type":"Point"}
}