{
  "type": "Feature",
  "properties": {
    "gn:admin1_code":"23.0",
    "gn:asciiname":"Chenarmodavi-ye Bala",
    "gn:country_code":"IR",
    "gn:dem":1407,
    "gn:feature_class":"P",
    "gn:feature_code":"PPL",
    "gn:name":"Chen\u0101rmodav\u012b-ye B\u0101l\u0101",
    "gn:population":0,
    "gn:timezone":"Asia/Tehran",
    "iso:country":"IR",
    "name:fas_x_preferred":[
        "\u0686\u0646\u0627\u0631\u0645\u062f\u0648\u06cc \u0628\u0627\u0644\u0627"
    ],
    "name:und_x_variant":[
        "Chen\u0101rmodav\u012b-ye B\u0101l\u0101"
    ],
    "wof:name":"Chenarmodavi-ye Bala",
    "wof:placetype":"locality"
},
  "geometry": {"coordinates":[47.59899,33.89856],"type":"Point"}
}