{
  "type": "Feature",
  "properties": {
    "gn:admin1_code":"8",
    "gn:asciiname":"Talesh Mahalleh",
    "gn:country_code":"IR",
    "gn:dem":7,
    "gn:feature_class":"P",
    "gn:feature_code":"PPL",
    "gn:name":"T\u0101lesh Ma\u1e29alleh",
    "gn:population":0,
    "gn:timezone":"Asia/Tehran",
    "iso:country":"IR",
    "name:fas_x_preferred":[
        "\u0162\u0101lesh Ma\u1e29alleh"
    ],
    "name:fas_x_variant":[
        "\u0637\u0627\u0644\u0634 \u0645\u062d\u0644\u0647",
        "\u062a\u0627\u0644\u0634 \u0645\u062d\u0644\u0647",
        "\u0637\u0627\u0644\u0634\u200c\u0645\u062d\u0644\u0647"
    ],
    "name:msa_x_preferred":[
        "Talesh Mahalleh"
    ],
    "name:ukr_x_preferred":[
        "\u0422\u0430\u043b\u0435\u0448-\u041c\u0430\u0433\u0430\u043b\u043b\u0454"
    ],
    "name:und_x_variant":[
        "\u0637\u0627\u0644\u0634 \u0645\u062d\u0644\u0647",
        "T\u0101lesh Ma\u1e29alleh"
    ],
    "wof:name":"Talesh Mahalleh",
    "wof:placetype":"locality"
},
  "geometry": {"coordinates":[50.10262,37.18463],"type":"Point"}
}