{
  "type": "Feature",
  "properties": {
    "gn:admin1_code":"23",
    "gn:asciiname":"Gandabeh Shiravand",
    "gn:country_code":"IR",
    "gn:dem":1305,
    "gn:feature_class":"P",
    "gn:feature_code":"PPL",
    "gn:name":"Gand\u0101beh Sh\u012br\u0101vand",
    "gn:population":0,
    "gn:timezone":"Asia/Tehran",
    "iso:country":"IR",
    "name:fas_x_preferred":[
        "\u06af\u064e\u0646\u062f\u0627\u0628\u0650\u06c0 \u0634\u064a\u0631\u0627\u0648\u064e\u0646\u062f"
    ],
    "name:fas_x_variant":[
        "\u06af\u0646\u062f\u0627\u0628\u0647 \u0634\u06cc\u0631\u0627\u0648\u0646\u062f",
        "\u06af\u0646\u062f\u0627\u0628\u0647 \u0634\u06cc\u0631\u0622\u0648\u0646\u062f"
    ],
    "name:und_x_variant":[
        "Gand\u0101beh Sh\u012br\u0101vand"
    ],
    "wof:name":"Gandabeh Shiravand",
    "wof:placetype":"locality"
},
  "geometry": {"coordinates":[47.4932,33.5163],"type":"Point"}
}