{
  "type": "Feature",
  "properties": {
    "gn:admin1_code":"4.0",
    "gn:asciiname":"Tang-e Daf",
    "gn:country_code":"IR",
    "gn:dem":220,
    "gn:feature_class":"P",
    "gn:feature_code":"PPL",
    "gn:name":"Tang-e Daf",
    "gn:population":0,
    "gn:timezone":"Asia/Tehran",
    "iso:country":"IR",
    "name:fas_x_preferred":[
        "\u062a\u0646\u06af \u062f\u0641"
    ],
    "wof:name":"Tang-e Daf",
    "wof:placetype":"locality"
},
  "geometry": {"coordinates":[59.00493,26.06744],"type":"Point"}
}