{
  "type": "Feature",
  "properties": {
    "gn:admin1_code":"28",
    "gn:asciiname":"Tameh",
    "gn:country_code":"IR",
    "gn:dem":2045,
    "gn:feature_class":"P",
    "gn:feature_code":"PPL",
    "gn:name":"\u0162\u0101meh",
    "gn:population":0,
    "gn:timezone":"Asia/Tehran",
    "iso:country":"IR",
    "name:fas_x_preferred":[
        "\u0162\u0101meh"
    ],
    "name:fas_x_variant":[
        "\u0637\u0627\u0645\u0647"
    ],
    "name:und_x_variant":[
        "Teh\u0101mi"
    ],
    "wof:name":"Tameh",
    "wof:placetype":"locality"
},
  "geometry": {"coordinates":[51.8794,33.46575],"type":"Point"}
}