{
  "type": "Feature",
  "properties": {
    "gn:admin1_code":"32",
    "gn:asciiname":"Zand",
    "gn:country_code":"IR",
    "gn:dem":1627,
    "gn:feature_class":"P",
    "gn:feature_code":"PPL",
    "gn:name":"Zand",
    "gn:population":0,
    "gn:timezone":"Asia/Tehran",
    "iso:country":"IR",
    "name:fas_x_preferred":[
        "\u0632\u0646\u062f"
    ],
    "name:msa_x_preferred":[
        "Zand"
    ],
    "wof:name":"Zand",
    "wof:placetype":"locality"
},
  "geometry": {"coordinates":[48.15485,37.59286],"type":"Point"}
}