{
  "type": "Feature",
  "properties": {
    "gn:admin1_code":"34",
    "gn:asciiname":"Maragheh",
    "gn:country_code":"IR",
    "gn:dem":1992,
    "gn:feature_class":"P",
    "gn:feature_code":"PPL",
    "gn:name":"Mar\u0101gheh",
    "gn:population":0,
    "gn:timezone":"Asia/Tehran",
    "iso:country":"IR",
    "name:ara_x_preferred":[
        "\u0645\u0631\u0627\u063a\u0629"
    ],
    "name:arz_x_preferred":[
        "\u0645\u0631\u0627\u063a\u0647"
    ],
    "name:azb_x_preferred":[
        "\u0645\u0631\u0627\u063a\u0647"
    ],
    "name:aze_x_preferred":[
        "Mara\u011fa"
    ],
    "name:ben_x_preferred":[
        "\u09ae\u09be\u09b0\u09be\u0998\u09c7\u09b9"
    ],
    "name:bre_x_preferred":[
        "Maragheh"
    ],
    "name:bul_x_preferred":[
        "\u041c\u0430\u0440\u0430\u043a\u0435"
    ],
    "name:cat_x_preferred":[
        "Maragha"
    ],
    "name:ceb_x_preferred":[
        "Mar\u0101gheh"
    ],
    "name:ckb_x_preferred":[
        "\u0645\u06d5\u0631\u0627\u063a\u06d5"
    ],
    "name:deu_x_preferred":[
        "Maragha"
    ],
    "name:ell_x_preferred":[
        "\u039c\u03b1\u03c1\u03b1\u03b3\u03ba\u03ad\u03c7"
    ],
    "name:fas_x_preferred":[
        "Mar\u0101gheh-ye P\u0101\u2019\u012bn"
    ],
    "name:fas_x_variant":[
        "\u0645\u0631\u0627\u063a\u0647"
    ],
    "name:fin_x_preferred":[
        "Maragheh"
    ],
    "name:fra_x_preferred":[
        "Maragha"
    ],
    "name:heb_x_preferred":[
        "\u05de\u05e8\u05d0\u05d2\u05d4"
    ],
    "name:hin_x_preferred":[
        "\u092e\u0930\u093e\u0918\u0947"
    ],
    "name:hrv_x_preferred":[
        "Maraga"
    ],
    "name:hun_x_preferred":[
        "Maragheh"
    ],
    "name:hye_x_preferred":[
        "\u0544\u0561\u0580\u0561\u0572\u0561"
    ],
    "name:ind_x_preferred":[
        "Maragheh"
    ],
    "name:ita_x_preferred":[
        "Maragheh"
    ],
    "name:jpn_x_preferred":[
        "\u30de\u30e9\u30fc\u30b2"
    ],
    "name:kor_x_preferred":[
        "\ub9c8\ub77c\uac8c"
    ],
    "name:mlg_x_preferred":[
        "Maragheh"
    ],
    "name:msa_x_preferred":[
        "Maragheh"
    ],
    "name:nld_x_preferred":[
        "Maragha"
    ],
    "name:nor_x_preferred":[
        "Maragheh"
    ],
    "name:pnb_x_preferred":[
        "\u0645\u0631\u0627\u063a\u0647"
    ],
    "name:pol_x_preferred":[
        "Maraghe"
    ],
    "name:por_x_preferred":[
        "Maragha"
    ],
    "name:ron_x_preferred":[
        "Maragheh"
    ],
    "name:rus_x_preferred":[
        "\u041c\u0435\u0440\u0430\u0433\u0435"
    ],
    "name:spa_x_preferred":[
        "Maraghe"
    ],
    "name:swe_x_preferred":[
        "Maragheh"
    ],
    "name:tgk_x_preferred":[
        "\u041c\u0430\u0440\u043e\u0493\u0430"
    ],
    "name:tur_x_preferred":[
        "Meraga"
    ],
    "name:ukr_x_preferred":[
        "\u041c\u0435\u0440\u0430\u0433\u0435"
    ],
    "name:und_x_variant":[
        "Mar\u0101gheh-ye B\u0101l\u0101",
        "Marageh"
    ],
    "name:urd_x_preferred":[
        "\u0645\u0631\u0627\u063a\u06c1"
    ],
    "name:uzb_x_preferred":[
        "Marog\u02bba"
    ],
    "name:vie_x_preferred":[
        "Maragheh"
    ],
    "name:war_x_preferred":[
        "Maraqeh"
    ],
    "name:zho_x_preferred":[
        "\u99ac\u62c9\u84cb"
    ],
    "wof:name":"Maragheh",
    "wof:placetype":"locality"
},
  "geometry": {"coordinates":[49.70968,35.22886],"type":"Point"}
}