{
  "type": "Feature",
  "properties": {
    "gn:admin1_code":"34",
    "gn:asciiname":"Maragheh",
    "gn:country_code":"IR",
    "gn:dem":1992,
    "gn:feature_class":"P",
    "gn:feature_code":"PPL",
    "gn:name":"Mar\u0101gheh",
    "gn:population":0,
    "gn:timezone":"Asia/Tehran",
    "iso:country":"IR",
    "name:fas_x_preferred":[
        "Mar\u0101gheh-ye P\u0101\u2019\u012bn"
    ],
    "name:fas_x_variant":[
        "\u0645\u0631\u0627\u063a\u0647"
    ],
    "name:und_x_variant":[
        "Mar\u0101gheh",
        "Mar\u0101gheh-ye B\u0101l\u0101",
        "Marageh"
    ],
    "wof:name":"Maragheh",
    "wof:placetype":"locality"
},
  "geometry": {"coordinates":[49.70968,35.22886],"type":"Point"}
}