{
  "type": "Feature",
  "properties": {
    "gn:admin1_code":"9",
    "gn:asciiname":"Tajar",
    "gn:country_code":"IR",
    "gn:dem":1982,
    "gn:feature_class":"P",
    "gn:feature_code":"PPL",
    "gn:name":"\u0162ajar",
    "gn:population":0,
    "gn:timezone":"Asia/Tehran",
    "iso:country":"IR",
    "name:ceb_x_preferred":[
        "\u0162ajar-e S\u0101men"
    ],
    "name:fas_x_preferred":[
        "\u062a\u064e\u062c\u064e\u0631"
    ],
    "name:fas_x_variant":[
        "\u0162ajar-e S\u0101men",
        "\u0637\u062c\u0631 \u0633\u0627\u0645\u0646",
        "\u0637\u062c\u0631",
        "\u062a\u062c\u0631"
    ],
    "name:msa_x_preferred":[
        "Tajar-e Samen"
    ],
    "name:swe_x_preferred":[
        "\u0162ajar-e S\u0101men"
    ],
    "name:und_x_variant":[
        "\u0637\u062c\u0631 \u0633\u0627\u0645\u0646",
        "\u0162ajar"
    ],
    "wof:name":"Tajar",
    "wof:placetype":"locality"
},
  "geometry": {"coordinates":[48.6655,34.22544],"type":"Point"}
}