{
  "type": "Feature",
  "properties": {
    "gn:admin1_code":"33",
    "gn:asciiname":"Khalifeh Kamal",
    "gn:country_code":"IR",
    "gn:dem":1740,
    "gn:feature_class":"P",
    "gn:feature_code":"PPL",
    "gn:name":"Khal\u012bfeh Kam\u0101l",
    "gn:population":0,
    "gn:timezone":"Asia/Tehran",
    "iso:country":"IR",
    "name:fas_x_preferred":[
        "\u062e\u0644\u06cc\u0641\u0647 \u06a9\u0645\u0627\u0644"
    ],
    "name:fas_x_variant":[
        "Khal\u012bfeh Kam\u0101l"
    ],
    "wof:name":"Khalifeh Kamal",
    "wof:placetype":"locality"
},
  "geometry": {"coordinates":[47.3127,37.2871],"type":"Point"}
}