{
  "type": "Feature",
  "properties": {
    "gn:admin1_code":"23",
    "gn:asciiname":"Sireh-ye Bala",
    "gn:cc2":"IR",
    "gn:country_code":"IR",
    "gn:dem":1832,
    "gn:feature_class":"P",
    "gn:feature_code":"PPL",
    "gn:name":"S\u012breh-ye B\u0101l\u0101",
    "gn:population":0,
    "gn:timezone":"Asia/Tehran",
    "iso:country":"IR",
    "name:fas_x_preferred":[
        "\u0633\u064a\u0631\u0650\u06c0 \u0628\u0627\u0644\u0627"
    ],
    "name:fas_x_variant":[
        "\u0633\u064a\u0631\u0650\u06c0 \u0639\u064f\u0644\u064a\u0627"
    ],
    "name:und_x_variant":[
        "S\u012breh-ye `Oly\u0101"
    ],
    "wof:name":"Sireh-ye Bala",
    "wof:placetype":"locality"
},
  "geometry": {"coordinates":[49.16222,33.41278],"type":"Point"}
}