{
  "type": "Feature",
  "properties": {
    "gn:admin1_code":"16.0",
    "gn:asciiname":"Zarrinabad",
    "gn:country_code":"IR",
    "gn:dem":1878,
    "gn:feature_class":"P",
    "gn:feature_code":"PPL",
    "gn:name":"Zarr\u012bn\u0101b\u0101d",
    "gn:population":0,
    "gn:timezone":"Asia/Tehran",
    "iso:country":"IR",
    "name:ara_x_preferred":[
        "\u0632\u0631\u064a\u0646 \u0623\u0628\u0627\u062f"
    ],
    "name:aze_x_preferred":[
        "Z\u0259rrinabad"
    ],
    "name:ceb_x_preferred":[
        "Zarr\u012bn\u0101b\u0101d"
    ],
    "name:fas_x_preferred":[
        "\u0632\u0631\u06cc\u0646 \u0622\u0628\u0627\u062f"
    ],
    "name:fas_x_variant":[
        "Zarr\u012bn\u0101b\u0101d",
        "\u0632\u0631\u06cc\u0646\u200c\u0622\u0628\u0627\u062f"
    ],
    "name:hun_x_preferred":[
        "Zarrinabad"
    ],
    "name:ita_x_preferred":[
        "Zarrinabad"
    ],
    "name:mlg_x_preferred":[
        "Zarrinabad"
    ],
    "name:rus_x_preferred":[
        "\u0417\u0435\u0440\u0440\u0438\u043d\u0430\u0431\u0430\u0434"
    ],
    "name:swe_x_preferred":[
        "Zarr\u012bn\u0101b\u0101d"
    ],
    "name:tur_x_preferred":[
        "Zerrinabad"
    ],
    "name:zho_x_preferred":[
        "\u624e\u91cc\u7d0d\u5df4\u5fb7"
    ],
    "wof:name":"Zarrinabad",
    "wof:placetype":"locality"
},
  "geometry": {"coordinates":[47.57872,35.59524000000001],"type":"Point"}
}