{
  "type": "Feature",
  "properties": {
    "gn:admin1_code":"16.0",
    "gn:asciiname":"Zarrinabad",
    "gn:country_code":"IR",
    "gn:dem":1878,
    "gn:feature_class":"P",
    "gn:feature_code":"PPL",
    "gn:name":"Zarr\u012bn\u0101b\u0101d",
    "gn:population":0,
    "gn:timezone":"Asia/Tehran",
    "iso:country":"IR",
    "name:fas_x_preferred":[
        "\u0632\u0631\u06cc\u0646 \u0622\u0628\u0627\u062f"
    ],
    "name:fas_x_variant":[
        "Zarr\u012bn\u0101b\u0101d"
    ],
    "wof:name":"Zarrinabad",
    "wof:placetype":"locality"
},
  "geometry": {"coordinates":[47.57872,35.59524000000001],"type":"Point"}
}