{
  "type": "Feature",
  "properties": {
    "gn:admin1_code":"33",
    "gn:asciiname":"Basirabad",
    "gn:country_code":"IR",
    "gn:dem":1664,
    "gn:elevation":"0.0",
    "gn:feature_class":"P",
    "gn:feature_code":"PPL",
    "gn:name":"Ba\u015f\u012br\u0101b\u0101d",
    "gn:population":0,
    "gn:timezone":"Asia/Tehran",
    "iso:country":"IR",
    "name:ara_x_preferred":[
        "\u0628\u0634\u064a\u0631 \u0623\u0628\u0627\u062f"
    ],
    "name:fas_x_preferred":[
        "\u0628\u0635\u06cc\u0631 \u0622\u0628\u0627\u062f"
    ],
    "name:fas_x_variant":[
        "Ba\u015f\u012br\u0101b\u0101d",
        "\u0628\u0635\u06cc\u0631\u0622\u0628\u0627\u062f"
    ],
    "name:msa_x_preferred":[
        "Basirabad"
    ],
    "wof:name":"Basirabad",
    "wof:placetype":"locality"
},
  "geometry": {"coordinates":[47.2848,38.5467],"type":"Point"}
}