{
  "type": "Feature",
  "properties": {
    "gn:admin1_code":"28.0",
    "gn:asciiname":"Abuol Ma`ali",
    "gn:country_code":"IR",
    "gn:dem":1482,
    "gn:feature_class":"P",
    "gn:feature_code":"PPL",
    "gn:name":"Ab\u016bol Ma\u2018\u0101l\u012b",
    "gn:population":0,
    "gn:timezone":"Asia/Tehran",
    "iso:country":"IR",
    "name:fas_x_preferred":[
        "Ab\u016bol Ma\u2018\u0101l\u012b"
    ],
    "name:und_x_variant":[
        "Abowlma \u2018\u0101l\u012b"
    ],
    "wof:name":"Abuol Ma`ali",
    "wof:placetype":"locality"
},
  "geometry": {"coordinates":[52.55111,32.45],"type":"Point"}
}