{
  "type": "Feature",
  "properties": {
    "gn:admin1_code":"4.0",
    "gn:asciiname":"Deh-e Hoseyn`ali Khan",
    "gn:country_code":"IR",
    "gn:dem":486,
    "gn:feature_class":"P",
    "gn:feature_code":"PPL",
    "gn:name":"Deh-e \u1e28oseyn\u2018al\u012b Kh\u0101n",
    "gn:population":0,
    "gn:timezone":"Asia/Tehran",
    "iso:country":"IR",
    "name:fas_x_preferred":[
        "\u062f\u0647 \u062d\u0633\u06cc\u0646\u0639\u0644\u06cc \u062e\u0627\u0646"
    ],
    "name:fas_x_variant":[
        "\u1e28oseyn-e \u2018Al\u012b Kh\u0101n",
        "Deh-e \u1e28oseyn\u2018al\u012b Kh\u0101n",
        "\u062f\u0647 \u062d\u0633\u06cc\u0646\u200c\u0639\u0644\u06cc \u062e\u0627\u0646"
    ],
    "wof:name":"Deh-e Hoseyn`ali Khan",
    "wof:placetype":"locality"
},
  "geometry": {"coordinates":[61.74799,31.10189],"type":"Point"}
}