{
  "type": "Feature",
  "properties": {
    "gn:admin1_code":"29",
    "gn:asciiname":"Banan",
    "gn:country_code":"IR",
    "gn:dem":413,
    "gn:feature_class":"P",
    "gn:feature_code":"PPLL",
    "gn:name":"Ban\u0101n",
    "gn:population":0,
    "gn:timezone":"Asia/Tehran",
    "iso:country":"IR",
    "name:fas_x_preferred":[
        "\u0628\u0646\u0627\u0646"
    ],
    "name:fas_x_variant":[
        "Ban\u0101n"
    ],
    "wof:name":"Banan",
    "wof:placetype":"locality"
},
  "geometry": {"coordinates":[58.18117,27.32837],"type":"Point"}
}