{
  "type": "Feature",
  "properties": {
    "gn:admin1_code":"7",
    "gn:asciiname":"Dehu",
    "gn:country_code":"IR",
    "gn:dem":394,
    "gn:feature_class":"P",
    "gn:feature_code":"PPL",
    "gn:name":"Deh\u016b",
    "gn:population":0,
    "gn:timezone":"Asia/Tehran",
    "iso:country":"IR",
    "name:fas_x_preferred":[
        "\u062f\u06cc\u0651\u0648"
    ],
    "name:fas_x_variant":[
        "Deh\u016b",
        "Deyy\u016b",
        "\u062f\u0647\u0648"
    ],
    "wof:name":"Dehu",
    "wof:placetype":"locality"
},
  "geometry": {"coordinates":[53.7747,27.1607],"type":"Point"}
}