{
  "type": "Feature",
  "properties": {
    "gn:admin1_code":"41",
    "gn:asciiname":"Boshgaz",
    "gn:country_code":"IR",
    "gn:dem":2200,
    "gn:feature_class":"P",
    "gn:feature_code":"PPL",
    "gn:name":"Boshgaz",
    "gn:population":0,
    "gn:timezone":"Asia/Tehran",
    "iso:country":"IR",
    "name:ceb_x_preferred":[
        "Boshgaz"
    ],
    "name:fas_x_preferred":[
        "\u0628\u0634\u06af\u0632"
    ],
    "name:swe_x_preferred":[
        "Boshgaz"
    ],
    "name:und_x_variant":[
        "B\u0101shgaz",
        "Bocgaz",
        "Bazqush",
        "Boshgaz"
    ],
    "wof:name":"Boshgaz",
    "wof:placetype":"locality"
},
  "geometry": {"coordinates":[59.69539,32.84469],"type":"Point"}
}