{
  "type": "Feature",
  "properties": {
    "gn:admin1_code":"11",
    "gn:asciiname":"Shahrak-e Darjenan Ebrahimi",
    "gn:country_code":"IR",
    "gn:dem":240,
    "gn:feature_class":"P",
    "gn:feature_code":"PPL",
    "gn:name":"Shahrak-e Darjen\u0101n Ebr\u0101h\u012bm\u012b",
    "gn:population":0,
    "gn:timezone":"Asia/Tehran",
    "iso:country":"IR",
    "name:fas_x_preferred":[
        "\u0627\u0628\u0631\u0627\u0647\u064a\u0645\u06cc"
    ],
    "name:fas_x_variant":[
        "\u0634\u0647\u0631\u06a9 \u062f\u0631\u062c\u0646\u0627\u0646 \u0627\u0628\u0631\u0627\u0647\u06cc\u0645\u06cc",
        "Ebr\u0101h\u012bm\u012b",
        "Shahrak-e Darjen\u0101n Ebr\u0101h\u012bm\u012b"
    ],
    "wof:name":"Shahrak-e Darjenan Ebrahimi",
    "wof:placetype":"locality"
},
  "geometry": {"coordinates":[56.4651,27.5641],"type":"Point"}
}