{
  "type": "Feature",
  "properties": {
    "gn:admin1_code":"28.0",
    "gn:asciiname":"Tolombeh-ye Karbala Ramazan",
    "gn:country_code":"IR",
    "gn:dem":1688,
    "gn:feature_class":"P",
    "gn:feature_code":"PPL",
    "gn:name":"Tolombeh-ye Karbal\u0101 Rama\u1e95\u0101n",
    "gn:population":0,
    "gn:timezone":"Asia/Tehran",
    "iso:country":"IR",
    "name:fas_x_preferred":[
        "Tolombeh-ye Karbal\u0101 Rama\u1e95\u0101n"
    ],
    "wof:name":"Tolombeh-ye Karbala Ramazan",
    "wof:placetype":"locality"
},
  "geometry": {"coordinates":[51.62222,32.36278],"type":"Point"}
}