{
  "type": "Feature",
  "properties": {
    "gn:admin1_code":"8",
    "gn:asciiname":"Galesh Gacheh",
    "gn:country_code":"IR",
    "gn:dem":-24,
    "gn:feature_class":"P",
    "gn:feature_code":"PPL",
    "gn:name":"G\u0101lesh G\u0101cheh",
    "gn:population":0,
    "gn:timezone":"Asia/Tehran",
    "iso:country":"IR",
    "name:ceb_x_preferred":[
        "G\u0101lesh G\u0101cheh"
    ],
    "name:fas_x_preferred":[
        "G\u0101lesh G\u0101cheh"
    ],
    "name:fas_x_variant":[
        "\u06af\u0627\u0644\u0634 \u06af\u0627\u0686\u0647",
        "\u06af\u0627\u0644\u0634\u200c\u06af\u0627\u0686\u0647"
    ],
    "name:msa_x_preferred":[
        "Galesh Gacheh"
    ],
    "name:swe_x_preferred":[
        "G\u0101lesh G\u0101cheh"
    ],
    "name:ukr_x_preferred":[
        "\u0490\u0430\u043b\u0435\u0448-\u0490\u0430\u0447\u0435"
    ],
    "wof:name":"Galesh Gacheh",
    "wof:placetype":"locality"
},
  "geometry": {"coordinates":[49.53543,37.35293],"type":"Point"}
}