{
  "type": "Feature",
  "properties": {
    "gn:admin1_code":"35.0",
    "gn:asciiname":"Miandeh",
    "gn:country_code":"IR",
    "gn:dem":-15,
    "gn:feature_class":"P",
    "gn:feature_code":"PPL",
    "gn:name":"M\u012b\u0101ndeh",
    "gn:population":0,
    "gn:timezone":"Asia/Tehran",
    "iso:country":"IR",
    "name:fas_x_preferred":[
        "M\u012b\u0101ndeh"
    ],
    "name:fas_x_variant":[
        "\u0645\u064a\u0627\u0646\u062f\u0647"
    ],
    "wof:name":"Miandeh",
    "wof:placetype":"locality"
},
  "geometry": {"coordinates":[52.84173000000001,36.64981],"type":"Point"}
}