{
  "type": "Feature",
  "properties": {
    "gn:admin1_code":"36",
    "gn:asciiname":"Mazra`eh-ye Zareh Kuband",
    "gn:country_code":"IR",
    "gn:dem":1660,
    "gn:feature_class":"P",
    "gn:feature_code":"PPL",
    "gn:name":"Mazra\u2018eh-ye Zareh K\u016bband",
    "gn:population":0,
    "gn:timezone":"Asia/Tehran",
    "iso:country":"IR",
    "name:fas_x_preferred":[
        "\u0645\u0632\u0631\u0639\u0647 \u0632\u0631\u0647 \u0643\u0648\u0628\u0646\u062f"
    ],
    "name:und_x_variant":[
        "Mazra\u2018eh-ye Zareh K\u016bband"
    ],
    "wof:name":"Mazra`eh-ye Zareh Kuband",
    "wof:placetype":"locality"
},
  "geometry": {"coordinates":[49.19928,36.10011],"type":"Point"}
}