{
  "type": "Feature",
  "properties": {
    "gn:admin1_code":"25.0",
    "gn:asciiname":"`Aliabad-e Bala",
    "gn:country_code":"IR",
    "gn:dem":831,
    "gn:feature_class":"P",
    "gn:feature_code":"PPL",
    "gn:name":"\u2018Al\u012b\u0101b\u0101d-e B\u0101l\u0101",
    "gn:population":0,
    "gn:timezone":"Asia/Tehran",
    "iso:country":"IR",
    "name:fas_x_preferred":[
        "\u0639\u064e\u0644\u064a\u0627\u0628\u0627\u062f\u0650 \u0628\u0627\u0644\u0627"
    ],
    "name:fas_x_variant":[
        "\u0639\u064e\u0644\u06cc \u0622\u0628\u0627\u062f \u0628\u0627\u0644\u0627",
        "\u2018Al\u012b\u0101b\u0101d-e B\u0101l\u0101"
    ],
    "name:und_x_variant":[
        "\u2018Al\u012b\u0101b\u0101d B\u0101l\u0101"
    ],
    "wof:name":"`Aliabad-e Bala",
    "wof:placetype":"locality"
},
  "geometry": {"coordinates":[52.48333,35.18333],"type":"Point"}
}