{
  "type": "Feature",
  "properties": {
    "gn:admin1_code":"5.0",
    "gn:asciiname":"Cham Murd",
    "gn:country_code":"IR",
    "gn:dem":1060,
    "gn:feature_class":"P",
    "gn:feature_code":"PPL",
    "gn:name":"Cham M\u016brd",
    "gn:population":0,
    "gn:timezone":"Asia/Tehran",
    "iso:country":"IR",
    "name:fas_x_preferred":[
        "Cham M\u016brd"
    ],
    "name:fas_x_variant":[
        "\u0686\u0645 \u0645\u0648\u0631\u062f",
        "\u062f\u0647 \u06a9\u0644"
    ],
    "name:und_x_variant":[
        "\u0686\u0645 \u0645\u0648\u0631\u062f",
        "Deh Kol"
    ],
    "wof:name":"Cham Murd",
    "wof:placetype":"locality"
},
  "geometry": {"coordinates":[50.56567,31.06656],"type":"Point"}
}