{
  "type": "Feature",
  "properties": {
    "gn:admin1_code":"38.0",
    "gn:asciiname":"Sefiddar",
    "gn:country_code":"IR",
    "gn:dem":1498,
    "gn:feature_class":"P",
    "gn:feature_code":"PPL",
    "gn:name":"Sef\u012bddar",
    "gn:population":0,
    "gn:timezone":"Asia/Tehran",
    "iso:country":"IR",
    "name:fas_x_preferred":[
        "Sef\u012bddar"
    ],
    "name:fas_x_variant":[
        "\u0633\u0641\u06cc\u062f\u062f\u0631"
    ],
    "wof:name":"Sefiddar",
    "wof:placetype":"locality"
},
  "geometry": {"coordinates":[50.61977,36.38639000000001],"type":"Point"}
}