{
  "type": "Feature",
  "properties": {
    "gn:admin1_code":"13",
    "gn:asciiname":"Tanur Dul",
    "gn:country_code":"IR",
    "gn:dem":1321,
    "gn:feature_class":"P",
    "gn:feature_code":"PPL",
    "gn:name":"Tan\u016br D\u016bl",
    "gn:population":0,
    "gn:timezone":"Asia/Tehran",
    "iso:country":"IR",
    "name:ceb_x_preferred":[
        "Tan\u016br D\u016bl"
    ],
    "name:fas_x_preferred":[
        "\u062a\u0646\u0648\u0631 \u062f\u0648\u0644"
    ],
    "name:fas_x_variant":[
        "Tan\u016br D\u016bl"
    ],
    "name:swe_x_preferred":[
        "Tan\u016br D\u016bl"
    ],
    "wof:name":"Tanur Dul",
    "wof:placetype":"locality"
},
  "geometry": {"coordinates":[46.825,34.4332],"type":"Point"}
}