{
  "type": "Feature",
  "properties": {
    "gn:admin1_code":"23",
    "gn:asciiname":"La`labad Qola'i",
    "gn:country_code":"IR",
    "gn:dem":1565,
    "gn:feature_class":"P",
    "gn:feature_code":"PPL",
    "gn:name":"La\u2018l\u0101b\u0101d Qol\u0101\u2019\u012b",
    "gn:population":0,
    "gn:timezone":"Asia/Tehran",
    "iso:country":"IR",
    "name:fas_x_preferred":[
        "\u0644\u064e\u0639\u0644 \u0622\u0628\u0627\u062f"
    ],
    "name:fas_x_variant":[
        "\u0644\u0639\u0644 \u0622\u0628\u0627\u062f \u0642\u0644\u0627\u0626\u06cc",
        "La\u2018l\u0101b\u0101d"
    ],
    "name:und_x_variant":[
        "La\u2018l\u0101b\u0101d Qol\u0101\u2019\u012b"
    ],
    "wof:name":"La`labad Qola'i",
    "wof:placetype":"locality"
},
  "geometry": {"coordinates":[47.915,33.76009000000001],"type":"Point"}
}