{
  "type": "Feature",
  "properties": {
    "gn:admin1_code":"25",
    "gn:asciiname":"Qodratabad",
    "gn:country_code":"IR",
    "gn:dem":1134,
    "gn:feature_class":"P",
    "gn:feature_code":"PPL",
    "gn:name":"Qodrat\u0101b\u0101d",
    "gn:population":0,
    "gn:timezone":"Asia/Tehran",
    "iso:country":"IR",
    "name:fas_x_preferred":[
        "\u0642\u062f\u0631\u062a \u0622\u0628\u0627\u062f"
    ],
    "name:fas_x_variant":[
        "Qodrat\u0101b\u0101d"
    ],
    "wof:name":"Qodratabad",
    "wof:placetype":"locality"
},
  "geometry": {"coordinates":[54.20099,36.09172],"type":"Point"}
}