{
  "type": "Feature",
  "properties": {
    "gn:admin1_code":"7.0",
    "gn:asciiname":"Bagh Budarh",
    "gn:country_code":"IR",
    "gn:dem":1637,
    "gn:feature_class":"P",
    "gn:feature_code":"PPL",
    "gn:name":"B\u0101gh B\u016bdarh",
    "gn:population":0,
    "gn:timezone":"Asia/Tehran",
    "iso:country":"IR",
    "name:fas_x_preferred":[
        "B\u0101gh B\u016bdarh"
    ],
    "wof:name":"Bagh Budarh",
    "wof:placetype":"locality"
},
  "geometry": {"coordinates":[53.03611,29.92306],"type":"Point"}
}