{
  "type": "Feature",
  "properties": {
    "gn:admin1_code":"3",
    "gn:asciiname":"Allah Morad",
    "gn:country_code":"IR",
    "gn:dem":2063,
    "gn:feature_class":"P",
    "gn:feature_code":"PPL",
    "gn:name":"All\u0101h Mor\u0101d",
    "gn:population":0,
    "gn:timezone":"Asia/Tehran",
    "iso:country":"IR",
    "name:ceb_x_preferred":[
        "All\u0101h Mor\u0101d"
    ],
    "name:fas_x_preferred":[
        "\u062f\u0650\u0647 \u0646\u064f\u0648\u0650 \u0627\u064e\u0644\u0651\u0627\u0647 \u0645\u064f\u0631\u0627\u062f"
    ],
    "name:fas_x_variant":[
        "\u0627\u064e\u0644\u0651\u0627\u0647 \u0645\u064f\u0631\u0627\u062f",
        "Deh Now-e All\u0101h Mor\u0101d",
        "All\u0101h Mor\u0101d",
        "\u0627\u0644\u0644\u0647 \u0645\u0631\u0627\u062f",
        "\u062f\u0647\u0646\u0648 \u0627\u0644\u0644\u0647\u200c\u0645\u0631\u0627\u062f"
    ],
    "name:msa_x_preferred":[
        "Deh Now-e Allah Morad"
    ],
    "name:swe_x_preferred":[
        "All\u0101h Mor\u0101d"
    ],
    "wof:name":"Allah Morad",
    "wof:placetype":"locality"
},
  "geometry": {"coordinates":[51.05469,31.37971],"type":"Point"}
}