{
  "type": "Feature",
  "properties": {
    "gn:admin1_code":"15.0",
    "gn:asciiname":"Garashkan",
    "gn:country_code":"IR",
    "gn:dem":268,
    "gn:feature_class":"P",
    "gn:feature_code":"PPL",
    "gn:name":"Garashk\u0101n",
    "gn:population":0,
    "gn:timezone":"Asia/Tehran",
    "iso:country":"IR",
    "name:fas_x_preferred":[
        "\u06af\u0631\u0634\u06a9\u0627\u0646"
    ],
    "name:fas_x_variant":[
        "Garashk\u0101n"
    ],
    "wof:name":"Garashkan",
    "wof:placetype":"locality"
},
  "geometry": {"coordinates":[48.01,32.666],"type":"Point"}
}