{
  "type": "Feature",
  "properties": {
    "gn:admin1_code":"41.0",
    "gn:asciiname":"Yusefabad",
    "gn:country_code":"IR",
    "gn:dem":1784,
    "gn:feature_class":"P",
    "gn:feature_code":"PPLF",
    "gn:name":"Y\u016bsef\u0101b\u0101d",
    "gn:population":0,
    "gn:timezone":"Asia/Tehran",
    "iso:country":"IR",
    "name:fas_x_preferred":[
        "Y\u016bsef\u0101b\u0101d"
    ],
    "name:fas_x_variant":[
        "\u064a\u0648\u0633\u0641 \u0622\u0628\u0627\u062f",
        "\u0645\u0644\u06a9 \u0622\u0628\u0627\u062f"
    ],
    "name:und_x_variant":[
        "\u064a\u0648\u0633\u0641 \u0622\u0628\u0627\u062f",
        "Malak\u0101b\u0101d",
        "Malek\u0101b\u0101d"
    ],
    "wof:name":"Yusefabad",
    "wof:placetype":"locality"
},
  "geometry": {"coordinates":[59.32916,32.79192],"type":"Point"}
}