{
  "type": "Feature",
  "properties": {
    "gn:admin1_code":"29",
    "gn:asciiname":"Darkeln",
    "gn:country_code":"IR",
    "gn:dem":588,
    "gn:feature_class":"P",
    "gn:feature_code":"PPL",
    "gn:name":"Darkeln",
    "gn:population":0,
    "gn:timezone":"Asia/Tehran",
    "iso:country":"IR",
    "name:fas_x_preferred":[
        "\u062f\u0631\u06a9\u0644\u0646"
    ],
    "wof:name":"Darkeln",
    "wof:placetype":"locality"
},
  "geometry": {"coordinates":[58.2942,28.0727],"type":"Point"}
}