{
  "type": "Feature",
  "properties": {
    "gn:admin1_code":"29.0",
    "gn:asciiname":"Hojjatabad",
    "gn:country_code":"IR",
    "gn:dem":1395,
    "gn:feature_class":"P",
    "gn:feature_code":"PPLF",
    "gn:name":"\u1e28ojjat\u0101b\u0101d",
    "gn:population":0,
    "gn:timezone":"Asia/Tehran",
    "iso:country":"IR",
    "name:ara_x_preferred":[
        "\u062d\u062c\u062a \u0623\u0628\u0627\u062f"
    ],
    "name:fas_x_preferred":[
        "\u062d\u062c\u062a \u0622\u0628\u0627\u062f"
    ],
    "name:fas_x_variant":[
        "\u062d\u062c\u062a\u200c\u0622\u0628\u0627\u062f"
    ],
    "name:und_x_variant":[
        "\u1e28ojjat\u0101b\u0101d"
    ],
    "wof:name":"Hojjatabad",
    "wof:placetype":"locality"
},
  "geometry": {"coordinates":[55.38498000000001,30.8006],"type":"Point"}
}