{
  "type": "Feature",
  "properties": {
    "gn:admin1_code":"29",
    "gn:asciiname":"Kuh Joftan",
    "gn:cc2":"IR",
    "gn:country_code":"IR",
    "gn:dem":2631,
    "gn:feature_class":"P",
    "gn:feature_code":"PPL",
    "gn:name":"K\u016bh Joft\u0101n",
    "gn:population":0,
    "gn:timezone":"Asia/Tehran",
    "iso:country":"IR",
    "name:fas_x_preferred":[
        "K\u016bh Joft\u0101n"
    ],
    "name:und_x_variant":[
        "K\u016bh-e Joft\u0101n"
    ],
    "wof:name":"Kuh Joftan",
    "wof:placetype":"locality"
},
  "geometry": {"coordinates":[57.35278,30.24222],"type":"Point"}
}