{
  "type": "Feature",
  "properties": {
    "gn:admin1_code":"32",
    "gn:asciiname":"Chelleh Karan",
    "gn:country_code":"IR",
    "gn:dem":1537,
    "gn:feature_class":"P",
    "gn:feature_code":"PPL",
    "gn:name":"Chelleh Kar\u0101n",
    "gn:population":0,
    "gn:timezone":"Asia/Tehran",
    "iso:country":"IR",
    "name:aze_x_preferred":[
        "Col\u0259k\u0259ran"
    ],
    "name:fas_x_preferred":[
        "\u062c\u0644\u0647 \u06a9\u0631\u0627\u0646"
    ],
    "name:fas_x_variant":[
        "Chelleh Kar\u0101n"
    ],
    "wof:name":"Chelleh Karan",
    "wof:placetype":"locality"
},
  "geometry": {"coordinates":[48.5168,38.4335],"type":"Point"}
}