{
  "type": "Feature",
  "properties": {
    "gn:admin1_code":"36",
    "gn:asciiname":"Quyjuq Khan",
    "gn:country_code":"IR",
    "gn:dem":1597,
    "gn:feature_class":"P",
    "gn:feature_code":"PPL",
    "gn:name":"Q\u016byj\u016bq Kh\u0101n",
    "gn:population":0,
    "gn:timezone":"Asia/Tehran",
    "iso:country":"IR",
    "name:fas_x_preferred":[
        "\u0642\u0648\u064a\u062c\u0648\u0642 \u062e\u0627\u0646"
    ],
    "name:fas_x_variant":[
        "Q\u016byj\u016bq Kh\u0101n"
    ],
    "name:und_x_variant":[
        "G\u016by\u016bju",
        "Qey\u016bj\u016bq",
        "Guyudzhu"
    ],
    "wof:name":"Quyjuq Khan",
    "wof:placetype":"locality"
},
  "geometry": {"coordinates":[49.3551,36.1401],"type":"Point"}
}