{
  "type": "Feature",
  "properties": {
    "gn:admin1_code":"3",
    "gn:asciiname":"Por Khowr",
    "gn:country_code":"IR",
    "gn:dem":2176,
    "gn:feature_class":"P",
    "gn:feature_code":"PPL",
    "gn:name":"Por Khowr",
    "gn:population":0,
    "gn:timezone":"Asia/Tehran",
    "iso:country":"IR",
    "name:fas_x_preferred":[
        "\u067e\u064f\u0631 \u062e\u0648\u064f\u0631"
    ],
    "name:fas_x_variant":[
        "\u067e\u064e\u0631 \u062e\u064e\u0631"
    ],
    "name:und_x_variant":[
        "Par Khar",
        "Por Khowr"
    ],
    "wof:name":"Por Khowr",
    "wof:placetype":"locality"
},
  "geometry": {"coordinates":[50.81778,31.84861],"type":"Point"}
}