{
  "type": "Feature",
  "properties": {
    "gn:admin1_code":"13",
    "gn:asciiname":"Tahaneh-ye Vosta",
    "gn:country_code":"IR",
    "gn:dem":1486,
    "gn:feature_class":"P",
    "gn:feature_code":"PPL",
    "gn:name":"\u0162ahaneh-ye Vos\u0163\u00e1",
    "gn:population":0,
    "gn:timezone":"Asia/Tehran",
    "iso:country":"IR",
    "name:fas_x_preferred":[
        "\u0637\u0647\u0646\u0647 \u0648\u0633\u0637\u06cc"
    ],
    "name:fas_x_variant":[
        "\u0162ah\u0101neh-ye Vos\u0163\u00e1",
        "\u0162ahaneh-ye Vos\u0163\u00e1"
    ],
    "wof:name":"Tahaneh-ye Vosta",
    "wof:placetype":"locality"
},
  "geometry": {"coordinates":[47.1361,34.0963],"type":"Point"}
}