{
  "type": "Feature",
  "properties": {
    "gn:admin1_code":"34",
    "gn:asciiname":"Gardalin",
    "gn:country_code":"IR",
    "gn:dem":1758,
    "gn:feature_class":"P",
    "gn:feature_code":"PPL",
    "gn:name":"Gard\u0101l\u012bn",
    "gn:population":0,
    "gn:timezone":"Asia/Tehran",
    "iso:country":"IR",
    "name:fas_x_preferred":[
        "Gard\u0101l\u012bn"
    ],
    "name:und_x_variant":[
        "Kurdal\u012bn"
    ],
    "wof:name":"Gardalin",
    "wof:placetype":"locality"
},
  "geometry": {"coordinates":[49.35,34.61667],"type":"Point"}
}