{
  "type": "Feature",
  "properties": {
    "gn:admin1_code":"15",
    "gn:asciiname":"Hayatabad-e Khalifeh",
    "gn:country_code":"IR",
    "gn:dem":418,
    "gn:feature_class":"P",
    "gn:feature_code":"PPL",
    "gn:name":"\u1e28ay\u0101t\u0101b\u0101d-e Khal\u012bfeh",
    "gn:population":0,
    "gn:timezone":"Asia/Tehran",
    "iso:country":"IR",
    "name:azb_x_preferred":[
        "\u062d\u06cc\u0627\u062a \u0627\u0628\u0627\u062f\u062e\u0644\u06cc\u0641\u0647(\u0628\u0647\u0628\u0647\u0627\u0646)"
    ],
    "name:ceb_x_preferred":[
        "\u1e28ay\u0101t\u0101b\u0101d-e Khal\u012bfeh"
    ],
    "name:fas_x_preferred":[
        "\u062d\u06cc\u0627\u0637 \u0622\u0628\u0627\u062f \u062e\u0644\u06cc\u0641\u0647"
    ],
    "name:fas_x_variant":[
        "\u1e28ay\u0101t\u0101b\u0101d-e Khal\u012bfeh",
        "\u062d\u06cc\u0627\u062a\u200c\u0622\u0628\u0627\u062f \u062e\u0644\u06cc\u0641\u0647"
    ],
    "name:swe_x_preferred":[
        "\u1e28ay\u0101t\u0101b\u0101d-e Khal\u012bfeh"
    ],
    "name:und_x_variant":[
        "\u1e28ay\u0101\u0163\u0101b\u0101d-e Khal\u012bfeh"
    ],
    "wof:name":"Hayatabad-e Khalifeh",
    "wof:placetype":"locality"
},
  "geometry": {"coordinates":[50.198,30.7861],"type":"Point"}
}