{
  "type": "Feature",
  "properties": {
    "gn:admin1_code":"28.0",
    "gn:asciiname":"Goleh",
    "gn:country_code":"IR",
    "gn:dem":2313,
    "gn:feature_class":"P",
    "gn:feature_code":"PPL",
    "gn:name":"Goleh",
    "gn:population":0,
    "gn:timezone":"Asia/Tehran",
    "iso:country":"IR",
    "name:fas_x_preferred":[
        "\u06af\u0644\u0647"
    ],
    "wof:name":"Goleh",
    "wof:placetype":"locality"
},
  "geometry": {"coordinates":[52.5329,32.9024],"type":"Point"}
}