{
  "type": "Feature",
  "properties": {
    "gn:admin1_code":"40.0",
    "gn:asciiname":"Bonestan",
    "gn:country_code":"IR",
    "gn:dem":2070,
    "gn:feature_class":"P",
    "gn:feature_code":"PPL",
    "gn:name":"Bonest\u0101n",
    "gn:population":0,
    "gn:timezone":"Asia/Tehran",
    "iso:country":"IR",
    "name:fas_x_preferred":[
        "\u0628\u0646\u0633\u062a\u0627\u0646"
    ],
    "name:fas_x_variant":[
        "Bonest\u0101n"
    ],
    "wof:name":"Bonestan",
    "wof:placetype":"locality"
},
  "geometry": {"coordinates":[53.6705,31.9811],"type":"Point"}
}