{
  "type": "Feature",
  "properties": {
    "gn:admin1_code":"35.0",
    "gn:asciiname":"Shalandun",
    "gn:country_code":"IR",
    "gn:dem":385,
    "gn:feature_class":"P",
    "gn:feature_code":"PPL",
    "gn:name":"Shaland\u016bn",
    "gn:population":0,
    "gn:timezone":"Asia/Tehran",
    "iso:country":"IR",
    "name:fas_x_preferred":[
        "Shaland\u016bn"
    ],
    "name:fas_x_variant":[
        "\u0634\u0644\u0646\u062f\u0648\u0646",
        "\u0645\u0631\u062a\u0639 \u0634\u0644\u0646\u062f\u0627\u0646"
    ],
    "name:und_x_variant":[
        "\u0634\u0644\u0646\u062f\u0648\u0646",
        "Marta\u2018-ye Shaland\u0101n"
    ],
    "wof:name":"Shalandun",
    "wof:placetype":"locality"
},
  "geometry": {"coordinates":[50.74684,36.77378],"type":"Point"}
}