{
  "type": "Feature",
  "properties": {
    "gn:admin1_code":"35.0",
    "gn:asciiname":"Kalikhumand",
    "gn:country_code":"IR",
    "gn:dem":2272,
    "gn:feature_class":"P",
    "gn:feature_code":"PPL",
    "gn:name":"K\u0101l\u012bkh\u016bmand",
    "gn:population":0,
    "gn:timezone":"Asia/Tehran",
    "iso:country":"IR",
    "name:fas_x_preferred":[
        "\u06af\u0627\u0644\u06cc \u062e\u0645\u0646\u062f"
    ],
    "name:fas_x_variant":[
        "G\u0101l\u012b Khamand",
        "\u06a9\u0627\u0644\u06cc\u062e\u0648\u0645\u0646\u062f"
    ],
    "name:und_x_variant":[
        "K\u0101l\u012bkh\u016bmand"
    ],
    "wof:name":"Kalikhumand",
    "wof:placetype":"locality"
},
  "geometry": {"coordinates":[51.93221,36.35455],"type":"Point"}
}