{
  "type": "Feature",
  "properties": {
    "gn:admin1_code":"29",
    "gn:asciiname":"Mahalleh-ye Qal`eh Morteza",
    "gn:country_code":"IR",
    "gn:dem":2092,
    "gn:feature_class":"P",
    "gn:feature_code":"PPL",
    "gn:name":"Ma\u1e29alleh-ye Qal\u2018eh Morte\u1e95\u00e1",
    "gn:population":0,
    "gn:timezone":"Asia/Tehran",
    "iso:country":"IR",
    "name:fas_x_preferred":[
        "\u062f\u0631\u0647 \u0645\u0639\u062f\u0646"
    ],
    "name:fas_x_variant":[
        "Darreh Ma\u2018dan",
        "\u0645\u062d\u0644\u0647 \u0642\u0644\u0639\u0647 \u0645\u0631\u062a\u0636\u06cc"
    ],
    "name:und_x_variant":[
        "Ma\u1e29alleh-ye Qal\u2018eh Morte\u1e95\u00e1"
    ],
    "wof:name":"Mahalleh-ye Qal`eh Morteza",
    "wof:placetype":"locality"
},
  "geometry": {"coordinates":[56.34004,28.81888],"type":"Point"}
}