{
  "type": "Feature",
  "properties": {
    "gn:admin1_code":"4.0",
    "gn:asciiname":"Dartang",
    "gn:country_code":"IR",
    "gn:dem":1368,
    "gn:feature_class":"P",
    "gn:feature_code":"PPL",
    "gn:name":"Dartang",
    "gn:population":0,
    "gn:timezone":"Asia/Tehran",
    "iso:country":"IR",
    "name:fas_x_preferred":[
        "\u062f\u0631\u062a\u0646\u06af"
    ],
    "wof:name":"Dartang",
    "wof:placetype":"locality"
},
  "geometry": {"coordinates":[62.04077,27.42298],"type":"Point"}
}