{
  "type": "Feature",
  "properties": {
    "gn:admin1_code":"1.0",
    "gn:asciiname":"Bash Achiq",
    "gn:country_code":"IR",
    "gn:dem":1670,
    "gn:feature_class":"P",
    "gn:feature_code":"PPL",
    "gn:name":"Bash \u0100ch\u012bq",
    "gn:population":0,
    "gn:timezone":"Asia/Tehran",
    "iso:country":"IR",
    "name:fas_x_preferred":[
        "\u0628\u0627\u0634 \u0622\u0686\u064a\u0642"
    ],
    "name:fas_x_variant":[
        "Bash \u0100ch\u012bq"
    ],
    "wof:name":"Bash Achiq",
    "wof:placetype":"locality"
},
  "geometry": {"coordinates":[46.4542,36.9923],"type":"Point"}
}