{
  "type": "Feature",
  "properties": {
    "gn:admin1_code":"41",
    "gn:asciiname":"Jig",
    "gn:country_code":"IR",
    "gn:dem":1848,
    "gn:feature_class":"P",
    "gn:feature_code":"PPL",
    "gn:name":"J\u012bg",
    "gn:population":0,
    "gn:timezone":"Asia/Tehran",
    "iso:country":"IR",
    "name:cat_x_preferred":[
        "Slide"
    ],
    "name:deu_x_preferred":[
        "Jig"
    ],
    "name:ell_x_preferred":[
        "\u03a4\u03b6\u03b9\u03b3\u03ba"
    ],
    "name:fas_x_preferred":[
        "\u062c\u06cc\u06a9"
    ],
    "name:fas_x_variant":[
        "J\u012bk",
        "\u062c\u06cc\u06af",
        "\u062c\u06cc\u06a9 \u0633\u0641\u0644\u06cc"
    ],
    "name:fra_x_preferred":[
        "Jig"
    ],
    "name:ido_x_preferred":[
        "Jigo"
    ],
    "name:ita_x_preferred":[
        "Giga"
    ],
    "name:jpn_x_preferred":[
        "\u30b8\u30b0"
    ],
    "name:nno_x_preferred":[
        "Jig"
    ],
    "name:pol_x_preferred":[
        "Jig"
    ],
    "name:por_x_preferred":[
        "Jig"
    ],
    "name:rus_x_preferred":[
        "\u0414\u0436\u0438\u0433\u0430"
    ],
    "name:spa_x_preferred":[
        "Slide"
    ],
    "name:srp_x_preferred":[
        "\u0416\u0438\u0433\u0430"
    ],
    "name:swe_x_preferred":[
        "Jig"
    ],
    "name:ukr_x_preferred":[
        "\u0414\u0436\u0438\u0433\u0430"
    ],
    "name:und_x_variant":[
        "Jirag",
        "Jirg",
        "J\u012bg-e Sofl\u00e1",
        "J\u012brak",
        "J\u012bg",
        "J\u012bk-e Sofl\u00e1"
    ],
    "wof:name":"Jig",
    "wof:placetype":"locality"
},
  "geometry": {"coordinates":[59.5006,32.3088],"type":"Point"}
}