{
  "type": "Feature",
  "properties": {
    "gn:admin1_code":"4",
    "gn:asciiname":"Dehdari",
    "gn:country_code":"IR",
    "gn:dem":1443,
    "gn:feature_class":"P",
    "gn:feature_code":"PPL",
    "gn:name":"Dehd\u0101r\u012b",
    "gn:population":0,
    "gn:timezone":"Asia/Tehran",
    "iso:country":"IR",
    "name:fas_x_preferred":[
        "\u062f\u0647\u062f\u0627\u0631\u06cc"
    ],
    "name:fas_x_variant":[
        "Dehd\u0101r\u012b"
    ],
    "wof:name":"Dehdari",
    "wof:placetype":"locality"
},
  "geometry": {"coordinates":[60.38541,28.87354],"type":"Point"}
}