{
  "type": "Feature",
  "properties": {
    "gn:admin1_code":"15",
    "gn:asciiname":"Sanjar",
    "gn:country_code":"IR",
    "gn:dem":121,
    "gn:feature_class":"P",
    "gn:feature_code":"PPL",
    "gn:name":"Sanjar",
    "gn:population":0,
    "gn:timezone":"Asia/Tehran",
    "iso:country":"IR",
    "name:fas_x_preferred":[
        "\u0633\u0646\u062c\u0631"
    ],
    "name:und_x_variant":[
        "Senjar",
        "Sanjar"
    ],
    "wof:name":"Sanjar",
    "wof:placetype":"locality"
},
  "geometry": {"coordinates":[48.35516,32.38577],"type":"Point"}
}