{
  "type": "Feature",
  "properties": {
    "gn:admin1_code":"44.0",
    "gn:asciiname":"Biryanchal",
    "gn:country_code":"IR",
    "gn:dem":1955,
    "gn:feature_class":"P",
    "gn:feature_code":"PPLF",
    "gn:name":"B\u012bry\u0101nch\u0101l",
    "gn:population":0,
    "gn:timezone":"Asia/Tehran",
    "iso:country":"IR",
    "name:fas_x_preferred":[
        "\u0628\u0631\u064a\u0627\u0646\u0686\u0627\u0644"
    ],
    "name:fas_x_variant":[
        "Bery\u0101nch\u0101l",
        "\u0628\u064a\u0631\u064a\u0627\u0646\u0686\u0627\u0644"
    ],
    "name:und_x_variant":[
        "B\u012bry\u0101nch\u0101l"
    ],
    "wof:name":"Biryanchal",
    "wof:placetype":"locality"
},
  "geometry": {"coordinates":[51.00357,35.97531],"type":"Point"}
}