{
  "type": "Feature",
  "properties": {
    "gn:admin1_code":"13",
    "gn:asciiname":"Deh A`zam",
    "gn:country_code":"IR",
    "gn:dem":1320,
    "gn:feature_class":"P",
    "gn:feature_code":"PPL",
    "gn:name":"Deh A\u2018z\u0327am",
    "gn:population":0,
    "gn:timezone":"Asia/Tehran",
    "iso:country":"IR",
    "name:fas_x_preferred":[
        "\u062f\u0647 \u0627\u0639\u0638\u0645"
    ],
    "name:fas_x_variant":[
        "Deh A\u2018z\u0327am"
    ],
    "wof:name":"Deh A`zam",
    "wof:placetype":"locality"
},
  "geometry": {"coordinates":[46.7012,34.5396],"type":"Point"}
}