{
  "type": "Feature",
  "properties": {
    "gn:admin1_code":"8",
    "gn:asciiname":"Gar Garud",
    "gn:country_code":"IR",
    "gn:dem":117,
    "gn:feature_class":"P",
    "gn:feature_code":"PPL",
    "gn:name":"Gar Gar\u016bd",
    "gn:population":0,
    "gn:timezone":"Asia/Tehran",
    "iso:country":"IR",
    "name:ara_x_preferred":[
        "\u063a\u0631\u06a9\u0631\u0648\u062f"
    ],
    "name:fas_x_preferred":[
        "Gark\u016br\u016bd"
    ],
    "name:fas_x_variant":[
        "Garkar\u016bd",
        "\u06af\u0631\u06a9\u0631\u0648\u062f",
        "\u06af\u0631 \u06af\u0631\u0648\u062f"
    ],
    "name:msa_x_preferred":[
        "Garkarud"
    ],
    "name:ukr_x_preferred":[
        "\u0490\u0430\u0440\u043a\u0430\u0440\u0443\u0434"
    ],
    "name:und_x_variant":[
        "Garkr\u016bd",
        "Garkor\u016bd",
        "Garkar\u016bd",
        "\u06af\u0631\u06a9\u0631\u0648\u062f",
        "Gar Gar\u016bd"
    ],
    "wof:name":"Gar Garud",
    "wof:placetype":"locality"
},
  "geometry": {"coordinates":[50.23103,37.02987],"type":"Point"}
}