{
  "type": "Feature",
  "properties": {
    "gn:admin1_code":"15",
    "gn:asciiname":"Patuf",
    "gn:country_code":"IR",
    "gn:dem":956,
    "gn:feature_class":"P",
    "gn:feature_code":"PPL",
    "gn:name":"P\u0101t\u016bf",
    "gn:population":0,
    "gn:timezone":"Asia/Tehran",
    "iso:country":"IR",
    "name:fas_x_preferred":[
        "Konjek\u0101l"
    ],
    "name:fas_x_variant":[
        "Konj\u0101r-e B\u0101l\u0101",
        "\u06a9\u0646\u062c\u0627\u0631 \u0628\u0627\u0644\u0627",
        "\u067e\u0627\u062a\u0648\u0641"
    ],
    "name:und_x_variant":[
        "P\u0101t\u016bf"
    ],
    "wof:name":"Patuf",
    "wof:placetype":"locality"
},
  "geometry": {"coordinates":[50.02461,31.45938],"type":"Point"}
}