{
  "type": "Feature",
  "properties": {
    "gn:admin1_code":"32",
    "gn:asciiname":"`Asgar Kandi",
    "gn:country_code":"IR",
    "gn:dem":439,
    "gn:feature_class":"P",
    "gn:feature_code":"PPL",
    "gn:name":"\u2018Asgar Kand\u012b",
    "gn:population":0,
    "gn:timezone":"Asia/Tehran",
    "iso:country":"IR",
    "name:fas_x_preferred":[
        "\u0639\u0633\u06af\u0631 \u06a9\u0646\u062f\u06cc"
    ],
    "name:fas_x_variant":[
        "\u2018Asgar Kand\u012b"
    ],
    "wof:name":"`Asgar Kandi",
    "wof:placetype":"locality"
},
  "geometry": {"coordinates":[47.639,39.152],"type":"Point"}
}