{
  "type": "Feature",
  "properties": {
    "gn:admin1_code":"33",
    "gn:asciiname":"Khosrowshahr",
    "gn:country_code":"IR",
    "gn:dem":1354,
    "gn:feature_class":"P",
    "gn:feature_code":"PPL",
    "gn:name":"Khosrowshahr",
    "gn:population":0,
    "gn:timezone":"Asia/Tehran",
    "iso:country":"IR",
    "name:fas_x_preferred":[
        "\u062e\u0633\u0631\u0648 \u0634\u0647\u0631"
    ],
    "name:und_x_variant":[
        "Khusrosh\u0101h",
        "Khosrow Sh\u0101h",
        "Khusraush\u0101h",
        "Khosrowshahr"
    ],
    "wof:name":"Khosrowshahr",
    "wof:placetype":"locality"
},
  "geometry": {"coordinates":[46.0528,37.9497],"type":"Point"}
}