{
  "type": "Feature",
  "properties": {
    "gn:admin1_code":"42",
    "gn:asciiname":"Dor Badam",
    "gn:country_code":"IR",
    "gn:dem":1540,
    "gn:feature_class":"P",
    "gn:feature_code":"PPL",
    "gn:name":"Dor B\u0101d\u0101m",
    "gn:population":0,
    "gn:timezone":"Asia/Tehran",
    "iso:country":"IR",
    "name:ceb_x_preferred":[
        "Dor B\u0101d\u0101m"
    ],
    "name:fas_x_preferred":[
        "Dor B\u0101d\u0101m"
    ],
    "name:fas_x_variant":[
        "\u062f\u0631 \u0628\u0627\u062f\u0627\u0645",
        "\u062f\u0631\u0628\u0627\u062f\u0627\u0645"
    ],
    "name:swe_x_preferred":[
        "Dor B\u0101d\u0101m"
    ],
    "name:und_x_variant":[
        "Durb \u0100dam"
    ],
    "wof:name":"Dor Badam",
    "wof:placetype":"locality"
},
  "geometry": {"coordinates":[58.45941,37.49484],"type":"Point"}
}