{
  "type": "Feature",
  "properties": {
    "gn:admin1_code":"36",
    "gn:asciiname":"Kushkunlu",
    "gn:country_code":"IR",
    "gn:dem":1519,
    "gn:feature_class":"P",
    "gn:feature_code":"PPL",
    "gn:name":"K\u016bshk\u016bnl\u016b",
    "gn:population":0,
    "gn:timezone":"Asia/Tehran",
    "iso:country":"IR",
    "name:fas_x_preferred":[
        "\u0643\u0648\u0634\u0643\u0648\u0646\u0644\u0648"
    ],
    "name:fas_x_variant":[
        "K\u016bshk\u016bnl\u016b"
    ],
    "wof:name":"Kushkunlu",
    "wof:placetype":"locality"
},
  "geometry": {"coordinates":[48.2561,36.0006],"type":"Point"}
}