{
  "type": "Feature",
  "properties": {
    "gn:admin1_code":"36",
    "gn:asciiname":"Qamarlak",
    "gn:country_code":"IR",
    "gn:dem":1644,
    "gn:feature_class":"P",
    "gn:feature_code":"PPL",
    "gn:name":"Qamarlak",
    "gn:population":0,
    "gn:timezone":"Asia/Tehran",
    "iso:country":"IR",
    "name:fas_x_preferred":[
        "\u0642\u0645\u0631\u0644\u06a9"
    ],
    "name:fas_x_variant":[
        "\u0643\u064e\u0645\u064e\u0631\u0644\u064e\u0643",
        "\u0642\u0646\u0628\u0631\u0644\u06a9"
    ],
    "name:und_x_variant":[
        "Kamarlak",
        "Qanbarlek",
        "Qamarlak"
    ],
    "wof:name":"Qamarlak",
    "wof:placetype":"locality"
},
  "geometry": {"coordinates":[48.02544,36.34527],"type":"Point"}
}