{
  "type": "Feature",
  "properties": {
    "gn:admin1_code":"4.0",
    "gn:asciiname":"Daridar",
    "gn:country_code":"IR",
    "gn:dem":1029,
    "gn:feature_class":"P",
    "gn:feature_code":"PPL",
    "gn:name":"Dar\u012bd\u0101r",
    "gn:population":0,
    "gn:timezone":"Asia/Tehran",
    "iso:country":"IR",
    "name:fas_x_preferred":[
        "\u062f\u0631\u06cc\u062f\u0627\u0631"
    ],
    "name:fas_x_variant":[
        "Dar\u012bd\u0101r"
    ],
    "wof:name":"Daridar",
    "wof:placetype":"locality"
},
  "geometry": {"coordinates":[62.80072,27.11201],"type":"Point"}
}