{
  "type": "Feature",
  "properties": {
    "gn:admin1_code":"42.0",
    "gn:asciiname":"Hasan Bolbol",
    "gn:country_code":"IR",
    "gn:dem":1450,
    "gn:feature_class":"P",
    "gn:feature_code":"PPL",
    "gn:name":"\u1e28asan Bolbol",
    "gn:population":0,
    "gn:timezone":"Asia/Tehran",
    "iso:country":"IR",
    "name:ara_x_preferred":[
        "\u062d\u0633\u0646 \u0628\u0644\u0628\u0644"
    ],
    "name:fas_x_preferred":[
        "\u062d\u0633\u0646 \u0628\u0644\u0628\u0644"
    ],
    "name:fas_x_variant":[
        "\u1e28asan Bolbol"
    ],
    "name:und_x_variant":[
        "\u1e28asan\u0101b\u0101d"
    ],
    "wof:name":"Hasan Bolbol",
    "wof:placetype":"locality"
},
  "geometry": {"coordinates":[60.002,35.52685],"type":"Point"}
}