{
  "type": "Feature",
  "properties": {
    "gn:admin1_code":"34",
    "gn:asciiname":"Lala'in",
    "gn:country_code":"IR",
    "gn:dem":1007,
    "gn:feature_class":"P",
    "gn:feature_code":"PPL",
    "gn:name":"L\u0101l\u0101\u2019\u012bn",
    "gn:population":0,
    "gn:timezone":"Asia/Tehran",
    "iso:country":"IR",
    "name:fas_x_preferred":[
        "\u0644\u0627\u0644\u0627\u0626\u064a\u0646"
    ],
    "name:fas_x_variant":[
        "L\u0101l\u0101\u2019\u012bn"
    ],
    "name:und_x_variant":[
        "\u012arala\u012bn",
        "L\u0101l\u0101n"
    ],
    "wof:name":"Lala'in",
    "wof:placetype":"locality"
},
  "geometry": {"coordinates":[50.31289,34.9073],"type":"Point"}
}