{
  "type": "Feature",
  "properties": {
    "gn:admin1_code":"13",
    "gn:asciiname":"Khanjarabad",
    "gn:country_code":"IR",
    "gn:dem":1603,
    "gn:feature_class":"P",
    "gn:feature_code":"PPL",
    "gn:name":"Khanjar\u0101b\u0101d",
    "gn:population":0,
    "gn:timezone":"Asia/Tehran",
    "iso:country":"IR",
    "name:fas_x_preferred":[
        "\u062e\u0646\u062c\u0631 \u0622\u0628\u0627\u062f"
    ],
    "name:fas_x_variant":[
        "Khanjar\u0101b\u0101d",
        "\u062e\u0646\u062c\u0631\u0622\u0628\u0627\u062f"
    ],
    "wof:name":"Khanjarabad",
    "wof:placetype":"locality"
},
  "geometry": {"coordinates":[47.51803,34.76835],"type":"Point"}
}