{
  "type": "Feature",
  "properties": {
    "gn:admin1_code":"23",
    "gn:asciiname":"Nazarabad",
    "gn:country_code":"IR",
    "gn:dem":1565,
    "gn:feature_class":"P",
    "gn:feature_code":"PPL",
    "gn:name":"Naz\u0327ar\u0101b\u0101d",
    "gn:population":0,
    "gn:timezone":"Asia/Tehran",
    "iso:country":"IR",
    "name:ara_x_preferred":[
        "\u0646\u0638\u0631 \u0623\u0628\u0627\u062f"
    ],
    "name:aze_x_preferred":[
        "N\u0259z\u0259rabad"
    ],
    "name:ceb_x_preferred":[
        "Naz\u0327ar\u0101b\u0101d"
    ],
    "name:fas_x_preferred":[
        "\u0646\u0638\u0631 \u0622\u0628\u0627\u062f"
    ],
    "name:fas_x_variant":[
        "Naz\u0327ar\u0101b\u0101d",
        "\u0646\u0638\u0631\u0622\u0628\u0627\u062f"
    ],
    "name:hin_x_preferred":[
        "\u0928\u091c\u093c\u0930\u093e\u092c\u093e\u0926"
    ],
    "name:ita_x_preferred":[
        "Nazarabad"
    ],
    "name:mlg_x_preferred":[
        "Nazarabad"
    ],
    "name:msa_x_preferred":[
        "Nazarabad"
    ],
    "name:pnb_x_preferred":[
        "\u0646\u0638\u0631\u0622\u0628\u0627\u062f"
    ],
    "name:pol_x_preferred":[
        "Nazarabad"
    ],
    "name:ron_x_preferred":[
        "Nazarabad"
    ],
    "name:rus_x_preferred":[
        "\u041d\u0430\u0437\u0430\u0440\u0430\u0431\u0430\u0434"
    ],
    "name:swe_x_preferred":[
        "Naz\u0327ar\u0101b\u0101d"
    ],
    "name:tgk_x_preferred":[
        "\u041d\u0430\u0437\u0430\u0440\u043e\u0431\u043e\u0434"
    ],
    "name:tur_x_preferred":[
        "Nezerabad"
    ],
    "name:urd_x_preferred":[
        "\u0646\u0638\u0631\u0622\u0628\u0627\u062f"
    ],
    "wof:name":"Nazarabad",
    "wof:placetype":"locality"
},
  "geometry": {"coordinates":[48.2114,33.8407],"type":"Point"}
}