{
  "type": "Feature",
  "properties": {
    "gn:admin1_code":"23",
    "gn:asciiname":"Nazarabad",
    "gn:country_code":"IR",
    "gn:dem":1565,
    "gn:feature_class":"P",
    "gn:feature_code":"PPL",
    "gn:name":"Naz\u0327ar\u0101b\u0101d",
    "gn:population":0,
    "gn:timezone":"Asia/Tehran",
    "iso:country":"IR",
    "name:fas_x_preferred":[
        "\u0646\u0638\u0631 \u0622\u0628\u0627\u062f"
    ],
    "name:fas_x_variant":[
        "Naz\u0327ar\u0101b\u0101d"
    ],
    "wof:name":"Nazarabad",
    "wof:placetype":"locality"
},
  "geometry": {"coordinates":[48.2114,33.8407],"type":"Point"}
}