{
  "type": "Feature",
  "properties": {
    "gn:admin1_code":"15",
    "gn:asciiname":"Hoseyn Begi",
    "gn:country_code":"IR",
    "gn:dem":8,
    "gn:feature_class":"P",
    "gn:feature_code":"PPL",
    "gn:name":"\u1e28oseyn Beg\u012b",
    "gn:population":0,
    "gn:timezone":"Asia/Tehran",
    "iso:country":"IR",
    "name:ara_x_preferred":[
        "\u062d\u0633\u064a\u0646 \u0628\u064a\u063a\u064a"
    ],
    "name:fas_x_preferred":[
        "\u1e28oseyn Beyg\u012b"
    ],
    "name:fas_x_variant":[
        "\u1e28oseyn Yag\u012b",
        "\u062d\u0633\u06cc\u0646 \u0628\u06cc\u06af\u06cc",
        "\u062d\u0633\u06cc\u0646 \u0628\u06af\u06cc"
    ],
    "name:und_x_variant":[
        "\u1e28oseyn Beg\u012b"
    ],
    "wof:name":"Hoseyn Begi",
    "wof:placetype":"locality"
},
  "geometry": {"coordinates":[48.74547000000001,30.69999],"type":"Point"}
}