{
  "type": "Feature",
  "properties": {
    "gn:admin1_code":"4.0",
    "gn:asciiname":"Deh-e Anushirvan",
    "gn:country_code":"IR",
    "gn:dem":485,
    "gn:feature_class":"P",
    "gn:feature_code":"PPL",
    "gn:name":"Deh-e An\u016bsh\u012brv\u0101n",
    "gn:population":0,
    "gn:timezone":"Asia/Tehran",
    "iso:country":"IR",
    "name:fas_x_preferred":[
        "\u062f\u0647 \u0627\u0646\u0648\u0634\u06cc\u0631\u0648\u0627\u0646"
    ],
    "name:fas_x_variant":[
        "An\u016bsh\u012brv\u0101n",
        "Deh-e An\u016bsh\u012brv\u0101n"
    ],
    "wof:name":"Deh-e Anushirvan",
    "wof:placetype":"locality"
},
  "geometry": {"coordinates":[61.7673,31.1049],"type":"Point"}
}