{
  "type": "Feature",
  "properties": {
    "gn:admin1_code":"1",
    "gn:asciiname":"Salamabad",
    "gn:country_code":"IR",
    "gn:dem":1401,
    "gn:feature_class":"P",
    "gn:feature_code":"PPL",
    "gn:name":"Sal\u0101m\u0101b\u0101d",
    "gn:population":0,
    "gn:timezone":"Asia/Tehran",
    "iso:country":"IR",
    "name:fas_x_preferred":[
        "\u0633\u0644\u0627\u0645 \u0622\u0628\u0627\u062f"
    ],
    "name:fas_x_variant":[
        "Esl\u0101m\u0101b\u0101d",
        "Sal\u0101m\u0101b\u0101d"
    ],
    "name:und_x_variant":[
        "Kh\u0101nlar"
    ],
    "wof:name":"Salamabad",
    "wof:placetype":"locality"
},
  "geometry": {"coordinates":[45.1711,37.0405],"type":"Point"}
}