{
  "type": "Feature",
  "properties": {
    "gn:admin1_code":"36",
    "gn:asciiname":"Kaj Kolah",
    "gn:country_code":"IR",
    "gn:dem":2100,
    "gn:feature_class":"P",
    "gn:feature_code":"PPL",
    "gn:name":"Kaj Kol\u0101h",
    "gn:population":0,
    "gn:timezone":"Asia/Tehran",
    "iso:country":"IR",
    "name:azb_x_preferred":[
        "\u06a9\u062c \u06a9\u0644\u0627\u0647"
    ],
    "name:fas_x_preferred":[
        "\u06a9\u062c \u06a9\u0644\u0627\u0647"
    ],
    "name:fas_x_variant":[
        "Kaj Kol\u0101h",
        "\u06a9\u062c\u200c\u06a9\u0644\u0627\u0647"
    ],
    "name:und_x_variant":[
        "K\u016bsh Qal\u2018eh",
        "Gach Kol\u0101h",
        "Kush Kalekh"
    ],
    "wof:name":"Kaj Kolah",
    "wof:placetype":"locality"
},
  "geometry": {"coordinates":[48.6894,36.6637],"type":"Point"}
}