{
  "type": "Feature",
  "properties": {
    "gn:admin1_code":"11",
    "gn:asciiname":"Qaf",
    "gn:cc2":"IR",
    "gn:country_code":"IR",
    "gn:dem":-9999,
    "gn:feature_class":"P",
    "gn:feature_code":"PPL",
    "gn:name":"Q\u0101f",
    "gn:population":0,
    "gn:timezone":"Asia/Tehran",
    "iso:country":"IR",
    "name:fas_x_preferred":[
        "\u0642\u0627\u0641"
    ],
    "name:fas_x_variant":[
        "\u063a\u0627\u0641",
        "Q\u0101f"
    ],
    "name:fra_x_preferred":[
        "Qaf"
    ],
    "name:ind_x_preferred":[
        "Qaf"
    ],
    "name:msa_x_preferred":[
        "Qaf"
    ],
    "name:spa_x_preferred":[
        "Qaf"
    ],
    "name:und_x_variant":[
        "Gh\u0101f"
    ],
    "wof:name":"Qaf",
    "wof:placetype":"locality"
},
  "geometry": {"coordinates":[52.68333000000001,27.28333],"type":"Point"}
}