{
  "type": "Feature",
  "properties": {
    "gn:admin1_code":"29",
    "gn:asciiname":"Lay-e Tir Kuh",
    "gn:country_code":"IR",
    "gn:dem":2462,
    "gn:feature_class":"P",
    "gn:feature_code":"PPL",
    "gn:name":"L\u0101y-e T\u012br K\u016bh",
    "gn:population":0,
    "gn:timezone":"Asia/Tehran",
    "iso:country":"IR",
    "name:fas_x_preferred":[
        "L\u0101y-e T\u012br K\u016bh"
    ],
    "wof:name":"Lay-e Tir Kuh",
    "wof:placetype":"locality"
},
  "geometry": {"coordinates":[55.22306,30.34139],"type":"Point"}
}