{
  "type": "Feature",
  "properties": {
    "gn:admin1_code":"16.0",
    "gn:asciiname":"Qaderabad",
    "gn:country_code":"IR",
    "gn:dem":1720,
    "gn:feature_class":"P",
    "gn:feature_code":"PPL",
    "gn:name":"Q\u0101der\u0101b\u0101d",
    "gn:population":0,
    "gn:timezone":"Asia/Tehran",
    "iso:country":"IR",
    "name:fas_x_preferred":[
        "\u062f\u0631\u0648\u06cc\u0627\u0646 \u0642\u0627\u062f\u0631 \u0622\u0628\u0627\u062f"
    ],
    "name:fas_x_variant":[
        "Darevey\u0101n-e Q\u0101der\u0101b\u0101d",
        "\u0642\u0627\u062f\u0631 \u0622\u0628\u0627\u062f",
        "\u062f\u0631\u0648\u064a\u0627\u0646"
    ],
    "name:und_x_variant":[
        "Q\u0101der\u0101b\u0101d",
        "Darevey\u0101n"
    ],
    "wof:name":"Qaderabad",
    "wof:placetype":"locality"
},
  "geometry": {"coordinates":[46.63065,35.49953],"type":"Point"}
}