{
  "type": "Feature",
  "properties": {
    "gn:admin1_code":"23",
    "gn:asciiname":"Qoroq",
    "gn:country_code":"IR",
    "gn:dem":1500,
    "gn:feature_class":"P",
    "gn:feature_code":"PPL",
    "gn:name":"Qoroq",
    "gn:population":0,
    "gn:timezone":"Asia/Tehran",
    "iso:country":"IR",
    "name:ceb_x_preferred":[
        "Qoroq"
    ],
    "name:fas_x_preferred":[
        "\u0642\u0631\u0642"
    ],
    "name:mzn_x_preferred":[
        "\u0642\u0631\u0642"
    ],
    "name:swe_x_preferred":[
        "Qoroq"
    ],
    "name:und_x_variant":[
        "Q\u016bruq",
        "Qoroq"
    ],
    "wof:name":"Qoroq",
    "wof:placetype":"locality"
},
  "geometry": {"coordinates":[48.9028,33.71791],"type":"Point"}
}