{
  "type": "Feature",
  "properties": {
    "gn:admin1_code":"26",
    "gn:asciiname":"Mazra`eh-ye Sadat",
    "gn:country_code":"IR",
    "gn:dem":1907,
    "gn:feature_class":"P",
    "gn:feature_code":"PPL",
    "gn:name":"Mazra\u2018eh-ye S\u0101d\u0101t",
    "gn:population":0,
    "gn:timezone":"Asia/Tehran",
    "iso:country":"IR",
    "name:fas_x_preferred":[
        "\u0645\u0632\u0631\u0639\u0647 \u0633\u0627\u062f\u0627\u062a"
    ],
    "name:und_x_variant":[
        "Mazra\u2018eh-ye S\u0101d\u0101t"
    ],
    "wof:name":"Mazra`eh-ye Sadat",
    "wof:placetype":"locality"
},
  "geometry": {"coordinates":[51.6284,35.85609],"type":"Point"}
}