{
  "type": "Feature",
  "properties": {
    "gn:admin1_code":"36",
    "gn:asciiname":"Shin",
    "gn:country_code":"IR",
    "gn:dem":1910,
    "gn:feature_class":"P",
    "gn:feature_code":"PPL",
    "gn:name":"Sh\u012bn",
    "gn:population":0,
    "gn:timezone":"Asia/Tehran",
    "iso:country":"IR",
    "name:fas_x_preferred":[
        "\u0634\u06cc\u0646"
    ],
    "name:fas_x_variant":[
        "\u0633\u0650\u0646",
        "Sh\u012bn"
    ],
    "name:und_x_variant":[
        "Sen"
    ],
    "wof:name":"Shin",
    "wof:placetype":"locality"
},
  "geometry": {"coordinates":[48.4149,36.20266],"type":"Point"}
}