{
  "type": "Feature",
  "properties": {
    "gn:admin1_code":"41.0",
    "gn:asciiname":"Lidar",
    "gn:country_code":"IR",
    "gn:dem":2070,
    "gn:feature_class":"P",
    "gn:feature_code":"PPL",
    "gn:name":"L\u012bdar",
    "gn:population":0,
    "gn:timezone":"Asia/Tehran",
    "iso:country":"IR",
    "name:fas_x_preferred":[
        "Kal\u0101t-e P\u0101kd\u0101r"
    ],
    "name:fas_x_variant":[
        "\u06a9\u0644\u0627\u062a \u067e\u0627\u06a9\u062f\u0627\u0631",
        "\u0644\u064a\u062f\u0631",
        "\u06a9\u0644\u0627\u062a\u0647 \u067e\u0627\u06cc \u06af\u062f\u0627\u0631"
    ],
    "name:und_x_variant":[
        "\u06a9\u0644\u0627\u062a \u067e\u0627\u06a9\u062f\u0627\u0631",
        "L\u012bdar",
        "Kal\u0101teh-ye P\u0101-ye God\u0101r"
    ],
    "wof:name":"Lidar",
    "wof:placetype":"locality"
},
  "geometry": {"coordinates":[59.2868,32.78058],"type":"Point"}
}