{
  "type": "Feature",
  "properties": {
    "gn:admin1_code":"41.0",
    "gn:asciiname":"Lidar",
    "gn:country_code":"IR",
    "gn:dem":2070,
    "gn:feature_class":"P",
    "gn:feature_code":"PPL",
    "gn:name":"L\u012bdar",
    "gn:population":0,
    "gn:timezone":"Asia/Tehran",
    "iso:country":"IR",
    "name:ara_x_preferred":[
        "\u0644\u064a\u062f\u0627\u0631"
    ],
    "name:bul_x_preferred":[
        "\u041b\u0438\u0434\u0430\u0440"
    ],
    "name:ces_x_preferred":[
        "Lidar"
    ],
    "name:cym_x_preferred":[
        "Lidar"
    ],
    "name:deu_x_preferred":[
        "Lidar"
    ],
    "name:est_x_preferred":[
        "Lidar"
    ],
    "name:fas_x_preferred":[
        "Kal\u0101t-e P\u0101kd\u0101r"
    ],
    "name:fas_x_variant":[
        "\u06a9\u0644\u0627\u062a \u067e\u0627\u06a9\u062f\u0627\u0631",
        "\u0644\u064a\u062f\u0631",
        "\u06a9\u0644\u0627\u062a\u0647 \u067e\u0627\u06cc \u06af\u062f\u0627\u0631",
        "\u0644\u06cc\u062f\u0627\u0631"
    ],
    "name:fin_x_preferred":[
        "Lidar"
    ],
    "name:fra_x_preferred":[
        "Lidar"
    ],
    "name:glg_x_preferred":[
        "Lidar"
    ],
    "name:heb_x_preferred":[
        "\u05dc\u05d9\u05d3\u05d0\u05e8"
    ],
    "name:hin_x_preferred":[
        "\u0932\u093f\u0921\u093e\u0930"
    ],
    "name:hrv_x_preferred":[
        "Lidar"
    ],
    "name:ita_x_preferred":[
        "Lidar"
    ],
    "name:kor_x_preferred":[
        "\ub808\uc774\uc800 \ub808\uc774\ub2e4"
    ],
    "name:nld_x_preferred":[
        "Lidar"
    ],
    "name:nno_x_preferred":[
        "Lidar"
    ],
    "name:pol_x_preferred":[
        "Lidar"
    ],
    "name:rus_x_preferred":[
        "\u041b\u0438\u0434\u0430\u0440"
    ],
    "name:tha_x_preferred":[
        "\u0e44\u0e25\u0e14\u0e32\u0e23\u0e4c"
    ],
    "name:ukr_x_preferred":[
        "\u041b\u0456\u0434\u0430\u0440"
    ],
    "name:und_x_variant":[
        "\u06a9\u0644\u0627\u062a \u067e\u0627\u06a9\u062f\u0627\u0631",
        "L\u012bdar",
        "Kal\u0101teh-ye P\u0101-ye God\u0101r"
    ],
    "name:vie_x_preferred":[
        "Lidar"
    ],
    "name:zho_x_preferred":[
        "\u5149\u5b66\u96f7\u8fbe"
    ],
    "wof:name":"Lidar",
    "wof:placetype":"locality"
},
  "geometry": {"coordinates":[59.2868,32.78058],"type":"Point"}
}