{
  "type": "Feature",
  "properties": {
    "gn:admin1_code":"3",
    "gn:asciiname":"Kori-ye Chahar Picheh",
    "gn:country_code":"IR",
    "gn:dem":1827,
    "gn:feature_class":"P",
    "gn:feature_code":"PPL",
    "gn:name":"Kor\u012b-ye Chah\u0101r P\u012bcheh",
    "gn:population":0,
    "gn:timezone":"Asia/Tehran",
    "iso:country":"IR",
    "name:ara_x_preferred":[
        "\u0643\u0631\u064a \u062a\u0634\u0647\u0627\u0631 \u0628\u0646\u064a\u062a\u0634\u0629"
    ],
    "name:ceb_x_preferred":[
        "Kor\u012b-ye Chah\u0101r P\u012bcheh"
    ],
    "name:fas_x_preferred":[
        "K\u016by-ye Chah\u0101r Bon\u012bsheh"
    ],
    "name:fas_x_variant":[
        "\u0643\u0648\u064a\u06cc \u0686\u064e\u0647\u0627\u0631 \u0628\u064f\u0646\u064a\u0634\u0650\u0647",
        "\u0643\u064e\u0631\u0651\u06cc \u0686\u064e\u0647\u0627\u0631 \u0628\u064f\u0646\u064a\u0634\u0650\u0647",
        "Kor\u012b-ye Chah\u0101r P\u012bcheh",
        "Kor\u012b Chah\u0101r B\u012bncheh",
        "\u0643\u064e\u0631\u0651\u06cc \u0686\u064e\u0647\u0627\u0631 \u0628\u064f\u0646\u064a\u0686\u0650\u0647",
        "\u0643\u064f\u0631\u06cc \u0686\u064e\u0647\u0627\u0631 \u0628\u064a\u0646\u0686\u0650\u0647",
        "\u06a9\u0631\u06cc \u0686\u0647\u0627\u0631 \u067e\u06cc\u0686\u0647",
        "\u06a9\u0631\u06cc \u0686\u0647\u0627\u0631\u0628\u0646\u06cc\u0686\u0647"
    ],
    "name:msa_x_preferred":[
        "Karri Chahar Bonicheh"
    ],
    "name:swe_x_preferred":[
        "Kor\u012b-ye Chah\u0101r P\u012bcheh"
    ],
    "name:und_x_variant":[
        "Karr\u012b Chah\u0101r Bon\u012bcheh",
        "Karr\u012b Chah\u0101r Bon\u012bsheh"
    ],
    "wof:name":"Kori-ye Chahar Picheh",
    "wof:placetype":"locality"
},
  "geometry": {"coordinates":[50.46368,31.9565],"type":"Point"}
}