{
  "type": "Feature",
  "properties": {
    "gn:admin1_code":"42.0",
    "gn:asciiname":"Kamaneh-ye Mohammad Khan",
    "gn:country_code":"IR",
    "gn:dem":685,
    "gn:feature_class":"P",
    "gn:feature_code":"PPL",
    "gn:name":"Kam\u0101neh-ye Mo\u1e29ammad Kh\u0101n",
    "gn:population":0,
    "gn:timezone":"Asia/Tehran",
    "iso:country":"IR",
    "name:fas_x_preferred":[
        "Kam\u0101neh-ye Mo\u1e29ammad Kh\u0101n"
    ],
    "name:und_x_variant":[
        "Kam\u0101neh-ye K\u016bchek"
    ],
    "wof:name":"Kamaneh-ye Mohammad Khan",
    "wof:placetype":"locality"
},
  "geometry": {"coordinates":[61.08444,34.98444],"type":"Point"}
}