{
  "type": "Feature",
  "properties": {
    "gn:admin1_code":"8",
    "gn:asciiname":"Lasavandan",
    "gn:country_code":"IR",
    "gn:dem":-7,
    "gn:feature_class":"P",
    "gn:feature_code":"PPL",
    "gn:name":"Las\u0101vand\u0101n",
    "gn:population":0,
    "gn:timezone":"Asia/Tehran",
    "iso:country":"IR",
    "name:fas_x_preferred":[
        "L\u012bs\u0101vand\u0101n"
    ],
    "name:fas_x_variant":[
        "\u0644\u0633\u0627\u0648\u0646\u062f\u0627\u0646",
        "\u06af\u0648\u0631\u0627\u0628 \u0644\u0634\u0627\u0648\u0646\u062f\u0627\u0646"
    ],
    "name:und_x_variant":[
        "Las\u0101vand\u0101n",
        "G\u016br\u0101b-e L\u012bsh\u0101vand\u0101n",
        "G\u016br\u0101b-e Lash\u0101vand\u0101n"
    ],
    "wof:name":"Lasavandan",
    "wof:placetype":"locality"
},
  "geometry": {"coordinates":[49.42986,37.27535],"type":"Point"}
}