{
  "type": "Feature",
  "properties": {
    "gn:admin1_code":"7.0",
    "gn:asciiname":"Rostamabad",
    "gn:country_code":"IR",
    "gn:dem":764,
    "gn:feature_class":"P",
    "gn:feature_code":"PPL",
    "gn:name":"Rostam\u0101b\u0101d",
    "gn:population":0,
    "gn:timezone":"Asia/Tehran",
    "iso:country":"IR",
    "name:fas_x_preferred":[
        "Rostam\u0101b\u0101d"
    ],
    "name:fas_x_variant":[
        "\u0631\u0633\u062a\u0645 \u0622\u0628\u0627\u062f",
        "\u0631\u0633\u062a\u0645\u200c\u0622\u0628\u0627\u062f"
    ],
    "name:und_x_variant":[
        "\u0631\u0633\u062a\u0645 \u0622\u0628\u0627\u062f"
    ],
    "wof:name":"Rostamabad",
    "wof:placetype":"locality"
},
  "geometry": {"coordinates":[51.54019,29.7482],"type":"Point"}
}