{
  "type": "Feature",
  "properties": {
    "gn:admin1_code":"30",
    "gn:asciiname":"Dashli Qal`eh",
    "gn:country_code":"IR",
    "gn:dem":1482,
    "gn:feature_class":"P",
    "gn:feature_code":"PPL",
    "gn:name":"D\u0101shl\u012b Qal`eh",
    "gn:population":0,
    "gn:timezone":"Asia/Tehran",
    "iso:country":"IR",
    "wof:name":"Dashli Qal`eh",
    "wof:placetype":"locality"
},
  "geometry": {"coordinates":[57.23333,38.11667],"type":"Point"}
}