{
  "type": "Feature",
  "properties": {
    "gn:admin1_code":"7.0",
    "gn:asciiname":"`Aliabad-e `Olya",
    "gn:country_code":"IR",
    "gn:dem":1737,
    "gn:feature_class":"P",
    "gn:feature_code":"PPL",
    "gn:name":"\u2018Al\u012b\u0101b\u0101d-e \u2018Oly\u0101",
    "gn:population":0,
    "gn:timezone":"Asia/Tehran",
    "iso:country":"IR",
    "name:fas_x_preferred":[
        "\u0639\u0644\u06cc \u0622\u0628\u0627\u062f \u06a9\u0627\u0645\u0641\u06cc\u0631\u0648\u0632 \u0639\u0644\u06cc\u0627"
    ],
    "name:fas_x_variant":[
        "\u2018Al\u012b\u0101b\u0101d-e B\u0101l\u0101",
        "\u2018Al\u012b\u0101b\u0101d-e K\u0101mf\u012br\u016bz-e \u2018Oly\u0101",
        "\u0639\u0644\u06cc \u0622\u0628\u0627\u062f \u0639\u0644\u06cc\u0627"
    ],
    "name:und_x_variant":[
        "\u2018Al\u012b\u0101b\u0101d",
        "\u2018Al\u012b\u0101b\u0101d-e \u2018Oly\u0101"
    ],
    "wof:name":"`Aliabad-e `Olya",
    "wof:placetype":"locality"
},
  "geometry": {"coordinates":[52.18361,30.36294],"type":"Point"}
}