{
  "type": "Feature",
  "properties": {
    "gn:admin1_code":"23",
    "gn:asciiname":"Jelowgir",
    "gn:country_code":"IR",
    "gn:dem":2188,
    "gn:feature_class":"P",
    "gn:feature_code":"PPL",
    "gn:name":"Jelowg\u012br",
    "gn:population":0,
    "gn:timezone":"Asia/Tehran",
    "iso:country":"IR",
    "name:fas_x_preferred":[
        "K\u012bvarz-e Jelowg\u012br"
    ],
    "name:fas_x_variant":[
        "\u0643\u064a\u0648\u0631\u0632 \u062c\u0644\u0648\u06af\u064a\u0631",
        "\u062c\u0644\u0648\u06af\u06cc\u0631"
    ],
    "name:und_x_variant":[
        "Jelowg\u012br"
    ],
    "wof:name":"Jelowgir",
    "wof:placetype":"locality"
},
  "geometry": {"coordinates":[49.71997,33.13865],"type":"Point"}
}