{
  "type": "Feature",
  "properties": {
    "gn:admin1_code":"11",
    "gn:asciiname":"Poshtkuh",
    "gn:country_code":"IR",
    "gn:dem":19,
    "gn:feature_class":"P",
    "gn:feature_code":"PPL",
    "gn:name":"Poshtk\u016bh",
    "gn:population":0,
    "gn:timezone":"Asia/Tehran",
    "iso:country":"IR",
    "name:fas_x_preferred":[
        "\u067e\u0634\u062a\u0643\u0648\u0647"
    ],
    "name:fas_x_variant":[
        "\u067e\u064f\u0634\u062a \u0643\u064f\u0651\u0647",
        "\u067e\u0634\u062a \u0643\u0648\u0647",
        "Poshtk\u016bh"
    ],
    "name:und_x_variant":[
        "Posht Kooh",
        "Posht K\u016bh"
    ],
    "wof:name":"Poshtkuh",
    "wof:placetype":"locality"
},
  "geometry": {"coordinates":[56.7239,27.3579],"type":"Point"}
}