{
  "type": "Feature",
  "properties": {
    "gn:admin1_code":"29",
    "gn:asciiname":"Mansuriyeh",
    "gn:country_code":"IR",
    "gn:dem":586,
    "gn:feature_class":"P",
    "gn:feature_code":"PPL",
    "gn:name":"Man\u015f\u016br\u012byeh",
    "gn:population":0,
    "gn:timezone":"Asia/Tehran",
    "iso:country":"IR",
    "name:ara_x_preferred":[
        "\u0645\u0646\u0635\u0648\u0631\u064a\u0629"
    ],
    "name:fas_x_preferred":[
        "Man\u015f\u016br\u012byeh"
    ],
    "name:fas_x_variant":[
        "\u0645\u0646\u0635\u0648\u0631\u06cc\u0647"
    ],
    "wof:name":"Mansuriyeh",
    "wof:placetype":"locality"
},
  "geometry": {"coordinates":[57.83333,28.45],"type":"Point"}
}