{
  "type": "Feature",
  "properties": {
    "gn:admin1_code":"33.0",
    "gn:asciiname":"Zaker",
    "gn:country_code":"IR",
    "gn:dem":1736,
    "gn:feature_class":"P",
    "gn:feature_code":"PPL",
    "gn:name":"Z\u0304\u0101ker",
    "gn:population":0,
    "gn:timezone":"Asia/Tehran",
    "iso:country":"IR",
    "name:fas_x_preferred":[
        "\u0630\u0627\u06a9\u0631"
    ],
    "name:fas_x_variant":[
        "Z\u0304\u0101ker"
    ],
    "name:und_x_variant":[
        "Zakir"
    ],
    "wof:name":"Zaker",
    "wof:placetype":"locality"
},
  "geometry": {"coordinates":[48.03914,37.76575],"type":"Point"}
}