{
  "type": "Feature",
  "properties": {
    "gn:admin1_code":"16",
    "gn:asciiname":"Sheykh `Attar",
    "gn:country_code":"IR",
    "gn:dem":1570,
    "gn:feature_class":"P",
    "gn:feature_code":"PPL",
    "gn:name":"Sheykh \u2018A\u0163\u0163\u0101r",
    "gn:population":0,
    "gn:timezone":"Asia/Tehran",
    "iso:country":"IR",
    "name:fas_x_preferred":[
        "\u0634\u0650\u064a\u062e"
    ],
    "name:fas_x_variant":[
        "\u0634\u06cc\u062e \u0639\u0637\u0627\u0631",
        "Sheykh \u2018A\u0163\u0163\u0101r"
    ],
    "name:und_x_variant":[
        "Shaikh Att\u0101r",
        "Sheykh"
    ],
    "wof:name":"Sheykh `Attar",
    "wof:placetype":"locality"
},
  "geometry": {"coordinates":[46.4663,35.5134],"type":"Point"}
}