{
  "type": "Feature",
  "properties": {
    "gn:admin1_code":"42.0",
    "gn:asciiname":"Esfaraq",
    "gn:country_code":"IR",
    "gn:dem":1189,
    "gn:feature_class":"P",
    "gn:feature_code":"PPL",
    "gn:name":"Esfaraq",
    "gn:population":0,
    "gn:timezone":"Asia/Tehran",
    "iso:country":"IR",
    "name:fas_x_preferred":[
        "\u0627\u0633\u0641\u0631\u0642"
    ],
    "wof:name":"Esfaraq",
    "wof:placetype":"locality"
},
  "geometry": {"coordinates":[60.02477,33.51028],"type":"Point"}
}