{
  "type": "Feature",
  "properties": {
    "gn:admin1_code":"41",
    "gn:asciiname":"Karsunak",
    "gn:country_code":"IR",
    "gn:dem":969,
    "gn:feature_class":"P",
    "gn:feature_code":"PPL",
    "gn:name":"Kars\u016bnak",
    "gn:population":0,
    "gn:timezone":"Asia/Tehran",
    "iso:country":"IR",
    "name:fas_x_preferred":[
        "\u06a9\u0631\u0633\u0648\u0646\u06a9"
    ],
    "name:fas_x_variant":[
        "Kars\u016bnak"
    ],
    "wof:name":"Karsunak",
    "wof:placetype":"locality"
},
  "geometry": {"coordinates":[60.7066,32.09476],"type":"Point"}
}