{
  "type": "Feature",
  "properties": {
    "gn:admin1_code":"35.0",
    "gn:asciiname":"Soleyman Mahalleh",
    "gn:country_code":"IR",
    "gn:dem":268,
    "gn:feature_class":"P",
    "gn:feature_code":"PPL",
    "gn:name":"Soleym\u0101n Ma\u1e29alleh",
    "gn:population":0,
    "gn:timezone":"Asia/Tehran",
    "iso:country":"IR",
    "name:fas_x_preferred":[
        "Soleym\u0101n Ma\u1e29alleh"
    ],
    "name:fas_x_variant":[
        "\u0633\u0644\u06cc\u0645\u0627\u0646 \u0645\u062d\u0644\u0647"
    ],
    "name:und_x_variant":[
        "\u0633\u0644\u06cc\u0645\u0627\u0646 \u0645\u062d\u0644\u0647"
    ],
    "wof:name":"Soleyman Mahalleh",
    "wof:placetype":"locality"
},
  "geometry": {"coordinates":[50.89484,36.72449],"type":"Point"}
}