{
  "type": "Feature",
  "properties": {
    "gn:admin1_code":"37",
    "gn:asciiname":"Arkh-e Kuchak",
    "gn:country_code":"IR",
    "gn:dem":-17,
    "gn:feature_class":"P",
    "gn:feature_code":"PPL",
    "gn:name":"\u0100rkh-e K\u016bchak",
    "gn:population":0,
    "gn:timezone":"Asia/Tehran",
    "iso:country":"IR",
    "name:ceb_x_preferred":[
        "Arkh-e K\u016bchek"
    ],
    "name:fas_x_preferred":[
        "\u0627\u0631\u062e \u0643\u0648\u0686\u06a9"
    ],
    "name:fas_x_variant":[
        "Arkh-e K\u016bchek",
        "\u0622\u0631\u062e \u06a9\u0648\u0686\u06a9",
        "\u0627\u0631\u062e \u06a9\u0648\u0686\u06a9"
    ],
    "name:msa_x_preferred":[
        "Arkh-e Kuchek"
    ],
    "name:swe_x_preferred":[
        "Arkh-e K\u016bchek"
    ],
    "name:und_x_variant":[
        "\u0100rkh-e K\u016bchak"
    ],
    "wof:name":"Arkh-e Kuchak",
    "wof:placetype":"locality"
},
  "geometry": {"coordinates":[54.2526,36.95882],"type":"Point"}
}