{
  "type": "Feature",
  "properties": {
    "gn:admin1_code":"4",
    "gn:asciiname":"Zebrabad",
    "gn:country_code":"IR",
    "gn:dem":864,
    "gn:feature_class":"P",
    "gn:feature_code":"PPL",
    "gn:name":"Z\u0327ebr\u0101b\u0101d",
    "gn:population":0,
    "gn:timezone":"Asia/Tehran",
    "iso:country":"IR",
    "name:fas_x_preferred":[
        "Z\u0327ebr\u0101b\u0101d"
    ],
    "wof:name":"Zebrabad",
    "wof:placetype":"locality"
},
  "geometry": {"coordinates":[59.98333,28.46667],"type":"Point"}
}