{
  "type": "Feature",
  "properties": {
    "gn:admin1_code":"13",
    "gn:asciiname":"Baktar-e Sofla",
    "gn:country_code":"IR",
    "gn:dem":1924,
    "gn:feature_class":"P",
    "gn:feature_code":"PPL",
    "gn:name":"Baktar-e Sofl\u00e1",
    "gn:population":0,
    "gn:timezone":"Asia/Tehran",
    "iso:country":"IR",
    "name:fas_x_preferred":[
        "\u0628\u06a9\u062a\u0631 \u0633\u0641\u0644\u06cc"
    ],
    "name:fas_x_variant":[
        "Baktar-e Sofl\u00e1"
    ],
    "name:und_x_variant":[
        "Baktar-e P\u0101\u2019\u012bn",
        "Baktar"
    ],
    "wof:name":"Baktar-e Sofla",
    "wof:placetype":"locality"
},
  "geometry": {"coordinates":[47.58355,34.64108],"type":"Point"}
}