{
  "type": "Feature",
  "properties": {
    "gn:admin1_code":"11",
    "gn:asciiname":"Mohammad Kahuri",
    "gn:country_code":"IR",
    "gn:dem":527,
    "gn:feature_class":"P",
    "gn:feature_code":"PPLF",
    "gn:name":"Mo\u1e29ammad Kah\u016br\u012b",
    "gn:population":0,
    "gn:timezone":"Asia/Tehran",
    "iso:country":"IR",
    "name:fas_x_preferred":[
        "\u0645\u064f\u062d\u064e\u0645\u064e\u0651\u062f \u0643\u064e\u0647\u0648\u0631\u06cc"
    ],
    "name:fas_x_variant":[
        "Mo\u1e29ammad Kah\u016br\u012b"
    ],
    "wof:name":"Mohammad Kahuri",
    "wof:placetype":"locality"
},
  "geometry": {"coordinates":[56.00167,27.63306],"type":"Point"}
}