{
  "type": "Feature",
  "properties": {
    "gn:admin1_code":"7",
    "gn:asciiname":"Cham Bolbol",
    "gn:country_code":"IR",
    "gn:dem":751,
    "gn:feature_class":"P",
    "gn:feature_code":"PPL",
    "gn:name":"Cham Bolbol",
    "gn:population":0,
    "gn:timezone":"Asia/Tehran",
    "iso:country":"IR",
    "name:ara_x_preferred":[
        "\u062a\u0634\u0645 \u0628\u0644\u0628\u0644"
    ],
    "name:ceb_x_preferred":[
        "Cham Bolbol"
    ],
    "name:fas_x_preferred":[
        "\u062a\u064e\u0646\u06af\u0650 \u0628\u064a\u0631\u064a\u0645"
    ],
    "name:fas_x_variant":[
        "\u0686\u0645 \u0628\u0644\u0628\u0644"
    ],
    "name:swe_x_preferred":[
        "Cham Bolbol"
    ],
    "name:und_x_variant":[
        "Tang-e B\u012br\u012bm",
        "\u0686\u0645 \u0628\u0644\u0628\u0644",
        "Cham Bolbol"
    ],
    "wof:name":"Cham Bolbol",
    "wof:placetype":"locality"
},
  "geometry": {"coordinates":[51.24009,30.31731],"type":"Point"}
}