{
  "type": "Feature",
  "properties": {
    "gn:admin1_code":"35.0",
    "gn:asciiname":"Qadi Mahalleh",
    "gn:country_code":"IR",
    "gn:dem":-7,
    "gn:feature_class":"P",
    "gn:feature_code":"PPL",
    "gn:name":"Q\u0101d\u012b Ma\u1e29alleh",
    "gn:population":0,
    "gn:timezone":"Asia/Tehran",
    "iso:country":"IR",
    "name:fas_x_preferred":[
        "\u0642\u0627\u062f\u06cc \u0645\u062d\u0644\u0647"
    ],
    "name:fas_x_variant":[
        "Q\u0101d\u012b Ma\u1e29alleh"
    ],
    "wof:name":"Qadi Mahalleh",
    "wof:placetype":"locality"
},
  "geometry": {"coordinates":[52.93527,36.63374],"type":"Point"}
}