{
  "type": "Feature",
  "properties": {
    "gn:admin1_code":"32.0",
    "gn:asciiname":"Qeshlaq-e Havar",
    "gn:country_code":"IR",
    "gn:dem":195,
    "gn:feature_class":"P",
    "gn:feature_code":"PPL",
    "gn:name":"Qeshl\u0101q-e H\u0101v\u0101r",
    "gn:population":0,
    "gn:timezone":"Asia/Tehran",
    "iso:country":"IR",
    "name:fas_x_preferred":[
        "\u0642\u0634\u0644\u0627\u0642 \u0647\u0627\u0648\u0627\u0631"
    ],
    "name:fas_x_variant":[
        "Qeshl\u0101q-e H\u0101v\u0101r"
    ],
    "wof:name":"Qeshlaq-e Havar",
    "wof:placetype":"locality"
},
  "geometry": {"coordinates":[48.0461,39.4258],"type":"Point"}
}