{
  "type": "Feature",
  "properties": {
    "gn:admin1_code":"35.0",
    "gn:asciiname":"Tarsi Kola",
    "gn:country_code":"IR",
    "gn:dem":62,
    "gn:feature_class":"P",
    "gn:feature_code":"PPL",
    "gn:name":"\u0162\u0101rs\u012b Kol\u0101",
    "gn:population":0,
    "gn:timezone":"Asia/Tehran",
    "iso:country":"IR",
    "name:fas_x_preferred":[
        "\u0637\u064e\u0631\u0633\u06cc \u0643\u064f\u0644\u0627"
    ],
    "name:fas_x_variant":[
        "\u0637\u064e\u0631\u0633\u06cc \u0643\u064e\u0644\u0627",
        "\u0162ars\u012b Kol\u0101",
        "\u0162\u0101rs\u012b Kol\u0101",
        "\u0637\u0627\u0631\u0633\u06cc \u0643\u0644\u0627"
    ],
    "name:und_x_variant":[
        "\u0162ars\u012b Kal\u0101"
    ],
    "wof:name":"Tarsi Kola",
    "wof:placetype":"locality"
},
  "geometry": {"coordinates":[52.78402,36.43731],"type":"Point"}
}