{
  "type": "Feature",
  "properties": {
    "gn:admin1_code":"9",
    "gn:asciiname":"Pisijan",
    "gn:country_code":"IR",
    "gn:dem":2020,
    "gn:feature_class":"P",
    "gn:feature_code":"PPL",
    "gn:name":"P\u012bs\u012bj\u0101n",
    "gn:population":0,
    "gn:timezone":"Asia/Tehran",
    "iso:country":"IR",
    "name:ara_x_preferred":[
        "\u0641\u0633\u064a\u062c\u0627\u0646"
    ],
    "name:ceb_x_preferred":[
        "P\u012bs\u012bj\u0101n"
    ],
    "name:fas_x_preferred":[
        "\u0641\u0650\u0633\u064a\u062c\u0627\u0646"
    ],
    "name:fas_x_variant":[
        "\u0641\u064e\u0633\u064a\u062c\u0627\u0646",
        "\u067e\u064a\u0633\u064a\u062c\u0627\u0646",
        "Fes\u012bj\u0101n",
        "P\u012bs\u012bj\u0101n",
        "\u067e\u06cc \u0633\u06cc \u062c\u0627\u0646",
        "\u0641\u0633\u06cc\u062c\u0627\u0646"
    ],
    "name:msa_x_preferred":[
        "Fasijan"
    ],
    "name:swe_x_preferred":[
        "P\u012bs\u012bj\u0101n"
    ],
    "name:und_x_variant":[
        "Fas\u012bj\u0101n"
    ],
    "wof:name":"Pisijan",
    "wof:placetype":"locality"
},
  "geometry": {"coordinates":[48.30472,34.83664],"type":"Point"}
}