{
  "type": "Feature",
  "properties": {
    "gn:admin1_code":"42.0",
    "gn:asciiname":"Mazra`eh-ye Garab",
    "gn:country_code":"IR",
    "gn:dem":1355,
    "gn:feature_class":"P",
    "gn:feature_code":"PPL",
    "gn:name":"Mazra\u2018eh-ye Gar\u0101b",
    "gn:population":0,
    "gn:timezone":"Asia/Tehran",
    "iso:country":"IR",
    "name:fas_x_preferred":[
        "Gar\u016b"
    ],
    "name:fas_x_variant":[
        "Gar\u0101b",
        "\u06af\u0631\u0648",
        "\u0645\u0632\u0631\u0639\u0647 \u06af\u0631\u0622\u0628"
    ],
    "name:und_x_variant":[
        "Mazra\u2018eh-ye Gar\u0101b"
    ],
    "wof:name":"Mazra`eh-ye Garab",
    "wof:placetype":"locality"
},
  "geometry": {"coordinates":[58.0904,36.6468],"type":"Point"}
}