{
  "type": "Feature",
  "properties": {
    "gn:admin1_code":"11",
    "gn:asciiname":"Koohi",
    "gn:country_code":"IR",
    "gn:dem":15,
    "gn:feature_class":"P",
    "gn:feature_code":"PPL",
    "gn:name":"Koohi",
    "gn:population":0,
    "gn:timezone":"Asia/Tehran",
    "iso:country":"IR",
    "name:ara_x_preferred":[
        "\u06a9\u0648\u0647\u064a"
    ],
    "name:fas_x_preferred":[
        "\u0643\u0648\u0647\u06cc"
    ],
    "name:fas_x_variant":[
        "K\u016bh\u012b",
        "\u06a9\u0648\u0647\u06cc"
    ],
    "name:msa_x_preferred":[
        "Kuhi"
    ],
    "wof:name":"Koohi",
    "wof:placetype":"locality"
},
  "geometry": {"coordinates":[54.97227,26.62428],"type":"Point"}
}