{
  "type": "Feature",
  "properties": {
    "gn:admin1_code":"36",
    "gn:asciiname":"Bigam Agha",
    "gn:country_code":"IR",
    "gn:dem":1887,
    "gn:feature_class":"P",
    "gn:feature_code":"PPL",
    "gn:name":"B\u012bgam \u0100gh\u0101",
    "gn:population":0,
    "gn:timezone":"Asia/Tehran",
    "iso:country":"IR",
    "name:fas_x_preferred":[
        "\u0628\u0650\u06af\u064a\u0645 \u0622\u0642\u0627"
    ],
    "name:fas_x_variant":[
        "\u0628\u0650\u064a\u06af\u064f\u0645 \u0622\u0642\u0627",
        "\u0628\u064e\u06af\u064f\u0645 \u0622\u0642\u0627",
        "\u0628\u064e\u06af\u064f\u0645",
        "\u0628\u06af\u06cc\u0645 \u0622\u063a\u0627",
        "Beg\u012bm \u0100q\u0101",
        "Beg\u012bm \u0100gh\u0101",
        "\u0628\u06cc\u06af\u0645 \u0622\u063a\u0627"
    ],
    "name:und_x_variant":[
        "Bagom \u0100q\u0101",
        "Pa yi Mega",
        "Bagom",
        "Beygom \u0100q\u0101",
        "B\u012bgam \u0100gh\u0101"
    ],
    "wof:name":"Bigam Agha",
    "wof:placetype":"locality"
},
  "geometry": {"coordinates":[48.48432,35.9128],"type":"Point"}
}