{
  "type": "Feature",
  "properties": {
    "gn:admin1_code":"15.0",
    "gn:asciiname":"Abu `Arabid",
    "gn:country_code":"IR",
    "gn:dem":6,
    "gn:feature_class":"P",
    "gn:feature_code":"PPL",
    "gn:name":"Ab\u016b \u2018Ar\u0101b\u012bd",
    "gn:population":0,
    "gn:timezone":"Asia/Tehran",
    "iso:country":"IR",
    "name:fas_x_preferred":[
        "Ab\u016b \u2018Arb\u012bdeh"
    ],
    "name:fas_x_variant":[
        "\u0627\u0628\u0648 \u0639\u0631\u0628\u06cc\u062f\u0647",
        "Ab\u016b \u2018Ar\u0101b\u012bd",
        "\u0627\u0628\u0648 \u0639\u0631\u0627\u0628\u06cc\u062f"
    ],
    "wof:name":"Abu `Arabid",
    "wof:placetype":"locality"
},
  "geometry": {"coordinates":[48.62514,30.76859],"type":"Point"}
}