{
  "type": "Feature",
  "properties": {
    "gn:admin1_code":"8",
    "gn:asciiname":"Zarkolam",
    "gn:country_code":"IR",
    "gn:dem":12,
    "gn:feature_class":"P",
    "gn:feature_code":"PPL",
    "gn:name":"Zarkol\u0101m",
    "gn:population":0,
    "gn:timezone":"Asia/Tehran",
    "iso:country":"IR",
    "name:fas_x_preferred":[
        "Zarkol\u0101m"
    ],
    "name:fas_x_variant":[
        "\u0632\u0631\u06a9\u0644\u0627\u0645"
    ],
    "wof:name":"Zarkolam",
    "wof:placetype":"locality"
},
  "geometry": {"coordinates":[50.32006,37.07301],"type":"Point"}
}