{
  "type": "Feature",
  "properties": {
    "gn:admin1_code":"13",
    "gn:asciiname":"Kalah Hu",
    "gn:country_code":"IR",
    "gn:dem":1465,
    "gn:feature_class":"P",
    "gn:feature_code":"PPL",
    "gn:name":"Kalah H\u016b",
    "gn:population":0,
    "gn:timezone":"Asia/Tehran",
    "iso:country":"IR",
    "name:fas_x_preferred":[
        "\u06a9\u0644\u0647 \u0647\u0648"
    ],
    "name:fas_x_variant":[
        "Kalah H\u016b"
    ],
    "wof:name":"Kalah Hu",
    "wof:placetype":"locality"
},
  "geometry": {"coordinates":[47.4229,34.1369],"type":"Point"}
}