{
  "type": "Feature",
  "properties": {
    "gn:admin1_code":"35.0",
    "gn:asciiname":"Salimabad",
    "gn:country_code":"IR",
    "gn:dem":178,
    "gn:feature_class":"P",
    "gn:feature_code":"PPL",
    "gn:name":"Sal\u012bm\u0101b\u0101d",
    "gn:population":0,
    "gn:timezone":"Asia/Tehran",
    "iso:country":"IR",
    "name:fas_x_preferred":[
        "\u0633\u0644\u064a\u0645 \u0622\u0628\u0627\u062f"
    ],
    "name:fas_x_variant":[
        "\u0633\u0644\u064a\u0645 \u0622\u0628\u0627\u062f \u067e\u0627\u0626\u064a\u0646"
    ],
    "name:und_x_variant":[
        "Sal\u012bm\u0101b\u0101d",
        "Sal\u012bm\u0101b\u0101d-e P\u0101\u2019\u012bn"
    ],
    "wof:name":"Salimabad",
    "wof:placetype":"locality"
},
  "geometry": {"coordinates":[50.79256,36.7832],"type":"Point"}
}