{
  "type": "Feature",
  "properties": {
    "gn:admin1_code":"23.0",
    "gn:asciiname":"Chahzal",
    "gn:country_code":"IR",
    "gn:dem":1383,
    "gn:feature_class":"P",
    "gn:feature_code":"PPL",
    "gn:name":"Chahz\u0101l",
    "gn:population":0,
    "gn:timezone":"Asia/Tehran",
    "iso:country":"IR",
    "name:ceb_x_preferred":[
        "Chahz\u0101l"
    ],
    "name:fas_x_preferred":[
        "Chaz\u0101l"
    ],
    "name:fas_x_variant":[
        "Chehz\u0101l",
        "Chahz\u0101l",
        "\u0686\u0632\u0627\u0644",
        "\u0686\u0647\u0632\u0627\u0644"
    ],
    "name:swe_x_preferred":[
        "Chahz\u0101l"
    ],
    "name:und_x_variant":[
        "\u0686\u0632\u0627\u0644"
    ],
    "wof:name":"Chahzal",
    "wof:placetype":"locality"
},
  "geometry": {"coordinates":[48.4749,33.3921],"type":"Point"}
}