{
  "type": "Feature",
  "properties": {
    "gn:admin1_code":"7",
    "gn:asciiname":"Tal-e Kohneh",
    "gn:cc2":"IR",
    "gn:country_code":"IR",
    "gn:dem":801,
    "gn:feature_class":"P",
    "gn:feature_code":"PPL",
    "gn:name":"Tal-e Kohneh",
    "gn:population":0,
    "gn:timezone":"Asia/Tehran",
    "iso:country":"IR",
    "name:und_x_variant":[
        "Tol-e Khoneh"
    ],
    "wof:name":"Tal-e Kohneh",
    "wof:placetype":"locality"
},
  "geometry": {"coordinates":[51.41306,30.25528],"type":"Point"}
}