{
  "type": "Feature",
  "properties": {
    "gn:admin1_code":"37",
    "gn:asciiname":"Qarah Ternav",
    "gn:country_code":"IR",
    "gn:dem":548,
    "gn:feature_class":"P",
    "gn:feature_code":"PPL",
    "gn:name":"Qarah Tern\u0101v",
    "gn:population":0,
    "gn:timezone":"Asia/Tehran",
    "iso:country":"IR",
    "name:fas_x_preferred":[
        "Kech\u012b S\u016b"
    ],
    "name:fas_x_variant":[
        "\u06a9\u0686\u06cc \u0633\u0648",
        "\u0642\u0631\u0647 \u062a\u0631\u0646\u0627\u0648",
        "\u06a9\u0686 \u0633\u0648 \u067e\u0627\u0626\u064a\u0646"
    ],
    "name:und_x_variant":[
        "Qarah Tern\u0101v",
        "Kech-e S\u016b-ye P\u0101\u2019\u012bn"
    ],
    "wof:name":"Qarah Ternav",
    "wof:placetype":"locality"
},
  "geometry": {"coordinates":[55.47823,37.74296],"type":"Point"}
}