{
  "type": "Feature",
  "properties": {
    "gn:admin1_code":"8",
    "gn:asciiname":"Kharapu",
    "gn:cc2":"IR",
    "gn:country_code":"IR",
    "gn:dem":1662,
    "gn:feature_class":"P",
    "gn:feature_code":"PPL",
    "gn:name":"Kharap\u016b",
    "gn:population":0,
    "gn:timezone":"Asia/Tehran",
    "iso:country":"IR",
    "name:fas_x_preferred":[
        "Kharap\u016b"
    ],
    "name:fas_x_variant":[
        "\u062e\u0631\u0645\u200c\u06a9\u0648\u0647"
    ],
    "name:glk_x_preferred":[
        "\u062e\u0631\u0645\u06a9\u0648\u0647"
    ],
    "name:msa_x_preferred":[
        "Kharehpu"
    ],
    "name:ukr_x_preferred":[
        "\u0425\u0430\u0440\u0435-\u041f\u0443"
    ],
    "name:und_x_variant":[
        "Kharpu",
        "Kharpooh",
        "Kharehp\u016b",
        "Khar\u016b"
    ],
    "wof:name":"Kharapu",
    "wof:placetype":"locality"
},
  "geometry": {"coordinates":[49.88861,36.7325],"type":"Point"}
}