{
  "type": "Feature",
  "properties": {
    "gn:admin1_code":"8",
    "gn:asciiname":"Vajargah",
    "gn:country_code":"IR",
    "gn:dem":9,
    "gn:feature_class":"P",
    "gn:feature_code":"PPL",
    "gn:name":"V\u0101j\u0101rg\u0101h",
    "gn:population":0,
    "gn:timezone":"Asia/Tehran",
    "iso:country":"IR",
    "name:ara_x_preferred":[
        "\u0648\u0627\u062c\u0627\u0631\u063a\u0627\u0647"
    ],
    "name:aze_x_preferred":[
        "Vacargah"
    ],
    "name:ceb_x_preferred":[
        "V\u0101j\u0101rg\u0101h"
    ],
    "name:fas_x_preferred":[
        "V\u0101j\u0101rg\u0101h"
    ],
    "name:fas_x_variant":[
        "\u0648\u0627\u062c\u0627\u0631\u06af\u0627\u0647",
        "Ownd\u012bm Sar\u0101"
    ],
    "name:mlg_x_preferred":[
        "Vajargah"
    ],
    "name:msa_x_preferred":[
        "Vajargah"
    ],
    "name:swe_x_preferred":[
        "V\u0101j\u0101rg\u0101h"
    ],
    "name:tur_x_preferred":[
        "Vacargah"
    ],
    "name:und_x_variant":[
        "Ownd\u012bm Sar\u0101",
        "\u0648\u0627\u062c\u0627\u0631\u06af\u0627\u0647"
    ],
    "wof:name":"Vajargah",
    "wof:placetype":"locality"
},
  "geometry": {"coordinates":[50.40571,37.03876],"type":"Point"}
}