{
  "type": "Feature",
  "properties": {
    "gn:admin1_code":"13",
    "gn:asciiname":"Milkeh-ye Baqer",
    "gn:country_code":"IR",
    "gn:dem":1584,
    "gn:feature_class":"P",
    "gn:feature_code":"PPL",
    "gn:name":"M\u012blkeh-ye B\u0101qer",
    "gn:population":0,
    "gn:timezone":"Asia/Tehran",
    "iso:country":"IR",
    "name:fas_x_preferred":[
        "\u0645\u06cc\u0644\u06a9\u0647 \u0628\u0627\u0642\u0631"
    ],
    "name:fas_x_variant":[
        "M\u012blgeh-e B\u0101qar",
        "M\u012blkeh-ye B\u0101qer"
    ],
    "name:und_x_variant":[
        "Millehg\u0101h"
    ],
    "wof:name":"Milkeh-ye Baqer",
    "wof:placetype":"locality"
},
  "geometry": {"coordinates":[46.6046,34.3322],"type":"Point"}
}