{
  "type": "Feature",
  "properties": {
    "gn:admin1_code":"16",
    "gn:asciiname":"Barudar",
    "gn:country_code":"IR",
    "gn:dem":1875,
    "gn:feature_class":"P",
    "gn:feature_code":"PPL",
    "gn:name":"Bar\u016bdar",
    "gn:population":0,
    "gn:timezone":"Asia/Tehran",
    "iso:country":"IR",
    "name:ceb_x_preferred":[
        "Bar\u016bdar"
    ],
    "name:ckb_x_preferred":[
        "\u0628\u06d5\u0695\u0648\u06d5\u0631"
    ],
    "name:fas_x_preferred":[
        "\u0628\u064e\u0631\u062a\u0648\u062f\u0627\u0631"
    ],
    "name:fas_x_variant":[
        "Bar\u016bdar",
        "\u0628\u0631\u0648\u062f\u0631",
        "Bart\u016bd\u0101r"
    ],
    "name:kur_x_preferred":[
        "Berwer"
    ],
    "name:swe_x_preferred":[
        "Bar\u016bdar"
    ],
    "name:und_x_variant":[
        "Bart\u016bd\u0101r",
        "\u0628\u0631\u0648\u062f\u0631"
    ],
    "wof:name":"Barudar",
    "wof:placetype":"locality"
},
  "geometry": {"coordinates":[46.7492,35.4911],"type":"Point"}
}