{
  "type": "Feature",
  "properties": {
    "gn:admin1_code":"13",
    "gn:asciiname":"Darvish Beygeh",
    "gn:country_code":"IR",
    "gn:dem":1376,
    "gn:feature_class":"P",
    "gn:feature_code":"PPL",
    "gn:name":"Darv\u012bsh Beygeh",
    "gn:population":0,
    "gn:timezone":"Asia/Tehran",
    "iso:country":"IR",
    "name:fas_x_preferred":[
        "\u062f\u0631\u0648\u06cc\u0634 \u0628\u06cc\u06af\u0647"
    ],
    "name:fas_x_variant":[
        "Darv\u012bsh Beygeh",
        "\u062f\u0631\u0648\u06cc\u0634\u200c\u0628\u06cc\u06af\u0647"
    ],
    "wof:name":"Darvish Beygeh",
    "wof:placetype":"locality"
},
  "geometry": {"coordinates":[46.5705,34.4779],"type":"Point"}
}