{
  "type": "Feature",
  "properties": {
    "gn:admin1_code":"8",
    "gn:asciiname":"Dakan Veshaleh",
    "gn:country_code":"IR",
    "gn:dem":446,
    "gn:feature_class":"P",
    "gn:feature_code":"PPL",
    "gn:name":"Dak\u0101n Vesh\u0101leh",
    "gn:population":0,
    "gn:timezone":"Asia/Tehran",
    "iso:country":"IR",
    "name:fas_x_preferred":[
        "Dak\u0101n Vesh\u0101leh"
    ],
    "wof:name":"Dakan Veshaleh",
    "wof:placetype":"locality"
},
  "geometry": {"coordinates":[48.89694,37.585],"type":"Point"}
}