{
  "type": "Feature",
  "properties": {
    "gn:admin1_code":"29",
    "gn:asciiname":"Bidu'iyeh",
    "gn:country_code":"IR",
    "gn:dem":1647,
    "gn:feature_class":"P",
    "gn:feature_code":"PPLL",
    "gn:name":"B\u012bd\u016b\u2019\u012byeh",
    "gn:population":0,
    "gn:timezone":"Asia/Tehran",
    "iso:country":"IR",
    "name:fas_x_preferred":[
        "\u0622\u0628 \u0628\u06cc\u062f \u0633\u0641\u0644\u06cc"
    ],
    "name:fas_x_variant":[
        "\u0100b B\u012bd-e Sofl\u00e1",
        "\u0628\u064a\u062f\u0648\u0626\u064a\u0647"
    ],
    "name:und_x_variant":[
        "B\u012bd\u016b\u2019\u012byeh"
    ],
    "wof:name":"Bidu'iyeh",
    "wof:placetype":"locality"
},
  "geometry": {"coordinates":[57.01288,28.16675],"type":"Point"}
}