{
  "type": "Feature",
  "properties": {
    "gn:admin1_code":"4",
    "gn:asciiname":"Khosrin",
    "gn:country_code":"IR",
    "gn:dem":492,
    "gn:feature_class":"P",
    "gn:feature_code":"PPL",
    "gn:name":"Khosr\u012bn",
    "gn:population":0,
    "gn:timezone":"Asia/Tehran",
    "iso:country":"IR",
    "name:fas_x_preferred":[
        "\u062e\u0633\u0631\u06cc"
    ],
    "name:fas_x_variant":[
        "Khosr\u012bn",
        "Khosr\u012b",
        "\u062e\u0633\u0631\u06cc\u0646",
        "\u0648\u0633\u0631\u064a\u0646",
        "\u0648\u0633\u064a\u0631\u064a\u0646"
    ],
    "name:und_x_variant":[
        "Vasr\u012bn",
        "Vas\u012br\u012bn"
    ],
    "wof:name":"Khosrin",
    "wof:placetype":"locality"
},
  "geometry": {"coordinates":[59.34395,27.71752],"type":"Point"}
}