{
  "type": "Feature",
  "properties": {
    "gn:admin1_code":"36",
    "gn:asciiname":"Panbeh Zaban",
    "gn:country_code":"IR",
    "gn:dem":1902,
    "gn:feature_class":"P",
    "gn:feature_code":"PPL",
    "gn:name":"Panbeh Zab\u0101n",
    "gn:population":0,
    "gn:timezone":"Asia/Tehran",
    "iso:country":"IR",
    "name:fas_x_preferred":[
        "\u067e\u0646\u0628\u0647 \u0632\u0628\u0627\u0646"
    ],
    "name:fas_x_variant":[
        "Panbeh Zan\u0101n",
        "Panbeh Zab\u0101n"
    ],
    "wof:name":"Panbeh Zaban",
    "wof:placetype":"locality"
},
  "geometry": {"coordinates":[48.56228,35.85755],"type":"Point"}
}