{
  "type": "Feature",
  "properties": {
    "gn:admin1_code":"37",
    "gn:asciiname":"Tamer-e Qarah Quzi",
    "gn:country_code":"IR",
    "gn:dem":172,
    "gn:feature_class":"P",
    "gn:feature_code":"PPL",
    "gn:name":"Tamer-e Qarah Q\u016bz\u012b",
    "gn:population":0,
    "gn:timezone":"Asia/Tehran",
    "iso:country":"IR",
    "name:fas_x_preferred":[
        "Tamereh-ye Qarah Q\u016bz\u012b"
    ],
    "name:fas_x_variant":[
        "\u062a\u0645\u0631\u0647 \u0642\u0631\u0647 \u0642\u0648\u0632\u06cc",
        "\u062a\u0645\u0631\u0642\u0631\u0647 \u0642\u0648\u0632\u06cc",
        "\u062a\u0645\u0631\u0642\u0631\u0647 \u0642\u0648\u0632\u06cc \u0639\u0644\u06cc\u0627",
        "\u0642\u064e\u0631\u0650\u0647 \u0642\u0648\u0632\u06cc",
        "\u0642\u064e\u0631\u0650\u0647 \u0642\u0648\u0632\u064a\u0650 \u062f\u064f\u0648",
        "\u0642\u0631\u0647 \u0642\u0648\u0632\u06cc \u067e\u0627\u0626\u06cc\u0646"
    ],
    "name:und_x_variant":[
        "\u062a\u0645\u0631\u0647 \u0642\u0631\u0647 \u0642\u0648\u0632\u06cc",
        "Tamer-e Qarah Q\u016bz\u012b",
        "Tamer",
        "Tamer-e Qarah Q\u016bz\u012b-ye \u2018Oly\u0101",
        "Qareh Q\u016bz\u012b-e Do",
        "Qareh Q\u016bz\u012b",
        "Qara K\u016bzi",
        "Qarah Q\u016bz\u012b-ye P\u0101\u2019\u012bn"
    ],
    "wof:name":"Tamer-e Qarah Quzi",
    "wof:placetype":"locality"
},
  "geometry": {"coordinates":[55.49992,37.49777],"type":"Point"}
}