{
  "type": "Feature",
  "properties": {
    "gn:admin1_code":"16",
    "gn:asciiname":"Chumlu",
    "gn:country_code":"IR",
    "gn:dem":1556,
    "gn:feature_class":"P",
    "gn:feature_code":"PPL",
    "gn:name":"Ch\u016bml\u016b",
    "gn:population":0,
    "gn:timezone":"Asia/Tehran",
    "iso:country":"IR",
    "name:ara_x_preferred":[
        "\u062a\u0634\u0648\u0645\u0644\u0648"
    ],
    "name:ceb_x_preferred":[
        "Charml\u016b"
    ],
    "name:ckb_x_preferred":[
        "\u0686\u06c6\u0645\u06d5\u06b5\u0648\u0648"
    ],
    "name:fas_x_preferred":[
        "\u0686\u0631\u0645\u0644\u0648"
    ],
    "name:fas_x_variant":[
        "Ch\u016bmol\u016b",
        "Charml\u016b",
        "\u0686\u0648\u0645\u0644\u0648",
        "\u0686\u0648\u0644 \u0645\u0644\u0648"
    ],
    "name:kur_x_preferred":[
        "\u00c7omel\u00fb"
    ],
    "name:swe_x_preferred":[
        "Charml\u016b"
    ],
    "name:und_x_variant":[
        "Ch\u016bml\u016b",
        "Ch\u016bl Mal\u016b"
    ],
    "wof:name":"Chumlu",
    "wof:placetype":"locality"
},
  "geometry": {"coordinates":[46.62932,36.32495],"type":"Point"}
}