{
  "type": "Feature",
  "properties": {
    "gn:admin1_code":"1",
    "gn:asciiname":"Yaghlan Tappeh",
    "gn:country_code":"IR",
    "gn:dem":1290,
    "gn:feature_class":"P",
    "gn:feature_code":"PPL",
    "gn:name":"Y\u0101ghl\u0101n Tappeh",
    "gn:population":0,
    "gn:timezone":"Asia/Tehran",
    "iso:country":"IR",
    "name:fas_x_preferred":[
        "\u064a\u064e\u063a\u0646\u0639\u064e\u0644\u06cc \u062a\u064e\u067e\u0650\u0651\u0647"
    ],
    "name:fas_x_variant":[
        "\u06cc\u0627\u063a\u0644\u0627\u0646 \u062a\u067e\u0651\u0647",
        "Yaghn\u2018al\u012b Tappeh",
        "Y\u0101ghl\u0101n Tappeh"
    ],
    "wof:name":"Yaghlan Tappeh",
    "wof:placetype":"locality"
},
  "geometry": {"coordinates":[46.0506,36.9947],"type":"Point"}
}