{
  "type": "Feature",
  "properties": {
    "gn:admin1_code":"42",
    "gn:asciiname":"Mohsenabad",
    "gn:country_code":"IR",
    "gn:dem":1218,
    "gn:feature_class":"P",
    "gn:feature_code":"PPL",
    "gn:name":"Mo\u1e29sen\u0101b\u0101d",
    "gn:population":0,
    "gn:timezone":"Asia/Tehran",
    "iso:country":"IR",
    "name:ara_x_preferred":[
        "\u0645\u062d\u0633\u0646\u200c\u0622\u0628\u0627\u062f"
    ],
    "name:fas_x_preferred":[
        "\u0645\u062d\u0633\u0646 \u0622\u0628\u0627\u062f"
    ],
    "name:fas_x_variant":[
        "Mo\u1e29sen\u0101b\u0101d",
        "\u0645\u062d\u0633\u0646\u200c\u0622\u0628\u0627\u062f"
    ],
    "wof:name":"Mohsenabad",
    "wof:placetype":"locality"
},
  "geometry": {"coordinates":[59.8077,35.90932],"type":"Point"}
}