{
  "type": "Feature",
  "properties": {
    "gn:admin1_code":"13",
    "gn:asciiname":"Garmianak",
    "gn:country_code":"IR",
    "gn:dem":1305,
    "gn:feature_class":"P",
    "gn:feature_code":"PPL",
    "gn:name":"Garm\u012b\u0101nak",
    "gn:population":0,
    "gn:timezone":"Asia/Tehran",
    "iso:country":"IR",
    "name:fas_x_preferred":[
        "\u06af\u0631\u0645\u06cc\u0627\u0646\u06a9"
    ],
    "name:fas_x_variant":[
        "Garm\u012b\u0101nak"
    ],
    "name:und_x_variant":[
        "Qal\u2018a Garmianeh",
        "Garm\u012b\u0101neh",
        "Qal\u2018eh Garmi\u0101nek",
        "Garmey\u0101nak"
    ],
    "wof:name":"Garmianak",
    "wof:placetype":"locality"
},
  "geometry": {"coordinates":[47.4306,34.2783],"type":"Point"}
}