{
  "type": "Feature",
  "properties": {
    "gn:admin1_code":"29",
    "gn:asciiname":"Sardar Khaneh",
    "gn:country_code":"IR",
    "gn:dem":2278,
    "gn:feature_class":"P",
    "gn:feature_code":"PPL",
    "gn:name":"Sardar Kh\u0101neh",
    "gn:population":0,
    "gn:timezone":"Asia/Tehran",
    "iso:country":"IR",
    "name:fas_x_preferred":[
        "\u0633\u0631\u062f\u0631 \u062e\u0627\u0646\u0647"
    ],
    "name:fas_x_variant":[
        "Sardar Kh\u0101neh",
        "\u0633\u0631\u062f\u0631\u0648\u062f \u062e\u0627\u0646\u0647"
    ],
    "name:und_x_variant":[
        "Sardar\u016bd Kh\u0101neh"
    ],
    "wof:name":"Sardar Khaneh",
    "wof:placetype":"locality"
},
  "geometry": {"coordinates":[55.1699,30.3392],"type":"Point"}
}