{
  "type": "Feature",
  "properties": {
    "gn:admin1_code":"4",
    "gn:asciiname":"Gowhar Kuh",
    "gn:country_code":"IR",
    "gn:dem":445,
    "gn:feature_class":"P",
    "gn:feature_code":"PPL",
    "gn:name":"Gowhar K\u016bh",
    "gn:population":0,
    "gn:timezone":"Asia/Tehran",
    "iso:country":"IR",
    "name:fas_x_preferred":[
        "G\u016br K\u016bh"
    ],
    "name:fas_x_variant":[
        "\u06af\u0648\u0631 \u06a9\u0648\u0647",
        "\u06af\u0648\u0647\u0631 \u06a9\u0648\u0647"
    ],
    "name:und_x_variant":[
        "Gowhar K\u016bh"
    ],
    "wof:name":"Gowhar Kuh",
    "wof:placetype":"locality"
},
  "geometry": {"coordinates":[59.54391,26.33544],"type":"Point"}
}