{
  "type": "Feature",
  "properties": {
    "gn:admin1_code":"22",
    "gn:asciiname":"Chah Mush",
    "gn:country_code":"IR",
    "gn:dem":28,
    "gn:feature_class":"P",
    "gn:feature_code":"PPL",
    "gn:name":"Ch\u0101h M\u016bsh",
    "gn:population":0,
    "gn:timezone":"Asia/Tehran",
    "iso:country":"IR",
    "name:fas_x_preferred":[
        "\u0686\u0627\u0647 \u0645\u0648\u0634\u06cc"
    ],
    "name:fas_x_variant":[
        "\u0686\u0627 \u0645\u0648\u0634\u06cc",
        "\u0686\u0627\u0647\u0650 \u0645\u064f\u0634\u0643",
        "Ch\u0101h M\u016bsh\u012b",
        "Ch\u0101h M\u016bsh\u012b-ye \u2018Oly\u0101",
        "\u0686\u0627\u0647 \u0645\u0648\u0634\u06cc \u0639\u0644\u06cc\u0627",
        "\u0686\u0627\u0647 \u0645\u0648\u0634"
    ],
    "name:und_x_variant":[
        "Ch\u0101h Mushki",
        "Ch\u0101h-e Moshk",
        "Ch\u0101 M\u016bsh\u012b",
        "Ch\u0101h M\u016bsh"
    ],
    "wof:name":"Chah Mush",
    "wof:placetype":"locality"
},
  "geometry": {"coordinates":[51.0439,29.4042],"type":"Point"}
}