{
  "type": "Feature",
  "properties": {
    "gn:admin1_code":"7",
    "gn:asciiname":"Kushk",
    "gn:country_code":"IR",
    "gn:dem":1617,
    "gn:feature_class":"P",
    "gn:feature_code":"PPL",
    "gn:name":"K\u016bshk",
    "gn:population":0,
    "gn:timezone":"Asia/Tehran",
    "iso:country":"IR",
    "name:ceb_x_preferred":[
        "Kushk"
    ],
    "name:ces_x_preferred":[
        "Ku\u0161ka"
    ],
    "name:fas_x_preferred":[
        "\u06a9\u0648\u0634\u06a9\u06a9"
    ],
    "name:fas_x_variant":[
        "K\u016bshkak",
        "\u06a9\u0648\u0634\u06a9"
    ],
    "name:rus_x_preferred":[
        "\u041a\u0443\u0448\u043a"
    ],
    "name:slk_x_preferred":[
        "Ku\u0161ka"
    ],
    "name:swe_x_preferred":[
        "Kushk"
    ],
    "name:und_x_variant":[
        "K\u016bshk"
    ],
    "wof:name":"Kushk",
    "wof:placetype":"locality"
},
  "geometry": {"coordinates":[52.5926,30.0751],"type":"Point"}
}