{
  "type": "Feature",
  "properties": {
    "gn:admin1_code":"7",
    "gn:asciiname":"Bala Deh",
    "gn:country_code":"IR",
    "gn:dem":522,
    "gn:feature_class":"P",
    "gn:feature_code":"PPL",
    "gn:name":"B\u0101l\u0101 Deh",
    "gn:population":0,
    "gn:timezone":"Asia/Tehran",
    "iso:country":"IR",
    "name:ara_x_preferred":[
        "\u0628\u0644\u0627\u062f\u0647"
    ],
    "name:fas_x_preferred":[
        "\u0628\u0627\u0644\u0627 \u062f\u0647"
    ],
    "name:fas_x_variant":[
        "B\u0101l\u0101 Deh",
        "\u0628\u0627\u0644\u0627\u062f\u0647"
    ],
    "name:msa_x_preferred":[
        "Bala Deh"
    ],
    "wof:name":"Bala Deh",
    "wof:placetype":"locality"
},
  "geometry": {"coordinates":[53.5799,27.4023],"type":"Point"}
}