{
  "type": "Feature",
  "properties": {
    "gn:admin1_code":"4",
    "gn:asciiname":"Shahr Dar",
    "gn:country_code":"IR",
    "gn:dem":18,
    "gn:feature_class":"P",
    "gn:feature_code":"PPL",
    "gn:name":"Shahr Dar",
    "gn:population":0,
    "gn:timezone":"Asia/Tehran",
    "iso:country":"IR",
    "name:fas_x_preferred":[
        "\u0634\u0647\u0631 \u062f\u0631"
    ],
    "name:und_x_variant":[
        "Shahr-i-d\u0101r",
        "Shahr Dar"
    ],
    "wof:name":"Shahr Dar",
    "wof:placetype":"locality"
},
  "geometry": {"coordinates":[59.27477,25.6726],"type":"Point"}
}