{
  "type": "Feature",
  "properties": {
    "gn:admin1_code":"26",
    "gn:asciiname":"Agh Qu'i",
    "gn:country_code":"IR",
    "gn:dem":1568,
    "gn:feature_class":"P",
    "gn:feature_code":"PPL",
    "gn:name":"\u0100gh Q\u016b\u2019\u012b",
    "gn:population":0,
    "gn:timezone":"Asia/Tehran",
    "iso:country":"IR",
    "name:fas_x_preferred":[
        "\u0622\u063a \u0642\u0648\u0626\u06cc"
    ],
    "name:fas_x_variant":[
        "\u0100gh Q\u016b\u2019\u012b",
        "\u0622\u0642 \u0642\u0648\u06cc\u06cc"
    ],
    "name:und_x_variant":[
        "\u0100q Q\u016b\u2019\u012b",
        "D\u0101gh Q\u016b\u2019\u012b",
        "\u062f\u0627\u063a \u0642\u0648\u0626\u06cc"
    ],
    "wof:name":"Agh Qu'i",
    "wof:placetype":"locality"
},
  "geometry": {"coordinates":[50.504,35.6538],"type":"Point"}
}