{
  "type": "Feature",
  "properties": {
    "gn:admin1_code":"4.0",
    "gn:asciiname":"Garbon",
    "gn:country_code":"IR",
    "gn:dem":681,
    "gn:feature_class":"P",
    "gn:feature_code":"PPL",
    "gn:name":"Garbon",
    "gn:population":0,
    "gn:timezone":"Asia/Tehran",
    "iso:country":"IR",
    "name:fas_x_preferred":[
        "\u06af\u0631\u0628\u0646"
    ],
    "name:und_x_variant":[
        "K\u0101bon",
        "G\u0101rb\u016bn",
        "Garbon"
    ],
    "wof:name":"Garbon",
    "wof:placetype":"locality"
},
  "geometry": {"coordinates":[61.4475,26.4156],"type":"Point"}
}