{
  "type": "Feature",
  "properties": {
    "gn:admin1_code":"15",
    "gn:asciiname":"Zargan",
    "gn:country_code":"IR",
    "gn:dem":23,
    "gn:feature_class":"P",
    "gn:feature_code":"PPL",
    "gn:name":"Zarg\u0101n",
    "gn:population":0,
    "gn:timezone":"Asia/Tehran",
    "iso:country":"IR",
    "name:fas_x_preferred":[
        "\u0634\u0639\u0645\u06cc\u0637 \u06cc\u06a9"
    ],
    "name:fas_x_variant":[
        "Sho\u2018ayma\u0163-e Yek",
        "Sho\u2018amya\u0163-e Yek",
        "\u0632\u0631\u06af\u0627\u0646",
        "\u0634\u0639\u06cc\u0645\u0637 \u06cc\u06a9"
    ],
    "name:und_x_variant":[
        "Sho\u2018aimate Bavi",
        "Sha\u2018m\u012b\u0163",
        "Sho\u2018eyme\u0163-e B\u0101v\u012b",
        "Maj\u012bd\u0101b\u0101d",
        "Zarg\u0101n"
    ],
    "wof:name":"Zargan",
    "wof:placetype":"locality"
},
  "geometry": {"coordinates":[48.7813,31.4879],"type":"Point"}
}