{
  "type": "Feature",
  "properties": {
    "gn:admin1_code":"32",
    "gn:asciiname":"Dustlu",
    "gn:country_code":"IR",
    "gn:dem":1636,
    "gn:feature_class":"P",
    "gn:feature_code":"PPL",
    "gn:name":"D\u016bstl\u016b",
    "gn:population":0,
    "gn:timezone":"Asia/Tehran",
    "iso:country":"IR",
    "name:fas_x_preferred":[
        "D\u016bstel\u016b"
    ],
    "name:fas_x_variant":[
        "\u062f\u0648\u0633\u062a \u0644\u0648",
        "\u062f\u0648\u0633\u062a\u0644\u06cc"
    ],
    "name:und_x_variant":[
        "D\u016bstl\u016b",
        "Dostulu",
        "D\u016bstl\u012b"
    ],
    "wof:name":"Dustlu",
    "wof:placetype":"locality"
},
  "geometry": {"coordinates":[48.38524,37.45853],"type":"Point"}
}