{
  "type": "Feature",
  "properties": {
    "gn:admin1_code":"40",
    "gn:asciiname":"Sengerd",
    "gn:country_code":"IR",
    "gn:dem":2188,
    "gn:feature_class":"P",
    "gn:feature_code":"PPL",
    "gn:name":"Sengerd",
    "gn:population":0,
    "gn:timezone":"Asia/Tehran",
    "iso:country":"IR",
    "name:ara_x_preferred":[
        "\u0633\u0646\u062c\u062f"
    ],
    "name:fas_x_preferred":[
        "\u0633\u0646\u062c\u062f"
    ],
    "name:fas_x_variant":[
        "\u0633\u0646\u06af\u0631\u062f"
    ],
    "name:und_x_variant":[
        "Senjed",
        "Sengerd"
    ],
    "wof:name":"Sengerd",
    "wof:placetype":"locality"
},
  "geometry": {"coordinates":[54.58991,32.38815],"type":"Point"}
}