{
  "type": "Feature",
  "properties": {
    "gn:admin1_code":"29",
    "gn:asciiname":"Sabalu",
    "gn:country_code":"IR",
    "gn:dem":2322,
    "gn:feature_class":"P",
    "gn:feature_code":"PPL",
    "gn:name":"Sabal\u016b",
    "gn:population":0,
    "gn:timezone":"Asia/Tehran",
    "iso:country":"IR",
    "name:fas_x_preferred":[
        "\u0633\u0628\u0644\u0648"
    ],
    "name:fas_x_variant":[
        "Sabal\u016b"
    ],
    "wof:name":"Sabalu",
    "wof:placetype":"locality"
},
  "geometry": {"coordinates":[55.4355,30.2366],"type":"Point"}
}