{
  "type": "Feature",
  "properties": {
    "gn:admin1_code":"4",
    "gn:asciiname":"Rahmanabad",
    "gn:country_code":"IR",
    "gn:dem":1394,
    "gn:feature_class":"P",
    "gn:feature_code":"PPL",
    "gn:name":"Ra\u1e29m\u0101n\u0101b\u0101d",
    "gn:population":0,
    "gn:timezone":"Asia/Tehran",
    "iso:country":"IR",
    "name:ceb_x_preferred":[
        "Ra\u1e29m\u0101n\u0101b\u0101d"
    ],
    "name:fas_x_preferred":[
        "\u0631\u062d\u0645\u0627\u0646 \u0622\u0628\u0627\u062f"
    ],
    "name:fas_x_variant":[
        "Ra\u1e29m\u0101n\u0101b\u0101d",
        "\u0631\u062d\u0645\u0627\u0646\u200c\u0622\u0628\u0627\u062f"
    ],
    "name:swe_x_preferred":[
        "Ra\u1e29m\u0101n\u0101b\u0101d"
    ],
    "wof:name":"Rahmanabad",
    "wof:placetype":"locality"
},
  "geometry": {"coordinates":[60.8301,28.0573],"type":"Point"}
}