{
  "type": "Feature",
  "properties": {
    "gn:admin1_code":"13.0",
    "gn:asciiname":"Shahrak-e Allah Akbar",
    "gn:country_code":"IR",
    "gn:dem":1533,
    "gn:feature_class":"P",
    "gn:feature_code":"PPL",
    "gn:name":"Shahrak-e All\u0101h Akbar",
    "gn:population":0,
    "gn:timezone":"Asia/Tehran",
    "iso:country":"IR",
    "name:fas_x_preferred":[
        "\u0634\u0647\u0631\u06a9 \u0627\u0644\u0644\u0647 \u0627\u06a9\u0628\u0631"
    ],
    "name:fas_x_variant":[
        "Shahrak-e All\u0101h Akbar"
    ],
    "wof:name":"Shahrak-e Allah Akbar",
    "wof:placetype":"locality"
},
  "geometry": {"coordinates":[46.22203,34.28532],"type":"Point"}
}