{
  "type": "Feature",
  "properties": {
    "gn:admin1_code":"9",
    "gn:asciiname":"Shilandar-e Pa'in",
    "gn:country_code":"IR",
    "gn:dem":1692,
    "gn:feature_class":"P",
    "gn:feature_code":"PPL",
    "gn:name":"Sh\u012bl\u0101ndar-e P\u0101\u2019\u012bn",
    "gn:population":0,
    "gn:timezone":"Asia/Tehran",
    "iso:country":"IR",
    "name:fas_x_preferred":[
        "\u0634\u064a\u0644\u0627\u0646 \u062f\u0631\u0650 \u0633\u0641\u0644\u0649"
    ],
    "name:fas_x_variant":[
        "\u0634\u064a\u0644\u0627\u0646 \u062f\u064e\u0631",
        "\u0634\u064a\u0644\u0627\u0646\u062f\u0650\u0631",
        "Sh\u012bl\u0101ndar-e P\u0101\u2019\u012bn",
        "Sh\u012bl\u0101n Dar-e Sofl\u00e1",
        "\u0634\u06cc\u0644\u0627\u0646\u062f\u0631 \u067e\u0627\u06cc\u06cc\u0646"
    ],
    "name:und_x_variant":[
        "Sh\u012bl\u0101nder",
        "Sh\u012bl\u0101n Dar",
        "\u0634\u06cc\u0644\u0627\u0646\u062f\u0631 \u067e\u0627\u06cc\u06cc\u0646"
    ],
    "wof:name":"Shilandar-e Pa'in",
    "wof:placetype":"locality"
},
  "geometry": {"coordinates":[48.15447,34.66426],"type":"Point"}
}