{
  "type": "Feature",
  "properties": {
    "gn:admin1_code":"1",
    "gn:asciiname":"Hesar",
    "gn:country_code":"IR",
    "gn:dem":1457,
    "gn:feature_class":"P",
    "gn:feature_code":"PPL",
    "gn:name":"\u1e28e\u015f\u0101r",
    "gn:population":0,
    "gn:timezone":"Asia/Tehran",
    "iso:country":"IR",
    "name:azb_x_preferred":[
        "\u062d\u06cc\u0635\u0627\u0631\u062e\u0627\u0631\u0627\u0628\u0627"
    ],
    "name:aze_x_preferred":[
        "Hisarxaraba"
    ],
    "name:fas_x_preferred":[
        "\u062d\u0650\u0635\u0627\u0631 \u0633\u064e\u0631\u062f\u0627\u0631"
    ],
    "name:fas_x_variant":[
        "\u062d\u0635\u0627\u0631",
        "\u1e28e\u015f\u0101r Khar\u0101beh",
        "\u1e28e\u015f\u0101r",
        "\u062d\u0650\u0635\u0627\u0631 \u062e\u064e\u0631\u0627\u0628\u0650\u0647",
        "\u062d\u0635\u0627\u0631\u062e\u0631\u0627\u0628\u0647"
    ],
    "name:msa_x_preferred":[
        "Hesar Kharabeh"
    ],
    "name:und_x_variant":[
        "\u1e28e\u015f\u0101r Sard\u0101r"
    ],
    "wof:name":"Hesar",
    "wof:placetype":"locality"
},
  "geometry": {"coordinates":[44.9397,37.7099],"type":"Point"}
}