{
  "type": "Feature",
  "properties": {
    "gn:admin1_code":"44.0",
    "gn:asciiname":"Torkan Pordeh Sar",
    "gn:country_code":"IR",
    "gn:dem":1857,
    "gn:feature_class":"P",
    "gn:feature_code":"PPL",
    "gn:name":"Tork\u0101n Pordeh Sar",
    "gn:population":0,
    "gn:timezone":"Asia/Tehran",
    "iso:country":"IR",
    "name:fas_x_preferred":[
        "\u062a\u0631\u06a9\u0627\u0646 \u067e\u0631\u062f\u0647 \u0633\u0631"
    ],
    "name:und_x_variant":[
        "Tork\u0101n Pordeh Sar"
    ],
    "wof:name":"Torkan Pordeh Sar",
    "wof:placetype":"locality"
},
  "geometry": {"coordinates":[50.79171,36.17246],"type":"Point"}
}