{
  "type": "Feature",
  "properties": {
    "gn:admin1_code":"8.0",
    "gn:asciiname":"Pudeh",
    "gn:country_code":"IR",
    "gn:dem":1491,
    "gn:feature_class":"P",
    "gn:feature_code":"PPL",
    "gn:name":"P\u016bdeh",
    "gn:population":0,
    "gn:timezone":"Asia/Tehran",
    "iso:country":"IR",
    "name:fas_x_preferred":[
        "P\u016bdeh"
    ],
    "name:fas_x_variant":[
        "\u067e\u0648\u062f\u0647"
    ],
    "name:msa_x_preferred":[
        "Pudeh"
    ],
    "name:ukr_x_preferred":[
        "\u041f\u0443\u0434\u0435"
    ],
    "wof:name":"Pudeh",
    "wof:placetype":"locality"
},
  "geometry": {"coordinates":[50.28992,36.76056],"type":"Point"}
}