{
  "type": "Feature",
  "properties": {
    "gn:admin1_code":"33",
    "gn:asciiname":"Kohlu",
    "gn:country_code":"IR",
    "gn:dem":407,
    "gn:feature_class":"P",
    "gn:feature_code":"PPL",
    "gn:name":"Kohl\u016b",
    "gn:population":0,
    "gn:timezone":"Asia/Tehran",
    "iso:country":"IR",
    "name:ceb_x_preferred":[
        "Kohlu"
    ],
    "name:fas_x_preferred":[
        "\u0643\u064f\u0647\u0644\u0648\u06cc \u0633\u064f\u0641\u0644\u064e\u0649"
    ],
    "name:fas_x_variant":[
        "\u0643\u0647\u0644\u0648",
        "Kohl\u016b-ye Sofl\u00e1",
        "Kohl\u016b",
        "\u06a9\u0647\u0644\u0648"
    ],
    "name:msa_x_preferred":[
        "Kohlu"
    ],
    "name:pnb_x_preferred":[
        "\u06a9\u0648\u06c1\u0644\u0648"
    ],
    "name:por_x_preferred":[
        "Kohlu"
    ],
    "name:rus_x_preferred":[
        "\u041a\u043e\u0445\u043b\u0443"
    ],
    "name:spa_x_preferred":[
        "Kohlu"
    ],
    "name:swe_x_preferred":[
        "Kohlu"
    ],
    "name:tur_x_preferred":[
        "Kohlu"
    ],
    "name:urd_x_preferred":[
        "\u06a9\u0648\u06c1\u0644\u0648"
    ],
    "wof:name":"Kohlu",
    "wof:placetype":"locality"
},
  "geometry": {"coordinates":[47.4033,39.2312],"type":"Point"}
}