{
  "type": "Feature",
  "properties": {
    "gn:admin1_code":"7",
    "gn:asciiname":"Darreh Mordi",
    "gn:country_code":"IR",
    "gn:dem":1099,
    "gn:feature_class":"P",
    "gn:feature_code":"PPL",
    "gn:name":"Darreh Mord\u012b",
    "gn:population":0,
    "gn:timezone":"Asia/Tehran",
    "iso:country":"IR",
    "name:fas_x_preferred":[
        "Darreh M\u016brd\u012b"
    ],
    "name:fas_x_variant":[
        "\u062f\u0631\u0647 \u0645\u0631\u062f\u06cc",
        "\u062f\u0631\u0647 \u0645\u0648\u0631\u062f\u06cc"
    ],
    "name:und_x_variant":[
        "Darreh Mord\u012b"
    ],
    "wof:name":"Darreh Mordi",
    "wof:placetype":"locality"
},
  "geometry": {"coordinates":[51.48729,30.32366],"type":"Point"}
}