{
  "type": "Feature",
  "properties": {
    "gn:admin1_code":"0",
    "gn:asciiname":"Arkan",
    "gn:country_code":"IR",
    "gn:dem":1150,
    "gn:feature_class":"P",
    "gn:feature_code":"PPL",
    "gn:name":"Arkan",
    "gn:population":0,
    "gn:timezone":"Asia/Tehran",
    "iso:country":"IR",
    "name:fas_x_preferred":[
        "\u0627\u0631\u06a9\u0646"
    ],
    "wof:name":"Arkan",
    "wof:placetype":"locality"
},
  "geometry": {"coordinates":[57.6959,26.8854],"type":"Point"}
}