{
  "type": "Feature",
  "properties": {
    "gn:admin1_code":"15.0",
    "gn:asciiname":"Deh Ashkanan",
    "gn:country_code":"IR",
    "gn:dem":423,
    "gn:feature_class":"P",
    "gn:feature_code":"PPL",
    "gn:name":"Deh Ashkan\u0101n",
    "gn:population":0,
    "gn:timezone":"Asia/Tehran",
    "iso:country":"IR",
    "name:ara_x_preferred":[
        "\u062f\u0647 \u0627\u0634\u06a9\u0646\u0627\u0646"
    ],
    "name:azb_x_preferred":[
        "\u062f\u0647 \u0627\u0634\u06a9\u0646\u0627\u0646"
    ],
    "name:fas_x_preferred":[
        "Deh-e Ashkan\u0101n"
    ],
    "name:fas_x_variant":[
        "\u062f\u0647 \u0627\u0634\u06a9\u0646\u0627\u0646",
        "\u062f\u0647\u200c\u0627\u0634\u06a9\u0646\u0627\u0646"
    ],
    "name:und_x_variant":[
        "Ashkan\u0101n",
        "Deh Eshkenan",
        "Deh Eshkan\u0101n",
        "Deh Ashkan\u0101n"
    ],
    "wof:name":"Deh Ashkanan",
    "wof:placetype":"locality"
},
  "geometry": {"coordinates":[48.35662,32.72026],"type":"Point"}
}