{
  "type": "Feature",
  "properties": {
    "gn:admin1_code":"11",
    "gn:asciiname":"Karat",
    "gn:country_code":"IR",
    "gn:dem":530,
    "gn:feature_class":"P",
    "gn:feature_code":"PPL",
    "gn:name":"Karat",
    "gn:population":0,
    "gn:timezone":"Asia/Tehran",
    "iso:country":"IR",
    "name:fas_x_preferred":[
        "\u0643\u064e\u0631\u064e\u062a"
    ],
    "name:fas_x_variant":[
        "\u06a9\u0631\u062a"
    ],
    "name:msa_x_preferred":[
        "Karat"
    ],
    "wof:name":"Karat",
    "wof:placetype":"locality"
},
  "geometry": {"coordinates":[57.13972,27.73833],"type":"Point"}
}