{
  "type": "Feature",
  "properties": {
    "gn:admin1_code":"35.0",
    "gn:asciiname":"Par Kola",
    "gn:country_code":"IR",
    "gn:dem":1053,
    "gn:feature_class":"P",
    "gn:feature_code":"PPL",
    "gn:name":"Par Kol\u0101",
    "gn:population":0,
    "gn:timezone":"Asia/Tehran",
    "iso:country":"IR",
    "name:ara_x_preferred":[
        "\u0628\u0631\u06a9\u0644\u0627"
    ],
    "name:ceb_x_preferred":[
        "Par Kol\u0101"
    ],
    "name:fas_x_preferred":[
        "\u067e\u064e\u0631 \u0643\u064e\u0644\u0627"
    ],
    "name:fas_x_variant":[
        "\u067e\u064f\u0631 \u0643\u064e\u0644\u0627",
        "\u067e\u064f\u0631 \u0643\u064f\u0644\u0627",
        "Par Kol\u0101",
        "\u067e\u0631 \u0643\u0644\u0627",
        "\u067e\u0631\u06a9\u0644\u0627"
    ],
    "name:swe_x_preferred":[
        "Par Kol\u0101"
    ],
    "name:und_x_variant":[
        "Por Kal\u0101",
        "Par Kal\u0101",
        "Por Kol\u0101",
        "\u067e\u0631 \u0643\u0644\u0627"
    ],
    "wof:name":"Par Kola",
    "wof:placetype":"locality"
},
  "geometry": {"coordinates":[53.71308000000001,36.5463],"type":"Point"}
}