{
  "type": "Feature",
  "properties": {
    "gn:admin1_code":"3.0",
    "gn:asciiname":"Dar Hendu",
    "gn:country_code":"IR",
    "gn:dem":1587,
    "gn:feature_class":"P",
    "gn:feature_code":"PPL",
    "gn:name":"Dar Hend\u016b",
    "gn:population":0,
    "gn:timezone":"Asia/Tehran",
    "iso:country":"IR",
    "name:fas_x_preferred":[
        "Dar Hend\u016b"
    ],
    "name:fas_x_variant":[
        "\u062f\u0631 \u0647\u0646\u062f\u0648"
    ],
    "wof:name":"Dar Hendu",
    "wof:placetype":"locality"
},
  "geometry": {"coordinates":[49.98797,32.28413],"type":"Point"}
}