{
  "type": "Feature",
  "properties": {
    "gn:admin1_code":"16.0",
    "gn:asciiname":"Nowdeh",
    "gn:country_code":"IR",
    "gn:dem":1572,
    "gn:elevation":"0.0",
    "gn:feature_class":"P",
    "gn:feature_code":"PPL",
    "gn:name":"Nowdeh",
    "gn:population":0,
    "gn:timezone":"Asia/Tehran",
    "iso:country":"IR",
    "name:fas_x_preferred":[
        "\u0646\u064f\u0648\u062f\u0650\u0647"
    ],
    "name:fas_x_variant":[
        "\u0646\u0648\u062f\u0647"
    ],
    "wof:name":"Nowdeh",
    "wof:placetype":"locality"
},
  "geometry": {"coordinates":[45.8816,35.9368],"type":"Point"}
}