{
  "type": "Feature",
  "properties": {
    "gn:admin1_code":"1",
    "gn:asciiname":"Vaqaslu-ye `Olya",
    "gn:country_code":"IR",
    "gn:dem":1285,
    "gn:feature_class":"P",
    "gn:feature_code":"PPL",
    "gn:name":"Vaq\u0101\u015fl\u016b-ye \u2018Oly\u0101",
    "gn:population":0,
    "gn:timezone":"Asia/Tehran",
    "iso:country":"IR",
    "name:fas_x_preferred":[
        "\u0648\u0642\u0627\u0635\u0644\u0648\u06cc \u0639\u0644\u06cc\u0627"
    ],
    "name:fas_x_variant":[
        "\u0648\u064e\u0642\u0627\u0635\u0644\u0648\u06cc \u0639\u064f\u0644\u064a\u0627",
        "Vaq\u0101\u015fl\u016b-ye \u2018Oly\u0101",
        "\u0643\u064e\u0686\u064e\u0644\u0639\u064e\u0644\u0626 \u0639\u064f\u0644\u064a\u0627"
    ],
    "name:und_x_variant":[
        "Kachal\u2018al\u012b-ye \u2018Oly\u0101"
    ],
    "wof:name":"Vaqaslu-ye `Olya",
    "wof:placetype":"locality"
},
  "geometry": {"coordinates":[45.0981,37.7739],"type":"Point"}
}