{
  "type": "Feature",
  "properties": {
    "gn:admin1_code":"16.0",
    "gn:asciiname":"Bubaktan",
    "gn:country_code":"IR",
    "gn:dem":1647,
    "gn:feature_class":"P",
    "gn:feature_code":"PPL",
    "gn:name":"B\u016bbakt\u0101n",
    "gn:population":0,
    "gn:timezone":"Asia/Tehran",
    "iso:country":"IR",
    "name:fas_x_preferred":[
        "\u0628\u0648\u0628\u06a9\u062a\u0627\u0646"
    ],
    "name:fas_x_variant":[
        "B\u016bbakt\u0101n"
    ],
    "wof:name":"Bubaktan",
    "wof:placetype":"locality"
},
  "geometry": {"coordinates":[45.9956,36.2512],"type":"Point"}
}