{
  "type": "Feature",
  "properties": {
    "gn:admin1_code":"29",
    "gn:asciiname":"Jahanabad-e Pa'in",
    "gn:country_code":"IR",
    "gn:dem":697,
    "gn:feature_class":"P",
    "gn:feature_code":"PPL",
    "gn:name":"Jah\u0101n\u0101b\u0101d-e P\u0101\u2019\u012bn",
    "gn:population":0,
    "gn:timezone":"Asia/Tehran",
    "iso:country":"IR",
    "name:fas_x_preferred":[
        "\u062c\u0647\u0627\u0646 \u0622\u0628\u0627\u062f"
    ],
    "name:fas_x_variant":[
        "Jah\u0101n\u0101b\u0101d-e B\u0101l\u0101",
        "Jah\u0101n\u0101b\u0101d",
        "\u062c\u0647\u0627\u0646 \u0622\u0628\u0627\u062f \u067e\u0627\u0626\u06cc\u0646"
    ],
    "name:und_x_variant":[
        "Jeh\u0101n\u0101b\u0101d",
        "Jah\u0101n\u0101b\u0101d-e P\u0101\u2019\u012bn"
    ],
    "wof:name":"Jahanabad-e Pa'in",
    "wof:placetype":"locality"
},
  "geometry": {"coordinates":[58.8928,28.8859],"type":"Point"}
}