{
  "type": "Feature",
  "properties": {
    "gn:admin1_code":"13",
    "gn:asciiname":"Kani Rash",
    "gn:cc2":"IR",
    "gn:country_code":"IR",
    "gn:dem":932,
    "gn:feature_class":"P",
    "gn:feature_code":"PPL",
    "gn:name":"K\u0101n\u012b Rash",
    "gn:population":0,
    "gn:timezone":"Asia/Tehran",
    "iso:country":"IR",
    "name:fas_x_preferred":[
        "K\u0101n\u012b Rash"
    ],
    "name:und_x_variant":[
        "K\u0101n\u012b Resh"
    ],
    "wof:name":"Kani Rash",
    "wof:placetype":"locality"
},
  "geometry": {"coordinates":[45.96278,34.49583],"type":"Point"}
}