{
  "type": "Feature",
  "properties": {
    "gn:admin1_code":"41",
    "gn:asciiname":"Mas`udi",
    "gn:country_code":"IR",
    "gn:dem":1965,
    "gn:feature_class":"P",
    "gn:feature_code":"PPL",
    "gn:name":"Mas\u2018\u016bd\u012b",
    "gn:population":0,
    "gn:timezone":"Asia/Tehran",
    "iso:country":"IR",
    "name:fas_x_preferred":[
        "Mas\u2018oodi"
    ],
    "name:fas_x_variant":[
        "Mas\u2018\u016bd\u012b",
        "\u0645\u0633\u0639\u0648\u062f\u06cc"
    ],
    "name:und_x_variant":[
        "\u0645\u0633\u0639\u0648\u062f\u06cc"
    ],
    "wof:name":"Mas`udi",
    "wof:placetype":"locality"
},
  "geometry": {"coordinates":[59.43389000000001,32.22546],"type":"Point"}
}