{
  "type": "Feature",
  "properties": {
    "gn:admin1_code":"8.0",
    "gn:asciiname":"Jir Lashkaj",
    "gn:country_code":"IR",
    "gn:dem":675,
    "gn:feature_class":"P",
    "gn:feature_code":"PPL",
    "gn:name":"J\u012br Lashkaj",
    "gn:population":0,
    "gn:timezone":"Asia/Tehran",
    "iso:country":"IR",
    "name:fas_x_preferred":[
        "\u062c\u06cc\u0631 \u0644\u0634\u06a9\u062c"
    ],
    "name:und_x_variant":[
        "J\u012br Lashkaj"
    ],
    "wof:name":"Jir Lashkaj",
    "wof:placetype":"locality"
},
  "geometry": {"coordinates":[49.94432000000001,37.02843],"type":"Point"}
}