{
  "type": "Feature",
  "properties": {
    "gn:admin1_code":"25",
    "gn:asciiname":"Hoseynabad Saghari",
    "gn:country_code":"IR",
    "gn:dem":1239,
    "gn:feature_class":"P",
    "gn:feature_code":"PPLF",
    "gn:name":"\u1e28oseyn\u0101b\u0101d S\u0101ghar\u012b",
    "gn:population":0,
    "gn:timezone":"Asia/Tehran",
    "iso:country":"IR",
    "name:fas_x_preferred":[
        "\u1e28oseyn\u0101b\u0101d S\u0101ghar\u012b"
    ],
    "name:fas_x_variant":[
        "\u062d\u0633\u06cc\u0646 \u0622\u0628\u0627\u062f \u0633\u0627\u063a\u0631\u06cc"
    ],
    "wof:name":"Hoseynabad Saghari",
    "wof:placetype":"locality"
},
  "geometry": {"coordinates":[55.01043000000001,36.32804],"type":"Point"}
}