{
  "type": "Feature",
  "properties": {
    "gn:admin1_code":"29",
    "gn:asciiname":"Masinan",
    "gn:cc2":"IR",
    "gn:country_code":"IR",
    "gn:dem":2585,
    "gn:feature_class":"P",
    "gn:feature_code":"PPL",
    "gn:name":"Mas\u012bn\u0101n",
    "gn:population":0,
    "gn:timezone":"Asia/Tehran",
    "iso:country":"IR",
    "name:ceb_x_preferred":[
        "Mas\u012bn\u0101n"
    ],
    "name:fas_x_preferred":[
        "Mas\u012bn\u0101n"
    ],
    "name:fas_x_variant":[
        "\u0645\u0633\u064a\u0646\u0627\u0646",
        "\u0645\u0633\u06cc\u0646\u0627\u0646"
    ],
    "name:swe_x_preferred":[
        "Mas\u012bn\u0101n"
    ],
    "name:und_x_variant":[
        "Musinu",
        "Masineh"
    ],
    "wof:name":"Masinan",
    "wof:placetype":"locality"
},
  "geometry": {"coordinates":[55.3825,30.42111],"type":"Point"}
}