{
  "type": "Feature",
  "properties": {
    "gn:admin1_code":"11.0",
    "gn:asciiname":"Qal`eh-ye Dokhtaran",
    "gn:country_code":"IR",
    "gn:dem":162,
    "gn:feature_class":"P",
    "gn:feature_code":"PPL",
    "gn:name":"Qal\u2018eh-ye Dokhtar\u0101n",
    "gn:population":0,
    "gn:timezone":"Asia/Tehran",
    "iso:country":"IR",
    "name:fas_x_preferred":[
        "\u0642\u0644\u0639\u0647 \u062f\u062e\u062a\u0631\u0627\u0646"
    ],
    "name:fas_x_variant":[
        "Qal\u2018eh-ye Dokhtar\u0101n",
        "\u0642\u0644\u0639\u0647 \u0631\u0633\u062a\u0645"
    ],
    "name:und_x_variant":[
        "Qal\u2018eh-ye Rostam"
    ],
    "wof:name":"Qal`eh-ye Dokhtaran",
    "wof:placetype":"locality"
},
  "geometry": {"coordinates":[57.32155,27.01813],"type":"Point"}
}