{
  "type": "Feature",
  "properties": {
    "gn:admin1_code":"22",
    "gn:asciiname":"Rud Faryab",
    "gn:country_code":"IR",
    "gn:dem":643,
    "gn:feature_class":"P",
    "gn:feature_code":"PPL",
    "gn:name":"R\u016bd F\u0101ry\u0101b",
    "gn:population":0,
    "gn:timezone":"Asia/Tehran",
    "iso:country":"IR",
    "name:ara_x_preferred":[
        "\u0631\u0648\u062f \u0641\u0627\u0631\u064a\u0627\u0628"
    ],
    "name:fas_x_preferred":[
        "\u0641\u0627\u0631\u064a\u0627\u0628"
    ],
    "name:fas_x_variant":[
        "\u0631\u0648\u0647 \u0641\u0627\u0631\u064a\u0627\u0628",
        "\u067e\u0627\u0631\u0650\u064a\u064f\u0648",
        "\u0631\u0648\u062d \u0641\u0627\u0631\u064a\u0627\u0628",
        "\u0631\u0648\u062f \u0641\u0627\u0631\u064a\u0627\u0628",
        "F\u0101r\u012b\u0101b",
        "\u0631\u0648\u062f\u0641\u0627\u0631\u06cc\u0627\u0628"
    ],
    "name:msa_x_preferred":[
        "Rud-e-Faryab"
    ],
    "name:und_x_variant":[
        "P\u0101reyow",
        "R\u016bd-e-F\u0101ry\u0101b",
        "R\u016b\u1e29 F\u0101ry\u0101b",
        "R\u016bh F\u0101r\u012b\u0101b",
        "R\u016bd F\u0101ry\u0101b"
    ],
    "wof:name":"Rud Faryab",
    "wof:placetype":"locality"
},
  "geometry": {"coordinates":[51.48128,29.25088],"type":"Point"}
}