{
  "type": "Feature",
  "properties": {
    "gn:admin1_code":"8",
    "gn:asciiname":"Lalik Sara",
    "gn:country_code":"IR",
    "gn:dem":5,
    "gn:feature_class":"P",
    "gn:feature_code":"PPL",
    "gn:name":"Lal\u012bk Sar\u0101",
    "gn:population":0,
    "gn:timezone":"Asia/Tehran",
    "iso:country":"IR",
    "name:fas_x_preferred":[
        "Lal\u012bk Sar\u0101"
    ],
    "wof:name":"Lalik Sara",
    "wof:placetype":"locality"
},
  "geometry": {"coordinates":[50.23972,37.09417],"type":"Point"}
}