{
  "type": "Feature",
  "properties": {
    "gn:admin1_code":"8",
    "gn:asciiname":"Sardakhaneh-ye Posht",
    "gn:country_code":"IR",
    "gn:dem":1495,
    "gn:feature_class":"P",
    "gn:feature_code":"PPL",
    "gn:name":"Sard\u0101kh\u0101neh-ye Posht",
    "gn:population":0,
    "gn:timezone":"Asia/Tehran",
    "iso:country":"IR",
    "name:fas_x_preferred":[
        "\u062f\u0631\u0647 \u062f\u0634\u062a"
    ],
    "name:fas_x_variant":[
        "\u0633\u0631\u062f\u0627\u062e\u0627\u0646\u0647 \u067e\u0634\u062a",
        "\u0633\u0631\u062f\u0627\u0628\u062e\u0627\u0646\u0647 \u067e\u0634\u062a"
    ],
    "name:und_x_variant":[
        "Darreh Dasht",
        "Sard\u0101kh\u0101neh-ye Posht",
        "Sard\u0101bkh\u0101neh-ye Posht"
    ],
    "wof:name":"Sardakhaneh-ye Posht",
    "wof:placetype":"locality"
},
  "geometry": {"coordinates":[48.7137,37.7668],"type":"Point"}
}