{
  "type": "Feature",
  "properties": {
    "gn:admin1_code":"35.0",
    "gn:asciiname":"Anand",
    "gn:country_code":"IR",
    "gn:dem":1854,
    "gn:feature_class":"P",
    "gn:feature_code":"PPL",
    "gn:name":"Anand",
    "gn:population":0,
    "gn:timezone":"Asia/Tehran",
    "iso:country":"IR",
    "name:fas_x_preferred":[
        "\u0627\u0646\u0646\u062f"
    ],
    "name:und_x_variant":[
        "An\u0101neh",
        "Anand"
    ],
    "wof:name":"Anand",
    "wof:placetype":"locality"
},
  "geometry": {"coordinates":[52.72316,35.99512],"type":"Point"}
}