{
  "type": "Feature",
  "properties": {
    "gn:admin1_code":"35.0",
    "gn:asciiname":"Anand",
    "gn:country_code":"IR",
    "gn:dem":1854,
    "gn:feature_class":"P",
    "gn:feature_code":"PPL",
    "gn:name":"Anand",
    "gn:population":0,
    "gn:timezone":"Asia/Tehran",
    "iso:country":"IR",
    "name:ara_x_preferred":[
        "\u0623\u0646\u0627\u0646\u062f"
    ],
    "name:bel_x_preferred":[
        "\u0410\u043d\u0430\u043d\u0434"
    ],
    "name:bih_x_preferred":[
        "\u0906\u0928\u0902\u0926"
    ],
    "name:cat_x_preferred":[
        "Anand"
    ],
    "name:ceb_x_preferred":[
        "Anand"
    ],
    "name:deu_x_preferred":[
        "Anand"
    ],
    "name:fas_x_preferred":[
        "\u0627\u0646\u0646\u062f"
    ],
    "name:fin_x_preferred":[
        "Anand"
    ],
    "name:fra_x_preferred":[
        "Anand"
    ],
    "name:mal_x_preferred":[
        "\u0d06\u0d28\u0d28\u0d4d\u0d26\u0d4d"
    ],
    "name:nds_x_preferred":[
        "Anand"
    ],
    "name:nld_x_preferred":[
        "Anand"
    ],
    "name:nor_x_preferred":[
        "Anand"
    ],
    "name:rus_x_preferred":[
        "\u0410\u043d\u0430\u043d\u0434"
    ],
    "name:slv_x_preferred":[
        "Anand"
    ],
    "name:swe_x_preferred":[
        "Anand"
    ],
    "name:tel_x_preferred":[
        "\u0c06\u0c28\u0c02\u0c26\u0c4d"
    ],
    "name:und_x_variant":[
        "An\u0101neh"
    ],
    "name:vie_x_preferred":[
        "Anand"
    ],
    "wof:name":"Anand",
    "wof:placetype":"locality"
},
  "geometry": {"coordinates":[52.72316,35.99512],"type":"Point"}
}