{
  "type": "Feature",
  "properties": {
    "gn:admin1_code":"32",
    "gn:asciiname":"Golestan-e `Olya",
    "gn:country_code":"IR",
    "gn:dem":1926,
    "gn:feature_class":"P",
    "gn:feature_code":"PPL",
    "gn:name":"Golest\u0101n-e \u2018Oly\u0101",
    "gn:population":0,
    "gn:timezone":"Asia/Tehran",
    "iso:country":"IR",
    "name:fas_x_preferred":[
        "\u06af\u0644\u0633\u062a\u0627\u0646 \u0628\u0627\u0644\u0627"
    ],
    "name:fas_x_variant":[
        "Kalest\u0101n-e \u2018Oly\u0101",
        "Golest\u0101n-e B\u0101l\u0101",
        "\u06af\u0644\u0633\u062a\u0627\u0646 \u0639\u0644\u06cc\u0627"
    ],
    "name:und_x_variant":[
        "Kyal\u2019ston",
        "Kalest\u0101n",
        "Kialston",
        "Golest\u0101n-e \u2018Oly\u0101"
    ],
    "wof:name":"Golestan-e `Olya",
    "wof:placetype":"locality"
},
  "geometry": {"coordinates":[48.56817,37.74361],"type":"Point"}
}