{
  "type": "Feature",
  "properties": {
    "gn:admin1_code":"4.0",
    "gn:asciiname":"Qatar Khonjak",
    "gn:country_code":"IR",
    "gn:dem":1721,
    "gn:feature_class":"P",
    "gn:feature_code":"PPL",
    "gn:name":"Qa\u0163\u0101r Khonjak",
    "gn:population":0,
    "gn:timezone":"Asia/Tehran",
    "iso:country":"IR",
    "name:fas_x_preferred":[
        "\u0642\u0637\u0627\u0631\u062e\u0646\u062c\u06a9"
    ],
    "name:fas_x_variant":[
        "Qa\u0163\u0101r Khonjak"
    ],
    "wof:name":"Qatar Khonjak",
    "wof:placetype":"locality"
},
  "geometry": {"coordinates":[60.7483,29.2311],"type":"Point"}
}