{
  "type": "Feature",
  "properties": {
    "gn:admin1_code":"9",
    "gn:asciiname":"Uch Tappeh",
    "gn:country_code":"IR",
    "gn:dem":1646,
    "gn:feature_class":"P",
    "gn:feature_code":"PPL",
    "gn:name":"\u016ach Tappeh",
    "gn:population":0,
    "gn:timezone":"Asia/Tehran",
    "iso:country":"IR",
    "name:fas_x_preferred":[
        "\u016ach Tappeh"
    ],
    "name:fas_x_variant":[
        "\u0627\u0648\u0686 \u062a\u067e\u0647"
    ],
    "wof:name":"Uch Tappeh",
    "wof:placetype":"locality"
},
  "geometry": {"coordinates":[48.98739000000001,34.59990999999999],"type":"Point"}
}