{
  "type": "Feature",
  "properties": {
    "gn:admin1_code":"37.0",
    "gn:asciiname":"Dowlat-e Nazar Nazari",
    "gn:country_code":"IR",
    "gn:dem":53,
    "gn:feature_class":"P",
    "gn:feature_code":"PPL",
    "gn:name":"Dowlat-e Naz\u0327ar Naz\u0327ar\u012b",
    "gn:population":0,
    "gn:timezone":"Asia/Tehran",
    "iso:country":"IR",
    "name:fas_x_preferred":[
        "\u062f\u0648\u0644\u062a \u0646\u0638\u0631 \u0646\u0638\u0631\u06cc"
    ],
    "name:fas_x_variant":[
        "\u062e\u064a\u0631 \u062e\u0648\u0627\u062c\u0647",
        "\u062e\u064a\u0631 \u062e\u0648\u0627\u062c\u0647 \u0633\u0641\u0644\u06cc"
    ],
    "name:und_x_variant":[
        "Dowlat-e Naz\u0327ar Naz\u0327ar\u012b",
        "Kheyr Khv\u0101jeh",
        "Kheyr Khv\u0101jeh-ye Sofl\u00e1"
    ],
    "wof:name":"Dowlat-e Nazar Nazari",
    "wof:placetype":"locality"
},
  "geometry": {"coordinates":[54.95105,37.77065],"type":"Point"}
}