{
  "type": "Feature",
  "properties": {
    "gn:admin1_code":"36",
    "gn:admin2_code":"449564",
    "gn:asciiname":"Hesar",
    "gn:country_code":"IR",
    "gn:dem":1927,
    "gn:feature_class":"P",
    "gn:feature_code":"PPL",
    "gn:name":"Hesar",
    "gn:population":0,
    "gn:timezone":"Asia/Tehran",
    "iso:country":"IR",
    "name:azb_x_preferred":[
        "\u062d\u0635\u0627\u0631"
    ],
    "name:fas_x_preferred":[
        "\u062d\u0635\u0627\u0631"
    ],
    "name:fas_x_variant":[
        "\u1e28e\u015f\u0101r"
    ],
    "name:und_x_variant":[
        "Khissar",
        "His\u0101r",
        "Hiss\u0101r"
    ],
    "wof:name":"Hesar",
    "wof:placetype":"locality"
},
  "geometry": {"coordinates":[48.581,36.0633],"type":"Point"}
}