{
  "type": "Feature",
  "properties": {
    "gn:admin1_code":"1",
    "gn:asciiname":"Anbar-e Vasat",
    "gn:country_code":"IR",
    "gn:dem":2312,
    "gn:feature_class":"P",
    "gn:feature_code":"PPL",
    "gn:name":"Anb\u0101r-e Vasa\u0163",
    "gn:population":0,
    "gn:timezone":"Asia/Tehran",
    "iso:country":"IR",
    "name:fas_x_preferred":[
        "Anb\u0101r-e M\u012b\u0101n\u012b"
    ],
    "name:fas_x_variant":[
        "\u0627\u0646\u0628\u0627\u0631 \u0648\u0633\u0637",
        "Anb\u0101r-e Vasa\u0163"
    ],
    "wof:name":"Anbar-e Vasat",
    "wof:placetype":"locality"
},
  "geometry": {"coordinates":[44.4957,38.9631],"type":"Point"}
}