{
  "type": "Feature",
  "properties": {
    "gn:admin1_code":"28",
    "gn:asciiname":"Hunejan",
    "gn:country_code":"IR",
    "gn:dem":2368,
    "gn:feature_class":"P",
    "gn:feature_code":"PPL",
    "gn:name":"H\u016bnej\u0101n",
    "gn:population":0,
    "gn:timezone":"Asia/Tehran",
    "iso:country":"IR",
    "name:fas_x_preferred":[
        "H\u016bnej\u0101n"
    ],
    "name:fas_x_variant":[
        "\u0647\u0648\u0646\u062c\u0627\u0646"
    ],
    "name:und_x_variant":[
        "Hinij\u0101n",
        "Hunj\u0101n"
    ],
    "wof:name":"Hunejan",
    "wof:placetype":"locality"
},
  "geometry": {"coordinates":[51.86929,31.60974],"type":"Point"}
}