{
  "type": "Feature",
  "properties": {
    "gn:admin1_code":"1.0",
    "gn:asciiname":"Maturbash",
    "gn:country_code":"IR",
    "gn:dem":1326,
    "gn:feature_class":"P",
    "gn:feature_code":"PPL",
    "gn:name":"M\u0101t\u016brb\u0101sh",
    "gn:population":0,
    "gn:timezone":"Asia/Tehran",
    "iso:country":"IR",
    "name:fas_x_preferred":[
        "\u0645\u0627\u062a\u0648\u0631\u0628\u0627\u0634"
    ],
    "name:fas_x_variant":[
        "M\u0101t\u016brb\u0101sh"
    ],
    "wof:name":"Maturbash",
    "wof:placetype":"locality"
},
  "geometry": {"coordinates":[45.07963,37.57887],"type":"Point"}
}