{
  "type": "Feature",
  "properties": {
    "gn:admin1_code":"33",
    "gn:asciiname":"Miandaraq",
    "gn:country_code":"IR",
    "gn:dem":1381,
    "gn:feature_class":"P",
    "gn:feature_code":"PPL",
    "gn:name":"M\u012b\u0101ndaraq",
    "gn:population":0,
    "gn:timezone":"Asia/Tehran",
    "iso:country":"IR",
    "name:fas_x_preferred":[
        "M\u012b\u0101ndaraq"
    ],
    "name:fas_x_variant":[
        "\u0645\u06cc\u0627\u0646\u062f\u0631\u0642",
        "\u0645\u064a\u0627\u0646 \u062f\u0631\u0647"
    ],
    "name:msa_x_preferred":[
        "Miandaraq"
    ],
    "name:und_x_variant":[
        "M\u012b\u0101n Darreh"
    ],
    "wof:name":"Miandaraq",
    "wof:placetype":"locality"
},
  "geometry": {"coordinates":[47.19347,38.93102],"type":"Point"}
}