{
  "type": "Feature",
  "properties": {
    "gn:admin1_code":"28",
    "gn:asciiname":"Jeshuqan",
    "gn:country_code":"IR",
    "gn:dem":2057,
    "gn:feature_class":"P",
    "gn:feature_code":"PPL",
    "gn:name":"Jesh\u016bq\u0101n",
    "gn:population":0,
    "gn:timezone":"Asia/Tehran",
    "iso:country":"IR",
    "name:fas_x_preferred":[
        "\u062c\u0634\u0648\u0642\u0627\u0646"
    ],
    "name:fas_x_variant":[
        "Jesh\u016bq\u0101n"
    ],
    "name:und_x_variant":[
        "Gashk\u016bn",
        "Haft Y\u0101r\u0101n"
    ],
    "wof:name":"Jeshuqan",
    "wof:placetype":"locality"
},
  "geometry": {"coordinates":[52.7297,32.6925],"type":"Point"}
}