{
  "type": "Feature",
  "properties": {
    "gn:admin1_code":"5",
    "gn:asciiname":"Dasht-e Azadi",
    "gn:country_code":"IR",
    "gn:dem":1095,
    "gn:feature_class":"P",
    "gn:feature_code":"PPL",
    "gn:name":"Dasht-e \u0100z\u0101d\u012b",
    "gn:population":0,
    "gn:timezone":"Asia/Tehran",
    "iso:country":"IR",
    "name:fas_x_preferred":[
        "Gonb\u016bl\u012b"
    ],
    "name:fas_x_variant":[
        "\u062f\u0647\u062f\u0627\u0631\u06cc",
        "\u062f\u0633\u062a \u0622\u0632\u0627\u062f\u06cc",
        "\u062f\u0634\u062a \u0622\u0632\u0627\u062f\u06cc"
    ],
    "name:und_x_variant":[
        "Dehd\u0101r\u012b",
        "Dast \u0100z\u0101d\u012b",
        "Dasht-e \u0100z\u0101d\u012b"
    ],
    "wof:name":"Dasht-e Azadi",
    "wof:placetype":"locality"
},
  "geometry": {"coordinates":[50.50135,31.1343],"type":"Point"}
}