{
  "type": "Feature",
  "properties": {
    "gn:admin1_code":"41",
    "gn:asciiname":"Galleh Chah",
    "gn:country_code":"IR",
    "gn:dem":1265,
    "gn:feature_class":"P",
    "gn:feature_code":"PPLL",
    "gn:name":"Galleh Ch\u0101h",
    "gn:population":0,
    "gn:timezone":"Asia/Tehran",
    "iso:country":"IR",
    "name:fas_x_preferred":[
        "Galleh Ch\u0101h"
    ],
    "name:fas_x_variant":[
        "Qal\u2018eh Ch\u0101h",
        "\u06af\u0644\u0647 \u0686\u0627\u0647"
    ],
    "name:und_x_variant":[
        "\u06af\u0644\u0647 \u0686\u0627\u0647"
    ],
    "wof:name":"Galleh Chah",
    "wof:placetype":"locality"
},
  "geometry": {"coordinates":[58.1305,33.56989],"type":"Point"}
}