{
  "type": "Feature",
  "properties": {
    "gn:admin1_code":"1",
    "gn:asciiname":"Qarah Zamin",
    "gn:country_code":"IR",
    "gn:dem":1078,
    "gn:feature_class":"P",
    "gn:feature_code":"PPL",
    "gn:name":"Qarah Zam\u012bn",
    "gn:population":0,
    "gn:timezone":"Asia/Tehran",
    "iso:country":"IR",
    "name:azb_x_preferred":[
        "\u0642\u0627\u0631\u0627 \u0632\u0645\u06cc\u0646"
    ],
    "name:aze_x_preferred":[
        "Qara Zamin"
    ],
    "name:ceb_x_preferred":[
        "Qarah Zam\u012bn"
    ],
    "name:fas_x_preferred":[
        "\u0642\u064e\u0631\u064e\u0647 \u0632\u064e\u0645\u064a\u0646"
    ],
    "name:fas_x_variant":[
        "\u0642\u0631\u0647 \u0632\u0645\u06cc\u0646",
        "Qarah Zam\u012bn",
        "\u0642\u0631\u0647\u200c\u0632\u0645\u06cc\u0646"
    ],
    "name:kur_x_preferred":[
        "Qerezamin"
    ],
    "name:msa_x_preferred":[
        "Qarah Zamin"
    ],
    "name:swe_x_preferred":[
        "Qarah Zam\u012bn"
    ],
    "wof:name":"Qarah Zamin",
    "wof:placetype":"locality"
},
  "geometry": {"coordinates":[44.8432,39.1784],"type":"Point"}
}