{
  "type": "Feature",
  "properties": {
    "gn:admin1_code":"5.0",
    "gn:asciiname":"Qal`eh-ye Dezh",
    "gn:country_code":"IR",
    "gn:dem":828,
    "gn:feature_class":"P",
    "gn:feature_code":"PPL",
    "gn:name":"Qal\u2018eh-ye Dezh",
    "gn:population":0,
    "gn:timezone":"Asia/Tehran",
    "iso:country":"IR",
    "name:fas_x_preferred":[
        "Qal\u2018eh-ye Dezh"
    ],
    "name:fas_x_variant":[
        "\u0642\u0644\u0639\u0647 \u062f\u0698"
    ],
    "name:und_x_variant":[
        "\u0642\u0644\u0639\u0647 \u062f\u0698"
    ],
    "wof:name":"Qal`eh-ye Dezh",
    "wof:placetype":"locality"
},
  "geometry": {"coordinates":[50.64362,30.68265],"type":"Point"}
}