{
  "type": "Feature",
  "properties": {
    "gn:admin1_code":"11.0",
    "gn:asciiname":"Mazra",
    "gn:country_code":"IR",
    "gn:dem":280,
    "gn:feature_class":"P",
    "gn:feature_code":"PPL",
    "gn:name":"Mazr\u0101",
    "gn:population":0,
    "gn:timezone":"Asia/Tehran",
    "iso:country":"IR",
    "name:fas_x_preferred":[
        "\u0645\u0632\u0631\u0627"
    ],
    "name:und_x_variant":[
        "Mazr\u0101"
    ],
    "wof:name":"Mazra",
    "wof:placetype":"locality"
},
  "geometry": {"coordinates":[55.75209,27.49007000000001],"type":"Point"}
}