{
  "type": "Feature",
  "properties": {
    "gn:admin1_code":"11.0",
    "gn:asciiname":"Mazra",
    "gn:country_code":"IR",
    "gn:dem":280,
    "gn:feature_class":"P",
    "gn:feature_code":"PPL",
    "gn:name":"Mazr\u0101",
    "gn:population":0,
    "gn:timezone":"Asia/Tehran",
    "iso:country":"IR",
    "name:aze_x_preferred":[
        "M\u0259zr\u0259"
    ],
    "name:ceb_x_preferred":[
        "Mazra"
    ],
    "name:ckb_x_preferred":[
        "\u0645\u06d5\u0632\u0631\u06d5"
    ],
    "name:fas_x_preferred":[
        "\u0645\u0632\u0631\u0627"
    ],
    "name:hye_x_preferred":[
        "\u0544\u0561\u0566\u0580\u0561"
    ],
    "name:kat_x_preferred":[
        "\u10db\u10d0\u10d6\u10e0\u10d0"
    ],
    "name:swe_x_preferred":[
        "Mazra"
    ],
    "name:und_x_variant":[
        "Mazr\u0101"
    ],
    "wof:name":"Mazra",
    "wof:placetype":"locality"
},
  "geometry": {"coordinates":[55.75209,27.49007000000001],"type":"Point"}
}