{
  "type": "Feature",
  "properties": {
    "gn:admin1_code":"38",
    "gn:asciiname":"Atash Anbar",
    "gn:country_code":"IR",
    "gn:dem":1530,
    "gn:feature_class":"P",
    "gn:feature_code":"PPL",
    "gn:name":"\u0100tash Anb\u0101r",
    "gn:population":0,
    "gn:timezone":"Asia/Tehran",
    "iso:country":"IR",
    "name:fas_x_preferred":[
        "\u0622\u062a\u0634 \u0627\u0646\u0628\u0627\u0631"
    ],
    "name:fas_x_variant":[
        "\u0100tash Anb\u0101r",
        "\u0622\u062a\u0634\u200c\u0627\u0646\u0628\u0627\u0631"
    ],
    "wof:name":"Atash Anbar",
    "wof:placetype":"locality"
},
  "geometry": {"coordinates":[49.61409,35.78949],"type":"Point"}
}