{
  "type": "Feature",
  "properties": {
    "gn:admin1_code":"41",
    "gn:asciiname":"Kalateh-ye Khan",
    "gn:country_code":"IR",
    "gn:dem":1823,
    "gn:feature_class":"P",
    "gn:feature_code":"PPL",
    "gn:name":"Kal\u0101teh-ye Kh\u0101n",
    "gn:population":0,
    "gn:timezone":"Asia/Tehran",
    "iso:country":"IR",
    "name:fas_x_preferred":[
        "Kal\u0101teh-ye Kh\u0101n"
    ],
    "name:und_x_variant":[
        "Kal\u0101teh-i-Kh\u0101n"
    ],
    "wof:name":"Kalateh-ye Khan",
    "wof:placetype":"locality"
},
  "geometry": {"coordinates":[59.58333,32.75],"type":"Point"}
}