{
  "type": "Feature",
  "properties": {
    "gn:admin1_code":"28.0",
    "gn:admin2_code":"449483",
    "gn:asciiname":"Jonbozeh",
    "gn:country_code":"IR",
    "gn:dem":1782,
    "gn:feature_class":"P",
    "gn:feature_code":"PPL",
    "gn:name":"Jonbozeh",
    "gn:population":0,
    "gn:timezone":"Asia/Tehran",
    "iso:country":"IR",
    "name:fas_x_preferred":[
        "\u0631\u0648\u0633\u062a\u0627\u06cc \u062c\u0645\u0628\u0632\u0647"
    ],
    "name:fas_x_variant":[
        "\u062c\u0646\u0628\u0632\u0647"
    ],
    "name:und_x_variant":[
        "Jombezeh",
        "Jonbozeh",
        "\u062c\u0646\u0628\u0632\u0647",
        "Jombozeh",
        "Jumbazeh"
    ],
    "wof:name":"Jonbozeh",
    "wof:placetype":"locality"
},
  "geometry": {"coordinates":[51.62898,32.16769],"type":"Point"}
}