{
  "type": "Feature",
  "properties": {
    "gn:admin1_code":"8",
    "gn:asciiname":"Kharashk-e Bala",
    "gn:country_code":"IR",
    "gn:dem":169,
    "gn:feature_class":"P",
    "gn:feature_code":"PPL",
    "gn:name":"Kharashk-e B\u0101l\u0101",
    "gn:population":0,
    "gn:timezone":"Asia/Tehran",
    "iso:country":"IR",
    "name:fas_x_preferred":[
        "Kharashk-e B\u0101l\u0101"
    ],
    "wof:name":"Kharashk-e Bala",
    "wof:placetype":"locality"
},
  "geometry": {"coordinates":[49.53923,36.88243],"type":"Point"}
}