{
  "type": "Feature",
  "properties": {
    "gn:admin1_code":"41",
    "gn:asciiname":"Bidmeshk",
    "gn:country_code":"IR",
    "gn:dem":1701,
    "gn:feature_class":"P",
    "gn:feature_code":"PPL",
    "gn:name":"B\u012bdmeshk",
    "gn:population":0,
    "gn:timezone":"Asia/Tehran",
    "iso:country":"IR",
    "name:fas_x_preferred":[
        "\u0628\u06cc\u062f\u0645\u0634\u06a9"
    ],
    "name:fas_x_variant":[
        "B\u012bdmeshk"
    ],
    "name:und_x_variant":[
        "B\u012bdmushk",
        "B\u012bdmoshk"
    ],
    "wof:name":"Bidmeshk",
    "wof:placetype":"locality"
},
  "geometry": {"coordinates":[59.17818000000001,33.59958],"type":"Point"}
}