{
  "type": "Feature",
  "properties": {
    "gn:admin1_code":"8",
    "gn:asciiname":"Barmacheh",
    "gn:country_code":"IR",
    "gn:dem":-12,
    "gn:feature_class":"P",
    "gn:feature_code":"PPL",
    "gn:name":"Barmacheh",
    "gn:population":0,
    "gn:timezone":"Asia/Tehran",
    "iso:country":"IR",
    "name:fas_x_preferred":[
        "\u0628\u0631\u0645\u0686\u0647"
    ],
    "name:fas_x_variant":[
        "\u0628\u0632\u0645\u0686\u0647 \u067e\u0627\u064a\u064a\u0646 \u0645\u062d\u0644\u0647"
    ],
    "name:und_x_variant":[
        "Barmacheh-ye B\u0101l\u0101 Ma\u1e29alleh",
        "Barmache",
        "Barmacheh",
        "\u0628\u0631\u0645\u0686\u0647",
        "Bazmacheh-ye P\u0101\u2019\u012bn Ma\u1e29alleh"
    ],
    "wof:name":"Barmacheh",
    "wof:placetype":"locality"
},
  "geometry": {"coordinates":[49.66956,37.35567],"type":"Point"}
}