{
  "type": "Feature",
  "properties": {
    "gn:admin1_code":"15.0",
    "gn:asciiname":"Benvar-e `Olya",
    "gn:country_code":"IR",
    "gn:dem":6,
    "gn:feature_class":"P",
    "gn:feature_code":"PPL",
    "gn:name":"Benv\u0101r-e \u2018Oly\u0101",
    "gn:population":0,
    "gn:timezone":"Asia/Tehran",
    "iso:country":"IR",
    "name:fas_x_preferred":[
        "\u0628\u0646\u0648\u0627\u0631 \u0639\u0644\u06cc\u0627"
    ],
    "name:fas_x_variant":[
        "\u0628\u0646\u0648\u0627\u0631"
    ],
    "name:und_x_variant":[
        "Benv\u0101r-e \u2018Oly\u0101",
        "Benv\u0101r"
    ],
    "wof:name":"Benvar-e `Olya",
    "wof:placetype":"locality"
},
  "geometry": {"coordinates":[48.69626,30.76111],"type":"Point"}
}