{
  "type": "Feature",
  "properties": {
    "gn:admin1_code":"37",
    "gn:asciiname":"Qezel Otaq",
    "gn:country_code":"IR",
    "gn:dem":377,
    "gn:feature_class":"P",
    "gn:feature_code":"PPL",
    "gn:name":"Qezel O\u0163\u0101q",
    "gn:population":0,
    "gn:timezone":"Asia/Tehran",
    "iso:country":"IR",
    "name:fas_x_preferred":[
        "\u0642\u0650\u0632\u0650\u0644 \u0627\u064e\u062a\u064e\u0648\u0621\u0627\u0631\u064e\u0628"
    ],
    "name:fas_x_variant":[
        "Qezel O\u0163\u0101q",
        "\u0642\u0632\u0644 \u0627\u0637\u0627\u0642"
    ],
    "name:und_x_variant":[
        "Qezel Atav\u2019\u0101rab",
        "\u0642\u0632\u0644 \u0627\u0637\u0627\u0642"
    ],
    "wof:name":"Qezel Otaq",
    "wof:placetype":"locality"
},
  "geometry": {"coordinates":[55.78059,37.63018],"type":"Point"}
}