{
  "type": "Feature",
  "properties": {
    "gn:admin1_code":"11",
    "gn:asciiname":"Lavar Khesht",
    "gn:country_code":"IR",
    "gn:dem":519,
    "gn:feature_class":"P",
    "gn:feature_code":"PPL",
    "gn:name":"L\u0101var Khesht",
    "gn:population":0,
    "gn:timezone":"Asia/Tehran",
    "iso:country":"IR",
    "name:ara_x_preferred":[
        "\u0644\u0627\u0648\u0631 \u062e\u0634\u062a"
    ],
    "name:fas_x_preferred":[
        "\u0644\u0627\u0648\u0631 \u062e\u0634\u062a"
    ],
    "name:fas_x_variant":[
        "L\u0101var-e Khasht",
        "\u0644\u0627\u0648\u0631 \u062e\u0634\u062a \u0634\u0645\u0627\u0644\u06cc",
        "\u0644\u0627\u0648\u0631\u062e\u0634\u062a"
    ],
    "name:msa_x_preferred":[
        "Lavar Khesht"
    ],
    "name:und_x_variant":[
        "L\u0101var Khesht",
        "L\u0101var Khesht-e Shom\u0101l\u012b"
    ],
    "wof:name":"Lavar Khesht",
    "wof:placetype":"locality"
},
  "geometry": {"coordinates":[53.44531,27.14497],"type":"Point"}
}