{
  "type": "Feature",
  "properties": {
    "gn:admin1_code":"5",
    "gn:asciiname":"`Emarat",
    "gn:country_code":"IR",
    "gn:dem":809,
    "gn:feature_class":"P",
    "gn:feature_code":"PPL",
    "gn:name":"\u2018Em\u0101rat",
    "gn:population":0,
    "gn:timezone":"Asia/Tehran",
    "iso:country":"IR",
    "name:fas_x_preferred":[
        "\u0639\u0645\u0627\u0631\u062a"
    ],
    "name:fas_x_variant":[
        "\u0627\u064e\u0645\u0627\u0631\u064e\u062a",
        "\u2018Em\u0101rat"
    ],
    "name:und_x_variant":[
        "Am\u0101rat"
    ],
    "wof:name":"`Emarat",
    "wof:placetype":"locality"
},
  "geometry": {"coordinates":[50.63719,30.95791],"type":"Point"}
}