{
  "type": "Feature",
  "properties": {
    "gn:admin1_code":"13",
    "gn:asciiname":"Zardeh",
    "gn:country_code":"IR",
    "gn:dem":1074,
    "gn:feature_class":"P",
    "gn:feature_code":"PPL",
    "gn:name":"Zardeh",
    "gn:population":0,
    "gn:timezone":"Asia/Tehran",
    "iso:country":"IR",
    "name:fas_x_preferred":[
        "\u0632\u0631\u062f\u0647"
    ],
    "name:und_x_variant":[
        "Razdeh",
        "Zarde",
        "Zardeh"
    ],
    "wof:name":"Zardeh",
    "wof:placetype":"locality"
},
  "geometry": {"coordinates":[45.95271,34.54875999999999],"type":"Point"}
}