{
  "type": "Feature",
  "properties": {
    "gn:admin1_code":"33.0",
    "gn:asciiname":"`Aliabad-e Pa'in",
    "gn:country_code":"IR",
    "gn:dem":1609,
    "gn:feature_class":"P",
    "gn:feature_code":"PPL",
    "gn:name":"\u2018Al\u012b\u0101b\u0101d-e P\u0101\u2019\u012bn",
    "gn:population":0,
    "gn:timezone":"Asia/Tehran",
    "iso:country":"IR",
    "name:fas_x_preferred":[
        "\u0639\u0644\u06cc \u0622\u0628\u0627\u062f \u067e\u0627\u0626\u06cc\u0646"
    ],
    "name:fas_x_variant":[
        "\u2018Al\u012b\u0101b\u0101d-e Sofl\u00e1",
        "\u2018Al\u012b\u0101b\u0101d-e P\u0101\u2019\u012bn"
    ],
    "name:und_x_variant":[
        "\u2018Al\u012b\u0101b\u0101d"
    ],
    "wof:name":"`Aliabad-e Pa'in",
    "wof:placetype":"locality"
},
  "geometry": {"coordinates":[47.1005,37.4524],"type":"Point"}
}