{
  "type": "Feature",
  "properties": {
    "gn:admin1_code":"15.0",
    "gn:asciiname":"Sharu",
    "gn:country_code":"IR",
    "gn:dem":1153,
    "gn:feature_class":"P",
    "gn:feature_code":"PPL",
    "gn:name":"Shar\u016b",
    "gn:population":0,
    "gn:timezone":"Asia/Tehran",
    "iso:country":"IR",
    "name:ara_x_preferred":[
        "\u0634\u0631\u0648"
    ],
    "name:azb_x_preferred":[
        "\u0634\u0631\u0648(\u0627\u0646\u062f\u06cc\u0645\u0634\u06a9)"
    ],
    "name:fas_x_preferred":[
        "\u0634\u0631\u0648"
    ],
    "name:fas_x_variant":[
        "Shar\u016b"
    ],
    "wof:name":"Sharu",
    "wof:placetype":"locality"
},
  "geometry": {"coordinates":[48.2452,32.9276],"type":"Point"}
}