{
  "type": "Feature",
  "properties": {
    "gn:admin1_code":"32.0",
    "gn:asciiname":"Qeshlaq-e Tang",
    "gn:country_code":"IR",
    "gn:dem":907,
    "gn:feature_class":"P",
    "gn:feature_code":"PPL",
    "gn:name":"Qeshl\u0101q-e Tang",
    "gn:population":0,
    "gn:timezone":"Asia/Tehran",
    "iso:country":"IR",
    "name:fas_x_preferred":[
        "\u0642\u0634\u0644\u0627\u0642 \u062a\u0646\u06af"
    ],
    "name:und_x_variant":[
        "Qeshl\u0101q-e Tang"
    ],
    "wof:name":"Qeshlaq-e Tang",
    "wof:placetype":"locality"
},
  "geometry": {"coordinates":[47.6696,38.53942],"type":"Point"}
}