{
  "type": "Feature",
  "properties": {
    "gn:admin1_code":"32",
    "gn:asciiname":"Maqsudlu",
    "gn:country_code":"IR",
    "gn:dem":188,
    "gn:feature_class":"P",
    "gn:feature_code":"PPL",
    "gn:name":"Maq\u015f\u016bdl\u016b",
    "gn:population":0,
    "gn:timezone":"Asia/Tehran",
    "iso:country":"IR",
    "name:aze_x_preferred":[
        "Maqsudlu"
    ],
    "name:fas_x_preferred":[
        "\u0645\u064e\u0642\u0635\u0648\u062f\u0644\u0648"
    ],
    "name:fas_x_variant":[
        "\u0645\u0642\u0635\u0648\u062f\u0644\u0648"
    ],
    "name:kat_x_preferred":[
        "\u10db\u10d0\u10e5\u10e1\u10e3\u10d3\u10da\u10e3"
    ],
    "name:und_x_variant":[
        "Maq\u015f\u016bdl\u016b"
    ],
    "wof:name":"Maqsudlu",
    "wof:placetype":"locality"
},
  "geometry": {"coordinates":[47.54333,39.4675],"type":"Point"}
}