{
  "type": "Feature",
  "properties": {
    "gn:admin1_code":"15",
    "gn:asciiname":"Sarguf",
    "gn:country_code":"IR",
    "gn:dem":918,
    "gn:feature_class":"P",
    "gn:feature_code":"PPL",
    "gn:name":"Sarg\u016bf",
    "gn:population":0,
    "gn:timezone":"Asia/Tehran",
    "iso:country":"IR",
    "name:fas_x_preferred":[
        "Sarg\u016bf"
    ],
    "wof:name":"Sarguf",
    "wof:placetype":"locality"
},
  "geometry": {"coordinates":[50.29917,31.59917],"type":"Point"}
}