{
  "type": "Feature",
  "properties": {
    "gn:admin1_code":"26.0",
    "gn:asciiname":"Davudiyeh",
    "gn:country_code":"IR",
    "gn:dem":1048,
    "gn:feature_class":"P",
    "gn:feature_code":"PPL",
    "gn:name":"D\u0101v\u016bd\u012byeh",
    "gn:population":0,
    "gn:timezone":"Asia/Tehran",
    "iso:country":"IR",
    "name:fas_x_preferred":[
        "\u062f\u0627\u0648\u0648\u062f\u06cc\u0647"
    ],
    "name:fas_x_variant":[
        "D\u0101v\u016bd\u012byeh"
    ],
    "wof:name":"Davudiyeh",
    "wof:placetype":"locality"
},
  "geometry": {"coordinates":[51.0643,35.4905],"type":"Point"}
}