{
  "type": "Feature",
  "properties": {
    "gn:admin1_code":"13",
    "gn:asciiname":"Ahangaran",
    "gn:country_code":"IR",
    "gn:dem":1290,
    "gn:feature_class":"P",
    "gn:feature_code":"PPL",
    "gn:name":"\u0100hangar\u0101n",
    "gn:population":0,
    "gn:timezone":"Asia/Tehran",
    "iso:country":"IR",
    "name:fas_x_preferred":[
        "\u0622\u0647\u0646\u06af\u0631\u0627\u0646"
    ],
    "name:fas_x_variant":[
        "\u0100hangar\u0101n"
    ],
    "name:urd_x_preferred":[
        "\u0622\u06c1\u0646\u06af\u0627\u0631\u0627\u0646"
    ],
    "wof:name":"Ahangaran",
    "wof:placetype":"locality"
},
  "geometry": {"coordinates":[47.5786,34.4495],"type":"Point"}
}