{
  "type": "Feature",
  "properties": {
    "gn:admin1_code":"29",
    "gn:asciiname":"Dehnow-ye Borhani",
    "gn:country_code":"IR",
    "gn:dem":701,
    "gn:feature_class":"P",
    "gn:feature_code":"PPL",
    "gn:name":"Dehnow-ye Borh\u0101n\u012b",
    "gn:population":0,
    "gn:timezone":"Asia/Tehran",
    "iso:country":"IR",
    "name:fas_x_preferred":[
        "\u062f\u0647\u0646\u0648 \u0628\u0631\u0647\u0627\u0646\u06cc"
    ],
    "name:fas_x_variant":[
        "Deh Now-e Borh\u0101n\u012b",
        "\u062f\u0647\u0646\u0648 \u0627\u0646\u0635\u0627\u0631\u06cc"
    ],
    "name:und_x_variant":[
        "Dehnow-ye Borh\u0101n\u012b",
        "Dehnow-ye An\u015f\u0101r\u012b",
        "Deh Now-e Rabb\u0101n\u012b",
        "Deh Now Rabb\u0101n\u012b",
        "Deh Now-ye Rabb\u0101n\u012b"
    ],
    "wof:name":"Dehnow-ye Borhani",
    "wof:placetype":"locality"
},
  "geometry": {"coordinates":[58.8546,28.9233],"type":"Point"}
}