{
  "type": "Feature",
  "properties": {
    "gn:admin1_code":"42",
    "gn:asciiname":"Hesar Now",
    "gn:country_code":"IR",
    "gn:dem":1125,
    "gn:feature_class":"P",
    "gn:feature_code":"PPL",
    "gn:name":"\u1e28e\u015f\u0101r Now",
    "gn:population":0,
    "gn:timezone":"Asia/Tehran",
    "iso:country":"IR",
    "name:fas_x_preferred":[
        "\u062d\u0635\u0627\u0631 \u0646\u0648"
    ],
    "name:fas_x_variant":[
        "\u1e28e\u015f\u0101r Now",
        "\u062d\u0635\u0627\u0631\u0646\u0648"
    ],
    "wof:name":"Hesar Now",
    "wof:placetype":"locality"
},
  "geometry": {"coordinates":[58.65996,36.04169],"type":"Point"}
}