{
  "type": "Feature",
  "properties": {
    "gn:admin1_code":"42",
    "gn:asciiname":"Kaj",
    "gn:country_code":"IR",
    "gn:dem":1627,
    "gn:feature_class":"P",
    "gn:feature_code":"PPL",
    "gn:name":"K\u0101j",
    "gn:population":0,
    "gn:timezone":"Asia/Tehran",
    "iso:country":"IR",
    "name:fas_x_preferred":[
        "\u06af\u0627\u0686"
    ],
    "name:fas_x_variant":[
        "G\u0101ch",
        "\u06a9\u0627\u062c"
    ],
    "name:und_x_variant":[
        "K\u0101j"
    ],
    "wof:name":"Kaj",
    "wof:placetype":"locality"
},
  "geometry": {"coordinates":[57.69886,35.92471],"type":"Point"}
}