{
  "type": "Feature",
  "properties": {
    "gn:admin1_code":"15",
    "gn:asciiname":"Posht Darb-e `Olya",
    "gn:country_code":"IR",
    "gn:dem":85,
    "gn:feature_class":"P",
    "gn:feature_code":"PPL",
    "gn:name":"Posht Darb-e \u2018Oly\u0101",
    "gn:population":0,
    "gn:timezone":"Asia/Tehran",
    "iso:country":"IR",
    "name:fas_x_preferred":[
        "\u067e\u0634\u062a \u062f\u0631\u0628 \u0639\u0644\u06cc\u0627"
    ],
    "name:fas_x_variant":[
        "Posht Darb-e \u2018Oly\u0101",
        "\u0628\u0646\u0647 \u0631\u062d\u0645\u0627\u0646\u06cc",
        "\u067e\u0634\u062a \u062f\u0631\u0628"
    ],
    "name:und_x_variant":[
        "Boneh-ye Rahm\u0101n\u012b",
        "Posht Darb"
    ],
    "wof:name":"Posht Darb-e `Olya",
    "wof:placetype":"locality"
},
  "geometry": {"coordinates":[48.89685,32.22584000000001],"type":"Point"}
}