{
  "type": "Feature",
  "properties": {
    "gn:admin1_code":"7",
    "gn:asciiname":"Murdabi-ye Bala",
    "gn:country_code":"IR",
    "gn:dem":960,
    "gn:feature_class":"P",
    "gn:feature_code":"PPL",
    "gn:name":"M\u016brd\u0101b\u012b-ye B\u0101l\u0101",
    "gn:population":0,
    "gn:timezone":"Asia/Tehran",
    "iso:country":"IR",
    "name:fas_x_preferred":[
        "M\u016brd\u0101b\u012b-ye B\u0101l\u0101"
    ],
    "wof:name":"Murdabi-ye Bala",
    "wof:placetype":"locality"
},
  "geometry": {"coordinates":[51.53333,30.11667000000001],"type":"Point"}
}