{
  "type": "Feature",
  "properties": {
    "gn:admin1_code":"34",
    "gn:asciiname":"Masanabad",
    "gn:country_code":"IR",
    "gn:dem":1673,
    "gn:feature_class":"P",
    "gn:feature_code":"PPL",
    "gn:name":"Masan\u0101b\u0101d",
    "gn:population":0,
    "gn:timezone":"Asia/Tehran",
    "iso:country":"IR",
    "name:ara_x_preferred":[
        "\u0645\u0633\u0646 \u0623\u0628\u0627\u062f"
    ],
    "name:ceb_x_preferred":[
        "Masen\u0101b\u0101d"
    ],
    "name:fas_x_preferred":[
        "\u0645\u064e\u0633\u0646 \u0622\u0628\u0627\u062f"
    ],
    "name:fas_x_variant":[
        "Masen\u0101b\u0101d",
        "\u0645\u0633\u0646 \u0622\u0628\u0627\u062f",
        "\u0645\u0633\u0646\u200c\u0622\u0628\u0627\u062f"
    ],
    "name:swe_x_preferred":[
        "Masen\u0101b\u0101d"
    ],
    "name:ukr_x_preferred":[
        "\u041c\u0430\u0441\u0435\u043d\u0430\u0431\u0430\u0434"
    ],
    "name:und_x_variant":[
        "Masan\u0101b\u0101d",
        "Masn\u0101b\u0101d",
        "\u0645\u0633\u0646 \u0622\u0628\u0627\u062f"
    ],
    "wof:name":"Masanabad",
    "wof:placetype":"locality"
},
  "geometry": {"coordinates":[49.65628,34.28713],"type":"Point"}
}