{
  "type": "Feature",
  "properties": {
    "gn:admin1_code":"15",
    "gn:asciiname":"`Azib",
    "gn:country_code":"IR",
    "gn:dem":45,
    "gn:feature_class":"P",
    "gn:feature_code":"PPL",
    "gn:name":"\u2018Az\u012bb",
    "gn:population":0,
    "gn:timezone":"Asia/Tehran",
    "iso:country":"IR",
    "name:fas_x_preferred":[
        "\u2018Az\u012bb"
    ],
    "name:und_x_variant":[
        "\u1e28am\u012bd"
    ],
    "wof:name":"`Azib",
    "wof:placetype":"locality"
},
  "geometry": {"coordinates":[48.57861,31.98889],"type":"Point"}
}