{
  "type": "Feature",
  "properties": {
    "gn:admin1_code":"8",
    "gn:asciiname":"Owlaru",
    "gn:country_code":"IR",
    "gn:dem":643,
    "gn:feature_class":"P",
    "gn:feature_code":"PPLL",
    "gn:name":"Owl\u0101r\u016b",
    "gn:population":0,
    "gn:timezone":"Asia/Tehran",
    "iso:country":"IR",
    "name:fas_x_preferred":[
        "Past\u012b Ras\u016bn"
    ],
    "name:fas_x_variant":[
        "Posht\u012b Ras\u016bn",
        "\u0627\u0648\u0644\u0627\u0631\u0648",
        "\u067e\u0633\u06cc \u0631\u0633\u0648\u0646"
    ],
    "name:und_x_variant":[
        "Owl\u0101r\u016b",
        "Pas\u012b Ras\u016bn"
    ],
    "wof:name":"Owlaru",
    "wof:placetype":"locality"
},
  "geometry": {"coordinates":[48.80458,37.77555],"type":"Point"}
}