{
  "type": "Feature",
  "properties": {
    "gn:admin1_code":"4.0",
    "gn:asciiname":"Kamu Bazar",
    "gn:country_code":"IR",
    "gn:dem":34,
    "gn:feature_class":"P",
    "gn:feature_code":"PPL",
    "gn:name":"K\u0101m\u016b B\u0101z\u0101r",
    "gn:population":0,
    "gn:timezone":"Asia/Tehran",
    "iso:country":"IR",
    "name:ara_x_preferred":[
        "\u0643\u0645\u0648\u0628\u0627\u0632\u0627\u0631"
    ],
    "name:fas_x_preferred":[
        "K\u0101m\u016b B\u0101z\u0101r"
    ],
    "name:fas_x_variant":[
        "\u06a9\u0627\u0645\u0648 \u0628\u0627\u0632\u0627\u0631",
        "\u06a9\u0645\u0648\u0628\u0627\u0632\u0627\u0631"
    ],
    "wof:name":"Kamu Bazar",
    "wof:placetype":"locality"
},
  "geometry": {"coordinates":[61.09172,25.57996],"type":"Point"}
}