{
  "type": "Feature",
  "properties": {
    "gn:admin1_code":"7",
    "gn:asciiname":"Kuh-e Sar Gachineh",
    "gn:country_code":"IR",
    "gn:dem":2538,
    "gn:feature_class":"P",
    "gn:feature_code":"PPL",
    "gn:name":"K\u016bh-e Sar Gach\u012bneh",
    "gn:population":0,
    "gn:timezone":"Asia/Tehran",
    "iso:country":"IR",
    "name:fas_x_preferred":[
        "K\u016bh-e Sar Gach\u012bneh"
    ],
    "wof:name":"Kuh-e Sar Gachineh",
    "wof:placetype":"locality"
},
  "geometry": {"coordinates":[51.57944000000001,30.41694],"type":"Point"}
}