{
  "type": "Feature",
  "properties": {
    "gn:admin1_code":"32",
    "gn:asciiname":"Ja`far Qoli Khan",
    "gn:country_code":"IR",
    "gn:dem":42,
    "gn:feature_class":"P",
    "gn:feature_code":"PPL",
    "gn:name":"Ja\u2018far Qol\u012b Kh\u0101n",
    "gn:population":0,
    "gn:timezone":"Asia/Tehran",
    "iso:country":"IR",
    "name:fas_x_preferred":[
        "\u062c\u0639\u0641\u0631 \u0642\u0644\u06cc \u062e\u0627\u0646"
    ],
    "name:fas_x_variant":[
        "Ja\u2018far Qol\u012b Kh\u0101n"
    ],
    "wof:name":"Ja`far Qoli Khan",
    "wof:placetype":"locality"
},
  "geometry": {"coordinates":[47.9272,39.6572],"type":"Point"}
}