{
  "type": "Feature",
  "properties": {
    "gn:admin1_code":"8",
    "gn:asciiname":"Karsang",
    "gn:country_code":"IR",
    "gn:dem":1621,
    "gn:feature_class":"P",
    "gn:feature_code":"PPL",
    "gn:name":"K\u0101rsang",
    "gn:population":0,
    "gn:timezone":"Asia/Tehran",
    "iso:country":"IR",
    "name:fas_x_preferred":[
        "K\u0101rsang"
    ],
    "name:fas_x_variant":[
        "\u06a9\u0627\u0631\u0633\u0646\u06af",
        "\u06a9\u0627\u0631\u0633\u0646\u06af \u0634\u0627\u0647\u06cc \u062c\u0627\u0646"
    ],
    "name:ukr_x_preferred":[
        "\u041a\u0430\u0440\u0441\u0430\u043d\u0491-\u0435-\u0428\u0430\u0433\u0456-\u0414\u0436\u0430\u043d"
    ],
    "name:und_x_variant":[
        "\u06a9\u0627\u0631\u0633\u0646\u06af",
        "K\u0101rsang-e Sh\u0101h\u012b J\u0101n"
    ],
    "wof:name":"Karsang",
    "wof:placetype":"locality"
},
  "geometry": {"coordinates":[50.07671,36.75524],"type":"Point"}
}