{
  "type": "Feature",
  "properties": {
    "gn:admin1_code":"29",
    "gn:asciiname":"Jalalabad",
    "gn:country_code":"IR",
    "gn:dem":2227,
    "gn:feature_class":"P",
    "gn:feature_code":"PPL",
    "gn:name":"Jal\u0101l\u0101b\u0101d",
    "gn:population":0,
    "gn:timezone":"Asia/Tehran",
    "iso:country":"IR",
    "name:fas_x_preferred":[
        "\u062c\u0644\u0627\u0644 \u0622\u0628\u0627\u062f"
    ],
    "name:fas_x_variant":[
        "Jal\u0101l\u0101b\u0101d"
    ],
    "wof:name":"Jalalabad",
    "wof:placetype":"locality"
},
  "geometry": {"coordinates":[55.4399,30.354],"type":"Point"}
}