{
  "type": "Feature",
  "properties": {
    "gn:admin1_code":"7",
    "gn:asciiname":"Faryab",
    "gn:country_code":"IR",
    "gn:dem":443,
    "gn:feature_class":"P",
    "gn:feature_code":"PPL",
    "gn:name":"F\u0101ry\u0101b",
    "gn:population":0,
    "gn:timezone":"Asia/Tehran",
    "iso:country":"IR",
    "name:fas_x_preferred":[
        "\u0641\u0627\u0631\u06cc\u0627\u0628"
    ],
    "name:fas_x_variant":[
        "F\u0101ry\u0101b"
    ],
    "name:msa_x_preferred":[
        "Faryab"
    ],
    "name:und_x_variant":[
        "F\u0101ry\u0101b-e Var\u0101d\u012b",
        "F\u0101ri\u0101b",
        "F\u0101rey\u0101b",
        "Fariyab Varadi"
    ],
    "wof:name":"Faryab",
    "wof:placetype":"locality"
},
  "geometry": {"coordinates":[52.9399,27.4905],"type":"Point"}
}