{
  "type": "Feature",
  "properties": {
    "gn:admin1_code":"23",
    "gn:asciiname":"Mahrokhi",
    "gn:country_code":"IR",
    "gn:dem":1734,
    "gn:feature_class":"P",
    "gn:feature_code":"PPL",
    "gn:name":"M\u0101hrokh\u012b",
    "gn:population":0,
    "gn:timezone":"Asia/Tehran",
    "iso:country":"IR",
    "name:fas_x_preferred":[
        "\u0645\u0631\u0651\u064a\u062e\u06cc"
    ],
    "name:fas_x_variant":[
        "Merr\u012bkh\u012b",
        "\u0645\u0627\u0647\u0631\u062e\u06cc"
    ],
    "name:und_x_variant":[
        "M\u0101hrokh\u012b"
    ],
    "wof:name":"Mahrokhi",
    "wof:placetype":"locality"
},
  "geometry": {"coordinates":[48.6609,33.6525],"type":"Point"}
}