{
  "type": "Feature",
  "properties": {
    "gn:admin1_code":"26",
    "gn:asciiname":"Haft Jubeh",
    "gn:country_code":"IR",
    "gn:dem":868,
    "gn:feature_class":"P",
    "gn:feature_code":"PPL",
    "gn:name":"Haft J\u016bbeh",
    "gn:population":0,
    "gn:timezone":"Asia/Tehran",
    "iso:country":"IR",
    "name:ceb_x_preferred":[
        "Haft J\u016bbeh"
    ],
    "name:fas_x_preferred":[
        "Haft J\u016bbeh"
    ],
    "name:fas_x_variant":[
        "\u0647\u0641\u062a \u062c\u0648\u0628\u0647"
    ],
    "name:swe_x_preferred":[
        "Haft J\u016bbeh"
    ],
    "name:und_x_variant":[
        "\u0647\u0641\u062a \u062c\u0648\u0628\u0647"
    ],
    "wof:name":"Haft Jubeh",
    "wof:placetype":"locality"
},
  "geometry": {"coordinates":[51.681,35.2529],"type":"Point"}
}