{
  "type": "Feature",
  "properties": {
    "gn:admin1_code":"7",
    "gn:asciiname":"Gar-e Sefid",
    "gn:country_code":"IR",
    "gn:dem":1198,
    "gn:feature_class":"P",
    "gn:feature_code":"PPL",
    "gn:name":"Gar-e Sef\u012bd",
    "gn:population":0,
    "gn:timezone":"Asia/Tehran",
    "iso:country":"IR",
    "name:fas_x_preferred":[
        "Gar-e Sef\u012bd"
    ],
    "wof:name":"Gar-e Sefid",
    "wof:placetype":"locality"
},
  "geometry": {"coordinates":[51.36417,30.04194],"type":"Point"}
}