{
  "type": "Feature",
  "properties": {
    "gn:admin1_code":"4.0",
    "gn:asciiname":"Akhovvatabad",
    "gn:country_code":"IR",
    "gn:dem":1233,
    "gn:feature_class":"P",
    "gn:feature_code":"PPL",
    "gn:name":"Akhovvat\u0101b\u0101d",
    "gn:population":0,
    "gn:timezone":"Asia/Tehran",
    "iso:country":"IR",
    "name:fas_x_preferred":[
        "\u0627\u062e\u0648\u062a \u0622\u0628\u0627\u062f"
    ],
    "name:und_x_variant":[
        "Akhovvat\u0101b\u0101d"
    ],
    "wof:name":"Akhovvatabad",
    "wof:placetype":"locality"
},
  "geometry": {"coordinates":[62.05585,27.34763],"type":"Point"}
}