{
  "type": "Feature",
  "properties": {
    "gn:admin1_code":"11",
    "gn:asciiname":"Negar-e Pa'in",
    "gn:country_code":"IR",
    "gn:dem":16,
    "gn:feature_class":"P",
    "gn:feature_code":"PPL",
    "gn:name":"Negar-e P\u0101\u2019\u012bn",
    "gn:population":0,
    "gn:timezone":"Asia/Tehran",
    "iso:country":"IR",
    "name:fas_x_preferred":[
        "\u0646\u0648\u0648\u0627\u0631\u0650 \u0628\u0627\u0644\u0627"
    ],
    "name:fas_x_variant":[
        "Negar-e P\u0101\u2019\u012bn",
        "\u0646\u06af\u0631 \u067e\u0627\u0626\u064a\u0646",
        "\u0646\u06af\u0631 \u067e\u0627\u06cc\u06cc\u0646"
    ],
    "name:msa_x_preferred":[
        "Negar-e Pain"
    ],
    "name:und_x_variant":[
        "N\u016bv\u0101r-e B\u0101l\u0101",
        "\u0646\u06af\u0631 \u067e\u0627\u0626\u064a\u0646"
    ],
    "wof:name":"Negar-e Pa'in",
    "wof:placetype":"locality"
},
  "geometry": {"coordinates":[57.61496,25.83877],"type":"Point"}
}