{
  "type": "Feature",
  "properties": {
    "gn:admin1_code":"23",
    "gn:asciiname":"Ziveh Dar",
    "gn:country_code":"IR",
    "gn:dem":1591,
    "gn:feature_class":"P",
    "gn:feature_code":"PPL",
    "gn:name":"Z\u012bveh D\u0101r",
    "gn:population":0,
    "gn:timezone":"Asia/Tehran",
    "iso:country":"IR",
    "name:ara_x_preferred":[
        "\u0632\u064a\u0648\u0629 \u062f\u0627\u0631"
    ],
    "name:fas_x_preferred":[
        "\u0632\u064a\u0648\u0647 \u062f\u0627\u0631"
    ],
    "name:fas_x_variant":[
        "Z\u012bvar D\u0101r",
        "Z\u012bveh D\u0101r",
        "\u0632\u06cc\u0648\u0647 \u062f\u0627\u0631"
    ],
    "name:und_x_variant":[
        "S\u012bveh Dar",
        "Siwadar",
        "Zobeyd\u0101r"
    ],
    "wof:name":"Ziveh Dar",
    "wof:placetype":"locality"
},
  "geometry": {"coordinates":[48.8662,33.6419],"type":"Point"}
}