{
  "type": "Feature",
  "properties": {
    "gn:admin1_code":"0",
    "gn:asciiname":"Dahaneh-ye Na'iz",
    "gn:country_code":"IR",
    "gn:dem":372,
    "gn:feature_class":"P",
    "gn:feature_code":"PPL",
    "gn:name":"Dahaneh-ye N\u0101\u2019\u012bz",
    "gn:population":0,
    "gn:timezone":"Asia/Tehran",
    "iso:country":"IR",
    "name:fas_x_preferred":[
        "\u062f\u0647\u0646\u0647 \u0646\u0627\u0626\u06cc\u0632"
    ],
    "name:fas_x_variant":[
        "Dahaneh-ye N\u0101\u2019\u012bz"
    ],
    "wof:name":"Dahaneh-ye Na'iz",
    "wof:placetype":"locality"
},
  "geometry": {"coordinates":[57.505,27.4718],"type":"Point"}
}