{
  "type": "Feature",
  "properties": {
    "gn:admin1_code":"29",
    "gn:asciiname":"Marzabad-e Sang-e Bahram",
    "gn:country_code":"IR",
    "gn:dem":1717,
    "gn:feature_class":"P",
    "gn:feature_code":"PPL",
    "gn:name":"Marz\u0101b\u0101d-e Sang-e Bahr\u0101m",
    "gn:population":0,
    "gn:timezone":"Asia/Tehran",
    "iso:country":"IR",
    "name:fas_x_preferred":[
        "Marz\u0101b\u0101d-e Sang-e Bahr\u0101m"
    ],
    "wof:name":"Marzabad-e Sang-e Bahram",
    "wof:placetype":"locality"
},
  "geometry": {"coordinates":[55.81667,28.95],"type":"Point"}
}