{
  "type": "Feature",
  "properties": {
    "gn:admin1_code":"7",
    "gn:asciiname":"Hoseynabad",
    "gn:country_code":"IR",
    "gn:dem":1596,
    "gn:feature_class":"P",
    "gn:feature_code":"PPL",
    "gn:name":"\u1e28oseyn\u0101b\u0101d",
    "gn:population":0,
    "gn:timezone":"Asia/Tehran",
    "iso:country":"IR",
    "name:aze_x_preferred":[
        "H\u00fcseynabad"
    ],
    "name:ceb_x_preferred":[
        "Hoseynabad"
    ],
    "name:fas_x_preferred":[
        "\u0686\u0627\u0647 \u0645\u062d\u0645\u062f \u0639\u0627\u0628\u062f\u06cc"
    ],
    "name:fas_x_variant":[
        "Ch\u0101h Mo\u1e29ammad-e \u2018\u0100bed\u012b",
        "\u062d\u0633\u064a\u0646 \u0622\u0628\u0627\u062f",
        "\u062d\u0633\u06cc\u0646\u200c\u0622\u0628\u0627\u062f"
    ],
    "name:mzn_x_preferred":[
        "\u062d\u0633\u06cc\u0646\u200c\u0622\u0628\u0627\u062f"
    ],
    "name:swe_x_preferred":[
        "Hoseynabad"
    ],
    "name:und_x_variant":[
        "\u1e28oseyn\u0101b\u0101d"
    ],
    "wof:name":"Hoseynabad",
    "wof:placetype":"locality"
},
  "geometry": {"coordinates":[55.0425,28.8481],"type":"Point"}
}