{
  "type": "Feature",
  "properties": {
    "gn:admin1_code":"11",
    "gn:asciiname":"Posht Band",
    "gn:country_code":"IR",
    "gn:dem":1126,
    "gn:feature_class":"P",
    "gn:feature_code":"PPL",
    "gn:name":"Posht Band",
    "gn:population":0,
    "gn:timezone":"Asia/Tehran",
    "iso:country":"IR",
    "name:fas_x_preferred":[
        "\u067e\u0634\u062a \u0628\u0646\u062f"
    ],
    "name:fas_x_variant":[
        "\u067e\u064f\u0634\u062a\u0650 \u0628\u064e\u0646\u062f"
    ],
    "name:und_x_variant":[
        "Posht-e Band",
        "Posht Band"
    ],
    "wof:name":"Posht Band",
    "wof:placetype":"locality"
},
  "geometry": {"coordinates":[56.3806,27.8273],"type":"Point"}
}