{
  "type": "Feature",
  "properties": {
    "gn:admin1_code":"23",
    "gn:asciiname":"Gorizan-e Pa'in",
    "gn:country_code":"IR",
    "gn:dem":1616,
    "gn:feature_class":"P",
    "gn:feature_code":"PPL",
    "gn:name":"Gor\u012bz\u0101n-e P\u0101\u2019\u012bn",
    "gn:population":0,
    "gn:timezone":"Asia/Tehran",
    "iso:country":"IR",
    "name:ceb_x_preferred":[
        "Gor\u012bz\u0101n-e P\u0101'\u012bn"
    ],
    "name:fas_x_preferred":[
        "\u06af\u0631\u06cc\u0631\u0627\u0646 \u0633\u0641\u0644\u06cc"
    ],
    "name:fas_x_variant":[
        "Gor\u012br\u0101n-e Sofl\u00e1",
        "\u06af\u0631\u06cc\u0632\u0627\u0646 \u067e\u0627\u0626\u06cc\u0646"
    ],
    "name:swe_x_preferred":[
        "Gor\u012bz\u0101n-e P\u0101'\u012bn"
    ],
    "name:und_x_variant":[
        "Gor\u012bz\u0101n-e P\u0101\u2019\u012bn"
    ],
    "wof:name":"Gorizan-e Pa'in",
    "wof:placetype":"locality"
},
  "geometry": {"coordinates":[48.2351,33.9006],"type":"Point"}
}