{
  "type": "Feature",
  "properties": {
    "gn:admin1_code":"29",
    "gn:asciiname":"Mohammadabad-e Saqi",
    "gn:country_code":"IR",
    "gn:dem":1422,
    "gn:feature_class":"P",
    "gn:feature_code":"PPL",
    "gn:name":"Mo\u1e29ammad\u0101b\u0101d-e S\u0101q\u012b",
    "gn:population":0,
    "gn:timezone":"Asia/Tehran",
    "iso:country":"IR",
    "name:fas_x_preferred":[
        "Mo\u1e29ammad\u0101b\u0101d-e S\u0101q\u012b"
    ],
    "name:fas_x_variant":[
        "\u0645\u062d\u0645\u062f \u0622\u0628\u0627\u062f \u0633\u0627\u0642\u06cc",
        "\u0645\u062d\u0645\u062f\u0622\u0628\u0627\u062f \u0633\u0627\u0642\u06cc"
    ],
    "name:und_x_variant":[
        "\u0645\u062d\u0645\u062f \u0622\u0628\u0627\u062f \u0633\u0627\u0642\u06cc"
    ],
    "wof:name":"Mohammadabad-e Saqi",
    "wof:placetype":"locality"
},
  "geometry": {"coordinates":[55.51893000000001,30.64],"type":"Point"}
}