{
  "type": "Feature",
  "properties": {
    "gn:admin1_code":"36",
    "gn:asciiname":"Olkash",
    "gn:country_code":"IR",
    "gn:dem":1970,
    "gn:feature_class":"P",
    "gn:feature_code":"PPL",
    "gn:name":"Olkash",
    "gn:population":0,
    "gn:timezone":"Asia/Tehran",
    "iso:country":"IR",
    "name:fas_x_preferred":[
        "\u0627\u0644\u0643\u0634"
    ],
    "name:fas_x_variant":[
        "\u0627\u064e\u0644\u0650\u0646\u0643\u064e\u0634"
    ],
    "name:msa_x_preferred":[
        "Olkash"
    ],
    "name:und_x_variant":[
        "Ulkash",
        "Alenkash"
    ],
    "wof:name":"Olkash",
    "wof:placetype":"locality"
},
  "geometry": {"coordinates":[48.78025,37.15281],"type":"Point"}
}