{
  "type": "Feature",
  "properties": {
    "gn:admin1_code":"8",
    "gn:asciiname":"Dustku",
    "gn:country_code":"IR",
    "gn:dem":-15,
    "gn:feature_class":"P",
    "gn:feature_code":"PPL",
    "gn:name":"D\u016bstk\u016b",
    "gn:population":0,
    "gn:timezone":"Asia/Tehran",
    "iso:country":"IR",
    "name:ceb_x_preferred":[
        "D\u016bstk\u016b"
    ],
    "name:fas_x_preferred":[
        "D\u016bstk\u016bh"
    ],
    "name:fas_x_variant":[
        "D\u016bstk\u016b",
        "\u062f\u0648\u0633\u062a\u06a9\u0648",
        "\u062f\u0648\u0633\u062a\u06a9\u0648\u0647"
    ],
    "name:msa_x_preferred":[
        "Dustkuh"
    ],
    "name:ukr_x_preferred":[
        "\u0414\u0443\u0441\u0442\u043a\u0443\u0445"
    ],
    "name:und_x_variant":[
        "D\u016bstkadeh"
    ],
    "wof:name":"Dustku",
    "wof:placetype":"locality"
},
  "geometry": {"coordinates":[50.32394,37.10944],"type":"Point"}
}