{
  "type": "Feature",
  "properties": {
    "gn:admin1_code":"15",
    "gn:asciiname":"Boneh-ye Eskandar",
    "gn:country_code":"IR",
    "gn:dem":534,
    "gn:feature_class":"P",
    "gn:feature_code":"PPL",
    "gn:name":"Boneh-ye Eskandar",
    "gn:population":0,
    "gn:timezone":"Asia/Tehran",
    "iso:country":"IR",
    "wof:name":"Boneh-ye Eskandar",
    "wof:placetype":"locality"
},
  "geometry": {"coordinates":[49.43333,32.05],"type":"Point"}
}