{
  "type": "Feature",
  "properties": {
    "gn:admin1_code":"43",
    "gn:asciiname":"Shahrak-e Qarah Kanlu",
    "gn:country_code":"IR",
    "gn:dem":1144,
    "gn:feature_class":"P",
    "gn:feature_code":"PPL",
    "gn:name":"Shahrak-e Qarah K\u0101nl\u016b",
    "gn:population":0,
    "gn:timezone":"Asia/Tehran",
    "iso:country":"IR",
    "name:fas_x_preferred":[
        "Shahrak-e Qarah K\u0101nl\u016b"
    ],
    "name:fas_x_variant":[
        "\u0634\u0647\u0631\u06a9 \u0642\u0631\u0647 \u06a9\u0627\u0646\u0644\u0648"
    ],
    "name:und_x_variant":[
        "\u0634\u0647\u0631\u06a9 \u0642\u0631\u0647 \u06a9\u0627\u0646\u0644\u0648"
    ],
    "wof:name":"Shahrak-e Qarah Kanlu",
    "wof:placetype":"locality"
},
  "geometry": {"coordinates":[57.13457,37.60024],"type":"Point"}
}