{
  "type": "Feature",
  "properties": {
    "gn:admin1_code":"16",
    "gn:asciiname":"Dowsar",
    "gn:country_code":"IR",
    "gn:dem":1734,
    "gn:feature_class":"P",
    "gn:feature_code":"PPL",
    "gn:name":"Dowsar",
    "gn:population":0,
    "gn:timezone":"Asia/Tehran",
    "iso:country":"IR",
    "name:fas_x_preferred":[
        "\u062f\u0648 \u0633\u0631"
    ],
    "name:fas_x_variant":[
        "\u062f\u0648\u0633\u064e\u0631"
    ],
    "name:und_x_variant":[
        "D\u016bsar",
        "Do Sar"
    ],
    "wof:name":"Dowsar",
    "wof:placetype":"locality"
},
  "geometry": {"coordinates":[47.70078,35.5249],"type":"Point"}
}