{
  "type": "Feature",
  "properties": {
    "gn:admin1_code":"15",
    "gn:asciiname":"Omm ol Heyl",
    "gn:country_code":"IR",
    "gn:dem":116,
    "gn:feature_class":"P",
    "gn:feature_code":"PPL",
    "gn:name":"Omm ol \u1e28eyl",
    "gn:population":0,
    "gn:timezone":"Asia/Tehran",
    "iso:country":"IR",
    "name:fas_x_preferred":[
        "\u0627\u0645 \u0627\u0644\u062d\u06cc\u0644"
    ],
    "name:fas_x_variant":[
        "Omm ol \u1e28eyl"
    ],
    "wof:name":"Omm ol Heyl",
    "wof:placetype":"locality"
},
  "geometry": {"coordinates":[47.9846,32.20013],"type":"Point"}
}