{
  "type": "Feature",
  "properties": {
    "gn:admin1_code":"15",
    "gn:asciiname":"Yahmureh-ye Yek",
    "gn:country_code":"IR",
    "gn:dem":26,
    "gn:feature_class":"P",
    "gn:feature_code":"PPL",
    "gn:name":"Ya\u1e29m\u016breh-ye Yek",
    "gn:population":0,
    "gn:timezone":"Asia/Tehran",
    "iso:country":"IR",
    "name:ceb_x_preferred":[
        "Ya\u1e29m\u016breh-ye Yek"
    ],
    "name:fas_x_preferred":[
        "\u06cc\u062d\u0645\u0648\u0631\u0647 \u06cc\u06a9"
    ],
    "name:fas_x_variant":[
        "Ya\u1e29m\u016breh-ye Yek"
    ],
    "name:swe_x_preferred":[
        "Ya\u1e29m\u016breh-ye Yek"
    ],
    "name:und_x_variant":[
        "Yo\u1e29m\u016breh",
        "Ya\u1e29m\u016breh"
    ],
    "name:urd_x_preferred":[
        "\u06cc\u06c1\u0645\u0631\u06c1-\u06cc\u06a9"
    ],
    "wof:name":"Yahmureh-ye Yek",
    "wof:placetype":"locality"
},
  "geometry": {"coordinates":[48.7051,31.66800000000001],"type":"Point"}
}