{
  "type": "Feature",
  "properties": {
    "gn:admin1_code":"4.0",
    "gn:asciiname":"Deh-e Kanal",
    "gn:country_code":"IR",
    "gn:dem":478,
    "gn:feature_class":"P",
    "gn:feature_code":"PPL",
    "gn:name":"Deh-e K\u0101n\u0101l",
    "gn:population":0,
    "gn:timezone":"Asia/Tehran",
    "iso:country":"IR",
    "name:fas_x_preferred":[
        "Deh-e K\u0101n\u0101l"
    ],
    "name:fas_x_variant":[
        "\u062f\u0647 \u06a9\u0627\u0646\u0627\u0644"
    ],
    "name:und_x_variant":[
        "\u062f\u0647 \u06a9\u0627\u0646\u0627\u0644"
    ],
    "wof:name":"Deh-e Kanal",
    "wof:placetype":"locality"
},
  "geometry": {"coordinates":[61.7618,31.2272],"type":"Point"}
}