{
  "type": "Feature",
  "properties": {
    "gn:admin1_code":"7",
    "gn:asciiname":"Zar Qalat",
    "gn:country_code":"IR",
    "gn:dem":1237,
    "gn:feature_class":"P",
    "gn:feature_code":"PPL",
    "gn:name":"Zar Qal\u0101t",
    "gn:population":0,
    "gn:timezone":"Asia/Tehran",
    "iso:country":"IR",
    "name:fas_x_preferred":[
        "\u0632\u0631 \u0642\u0644\u0627\u062a"
    ],
    "name:fas_x_variant":[
        "Zar Qal\u0101t"
    ],
    "wof:name":"Zar Qalat",
    "wof:placetype":"locality"
},
  "geometry": {"coordinates":[53.1452,28.8632],"type":"Point"}
}