{
  "type": "Feature",
  "properties": {
    "gn:admin1_code":"26",
    "gn:asciiname":"Qal`eh Now-e Chaman",
    "gn:country_code":"IR",
    "gn:dem":1023,
    "gn:feature_class":"P",
    "gn:feature_code":"PPL",
    "gn:name":"Qal\u2018eh Now-e Chaman",
    "gn:population":0,
    "gn:timezone":"Asia/Tehran",
    "iso:country":"IR",
    "name:fas_x_preferred":[
        "\u0642\u064e\u0644\u0639\u0650\u0647 \u0646\u064f\u0648\u0650 \u0686\u064e\u0645\u064e\u0646"
    ],
    "name:fas_x_variant":[
        "\u0642\u064e\u0644\u0639\u0650\u06c0 \u0646\u064f\u0648",
        "\u0642\u064e\u0644\u0639\u0650\u0647 \u0646\u064f\u0648",
        "\u0642\u064e\u0644\u0639\u0650\u06c0 \u0646\u064f\u0648 \u0686\u064e\u0645\u064e\u0646 \u0632\u064e\u0645\u064a\u0646",
        "Qal\u2018eh Now-e Chaman"
    ],
    "name:und_x_variant":[
        "Qal\u2018eh Nau",
        "Qal\u2018eh Now",
        "Qal\u2018eh-ye Now Chaman Zam\u012bn",
        "Qal\u2018eh-ye Now"
    ],
    "wof:name":"Qal`eh Now-e Chaman",
    "wof:placetype":"locality"
},
  "geometry": {"coordinates":[51.40499000000001,35.53317],"type":"Point"}
}