{
  "type": "Feature",
  "properties": {
    "gn:admin1_code":"8",
    "gn:asciiname":"Palang Sara",
    "gn:country_code":"IR",
    "gn:dem":87,
    "gn:feature_class":"P",
    "gn:feature_code":"PPL",
    "gn:name":"Palang Sar\u0101",
    "gn:population":0,
    "gn:timezone":"Asia/Tehran",
    "iso:country":"IR",
    "name:ceb_x_preferred":[
        "Palang Sar\u0101"
    ],
    "name:fas_x_preferred":[
        "\u067e\u0644\u0646\u06af \u0633\u0631\u0627"
    ],
    "name:fas_x_variant":[
        "Palang Sar\u0101"
    ],
    "name:msa_x_preferred":[
        "Palang Sara"
    ],
    "name:swe_x_preferred":[
        "Palang Sar\u0101"
    ],
    "name:ukr_x_preferred":[
        "\u041f\u0430\u043b\u0430\u043d\u0491-\u0421\u0430\u0440\u0430"
    ],
    "wof:name":"Palang Sara",
    "wof:placetype":"locality"
},
  "geometry": {"coordinates":[49.0916,37.4279],"type":"Point"}
}