{
  "type": "Feature",
  "properties": {
    "gn:admin1_code":"28",
    "gn:asciiname":"Seh",
    "gn:country_code":"IR",
    "gn:dem":2344,
    "gn:feature_class":"P",
    "gn:feature_code":"PPL",
    "gn:name":"Seh",
    "gn:population":0,
    "gn:timezone":"Asia/Tehran",
    "iso:country":"IR",
    "name:fas_x_preferred":[
        "\u0633\u0647"
    ],
    "name:und_x_variant":[
        "S\u014d",
        "S\u016bh",
        "Seh"
    ],
    "wof:name":"Seh",
    "wof:placetype":"locality"
},
  "geometry": {"coordinates":[51.45212,33.43963],"type":"Point"}
}