{
  "type": "Feature",
  "properties": {
    "gn:admin1_code":"41.0",
    "gn:asciiname":"Kalateh-ye Musa",
    "gn:country_code":"IR",
    "gn:dem":1922,
    "gn:feature_class":"P",
    "gn:feature_code":"PPL",
    "gn:name":"Kal\u0101teh-ye M\u016bs\u00e1",
    "gn:population":0,
    "gn:timezone":"Asia/Tehran",
    "iso:country":"IR",
    "name:fas_x_preferred":[
        "\u06a9\u0644\u0627\u062a\u0647 \u0645\u0648\u0633\u06cc"
    ],
    "name:fas_x_variant":[
        "Kal\u0101teh-ye M\u016bs\u00e1",
        "\u06a9\u0644\u0627\u062a\u0647 \u0645\u0648\u0633\u06cc \u0622\u0628\u0627\u062f"
    ],
    "name:und_x_variant":[
        "Kal\u0101teh-ye M\u016bs\u00e1\u0101b\u0101d"
    ],
    "wof:name":"Kalateh-ye Musa",
    "wof:placetype":"locality"
},
  "geometry": {"coordinates":[60.1704,33.21348],"type":"Point"}
}