{
  "type": "Feature",
  "properties": {
    "gn:admin1_code":"1",
    "gn:asciiname":"Tazeh Kand-e Afshar",
    "gn:country_code":"IR",
    "gn:dem":1327,
    "gn:feature_class":"P",
    "gn:feature_code":"PPL",
    "gn:name":"T\u0101zeh Kand-e Afsh\u0101r",
    "gn:population":0,
    "gn:timezone":"Asia/Tehran",
    "iso:country":"IR",
    "name:fas_x_preferred":[
        "\u062a\u0627\u0632\u0650\u0647 \u0643\u064e\u0646\u062f\u0650 \u0627\u064e\u0641\u0634\u0627\u0631"
    ],
    "name:fas_x_variant":[
        "\u062a\u0627\u0632\u0647 \u06a9\u0646\u062f \u0627\u0641\u0634\u0627\u0631",
        "\u062a\u0627\u0632\u0650\u0647\u0643\u064e\u0646\u062f\u0650 \u06af\u064e\u0631\u062f \u0622\u0628\u0627\u062f",
        "T\u0101zeh Kand-e Afsh\u0101r"
    ],
    "name:und_x_variant":[
        "T\u0101zehkand-e Gard\u0101b\u0101d"
    ],
    "wof:name":"Tazeh Kand-e Afshar",
    "wof:placetype":"locality"
},
  "geometry": {"coordinates":[45.0609,37.6328],"type":"Point"}
}