{
  "type": "Feature",
  "properties": {
    "gn:admin1_code":"15",
    "gn:asciiname":"Balutak Shalu",
    "gn:country_code":"IR",
    "gn:dem":883,
    "gn:feature_class":"P",
    "gn:feature_code":"PPL",
    "gn:name":"Bal\u016b\u0163ak Sh\u0101l\u016b",
    "gn:population":0,
    "gn:timezone":"Asia/Tehran",
    "iso:country":"IR",
    "name:fas_x_preferred":[
        "Bal\u016b\u0163ak Sh\u0101l\u016b"
    ],
    "name:fas_x_variant":[
        "\u0628\u0644\u0648\u0637\u06a9 \u0634\u0627\u0644\u0648"
    ],
    "wof:name":"Balutak Shalu",
    "wof:placetype":"locality"
},
  "geometry": {"coordinates":[50.12,31.73389],"type":"Point"}
}