{
  "type": "Feature",
  "properties": {
    "gn:admin1_code":"13",
    "gn:asciiname":"Shamshir-e Bala",
    "gn:country_code":"IR",
    "gn:dem":584,
    "gn:feature_class":"P",
    "gn:feature_code":"PPL",
    "gn:name":"Shamsh\u012br-e B\u0101l\u0101",
    "gn:population":0,
    "gn:timezone":"Asia/Tehran",
    "iso:country":"IR",
    "name:fas_x_preferred":[
        "\u0634\u0645\u0634\u064a\u0631 \u0628\u0627\u0644\u0627"
    ],
    "name:fas_x_variant":[
        "Shamsh\u012br-e B\u0101l\u0101"
    ],
    "wof:name":"Shamshir-e Bala",
    "wof:placetype":"locality"
},
  "geometry": {"coordinates":[45.86624000000001,34.5453],"type":"Point"}
}