{
  "type": "Feature",
  "properties": {
    "gn:admin1_code":"26.0",
    "gn:asciiname":"Kuy-e Vahdat",
    "gn:country_code":"IR",
    "gn:dem":1119,
    "gn:feature_class":"P",
    "gn:feature_code":"PPL",
    "gn:name":"K\u016by-e Va\u1e29dat",
    "gn:population":0,
    "gn:timezone":"Asia/Tehran",
    "iso:country":"IR",
    "name:fas_x_preferred":[
        "\u06a9\u0648\u06cc \u0648\u062d\u062f\u062a"
    ],
    "name:und_x_variant":[
        "K\u016by-e Va\u1e29dat"
    ],
    "wof:name":"Kuy-e Vahdat",
    "wof:placetype":"locality"
},
  "geometry": {"coordinates":[51.03621,35.61077],"type":"Point"}
}