{
  "type": "Feature",
  "properties": {
    "gn:admin1_code":"15",
    "gn:asciiname":"Nahr-e Sheykh",
    "gn:country_code":"IR",
    "gn:dem":14,
    "gn:feature_class":"P",
    "gn:feature_code":"PPL",
    "gn:name":"Nahr-e Sheykh",
    "gn:population":0,
    "gn:timezone":"Asia/Tehran",
    "iso:country":"IR",
    "name:fas_x_preferred":[
        "\u0646\u0647\u0631 \u0634\u06cc\u062e"
    ],
    "name:und_x_variant":[
        "\u0646\u0647\u0631 \u0634\u06cc\u062e"
    ],
    "wof:name":"Nahr-e Sheykh",
    "wof:placetype":"locality"
},
  "geometry": {"coordinates":[48.86735,30.75849],"type":"Point"}
}