{
  "type": "Feature",
  "properties": {
    "gn:admin1_code":"29",
    "gn:asciiname":"Tomu",
    "gn:country_code":"IR",
    "gn:dem":2118,
    "gn:feature_class":"P",
    "gn:feature_code":"PPL",
    "gn:name":"Tom\u016b",
    "gn:population":0,
    "gn:timezone":"Asia/Tehran",
    "iso:country":"IR",
    "name:fas_x_preferred":[
        "\u062a\u0645\u0648"
    ],
    "name:fas_x_variant":[
        "Tomb\u016b\u2019\u012byeh",
        "Tom\u016b"
    ],
    "name:und_x_variant":[
        "Yakh M\u016br",
        "Tom\u016b\u2019\u012byeh"
    ],
    "wof:name":"Tomu",
    "wof:placetype":"locality"
},
  "geometry": {"coordinates":[56.8689,29.1479],"type":"Point"}
}