{
  "type": "Feature",
  "properties": {
    "gn:admin1_code":"7",
    "gn:asciiname":"Khaliun",
    "gn:country_code":"IR",
    "gn:dem":2410,
    "gn:feature_class":"P",
    "gn:feature_code":"PPL",
    "gn:name":"Khal\u012b\u016bn",
    "gn:population":0,
    "gn:timezone":"Asia/Tehran",
    "iso:country":"IR",
    "name:fas_x_preferred":[
        "\u062e\u0648\u0644\u06cc\u0627\u0646"
    ],
    "name:fas_x_variant":[
        "Kh\u016bl\u012b\u0101n",
        "\u062e\u0644\u064a\u0648\u0646"
    ],
    "name:und_x_variant":[
        "Khal\u012b\u016bn"
    ],
    "wof:name":"Khaliun",
    "wof:placetype":"locality"
},
  "geometry": {"coordinates":[53.8945,30.2289],"type":"Point"}
}