{
  "type": "Feature",
  "properties": {
    "gn:admin1_code":"4",
    "gn:asciiname":"Rowghani",
    "gn:country_code":"IR",
    "gn:dem":670,
    "gn:feature_class":"P",
    "gn:feature_code":"PPL",
    "gn:name":"Rowghan\u012b",
    "gn:population":0,
    "gn:timezone":"Asia/Tehran",
    "iso:country":"IR",
    "name:fas_x_preferred":[
        "Rowghan\u012b"
    ],
    "name:fas_x_variant":[
        "\u0631\u0648\u063a\u0646\u06cc"
    ],
    "name:und_x_variant":[
        "\u0631\u0648\u063a\u0646\u06cc"
    ],
    "wof:name":"Rowghani",
    "wof:placetype":"locality"
},
  "geometry": {"coordinates":[61.20452,26.36959],"type":"Point"}
}