{
  "type": "Feature",
  "properties": {
    "gn:admin1_code":"38.0",
    "gn:asciiname":"Arunqash",
    "gn:country_code":"IR",
    "gn:dem":1893,
    "gn:feature_class":"P",
    "gn:feature_code":"PPL",
    "gn:name":"Ar\u016bnq\u0101sh",
    "gn:population":0,
    "gn:timezone":"Asia/Tehran",
    "iso:country":"IR",
    "name:ceb_x_preferred":[
        "Ar\u016bnq\u0101sh"
    ],
    "name:fas_x_preferred":[
        "\u0627\u0631\u0648\u0646\u0642\u0627\u0634"
    ],
    "name:fas_x_variant":[
        "\u016aranq\u0101sh",
        "Ar\u016bnq\u0101sh"
    ],
    "name:swe_x_preferred":[
        "Ar\u016bnq\u0101sh"
    ],
    "name:und_x_variant":[
        "Urung\u0101sh",
        "Owranq\u0101sh",
        "Oroonghash"
    ],
    "wof:name":"Arunqash",
    "wof:placetype":"locality"
},
  "geometry": {"coordinates":[49.27739,35.9012],"type":"Point"}
}