{
  "type": "Feature",
  "properties": {
    "gn:admin1_code":"32",
    "gn:asciiname":"Hiq",
    "gn:country_code":"IR",
    "gn:dem":1306,
    "gn:feature_class":"P",
    "gn:feature_code":"PPL",
    "gn:name":"\u1e28\u012bq",
    "gn:population":0,
    "gn:timezone":"Asia/Tehran",
    "iso:country":"IR",
    "name:fas_x_preferred":[
        "\u062d\u064a\u0642"
    ],
    "name:fas_x_variant":[
        "\u1e28\u012bq",
        "\u062d\u06cc\u0642"
    ],
    "name:msa_x_preferred":[
        "Hiq"
    ],
    "name:mzn_x_preferred":[
        "\u062d\u06cc\u0642"
    ],
    "wof:name":"Hiq",
    "wof:placetype":"locality"
},
  "geometry": {"coordinates":[47.581,38.3828],"type":"Point"}
}