{
  "type": "Feature",
  "properties": {
    "gn:admin1_code":"33",
    "gn:asciiname":"Khaneh-ye Khosrow",
    "gn:country_code":"IR",
    "gn:dem":1055,
    "gn:feature_class":"P",
    "gn:feature_code":"PPL",
    "gn:name":"Kh\u0101neh-ye Khosrow",
    "gn:population":0,
    "gn:timezone":"Asia/Tehran",
    "iso:country":"IR",
    "name:fas_x_preferred":[
        "Kh\u0101neh-ye Khosrow"
    ],
    "name:fas_x_variant":[
        "\u062e\u0627\u0646\u0647 \u062e\u0633\u0631\u0648"
    ],
    "name:msa_x_preferred":[
        "Khaneh-ye Khosrow"
    ],
    "wof:name":"Khaneh-ye Khosrow",
    "wof:placetype":"locality"
},
  "geometry": {"coordinates":[47.03827,38.88196],"type":"Point"}
}