{
  "type": "Feature",
  "properties": {
    "gn:admin1_code":"8",
    "gn:asciiname":"Felideh",
    "gn:country_code":"IR",
    "gn:dem":729,
    "gn:feature_class":"P",
    "gn:feature_code":"PPL",
    "gn:name":"Fel\u012bdeh",
    "gn:population":0,
    "gn:timezone":"Asia/Tehran",
    "iso:country":"IR",
    "name:fas_x_preferred":[
        "\u0641\u0644\u06cc\u062f\u0647"
    ],
    "name:fas_x_variant":[
        "Fel\u012bdeh",
        "\u0641\u06cc\u0644\u062f\u0647"
    ],
    "name:msa_x_preferred":[
        "Fildeh"
    ],
    "name:ukr_x_preferred":[
        "\u0424\u0456\u043b\u044c\u0434\u0435\u0433"
    ],
    "name:und_x_variant":[
        "F\u012bldeh",
        "Fal\u012bdeh",
        "Fil\u2019dy",
        "Fel\u012bd",
        "Fal\u012bdah"
    ],
    "wof:name":"Felideh",
    "wof:placetype":"locality"
},
  "geometry": {"coordinates":[49.3885,36.8215],"type":"Point"}
}