{
  "type": "Feature",
  "properties": {
    "gn:admin1_code":"32.0",
    "gn:asciiname":"Esma`il Khan Gazi",
    "gn:country_code":"IR",
    "gn:dem":2416,
    "gn:feature_class":"P",
    "gn:feature_code":"PPL",
    "gn:name":"Esm\u0101\u2018\u012bl Kh\u0101n Gaz\u012b",
    "gn:population":0,
    "gn:timezone":"Asia/Tehran",
    "iso:country":"IR",
    "name:fas_x_preferred":[
        "\u0627\u0633\u0645\u0627\u0639\u064a\u0644 \u062e\u0627\u0646 \u06af\u0632\u06cc"
    ],
    "name:und_x_variant":[
        "Esm\u0101\u2018\u012bl Kh\u0101n Gaz\u012b"
    ],
    "wof:name":"Esma`il Khan Gazi",
    "wof:placetype":"locality"
},
  "geometry": {"coordinates":[47.97957,38.38109],"type":"Point"}
}