{
  "type": "Feature",
  "properties": {
    "gn:admin1_code":"42",
    "gn:asciiname":"Kamirdar",
    "gn:country_code":"IR",
    "gn:dem":1077,
    "gn:feature_class":"P",
    "gn:feature_code":"PPL",
    "gn:name":"Kam\u012brdar",
    "gn:population":0,
    "gn:timezone":"Asia/Tehran",
    "iso:country":"IR",
    "name:fas_x_preferred":[
        "\u06a9\u0645\u06cc\u0631\u062f\u0631"
    ],
    "name:fas_x_variant":[
        "Gom\u012bzdar",
        "Kam\u012brdar",
        "\u06af\u0645\u06cc\u0632\u062f\u0631"
    ],
    "name:und_x_variant":[
        "Gam\u012bzdar"
    ],
    "wof:name":"Kamirdar",
    "wof:placetype":"locality"
},
  "geometry": {"coordinates":[59.6826,36.4918],"type":"Point"}
}