{
  "type": "Feature",
  "properties": {
    "gn:admin1_code":"41",
    "gn:asciiname":"Sistanak",
    "gn:country_code":"IR",
    "gn:dem":1489,
    "gn:feature_class":"P",
    "gn:feature_code":"PPLL",
    "gn:name":"S\u012bst\u0101nak",
    "gn:population":0,
    "gn:timezone":"Asia/Tehran",
    "iso:country":"IR",
    "name:fas_x_preferred":[
        "S\u012bst\u0101nak"
    ],
    "name:fas_x_variant":[
        "\u0633\u064a\u0633\u062a\u0627\u0646\u06a9",
        "S\u012bst\u016bnak"
    ],
    "name:und_x_variant":[
        "S\u012bst\u016bnak",
        "\u0633\u064a\u0633\u062a\u0627\u0646\u06a9"
    ],
    "wof:name":"Sistanak",
    "wof:placetype":"locality"
},
  "geometry": {"coordinates":[59.25709000000001,32.89997],"type":"Point"}
}