{
  "type": "Feature",
  "properties": {
    "gn:admin1_code":"5",
    "gn:asciiname":"Taveh Chenar",
    "gn:country_code":"IR",
    "gn:dem":2180,
    "gn:feature_class":"P",
    "gn:feature_code":"PPL",
    "gn:name":"T\u0101veh Chen\u0101r",
    "gn:population":0,
    "gn:timezone":"Asia/Tehran",
    "iso:country":"IR",
    "name:fas_x_preferred":[
        "\u062a\u0627\u0648\u0650\u0647 \u0686\u0650\u0646\u0627\u0631"
    ],
    "name:fas_x_variant":[
        "T\u0101veh Chen\u0101r"
    ],
    "wof:name":"Taveh Chenar",
    "wof:placetype":"locality"
},
  "geometry": {"coordinates":[51.64139,30.61222],"type":"Point"}
}