{
  "type": "Feature",
  "properties": {
    "gn:admin1_code":"7",
    "gn:asciiname":"Qanat-e Now",
    "gn:country_code":"IR",
    "gn:dem":2351,
    "gn:feature_class":"P",
    "gn:feature_code":"PPL",
    "gn:name":"Qan\u0101t-e Now",
    "gn:population":0,
    "gn:timezone":"Asia/Tehran",
    "iso:country":"IR",
    "name:fas_x_preferred":[
        "\u0642\u0646\u0627\u062a \u0646\u0648 \u0633\u0631 \u0645\u0644\u06a9\u06cc"
    ],
    "name:fas_x_variant":[
        "Sar Molk\u012b",
        "\u0642\u0646\u0627\u062a \u0646\u0648",
        "\u0633\u0631 \u0645\u0644\u06a9\u06cc \u0642\u0646\u0627\u062a \u0646\u0648"
    ],
    "name:und_x_variant":[
        "Qan\u0101t-e Now-e Sar Malek\u012b",
        "Qan\u0101t-e Now",
        "Sar Malek\u012b-ye Qan\u0101t-e Now"
    ],
    "wof:name":"Qanat-e Now",
    "wof:placetype":"locality"
},
  "geometry": {"coordinates":[53.2249,30.6385],"type":"Point"}
}