{
  "type": "Feature",
  "properties": {
    "gn:admin1_code":"23.0",
    "gn:asciiname":"Dul-e Hulian",
    "gn:country_code":"IR",
    "gn:dem":1210,
    "gn:feature_class":"P",
    "gn:feature_code":"PPL",
    "gn:name":"D\u016bl-e H\u016bl\u012b\u0101n",
    "gn:population":0,
    "gn:timezone":"Asia/Tehran",
    "iso:country":"IR",
    "name:fas_x_preferred":[
        "\u062f\u0648\u0644 \u0647\u0648\u0644\u064a\u0627\u0646"
    ],
    "name:und_x_variant":[
        "D\u016bl-e H\u016bl\u012b\u0101n"
    ],
    "wof:name":"Dul-e Hulian",
    "wof:placetype":"locality"
},
  "geometry": {"coordinates":[48.07147,33.24172],"type":"Point"}
}