{
  "type": "Feature",
  "properties": {
    "gn:admin1_code":"42",
    "gn:asciiname":"Quzhdabad",
    "gn:country_code":"IR",
    "gn:dem":907,
    "gn:feature_class":"P",
    "gn:feature_code":"PPL",
    "gn:name":"Q\u016bzhd\u0101b\u0101d",
    "gn:population":0,
    "gn:timezone":"Asia/Tehran",
    "iso:country":"IR",
    "name:ara_x_preferred":[
        "\u0642\u0648\u062c\u062f \u0623\u0628\u0627\u062f"
    ],
    "name:ceb_x_preferred":[
        "Q\u016bzhd\u0101b\u0101d"
    ],
    "name:fas_x_preferred":[
        "Q\u016bzhd\u0101b\u0101d"
    ],
    "name:fas_x_variant":[
        "\u0642\u0648\u0698\u062f\u0622\u0628\u0627\u062f"
    ],
    "name:mzn_x_preferred":[
        "\u0642\u0648\u0698\u062f\u0622\u0628\u0627\u062f"
    ],
    "name:swe_x_preferred":[
        "Q\u016bzhd\u0101b\u0101d"
    ],
    "wof:name":"Quzhdabad",
    "wof:placetype":"locality"
},
  "geometry": {"coordinates":[58.03511,35.14080999999999],"type":"Point"}
}