{
  "type": "Feature",
  "properties": {
    "gn:admin1_code":"22",
    "gn:asciiname":"Govabin",
    "gn:country_code":"IR",
    "gn:dem":7,
    "gn:feature_class":"P",
    "gn:feature_code":"PPL",
    "gn:name":"Gov\u0101b\u012bn",
    "gn:population":0,
    "gn:timezone":"Asia/Tehran",
    "iso:country":"IR",
    "name:fas_x_preferred":[
        "\u0643\u064f\u0648\u0627\u0628\u064a\u0646"
    ],
    "name:fas_x_variant":[
        "\u06af\u064e\u0648\u0627\u0628\u064a\u0646",
        "\u06af\u064e\u0648\u0627\u067e\u0650\u0646",
        "\u06af\u0648\u0627\u0628\u064a\u0646",
        "Kov\u0101b\u012bn",
        "Gov\u0101b\u012bn"
    ],
    "name:und_x_variant":[
        "Gav\u0101pen",
        "Gav\u0101b\u012bn"
    ],
    "wof:name":"Govabin",
    "wof:placetype":"locality"
},
  "geometry": {"coordinates":[50.76300000000001,29.2756],"type":"Point"}
}