{
  "type": "Feature",
  "properties": {
    "gn:admin1_code":"29",
    "gn:asciiname":"Abad-e Sivandi",
    "gn:country_code":"IR",
    "gn:dem":1838,
    "gn:feature_class":"P",
    "gn:feature_code":"PPL",
    "gn:name":"\u0100b\u0101d-e S\u012bvand\u012b",
    "gn:population":0,
    "gn:timezone":"Asia/Tehran",
    "iso:country":"IR",
    "name:fas_x_preferred":[
        "\u0100b B\u0101d-e S\u012bvand\u012b"
    ],
    "name:fas_x_variant":[
        "\u0622\u0628\u0627\u062f \u0633\u06cc\u0648\u0646\u062f\u06cc"
    ],
    "name:und_x_variant":[
        "\u0100b B\u0101d",
        "\u0100b\u0101d-e S\u012bvand\u012b"
    ],
    "wof:name":"Abad-e Sivandi",
    "wof:placetype":"locality"
},
  "geometry": {"coordinates":[56.25137,28.82514],"type":"Point"}
}