{
  "type": "Feature",
  "properties": {
    "gn:admin1_code":"8",
    "gn:asciiname":"Sad Sazi",
    "gn:country_code":"IR",
    "gn:dem":-11,
    "gn:feature_class":"P",
    "gn:feature_code":"PPL",
    "gn:name":"Sad S\u0101z\u012b",
    "gn:population":0,
    "gn:timezone":"Asia/Tehran",
    "iso:country":"IR",
    "name:fas_x_preferred":[
        "Sad S\u0101z\u012b"
    ],
    "wof:name":"Sad Sazi",
    "wof:placetype":"locality"
},
  "geometry": {"coordinates":[49.91667,37.25],"type":"Point"}
}