{
  "type": "Feature",
  "properties": {
    "gn:admin1_code":"33.0",
    "gn:asciiname":"Barazin",
    "gn:country_code":"IR",
    "gn:dem":1254,
    "gn:feature_class":"P",
    "gn:feature_code":"PPL",
    "gn:name":"Bar\u0101z\u012bn",
    "gn:population":0,
    "gn:timezone":"Asia/Tehran",
    "iso:country":"IR",
    "name:fas_x_preferred":[
        "\u0628\u0631\u0627\u0632\u06cc\u0646"
    ],
    "name:fas_x_variant":[
        "Araz\u012bn",
        "Bar\u0101z\u012bn"
    ],
    "name:nno_x_preferred":[
        "Barazin"
    ],
    "name:sco_x_preferred":[
        "Barazin"
    ],
    "name:sqi_x_preferred":[
        "Barazin"
    ],
    "name:und_x_variant":[
        "Arz\u012bn",
        "Bar\u0101z\u012bn"
    ],
    "wof:name":"Barazin",
    "wof:placetype":"locality"
},
  "geometry": {"coordinates":[46.7094,38.8716],"type":"Point"}
}