{
  "type": "Feature",
  "properties": {
    "gn:admin1_code":"8.0",
    "gn:asciiname":"Shaquz Bari",
    "gn:country_code":"IR",
    "gn:dem":315,
    "gn:feature_class":"P",
    "gn:feature_code":"PPL",
    "gn:name":"Sh\u0101q\u016bz Bar\u012b",
    "gn:population":0,
    "gn:timezone":"Asia/Tehran",
    "iso:country":"IR",
    "name:fas_x_preferred":[
        "\u0634\u0627\u0642\u0648\u0632 \u0628\u0631\u06cc"
    ],
    "name:und_x_variant":[
        "Sh\u0101q\u016bz Bar\u012b"
    ],
    "wof:name":"Shaquz Bari",
    "wof:placetype":"locality"
},
  "geometry": {"coordinates":[49.77525,37.03309],"type":"Point"}
}