{
  "type": "Feature",
  "properties": {
    "gn:admin1_code":"4",
    "gn:asciiname":"Chah-e Fath `Ali",
    "gn:country_code":"IR",
    "gn:dem":378,
    "gn:feature_class":"P",
    "gn:feature_code":"PPL",
    "gn:name":"Ch\u0101h-e Fat\u1e29 \u2018Al\u012b",
    "gn:population":0,
    "gn:timezone":"Asia/Tehran",
    "iso:country":"IR",
    "name:fas_x_preferred":[
        "Ch\u0101h-e Fat\u1e29 \u2018Al\u012b"
    ],
    "wof:name":"Chah-e Fath `Ali",
    "wof:placetype":"locality"
},
  "geometry": {"coordinates":[59.26667,27.55],"type":"Point"}
}