{
  "type": "Feature",
  "properties": {
    "gn:admin1_code":"37",
    "gn:asciiname":"Qarah Dam-e Jonubi",
    "gn:country_code":"IR",
    "gn:dem":202,
    "gn:feature_class":"P",
    "gn:feature_code":"PPL",
    "gn:name":"Qarah D\u0101m-e Jon\u016bb\u012b",
    "gn:population":0,
    "gn:timezone":"Asia/Tehran",
    "iso:country":"IR",
    "name:fas_x_preferred":[
        "\u0642\u0631\u0647 \u062f\u0627\u0645 \u062c\u0646\u0648\u0628\u06cc"
    ],
    "name:fas_x_variant":[
        "Qarah D\u0101m-e Jon\u016bb\u012b"
    ],
    "wof:name":"Qarah Dam-e Jonubi",
    "wof:placetype":"locality"
},
  "geometry": {"coordinates":[55.91918,37.89358],"type":"Point"}
}