{
  "type": "Feature",
  "properties": {
    "gn:admin1_code":"10.0",
    "gn:asciiname":"Tazehabad-e Mileh Siah",
    "gn:country_code":"IR",
    "gn:dem":1339,
    "gn:feature_class":"P",
    "gn:feature_code":"PPL",
    "gn:name":"T\u0101zeh\u0101b\u0101d-e M\u012bleh S\u012b\u0101h",
    "gn:population":0,
    "gn:timezone":"Asia/Tehran",
    "iso:country":"IR",
    "name:fas_x_preferred":[
        "\u062a\u0627\u0632\u0647 \u0622\u0628\u0627\u062f \u0645\u06cc\u0644\u0647 \u0633\u06cc\u0627\u0647"
    ],
    "name:fas_x_variant":[
        "T\u0101zeh\u0101b\u0101d-e Melah S\u012b\u0101h",
        "T\u0101zeh\u0101b\u0101d-e M\u012bleh S\u012b\u0101h"
    ],
    "wof:name":"Tazehabad-e Mileh Siah",
    "wof:placetype":"locality"
},
  "geometry": {"coordinates":[46.2342,33.7561],"type":"Point"}
}