{
  "type": "Feature",
  "properties": {
    "gn:admin1_code":"22",
    "gn:asciiname":"Gurak Kalbandi",
    "gn:country_code":"IR",
    "gn:dem":13,
    "gn:feature_class":"P",
    "gn:feature_code":"PPL",
    "gn:name":"G\u016brak Kalband\u012b",
    "gn:population":0,
    "gn:timezone":"Asia/Tehran",
    "iso:country":"IR",
    "name:fas_x_preferred":[
        "\u06a9\u0644\u0628\u0646\u062f\u06cc"
    ],
    "name:fas_x_variant":[
        "\u0642\u064e\u0644\u0639\u0650\u0647 \u0628\u064e\u0646\u062f\u06cc",
        "Kalband\u012b",
        "\u06af\u0648\u0631\u06a9 \u06a9\u0644\u0628\u0646\u062f\u06cc",
        "\u06af\u064f\u0644 \u0628\u064e\u0646\u062f\u06cc",
        "\u06a9\u0644\u0647 \u0628\u0646\u062f\u06cc"
    ],
    "name:und_x_variant":[
        "Qal\u2018eh Band\u012b",
        "Kelband\u012b",
        "G\u016brak Kalband\u012b",
        "Gol Band\u012b",
        "Kaleh Band\u012b"
    ],
    "wof:name":"Gurak Kalbandi",
    "wof:placetype":"locality"
},
  "geometry": {"coordinates":[51.04069000000001,28.93725],"type":"Point"}
}