{
  "type": "Feature",
  "properties": {
    "gn:admin1_code":"15",
    "gn:asciiname":"Lazm Zobeydi",
    "gn:country_code":"IR",
    "gn:dem":47,
    "gn:feature_class":"P",
    "gn:feature_code":"PPL",
    "gn:name":"L\u0101zm Zobeyd\u012b",
    "gn:population":0,
    "gn:timezone":"Asia/Tehran",
    "iso:country":"IR",
    "name:fas_x_preferred":[
        "\u0634\u06cc\u062e \u0644\u0627\u0632\u0645"
    ],
    "name:fas_x_variant":[
        "Boneh-ye L\u0101zem",
        "Sheykh L\u0101zem",
        "\u0644\u0627\u0632\u0645 \u0632\u0628\u06cc\u062f\u06cc",
        "\u0628\u0646\u0647 \u0644\u0627\u0632\u0645"
    ],
    "name:und_x_variant":[
        "Boneh Lazem",
        "L\u0101zm Zobeyd\u012b"
    ],
    "wof:name":"Lazm Zobeydi",
    "wof:placetype":"locality"
},
  "geometry": {"coordinates":[48.51244000000001,32.07953],"type":"Point"}
}