{
  "type": "Feature",
  "properties": {
    "gn:admin1_code":"8",
    "gn:asciiname":"Khajbaneh",
    "gn:country_code":"IR",
    "gn:dem":776,
    "gn:feature_class":"P",
    "gn:feature_code":"PPL",
    "gn:name":"Khajbaneh",
    "gn:population":0,
    "gn:timezone":"Asia/Tehran",
    "iso:country":"IR",
    "name:fas_x_preferred":[
        "\u062e\u062c\u0647 \u0628\u0648\u0646\u0647"
    ],
    "name:fas_x_variant":[
        "Khojeh B\u016bneh",
        "\u062e\u062c\u0628\u0646\u0647"
    ],
    "wof:name":"Khajbaneh",
    "wof:placetype":"locality"
},
  "geometry": {"coordinates":[48.9959,37.30933],"type":"Point"}
}