{
  "type": "Feature",
  "properties": {
    "gn:admin1_code":"42",
    "gn:asciiname":"Kazemabad",
    "gn:country_code":"IR",
    "gn:dem":867,
    "gn:feature_class":"P",
    "gn:feature_code":"PPL",
    "gn:name":"K\u0101z\u0327em\u0101b\u0101d",
    "gn:population":0,
    "gn:timezone":"Asia/Tehran",
    "iso:country":"IR",
    "name:ara_x_preferred":[
        "\u0643\u0627\u0638\u0645 \u0623\u0628\u0627\u062f"
    ],
    "name:fas_x_preferred":[
        "K\u0101z\u0327em\u0101b\u0101d"
    ],
    "name:fas_x_variant":[
        "\u06a9\u0627\u0638\u0645 \u0622\u0628\u0627\u062f",
        "\u06a9\u0627\u0638\u0645\u200c\u0622\u0628\u0627\u062f"
    ],
    "name:mzn_x_preferred":[
        "\u06a9\u0627\u0638\u0645\u200c\u0622\u0628\u0627\u062f"
    ],
    "wof:name":"Kazemabad",
    "wof:placetype":"locality"
},
  "geometry": {"coordinates":[57.89917,35.12375],"type":"Point"}
}