{
  "type": "Feature",
  "properties": {
    "gn:admin1_code":"4.0",
    "gn:asciiname":"Dowlatabad-e Qadim",
    "gn:country_code":"IR",
    "gn:dem":480,
    "gn:feature_class":"P",
    "gn:feature_code":"PPL",
    "gn:name":"Dowlat\u0101b\u0101d-e Qad\u012bm",
    "gn:population":0,
    "gn:timezone":"Asia/Tehran",
    "iso:country":"IR",
    "name:fas_x_preferred":[
        "\u062f\u0648\u0644\u062a \u0622\u0628\u0627\u062f \u0642\u062f\u06cc\u0645"
    ],
    "name:fas_x_variant":[
        "Dowlat\u0101b\u0101d",
        "Dowlat\u0101b\u0101d-e Qad\u012bm"
    ],
    "wof:name":"Dowlatabad-e Qadim",
    "wof:placetype":"locality"
},
  "geometry": {"coordinates":[61.6393,31.2399],"type":"Point"}
}