{
  "type": "Feature",
  "properties": {
    "gn:admin1_code":"7",
    "gn:asciiname":"Mahalleh-ye Molla'i",
    "gn:country_code":"IR",
    "gn:dem":406,
    "gn:feature_class":"P",
    "gn:feature_code":"PPL",
    "gn:name":"Ma\u1e29alleh-ye Moll\u0101\u2019\u012b",
    "gn:population":0,
    "gn:timezone":"Asia/Tehran",
    "iso:country":"IR",
    "name:fas_x_preferred":[
        "\u0645\u0644\u0651\u0627\u0626\u06cc"
    ],
    "name:fas_x_variant":[
        "Moll\u0101\u2019\u012b",
        "\u0645\u062d\u0644\u0647 \u0645\u0648\u0644\u0627\u0626\u06cc"
    ],
    "name:und_x_variant":[
        "Ma\u1e29alleh-ye Moll\u0101\u2019\u012b"
    ],
    "wof:name":"Mahalleh-ye Molla'i",
    "wof:placetype":"locality"
},
  "geometry": {"coordinates":[53.2401,27.3271],"type":"Point"}
}