{
  "type": "Feature",
  "properties": {
    "gn:admin1_code":"11",
    "gn:asciiname":"Dargaz",
    "gn:country_code":"IR",
    "gn:dem":1175,
    "gn:feature_class":"P",
    "gn:feature_code":"PPL",
    "gn:name":"Dargaz",
    "gn:population":0,
    "gn:timezone":"Asia/Tehran",
    "iso:country":"IR",
    "name:fas_x_preferred":[
        "\u062f\u0631\u06af\u0632\u0648"
    ],
    "name:fas_x_variant":[
        "\u062f\u0631\u06af\u0632",
        "\u062f\u064e\u0631\u06af\u0650\u0632\u0648",
        "Dargaz\u016b"
    ],
    "name:msa_x_preferred":[
        "Dargaz"
    ],
    "name:und_x_variant":[
        "Dargez\u016b"
    ],
    "wof:name":"Dargaz",
    "wof:placetype":"locality"
},
  "geometry": {"coordinates":[56.7312,28.0391],"type":"Point"}
}