{
  "type": "Feature",
  "properties": {
    "gn:admin1_code":"13",
    "gn:asciiname":"Chalaveh",
    "gn:country_code":"IR",
    "gn:dem":1329,
    "gn:feature_class":"P",
    "gn:feature_code":"PPL",
    "gn:name":"Ch\u0101l\u0101veh",
    "gn:population":0,
    "gn:timezone":"Asia/Tehran",
    "iso:country":"IR",
    "wof:name":"Chalaveh",
    "wof:placetype":"locality"
},
  "geometry": {"coordinates":[46.28333,34.56278],"type":"Point"}
}