{
  "type": "Feature",
  "properties": {
    "gn:admin1_code":"41",
    "gn:asciiname":"Gusheh-ye Bala",
    "gn:country_code":"IR",
    "gn:dem":1840,
    "gn:feature_class":"P",
    "gn:feature_code":"PPLF",
    "gn:name":"G\u016bsheh-ye B\u0101l\u0101",
    "gn:population":0,
    "gn:timezone":"Asia/Tehran",
    "iso:country":"IR",
    "name:fas_x_preferred":[
        "\u06a9\u0644\u0627\u062a \u06a9\u0648\u0634\u0647"
    ],
    "name:fas_x_variant":[
        "K\u016bsheh-ye B\u0101l\u0101",
        "Kal\u0101t-e K\u016bsheh",
        "\u06af\u0648\u0634\u0647 \u0628\u0627\u0644\u0627",
        "\u06a9\u0648\u0634\u0647 \u0639\u0644\u06cc\u0627"
    ],
    "name:und_x_variant":[
        "Kal\u0101teh Q\u016bsheh",
        "Q\u016bsheh",
        "Kal\u0101teh K\u016bsheh",
        "G\u016bsheh-ye B\u0101l\u0101",
        "K\u016bsheh",
        "K\u016bsheh-ye \u2018Oly\u0101"
    ],
    "wof:name":"Gusheh-ye Bala",
    "wof:placetype":"locality"
},
  "geometry": {"coordinates":[59.6887,32.2043],"type":"Point"}
}