{
  "type": "Feature",
  "properties": {
    "gn:admin1_code":"11",
    "gn:asciiname":"Ba'ini",
    "gn:country_code":"IR",
    "gn:dem":1476,
    "gn:feature_class":"P",
    "gn:feature_code":"PPL",
    "gn:name":"B\u0101\u2019\u012bn\u012b",
    "gn:population":0,
    "gn:timezone":"Asia/Tehran",
    "iso:country":"IR",
    "name:fas_x_preferred":[
        "\u0628\u0627\u0626\u064a\u0646\u06cc"
    ],
    "name:fas_x_variant":[
        "B\u0101\u2019\u012bn\u012b"
    ],
    "wof:name":"Ba'ini",
    "wof:placetype":"locality"
},
  "geometry": {"coordinates":[57.7781,26.7058],"type":"Point"}
}