{
  "type": "Feature",
  "properties": {
    "gn:admin1_code":"23",
    "gn:asciiname":"Bareh Jula",
    "gn:country_code":"IR",
    "gn:dem":1507,
    "gn:feature_class":"P",
    "gn:feature_code":"PPL",
    "gn:name":"Bareh J\u016bl\u0101",
    "gn:population":0,
    "gn:timezone":"Asia/Tehran",
    "iso:country":"IR",
    "name:fas_x_preferred":[
        "\u0628\u064e\u0631\u0650\u0647 \u062c\u0648\u0644\u0627"
    ],
    "name:fas_x_variant":[
        "\u0628\u064e\u0631\u0627 \u062c\u0648\u0644\u0627",
        "\u0628\u0650\u0631\u064e\u0647 \u062c\u0648\u0644\u0627",
        "\u0628\u0631\u0647 \u062c\u0648\u0644\u0627",
        "Bareh J\u016bl\u0101"
    ],
    "name:und_x_variant":[
        "Bar\u0101 J\u016bl\u0101",
        "Berah J\u016bl\u0101"
    ],
    "wof:name":"Bareh Jula",
    "wof:placetype":"locality"
},
  "geometry": {"coordinates":[47.3479,33.5603],"type":"Point"}
}