{
  "type": "Feature",
  "properties": {
    "gn:admin1_code":"33.0",
    "gn:asciiname":"Jaliz",
    "gn:country_code":"IR",
    "gn:dem":1789,
    "gn:feature_class":"P",
    "gn:feature_code":"PPL",
    "gn:name":"Jal\u012bz",
    "gn:population":0,
    "gn:timezone":"Asia/Tehran",
    "iso:country":"IR",
    "wof:name":"Jaliz",
    "wof:placetype":"locality"
},
  "geometry": {"coordinates":[47.35222,38.54944],"type":"Point"}
}