{
  "type": "Feature",
  "properties": {
    "gn:admin1_code":"29",
    "gn:asciiname":"Deh Khezri",
    "gn:cc2":"IR",
    "gn:country_code":"IR",
    "gn:dem":1953,
    "gn:feature_class":"P",
    "gn:feature_code":"PPL",
    "gn:name":"Deh Khe\u1e95r\u012b",
    "gn:population":0,
    "gn:timezone":"Asia/Tehran",
    "iso:country":"IR",
    "name:fas_x_preferred":[
        "Deh Khe\u1e95r\u012b"
    ],
    "name:und_x_variant":[
        "T\u0101j\u0101b\u0101d"
    ],
    "wof:name":"Deh Khezri",
    "wof:placetype":"locality"
},
  "geometry": {"coordinates":[56.83333,30.36361],"type":"Point"}
}