{
  "type": "Feature",
  "properties": {
    "gn:admin1_code":"15",
    "gn:asciiname":"Dehzanan",
    "gn:country_code":"IR",
    "gn:dem":769,
    "gn:feature_class":"P",
    "gn:feature_code":"PPLL",
    "gn:name":"Dehzan\u0101n",
    "gn:population":0,
    "gn:timezone":"Asia/Tehran",
    "iso:country":"IR",
    "name:fas_x_preferred":[
        "Dehzan\u0101n"
    ],
    "name:fas_x_variant":[
        "\u062f\u0647\u0632\u0646\u0627\u0646"
    ],
    "wof:name":"Dehzanan",
    "wof:placetype":"locality"
},
  "geometry": {"coordinates":[48.9939,32.86813],"type":"Point"}
}