{
  "type": "Feature",
  "properties": {
    "gn:admin1_code":"15.0",
    "gn:asciiname":"Bu Mashilash",
    "gn:country_code":"IR",
    "gn:dem":12,
    "gn:feature_class":"P",
    "gn:feature_code":"PPL",
    "gn:name":"B\u016b Mash\u012blash",
    "gn:population":0,
    "gn:timezone":"Asia/Tehran",
    "iso:country":"IR",
    "name:azb_x_preferred":[
        "\u0627\u0628\u0648\u0645\u0634\u06cc\u0644\u0634"
    ],
    "name:ceb_x_preferred":[
        "Ab\u016b Mosheyleysh"
    ],
    "name:fas_x_preferred":[
        "\u0627\u0628\u0648 \u0645\u0634\u06cc\u0644\u0634"
    ],
    "name:fas_x_variant":[
        "Ab\u016b Mosheyleysh",
        "\u0628\u0648 \u0645\u0634\u06cc\u0644\u0634",
        "\u0627\u0628\u0648\u0645\u0634\u06cc\u0644\u0634"
    ],
    "name:swe_x_preferred":[
        "Ab\u016b Mosheyleysh"
    ],
    "name:und_x_variant":[
        "Ab\u016b Mash\u012bl\u012bsh",
        "Aboo Meshilesh",
        "B\u016b Mash\u012blash"
    ],
    "wof:name":"Bu Mashilash",
    "wof:placetype":"locality"
},
  "geometry": {"coordinates":[48.38821,31.06003],"type":"Point"}
}