{
  "type": "Feature",
  "properties": {
    "gn:admin1_code":"35",
    "gn:asciiname":"Valaji Mahalleh",
    "gn:country_code":"IR",
    "gn:dem":68,
    "gn:feature_class":"P",
    "gn:feature_code":"PPL",
    "gn:name":"Valaj\u012b Ma\u1e29alleh",
    "gn:population":0,
    "gn:timezone":"Asia/Tehran",
    "iso:country":"IR",
    "name:fas_x_preferred":[
        "\u0648\u064e\u0644\u064e\u062c\u06cc \u0645\u064e\u062d\u064e\u0644\u0650\u0651\u0647"
    ],
    "name:fas_x_variant":[
        "Valaj\u012b Ma\u1e29alleh"
    ],
    "wof:name":"Valaji Mahalleh",
    "wof:placetype":"locality"
},
  "geometry": {"coordinates":[53.28333000000001,36.61667],"type":"Point"}
}