{
  "type": "Feature",
  "properties": {
    "gn:admin1_code":"42.0",
    "gn:asciiname":"Golarcheh-ye Sofla",
    "gn:country_code":"IR",
    "gn:dem":849,
    "gn:feature_class":"P",
    "gn:feature_code":"PPL",
    "gn:name":"Gol\u0101rcheh-ye Sofl\u00e1",
    "gn:population":0,
    "gn:timezone":"Asia/Tehran",
    "iso:country":"IR",
    "name:ceb_x_preferred":[
        "Gol\u0101rcheh-ye Sofl\u00e1"
    ],
    "name:fas_x_preferred":[
        "Gol\u0101rcheh-ye Sofl\u00e1"
    ],
    "name:fas_x_variant":[
        "Gol\u0101rcheh-ye P\u0101\u2019\u012bn",
        "\u06af\u0644\u0627\u0631\u0686\u0647 \u0633\u0641\u0644\u06cc",
        "\u06af\u0644\u062f\u0631\u0686\u0647 \u0633\u0641\u0644\u06cc"
    ],
    "name:swe_x_preferred":[
        "Gol\u0101rcheh-ye Sofl\u00e1"
    ],
    "name:und_x_variant":[
        "\u06af\u0644\u0627\u0631\u0686\u0647 \u0633\u0641\u0644\u06cc"
    ],
    "wof:name":"Golarcheh-ye Sofla",
    "wof:placetype":"locality"
},
  "geometry": {"coordinates":[61.04827,35.59966],"type":"Point"}
}