{
  "type": "Feature",
  "properties": {
    "gn:admin1_code":"41.0",
    "gn:asciiname":"Chah-e Vali `Asr Shomareh Yek",
    "gn:country_code":"IR",
    "gn:dem":1505,
    "gn:feature_class":"P",
    "gn:feature_code":"PPL",
    "gn:name":"Chah-e Val\u012b \u2018A\u015fr Shom\u0101reh Yek",
    "gn:population":0,
    "gn:timezone":"Asia/Tehran",
    "iso:country":"IR",
    "name:fas_x_preferred":[
        "\u0686\u0627\u0647 \u0648\u0644\u06cc \u0639\u0635\u0631 \u0634\u0645\u0627\u0631\u0647 \u06f1"
    ],
    "name:und_x_variant":[
        "Chah-e Val\u012b \u2018A\u015fr Shom\u0101reh Yek"
    ],
    "wof:name":"Chah-e Vali `Asr Shomareh Yek",
    "wof:placetype":"locality"
},
  "geometry": {"coordinates":[59.16297,32.49409],"type":"Point"}
}