{
  "type": "Feature",
  "properties": {
    "gn:admin1_code":"35.0",
    "gn:asciiname":"Dulmarz",
    "gn:country_code":"IR",
    "gn:dem":-12,
    "gn:feature_class":"P",
    "gn:feature_code":"PPL",
    "gn:name":"D\u016blmarz",
    "gn:population":0,
    "gn:timezone":"Asia/Tehran",
    "iso:country":"IR",
    "name:fas_x_preferred":[
        "\u062f\u064f\u0648\u0644\u0650\u0645\u064e\u0631\u0632"
    ],
    "name:fas_x_variant":[
        "D\u016blmarz",
        "\u062f\u0648\u0644\u0645\u0631\u0632"
    ],
    "name:und_x_variant":[
        "Dowlemarz"
    ],
    "wof:name":"Dulmarz",
    "wof:placetype":"locality"
},
  "geometry": {"coordinates":[53.19079,36.74554000000001],"type":"Point"}
}