{
  "type": "Feature",
  "properties": {
    "gn:admin1_code":"7",
    "gn:asciiname":"Bagh-e Viskaneh",
    "gn:cc2":"IR",
    "gn:country_code":"IR",
    "gn:dem":1741,
    "gn:feature_class":"P",
    "gn:feature_code":"PPL",
    "gn:name":"B\u0101gh-e V\u012bskaneh",
    "gn:population":0,
    "gn:timezone":"Asia/Tehran",
    "iso:country":"IR",
    "name:fas_x_preferred":[
        "B\u0101gh-e V\u012bskaneh"
    ],
    "name:und_x_variant":[
        "Visvan",
        "B\u0101gh-e Vast\u0101neh",
        "Vishaneh",
        "B\u0101gh-i-Vishaneh"
    ],
    "wof:name":"Bagh-e Viskaneh",
    "wof:placetype":"locality"
},
  "geometry": {"coordinates":[54.81667,29.35],"type":"Point"}
}