{
  "type": "Feature",
  "properties": {
    "gn:admin1_code":"15",
    "gn:asciiname":"Dehliz",
    "gn:country_code":"IR",
    "gn:dem":19,
    "gn:feature_class":"P",
    "gn:feature_code":"PPL",
    "gn:name":"Dehl\u012bz",
    "gn:population":0,
    "gn:timezone":"Asia/Tehran",
    "iso:country":"IR",
    "name:ara_x_preferred":[
        "\u062f\u0647\u0644\u064a\u0632"
    ],
    "name:azb_x_preferred":[
        "\u062f\u0647\u0644\u06cc\u0632(\u0627\u0647\u0648\u0627\u0632)"
    ],
    "name:fas_x_preferred":[
        "\u062f\u0647\u0644\u06cc\u0632 \u06cc\u06a9"
    ],
    "name:fas_x_variant":[
        "Dehl\u012bz",
        "Dehl\u012bz-e Yek",
        "\u062f\u0647\u0644\u06cc\u0632",
        "\u062f\u0647\u0644\u06cc\u0632 \u062f\u0648"
    ],
    "name:und_x_variant":[
        "Dehl\u012bz-e Do"
    ],
    "wof:name":"Dehliz",
    "wof:placetype":"locality"
},
  "geometry": {"coordinates":[48.45914000000001,31.36654],"type":"Point"}
}