{
  "type": "Feature",
  "properties": {
    "gn:admin1_code":"42",
    "gn:asciiname":"`Abbasabad",
    "gn:country_code":"IR",
    "gn:dem":1754,
    "gn:feature_class":"P",
    "gn:feature_code":"PPL",
    "gn:name":"\u2018Abb\u0101s\u0101b\u0101d",
    "gn:population":0,
    "gn:timezone":"Asia/Tehran",
    "iso:country":"IR",
    "name:fas_x_preferred":[
        "\u0639\u0628\u0627\u0633 \u0622\u0628\u0627\u062f"
    ],
    "name:fas_x_variant":[
        "\u2018Abb\u0101s\u0101b\u0101d"
    ],
    "wof:name":"`Abbasabad",
    "wof:placetype":"locality"
},
  "geometry": {"coordinates":[59.39366999999999,35.77473],"type":"Point"}
}