{
  "type": "Feature",
  "properties": {
    "gn:admin1_code":"11",
    "gn:asciiname":"Sang Tarash",
    "gn:country_code":"IR",
    "gn:dem":629,
    "gn:feature_class":"P",
    "gn:feature_code":"PPL",
    "gn:name":"Sang Tar\u0101sh",
    "gn:population":0,
    "gn:timezone":"Asia/Tehran",
    "iso:country":"IR",
    "name:fas_x_preferred":[
        "\u0633\u0646\u06af \u062a\u0631\u0627\u0634"
    ],
    "name:fas_x_variant":[
        "Sang Tar\u0101sh"
    ],
    "wof:name":"Sang Tarash",
    "wof:placetype":"locality"
},
  "geometry": {"coordinates":[57.5625,26.7658],"type":"Point"}
}