{
  "type": "Feature",
  "properties": {
    "gn:admin1_code":"13",
    "gn:asciiname":"Shah Maleki",
    "gn:country_code":"IR",
    "gn:dem":1281,
    "gn:feature_class":"P",
    "gn:feature_code":"PPL",
    "gn:name":"Sh\u0101h Malek\u012b",
    "gn:population":0,
    "gn:timezone":"Asia/Tehran",
    "iso:country":"IR",
    "name:ceb_x_preferred":[
        "Sh\u0101h Malek\u012b"
    ],
    "name:fas_x_preferred":[
        "\u0634\u0627\u0647 \u0645\u0644\u06a9\u06cc"
    ],
    "name:fas_x_variant":[
        "Sh\u0101h Malek\u012b",
        "\u0634\u0627\u0647\u200c\u0645\u0644\u06a9\u06cc"
    ],
    "name:swe_x_preferred":[
        "Sh\u0101h Malek\u012b"
    ],
    "name:und_x_variant":[
        "Ch\u0101h Malak\u012b",
        "Sh\u0101h Molk\u012b",
        "Sh\u0101h Malak\u012b",
        "Sh\u0101h M\u0101l\u012bk\u012b"
    ],
    "wof:name":"Shah Maleki",
    "wof:placetype":"locality"
},
  "geometry": {"coordinates":[47.3988,34.3037],"type":"Point"}
}