{
  "type": "Feature",
  "properties": {
    "gn:admin1_code":"22",
    "gn:asciiname":"Jamali",
    "gn:country_code":"IR",
    "gn:dem":45,
    "gn:feature_class":"P",
    "gn:feature_code":"PPL",
    "gn:name":"Jam\u0101l\u012b",
    "gn:population":0,
    "gn:timezone":"Asia/Tehran",
    "iso:country":"IR",
    "name:ceb_x_preferred":[
        "Jam\u0101l\u012b"
    ],
    "name:fas_x_preferred":[
        "\u062c\u0645\u0627\u0644\u06cc \u0632\u0627\u064a\u0631 \u062d\u0633\u064a\u0646"
    ],
    "name:fas_x_variant":[
        "\u0632\u0627\u0626\u0650\u0631 \u0647\u064e\u0633\u064e\u0646 \u062c\u064e\u0645\u0627\u0644\u06cc",
        "\u062c\u064e\u0645\u0627\u0644\u06cc \u0632\u0627\u0626\u0650\u0631 \u062d\u064e\u0633\u064e\u0646",
        "\u0632\u0627\u0626\u0631 \u062d\u0633\u064a\u0646 \u062c\u0645\u0627\u0644\u06cc",
        "Z\u0101\u2019er \u1e28oseyn-e Jam\u0101l\u012b",
        "\u062c\u0645\u0627\u0644\u06cc",
        "\u062c\u0645\u0627\u0644\u06cc \u0632\u0627\u06cc\u0631\u062d\u0633\u06cc\u0646"
    ],
    "name:swe_x_preferred":[
        "Jam\u0101l\u012b"
    ],
    "name:und_x_variant":[
        "Z\u0101\u2019er Hasan Jam\u0101l\u012b",
        "Jam\u0101l\u012b Z\u0101\u2019er \u1e28asan",
        "Jam\u0101l\u012b Z\u0101yer \u1e28oseyn",
        "Jam\u0101l\u012b"
    ],
    "name:urd_x_preferred":[
        "\u062c\u0645\u0627\u0644\u06cc \u0632\u0627\u06cc\u0631\u062d\u0633\u06cc\u0646"
    ],
    "wof:name":"Jamali",
    "wof:placetype":"locality"
},
  "geometry": {"coordinates":[51.272,28.9292],"type":"Point"}
}