{
  "type": "Feature",
  "properties": {
    "gn:admin1_code":"29",
    "gn:asciiname":"Baluchi",
    "gn:country_code":"IR",
    "gn:dem":1565,
    "gn:feature_class":"P",
    "gn:feature_code":"PPL",
    "gn:name":"Bal\u016bch\u012b",
    "gn:population":0,
    "gn:timezone":"Asia/Tehran",
    "iso:country":"IR",
    "name:deu_x_preferred":[
        "Baluchi"
    ],
    "name:fas_x_preferred":[
        "\u0628\u0644\u0648\u0686\u06cc"
    ],
    "name:fas_x_variant":[
        "Bal\u016bch\u012b"
    ],
    "name:fra_x_preferred":[
        "Baluchi"
    ],
    "wof:name":"Baluchi",
    "wof:placetype":"locality"
},
  "geometry": {"coordinates":[57.0801,28.9231],"type":"Point"}
}