{
  "type": "Feature",
  "properties": {
    "gn:admin1_code":"35.0",
    "gn:asciiname":"Karchak-e Nava'i",
    "gn:country_code":"IR",
    "gn:dem":15,
    "gn:feature_class":"P",
    "gn:feature_code":"PPL",
    "gn:name":"Karchak-e Nav\u0101\u2019\u012b",
    "gn:population":0,
    "gn:timezone":"Asia/Tehran",
    "iso:country":"IR",
    "name:fas_x_preferred":[
        "\u0643\u0631\u0686\u06a9 \u0646\u0648\u0627\u0626\u06cc"
    ],
    "name:fas_x_variant":[
        "Karchak-e Nav\u0101\u2019\u012b"
    ],
    "wof:name":"Karchak-e Nava'i",
    "wof:placetype":"locality"
},
  "geometry": {"coordinates":[52.3206,36.54734000000001],"type":"Point"}
}