{
  "type": "Feature",
  "properties": {
    "gn:admin1_code":"15",
    "gn:asciiname":"Chehel Howzan",
    "gn:country_code":"IR",
    "gn:dem":780,
    "gn:feature_class":"P",
    "gn:feature_code":"PPL",
    "gn:name":"Chehel Howz\u0101n",
    "gn:population":0,
    "gn:timezone":"Asia/Tehran",
    "iso:country":"IR",
    "name:fas_x_preferred":[
        "Chehel Howz\u0101n"
    ],
    "wof:name":"Chehel Howzan",
    "wof:placetype":"locality"
},
  "geometry": {"coordinates":[49.98333,31.98417],"type":"Point"}
}