{
  "type": "Feature",
  "properties": {
    "gn:admin1_code":"7",
    "gn:asciiname":"Hoseynabad",
    "gn:country_code":"IR",
    "gn:dem":2322,
    "gn:feature_class":"P",
    "gn:feature_code":"PPL",
    "gn:name":"\u1e28oseyn\u0101b\u0101d",
    "gn:population":0,
    "gn:timezone":"Asia/Tehran",
    "iso:country":"IR",
    "name:ara_x_preferred":[
        "\u062d\u0633\u064a\u0646\u200c\u0622\u0628\u0627\u062f"
    ],
    "name:fas_x_preferred":[
        "\u062d\u0633\u06cc\u0646 \u0622\u0628\u0627\u062f"
    ],
    "name:fas_x_variant":[
        "\u1e28oseyn\u0101b\u0101d",
        "\u062d\u0633\u06cc\u0646\u200c\u0622\u0628\u0627\u062f"
    ],
    "name:msa_x_preferred":[
        "Hoseynabad"
    ],
    "name:und_x_variant":[
        "Qal\u2018eh-e \u1e28oseyn\u0101b\u0101d"
    ],
    "wof:name":"Hoseynabad",
    "wof:placetype":"locality"
},
  "geometry": {"coordinates":[52.5959,30.6886],"type":"Point"}
}