{
  "type": "Feature",
  "properties": {
    "gn:admin1_code":"32.0",
    "gn:asciiname":"Qoli Beyglu",
    "gn:country_code":"IR",
    "gn:dem":1388,
    "gn:feature_class":"P",
    "gn:feature_code":"PPL",
    "gn:name":"Qol\u012b Beygl\u016b",
    "gn:population":0,
    "gn:timezone":"Asia/Tehran",
    "iso:country":"IR",
    "name:fas_x_preferred":[
        "\u0642\u0644\u06cc \u0628\u06cc\u06af\u0644\u0648"
    ],
    "name:fas_x_variant":[
        "Qol\u012b Beygl\u016b"
    ],
    "wof:name":"Qoli Beyglu",
    "wof:placetype":"locality"
},
  "geometry": {"coordinates":[48.0942,38.5024],"type":"Point"}
}