{
  "type": "Feature",
  "properties": {
    "gn:admin1_code":"7",
    "gn:asciiname":"Mazru",
    "gn:country_code":"IR",
    "gn:dem":1787,
    "gn:feature_class":"P",
    "gn:feature_code":"PPL",
    "gn:name":"Mazr\u016b",
    "gn:population":0,
    "gn:timezone":"Asia/Tehran",
    "iso:country":"IR",
    "name:fas_x_preferred":[
        "\u0645\u0632\u0631\u0648"
    ],
    "name:fas_x_variant":[
        "Mazr\u016b"
    ],
    "name:msa_x_preferred":[
        "Mazru"
    ],
    "name:und_x_variant":[
        "Mazroo",
        "Marr\u016b",
        "Mazrow"
    ],
    "wof:name":"Mazru",
    "wof:placetype":"locality"
},
  "geometry": {"coordinates":[54.469,28.8572],"type":"Point"}
}