{
  "type": "Feature",
  "properties": {
    "gn:admin1_code":"13",
    "gn:asciiname":"Toveh Sorkhak-e `Olya Bar Aftab",
    "gn:country_code":"IR",
    "gn:dem":1381,
    "gn:feature_class":"P",
    "gn:feature_code":"PPL",
    "gn:name":"Toveh Sorkhak-e \u2018Oly\u0101 Bar \u0100ft\u0101b",
    "gn:population":0,
    "gn:timezone":"Asia/Tehran",
    "iso:country":"IR",
    "name:fas_x_preferred":[
        "\u062a\u0648\u0647 \u0633\u0631\u062e\u06a9 \u0639\u0644\u06cc\u0627"
    ],
    "name:fas_x_variant":[
        "Tovasorkhak-e \u2018Oly\u0101",
        "\u0632\u0646\u06af\u0646\u0647",
        "Toveh Sorkhak-e \u2018Oly\u0101",
        "\u062a\u0648\u0647 \u0633\u0631\u062e\u06a9 \u0639\u0644\u06cc\u0627 \u0628\u0631 \u0622\u0641\u062a\u0627\u0628"
    ],
    "name:und_x_variant":[
        "Tuvehsorkhak",
        "Toveh Sorkhak",
        "Tu yi S\u0101r-i-Kh\u0101k",
        "Toveh-ye Sorkhak",
        "T\u016b-ye Sari Khak",
        "T\u016b Sorkhak-e \u1e28ajj Val\u012b",
        "Toveh Sorkhak-e P\u0101\u2019\u012bn",
        "Tua Sarkhak",
        "Zangeneh",
        "Toveh Sorkhak-e \u2018Oly\u0101 Bar \u0100ft\u0101b",
        "Zanganeh"
    ],
    "wof:name":"Toveh Sorkhak-e `Olya Bar Aftab",
    "wof:placetype":"locality"
},
  "geometry": {"coordinates":[46.8414,33.9712],"type":"Point"}
}