{
  "type": "Feature",
  "properties": {
    "gn:admin1_code":"16",
    "gn:asciiname":"Yalquz Aghaj",
    "gn:country_code":"IR",
    "gn:dem":1778,
    "gn:feature_class":"P",
    "gn:feature_code":"PPL",
    "gn:name":"Yalq\u016bz \u0100gh\u0101j",
    "gn:population":0,
    "gn:timezone":"Asia/Tehran",
    "iso:country":"IR",
    "name:fas_x_preferred":[
        "\u064a\u0627\u0644\u063a\u0648\u0632 \u0622\u063a\u0627\u062c"
    ],
    "name:fas_x_variant":[
        "Y\u0101lq\u016bz \u0100gh\u0101j",
        "Yalq\u016bz \u0100q\u0101j",
        "\u064a\u0644\u0642\u0648\u0632 \u0622\u0642\u0627\u062c",
        "\u06cc\u0644\u0642\u0648\u0632 \u0622\u063a\u0627\u062c",
        "\u06cc\u0627\u0644\u063a\u0648\u0632 \u0622\u063a\u0627\u062c"
    ],
    "name:und_x_variant":[
        "\u0100l\u016bz\u0101qaj",
        "Holz\u0101q\u0101ch",
        "Yalq\u016bz Agh\u0101j",
        "Huluzagach",
        "Yalghuz Aghach",
        "Y\u0101lgh\u016bz \u0100gh\u0101j",
        "\u064a\u0644\u0642\u0648\u0632 \u0622\u0642\u0627\u062c",
        "Yalq\u016bz \u0100gh\u0101j"
    ],
    "name:urd_x_preferred":[
        "\u06cc\u0644\u06af\u062d\u0632 \u0627\u063a\u0627\u062c"
    ],
    "wof:name":"Yalquz Aghaj",
    "wof:placetype":"locality"
},
  "geometry": {"coordinates":[47.59483,35.29924000000001],"type":"Point"}
}