{
  "type": "Feature",
  "properties": {
    "gn:admin1_code":"35.0",
    "gn:asciiname":"Amirabad-e Mian Rud",
    "gn:country_code":"IR",
    "gn:dem":58,
    "gn:feature_class":"P",
    "gn:feature_code":"PPL",
    "gn:name":"Am\u012br\u0101b\u0101d-e M\u012b\u0101n R\u016bd",
    "gn:population":0,
    "gn:timezone":"Asia/Tehran",
    "iso:country":"IR",
    "name:fas_x_preferred":[
        "\u0627\u0645\u064a\u0631 \u0622\u0628\u0627\u062f"
    ],
    "name:fas_x_variant":[
        "Am\u012br\u0101b\u0101d",
        "\u0627\u0645\u06cc\u0631 \u0622\u0628\u0627\u062f \u0645\u06cc\u0627\u0646 \u0631\u0648\u062f"
    ],
    "name:und_x_variant":[
        "Am\u012br\u0101b\u0101d-e M\u012b\u0101n R\u016bd"
    ],
    "wof:name":"Amirabad-e Mian Rud",
    "wof:placetype":"locality"
},
  "geometry": {"coordinates":[52.23616,36.4676],"type":"Point"}
}