{
  "type": "Feature",
  "properties": {
    "gn:admin1_code":"35",
    "gn:asciiname":"Terkam",
    "gn:country_code":"IR",
    "gn:dem":1394,
    "gn:feature_class":"P",
    "gn:feature_code":"PPL",
    "gn:name":"Terk\u0101m",
    "gn:population":0,
    "gn:timezone":"Asia/Tehran",
    "iso:country":"IR",
    "name:fas_x_preferred":[
        "\u062a\u0650\u0631\u0643\u0627\u0645"
    ],
    "name:fas_x_variant":[
        "Terk\u0101m"
    ],
    "wof:name":"Terkam",
    "wof:placetype":"locality"
},
  "geometry": {"coordinates":[53.61666999999999,36.26667],"type":"Point"}
}