{
  "type": "Feature",
  "properties": {
    "gn:admin1_code":"43",
    "gn:asciiname":"Khvosh-e Bala",
    "gn:country_code":"IR",
    "gn:dem":1112,
    "gn:feature_class":"P",
    "gn:feature_code":"PPL",
    "gn:name":"Khvosh-e B\u0101l\u0101",
    "gn:population":0,
    "gn:timezone":"Asia/Tehran",
    "iso:country":"IR",
    "name:ceb_x_preferred":[
        "Khvosh-e B\u0101l\u0101"
    ],
    "name:fas_x_preferred":[
        "Khvosh-e B\u0101l\u0101"
    ],
    "name:fas_x_variant":[
        "\u062e\u0648\u0634 \u0628\u0627\u0644\u0627"
    ],
    "name:swe_x_preferred":[
        "Khvosh-e B\u0101l\u0101"
    ],
    "name:und_x_variant":[
        "J\u016bsh",
        "K\u016bshk B\u0101l\u0101",
        "Khvosh B\u0101l\u0101"
    ],
    "wof:name":"Khvosh-e Bala",
    "wof:placetype":"locality"
},
  "geometry": {"coordinates":[57.34339,37.12673],"type":"Point"}
}