{
  "type": "Feature",
  "properties": {
    "gn:admin1_code":"11",
    "gn:asciiname":"Estakhr-e Bala",
    "gn:country_code":"IR",
    "gn:dem":1472,
    "gn:feature_class":"P",
    "gn:feature_code":"PPL",
    "gn:name":"Estakhr-e B\u0101l\u0101",
    "gn:population":0,
    "gn:timezone":"Asia/Tehran",
    "iso:country":"IR",
    "name:fas_x_preferred":[
        "\u0627\u0633\u062a\u062e\u0631 \u0639\u0644\u06cc\u0627"
    ],
    "name:fas_x_variant":[
        "Estakhr-e \u2018Oly\u0101",
        "\u0627\u0633\u062a\u062e\u0631 \u0628\u0627\u0644\u0627",
        "\u0627\u0633\u062a\u062e\u0631"
    ],
    "name:und_x_variant":[
        "Estakhr-e B\u0101l\u0101",
        "Estakhr"
    ],
    "wof:name":"Estakhr-e Bala",
    "wof:placetype":"locality"
},
  "geometry": {"coordinates":[55.4267,28.5035],"type":"Point"}
}