{
  "type": "Feature",
  "properties": {
    "gn:admin1_code":"35",
    "gn:asciiname":"Buran",
    "gn:country_code":"IR",
    "gn:dem":87,
    "gn:feature_class":"P",
    "gn:feature_code":"PPL",
    "gn:name":"B\u016br\u0101n",
    "gn:population":0,
    "gn:timezone":"Asia/Tehran",
    "iso:country":"IR",
    "name:fas_x_preferred":[
        "\u0628\u0648\u0631\u0627\u0646"
    ],
    "name:fas_x_variant":[
        "B\u016br\u0101n"
    ],
    "wof:name":"Buran",
    "wof:placetype":"locality"
},
  "geometry": {"coordinates":[52.40213,36.46457],"type":"Point"}
}