{
  "type": "Feature",
  "properties": {
    "gn:admin1_code":"35",
    "gn:asciiname":"Buran",
    "gn:country_code":"IR",
    "gn:dem":87,
    "gn:feature_class":"P",
    "gn:feature_code":"PPL",
    "gn:name":"B\u016br\u0101n",
    "gn:population":0,
    "gn:timezone":"Asia/Tehran",
    "iso:country":"IR",
    "name:ara_x_preferred":[
        "\u0628\u0648\u0631\u0627\u0646"
    ],
    "name:aze_x_preferred":[
        "Buran"
    ],
    "name:ceb_x_preferred":[
        "Buran"
    ],
    "name:ces_x_preferred":[
        "Buran"
    ],
    "name:deu_x_preferred":[
        "Buran"
    ],
    "name:ell_x_preferred":[
        "\u039c\u03c0\u03bf\u03c5\u03c1\u03ac\u03bd"
    ],
    "name:fas_x_preferred":[
        "\u0628\u0648\u0631\u0627\u0646"
    ],
    "name:fas_x_variant":[
        "B\u016br\u0101n"
    ],
    "name:fra_x_preferred":[
        "Buran"
    ],
    "name:hye_x_preferred":[
        "\u0532\u0578\u0582\u0580\u0561\u0576"
    ],
    "name:ita_x_preferred":[
        "Buran"
    ],
    "name:jpn_x_preferred":[
        "\u30d6\u30e9\u30f3"
    ],
    "name:msa_x_preferred":[
        "Buran"
    ],
    "name:mzn_x_preferred":[
        "\u0628\u0648\u0631\u0627\u0646"
    ],
    "name:nld_x_preferred":[
        "Buran"
    ],
    "name:nor_x_preferred":[
        "Buran"
    ],
    "name:pol_x_preferred":[
        "Buran"
    ],
    "name:ron_x_preferred":[
        "Buran"
    ],
    "name:slk_x_preferred":[
        "Buran"
    ],
    "name:spa_x_preferred":[
        "Bur\u00e1n"
    ],
    "name:tur_x_preferred":[
        "Buran"
    ],
    "name:vie_x_preferred":[
        "Buran"
    ],
    "wof:name":"Buran",
    "wof:placetype":"locality"
},
  "geometry": {"coordinates":[52.40213,36.46457],"type":"Point"}
}