{
  "type": "Feature",
  "properties": {
    "gn:admin1_code":"7",
    "gn:asciiname":"Kushk-e Bibicheh",
    "gn:country_code":"IR",
    "gn:dem":1661,
    "gn:feature_class":"P",
    "gn:feature_code":"PPL",
    "gn:name":"K\u016bshk-e B\u012bb\u012bcheh",
    "gn:population":0,
    "gn:timezone":"Asia/Tehran",
    "iso:country":"IR",
    "name:fas_x_preferred":[
        "K\u016bshk-e B\u012bb\u012bcheh"
    ],
    "wof:name":"Kushk-e Bibicheh",
    "wof:placetype":"locality"
},
  "geometry": {"coordinates":[52.4675,29.69583],"type":"Point"}
}