{
  "type": "Feature",
  "properties": {
    "gn:admin1_code":"9.0",
    "gn:asciiname":"Sadd-e-Ekbatan",
    "gn:country_code":"IR",
    "gn:dem":2028,
    "gn:feature_class":"P",
    "gn:feature_code":"PPL",
    "gn:name":"Sadd-e-Ekb\u0101t\u0101n",
    "gn:population":0,
    "gn:timezone":"Asia/Tehran",
    "iso:country":"IR",
    "wof:name":"Sadd-e-Ekbatan",
    "wof:placetype":"locality"
},
  "geometry": {"coordinates":[48.58528,34.74444],"type":"Point"}
}