{
  "type": "Feature",
  "properties": {
    "gn:admin1_code":"28",
    "gn:asciiname":"Sadian",
    "gn:country_code":"IR",
    "gn:dem":1689,
    "gn:feature_class":"P",
    "gn:feature_code":"PPL",
    "gn:name":"S\u0101d\u012b\u0101n",
    "gn:population":0,
    "gn:timezone":"Asia/Tehran",
    "iso:country":"IR",
    "name:fas_x_preferred":[
        "\u0633\u0627\u062f\u06cc\u0627\u0646"
    ],
    "name:fas_x_variant":[
        "S\u0101d\u012b\u0101n"
    ],
    "name:und_x_variant":[
        "B\u012bd\u012b\u0101n",
        "S\u0101d\u012by\u0101n"
    ],
    "wof:name":"Sadian",
    "wof:placetype":"locality"
},
  "geometry": {"coordinates":[51.1671,33.9101],"type":"Point"}
}