{
  "type": "Feature",
  "properties": {
    "gn:admin1_code":"41",
    "gn:asciiname":"Kalateh-ye Arreh Kuh",
    "gn:country_code":"IR",
    "gn:dem":1952,
    "gn:feature_class":"P",
    "gn:feature_code":"PPLF",
    "gn:name":"Kal\u0101teh-ye Arreh K\u016bh",
    "gn:population":0,
    "gn:timezone":"Asia/Tehran",
    "iso:country":"IR",
    "name:fas_x_preferred":[
        "\u06a9\u0644\u0627\u062a \u062d\u0627\u062c\u062a\u0627"
    ],
    "name:fas_x_variant":[
        "Kal\u0101teh-ye \u1e28\u0101jj\u012b\u0101n",
        "Kal\u0101t-e \u1e28\u0101jjt\u0101",
        "\u06a9\u0644\u0627\u062a\u0647 \u0627\u0631\u0647 \u06a9\u0648\u0647",
        "\u06a9\u0644\u0627\u062a \u0627\u0631\u0647 \u06a9\u0648",
        "\u06a9\u0644\u0627\u062a\u0647 \u062d\u0627\u062c\u06cc \u0639\u0637\u0627",
        "\u0627\u0631\u0647 \u06a9\u0648\u0647"
    ],
    "name:und_x_variant":[
        "Hajiyan",
        "Kal\u0101teh-i-H\u0101j\u012b\u0101n",
        "Kal\u0101teh-ye Arreh K\u016bh",
        "Kal\u0101t-e Arreh K\u016b",
        "Kal\u0101teh-ye \u1e28\u0101jj\u012b \u2018A\u0163\u0101",
        "Arreh K\u016bh"
    ],
    "wof:name":"Kalateh-ye Arreh Kuh",
    "wof:placetype":"locality"
},
  "geometry": {"coordinates":[59.95713000000001,32.75756],"type":"Point"}
}