{
  "type": "Feature",
  "properties": {
    "gn:admin1_code":"7",
    "gn:asciiname":"Ma`dan Ros",
    "gn:country_code":"IR",
    "gn:dem":1800,
    "gn:feature_class":"P",
    "gn:feature_code":"PPL",
    "gn:name":"Ma\u2018dan Ros",
    "gn:population":0,
    "gn:timezone":"Asia/Tehran",
    "iso:country":"IR",
    "name:fas_x_preferred":[
        "\u0645\u0639\u062f\u0646 \u0631\u0633"
    ],
    "name:fas_x_variant":[
        "M\u016br\u0101n D\u012bz",
        "Ma\u2018dan Ros"
    ],
    "name:und_x_variant":[
        "Mard\u0101n R\u012bz",
        "Mudan R\u012bz",
        "Modan R\u012bz"
    ],
    "wof:name":"Ma`dan Ros",
    "wof:placetype":"locality"
},
  "geometry": {"coordinates":[55.3183,28.7332],"type":"Point"}
}