{
  "type": "Feature",
  "properties": {
    "gn:admin1_code":"3",
    "gn:asciiname":"Monj-e Jahrubeh",
    "gn:country_code":"IR",
    "gn:dem":1388,
    "gn:feature_class":"P",
    "gn:feature_code":"PPL",
    "gn:name":"Monj-e Jahr\u016bbeh",
    "gn:population":0,
    "gn:timezone":"Asia/Tehran",
    "iso:country":"IR",
    "name:fas_x_preferred":[
        "Monj-e Char\u016bb"
    ],
    "name:fas_x_variant":[
        "\u0645\u064f\u0646\u062c\u0650 \u0686\u064e\u0631\u0648\u0628",
        "Char\u016bb",
        "\u0686\u0631\u0648\u0628",
        "\u0645\u0646\u062c \u062c\u0647\u0631\u0648\u0628\u0647",
        "\u0645\u0646\u062c \u062c\u0647\u0631\u0648\u0628"
    ],
    "name:und_x_variant":[
        "Monj-e Jahr\u016bbeh",
        "Monj-e Jahr\u016bb"
    ],
    "wof:name":"Monj-e Jahrubeh",
    "wof:placetype":"locality"
},
  "geometry": {"coordinates":[50.6269,31.54237],"type":"Point"}
}