{
  "type": "Feature",
  "properties": {
    "gn:admin1_code":"8.0",
    "gn:asciiname":"Mahalleh-ye Gazaf Rud-e Pa'in",
    "gn:country_code":"IR",
    "gn:dem":-5,
    "gn:feature_class":"P",
    "gn:feature_code":"PPL",
    "gn:name":"Ma\u1e29alleh-ye Gaz\u0101f R\u016bd-e P\u0101\u2019\u012bn",
    "gn:population":0,
    "gn:timezone":"Asia/Tehran",
    "iso:country":"IR",
    "name:fas_x_preferred":[
        "Gaz\u0101f R\u016bd"
    ],
    "name:fas_x_variant":[
        "\u06af\u0632\u0627\u0641 \u0631\u0648\u062f",
        "\u0645\u062d\u0644\u0647 \u06af\u0632\u0627\u0641 \u0631\u0648\u062f \u067e\u0627\u0626\u06cc\u0646"
    ],
    "name:und_x_variant":[
        "\u06af\u0632\u0627\u0641 \u0631\u0648\u062f",
        "Ma\u1e29alleh-ye Gaz\u0101f R\u016bd-e P\u0101\u2019\u012bn"
    ],
    "wof:name":"Mahalleh-ye Gazaf Rud-e Pa'in",
    "wof:placetype":"locality"
},
  "geometry": {"coordinates":[50.39016,37.06946],"type":"Point"}
}