{
  "type": "Feature",
  "properties": {
    "gn:admin1_code":"7.0",
    "gn:asciiname":"Dowlatabad-e Seh",
    "gn:country_code":"IR",
    "gn:dem":1574,
    "gn:feature_class":"P",
    "gn:feature_code":"PPL",
    "gn:name":"Dowlat\u0101b\u0101d-e Seh",
    "gn:population":0,
    "gn:timezone":"Asia/Tehran",
    "iso:country":"IR",
    "name:ara_x_preferred":[
        "\u062f\u0648\u0644\u062a \u0623\u0628\u0627\u062f \u0633\u0647"
    ],
    "name:fas_x_preferred":[
        "\u062f\u0648\u0644\u062a \u0622\u0628\u0627\u062f \u0633\u0647"
    ],
    "name:und_x_variant":[
        "Dowlat\u0101b\u0101d-e Seh"
    ],
    "wof:name":"Dowlatabad-e Seh",
    "wof:placetype":"locality"
},
  "geometry": {"coordinates":[54.22214,29.2865],"type":"Point"}
}