{
  "type": "Feature",
  "properties": {
    "gn:admin1_code":"1.0",
    "gn:asciiname":"Qal`eh Jugheh",
    "gn:country_code":"IR",
    "gn:dem":1580,
    "gn:feature_class":"P",
    "gn:feature_code":"PPL",
    "gn:name":"Qal\u2018eh J\u016bgheh",
    "gn:population":0,
    "gn:timezone":"Asia/Tehran",
    "iso:country":"IR",
    "name:fas_x_preferred":[
        "\u0642\u064e\u0644\u0639\u0650\u0647 \u062c\u0648\u0642\u0650\u0647"
    ],
    "name:fas_x_variant":[
        "\u0642\u0644\u0639\u0647 \u062c\u0648\u063a\u0647",
        "Qal\u2018eh J\u016bgheh"
    ],
    "wof:name":"Qal`eh Jugheh",
    "wof:placetype":"locality"
},
  "geometry": {"coordinates":[45.7599,36.538],"type":"Point"}
}