{
  "type": "Feature",
  "properties": {
    "gn:admin1_code":"29",
    "gn:asciiname":"Dozru",
    "gn:country_code":"IR",
    "gn:dem":2176,
    "gn:feature_class":"P",
    "gn:feature_code":"PPL",
    "gn:name":"Dozr\u016b",
    "gn:population":0,
    "gn:timezone":"Asia/Tehran",
    "iso:country":"IR",
    "name:fas_x_preferred":[
        "Dozr\u016b"
    ],
    "wof:name":"Dozru",
    "wof:placetype":"locality"
},
  "geometry": {"coordinates":[58.15,28.88333],"type":"Point"}
}