{
  "type": "Feature",
  "properties": {
    "gn:admin1_code":"41.0",
    "gn:asciiname":"Mehrak Dahaneh",
    "gn:country_code":"IR",
    "gn:dem":1146,
    "gn:feature_class":"P",
    "gn:feature_code":"PPL",
    "gn:name":"Mehrak Dahaneh",
    "gn:population":0,
    "gn:timezone":"Asia/Tehran",
    "iso:country":"IR",
    "name:fas_x_preferred":[
        "\u06a9\u0644\u0627\u062a\u0647 \u0645\u0647\u0631\u06a9"
    ],
    "name:fas_x_variant":[
        "Kal\u0101teh-ye Mehrak",
        "\u0645\u0647\u0631\u06a9 \u062f\u0647\u0646\u0647"
    ],
    "name:und_x_variant":[
        "Mehrak",
        "Mehrak Dahaneh"
    ],
    "wof:name":"Mehrak Dahaneh",
    "wof:placetype":"locality"
},
  "geometry": {"coordinates":[59.93038000000001,33.58499],"type":"Point"}
}