{
  "type": "Feature",
  "properties": {
    "gn:admin1_code":"7",
    "gn:asciiname":"Shahrak-e Shahed",
    "gn:country_code":"IR",
    "gn:dem":2159,
    "gn:feature_class":"P",
    "gn:feature_code":"PPL",
    "gn:name":"Shahrak-e Sh\u0101hed",
    "gn:population":0,
    "gn:timezone":"Asia/Tehran",
    "iso:country":"IR",
    "name:fas_x_preferred":[
        "\u0634\u0647\u0631\u06a9 \u0645\u0634\u06a9\u0627\u0646"
    ],
    "name:fas_x_variant":[
        "Shahrak-e Meshk\u0101n",
        "\u0634\u0647\u0631\u06a9 \u0634\u0627\u0647\u062f"
    ],
    "name:und_x_variant":[
        "Shahrak-e Sh\u0101hed"
    ],
    "wof:name":"Shahrak-e Shahed",
    "wof:placetype":"locality"
},
  "geometry": {"coordinates":[54.3619,29.4723],"type":"Point"}
}