{
  "type": "Feature",
  "properties": {
    "gn:admin1_code":"7",
    "gn:asciiname":"Pir Ab-e Siah",
    "gn:country_code":"IR",
    "gn:dem":794,
    "gn:feature_class":"P",
    "gn:feature_code":"PPL",
    "gn:name":"P\u012br \u0100b-e S\u012b\u0101h",
    "gn:population":0,
    "gn:timezone":"Asia/Tehran",
    "iso:country":"IR",
    "name:fas_x_preferred":[
        "Sar\u0101b-e S\u012b\u0101h"
    ],
    "name:fas_x_variant":[
        "Sar\u0101b-e Sh\u0101h Nesh\u012bn",
        "\u0633\u0631\u0627\u0628 \u0633\u06cc\u0627\u0647",
        "\u067e\u064a\u0631 \u0622\u0628 \u0633\u064a\u0627\u0647"
    ],
    "name:und_x_variant":[
        "Sar\u0101b-e Sh\u0101n Nesh\u012bn",
        "\u0633\u0631\u0627\u0628 \u0633\u06cc\u0627\u0647",
        "P\u012br \u0100b-e S\u012b\u0101h"
    ],
    "wof:name":"Pir Ab-e Siah",
    "wof:placetype":"locality"
},
  "geometry": {"coordinates":[51.34446,30.35657],"type":"Point"}
}