{
  "type": "Feature",
  "properties": {
    "gn:admin1_code":"4.0",
    "gn:asciiname":"Sahr Sekon",
    "gn:country_code":"IR",
    "gn:dem":1325,
    "gn:feature_class":"P",
    "gn:feature_code":"PPL",
    "gn:name":"Sahr Sekon",
    "gn:population":0,
    "gn:timezone":"Asia/Tehran",
    "iso:country":"IR",
    "name:fas_x_preferred":[
        "\u0633\u0647\u0631 \u0633\u06a9\u0646"
    ],
    "wof:name":"Sahr Sekon",
    "wof:placetype":"locality"
},
  "geometry": {"coordinates":[61.94199,27.6583],"type":"Point"}
}