{
  "type": "Feature",
  "properties": {
    "gn:admin1_code":"13",
    "gn:asciiname":"Balvan",
    "gn:country_code":"IR",
    "gn:dem":641,
    "gn:feature_class":"P",
    "gn:feature_code":"PPL",
    "gn:name":"Balv\u0101n",
    "gn:population":0,
    "gn:timezone":"Asia/Tehran",
    "iso:country":"IR",
    "name:fas_x_preferred":[
        "\u0628\u0644\u0648\u0627\u0646"
    ],
    "name:fas_x_variant":[
        "Balv\u0101n"
    ],
    "wof:name":"Balvan",
    "wof:placetype":"locality"
},
  "geometry": {"coordinates":[45.91252,34.49081],"type":"Point"}
}