{
  "type": "Feature",
  "properties": {
    "gn:admin1_code":"5.0",
    "gn:asciiname":"Tang Kalajiki",
    "gn:country_code":"IR",
    "gn:dem":2003,
    "gn:feature_class":"P",
    "gn:feature_code":"PPL",
    "gn:name":"Tang Kal\u0101j\u012bk\u012b",
    "gn:population":0,
    "gn:timezone":"Asia/Tehran",
    "iso:country":"IR",
    "name:fas_x_preferred":[
        "Tang Kal\u0101j\u012bk\u012b"
    ],
    "name:fas_x_variant":[
        "\u062a\u0646\u06af \u06a9\u0644\u0627\u062c\u06cc\u06a9\u06cc"
    ],
    "name:und_x_variant":[
        "\u062a\u0646\u06af \u06a9\u0644\u0627\u062c\u06cc\u06a9\u06cc"
    ],
    "wof:name":"Tang Kalajiki",
    "wof:placetype":"locality"
},
  "geometry": {"coordinates":[50.85707,31.07347],"type":"Point"}
}