{
  "type": "Feature",
  "properties": {
    "gn:admin1_code":"5.0",
    "gn:asciiname":"`Ali Nia'",
    "gn:country_code":"IR",
    "gn:dem":1723,
    "gn:feature_class":"P",
    "gn:feature_code":"PPLF",
    "gn:name":"\u2018Al\u012b N\u012b\u0101\u2019",
    "gn:population":0,
    "gn:timezone":"Asia/Tehran",
    "iso:country":"IR",
    "name:fas_x_preferred":[
        "\u0639\u0644\u06cc \u0646\u06cc\u0627\u0621"
    ],
    "name:und_x_variant":[
        "\u2018Al\u012b N\u012b\u0101\u2019"
    ],
    "wof:name":"`Ali Nia'",
    "wof:placetype":"locality"
},
  "geometry": {"coordinates":[50.37329,31.36107],"type":"Point"}
}