{
  "type": "Feature",
  "properties": {
    "gn:admin1_code":"32",
    "gn:asciiname":"Oruj Qeshlaq-e Hajj `Omran",
    "gn:country_code":"IR",
    "gn:dem":153,
    "gn:feature_class":"P",
    "gn:feature_code":"PPL",
    "gn:name":"Or\u016bj Qeshl\u0101q-e \u1e28\u0101jj \u2018Omr\u0101n",
    "gn:population":0,
    "gn:timezone":"Asia/Tehran",
    "iso:country":"IR",
    "name:azb_x_preferred":[
        "\u0627\u0648\u0631\u0648\u062c \u0642\u06cc\u0634\u0644\u0627\u0642 \u062d\u0627\u062c \u0639\u0648\u0645\u0631\u0627\u0646"
    ],
    "name:fas_x_preferred":[
        "\u0627\u064f\u0631\u0648\u062c \u0642\u0650\u0634\u0644\u0627\u0642\u0650 \u062d\u0627\u062c\u0651 \u0639\u064f\u0645\u0631\u0627\u0646"
    ],
    "name:fas_x_variant":[
        "Or\u016bj Qeshl\u0101q-e \u1e28\u0101jj \u2018Omr\u0101n",
        "\u0627\u0631\u0648\u062c\u200c\u0642\u0634\u0644\u0627\u0642 \u062d\u0627\u062c\u200c\u0639\u0645\u0631\u0627\u0646"
    ],
    "name:msa_x_preferred":[
        "Oruj Qeshlaq-e Hajj Omran"
    ],
    "name:mzn_x_preferred":[
        "\u0627\u0631\u0648\u062c\u200c\u0642\u0634\u0644\u0627\u0642 \u062d\u0627\u062c\u200c\u0639\u0645\u0631\u0627\u0646"
    ],
    "wof:name":"Oruj Qeshlaq-e Hajj `Omran",
    "wof:placetype":"locality"
},
  "geometry": {"coordinates":[47.75,39.51667],"type":"Point"}
}