{
  "type": "Feature",
  "properties": {
    "gn:admin1_code":"23.0",
    "gn:asciiname":"`Ali Mirza'i-ye Sofla",
    "gn:country_code":"IR",
    "gn:dem":1874,
    "gn:feature_class":"P",
    "gn:feature_code":"PPL",
    "gn:name":"\u2018Al\u012b M\u012brz\u0101\u2019\u012b-ye Sofl\u00e1",
    "gn:population":0,
    "gn:timezone":"Asia/Tehran",
    "iso:country":"IR",
    "name:fas_x_preferred":[
        "\u2018Al\u012b M\u012brz\u0101\u2019\u012b-ye Sofl\u00e1"
    ],
    "name:fas_x_variant":[
        "\u0639\u0644\u06cc \u0645\u06cc\u0631\u0632\u0627\u0626\u06cc \u0633\u0641\u0644\u06cc"
    ],
    "name:und_x_variant":[
        "\u2018Al\u012b M\u012brz\u0101\u2019\u012b",
        "\u0639\u0644\u06cc \u0645\u06cc\u0631\u0632\u0627\u0626\u06cc \u0633\u0641\u0644\u06cc"
    ],
    "wof:name":"`Ali Mirza'i-ye Sofla",
    "wof:placetype":"locality"
},
  "geometry": {"coordinates":[48.12764,34.04774],"type":"Point"}
}