{
  "type": "Feature",
  "properties": {
    "gn:admin1_code":"10",
    "gn:asciiname":"Vahdatabad",
    "gn:country_code":"IR",
    "gn:dem":647,
    "gn:feature_class":"P",
    "gn:feature_code":"PPL",
    "gn:name":"Va\u1e29dat\u0101b\u0101d",
    "gn:population":0,
    "gn:timezone":"Asia/Tehran",
    "iso:country":"IR",
    "name:fas_x_preferred":[
        "\u0648\u062d\u062f\u062a \u0622\u0628\u0627\u062f"
    ],
    "name:fas_x_variant":[
        "Va\u1e29dat\u0101b\u0101d"
    ],
    "name:und_x_variant":[
        "Kh\u0101npar\u012b",
        "Kh\u0101n Par\u012b va Sh\u0101h Par\u012b"
    ],
    "wof:name":"Vahdatabad",
    "wof:placetype":"locality"
},
  "geometry": {"coordinates":[47.28689,33.21617],"type":"Point"}
}