{
  "type": "Feature",
  "properties": {
    "gn:admin1_code":"33",
    "gn:asciiname":"Qusheh Bolagh",
    "gn:country_code":"IR",
    "gn:dem":1972,
    "gn:feature_class":"P",
    "gn:feature_code":"PPL",
    "gn:name":"Q\u016bsheh Bol\u0101gh",
    "gn:population":0,
    "gn:timezone":"Asia/Tehran",
    "iso:country":"IR",
    "name:fas_x_preferred":[
        "\u0642\u0648\u0634\u0647 \u0628\u0644\u0627\u063a"
    ],
    "name:fas_x_variant":[
        "Q\u016bsheh Bol\u0101gh"
    ],
    "wof:name":"Qusheh Bolagh",
    "wof:placetype":"locality"
},
  "geometry": {"coordinates":[46.6184,37.1437],"type":"Point"}
}