{
  "type": "Feature",
  "properties": {
    "gn:admin1_code":"41",
    "gn:asciiname":"Shirak",
    "gn:country_code":"IR",
    "gn:dem":1552,
    "gn:feature_class":"P",
    "gn:feature_code":"PPL",
    "gn:name":"Sh\u012brak",
    "gn:population":0,
    "gn:timezone":"Asia/Tehran",
    "iso:country":"IR",
    "name:ara_x_preferred":[
        "\u0634\u064a\u0631\u063a"
    ],
    "name:ceb_x_preferred":[
        "Sh\u012br\u012bk"
    ],
    "name:fas_x_preferred":[
        "Sh\u012brg"
    ],
    "name:fas_x_variant":[
        "Sh\u012br\u012bk",
        "\u0634\u06cc\u0631\u06cc\u06a9",
        "Sh\u012brak",
        "Sh\u012brag",
        "\u0634\u06cc\u0631\u06a9",
        "\u0634\u06cc\u0631\u06af"
    ],
    "name:swe_x_preferred":[
        "Sh\u012br\u012bk"
    ],
    "name:und_x_variant":[
        "Sherk"
    ],
    "wof:name":"Shirak",
    "wof:placetype":"locality"
},
  "geometry": {"coordinates":[59.09038,33.21098],"type":"Point"}
}