{
  "type": "Feature",
  "properties": {
    "gn:admin1_code":"29.0",
    "gn:asciiname":"Akhowrak",
    "gn:country_code":"IR",
    "gn:dem":2816,
    "gn:feature_class":"P",
    "gn:feature_code":"PPL",
    "gn:name":"\u0100khowrak",
    "gn:population":0,
    "gn:timezone":"Asia/Tehran",
    "iso:country":"IR",
    "name:fas_x_preferred":[
        "\u0622\u0628\u062e\u0631\u06a9"
    ],
    "name:fas_x_variant":[
        "\u0100khowrak",
        "\u0100bkharak",
        "\u0100bkhvorak",
        "\u0622\u0628\u062e\u0648\u0631\u06a9",
        "\u0100bkhorak"
    ],
    "name:und_x_variant":[
        "\u0100kh\u016brak",
        "Akhorak"
    ],
    "wof:name":"Akhowrak",
    "wof:placetype":"locality"
},
  "geometry": {"coordinates":[56.7494,29.6048],"type":"Point"}
}