{
  "type": "Feature",
  "properties": {
    "gn:admin1_code":"4.0",
    "gn:asciiname":"Marishan",
    "gn:country_code":"IR",
    "gn:dem":1935,
    "gn:feature_class":"P",
    "gn:feature_code":"PPL",
    "gn:name":"M\u0101r\u012bsh\u0101n",
    "gn:population":0,
    "gn:timezone":"Asia/Tehran",
    "iso:country":"IR",
    "name:fas_x_preferred":[
        "\u0645\u0627\u0631\u06cc\u0634\u0627\u0646"
    ],
    "name:fas_x_variant":[
        "M\u0101r\u012bsh\u0101n"
    ],
    "wof:name":"Marishan",
    "wof:placetype":"locality"
},
  "geometry": {"coordinates":[60.9198,28.571],"type":"Point"}
}