{
  "type": "Feature",
  "properties": {
    "gn:admin1_code":"35",
    "gn:asciiname":"Lak Tarashan",
    "gn:country_code":"IR",
    "gn:dem":1991,
    "gn:feature_class":"P",
    "gn:feature_code":"PPL",
    "gn:name":"L\u0101k Tar\u0101sh\u0101n",
    "gn:population":0,
    "gn:timezone":"Asia/Tehran",
    "iso:country":"IR",
    "name:fas_x_preferred":[
        "\u0644\u0627\u0643 \u062a\u0631\u0627\u0634\u0627\u0646"
    ],
    "name:fas_x_variant":[
        "L\u0101kter\u0101sh\u0101n",
        "\u0644\u0627\u0643\u062a\u0631\u0627\u0634\u0627\u0646"
    ],
    "name:und_x_variant":[
        "L\u0101k Tar\u0101sh\u0101n"
    ],
    "wof:name":"Lak Tarashan",
    "wof:placetype":"locality"
},
  "geometry": {"coordinates":[50.58852,36.67531],"type":"Point"}
}