{
  "type": "Feature",
  "properties": {
    "gn:admin1_code":"35.0",
    "gn:asciiname":"Mandi Mahalleh",
    "gn:country_code":"IR",
    "gn:dem":-14,
    "gn:feature_class":"P",
    "gn:feature_code":"PPL",
    "gn:name":"M\u0101nd\u012b Ma\u1e29alleh",
    "gn:population":0,
    "gn:timezone":"Asia/Tehran",
    "iso:country":"IR",
    "name:ceb_x_preferred":[
        "M\u0101nd\u012b Ma\u1e29alleh"
    ],
    "name:fas_x_preferred":[
        "\u0645\u0627\u0646\u062f\u06cc \u0645\u062d\u0644\u0647"
    ],
    "name:fas_x_variant":[
        "M\u0101nd\u012b Ma\u1e29alleh",
        "\u0645\u0627\u0646\u062f\u06cc\u200c\u0645\u062d\u0644\u0647"
    ],
    "name:swe_x_preferred":[
        "M\u0101nd\u012b Ma\u1e29alleh"
    ],
    "wof:name":"Mandi Mahalleh",
    "wof:placetype":"locality"
},
  "geometry": {"coordinates":[52.95024,36.66582],"type":"Point"}
}