{
  "type": "Feature",
  "properties": {
    "gn:admin1_code":"35.0",
    "gn:asciiname":"Marzud",
    "gn:country_code":"IR",
    "gn:dem":-10,
    "gn:feature_class":"P",
    "gn:feature_code":"PPL",
    "gn:name":"Marz\u016bd",
    "gn:population":0,
    "gn:timezone":"Asia/Tehran",
    "iso:country":"IR",
    "name:fas_x_preferred":[
        "Marz\u016bd"
    ],
    "name:fas_x_variant":[
        "Mazr\u016bd",
        "\u0645\u064e\u0632\u0631\u0648\u062f",
        "\u0645\u0631\u0632\u0648\u062f"
    ],
    "wof:name":"Marzud",
    "wof:placetype":"locality"
},
  "geometry": {"coordinates":[53.09469,36.69175],"type":"Point"}
}