{
  "type": "Feature",
  "properties": {
    "gn:admin1_code":"32",
    "gn:asciiname":"Ma`sumabad",
    "gn:country_code":"IR",
    "gn:dem":1320,
    "gn:feature_class":"P",
    "gn:feature_code":"PPL",
    "gn:name":"Ma\u2018\u015f\u016bm\u0101b\u0101d",
    "gn:population":0,
    "gn:timezone":"Asia/Tehran",
    "iso:country":"IR",
    "name:fas_x_preferred":[
        "\u0645\u0639\u0635\u0648\u0645 \u0622\u0628\u0627\u062f"
    ],
    "name:fas_x_variant":[
        "Ma\u2018\u015f\u016bm\u0101b\u0101d"
    ],
    "wof:name":"Ma`sumabad",
    "wof:placetype":"locality"
},
  "geometry": {"coordinates":[48.2014,38.361],"type":"Point"}
}