{
  "type": "Feature",
  "properties": {
    "gn:admin1_code":"41.0",
    "gn:asciiname":"Nargeh Sag",
    "gn:country_code":"IR",
    "gn:dem":1258,
    "gn:feature_class":"P",
    "gn:feature_code":"PPL",
    "gn:name":"Nargeh Sag",
    "gn:population":0,
    "gn:timezone":"Asia/Tehran",
    "iso:country":"IR",
    "name:fas_x_preferred":[
        "\u0646\u0631\u06af\u0647 \u0633\u06af"
    ],
    "name:und_x_variant":[
        "Nargesak",
        "Nargeh Sag"
    ],
    "wof:name":"Nargeh Sag",
    "wof:placetype":"locality"
},
  "geometry": {"coordinates":[60.6582,32.3152],"type":"Point"}
}