{
  "type": "Feature",
  "properties": {
    "gn:admin1_code":"8.0",
    "gn:asciiname":"Baz Qal`eh-ye Dezh",
    "gn:country_code":"IR",
    "gn:dem":32,
    "gn:feature_class":"P",
    "gn:feature_code":"PPL",
    "gn:name":"B\u0101z Qal\u2018eh-ye Dezh",
    "gn:population":0,
    "gn:timezone":"Asia/Tehran",
    "iso:country":"IR",
    "name:fas_x_preferred":[
        "\u0628\u0627\u0632 \u0642\u0644\u0639\u0647 \u062f\u0698"
    ],
    "name:und_x_variant":[
        "B\u0101z Qal\u2018eh-ye Dezh"
    ],
    "wof:name":"Baz Qal`eh-ye Dezh",
    "wof:placetype":"locality"
},
  "geometry": {"coordinates":[49.75208,37.14385],"type":"Point"}
}