{
  "type": "Feature",
  "properties": {
    "gn:admin1_code":"36.0",
    "gn:asciiname":"Hezarrud-e Sofla",
    "gn:country_code":"IR",
    "gn:dem":438,
    "gn:feature_class":"P",
    "gn:feature_code":"PPL",
    "gn:name":"Hez\u0101rr\u016bd-e Sofl\u00e1",
    "gn:population":0,
    "gn:timezone":"Asia/Tehran",
    "iso:country":"IR",
    "name:fas_x_preferred":[
        "\u0647\u0632\u0627\u0631\u0631\u0648\u062f \u0633\u0641\u0644\u06cc"
    ],
    "name:und_x_variant":[
        "Hez\u0101rr\u016bd-e Sofl\u00e1"
    ],
    "wof:name":"Hezarrud-e Sofla",
    "wof:placetype":"locality"
},
  "geometry": {"coordinates":[48.8793,36.94212],"type":"Point"}
}