{
  "type": "Feature",
  "properties": {
    "gn:admin1_code":"42",
    "gn:asciiname":"Borjak",
    "gn:country_code":"IR",
    "gn:dem":1145,
    "gn:feature_class":"P",
    "gn:feature_code":"PPL",
    "gn:name":"Borjak",
    "gn:population":0,
    "gn:timezone":"Asia/Tehran",
    "iso:country":"IR",
    "name:ara_x_preferred":[
        "\u0628\u0631\u062c\u0643"
    ],
    "name:fas_x_preferred":[
        "\u0628\u0631\u062c\u06a9"
    ],
    "name:mzn_x_preferred":[
        "\u0628\u0631\u062c\u06a9"
    ],
    "wof:name":"Borjak",
    "wof:placetype":"locality"
},
  "geometry": {"coordinates":[57.87042,35.33153],"type":"Point"}
}