{
  "type": "Feature",
  "properties": {
    "gn:admin1_code":"7",
    "gn:asciiname":"Mahalleh-ye Khorrami Safashahr",
    "gn:country_code":"IR",
    "gn:dem":2211,
    "gn:feature_class":"P",
    "gn:feature_code":"PPL",
    "gn:name":"Ma\u1e29alleh-ye Khorram\u012b \u015eaf\u0101shahr",
    "gn:population":0,
    "gn:timezone":"Asia/Tehran",
    "iso:country":"IR",
    "name:fas_x_preferred":[
        "\u062e\u0631\u0651\u0645\u06cc"
    ],
    "name:fas_x_variant":[
        "Khorram\u012b",
        "\u0645\u062d\u0644\u0647 \u062e\u0631\u0645\u06cc \u0635\u0641\u0627\u0634\u0647\u0631"
    ],
    "name:und_x_variant":[
        "Khurrami",
        "Khowrahm\u012b",
        "Korram\u012b",
        "Ma\u1e29alleh-ye Khorram\u012b \u015eaf\u0101shahr"
    ],
    "wof:name":"Mahalleh-ye Khorrami Safashahr",
    "wof:placetype":"locality"
},
  "geometry": {"coordinates":[53.1203,30.5774],"type":"Point"}
}