{
  "type": "Feature",
  "properties": {
    "gn:admin1_code":"42",
    "gn:asciiname":"Pustin Duz",
    "gn:country_code":"IR",
    "gn:dem":1903,
    "gn:feature_class":"P",
    "gn:feature_code":"PPL",
    "gn:name":"P\u016bst\u012bn D\u016bz",
    "gn:population":0,
    "gn:timezone":"Asia/Tehran",
    "iso:country":"IR",
    "name:fas_x_preferred":[
        "\u067e\u0648\u0633\u062a\u06cc\u0646 \u062f\u0648\u0632"
    ],
    "name:fas_x_variant":[
        "P\u016bst\u012bn D\u016bz"
    ],
    "wof:name":"Pustin Duz",
    "wof:placetype":"locality"
},
  "geometry": {"coordinates":[59.44206,35.67601],"type":"Point"}
}