{
  "type": "Feature",
  "properties": {
    "gn:admin1_code":"16.0",
    "gn:asciiname":"Istgah",
    "gn:country_code":"IR",
    "gn:dem":2120,
    "gn:feature_class":"P",
    "gn:feature_code":"PPL",
    "gn:name":"\u012astg\u0101h",
    "gn:population":0,
    "gn:timezone":"Asia/Tehran",
    "iso:country":"IR",
    "name:fas_x_preferred":[
        "\u064a\u0633\u062a\u06af\u0627\u0647"
    ],
    "name:fas_x_variant":[
        "\u012astg\u0101h"
    ],
    "wof:name":"Istgah",
    "wof:placetype":"locality"
},
  "geometry": {"coordinates":[46.16667,36.23333],"type":"Point"}
}