{
  "type": "Feature",
  "properties": {
    "gn:admin1_code":"16.0",
    "gn:asciiname":"Irankhvah",
    "gn:country_code":"IR",
    "gn:dem":1943,
    "gn:feature_class":"P",
    "gn:feature_code":"PPL",
    "gn:name":"Ir\u0101nkhv\u0101h",
    "gn:population":0,
    "gn:timezone":"Asia/Tehran",
    "iso:country":"IR",
    "name:fas_x_preferred":[
        "\u0627\u06cc\u0631\u0627\u0646\u0634\u0627\u0647"
    ],
    "name:fas_x_variant":[
        "\u012ar\u0101nsh\u0101h",
        "\u0627\u06cc\u0631\u0627\u0646\u062e\u0648\u0627\u0647"
    ],
    "name:und_x_variant":[
        "Ir\u0101nkhv\u0101h"
    ],
    "wof:name":"Irankhvah",
    "wof:placetype":"locality"
},
  "geometry": {"coordinates":[46.7475,36.14059],"type":"Point"}
}