{
  "type": "Feature",
  "properties": {
    "gn:admin1_code":"29",
    "gn:asciiname":"Narvand-e Sofla",
    "gn:country_code":"IR",
    "gn:dem":1155,
    "gn:feature_class":"P",
    "gn:feature_code":"PPL",
    "gn:name":"N\u0101rvand-e Sofl\u00e1",
    "gn:population":0,
    "gn:timezone":"Asia/Tehran",
    "iso:country":"IR",
    "name:fas_x_preferred":[
        "\u0646\u0627\u0631\u0648\u0646\u062f"
    ],
    "name:fas_x_variant":[
        "N\u0101rmand",
        "N\u0101rvand",
        "\u0646\u0627\u0631\u0648\u0646\u062f \u0633\u0641\u0644\u06cc"
    ],
    "name:und_x_variant":[
        "N\u0101rvand-e Sofl\u00e1"
    ],
    "wof:name":"Narvand-e Sofla",
    "wof:placetype":"locality"
},
  "geometry": {"coordinates":[57.05434,28.18917],"type":"Point"}
}