{
  "type": "Feature",
  "properties": {
    "gn:admin1_code":"23",
    "gn:asciiname":"Akbarabad",
    "gn:country_code":"IR",
    "gn:dem":1756,
    "gn:feature_class":"P",
    "gn:feature_code":"PPL",
    "gn:name":"Akbar\u0101b\u0101d",
    "gn:population":0,
    "gn:timezone":"Asia/Tehran",
    "iso:country":"IR",
    "name:ara_x_preferred":[
        "\u0623\u06a9\u0628\u0631 \u0623\u0628\u0627\u062f"
    ],
    "name:fas_x_preferred":[
        "\u0627\u06a9\u0628\u0631 \u0622\u0628\u0627\u062f"
    ],
    "name:fas_x_variant":[
        "Akbar\u0101b\u0101d",
        "\u0627\u06a9\u0628\u0631\u0622\u0628\u0627\u062f"
    ],
    "name:ron_x_preferred":[
        "Akbarabad"
    ],
    "wof:name":"Akbarabad",
    "wof:placetype":"locality"
},
  "geometry": {"coordinates":[48.66056,33.40515],"type":"Point"}
}