{
  "type": "Feature",
  "properties": {
    "gn:admin1_code":"29.0",
    "gn:asciiname":"`Abdolabad",
    "gn:country_code":"IR",
    "gn:dem":1839,
    "gn:feature_class":"P",
    "gn:feature_code":"PPLF",
    "gn:name":"\u2018Abdol\u0101b\u0101d",
    "gn:population":0,
    "gn:timezone":"Asia/Tehran",
    "iso:country":"IR",
    "name:fas_x_preferred":[
        "\u0639\u0628\u062f \u0627\u0644\u0644\u0647 \u0622\u0628\u0627\u062f"
    ],
    "name:fas_x_variant":[
        "\u2018Abdol\u0101b\u0101d",
        "\u2018Abdoll\u0101h\u0101b\u0101d",
        "\u0639\u0628\u062f\u0644 \u0622\u0628\u0627\u062f"
    ],
    "wof:name":"`Abdolabad",
    "wof:placetype":"locality"
},
  "geometry": {"coordinates":[55.21493,30.07148],"type":"Point"}
}