{
  "type": "Feature",
  "properties": {
    "gn:admin1_code":"13",
    "gn:asciiname":"Cheshmeh Sefid-e Shahmorad-e Chalanchu",
    "gn:country_code":"IR",
    "gn:dem":1631,
    "gn:feature_class":"P",
    "gn:feature_code":"PPL",
    "gn:name":"Cheshmeh Sef\u012bd-e Sh\u0101hmor\u0101d-e Chalanch\u016b",
    "gn:population":0,
    "gn:timezone":"Asia/Tehran",
    "iso:country":"IR",
    "name:fas_x_preferred":[
        "\u0686\u0634\u0645\u0647 \u0633\u0641\u06cc\u062f \u0634\u0627\u0647\u0645\u0631\u0627\u062f \u0686\u0644\u0646\u0686\u0648"
    ],
    "name:fas_x_variant":[
        "Cheshmeh Sef\u012bd-e Sh\u0101h Mor\u0101d",
        "Cheshmeh Sef\u012bd-e Sh\u0101hmor\u0101d-e Chalanch\u016b"
    ],
    "wof:name":"Cheshmeh Sefid-e Shahmorad-e Chalanchu",
    "wof:placetype":"locality"
},
  "geometry": {"coordinates":[46.5323,34.3965],"type":"Point"}
}