{
  "type": "Feature",
  "properties": {
    "gn:admin1_code":"13",
    "gn:asciiname":"Nuryab",
    "gn:country_code":"IR",
    "gn:dem":1376,
    "gn:feature_class":"P",
    "gn:feature_code":"PPL",
    "gn:name":"N\u016bry\u0101b",
    "gn:population":0,
    "gn:timezone":"Asia/Tehran",
    "iso:country":"IR",
    "name:fas_x_preferred":[
        "\u0646\u0648\u0631\u06cc\u0627\u0628"
    ],
    "name:fas_x_variant":[
        "N\u016bry\u0101b"
    ],
    "name:und_x_variant":[
        "N\u016br-i-\u0100b"
    ],
    "wof:name":"Nuryab",
    "wof:placetype":"locality"
},
  "geometry": {"coordinates":[46.3363,35.058],"type":"Point"}
}