{
  "type": "Feature",
  "properties": {
    "gn:admin1_code":"35.0",
    "gn:asciiname":"Motahhar-e Bala",
    "gn:country_code":"IR",
    "gn:dem":14,
    "gn:feature_class":"P",
    "gn:feature_code":"PPL",
    "gn:name":"Mo\u0163ahhar-e B\u0101l\u0101",
    "gn:population":0,
    "gn:timezone":"Asia/Tehran",
    "iso:country":"IR",
    "name:fas_x_preferred":[
        "\u0645\u064f\u0637\u064e\u0647\u064e\u0651\u0631\u0650 \u0639\u064f\u0644\u064a\u0627"
    ],
    "name:fas_x_variant":[
        "Mo\u0163ahhar-e \u2018Oly\u0101",
        "Mo\u0163ahhar-e B\u0101l\u0101",
        "\u0645\u0637\u0647\u0631 \u0628\u0627\u0644\u0627"
    ],
    "wof:name":"Motahhar-e Bala",
    "wof:placetype":"locality"
},
  "geometry": {"coordinates":[52.49883000000001,36.50185],"type":"Point"}
}