{
  "type": "Feature",
  "properties": {
    "gn:admin1_code":"15",
    "gn:asciiname":"Ab Konar",
    "gn:country_code":"IR",
    "gn:dem":376,
    "gn:feature_class":"P",
    "gn:feature_code":"PPL",
    "gn:name":"\u0100b Kon\u0101r",
    "gn:population":0,
    "gn:timezone":"Asia/Tehran",
    "iso:country":"IR",
    "name:fas_x_preferred":[
        "\u0622\u0628 \u06a9\u0646\u0627\u0631"
    ],
    "name:fas_x_variant":[
        "Chehel Kon\u0101r",
        "\u0100b Kon\u0101r"
    ],
    "wof:name":"Ab Konar",
    "wof:placetype":"locality"
},
  "geometry": {"coordinates":[50.052,30.7516],"type":"Point"}
}