{
  "type": "Feature",
  "properties": {
    "gn:admin1_code":"34.0",
    "gn:asciiname":"Chehel Raz",
    "gn:country_code":"IR",
    "gn:dem":1613,
    "gn:feature_class":"P",
    "gn:feature_code":"PPL",
    "gn:name":"Chehel Raz",
    "gn:population":0,
    "gn:timezone":"Asia/Tehran",
    "iso:country":"IR",
    "name:fas_x_preferred":[
        "\u0686\u0647\u0644 \u0631\u0632"
    ],
    "name:fas_x_variant":[
        "\u0686\u0647\u0644 \u0631\u0632\u0631\u0634"
    ],
    "name:ukr_x_preferred":[
        "\u0427\u0435\u0433\u0435\u043b\u044c-\u0420\u0430\u0437"
    ],
    "wof:name":"Chehel Raz",
    "wof:placetype":"locality"
},
  "geometry": {"coordinates":[50.42571,33.7383],"type":"Point"}
}