{
  "type": "Feature",
  "properties": {
    "gn:admin1_code":"43",
    "gn:asciiname":"Mahmudi",
    "gn:country_code":"IR",
    "gn:dem":1453,
    "gn:feature_class":"P",
    "gn:feature_code":"PPL",
    "gn:name":"Ma\u1e29m\u016bd\u012b",
    "gn:population":0,
    "gn:timezone":"Asia/Tehran",
    "iso:country":"IR",
    "name:fas_x_preferred":[
        "Ma\u1e29m\u016bd\u012b"
    ],
    "name:fas_x_variant":[
        "\u0645\u062d\u0645\u0648\u062f\u06cc"
    ],
    "wof:name":"Mahmudi",
    "wof:placetype":"locality"
},
  "geometry": {"coordinates":[57.44501,37.19423],"type":"Point"}
}