{
  "type": "Feature",
  "properties": {
    "gn:admin1_code":"41",
    "gn:asciiname":"Heydarabad",
    "gn:country_code":"IR",
    "gn:dem":1650,
    "gn:feature_class":"P",
    "gn:feature_code":"PPL",
    "gn:name":"\u1e28eydar\u0101b\u0101d",
    "gn:population":0,
    "gn:timezone":"Asia/Tehran",
    "iso:country":"IR",
    "name:aze_x_preferred":[
        "Heyd\u0259rabad"
    ],
    "name:ceb_x_preferred":[
        "Heydarabad"
    ],
    "name:fas_x_preferred":[
        "\u062d\u06cc\u062f\u0631 \u0622\u0628\u0627\u062f"
    ],
    "name:fas_x_variant":[
        "\u1e28eydar\u0101b\u0101d"
    ],
    "name:pnb_x_preferred":[
        "\u062d\u06cc\u062f\u0631\u0622\u0628\u0627\u062f"
    ],
    "name:swe_x_preferred":[
        "Heydarabad"
    ],
    "name:und_x_variant":[
        "Haidar\u0101b\u0101d"
    ],
    "wof:name":"Heydarabad",
    "wof:placetype":"locality"
},
  "geometry": {"coordinates":[59.22327,33.30324],"type":"Point"}
}