{
  "type": "Feature",
  "properties": {
    "gn:admin1_code":"7",
    "gn:asciiname":"Puzeh Abadi",
    "gn:country_code":"IR",
    "gn:dem":852,
    "gn:feature_class":"P",
    "gn:feature_code":"PPL",
    "gn:name":"P\u016bzeh \u0100b\u0101d\u012b",
    "gn:population":0,
    "gn:timezone":"Asia/Tehran",
    "iso:country":"IR",
    "name:fas_x_preferred":[
        "P\u016bzeh \u0100b\u0101d\u012b"
    ],
    "name:fas_x_variant":[
        "\u067e\u0648\u0632\u0647 \u0622\u0628\u0627\u062f\u06cc",
        "\u067e\u0648\u0632\u0647 \u0628\u0627\u062f\u06cc"
    ],
    "name:msa_x_preferred":[
        "Puzeh Badi"
    ],
    "name:und_x_variant":[
        "P\u016bzeh B\u0101d\u012b",
        "\u067e\u0648\u0632\u0647 \u0622\u0628\u0627\u062f\u06cc"
    ],
    "wof:name":"Puzeh Abadi",
    "wof:placetype":"locality"
},
  "geometry": {"coordinates":[51.76862,29.55875],"type":"Point"}
}