{
  "type": "Feature",
  "properties": {
    "gn:admin1_code":"8",
    "gn:asciiname":"Ruvol",
    "gn:country_code":"IR",
    "gn:dem":1585,
    "gn:feature_class":"P",
    "gn:feature_code":"PPL",
    "gn:name":"R\u016bvol",
    "gn:population":0,
    "gn:timezone":"Asia/Tehran",
    "iso:country":"IR",
    "name:fas_x_preferred":[
        "\u0631\u0648\u0648\u0644"
    ],
    "name:fas_x_variant":[
        "R\u016bvol"
    ],
    "wof:name":"Ruvol",
    "wof:placetype":"locality"
},
  "geometry": {"coordinates":[48.8674,37.4743],"type":"Point"}
}