{
  "type": "Feature",
  "properties": {
    "gn:admin1_code":"10",
    "gn:asciiname":"Cheshmeh Shirin",
    "gn:country_code":"IR",
    "gn:dem":895,
    "gn:feature_class":"P",
    "gn:feature_code":"PPL",
    "gn:name":"Cheshmeh Sh\u012br\u012bn",
    "gn:population":0,
    "gn:timezone":"Asia/Tehran",
    "iso:country":"IR",
    "name:ara_x_preferred":[
        "\u062c\u0634\u0645\u0629 \u0634\u064a\u0631\u064a\u0646"
    ],
    "name:fas_x_preferred":[
        "\u0686\u0634\u0645\u0647 \u0634\u06cc\u0631\u06cc\u0646"
    ],
    "name:fas_x_variant":[
        "Cheshmeh Sh\u012br\u012bn"
    ],
    "name:msa_x_preferred":[
        "Cheshmeh Shirin"
    ],
    "wof:name":"Cheshmeh Shirin",
    "wof:placetype":"locality"
},
  "geometry": {"coordinates":[47.16074,33.27362],"type":"Point"}
}