{
  "type": "Feature",
  "properties": {
    "gn:admin1_code":"13",
    "gn:asciiname":"Chaqa Bur-e Darab",
    "gn:country_code":"IR",
    "gn:dem":1687,
    "gn:feature_class":"P",
    "gn:feature_code":"PPL",
    "gn:name":"Chaq\u0101 B\u016br-e D\u0101r\u0101b",
    "gn:population":0,
    "gn:timezone":"Asia/Tehran",
    "iso:country":"IR",
    "name:fas_x_preferred":[
        "\u0686\u0642\u0627 \u0628\u0648\u0631 \u062f\u0627\u0631\u0627\u0628"
    ],
    "name:fas_x_variant":[
        "Choq\u0101 B\u016br-e D\u0101r\u0101b",
        "Chaq\u0101 B\u016br-e D\u0101r\u0101b"
    ],
    "wof:name":"Chaqa Bur-e Darab",
    "wof:placetype":"locality"
},
  "geometry": {"coordinates":[46.5111,34.3342],"type":"Point"}
}