{
  "type": "Feature",
  "properties": {
    "gn:admin1_code":"23",
    "gn:asciiname":"Gholamabad",
    "gn:country_code":"IR",
    "gn:dem":1684,
    "gn:feature_class":"P",
    "gn:feature_code":"PPL",
    "gn:name":"Ghol\u0101m\u0101b\u0101d",
    "gn:population":0,
    "gn:timezone":"Asia/Tehran",
    "iso:country":"IR",
    "name:fas_x_preferred":[
        "\u062e\u064e\u064a\u064e\u0651\u0637\u0650 \u063a\u064f\u0644\u0627\u0645 \u0622\u0628\u0627\u062f"
    ],
    "name:fas_x_variant":[
        "\u062e\u064e\u064a\u0627\u062a",
        "\u062e\u064e\u064a\u0651\u0627\u0637",
        "\u063a\u0644\u0627\u0645 \u0622\u0628\u0627\u062f \u062e\u06cc\u0651\u0627\u0637",
        "Khayya\u0163-e Ghol\u0101m\u0101b\u0101d",
        "Ghol\u0101m\u0101b\u0101d-e Khayy\u0101\u0163",
        "\u063a\u0644\u0627\u0645 \u0622\u0628\u0627\u062f",
        "\u063a\u0644\u0627\u0645\u200c\u0622\u0628\u0627\u062f \u062e\u06cc\u0627\u0637"
    ],
    "name:und_x_variant":[
        "Khay\u0101t",
        "Khayy\u0101\u0163",
        "Ghol\u0101m\u0101b\u0101d"
    ],
    "wof:name":"Gholamabad",
    "wof:placetype":"locality"
},
  "geometry": {"coordinates":[48.04188,33.90266],"type":"Point"}
}