{
  "type": "Feature",
  "properties": {
    "gn:admin1_code":"4.0",
    "gn:asciiname":"Bibi Mah",
    "gn:country_code":"IR",
    "gn:dem":1904,
    "gn:feature_class":"P",
    "gn:feature_code":"PPL",
    "gn:name":"B\u012bb\u012b Mah",
    "gn:population":0,
    "gn:timezone":"Asia/Tehran",
    "iso:country":"IR",
    "name:fas_x_preferred":[
        "B\u012bb\u012b Mah"
    ],
    "wof:name":"Bibi Mah",
    "wof:placetype":"locality"
},
  "geometry": {"coordinates":[60.81667,29.05],"type":"Point"}
}