{
  "type": "Feature",
  "properties": {
    "gn:admin1_code":"11",
    "gn:asciiname":"Behdeh",
    "gn:country_code":"IR",
    "gn:dem":181,
    "gn:feature_class":"P",
    "gn:feature_code":"PPL",
    "gn:name":"Behdeh",
    "gn:population":0,
    "gn:timezone":"Asia/Tehran",
    "iso:country":"IR",
    "name:fas_x_preferred":[
        "\u0628\u0647 \u062f\u0647"
    ],
    "name:fas_x_variant":[
        "\u0628\u0647\u062f\u0647"
    ],
    "name:msa_x_preferred":[
        "Beh Deh"
    ],
    "name:und_x_variant":[
        "Beh Deh",
        "Behdeh"
    ],
    "wof:name":"Behdeh",
    "wof:placetype":"locality"
},
  "geometry": {"coordinates":[53.3682,27.108],"type":"Point"}
}