{
  "type": "Feature",
  "properties": {
    "gn:admin1_code":"7.0",
    "gn:asciiname":"Darreh Korreh'i",
    "gn:country_code":"IR",
    "gn:dem":1528,
    "gn:feature_class":"P",
    "gn:feature_code":"PPL",
    "gn:name":"Darreh Korreh\u2019\u012b",
    "gn:population":0,
    "gn:timezone":"Asia/Tehran",
    "iso:country":"IR",
    "name:fas_x_preferred":[
        "\u062f\u0631\u0651\u0647 \u06a9\u0631\u0651\u0647 \u0627\u06cc"
    ],
    "name:und_x_variant":[
        "Darreh Korreh\u2019\u012b"
    ],
    "wof:name":"Darreh Korreh'i",
    "wof:placetype":"locality"
},
  "geometry": {"coordinates":[52.2897,29.1268],"type":"Point"}
}