{
  "type": "Feature",
  "properties": {
    "gn:admin1_code":"0",
    "gn:asciiname":"Pol Zarreh",
    "gn:cc2":"IR",
    "gn:country_code":"IR",
    "gn:dem":1836,
    "gn:feature_class":"P",
    "gn:feature_code":"PPL",
    "gn:name":"Pol Z\u0304arreh",
    "gn:population":0,
    "gn:timezone":"Asia/Tehran",
    "iso:country":"IR",
    "name:fas_x_preferred":[
        "\u067e\u064f\u0644 \u0630\u064e\u0631\u0650\u0651\u0647"
    ],
    "name:fas_x_variant":[
        "Pol Z\u0304arreh"
    ],
    "name:und_x_variant":[
        "Pul-i-Zarrah"
    ],
    "wof:name":"Pol Zarreh",
    "wof:placetype":"locality"
},
  "geometry": {"coordinates":[49.71667,32.75],"type":"Point"}
}