{
  "type": "Feature",
  "properties": {
    "gn:admin1_code":"8",
    "gn:asciiname":"Sar Kalleh",
    "gn:country_code":"IR",
    "gn:dem":20,
    "gn:feature_class":"P",
    "gn:feature_code":"PPL",
    "gn:name":"Sar Kalleh",
    "gn:population":0,
    "gn:timezone":"Asia/Tehran",
    "iso:country":"IR",
    "name:fas_x_preferred":[
        "\u0633\u0631 \u06a9\u0644\u0647"
    ],
    "name:und_x_variant":[
        "\u0633\u0631 \u06a9\u0644\u0647"
    ],
    "wof:name":"Sar Kalleh",
    "wof:placetype":"locality"
},
  "geometry": {"coordinates":[50.2624,37.06302],"type":"Point"}
}