{
  "type": "Feature",
  "properties": {
    "gn:admin1_code":"1.0",
    "gn:asciiname":"Benavileh-ye Kuchak",
    "gn:country_code":"IR",
    "gn:dem":1299,
    "gn:feature_class":"P",
    "gn:feature_code":"PPL",
    "gn:name":"Ben\u0101v\u012bleh-ye K\u016bchak",
    "gn:population":0,
    "gn:timezone":"Asia/Tehran",
    "iso:country":"IR",
    "name:fas_x_preferred":[
        "\u0628\u0646\u0627\u0648\u06cc\u0644\u0647 \u06a9\u0648\u0686\u06a9"
    ],
    "name:fas_x_variant":[
        "Ben\u0101v\u012bleh-ye K\u016bchak"
    ],
    "wof:name":"Benavileh-ye Kuchak",
    "wof:placetype":"locality"
},
  "geometry": {"coordinates":[45.6182,36.1215],"type":"Point"}
}