{
  "type": "Feature",
  "properties": {
    "gn:admin1_code":"41",
    "gn:asciiname":"Shekasteh-ye Bakhtak",
    "gn:country_code":"IR",
    "gn:dem":638,
    "gn:feature_class":"P",
    "gn:feature_code":"PPL",
    "gn:name":"Shekasteh-ye Bakhtak",
    "gn:population":0,
    "gn:timezone":"Asia/Tehran",
    "iso:country":"IR",
    "wof:name":"Shekasteh-ye Bakhtak",
    "wof:placetype":"locality"
},
  "geometry": {"coordinates":[58.08333,31.75],"type":"Point"}
}