{
  "type": "Feature",
  "properties": {
    "gn:admin1_code":"42",
    "gn:asciiname":"Jarf",
    "gn:country_code":"IR",
    "gn:dem":1836,
    "gn:feature_class":"P",
    "gn:feature_code":"PPL",
    "gn:name":"Jarf",
    "gn:population":0,
    "gn:timezone":"Asia/Tehran",
    "iso:country":"IR",
    "name:fas_x_preferred":[
        "\u062c\u0631\u0641"
    ],
    "name:fas_x_variant":[
        "\u062c\u0627\u0631\u0641"
    ],
    "name:por_x_preferred":[
        "Jarf"
    ],
    "name:rus_x_preferred":[
        "\u0414\u0436\u043e\u0440\u0444"
    ],
    "name:und_x_variant":[
        "Jaraf",
        "Jarif",
        "Zharf"
    ],
    "name:urd_x_preferred":[
        "\u062c\u0631\u0641"
    ],
    "wof:name":"Jarf",
    "wof:placetype":"locality"
},
  "geometry": {"coordinates":[59.66833000000001,36.91421],"type":"Point"}
}