{
  "type": "Feature",
  "properties": {
    "gn:admin1_code":"23",
    "gn:asciiname":"Hemmatabad",
    "gn:country_code":"IR",
    "gn:dem":1522,
    "gn:feature_class":"P",
    "gn:feature_code":"PPL",
    "gn:name":"Hemmat\u0101b\u0101d",
    "gn:population":0,
    "gn:timezone":"Asia/Tehran",
    "iso:country":"IR",
    "name:fas_x_preferred":[
        "\u0647\u0645\u062a \u0622\u0628\u0627\u062f"
    ],
    "name:fas_x_variant":[
        "Hemmat\u0101b\u0101d"
    ],
    "wof:name":"Hemmatabad",
    "wof:placetype":"locality"
},
  "geometry": {"coordinates":[48.79302,33.83957],"type":"Point"}
}