{
  "type": "Feature",
  "properties": {
    "gn:admin1_code":"10",
    "gn:asciiname":"Daruneh",
    "gn:country_code":"IR",
    "gn:dem":1124,
    "gn:feature_class":"P",
    "gn:feature_code":"PPL",
    "gn:name":"D\u0101r\u016bneh",
    "gn:population":0,
    "gn:timezone":"Asia/Tehran",
    "iso:country":"IR",
    "name:fas_x_preferred":[
        "\u062f\u0627\u0631\u0648\u0646\u0647"
    ],
    "name:fas_x_variant":[
        "D\u0101rvaneh",
        "D\u0101r\u016bneh"
    ],
    "wof:name":"Daruneh",
    "wof:placetype":"locality"
},
  "geometry": {"coordinates":[47.0646,33.8238],"type":"Point"}
}