{
  "type": "Feature",
  "properties": {
    "gn:admin1_code":"29",
    "gn:asciiname":"Deh-e Mirza",
    "gn:country_code":"IR",
    "gn:dem":2087,
    "gn:feature_class":"P",
    "gn:feature_code":"PPL",
    "gn:name":"Deh-e M\u012brz\u0101",
    "gn:population":0,
    "gn:timezone":"Asia/Tehran",
    "iso:country":"IR",
    "name:fas_x_preferred":[
        "\u062f\u0647 \u0645\u06cc\u0631\u0632\u0627"
    ],
    "name:fas_x_variant":[
        "Deh-e M\u012brz\u0101"
    ],
    "name:und_x_variant":[
        "Deh M\u012brz\u0101"
    ],
    "wof:name":"Deh-e Mirza",
    "wof:placetype":"locality"
},
  "geometry": {"coordinates":[57.4846,29.5927],"type":"Point"}
}