{
  "type": "Feature",
  "properties": {
    "gn:admin1_code":"32.0",
    "gn:asciiname":"Tazeh Kandeh-ye Zahra",
    "gn:country_code":"IR",
    "gn:dem":712,
    "gn:feature_class":"P",
    "gn:feature_code":"PPL",
    "gn:name":"T\u0101zeh Kandeh-ye Zahr\u0101",
    "gn:population":0,
    "gn:timezone":"Asia/Tehran",
    "iso:country":"IR",
    "name:ara_x_preferred":[
        "\u062a\u0627\u0632\u0629 \u0643\u0646\u062f\u0645\u0648\u0631\u0627\u0646"
    ],
    "name:azb_x_preferred":[
        "\u062a\u0632\u0647 \u06a9\u0646\u062f"
    ],
    "name:ceb_x_preferred":[
        "T\u0101zeh Kandeh-ye Zahr\u0101"
    ],
    "name:fas_x_preferred":[
        "\u062a\u0627\u0632\u0647 \u06a9\u0646\u062f\u0647 \u0632\u0647\u0631\u0627"
    ],
    "name:fas_x_variant":[
        "T\u0101zeh Kand-e M\u016br\u0101n",
        "T\u0101zeh Kandeh-ye Zahr\u0101",
        "T\u0101zeh Kand-e Zahr\u0101",
        "\u062a\u0627\u0632\u0647 \u06a9\u0646\u062f\u0645\u0648\u0631\u0627\u0646"
    ],
    "name:msa_x_preferred":[
        "Tazeh Kand-e Muran"
    ],
    "name:swe_x_preferred":[
        "T\u0101zeh Kandeh-ye Zahr\u0101"
    ],
    "name:und_x_variant":[
        "T\u0101zeh Kand-e Zahr\u0101",
        "Tazeh Kand-e"
    ],
    "wof:name":"Tazeh Kandeh-ye Zahra",
    "wof:placetype":"locality"
},
  "geometry": {"coordinates":[48.2874,39.0377],"type":"Point"}
}