{
  "type": "Feature",
  "properties": {
    "gn:admin1_code":"13",
    "gn:asciiname":"Beznabad-e Pa'in",
    "gn:country_code":"IR",
    "gn:dem":1283,
    "gn:feature_class":"P",
    "gn:feature_code":"PPL",
    "gn:name":"Bezn\u0101b\u0101d-e P\u0101\u2019\u012bn",
    "gn:population":0,
    "gn:timezone":"Asia/Tehran",
    "iso:country":"IR",
    "name:ceb_x_preferred":[
        "Bezn\u0101b\u0101d-e P\u0101'\u012bn"
    ],
    "name:fas_x_preferred":[
        "\u0628\u0632\u0646 \u0622\u0628\u0627\u062f \u067e\u0627\u0626\u06cc\u0646"
    ],
    "name:fas_x_variant":[
        "Bezn\u0101b\u0101d-e Sofl\u00e1",
        "Baz\u012bn\u0101b\u0101d-e P\u0101\u2019\u012bn",
        "\u0628\u0632\u0646\u200c\u0622\u0628\u0627\u062f \u0633\u0641\u0644\u06cc"
    ],
    "name:swe_x_preferred":[
        "Bezn\u0101b\u0101d-e P\u0101'\u012bn"
    ],
    "name:und_x_variant":[
        "Bezn\u0101b\u0101d-e P\u0101\u2019\u012bn"
    ],
    "wof:name":"Beznabad-e Pa'in",
    "wof:placetype":"locality"
},
  "geometry": {"coordinates":[47.4618,34.3735],"type":"Point"}
}