{
  "type": "Feature",
  "properties": {
    "gn:admin1_code":"7.0",
    "gn:asciiname":"Mahalleh-ye Kushkak",
    "gn:country_code":"IR",
    "gn:dem":1060,
    "gn:feature_class":"P",
    "gn:feature_code":"PPL",
    "gn:name":"Ma\u1e29alleh-ye K\u016bshkak",
    "gn:population":0,
    "gn:timezone":"Asia/Tehran",
    "iso:country":"IR",
    "name:fas_x_preferred":[
        "\u0645\u062d\u0644\u0647 \u06a9\u0648\u0634\u06a9\u06a9"
    ],
    "name:und_x_variant":[
        "Ma\u1e29alleh-ye K\u016bshkak"
    ],
    "wof:name":"Mahalleh-ye Kushkak",
    "wof:placetype":"locality"
},
  "geometry": {"coordinates":[53.57317,28.49134],"type":"Point"}
}