{
  "type": "Feature",
  "properties": {
    "gn:admin1_code":"15",
    "gn:asciiname":"Emamzadeh `Ali",
    "gn:country_code":"IR",
    "gn:dem":345,
    "gn:feature_class":"P",
    "gn:feature_code":"PPL",
    "gn:name":"Em\u0101mz\u0101deh \u2018Al\u012b",
    "gn:population":0,
    "gn:timezone":"Asia/Tehran",
    "iso:country":"IR",
    "name:fas_x_preferred":[
        "\u0627\u0645\u0627\u0645\u0632\u0627\u062f\u0647 \u062d\u0636\u0631\u062a \u0639\u0644\u06cc"
    ],
    "name:fas_x_variant":[
        "Em\u0101mz\u0101deh \u2018Al\u012b",
        "Em\u0101mz\u0101deh \u1e28a\u1e95rat-e \u2018Al\u012b",
        "\u0627\u0645\u0627\u0645\u0632\u0627\u062f\u0647 \u0639\u0644\u06cc"
    ],
    "wof:name":"Emamzadeh `Ali",
    "wof:placetype":"locality"
},
  "geometry": {"coordinates":[50.28045,30.49738],"type":"Point"}
}