{
  "type": "Feature",
  "properties": {
    "gn:admin1_code":"33.0",
    "gn:asciiname":"Piri Kandi",
    "gn:country_code":"IR",
    "gn:dem":1757,
    "gn:feature_class":"P",
    "gn:feature_code":"PPL",
    "gn:name":"P\u012br\u012b Kand\u012b",
    "gn:population":0,
    "gn:timezone":"Asia/Tehran",
    "iso:country":"IR",
    "name:aze_x_preferred":[
        "Piri k\u0259ndi"
    ],
    "name:fas_x_preferred":[
        "\u067e\u064e\u0631\u06cc \u0643\u064e\u0646\u062f\u06cc"
    ],
    "name:fas_x_variant":[
        "Par\u012b Kand\u012b",
        "\u067e\u06cc\u0631\u06cc \u0643\u0646\u062f\u06cc",
        "\u067e\u06cc\u0631\u06cc\u200c\u06a9\u0646\u062f\u06cc"
    ],
    "name:msa_x_preferred":[
        "Piri Kandi"
    ],
    "name:und_x_variant":[
        "P\u012br\u012b Kand\u012b"
    ],
    "wof:name":"Piri Kandi",
    "wof:placetype":"locality"
},
  "geometry": {"coordinates":[47.11911,38.81293],"type":"Point"}
}