{
  "type": "Feature",
  "properties": {
    "gn:admin1_code":"23",
    "gn:asciiname":"Kuleh Marz-e Sofla",
    "gn:country_code":"IR",
    "gn:dem":1714,
    "gn:feature_class":"P",
    "gn:feature_code":"PPL",
    "gn:name":"K\u016bleh Marz-e Sofl\u00e1",
    "gn:population":0,
    "gn:timezone":"Asia/Tehran",
    "iso:country":"IR",
    "name:fas_x_preferred":[
        "\u0643\u0648\u0644\u0650\u0647 \u0645\u064e\u0631\u0632\u0650 \u0633\u064f\u0641\u0644\u064e\u0649"
    ],
    "name:fas_x_variant":[
        "\u06a9\u0648\u0644\u0647 \u0645\u0631\u0632 \u0633\u0641\u0644\u06cc",
        "K\u016bleh Marz-e Sofl\u00e1"
    ],
    "wof:name":"Kuleh Marz-e Sofla",
    "wof:placetype":"locality"
},
  "geometry": {"coordinates":[47.8292,34.1346],"type":"Point"}
}