{
  "type": "Feature",
  "properties": {
    "gn:admin1_code":"8",
    "gn:asciiname":"Fiyeh Chal",
    "gn:country_code":"IR",
    "gn:dem":1674,
    "gn:feature_class":"P",
    "gn:feature_code":"PPL",
    "gn:name":"F\u012byeh Ch\u0101l",
    "gn:population":0,
    "gn:timezone":"Asia/Tehran",
    "iso:country":"IR",
    "name:fas_x_preferred":[
        "\u0641\u06cc\u0647 \u0686\u0627\u0644"
    ],
    "name:fas_x_variant":[
        "\u016ayeh Ch\u0101l",
        "F\u012byeh Ch\u0101l",
        "\u0627\u0648\u06cc\u0647 \u0686\u0627\u0644"
    ],
    "wof:name":"Fiyeh Chal",
    "wof:placetype":"locality"
},
  "geometry": {"coordinates":[49.0386,37.13800000000001],"type":"Point"}
}