{
  "type": "Feature",
  "properties": {
    "gn:admin1_code":"29",
    "gn:asciiname":"Sanjedu'iyeh",
    "gn:country_code":"IR",
    "gn:dem":2142,
    "gn:feature_class":"P",
    "gn:feature_code":"PPL",
    "gn:name":"Sanjed\u016b\u2019\u012byeh",
    "gn:population":0,
    "gn:timezone":"Asia/Tehran",
    "iso:country":"IR",
    "name:fas_x_preferred":[
        "Sanjed\u016b\u2019\u012byeh"
    ],
    "wof:name":"Sanjedu'iyeh",
    "wof:placetype":"locality"
},
  "geometry": {"coordinates":[56.16972,30.64556],"type":"Point"}
}