{
  "type": "Feature",
  "properties": {
    "gn:admin1_code":"33",
    "gn:asciiname":"Yuzi",
    "gn:country_code":"IR",
    "gn:dem":1664,
    "gn:feature_class":"P",
    "gn:feature_code":"PPL",
    "gn:name":"Yuzi",
    "gn:population":0,
    "gn:timezone":"Asia/Tehran",
    "iso:country":"IR",
    "name:fas_x_preferred":[
        "\u0627\u0648\u0632\u06cc"
    ],
    "name:fas_x_variant":[
        "\u016az\u012b"
    ],
    "name:msa_x_preferred":[
        "Uzi"
    ],
    "wof:name":"Yuzi",
    "wof:placetype":"locality"
},
  "geometry": {"coordinates":[46.6727,38.7308],"type":"Point"}
}