{
  "type": "Feature",
  "properties": {
    "gn:admin1_code":"42.0",
    "gn:asciiname":"Kalateh-ye Kur Safar",
    "gn:country_code":"IR",
    "gn:dem":1104,
    "gn:feature_class":"P",
    "gn:feature_code":"PPLF",
    "gn:name":"Kal\u0101teh-ye K\u016br \u015eafar",
    "gn:population":0,
    "gn:timezone":"Asia/Tehran",
    "iso:country":"IR",
    "name:fas_x_preferred":[
        "\u06a9\u0644\u0627\u062a\u0647 \u06a9\u0648\u0631 \u0635\u0641\u0631"
    ],
    "name:und_x_variant":[
        "Kal\u0101teh-ye K\u016br \u015eafar"
    ],
    "wof:name":"Kalateh-ye Kur Safar",
    "wof:placetype":"locality"
},
  "geometry": {"coordinates":[57.52398,36.25474000000001],"type":"Point"}
}