{
  "type": "Feature",
  "properties": {
    "gn:admin1_code":"11",
    "gn:asciiname":"Seyfabad",
    "gn:country_code":"IR",
    "gn:dem":1471,
    "gn:feature_class":"P",
    "gn:feature_code":"PPL",
    "gn:name":"Seyf\u0101b\u0101d",
    "gn:population":0,
    "gn:timezone":"Asia/Tehran",
    "iso:country":"IR",
    "name:fas_x_preferred":[
        "\u0633\u06cc\u0641 \u0622\u0628\u0627\u062f"
    ],
    "name:fas_x_variant":[
        "Seyf\u0101b\u0101d",
        "\u0633\u06cc\u0641\u200c\u0622\u0628\u0627\u062f"
    ],
    "name:msa_x_preferred":[
        "Seyfabad"
    ],
    "wof:name":"Seyfabad",
    "wof:placetype":"locality"
},
  "geometry": {"coordinates":[55.4529,28.5071],"type":"Point"}
}