{
  "type": "Feature",
  "properties": {
    "gn:admin1_code":"44",
    "gn:asciiname":"Kamalshahr",
    "gn:country_code":"IR",
    "gn:dem":1269,
    "gn:feature_class":"P",
    "gn:feature_code":"PPL",
    "gn:name":"Kam\u0101lshahr",
    "gn:population":0,
    "gn:timezone":"Asia/Tehran",
    "iso:country":"IR",
    "name:ara_x_preferred":[
        "\u0643\u0645\u0627\u0644 \u0634\u0647\u0631"
    ],
    "name:aze_x_preferred":[
        "K\u0259mal\u015f\u0259hr"
    ],
    "name:fas_x_preferred":[
        "\u0642\u064e\u0631\u064e\u0646\u0637\u064a\u0646\u0650\u06c0 \u0643\u064e\u0645\u0627\u0644 \u0622\u0628\u0627\u062f"
    ],
    "name:fas_x_variant":[
        "Qaran\u0163\u012bneh-ye Kam\u0101l\u0101b\u0101d",
        "\u06a9\u0645\u0627\u0644\u0634\u0647\u0631",
        "\u06a9\u0645\u0627\u0644 \u0634\u0647\u0631",
        "\u06a9\u0645\u0627\u0644 \u0622\u0628\u0627\u062f",
        "\u06a9\u0645\u0627\u0644\u200c\u0634\u0647\u0631"
    ],
    "name:hin_x_preferred":[
        "\u0915\u092e\u093e\u0932\u0936\u0939\u0930"
    ],
    "name:ita_x_preferred":[
        "Kamal Shahr"
    ],
    "name:mlg_x_preferred":[
        "Kamal Shahr"
    ],
    "name:msa_x_preferred":[
        "Kamal Shahr"
    ],
    "name:pol_x_preferred":[
        "Kamalszahr"
    ],
    "name:rus_x_preferred":[
        "\u041a\u0435\u043c\u0430\u043b\u044c\u0448\u0435\u0445\u0440"
    ],
    "name:tur_x_preferred":[
        "Kemal\u015fehr"
    ],
    "name:und_x_variant":[
        "Kam\u0101lshahr",
        "Kam\u0101l\u0101b\u0101d",
        "Kam\u0101l Shahr"
    ],
    "name:urd_x_preferred":[
        "\u06a9\u0645\u0627\u0644\u200c\u0634\u06c1\u0631"
    ],
    "wof:name":"Kamalshahr",
    "wof:placetype":"locality"
},
  "geometry": {"coordinates":[50.87424,35.86187],"type":"Point"}
}