{
  "type": "Feature",
  "properties": {
    "gn:admin1_code":"8.0",
    "gn:asciiname":"Zenash",
    "gn:country_code":"IR",
    "gn:dem":1863,
    "gn:feature_class":"P",
    "gn:feature_code":"PPL",
    "gn:name":"Zenash",
    "gn:population":0,
    "gn:timezone":"Asia/Tehran",
    "iso:country":"IR",
    "name:fas_x_preferred":[
        "\u0632\u0646\u0634"
    ],
    "name:und_x_variant":[
        "\u0632\u0646\u0634"
    ],
    "wof:name":"Zenash",
    "wof:placetype":"locality"
},
  "geometry": {"coordinates":[50.11457,36.78614],"type":"Point"}
}