{
  "type": "Feature",
  "properties": {
    "gn:admin1_code":"8.0",
    "gn:asciiname":"Zenash",
    "gn:country_code":"IR",
    "gn:dem":1863,
    "gn:feature_class":"P",
    "gn:feature_code":"PPL",
    "gn:name":"Zenash",
    "gn:population":0,
    "gn:timezone":"Asia/Tehran",
    "iso:country":"IR",
    "name:fas_x_preferred":[
        "\u0632\u0646\u0634"
    ],
    "name:msa_x_preferred":[
        "Zenash"
    ],
    "name:ukr_x_preferred":[
        "\u0417\u0435\u043d\u0430\u0448"
    ],
    "wof:name":"Zenash",
    "wof:placetype":"locality"
},
  "geometry": {"coordinates":[50.11457,36.78614],"type":"Point"}
}