{
  "type": "Feature",
  "properties": {
    "gn:admin1_code":"1.0",
    "gn:asciiname":"Gezelan",
    "gn:country_code":"IR",
    "gn:dem":1284,
    "gn:feature_class":"P",
    "gn:feature_code":"PPL",
    "gn:name":"Gezel\u0101n",
    "gn:population":0,
    "gn:timezone":"Asia/Tehran",
    "iso:country":"IR",
    "name:fas_x_preferred":[
        "\u06af\u0650\u0632\u0650\u0644\u0627\u0646"
    ],
    "name:fas_x_variant":[
        "\u06af\u0632\u0644\u0627\u0646",
        "Gezel\u0101n"
    ],
    "wof:name":"Gezelan",
    "wof:placetype":"locality"
},
  "geometry": {"coordinates":[45.9591,36.985],"type":"Point"}
}