{
  "type": "Feature",
  "properties": {
    "gn:admin1_code":"8.0",
    "gn:asciiname":"Esfandiar Sara",
    "gn:country_code":"IR",
    "gn:dem":437,
    "gn:feature_class":"P",
    "gn:feature_code":"PPL",
    "gn:name":"Esfand\u012b\u0101r Sar\u0101",
    "gn:population":0,
    "gn:timezone":"Asia/Tehran",
    "iso:country":"IR",
    "name:fas_x_preferred":[
        "\u0627\u0633\u0641\u0646\u062f\u06cc\u0627\u0631 \u0633\u0631\u0627"
    ],
    "name:und_x_variant":[
        "Esfand\u012b\u0101r Sar\u0101"
    ],
    "wof:name":"Esfandiar Sara",
    "wof:placetype":"locality"
},
  "geometry": {"coordinates":[49.88761,37.0287],"type":"Point"}
}