{
  "type": "Feature",
  "properties": {
    "gn:admin1_code":"33",
    "gn:asciiname":"Qazan Quzan",
    "gn:country_code":"IR",
    "gn:dem":1972,
    "gn:feature_class":"P",
    "gn:feature_code":"PPL",
    "gn:name":"Q\u0101z\u0101n Q\u016bz\u0101n",
    "gn:population":0,
    "gn:timezone":"Asia/Tehran",
    "iso:country":"IR",
    "name:fas_x_preferred":[
        "\u0642\u0627\u0632\u0627\u0646 \u0642\u0648\u0632\u0627\u0646"
    ],
    "name:fas_x_variant":[
        "Q\u0101z\u0101n Q\u016bz\u0101n"
    ],
    "wof:name":"Qazan Quzan",
    "wof:placetype":"locality"
},
  "geometry": {"coordinates":[46.8005,37.6751],"type":"Point"}
}