{
  "type": "Feature",
  "properties": {
    "gn:admin1_code":"40.0",
    "gn:asciiname":"Chah-e Qarb`ali",
    "gn:country_code":"IR",
    "gn:dem":1332,
    "gn:feature_class":"P",
    "gn:feature_code":"PPLL",
    "gn:name":"Ch\u0101h-e Qarb\u2018al\u012b",
    "gn:population":0,
    "gn:timezone":"Asia/Tehran",
    "iso:country":"IR",
    "name:fas_x_preferred":[
        "\u0686\u0627\u0647 \u0642\u0631\u0628\u0639\u0644\u06cc"
    ],
    "name:fas_x_variant":[
        "\u0686\u0627\u0647 \u0642\u0631\u0628\u0627\u0646\u0639\u0644\u06cc"
    ],
    "name:und_x_variant":[
        "Ch\u0101h-e Qarb\u2018al\u012b",
        "Ch\u0101h-e Qarb\u0101n\u2018al\u012b"
    ],
    "wof:name":"Chah-e Qarb`ali",
    "wof:placetype":"locality"
},
  "geometry": {"coordinates":[57.20098,34.89646],"type":"Point"}
}