{
  "type": "Feature",
  "properties": {
    "gn:admin1_code":"42.0",
    "gn:asciiname":"Kalateh-ye Naser",
    "gn:country_code":"IR",
    "gn:dem":1671,
    "gn:feature_class":"P",
    "gn:feature_code":"PPL",
    "gn:name":"Kal\u0101teh-ye N\u0101\u015fer",
    "gn:population":0,
    "gn:timezone":"Asia/Tehran",
    "iso:country":"IR",
    "name:fas_x_preferred":[
        "Qal\u2018eh Nasir"
    ],
    "name:fas_x_variant":[
        "\u06a9\u0644\u0627\u062a\u0647 \u0646\u0627\u0635\u0631",
        "Kal\u0101teh-ye N\u0101\u015fer",
        "N\u0101\u015fer"
    ],
    "name:und_x_variant":[
        "N\u0101\u015fer"
    ],
    "wof:name":"Kalateh-ye Naser",
    "wof:placetype":"locality"
},
  "geometry": {"coordinates":[60.14757,33.32666],"type":"Point"}
}