{
  "type": "Feature",
  "properties": {
    "gn:admin1_code":"42",
    "gn:asciiname":"Mahalleh",
    "gn:country_code":"IR",
    "gn:dem":848,
    "gn:feature_class":"P",
    "gn:feature_code":"PPL",
    "gn:name":"Ma\u1e29alleh",
    "gn:population":0,
    "gn:timezone":"Asia/Tehran",
    "iso:country":"IR",
    "name:fas_x_preferred":[
        "\u0645\u062d\u0644\u0651\u0647"
    ],
    "name:fas_x_variant":[
        "Ma\u1e29alleh"
    ],
    "wof:name":"Mahalleh",
    "wof:placetype":"locality"
},
  "geometry": {"coordinates":[58.54926,35.01757],"type":"Point"}
}