{
  "type": "Feature",
  "properties": {
    "gn:admin1_code":"25",
    "gn:asciiname":"Towchal",
    "gn:country_code":"IR",
    "gn:dem":1100,
    "gn:feature_class":"P",
    "gn:feature_code":"PPL",
    "gn:name":"Towch\u0101l",
    "gn:population":0,
    "gn:timezone":"Asia/Tehran",
    "iso:country":"IR",
    "name:fas_x_preferred":[
        "Towch\u0101l"
    ],
    "name:fas_x_variant":[
        "Tow Ch\u0101h",
        "T\u016b Ch\u0101h",
        "Tu-i-Ch\u0101h",
        "\u062a\u0648\u0686\u0627\u0644",
        "\u062a\u0648 \u0686\u0627\u0647"
    ],
    "name:und_x_variant":[
        "\u062a\u0648\u0686\u0627\u0644",
        "\u062a\u0648 \u0686\u0627\u0647"
    ],
    "wof:name":"Towchal",
    "wof:placetype":"locality"
},
  "geometry": {"coordinates":[56.65283,35.64169000000001],"type":"Point"}
}