{
  "type": "Feature",
  "properties": {
    "gn:admin1_code":"28",
    "gn:asciiname":"Kujar",
    "gn:country_code":"IR",
    "gn:dem":2164,
    "gn:feature_class":"P",
    "gn:feature_code":"PPL",
    "gn:name":"K\u016bj\u0101r",
    "gn:population":0,
    "gn:timezone":"Asia/Tehran",
    "iso:country":"IR",
    "name:fas_x_preferred":[
        "\u06af\u0648\u062c\u0627\u0631"
    ],
    "name:fas_x_variant":[
        "\u06a9\u0648\u062c\u0627\u0631",
        "G\u016bj\u0101r",
        "K\u016bj\u0101r"
    ],
    "wof:name":"Kujar",
    "wof:placetype":"locality"
},
  "geometry": {"coordinates":[51.3612,33.8088],"type":"Point"}
}