{
  "type": "Feature",
  "properties": {
    "gn:admin1_code":"5",
    "gn:asciiname":"Puzeh Barda Sepid",
    "gn:country_code":"IR",
    "gn:dem":2216,
    "gn:feature_class":"P",
    "gn:feature_code":"PPL",
    "gn:name":"P\u016bzeh Bard\u0101 Sep\u012bd",
    "gn:population":0,
    "gn:timezone":"Asia/Tehran",
    "iso:country":"IR",
    "name:ara_x_preferred":[
        "\u0628\u0648\u0632\u0629 \u0633\u0641\u064a\u062f"
    ],
    "name:fas_x_preferred":[
        "P\u016bzeh Sef\u012bd"
    ],
    "name:fas_x_variant":[
        "\u067e\u0648\u0632\u0647 \u0628\u0631\u062f\u0627\u0633\u067e\u064a\u062f",
        "\u0645\u0627\u0644\u06a9 \u0627\u0634\u062a\u0631",
        "\u067e\u0648\u0632\u0647 \u0633\u0641\u06cc\u062f"
    ],
    "name:und_x_variant":[
        "Bard Esp\u012bd",
        "P\u016bzeh Bard\u0101 Sep\u012bd",
        "M\u0101lek-e Ashtar"
    ],
    "wof:name":"Puzeh Barda Sepid",
    "wof:placetype":"locality"
},
  "geometry": {"coordinates":[51.83452,30.57919],"type":"Point"}
}