{
  "type": "Feature",
  "properties": {
    "gn:admin1_code":"7",
    "gn:asciiname":"Ta`viq",
    "gn:country_code":"IR",
    "gn:dem":2194,
    "gn:feature_class":"P",
    "gn:feature_code":"PPL",
    "gn:name":"Ta\u2018v\u012bq",
    "gn:population":0,
    "gn:timezone":"Asia/Tehran",
    "iso:country":"IR",
    "name:fas_x_preferred":[
        "\u062a\u0639\u0648\u06cc\u0642"
    ],
    "name:fas_x_variant":[
        "Ta\u2018v\u012bq",
        "\u0648\u062d\u062f\u062a\u06cc"
    ],
    "name:und_x_variant":[
        "Taveyt",
        "Tavait",
        "Va\u1e29dat\u012b"
    ],
    "wof:name":"Ta`viq",
    "wof:placetype":"locality"
},
  "geometry": {"coordinates":[55.1277,28.5773],"type":"Point"}
}