{
  "type": "Feature",
  "properties": {
    "gn:admin1_code":"33",
    "gn:asciiname":"Qurtlar",
    "gn:country_code":"IR",
    "gn:dem":1561,
    "gn:feature_class":"P",
    "gn:feature_code":"PPL",
    "gn:name":"Q\u016brtl\u0101r",
    "gn:population":0,
    "gn:timezone":"Asia/Tehran",
    "iso:country":"IR",
    "name:fas_x_preferred":[
        "Q\u016brtl\u0101r"
    ],
    "name:und_x_variant":[
        "Kyurtar",
        "Ghoort Lar",
        "K\u016brt\u0101r",
        "Q\u016bdl\u0101r"
    ],
    "wof:name":"Qurtlar",
    "wof:placetype":"locality"
},
  "geometry": {"coordinates":[46.68333,38.73333],"type":"Point"}
}