{
  "type": "Feature",
  "properties": {
    "gn:admin1_code":"15",
    "gn:asciiname":"Shomaleh",
    "gn:country_code":"IR",
    "gn:dem":65,
    "gn:feature_class":"P",
    "gn:feature_code":"PPL",
    "gn:name":"Shom\u0101leh",
    "gn:population":0,
    "gn:timezone":"Asia/Tehran",
    "iso:country":"IR",
    "name:fas_x_preferred":[
        "\u0633\u0645\u0627\u0644\u0647"
    ],
    "name:fas_x_variant":[
        "Som\u0101leh",
        "\u0634\u0645\u0627\u0644\u0647"
    ],
    "name:und_x_variant":[
        "Sim\u0101leh",
        "Shom\u0101leh"
    ],
    "wof:name":"Shomaleh",
    "wof:placetype":"locality"
},
  "geometry": {"coordinates":[48.86066,32.20053],"type":"Point"}
}