{
  "type": "Feature",
  "properties": {
    "gn:admin1_code":"35.0",
    "gn:asciiname":"Bi Namad",
    "gn:country_code":"IR",
    "gn:dem":-10,
    "gn:feature_class":"P",
    "gn:feature_code":"PPL",
    "gn:name":"B\u012b Namad",
    "gn:population":0,
    "gn:timezone":"Asia/Tehran",
    "iso:country":"IR",
    "name:fas_x_preferred":[
        "\u0628\u064a\u0646\u064e\u0645\u064e\u062f"
    ],
    "name:fas_x_variant":[
        "\u0628\u06cc \u0646\u0645\u062f",
        "B\u012bnamad",
        "B\u012b Namad"
    ],
    "name:und_x_variant":[
        "B\u012b Namad"
    ],
    "wof:name":"Bi Namad",
    "wof:placetype":"locality"
},
  "geometry": {"coordinates":[52.51529,36.59483],"type":"Point"}
}