{
  "type": "Feature",
  "properties": {
    "gn:admin1_code":"3",
    "gn:asciiname":"Sarveh-ye Pa'in",
    "gn:country_code":"IR",
    "gn:dem":1492,
    "gn:feature_class":"P",
    "gn:feature_code":"PPL",
    "gn:name":"Sarveh-ye P\u0101\u2019\u012bn",
    "gn:population":0,
    "gn:timezone":"Asia/Tehran",
    "iso:country":"IR",
    "name:fas_x_preferred":[
        "\u0633\u064e\u0631\u0648\u0650\u06c0 \u067e\u0627\u0626\u064a\u0646"
    ],
    "name:fas_x_variant":[
        "Sarveh-ye P\u0101\u2019\u012bn"
    ],
    "wof:name":"Sarveh-ye Pa'in",
    "wof:placetype":"locality"
},
  "geometry": {"coordinates":[50.10333,32.13611],"type":"Point"}
}