{
  "type": "Feature",
  "properties": {
    "gn:admin1_code":"42.0",
    "gn:asciiname":"Salehabad",
    "gn:country_code":"IR",
    "gn:dem":667,
    "gn:feature_class":"P",
    "gn:feature_code":"PPL",
    "gn:name":"\u015e\u0101le\u1e29\u0101b\u0101d",
    "gn:population":0,
    "gn:timezone":"Asia/Tehran",
    "iso:country":"IR",
    "name:ara_x_preferred":[
        "\u0635\u0627\u0644\u062d \u0623\u0628\u0627\u062f"
    ],
    "name:aze_x_preferred":[
        "Salehabad"
    ],
    "name:ceb_x_preferred":[
        "\u015e\u0101le\u1e29\u0101b\u0101d"
    ],
    "name:fas_x_preferred":[
        "\u015e\u0101le\u1e29\u0101b\u0101d"
    ],
    "name:fas_x_variant":[
        "\u0635\u0627\u0644\u062d \u0622\u0628\u0627\u062f",
        "\u0635\u0627\u0644\u062d\u200c\u0622\u0628\u0627\u062f"
    ],
    "name:ita_x_preferred":[
        "Salehabad"
    ],
    "name:mlg_x_preferred":[
        "Salehabad"
    ],
    "name:tur_x_preferred":[
        "Salihabad"
    ],
    "name:und_x_variant":[
        "\u0635\u0627\u0644\u062d \u0622\u0628\u0627\u062f"
    ],
    "wof:name":"Salehabad",
    "wof:placetype":"locality"
},
  "geometry": {"coordinates":[61.09548,35.68805],"type":"Point"}
}