{
  "type": "Feature",
  "properties": {
    "gn:admin1_code":"5",
    "gn:asciiname":"Darreh Garm",
    "gn:country_code":"IR",
    "gn:dem":2144,
    "gn:feature_class":"P",
    "gn:feature_code":"PPL",
    "gn:name":"Darreh Garm",
    "gn:population":0,
    "gn:timezone":"Asia/Tehran",
    "iso:country":"IR",
    "name:fas_x_preferred":[
        "\u062f\u064e\u0631\u0650\u0651\u0647 \u06af\u064e\u0631\u0645\u0650 \u0645\u064a\u0627\u0646 \u0686\u0650\u0646\u0627\u0631"
    ],
    "name:fas_x_variant":[
        "\u062f\u0631\u0651\u0647 \u06af\u0631\u0645",
        "Darreh Garm-e M\u012b\u0101n Chen\u0101r"
    ],
    "wof:name":"Darreh Garm",
    "wof:placetype":"locality"
},
  "geometry": {"coordinates":[51.13779,30.88089],"type":"Point"}
}