{
  "type": "Feature",
  "properties": {
    "gn:admin1_code":"8",
    "gn:asciiname":"Shilat-e Karganrud",
    "gn:cc2":"IR",
    "gn:country_code":"IR",
    "gn:dem":-26,
    "gn:feature_class":"P",
    "gn:feature_code":"PPL",
    "gn:name":"Sh\u012bl\u0101t-e Karg\u0101nr\u016bd",
    "gn:population":0,
    "gn:timezone":"Asia/Tehran",
    "iso:country":"IR",
    "name:fas_x_preferred":[
        "Sh\u012bl\u0101t-e Karg\u0101nr\u016bd"
    ],
    "name:und_x_variant":[
        "Sh\u012bl\u0101t-e Gorg\u0101n R\u016bd"
    ],
    "wof:name":"Shilat-e Karganrud",
    "wof:placetype":"locality"
},
  "geometry": {"coordinates":[48.95361,37.84972],"type":"Point"}
}