{
  "type": "Feature",
  "properties": {
    "gn:admin1_code":"40",
    "gn:asciiname":"Deh Ab",
    "gn:cc2":"IR",
    "gn:country_code":"IR",
    "gn:dem":1072,
    "gn:feature_class":"P",
    "gn:feature_code":"PPL",
    "gn:name":"Deh \u0100b",
    "gn:population":0,
    "gn:timezone":"Asia/Tehran",
    "iso:country":"IR",
    "name:fas_x_preferred":[
        "\u062f\u0650\u0647 \u0622\u0628"
    ],
    "name:fas_x_variant":[
        "\u062f\u0650\u0647 \u0622\u0628\u0627\u062f",
        "Deh \u0100b"
    ],
    "name:und_x_variant":[
        "Deh\u0101b\u0101d"
    ],
    "wof:name":"Deh Ab",
    "wof:placetype":"locality"
},
  "geometry": {"coordinates":[53.98333,32.25],"type":"Point"}
}