{
  "type": "Feature",
  "properties": {
    "gn:admin1_code":"15",
    "gn:asciiname":"Boneh-ye `Isa",
    "gn:country_code":"IR",
    "gn:dem":62,
    "gn:feature_class":"P",
    "gn:feature_code":"PPL",
    "gn:name":"Boneh-ye \u2018\u012as\u00e1",
    "gn:population":0,
    "gn:timezone":"Asia/Tehran",
    "iso:country":"IR",
    "name:fas_x_preferred":[
        "\u0628\u0646\u0647 \u0639\u06cc\u0633\u06cc"
    ],
    "name:fas_x_variant":[
        "Boneh-ye \u2018\u012as\u00e1"
    ],
    "name:und_x_variant":[
        "Boneh Isa"
    ],
    "wof:name":"Boneh-ye `Isa",
    "wof:placetype":"locality"
},
  "geometry": {"coordinates":[48.53059,32.1684],"type":"Point"}
}