{
  "type": "Feature",
  "properties": {
    "gn:admin1_code":"1",
    "gn:asciiname":"Lulikabad-e Bala",
    "gn:country_code":"IR",
    "gn:dem":2089,
    "gn:feature_class":"P",
    "gn:feature_code":"PPL",
    "gn:name":"L\u016bl\u012bk\u0101b\u0101d-e B\u0101l\u0101",
    "gn:population":0,
    "gn:timezone":"Asia/Tehran",
    "iso:country":"IR",
    "name:fas_x_preferred":[
        "\u0644\u0648\u0644\u064a\u0643\u0650 \u0639\u064f\u0644\u064a\u0627"
    ],
    "name:fas_x_variant":[
        "\u0644\u0648\u0644\u06cc\u06a9 \u0622\u0628\u0627\u062f \u0628\u0627\u0644\u0627",
        "L\u016bl\u012bk-e \u2018Oly\u0101",
        "L\u016bl\u012bk\u0101b\u0101d-e B\u0101l\u0101",
        "\u0644\u0648\u0644\u064a\u0643\u0627\u0628\u0627\u062f\u0650 \u0639\u064f\u0644\u064a\u0627"
    ],
    "name:und_x_variant":[
        "L\u016bl\u012bk\u0101b\u0101d-e \u2018Oly\u0101"
    ],
    "wof:name":"Lulikabad-e Bala",
    "wof:placetype":"locality"
},
  "geometry": {"coordinates":[44.588,37.9805],"type":"Point"}
}