{
  "type": "Feature",
  "properties": {
    "gn:admin1_code":"11",
    "gn:asciiname":"Gavajeg Seyfiun",
    "gn:country_code":"IR",
    "gn:dem":545,
    "gn:feature_class":"P",
    "gn:feature_code":"PPL",
    "gn:name":"Gav\u0101jeg Seyf\u012b\u016bn",
    "gn:population":0,
    "gn:timezone":"Asia/Tehran",
    "iso:country":"IR",
    "name:fas_x_preferred":[
        "\u06af\u0648\u0627\u062c\u06af \u0633\u06cc\u0641\u06cc\u0648\u0646"
    ],
    "name:fas_x_variant":[
        "Gav\u0101jeg Seyf\u012b\u016bn"
    ],
    "wof:name":"Gavajeg Seyfiun",
    "wof:placetype":"locality"
},
  "geometry": {"coordinates":[57.1063,27.6767],"type":"Point"}
}