{
  "type": "Feature",
  "properties": {
    "gn:admin1_code":"41.0",
    "gn:asciiname":"Alvand",
    "gn:country_code":"IR",
    "gn:dem":1900,
    "gn:feature_class":"P",
    "gn:feature_code":"PPL",
    "gn:name":"Alvand",
    "gn:population":0,
    "gn:timezone":"Asia/Tehran",
    "iso:country":"IR",
    "name:fas_x_preferred":[
        "\u0627\u0644\u0648\u0646\u062f"
    ],
    "name:und_x_variant":[
        "Alwand",
        "Alvand"
    ],
    "wof:name":"Alvand",
    "wof:placetype":"locality"
},
  "geometry": {"coordinates":[59.879,31.75],"type":"Point"}
}