{
  "type": "Feature",
  "properties": {
    "gn:admin1_code":"26",
    "gn:asciiname":"Khavar Shahr",
    "gn:country_code":"IR",
    "gn:dem":1043,
    "gn:feature_class":"P",
    "gn:feature_code":"PPL",
    "gn:name":"Kh\u0101var Shahr",
    "gn:population":0,
    "gn:timezone":"Asia/Tehran",
    "iso:country":"IR",
    "name:fas_x_preferred":[
        "\u0634\u064e\u0647\u0631\u064e\u0643\u0650 \u062e\u0627\u0648\u064e\u0631 \u0634\u064e\u0647\u0631"
    ],
    "name:fas_x_variant":[
        "Kh\u0101var Shahr",
        "\u062e\u0627\u0648\u0631 \u0634\u0647\u0631",
        "Shahrak-e Kh\u0101var Shahr"
    ],
    "wof:name":"Khavar Shahr",
    "wof:placetype":"locality"
},
  "geometry": {"coordinates":[51.55892,35.55597],"type":"Point"}
}