{
  "type": "Feature",
  "properties": {
    "gn:admin1_code":"32",
    "gn:asciiname":"Maqvan",
    "gn:country_code":"IR",
    "gn:dem":1101,
    "gn:feature_class":"P",
    "gn:feature_code":"PPL",
    "gn:name":"Maqv\u0101n",
    "gn:population":0,
    "gn:timezone":"Asia/Tehran",
    "iso:country":"IR",
    "name:fas_x_preferred":[
        "\u0645\u064e\u063a\u0648\u0627\u0646"
    ],
    "name:fas_x_variant":[
        "\u0645\u0642\u0648\u0627\u0646",
        "Maghv\u0101n",
        "Maqv\u0101n"
    ],
    "wof:name":"Maqvan",
    "wof:placetype":"locality"
},
  "geometry": {"coordinates":[48.0447,39.0061],"type":"Point"}
}