{
  "type": "Feature",
  "properties": {
    "gn:admin1_code":"35.0",
    "gn:asciiname":"Baghban Kola",
    "gn:country_code":"IR",
    "gn:dem":31,
    "gn:feature_class":"P",
    "gn:feature_code":"PPL",
    "gn:name":"B\u0101ghb\u0101n Kol\u0101",
    "gn:population":0,
    "gn:timezone":"Asia/Tehran",
    "iso:country":"IR",
    "name:fas_x_preferred":[
        "\u0628\u0627\u063a\u0628\u0627\u0646 \u0643\u0644\u0627"
    ],
    "name:fas_x_variant":[
        "B\u0101ghb\u0101n Kol\u0101"
    ],
    "wof:name":"Baghban Kola",
    "wof:placetype":"locality"
},
  "geometry": {"coordinates":[52.47267,36.47749],"type":"Point"}
}