{
  "type": "Feature",
  "properties": {
    "gn:admin1_code":"22",
    "gn:asciiname":"Azhdar Khvab",
    "gn:country_code":"IR",
    "gn:dem":497,
    "gn:feature_class":"P",
    "gn:feature_code":"PPL",
    "gn:name":"Azhdar Khv\u0101b",
    "gn:population":0,
    "gn:timezone":"Asia/Tehran",
    "iso:country":"IR",
    "name:ara_x_preferred":[
        "\u0627\u062c\u062f\u0631\u062e\u0648\u0633"
    ],
    "name:fas_x_preferred":[
        "\u0627\u064e\u0698\u062f\u064e\u0631 \u062e\u064f\u0648\u0634"
    ],
    "name:fas_x_variant":[
        "\u0627\u0698\u062f\u0631 \u062e\u0648\u0627\u0628",
        "\u0627\u0698\u062f\u0631\u062e\u0648\u0633"
    ],
    "name:msa_x_preferred":[
        "Azhdar Khowsh"
    ],
    "name:und_x_variant":[
        "Azhdar Khv\u0101b"
    ],
    "wof:name":"Azhdar Khvab",
    "wof:placetype":"locality"
},
  "geometry": {"coordinates":[51.827,28.5006],"type":"Point"}
}