{
  "type": "Feature",
  "properties": {
    "gn:admin1_code":"4.0",
    "gn:asciiname":"Luterak",
    "gn:country_code":"IR",
    "gn:dem":986,
    "gn:feature_class":"P",
    "gn:feature_code":"PPL",
    "gn:name":"L\u016bterak",
    "gn:population":0,
    "gn:timezone":"Asia/Tehran",
    "iso:country":"IR",
    "name:fas_x_preferred":[
        "\u0644\u0648\u062a\u0631\u06a9"
    ],
    "name:fas_x_variant":[
        "L\u016bterak"
    ],
    "wof:name":"Luterak",
    "wof:placetype":"locality"
},
  "geometry": {"coordinates":[60.12879,27.8184],"type":"Point"}
}