{
  "type": "Feature",
  "properties": {
    "gn:admin1_code":"33",
    "gn:asciiname":"Qushqovan-e `Olya",
    "gn:country_code":"IR",
    "gn:dem":1844,
    "gn:feature_class":"P",
    "gn:feature_code":"PPL",
    "gn:name":"Q\u016bshqov\u0101n-e \u2018Oly\u0101",
    "gn:population":0,
    "gn:timezone":"Asia/Tehran",
    "iso:country":"IR",
    "name:ara_x_preferred":[
        "\u0642\u0648\u0634\u0642\u0648\u0627\u0646 \u0639\u0644\u064a\u0627"
    ],
    "name:fas_x_preferred":[
        "\u0642\u0648\u0634\u0642\u0648\u0627\u0646 \u0639\u0644\u06cc\u0627"
    ],
    "name:fas_x_variant":[
        "Q\u016bshqov\u0101n-e \u2018Oly\u0101"
    ],
    "name:mlg_x_preferred":[
        "Qushqovan-e Olya"
    ],
    "name:msa_x_preferred":[
        "Qushqovan-e Olya"
    ],
    "wof:name":"Qushqovan-e `Olya",
    "wof:placetype":"locality"
},
  "geometry": {"coordinates":[47.0331,37.1321],"type":"Point"}
}