{
  "type": "Feature",
  "properties": {
    "gn:admin1_code":"26.0",
    "gn:asciiname":"Raziabad-e Pa'in",
    "gn:country_code":"IR",
    "gn:dem":1140,
    "gn:feature_class":"P",
    "gn:feature_code":"PPL",
    "gn:name":"Ra\u1e95\u012b\u0101b\u0101d-e P\u0101\u2019\u012bn",
    "gn:population":0,
    "gn:timezone":"Asia/Tehran",
    "iso:country":"IR",
    "name:fas_x_preferred":[
        "\u0631\u064e\u0636\u064a\u0627\u0628\u0627\u062f\u0650 \u067e\u0627\u0626\u064a\u0646"
    ],
    "name:fas_x_variant":[
        "Ra\u1e95\u012b\u0101b\u0101d-e P\u0101\u2019\u012bn",
        "\u0631\u0636\u06cc \u0622\u0628\u0627\u062f \u067e\u0627\u0626\u064a\u0646",
        "\u0631\u0636\u06cc\u200c\u0622\u0628\u0627\u062f \u067e\u0627\u06cc\u06cc\u0646"
    ],
    "name:und_x_variant":[
        "Ra\u1e95\u012b\u0101b\u0101d P\u0101\u2019\u012bn",
        "\u0631\u0636\u06cc \u0622\u0628\u0627\u062f \u067e\u0627\u0626\u064a\u0646"
    ],
    "wof:name":"Raziabad-e Pa'in",
    "wof:placetype":"locality"
},
  "geometry": {"coordinates":[51.0832,35.6524],"type":"Point"}
}