{
  "type": "Feature",
  "properties": {
    "gn:admin1_code":"38.0",
    "gn:asciiname":"Khosknat",
    "gn:country_code":"IR",
    "gn:dem":1619,
    "gn:feature_class":"P",
    "gn:feature_code":"PPL",
    "gn:name":"Khoskn\u0101t",
    "gn:population":0,
    "gn:timezone":"Asia/Tehran",
    "iso:country":"IR",
    "name:fas_x_preferred":[
        "Khoshkn\u0101t-e B\u0101l\u0101"
    ],
    "name:fas_x_variant":[
        "\u062e\u0634\u06a9\u0646\u0627\u062a \u0628\u0627\u0644\u0627",
        "\u062e\u0634\u06a9\u0646\u0627\u062a"
    ],
    "name:und_x_variant":[
        "Khoskn\u0101t"
    ],
    "wof:name":"Khosknat",
    "wof:placetype":"locality"
},
  "geometry": {"coordinates":[49.7926,36.53785],"type":"Point"}
}