{
  "type": "Feature",
  "properties": {
    "gn:admin1_code":"8",
    "gn:asciiname":"Jir Mahalleh-ye Chamacha",
    "gn:country_code":"IR",
    "gn:dem":56,
    "gn:feature_class":"P",
    "gn:feature_code":"PPL",
    "gn:name":"J\u012br Ma\u1e29alleh-ye Cham\u0101ch\u0101",
    "gn:population":0,
    "gn:timezone":"Asia/Tehran",
    "iso:country":"IR",
    "name:fas_x_preferred":[
        "J\u012br Ma\u1e29alleh-ye Cham\u0101ch\u0101"
    ],
    "name:fas_x_variant":[
        "Chamch\u0101",
        "\u062c\u06cc\u0631 \u0645\u062d\u0644\u0647 \u0686\u0645\u0627\u0686\u0627",
        "\u0686\u0645\u0627\u0686\u0627"
    ],
    "name:msa_x_preferred":[
        "Chomacha"
    ],
    "name:ukr_x_preferred":[
        "\u0427\u043e\u043c\u0430\u0447\u0430"
    ],
    "name:und_x_variant":[
        "Jir Ma\u1e29alleh Cham\u0101ch\u0101",
        "Cheshmeh-ye Sar",
        "Chumacha",
        "Chom\u0101ch\u0101h",
        "Chom\u0101ch\u0101",
        "\u062c\u06cc\u0631 \u0645\u062d\u0644\u0647 \u0686\u0645\u0627\u0686\u0627"
    ],
    "wof:name":"Jir Mahalleh-ye Chamacha",
    "wof:placetype":"locality"
},
  "geometry": {"coordinates":[49.51113,37.13019],"type":"Point"}
}