{
  "type": "Feature",
  "properties": {
    "gn:admin1_code":"23",
    "gn:asciiname":"Zereshkeh",
    "gn:country_code":"IR",
    "gn:dem":1582,
    "gn:feature_class":"P",
    "gn:feature_code":"PPL",
    "gn:name":"Zereshkeh",
    "gn:population":0,
    "gn:timezone":"Asia/Tehran",
    "iso:country":"IR",
    "name:ara_x_preferred":[
        "\u0632\u0631\u0634\u063a\u0629"
    ],
    "name:fas_x_preferred":[
        "\u0632\u0631\u0634\u06af\u0647"
    ],
    "name:fas_x_variant":[
        "\u0632\u0631\u0634\u06a9\u0647"
    ],
    "name:und_x_variant":[
        "Zereshg\u0101h",
        "Zarishkah",
        "Zereshgeh",
        "Zereshkeh"
    ],
    "wof:name":"Zereshkeh",
    "wof:placetype":"locality"
},
  "geometry": {"coordinates":[48.7103,33.86117],"type":"Point"}
}