{
  "type": "Feature",
  "properties": {
    "gn:admin1_code":"29",
    "gn:asciiname":"Cheshmeh Sefid",
    "gn:country_code":"IR",
    "gn:dem":2294,
    "gn:feature_class":"P",
    "gn:feature_code":"PPL",
    "gn:name":"Cheshmeh Sef\u012bd",
    "gn:population":0,
    "gn:timezone":"Asia/Tehran",
    "iso:country":"IR",
    "name:fas_x_preferred":[
        "\u0686\u0634\u0645\u0647 \u0633\u0641\u06cc\u062f"
    ],
    "name:fas_x_variant":[
        "Cheshmeh Sef\u012bd"
    ],
    "wof:name":"Cheshmeh Sefid",
    "wof:placetype":"locality"
},
  "geometry": {"coordinates":[55.4835,30.2258],"type":"Point"}
}