{
  "type": "Feature",
  "properties": {
    "gn:admin1_code":"29",
    "gn:asciiname":"Hey'atabad",
    "gn:country_code":"IR",
    "gn:dem":676,
    "gn:feature_class":"P",
    "gn:feature_code":"PPL",
    "gn:name":"Hey\u2019at\u0101b\u0101d",
    "gn:population":0,
    "gn:timezone":"Asia/Tehran",
    "iso:country":"IR",
    "name:fas_x_preferred":[
        "\u0647\u06cc\u0626\u062a \u0622\u0628\u0627\u062f"
    ],
    "name:fas_x_variant":[
        "Hey\u2019at\u0101b\u0101d"
    ],
    "wof:name":"Hey'atabad",
    "wof:placetype":"locality"
},
  "geometry": {"coordinates":[57.9327,28.4485],"type":"Point"}
}