{
  "type": "Feature",
  "properties": {
    "gn:admin1_code":"41",
    "gn:asciiname":"Kalateh-ye Nasir",
    "gn:country_code":"IR",
    "gn:dem":1614,
    "gn:feature_class":"P",
    "gn:feature_code":"PPL",
    "gn:name":"Kal\u0101teh-ye Na\u015f\u012br",
    "gn:population":0,
    "gn:timezone":"Asia/Tehran",
    "iso:country":"IR",
    "name:fas_x_preferred":[
        "\u0646\u0635\u06cc\u0631"
    ],
    "name:fas_x_variant":[
        "Kal\u0101teh-ye Na\u015f\u012br",
        "Na\u015f\u012br",
        "\u06a9\u0644\u0627\u062a\u0647 \u0646\u0635\u06cc\u0631"
    ],
    "name:und_x_variant":[
        "Nas\u012br\u0101b\u0101d"
    ],
    "wof:name":"Kalateh-ye Nasir",
    "wof:placetype":"locality"
},
  "geometry": {"coordinates":[59.03627,33.7713],"type":"Point"}
}