{
  "type": "Feature",
  "properties": {
    "gn:admin1_code":"15",
    "gn:asciiname":"Sheykh `Abar",
    "gn:country_code":"IR",
    "gn:dem":75,
    "gn:feature_class":"P",
    "gn:feature_code":"PPL",
    "gn:name":"Sheykh \u2018Ab\u0101r",
    "gn:population":0,
    "gn:timezone":"Asia/Tehran",
    "iso:country":"IR",
    "name:fas_x_preferred":[
        "Sheykh \u2018Ab\u0101r"
    ],
    "wof:name":"Sheykh `Abar",
    "wof:placetype":"locality"
},
  "geometry": {"coordinates":[48.2001,32.13247],"type":"Point"}
}