{
  "type": "Feature",
  "properties": {
    "gn:admin1_code":"11",
    "gn:asciiname":"Pish Baluku",
    "gn:country_code":"IR",
    "gn:dem":354,
    "gn:feature_class":"P",
    "gn:feature_code":"PPL",
    "gn:name":"P\u012bsh Bal\u016bk\u016b",
    "gn:population":0,
    "gn:timezone":"Asia/Tehran",
    "iso:country":"IR",
    "name:fas_x_preferred":[
        "\u067e\u06cc\u0634 \u0628\u0644\u0648\u06a9\u0648"
    ],
    "name:fas_x_variant":[
        "P\u012bsh Bal\u016bk\u016b"
    ],
    "wof:name":"Pish Baluku",
    "wof:placetype":"locality"
},
  "geometry": {"coordinates":[57.7526,26.23],"type":"Point"}
}