{
  "type": "Feature",
  "properties": {
    "gn:admin1_code":"39",
    "gn:asciiname":"Sadeqabad",
    "gn:country_code":"IR",
    "gn:dem":1209,
    "gn:feature_class":"P",
    "gn:feature_code":"PPL",
    "gn:name":"\u015e\u0101deq\u0101b\u0101d",
    "gn:population":0,
    "gn:timezone":"Asia/Tehran",
    "iso:country":"IR",
    "name:fas_x_preferred":[
        "\u015e\u0101deq\u0101b\u0101d"
    ],
    "name:fas_x_variant":[
        "\u0635\u0627\u062f\u0642 \u0622\u0628\u0627\u062f"
    ],
    "name:und_x_variant":[
        "\u0635\u0627\u062f\u0642 \u0622\u0628\u0627\u062f"
    ],
    "wof:name":"Sadeqabad",
    "wof:placetype":"locality"
},
  "geometry": {"coordinates":[50.42749,34.69425],"type":"Point"}
}