{
  "type": "Feature",
  "properties": {
    "gn:admin1_code":"33",
    "gn:asciiname":"Qinarjeh",
    "gn:country_code":"IR",
    "gn:dem":1671,
    "gn:feature_class":"P",
    "gn:feature_code":"PPL",
    "gn:name":"Q\u012bnarjeh",
    "gn:population":0,
    "gn:timezone":"Asia/Tehran",
    "iso:country":"IR",
    "name:fas_x_preferred":[
        "Q\u012bnarjeh"
    ],
    "name:fas_x_variant":[
        "\u0642\u06cc\u0646\u0631\u062c\u0647",
        "\u0642\u06cc\u0632\u0686\u0647"
    ],
    "name:msa_x_preferred":[
        "Qizcheh"
    ],
    "name:und_x_variant":[
        "Q\u012bzcheh"
    ],
    "wof:name":"Qinarjeh",
    "wof:placetype":"locality"
},
  "geometry": {"coordinates":[46.5971,37.2335],"type":"Point"}
}