{
  "type": "Feature",
  "properties": {
    "gn:admin1_code":"23",
    "gn:asciiname":"Mahmudabad-e Bi Ab",
    "gn:country_code":"IR",
    "gn:dem":2093,
    "gn:feature_class":"P",
    "gn:feature_code":"PPL",
    "gn:name":"Ma\u1e29m\u016bd\u0101b\u0101d-e B\u012b \u0100b",
    "gn:population":0,
    "gn:timezone":"Asia/Tehran",
    "iso:country":"IR",
    "name:fas_x_preferred":[
        "\u0645\u062d\u0645\u0648\u062f \u0622\u0628\u0627\u062f \u0628\u06cc \u0622\u0628"
    ],
    "name:fas_x_variant":[
        "Ma\u1e29m\u016bd\u0101b\u0101d-e B\u012b\u0101b",
        "B\u012b\u0101b",
        "Ma\u1e29m\u016bd\u0101b\u0101d-e B\u012b \u0100b"
    ],
    "name:und_x_variant":[
        "Ma\u1e29m\u016bd\u0101b\u0101d"
    ],
    "wof:name":"Mahmudabad-e Bi Ab",
    "wof:placetype":"locality"
},
  "geometry": {"coordinates":[49.34399000000001,33.70927],"type":"Point"}
}