{
  "type": "Feature",
  "properties": {
    "gn:admin1_code":"8",
    "gn:asciiname":"Lakan",
    "gn:country_code":"IR",
    "gn:dem":28,
    "gn:feature_class":"P",
    "gn:feature_code":"PPL",
    "gn:name":"L\u0101k\u0101n",
    "gn:population":0,
    "gn:timezone":"Asia/Tehran",
    "iso:country":"IR",
    "name:fas_x_preferred":[
        "S\u012bmbar-e L\u0101k\u0101n"
    ],
    "name:fas_x_variant":[
        "L\u0101k\u0101n",
        "\u0644\u0627\u06a9\u0627\u0646"
    ],
    "name:msa_x_preferred":[
        "Lakan"
    ],
    "name:ukr_x_preferred":[
        "\u041b\u044f\u043a\u0430\u043d"
    ],
    "name:urd_x_preferred":[
        "\u0644\u0627\u06a9\u0627\u0646"
    ],
    "wof:name":"Lakan",
    "wof:placetype":"locality"
},
  "geometry": {"coordinates":[49.58575,37.19202],"type":"Point"}
}