{
  "type": "Feature",
  "properties": {
    "gn:admin1_code":"41",
    "gn:asciiname":"Gazan",
    "gn:country_code":"IR",
    "gn:dem":1937,
    "gn:feature_class":"P",
    "gn:feature_code":"PPL",
    "gn:name":"Gaz\u0101n",
    "gn:population":0,
    "gn:timezone":"Asia/Tehran",
    "iso:country":"IR",
    "name:ceb_x_preferred":[
        "Gazan"
    ],
    "name:fas_x_preferred":[
        "\u06af\u0632\u0627\u0646"
    ],
    "name:fas_x_variant":[
        "Gaz\u0101n"
    ],
    "name:fra_x_preferred":[
        "Gazan"
    ],
    "name:swe_x_preferred":[
        "Gazan"
    ],
    "name:und_x_variant":[
        "Qaz\u0101n"
    ],
    "wof:name":"Gazan",
    "wof:placetype":"locality"
},
  "geometry": {"coordinates":[59.5026,32.2054],"type":"Point"}
}