{
  "type": "Feature",
  "properties": {
    "gn:admin1_code":"34",
    "gn:asciiname":"Dizaj",
    "gn:country_code":"IR",
    "gn:dem":1641,
    "gn:feature_class":"P",
    "gn:feature_code":"PPL",
    "gn:name":"D\u012bzaj",
    "gn:population":0,
    "gn:timezone":"Asia/Tehran",
    "iso:country":"IR",
    "name:fas_x_preferred":[
        "\u062f\u064a\u0632\u064e\u0643"
    ],
    "name:fas_x_variant":[
        "D\u012bzaj",
        "\u062f\u064a\u0632\u062c",
        "\u062f\u06cc\u0632\u062c"
    ],
    "name:und_x_variant":[
        "D\u012bzak"
    ],
    "wof:name":"Dizaj",
    "wof:placetype":"locality"
},
  "geometry": {"coordinates":[50.11405,34.83133],"type":"Point"}
}