{
  "type": "Feature",
  "properties": {
    "gn:admin1_code":"15",
    "gn:asciiname":"Shannuf",
    "gn:country_code":"IR",
    "gn:dem":2,
    "gn:feature_class":"P",
    "gn:feature_code":"PPL",
    "gn:name":"Shann\u016bf",
    "gn:population":0,
    "gn:timezone":"Asia/Tehran",
    "iso:country":"IR",
    "name:fas_x_preferred":[
        "Shann\u016bf"
    ],
    "wof:name":"Shannuf",
    "wof:placetype":"locality"
},
  "geometry": {"coordinates":[48.54667,29.97111],"type":"Point"}
}