{
  "type": "Feature",
  "properties": {
    "gn:admin1_code":"41",
    "gn:asciiname":"Darreh Charm",
    "gn:country_code":"IR",
    "gn:dem":1783,
    "gn:feature_class":"P",
    "gn:feature_code":"PPL",
    "gn:name":"Darreh Charm",
    "gn:population":0,
    "gn:timezone":"Asia/Tehran",
    "iso:country":"IR",
    "name:fas_x_preferred":[
        "\u062f\u0631\u0647 \u0686\u0631\u0645"
    ],
    "name:und_x_variant":[
        "Dar-i-Charm",
        "Darreh-ye Charm",
        "Darreh Charm"
    ],
    "wof:name":"Darreh Charm",
    "wof:placetype":"locality"
},
  "geometry": {"coordinates":[59.9027,33.12388],"type":"Point"}
}