{
  "type": "Feature",
  "properties": {
    "gn:admin1_code":"38.0",
    "gn:asciiname":"Asbak",
    "gn:country_code":"IR",
    "gn:dem":1448,
    "gn:feature_class":"P",
    "gn:feature_code":"PPL",
    "gn:name":"Asbak",
    "gn:population":0,
    "gn:timezone":"Asia/Tehran",
    "iso:country":"IR",
    "name:fas_x_preferred":[
        "\u0627\u0633\u0628\u06a9"
    ],
    "name:und_x_variant":[
        "Aspak",
        "Asbak"
    ],
    "wof:name":"Asbak",
    "wof:placetype":"locality"
},
  "geometry": {"coordinates":[49.57675,36.51519],"type":"Point"}
}