{
  "type": "Feature",
  "properties": {
    "gn:admin1_code":"35.0",
    "gn:asciiname":"Kalam Var",
    "gn:country_code":"IR",
    "gn:dem":651,
    "gn:feature_class":"P",
    "gn:feature_code":"PPL",
    "gn:name":"Kalam Var",
    "gn:population":0,
    "gn:timezone":"Asia/Tehran",
    "iso:country":"IR",
    "name:fas_x_preferred":[
        "\u0648\u0644\u0631 \u062f\u0647"
    ],
    "name:fas_x_variant":[
        "\u06a9\u0644\u0645 \u0648\u0631",
        "\u0643\u064e\u0644\u0650\u0646\u064f\u0648",
        "\u0643\u064e\u0644\u0650\u0646\u064f\u0648\u06cc \u0628\u0627\u0644\u0627",
        "\u0643\u064e\u0644 \u0646\u064f\u0648",
        "\u06a9\u0644\u0627\u0645 \u0648\u0631"
    ],
    "name:und_x_variant":[
        "\u0648\u0644\u0631 \u062f\u0647",
        "Valar Deh",
        "Kalam Var",
        "Kal Now",
        "Kalenow",
        "Kalenow-ye B\u0101l\u0101",
        "Kal\u0101mvar",
        "Kal\u0101m Var"
    ],
    "wof:name":"Kalam Var",
    "wof:placetype":"locality"
},
  "geometry": {"coordinates":[51.29354,36.4872],"type":"Point"}
}