{
  "type": "Feature",
  "properties": {
    "gn:admin1_code":"5",
    "gn:asciiname":"Bard-e Pahn",
    "gn:country_code":"IR",
    "gn:dem":1485,
    "gn:feature_class":"P",
    "gn:feature_code":"PPL",
    "gn:name":"Bard-e Pahn",
    "gn:population":0,
    "gn:timezone":"Asia/Tehran",
    "iso:country":"IR",
    "name:fas_x_preferred":[
        "\u0628\u0631\u062f \u067e\u0647\u0646"
    ],
    "name:fas_x_variant":[
        "\u0645\u0646\u062f\u0647"
    ],
    "name:und_x_variant":[
        "Bard-e Pahn",
        "Mandeh"
    ],
    "wof:name":"Bard-e Pahn",
    "wof:placetype":"locality"
},
  "geometry": {"coordinates":[50.66038,31.39283],"type":"Point"}
}