{
  "type": "Feature",
  "properties": {
    "gn:admin1_code":"16",
    "gn:asciiname":"Yaminan-e Bala",
    "gn:country_code":"IR",
    "gn:dem":1653,
    "gn:feature_class":"P",
    "gn:feature_code":"PPL",
    "gn:name":"Yam\u012bn\u0101n-e B\u0101l\u0101",
    "gn:population":0,
    "gn:timezone":"Asia/Tehran",
    "iso:country":"IR",
    "name:fas_x_preferred":[
        "\u064a\u064e\u0645\u0646\u0627\u0646\u0650 \u0639\u064f\u0644\u064a\u0627"
    ],
    "name:fas_x_variant":[
        "\u064a\u064e\u0645\u064a\u0646\u0627\u0646\u0650 \u0639\u064f\u0644\u064a\u064e",
        "\u064a\u064e\u0645\u0646\u0627\u0646\u0650 \u0628\u0627\u0644\u0627",
        "\u06cc\u0645\u06cc\u0646\u0627\u0646 \u0628\u0627\u0644\u0627",
        "Yamn\u0101n-e \u2018Oly\u0101",
        "Yam\u012bn\u0101n-e B\u0101l\u0101"
    ],
    "name:und_x_variant":[
        "Yam\u012bn\u0101n-e \u2018Olya",
        "Yamn\u0101n-e B\u0101l\u0101"
    ],
    "wof:name":"Yaminan-e Bala",
    "wof:placetype":"locality"
},
  "geometry": {"coordinates":[46.9212,34.9925],"type":"Point"}
}