{
  "type": "Feature",
  "properties": {
    "gn:admin1_code":"7",
    "gn:asciiname":"Kereh",
    "gn:country_code":"IR",
    "gn:dem":1393,
    "gn:feature_class":"P",
    "gn:feature_code":"PPL",
    "gn:name":"Kereh",
    "gn:population":0,
    "gn:timezone":"Asia/Tehran",
    "iso:country":"IR",
    "name:fas_x_preferred":[
        "\u0646\u0638\u0627\u0645 \u0622\u0628\u0627\u062f"
    ],
    "name:fas_x_variant":[
        "Nez\u0327\u0101m\u0101b\u0101d",
        "\u06a9\u0631\u0647"
    ],
    "name:und_x_variant":[
        "Niz\u0101m\u0101b\u0101d",
        "Kereh"
    ],
    "wof:name":"Kereh",
    "wof:placetype":"locality"
},
  "geometry": {"coordinates":[54.0613,28.9498],"type":"Point"}
}