{
  "type": "Feature",
  "properties": {
    "gn:admin1_code":"29",
    "gn:asciiname":"Dowlatabad-e Ansari",
    "gn:country_code":"IR",
    "gn:dem":885,
    "gn:feature_class":"P",
    "gn:feature_code":"PPL",
    "gn:name":"Dowlat\u0101b\u0101d-e An\u015f\u0101r\u012b",
    "gn:population":0,
    "gn:timezone":"Asia/Tehran",
    "iso:country":"IR",
    "name:fas_x_preferred":[
        "\u062f\u0648\u0644\u062a \u0622\u0628\u0627\u062f \u0627\u0646\u0635\u0627\u0631\u06cc"
    ],
    "name:fas_x_variant":[
        "Dowlat\u0101b\u0101d",
        "Dowlat\u0101b\u0101d-e An\u015f\u0101r\u012b",
        "\u062f\u0648\u0644\u062a\u200c\u0622\u0628\u0627\u062f \u0627\u0646\u0635\u0627\u0631\u06cc"
    ],
    "wof:name":"Dowlatabad-e Ansari",
    "wof:placetype":"locality"
},
  "geometry": {"coordinates":[58.458,28.9308],"type":"Point"}
}