{
  "type": "Feature",
  "properties": {
    "gn:admin1_code":"15.0",
    "gn:asciiname":"Juhi",
    "gn:country_code":"IR",
    "gn:dem":50,
    "gn:feature_class":"P",
    "gn:feature_code":"PPL",
    "gn:name":"J\u016b\u1e29\u012b",
    "gn:population":0,
    "gn:timezone":"Asia/Tehran",
    "iso:country":"IR",
    "name:fas_x_preferred":[
        "J\u016bkh\u012b"
    ],
    "name:fas_x_variant":[
        "\u062c\u0648\u062d\u06cc"
    ],
    "name:und_x_variant":[
        "J\u016b\u1e29\u012b"
    ],
    "wof:name":"Juhi",
    "wof:placetype":"locality"
},
  "geometry": {"coordinates":[48.27915,32.00605],"type":"Point"}
}