{
  "type": "Feature",
  "properties": {
    "gn:admin1_code":"35.0",
    "gn:asciiname":"Mazu Kaleh",
    "gn:country_code":"IR",
    "gn:dem":698,
    "gn:feature_class":"P",
    "gn:feature_code":"PPL",
    "gn:name":"M\u0101z\u016b Kaleh",
    "gn:population":0,
    "gn:timezone":"Asia/Tehran",
    "iso:country":"IR",
    "name:fas_x_preferred":[
        "M\u0101z\u016b Kaleh"
    ],
    "name:fas_x_variant":[
        "\u0645\u0627\u0632\u0648 \u06a9\u0644\u0647"
    ],
    "name:und_x_variant":[
        "\u0645\u0627\u0632\u0648 \u06a9\u0644\u0647"
    ],
    "wof:name":"Mazu Kaleh",
    "wof:placetype":"locality"
},
  "geometry": {"coordinates":[50.79705,36.65953],"type":"Point"}
}