{
  "type": "Feature",
  "properties": {
    "gn:admin1_code":"36",
    "gn:asciiname":"Chamlugin",
    "gn:country_code":"IR",
    "gn:dem":1739,
    "gn:feature_class":"P",
    "gn:feature_code":"PPL",
    "gn:name":"Chaml\u016bg\u012bn",
    "gn:population":0,
    "gn:timezone":"Asia/Tehran",
    "iso:country":"IR",
    "name:fas_x_preferred":[
        "\u0686\u064e\u0645\u0644\u0650\u0647 \u062c\u064e\u0628\u064e\u0646"
    ],
    "name:fas_x_variant":[
        "\u0686\u0645\u0644\u0648 \u06af\u0628\u064a\u0646",
        "\u0686\u064e\u0645\u0644\u064e\u06af\u064e\u0628\u064e\u0646",
        "Chaml\u016bgaben",
        "Chaml\u016b Gab\u012bn",
        "\u0686\u0645\u0644\u0648\u06af\u06cc\u0646",
        "\u0686\u0645\u0644\u0648 \u06af\u0628\u064a\u0646 \u06cc\u0627\u0647\u0644\u06cc\u0642"
    ],
    "name:und_x_variant":[
        "Chamlagaban",
        "Chamleh Jaban",
        "Chaml\u016bg\u012bn",
        "Chaml\u016b Gab\u012bn Y\u0101hl\u012bq"
    ],
    "wof:name":"Chamlugin",
    "wof:placetype":"locality"
},
  "geometry": {"coordinates":[48.79463,37.16795],"type":"Point"}
}