{
  "type": "Feature",
  "properties": {
    "gn:admin1_code":"4.0",
    "gn:asciiname":"Chishi",
    "gn:country_code":"IR",
    "gn:dem":8,
    "gn:feature_class":"P",
    "gn:feature_code":"PPL",
    "gn:name":"Ch\u012bsh\u012b",
    "gn:population":0,
    "gn:timezone":"Asia/Tehran",
    "iso:country":"IR",
    "name:fas_x_preferred":[
        "Ch\u012bsh\u012b"
    ],
    "wof:name":"Chishi",
    "wof:placetype":"locality"
},
  "geometry": {"coordinates":[60.31667,25.48333],"type":"Point"}
}