{
  "type": "Feature",
  "properties": {
    "gn:admin1_code":"15",
    "gn:asciiname":"Boneh-ye Farz `Ali",
    "gn:country_code":"IR",
    "gn:dem":332,
    "gn:feature_class":"P",
    "gn:feature_code":"PPL",
    "gn:name":"Boneh-ye Farz \u2018Al\u012b",
    "gn:population":0,
    "gn:timezone":"Asia/Tehran",
    "iso:country":"IR",
    "name:fas_x_preferred":[
        "Boneh-ye Farz \u2018Al\u012b"
    ],
    "name:und_x_variant":[
        "Boneh Farzali"
    ],
    "wof:name":"Boneh-ye Farz `Ali",
    "wof:placetype":"locality"
},
  "geometry": {"coordinates":[49.11667,32.13333],"type":"Point"}
}