{
  "type": "Feature",
  "properties": {
    "gn:admin1_code":"34",
    "gn:asciiname":"Deh-e Mir Qasem",
    "gn:country_code":"IR",
    "gn:dem":1902,
    "gn:feature_class":"P",
    "gn:feature_code":"PPL",
    "gn:name":"Deh-e M\u012br Q\u0101sem",
    "gn:population":0,
    "gn:timezone":"Asia/Tehran",
    "iso:country":"IR",
    "name:fas_x_preferred":[
        "\u0645\u064a\u0631 \u0642\u0627\u0633\u0645"
    ],
    "name:fas_x_variant":[
        "M\u012br Q\u0101sem",
        "\u062f\u0647 \u0645\u06cc\u0631 \u0642\u0627\u0633\u0645"
    ],
    "name:und_x_variant":[
        "Deh-e M\u012br Q\u0101sem"
    ],
    "wof:name":"Deh-e Mir Qasem",
    "wof:placetype":"locality"
},
  "geometry": {"coordinates":[49.27121,33.6823],"type":"Point"}
}