{
  "type": "Feature",
  "properties": {
    "gn:admin1_code":"16.0",
    "gn:asciiname":"Tut Sorkhan",
    "gn:country_code":"IR",
    "gn:dem":1950,
    "gn:feature_class":"P",
    "gn:feature_code":"PPL",
    "gn:name":"T\u016bt Sorkh\u0101n",
    "gn:population":0,
    "gn:timezone":"Asia/Tehran",
    "iso:country":"IR",
    "name:ceb_x_preferred":[
        "T\u016bt Sorkh\u0101n"
    ],
    "name:ckb_x_preferred":[
        "\u062a\u0648\u0648\u06d5\u0633\u0648\u0648\u0631\u0627\u0646"
    ],
    "name:fas_x_preferred":[
        "\u062a\u0648\u062a \u0633\u064f\u0631\u062e\u0627\u0646"
    ],
    "name:fas_x_variant":[
        "\u062a\u0648\u062a \u0633\u0631\u062e\u0627\u0646",
        "T\u016bt Sorkh\u0101n"
    ],
    "name:swe_x_preferred":[
        "T\u016bt Sorkh\u0101n"
    ],
    "wof:name":"Tut Sorkhan",
    "wof:placetype":"locality"
},
  "geometry": {"coordinates":[46.365,35.6914],"type":"Point"}
}