{
  "type": "Feature",
  "properties": {
    "gn:admin1_code":"28",
    "gn:asciiname":"Golestan-e Mehdi",
    "gn:country_code":"IR",
    "gn:dem":988,
    "gn:feature_class":"P",
    "gn:feature_code":"PPL",
    "gn:name":"Golest\u0101n-e Mehd\u012b",
    "gn:population":0,
    "gn:timezone":"Asia/Tehran",
    "iso:country":"IR",
    "name:fas_x_preferred":[
        "\u06af\u0644\u0633\u062a\u0627\u0646 \u0645\u0647\u062f\u06cc"
    ],
    "name:fas_x_variant":[
        "Golest\u0101n-e Mehd\u012b"
    ],
    "wof:name":"Golestan-e Mehdi",
    "wof:placetype":"locality"
},
  "geometry": {"coordinates":[52.3347,33.4865],"type":"Point"}
}