{
  "type": "Feature",
  "properties": {
    "gn:admin1_code":"3",
    "gn:asciiname":"Darreh Yas",
    "gn:cc2":"IR",
    "gn:country_code":"IR",
    "gn:dem":1800,
    "gn:feature_class":"P",
    "gn:feature_code":"PPL",
    "gn:name":"Darreh Y\u0101s",
    "gn:population":0,
    "gn:timezone":"Asia/Tehran",
    "iso:country":"IR",
    "name:ceb_x_preferred":[
        "Darreh Y\u0101s"
    ],
    "name:fas_x_preferred":[
        "\u0631\u0648\u062f \u0648\u0627\u0631"
    ],
    "name:fas_x_variant":[
        "Darreh Y\u0101s",
        "\u062f\u064e\u0631\u0650\u0651\u0647 \u064a\u0627\u0633",
        "\u062f\u0631\u0647 \u06cc\u0627\u0633"
    ],
    "name:msa_x_preferred":[
        "Darreh Yas"
    ],
    "name:swe_x_preferred":[
        "Darreh Y\u0101s"
    ],
    "name:und_x_variant":[
        "R\u016bdw\u0101r",
        "R\u016bd V\u0101r"
    ],
    "wof:name":"Darreh Yas",
    "wof:placetype":"locality"
},
  "geometry": {"coordinates":[50.51667,31.93333],"type":"Point"}
}