{
  "type": "Feature",
  "properties": {
    "gn:admin1_code":"36.0",
    "gn:asciiname":"Zeralu",
    "gn:country_code":"IR",
    "gn:dem":2192,
    "gn:feature_class":"P",
    "gn:feature_code":"PPL",
    "gn:name":"Zeralu",
    "gn:population":0,
    "gn:timezone":"Asia/Tehran",
    "iso:country":"IR",
    "name:fas_x_preferred":[
        "\u0639\u0644\u06cc \u0622\u0628\u0627\u062f \u0645\u0648\u0633\u0648\u06cc"
    ],
    "name:fas_x_variant":[
        "\u2018Al\u012b\u0101b\u0101d-e M\u016bsav\u012b",
        "\u0639\u0644\u06cc \u0622\u0628\u0627\u062f",
        "\u0639\u0644\u06cc \u0622\u0628\u0627\u062f \u0634\u0631\u0642\u06cc"
    ],
    "name:und_x_variant":[
        "\u2018Al\u012b\u0101b\u0101d Z\u012brehl\u016b",
        "\u2018Al\u012b\u0101b\u0101d",
        "\u2018Al\u012b\u0101b\u0101d-e Sharq\u012b"
    ],
    "wof:name":"Zeralu",
    "wof:placetype":"locality"
},
  "geometry": {"coordinates":[48.73507,36.74091],"type":"Point"}
}