{
  "type": "Feature",
  "properties": {
    "gn:admin1_code":"35.0",
    "gn:asciiname":"Malar",
    "gn:country_code":"IR",
    "gn:dem":2315,
    "gn:feature_class":"P",
    "gn:feature_code":"PPL",
    "gn:name":"Mal\u0101r",
    "gn:population":0,
    "gn:timezone":"Asia/Tehran",
    "iso:country":"IR",
    "name:fas_x_preferred":[
        "\u0645\u0644\u0627\u0631"
    ],
    "name:fas_x_variant":[
        "Mal\u0101r"
    ],
    "wof:name":"Malar",
    "wof:placetype":"locality"
},
  "geometry": {"coordinates":[52.19281,35.92488],"type":"Point"}
}