{
  "type": "Feature",
  "properties": {
    "gn:admin1_code":"8",
    "gn:asciiname":"Kia Kolayeh",
    "gn:country_code":"IR",
    "gn:dem":-23,
    "gn:feature_class":"P",
    "gn:feature_code":"PPL",
    "gn:name":"K\u012b\u0101 Kol\u0101yeh",
    "gn:population":0,
    "gn:timezone":"Asia/Tehran",
    "iso:country":"IR",
    "name:fas_x_preferred":[
        "K\u012b\u0101 Kol\u0101yeh"
    ],
    "wof:name":"Kia Kolayeh",
    "wof:placetype":"locality"
},
  "geometry": {"coordinates":[50.16667,37.18278],"type":"Point"}
}