{
  "type": "Feature",
  "properties": {
    "gn:admin1_code":"8.0",
    "gn:asciiname":"Bala Tiv Dasht",
    "gn:country_code":"IR",
    "gn:dem":238,
    "gn:feature_class":"P",
    "gn:feature_code":"PPL",
    "gn:name":"B\u0101l\u0101 T\u012bv Dasht",
    "gn:population":0,
    "gn:timezone":"Asia/Tehran",
    "iso:country":"IR",
    "name:fas_x_preferred":[
        "\u0628\u0627\u0644\u0627 \u062a\u06cc\u0648 \u062f\u0634\u062a"
    ],
    "name:und_x_variant":[
        "B\u0101l\u0101 T\u012bv Dasht"
    ],
    "wof:name":"Bala Tiv Dasht",
    "wof:placetype":"locality"
},
  "geometry": {"coordinates":[49.76877,37.05484000000001],"type":"Point"}
}