{
  "type": "Feature",
  "properties": {
    "gn:admin1_code":"29.0",
    "gn:asciiname":"Kam Kasur",
    "gn:country_code":"IR",
    "gn:dem":1141,
    "gn:feature_class":"P",
    "gn:feature_code":"PPL",
    "gn:name":"Kam Kas\u016br",
    "gn:population":0,
    "gn:timezone":"Asia/Tehran",
    "iso:country":"IR",
    "name:fas_x_preferred":[
        "\u06a9\u0645 \u06a9\u0633\u0648\u0631"
    ],
    "name:und_x_variant":[
        "Kam Kas\u016br"
    ],
    "wof:name":"Kam Kasur",
    "wof:placetype":"locality"
},
  "geometry": {"coordinates":[58.77213,28.26869000000001],"type":"Point"}
}