{
  "type": "Feature",
  "properties": {
    "gn:admin1_code":"7",
    "gn:asciiname":"`Aliabad-e Kohandal",
    "gn:country_code":"IR",
    "gn:dem":2033,
    "gn:feature_class":"P",
    "gn:feature_code":"PPL",
    "gn:name":"\u2018Al\u012b\u0101b\u0101d-e Kohandal",
    "gn:population":0,
    "gn:timezone":"Asia/Tehran",
    "iso:country":"IR",
    "name:fas_x_preferred":[
        "\u0639\u0644\u06cc \u0622\u0628\u0627\u062f \u06a9\u0647\u0646\u062f\u0644"
    ],
    "name:fas_x_variant":[
        "\u2018Al\u012b\u0101b\u0101d-e Kohandal"
    ],
    "wof:name":"`Aliabad-e Kohandal",
    "wof:placetype":"locality"
},
  "geometry": {"coordinates":[53.4252,29.9578],"type":"Point"}
}