{
  "type": "Feature",
  "properties": {
    "gn:admin1_code":"5",
    "gn:asciiname":"Kabas `Ali",
    "gn:country_code":"IR",
    "gn:dem":1905,
    "gn:feature_class":"P",
    "gn:feature_code":"PPL",
    "gn:name":"K\u0101b\u0101s \u2018Al\u012b",
    "gn:population":0,
    "gn:timezone":"Asia/Tehran",
    "iso:country":"IR",
    "name:fas_x_preferred":[
        "\u0643\u0627\u0628\u0627\u0633 \u0639\u064e\u0644\u06cc"
    ],
    "name:fas_x_variant":[
        "K\u0101b\u0101s \u2018Al\u012b"
    ],
    "wof:name":"Kabas `Ali",
    "wof:placetype":"locality"
},
  "geometry": {"coordinates":[50.85,30.68333],"type":"Point"}
}