{
  "type": "Feature",
  "properties": {
    "gn:admin1_code":"42",
    "gn:asciiname":"Archang",
    "gn:country_code":"IR",
    "gn:dem":1332,
    "gn:feature_class":"P",
    "gn:feature_code":"PPL",
    "gn:name":"Archang",
    "gn:population":0,
    "gn:timezone":"Asia/Tehran",
    "iso:country":"IR",
    "name:fas_x_preferred":[
        "\u0627\u0631\u0686\u0646\u06af"
    ],
    "wof:name":"Archang",
    "wof:placetype":"locality"
},
  "geometry": {"coordinates":[59.31800000000001,36.3942],"type":"Point"}
}