{
  "type": "Feature",
  "properties": {
    "gn:admin1_code":"42.0",
    "gn:asciiname":"Siman",
    "gn:country_code":"IR",
    "gn:dem":1532,
    "gn:feature_class":"P",
    "gn:feature_code":"PPL",
    "gn:name":"S\u012bm\u0101n",
    "gn:population":0,
    "gn:timezone":"Asia/Tehran",
    "iso:country":"IR",
    "name:fas_x_preferred":[
        "S\u012bm\u0101n"
    ],
    "name:fas_x_variant":[
        "\u0633\u06cc\u0645\u0627\u0646"
    ],
    "wof:name":"Siman",
    "wof:placetype":"locality"
},
  "geometry": {"coordinates":[58.19021,36.74408],"type":"Point"}
}