{
  "type": "Feature",
  "properties": {
    "gn:admin1_code":"8",
    "gn:asciiname":"Dasht-e Kur",
    "gn:country_code":"IR",
    "gn:dem":372,
    "gn:feature_class":"P",
    "gn:feature_code":"PPL",
    "gn:name":"Dasht-e K\u016br",
    "gn:population":0,
    "gn:timezone":"Asia/Tehran",
    "iso:country":"IR",
    "name:fas_x_preferred":[
        "Dasht-e K\u016br"
    ],
    "wof:name":"Dasht-e Kur",
    "wof:placetype":"locality"
},
  "geometry": {"coordinates":[49.48333,36.83333],"type":"Point"}
}