{
  "type": "Feature",
  "properties": {
    "gn:admin1_code":"23",
    "gn:asciiname":"Cham Kabud",
    "gn:country_code":"IR",
    "gn:dem":1441,
    "gn:feature_class":"P",
    "gn:feature_code":"PPL",
    "gn:name":"Cham Kab\u016bd",
    "gn:population":0,
    "gn:timezone":"Asia/Tehran",
    "iso:country":"IR",
    "name:fas_x_preferred":[
        "\u0686\u0645 \u06a9\u0628\u0648\u062f"
    ],
    "name:und_x_variant":[
        "Cham Kab\u016bd"
    ],
    "wof:name":"Cham Kabud",
    "wof:placetype":"locality"
},
  "geometry": {"coordinates":[47.93511,33.89503],"type":"Point"}
}