{
  "type": "Feature",
  "properties": {
    "gn:admin1_code":"16.0",
    "gn:asciiname":"Kani Kabud",
    "gn:country_code":"IR",
    "gn:dem":1923,
    "gn:feature_class":"P",
    "gn:feature_code":"PPL",
    "gn:name":"K\u0101n\u012b Kab\u016bd",
    "gn:population":0,
    "gn:timezone":"Asia/Tehran",
    "iso:country":"IR",
    "name:fas_x_preferred":[
        "K\u0101n\u012b Kab\u016bd"
    ],
    "name:fas_x_variant":[
        "\u0643\u0627\u0646\u06cc \u0643\u0628\u0648\u062f"
    ],
    "name:und_x_variant":[
        "\u0643\u0627\u0646\u06cc \u0643\u0628\u0648\u062f"
    ],
    "wof:name":"Kani Kabud",
    "wof:placetype":"locality"
},
  "geometry": {"coordinates":[46.94964,35.7982],"type":"Point"}
}