{
  "type": "Feature",
  "properties": {
    "gn:admin1_code":"42",
    "gn:asciiname":"Kalateh-ye Shuravak",
    "gn:country_code":"IR",
    "gn:dem":1453,
    "gn:feature_class":"P",
    "gn:feature_code":"PPL",
    "gn:name":"Kal\u0101teh-ye Sh\u016br\u0101vak",
    "gn:population":0,
    "gn:timezone":"Asia/Tehran",
    "iso:country":"IR",
    "name:fas_x_preferred":[
        "\u06a9\u0644\u0627\u062a\u0647 \u0634\u0648\u0631\u0627\u0648\u06a9"
    ],
    "name:fas_x_variant":[
        "Kal\u0101teh-ye Sh\u016br\u0101vak"
    ],
    "wof:name":"Kalateh-ye Shuravak",
    "wof:placetype":"locality"
},
  "geometry": {"coordinates":[59.06177,35.7478],"type":"Point"}
}