{
  "type": "Feature",
  "properties": {
    "gn:admin1_code":"26.0",
    "gn:asciiname":"Ziba Shahr",
    "gn:country_code":"IR",
    "gn:dem":1323,
    "gn:feature_class":"P",
    "gn:feature_code":"PPL",
    "gn:name":"Z\u012bb\u0101 Shahr",
    "gn:population":0,
    "gn:timezone":"Asia/Tehran",
    "iso:country":"IR",
    "name:fas_x_preferred":[
        "\u0632\u064a\u0628\u0627 \u0634\u0647\u0631"
    ],
    "name:fas_x_variant":[
        "Z\u012bb\u0101 Shahr"
    ],
    "wof:name":"Ziba Shahr",
    "wof:placetype":"locality"
},
  "geometry": {"coordinates":[51.2981,35.7406],"type":"Point"}
}