{
  "type": "Feature",
  "properties": {
    "gn:admin1_code":"10",
    "gn:asciiname":"Khowrdeh Cheshmeh",
    "gn:country_code":"IR",
    "gn:dem":938,
    "gn:feature_class":"P",
    "gn:feature_code":"PPL",
    "gn:name":"Khowrdeh Cheshmeh",
    "gn:population":0,
    "gn:timezone":"Asia/Tehran",
    "iso:country":"IR",
    "name:fas_x_preferred":[
        "\u062e\u0648\u064f\u0631\u062f\u0650\u0647 \u0686\u0650\u0634\u0645\u0650\u0647"
    ],
    "name:fas_x_variant":[
        "\u0686\u0634\u0645\u0647 \u062e\u0648\u0631\u062f\u0647",
        "\u062e\u064f\u0631\u062f\u0650\u0647 \u0686\u0650\u0634\u0645\u0650\u0647",
        "\u062e\u0648\u0631\u062f\u0650\u0647 \u0686\u0650\u0634\u0645\u0650\u0647",
        "\u062e\u0648\u0631\u062f\u0647 \u0686\u0634\u0645\u0647"
    ],
    "name:und_x_variant":[
        "Khordeh Cheshmeh",
        "Kh\u016brdeh Cheshmeh",
        "Khowrdeh Cheshmeh",
        "Cheshmeh Khvordeh"
    ],
    "wof:name":"Khowrdeh Cheshmeh",
    "wof:placetype":"locality"
},
  "geometry": {"coordinates":[47.1307,33.7357],"type":"Point"}
}