{
  "type": "Feature",
  "properties": {
    "gn:admin1_code":"7.0",
    "gn:asciiname":"Chah Gazi",
    "gn:country_code":"IR",
    "gn:dem":856,
    "gn:feature_class":"P",
    "gn:feature_code":"PPL",
    "gn:name":"Ch\u0101h Gaz\u012b",
    "gn:population":0,
    "gn:timezone":"Asia/Tehran",
    "iso:country":"IR",
    "name:fas_x_preferred":[
        "Ch\u0101h Gaz\u012b"
    ],
    "name:fas_x_variant":[
        "\u0686\u0627\u0647 \u06af\u0632\u06cc"
    ],
    "name:und_x_variant":[
        "\u0686\u0627\u0647 \u06af\u0632\u06cc"
    ],
    "wof:name":"Chah Gazi",
    "wof:placetype":"locality"
},
  "geometry": {"coordinates":[54.06836,28.22308],"type":"Point"}
}