{
  "type": "Feature",
  "properties": {
    "gn:admin1_code":"36",
    "gn:asciiname":"Jom`ehlu",
    "gn:country_code":"IR",
    "gn:dem":1469,
    "gn:feature_class":"P",
    "gn:feature_code":"PPL",
    "gn:name":"Jom\u2018ehl\u016b",
    "gn:population":0,
    "gn:timezone":"Asia/Tehran",
    "iso:country":"IR",
    "name:azb_x_preferred":[
        "\u062c\u0645\u0639\u0647 \u0644\u0648"
    ],
    "name:fas_x_preferred":[
        "\u062c\u064f\u0645\u0639\u0650\u0647\u0644\u0648"
    ],
    "name:fas_x_variant":[
        "\u062c\u0645\u0639\u0647 \u0644\u0648",
        "Jom\u2018ehl\u016b",
        "\u062c\u0645\u0639\u0647\u200c\u0644\u0648"
    ],
    "name:und_x_variant":[
        "Jum\u2018alu",
        "Dzhamlu"
    ],
    "wof:name":"Jom`ehlu",
    "wof:placetype":"locality"
},
  "geometry": {"coordinates":[48.18096,36.05942],"type":"Point"}
}