{
  "type": "Feature",
  "properties": {
    "gn:admin1_code":"42",
    "gn:asciiname":"Shurab",
    "gn:country_code":"IR",
    "gn:dem":1661,
    "gn:feature_class":"P",
    "gn:feature_code":"PPL",
    "gn:name":"Sh\u016br\u0101b",
    "gn:population":0,
    "gn:timezone":"Asia/Tehran",
    "iso:country":"IR",
    "name:fas_x_preferred":[
        "\u0634\u0648\u0631\u0627\u0628"
    ],
    "name:fas_x_variant":[
        "Sh\u016br\u0101b"
    ],
    "wof:name":"Shurab",
    "wof:placetype":"locality"
},
  "geometry": {"coordinates":[59.81059000000001,35.33622000000001],"type":"Point"}
}