{
  "type": "Feature",
  "properties": {
    "gn:admin1_code":"41",
    "gn:asciiname":"Bid Kaj",
    "gn:country_code":"IR",
    "gn:dem":2022,
    "gn:feature_class":"P",
    "gn:feature_code":"PPL",
    "gn:name":"B\u012bd Kaj",
    "gn:population":0,
    "gn:timezone":"Asia/Tehran",
    "iso:country":"IR",
    "name:ara_x_preferred":[
        "\u0628\u064a\u062f\u06a9\u062c"
    ],
    "name:fas_x_preferred":[
        "\u062f\u0631\u0648\u06cc\u0634 \u0622\u0628\u0627\u062f"
    ],
    "name:fas_x_variant":[
        "Darv\u012bsh\u0101b\u0101d",
        "\u0628\u06cc\u062f \u06a9\u062c",
        "\u0628\u06cc\u062f\u06a9\u062c"
    ],
    "name:msa_x_preferred":[
        "Bid Kaj"
    ],
    "name:und_x_variant":[
        "Derv\u012bsh\u0101b\u0101d",
        "B\u012bd Kaj"
    ],
    "wof:name":"Bid Kaj",
    "wof:placetype":"locality"
},
  "geometry": {"coordinates":[59.71948,32.7708],"type":"Point"}
}