{
  "type": "Feature",
  "properties": {
    "gn:admin1_code":"13",
    "gn:asciiname":"Zeyn od Din",
    "gn:country_code":"IR",
    "gn:dem":1602,
    "gn:feature_class":"P",
    "gn:feature_code":"PPL",
    "gn:name":"Zeyn od D\u012bn",
    "gn:population":0,
    "gn:timezone":"Asia/Tehran",
    "iso:country":"IR",
    "name:fas_x_preferred":[
        "\u0632\u06cc\u0646 \u0627\u0644\u062f\u0651\u06cc\u0646"
    ],
    "name:fas_x_variant":[
        "Zeyn od D\u012bn"
    ],
    "name:und_x_variant":[
        "Zeyn Ad D\u012bn"
    ],
    "wof:name":"Zeyn od Din",
    "wof:placetype":"locality"
},
  "geometry": {"coordinates":[47.1083,34.6953],"type":"Point"}
}