{
  "type": "Feature",
  "properties": {
    "gn:admin1_code":"15",
    "gn:asciiname":"Omm ol Khesey",
    "gn:cc2":"IR",
    "gn:country_code":"IR",
    "gn:dem":19,
    "gn:feature_class":"P",
    "gn:feature_code":"PPL",
    "gn:name":"Omm ol Khes\u0304ey",
    "gn:population":0,
    "gn:timezone":"Asia/Tehran",
    "iso:country":"IR",
    "name:fas_x_preferred":[
        "Omm ol Khes\u0304ey"
    ],
    "name:und_x_variant":[
        "Omm ol Khash\u0101-ye",
        "Omm Khos\u0304\u012b-ye \u2018Oly\u0101",
        "Omm Khos\u0304\u012b-ye B\u0101l\u0101",
        "Omm ol Khash\u0101-ye Vos\u0163a"
    ],
    "wof:name":"Omm ol Khesey",
    "wof:placetype":"locality"
},
  "geometry": {"coordinates":[49.46417,30.74639],"type":"Point"}
}