{
  "type": "Feature",
  "properties": {
    "gn:admin1_code":"23",
    "gn:asciiname":"Chahar Ab",
    "gn:country_code":"IR",
    "gn:dem":1304,
    "gn:feature_class":"P",
    "gn:feature_code":"PPL",
    "gn:name":"Chah\u0101r \u0100b",
    "gn:population":0,
    "gn:timezone":"Asia/Tehran",
    "iso:country":"IR",
    "name:fas_x_preferred":[
        "\u0686\u0647\u0627\u0631 \u0622\u0628"
    ],
    "name:fas_x_variant":[
        "Chah\u0101r \u0100b"
    ],
    "wof:name":"Chahar Ab",
    "wof:placetype":"locality"
},
  "geometry": {"coordinates":[47.81772,33.78932],"type":"Point"}
}