{
  "type": "Feature",
  "properties": {
    "gn:admin1_code":"16",
    "gn:asciiname":"Chopoqlu",
    "gn:country_code":"IR",
    "gn:dem":1603,
    "gn:feature_class":"P",
    "gn:feature_code":"PPL",
    "gn:name":"Chopoql\u016b",
    "gn:population":0,
    "gn:timezone":"Asia/Tehran",
    "iso:country":"IR",
    "name:fas_x_preferred":[
        "\u0686\u064f\u0628\u064f\u0642\u0644\u0648"
    ],
    "name:fas_x_variant":[
        "\u062c\u064e\u0628\u0648\u0643\u0621\u064e\u0644\u0648",
        "\u0686\u064e\u0628\u0642\u064f\u0644\u0648",
        "\u0686\u067e\u0642 \u0644\u0648",
        "Chopoql\u016b",
        "\u0686\u067e\u0642\u0644\u0648"
    ],
    "name:und_x_variant":[
        "Chabqol\u016b",
        "Choboql\u016b",
        "Jab\u016bk\u2019al\u016b"
    ],
    "wof:name":"Chopoqlu",
    "wof:placetype":"locality"
},
  "geometry": {"coordinates":[47.95975,35.89748],"type":"Point"}
}