{
  "type": "Feature",
  "properties": {
    "gn:admin1_code":"11",
    "gn:asciiname":"Tifakan-e Pa'in",
    "gn:country_code":"IR",
    "gn:dem":560,
    "gn:feature_class":"P",
    "gn:feature_code":"PPL",
    "gn:name":"T\u012bfak\u0101n-e P\u0101\u2019\u012bn",
    "gn:population":0,
    "gn:timezone":"Asia/Tehran",
    "iso:country":"IR",
    "name:ara_x_preferred":[
        "\u0637\u064a\u0641\u06a9\u0627\u0646"
    ],
    "name:ceb_x_preferred":[
        "T\u012bfak\u0101n-e P\u0101'\u012bn"
    ],
    "name:fas_x_preferred":[
        "\u0637\u064a\u0641\u0643\u0627\u0646"
    ],
    "name:fas_x_variant":[
        "\u0637\u064a\u0642\u064e\u0643\u0627\u0646",
        "\u062a\u06cc\u0641\u06a9\u0627\u0646 \u067e\u0627\u0626\u06cc\u0646",
        "\u0162\u012bfak\u0101n",
        "T\u012bfak\u0101n-e P\u0101\u2019\u012bn",
        "\u0637\u06cc\u0641\u06a9\u0627\u0646"
    ],
    "name:msa_x_preferred":[
        "Tifakan"
    ],
    "name:swe_x_preferred":[
        "T\u012bfak\u0101n-e P\u0101'\u012bn"
    ],
    "name:und_x_variant":[
        "Tikakun",
        "Tifk\u0101n",
        "Titakun",
        "\u0162\u012bqak\u0101n"
    ],
    "wof:name":"Tifakan-e Pa'in",
    "wof:placetype":"locality"
},
  "geometry": {"coordinates":[56.4605,27.7254],"type":"Point"}
}