{
  "type": "Feature",
  "properties": {
    "gn:admin1_code":"43",
    "gn:asciiname":"Rahimabad",
    "gn:country_code":"IR",
    "gn:dem":1128,
    "gn:feature_class":"P",
    "gn:feature_code":"PPL",
    "gn:name":"Ra\u1e29\u012bm\u0101b\u0101d",
    "gn:population":0,
    "gn:timezone":"Asia/Tehran",
    "iso:country":"IR",
    "name:fas_x_preferred":[
        "Ra\u1e29\u012bm\u0101b\u0101d"
    ],
    "name:fas_x_variant":[
        "\u0631\u062d\u06cc\u0645 \u0622\u0628\u0627\u062f"
    ],
    "wof:name":"Rahimabad",
    "wof:placetype":"locality"
},
  "geometry": {"coordinates":[57.37439000000001,37.05778],"type":"Point"}
}