{
  "type": "Feature",
  "properties": {
    "gn:admin1_code":"32",
    "gn:asciiname":"Keshab",
    "gn:country_code":"IR",
    "gn:dem":1489,
    "gn:feature_class":"P",
    "gn:feature_code":"PPL",
    "gn:name":"Kesh\u0101b",
    "gn:population":0,
    "gn:timezone":"Asia/Tehran",
    "iso:country":"IR",
    "name:fas_x_preferred":[
        "\u0643\u0634\u0627\u0628"
    ],
    "name:fas_x_variant":[
        "Kesh\u0101b"
    ],
    "name:und_x_variant":[
        "Kash\u0101b"
    ],
    "wof:name":"Keshab",
    "wof:placetype":"locality"
},
  "geometry": {"coordinates":[48.32115,37.3115],"type":"Point"}
}