{
  "type": "Feature",
  "properties": {
    "gn:admin1_code":"34.0",
    "gn:asciiname":"Ab Barik",
    "gn:country_code":"IR",
    "gn:dem":2103,
    "gn:feature_class":"P",
    "gn:feature_code":"PPL",
    "gn:name":"\u0100b B\u0101r\u012bk",
    "gn:population":0,
    "gn:timezone":"Asia/Tehran",
    "iso:country":"IR",
    "name:fas_x_preferred":[
        "\u0622\u0628 \u0628\u0627\u0631\u06cc\u06a9"
    ],
    "name:fas_x_variant":[
        "\u0622\u0628\u0650 \u0628\u0627\u0631\u064a\u0643",
        "\u0100b B\u0101r\u012bk",
        "\u0627\u0628\u0628\u0627\u0631\u06cc\u06a9"
    ],
    "name:und_x_variant":[
        "\u0100b-e B\u0101r\u012bk"
    ],
    "wof:name":"Ab Barik",
    "wof:placetype":"locality"
},
  "geometry": {"coordinates":[49.6364,33.80699],"type":"Point"}
}