{
  "type": "Feature",
  "properties": {
    "gn:admin1_code":"5",
    "gn:asciiname":"Kun Mishi",
    "gn:country_code":"IR",
    "gn:dem":1114,
    "gn:feature_class":"P",
    "gn:feature_code":"PPL",
    "gn:name":"K\u016bn M\u012bsh\u012b",
    "gn:population":0,
    "gn:timezone":"Asia/Tehran",
    "iso:country":"IR",
    "name:fas_x_preferred":[
        "\u0643\u0648\u0647 \u0645\u064a\u0634\u06cc"
    ],
    "name:fas_x_variant":[
        "K\u016bh M\u012bsh\u012b",
        "K\u016bh M\u012bsh M\u012br\u016b",
        "\u06a9\u0648\u0647 \u0645\u06cc\u0634 \u0645\u06cc\u0631\u0648",
        "\u0643\u0648\u0646 \u0645\u064a\u0634\u06cc",
        "\u0686\u0634\u0645\u0647 \u0642\u0646\u062f\u06cc"
    ],
    "name:und_x_variant":[
        "\u06a9\u0648\u0647 \u0645\u06cc\u0634 \u0645\u06cc\u0631\u0648",
        "K\u016bn M\u012bsh\u012b",
        "Cheshmeh Qand\u012b"
    ],
    "wof:name":"Kun Mishi",
    "wof:placetype":"locality"
},
  "geometry": {"coordinates":[50.54726,31.15549],"type":"Point"}
}