{
  "type": "Feature",
  "properties": {
    "gn:admin1_code":"11",
    "gn:asciiname":"`Aliabad-e Siahu",
    "gn:country_code":"IR",
    "gn:dem":638,
    "gn:feature_class":"P",
    "gn:feature_code":"PPL",
    "gn:name":"\u2018Al\u012b\u0101b\u0101d-e S\u012b\u0101h\u016b",
    "gn:population":0,
    "gn:timezone":"Asia/Tehran",
    "iso:country":"IR",
    "name:fas_x_preferred":[
        "\u0639\u0644\u06cc \u0622\u0628\u0627\u062f \u0633\u06cc\u0627\u0647\u0648"
    ],
    "name:fas_x_variant":[
        "\u2018Al\u012b\u0101b\u0101d-e S\u012b\u0101h\u016b"
    ],
    "wof:name":"`Aliabad-e Siahu",
    "wof:placetype":"locality"
},
  "geometry": {"coordinates":[56.3299,27.7573],"type":"Point"}
}