{
  "type": "Feature",
  "properties": {
    "gn:admin1_code":"15",
    "gn:asciiname":"Sar Takht-e Do Rahan",
    "gn:cc2":"IR",
    "gn:country_code":"IR",
    "gn:dem":1140,
    "gn:feature_class":"P",
    "gn:feature_code":"PPL",
    "gn:name":"Sar Takht-e Do R\u0101h\u0101n",
    "gn:population":0,
    "gn:timezone":"Asia/Tehran",
    "iso:country":"IR",
    "name:ara_x_preferred":[
        "\u0633\u0631\u062a\u062e\u062a \u062f\u0648\u0631\u0627\u0647\u0627\u0646"
    ],
    "name:azb_x_preferred":[
        "\u0633\u0631\u062a\u062e\u062a \u062f\u0648\u0631\u0627\u0647\u0627\u0646(\u0627\u0646\u062f\u06cc\u0645\u0634\u06a9)"
    ],
    "name:fas_x_preferred":[
        "Sar Takht-e Do R\u0101h\u0101n"
    ],
    "name:fas_x_variant":[
        "\u0633\u0631\u062a\u062e\u062a \u062f\u0648\u0631\u0627\u0647\u0627\u0646"
    ],
    "name:und_x_variant":[
        "Sar Takht",
        "Sar Takht-e D\u016br\u0101h\u0101n"
    ],
    "wof:name":"Sar Takht-e Do Rahan",
    "wof:placetype":"locality"
},
  "geometry": {"coordinates":[48.30194,32.86528],"type":"Point"}
}