{
  "type": "Feature",
  "properties": {
    "gn:admin1_code":"23",
    "gn:asciiname":"Sharafabad",
    "gn:country_code":"IR",
    "gn:dem":1453,
    "gn:feature_class":"P",
    "gn:feature_code":"PPL",
    "gn:name":"Sharaf\u0101b\u0101d",
    "gn:population":0,
    "gn:timezone":"Asia/Tehran",
    "iso:country":"IR",
    "name:fas_x_preferred":[
        "\u0634\u064e\u0631\u064e\u0641 \u0622\u0628\u0627\u062f"
    ],
    "name:fas_x_variant":[
        "Sharaf\u0101b\u0101d",
        "\u0634\u0631\u0641\u200c\u0622\u0628\u0627\u062f"
    ],
    "wof:name":"Sharafabad",
    "wof:placetype":"locality"
},
  "geometry": {"coordinates":[47.61667,33.65],"type":"Point"}
}