{
  "type": "Feature",
  "properties": {
    "gn:admin1_code":"4.0",
    "gn:asciiname":"Mazra`eh-ye Khukan",
    "gn:country_code":"IR",
    "gn:dem":561,
    "gn:feature_class":"P",
    "gn:feature_code":"PPL",
    "gn:name":"Mazra\u2018eh-ye Kh\u016bk\u0101n",
    "gn:population":0,
    "gn:timezone":"Asia/Tehran",
    "iso:country":"IR",
    "name:fas_x_preferred":[
        "Mazra\u2018eh-ye Khowk\u0101n"
    ],
    "name:fas_x_variant":[
        "\u0645\u0632\u0631\u0639\u0647 \u062e\u0648\u06a9\u0627\u0646",
        "\u0645\u0648\u0631\u06a9\u0627\u0646"
    ],
    "name:und_x_variant":[
        "Mazra\u2018eh-ye Kh\u016bk\u0101n",
        "M\u016brk\u0101n"
    ],
    "wof:name":"Mazra`eh-ye Khukan",
    "wof:placetype":"locality"
},
  "geometry": {"coordinates":[59.24211,26.86258],"type":"Point"}
}