{
  "type": "Feature",
  "properties": {
    "gn:admin1_code":"15",
    "gn:asciiname":"Darreh Chineh",
    "gn:country_code":"IR",
    "gn:dem":787,
    "gn:feature_class":"P",
    "gn:feature_code":"PPL",
    "gn:name":"Darreh Ch\u012bneh",
    "gn:population":0,
    "gn:timezone":"Asia/Tehran",
    "iso:country":"IR",
    "name:azb_x_preferred":[
        "\u062f\u0631\u0647 \u0686\u06cc\u0646\u0647(\u0627\u06cc\u0630\u0647)"
    ],
    "name:fas_x_preferred":[
        "Darreh Ch\u012bneh"
    ],
    "name:fas_x_variant":[
        "\u062f\u0631\u0651\u0647 \u0686\u06cc\u0646\u0647",
        "\u062f\u0631\u0647 \u0686\u06cc\u0646\u0647"
    ],
    "name:und_x_variant":[
        "Darreh Ch\u012bneh-ye P\u0101\u2019\u012bn",
        "Darreh Ch\u012bneh Two"
    ],
    "wof:name":"Darreh Chineh",
    "wof:placetype":"locality"
},
  "geometry": {"coordinates":[50.0481,31.90684000000001],"type":"Point"}
}