{
  "type": "Feature",
  "properties": {
    "gn:admin1_code":"42",
    "gn:asciiname":"Beheshtabad",
    "gn:country_code":"IR",
    "gn:dem":1238,
    "gn:feature_class":"P",
    "gn:feature_code":"PPLF",
    "gn:name":"Behesht\u0101b\u0101d",
    "gn:population":0,
    "gn:timezone":"Asia/Tehran",
    "iso:country":"IR",
    "name:fas_x_preferred":[
        "Behesht\u0101b\u0101d"
    ],
    "name:fas_x_variant":[
        "\u0628\u0647\u0634\u062a \u0622\u0628\u0627\u062f"
    ],
    "wof:name":"Beheshtabad",
    "wof:placetype":"locality"
},
  "geometry": {"coordinates":[57.18557,33.89685],"type":"Point"}
}