{
  "type": "Feature",
  "properties": {
    "gn:admin1_code":"32",
    "gn:asciiname":"Qal`ehcheh",
    "gn:country_code":"IR",
    "gn:dem":1693,
    "gn:feature_class":"P",
    "gn:feature_code":"PPL",
    "gn:name":"Qal\u2018ehcheh",
    "gn:population":0,
    "gn:timezone":"Asia/Tehran",
    "iso:country":"IR",
    "name:ara_x_preferred":[
        "\u0642\u0644\u064a\u062a\u0634\u064a"
    ],
    "name:ceb_x_preferred":[
        "Qal\u2018ehcheh"
    ],
    "name:fas_x_preferred":[
        "\u0642\u0650\u0644\u064a\u0686\u06cc"
    ],
    "name:fas_x_variant":[
        "\u0642\u0644\u0639\u0647 \u0686\u0647",
        "Qel\u012bch\u012b",
        "Qal\u2018ehcheh",
        "\u0642\u0644\u06cc\u0686\u06cc"
    ],
    "name:msa_x_preferred":[
        "Qelichi"
    ],
    "wof:name":"Qal`ehcheh",
    "wof:placetype":"locality"
},
  "geometry": {"coordinates":[48.2257,38.1002],"type":"Point"}
}