{
  "type": "Feature",
  "properties": {
    "gn:admin1_code":"4.0",
    "gn:asciiname":"Deh-e Qajar",
    "gn:country_code":"IR",
    "gn:dem":480,
    "gn:feature_class":"P",
    "gn:feature_code":"PPL",
    "gn:name":"Deh-e Qajar",
    "gn:population":0,
    "gn:timezone":"Asia/Tehran",
    "iso:country":"IR",
    "name:fas_x_preferred":[
        "\u062f\u0647 \u0642\u062c\u0631"
    ],
    "name:und_x_variant":[
        "Qajar",
        "Deh Qajar",
        "Deh-e Qajar"
    ],
    "wof:name":"Deh-e Qajar",
    "wof:placetype":"locality"
},
  "geometry": {"coordinates":[61.7644,31.1738],"type":"Point"}
}