{
  "type": "Feature",
  "properties": {
    "gn:admin1_code":"28.0",
    "gn:asciiname":"Shahr Bazi",
    "gn:country_code":"IR",
    "gn:dem":2212,
    "gn:feature_class":"P",
    "gn:feature_code":"PPL",
    "gn:name":"Shahr B\u0101z\u012b",
    "gn:population":0,
    "gn:timezone":"Asia/Tehran",
    "iso:country":"IR",
    "name:fas_x_preferred":[
        "Shahr B\u0101z\u012b"
    ],
    "name:fas_x_variant":[
        "\u0634\u0647\u0631 \u0628\u0627\u0632\u06cc"
    ],
    "name:und_x_variant":[
        "\u0634\u0647\u0631 \u0628\u0627\u0632\u06cc"
    ],
    "wof:name":"Shahr Bazi",
    "wof:placetype":"locality"
},
  "geometry": {"coordinates":[51.92904,31.6658],"type":"Point"}
}