{
  "type": "Feature",
  "properties": {
    "gn:admin1_code":"11.0",
    "gn:asciiname":"Anjireh",
    "gn:country_code":"IR",
    "gn:dem":218,
    "gn:feature_class":"P",
    "gn:feature_code":"PPL",
    "gn:name":"Anj\u012breh",
    "gn:population":0,
    "gn:timezone":"Asia/Tehran",
    "iso:country":"IR",
    "name:fas_x_preferred":[
        "Anj\u012breh"
    ],
    "name:fas_x_variant":[
        "\u0627\u0646\u062c\u064a\u0631\u0647",
        "\u0627\u0646\u062c\u06cc\u0631\u0647"
    ],
    "name:msa_x_preferred":[
        "Anjireh"
    ],
    "name:und_x_variant":[
        "Anj\u012br",
        "\u0627\u0646\u062c\u064a\u0631\u0647"
    ],
    "wof:name":"Anjireh",
    "wof:placetype":"locality"
},
  "geometry": {"coordinates":[54.80313,26.99909],"type":"Point"}
}