{
  "type": "Feature",
  "properties": {
    "gn:admin1_code":"15",
    "gn:asciiname":"`Eyna Shehamiyeh",
    "gn:country_code":"IR",
    "gn:dem":125,
    "gn:feature_class":"P",
    "gn:feature_code":"PPL",
    "gn:name":"\u2018Eyna She\u1e29am\u012byeh",
    "gn:population":0,
    "gn:timezone":"Asia/Tehran",
    "iso:country":"IR",
    "name:fas_x_preferred":[
        "\u2018Eyna She\u1e29am\u012byeh"
    ],
    "name:und_x_variant":[
        "\u2018Eyn"
    ],
    "wof:name":"`Eyna Shehamiyeh",
    "wof:placetype":"locality"
},
  "geometry": {"coordinates":[49.54972,31.28389],"type":"Point"}
}