{
  "type": "Feature",
  "properties": {
    "gn:admin1_code":"29.0",
    "gn:asciiname":"Ab-e Dasht",
    "gn:country_code":"IR",
    "gn:dem":2056,
    "gn:feature_class":"P",
    "gn:feature_code":"PPLF",
    "gn:name":"\u0100b-e Dasht",
    "gn:population":0,
    "gn:timezone":"Asia/Tehran",
    "iso:country":"IR",
    "name:fas_x_preferred":[
        "\u0100b-e Dasht"
    ],
    "name:fas_x_variant":[
        "\u0622\u0628 \u062f\u0634\u062a"
    ],
    "name:und_x_variant":[
        "\u0622\u0628 \u062f\u0634\u062a"
    ],
    "wof:name":"Ab-e Dasht",
    "wof:placetype":"locality"
},
  "geometry": {"coordinates":[56.61778,30.49999],"type":"Point"}
}