{
  "type": "Feature",
  "properties": {
    "gn:admin1_code":"41.0",
    "gn:asciiname":"Damdameh",
    "gn:country_code":"IR",
    "gn:dem":1637,
    "gn:feature_class":"P",
    "gn:feature_code":"PPL",
    "gn:name":"D\u0101md\u0101meh",
    "gn:population":0,
    "gn:timezone":"Asia/Tehran",
    "iso:country":"IR",
    "name:fas_x_preferred":[
        "\u062f\u0627\u0645\u062f\u0627\u0645\u0647"
    ],
    "name:fas_x_variant":[
        "D\u0101md\u0101meh"
    ],
    "wof:name":"Damdameh",
    "wof:placetype":"locality"
},
  "geometry": {"coordinates":[60.3353,32.4934],"type":"Point"}
}