{
  "type": "Feature",
  "properties": {
    "gn:admin1_code":"5.0",
    "gn:asciiname":"Chehel Dokhtari",
    "gn:country_code":"IR",
    "gn:dem":1374,
    "gn:feature_class":"P",
    "gn:feature_code":"PPL",
    "gn:name":"Chehel Dokhtar\u012b",
    "gn:population":0,
    "gn:timezone":"Asia/Tehran",
    "iso:country":"IR",
    "name:fas_x_preferred":[
        "Chehel Dokhtar\u012b"
    ],
    "name:fas_x_variant":[
        "\u0686\u0647\u0644 \u062f\u062e\u062a\u0631\u06cc"
    ],
    "wof:name":"Chehel Dokhtari",
    "wof:placetype":"locality"
},
  "geometry": {"coordinates":[50.5912,31.1758],"type":"Point"}
}