{
  "type": "Feature",
  "properties": {
    "gn:admin1_code":"23",
    "gn:asciiname":"Marzian",
    "gn:country_code":"IR",
    "gn:dem":1904,
    "gn:feature_class":"P",
    "gn:feature_code":"PPL",
    "gn:name":"Marz\u012b\u0101n",
    "gn:population":0,
    "gn:timezone":"Asia/Tehran",
    "iso:country":"IR",
    "name:ceb_x_preferred":[
        "Marz\u012b\u0101n"
    ],
    "name:fas_x_preferred":[
        "\u0645\u0631\u0632\u06cc\u0627\u0646"
    ],
    "name:fas_x_variant":[
        "\u0645\u064e\u0631\u0632\u0650\u064a\u0627\u0646",
        "\u0645\u064e\u0631\u0632\u064a\u064e\u0651\u0646",
        "Marz\u012b\u0101n"
    ],
    "name:swe_x_preferred":[
        "Marz\u012b\u0101n"
    ],
    "name:und_x_variant":[
        "Marzey\u0101n",
        "Marz\u012byan"
    ],
    "wof:name":"Marzian",
    "wof:placetype":"locality"
},
  "geometry": {"coordinates":[49.51077,33.53678],"type":"Point"}
}