{
  "type": "Feature",
  "properties": {
    "gn:admin1_code":"8",
    "gn:asciiname":"Charudeh",
    "gn:country_code":"IR",
    "gn:dem":955,
    "gn:feature_class":"P",
    "gn:feature_code":"PPL",
    "gn:name":"Char\u016bdeh",
    "gn:population":0,
    "gn:timezone":"Asia/Tehran",
    "iso:country":"IR",
    "name:ceb_x_preferred":[
        "Charvadeh-e P\u0101\u2018\u012bn"
    ],
    "name:fas_x_preferred":[
        "\u0686\u0631\u0648\u062f\u0647 \u067e\u0627\u0626\u06cc\u0646"
    ],
    "name:fas_x_variant":[
        "\u0686\u0631\u0648\u062f\u0647",
        "\u0686\u0631\u0648\u062f\u0647 \u0628\u0627\u0644\u0627"
    ],
    "name:msa_x_preferred":[
        "Charvadeh"
    ],
    "name:swe_x_preferred":[
        "Charvadeh-e P\u0101\u2018\u012bn"
    ],
    "name:ukr_x_preferred":[
        "\u0427\u0430\u0440\u0432\u0430\u0434\u0435\u0433"
    ],
    "name:und_x_variant":[
        "Cher\u016b Deh",
        "Charvadeh",
        "Charvadeh-e P\u0101\u2019\u012bn",
        "Char\u016bdeh",
        "Charvadeh-e B\u0101l\u0101",
        "Char\u016bdeh-e B\u0101l\u0101",
        "Char\u016bdeh-e P\u0101\u2019\u012bn"
    ],
    "wof:name":"Charudeh",
    "wof:placetype":"locality"
},
  "geometry": {"coordinates":[48.85569,37.54744],"type":"Point"}
}