{
  "type": "Feature",
  "properties": {
    "gn:admin1_code":"15",
    "gn:asciiname":"Bukhameh-ye Sofla",
    "gn:country_code":"IR",
    "gn:dem":21,
    "gn:feature_class":"P",
    "gn:feature_code":"PPL",
    "gn:name":"B\u016bkh\u0101meh-ye Sofl\u00e1",
    "gn:population":0,
    "gn:timezone":"Asia/Tehran",
    "iso:country":"IR",
    "name:ceb_x_preferred":[
        "B\u016bkh\u0101meh-ye Sofl\u00e1"
    ],
    "name:fas_x_preferred":[
        "\u0628\u0648\u062e\u0627\u0645\u0647 \u0633\u0641\u0644\u06cc"
    ],
    "name:fas_x_variant":[
        "Volkh\u0101meh-ye p\u0101\u2019\u012bn",
        "Valkh\u0101meh-ye P\u0101\u2019\u012bn",
        "D\u016bby\u0101n",
        "Vikh\u0101ma",
        "B\u016bkh\u0101meh-ye P\u0101\u2019\u012bn",
        "Vakh\u0101meh",
        "Valkh\u0101mah-e Sofl\u00e1",
        "B\u016bkh\u0101meh-ye Sofl\u00e1"
    ],
    "name:swe_x_preferred":[
        "B\u016bkh\u0101meh-ye Sofl\u00e1"
    ],
    "name:und_x_variant":[
        "B\u016bkh\u0101meh",
        "Safhaw"
    ],
    "wof:name":"Bukhameh-ye Sofla",
    "wof:placetype":"locality"
},
  "geometry": {"coordinates":[49.33744,30.85527],"type":"Point"}
}