{
  "type": "Feature",
  "properties": {
    "gn:admin1_code":"8",
    "gn:asciiname":"Masihabad-e Mir Daryasar",
    "gn:country_code":"IR",
    "gn:dem":-9,
    "gn:feature_class":"P",
    "gn:feature_code":"PPL",
    "gn:name":"Mas\u012b\u1e29\u0101b\u0101d-e M\u012br Dary\u0101sar",
    "gn:population":0,
    "gn:timezone":"Asia/Tehran",
    "iso:country":"IR",
    "name:ceb_x_preferred":[
        "M\u012br Dary\u0101sar"
    ],
    "name:fas_x_preferred":[
        "M\u012br Dary\u0101sar"
    ],
    "name:fas_x_variant":[
        "\u0645\u06cc\u0631 \u062f\u0631\u06cc\u0627\u0633\u0631",
        "\u0645\u0633\u06cc\u062d \u0622\u0628\u0627\u062f \u0645\u06cc\u0631 \u062f\u0631\u06cc\u0627\u0633\u0631",
        "\u0645\u06cc\u0631\u062f\u0631\u06cc\u0627\u0633\u0631"
    ],
    "name:msa_x_preferred":[
        "Mir Daryasar"
    ],
    "name:swe_x_preferred":[
        "M\u012br Dary\u0101sar"
    ],
    "name:ukr_x_preferred":[
        "\u041c\u0456\u0440-\u0414\u0430\u0440'\u044f\u0441\u0430\u0440"
    ],
    "name:und_x_variant":[
        "Mas\u012b\u1e29\u0101b\u0101d-e M\u012br Dary\u0101sar"
    ],
    "wof:name":"Masihabad-e Mir Daryasar",
    "wof:placetype":"locality"
},
  "geometry": {"coordinates":[50.18149,37.26836],"type":"Point"}
}