{
  "type": "Feature",
  "properties": {
    "gn:admin1_code":"33",
    "gn:asciiname":"Qujur",
    "gn:country_code":"IR",
    "gn:dem":1907,
    "gn:feature_class":"P",
    "gn:feature_code":"PPL",
    "gn:name":"Q\u016bj\u016br",
    "gn:population":0,
    "gn:timezone":"Asia/Tehran",
    "iso:country":"IR",
    "name:fas_x_preferred":[
        "\u0642\u0648\u062c\u0648\u0631"
    ],
    "name:fas_x_variant":[
        "Q\u016bj\u016br"
    ],
    "name:msa_x_preferred":[
        "Qujur"
    ],
    "wof:name":"Qujur",
    "wof:placetype":"locality"
},
  "geometry": {"coordinates":[46.7206,37.5453],"type":"Point"}
}