{
  "type": "Feature",
  "properties": {
    "gn:admin1_code":"15",
    "gn:asciiname":"Seyyed Hoseyn",
    "gn:country_code":"IR",
    "gn:dem":55,
    "gn:feature_class":"P",
    "gn:feature_code":"PPL",
    "gn:name":"Seyyed \u1e28oseyn",
    "gn:population":0,
    "gn:timezone":"Asia/Tehran",
    "iso:country":"IR",
    "name:fas_x_preferred":[
        "\u0633\u06cc\u062f \u062d\u0633\u0646"
    ],
    "wof:name":"Seyyed Hoseyn",
    "wof:placetype":"locality"
},
  "geometry": {"coordinates":[48.46667,32.06667],"type":"Point"}
}