{
  "type": "Feature",
  "properties": {
    "gn:admin1_code":"13",
    "gn:asciiname":"Vizheh",
    "gn:country_code":"IR",
    "gn:dem":1639,
    "gn:feature_class":"P",
    "gn:feature_code":"PPL",
    "gn:name":"V\u012bzheh",
    "gn:population":0,
    "gn:timezone":"Asia/Tehran",
    "iso:country":"IR",
    "name:ceb_x_preferred":[
        "V\u012bzheh"
    ],
    "name:fas_x_preferred":[
        "\u0648\u06cc\u0698\u0647"
    ],
    "name:fas_x_variant":[
        "V\u012bzheh"
    ],
    "name:swe_x_preferred":[
        "V\u012bzheh"
    ],
    "name:und_x_variant":[
        "V\u012bzhah"
    ],
    "wof:name":"Vizheh",
    "wof:placetype":"locality"
},
  "geometry": {"coordinates":[47.1974,34.9102],"type":"Point"}
}