{
  "type": "Feature",
  "properties": {
    "gn:admin1_code":"32",
    "gn:asciiname":"Bijaq",
    "gn:country_code":"IR",
    "gn:dem":1148,
    "gn:feature_class":"P",
    "gn:feature_code":"PPL",
    "gn:name":"B\u012bjaq",
    "gn:population":0,
    "gn:timezone":"Asia/Tehran",
    "iso:country":"IR",
    "name:ceb_x_preferred":[
        "B\u012bjaq"
    ],
    "name:fas_x_preferred":[
        "\u0628\u064a\u062c\u0642"
    ],
    "name:fas_x_variant":[
        "B\u012bjaq",
        "\u0628\u06cc\u062c\u0642"
    ],
    "name:msa_x_preferred":[
        "Bijaq"
    ],
    "name:mzn_x_preferred":[
        "\u0628\u06cc\u062c\u0642"
    ],
    "name:swe_x_preferred":[
        "B\u012bjaq"
    ],
    "name:und_x_variant":[
        "Bey\u1e29aq"
    ],
    "wof:name":"Bijaq",
    "wof:placetype":"locality"
},
  "geometry": {"coordinates":[47.7041,38.4796],"type":"Point"}
}