{
  "type": "Feature",
  "properties": {
    "gn:admin1_code":"5.0",
    "gn:asciiname":"Sherang Rang",
    "gn:country_code":"IR",
    "gn:dem":2093,
    "gn:feature_class":"P",
    "gn:feature_code":"PPL",
    "gn:name":"Sherang Rang",
    "gn:population":0,
    "gn:timezone":"Asia/Tehran",
    "iso:country":"IR",
    "name:fas_x_preferred":[
        "\u0634\u0631\u0646\u06af \u0631\u0646\u06af"
    ],
    "name:fas_x_variant":[
        "\u0634\u0631\u0646\u06af \u0631\u0646\u06af \u0645\u0648\u0631 \u0632\u0631\u062f"
    ],
    "name:und_x_variant":[
        "Sherang Rang Mowr-e Zard"
    ],
    "wof:name":"Sherang Rang",
    "wof:placetype":"locality"
},
  "geometry": {"coordinates":[50.75271,31.25582],"type":"Point"}
}