{
  "type": "Feature",
  "properties": {
    "gn:admin1_code":"43",
    "gn:asciiname":"Qarah Kanlu",
    "gn:country_code":"IR",
    "gn:dem":747,
    "gn:feature_class":"P",
    "gn:feature_code":"PPL",
    "gn:name":"Qarah K\u0101nl\u016b",
    "gn:population":0,
    "gn:timezone":"Asia/Tehran",
    "iso:country":"IR",
    "name:fas_x_preferred":[
        "Qarah K\u0101nl\u016b"
    ],
    "name:fas_x_variant":[
        "\u0642\u0631\u0647 \u06a9\u0627\u0646\u0644\u0648"
    ],
    "name:und_x_variant":[
        "\u0642\u0631\u0647 \u06a9\u0627\u0646\u0644\u0648"
    ],
    "wof:name":"Qarah Kanlu",
    "wof:placetype":"locality"
},
  "geometry": {"coordinates":[57.14597,37.73356],"type":"Point"}
}