{
  "type": "Feature",
  "properties": {
    "gn:admin1_code":"33",
    "gn:asciiname":"Gol",
    "gn:country_code":"IR",
    "gn:dem":1695,
    "gn:feature_class":"P",
    "gn:feature_code":"PPL",
    "gn:name":"Gol",
    "gn:population":0,
    "gn:timezone":"Asia/Tehran",
    "iso:country":"IR",
    "name:fas_x_preferred":[
        "\u06af\u0644"
    ],
    "wof:name":"Gol",
    "wof:placetype":"locality"
},
  "geometry": {"coordinates":[46.3815,37.3015],"type":"Point"}
}