{
  "type": "Feature",
  "properties": {
    "gn:admin1_code":"15",
    "gn:asciiname":"Hamidani",
    "gn:country_code":"IR",
    "gn:dem":9,
    "gn:feature_class":"P",
    "gn:feature_code":"PPL",
    "gn:name":"\u1e28am\u012bd\u0101n\u012b",
    "gn:population":0,
    "gn:timezone":"Asia/Tehran",
    "iso:country":"IR",
    "name:fas_x_preferred":[
        "\u1e28am\u012bd\u0101n\u012b"
    ],
    "wof:name":"Hamidani",
    "wof:placetype":"locality"
},
  "geometry": {"coordinates":[47.91667,31.71667],"type":"Point"}
}