{
  "type": "Feature",
  "properties": {
    "gn:admin1_code":"35.0",
    "gn:asciiname":"Kian",
    "gn:country_code":"IR",
    "gn:dem":1897,
    "gn:feature_class":"P",
    "gn:feature_code":"PPL",
    "gn:name":"K\u012b\u0101n",
    "gn:population":0,
    "gn:timezone":"Asia/Tehran",
    "iso:country":"IR",
    "name:ara_x_preferred":[
        "\u0645\u062f\u064a\u0646\u0629 \u0643\u064a\u0627\u0646"
    ],
    "name:aze_x_preferred":[
        "Kiyan"
    ],
    "name:fas_x_preferred":[
        "\u06a9\u06cc\u0627\u0646"
    ],
    "name:fas_x_variant":[
        "\u0643\u064a\u0627\u0646 \u062f\u0650\u0647",
        "K\u012b\u0101n"
    ],
    "name:ita_x_preferred":[
        "Kian"
    ],
    "name:mlg_x_preferred":[
        "Kian"
    ],
    "name:msa_x_preferred":[
        "Shahr-e K\u012b\u0101n"
    ],
    "name:rus_x_preferred":[
        "\u041a\u0438\u0430\u043d"
    ],
    "name:tur_x_preferred":[
        "Kiyan"
    ],
    "name:und_x_variant":[
        "K\u012b\u0101n Deh"
    ],
    "name:urd_x_preferred":[
        "\u0634\u06c1\u0631 \u06a9\u06cc\u0627\u0646"
    ],
    "wof:name":"Kian",
    "wof:placetype":"locality"
},
  "geometry": {"coordinates":[52.21451,36.05641],"type":"Point"}
}