{
  "type": "Feature",
  "properties": {
    "gn:admin1_code":"1",
    "gn:asciiname":"Tizkharab",
    "gn:country_code":"IR",
    "gn:dem":1389,
    "gn:feature_class":"P",
    "gn:feature_code":"PPL",
    "gn:name":"T\u012bzkhar\u0101b",
    "gn:population":0,
    "gn:timezone":"Asia/Tehran",
    "iso:country":"IR",
    "name:fas_x_preferred":[
        "\u062a\u064a\u0632\u062e\u064e\u0631\u0627\u0628"
    ],
    "name:fas_x_variant":[
        "\u062a\u06cc\u0632\u062e\u0631\u0627\u0628",
        "T\u012bzkhar\u0101b"
    ],
    "wof:name":"Tizkharab",
    "wof:placetype":"locality"
},
  "geometry": {"coordinates":[44.9856,37.6251],"type":"Point"}
}