{
  "type": "Feature",
  "properties": {
    "gn:admin1_code":"16",
    "gn:asciiname":"Kacheh Gonbad-e Mir Tash",
    "gn:country_code":"IR",
    "gn:dem":1832,
    "gn:feature_class":"P",
    "gn:feature_code":"PPL",
    "gn:name":"Kacheh Gonbad-e M\u012br T\u0101sh",
    "gn:population":0,
    "gn:timezone":"Asia/Tehran",
    "iso:country":"IR",
    "name:fas_x_preferred":[
        "\u06af\u0686\u0647 \u06af\u0646\u0628\u062f"
    ],
    "name:fas_x_variant":[
        "\u0643\u0686\u0647 \u06af\u0646\u0628\u062f",
        "\u06af\u064e\u0686\u0650\u0647 \u06af\u064f\u0646\u0628\u064e\u062f",
        "\u06a9\u0686\u0647 \u06af\u0646\u0628\u062f \u0645\u06cc\u0631 \u062a\u0627\u0634"
    ],
    "name:und_x_variant":[
        "Kacheh Gonbad",
        "Gacheh Gunb\u0101d",
        "Gacheh Gonbad",
        "Gecheh Gonbad",
        "Kacheh Gonbad-e M\u012br T\u0101sh"
    ],
    "wof:name":"Kacheh Gonbad-e Mir Tash",
    "wof:placetype":"locality"
},
  "geometry": {"coordinates":[47.99255,35.71120999999999],"type":"Point"}
}