{
  "type": "Feature",
  "properties": {
    "gn:admin1_code":"29.0",
    "gn:asciiname":"Zey Bandan",
    "gn:country_code":"IR",
    "gn:dem":2178,
    "gn:feature_class":"P",
    "gn:feature_code":"PPL",
    "gn:name":"Zey Band\u0101n",
    "gn:population":0,
    "gn:timezone":"Asia/Tehran",
    "iso:country":"IR",
    "name:fas_x_preferred":[
        "\u0632\u06cc \u0628\u0646\u062f\u0627\u0646"
    ],
    "name:und_x_variant":[
        "Zey Band\u0101n"
    ],
    "wof:name":"Zey Bandan",
    "wof:placetype":"locality"
},
  "geometry": {"coordinates":[55.05411,30.504],"type":"Point"}
}