{
  "type": "Feature",
  "properties": {
    "gn:admin1_code":"4",
    "gn:asciiname":"Zebring",
    "gn:country_code":"IR",
    "gn:dem":612,
    "gn:feature_class":"P",
    "gn:feature_code":"PPL",
    "gn:name":"Zebr\u012bng",
    "gn:population":0,
    "gn:timezone":"Asia/Tehran",
    "iso:country":"IR",
    "name:fas_x_preferred":[
        "\u0632\u0628\u0631\u0646\u06af"
    ],
    "name:fas_x_variant":[
        "Zebr\u012bng",
        "\u0632\u0628\u0631\u06cc\u0646\u06af",
        "\u0632\u0648\u0631\u0646\u06cc\u06a9"
    ],
    "name:und_x_variant":[
        "Zebreng",
        "Z\u016brn\u012bk"
    ],
    "wof:name":"Zebring",
    "wof:placetype":"locality"
},
  "geometry": {"coordinates":[59.06081999999999,26.77532],"type":"Point"}
}