{
  "type": "Feature",
  "properties": {
    "gn:admin1_code":"16",
    "gn:asciiname":"Meleh Qeshlaq",
    "gn:country_code":"IR",
    "gn:dem":1778,
    "gn:feature_class":"P",
    "gn:feature_code":"PPL",
    "gn:name":"Meleh Qeshl\u0101q",
    "gn:population":0,
    "gn:timezone":"Asia/Tehran",
    "iso:country":"IR",
    "name:ara_x_preferred":[
        "\u0645\u0644\u0647"
    ],
    "name:ceb_x_preferred":[
        "Meleh Qeshl\u0101q"
    ],
    "name:ckb_x_preferred":[
        "\u0645\u0644\u06d5"
    ],
    "name:fas_x_preferred":[
        "\u0645\u0650\u0644\u0650\u0647"
    ],
    "name:fas_x_variant":[
        "\u0645\u0644\u0647 \u0642\u0634\u0644\u0627\u0642",
        "Meleh Qeshl\u0101q",
        "\u0645\u0644\u0647"
    ],
    "name:kur_x_preferred":[
        "Mile"
    ],
    "name:swe_x_preferred":[
        "Meleh Qeshl\u0101q"
    ],
    "name:und_x_variant":[
        "Meleh"
    ],
    "wof:name":"Meleh Qeshlaq",
    "wof:placetype":"locality"
},
  "geometry": {"coordinates":[46.4243,36.0575],"type":"Point"}
}