{
  "type": "Feature",
  "properties": {
    "gn:admin1_code":"13.0",
    "gn:asciiname":"Taqi",
    "gn:country_code":"IR",
    "gn:dem":1194,
    "gn:feature_class":"P",
    "gn:feature_code":"PPL",
    "gn:name":"Taq\u012b",
    "gn:population":0,
    "gn:timezone":"Asia/Tehran",
    "iso:country":"IR",
    "name:fas_x_preferred":[
        "\u062a\u0642\u06cc"
    ],
    "name:fas_x_variant":[
        "Taq\u012b",
        "\u062d\u0644\u0651\u0627\u062c",
        "\u1e28all\u0101j"
    ],
    "name:und_x_variant":[
        "Drapni\u0107i",
        "Gornji Drapni\u0107i",
        "\u1e28all\u0101j"
    ],
    "wof:name":"Taqi",
    "wof:placetype":"locality"
},
  "geometry": {"coordinates":[46.17,34.0231],"type":"Point"}
}