{
  "type": "Feature",
  "properties": {
    "gn:admin1_code":"37",
    "gn:asciiname":"Charqoli",
    "gn:country_code":"IR",
    "gn:dem":-24,
    "gn:feature_class":"P",
    "gn:feature_code":"PPL",
    "gn:name":"Ch\u0101rqol\u012b",
    "gn:population":0,
    "gn:timezone":"Asia/Tehran",
    "iso:country":"IR",
    "name:fas_x_preferred":[
        "Ch\u0101rqol\u012b"
    ],
    "name:fas_x_variant":[
        "\u0686\u0627\u0631\u0642\u0644\u06cc",
        "\u062a\u0648\u0645\u0627\u0686\u0644\u064e\u0631\u0650 \u0686\u0627\u0631\u0642\u064f\u0644\u06cc"
    ],
    "name:und_x_variant":[
        "\u0686\u0627\u0631\u0642\u0644\u06cc",
        "T\u016bm\u0101chlar-e Ch\u0101rqol\u012b"
    ],
    "wof:name":"Charqoli",
    "wof:placetype":"locality"
},
  "geometry": {"coordinates":[54.04941,36.9901],"type":"Point"}
}