{
  "type": "Feature",
  "properties": {
    "gn:admin1_code":"28",
    "gn:asciiname":"Behiyeh",
    "gn:country_code":"IR",
    "gn:dem":2151,
    "gn:feature_class":"P",
    "gn:feature_code":"PPL",
    "gn:name":"Beh\u012byeh",
    "gn:population":0,
    "gn:timezone":"Asia/Tehran",
    "iso:country":"IR",
    "name:fas_x_preferred":[
        "\u0628\u0647\u06cc\u0647"
    ],
    "name:fas_x_variant":[
        "Beh\u012byeh"
    ],
    "wof:name":"Behiyeh",
    "wof:placetype":"locality"
},
  "geometry": {"coordinates":[52.5539,33.2112],"type":"Point"}
}