{
  "type": "Feature",
  "properties": {
    "gn:admin1_code":"29",
    "gn:asciiname":"Riseh",
    "gn:country_code":"IR",
    "gn:dem":2322,
    "gn:feature_class":"P",
    "gn:feature_code":"PPL",
    "gn:name":"R\u012bseh",
    "gn:population":0,
    "gn:timezone":"Asia/Tehran",
    "iso:country":"IR",
    "name:fas_x_preferred":[
        "\u0631\u06cc\u0633\u0647"
    ],
    "name:fas_x_variant":[
        "R\u012bseh"
    ],
    "name:und_x_variant":[
        "R\u012bzh",
        "R\u012bzeh"
    ],
    "wof:name":"Riseh",
    "wof:placetype":"locality"
},
  "geometry": {"coordinates":[55.4093,30.3167],"type":"Point"}
}