{
  "type": "Feature",
  "properties": {
    "gn:admin1_code":"38",
    "gn:asciiname":"Changureh",
    "gn:country_code":"IR",
    "gn:dem":1644,
    "gn:feature_class":"P",
    "gn:feature_code":"PPL",
    "gn:name":"Chang\u016breh",
    "gn:population":0,
    "gn:timezone":"Asia/Tehran",
    "iso:country":"IR",
    "name:fas_x_preferred":[
        "\u0686\u0646\u06af\u0648\u0631\u0647"
    ],
    "name:fas_x_variant":[
        "Chang\u016breh"
    ],
    "wof:name":"Changureh",
    "wof:placetype":"locality"
},
  "geometry": {"coordinates":[49.48378,36.23573],"type":"Point"}
}