{
  "type": "Feature",
  "properties": {
    "gn:admin1_code":"29",
    "gn:asciiname":"Chehel Maneh",
    "gn:country_code":"IR",
    "gn:dem":562,
    "gn:feature_class":"P",
    "gn:feature_code":"PPL",
    "gn:name":"Chehel Maneh",
    "gn:population":0,
    "gn:timezone":"Asia/Tehran",
    "iso:country":"IR",
    "name:fas_x_preferred":[
        "\u0686\u0647\u0644 \u0645\u0646\u0647"
    ],
    "wof:name":"Chehel Maneh",
    "wof:placetype":"locality"
},
  "geometry": {"coordinates":[57.8387,28.3084],"type":"Point"}
}