{
  "type": "Feature",
  "properties": {
    "gn:admin1_code":"35.0",
    "gn:asciiname":"Sanar-e Sofla",
    "gn:country_code":"IR",
    "gn:dem":868,
    "gn:feature_class":"P",
    "gn:feature_code":"PPL",
    "gn:name":"San\u0101r-e Sofl\u00e1",
    "gn:population":0,
    "gn:timezone":"Asia/Tehran",
    "iso:country":"IR",
    "name:fas_x_preferred":[
        "San\u0101r-e P\u0101\u2019\u012bn"
    ],
    "name:fas_x_variant":[
        "\u0633\u0646\u0627\u0631 \u067e\u0627\u0626\u064a\u0646",
        "\u0633\u0646\u0627\u0631 \u0633\u0641\u0644\u06cc"
    ],
    "name:und_x_variant":[
        "\u0633\u0646\u0627\u0631 \u067e\u0627\u0626\u064a\u0646",
        "San\u0101r-e Sofl\u00e1"
    ],
    "wof:name":"Sanar-e Sofla",
    "wof:placetype":"locality"
},
  "geometry": {"coordinates":[51.29411,36.50464],"type":"Point"}
}