{
  "type": "Feature",
  "properties": {
    "gn:admin1_code":"33",
    "gn:asciiname":"Darandash",
    "gn:country_code":"IR",
    "gn:dem":1765,
    "gn:feature_class":"P",
    "gn:feature_code":"PPL",
    "gn:name":"D\u0101r\u0101nd\u0101sh",
    "gn:population":0,
    "gn:timezone":"Asia/Tehran",
    "iso:country":"IR",
    "name:azb_x_preferred":[
        "\u062f\u0627\u0631\u0627\u0646\u062f\u0627\u0634"
    ],
    "name:aze_x_preferred":[
        "Daranda\u015f"
    ],
    "name:ceb_x_preferred":[
        "D\u0101r\u0101nd\u0101sh"
    ],
    "name:fas_x_preferred":[
        "\u062f\u0627\u0631\u0627\u0646\u062f\u0627\u0634"
    ],
    "name:fas_x_variant":[
        "D\u0101r\u0101nd\u0101sh"
    ],
    "name:msa_x_preferred":[
        "Darandash"
    ],
    "name:swe_x_preferred":[
        "D\u0101r\u0101nd\u0101sh"
    ],
    "name:und_x_variant":[
        "Tarandash"
    ],
    "wof:name":"Darandash",
    "wof:placetype":"locality"
},
  "geometry": {"coordinates":[45.9318,38.6948],"type":"Point"}
}