{
  "type": "Feature",
  "properties": {
    "gn:admin1_code":"34.0",
    "gn:asciiname":"Bidlu-ye Pa'in",
    "gn:country_code":"IR",
    "gn:dem":1563,
    "gn:feature_class":"P",
    "gn:feature_code":"PPL",
    "gn:name":"B\u012bdl\u016b-ye P\u0101\u2019\u012bn",
    "gn:population":0,
    "gn:timezone":"Asia/Tehran",
    "iso:country":"IR",
    "name:fas_x_preferred":[
        "\u0628\u06cc\u062f\u0644\u06cc"
    ],
    "name:fas_x_variant":[
        "B\u012bdel\u012b",
        "\u0628\u06cc\u062f\u0644\u0648 \u067e\u0627\u0626\u064a\u0646"
    ],
    "name:und_x_variant":[
        "B\u012bdl\u016b-ye P\u0101\u2019\u012bn"
    ],
    "wof:name":"Bidlu-ye Pa'in",
    "wof:placetype":"locality"
},
  "geometry": {"coordinates":[50.3426,35.52251],"type":"Point"}
}