{
  "type": "Feature",
  "properties": {
    "gn:admin1_code":"8",
    "gn:asciiname":"Feshkecheh",
    "gn:country_code":"IR",
    "gn:dem":-3,
    "gn:feature_class":"P",
    "gn:feature_code":"PPL",
    "gn:name":"Feshkecheh",
    "gn:population":0,
    "gn:timezone":"Asia/Tehran",
    "iso:country":"IR",
    "name:fas_x_preferred":[
        "\u0641\u0634\u06a9\u0686\u0647"
    ],
    "name:und_x_variant":[
        "Fashkeh",
        "Feshke",
        "Fashkacheh",
        "Fashgj\u0101h",
        "Feshkacheh",
        "Feshkecheh",
        "\u0641\u0634\u06a9\u0686\u0647"
    ],
    "wof:name":"Feshkecheh",
    "wof:placetype":"locality"
},
  "geometry": {"coordinates":[49.72546,37.3049],"type":"Point"}
}