{
  "type": "Feature",
  "properties": {
    "gn:admin1_code":"8",
    "gn:asciiname":"Feshkecheh",
    "gn:country_code":"IR",
    "gn:dem":-3,
    "gn:feature_class":"P",
    "gn:feature_code":"PPL",
    "gn:name":"Feshkecheh",
    "gn:population":0,
    "gn:timezone":"Asia/Tehran",
    "iso:country":"IR",
    "name:ceb_x_preferred":[
        "Feshkecheh"
    ],
    "name:fas_x_preferred":[
        "\u0641\u0634\u06a9\u0686\u0647"
    ],
    "name:msa_x_preferred":[
        "Feshkecheh"
    ],
    "name:swe_x_preferred":[
        "Feshkecheh"
    ],
    "name:ukr_x_preferred":[
        "\u0424\u0430\u0448\u043a\u0435\u0447\u0435"
    ],
    "name:und_x_variant":[
        "Fashkeh",
        "Feshke",
        "Fashkacheh",
        "Fashgj\u0101h",
        "Feshkacheh"
    ],
    "wof:name":"Feshkecheh",
    "wof:placetype":"locality"
},
  "geometry": {"coordinates":[49.72546,37.3049],"type":"Point"}
}