{
  "type": "Feature",
  "properties": {
    "gn:admin1_code":"29",
    "gn:asciiname":"Mowtowr-e Ettehad-e Do",
    "gn:country_code":"IR",
    "gn:dem":2052,
    "gn:feature_class":"P",
    "gn:feature_code":"PPL",
    "gn:name":"Mowtowr-e Ette\u1e29\u0101d-e Do",
    "gn:population":0,
    "gn:timezone":"Asia/Tehran",
    "iso:country":"IR",
    "name:fas_x_preferred":[
        "\u0686\u0627\u062e\u0648\u0632\u0627\u062f\u0647"
    ],
    "name:fas_x_variant":[
        "Ch\u0101kh\u016bz\u0101deh",
        "\u0645\u0648\u062a\u0648\u0631 \u0627\u062a\u062d\u0627\u062f \u06f2"
    ],
    "name:und_x_variant":[
        "Mowtowr-e Ette\u1e29\u0101d-e Do"
    ],
    "wof:name":"Mowtowr-e Ettehad-e Do",
    "wof:placetype":"locality"
},
  "geometry": {"coordinates":[56.55774,28.92169],"type":"Point"}
}