{
  "type": "Feature",
  "properties": {
    "gn:admin1_code":"11.0",
    "gn:asciiname":"Penar",
    "gn:country_code":"IR",
    "gn:dem":255,
    "gn:feature_class":"P",
    "gn:feature_code":"PPL",
    "gn:name":"Pen\u0101r",
    "gn:population":0,
    "gn:timezone":"Asia/Tehran",
    "iso:country":"IR",
    "name:fas_x_preferred":[
        "\u067e\u0646\u0627\u0631"
    ],
    "name:und_x_variant":[
        "Pen\u0101r"
    ],
    "wof:name":"Penar",
    "wof:placetype":"locality"
},
  "geometry": {"coordinates":[55.25353000000001,27.30577000000001],"type":"Point"}
}