{
  "type": "Feature",
  "properties": {
    "gn:admin1_code":"22",
    "gn:asciiname":"Puder",
    "gn:cc2":"IR",
    "gn:country_code":"IR",
    "gn:dem":13,
    "gn:feature_class":"P",
    "gn:feature_code":"PPL",
    "gn:name":"P\u016bder",
    "gn:population":0,
    "gn:timezone":"Asia/Tehran",
    "iso:country":"IR",
    "name:fas_x_preferred":[
        "\u067e\u0648\u062f\u0650\u0631"
    ],
    "name:fas_x_variant":[
        "\u067e\u0648\u062f\u064e\u0631",
        "P\u016bder"
    ],
    "name:und_x_variant":[
        "P\u016bdar"
    ],
    "wof:name":"Puder",
    "wof:placetype":"locality"
},
  "geometry": {"coordinates":[50.86111,28.975],"type":"Point"}
}