{
  "type": "Feature",
  "properties": {
    "gn:admin1_code":"33",
    "gn:asciiname":"Koli",
    "gn:country_code":"IR",
    "gn:dem":1943,
    "gn:feature_class":"P",
    "gn:feature_code":"PPL",
    "gn:name":"Kol\u012b",
    "gn:population":0,
    "gn:timezone":"Asia/Tehran",
    "iso:country":"IR",
    "name:ceb_x_preferred":[
        "Koli"
    ],
    "name:deu_x_preferred":[
        "Koli"
    ],
    "name:fas_x_preferred":[
        "\u06a9\u0644\u06cc"
    ],
    "name:fas_x_variant":[
        "Kol\u012b"
    ],
    "name:fin_x_preferred":[
        "Koli"
    ],
    "name:isl_x_preferred":[
        "Koli"
    ],
    "name:swe_x_preferred":[
        "Koli"
    ],
    "name:tgl_x_preferred":[
        "Koli"
    ],
    "wof:name":"Koli",
    "wof:placetype":"locality"
},
  "geometry": {"coordinates":[47.7055,37.9844],"type":"Point"}
}