{
  "type": "Feature",
  "properties": {
    "gn:admin1_code":"11",
    "gn:asciiname":"`Ali Khani",
    "gn:country_code":"IR",
    "gn:dem":14,
    "gn:feature_class":"P",
    "gn:feature_code":"PPL",
    "gn:name":"\u2018Al\u012b Kh\u0101n\u012b",
    "gn:population":0,
    "gn:timezone":"Asia/Tehran",
    "iso:country":"IR",
    "name:fas_x_preferred":[
        "\u0639\u0644\u06cc \u062e\u0627\u0646\u06cc"
    ],
    "name:fas_x_variant":[
        "\u0642\u0627\u062f\u0631 \u062e\u0627\u0646\u06cc"
    ],
    "name:und_x_variant":[
        "\u2018Al\u012b Kh\u0101n\u012b",
        "Q\u0101der Kh\u0101n\u012b"
    ],
    "wof:name":"`Ali Khani",
    "wof:placetype":"locality"
},
  "geometry": {"coordinates":[57.10225,26.9738],"type":"Point"}
}