{
  "type": "Feature",
  "properties": {
    "gn:admin1_code":"7",
    "gn:asciiname":"Sho`leh",
    "gn:country_code":"IR",
    "gn:dem":1620,
    "gn:feature_class":"P",
    "gn:feature_code":"PPL",
    "gn:name":"Sho\u2018leh",
    "gn:population":0,
    "gn:timezone":"Asia/Tehran",
    "iso:country":"IR",
    "name:fas_x_preferred":[
        "Sho\u2018leh"
    ],
    "wof:name":"Sho`leh",
    "wof:placetype":"locality"
},
  "geometry": {"coordinates":[52.7625,28.90472],"type":"Point"}
}