{
  "type": "Feature",
  "properties": {
    "gn:admin1_code":"7",
    "gn:asciiname":"Falini",
    "gn:country_code":"IR",
    "gn:dem":1242,
    "gn:feature_class":"P",
    "gn:feature_code":"PPL",
    "gn:name":"F\u0101l\u012bn\u012b",
    "gn:population":0,
    "gn:timezone":"Asia/Tehran",
    "iso:country":"IR",
    "name:fas_x_preferred":[
        "\u0641\u0627\u0644\u06cc\u0646\u06cc"
    ],
    "name:fas_x_variant":[
        "Q\u0101l\u012bn\u012b",
        "F\u0101l\u012bn\u012b"
    ],
    "name:und_x_variant":[
        "Q\u0101leyn\u012b-ye \u2018Oly\u0101",
        "Q\u0101leyn\u012b"
    ],
    "wof:name":"Falini",
    "wof:placetype":"locality"
},
  "geometry": {"coordinates":[53.2131,28.7798],"type":"Point"}
}