{
  "type": "Feature",
  "properties": {
    "gn:admin1_code":"35.0",
    "gn:asciiname":"Siahrud Sar",
    "gn:country_code":"IR",
    "gn:dem":-21,
    "gn:feature_class":"P",
    "gn:feature_code":"PPL",
    "gn:name":"S\u012b\u0101hr\u016bd Sar",
    "gn:population":0,
    "gn:timezone":"Asia/Tehran",
    "iso:country":"IR",
    "name:fas_x_preferred":[
        "\u0633\u064a\u0627\u0647\u0631\u0648\u062f \u0633\u0631"
    ],
    "name:fas_x_variant":[
        "S\u012b\u0101hr\u016bd Sar"
    ],
    "wof:name":"Siahrud Sar",
    "wof:placetype":"locality"
},
  "geometry": {"coordinates":[52.32135,36.64114],"type":"Point"}
}