{
  "type": "Feature",
  "properties": {
    "gn:admin1_code":"29",
    "gn:asciiname":"Behzadun",
    "gn:country_code":"IR",
    "gn:dem":2435,
    "gn:feature_class":"P",
    "gn:feature_code":"PPL",
    "gn:name":"Behz\u0101d\u016bn",
    "gn:population":0,
    "gn:timezone":"Asia/Tehran",
    "iso:country":"IR",
    "name:fas_x_preferred":[
        "\u0628\u0647\u0632\u0627\u062f\u0648\u0646"
    ],
    "name:fas_x_variant":[
        "Behz\u0101d\u0101n",
        "Behz\u0101d\u016bn",
        "\u06af\u0632\u0631\u0648\u0626\u064a\u0647"
    ],
    "name:und_x_variant":[
        "Gazr\u016b\u2019\u012byeh"
    ],
    "wof:name":"Behzadun",
    "wof:placetype":"locality"
},
  "geometry": {"coordinates":[55.2214,30.4532],"type":"Point"}
}