{
  "type": "Feature",
  "properties": {
    "gn:admin1_code":"28",
    "gn:asciiname":"Shoja`abad",
    "gn:country_code":"IR",
    "gn:dem":1226,
    "gn:feature_class":"P",
    "gn:feature_code":"PPL",
    "gn:name":"Shoj\u0101\u2018\u0101b\u0101d",
    "gn:population":0,
    "gn:timezone":"Asia/Tehran",
    "iso:country":"IR",
    "name:fas_x_preferred":[
        "\u0634\u062c\u0627\u0639 \u0622\u0628\u0627\u062f"
    ],
    "name:fas_x_variant":[
        "Shoj\u0101\u2018\u0101b\u0101d"
    ],
    "name:und_x_variant":[
        "Shuja\u2018\u0101b\u0101d"
    ],
    "wof:name":"Shoja`abad",
    "wof:placetype":"locality"
},
  "geometry": {"coordinates":[51.7117,33.7686],"type":"Point"}
}