{
  "type": "Feature",
  "properties": {
    "gn:admin1_code":"42",
    "gn:asciiname":"Farkhan-e Pa'in",
    "gn:country_code":"IR",
    "gn:dem":1331,
    "gn:feature_class":"P",
    "gn:feature_code":"PPL",
    "gn:name":"Farkh\u0101n-e P\u0101\u2019\u012bn",
    "gn:population":0,
    "gn:timezone":"Asia/Tehran",
    "iso:country":"IR",
    "name:fas_x_preferred":[
        "Farkh\u0101n-e P\u0101\u2019\u012bn"
    ],
    "name:fas_x_variant":[
        "Farkh\u0101n-e Sofl\u0101",
        "\u0641\u0631\u062e\u0627\u0646 \u067e\u0627\u0626\u06cc\u0646",
        "\u0641\u0631\u062e\u0627\u0646 \u0633\u0641\u0644\u06cc"
    ],
    "name:und_x_variant":[
        "Farkh\u0101n-e \u2018Olya",
        "\u0641\u0631\u062e\u0627\u0646 \u067e\u0627\u0626\u06cc\u0646"
    ],
    "wof:name":"Farkhan-e Pa'in",
    "wof:placetype":"locality"
},
  "geometry": {"coordinates":[58.53867,37.07975],"type":"Point"}
}