{
  "type": "Feature",
  "properties": {
    "gn:admin1_code":"4.0",
    "gn:asciiname":"Nangaru",
    "gn:country_code":"IR",
    "gn:dem":176,
    "gn:feature_class":"P",
    "gn:feature_code":"PPL",
    "gn:name":"Nang\u0101r\u016b",
    "gn:population":0,
    "gn:timezone":"Asia/Tehran",
    "iso:country":"IR",
    "name:fas_x_preferred":[
        "\u0646\u0646\u06af\u0627\u0631\u0648"
    ],
    "name:fas_x_variant":[
        "Lang\u0101r\u016b",
        "Nang\u0101r\u016b"
    ],
    "wof:name":"Nangaru",
    "wof:placetype":"locality"
},
  "geometry": {"coordinates":[61.7721,25.8845],"type":"Point"}
}