{
  "type": "Feature",
  "properties": {
    "gn:admin1_code":"41.0",
    "gn:asciiname":"Godar-e Jowz",
    "gn:country_code":"IR",
    "gn:dem":1521,
    "gn:feature_class":"P",
    "gn:feature_code":"PPL",
    "gn:name":"God\u0101r-e Jowz",
    "gn:population":0,
    "gn:timezone":"Asia/Tehran",
    "iso:country":"IR",
    "name:fas_x_preferred":[
        "Chashmeh-i-G\u016bdar-i-J\u016bj"
    ],
    "name:fas_x_variant":[
        "\u06af\u062f\u0627\u0631\u062c\u0648\u0632",
        "Cheshmeh-ye God\u0101r-e J\u016bj",
        "God\u0101r-e Jowz"
    ],
    "wof:name":"Godar-e Jowz",
    "wof:placetype":"locality"
},
  "geometry": {"coordinates":[60.30451,33.01981],"type":"Point"}
}