{
  "type": "Feature",
  "properties": {
    "gn:admin1_code":"42.0",
    "gn:asciiname":"Jangah",
    "gn:country_code":"IR",
    "gn:dem":939,
    "gn:feature_class":"P",
    "gn:feature_code":"PPL",
    "gn:name":"Jang\u0101h",
    "gn:population":0,
    "gn:timezone":"Asia/Tehran",
    "iso:country":"IR",
    "name:fas_x_preferred":[
        "\u062c\u0646\u06af\u0627\u0647"
    ],
    "name:fas_x_variant":[
        "Jang\u0101h"
    ],
    "name:und_x_variant":[
        "Jang G\u0101h"
    ],
    "name:urd_x_preferred":[
        "\u062c\u0646\u06af\u0627\u06c1"
    ],
    "wof:name":"Jangah",
    "wof:placetype":"locality"
},
  "geometry": {"coordinates":[60.5851,35.3033],"type":"Point"}
}