{
  "type": "Feature",
  "properties": {
    "gn:admin1_code":"42",
    "gn:asciiname":"Marjaneh",
    "gn:country_code":"IR",
    "gn:dem":1551,
    "gn:feature_class":"P",
    "gn:feature_code":"PPL",
    "gn:name":"Marj\u0101neh",
    "gn:population":0,
    "gn:timezone":"Asia/Tehran",
    "iso:country":"IR",
    "name:fas_x_preferred":[
        "Marj\u0101neh"
    ],
    "name:fas_x_variant":[
        "\u0645\u0631\u062c\u0627\u0646\u0647"
    ],
    "wof:name":"Marjaneh",
    "wof:placetype":"locality"
},
  "geometry": {"coordinates":[59.3428,35.39612],"type":"Point"}
}