{
  "type": "Feature",
  "properties": {
    "gn:admin1_code":"11.0",
    "gn:asciiname":"Tappeh Molla",
    "gn:cc2":"IR",
    "gn:country_code":"IR",
    "gn:dem":160,
    "gn:feature_class":"P",
    "gn:feature_code":"PPL",
    "gn:name":"Tappeh Moll\u0101",
    "gn:population":0,
    "gn:timezone":"Asia/Tehran",
    "iso:country":"IR",
    "name:fas_x_preferred":[
        "\u062a\u064e\u067e\u0650\u0651\u0647 \u0645\u064f\u0644\u0651\u0627"
    ],
    "name:fas_x_variant":[
        "\u062a\u064e\u067e\u0650\u0651\u06c0 \u0645\u064f\u0644\u0651\u0627",
        "Tappeh Moll\u0101"
    ],
    "name:und_x_variant":[
        "Tappeh-ye Moll\u0101"
    ],
    "wof:name":"Tappeh Molla",
    "wof:placetype":"locality"
},
  "geometry": {"coordinates":[57.2425,27.27333],"type":"Point"}
}