{
  "type": "Feature",
  "properties": {
    "gn:admin1_code":"28.0",
    "gn:asciiname":"Sumareh",
    "gn:country_code":"IR",
    "gn:dem":1567,
    "gn:feature_class":"P",
    "gn:feature_code":"PPL",
    "gn:name":"S\u016bm\u0101reh",
    "gn:population":0,
    "gn:timezone":"Asia/Tehran",
    "iso:country":"IR",
    "name:fas_x_preferred":[
        "\u0633\u0648\u0645\u0627\u0631\u0650\u0647"
    ],
    "name:fas_x_variant":[
        "S\u016bm\u0101reh"
    ],
    "name:und_x_variant":[
        "Sum\u0101rah"
    ],
    "wof:name":"Sumareh",
    "wof:placetype":"locality"
},
  "geometry": {"coordinates":[51.73333,32.63333],"type":"Point"}
}