{
  "type": "Feature",
  "properties": {
    "gn:admin1_code":"37.0",
    "gn:asciiname":"Sufi Sheykh Ansari",
    "gn:country_code":"IR",
    "gn:dem":109,
    "gn:feature_class":"P",
    "gn:feature_code":"PPL",
    "gn:name":"\u015e\u016bf\u012b Sheykh An\u015f\u0101r\u012b",
    "gn:population":0,
    "gn:timezone":"Asia/Tehran",
    "iso:country":"IR",
    "name:fas_x_preferred":[
        "Mazra\u2018eh-ye \u015e\u016bf\u012b Sheykh"
    ],
    "name:fas_x_variant":[
        "\u0635\u0648\u0641\u06cc \u0634\u06cc\u062e \u0627\u0646\u0635\u0627\u0631\u06cc",
        "\u0635\u0648\u0641\u06cc \u0634\u06cc\u062e"
    ],
    "name:und_x_variant":[
        "\u015e\u016bf\u012b Sheykh An\u015f\u0101r\u012b",
        "\u015e\u016bf\u012b Sheykh"
    ],
    "wof:name":"Sufi Sheykh Ansari",
    "wof:placetype":"locality"
},
  "geometry": {"coordinates":[55.39678000000001,37.41685],"type":"Point"}
}