{
  "type": "Feature",
  "properties": {
    "gn:admin1_code":"28.0",
    "gn:asciiname":"Mazra`eh-ye Now",
    "gn:country_code":"IR",
    "gn:dem":1823,
    "gn:feature_class":"P",
    "gn:feature_code":"PPL",
    "gn:name":"Mazra\u2018eh-ye Now",
    "gn:population":0,
    "gn:timezone":"Asia/Tehran",
    "iso:country":"IR",
    "name:fas_x_preferred":[
        "\u0645\u0632\u0631\u0639\u0647 \u0646\u0648"
    ],
    "name:fas_x_variant":[
        "Mazra\u2018eh-ye Now"
    ],
    "wof:name":"Mazra`eh-ye Now",
    "wof:placetype":"locality"
},
  "geometry": {"coordinates":[52.9669,32.7965],"type":"Point"}
}