{
  "type": "Feature",
  "properties": {
    "gn:admin1_code":"43",
    "gn:asciiname":"Shalakh",
    "gn:country_code":"IR",
    "gn:dem":1367,
    "gn:feature_class":"P",
    "gn:feature_code":"PPL",
    "gn:name":"Shal\u0101kh",
    "gn:population":0,
    "gn:timezone":"Asia/Tehran",
    "iso:country":"IR",
    "name:fas_x_preferred":[
        "Shal\u0101kh"
    ],
    "wof:name":"Shalakh",
    "wof:placetype":"locality"
},
  "geometry": {"coordinates":[57.18333000000001,37.56667],"type":"Point"}
}