{
  "type": "Feature",
  "properties": {
    "gn:admin1_code":"34",
    "gn:asciiname":"Tut Sefid",
    "gn:country_code":"IR",
    "gn:dem":1836,
    "gn:feature_class":"P",
    "gn:feature_code":"PPL",
    "gn:name":"T\u016bt Sef\u012bd",
    "gn:population":0,
    "gn:timezone":"Asia/Tehran",
    "iso:country":"IR",
    "name:fas_x_preferred":[
        "T\u016bt Sef\u012bd"
    ],
    "name:fas_x_variant":[
        "\u062a\u0648\u062a \u0633\u0641\u06cc\u062f"
    ],
    "wof:name":"Tut Sefid",
    "wof:placetype":"locality"
},
  "geometry": {"coordinates":[50.47924,33.65457],"type":"Point"}
}