{
  "type": "Feature",
  "properties": {
    "gn:admin1_code":"42",
    "gn:asciiname":"Qorbanabad",
    "gn:country_code":"IR",
    "gn:dem":845,
    "gn:feature_class":"P",
    "gn:feature_code":"PPLL",
    "gn:name":"Qorb\u0101n\u0101b\u0101d",
    "gn:population":0,
    "gn:timezone":"Asia/Tehran",
    "iso:country":"IR",
    "name:fas_x_preferred":[
        "Qorb\u0101n\u0101b\u0101d"
    ],
    "name:fas_x_variant":[
        "\u0642\u0631\u0628\u0627\u0646 \u0622\u0628\u0627\u062f",
        "\u0642\u0631\u0628\u0627\u0646\u200c\u0622\u0628\u0627\u062f"
    ],
    "name:und_x_variant":[
        "\u0642\u0631\u0628\u0627\u0646 \u0622\u0628\u0627\u062f"
    ],
    "wof:name":"Qorbanabad",
    "wof:placetype":"locality"
},
  "geometry": {"coordinates":[58.56562,34.97297],"type":"Point"}
}