{
  "type": "Feature",
  "properties": {
    "gn:admin1_code":"15",
    "gn:asciiname":"Beyt-e Deris",
    "gn:country_code":"IR",
    "gn:dem":6,
    "gn:feature_class":"P",
    "gn:feature_code":"PPL",
    "gn:name":"Beyt-e Der\u012bs",
    "gn:population":0,
    "gn:timezone":"Asia/Tehran",
    "iso:country":"IR",
    "name:fas_x_preferred":[
        "Der\u012bs"
    ],
    "name:fas_x_variant":[
        "\u0628\u06cc\u062a \u062f\u0631\u06cc\u0633",
        "\u062f\u0631\u06cc\u0651\u0633"
    ],
    "name:und_x_variant":[
        "Beyt-e Der\u012bs",
        "Darayyas"
    ],
    "wof:name":"Beyt-e Deris",
    "wof:placetype":"locality"
},
  "geometry": {"coordinates":[48.70323,30.7668],"type":"Point"}
}