{
  "type": "Feature",
  "properties": {
    "gn:admin1_code":"26.0",
    "gn:asciiname":"Shahrak-e Yas",
    "gn:country_code":"IR",
    "gn:dem":1375,
    "gn:feature_class":"P",
    "gn:feature_code":"PPL",
    "gn:name":"Shahrak-e Y\u0101s",
    "gn:population":0,
    "gn:timezone":"Asia/Tehran",
    "iso:country":"IR",
    "name:fas_x_preferred":[
        "\u0634\u0647\u0631\u06a9 \u06cc\u0627\u0633"
    ],
    "name:und_x_variant":[
        "Shahrak-e Y\u0101s"
    ],
    "wof:name":"Shahrak-e Yas",
    "wof:placetype":"locality"
},
  "geometry": {"coordinates":[50.937,35.865],"type":"Point"}
}