{
  "type": "Feature",
  "properties": {
    "gn:admin1_code":"8.0",
    "gn:asciiname":"Bala Holu Sara",
    "gn:country_code":"IR",
    "gn:dem":317,
    "gn:feature_class":"P",
    "gn:feature_code":"PPL",
    "gn:name":"B\u0101l\u0101 Hol\u016b Sar\u0101",
    "gn:population":0,
    "gn:timezone":"Asia/Tehran",
    "iso:country":"IR",
    "name:ara_x_preferred":[
        "\u0628\u0627\u0644\u0627\u0647\u0644\u0648\u0633\u0631\u0627"
    ],
    "name:ceb_x_preferred":[
        "B\u0101l\u0101 Hol\u016b Sar\u0101"
    ],
    "name:fas_x_preferred":[
        "\u0628\u0627\u0644\u0627 \u0647\u0644\u0648 \u0633\u0631\u0627"
    ],
    "name:fas_x_variant":[
        "\u0628\u0627\u0644\u0627\u0647\u0644\u0648\u0633\u0631\u0627"
    ],
    "name:msa_x_preferred":[
        "Bala Holu Sara"
    ],
    "name:swe_x_preferred":[
        "B\u0101l\u0101 Hol\u016b Sar\u0101"
    ],
    "name:ukr_x_preferred":[
        "\u0411\u0430\u043b\u0430-\u0413\u043e\u043b\u044e-\u0421\u0430\u0440\u0430"
    ],
    "wof:name":"Bala Holu Sara",
    "wof:placetype":"locality"
},
  "geometry": {"coordinates":[50.25819,37.02918],"type":"Point"}
}