{
  "type": "Feature",
  "properties": {
    "gn:admin1_code":"9",
    "gn:asciiname":"Mohammad Gap-e `Olya",
    "gn:country_code":"IR",
    "gn:dem":1784,
    "gn:feature_class":"P",
    "gn:feature_code":"PPL",
    "gn:name":"Mo\u1e29ammad Gap-e \u2018Oly\u0101",
    "gn:population":0,
    "gn:timezone":"Asia/Tehran",
    "iso:country":"IR",
    "name:fas_x_preferred":[
        "Mo\u1e29ammad\u012byeh-e \u2018Oly\u0101"
    ],
    "name:fas_x_variant":[
        "\u0645\u062d\u0645\u0651\u062f\u06cc\u0647 \u0639\u0644\u06cc\u0627",
        "\u0645\u062d\u0645\u062f \u06af\u067e \u0639\u0644\u06cc\u0627",
        "\u0645\u062d\u0645\u062f\u06cc\u0647 \u0639\u0644\u06cc\u0627"
    ],
    "name:msa_x_preferred":[
        "Mohammadiyeh-e Olya"
    ],
    "name:pol_x_preferred":[
        "Mohammadije-je Olja"
    ],
    "name:und_x_variant":[
        "Mo\u1e29ammad Kap",
        "Mo\u1e29ammad Gap \u2018Oly\u0101",
        "Mo\u1e29ammad Gap-e \u2018Oly\u0101"
    ],
    "wof:name":"Mohammad Gap-e `Olya",
    "wof:placetype":"locality"
},
  "geometry": {"coordinates":[48.32676,34.13461],"type":"Point"}
}