{
  "type": "Feature",
  "properties": {
    "gn:admin1_code":"7",
    "gn:asciiname":"Esfian",
    "gn:country_code":"IR",
    "gn:dem":2178,
    "gn:feature_class":"P",
    "gn:feature_code":"PPL",
    "gn:name":"Esf\u012b\u0101n",
    "gn:population":0,
    "gn:timezone":"Asia/Tehran",
    "iso:country":"IR",
    "name:fas_x_preferred":[
        "Esf\u012b\u0101n"
    ],
    "name:fas_x_variant":[
        "\u0627\u0633\u0641\u06cc\u0627\u0646"
    ],
    "name:msa_x_preferred":[
        "Esfian"
    ],
    "name:und_x_variant":[
        "Esfey\u0101n",
        "Esf\u012by\u0101n"
    ],
    "wof:name":"Esfian",
    "wof:placetype":"locality"
},
  "geometry": {"coordinates":[51.95021,30.52037],"type":"Point"}
}