{
  "type": "Feature",
  "properties": {
    "gn:admin1_code":"4",
    "gn:asciiname":"Mahalabad",
    "gn:country_code":"IR",
    "gn:dem":1173,
    "gn:feature_class":"P",
    "gn:feature_code":"PPL",
    "gn:name":"Ma\u1e29\u0101l\u0101b\u0101d",
    "gn:population":0,
    "gn:timezone":"Asia/Tehran",
    "iso:country":"IR",
    "name:fas_x_preferred":[
        "\u0686\u0627\u0647 \u06a9\u0645\u0627\u0644"
    ],
    "name:fas_x_variant":[
        "Ch\u0101h-e Kam\u0101l",
        "\u0645\u062d\u0627\u0644 \u0622\u0628\u0627\u062f"
    ],
    "name:und_x_variant":[
        "Ma\u1e29\u0101l\u0101b\u0101d"
    ],
    "wof:name":"Mahalabad",
    "wof:placetype":"locality"
},
  "geometry": {"coordinates":[61.8457,27.3772],"type":"Point"}
}