{
  "type": "Feature",
  "properties": {
    "gn:admin1_code":"42.0",
    "gn:asciiname":"Qush-e Kohneh",
    "gn:country_code":"IR",
    "gn:dem":287,
    "gn:feature_class":"P",
    "gn:feature_code":"PPL",
    "gn:name":"Q\u016bsh-e Kohneh",
    "gn:population":0,
    "gn:timezone":"Asia/Tehran",
    "iso:country":"IR",
    "name:fas_x_preferred":[
        "Q\u016bsh-e Kohneh"
    ],
    "name:fas_x_variant":[
        "\u0642\u0648\u0634 \u06a9\u0647\u0646\u0647"
    ],
    "name:und_x_variant":[
        "\u0642\u0648\u0634 \u06a9\u0647\u0646\u0647",
        "Kuna"
    ],
    "wof:name":"Qush-e Kohneh",
    "wof:placetype":"locality"
},
  "geometry": {"coordinates":[61.1323,36.4828],"type":"Point"}
}