{
  "type": "Feature",
  "properties": {
    "gn:admin1_code":"16",
    "gn:asciiname":"Turbeh Riz",
    "gn:country_code":"IR",
    "gn:dem":1795,
    "gn:feature_class":"P",
    "gn:feature_code":"PPL",
    "gn:name":"T\u016brbeh R\u012bz",
    "gn:population":0,
    "gn:timezone":"Asia/Tehran",
    "iso:country":"IR",
    "name:fas_x_preferred":[
        "\u062a\u0648\u0628\u0631\u0647 \u0631\u064a\u0632"
    ],
    "name:fas_x_variant":[
        "T\u016bbreh R\u012bz",
        "\u062a\u0648\u0631\u0628\u0647 \u0631\u06cc\u0632"
    ],
    "name:und_x_variant":[
        "Tarbur\u012bz",
        "T\u016brbeh R\u012bz",
        "T\u014drbeh R\u012bz",
        "Torbr\u012bz"
    ],
    "wof:name":"Turbeh Riz",
    "wof:placetype":"locality"
},
  "geometry": {"coordinates":[47.4773,35.22866],"type":"Point"}
}