{
  "type": "Feature",
  "properties": {
    "gn:admin1_code":"43",
    "gn:asciiname":"Zartanlu",
    "gn:country_code":"IR",
    "gn:dem":1556,
    "gn:feature_class":"P",
    "gn:feature_code":"PPL",
    "gn:name":"Zart\u0101nl\u016b",
    "gn:population":0,
    "gn:timezone":"Asia/Tehran",
    "iso:country":"IR",
    "name:ceb_x_preferred":[
        "Zart\u0101nl\u016b"
    ],
    "name:fas_x_preferred":[
        "\u015e\u016bf\u012b\u0101nl\u016b"
    ],
    "name:fas_x_variant":[
        "Zart\u0101nl\u016b",
        "\u0632\u0631\u062a\u0627\u0646\u0644\u0648"
    ],
    "name:swe_x_preferred":[
        "Zart\u0101nl\u016b"
    ],
    "name:und_x_variant":[
        "Zort\u0101nl\u016b",
        "Zartanu"
    ],
    "wof:name":"Zartanlu",
    "wof:placetype":"locality"
},
  "geometry": {"coordinates":[58.14413,37.52639],"type":"Point"}
}