{
  "type": "Feature",
  "properties": {
    "gn:admin1_code":"41",
    "gn:asciiname":"Monond",
    "gn:country_code":"IR",
    "gn:dem":2242,
    "gn:feature_class":"P",
    "gn:feature_code":"PPL",
    "gn:name":"Monond",
    "gn:population":0,
    "gn:timezone":"Asia/Tehran",
    "iso:country":"IR",
    "name:fas_x_preferred":[
        "\u0645\u0646\u0646\u062f"
    ],
    "name:fas_x_variant":[
        "\u0645\u0646\u0646\u062f \u0628\u0627\u0644\u0627"
    ],
    "name:und_x_variant":[
        "Man\u016bn",
        "Monond",
        "Monond-e B\u0101l\u0101"
    ],
    "wof:name":"Monond",
    "wof:placetype":"locality"
},
  "geometry": {"coordinates":[59.642,33.19863],"type":"Point"}
}