{
  "type": "Feature",
  "properties": {
    "gn:admin1_code":"33",
    "gn:asciiname":"Rashtabad-e Qadim",
    "gn:country_code":"IR",
    "gn:dem":1522,
    "gn:feature_class":"P",
    "gn:feature_code":"PPL",
    "gn:name":"Rasht\u0101b\u0101d-e Qad\u012bm",
    "gn:population":0,
    "gn:timezone":"Asia/Tehran",
    "iso:country":"IR",
    "name:ara_x_preferred":[
        "\u0631\u0634\u062a \u0623\u0628\u0627\u062f \u0627\u0644\u0642\u062f\u064a\u0645"
    ],
    "name:azb_x_preferred":[
        "\u0631\u0634\u062a\u0627\u0628\u0627\u062f \u0642\u062f\u06cc\u0645"
    ],
    "name:fas_x_preferred":[
        "\u0631\u0634\u062a \u0622\u0628\u0627\u062f \u0642\u062f\u06cc\u0645"
    ],
    "name:fas_x_variant":[
        "Rasht\u0101b\u0101d-e Jad\u012bd",
        "Rasht\u0101b\u0101d-e Qad\u012bm",
        "\u0631\u0634\u062a\u0627\u0628\u0627\u062f \u0642\u062f\u06cc\u0645"
    ],
    "name:msa_x_preferred":[
        "Rashtabad-e Qadim"
    ],
    "name:und_x_variant":[
        "Rasht\u0101b\u0101d",
        "Risht-Abad",
        "Rasht Abad Jadid"
    ],
    "wof:name":"Rashtabad-e Qadim",
    "wof:placetype":"locality"
},
  "geometry": {"coordinates":[46.844,38.5094],"type":"Point"}
}