{
  "type": "Feature",
  "properties": {
    "gn:admin1_code":"40.0",
    "gn:asciiname":"Bagh Pahlavanpur",
    "gn:country_code":"IR",
    "gn:dem":1488,
    "gn:feature_class":"P",
    "gn:feature_code":"PPL",
    "gn:name":"B\u0101gh Pahlav\u0101np\u016br",
    "gn:population":0,
    "gn:timezone":"Asia/Tehran",
    "iso:country":"IR",
    "name:fas_x_preferred":[
        "\u0628\u0627\u063a \u067e\u0647\u0644\u0648\u0627\u0646\u067e\u0648\u0631"
    ],
    "name:und_x_variant":[
        "B\u0101gh Pahlav\u0101np\u016br"
    ],
    "wof:name":"Bagh Pahlavanpur",
    "wof:placetype":"locality"
},
  "geometry": {"coordinates":[54.43469,31.56397],"type":"Point"}
}