{
  "type": "Feature",
  "properties": {
    "gn:admin1_code":"8",
    "gn:asciiname":"Fatideh",
    "gn:country_code":"IR",
    "gn:dem":-1,
    "gn:feature_class":"P",
    "gn:feature_code":"PPL",
    "gn:name":"Fat\u012bdeh",
    "gn:population":0,
    "gn:timezone":"Asia/Tehran",
    "iso:country":"IR",
    "name:fas_x_preferred":[
        "Fat\u012bdeh"
    ],
    "name:fas_x_variant":[
        "\u0641\u062a\u06cc\u062f\u0647"
    ],
    "name:msa_x_preferred":[
        "Fatideh"
    ],
    "name:ukr_x_preferred":[
        "\u0424\u0430\u0442\u0456\u0434\u0435"
    ],
    "name:und_x_variant":[
        "Fateydeh"
    ],
    "wof:name":"Fatideh",
    "wof:placetype":"locality"
},
  "geometry": {"coordinates":[50.2188,37.18655],"type":"Point"}
}