{
  "type": "Feature",
  "properties": {
    "gn:admin1_code":"40",
    "gn:asciiname":"Hasanabad",
    "gn:country_code":"IR",
    "gn:dem":1227,
    "gn:feature_class":"P",
    "gn:feature_code":"PPL",
    "gn:name":"\u1e28asan\u0101b\u0101d",
    "gn:population":0,
    "gn:timezone":"Asia/Tehran",
    "iso:country":"IR",
    "name:fas_x_preferred":[
        "\u0621\u064e\u0633\u064e\u0646 \u0622\u0628\u0627\u062f"
    ],
    "name:fas_x_variant":[
        "\u0647\u064e\u0633\u064e\u0646 \u0627\u064e\u0628\u064e\u062f \u0647\u064f\u0651\u0645\u0650\u0647",
        "\u2019asan\u0101b\u0101d",
        "\u1e28asan\u0101b\u0101d",
        "\u062d\u0633\u0646 \u0622\u0628\u0627\u062f"
    ],
    "name:und_x_variant":[
        "Hasan Abad Hoomeh"
    ],
    "wof:name":"Hasanabad",
    "wof:placetype":"locality"
},
  "geometry": {"coordinates":[54.4057,31.89666],"type":"Point"}
}