{
  "type": "Feature",
  "properties": {
    "gn:admin1_code":"13",
    "gn:asciiname":"Sararud-e Pa`in",
    "gn:country_code":"IR",
    "gn:dem":1364,
    "gn:feature_class":"P",
    "gn:feature_code":"PPL",
    "gn:name":"Sar\u0101r\u016bd-e P\u0101\u2018\u012bn",
    "gn:population":0,
    "gn:timezone":"Asia/Tehran",
    "iso:country":"IR",
    "name:ceb_x_preferred":[
        "Sar\u0101r\u016bd-e P\u0101\u2018\u012bn"
    ],
    "name:fas_x_preferred":[
        "\u0633\u0631\u0627\u0631\u0648\u062f \u067e\u0627\u0626\u06cc\u0646"
    ],
    "name:fas_x_variant":[
        "Sar\u0101r\u016bd-e Sofl\u00e1",
        "Sar\u0101r\u016bd-e P\u0101\u2018\u012bn",
        "\u0633\u0631\u0627\u0631\u0648\u062f \u0633\u0641\u0644\u06cc"
    ],
    "name:swe_x_preferred":[
        "Sar\u0101r\u016bd-e P\u0101\u2018\u012bn"
    ],
    "name:und_x_variant":[
        "Sar\u0101r\u016bd",
        "Sar\u0101r\u016b",
        "Sarar\u016bd-e P\u0101\u2019\u012bn"
    ],
    "wof:name":"Sararud-e Pa`in",
    "wof:placetype":"locality"
},
  "geometry": {"coordinates":[47.3237,34.3356],"type":"Point"}
}