{
  "type": "Feature",
  "properties": {
    "gn:admin1_code":"7",
    "gn:asciiname":"Gol Damcheh",
    "gn:country_code":"IR",
    "gn:dem":1011,
    "gn:feature_class":"P",
    "gn:feature_code":"PPL",
    "gn:name":"Gol D\u0101mcheh",
    "gn:population":0,
    "gn:timezone":"Asia/Tehran",
    "iso:country":"IR",
    "name:fas_x_preferred":[
        "\u06af\u0644\u062f\u0627\u0645\u0686\u0647"
    ],
    "name:fas_x_variant":[
        "Gold\u0101mcheh",
        "\u06af\u0644 \u062f\u0627\u0645\u0686\u0647"
    ],
    "name:und_x_variant":[
        "Gol D\u0101mcheh"
    ],
    "wof:name":"Gol Damcheh",
    "wof:placetype":"locality"
},
  "geometry": {"coordinates":[53.51962,28.64442],"type":"Point"}
}