{
  "type": "Feature",
  "properties": {
    "gn:admin1_code":"5.0",
    "gn:asciiname":"Kuy-e Karkonan-e Dowlat",
    "gn:country_code":"IR",
    "gn:dem":757,
    "gn:feature_class":"P",
    "gn:feature_code":"PPL",
    "gn:name":"K\u016by-e K\u0101rkon\u0101n-e Dowlat",
    "gn:population":0,
    "gn:timezone":"Asia/Tehran",
    "iso:country":"IR",
    "name:fas_x_preferred":[
        "\u06a9\u0648\u06cc \u06a9\u0627\u0631\u06a9\u0646\u0627\u0646 \u062f\u0648\u0644\u062a"
    ],
    "name:fas_x_variant":[
        "K\u016by-e K\u0101rkon\u0101n-e Dowlat"
    ],
    "wof:name":"Kuy-e Karkonan-e Dowlat",
    "wof:placetype":"locality"
},
  "geometry": {"coordinates":[50.75,30.3629],"type":"Point"}
}