{
  "type": "Feature",
  "properties": {
    "gn:admin1_code":"16",
    "gn:asciiname":"Cheshmeh Tatar",
    "gn:country_code":"IR",
    "gn:dem":1613,
    "gn:feature_class":"P",
    "gn:feature_code":"PPL",
    "gn:name":"Cheshmeh T\u0101t\u0101r",
    "gn:population":0,
    "gn:timezone":"Asia/Tehran",
    "iso:country":"IR",
    "name:azb_x_preferred":[
        "\u06a9\u0646\u062f \u062a\u0627\u062a\u0627\u0631"
    ],
    "name:fas_x_preferred":[
        "\u0686\u064e\u0634\u0645\u0650\u0647 \u062a\u0647\u0627\u062a\u0647\u0627\u0631"
    ],
    "name:fas_x_variant":[
        "\u0686\u0634\u0645\u0647 \u062a\u0627\u062a\u0627",
        "\u0643\u064e\u0646\u062f \u062a\u0627\u062a\u0627",
        "\u0686\u064e\u0634\u0645\u0650\u06c0 \u062a\u0627\u062a\u0650\u0647",
        "\u0643\u064e\u0646\u062f\u0650 \u062a\u0627\u062a\u0627\u0631",
        "\u0686\u0650\u0634\u0645\u0650\u06c0 \u062a\u0627\u062a\u0650\u0647",
        "Cheshmeh T\u0101t\u0101r",
        "Cheshmeh T\u0101t\u0101",
        "\u0686\u0634\u0645\u0647 \u062a\u0627\u062a\u0627\u0631",
        "\u06a9\u0646\u062f \u062a\u0627\u062a\u0627\u0631"
    ],
    "name:und_x_variant":[
        "Kand T\u0101t\u0101r",
        "Chashmeh Th\u0101th\u0101r",
        "Kand-e T\u0101t\u0101r",
        "Cheshmeh-ye T\u0101teh",
        "Kand T\u0101t\u0101",
        "Chashmeh-ye T\u0101teh"
    ],
    "wof:name":"Cheshmeh Tatar",
    "wof:placetype":"locality"
},
  "geometry": {"coordinates":[47.91195,35.89965],"type":"Point"}
}