{
  "type": "Feature",
  "properties": {
    "gn:admin1_code":"23",
    "gn:asciiname":"Kaliab",
    "gn:country_code":"IR",
    "gn:dem":1008,
    "gn:feature_class":"P",
    "gn:feature_code":"PPL",
    "gn:name":"K\u0101l\u012b\u0101b",
    "gn:population":0,
    "gn:timezone":"Asia/Tehran",
    "iso:country":"IR",
    "name:ara_x_preferred":[
        "\u0627\u062b\u0631\u0632\u0645\u064a\u0646 \u0643\u0627\u0644\u064a\u0627\u0628"
    ],
    "name:fas_x_preferred":[
        "\u0627\u064e\u062b\u064e\u0631 \u0632\u064e\u0645\u064a\u0646\u0650 \u0643\u0627\u0644\u064a\u0627\u0628"
    ],
    "name:fas_x_variant":[
        "\u0627\u062b\u0631 \u0632\u0645\u06cc\u0646",
        "As\u0304ar Zam\u012bn-e K\u0101l\u012b\u0101b",
        "As\u0304ar Zam\u012bn",
        "\u06a9\u0627\u0644\u06cc\u0627\u0628",
        "\u0627\u062b\u0631\u0632\u0645\u06cc\u0646 \u06a9\u0627\u0644\u06cc\u0627\u0628"
    ],
    "name:und_x_variant":[
        "K\u0101l\u012b\u0101b"
    ],
    "wof:name":"Kaliab",
    "wof:placetype":"locality"
},
  "geometry": {"coordinates":[47.8911,33.4699],"type":"Point"}
}