{
  "type": "Feature",
  "properties": {
    "gn:admin1_code":"29",
    "gn:asciiname":"Shuri",
    "gn:country_code":"IR",
    "gn:dem":667,
    "gn:feature_class":"P",
    "gn:feature_code":"PPL",
    "gn:name":"Sh\u016br\u012b",
    "gn:population":0,
    "gn:timezone":"Asia/Tehran",
    "iso:country":"IR",
    "name:ceb_x_preferred":[
        "Shuri"
    ],
    "name:deu_x_preferred":[
        "Shuri"
    ],
    "name:fas_x_preferred":[
        "\u0634\u0648\u0631\u06cc"
    ],
    "name:fas_x_variant":[
        "Sh\u016br\u012b"
    ],
    "name:pol_x_preferred":[
        "Shuri"
    ],
    "name:rus_x_preferred":[
        "\u0421\u044e\u0440\u0438"
    ],
    "wof:name":"Shuri",
    "wof:placetype":"locality"
},
  "geometry": {"coordinates":[57.5058,28.1499],"type":"Point"}
}