{
  "type": "Feature",
  "properties": {
    "gn:admin1_code":"10",
    "gn:asciiname":"Qazi Khan-e Sofla",
    "gn:country_code":"IR",
    "gn:dem":937,
    "gn:feature_class":"P",
    "gn:feature_code":"PPL",
    "gn:name":"Q\u0101\u1e95\u012b Kh\u0101n-e Sofl\u00e1",
    "gn:population":0,
    "gn:timezone":"Asia/Tehran",
    "iso:country":"IR",
    "name:ceb_x_preferred":[
        "Q\u0101\u1e95\u012b Kh\u0101n-e Sofl\u00e1"
    ],
    "name:fas_x_preferred":[
        "\u0642\u0627\u0636\u06cc \u062e\u0627\u0646 \u0633\u0641\u0644\u06cc"
    ],
    "name:fas_x_variant":[
        "Q\u0101\u1e95\u012b Kh\u0101n-e Sofl\u00e1"
    ],
    "name:msa_x_preferred":[
        "Qazi Khan-e Sofla"
    ],
    "name:swe_x_preferred":[
        "Q\u0101\u1e95\u012b Kh\u0101n-e Sofl\u00e1"
    ],
    "name:und_x_variant":[
        "Q\u0101\u1e95\u012b Kh\u0101n"
    ],
    "wof:name":"Qazi Khan-e Sofla",
    "wof:placetype":"locality"
},
  "geometry": {"coordinates":[46.9165,33.454],"type":"Point"}
}