{
  "type": "Feature",
  "properties": {
    "gn:admin1_code":"5",
    "gn:asciiname":"Hazim",
    "gn:country_code":"IR",
    "gn:dem":1806,
    "gn:feature_class":"P",
    "gn:feature_code":"PPL",
    "gn:name":"Haz\u012bm",
    "gn:population":0,
    "gn:timezone":"Asia/Tehran",
    "iso:country":"IR",
    "name:fas_x_preferred":[
        "\u0647\u064e\u0632\u064a\u0645"
    ],
    "wof:name":"Hazim",
    "wof:placetype":"locality"
},
  "geometry": {"coordinates":[51.12278,30.48278],"type":"Point"}
}