{
  "type": "Feature",
  "properties": {
    "gn:admin1_code":"9",
    "gn:asciiname":"Ommatlar",
    "gn:country_code":"IR",
    "gn:dem":1891,
    "gn:feature_class":"P",
    "gn:feature_code":"PPL",
    "gn:name":"Ommatlar",
    "gn:population":0,
    "gn:timezone":"Asia/Tehran",
    "iso:country":"IR",
    "name:fas_x_preferred":[
        "\u0627\u0645\u062a\u0644\u0631"
    ],
    "name:msa_x_preferred":[
        "Ommatlar"
    ],
    "name:und_x_variant":[
        "Ammatlar",
        "Amatlar",
        "Ommatlar"
    ],
    "wof:name":"Ommatlar",
    "wof:placetype":"locality"
},
  "geometry": {"coordinates":[48.96694,35.4365],"type":"Point"}
}