{
  "type": "Feature",
  "properties": {
    "gn:admin1_code":"8",
    "gn:asciiname":"Sarleyl",
    "gn:country_code":"IR",
    "gn:dem":526,
    "gn:feature_class":"P",
    "gn:feature_code":"PPL",
    "gn:name":"Sarleyl",
    "gn:population":0,
    "gn:timezone":"Asia/Tehran",
    "iso:country":"IR",
    "name:fas_x_preferred":[
        "\u0633\u0631\u0644\u06cc\u0644"
    ],
    "name:fas_x_variant":[
        "\u0633\u0631\u0644\u06cc\u0644\u06cc"
    ],
    "name:und_x_variant":[
        "\u0633\u0631\u0644\u06cc\u0644",
        "Sarleyl\u012b"
    ],
    "wof:name":"Sarleyl",
    "wof:placetype":"locality"
},
  "geometry": {"coordinates":[50.04506,37.01177],"type":"Point"}
}