{
  "type": "Feature",
  "properties": {
    "gn:admin1_code":"33",
    "gn:asciiname":"Qareh Chay-e Naqshineh",
    "gn:country_code":"IR",
    "gn:dem":1996,
    "gn:feature_class":"P",
    "gn:feature_code":"PPL",
    "gn:name":"Qareh Ch\u0101y-e Naqsh\u012bneh",
    "gn:population":0,
    "gn:timezone":"Asia/Tehran",
    "iso:country":"IR",
    "name:fas_x_preferred":[
        "\u0642\u0631\u0647 \u0686\u0627\u06cc \u0646\u0642\u0634\u06cc"
    ],
    "name:fas_x_variant":[
        "\u0642\u0631\u0647 \u0686\u0627\u06cc \u0646\u0642\u0634\u06cc\u0646\u0647"
    ],
    "name:und_x_variant":[
        "Qareh Ch\u0101y-e Naqsh\u012bneh",
        "Qareh Ch\u0101y-e Naqsh\u012b"
    ],
    "wof:name":"Qareh Chay-e Naqshineh",
    "wof:placetype":"locality"
},
  "geometry": {"coordinates":[46.908,37.6918],"type":"Point"}
}