{
  "type": "Feature",
  "properties": {
    "gn:admin1_code":"4.0",
    "gn:asciiname":"Hiduch",
    "gn:country_code":"IR",
    "gn:dem":1230,
    "gn:feature_class":"P",
    "gn:feature_code":"PPL",
    "gn:name":"H\u012bd\u016bch",
    "gn:population":0,
    "gn:timezone":"Asia/Tehran",
    "iso:country":"IR",
    "name:ara_x_preferred":[
        "\u0647\u064a\u062f\u0648\u062a\u0634"
    ],
    "name:aze_x_preferred":[
        "Hiduc"
    ],
    "name:ceb_x_preferred":[
        "H\u012bd\u016bj-e P\u0101'\u012bn"
    ],
    "name:fas_x_preferred":[
        "\u0647\u06cc\u062f\u0648\u062c \u067e\u0627\u0626\u06cc\u0646"
    ],
    "name:fas_x_variant":[
        "H\u012bdach",
        "H\u012bd\u016bj",
        "H\u012bd\u016bj-e P\u0101\u2019\u012bn",
        "\u0647\u06cc\u062f\u0648\u0686",
        "\u0647\u06cc\u062f\u0648\u062c"
    ],
    "name:ita_x_preferred":[
        "Hiduch"
    ],
    "name:mlg_x_preferred":[
        "Hiduj"
    ],
    "name:swe_x_preferred":[
        "H\u012bd\u016bj-e P\u0101'\u012bn"
    ],
    "name:tur_x_preferred":[
        "Hiduc"
    ],
    "name:und_x_variant":[
        "\u012adoj-e P\u0101\u2019\u012bn",
        "Hindugeh",
        "Hiduch",
        "H\u012bd\u016bch"
    ],
    "wof:name":"Hiduch",
    "wof:placetype":"locality"
},
  "geometry": {"coordinates":[62.11779,27.00048],"type":"Point"}
}