{
  "type": "Feature",
  "properties": {
    "gn:admin1_code":"4",
    "gn:asciiname":"Cheshmeh Suba'i",
    "gn:country_code":"IR",
    "gn:dem":1404,
    "gn:feature_class":"P",
    "gn:feature_code":"PPL",
    "gn:name":"Cheshmeh S\u016bb\u0101\u2019\u012b",
    "gn:population":0,
    "gn:timezone":"Asia/Tehran",
    "iso:country":"IR",
    "name:fas_x_preferred":[
        "\u0686\u0634\u0645\u0647 \u0633\u0648\u0628\u0627\u0626\u06cc"
    ],
    "name:fas_x_variant":[
        "Cheshmeh S\u016bb\u0101\u2019\u012b"
    ],
    "wof:name":"Cheshmeh Suba'i",
    "wof:placetype":"locality"
},
  "geometry": {"coordinates":[60.8853,28.0313],"type":"Point"}
}