{
  "type": "Feature",
  "properties": {
    "gn:admin1_code":"8",
    "gn:asciiname":"Haviq",
    "gn:country_code":"IR",
    "gn:dem":-7,
    "gn:feature_class":"P",
    "gn:feature_code":"PPL",
    "gn:name":"\u1e28av\u012bq",
    "gn:population":0,
    "gn:timezone":"Asia/Tehran",
    "iso:country":"IR",
    "name:ara_x_preferred":[
        "\u062d\u0648\u064a\u0642"
    ],
    "name:aze_x_preferred":[
        "H\u0259viq"
    ],
    "name:ceb_x_preferred":[
        "\u1e28av\u012bq"
    ],
    "name:fas_x_preferred":[
        "\u062d\u0648\u06cc\u0642"
    ],
    "name:fas_x_variant":[
        "\u1e28av\u012bq"
    ],
    "name:mlg_x_preferred":[
        "Haviq"
    ],
    "name:msa_x_preferred":[
        "Haviq"
    ],
    "name:swe_x_preferred":[
        "\u1e28av\u012bq"
    ],
    "name:und_x_variant":[
        "Hevik"
    ],
    "wof:name":"Haviq",
    "wof:placetype":"locality"
},
  "geometry": {"coordinates":[48.8921,38.1476],"type":"Point"}
}