{
  "type": "Feature",
  "properties": {
    "gn:admin1_code":"23",
    "gn:asciiname":"Kenar Takhteh",
    "gn:country_code":"IR",
    "gn:dem":1654,
    "gn:feature_class":"P",
    "gn:feature_code":"PPL",
    "gn:name":"Ken\u0101r Takhteh",
    "gn:population":0,
    "gn:timezone":"Asia/Tehran",
    "iso:country":"IR",
    "name:fas_x_preferred":[
        "\u0686\u0647\u0627\u0631 \u062a\u062e\u062a\u0647"
    ],
    "name:fas_x_variant":[
        "Chah\u0101r Takhteh",
        "\u06a9\u0646\u0627\u0631 \u062a\u062e\u062a\u0647"
    ],
    "name:und_x_variant":[
        "Ken\u0101r Takhteh"
    ],
    "wof:name":"Kenar Takhteh",
    "wof:placetype":"locality"
},
  "geometry": {"coordinates":[48.30189,33.7962],"type":"Point"}
}