{
  "type": "Feature",
  "properties": {
    "gn:admin1_code":"22.0",
    "gn:asciiname":"Soheyl",
    "gn:country_code":"IR",
    "gn:dem":11,
    "gn:feature_class":"P",
    "gn:feature_code":"PPL",
    "gn:name":"Soheyl",
    "gn:population":0,
    "gn:timezone":"Asia/Tehran",
    "iso:country":"IR",
    "name:fas_x_preferred":[
        "\u0633\u0647\u0644"
    ],
    "name:fas_x_variant":[
        "\u0633\u0647\u06cc\u0644"
    ],
    "name:und_x_variant":[
        "Sahl",
        "Soheyl"
    ],
    "wof:name":"Soheyl",
    "wof:placetype":"locality"
},
  "geometry": {"coordinates":[52.48724,27.61647],"type":"Point"}
}