{
  "type": "Feature",
  "properties": {
    "gn:admin1_code":"7",
    "gn:asciiname":"Tis Khani",
    "gn:country_code":"IR",
    "gn:dem":2020,
    "gn:feature_class":"P",
    "gn:feature_code":"PPL",
    "gn:name":"T\u012bs Kh\u0101n\u012b",
    "gn:population":0,
    "gn:timezone":"Asia/Tehran",
    "iso:country":"IR",
    "name:fas_x_preferred":[
        "\u062a\u06cc\u0632 \u062e\u0627\u0646\u06cc"
    ],
    "name:fas_x_variant":[
        "Qal\u2018eh-ye \u0162\u012bzkh\u0101n\u012b",
        "T\u012bz Kh\u0101n\u012b",
        "\u062a\u06cc\u0633 \u062e\u0627\u0646\u06cc"
    ],
    "name:und_x_variant":[
        "T\u012bskh\u0101n\u012b",
        "T\u012bs Kh\u0101n\u012b"
    ],
    "wof:name":"Tis Khani",
    "wof:placetype":"locality"
},
  "geometry": {"coordinates":[52.0948,30.1148],"type":"Point"}
}