{
  "type": "Feature",
  "properties": {
    "gn:admin1_code":"39.0",
    "gn:asciiname":"Mowmenabad",
    "gn:country_code":"IR",
    "gn:dem":870,
    "gn:feature_class":"P",
    "gn:feature_code":"PPL",
    "gn:name":"Mowmen\u0101b\u0101d",
    "gn:population":0,
    "gn:timezone":"Asia/Tehran",
    "iso:country":"IR",
    "name:fas_x_preferred":[
        "\u0645\u064f\u0621\u0645\u0650\u0646 \u0622\u0628\u0627\u062f"
    ],
    "name:fas_x_variant":[
        "\u0645\u0648\u0645\u0646 \u0622\u0628\u0627\u062f",
        "Mo\u2019men\u0101b\u0101d",
        "\u0645\u0624\u0645\u0646\u200c\u0622\u0628\u0627\u062f"
    ],
    "name:und_x_variant":[
        "Mowmen\u0101b\u0101d"
    ],
    "wof:name":"Mowmenabad",
    "wof:placetype":"locality"
},
  "geometry": {"coordinates":[51.0607,34.606],"type":"Point"}
}