{
  "type": "Feature",
  "properties": {
    "gn:admin1_code":"37",
    "gn:asciiname":"Siah Rudbar",
    "gn:country_code":"IR",
    "gn:dem":788,
    "gn:feature_class":"P",
    "gn:feature_code":"PPL",
    "gn:name":"S\u012b\u0101h R\u016bdb\u0101r",
    "gn:population":0,
    "gn:timezone":"Asia/Tehran",
    "iso:country":"IR",
    "name:ara_x_preferred":[
        "\u0633\u064a\u0627\u0647 \u0631\u0648\u062f\u0628\u0627\u0631"
    ],
    "name:fas_x_preferred":[
        "\u0633\u064a\u0627\u0647 \u0631\u0648\u062f\u0628\u0627\u0631"
    ],
    "name:fas_x_variant":[
        "S\u012b\u0101h R\u016bdb\u0101r",
        "\u0633\u06cc\u0627\u0647\u200c\u0631\u0648\u062f\u0628\u0627\u0631"
    ],
    "name:msa_x_preferred":[
        "Siah Rudbar"
    ],
    "wof:name":"Siah Rudbar",
    "wof:placetype":"locality"
},
  "geometry": {"coordinates":[55.0461,36.81693],"type":"Point"}
}