{
  "type": "Feature",
  "properties": {
    "gn:admin1_code":"42.0",
    "gn:asciiname":"Qal`eh Hammam-e Hajji Rasul",
    "gn:country_code":"IR",
    "gn:dem":1034,
    "gn:feature_class":"P",
    "gn:feature_code":"PPL",
    "gn:name":"Qal\u2018eh \u1e28amm\u0101m-e \u1e28\u0101jj\u012b Ras\u016bl",
    "gn:population":0,
    "gn:timezone":"Asia/Tehran",
    "iso:country":"IR",
    "name:fas_x_preferred":[
        "Qal\u2018eh \u1e28amm\u0101m-e \u1e28\u0101jj\u012b Ras\u016bl"
    ],
    "name:fas_x_variant":[
        "Qal\u2018eh \u1e28amm\u0101m",
        "\u0642\u0644\u0639\u0647 \u062d\u0645\u0627\u0645 \u062d\u0627\u062c\u06cc \u0631\u0633\u0648\u0644"
    ],
    "name:und_x_variant":[
        "Ham\u0101mi",
        "Qal\u2018eh-ye \u1e28amm\u0101m",
        "Qal\u2018eh-ye \u1e28amm\u0101m Ras\u016bl"
    ],
    "wof:name":"Qal`eh Hammam-e Hajji Rasul",
    "wof:placetype":"locality"
},
  "geometry": {"coordinates":[60.75541,35.80173],"type":"Point"}
}