{
  "type": "Feature",
  "properties": {
    "gn:admin1_code":"13.0",
    "gn:asciiname":"Pur Hasan",
    "gn:country_code":"IR",
    "gn:dem":1158,
    "gn:feature_class":"P",
    "gn:feature_code":"PPL",
    "gn:name":"P\u016br \u1e28asan",
    "gn:population":0,
    "gn:timezone":"Asia/Tehran",
    "iso:country":"IR",
    "name:fas_x_preferred":[
        "\u067e\u0648\u0631\u062d\u0633\u0646"
    ],
    "name:fas_x_variant":[
        "P\u016br \u1e28asan"
    ],
    "wof:name":"Pur Hasan",
    "wof:placetype":"locality"
},
  "geometry": {"coordinates":[46.0386,34.3179],"type":"Point"}
}