{
  "type": "Feature",
  "properties": {
    "gn:admin1_code":"23.0",
    "gn:asciiname":"Shahabad",
    "gn:country_code":"IR",
    "gn:dem":1569,
    "gn:feature_class":"P",
    "gn:feature_code":"PPL",
    "gn:name":"Sh\u0101h\u0101b\u0101d",
    "gn:population":0,
    "gn:timezone":"Asia/Tehran",
    "iso:country":"IR",
    "name:fas_x_preferred":[
        "\u0634\u0627\u0647 \u0622\u0628\u0627\u062f"
    ],
    "name:und_x_variant":[
        "Sh\u0101h\u0101b\u0101d"
    ],
    "wof:name":"Shahabad",
    "wof:placetype":"locality"
},
  "geometry": {"coordinates":[48.2579,33.83042],"type":"Point"}
}