{
  "type": "Feature",
  "properties": {
    "gn:admin1_code":"4.0",
    "gn:asciiname":"Safdar-e Mir",
    "gn:country_code":"IR",
    "gn:dem":482,
    "gn:feature_class":"P",
    "gn:feature_code":"PPL",
    "gn:name":"\u015eafdar-e M\u012br",
    "gn:population":0,
    "gn:timezone":"Asia/Tehran",
    "iso:country":"IR",
    "name:fas_x_preferred":[
        "\u015eafdar-e M\u012br"
    ],
    "wof:name":"Safdar-e Mir",
    "wof:placetype":"locality"
},
  "geometry": {"coordinates":[61.55,30.88333],"type":"Point"}
}