{
  "type": "Feature",
  "properties": {
    "gn:admin1_code":"5",
    "gn:asciiname":"Kaveh Badam",
    "gn:country_code":"IR",
    "gn:dem":2039,
    "gn:feature_class":"P",
    "gn:feature_code":"PPL",
    "gn:name":"K\u0101veh B\u0101d\u0101m",
    "gn:population":0,
    "gn:timezone":"Asia/Tehran",
    "iso:country":"IR",
    "name:fas_x_preferred":[
        "\u062a\u0627\u0648\u064a\u0650\u0647 \u0628\u0627\u062f\u064f\u0645"
    ],
    "name:fas_x_variant":[
        "K\u0101veh B\u0101d\u0101m",
        "T\u0101v\u012beh B\u0101dom",
        "\u06a9\u0627\u0648\u0647 \u0628\u0627\u062f\u0627\u0645"
    ],
    "name:und_x_variant":[
        "\u06a9\u0627\u0648\u0647 \u0628\u0627\u062f\u0627\u0645"
    ],
    "wof:name":"Kaveh Badam",
    "wof:placetype":"locality"
},
  "geometry": {"coordinates":[51.47293,30.64409],"type":"Point"}
}