{
  "type": "Feature",
  "properties": {
    "gn:admin1_code":"41",
    "gn:asciiname":"Mu Gerd",
    "gn:country_code":"IR",
    "gn:dem":1926,
    "gn:feature_class":"P",
    "gn:feature_code":"PPL",
    "gn:name":"M\u016b Gerd",
    "gn:population":0,
    "gn:timezone":"Asia/Tehran",
    "iso:country":"IR",
    "name:fas_x_preferred":[
        "M\u016b Gerd"
    ],
    "name:fas_x_variant":[
        "\u0645\u0648 \u06af\u0631\u062f"
    ],
    "name:und_x_variant":[
        "\u0645\u0648 \u06af\u0631\u062f"
    ],
    "wof:name":"Mu Gerd",
    "wof:placetype":"locality"
},
  "geometry": {"coordinates":[59.35247,33.07171],"type":"Point"}
}