{
  "type": "Feature",
  "properties": {
    "gn:admin1_code":"4.0",
    "gn:asciiname":"Yusef Salam",
    "gn:country_code":"IR",
    "gn:dem":485,
    "gn:feature_class":"P",
    "gn:feature_code":"PPL",
    "gn:name":"Y\u016bsef Sal\u0101m",
    "gn:population":0,
    "gn:timezone":"Asia/Tehran",
    "iso:country":"IR",
    "name:fas_x_preferred":[
        "\u06cc\u0648\u0633\u0641 \u0633\u0644\u0627\u0645"
    ],
    "name:fas_x_variant":[
        "Y\u016bsef-e Esl\u0101m",
        "Y\u016bsef Sal\u0101m",
        "\u06cc\u0648\u0633\u0641 \u0627\u0633\u0644\u0627\u0645"
    ],
    "name:und_x_variant":[
        "Y\u016bsof Sal\u0101m"
    ],
    "name:urd_x_preferred":[
        "\u06cc\u0648\u0633\u0641-\u0627\u0633\u0644\u0645"
    ],
    "wof:name":"Yusef Salam",
    "wof:placetype":"locality"
},
  "geometry": {"coordinates":[61.74867,31.14742],"type":"Point"}
}