{
  "type": "Feature",
  "properties": {
    "gn:admin1_code":"42",
    "gn:asciiname":"Samadiyeh",
    "gn:country_code":"IR",
    "gn:dem":1159,
    "gn:feature_class":"P",
    "gn:feature_code":"PPL",
    "gn:name":"\u015eamad\u012byeh",
    "gn:population":0,
    "gn:timezone":"Asia/Tehran",
    "iso:country":"IR",
    "name:fas_x_preferred":[
        "\u0635\u0645\u062f\u06cc\u0647"
    ],
    "name:fas_x_variant":[
        "\u015eamad\u012byeh"
    ],
    "wof:name":"Samadiyeh",
    "wof:placetype":"locality"
},
  "geometry": {"coordinates":[58.78596,36.02066],"type":"Point"}
}