{
  "type": "Feature",
  "properties": {
    "gn:admin1_code":"8.0",
    "gn:asciiname":"Shalesh",
    "gn:country_code":"IR",
    "gn:dem":488,
    "gn:feature_class":"P",
    "gn:feature_code":"PPL",
    "gn:name":"Sh\u0101lesh",
    "gn:population":0,
    "gn:timezone":"Asia/Tehran",
    "iso:country":"IR",
    "name:fas_x_preferred":[
        "\u0634\u0627\u0644\u0634"
    ],
    "name:und_x_variant":[
        "Sh\u0101lesh"
    ],
    "wof:name":"Shalesh",
    "wof:placetype":"locality"
},
  "geometry": {"coordinates":[49.25085,37.0095],"type":"Point"}
}