{
  "type": "Feature",
  "properties": {
    "gn:admin1_code":"11",
    "gn:asciiname":"Gav Bandi",
    "gn:country_code":"IR",
    "gn:dem":8,
    "gn:feature_class":"P",
    "gn:feature_code":"PPL",
    "gn:name":"G\u0101v Band\u012b",
    "gn:population":0,
    "gn:timezone":"Asia/Tehran",
    "iso:country":"IR",
    "name:ceb_x_preferred":[
        "G\u0101v Band\u012b"
    ],
    "name:fas_x_preferred":[
        "G\u0101v Band\u012b"
    ],
    "name:fas_x_variant":[
        "\u06af\u0627\u0648 \u0628\u0646\u062f\u06cc",
        "\u06af\u0627\u0648\u0628\u0646\u062f\u06cc"
    ],
    "name:msa_x_preferred":[
        "Gav Bandi"
    ],
    "name:swe_x_preferred":[
        "G\u0101v Band\u012b"
    ],
    "name:und_x_variant":[
        "\u06af\u0627\u0648 \u0628\u0646\u062f\u06cc"
    ],
    "wof:name":"Gav Bandi",
    "wof:placetype":"locality"
},
  "geometry": {"coordinates":[57.50496999999999,25.81512],"type":"Point"}
}