{
  "type": "Feature",
  "properties": {
    "gn:admin1_code":"9",
    "gn:asciiname":"Mahalleh-ye Eslamabad-e Qal`eh Qazi",
    "gn:country_code":"IR",
    "gn:dem":1769,
    "gn:feature_class":"P",
    "gn:feature_code":"PPL",
    "gn:name":"Ma\u1e29alleh-ye Esl\u0101m\u0101b\u0101d-e Qal\u2018eh Q\u0101\u1e95\u012b",
    "gn:population":0,
    "gn:timezone":"Asia/Tehran",
    "iso:country":"IR",
    "name:fas_x_preferred":[
        "\u0642\u064e\u0644\u0639\u0650\u0647 \u0642\u0627\u0632\u06cc"
    ],
    "name:fas_x_variant":[
        "Qal\u2018eh Q\u0101\u1e95\u012b",
        "\u0642\u0644\u0639\u0647 \u0642\u0627\u0636\u06cc",
        "\u0645\u062d\u0644\u0647 \u0627\u0633\u0644\u0627\u0645 \u0622\u0628\u0627\u062f \u0642\u0644\u0639\u0647 \u0642\u0627\u0636\u06cc"
    ],
    "name:und_x_variant":[
        "Ma\u1e29alleh-ye Esl\u0101m\u0101b\u0101d-e Qal\u2018eh Q\u0101\u1e95\u012b"
    ],
    "wof:name":"Mahalleh-ye Eslamabad-e Qal`eh Qazi",
    "wof:placetype":"locality"
},
  "geometry": {"coordinates":[48.43182,34.53505999999999],"type":"Point"}
}