{
  "type": "Feature",
  "properties": {
    "gn:admin1_code":"9.0",
    "gn:asciiname":"Baba `Ali",
    "gn:country_code":"IR",
    "gn:dem":2031,
    "gn:feature_class":"P",
    "gn:feature_code":"PPL",
    "gn:name":"B\u0101b\u0101 \u2018Al\u012b",
    "gn:population":0,
    "gn:timezone":"Asia/Tehran",
    "iso:country":"IR",
    "name:ara_x_preferred":[
        "\u0628\u0627\u0628\u0627 \u0639\u0644\u064a"
    ],
    "name:azb_x_preferred":[
        "\u0628\u0627\u0628\u0627\u0639\u0644\u06cc"
    ],
    "name:fas_x_preferred":[
        "\u0628\u0627\u0628\u0627 \u0639\u064e\u0644\u06cc"
    ],
    "name:fas_x_variant":[
        "B\u0101b\u0101 \u2018Al\u012b",
        "\u0628\u0627\u0628\u0627 \u0639\u0644\u06cc",
        "\u0628\u0627\u0628\u0627\u0639\u0644\u06cc"
    ],
    "name:msa_x_preferred":[
        "Baba Ali"
    ],
    "wof:name":"Baba `Ali",
    "wof:placetype":"locality"
},
  "geometry": {"coordinates":[48.2094,34.93484],"type":"Point"}
}