{
  "type": "Feature",
  "properties": {
    "gn:admin1_code":"29",
    "gn:asciiname":"Sabzdasht-e Sirus",
    "gn:country_code":"IR",
    "gn:dem":1730,
    "gn:feature_class":"P",
    "gn:feature_code":"PPL",
    "gn:name":"Sabzdasht-e S\u012br\u016bs",
    "gn:population":0,
    "gn:timezone":"Asia/Tehran",
    "iso:country":"IR",
    "name:fas_x_preferred":[
        "Sabzdasht-e S\u012br\u016bs"
    ],
    "wof:name":"Sabzdasht-e Sirus",
    "wof:placetype":"locality"
},
  "geometry": {"coordinates":[55.93083000000001,29.13639],"type":"Point"}
}