{
  "type": "Feature",
  "properties": {
    "gn:admin1_code":"28.0",
    "gn:asciiname":"Karavieh",
    "gn:country_code":"IR",
    "gn:dem":1620,
    "gn:feature_class":"P",
    "gn:feature_code":"PPL",
    "gn:name":"K\u0101rav\u012beh",
    "gn:population":0,
    "gn:timezone":"Asia/Tehran",
    "iso:country":"IR",
    "name:fas_x_preferred":[
        "\u06a9\u0627\u0631\u0648\u06cc\u0647"
    ],
    "name:fas_x_variant":[
        "K\u0101rav\u012beh"
    ],
    "wof:name":"Karavieh",
    "wof:placetype":"locality"
},
  "geometry": {"coordinates":[51.4786,32.5001],"type":"Point"}
}