{
  "type": "Feature",
  "properties": {
    "gn:admin1_code":"22",
    "gn:asciiname":"Sar Korreh",
    "gn:country_code":"IR",
    "gn:dem":64,
    "gn:feature_class":"P",
    "gn:feature_code":"PPL",
    "gn:name":"Sar Korreh",
    "gn:population":0,
    "gn:timezone":"Asia/Tehran",
    "iso:country":"IR",
    "name:ara_x_preferred":[
        "\u0633\u0631\u0643\u0631\u0629"
    ],
    "name:fas_x_preferred":[
        "\u0633\u0631 \u0643\u0631\u0647"
    ],
    "name:fas_x_variant":[
        "\u0633\u064e\u0631 \u0643\u0648\u0631\u0650\u0647",
        "\u0633\u0631\u06a9\u0631\u0647"
    ],
    "name:msa_x_preferred":[
        "Sar Korreh"
    ],
    "name:und_x_variant":[
        "Sar K\u016breh",
        "Sarkurreh",
        "Sarkorreh"
    ],
    "wof:name":"Sar Korreh",
    "wof:placetype":"locality"
},
  "geometry": {"coordinates":[51.2094,29.1955],"type":"Point"}
}