{
  "type": "Feature",
  "properties": {
    "gn:admin1_code":"29",
    "gn:asciiname":"Bideshak",
    "gn:country_code":"IR",
    "gn:dem":2073,
    "gn:feature_class":"P",
    "gn:feature_code":"PPL",
    "gn:name":"B\u012bdeshak",
    "gn:population":0,
    "gn:timezone":"Asia/Tehran",
    "iso:country":"IR",
    "name:fas_x_preferred":[
        "\u0628\u06cc\u062f\u0634\u06a9"
    ],
    "name:fas_x_variant":[
        "B\u012bdeshk",
        "B\u012bdeshak"
    ],
    "name:und_x_variant":[
        "Bidashk",
        "Bidishk"
    ],
    "wof:name":"Bideshak",
    "wof:placetype":"locality"
},
  "geometry": {"coordinates":[56.16602,28.92251],"type":"Point"}
}