{
  "type": "Feature",
  "properties": {
    "gn:admin1_code":"15.0",
    "gn:asciiname":"Far` Zayer",
    "gn:country_code":"IR",
    "gn:dem":4,
    "gn:feature_class":"P",
    "gn:feature_code":"PPL",
    "gn:name":"Far\u2018 Z\u0101yer",
    "gn:population":0,
    "gn:timezone":"Asia/Tehran",
    "iso:country":"IR",
    "name:ara_x_preferred":[
        "\u0641\u0631\u0642 \u0632\u0627\u064a\u0631"
    ],
    "name:ceb_x_preferred":[
        "Fargh Z\u0101yer"
    ],
    "name:fas_x_preferred":[
        "Fargh Z\u0101yer"
    ],
    "name:fas_x_variant":[
        "\u0641\u0631\u063a \u0632\u0627\u06cc\u0631",
        "\u0641\u0631\u0639 \u0632\u0627\u06cc\u0631"
    ],
    "name:swe_x_preferred":[
        "Fargh Z\u0101yer"
    ],
    "name:und_x_variant":[
        "Far\u2018 Z\u0101yer"
    ],
    "wof:name":"Far` Zayer",
    "wof:placetype":"locality"
},
  "geometry": {"coordinates":[48.63145,30.66871],"type":"Point"}
}