{
  "type": "Feature",
  "properties": {
    "gn:admin1_code":"8",
    "gn:asciiname":"Gotag Sar",
    "gn:country_code":"IR",
    "gn:dem":-21,
    "gn:feature_class":"P",
    "gn:feature_code":"PPL",
    "gn:name":"Gotag Sar",
    "gn:population":0,
    "gn:timezone":"Asia/Tehran",
    "iso:country":"IR",
    "name:fas_x_preferred":[
        "\u06af\u062a\u06af \u0633\u0631\u0627"
    ],
    "name:fas_x_variant":[
        "Getge Sar\u0101",
        "\u06af\u062a\u06af \u0633\u0631"
    ],
    "name:und_x_variant":[
        "Kangeh Sar\u0101y",
        "Gatkah Sar\u0101i",
        "Gotag Sar\u0101",
        "Gatka-Saray",
        "Gatkasar\u0101",
        "Gatgesar",
        "Gotag Sar"
    ],
    "wof:name":"Gotag Sar",
    "wof:placetype":"locality"
},
  "geometry": {"coordinates":[49.032,37.6862],"type":"Point"}
}