{
  "type": "Feature",
  "properties": {
    "gn:admin1_code":"23",
    "gn:asciiname":"Kondar",
    "gn:country_code":"IR",
    "gn:dem":2153,
    "gn:feature_class":"P",
    "gn:feature_code":"PPL",
    "gn:name":"Kondar",
    "gn:population":0,
    "gn:timezone":"Asia/Tehran",
    "iso:country":"IR",
    "name:fas_x_preferred":[
        "\u06a9\u0646\u062f\u0631"
    ],
    "name:und_x_variant":[
        "Kundar",
        "\u06a9\u0646\u062f\u0631",
        "Kondor",
        "Kondar"
    ],
    "wof:name":"Kondar",
    "wof:placetype":"locality"
},
  "geometry": {"coordinates":[49.69504000000001,33.52718],"type":"Point"}
}