{
  "type": "Feature",
  "properties": {
    "gn:admin1_code":"29",
    "gn:asciiname":"Kaleh Kuhi",
    "gn:country_code":"IR",
    "gn:dem":2469,
    "gn:feature_class":"P",
    "gn:feature_code":"PPL",
    "gn:name":"Kaleh K\u016bh\u012b",
    "gn:population":0,
    "gn:timezone":"Asia/Tehran",
    "iso:country":"IR",
    "name:fas_x_preferred":[
        "\u06a9\u0644\u0647 \u06a9\u0648\u0647\u06cc"
    ],
    "name:fas_x_variant":[
        "Kaleh K\u016bh\u012b"
    ],
    "wof:name":"Kaleh Kuhi",
    "wof:placetype":"locality"
},
  "geometry": {"coordinates":[56.2381,29.853],"type":"Point"}
}