{
  "type": "Feature",
  "properties": {
    "gn:admin1_code":"22.0",
    "gn:asciiname":"Pakuh",
    "gn:country_code":"IR",
    "gn:dem":773,
    "gn:feature_class":"P",
    "gn:feature_code":"PPL",
    "gn:name":"P\u0101k\u016bh",
    "gn:population":0,
    "gn:timezone":"Asia/Tehran",
    "iso:country":"IR",
    "name:fas_x_preferred":[
        "\u067e\u0627\u0643\u0648\u0647"
    ],
    "name:fas_x_variant":[
        "\u067e\u0643\u0648\u0647",
        "P\u0101k\u016bh"
    ],
    "name:und_x_variant":[
        "Pak\u016bh"
    ],
    "wof:name":"Pakuh",
    "wof:placetype":"locality"
},
  "geometry": {"coordinates":[52.4054,27.7858],"type":"Point"}
}