{
  "type": "Feature",
  "properties": {
    "gn:admin1_code":"9",
    "gn:asciiname":"Shahrak-e Shahid Qodusi",
    "gn:country_code":"IR",
    "gn:dem":1588,
    "gn:feature_class":"P",
    "gn:feature_code":"PPL",
    "gn:name":"Shahrak-e Shah\u012bd Qod\u016bs\u012b",
    "gn:population":0,
    "gn:timezone":"Asia/Tehran",
    "iso:country":"IR",
    "name:fas_x_preferred":[
        "\u0634\u0647\u0631\u06a9 \u0642\u062f\u0648\u0633"
    ],
    "name:fas_x_variant":[
        "\u0634\u0647\u0631\u06a9 \u0634\u0647\u06cc\u062f \u0642\u062f\u0648\u0633\u06cc"
    ],
    "name:und_x_variant":[
        "Shahrak-e Qod\u016bs",
        "Shahrak-e Shah\u012bd Qod\u016bs\u012b"
    ],
    "wof:name":"Shahrak-e Shahid Qodusi",
    "wof:placetype":"locality"
},
  "geometry": {"coordinates":[48.33427,34.23317],"type":"Point"}
}