{
  "type": "Feature",
  "properties": {
    "gn:admin1_code":"29",
    "gn:asciiname":"Sohrengan",
    "gn:country_code":"IR",
    "gn:dem":735,
    "gn:feature_class":"P",
    "gn:feature_code":"PPL",
    "gn:name":"Sohreng\u0101n",
    "gn:population":0,
    "gn:timezone":"Asia/Tehran",
    "iso:country":"IR",
    "name:fas_x_preferred":[
        "Sohreng\u0101n"
    ],
    "wof:name":"Sohrengan",
    "wof:placetype":"locality"
},
  "geometry": {"coordinates":[57.72861,27.16667],"type":"Point"}
}