{
  "type": "Feature",
  "properties": {
    "gn:admin1_code":"1",
    "gn:asciiname":"Jabbar Kandi",
    "gn:country_code":"IR",
    "gn:dem":2042,
    "gn:feature_class":"P",
    "gn:feature_code":"PPL",
    "gn:name":"Jabb\u0101r Kand\u012b",
    "gn:population":0,
    "gn:timezone":"Asia/Tehran",
    "iso:country":"IR",
    "name:ara_x_preferred":[
        "\u062c\u0628\u0627\u0631\u0643\u0646\u062f\u064a"
    ],
    "name:aze_x_preferred":[
        "Cabbar k\u0259ndi"
    ],
    "name:fas_x_preferred":[
        "\u062c\u064e\u0628\u0651\u0627\u0631 \u0643\u064e\u0646\u062f\u06cc"
    ],
    "name:fas_x_variant":[
        "\u062c\u0628\u0651\u0627\u0631 \u06a9\u0646\u062f\u06cc",
        "Jabb\u0101r Kand\u012b",
        "\u062c\u0628\u0627\u0631\u06a9\u0646\u062f\u06cc"
    ],
    "name:msa_x_preferred":[
        "Jabbar Kandi"
    ],
    "name:urd_x_preferred":[
        "\u062c\u0628\u0627\u0631 \u06a9\u0646\u062f\u06cc"
    ],
    "wof:name":"Jabbar Kandi",
    "wof:placetype":"locality"
},
  "geometry": {"coordinates":[44.4841,39.0353],"type":"Point"}
}