{
  "type": "Feature",
  "properties": {
    "gn:admin1_code":"9",
    "gn:asciiname":"Gostar",
    "gn:country_code":"IR",
    "gn:dem":1896,
    "gn:feature_class":"P",
    "gn:feature_code":"PPL",
    "gn:name":"Gostar",
    "gn:population":0,
    "gn:timezone":"Asia/Tehran",
    "iso:country":"IR",
    "name:fas_x_preferred":[
        "\u06af\u0633\u062a\u0631"
    ],
    "name:msa_x_preferred":[
        "Gostar"
    ],
    "name:und_x_variant":[
        "Sard\u0101r\u0101b\u0101d"
    ],
    "wof:name":"Gostar",
    "wof:placetype":"locality"
},
  "geometry": {"coordinates":[48.87627,35.46411],"type":"Point"}
}