{
  "type": "Feature",
  "properties": {
    "gn:admin1_code":"32",
    "gn:asciiname":"Qarah Qanlu",
    "gn:country_code":"IR",
    "gn:dem":99,
    "gn:feature_class":"P",
    "gn:feature_code":"PPL",
    "gn:name":"Qarah Q\u0101nl\u016b",
    "gn:population":0,
    "gn:timezone":"Asia/Tehran",
    "iso:country":"IR",
    "name:fas_x_preferred":[
        "\u0642\u064e\u0631\u064e\u0647 \u0642\u0627\u0646\u0644\u0648\u06cc \u0648\u064f\u0633\u0637\u064e\u0649"
    ],
    "name:fas_x_variant":[
        "\u0642\u0631\u0647 \u0642\u0627\u0646\u0644\u0648",
        "Qarah Q\u0101nl\u016b-ye Vos\u0163\u00e1",
        "Qarah Q\u0101nl\u016b"
    ],
    "wof:name":"Qarah Qanlu",
    "wof:placetype":"locality"
},
  "geometry": {"coordinates":[47.6377,39.5342],"type":"Point"}
}