{
  "type": "Feature",
  "properties": {
    "gn:admin1_code":"42",
    "gn:asciiname":"Kortu",
    "gn:country_code":"IR",
    "gn:dem":1127,
    "gn:feature_class":"P",
    "gn:feature_code":"PPL",
    "gn:name":"Kort\u016b",
    "gn:population":0,
    "gn:timezone":"Asia/Tehran",
    "iso:country":"IR",
    "name:ara_x_preferred":[
        "\u0643\u0631\u062a\u0648"
    ],
    "name:fas_x_preferred":[
        "\u06a9\u0631\u062a\u0648"
    ],
    "name:fas_x_variant":[
        "Kort\u016b"
    ],
    "wof:name":"Kortu",
    "wof:placetype":"locality"
},
  "geometry": {"coordinates":[59.26011999999999,36.6046],"type":"Point"}
}