{
  "type": "Feature",
  "properties": {
    "gn:admin1_code":"28.0",
    "gn:asciiname":"Yusofabad",
    "gn:country_code":"IR",
    "gn:dem":1933,
    "gn:feature_class":"P",
    "gn:feature_code":"PPL",
    "gn:name":"Y\u016bsof\u0101b\u0101d",
    "gn:population":0,
    "gn:timezone":"Asia/Tehran",
    "iso:country":"IR",
    "name:fas_x_preferred":[
        "Y\u016bsof\u0101b\u0101d"
    ],
    "wof:name":"Yusofabad",
    "wof:placetype":"locality"
},
  "geometry": {"coordinates":[52.53861,32.74028],"type":"Point"}
}