{
  "type": "Feature",
  "properties": {
    "gn:admin1_code":"10.0",
    "gn:asciiname":"Kani Chenan",
    "gn:country_code":"IR",
    "gn:dem":1129,
    "gn:feature_class":"P",
    "gn:feature_code":"PPL",
    "gn:name":"K\u0101n\u012b Chen\u0101n",
    "gn:population":0,
    "gn:timezone":"Asia/Tehran",
    "iso:country":"IR",
    "name:fas_x_preferred":[
        "\u0643\u0627\u0646\u06cc \u0686\u0650\u0646\u0627\u0646"
    ],
    "wof:name":"Kani Chenan",
    "wof:placetype":"locality"
},
  "geometry": {"coordinates":[46.18333,33.76667],"type":"Point"}
}