{
  "type": "Feature",
  "properties": {
    "gn:admin1_code":"7",
    "gn:asciiname":"Romeqan",
    "gn:country_code":"IR",
    "gn:dem":1374,
    "gn:feature_class":"P",
    "gn:feature_code":"PPL",
    "gn:name":"Romeq\u0101n",
    "gn:population":0,
    "gn:timezone":"Asia/Tehran",
    "iso:country":"IR",
    "name:fas_x_preferred":[
        "\u0631\u0645\u0642\u0627\u0646"
    ],
    "name:fas_x_variant":[
        "Romeq\u0101n"
    ],
    "name:und_x_variant":[
        "Romq\u0101n",
        "R\u0101ng\u016bn"
    ],
    "wof:name":"Romeqan",
    "wof:placetype":"locality"
},
  "geometry": {"coordinates":[52.1634,29.3767],"type":"Point"}
}