{
  "type": "Feature",
  "properties": {
    "gn:admin1_code":"13",
    "gn:asciiname":"Ban Meydan-e Sofla",
    "gn:country_code":"IR",
    "gn:dem":1073,
    "gn:feature_class":"P",
    "gn:feature_code":"PPL",
    "gn:name":"B\u0101n Meyd\u0101n-e Sofl\u0101",
    "gn:population":0,
    "gn:timezone":"Asia/Tehran",
    "iso:country":"IR",
    "name:fas_x_preferred":[
        "\u0628\u0627\u0646 \u0645\u06cc\u062f\u0627\u0646 \u0633\u0641\u0644\u06cc"
    ],
    "name:fas_x_variant":[
        "B\u0101nmeyd\u0101n",
        "B\u0101n Meyd\u0101n-e Sofl\u0101"
    ],
    "name:und_x_variant":[
        "B\u0101m\u012b\u0101n \u2018Abdoll\u0101h"
    ],
    "wof:name":"Ban Meydan-e Sofla",
    "wof:placetype":"locality"
},
  "geometry": {"coordinates":[46.0187,34.1173],"type":"Point"}
}