{
  "type": "Feature",
  "properties": {
    "gn:admin1_code":"8",
    "gn:asciiname":"Liavol-e Bala",
    "gn:country_code":"IR",
    "gn:dem":1052,
    "gn:feature_class":"P",
    "gn:feature_code":"PPL",
    "gn:name":"L\u012b\u0101vol-e B\u0101l\u0101",
    "gn:population":0,
    "gn:timezone":"Asia/Tehran",
    "iso:country":"IR",
    "name:fas_x_preferred":[
        "L\u012b\u0101vol-e B\u0101l\u0101"
    ],
    "name:fas_x_variant":[
        "\u0644\u06cc\u0627\u0648\u0644 \u0628\u0627\u0644\u0627",
        "\u0644\u06cc\u0627\u0648\u0644 \u0639\u0644\u06cc\u0627"
    ],
    "name:msa_x_preferred":[
        "Liavol-e Olya"
    ],
    "name:ukr_x_preferred":[
        "\u041b\u0456\u044f\u0432\u043e\u043b-\u0454-\u0410\u043b\u0456\u044f"
    ],
    "name:und_x_variant":[
        "Li\u0101walb\u0101la",
        "L\u012b\u0101vol-e \u2018Oly\u0101",
        "Liavalbala",
        "Liyavol Olya",
        "L\u012b\u0101vol B\u0101l\u0101",
        "L\u012b\u0101v\u0101 B\u0101l\u0101",
        "\u0644\u06cc\u0627\u0648\u0644 \u0628\u0627\u0644\u0627"
    ],
    "wof:name":"Liavol-e Bala",
    "wof:placetype":"locality"
},
  "geometry": {"coordinates":[49.71292,36.77402],"type":"Point"}
}