{
  "type": "Feature",
  "properties": {
    "gn:admin1_code":"23",
    "gn:asciiname":"Band Jub-e Do",
    "gn:country_code":"IR",
    "gn:dem":1670,
    "gn:feature_class":"P",
    "gn:feature_code":"PPL",
    "gn:name":"Band J\u016bb-e Do",
    "gn:population":0,
    "gn:timezone":"Asia/Tehran",
    "iso:country":"IR",
    "name:fas_x_preferred":[
        "\u0628\u0646\u062f \u062c\u0648\u0628 \u062f\u0648"
    ],
    "name:fas_x_variant":[
        "Band J\u016bb-e Chah\u0101r Borj\u012b-ye Do",
        "Band J\u016bb-e Do",
        "\u0628\u0646\u062f\u062c\u0648\u0628 \u062f\u0648"
    ],
    "name:und_x_variant":[
        "Band-e J\u016bb",
        "Bandj\u016bb"
    ],
    "wof:name":"Band Jub-e Do",
    "wof:placetype":"locality"
},
  "geometry": {"coordinates":[48.5916,33.6477],"type":"Point"}
}