{
  "type": "Feature",
  "properties": {
    "gn:admin1_code":"29",
    "gn:asciiname":"Gand",
    "gn:cc2":"IR",
    "gn:country_code":"IR",
    "gn:dem":763,
    "gn:feature_class":"P",
    "gn:feature_code":"PPL",
    "gn:name":"Gand",
    "gn:population":0,
    "gn:timezone":"Asia/Tehran",
    "iso:country":"IR",
    "name:und_x_variant":[
        "Gumbardi",
        "Gombad",
        "Gumbadi",
        "Gand"
    ],
    "wof:name":"Gand",
    "wof:placetype":"locality"
},
  "geometry": {"coordinates":[58.85,28.63333],"type":"Point"}
}