{
  "type": "Feature",
  "properties": {
    "gn:admin1_code":"15.0",
    "gn:asciiname":"Vostaniyeh-ye Yek",
    "gn:country_code":"IR",
    "gn:dem":6,
    "gn:feature_class":"P",
    "gn:feature_code":"PPL",
    "gn:name":"Vos\u0163\u0101n\u012byeh-ye Yek",
    "gn:population":0,
    "gn:timezone":"Asia/Tehran",
    "iso:country":"IR",
    "name:fas_x_preferred":[
        "\u0648\u0633\u062a\u0627\u0646\u06cc\u0651\u0647 \u06cc\u06a9"
    ],
    "name:fas_x_variant":[
        "Vost\u0101n\u012byeh-ye Yek",
        "\u0648\u0633\u0637\u0627\u0646\u06cc\u0647 \u06cc\u06a9"
    ],
    "name:und_x_variant":[
        "Vos\u0163\u0101n\u012byeh-ye Yek"
    ],
    "wof:name":"Vostaniyeh-ye Yek",
    "wof:placetype":"locality"
},
  "geometry": {"coordinates":[48.49198,30.82261],"type":"Point"}
}