{
  "type": "Feature",
  "properties": {
    "gn:admin1_code":"4.0",
    "gn:asciiname":"Nikshahr",
    "gn:country_code":"IR",
    "gn:dem":466,
    "gn:feature_class":"P",
    "gn:feature_code":"PPLA2",
    "gn:name":"N\u012bkshahr",
    "gn:population":0,
    "gn:timezone":"Asia/Tehran",
    "iso:country":"IR",
    "name:ara_x_preferred":[
        "\u0646\u064a\u0643 \u0634\u0647\u0631"
    ],
    "name:azb_x_preferred":[
        "\u0646\u06cc\u06a9\u200c\u0634\u0647\u0631"
    ],
    "name:aze_x_preferred":[
        "Nik\u015f\u0259hr"
    ],
    "name:ceb_x_preferred":[
        "N\u012bkshahr"
    ],
    "name:fas_x_preferred":[
        "\u0646\u06cc\u06a9\u0634\u0647\u0631"
    ],
    "name:fas_x_variant":[
        "\u0646\u06cc\u06a9\u200c\u0634\u0647\u0631"
    ],
    "name:ita_x_preferred":[
        "Nikshahr"
    ],
    "name:mlg_x_preferred":[
        "Nik Shahr"
    ],
    "name:tur_x_preferred":[
        "Nik\u015fehr"
    ],
    "name:und_x_variant":[
        "Geh",
        "N\u012bk",
        "Keh"
    ],
    "name:zho_x_preferred":[
        "\u8042\u8d6b\u5c14"
    ],
    "wof:name":"Nikshahr",
    "wof:placetype":"locality"
},
  "geometry": {"coordinates":[60.2143,26.2258],"type":"Point"}
}