{
  "type": "Feature",
  "properties": {
    "gn:admin1_code":"32",
    "gn:asciiname":"Hazar Kandi Qeshlaqi",
    "gn:country_code":"IR",
    "gn:dem":116,
    "gn:feature_class":"P",
    "gn:feature_code":"PPL",
    "gn:name":"H\u0101zar Kand\u012b Qeshl\u0101q\u012b",
    "gn:population":0,
    "gn:timezone":"Asia/Tehran",
    "iso:country":"IR",
    "name:fas_x_preferred":[
        "\u0647\u0627\u0632\u064e\u0631 \u0643\u064e\u0646\u062f\u06cc \u0642\u0650\u0634\u0644\u0627\u0642\u06cc"
    ],
    "name:fas_x_variant":[
        "H\u0101zar Kand\u012b Qeshl\u0101q\u012b"
    ],
    "wof:name":"Hazar Kandi Qeshlaqi",
    "wof:placetype":"locality"
},
  "geometry": {"coordinates":[47.59444000000001,39.51722],"type":"Point"}
}