{
  "type": "Feature",
  "properties": {
    "gn:admin1_code":"35.0",
    "gn:asciiname":"Anarak",
    "gn:country_code":"IR",
    "gn:dem":918,
    "gn:feature_class":"P",
    "gn:feature_code":"PPL",
    "gn:name":"An\u0101rak",
    "gn:population":0,
    "gn:timezone":"Asia/Tehran",
    "iso:country":"IR",
    "name:ara_x_preferred":[
        "\u0623\u0646\u0627\u0631\u0643"
    ],
    "name:aze_x_preferred":[
        "Anar\u0259k"
    ],
    "name:bul_x_preferred":[
        "\u0410\u043d\u0430\u0440\u0430\u043a"
    ],
    "name:fas_x_preferred":[
        "\u0627\u0646\u0627\u0631\u06a9"
    ],
    "name:fas_x_variant":[
        "An\u0101rak"
    ],
    "name:fra_x_preferred":[
        "Anarak"
    ],
    "name:mlg_x_preferred":[
        "Anarak"
    ],
    "name:pol_x_preferred":[
        "Anarak"
    ],
    "name:rus_x_preferred":[
        "\u042d\u043d\u0430\u0440\u0435\u043a"
    ],
    "name:spa_x_preferred":[
        "Anarak"
    ],
    "name:tur_x_preferred":[
        "Anarek"
    ],
    "wof:name":"Anarak",
    "wof:placetype":"locality"
},
  "geometry": {"coordinates":[51.24833,36.31001],"type":"Point"}
}