{
  "type": "Feature",
  "properties": {
    "gn:admin1_code":"35.0",
    "gn:asciiname":"Anarak",
    "gn:country_code":"IR",
    "gn:dem":918,
    "gn:feature_class":"P",
    "gn:feature_code":"PPL",
    "gn:name":"An\u0101rak",
    "gn:population":0,
    "gn:timezone":"Asia/Tehran",
    "iso:country":"IR",
    "name:fas_x_preferred":[
        "\u0627\u0646\u0627\u0631\u06a9"
    ],
    "name:fas_x_variant":[
        "An\u0101rak"
    ],
    "wof:name":"Anarak",
    "wof:placetype":"locality"
},
  "geometry": {"coordinates":[51.24833,36.31001],"type":"Point"}
}