{
  "type": "Feature",
  "properties": {
    "gn:admin1_code":"29",
    "gn:asciiname":"Luperaman",
    "gn:country_code":"IR",
    "gn:dem":383,
    "gn:feature_class":"P",
    "gn:feature_code":"PPLL",
    "gn:name":"L\u016bper\u0101m\u0101n",
    "gn:population":0,
    "gn:timezone":"Asia/Tehran",
    "iso:country":"IR",
    "name:fas_x_preferred":[
        "\u0644\u0648\u067e\u0631\u0627\u0645\u0627\u0646"
    ],
    "name:fas_x_variant":[
        "L\u016bper\u0101m\u0101n"
    ],
    "wof:name":"Luperaman",
    "wof:placetype":"locality"
},
  "geometry": {"coordinates":[58.74318,27.76716],"type":"Point"}
}