{
  "type": "Feature",
  "properties": {
    "gn:admin1_code":"1.0",
    "gn:asciiname":"Qezeljeh-ye Olya",
    "gn:country_code":"IR",
    "gn:dem":1867,
    "gn:feature_class":"P",
    "gn:feature_code":"PPL",
    "gn:name":"Qezeljeh-ye Oly\u00e1",
    "gn:population":0,
    "gn:timezone":"Asia/Tehran",
    "iso:country":"IR",
    "name:azb_x_preferred":[
        "\u0642\u0632\u0644\u062c\u0647 \u0639\u0644\u06cc\u0627"
    ],
    "name:fas_x_preferred":[
        "\u0642\u0650\u0632\u0650\u0644\u062c\u0650\u06c0 \u0628\u0627\u0644\u0627"
    ],
    "name:fas_x_variant":[
        "\u0642\u0632\u0644\u062c\u0647 \u0639\u0644\u06cc\u0627",
        "Qezeljeh-ye B\u0101l\u0101",
        "Qezeljeh-ye Oly\u00e1"
    ],
    "wof:name":"Qezeljeh-ye Olya",
    "wof:placetype":"locality"
},
  "geometry": {"coordinates":[45.8347,36.654],"type":"Point"}
}