{
  "type": "Feature",
  "properties": {
    "gn:admin1_code":"33.0",
    "gn:asciiname":"Mohammadkhan Yarlari",
    "gn:country_code":"IR",
    "gn:dem":1088,
    "gn:feature_class":"P",
    "gn:feature_code":"PPL",
    "gn:name":"Mo\u1e29ammadkh\u0101n Yarlar\u012b",
    "gn:population":0,
    "gn:timezone":"Asia/Tehran",
    "iso:country":"IR",
    "name:fas_x_preferred":[
        "\u0645\u062d\u0645\u062f\u062e\u0627\u0646 \u06cc\u0631\u0644\u0631\u06cc"
    ],
    "name:und_x_variant":[
        "Mo\u1e29ammadkh\u0101n Yarlar\u012b"
    ],
    "wof:name":"Mohammadkhan Yarlari",
    "wof:placetype":"locality"
},
  "geometry": {"coordinates":[46.26828,38.65522],"type":"Point"}
}