{
  "type": "Feature",
  "properties": {
    "gn:admin1_code":"7",
    "gn:asciiname":"Kamaraj-e Markazi",
    "gn:country_code":"IR",
    "gn:dem":852,
    "gn:feature_class":"P",
    "gn:feature_code":"PPL",
    "gn:name":"Kam\u0101raj-e Markaz\u012b",
    "gn:population":0,
    "gn:timezone":"Asia/Tehran",
    "iso:country":"IR",
    "name:fas_x_preferred":[
        "\u06a9\u0645\u0627\u0631\u062c \u0645\u0631\u06a9\u0632\u06cc"
    ],
    "name:fas_x_variant":[
        "Kam\u0101rej",
        "Kam\u0101raj-e Markaz\u012b"
    ],
    "name:und_x_variant":[
        "Komaradj",
        "Kam\u0101r\u012bj",
        "Kamarady",
        "Kam\u0101raj"
    ],
    "wof:name":"Kamaraj-e Markazi",
    "wof:placetype":"locality"
},
  "geometry": {"coordinates":[51.477,29.6101],"type":"Point"}
}