{
  "type": "Feature",
  "properties": {
    "gn:admin1_code":"42",
    "gn:asciiname":"Lukhi",
    "gn:country_code":"IR",
    "gn:dem":1795,
    "gn:feature_class":"P",
    "gn:feature_code":"PPL",
    "gn:name":"L\u016bkh\u012b",
    "gn:population":0,
    "gn:timezone":"Asia/Tehran",
    "iso:country":"IR",
    "name:ara_x_preferred":[
        "\u0644\u0648\u062e\u064a"
    ],
    "name:fas_x_preferred":[
        "\u0644\u0648\u062e\u06cc"
    ],
    "name:fas_x_variant":[
        "L\u016bkh\u012b"
    ],
    "wof:name":"Lukhi",
    "wof:placetype":"locality"
},
  "geometry": {"coordinates":[59.85526,35.50297],"type":"Point"}
}