{
  "type": "Feature",
  "properties": {
    "gn:admin1_code":"32",
    "gn:asciiname":"Sati-ye Sofla",
    "gn:country_code":"IR",
    "gn:dem":1213,
    "gn:elevation":"0.0",
    "gn:feature_class":"P",
    "gn:feature_code":"PPL",
    "gn:name":"S\u0101\u0163\u012b-ye Sofl\u00e1",
    "gn:population":0,
    "gn:timezone":"Asia/Tehran",
    "iso:country":"IR",
    "name:ceb_x_preferred":[
        "S\u0101\u0163\u012b-ye Sofl\u00e1"
    ],
    "name:fas_x_preferred":[
        "\u0633\u0627\u0637\u06cc \u0633\u0641\u0644\u0649"
    ],
    "name:fas_x_variant":[
        "S\u0101\u0163\u012b-ye Sofl\u00e1",
        "\u0633\u0627\u0637\u06cc \u0633\u0641\u0644\u06cc"
    ],
    "name:msa_x_preferred":[
        "Sati-ye Sofla"
    ],
    "name:swe_x_preferred":[
        "S\u0101\u0163\u012b-ye Sofl\u00e1"
    ],
    "wof:name":"Sati-ye Sofla",
    "wof:placetype":"locality"
},
  "geometry": {"coordinates":[47.41024,38.37273],"type":"Point"}
}