{
  "type": "Feature",
  "properties": {
    "gn:admin1_code":"38",
    "gn:asciiname":"Ajor Pazi-ye Naderi",
    "gn:country_code":"IR",
    "gn:dem":1201,
    "gn:feature_class":"P",
    "gn:feature_code":"PPL",
    "gn:name":"\u0100jor Paz\u012b-ye N\u0101der\u012b",
    "gn:population":0,
    "gn:timezone":"Asia/Tehran",
    "iso:country":"IR",
    "name:fas_x_preferred":[
        "\u0100jor Paz\u012b-ye N\u0101der\u012b"
    ],
    "wof:name":"Ajor Pazi-ye Naderi",
    "wof:placetype":"locality"
},
  "geometry": {"coordinates":[50.18333,35.73333],"type":"Point"}
}