{
  "type": "Feature",
  "properties": {
    "gn:admin1_code":"11",
    "gn:asciiname":"Sang Kani",
    "gn:country_code":"IR",
    "gn:dem":6,
    "gn:feature_class":"P",
    "gn:feature_code":"PPL",
    "gn:name":"Sang Kan\u012b",
    "gn:population":0,
    "gn:timezone":"Asia/Tehran",
    "iso:country":"IR",
    "name:fas_x_preferred":[
        "\u0633\u064e\u0646\u06af \u0643\u064e\u0646\u0648"
    ],
    "name:fas_x_variant":[
        "Sang Kan\u016b",
        "Sang Kan\u012b",
        "\u0633\u0646\u06af \u06a9\u0646\u064a"
    ],
    "wof:name":"Sang Kani",
    "wof:placetype":"locality"
},
  "geometry": {"coordinates":[56.36206,27.19796],"type":"Point"}
}