{
  "type": "Feature",
  "properties": {
    "gn:admin1_code":"4.0",
    "gn:asciiname":"Jowzdar",
    "gn:country_code":"IR",
    "gn:dem":490,
    "gn:feature_class":"P",
    "gn:feature_code":"PPL",
    "gn:name":"Jowzdar",
    "gn:population":0,
    "gn:timezone":"Asia/Tehran",
    "iso:country":"IR",
    "name:ara_x_preferred":[
        "\u062c\u0648\u0632\u062f\u0627\u0631"
    ],
    "name:fas_x_preferred":[
        "\u062c\u0648\u0632\u062f\u0631"
    ],
    "name:fas_x_variant":[
        "\u062c\u0648\u0632\u062f\u0627\u0631"
    ],
    "wof:name":"Jowzdar",
    "wof:placetype":"locality"
},
  "geometry": {"coordinates":[60.0004,26.2533],"type":"Point"}
}