{
  "type": "Feature",
  "properties": {
    "gn:admin1_code":"42.0",
    "gn:asciiname":"Mahalleh-ye Amirabad",
    "gn:country_code":"IR",
    "gn:dem":1873,
    "gn:feature_class":"P",
    "gn:feature_code":"PPL",
    "gn:name":"Ma\u1e29alleh-ye Am\u012br\u0101b\u0101d",
    "gn:population":0,
    "gn:timezone":"Asia/Tehran",
    "iso:country":"IR",
    "name:fas_x_preferred":[
        "\u0645\u062d\u0644\u0647 \u0627\u0645\u06cc\u0631 \u0622\u0628\u0627\u062f"
    ],
    "name:und_x_variant":[
        "Ma\u1e29alleh-ye Am\u012br\u0101b\u0101d"
    ],
    "wof:name":"Mahalleh-ye Amirabad",
    "wof:placetype":"locality"
},
  "geometry": {"coordinates":[58.7028,36.55026],"type":"Point"}
}