{
  "type": "Feature",
  "properties": {
    "gn:admin1_code":"35.0",
    "gn:asciiname":"Ashekar Kola",
    "gn:country_code":"IR",
    "gn:dem":3,
    "gn:feature_class":"P",
    "gn:feature_code":"PPL",
    "gn:name":"\u0100shek\u0101r Kol\u0101",
    "gn:population":0,
    "gn:timezone":"Asia/Tehran",
    "iso:country":"IR",
    "name:fas_x_preferred":[
        "\u0622\u0634\u0650\u0643\u0627\u0631 \u0643\u064f\u0644\u0627"
    ],
    "name:fas_x_variant":[
        "\u0100shek\u0101r Kol\u0101"
    ],
    "wof:name":"Ashekar Kola",
    "wof:placetype":"locality"
},
  "geometry": {"coordinates":[52.43333000000001,36.55],"type":"Point"}
}