{
  "type": "Feature",
  "properties": {
    "gn:admin1_code":"9",
    "gn:asciiname":"Hoseynabad-e Nazem",
    "gn:country_code":"IR",
    "gn:dem":1713,
    "gn:feature_class":"P",
    "gn:feature_code":"PPL",
    "gn:name":"\u1e28oseyn\u0101b\u0101d-e N\u0101z\u0327em",
    "gn:population":0,
    "gn:timezone":"Asia/Tehran",
    "iso:country":"IR",
    "name:fas_x_preferred":[
        "\u062d\u064f\u0633\u0650\u064a\u0646 \u0622\u0628\u0627\u062f"
    ],
    "name:fas_x_variant":[
        "\u1e28oseyn\u0101b\u0101d-e N\u0101z\u0327em",
        "\u062d\u0633\u06cc\u0646 \u0622\u0628\u0627\u062f \u0646\u0627\u0638\u0645"
    ],
    "name:und_x_variant":[
        "Hose\u012bn Abad Nazem",
        "\u1e28oseyn\u0101b\u0101d",
        "H\u016bsa\u012bn\u0101b\u0101d",
        "\u062d\u0633\u06cc\u0646 \u0622\u0628\u0627\u062f \u0646\u0627\u0638\u0645"
    ],
    "wof:name":"Hoseynabad-e Nazem",
    "wof:placetype":"locality"
},
  "geometry": {"coordinates":[48.6051,34.2963],"type":"Point"}
}