{
  "type": "Feature",
  "properties": {
    "gn:admin1_code":"34",
    "gn:asciiname":"Hajjiabad-e Yujan",
    "gn:country_code":"IR",
    "gn:dem":1768,
    "gn:feature_class":"P",
    "gn:feature_code":"PPL",
    "gn:name":"\u1e28\u0101jj\u012b\u0101b\u0101d-e Y\u016bj\u0101n",
    "gn:population":0,
    "gn:timezone":"Asia/Tehran",
    "iso:country":"IR",
    "name:fas_x_preferred":[
        "\u062d\u0627\u062c\u064a\u0627\u0628\u0627\u062f\u0650 \u064a\u0648\u062c\u0627\u0646"
    ],
    "name:fas_x_variant":[
        "\u062d\u0627\u062c\u0651\u06cc \u0622\u0628\u0627\u062f",
        "\u0642\u064e\u0644\u0639\u0650\u0647 \u0646\u064f\u0648",
        "\u1e28\u0101j\u012b\u0101b\u0101d-e Y\u016bj\u0101n",
        "\u1e28\u0101jj\u012b\u0101b\u0101d-e Y\u016bj\u0101n",
        "\u062d\u0627\u062c\u06cc \u0622\u0628\u0627\u062f \u06cc\u0648\u062c\u0627\u0646"
    ],
    "name:und_x_variant":[
        "Qal\u2018eh Now",
        "\u1e28\u0101jj\u012b\u0101b\u0101d",
        "\u062d\u0627\u062c\u06cc \u0622\u0628\u0627\u062f \u06cc\u0648\u062c\u0627\u0646"
    ],
    "wof:name":"Hajjiabad-e Yujan",
    "wof:placetype":"locality"
},
  "geometry": {"coordinates":[50.14533,33.73364],"type":"Point"}
}