{
  "type": "Feature",
  "properties": {
    "gn:admin1_code":"29",
    "gn:asciiname":"Bab Taher",
    "gn:country_code":"IR",
    "gn:dem":2130,
    "gn:feature_class":"P",
    "gn:feature_code":"PPL",
    "gn:name":"B\u0101b \u0162\u0101her",
    "gn:population":0,
    "gn:timezone":"Asia/Tehran",
    "iso:country":"IR",
    "name:fas_x_preferred":[
        "B\u0101b \u0162\u0101her"
    ],
    "wof:name":"Bab Taher",
    "wof:placetype":"locality"
},
  "geometry": {"coordinates":[57.25,30.51667],"type":"Point"}
}