{
  "type": "Feature",
  "properties": {
    "gn:admin1_code":"42",
    "gn:asciiname":"Zu Kalat",
    "gn:country_code":"IR",
    "gn:dem":1871,
    "gn:feature_class":"P",
    "gn:feature_code":"PPL",
    "gn:name":"Z\u016b Kal\u0101t",
    "gn:population":0,
    "gn:timezone":"Asia/Tehran",
    "iso:country":"IR",
    "name:fas_x_preferred":[
        "Z\u016b \u015e\u0101le\u1e29\u0101b\u0101d"
    ],
    "name:fas_x_variant":[
        "\u0632\u0648 \u06a9\u0644\u0627\u062a"
    ],
    "name:und_x_variant":[
        "Z\u016b Kal\u0101t"
    ],
    "wof:name":"Zu Kalat",
    "wof:placetype":"locality"
},
  "geometry": {"coordinates":[58.49614,34.15024],"type":"Point"}
}