{
  "type": "Feature",
  "properties": {
    "gn:admin1_code":"4.0",
    "gn:asciiname":"Band Batagi",
    "gn:country_code":"IR",
    "gn:dem":797,
    "gn:feature_class":"P",
    "gn:feature_code":"PPLL",
    "gn:name":"Band Batag\u012b",
    "gn:population":0,
    "gn:timezone":"Asia/Tehran",
    "iso:country":"IR",
    "name:fas_x_preferred":[
        "\u0628\u0646\u062f \u0628\u062a\u06af\u06cc"
    ],
    "name:und_x_variant":[
        "Band Batag\u012b"
    ],
    "wof:name":"Band Batagi",
    "wof:placetype":"locality"
},
  "geometry": {"coordinates":[59.69403000000001,26.60708],"type":"Point"}
}