{
  "type": "Feature",
  "properties": {
    "gn:admin1_code":"23",
    "gn:asciiname":"Baranazar",
    "gn:country_code":"IR",
    "gn:dem":1844,
    "gn:feature_class":"P",
    "gn:feature_code":"PPL",
    "gn:name":"Bar\u0101n\u0101z\u0101r",
    "gn:population":0,
    "gn:timezone":"Asia/Tehran",
    "iso:country":"IR",
    "name:fas_x_preferred":[
        "\u0628\u064e\u0631\u0627\u0646\u0627\u0632\u0627\u0631"
    ],
    "name:fas_x_variant":[
        "Bar\u0101n\u0101z\u0101r"
    ],
    "wof:name":"Baranazar",
    "wof:placetype":"locality"
},
  "geometry": {"coordinates":[47.61667,34.16667],"type":"Point"}
}