{
  "type": "Feature",
  "properties": {
    "gn:admin1_code":"5.0",
    "gn:asciiname":"Gahvareh-ye Hoseyn",
    "gn:country_code":"IR",
    "gn:dem":1226,
    "gn:feature_class":"P",
    "gn:feature_code":"PPL",
    "gn:name":"Gahv\u0101reh-ye \u1e28oseyn",
    "gn:population":0,
    "gn:timezone":"Asia/Tehran",
    "iso:country":"IR",
    "name:fas_x_preferred":[
        "\u06af\u0647\u0648\u0627\u0631\u0647 \u062d\u0633\u06cc\u0646"
    ],
    "name:und_x_variant":[
        "Gahv\u0101reh-ye \u1e28oseyn"
    ],
    "wof:name":"Gahvareh-ye Hoseyn",
    "wof:placetype":"locality"
},
  "geometry": {"coordinates":[50.57936,31.39417000000001],"type":"Point"}
}