{
  "type": "Feature",
  "properties": {
    "gn:admin1_code":"4",
    "gn:asciiname":"Langaru",
    "gn:country_code":"IR",
    "gn:dem":1290,
    "gn:feature_class":"P",
    "gn:feature_code":"PPL",
    "gn:name":"Lang\u0101r\u016b",
    "gn:population":0,
    "gn:timezone":"Asia/Tehran",
    "iso:country":"IR",
    "name:fas_x_preferred":[
        "\u0644\u0646\u06af\u0627\u0631\u0648"
    ],
    "name:fas_x_variant":[
        "Lang\u0101r\u016b"
    ],
    "wof:name":"Langaru",
    "wof:placetype":"locality"
},
  "geometry": {"coordinates":[62.6255,26.8098],"type":"Point"}
}