{
  "type": "Feature",
  "properties": {
    "gn:admin1_code":"29",
    "gn:asciiname":"Tall-e Sorkh",
    "gn:country_code":"IR",
    "gn:dem":2311,
    "gn:feature_class":"P",
    "gn:feature_code":"PPL",
    "gn:name":"Tall-e Sorkh",
    "gn:population":0,
    "gn:timezone":"Asia/Tehran",
    "iso:country":"IR",
    "name:fas_x_preferred":[
        "\u062a\u0644 \u0633\u0631\u062e"
    ],
    "name:msa_x_preferred":[
        "Tall-e Sorkh"
    ],
    "wof:name":"Tall-e Sorkh",
    "wof:placetype":"locality"
},
  "geometry": {"coordinates":[55.43826,30.37282],"type":"Point"}
}