{
  "type": "Feature",
  "properties": {
    "gn:admin1_code":"13",
    "gn:asciiname":"Babajani",
    "gn:country_code":"IR",
    "gn:dem":467,
    "gn:feature_class":"P",
    "gn:feature_code":"PPL",
    "gn:name":"B\u0101b\u0101j\u0101n\u012b",
    "gn:population":0,
    "gn:timezone":"Asia/Tehran",
    "iso:country":"IR",
    "name:fas_x_preferred":[
        "\u0628\u0627\u0628\u0627\u062c\u0627\u0646\u06cc"
    ],
    "name:fas_x_variant":[
        "B\u0101b\u0101j\u0101n\u012b"
    ],
    "wof:name":"Babajani",
    "wof:placetype":"locality"
},
  "geometry": {"coordinates":[45.72907,34.48058],"type":"Point"}
}