{
  "type": "Feature",
  "properties": {
    "gn:admin1_code":"42",
    "gn:asciiname":"Yurd-e Chupan Avval",
    "gn:country_code":"IR",
    "gn:dem":1169,
    "gn:feature_class":"P",
    "gn:feature_code":"PPL",
    "gn:name":"Y\u016brd-e Ch\u016bp\u0101n Avval",
    "gn:population":0,
    "gn:timezone":"Asia/Tehran",
    "iso:country":"IR",
    "name:fas_x_preferred":[
        "\u06cc\u0648\u0631\u062a \u0686\u0648\u067e\u0627\u0646"
    ],
    "name:fas_x_variant":[
        "B\u016brt Ch\u016bp\u0101n",
        "\u06cc\u0648\u0631\u062f \u0686\u0648\u067e\u0627\u0646 \u0627\u0648\u0644",
        "\u06cc\u0648\u0631\u062f \u0686\u0648\u067e\u0627\u0646"
    ],
    "name:und_x_variant":[
        "Y\u016brt-e Ch\u016bp\u0101n",
        "Y\u016brd-e Ch\u016bp\u0101n Avval",
        "Y\u016brt Ch\u016bp\u0101n-e B\u0101l\u0101",
        "Y\u016brd-e Ch\u016bp\u0101n"
    ],
    "wof:name":"Yurd-e Chupan Avval",
    "wof:placetype":"locality"
},
  "geometry": {"coordinates":[59.07637,36.6686],"type":"Point"}
}