{
  "type": "Feature",
  "properties": {
    "gn:admin1_code":"41",
    "gn:asciiname":"Kalat-e Hamzeh",
    "gn:country_code":"IR",
    "gn:dem":1015,
    "gn:feature_class":"P",
    "gn:feature_code":"PPL",
    "gn:name":"Kal\u0101t-e \u1e28amzeh",
    "gn:population":0,
    "gn:timezone":"Asia/Tehran",
    "iso:country":"IR",
    "name:fas_x_preferred":[
        "\u06a9\u0644\u0627\u062a \u062d\u0645\u0632\u0647"
    ],
    "name:fas_x_variant":[
        "Kal\u0101t-e \u1e28amzeh"
    ],
    "wof:name":"Kalat-e Hamzeh",
    "wof:placetype":"locality"
},
  "geometry": {"coordinates":[60.7287,32.3358],"type":"Point"}
}