{
  "type": "Feature",
  "properties": {
    "gn:admin1_code":"33",
    "gn:asciiname":"Qarah Aghaj Bazar",
    "gn:country_code":"IR",
    "gn:dem":1922,
    "gn:feature_class":"P",
    "gn:feature_code":"PPL",
    "gn:name":"Qarah \u0100gh\u0101j B\u0101z\u0101r",
    "gn:population":0,
    "gn:timezone":"Asia/Tehran",
    "iso:country":"IR",
    "name:ara_x_preferred":[
        "\u0642\u0631\u0629 \u0622\u063a\u0627\u062c"
    ],
    "name:azb_x_preferred":[
        "\u0642\u0631\u0647\u200c\u0622\u063a\u0627\u062c"
    ],
    "name:aze_x_preferred":[
        "Qaraa\u011fac"
    ],
    "name:fas_x_preferred":[
        "\u0642\u0631\u0647 \u0627\u063a\u0627\u062c"
    ],
    "name:fas_x_variant":[
        "Qareh \u0100gh\u0101j",
        "Qarah \u0100gh\u0101j B\u0101z\u0101r",
        "\u0642\u064e\u0631\u064e \u0627\u064e\u06af\u0627\u0686",
        "\u0642\u064e\u0631\u064e \u0627\u064e\u063a\u0627\u0686",
        "\u0642\u0631\u0647 \u0622\u063a\u0627\u062c \u0628\u0627\u0632\u0627\u0631",
        "\u0642\u0631\u0647\u200c\u0622\u063a\u0627\u062c"
    ],
    "name:ita_x_preferred":[
        "Qarah Aghaj"
    ],
    "name:mlg_x_preferred":[
        "Qarah Aghaj"
    ],
    "name:msa_x_preferred":[
        "Qarah Aghaj"
    ],
    "name:mzn_x_preferred":[
        "\u0642\u0631\u0647\u200c\u0622\u063a\u0627\u062c"
    ],
    "name:tur_x_preferred":[
        "Karaa\u011fa\u00e7"
    ],
    "name:und_x_variant":[
        "Qareh \u0100q\u0101j",
        "Qara Ag\u0101ch",
        "Qara Agh\u0101ch",
        "Qareh \u0100gh\u0101j B\u0101z\u0101r",
        "\u0642\u0631\u0647 \u0622\u063a\u0627\u062c \u0628\u0627\u0632\u0627\u0631",
        "Qarah \u0100gh\u0101j"
    ],
    "wof:name":"Qarah Aghaj Bazar",
    "wof:placetype":"locality"
},
  "geometry": {"coordinates":[46.9754,37.1288],"type":"Point"}
}