{
  "type": "Feature",
  "properties": {
    "gn:admin1_code":"13.0",
    "gn:asciiname":"Malachiyeh",
    "gn:country_code":"IR",
    "gn:dem":1391,
    "gn:feature_class":"P",
    "gn:feature_code":"PPL",
    "gn:name":"Mal\u0101ch\u012byeh",
    "gn:population":0,
    "gn:timezone":"Asia/Tehran",
    "iso:country":"IR",
    "name:fas_x_preferred":[
        "\u0645\u0644\u0627\u0686\u06cc\u0647"
    ],
    "name:fas_x_variant":[
        "Mal\u0101ch\u012byeh"
    ],
    "wof:name":"Malachiyeh",
    "wof:placetype":"locality"
},
  "geometry": {"coordinates":[46.0881,34.6447],"type":"Point"}
}