{
  "type": "Feature",
  "properties": {
    "gn:admin1_code":"9",
    "gn:asciiname":"Gilabad",
    "gn:country_code":"IR",
    "gn:dem":1538,
    "gn:feature_class":"P",
    "gn:feature_code":"PPL",
    "gn:name":"G\u012bl\u0101b\u0101d",
    "gn:population":0,
    "gn:timezone":"Asia/Tehran",
    "iso:country":"IR",
    "name:fas_x_preferred":[
        "G\u012bl\u0101b\u0101d"
    ],
    "name:fas_x_variant":[
        "\u06af\u06cc\u0644 \u0622\u0628\u0627\u062f",
        "Gel\u0101bad"
    ],
    "name:und_x_variant":[
        "Gel\u0101bad",
        "\u06af\u06cc\u0644 \u0622\u0628\u0627\u062f"
    ],
    "wof:name":"Gilabad",
    "wof:placetype":"locality"
},
  "geometry": {"coordinates":[48.2435,34.1989],"type":"Point"}
}