{
  "type": "Feature",
  "properties": {
    "gn:admin1_code":"5",
    "gn:asciiname":"Cheshmeh Neyzeh",
    "gn:country_code":"IR",
    "gn:dem":834,
    "gn:feature_class":"P",
    "gn:feature_code":"PPL",
    "gn:name":"Cheshmeh Neyzeh",
    "gn:population":0,
    "gn:timezone":"Asia/Tehran",
    "iso:country":"IR",
    "name:fas_x_preferred":[
        "\u0686\u0650\u0634\u0645\u0650\u0647 \u0646\u0650\u064a\u0632\u0650\u0647"
    ],
    "wof:name":"Cheshmeh Neyzeh",
    "wof:placetype":"locality"
},
  "geometry": {"coordinates":[50.66667,30.63333],"type":"Point"}
}