{
  "type": "Feature",
  "properties": {
    "gn:admin1_code":"32",
    "gn:asciiname":"Bahramabad",
    "gn:country_code":"IR",
    "gn:dem":31,
    "gn:feature_class":"P",
    "gn:feature_code":"PPL",
    "gn:name":"Bahr\u0101m\u0101b\u0101d",
    "gn:population":0,
    "gn:timezone":"Asia/Tehran",
    "iso:country":"IR",
    "name:ara_x_preferred":[
        "\u0628\u0647\u0631\u0627\u0645 \u0623\u0628\u0627\u062f"
    ],
    "name:fas_x_preferred":[
        "\u0628\u0647\u0631\u0627\u0645 \u0622\u0628\u0627\u062f"
    ],
    "name:fas_x_variant":[
        "Bahr\u0101m\u0101b\u0101d",
        "\u0628\u0647\u0631\u0627\u0645\u200c\u0622\u0628\u0627\u062f"
    ],
    "name:msa_x_preferred":[
        "Bahramabad"
    ],
    "wof:name":"Bahramabad",
    "wof:placetype":"locality"
},
  "geometry": {"coordinates":[48.056,39.6352],"type":"Point"}
}