{
  "type": "Feature",
  "properties": {
    "gn:admin1_code":"29",
    "gn:asciiname":"Kazemabad",
    "gn:country_code":"IR",
    "gn:dem":2191,
    "gn:feature_class":"P",
    "gn:feature_code":"PPL",
    "gn:name":"K\u0101z\u0327em\u0101b\u0101d",
    "gn:population":0,
    "gn:timezone":"Asia/Tehran",
    "iso:country":"IR",
    "name:fas_x_preferred":[
        "\u06a9\u0627\u0638\u0645 \u0622\u0628\u0627\u062f"
    ],
    "name:fas_x_variant":[
        "K\u0101z\u0327em\u0101b\u0101d"
    ],
    "wof:name":"Kazemabad",
    "wof:placetype":"locality"
},
  "geometry": {"coordinates":[56.6019,29.1795],"type":"Point"}
}