{
  "type": "Feature",
  "properties": {
    "gn:admin1_code":"29.0",
    "gn:asciiname":"Sharifabad Khvajeh",
    "gn:country_code":"IR",
    "gn:dem":1402,
    "gn:feature_class":"P",
    "gn:feature_code":"PPL",
    "gn:name":"Shar\u012bf\u0101b\u0101d Khv\u0101jeh",
    "gn:population":0,
    "gn:timezone":"Asia/Tehran",
    "iso:country":"IR",
    "name:ara_x_preferred":[
        "\u0634\u0631\u064a\u0641 \u0623\u0628\u0627\u062f"
    ],
    "name:fas_x_preferred":[
        "Shar\u012bf\u0101b\u0101d"
    ],
    "name:fas_x_variant":[
        "Shar\u012bf\u0101b\u0101d-e P\u0101\u2019\u012bn",
        "\u0634\u0631\u06cc\u0641 \u0622\u0628\u0627\u062f",
        "\u0634\u0631\u06cc\u0641 \u0622\u0628\u0627\u062f \u062e\u0648\u0627\u062c\u0647",
        "\u0634\u0631\u06cc\u0641\u200c\u0622\u0628\u0627\u062f"
    ],
    "name:und_x_variant":[
        "Shar\u012bf\u0101b\u0101d Khv\u0101jeh"
    ],
    "wof:name":"Sharifabad Khvajeh",
    "wof:placetype":"locality"
},
  "geometry": {"coordinates":[55.3089,30.86468],"type":"Point"}
}