{
  "type": "Feature",
  "properties": {
    "gn:admin1_code":"4.0",
    "gn:asciiname":"Nukabad",
    "gn:country_code":"IR",
    "gn:dem":1460,
    "gn:feature_class":"P",
    "gn:feature_code":"PPL",
    "gn:name":"N\u016bk\u0101b\u0101d",
    "gn:population":0,
    "gn:timezone":"Asia/Tehran",
    "iso:country":"IR",
    "name:ara_x_preferred":[
        "\u0646\u0648\u0643 \u0623\u0628\u0627\u062f"
    ],
    "name:aze_x_preferred":[
        "Nukabad"
    ],
    "name:ceb_x_preferred":[
        "Nok Abad"
    ],
    "name:fas_x_preferred":[
        "\u0646\u0648\u06a9 \u0622\u0628\u0627\u062f"
    ],
    "name:fas_x_variant":[
        "\u0646\u0648\u06a9\u200c\u0622\u0628\u0627\u062f"
    ],
    "name:ita_x_preferred":[
        "Nukabad"
    ],
    "name:mlg_x_preferred":[
        "Nukabad"
    ],
    "name:swe_x_preferred":[
        "Nok Abad"
    ],
    "name:tur_x_preferred":[
        "Nukabad"
    ],
    "name:und_x_variant":[
        "N\u016bk\u0101b\u0101d"
    ],
    "wof:name":"Nukabad",
    "wof:placetype":"locality"
},
  "geometry": {"coordinates":[59.99111,30.32072],"type":"Point"}
}