{
  "type": "Feature",
  "properties": {
    "gn:admin1_code":"29.0",
    "gn:asciiname":"Dahaneh Pachin",
    "gn:country_code":"IR",
    "gn:dem":998,
    "gn:feature_class":"P",
    "gn:feature_code":"PPL",
    "gn:name":"Dahaneh Pach\u012bn",
    "gn:population":0,
    "gn:timezone":"Asia/Tehran",
    "iso:country":"IR",
    "name:fas_x_preferred":[
        "\u062f\u0647\u0646\u0647 \u067e\u0686\u064a\u0646"
    ],
    "name:und_x_variant":[
        "Dahaneh Pach\u012bn"
    ],
    "wof:name":"Dahaneh Pachin",
    "wof:placetype":"locality"
},
  "geometry": {"coordinates":[58.86414,28.25131],"type":"Point"}
}