{
  "type": "Feature",
  "properties": {
    "gn:admin1_code":"3",
    "gn:asciiname":"Zarmitan-e Pa'in",
    "gn:country_code":"IR",
    "gn:dem":1838,
    "gn:feature_class":"P",
    "gn:feature_code":"PPL",
    "gn:name":"Zarm\u012bt\u0101n-e P\u0101\u2019\u012bn",
    "gn:population":0,
    "gn:timezone":"Asia/Tehran",
    "iso:country":"IR",
    "name:fas_x_preferred":[
        "Zarm\u012bt\u0101n-e P\u0101\u2019\u012bn"
    ],
    "name:fas_x_variant":[
        "\u0632\u064e\u0631\u0645\u064a\u062a\u0627\u0646\u0650 \u067e\u0627\u0626\u064a\u0646"
    ],
    "wof:name":"Zarmitan-e Pa'in",
    "wof:placetype":"locality"
},
  "geometry": {"coordinates":[50.51222,32.11333],"type":"Point"}
}