{
  "type": "Feature",
  "properties": {
    "gn:admin1_code":"15.0",
    "gn:asciiname":"Seyyed Ghazban",
    "gn:country_code":"IR",
    "gn:dem":33,
    "gn:feature_class":"P",
    "gn:feature_code":"PPL",
    "gn:name":"Seyyed Gha\u1e95b\u0101n",
    "gn:population":0,
    "gn:timezone":"Asia/Tehran",
    "iso:country":"IR",
    "name:fas_x_preferred":[
        "\u0633\u06cc\u062f \u063a\u0636\u0628\u0627\u0646"
    ],
    "name:und_x_variant":[
        "Seyyed Gha\u1e95b\u0101n"
    ],
    "wof:name":"Seyyed Ghazban",
    "wof:placetype":"locality"
},
  "geometry": {"coordinates":[48.55145,31.70522],"type":"Point"}
}