{
  "type": "Feature",
  "properties": {
    "gn:admin1_code":"22.0",
    "gn:asciiname":"Cheh Bak",
    "gn:country_code":"IR",
    "gn:dem":802,
    "gn:feature_class":"P",
    "gn:feature_code":"PPL",
    "gn:name":"Cheh Bak",
    "gn:population":0,
    "gn:timezone":"Asia/Tehran",
    "iso:country":"IR",
    "name:fas_x_preferred":[
        "\u0686\u0647 \u0628\u06a9"
    ],
    "name:und_x_variant":[
        "\u0686\u0647 \u0628\u06a9"
    ],
    "wof:name":"Cheh Bak",
    "wof:placetype":"locality"
},
  "geometry": {"coordinates":[51.58928,29.1056],"type":"Point"}
}