{
  "type": "Feature",
  "properties": {
    "gn:admin1_code":"5",
    "gn:asciiname":"Bar Aftab-e Emam Reza",
    "gn:country_code":"IR",
    "gn:dem":1446,
    "gn:feature_class":"P",
    "gn:feature_code":"PPL",
    "gn:name":"Bar \u0100ft\u0101b-e Em\u0101m Re\u1e95\u0101",
    "gn:population":0,
    "gn:timezone":"Asia/Tehran",
    "iso:country":"IR",
    "name:fas_x_preferred":[
        "\u0628\u064e\u0631 \u0622\u0641\u062a\u0627\u0628"
    ],
    "name:fas_x_variant":[
        "Bar \u0100ft\u0101b-e Em\u0101m Re\u1e95\u0101",
        "\u0628\u0631 \u0622\u0641\u062a\u0627\u0628 \u0627\u0645\u0627\u0645 \u0631\u0636\u0627",
        "Bar \u0100ft\u0101b"
    ],
    "name:und_x_variant":[
        "Bar \u0100ft\u0101b"
    ],
    "wof:name":"Bar Aftab-e Emam Reza",
    "wof:placetype":"locality"
},
  "geometry": {"coordinates":[50.41017,31.22566],"type":"Point"}
}