{
  "type": "Feature",
  "properties": {
    "gn:admin1_code":"33",
    "gn:asciiname":"Kujan",
    "gn:country_code":"IR",
    "gn:dem":1784,
    "gn:feature_class":"P",
    "gn:feature_code":"PPL",
    "gn:name":"K\u016bj\u0101n",
    "gn:population":0,
    "gn:timezone":"Asia/Tehran",
    "iso:country":"IR",
    "name:fas_x_preferred":[
        "\u06a9\u0648\u062c\u0627\u0646"
    ],
    "name:fas_x_variant":[
        "K\u016bj\u0101n"
    ],
    "name:und_x_variant":[
        "Koojan Dezmar",
        "K\u016bjey\u0101n",
        "Kudzhyan",
        "Kujian"
    ],
    "wof:name":"Kujan",
    "wof:placetype":"locality"
},
  "geometry": {"coordinates":[46.096,38.6689],"type":"Point"}
}