{
  "type": "Feature",
  "properties": {
    "gn:admin1_code":"1",
    "gn:asciiname":"Pirmand",
    "gn:country_code":"IR",
    "gn:dem":2316,
    "gn:feature_class":"P",
    "gn:feature_code":"PPL",
    "gn:name":"P\u012brmand",
    "gn:population":0,
    "gn:timezone":"Asia/Tehran",
    "iso:country":"IR",
    "name:fas_x_preferred":[
        "P\u012brmand"
    ],
    "name:fas_x_variant":[
        "\u067e\u06cc\u0631\u0645\u0646\u062f"
    ],
    "name:und_x_variant":[
        "\u067e\u06cc\u0631\u0645\u0646\u062f"
    ],
    "wof:name":"Pirmand",
    "wof:placetype":"locality"
},
  "geometry": {"coordinates":[44.4131,38.0854],"type":"Point"}
}