{
  "type": "Feature",
  "properties": {
    "gn:admin1_code":"23",
    "gn:asciiname":"Sang Chubeh",
    "gn:country_code":"IR",
    "gn:dem":1165,
    "gn:feature_class":"P",
    "gn:feature_code":"PPL",
    "gn:name":"Sang Ch\u016bbeh",
    "gn:population":0,
    "gn:timezone":"Asia/Tehran",
    "iso:country":"IR",
    "name:fas_x_preferred":[
        "\u0633\u0646\u06af \u0686\u0648\u0628\u0647"
    ],
    "name:fas_x_variant":[
        "Sang Ch\u016bbeh"
    ],
    "wof:name":"Sang Chubeh",
    "wof:placetype":"locality"
},
  "geometry": {"coordinates":[48.80569000000001,33.22653],"type":"Point"}
}