{
  "type": "Feature",
  "properties": {
    "gn:admin1_code":"25.0",
    "gn:asciiname":"Danbeh-ye Pa'in",
    "gn:country_code":"IR",
    "gn:dem":1691,
    "gn:feature_class":"P",
    "gn:feature_code":"PPL",
    "gn:name":"Danbeh-ye P\u0101\u2019\u012bn",
    "gn:population":0,
    "gn:timezone":"Asia/Tehran",
    "iso:country":"IR",
    "name:fas_x_preferred":[
        "Danbeh-ye P\u0101\u2019\u012bn"
    ],
    "name:fas_x_variant":[
        "\u062f\u0646\u0628\u0647 \u067e\u0627\u0626\u06cc\u0646",
        "\u062f\u0646\u0628\u0648 \u067e\u0627\u0626\u06cc\u0646"
    ],
    "name:und_x_variant":[
        "Danb\u016b-ye P\u0101\u2019\u012bn"
    ],
    "wof:name":"Danbeh-ye Pa'in",
    "wof:placetype":"locality"
},
  "geometry": {"coordinates":[54.14911,36.39673],"type":"Point"}
}