{
  "type": "Feature",
  "properties": {
    "gn:admin1_code":"42",
    "gn:asciiname":"Tavandar",
    "gn:country_code":"IR",
    "gn:dem":1852,
    "gn:feature_class":"P",
    "gn:feature_code":"PPL",
    "gn:name":"Tav\u0101ndar",
    "gn:population":0,
    "gn:timezone":"Asia/Tehran",
    "iso:country":"IR",
    "name:fas_x_preferred":[
        "\u062a\u0648\u0646\u062f\u0631"
    ],
    "name:fas_x_variant":[
        "\u062a\u0648\u0627\u0646\u062f\u0631"
    ],
    "name:und_x_variant":[
        "Avandar",
        "Toondar",
        "Awandar",
        "Tavandar",
        "\u062a\u0648\u0646\u062f\u0631",
        "Tav\u0101ndar"
    ],
    "wof:name":"Tavandar",
    "wof:placetype":"locality"
},
  "geometry": {"coordinates":[58.27884,35.56802000000001],"type":"Point"}
}