{
  "type": "Feature",
  "properties": {
    "gn:admin1_code":"42.0",
    "gn:asciiname":"Afchang",
    "gn:country_code":"IR",
    "gn:dem":1649,
    "gn:feature_class":"P",
    "gn:feature_code":"PPL",
    "gn:name":"Afchang",
    "gn:population":0,
    "gn:timezone":"Asia/Tehran",
    "iso:country":"IR",
    "name:fas_x_preferred":[
        "\u0627\u0641\u0686\u0646\u06af"
    ],
    "wof:name":"Afchang",
    "wof:placetype":"locality"
},
  "geometry": {"coordinates":[57.63797,36.40788],"type":"Point"}
}