{
  "type": "Feature",
  "properties": {
    "gn:admin1_code":"10",
    "gn:asciiname":"Maziyeh",
    "gn:country_code":"IR",
    "gn:dem":914,
    "gn:feature_class":"P",
    "gn:feature_code":"PPL",
    "gn:name":"Maz\u012byeh",
    "gn:population":0,
    "gn:timezone":"Asia/Tehran",
    "iso:country":"IR",
    "name:fas_x_preferred":[
        "\u0645\u064e\u0632\u064a\u0650\u0651\u0647"
    ],
    "name:fas_x_variant":[
        "Maz\u012byeh"
    ],
    "wof:name":"Maziyeh",
    "wof:placetype":"locality"
},
  "geometry": {"coordinates":[46.75,33.05],"type":"Point"}
}