{
  "type": "Feature",
  "properties": {
    "gn:admin1_code":"16",
    "gn:asciiname":"Qezel Bolagh",
    "gn:country_code":"IR",
    "gn:dem":2065,
    "gn:feature_class":"P",
    "gn:feature_code":"PPL",
    "gn:name":"Qezel Bol\u0101gh",
    "gn:population":0,
    "gn:timezone":"Asia/Tehran",
    "iso:country":"IR",
    "name:fas_x_preferred":[
        "\u0642\u0632\u0650\u0644 \u0628\u0644\u0627\u063a"
    ],
    "name:fas_x_variant":[
        "\u0642\u0650\u0632\u0650\u0644 \u0628\u064f\u0644\u0627\u0642",
        "Qezel Bol\u0101gh",
        "\u0642\u0632\u0644\u200c\u0628\u0644\u0627\u063a"
    ],
    "name:und_x_variant":[
        "Qezel Bol\u0101q"
    ],
    "wof:name":"Qezel Bolagh",
    "wof:placetype":"locality"
},
  "geometry": {"coordinates":[46.76825,35.80785],"type":"Point"}
}