{
  "type": "Feature",
  "properties": {
    "gn:admin1_code":"13.0",
    "gn:asciiname":"Qal`eh Gah",
    "gn:country_code":"IR",
    "gn:dem":1469,
    "gn:feature_class":"P",
    "gn:feature_code":"PPL",
    "gn:name":"Qal\u2018eh G\u0101h",
    "gn:population":0,
    "gn:timezone":"Asia/Tehran",
    "iso:country":"IR",
    "name:fas_x_preferred":[
        "\u0642\u0644\u0639\u0647 \u06af\u0627\u0647"
    ],
    "name:fas_x_variant":[
        "Qal\u2018eh G\u0101h"
    ],
    "wof:name":"Qal`eh Gah",
    "wof:placetype":"locality"
},
  "geometry": {"coordinates":[46.4586,34.9057],"type":"Point"}
}