{
  "type": "Feature",
  "properties": {
    "gn:admin1_code":"7",
    "gn:asciiname":"Murzian",
    "gn:country_code":"IR",
    "gn:dem":2148,
    "gn:feature_class":"P",
    "gn:feature_code":"PPL",
    "gn:name":"M\u016brz\u012b\u0101n",
    "gn:population":0,
    "gn:timezone":"Asia/Tehran",
    "iso:country":"IR",
    "name:fas_x_preferred":[
        "Morz\u012b\u0101n"
    ],
    "name:fas_x_variant":[
        "M\u016brz\u012b\u0101n",
        "\u0645\u0648\u0631\u0632\u06cc\u0627\u0646",
        "\u0645\u0631\u0632\u06cc\u0627\u0646"
    ],
    "name:msa_x_preferred":[
        "Morzian"
    ],
    "name:und_x_variant":[
        "Mowrzey\u0101n"
    ],
    "wof:name":"Murzian",
    "wof:placetype":"locality"
},
  "geometry": {"coordinates":[51.99334,30.48386],"type":"Point"}
}