{
  "type": "Feature",
  "properties": {
    "gn:admin1_code":"33",
    "gn:asciiname":"Valandaran",
    "gn:country_code":"IR",
    "gn:dem":1945,
    "gn:feature_class":"P",
    "gn:feature_code":"PPL",
    "gn:name":"Valandar\u0101n",
    "gn:population":0,
    "gn:timezone":"Asia/Tehran",
    "iso:country":"IR",
    "name:azb_x_preferred":[
        "\u0648\u0644\u0646\u062f\u0631\u0627\u0646"
    ],
    "name:ceb_x_preferred":[
        "Valandar\u0101n"
    ],
    "name:fas_x_preferred":[
        "\u0648\u0644\u0646\u062f\u0631\u0627\u0646"
    ],
    "name:fas_x_variant":[
        "\u0648\u064e\u0644\u064a\u064e\u0646\u062f\u064f\u0631\u064e\u0646",
        "Valandar\u0101n"
    ],
    "name:msa_x_preferred":[
        "Valandaran"
    ],
    "name:swe_x_preferred":[
        "Valandar\u0101n"
    ],
    "name:und_x_variant":[
        "Valyandoran"
    ],
    "wof:name":"Valandaran",
    "wof:placetype":"locality"
},
  "geometry": {"coordinates":[47.01841,38.7901],"type":"Point"}
}