{
  "type": "Feature",
  "properties": {
    "gn:admin1_code":"4.0",
    "gn:asciiname":"Khowshab",
    "gn:country_code":"IR",
    "gn:dem":453,
    "gn:feature_class":"P",
    "gn:feature_code":"PPLF",
    "gn:name":"Khowsh\u0101b",
    "gn:population":0,
    "gn:timezone":"Asia/Tehran",
    "iso:country":"IR",
    "name:fas_x_preferred":[
        "\u062e\u0648\u0634\u0627\u0628"
    ],
    "name:und_x_variant":[
        "Khowsh\u0101b"
    ],
    "wof:name":"Khowshab",
    "wof:placetype":"locality"
},
  "geometry": {"coordinates":[59.54472,26.35954000000001],"type":"Point"}
}