{
  "type": "Feature",
  "properties": {
    "gn:admin1_code":"16.0",
    "gn:asciiname":"Darreh Gavan",
    "gn:country_code":"IR",
    "gn:dem":2159,
    "gn:elevation":"0.0",
    "gn:feature_class":"P",
    "gn:feature_code":"PPL",
    "gn:name":"Darreh G\u0101v\u0101n",
    "gn:population":0,
    "gn:timezone":"Asia/Tehran",
    "iso:country":"IR",
    "name:ara_x_preferred":[
        "\u062f\u0631\u0629 \u063a\u0627\u0648\u0627\u0646"
    ],
    "name:ceb_x_preferred":[
        "Darreh G\u0101v\u0101n"
    ],
    "name:ckb_x_preferred":[
        "\u062f\u06d5\u0631\u06d5\u06af\u0627\u0648\u0627\u0646"
    ],
    "name:fas_x_preferred":[
        "\u062f\u0631\u0651\u0647 \u06af\u0627\u0648\u0627\u0646"
    ],
    "name:fas_x_variant":[
        "Darreh G\u0101v\u0101n",
        "\u062f\u0631\u0647 \u06af\u0627\u0648\u0627\u0646"
    ],
    "name:swe_x_preferred":[
        "Darreh G\u0101v\u0101n"
    ],
    "wof:name":"Darreh Gavan",
    "wof:placetype":"locality"
},
  "geometry": {"coordinates":[46.6586,35.7645],"type":"Point"}
}