{
  "type": "Feature",
  "properties": {
    "gn:admin1_code":"32",
    "gn:asciiname":"Lataran",
    "gn:country_code":"IR",
    "gn:dem":1963,
    "gn:feature_class":"P",
    "gn:feature_code":"PPL",
    "gn:name":"L\u0101\u0163ar\u0101n",
    "gn:population":0,
    "gn:timezone":"Asia/Tehran",
    "iso:country":"IR",
    "name:fas_x_preferred":[
        "\u0644\u0627\u0637\u0631\u0627\u0646"
    ],
    "name:fas_x_variant":[
        "L\u0101\u0163ar\u0101n"
    ],
    "wof:name":"Lataran",
    "wof:placetype":"locality"
},
  "geometry": {"coordinates":[48.0119,38.1779],"type":"Point"}
}