{
  "type": "Feature",
  "properties": {
    "gn:admin1_code":"0",
    "gn:asciiname":"Gholamabad",
    "gn:country_code":"IR",
    "gn:dem":459,
    "gn:feature_class":"P",
    "gn:feature_code":"PPL",
    "gn:name":"Ghol\u0101m\u0101b\u0101d",
    "gn:population":0,
    "gn:timezone":"Asia/Tehran",
    "iso:country":"IR",
    "name:fas_x_preferred":[
        "\u063a\u0644\u0627\u0645 \u0622\u0628\u0627\u062f"
    ],
    "name:fas_x_variant":[
        "Ghol\u0101m\u0101b\u0101d",
        "\u063a\u0644\u0627\u0645\u200c\u0622\u0628\u0627\u062f"
    ],
    "wof:name":"Gholamabad",
    "wof:placetype":"locality"
},
  "geometry": {"coordinates":[52.7553,27.5898],"type":"Point"}
}