{
  "type": "Feature",
  "properties": {
    "gn:admin1_code":"42",
    "gn:asciiname":"Mian Margh",
    "gn:country_code":"IR",
    "gn:dem":1385,
    "gn:feature_class":"P",
    "gn:feature_code":"PPL",
    "gn:name":"M\u012b\u0101n Margh",
    "gn:population":0,
    "gn:timezone":"Asia/Tehran",
    "iso:country":"IR",
    "name:ceb_x_preferred":[
        "M\u012b\u0101n Margh"
    ],
    "name:fas_x_preferred":[
        "\u0645\u06cc\u0627\u0646 \u0645\u0631\u063a"
    ],
    "name:fas_x_variant":[
        "M\u012b\u0101n Margh"
    ],
    "name:swe_x_preferred":[
        "M\u012b\u0101n Margh"
    ],
    "name:und_x_variant":[
        "M\u012b\u0101n Morkh",
        "M\u012b\u0101n Morgh",
        "Miy\u0101n Markh"
    ],
    "wof:name":"Mian Margh",
    "wof:placetype":"locality"
},
  "geometry": {"coordinates":[59.40946,36.77204],"type":"Point"}
}