{
  "type": "Feature",
  "properties": {
    "gn:admin1_code":"40.0",
    "gn:asciiname":"Sar Cheshmeh Zarach",
    "gn:country_code":"IR",
    "gn:dem":1182,
    "gn:feature_class":"P",
    "gn:feature_code":"PPL",
    "gn:name":"Sar Cheshmeh Z\u0101rach",
    "gn:population":0,
    "gn:timezone":"Asia/Tehran",
    "iso:country":"IR",
    "name:fas_x_preferred":[
        "\u0633\u0631 \u0686\u0634\u0645\u0647 \u0632\u0627\u0631\u062c"
    ],
    "name:fas_x_variant":[
        "\u0632\u0627\u0631\u062c"
    ],
    "name:und_x_variant":[
        "Sar Cheshmeh Z\u0101rach",
        "Z\u0101rach"
    ],
    "wof:name":"Sar Cheshmeh Zarach",
    "wof:placetype":"locality"
},
  "geometry": {"coordinates":[54.25425,31.97992],"type":"Point"}
}