{
  "type": "Feature",
  "properties": {
    "gn:admin1_code":"35.0",
    "gn:asciiname":"Delavar Kola-ye Bala",
    "gn:country_code":"IR",
    "gn:dem":22,
    "gn:feature_class":"P",
    "gn:feature_code":"PPL",
    "gn:name":"Del\u0101var Kol\u0101-ye B\u0101l\u0101",
    "gn:population":0,
    "gn:timezone":"Asia/Tehran",
    "iso:country":"IR",
    "name:fas_x_preferred":[
        "Del\u0101var Kol\u0101-ye B\u0101l\u0101"
    ],
    "name:fas_x_variant":[
        "\u062f\u0644\u0627\u0648\u0631 \u06a9\u0644\u0627 \u0628\u0627\u0644\u0627"
    ],
    "wof:name":"Delavar Kola-ye Bala",
    "wof:placetype":"locality"
},
  "geometry": {"coordinates":[52.54834,36.44545],"type":"Point"}
}