{
  "type": "Feature",
  "properties": {
    "gn:admin1_code":"4.0",
    "gn:asciiname":"Chah-e `Abbas",
    "gn:country_code":"IR",
    "gn:dem":1178,
    "gn:feature_class":"P",
    "gn:feature_code":"PPLF",
    "gn:name":"Ch\u0101h-e \u2018Abb\u0101s",
    "gn:population":0,
    "gn:timezone":"Asia/Tehran",
    "iso:country":"IR",
    "name:fas_x_preferred":[
        "\u0686\u0627\u0647 \u0639\u0628\u0651\u0627\u0633"
    ],
    "name:fas_x_variant":[
        "K\u016breh-ye \u1e28\u0101jj\u012b \u2018Abb\u0101s",
        "Ch\u0101h-e \u2018Abb\u0101s",
        "\u0686\u0627\u0647 \u062c\u0645\u0639\u0647 \u062e\u0627\u0646"
    ],
    "name:und_x_variant":[
        "Ch\u0101h-e \u2018Abb\u0101s",
        "Shom\u0101reh-ye Yek",
        "\u0634\u0645\u0627\u0631\u0647 \u064a\u06a9",
        "Ch\u0101h-e Jom\u2018eh Kh\u0101n"
    ],
    "wof:name":"Chah-e `Abbas",
    "wof:placetype":"locality"
},
  "geometry": {"coordinates":[61.8351,27.408],"type":"Point"}
}