{
  "type": "Feature",
  "properties": {
    "gn:admin1_code":"0",
    "gn:asciiname":"Howz-e Boland",
    "gn:cc2":"IR",
    "gn:country_code":"IR",
    "gn:dem":1736,
    "gn:feature_class":"P",
    "gn:feature_code":"PPL",
    "gn:name":"\u1e28ow\u1e95-e Boland",
    "gn:population":0,
    "gn:timezone":"Asia/Tehran",
    "iso:country":"IR",
    "name:fas_x_preferred":[
        "\u062d\u064f\u0648\u0636\u0650 \u0628\u064f\u0644\u064e\u0646\u062f"
    ],
    "name:fas_x_variant":[
        "\u1e28ow\u1e95-e Boland"
    ],
    "name:und_x_variant":[
        "Hauz-i-Buland"
    ],
    "wof:name":"Howz-e Boland",
    "wof:placetype":"locality"
},
  "geometry": {"coordinates":[55.78333000000001,31.26667],"type":"Point"}
}