{
  "type": "Feature",
  "properties": {
    "gn:admin1_code":"16",
    "gn:asciiname":"Merkeh Derizh",
    "gn:country_code":"IR",
    "gn:dem":1366,
    "gn:feature_class":"P",
    "gn:feature_code":"PPL",
    "gn:name":"Merkeh Der\u012bzh",
    "gn:population":0,
    "gn:timezone":"Asia/Tehran",
    "iso:country":"IR",
    "name:ceb_x_preferred":[
        "Merkeh Der\u012bzh"
    ],
    "name:ckb_x_preferred":[
        "\u0645\u06ce\u0631\u06af\u06d5\u062f\u0631\u06ce\u0698"
    ],
    "name:fas_x_preferred":[
        "\u0645\u064a\u0631\u06af\u0647 \u062f\u0631\u064a\u0698"
    ],
    "name:fas_x_variant":[
        "\u0645\u064a\u0631\u06af\u0650\u062f\u0631\u0650\u0698",
        "\u0645\u0650\u0631\u06af\u0650\u0647 \u062f\u0650\u0631\u064a\u0698",
        "\u0645\u0650\u0631\u06af\u0650\u0647 \u062f\u064f\u0631\u064a\u0698",
        "\u0645\u0650\u0631\u06af\u0650\u0647 \u062f\u064e\u0631\u0634\u064a\u0631",
        "\u0645\u0631\u06a9\u0647 \u062f\u0631\u06cc\u0698",
        "M\u012brgah-e Der\u012bzh",
        "Merkeh Der\u012bzh",
        "\u0645\u06cc\u0631\u06af\u0647 \u062f\u0631\u06cc\u0698"
    ],
    "name:swe_x_preferred":[
        "Merkeh Der\u012bzh"
    ],
    "name:und_x_variant":[
        "Mergeh Der\u012bzh",
        "Mergeh Darsh\u012br",
        "Mirgehdrij",
        "Mirg-i-Dariz",
        "M\u012brgedrezh",
        "Mirkeh Darizheh",
        "Mergeh Dor\u012bzh",
        "M\u012brgeh Der\u012bzh"
    ],
    "wof:name":"Merkeh Derizh",
    "wof:placetype":"locality"
},
  "geometry": {"coordinates":[46.1053,35.6733],"type":"Point"}
}