{
  "type": "Feature",
  "properties": {
    "gn:admin1_code":"4",
    "gn:asciiname":"Sarzeh",
    "gn:country_code":"IR",
    "gn:dem":1174,
    "gn:feature_class":"P",
    "gn:feature_code":"PPL",
    "gn:name":"Sarzeh",
    "gn:population":0,
    "gn:timezone":"Asia/Tehran",
    "iso:country":"IR",
    "name:und_x_variant":[
        "\u0633\u0631\u0632\u0647",
        "Sarzeh"
    ],
    "wof:name":"Sarzeh",
    "wof:placetype":"locality"
},
  "geometry": {"coordinates":[60.77278,26.67056],"type":"Point"}
}