{
  "type": "Feature",
  "properties": {
    "gn:admin1_code":"35",
    "gn:asciiname":"Sufian",
    "gn:cc2":"IR",
    "gn:country_code":"IR",
    "gn:dem":146,
    "gn:feature_class":"P",
    "gn:feature_code":"PPL",
    "gn:name":"\u015e\u016bf\u012b\u0101n",
    "gn:population":0,
    "gn:timezone":"Asia/Tehran",
    "iso:country":"IR",
    "name:fas_x_preferred":[
        "\u0635\u0648\u0641\u064a\u0627\u0646"
    ],
    "name:fas_x_variant":[
        "\u0633\u0648\u0641\u064a\u0651\u0627\u0646"
    ],
    "name:und_x_variant":[
        "S\u016bf\u012by\u0101n"
    ],
    "wof:name":"Sufian",
    "wof:placetype":"locality"
},
  "geometry": {"coordinates":[55.44583000000001,37.47028],"type":"Point"}
}