{
  "type": "Feature",
  "properties": {
    "gn:admin1_code":"42",
    "gn:asciiname":"Shah Taqi",
    "gn:country_code":"IR",
    "gn:dem":1414,
    "gn:feature_class":"P",
    "gn:feature_code":"PPL",
    "gn:name":"Sh\u0101h Taq\u012b",
    "gn:population":0,
    "gn:timezone":"Asia/Tehran",
    "iso:country":"IR",
    "name:ceb_x_preferred":[
        "Sh\u0101h Taq\u012b"
    ],
    "name:fas_x_preferred":[
        "\u0634\u0627\u0647 \u062a\u0642\u06cc"
    ],
    "name:fas_x_variant":[
        "Sh\u0101h Taq\u012b",
        "\u0627\u0645\u0627\u0645 \u062a\u0642\u06cc"
    ],
    "name:swe_x_preferred":[
        "Sh\u0101h Taq\u012b"
    ],
    "name:und_x_variant":[
        "Em\u0101m Taq\u012b",
        "Sh\u0101h Tak\u012b",
        "Sh\u0101h Taq\u012b-ye P\u012bveh Zhan"
    ],
    "wof:name":"Shah Taqi",
    "wof:placetype":"locality"
},
  "geometry": {"coordinates":[59.44112,35.96435],"type":"Point"}
}