{
  "type": "Feature",
  "properties": {
    "gn:admin1_code":"41.0",
    "gn:asciiname":"Deh-e Shib",
    "gn:country_code":"IR",
    "gn:dem":1307,
    "gn:feature_class":"P",
    "gn:feature_code":"PPL",
    "gn:name":"Deh-e Sh\u012bb",
    "gn:population":0,
    "gn:timezone":"Asia/Tehran",
    "iso:country":"IR",
    "name:fas_x_preferred":[
        "Deh-e Sh\u012bb"
    ],
    "name:fas_x_variant":[
        "\u062f\u0647 \u0634\u06cc\u0628"
    ],
    "name:und_x_variant":[
        "\u062f\u0647 \u0634\u06cc\u0628"
    ],
    "wof:name":"Deh-e Shib",
    "wof:placetype":"locality"
},
  "geometry": {"coordinates":[57.2473,33.38059000000001],"type":"Point"}
}