{
  "type": "Feature",
  "properties": {
    "gn:admin1_code":"13",
    "gn:asciiname":"Dar Badam-e `Olya",
    "gn:country_code":"IR",
    "gn:dem":1675,
    "gn:feature_class":"P",
    "gn:feature_code":"PPL",
    "gn:name":"D\u0101r B\u0101d\u0101m-e \u2018Oly\u0101",
    "gn:population":0,
    "gn:timezone":"Asia/Tehran",
    "iso:country":"IR",
    "name:ara_x_preferred":[
        "\u062f\u0627\u0631\u0628\u0627\u062f\u0627\u0645"
    ],
    "name:ceb_x_preferred":[
        "D\u0101r B\u0101d\u0101m-e \u2018Oly\u0101"
    ],
    "name:fas_x_preferred":[
        "\u062f\u0627\u0631 \u0628\u0627\u062f\u0627\u0645 \u0639\u0644\u06cc\u0627"
    ],
    "name:fas_x_variant":[
        "D\u0101r B\u0101d\u0101m",
        "D\u0101r B\u0101d\u0101m-e \u2018Oly\u0101",
        "\u062f\u0627\u0631\u0628\u0627\u062f\u0627\u0645"
    ],
    "name:swe_x_preferred":[
        "D\u0101r B\u0101d\u0101m-e \u2018Oly\u0101"
    ],
    "wof:name":"Dar Badam-e `Olya",
    "wof:placetype":"locality"
},
  "geometry": {"coordinates":[46.39989,34.02781],"type":"Point"}
}