{
  "type": "Feature",
  "properties": {
    "gn:admin1_code":"4",
    "gn:asciiname":"Chah-e Dadrahman",
    "gn:country_code":"IR",
    "gn:dem":1161,
    "gn:feature_class":"P",
    "gn:feature_code":"PPL",
    "gn:name":"Ch\u0101h-e D\u0101dra\u1e29m\u0101n",
    "gn:population":0,
    "gn:timezone":"Asia/Tehran",
    "iso:country":"IR",
    "name:fas_x_preferred":[
        "\u062c\u0645\u0639\u0627 \u0647\u0627\u0646"
    ],
    "name:fas_x_variant":[
        "\u0686\u0627\u0647 \u062f\u0627\u062f\u0631\u062d\u0645\u0627\u0646"
    ],
    "name:und_x_variant":[
        "Jom\u2018\u0101h\u0101n",
        "Ch\u0101h-e D\u0101dra\u1e29m\u0101n"
    ],
    "wof:name":"Chah-e Dadrahman",
    "wof:placetype":"locality"
},
  "geometry": {"coordinates":[61.9394,27.3729],"type":"Point"}
}