{
  "type": "Feature",
  "properties": {
    "gn:admin1_code":"1",
    "gn:asciiname":"`Abd or Razzaq",
    "gn:country_code":"IR",
    "gn:dem":2048,
    "gn:feature_class":"P",
    "gn:feature_code":"PPL",
    "gn:name":"\u2018Abd or Razz\u0101q",
    "gn:population":0,
    "gn:timezone":"Asia/Tehran",
    "iso:country":"IR",
    "name:fas_x_preferred":[
        "\u0639\u0628\u062f\u0627\u0644\u0631\u0632\u0651\u0627\u0642"
    ],
    "name:fas_x_variant":[
        "\u0639\u064e\u0628\u062f \u0627\u0644\u0631\u064e\u0632\u0651\u0627\u0642"
    ],
    "name:und_x_variant":[
        "\u2018Abd or Razz\u0101q"
    ],
    "wof:name":"`Abd or Razzaq",
    "wof:placetype":"locality"
},
  "geometry": {"coordinates":[44.6472,39.0033],"type":"Point"}
}