{
  "type": "Feature",
  "properties": {
    "gn:admin1_code":"5",
    "gn:asciiname":"Garab-e Pa'in",
    "gn:country_code":"IR",
    "gn:dem":1556,
    "gn:feature_class":"P",
    "gn:feature_code":"PPL",
    "gn:name":"Gar\u0101b-e P\u0101\u2019\u012bn",
    "gn:population":0,
    "gn:timezone":"Asia/Tehran",
    "iso:country":"IR",
    "name:fas_x_preferred":[
        "Gar\u0101b-e P\u0101\u2019\u012bn"
    ],
    "name:fas_x_variant":[
        "\u06af\u0631\u0627\u0628 \u067e\u0627\u0626\u064a\u0646"
    ],
    "name:und_x_variant":[
        "\u06af\u0631\u0627\u0628 \u067e\u0627\u0626\u064a\u0646"
    ],
    "wof:name":"Garab-e Pa'in",
    "wof:placetype":"locality"
},
  "geometry": {"coordinates":[50.88783,30.94735],"type":"Point"}
}