{
  "type": "Feature",
  "properties": {
    "gn:admin1_code":"5",
    "gn:asciiname":"Marin",
    "gn:country_code":"IR",
    "gn:dem":1120,
    "gn:feature_class":"P",
    "gn:feature_code":"PPL",
    "gn:name":"M\u0101r\u012bn",
    "gn:population":0,
    "gn:timezone":"Asia/Tehran",
    "iso:country":"IR",
    "name:bre_x_preferred":[
        "Marin"
    ],
    "name:bul_x_preferred":[
        "\u041c\u0430\u0440\u0438\u043d"
    ],
    "name:ceb_x_preferred":[
        "Marin"
    ],
    "name:ces_x_preferred":[
        "Marin"
    ],
    "name:deu_x_preferred":[
        "Marin"
    ],
    "name:epo_x_preferred":[
        "Marin"
    ],
    "name:est_x_preferred":[
        "Marin"
    ],
    "name:fas_x_preferred":[
        "\u0645\u064e\u0631\u064a\u0646"
    ],
    "name:fas_x_variant":[
        "M\u0101r\u012bn",
        "\u0645\u0627\u0631\u06cc\u0646"
    ],
    "name:fra_x_preferred":[
        "Marin"
    ],
    "name:hye_x_preferred":[
        "\u0544\u0561\u0580\u056b\u0576"
    ],
    "name:ita_x_preferred":[
        "Marin"
    ],
    "name:nds_x_preferred":[
        "Marin"
    ],
    "name:nld_x_preferred":[
        "Marin"
    ],
    "name:pol_x_preferred":[
        "Marin"
    ],
    "name:por_x_preferred":[
        "Marin"
    ],
    "name:ron_x_preferred":[
        "Marin"
    ],
    "name:rus_x_preferred":[
        "\u041c\u0430\u0440\u0438\u043d"
    ],
    "name:slv_x_preferred":[
        "Marin"
    ],
    "name:spa_x_preferred":[
        "Marin"
    ],
    "name:srp_x_preferred":[
        "\u041c\u0430\u0440\u0438\u043d"
    ],
    "name:swe_x_preferred":[
        "Marin"
    ],
    "name:ukr_x_preferred":[
        "\u041c\u0430\u0440\u0438\u043d"
    ],
    "name:und_x_variant":[
        "Mar\u012bn",
        "\u0645\u0627\u0631\u06cc\u0646"
    ],
    "wof:name":"Marin",
    "wof:placetype":"locality"
},
  "geometry": {"coordinates":[50.80284,30.55136],"type":"Point"}
}