{
  "type": "Feature",
  "properties": {
    "gn:admin1_code":"29",
    "gn:asciiname":"Choghukabad-e Bala",
    "gn:country_code":"IR",
    "gn:dem":796,
    "gn:feature_class":"P",
    "gn:feature_code":"PPL",
    "gn:name":"Chogh\u016bk\u0101b\u0101d-e B\u0101l\u0101",
    "gn:population":0,
    "gn:timezone":"Asia/Tehran",
    "iso:country":"IR",
    "name:fas_x_preferred":[
        "Shams\u0101b\u0101d"
    ],
    "name:fas_x_variant":[
        "\u0686\u063a\u0648\u06a9 \u0622\u0628\u0627\u062f \u0628\u0627\u0644\u0627",
        "\u0634\u0645\u0633 \u0622\u0628\u0627\u062f"
    ],
    "name:und_x_variant":[
        "Chogh\u016bk\u0101b\u0101d-e B\u0101l\u0101"
    ],
    "wof:name":"Choghukabad-e Bala",
    "wof:placetype":"locality"
},
  "geometry": {"coordinates":[58.65785,28.91735],"type":"Point"}
}