{
  "type": "Feature",
  "properties": {
    "gn:admin1_code":"40.0",
    "gn:asciiname":"Zarband",
    "gn:country_code":"IR",
    "gn:dem":1871,
    "gn:feature_class":"P",
    "gn:feature_code":"PPLF",
    "gn:name":"Zarband",
    "gn:population":0,
    "gn:timezone":"Asia/Tehran",
    "iso:country":"IR",
    "name:und_x_variant":[
        "Zorband",
        "Zarband",
        "\u0632\u0631\u0628\u0646\u062f"
    ],
    "wof:name":"Zarband",
    "wof:placetype":"locality"
},
  "geometry": {"coordinates":[54.00514,31.81946],"type":"Point"}
}