{
  "type": "Feature",
  "properties": {
    "gn:admin1_code":"35.0",
    "gn:asciiname":"Mur",
    "gn:country_code":"IR",
    "gn:dem":1237,
    "gn:feature_class":"P",
    "gn:feature_code":"PPL",
    "gn:name":"M\u016br",
    "gn:population":0,
    "gn:timezone":"Asia/Tehran",
    "iso:country":"IR",
    "name:ara_x_preferred":[
        "\u0645\u0648\u0631"
    ],
    "name:bel_x_preferred":[
        "\u041c\u0443\u0440"
    ],
    "name:ben_x_preferred":[
        "\u09ae\u09c1\u09b0"
    ],
    "name:bre_x_preferred":[
        "Mur"
    ],
    "name:bul_x_preferred":[
        "\u041c\u0443\u0440"
    ],
    "name:cat_x_preferred":[
        "Mur"
    ],
    "name:ceb_x_preferred":[
        "Mur"
    ],
    "name:dan_x_preferred":[
        "Mur"
    ],
    "name:deu_x_preferred":[
        "Mur"
    ],
    "name:eus_x_preferred":[
        "Mur"
    ],
    "name:fas_x_preferred":[
        "\u0645\u0648\u0631"
    ],
    "name:fas_x_variant":[
        "M\u016br"
    ],
    "name:fra_x_preferred":[
        "Mur"
    ],
    "name:heb_x_preferred":[
        "\u05de\u05d5\u05e8"
    ],
    "name:hin_x_preferred":[
        "\u092e\u0941\u0930"
    ],
    "name:hun_x_preferred":[
        "Mur"
    ],
    "name:nld_x_preferred":[
        "Mur"
    ],
    "name:nor_x_preferred":[
        "Mur"
    ],
    "name:pol_x_preferred":[
        "Mur"
    ],
    "name:por_x_preferred":[
        "Mur"
    ],
    "name:ron_x_preferred":[
        "Mur"
    ],
    "name:rus_x_preferred":[
        "\u041c\u0443\u0440"
    ],
    "name:srp_x_preferred":[
        "\u041c\u0443\u0440"
    ],
    "name:ukr_x_preferred":[
        "\u041c\u0443\u0440"
    ],
    "name:urd_x_preferred":[
        "\u0645\u0631"
    ],
    "name:vie_x_preferred":[
        "S\u00f4ng Mur"
    ],
    "wof:name":"Mur",
    "wof:placetype":"locality"
},
  "geometry": {"coordinates":[51.74025,36.50407],"type":"Point"}
}