{
  "type": "Feature",
  "properties": {
    "gn:admin1_code":"35.0",
    "gn:asciiname":"Mur",
    "gn:country_code":"IR",
    "gn:dem":1237,
    "gn:feature_class":"P",
    "gn:feature_code":"PPL",
    "gn:name":"M\u016br",
    "gn:population":0,
    "gn:timezone":"Asia/Tehran",
    "iso:country":"IR",
    "name:fas_x_preferred":[
        "\u0645\u0648\u0631"
    ],
    "name:fas_x_variant":[
        "M\u016br"
    ],
    "wof:name":"Mur",
    "wof:placetype":"locality"
},
  "geometry": {"coordinates":[51.74025,36.50407],"type":"Point"}
}