{
  "type": "Feature",
  "properties": {
    "gn:admin1_code":"10",
    "gn:asciiname":"Marun",
    "gn:country_code":"IR",
    "gn:dem":923,
    "gn:feature_class":"P",
    "gn:feature_code":"PPL",
    "gn:name":"M\u0101r\u016bn",
    "gn:population":0,
    "gn:timezone":"Asia/Tehran",
    "iso:country":"IR",
    "name:fas_x_preferred":[
        "\u0645\u0627\u0631\u0648\u0646"
    ],
    "name:fas_x_variant":[
        "M\u0101r\u016bn"
    ],
    "wof:name":"Marun",
    "wof:placetype":"locality"
},
  "geometry": {"coordinates":[47.5719,32.9396],"type":"Point"}
}