{
  "type": "Feature",
  "properties": {
    "gn:admin1_code":"0",
    "gn:asciiname":"Tam Siahu",
    "gn:country_code":"IR",
    "gn:dem":332,
    "gn:feature_class":"P",
    "gn:feature_code":"PPL",
    "gn:name":"Tam S\u012b\u0101h\u016b",
    "gn:population":0,
    "gn:timezone":"Asia/Tehran",
    "iso:country":"IR",
    "name:fas_x_preferred":[
        "\u062a\u0645 \u0633\u06cc\u0627\u0647\u0648"
    ],
    "name:fas_x_variant":[
        "Esl\u0101m\u0101b\u0101d",
        "\u0627\u0633\u0644\u0627\u0645 \u0622\u0628\u0627\u062f",
        "Tam S\u012b\u0101h\u016b"
    ],
    "wof:name":"Tam Siahu",
    "wof:placetype":"locality"
},
  "geometry": {"coordinates":[57.5303,27.3733],"type":"Point"}
}