{
  "type": "Feature",
  "properties": {
    "gn:admin1_code":"7.0",
    "gn:asciiname":"Kushk-e Hemindeh",
    "gn:country_code":"IR",
    "gn:dem":1056,
    "gn:feature_class":"P",
    "gn:feature_code":"PPL",
    "gn:name":"K\u016bshk-e Hem\u012bndeh",
    "gn:population":0,
    "gn:timezone":"Asia/Tehran",
    "iso:country":"IR",
    "name:fas_x_preferred":[
        "K\u016bshk-e Hem\u012bndeh"
    ],
    "wof:name":"Kushk-e Hemindeh",
    "wof:placetype":"locality"
},
  "geometry": {"coordinates":[53.01056,28.66972],"type":"Point"}
}