{
  "type": "Feature",
  "properties": {
    "gn:admin1_code":"29",
    "gn:asciiname":"Now Dasht",
    "gn:country_code":"IR",
    "gn:dem":2093,
    "gn:feature_class":"P",
    "gn:feature_code":"PPL",
    "gn:name":"Now Dasht",
    "gn:population":0,
    "gn:timezone":"Asia/Tehran",
    "iso:country":"IR",
    "name:fas_x_preferred":[
        "\u0646\u0648 \u062f\u0634\u062a"
    ],
    "wof:name":"Now Dasht",
    "wof:placetype":"locality"
},
  "geometry": {"coordinates":[56.6374,29.878],"type":"Point"}
}