{
  "type": "Feature",
  "properties": {
    "gn:admin1_code":"8.0",
    "gn:asciiname":"Kulari",
    "gn:country_code":"IR",
    "gn:dem":1375,
    "gn:feature_class":"P",
    "gn:feature_code":"PPL",
    "gn:name":"K\u016bl\u0101r\u012b",
    "gn:population":0,
    "gn:timezone":"Asia/Tehran",
    "iso:country":"IR",
    "name:fas_x_preferred":[
        "\u06a9\u0648\u0644\u0627\u0631\u06cc"
    ],
    "name:fas_x_variant":[
        "K\u016bl\u0101r\u012b"
    ],
    "wof:name":"Kulari",
    "wof:placetype":"locality"
},
  "geometry": {"coordinates":[48.6458,37.6628],"type":"Point"}
}