{
  "type": "Feature",
  "properties": {
    "gn:admin1_code":"4",
    "gn:asciiname":"Ti'i Dar",
    "gn:country_code":"IR",
    "gn:dem":557,
    "gn:feature_class":"P",
    "gn:feature_code":"PPL",
    "gn:name":"T\u012b\u2019\u012b Dar",
    "gn:population":0,
    "gn:timezone":"Asia/Tehran",
    "iso:country":"IR",
    "name:fas_x_preferred":[
        "T\u012b Dar"
    ],
    "name:fas_x_variant":[
        "D\u012b\u0101dar",
        "\u062a\u06cc \u062f\u0631",
        "Dey\u0101der",
        "Day\u0101dar",
        "\u062a\u06cc\u06cc \u062f\u0631"
    ],
    "name:und_x_variant":[
        "Day\u0101dar",
        "Dey\u0101der",
        "\u062a\u06cc \u062f\u0631",
        "T\u012b\u2019\u012b Dar"
    ],
    "wof:name":"Ti'i Dar",
    "wof:placetype":"locality"
},
  "geometry": {"coordinates":[59.27832,26.87569],"type":"Point"}
}