{
  "type": "Feature",
  "properties": {
    "gn:admin1_code":"13",
    "gn:asciiname":"Mirza Kuseh",
    "gn:country_code":"IR",
    "gn:dem":1431,
    "gn:feature_class":"P",
    "gn:feature_code":"PPL",
    "gn:name":"M\u012brz\u0101 K\u016bseh",
    "gn:population":0,
    "gn:timezone":"Asia/Tehran",
    "iso:country":"IR",
    "name:fas_x_preferred":[
        "\u0645\u06cc\u0631\u0632\u0627 \u06a9\u0648\u0633\u0647"
    ],
    "name:fas_x_variant":[
        "M\u012brz\u0101 K\u016bseh"
    ],
    "wof:name":"Mirza Kuseh",
    "wof:placetype":"locality"
},
  "geometry": {"coordinates":[47.3428,34.3026],"type":"Point"}
}