{
  "type": "Feature",
  "properties": {
    "gn:admin1_code":"16",
    "gn:asciiname":"Mahmudeh",
    "gn:country_code":"IR",
    "gn:dem":1942,
    "gn:feature_class":"P",
    "gn:feature_code":"PPL",
    "gn:name":"Ma\u1e29m\u016bdeh",
    "gn:population":0,
    "gn:timezone":"Asia/Tehran",
    "iso:country":"IR",
    "name:fas_x_preferred":[
        "\u0645\u062d\u0645\u0648\u062f\u0647"
    ],
    "name:fas_x_variant":[
        "\u0645\u062d\u0645\u0648\u062f \u0622\u0628\u0627\u062f",
        "Ma\u1e29m\u016bdeh",
        "Ma\u1e29m\u016bd\u0101b\u0101d"
    ],
    "name:und_x_variant":[
        "Muhammad\u0101b\u0101d",
        "Mo\u1e29ammad\u0101b\u0101d"
    ],
    "wof:name":"Mahmudeh",
    "wof:placetype":"locality"
},
  "geometry": {"coordinates":[47.0847,35.71609],"type":"Point"}
}