{
  "type": "Feature",
  "properties": {
    "gn:admin1_code":"13",
    "gn:asciiname":"Maryam Negar",
    "gn:country_code":"IR",
    "gn:dem":1385,
    "gn:feature_class":"P",
    "gn:feature_code":"PPL",
    "gn:name":"Maryam Neg\u0101r",
    "gn:population":0,
    "gn:timezone":"Asia/Tehran",
    "iso:country":"IR",
    "name:ceb_x_preferred":[
        "Maryam Neg\u0101r"
    ],
    "name:fas_x_preferred":[
        "\u0645\u0631\u06cc\u0645 \u0646\u06af\u0627\u0631"
    ],
    "name:fas_x_variant":[
        "Maryam Neg\u0101r",
        "\u0645\u0631\u06cc\u0645\u0646\u06af\u0627\u0631"
    ],
    "name:swe_x_preferred":[
        "Maryam Neg\u0101r"
    ],
    "wof:name":"Maryam Negar",
    "wof:placetype":"locality"
},
  "geometry": {"coordinates":[47.51594,34.58619],"type":"Point"}
}