{
  "type": "Feature",
  "properties": {
    "gn:admin1_code":"29",
    "gn:asciiname":"Seyyedabad",
    "gn:country_code":"IR",
    "gn:dem":2026,
    "gn:feature_class":"P",
    "gn:feature_code":"PPLF",
    "gn:name":"Seyyed\u0101b\u0101d",
    "gn:population":0,
    "gn:timezone":"Asia/Tehran",
    "iso:country":"IR",
    "name:fas_x_preferred":[
        "Seyyed\u0101b\u0101d"
    ],
    "name:fas_x_variant":[
        "\u0633\u06cc\u062f \u0622\u0628\u0627\u062f"
    ],
    "wof:name":"Seyyedabad",
    "wof:placetype":"locality"
},
  "geometry": {"coordinates":[56.45806,31.07442],"type":"Point"}
}