{
  "type": "Feature",
  "properties": {
    "gn:admin1_code":"7",
    "gn:asciiname":"Chah Khashdu",
    "gn:country_code":"IR",
    "gn:dem":1597,
    "gn:feature_class":"P",
    "gn:feature_code":"PPL",
    "gn:name":"Ch\u0101h Khashd\u016b",
    "gn:population":0,
    "gn:timezone":"Asia/Tehran",
    "iso:country":"IR",
    "name:fas_x_preferred":[
        "\u0686\u0627\u0647 \u062e\u0634\u062f\u0648"
    ],
    "name:fas_x_variant":[
        "Ch\u0101h Khashd\u016b"
    ],
    "wof:name":"Chah Khashdu",
    "wof:placetype":"locality"
},
  "geometry": {"coordinates":[55.1645,28.9638],"type":"Point"}
}