{
  "type": "Feature",
  "properties": {
    "gn:admin1_code":"35.0",
    "gn:asciiname":"Aqa Moqim Mahalleh",
    "gn:country_code":"IR",
    "gn:dem":35,
    "gn:feature_class":"P",
    "gn:feature_code":"PPL",
    "gn:name":"\u0100q\u0101 Moq\u012bm Ma\u1e29alleh",
    "gn:population":0,
    "gn:timezone":"Asia/Tehran",
    "iso:country":"IR",
    "name:fas_x_preferred":[
        "\u0622\u0642\u0627 \u0645\u0642\u06cc\u0645 \u0645\u062d\u0644\u0647"
    ],
    "name:fas_x_variant":[
        "\u0622\u0642\u0627\u0645\u0642\u06cc\u0645\u200c\u0645\u062d\u0644\u0647"
    ],
    "name:und_x_variant":[
        "\u0100q\u0101 Moq\u012bm Ma\u1e29alleh"
    ],
    "wof:name":"Aqa Moqim Mahalleh",
    "wof:placetype":"locality"
},
  "geometry": {"coordinates":[50.81232,36.80148],"type":"Point"}
}