{
  "type": "Feature",
  "properties": {
    "gn:admin1_code":"1",
    "gn:asciiname":"Maqsudabad",
    "gn:country_code":"IR",
    "gn:dem":2295,
    "gn:feature_class":"P",
    "gn:feature_code":"PPL",
    "gn:name":"Maq\u015f\u016bd\u0101b\u0101d",
    "gn:population":0,
    "gn:timezone":"Asia/Tehran",
    "iso:country":"IR",
    "name:fas_x_preferred":[
        "\u0645\u064e\u0642\u0635\u0648\u062f\u0627\u0628\u0627\u062f\u0650 \u0628\u0627\u0644\u0627"
    ],
    "name:fas_x_variant":[
        "\u0645\u0642\u0635\u0648\u062f \u0622\u0628\u0627\u062f",
        "Maq\u015f\u016bd\u0101b\u0101d-e B\u0101l\u0101",
        "Maq\u015f\u016bd\u0101b\u0101d",
        "\u0645\u0642\u0635\u0648\u062f\u0622\u0628\u0627\u062f"
    ],
    "wof:name":"Maqsudabad",
    "wof:placetype":"locality"
},
  "geometry": {"coordinates":[44.2286,39.2043],"type":"Point"}
}