{
  "type": "Feature",
  "properties": {
    "gn:admin1_code":"7",
    "gn:asciiname":"Qal`eh-ye Loqmani",
    "gn:country_code":"IR",
    "gn:dem":842,
    "gn:feature_class":"P",
    "gn:feature_code":"PPL",
    "gn:name":"Qal\u2018eh-ye Loqm\u0101n\u012b",
    "gn:population":0,
    "gn:timezone":"Asia/Tehran",
    "iso:country":"IR",
    "name:fas_x_preferred":[
        "Qal\u2018eh-ye Loqm\u0101n\u012b"
    ],
    "wof:name":"Qal`eh-ye Loqmani",
    "wof:placetype":"locality"
},
  "geometry": {"coordinates":[51.72667,29.50528],"type":"Point"}
}