{
  "type": "Feature",
  "properties": {
    "gn:admin1_code":"28.0",
    "gn:asciiname":"Nakhlak",
    "gn:country_code":"IR",
    "gn:dem":1014,
    "gn:feature_class":"P",
    "gn:feature_code":"PPL",
    "gn:name":"Nakhlak",
    "gn:population":0,
    "gn:timezone":"Asia/Tehran",
    "iso:country":"IR",
    "name:fas_x_preferred":[
        "\u0646\u062e\u0644\u06a9"
    ],
    "wof:name":"Nakhlak",
    "wof:placetype":"locality"
},
  "geometry": {"coordinates":[53.84297,33.56237],"type":"Point"}
}