{
  "type": "Feature",
  "properties": {
    "gn:admin1_code":"23.0",
    "gn:asciiname":"Hian",
    "gn:country_code":"IR",
    "gn:dem":1454,
    "gn:feature_class":"P",
    "gn:feature_code":"PPL",
    "gn:name":"H\u012b\u0101n",
    "gn:population":0,
    "gn:timezone":"Asia/Tehran",
    "iso:country":"IR",
    "name:fas_x_preferred":[
        "\u0647\u064a\u0627\u0646"
    ],
    "name:und_x_variant":[
        "H\u012b\u0101n"
    ],
    "wof:name":"Hian",
    "wof:placetype":"locality"
},
  "geometry": {"coordinates":[48.58014,33.22418],"type":"Point"}
}