{
  "type": "Feature",
  "properties": {
    "gn:admin1_code":"13",
    "gn:asciiname":"Masheh",
    "gn:country_code":"IR",
    "gn:dem":1553,
    "gn:feature_class":"P",
    "gn:feature_code":"PPL",
    "gn:name":"Masheh",
    "gn:population":0,
    "gn:timezone":"Asia/Tehran",
    "iso:country":"IR",
    "wof:name":"Masheh",
    "wof:placetype":"locality"
},
  "geometry": {"coordinates":[47.04972,34.26278],"type":"Point"}
}