{
  "type": "Feature",
  "properties": {
    "gn:admin1_code":"29",
    "gn:asciiname":"Bahrami-ye Bala",
    "gn:cc2":"IR",
    "gn:country_code":"IR",
    "gn:dem":596,
    "gn:feature_class":"P",
    "gn:feature_code":"PPL",
    "gn:name":"Bahr\u0101m\u012b-ye B\u0101l\u0101",
    "gn:population":0,
    "gn:timezone":"Asia/Tehran",
    "iso:country":"IR",
    "name:fas_x_preferred":[
        "Bahr\u0101m\u012b-ye B\u0101l\u0101"
    ],
    "name:und_x_variant":[
        "Bahr\u0101m\u012b-ye S\u0101rd\u016b\u2019\u012byeh",
        "Bahrami Sardoo\u2019iyeh",
        "Bahr\u0101m\u012b"
    ],
    "wof:name":"Bahrami-ye Bala",
    "wof:placetype":"locality"
},
  "geometry": {"coordinates":[57.8025,28.52944],"type":"Point"}
}