{
  "type": "Feature",
  "properties": {
    "gn:admin1_code":"3",
    "gn:asciiname":"Bahmanabad",
    "gn:country_code":"IR",
    "gn:dem":2516,
    "gn:feature_class":"P",
    "gn:feature_code":"PPL",
    "gn:name":"Bahman\u0101b\u0101d",
    "gn:population":0,
    "gn:timezone":"Asia/Tehran",
    "iso:country":"IR",
    "name:aze_x_preferred":[
        "B\u0259hm\u0259nabad"
    ],
    "name:fas_x_preferred":[
        "Bahman\u0101b\u0101d"
    ],
    "name:fas_x_variant":[
        "\u0628\u064e\u0647\u0645\u064e\u0646 \u0622\u0628\u0627\u062f",
        "\u0628\u0647\u0645\u0646\u200c\u0622\u0628\u0627\u062f"
    ],
    "name:sco_x_preferred":[
        "Bahmanabad"
    ],
    "wof:name":"Bahmanabad",
    "wof:placetype":"locality"
},
  "geometry": {"coordinates":[50.28972,32.20944],"type":"Point"}
}