{
  "type": "Feature",
  "properties": {
    "gn:admin1_code":"7",
    "gn:asciiname":"Faryabu",
    "gn:country_code":"IR",
    "gn:dem":609,
    "gn:feature_class":"P",
    "gn:feature_code":"PPL",
    "gn:name":"F\u0101ry\u0101b\u016b",
    "gn:population":0,
    "gn:timezone":"Asia/Tehran",
    "iso:country":"IR",
    "name:fas_x_preferred":[
        "\u0646\u062e\u0644 \u067e\u0627\u0631\u0648"
    ],
    "name:fas_x_variant":[
        "Nakhl P\u0101r\u016b",
        "\u0641\u0627\u0631\u06cc\u0627\u0628\u0648",
        "\u0646\u062e\u0644\u0633\u062a\u0627\u0646 \u0641\u0627\u0631\u06cc\u0627\u0628"
    ],
    "name:und_x_variant":[
        "F\u0101ry\u0101b\u016b",
        "Nakhlest\u0101n-e F\u0101ry\u0101b"
    ],
    "wof:name":"Faryabu",
    "wof:placetype":"locality"
},
  "geometry": {"coordinates":[53.6779,27.56969],"type":"Point"}
}