{
  "type": "Feature",
  "properties": {
    "gn:admin1_code":"36.0",
    "gn:asciiname":"Aq Bolagh",
    "gn:country_code":"IR",
    "gn:dem":2063,
    "gn:feature_class":"P",
    "gn:feature_code":"PPL",
    "gn:name":"\u0100q Bol\u0101gh",
    "gn:population":0,
    "gn:timezone":"Asia/Tehran",
    "iso:country":"IR",
    "name:azb_x_preferred":[
        "\u0622\u0642\u0628\u0644\u0627\u063a \u0633\u0641\u0644\u06cc"
    ],
    "name:ceb_x_preferred":[
        "\u0100qbol\u0101gh-e Sofl\u00e1"
    ],
    "name:fas_x_preferred":[
        "\u0622\u0642 \u0628\u064f\u0644\u0627\u063a\u0650 \u067e\u0627\u0626\u064a\u0646"
    ],
    "name:fas_x_variant":[
        "\u0622\u0642 \u0628\u064f\u0644\u0627\u063a",
        "\u0622\u0642\u0628\u0644\u0627\u063a \u0633\u0641\u0644\u06cc",
        "\u0100q Bol\u0101gh-e P\u0101\u2019\u012bn",
        "\u0100qbol\u0101gh-e Sofl\u00e1",
        "\u0622\u0642 \u0628\u0644\u0627\u063a",
        "\u0627\u0642\u0628\u0644\u0627\u063a \u0633\u0641\u0644\u06cc"
    ],
    "name:swe_x_preferred":[
        "\u0100qbol\u0101gh-e Sofl\u00e1"
    ],
    "name:und_x_variant":[
        "Aq Bul\u0101q",
        "\u0100q Bol\u0101gh"
    ],
    "wof:name":"Aq Bolagh",
    "wof:placetype":"locality"
},
  "geometry": {"coordinates":[48.37356,36.16545],"type":"Point"}
}