{
  "type": "Feature",
  "properties": {
    "gn:admin1_code":"4",
    "gn:asciiname":"Gharibabad",
    "gn:country_code":"IR",
    "gn:dem":1418,
    "gn:feature_class":"P",
    "gn:feature_code":"PPLF",
    "gn:name":"Ghar\u012bb\u0101b\u0101d",
    "gn:population":0,
    "gn:timezone":"Asia/Tehran",
    "iso:country":"IR",
    "name:fas_x_preferred":[
        "\u063a\u0631\u06cc\u0628 \u0622\u0628\u0627\u062f"
    ],
    "name:fas_x_variant":[
        "Ghar\u012bb\u0101b\u0101d"
    ],
    "wof:name":"Gharibabad",
    "wof:placetype":"locality"
},
  "geometry": {"coordinates":[61.24631,28.2949],"type":"Point"}
}