{
  "type": "Feature",
  "properties": {
    "gn:admin1_code":"26",
    "gn:asciiname":"Gaduk",
    "gn:country_code":"IR",
    "gn:dem":2123,
    "gn:feature_class":"P",
    "gn:feature_code":"PPL",
    "gn:name":"Gad\u016bk",
    "gn:population":0,
    "gn:timezone":"Asia/Tehran",
    "iso:country":"IR",
    "name:ara_x_preferred":[
        "\u063a\u062f\u0648\u0643"
    ],
    "name:fas_x_preferred":[
        "\u06af\u062f\u0648\u0643"
    ],
    "name:und_x_variant":[
        "Ged\u016bk",
        "Gad\u016bk",
        "Guduk",
        "Gadoit"
    ],
    "wof:name":"Gaduk",
    "wof:placetype":"locality"
},
  "geometry": {"coordinates":[52.91902,35.82688],"type":"Point"}
}