{
  "type": "Feature",
  "properties": {
    "gn:admin1_code":"16",
    "gn:asciiname":"Cheshmeh Mantash",
    "gn:country_code":"IR",
    "gn:dem":1880,
    "gn:feature_class":"P",
    "gn:feature_code":"PPL",
    "gn:name":"Cheshmeh Mantash",
    "gn:population":0,
    "gn:timezone":"Asia/Tehran",
    "iso:country":"IR",
    "name:ara_x_preferred":[
        "\u062c\u0634\u0645\u0629 \u0645\u0646\u062a\u0634"
    ],
    "name:fas_x_preferred":[
        "\u0686\u0634\u0645\u0647 \u0645\u0646\u062a\u0634"
    ],
    "name:und_x_variant":[
        "Cheshmeh M\u012bsh",
        "Chashmeh Mantash",
        "Cheshmeh Mansh",
        "Chashmeh Mantas",
        "Cheshmeh Mantash"
    ],
    "wof:name":"Cheshmeh Mantash",
    "wof:placetype":"locality"
},
  "geometry": {"coordinates":[47.48268,35.61549],"type":"Point"}
}