{
  "type": "Feature",
  "properties": {
    "gn:admin1_code":"29",
    "gn:asciiname":"Hoseynabad-e Molla Amir",
    "gn:country_code":"IR",
    "gn:dem":574,
    "gn:feature_class":"P",
    "gn:feature_code":"PPL",
    "gn:name":"\u1e28oseyn\u0101b\u0101d-e Moll\u0101 Am\u012br",
    "gn:population":0,
    "gn:timezone":"Asia/Tehran",
    "iso:country":"IR",
    "name:ara_x_preferred":[
        "\u062d\u0633\u064a\u0646\u200c\u0622\u0628\u0627\u062f \u0645\u0644\u0627\u0627\u0645\u064a\u0631"
    ],
    "name:ceb_x_preferred":[
        "\u1e28oseyn\u0101b\u0101d-e Moll\u0101 Am\u012br"
    ],
    "name:fas_x_preferred":[
        "\u062d\u0633\u064a\u0646 \u0622\u0628\u0627\u062f \u0645\u0644\u0627 \u0627\u0645\u064a\u0631"
    ],
    "name:fas_x_variant":[
        "\u1e28oseyn\u0101b\u0101d-e Moll\u0101 Am\u012br",
        "\u062d\u0633\u06cc\u0646\u200c\u0622\u0628\u0627\u062f \u0645\u0644\u0627\u0627\u0645\u06cc\u0631"
    ],
    "name:swe_x_preferred":[
        "\u1e28oseyn\u0101b\u0101d-e Moll\u0101 Am\u012br"
    ],
    "name:und_x_variant":[
        "Hosein Abad Molla Amir"
    ],
    "wof:name":"Hoseynabad-e Molla Amir",
    "wof:placetype":"locality"
},
  "geometry": {"coordinates":[59.10713000000001,28.78151],"type":"Point"}
}