{
  "type": "Feature",
  "properties": {
    "gn:admin1_code":"1",
    "gn:asciiname":"Tazeh Kand-e Janizeh",
    "gn:country_code":"IR",
    "gn:dem":1355,
    "gn:feature_class":"P",
    "gn:feature_code":"PPL",
    "gn:name":"T\u0101zeh Kand-e Jan\u012bzeh",
    "gn:population":0,
    "gn:timezone":"Asia/Tehran",
    "iso:country":"IR",
    "name:azb_x_preferred":[
        "\u062a\u0627\u0632\u0627 \u06a9\u0646\u062f\u062c\u0646\u06cc\u0632\u0647"
    ],
    "name:aze_x_preferred":[
        "T\u0259z\u0259k\u0259nd-i C\u0259niz\u0259"
    ],
    "name:ceb_x_preferred":[
        "T\u0101zeh Kand-e Jan\u012bzeh"
    ],
    "name:fas_x_preferred":[
        "\u062a\u0627\u0632\u0650\u0647 \u0643\u064e\u0646\u062f\u0650 \u062c\u064e\u0646\u064a\u0632\u0650\u0647"
    ],
    "name:fas_x_variant":[
        "\u062a\u0627\u0632\u0647 \u06a9\u0646\u062f \u062c\u0646\u06cc\u0632\u0647",
        "T\u0101zeh Kand-e Jan\u012bzeh",
        "\u062a\u0627\u0632\u0647\u200c\u06a9\u0646\u062f \u062c\u0646\u06cc\u0632\u0647"
    ],
    "name:msa_x_preferred":[
        "Tazeh Kand-e Janizeh"
    ],
    "name:swe_x_preferred":[
        "T\u0101zeh Kand-e Jan\u012bzeh"
    ],
    "wof:name":"Tazeh Kand-e Janizeh",
    "wof:placetype":"locality"
},
  "geometry": {"coordinates":[44.9703,37.6639],"type":"Point"}
}