{
  "type": "Feature",
  "properties": {
    "gn:admin1_code":"42",
    "gn:asciiname":"Jimabad",
    "gn:country_code":"IR",
    "gn:dem":1549,
    "gn:feature_class":"P",
    "gn:feature_code":"PPL",
    "gn:name":"J\u012bm\u0101b\u0101d",
    "gn:population":0,
    "gn:timezone":"Asia/Tehran",
    "iso:country":"IR",
    "name:fas_x_preferred":[
        "\u062c\u06cc\u0645 \u0622\u0628\u0627\u062f"
    ],
    "name:fas_x_variant":[
        "J\u012bm\u0101b\u0101d"
    ],
    "wof:name":"Jimabad",
    "wof:placetype":"locality"
},
  "geometry": {"coordinates":[59.96167,33.46533],"type":"Point"}
}