{
  "type": "Feature",
  "properties": {
    "gn:admin1_code":"15",
    "gn:asciiname":"Gach-e Dam Ab",
    "gn:cc2":"IR",
    "gn:country_code":"IR",
    "gn:dem":417,
    "gn:feature_class":"P",
    "gn:feature_code":"PPL",
    "gn:name":"Gach-e Dam \u0100b",
    "gn:population":0,
    "gn:timezone":"Asia/Tehran",
    "iso:country":"IR",
    "name:fas_x_preferred":[
        "Gach-e Dam \u0100b"
    ],
    "name:und_x_variant":[
        "Gach-e Dow\u0101b"
    ],
    "wof:name":"Gach-e Dam Ab",
    "wof:placetype":"locality"
},
  "geometry": {"coordinates":[49.43333,31.78333],"type":"Point"}
}