{
  "type": "Feature",
  "properties": {
    "gn:admin1_code":"23.0",
    "gn:asciiname":"Sam Sureh",
    "gn:country_code":"IR",
    "gn:dem":2066,
    "gn:feature_class":"P",
    "gn:feature_code":"PPLL",
    "gn:name":"Sam S\u016breh",
    "gn:population":0,
    "gn:timezone":"Asia/Tehran",
    "iso:country":"IR",
    "name:fas_x_preferred":[
        "Sam S\u016breh"
    ],
    "name:fas_x_variant":[
        "\u0633\u0645 \u0633\u0648\u0631\u0647"
    ],
    "name:und_x_variant":[
        "\u0633\u0645 \u0633\u0648\u0631\u0647"
    ],
    "wof:name":"Sam Sureh",
    "wof:placetype":"locality"
},
  "geometry": {"coordinates":[48.40178,33.02842],"type":"Point"}
}