{
  "type": "Feature",
  "properties": {
    "gn:admin1_code":"13",
    "gn:asciiname":"Siah Kamar",
    "gn:country_code":"IR",
    "gn:dem":1386,
    "gn:feature_class":"P",
    "gn:feature_code":"PPL",
    "gn:name":"S\u012b\u0101h Kamar",
    "gn:population":0,
    "gn:timezone":"Asia/Tehran",
    "iso:country":"IR",
    "name:fas_x_preferred":[
        "\u0633\u06cc\u0627\u0647 \u06a9\u0645\u0631"
    ],
    "name:fas_x_variant":[
        "S\u012by\u0101h Kamar",
        "S\u012b\u0101h Kamar"
    ],
    "wof:name":"Siah Kamar",
    "wof:placetype":"locality"
},
  "geometry": {"coordinates":[46.9931,34.3486],"type":"Point"}
}