{
  "type": "Feature",
  "properties": {
    "gn:admin1_code":"28",
    "gn:asciiname":"Jumin",
    "gn:country_code":"IR",
    "gn:dem":937,
    "gn:feature_class":"P",
    "gn:feature_code":"PPL",
    "gn:name":"J\u016bm\u012bn",
    "gn:population":0,
    "gn:timezone":"Asia/Tehran",
    "iso:country":"IR",
    "name:fas_x_preferred":[
        "\u062c\u0648\u0645\u064a\u0646"
    ],
    "name:fas_x_variant":[
        "\u062c\u064f\u0645\u064a\u0646",
        "J\u016bm\u012bn"
    ],
    "name:und_x_variant":[
        "Jom\u012bn"
    ],
    "wof:name":"Jumin",
    "wof:placetype":"locality"
},
  "geometry": {"coordinates":[55.08333,33.63333],"type":"Point"}
}