{
  "type": "Feature",
  "properties": {
    "gn:admin1_code":"4.0",
    "gn:asciiname":"Shisheh Posht",
    "gn:country_code":"IR",
    "gn:dem":990,
    "gn:feature_class":"P",
    "gn:feature_code":"PPL",
    "gn:name":"Sh\u012bsheh Posht",
    "gn:population":0,
    "gn:timezone":"Asia/Tehran",
    "iso:country":"IR",
    "name:fas_x_preferred":[
        "\u0634\u064a\u0634\u0647 \u067e\u0634\u062a"
    ],
    "name:fas_x_variant":[
        "Sh\u012bsheh Posht",
        "Sh\u012bsheh Pusht"
    ],
    "name:und_x_variant":[
        "Sh\u012bsheh Pusht"
    ],
    "wof:name":"Shisheh Posht",
    "wof:placetype":"locality"
},
  "geometry": {"coordinates":[60.38481,26.81876],"type":"Point"}
}