{
  "type": "Feature",
  "properties": {
    "gn:admin1_code":"15",
    "gn:asciiname":"Leneti",
    "gn:country_code":"IR",
    "gn:dem":811,
    "gn:feature_class":"P",
    "gn:feature_code":"PPL",
    "gn:name":"Lenet\u012b",
    "gn:population":0,
    "gn:timezone":"Asia/Tehran",
    "iso:country":"IR",
    "name:fas_x_preferred":[
        "Lenet\u012b"
    ],
    "wof:name":"Leneti",
    "wof:placetype":"locality"
},
  "geometry": {"coordinates":[49.71667,31.96667],"type":"Point"}
}