{
  "type": "Feature",
  "properties": {
    "gn:admin1_code":"5",
    "gn:asciiname":"Kushk-e Zafari",
    "gn:country_code":"IR",
    "gn:dem":1073,
    "gn:feature_class":"P",
    "gn:feature_code":"PPL",
    "gn:name":"K\u016bshk-e Z\u0327afar\u012b",
    "gn:population":0,
    "gn:timezone":"Asia/Tehran",
    "iso:country":"IR",
    "name:ara_x_preferred":[
        "\u06a9\u0648\u0634\u0643 \u0638\u0641\u0631\u064a"
    ],
    "name:fas_x_preferred":[
        "K\u016bshk-e Z\u0327afar\u012b"
    ],
    "name:fas_x_variant":[
        "\u06a9\u0648\u0634\u0643 \u0638\u0641\u0631\u06cc",
        "\u06a9\u0648\u0634\u06a9 \u0638\u0641\u0631\u06cc"
    ],
    "name:und_x_variant":[
        "\u06a9\u0648\u0634\u0643 \u0638\u0641\u0631\u06cc"
    ],
    "wof:name":"Kushk-e Zafari",
    "wof:placetype":"locality"
},
  "geometry": {"coordinates":[51.12659,30.4298],"type":"Point"}
}