{
  "type": "Feature",
  "properties": {
    "gn:admin1_code":"40",
    "gn:asciiname":"Gerd Faramarz Shahediyeh",
    "gn:country_code":"IR",
    "gn:dem":1195,
    "gn:feature_class":"P",
    "gn:feature_code":"PPL",
    "gn:name":"Gerd Far\u0101marz Sh\u0101hed\u012byeh",
    "gn:population":0,
    "gn:timezone":"Asia/Tehran",
    "iso:country":"IR",
    "name:fas_x_preferred":[
        "\u06af\u064f\u0631\u062f \u0641\u064e\u0631\u0627\u0645\u064e\u0631\u0632"
    ],
    "name:fas_x_variant":[
        "\u06af\u0650\u0631\u062f \u0641\u064e\u0631\u0627\u0645\u064e\u0631\u0632",
        "\u06af\u064f\u0631\u062f\u0650 \u0641\u064e\u0631\u0627\u0645\u064e\u0631\u0632",
        "Gord Far\u0101marz",
        "Gerd Far\u0101marz Sh\u0101hed\u012byeh",
        "\u06af\u0631\u062f \u0641\u0631\u0627\u0645\u0631\u0632 \u0634\u0627\u0647\u062f\u064a\u0647",
        "\u0634\u0627\u0647\u062f\u064a\u0647"
    ],
    "name:und_x_variant":[
        "Gerd Far\u0101marz",
        "Gord-e Far\u0101marz",
        "Gird-i-Far\u0101marz",
        "Sh\u0101hed\u012byeh"
    ],
    "wof:name":"Gerd Faramarz Shahediyeh",
    "wof:placetype":"locality"
},
  "geometry": {"coordinates":[54.26766,31.94169],"type":"Point"}
}