{
  "type": "Feature",
  "properties": {
    "gn:admin1_code":"32",
    "gn:asciiname":"Nowdeh",
    "gn:country_code":"IR",
    "gn:dem":1582,
    "gn:feature_class":"P",
    "gn:feature_code":"PPL",
    "gn:name":"Nowdeh",
    "gn:population":0,
    "gn:timezone":"Asia/Tehran",
    "iso:country":"IR",
    "name:fas_x_preferred":[
        "\u0646\u0648\u062f\u0647"
    ],
    "name:und_x_variant":[
        "Nardeh",
        "Now Deh",
        "Nudi",
        "Nudy",
        "Nowd\u012b",
        "Nowdeh"
    ],
    "wof:name":"Nowdeh",
    "wof:placetype":"locality"
},
  "geometry": {"coordinates":[48.35105,37.80185],"type":"Point"}
}