{
  "type": "Feature",
  "properties": {
    "gn:admin1_code":"26.0",
    "gn:asciiname":"Sar Gol",
    "gn:country_code":"IR",
    "gn:dem":968,
    "gn:feature_class":"P",
    "gn:feature_code":"PPL",
    "gn:name":"Sar Gol",
    "gn:population":0,
    "gn:timezone":"Asia/Tehran",
    "iso:country":"IR",
    "name:fas_x_preferred":[
        "\u0633\u0631 \u06af\u0644"
    ],
    "name:fas_x_variant":[
        "\u0633\u0631\u06af\u0644"
    ],
    "wof:name":"Sar Gol",
    "wof:placetype":"locality"
},
  "geometry": {"coordinates":[51.668,35.38],"type":"Point"}
}