{
  "type": "Feature",
  "properties": {
    "gn:admin1_code":"15",
    "gn:asciiname":"Borj-e Musavi",
    "gn:country_code":"IR",
    "gn:dem":435,
    "gn:feature_class":"P",
    "gn:feature_code":"PPL",
    "gn:name":"Borj-e M\u016bsav\u012b",
    "gn:population":0,
    "gn:timezone":"Asia/Tehran",
    "iso:country":"IR",
    "name:azb_x_preferred":[
        "\u0628\u0631\u062c \u0645\u0648\u0633\u0648\u06cc(\u0628\u0647\u0628\u0647\u0627\u0646)"
    ],
    "name:fas_x_preferred":[
        "\u0628\u0631\u062c \u0645\u0648\u0633\u0648\u06cc"
    ],
    "name:fas_x_variant":[
        "Borj-e M\u016bsav\u012b"
    ],
    "wof:name":"Borj-e Musavi",
    "wof:placetype":"locality"
},
  "geometry": {"coordinates":[50.2131,30.7969],"type":"Point"}
}