{
  "type": "Feature",
  "properties": {
    "gn:admin1_code":"35",
    "gn:asciiname":"Dozdak",
    "gn:country_code":"IR",
    "gn:dem":317,
    "gn:feature_class":"P",
    "gn:feature_code":"PPLF",
    "gn:name":"Dozdak",
    "gn:population":0,
    "gn:timezone":"Asia/Tehran",
    "iso:country":"IR",
    "name:fas_x_preferred":[
        "\u062f\u0632\u062f\u0643"
    ],
    "name:und_x_variant":[
        "\u062f\u0632\u062f\u0643",
        "Dozdak"
    ],
    "wof:name":"Dozdak",
    "wof:placetype":"locality"
},
  "geometry": {"coordinates":[53.27429,36.4421],"type":"Point"}
}