{
  "type": "Feature",
  "properties": {
    "gn:admin1_code":"25",
    "gn:asciiname":"Qatul",
    "gn:country_code":"IR",
    "gn:dem":861,
    "gn:feature_class":"P",
    "gn:feature_code":"PPL",
    "gn:name":"Q\u0101\u0163\u016bl",
    "gn:population":0,
    "gn:timezone":"Asia/Tehran",
    "iso:country":"IR",
    "name:fas_x_preferred":[
        "\u0642\u0627\u0637\u0648\u0644"
    ],
    "name:fas_x_variant":[
        "\u0642\u0627\u0637\u0648\u0646",
        "Q\u0101\u0163\u016bl"
    ],
    "name:und_x_variant":[
        "Q\u0101\u0163\u016bn"
    ],
    "wof:name":"Qatul",
    "wof:placetype":"locality"
},
  "geometry": {"coordinates":[52.38761,35.19913],"type":"Point"}
}