{
  "type": "Feature",
  "properties": {
    "gn:admin1_code":"28",
    "gn:asciiname":"Uzon-e Akhar",
    "gn:cc2":"IR",
    "gn:country_code":"IR",
    "gn:dem":2009,
    "gn:feature_class":"P",
    "gn:feature_code":"PPL",
    "gn:name":"\u016azon-e \u0100kh\u0101r",
    "gn:population":0,
    "gn:timezone":"Asia/Tehran",
    "iso:country":"IR",
    "name:fas_x_preferred":[
        "\u016azon-e \u0100kh\u0101r"
    ],
    "name:und_x_variant":[
        "Oz\u016bn \u0100kh\u0101r",
        "\u016az\u016bn \u0100kh\u0101r"
    ],
    "wof:name":"Uzon-e Akhar",
    "wof:placetype":"locality"
},
  "geometry": {"coordinates":[50.79778,32.71639],"type":"Point"}
}