{
  "type": "Feature",
  "properties": {
    "gn:admin1_code":"42",
    "gn:asciiname":"Cheshmeh `Alivan",
    "gn:country_code":"IR",
    "gn:dem":1037,
    "gn:feature_class":"P",
    "gn:feature_code":"PPL",
    "gn:name":"Cheshmeh \u2018Al\u012bv\u0101n",
    "gn:population":0,
    "gn:timezone":"Asia/Tehran",
    "iso:country":"IR",
    "name:fas_x_preferred":[
        "\u0686\u0634\u0645\u0647 \u0639\u0644\u06cc\u0648\u0627\u0646"
    ],
    "name:fas_x_variant":[
        "Cheshmeh-e \u2018Al\u012bv\u0101n",
        "Cheshmeh \u2018Al\u012bv\u0101n"
    ],
    "wof:name":"Cheshmeh `Alivan",
    "wof:placetype":"locality"
},
  "geometry": {"coordinates":[59.46978000000001,36.54034],"type":"Point"}
}