{
  "type": "Feature",
  "properties": {
    "gn:admin1_code":"43",
    "gn:asciiname":"Ughaz Tazeh",
    "gn:country_code":"IR",
    "gn:dem":1603,
    "gn:feature_class":"P",
    "gn:feature_code":"PPL",
    "gn:name":"\u016agh\u0101z T\u0101zeh",
    "gn:population":0,
    "gn:timezone":"Asia/Tehran",
    "iso:country":"IR",
    "name:fas_x_preferred":[
        "\u016agh\u0101z T\u0101zeh"
    ],
    "name:fas_x_variant":[
        "\u0627\u0648\u063a\u0627\u0632 \u062a\u0627\u0632\u0647"
    ],
    "name:und_x_variant":[
        "Owgh\u0101z-e T\u0101zeh",
        "Taza Ogh\u0101z",
        "Owgh\u0101z T\u0101zeh",
        "T\u0101zeh Owgh\u0101z"
    ],
    "wof:name":"Ughaz Tazeh",
    "wof:placetype":"locality"
},
  "geometry": {"coordinates":[58.19262,37.52711],"type":"Point"}
}