{
  "type": "Feature",
  "properties": {
    "gn:admin1_code":"4.0",
    "gn:asciiname":"Chad-e Bala",
    "gn:country_code":"IR",
    "gn:dem":1374,
    "gn:feature_class":"P",
    "gn:feature_code":"PPL",
    "gn:name":"Ch\u0101d-e B\u0101l\u0101",
    "gn:population":0,
    "gn:timezone":"Asia/Tehran",
    "iso:country":"IR",
    "name:fas_x_preferred":[
        "\u0686\u0627\u062f \u0628\u0627\u0644\u0627"
    ],
    "name:fas_x_variant":[
        "Ch\u0101d-e B\u0101l\u0101",
        "Chad-e Borz\u012b",
        "\u0686\u062f \u0628\u0627\u0644\u0627"
    ],
    "name:und_x_variant":[
        "Chad-e Borz\u012b",
        "Chad-e B\u0101l\u0101"
    ],
    "wof:name":"Chad-e Bala",
    "wof:placetype":"locality"
},
  "geometry": {"coordinates":[61.4243,27.30157],"type":"Point"}
}