{
  "type": "Feature",
  "properties": {
    "gn:admin1_code":"7.0",
    "gn:asciiname":"Kuhak-e Yek",
    "gn:country_code":"IR",
    "gn:dem":1584,
    "gn:feature_class":"P",
    "gn:feature_code":"PPL",
    "gn:name":"K\u016bhak-e Yek",
    "gn:population":0,
    "gn:timezone":"Asia/Tehran",
    "iso:country":"IR",
    "name:fas_x_preferred":[
        "\u06a9\u0648\u0647\u06a9 \u064a\u06a9"
    ],
    "name:fas_x_variant":[
        "K\u016bhak-e Yek"
    ],
    "name:und_x_variant":[
        "K\u016bhak-e Yek"
    ],
    "wof:name":"Kuhak-e Yek",
    "wof:placetype":"locality"
},
  "geometry": {"coordinates":[52.8991,29.6996],"type":"Point"}
}