{
  "type": "Feature",
  "properties": {
    "gn:admin1_code":"36",
    "gn:asciiname":"Vakil Qeshlaq",
    "gn:country_code":"IR",
    "gn:dem":1435,
    "gn:feature_class":"P",
    "gn:feature_code":"PPL",
    "gn:name":"Vak\u012bl Qeshl\u0101q",
    "gn:population":0,
    "gn:timezone":"Asia/Tehran",
    "iso:country":"IR",
    "name:azb_x_preferred":[
        "\u0648\u06a9\u06cc\u0644 \u0642\u0634\u0644\u0627\u0642"
    ],
    "name:fas_x_preferred":[
        "\u0648\u06a9\u06cc\u0644 \u0642\u0634\u0644\u0627\u0642"
    ],
    "name:fas_x_variant":[
        "\u0648\u064e\u0643\u064a\u0644 \u0642\u0650\u0634\u0644\u0627\u0642\u06cc",
        "\u062a\u0627\u0632\u0650\u0647 \u0642\u0650\u0634\u0644\u0627\u0642",
        "Vak\u012bl Qeshl\u0101q"
    ],
    "name:und_x_variant":[
        "Qishlaqs",
        "T\u0101zeh Qeshl\u0101q",
        "Vakil-Kishlaki",
        "Vak\u012bl Qeshl\u0101q\u012b"
    ],
    "wof:name":"Vakil Qeshlaq",
    "wof:placetype":"locality"
},
  "geometry": {"coordinates":[48.0463,36.14518],"type":"Point"}
}