{
  "type": "Feature",
  "properties": {
    "gn:admin1_code":"10",
    "gn:asciiname":"Sharan",
    "gn:country_code":"IR",
    "gn:dem":1817,
    "gn:feature_class":"P",
    "gn:feature_code":"PPL",
    "gn:name":"Sh\u0101r\u0101n",
    "gn:population":0,
    "gn:timezone":"Asia/Tehran",
    "iso:country":"IR",
    "name:ceb_x_preferred":[
        "Sharan"
    ],
    "name:dan_x_preferred":[
        "Sharan"
    ],
    "name:deu_x_preferred":[
        "Sharan"
    ],
    "name:fas_x_preferred":[
        "\u0634\u0627\u0631\u0627\u0646"
    ],
    "name:fas_x_variant":[
        "\u0634\u0627\u0631\u0627\u0646 \u0632\u0631\u062f\u0644\u0627\u0646",
        "Sh\u0101r\u0101n",
        "Sh\u0101r\u0101n Zardal\u0101n"
    ],
    "name:fra_x_preferred":[
        "Sharan"
    ],
    "name:swe_x_preferred":[
        "Sharan"
    ],
    "wof:name":"Sharan",
    "wof:placetype":"locality"
},
  "geometry": {"coordinates":[47.44818,33.90109],"type":"Point"}
}