{
  "type": "Feature",
  "properties": {
    "gn:admin1_code":"23.0",
    "gn:asciiname":"Beg Reza",
    "gn:country_code":"IR",
    "gn:dem":1878,
    "gn:feature_class":"P",
    "gn:feature_code":"PPL",
    "gn:name":"Beg Re\u1e95\u0101",
    "gn:population":0,
    "gn:timezone":"Asia/Tehran",
    "iso:country":"IR",
    "name:fas_x_preferred":[
        "\u0639\u0644\u06cc \u0622\u0628\u0627\u062f \u0628\u064a\u06af \u0631\u0636\u0627"
    ],
    "name:fas_x_variant":[
        "\u0628\u064a\u06af \u0631\u0636\u0627",
        "\u0628\u06af \u0631\u0632\u0627",
        "\u0639\u064e\u0644\u064a\u0627\u0628\u0627\u062f\u0650 \u0628\u0650\u064a\u06af \u0631\u0650\u0632\u0627",
        "\u2018Al\u012b\u0101b\u0101d-e Beyg Re\u1e95\u0101",
        "Beyg Re\u1e95\u0101",
        "\u0628\u06af \u0631\u0636\u0627"
    ],
    "name:und_x_variant":[
        "Bag Rez\u0101",
        "\u2018Al\u012b\u0101b\u0101d-e Beyg Rez\u0101",
        "Beg Re\u1e95\u0101"
    ],
    "wof:name":"Beg Reza",
    "wof:placetype":"locality"
},
  "geometry": {"coordinates":[48.8329,33.4683],"type":"Point"}
}