{
  "type": "Feature",
  "properties": {
    "gn:admin1_code":"13",
    "gn:asciiname":"Beleh Kabud",
    "gn:country_code":"IR",
    "gn:dem":1305,
    "gn:feature_class":"P",
    "gn:feature_code":"PPL",
    "gn:name":"Beleh Kab\u016bd",
    "gn:population":0,
    "gn:timezone":"Asia/Tehran",
    "iso:country":"IR",
    "name:fas_x_preferred":[
        "\u0628\u0644\u0647 \u06a9\u0628\u0648\u062f"
    ],
    "name:fas_x_variant":[
        "Beleh Kab\u016bd",
        "\u0628\u0644\u0647\u200c\u06a9\u0628\u0648\u062f"
    ],
    "name:fra_x_preferred":[
        "Beleh Kabud"
    ],
    "name:und_x_variant":[
        "Balla Kab\u016bd",
        "Bol Kab\u016bd",
        "Baleh Kabood",
        "Baleh Kab\u016bd",
        "B\u0101l\u0101 Kab\u016bd"
    ],
    "wof:name":"Beleh Kabud",
    "wof:placetype":"locality"
},
  "geometry": {"coordinates":[46.9651,34.4596],"type":"Point"}
}