{
  "type": "Feature",
  "properties": {
    "gn:admin1_code":"3.0",
    "gn:asciiname":"Darreh Garm",
    "gn:country_code":"IR",
    "gn:dem":1162,
    "gn:feature_class":"P",
    "gn:feature_code":"PPL",
    "gn:name":"Darreh Garm",
    "gn:population":0,
    "gn:timezone":"Asia/Tehran",
    "iso:country":"IR",
    "name:fas_x_preferred":[
        "\u062f\u0631\u0647 \u06af\u0631\u0645"
    ],
    "wof:name":"Darreh Garm",
    "wof:placetype":"locality"
},
  "geometry": {"coordinates":[50.52977,31.6306],"type":"Point"}
}