{
  "type": "Feature",
  "properties": {
    "gn:admin1_code":"13",
    "gn:asciiname":"Kochkineh",
    "gn:country_code":"IR",
    "gn:dem":2041,
    "gn:feature_class":"P",
    "gn:feature_code":"PPL",
    "gn:name":"Kochk\u012bneh",
    "gn:population":0,
    "gn:timezone":"Asia/Tehran",
    "iso:country":"IR",
    "name:ceb_x_preferred":[
        "K\u016bchk\u012bneh"
    ],
    "name:fas_x_preferred":[
        "\u06a9\u0648\u0686\u06a9\u06cc\u0646\u0647"
    ],
    "name:fas_x_variant":[
        "K\u016bchk\u012bneh",
        "\u06a9\u0686\u06a9\u06cc\u0646\u0647"
    ],
    "name:swe_x_preferred":[
        "K\u016bchk\u012bneh"
    ],
    "name:und_x_variant":[
        "K\u016bshk\u012bneh",
        "K\u016bchak\u012bneh",
        "K\u016bsh Ganeh",
        "Kochk\u012bneh"
    ],
    "wof:name":"Kochkineh",
    "wof:placetype":"locality"
},
  "geometry": {"coordinates":[47.71247,34.80243],"type":"Point"}
}