{
  "type": "Feature",
  "properties": {
    "gn:admin1_code":"4.0",
    "gn:asciiname":"Holonchekan",
    "gn:country_code":"IR",
    "gn:dem":529,
    "gn:feature_class":"P",
    "gn:feature_code":"PPL",
    "gn:name":"Holonchek\u0101n",
    "gn:population":0,
    "gn:timezone":"Asia/Tehran",
    "iso:country":"IR",
    "name:fas_x_preferred":[
        "Holonchek\u0101n"
    ],
    "name:fas_x_variant":[
        "\u0647\u0644\u0646\u0686\u06a9\u0627\u0646"
    ],
    "name:und_x_variant":[
        "\u2019al\u016bb Chek\u0101n",
        "Hel\u0101n Chek\u0101n",
        "Hol\u0101n Chok\u0101n"
    ],
    "wof:name":"Holonchekan",
    "wof:placetype":"locality"
},
  "geometry": {"coordinates":[60.75859000000001,26.25651],"type":"Point"}
}