{
  "type": "Feature",
  "properties": {
    "gn:admin1_code":"7.0",
    "gn:asciiname":"Gol Qur",
    "gn:country_code":"IR",
    "gn:dem":1900,
    "gn:feature_class":"P",
    "gn:feature_code":"PPL",
    "gn:name":"Gol Q\u016br",
    "gn:population":0,
    "gn:timezone":"Asia/Tehran",
    "iso:country":"IR",
    "name:fas_x_preferred":[
        "Kalah Gh\u016br"
    ],
    "name:fas_x_variant":[
        "\u06a9\u0644\u0647 \u063a\u0648\u0631",
        "\u06af\u0644 \u0642\u0648\u0631",
        "\u06a9\u0644 \u063a\u0648\u0631",
        "\u06a9\u0644 \u0642\u0648\u0631"
    ],
    "name:und_x_variant":[
        "Gol Q\u016br",
        "Kol Gh\u016br",
        "Kol Q\u016br"
    ],
    "wof:name":"Gol Qur",
    "wof:placetype":"locality"
},
  "geometry": {"coordinates":[51.45125,30.45679],"type":"Point"}
}