{
  "type": "Feature",
  "properties": {
    "gn:admin1_code":"23",
    "gn:asciiname":"Mehr`ali Khani",
    "gn:country_code":"IR",
    "gn:dem":1632,
    "gn:feature_class":"P",
    "gn:feature_code":"PPL",
    "gn:name":"Mehr\u2018al\u012b Kh\u0101n\u012b",
    "gn:population":0,
    "gn:timezone":"Asia/Tehran",
    "iso:country":"IR",
    "name:fas_x_preferred":[
        "\u0645\u064a\u0631 \u0639\u064e\u0644\u064a\u062e\u0627\u0646\u06cc"
    ],
    "name:fas_x_variant":[
        "\u0645\u0650\u0647\u0631 \u0639\u064e\u0644\u064a\u062e\u0627\u0646\u06cc",
        "\u067e\u06cc\u0631\u0639\u0644\u06cc \u062e\u0627\u0646\u06cc",
        "M\u012br \u2018Al\u012bkh\u0101n\u012b",
        "\u0645\u0647\u0631\u0639\u0644\u06cc \u062e\u0627\u0646\u06cc"
    ],
    "name:und_x_variant":[
        "Mehr \u2018Al\u012bkh\u0101n\u012b",
        "P\u012br\u2018al\u012b Kh\u0101n\u012b",
        "Mehr\u2018al\u012b Kh\u0101n\u012b"
    ],
    "wof:name":"Mehr`ali Khani",
    "wof:placetype":"locality"
},
  "geometry": {"coordinates":[48.4176,33.5804],"type":"Point"}
}