{
  "type": "Feature",
  "properties": {
    "gn:admin1_code":"1",
    "gn:asciiname":"`Ali Bolaghi",
    "gn:country_code":"IR",
    "gn:dem":1684,
    "gn:feature_class":"P",
    "gn:feature_code":"PPL",
    "gn:name":"\u2018Al\u012b Bol\u0101gh\u012b",
    "gn:population":0,
    "gn:timezone":"Asia/Tehran",
    "iso:country":"IR",
    "name:fas_x_preferred":[
        "\u0639\u0644\u06cc \u0628\u0644\u0627\u063a\u06cc"
    ],
    "name:fas_x_variant":[
        "\u2018Al\u012b Bol\u0101gh\u012b"
    ],
    "wof:name":"`Ali Bolaghi",
    "wof:placetype":"locality"
},
  "geometry": {"coordinates":[46.4675,37.0786],"type":"Point"}
}