{
  "type": "Feature",
  "properties": {
    "gn:admin1_code":"36",
    "gn:asciiname":"Cheragh Mazra`eh",
    "gn:country_code":"IR",
    "gn:dem":2020,
    "gn:feature_class":"P",
    "gn:feature_code":"PPL",
    "gn:name":"Cher\u0101gh Mazra\u2018eh",
    "gn:population":0,
    "gn:timezone":"Asia/Tehran",
    "iso:country":"IR",
    "name:azb_x_preferred":[
        "\u0686\u0631\u0627\u063a \u0645\u0632\u0631\u0639\u0647"
    ],
    "name:fas_x_preferred":[
        "\u0686\u0631\u0627\u063a \u0645\u0632\u0631\u0639\u0647"
    ],
    "name:fas_x_variant":[
        "Cher\u0101gh Mazra\u2018eh"
    ],
    "name:und_x_variant":[
        "Chir\u0101gh Mazreh"
    ],
    "wof:name":"Cheragh Mazra`eh",
    "wof:placetype":"locality"
},
  "geometry": {"coordinates":[48.3399,36.19828],"type":"Point"}
}