{
  "type": "Feature",
  "properties": {
    "gn:admin1_code":"23",
    "gn:asciiname":"Kalateh-ye Absardeh",
    "gn:country_code":"IR",
    "gn:dem":1871,
    "gn:feature_class":"P",
    "gn:feature_code":"PPL",
    "gn:name":"Kal\u0101teh-ye \u0100bsardeh",
    "gn:population":0,
    "gn:timezone":"Asia/Tehran",
    "iso:country":"IR",
    "name:fas_x_preferred":[
        "Kal\u0101teh"
    ],
    "name:fas_x_variant":[
        "\u06a9\u0644\u0627\u062a\u0647 \u0622\u0628\u0633\u0631\u062f\u0647",
        "\u0642\u0644\u0639\u0647 \u0622\u0628\u0633\u0631\u062f\u0647"
    ],
    "name:und_x_variant":[
        "Kal\u0101teh-ye \u0100bsardeh",
        "Qal\u2018eh-ye \u0100bsardeh"
    ],
    "wof:name":"Kalateh-ye Absardeh",
    "wof:placetype":"locality"
},
  "geometry": {"coordinates":[48.60936,33.79223],"type":"Point"}
}