{
  "type": "Feature",
  "properties": {
    "gn:admin1_code":"8",
    "gn:asciiname":"Ardeh Jan",
    "gn:country_code":"IR",
    "gn:dem":15,
    "gn:feature_class":"P",
    "gn:feature_code":"PPL",
    "gn:name":"Ardeh J\u0101n",
    "gn:population":0,
    "gn:timezone":"Asia/Tehran",
    "iso:country":"IR",
    "name:fas_x_preferred":[
        "\u0627\u0631\u062f\u0647 \u062c\u0627\u0646"
    ],
    "name:fas_x_variant":[
        "Ardeh J\u0101n"
    ],
    "wof:name":"Ardeh Jan",
    "wof:placetype":"locality"
},
  "geometry": {"coordinates":[49.1066,37.5604],"type":"Point"}
}