{
  "type": "Feature",
  "properties": {
    "gn:admin1_code":"29",
    "gn:asciiname":"Chamanzar",
    "gn:country_code":"IR",
    "gn:dem":1701,
    "gn:feature_class":"P",
    "gn:feature_code":"PPL",
    "gn:name":"Chamanz\u0101r",
    "gn:population":0,
    "gn:timezone":"Asia/Tehran",
    "iso:country":"IR",
    "name:fas_x_preferred":[
        "\u0686\u0645\u0646\u0632\u0627\u0631"
    ],
    "name:fas_x_variant":[
        "Chamanz\u0101r"
    ],
    "wof:name":"Chamanzar",
    "wof:placetype":"locality"
},
  "geometry": {"coordinates":[57.59822,30.16196],"type":"Point"}
}