{
  "type": "Feature",
  "properties": {
    "gn:admin1_code":"7.0",
    "gn:asciiname":"Hamdamabad",
    "gn:country_code":"IR",
    "gn:dem":1690,
    "gn:feature_class":"P",
    "gn:feature_code":"PPL",
    "gn:name":"Hamdam\u0101b\u0101d",
    "gn:population":0,
    "gn:timezone":"Asia/Tehran",
    "iso:country":"IR",
    "name:fas_x_preferred":[
        "\u0647\u0645\u062f\u0645 \u0622\u0628\u0627\u062f"
    ],
    "name:fas_x_variant":[
        "Hamdam\u0101b\u0101d",
        "\u0647\u0645\u062f\u0645\u200c\u0622\u0628\u0627\u062f"
    ],
    "name:msa_x_preferred":[
        "Hamdamabad"
    ],
    "wof:name":"Hamdamabad",
    "wof:placetype":"locality"
},
  "geometry": {"coordinates":[52.4967,29.2851],"type":"Point"}
}