{
  "type": "Feature",
  "properties": {
    "gn:admin1_code":"3",
    "gn:asciiname":"Gujan",
    "gn:country_code":"IR",
    "gn:dem":2048,
    "gn:feature_class":"P",
    "gn:feature_code":"PPL",
    "gn:name":"G\u016bj\u0101n",
    "gn:population":0,
    "gn:timezone":"Asia/Tehran",
    "iso:country":"IR",
    "name:fas_x_preferred":[
        "\u0643\u0648\u062c\u0627\u0646"
    ],
    "name:fas_x_variant":[
        "G\u016bj\u0101n",
        "\u06af\u0648\u062c\u0627\u0646",
        "\u06af\u0648\u06af\u0648\u0646"
    ],
    "name:und_x_variant":[
        "K\u016bj\u0101n",
        "G\u016bg\u016bn",
        "Guj\u016bn",
        "\u06af\u0648\u062c\u0627\u0646",
        "\u06af\u0648\u06af\u0648\u0646"
    ],
    "wof:name":"Gujan",
    "wof:placetype":"locality"
},
  "geometry": {"coordinates":[50.54189,32.24563],"type":"Point"}
}