{
  "type": "Feature",
  "properties": {
    "gn:admin1_code":"26.0",
    "gn:asciiname":"Hesarak-e Ghafari",
    "gn:country_code":"IR",
    "gn:dem":1161,
    "gn:feature_class":"P",
    "gn:feature_code":"PPL",
    "gn:name":"\u1e28e\u015f\u0101rak-e Ghaf\u0101r\u012b",
    "gn:population":0,
    "gn:timezone":"Asia/Tehran",
    "iso:country":"IR",
    "name:fas_x_preferred":[
        "\u062d\u0635\u0627\u0631 \u0642\u0648\u0634\u0686\u06cc"
    ],
    "name:fas_x_variant":[
        "\u1e28e\u015f\u0101r-e Q\u016bshch\u012b",
        "\u062d\u0635\u0627\u0631\u06a9 \u063a\u0641\u0627\u0631\u06cc"
    ],
    "name:und_x_variant":[
        "\u1e28e\u015f\u0101rak-e Ghaf\u0101r\u012b"
    ],
    "wof:name":"Hesarak-e Ghafari",
    "wof:placetype":"locality"
},
  "geometry": {"coordinates":[50.95603,35.66348],"type":"Point"}
}