{
  "type": "Feature",
  "properties": {
    "gn:admin1_code":"28",
    "gn:asciiname":"Humeh",
    "gn:country_code":"IR",
    "gn:dem":2533,
    "gn:feature_class":"P",
    "gn:feature_code":"PPL",
    "gn:name":"H\u016bmeh",
    "gn:population":0,
    "gn:timezone":"Asia/Tehran",
    "iso:country":"IR",
    "name:ara_x_preferred":[
        "\u0647\u0645\u0647"
    ],
    "name:fas_x_preferred":[
        "\u1e28\u016bmeh"
    ],
    "name:fas_x_variant":[
        "\u062d\u0648\u0645\u0647",
        "\u0647\u0648\u0645\u0647",
        "\u0647\u0645\u0647"
    ],
    "name:glk_x_preferred":[
        "Wikipedia:\u0641\u0627\u064a\u0644 \u062c\u0624\u0631\u0623\u06a9\u0634\u0626\u0646"
    ],
    "name:und_x_variant":[
        "H\u016bmeh",
        "Homeh"
    ],
    "wof:name":"Humeh",
    "wof:placetype":"locality"
},
  "geometry": {"coordinates":[49.87464,32.82623],"type":"Point"}
}