{
  "type": "Feature",
  "properties": {
    "gn:admin1_code":"5.0",
    "gn:asciiname":"Ab Bali",
    "gn:country_code":"IR",
    "gn:dem":2254,
    "gn:feature_class":"P",
    "gn:feature_code":"PPL",
    "gn:name":"\u0100b Bal\u012b",
    "gn:population":0,
    "gn:timezone":"Asia/Tehran",
    "iso:country":"IR",
    "name:fas_x_preferred":[
        "\u0100b Bal\u012b"
    ],
    "name:fas_x_variant":[
        "\u0622\u0628 \u0628\u0644\u06cc"
    ],
    "name:und_x_variant":[
        "\u0622\u0628 \u0628\u0644\u06cc"
    ],
    "wof:name":"Ab Bali",
    "wof:placetype":"locality"
},
  "geometry": {"coordinates":[50.51679,31.32015],"type":"Point"}
}