{
  "type": "Feature",
  "properties": {
    "gn:admin1_code":"7",
    "gn:asciiname":"Murjaki",
    "gn:country_code":"IR",
    "gn:dem":1171,
    "gn:feature_class":"P",
    "gn:feature_code":"PPL",
    "gn:name":"M\u016brjak\u012b",
    "gn:population":0,
    "gn:timezone":"Asia/Tehran",
    "iso:country":"IR",
    "name:fas_x_preferred":[
        "\u0645\u0648\u0631\u062c\u06a9\u06cc"
    ],
    "name:fas_x_variant":[
        "M\u016brjak\u012b"
    ],
    "name:und_x_variant":[
        "Moordak"
    ],
    "wof:name":"Murjaki",
    "wof:placetype":"locality"
},
  "geometry": {"coordinates":[53.1627,28.8492],"type":"Point"}
}