{
  "type": "Feature",
  "properties": {
    "gn:admin1_code":"15.0",
    "gn:asciiname":"Bazar Tembi",
    "gn:country_code":"IR",
    "gn:dem":197,
    "gn:feature_class":"P",
    "gn:feature_code":"PPL",
    "gn:name":"B\u0101z\u0101r Temb\u012b",
    "gn:population":0,
    "gn:timezone":"Asia/Tehran",
    "iso:country":"IR",
    "name:fas_x_preferred":[
        "\u062a\u0645\u0628\u06cc \u0628\u0627\u0632\u0627\u0631"
    ],
    "name:fas_x_variant":[
        "Temb\u012b B\u0101z\u0101r",
        "\u0628\u0627\u0632\u0627\u0631 \u062a\u0645\u0628\u06cc"
    ],
    "name:und_x_variant":[
        "B\u0101z\u0101r Temb\u012b"
    ],
    "wof:name":"Bazar Tembi",
    "wof:placetype":"locality"
},
  "geometry": {"coordinates":[49.27263,31.9267],"type":"Point"}
}