{
  "type": "Feature",
  "properties": {
    "gn:admin1_code":"5",
    "gn:asciiname":"Boneh-ye Kalu Morteza",
    "gn:country_code":"IR",
    "gn:dem":975,
    "gn:feature_class":"P",
    "gn:feature_code":"PPL",
    "gn:name":"Boneh-ye Kal\u016b Morte\u1e95\u00e1",
    "gn:population":0,
    "gn:timezone":"Asia/Tehran",
    "iso:country":"IR",
    "name:fas_x_preferred":[
        "Boneh-ye Kal\u016b"
    ],
    "name:fas_x_variant":[
        "\u0628\u0646\u0647 \u06a9\u0644\u0648",
        "\u0628\u0646\u0647 \u06a9\u0644\u0648 \u0645\u0631\u062a\u0636\u06cc"
    ],
    "name:und_x_variant":[
        "\u0628\u0646\u0647 \u06a9\u0644\u0648",
        "Boneh-ye Kal\u016b Morte\u1e95\u00e1"
    ],
    "wof:name":"Boneh-ye Kalu Morteza",
    "wof:placetype":"locality"
},
  "geometry": {"coordinates":[50.02547,31.16309],"type":"Point"}
}