{
  "type": "Feature",
  "properties": {
    "gn:admin1_code":"8",
    "gn:asciiname":"Kowsar",
    "gn:country_code":"IR",
    "gn:dem":1483,
    "gn:feature_class":"P",
    "gn:feature_code":"PPLL",
    "gn:name":"Kows\u0304ar",
    "gn:population":0,
    "gn:timezone":"Asia/Tehran",
    "iso:country":"IR",
    "name:fas_x_preferred":[
        "\u0686\u0644\u0647"
    ],
    "name:fas_x_variant":[
        "\u06a9\u0648\u062b\u0631"
    ],
    "name:und_x_variant":[
        "Chelleh",
        "Kows\u0304ar"
    ],
    "wof:name":"Kowsar",
    "wof:placetype":"locality"
},
  "geometry": {"coordinates":[48.8037,37.53805],"type":"Point"}
}