{
  "type": "Feature",
  "properties": {
    "gn:admin1_code":"25",
    "gn:asciiname":"Sar Avar",
    "gn:country_code":"IR",
    "gn:dem":2252,
    "gn:feature_class":"P",
    "gn:feature_code":"PPL",
    "gn:name":"Sar \u0100var",
    "gn:population":0,
    "gn:timezone":"Asia/Tehran",
    "iso:country":"IR",
    "name:ara_x_preferred":[
        "\u0633\u0631\u0627\u0648\u0631"
    ],
    "name:fas_x_preferred":[
        "\u0633\u064e\u0631\u0627\u0648\u064e\u0631"
    ],
    "name:fas_x_variant":[
        "\u0633\u0631 \u0622\u0648\u0631",
        "Sar\u0101var",
        "Sar \u0100var",
        "\u0633\u0631\u0627\u0648\u0631"
    ],
    "wof:name":"Sar Avar",
    "wof:placetype":"locality"
},
  "geometry": {"coordinates":[53.45895,35.89788],"type":"Point"}
}