{
  "type": "Feature",
  "properties": {
    "gn:admin1_code":"15",
    "gn:asciiname":"Kal Khvajeh-ye `Olya",
    "gn:country_code":"IR",
    "gn:dem":1382,
    "gn:feature_class":"P",
    "gn:feature_code":"PPL",
    "gn:name":"Kal Khv\u0101jeh-ye \u2018Oly\u0101",
    "gn:population":0,
    "gn:timezone":"Asia/Tehran",
    "iso:country":"IR",
    "name:fas_x_preferred":[
        "Kal Khv\u0101jeh-ye \u2018Oly\u0101"
    ],
    "wof:name":"Kal Khvajeh-ye `Olya",
    "wof:placetype":"locality"
},
  "geometry": {"coordinates":[50.31722,31.66944],"type":"Point"}
}