{
  "type": "Feature",
  "properties": {
    "gn:admin1_code":"4.0",
    "gn:asciiname":"Moshkadim",
    "gn:country_code":"IR",
    "gn:dem":1238,
    "gn:feature_class":"P",
    "gn:feature_code":"PPL",
    "gn:name":"Moshk\u0101d\u012bm",
    "gn:population":0,
    "gn:timezone":"Asia/Tehran",
    "iso:country":"IR",
    "name:fas_x_preferred":[
        "Moshk\u0101d\u012bm"
    ],
    "wof:name":"Moshkadim",
    "wof:placetype":"locality"
},
  "geometry": {"coordinates":[61.375,26.56306],"type":"Point"}
}