{
  "type": "Feature",
  "properties": {
    "gn:admin1_code":"9",
    "gn:asciiname":"Keytu",
    "gn:country_code":"IR",
    "gn:dem":2095,
    "gn:feature_class":"P",
    "gn:feature_code":"PPL",
    "gn:name":"Keyt\u016b",
    "gn:population":0,
    "gn:timezone":"Asia/Tehran",
    "iso:country":"IR",
    "name:ceb_x_preferred":[
        "Geytow"
    ],
    "name:fas_x_preferred":[
        "\u06a9\u06cc\u062a\u0648"
    ],
    "name:fas_x_variant":[
        "G\u012bto",
        "K\u012bt\u016b"
    ],
    "name:msa_x_preferred":[
        "Kitu"
    ],
    "name:swe_x_preferred":[
        "Geytow"
    ],
    "name:und_x_variant":[
        "Ka\u012bt\u016b",
        "Keyt\u016b"
    ],
    "wof:name":"Keytu",
    "wof:placetype":"locality"
},
  "geometry": {"coordinates":[48.15292,35.31984],"type":"Point"}
}