{
  "type": "Feature",
  "properties": {
    "gn:admin1_code":"32.0",
    "gn:asciiname":"Qeshlaq-e Mohammad",
    "gn:country_code":"IR",
    "gn:dem":159,
    "gn:feature_class":"P",
    "gn:feature_code":"PPL",
    "gn:name":"Qeshl\u0101q-e Mo\u1e29ammad",
    "gn:population":0,
    "gn:timezone":"Asia/Tehran",
    "iso:country":"IR",
    "name:fas_x_preferred":[
        "\u0642\u0634\u0644\u0627\u0642 \u0645\u062d\u0645\u062f"
    ],
    "name:fas_x_variant":[
        "Qeshl\u0101q-e Mo\u1e29ammad"
    ],
    "wof:name":"Qeshlaq-e Mohammad",
    "wof:placetype":"locality"
},
  "geometry": {"coordinates":[48.0581,39.4504],"type":"Point"}
}