{
  "type": "Feature",
  "properties": {
    "gn:admin1_code":"15",
    "gn:asciiname":"Deh-e Mah Bani",
    "gn:country_code":"IR",
    "gn:dem":923,
    "gn:feature_class":"P",
    "gn:feature_code":"PPL",
    "gn:name":"Deh-e M\u0101h Ban\u012b",
    "gn:population":0,
    "gn:timezone":"Asia/Tehran",
    "iso:country":"IR",
    "name:fas_x_preferred":[
        "Deh-e M\u0101h Ban\u012b"
    ],
    "wof:name":"Deh-e Mah Bani",
    "wof:placetype":"locality"
},
  "geometry": {"coordinates":[49.61944,32.37417],"type":"Point"}
}