{
  "type": "Feature",
  "properties": {
    "gn:admin1_code":"23",
    "gn:asciiname":"Fazelabad",
    "gn:country_code":"IR",
    "gn:dem":1608,
    "gn:feature_class":"P",
    "gn:feature_code":"PPL",
    "gn:name":"F\u0101\u1e95el\u0101b\u0101d",
    "gn:population":0,
    "gn:timezone":"Asia/Tehran",
    "iso:country":"IR",
    "name:fas_x_preferred":[
        "\u0641\u0627\u0636\u0644 \u0622\u0628\u0627\u062f"
    ],
    "name:fas_x_variant":[
        "F\u0101\u1e95el\u0101b\u0101d"
    ],
    "wof:name":"Fazelabad",
    "wof:placetype":"locality"
},
  "geometry": {"coordinates":[47.91401,33.85908],"type":"Point"}
}