{
  "type": "Feature",
  "properties": {
    "gn:admin1_code":"7",
    "gn:asciiname":"Mazra`eh-ye Jaldak",
    "gn:country_code":"IR",
    "gn:dem":1885,
    "gn:feature_class":"P",
    "gn:feature_code":"PPL",
    "gn:name":"Mazra\u2018eh-ye Jaldak",
    "gn:population":0,
    "gn:timezone":"Asia/Tehran",
    "iso:country":"IR",
    "name:fas_x_preferred":[
        "\u0645\u0632\u0631\u0639\u0647 \u062c\u0644\u062f\u06a9"
    ],
    "name:und_x_variant":[
        "Qal\u2018eh Jaldak",
        "Qal\u2018eh-ye Jaldak",
        "Jaldak",
        "Mazra\u2018eh-ye Jaldak"
    ],
    "wof:name":"Mazra`eh-ye Jaldak",
    "wof:placetype":"locality"
},
  "geometry": {"coordinates":[53.25377,30.08235],"type":"Point"}
}