{
  "type": "Feature",
  "properties": {
    "gn:admin1_code":"11",
    "gn:asciiname":"Deh Pirangan-e Bala",
    "gn:country_code":"IR",
    "gn:dem":511,
    "gn:feature_class":"P",
    "gn:feature_code":"PPL",
    "gn:name":"Deh P\u012brang\u0101n-e B\u0101l\u0101",
    "gn:population":0,
    "gn:timezone":"Asia/Tehran",
    "iso:country":"IR",
    "name:fas_x_preferred":[
        "\u062f\u0647 \u067e\u06cc\u0631\u0646\u06af\u0627\u0646 \u0628\u0627\u0644\u0627"
    ],
    "name:fas_x_variant":[
        "Deh P\u012brang\u0101n-e B\u0101l\u0101"
    ],
    "name:msa_x_preferred":[
        "Deh Pirangan-e Bala"
    ],
    "wof:name":"Deh Pirangan-e Bala",
    "wof:placetype":"locality"
},
  "geometry": {"coordinates":[57.1661,27.743],"type":"Point"}
}