{
  "type": "Feature",
  "properties": {
    "gn:admin1_code":"10",
    "gn:asciiname":"Tang-e Qir",
    "gn:country_code":"IR",
    "gn:dem":1194,
    "gn:feature_class":"P",
    "gn:feature_code":"PPL",
    "gn:name":"Tang-e Q\u012br",
    "gn:population":0,
    "gn:timezone":"Asia/Tehran",
    "iso:country":"IR",
    "name:ara_x_preferred":[
        "\u062a\u0646\u063a\u0642\u064a\u0631"
    ],
    "name:fas_x_preferred":[
        "Tang-e Q\u012br"
    ],
    "name:fas_x_variant":[
        "\u062a\u064e\u0646\u06af\u0650 \u0642\u064a\u0631",
        "\u062a\u0646\u06af\u0642\u06cc\u0631"
    ],
    "wof:name":"Tang-e Qir",
    "wof:placetype":"locality"
},
  "geometry": {"coordinates":[46.66667,33.76667],"type":"Point"}
}