{
  "type": "Feature",
  "properties": {
    "gn:admin1_code":"13",
    "gn:asciiname":"Poshteh Rizeh-ye Sofla",
    "gn:country_code":"IR",
    "gn:dem":1525,
    "gn:feature_class":"P",
    "gn:feature_code":"PPL",
    "gn:name":"Poshteh R\u012bzeh-ye Sofl\u00e1",
    "gn:population":0,
    "gn:timezone":"Asia/Tehran",
    "iso:country":"IR",
    "name:fas_x_preferred":[
        "\u067e\u0634\u062a\u0647 \u0631\u06cc\u0632\u0647 \u0633\u0641\u0644\u06cc"
    ],
    "name:fas_x_variant":[
        "Poshteh R\u012bzeh-ye Sofl\u00e1",
        "\u067e\u0634\u062a\u0647\u200c\u0631\u06cc\u0632\u0647 \u0633\u0641\u0644\u06cc"
    ],
    "wof:name":"Poshteh Rizeh-ye Sofla",
    "wof:placetype":"locality"
},
  "geometry": {"coordinates":[47.1886,34.076],"type":"Point"}
}