{
  "type": "Feature",
  "properties": {
    "gn:admin1_code":"10",
    "gn:asciiname":"Varmian",
    "gn:country_code":"IR",
    "gn:dem":1043,
    "gn:feature_class":"P",
    "gn:feature_code":"PPL",
    "gn:name":"Varm\u012b\u0101n",
    "gn:population":0,
    "gn:timezone":"Asia/Tehran",
    "iso:country":"IR",
    "name:ceb_x_preferred":[
        "Varm\u012b\u0101n"
    ],
    "name:fas_x_preferred":[
        "\u0648\u0631\u0645\u06cc\u0627\u0646 \u0633\u0641\u0644\u06cc"
    ],
    "name:fas_x_variant":[
        "Varm\u012b\u0101n-e Sofl\u00e1",
        "\u0648\u0631\u0645\u064a\u0627\u0646"
    ],
    "name:swe_x_preferred":[
        "Varm\u012b\u0101n"
    ],
    "name:und_x_variant":[
        "Varm\u012by\u0101n"
    ],
    "wof:name":"Varmian",
    "wof:placetype":"locality"
},
  "geometry": {"coordinates":[46.6509,33.65],"type":"Point"}
}