{
  "type": "Feature",
  "properties": {
    "gn:admin1_code":"15",
    "gn:asciiname":"Maksar-e Vosta",
    "gn:country_code":"IR",
    "gn:dem":18,
    "gn:feature_class":"P",
    "gn:feature_code":"PPL",
    "gn:name":"Maksar-e Vos\u0163\u00e1",
    "gn:population":0,
    "gn:timezone":"Asia/Tehran",
    "iso:country":"IR",
    "name:fas_x_preferred":[
        "\u0645\u06a9\u0633\u0631 \u0648\u0633\u0637\u06cc"
    ],
    "name:fas_x_variant":[
        "Maksar-e M\u012b\u0101n\u012b",
        "Maksar-e Vost\u00e1"
    ],
    "name:und_x_variant":[
        "Maksar-e Vos\u0163\u00e1"
    ],
    "wof:name":"Maksar-e Vosta",
    "wof:placetype":"locality"
},
  "geometry": {"coordinates":[49.21687,30.74557],"type":"Point"}
}