{
  "type": "Feature",
  "properties": {
    "gn:admin1_code":"43.0",
    "gn:asciiname":"Past Darreh-ye Khorasan",
    "gn:country_code":"IR",
    "gn:dem":714,
    "gn:feature_class":"P",
    "gn:feature_code":"PPL",
    "gn:name":"Past Darreh-ye Khor\u0101s\u0101n",
    "gn:population":0,
    "gn:timezone":"Asia/Tehran",
    "iso:country":"IR",
    "name:fas_x_preferred":[
        "\u067e\u0633\u062a \u062f\u0631\u0647 \u062e\u0631\u0627\u0633\u0627\u0646"
    ],
    "name:und_x_variant":[
        "Past Darreh-ye Khor\u0101s\u0101n"
    ],
    "wof:name":"Past Darreh-ye Khorasan",
    "wof:placetype":"locality"
},
  "geometry": {"coordinates":[56.33538000000001,38.02241],"type":"Point"}
}