{
  "type": "Feature",
  "properties": {
    "gn:admin1_code":"7",
    "gn:asciiname":"Abyan",
    "gn:country_code":"IR",
    "gn:dem":971,
    "gn:feature_class":"P",
    "gn:feature_code":"PPL",
    "gn:name":"\u0100by\u0101n",
    "gn:population":0,
    "gn:timezone":"Asia/Tehran",
    "iso:country":"IR",
    "name:fas_x_preferred":[
        "\u0100by\u0101n"
    ],
    "name:fas_x_variant":[
        "\u0622\u0628\u06cc\u0627\u0646",
        "\u0627\u0628\u06cc\u0627\u0646"
    ],
    "name:msa_x_preferred":[
        "Abyan"
    ],
    "wof:name":"Abyan",
    "wof:placetype":"locality"
},
  "geometry": {"coordinates":[51.53643,30.06799],"type":"Point"}
}