{
  "type": "Feature",
  "properties": {
    "gn:admin1_code":"43.0",
    "gn:asciiname":"Suteyli",
    "gn:country_code":"IR",
    "gn:dem":944,
    "gn:feature_class":"P",
    "gn:feature_code":"PPL",
    "gn:name":"S\u016bteyl\u012b",
    "gn:population":0,
    "gn:timezone":"Asia/Tehran",
    "iso:country":"IR",
    "name:fas_x_preferred":[
        "S\u016bteyl\u012b"
    ],
    "name:fas_x_variant":[
        "\u0633\u0648 \u062a\u06cc\u0644\u06cc",
        "\u0633\u0639\u0648 \u062f\u0644\u06cc"
    ],
    "name:und_x_variant":[
        "\u0633\u0648 \u062a\u06cc\u0644\u06cc",
        "So\u2018\u016bdl\u012b"
    ],
    "wof:name":"Suteyli",
    "wof:placetype":"locality"
},
  "geometry": {"coordinates":[56.65058000000001,38.2027],"type":"Point"}
}