{
  "type": "Feature",
  "properties": {
    "gn:admin1_code":"35.0",
    "gn:asciiname":"Zoghal Manzel",
    "gn:country_code":"IR",
    "gn:dem":-15,
    "gn:feature_class":"P",
    "gn:feature_code":"PPL",
    "gn:name":"Zogh\u0101l Manzel",
    "gn:population":0,
    "gn:timezone":"Asia/Tehran",
    "iso:country":"IR",
    "name:fas_x_preferred":[
        "Zogh\u0101l Manzel"
    ],
    "name:fas_x_variant":[
        "\u0632\u063a\u0627\u0644 \u0645\u0646\u0632\u0644"
    ],
    "wof:name":"Zoghal Manzel",
    "wof:placetype":"locality"
},
  "geometry": {"coordinates":[52.86341,36.67307],"type":"Point"}
}