{
  "type": "Feature",
  "properties": {
    "gn:admin1_code":"23",
    "gn:asciiname":"Ramazanabad-e Qorban `Ali",
    "gn:country_code":"IR",
    "gn:dem":1515,
    "gn:feature_class":"P",
    "gn:feature_code":"PPL",
    "gn:name":"Rama\u1e95\u0101n\u0101b\u0101d-e Qorb\u0101n `Al\u012b",
    "gn:population":0,
    "gn:timezone":"Asia/Tehran",
    "iso:country":"IR",
    "name:fas_x_preferred":[
        "\u0631\u064e\u0645\u064e\u0636\u0627\u0646\u0627\u0628\u0627\u062f\u0650 \u0642\u064f\u0631\u0628\u0627\u0646 \u0639\u064e\u0644\u06cc"
    ],
    "wof:name":"Ramazanabad-e Qorban `Ali",
    "wof:placetype":"locality"
},
  "geometry": {"coordinates":[47.98056,33.93360999999999],"type":"Point"}
}