{
  "type": "Feature",
  "properties": {
    "gn:admin1_code":"26.0",
    "gn:asciiname":"Bahmanabad",
    "gn:country_code":"IR",
    "gn:dem":1097,
    "gn:feature_class":"P",
    "gn:feature_code":"PPL",
    "gn:name":"Bahman\u0101b\u0101d",
    "gn:population":0,
    "gn:timezone":"Asia/Tehran",
    "iso:country":"IR",
    "name:ara_x_preferred":[
        "\u0628\u0647\u0645\u0646\u200c\u0622\u0628\u0627\u062f"
    ],
    "name:fas_x_preferred":[
        "\u0628\u0647\u0645\u0646 \u0622\u0628\u0627\u062f"
    ],
    "name:fas_x_variant":[
        "Bahman\u0101b\u0101d",
        "\u0628\u0647\u0645\u0646\u200c\u0622\u0628\u0627\u062f"
    ],
    "wof:name":"Bahmanabad",
    "wof:placetype":"locality"
},
  "geometry": {"coordinates":[51.1969,35.6021],"type":"Point"}
}