{
  "type": "Feature",
  "properties": {
    "gn:admin1_code":"15",
    "gn:asciiname":"Shahrak-e Enqelab",
    "gn:country_code":"IR",
    "gn:dem":78,
    "gn:feature_class":"P",
    "gn:feature_code":"PPL",
    "gn:name":"Shahrak-e Enqel\u0101b",
    "gn:population":0,
    "gn:timezone":"Asia/Tehran",
    "iso:country":"IR",
    "name:azb_x_preferred":[
        "\u0634\u0647\u0631\u06a9 \u0627\u0646\u0642\u0644\u0627\u0628"
    ],
    "name:fas_x_preferred":[
        "\u0634\u0647\u0631\u06a9 \u0627\u0646\u0642\u0644\u0627\u0628"
    ],
    "name:fas_x_variant":[
        "Shahrak-e Enqel\u0101b"
    ],
    "name:und_x_variant":[
        "Qal\u2018eh-ye \u2018Abd osh Sh\u0101h",
        "Ghal\u2018eh Abdolshah",
        "Qal\u2018eh \u2018Abdos\u0304h Sh\u0101h"
    ],
    "wof:name":"Shahrak-e Enqelab",
    "wof:placetype":"locality"
},
  "geometry": {"coordinates":[48.41472,32.19275],"type":"Point"}
}