{
  "type": "Feature",
  "properties": {
    "gn:admin1_code":"15",
    "gn:asciiname":"Ketf-e Gusheh",
    "gn:country_code":"IR",
    "gn:dem":852,
    "gn:feature_class":"P",
    "gn:feature_code":"PPL",
    "gn:name":"Ketf-e G\u016bsheh",
    "gn:population":0,
    "gn:timezone":"Asia/Tehran",
    "iso:country":"IR",
    "name:azb_x_preferred":[
        "\u0643\u0641\u062a \u06af\u0648\u0634\u0647(\u0627\u06cc\u0630\u0647)"
    ],
    "name:ceb_x_preferred":[
        "Ketf-e G\u016bsheh"
    ],
    "name:fas_x_preferred":[
        "Ketf-e G\u016bsheh"
    ],
    "name:fas_x_variant":[
        "\u06a9\u0641\u062a\u200c\u06af\u0648\u0634\u0647"
    ],
    "name:swe_x_preferred":[
        "Ketf-e G\u016bsheh"
    ],
    "wof:name":"Ketf-e Gusheh",
    "wof:placetype":"locality"
},
  "geometry": {"coordinates":[50.18333,31.66056],"type":"Point"}
}