{
  "type": "Feature",
  "properties": {
    "gn:admin1_code":"1",
    "gn:asciiname":"Molla Ahmad",
    "gn:country_code":"IR",
    "gn:dem":949,
    "gn:feature_class":"P",
    "gn:feature_code":"PPL",
    "gn:name":"Moll\u0101 A\u1e29mad",
    "gn:population":0,
    "gn:timezone":"Asia/Tehran",
    "iso:country":"IR",
    "name:fas_x_preferred":[
        "\u0645\u064f\u0644\u0651\u0627 \u0627\u064e\u062d\u0645\u064e\u062f"
    ],
    "name:fas_x_variant":[
        "\u0645\u0644\u0627\u0651 \u0627\u062d\u0645\u062f",
        "Moll\u0101 A\u1e29mad"
    ],
    "wof:name":"Molla Ahmad",
    "wof:placetype":"locality"
},
  "geometry": {"coordinates":[44.7813,39.2531],"type":"Point"}
}