{
  "type": "Feature",
  "properties": {
    "gn:admin1_code":"32",
    "gn:asciiname":"Kandeh",
    "gn:country_code":"IR",
    "gn:dem":1521,
    "gn:feature_class":"P",
    "gn:feature_code":"PPL",
    "gn:name":"Kandeh",
    "gn:population":0,
    "gn:timezone":"Asia/Tehran",
    "iso:country":"IR",
    "name:fas_x_preferred":[
        "\u0643\u0646\u062f\u0647"
    ],
    "name:fas_x_variant":[
        "\u0643\u064e\u0646\u062f\u0650\u0647 \u0643\u064e\u0646\u062f\u06cc"
    ],
    "name:und_x_variant":[
        "Kandeh Kand\u012b",
        "Kandeh"
    ],
    "wof:name":"Kandeh",
    "wof:placetype":"locality"
},
  "geometry": {"coordinates":[47.6752,38.8634],"type":"Point"}
}