{
  "type": "Feature",
  "properties": {
    "gn:admin1_code":"29",
    "gn:asciiname":"Savat",
    "gn:country_code":"IR",
    "gn:dem":1957,
    "gn:feature_class":"P",
    "gn:feature_code":"PPL",
    "gn:name":"S\u0101v\u0101t",
    "gn:population":0,
    "gn:timezone":"Asia/Tehran",
    "iso:country":"IR",
    "name:ara_x_preferred":[
        "\u0633\u0627\u0648\u0627\u062a"
    ],
    "name:fas_x_preferred":[
        "S\u0101v\u0101t"
    ],
    "name:fas_x_variant":[
        "\u0633\u0627\u0648\u0627\u062a"
    ],
    "wof:name":"Savat",
    "wof:placetype":"locality"
},
  "geometry": {"coordinates":[57.98556,29.04722000000001],"type":"Point"}
}