{
  "type": "Feature",
  "properties": {
    "gn:admin1_code":"8",
    "gn:asciiname":"Gileh Molk",
    "gn:country_code":"IR",
    "gn:dem":135,
    "gn:feature_class":"P",
    "gn:feature_code":"PPL",
    "gn:name":"G\u012bleh Molk",
    "gn:population":0,
    "gn:timezone":"Asia/Tehran",
    "iso:country":"IR",
    "name:ceb_x_preferred":[
        "G\u012bl\u0101molk"
    ],
    "name:fas_x_preferred":[
        "G\u012bl\u0101molk"
    ],
    "name:fas_x_variant":[
        "\u06af\u06cc\u0644\u0627\u0645\u0644\u06a9",
        "\u06af\u06cc\u0644\u0647 \u0645\u0644\u06a9"
    ],
    "name:msa_x_preferred":[
        "Gilamolk"
    ],
    "name:swe_x_preferred":[
        "G\u012bl\u0101molk"
    ],
    "name:ukr_x_preferred":[
        "\u0490\u0456\u043b\u0430\u043c\u043e\u043b\u044c\u043a"
    ],
    "name:und_x_variant":[
        "G\u012bleh Molk"
    ],
    "wof:name":"Gileh Molk",
    "wof:placetype":"locality"
},
  "geometry": {"coordinates":[50.38688,37.01036],"type":"Point"}
}