{
  "type": "Feature",
  "properties": {
    "gn:admin1_code":"29",
    "gn:asciiname":"Beyaz",
    "gn:country_code":"IR",
    "gn:dem":1438,
    "gn:feature_class":"P",
    "gn:feature_code":"PPL",
    "gn:name":"Bey\u0101\u1e95",
    "gn:population":0,
    "gn:timezone":"Asia/Tehran",
    "iso:country":"IR",
    "name:ara_x_preferred":[
        "\u0628\u06cc\u0627\u0636"
    ],
    "name:fas_x_preferred":[
        "Bay\u0101\u1e95"
    ],
    "name:fas_x_variant":[
        "\u0628\u06cc\u0627\u0636"
    ],
    "name:und_x_variant":[
        "Bey\u0101\u1e95"
    ],
    "wof:name":"Beyaz",
    "wof:placetype":"locality"
},
  "geometry": {"coordinates":[55.44563,30.70191],"type":"Point"}
}