{
  "type": "Feature",
  "properties": {
    "gn:admin1_code":"9",
    "gn:asciiname":"Varayneh",
    "gn:country_code":"IR",
    "gn:dem":1762,
    "gn:feature_class":"P",
    "gn:feature_code":"PPL",
    "gn:name":"Var\u0101yneh",
    "gn:population":0,
    "gn:timezone":"Asia/Tehran",
    "iso:country":"IR",
    "name:fas_x_preferred":[
        "\u0648\u0631 \u0622\u06cc\u0646\u0647"
    ],
    "name:fas_x_variant":[
        "Var\u0101\u2019\u012bneh",
        "Var\u0101yneh",
        "\u0648\u0631\u0627\u0626\u06cc\u0646\u0647",
        "\u0648\u0631\u0627\u06cc\u0646\u0647"
    ],
    "name:msa_x_preferred":[
        "Varayeneh"
    ],
    "name:und_x_variant":[
        "\u0100yeneh",
        "Varav\u012bna",
        "Varven\u012b",
        "Var \u0100yneh",
        "Waraweni",
        "Var\u0101m\u012bneh",
        "Var\u0101yeneh"
    ],
    "wof:name":"Varayneh",
    "wof:placetype":"locality"
},
  "geometry": {"coordinates":[48.40527,34.0786],"type":"Point"}
}