{
  "type": "Feature",
  "properties": {
    "gn:admin1_code":"4.0",
    "gn:asciiname":"Ramin",
    "gn:country_code":"IR",
    "gn:dem":20,
    "gn:feature_class":"P",
    "gn:feature_code":"PPL",
    "gn:name":"Ram\u012bn",
    "gn:population":0,
    "gn:timezone":"Asia/Tehran",
    "iso:country":"IR",
    "name:fas_x_preferred":[
        "\u0631\u0645\u06cc\u0646"
    ],
    "name:fas_x_variant":[
        "Ram\u012bn"
    ],
    "wof:name":"Ramin",
    "wof:placetype":"locality"
},
  "geometry": {"coordinates":[60.75723000000001,25.2728],"type":"Point"}
}