{
  "type": "Feature",
  "properties": {
    "gn:admin1_code":"35",
    "gn:asciiname":"`Arab Kheyl",
    "gn:country_code":"IR",
    "gn:dem":-16,
    "gn:feature_class":"P",
    "gn:feature_code":"PPL",
    "gn:name":"\u2018Arab Kheyl",
    "gn:population":0,
    "gn:timezone":"Asia/Tehran",
    "iso:country":"IR",
    "name:fas_x_preferred":[
        "\u0639\u0631\u0628 \u062e\u064a\u0644"
    ],
    "name:fas_x_variant":[
        "\u2018Arab Kheyl"
    ],
    "name:und_x_variant":[
        "\u2018Arab Ma\u1e29alleh",
        "\u0639\u064e\u0631\u064e\u0628 \u0645\u064e\u062d\u064e\u0644\u0650\u0651\u0647"
    ],
    "wof:name":"`Arab Kheyl",
    "wof:placetype":"locality"
},
  "geometry": {"coordinates":[53.04749,36.6889],"type":"Point"}
}