{
  "type": "Feature",
  "properties": {
    "gn:admin1_code":"29",
    "gn:asciiname":"Farahzad",
    "gn:country_code":"IR",
    "gn:dem":1421,
    "gn:feature_class":"P",
    "gn:feature_code":"PPL",
    "gn:name":"Fara\u1e29z\u0101d",
    "gn:population":0,
    "gn:timezone":"Asia/Tehran",
    "iso:country":"IR",
    "name:fas_x_preferred":[
        "Fara\u1e29z\u0101d"
    ],
    "name:fas_x_variant":[
        "\u0641\u0631\u062d\u0632\u0627\u062f"
    ],
    "name:fra_x_preferred":[
        "Farahzad"
    ],
    "wof:name":"Farahzad",
    "wof:placetype":"locality"
},
  "geometry": {"coordinates":[55.61361,30.59667],"type":"Point"}
}