{
  "type": "Feature",
  "properties": {
    "gn:admin1_code":"23",
    "gn:asciiname":"Bazvand Mohammadi",
    "gn:country_code":"IR",
    "gn:dem":1134,
    "gn:feature_class":"P",
    "gn:feature_code":"PPL",
    "gn:name":"B\u0101zvand Mo\u1e29ammad\u012b",
    "gn:population":0,
    "gn:timezone":"Asia/Tehran",
    "iso:country":"IR",
    "name:fas_x_preferred":[
        "\u0639\u064e\u0628\u062f\u064f\u0644\u0628\u0650\u064a\u06af\u06cc"
    ],
    "name:fas_x_variant":[
        "\u0639\u0628\u062f\u0627\u0644 \u0628\u06cc\u06af\u06cc",
        "\u2018Abdolbeyg\u012b",
        "\u2018Abd\u0101l Beyg\u012b",
        "\u0628\u0627\u0632\u0648\u0646\u062f \u0645\u062d\u0645\u062f\u06cc"
    ],
    "name:und_x_variant":[
        "B\u0101zvand Mo\u1e29ammad\u012b"
    ],
    "wof:name":"Bazvand Mohammadi",
    "wof:placetype":"locality"
},
  "geometry": {"coordinates":[47.5968,33.2602],"type":"Point"}
}