{
  "type": "Feature",
  "properties": {
    "gn:admin1_code":"43",
    "gn:asciiname":"Dehik",
    "gn:country_code":"IR",
    "gn:dem":1096,
    "gn:feature_class":"P",
    "gn:feature_code":"PPL",
    "gn:name":"Deh\u012bk",
    "gn:population":0,
    "gn:timezone":"Asia/Tehran",
    "iso:country":"IR",
    "name:fas_x_preferred":[
        "Deh\u012bk"
    ],
    "name:fas_x_variant":[
        "\u062f\u0647\u06cc\u06a9"
    ],
    "name:und_x_variant":[
        "Dehak"
    ],
    "wof:name":"Dehik",
    "wof:placetype":"locality"
},
  "geometry": {"coordinates":[57.08184,37.14699],"type":"Point"}
}