{
  "type": "Feature",
  "properties": {
    "gn:admin1_code":"42",
    "gn:asciiname":"Bagh `Abbas",
    "gn:country_code":"IR",
    "gn:dem":1628,
    "gn:feature_class":"P",
    "gn:feature_code":"PPL",
    "gn:name":"B\u0101gh \u2018Abb\u0101s",
    "gn:population":0,
    "gn:timezone":"Asia/Tehran",
    "iso:country":"IR",
    "name:ara_x_preferred":[
        "\u0628\u0627\u063a \u0639\u0628\u0627\u0633"
    ],
    "name:fas_x_preferred":[
        "\u0628\u0627\u063a \u0639\u0628\u0627\u0633"
    ],
    "name:fas_x_variant":[
        "B\u0101gh \u2018Abb\u0101s"
    ],
    "wof:name":"Bagh `Abbas",
    "wof:placetype":"locality"
},
  "geometry": {"coordinates":[59.74144,35.57728],"type":"Point"}
}