{
  "type": "Feature",
  "properties": {
    "gn:admin1_code":"33",
    "gn:asciiname":"Qayujakh",
    "gn:country_code":"IR",
    "gn:dem":1567,
    "gn:feature_class":"P",
    "gn:feature_code":"PPL",
    "gn:name":"Qay\u016bj\u0101kh",
    "gn:population":0,
    "gn:timezone":"Asia/Tehran",
    "iso:country":"IR",
    "name:fas_x_preferred":[
        "\u0642\u06cc\u0648\u062c\u0627\u062e"
    ],
    "name:fas_x_variant":[
        "Q\u016b\u012bj\u0101q",
        "Qay\u016bj\u0101kh"
    ],
    "name:und_x_variant":[
        "G\u016byj\u0101kh",
        "Ku\u012bjakh",
        "Ghooijagh",
        "Kuydzha",
        "Q\u016by\u016bj\u0101q",
        "Q\u016byj\u0101q"
    ],
    "wof:name":"Qayujakh",
    "wof:placetype":"locality"
},
  "geometry": {"coordinates":[46.7064,38.1085],"type":"Point"}
}