{
  "type": "Feature",
  "properties": {
    "gn:admin1_code":"41",
    "gn:asciiname":"Hari Shi",
    "gn:country_code":"IR",
    "gn:dem":2004,
    "gn:feature_class":"P",
    "gn:feature_code":"PPL",
    "gn:name":"Har\u012b Sh\u012b",
    "gn:population":0,
    "gn:timezone":"Asia/Tehran",
    "iso:country":"IR",
    "name:fas_x_preferred":[
        "H\u016brsh\u012bn"
    ],
    "name:fas_x_variant":[
        "Har\u012bsh\u012b",
        "\u0647\u0648\u0631\u0634\u064a\u0646",
        "\u0647\u0631\u06cc \u0634\u06cc",
        "\u0647\u0631\u064a\u0634\u06cc",
        "\u0647\u0631\u06cc\u0634\u06cc"
    ],
    "name:und_x_variant":[
        "Har\u012b Sh\u012b"
    ],
    "name:vie_x_preferred":[
        "Harishi"
    ],
    "wof:name":"Hari Shi",
    "wof:placetype":"locality"
},
  "geometry": {"coordinates":[59.43443000000001,32.23069],"type":"Point"}
}