{
  "type": "Feature",
  "properties": {
    "gn:admin1_code":"35.0",
    "gn:asciiname":"Galesh Kola",
    "gn:country_code":"IR",
    "gn:dem":63,
    "gn:feature_class":"P",
    "gn:feature_code":"PPL",
    "gn:name":"G\u0101lesh Kol\u0101",
    "gn:population":0,
    "gn:timezone":"Asia/Tehran",
    "iso:country":"IR",
    "name:fas_x_preferred":[
        "\u06af\u0627\u0644\u0634 \u0643\u0644\u0627"
    ],
    "name:fas_x_variant":[
        "G\u0101lesh Kol\u0101"
    ],
    "wof:name":"Galesh Kola",
    "wof:placetype":"locality"
},
  "geometry": {"coordinates":[52.39311,36.49216],"type":"Point"}
}