{
  "type": "Feature",
  "properties": {
    "gn:admin1_code":"4",
    "gn:asciiname":"Karam Shah",
    "gn:country_code":"IR",
    "gn:dem":389,
    "gn:feature_class":"P",
    "gn:feature_code":"PPL",
    "gn:name":"Karam Sh\u0101h",
    "gn:population":0,
    "gn:timezone":"Asia/Tehran",
    "iso:country":"IR",
    "name:fas_x_preferred":[
        "\u0643\u0631\u0645 \u0634\u0627\u0647"
    ],
    "name:fas_x_variant":[
        "Karam Sh\u0101h"
    ],
    "wof:name":"Karam Shah",
    "wof:placetype":"locality"
},
  "geometry": {"coordinates":[58.89108,27.10867],"type":"Point"}
}