{
  "type": "Feature",
  "properties": {
    "gn:admin1_code":"33.0",
    "gn:asciiname":"Qal`eh-ye Qolij Khan Kandi",
    "gn:country_code":"IR",
    "gn:dem":2281,
    "gn:feature_class":"P",
    "gn:feature_code":"PPL",
    "gn:name":"Qal\u2018eh-ye Qol\u012bj Khan Kand\u012b",
    "gn:population":0,
    "gn:timezone":"Asia/Tehran",
    "iso:country":"IR",
    "name:fas_x_preferred":[
        "\u0642\u064e\u0644\u0639\u0650\u06c0 \u0642\u064f\u0644\u064a\u062c \u062e\u064e\u0646 \u0643\u064e\u0646\u062f\u06cc"
    ],
    "name:fas_x_variant":[
        "Qal\u2018eh-ye Qol\u012bj Khan Kand\u012b"
    ],
    "wof:name":"Qal`eh-ye Qolij Khan Kandi",
    "wof:placetype":"locality"
},
  "geometry": {"coordinates":[47.24342,36.90401],"type":"Point"}
}