{
  "type": "Feature",
  "properties": {
    "gn:admin1_code":"15.0",
    "gn:asciiname":"Darreh Mianeh",
    "gn:country_code":"IR",
    "gn:dem":594,
    "gn:feature_class":"P",
    "gn:feature_code":"PPL",
    "gn:name":"Darreh M\u012b\u0101neh",
    "gn:population":0,
    "gn:timezone":"Asia/Tehran",
    "iso:country":"IR",
    "name:fas_x_preferred":[
        "Darreh M\u012b\u0101neh"
    ],
    "name:fas_x_variant":[
        "\u062f\u0631\u0651\u0647 \u0645\u06cc\u0627\u0646\u0647"
    ],
    "wof:name":"Darreh Mianeh",
    "wof:placetype":"locality"
},
  "geometry": {"coordinates":[49.9007,31.18593],"type":"Point"}
}