{
  "type": "Feature",
  "properties": {
    "gn:admin1_code":"15",
    "gn:asciiname":"Khowrshid",
    "gn:country_code":"IR",
    "gn:dem":34,
    "gn:feature_class":"P",
    "gn:feature_code":"PPL",
    "gn:name":"Khowrsh\u012bd",
    "gn:population":0,
    "gn:timezone":"Asia/Tehran",
    "iso:country":"IR",
    "name:fas_x_preferred":[
        "\u0641\u06cc\u0627\u0636 \u0622\u0628\u0627\u062f"
    ],
    "name:fas_x_variant":[
        "Fayy\u0101\u1e95\u0101b\u0101d",
        "\u062e\u0648\u0631\u0634\u06cc\u062f"
    ],
    "name:und_x_variant":[
        "Khowrsh\u012bd"
    ],
    "wof:name":"Khowrshid",
    "wof:placetype":"locality"
},
  "geometry": {"coordinates":[48.8795,31.89707000000001],"type":"Point"}
}