{
  "type": "Feature",
  "properties": {
    "gn:admin1_code":"23",
    "gn:asciiname":"Chahar Afshar-e Sofla",
    "gn:country_code":"IR",
    "gn:dem":1940,
    "gn:feature_class":"P",
    "gn:feature_code":"PPL",
    "gn:name":"Chah\u0101r Afsh\u0101r-e Sofl\u00e1",
    "gn:population":0,
    "gn:timezone":"Asia/Tehran",
    "iso:country":"IR",
    "name:ara_x_preferred":[
        "\u062a\u0634\u0647\u0627\u0631\u0627\u0641\u0634\u0627\u0631 \u0633\u0641\u0644\u064a"
    ],
    "name:ceb_x_preferred":[
        "Chah\u0101r Afsh\u0101r-e Sofl\u00e1"
    ],
    "name:fas_x_preferred":[
        "\u0686\u064e\u0647\u0627\u0631 \u0627\u064e\u0641\u0634\u0627\u0631\u0650 \u0633\u064f\u0641\u0644\u064e\u0649"
    ],
    "name:fas_x_variant":[
        "\u0686\u0647\u0627\u0631 \u0627\u0641\u0634\u0627\u0631 \u0633\u0641\u0644\u06cc",
        "Chah\u0101r Afsh\u0101r-e Sofl\u00e1",
        "\u0686\u0647\u0627\u0631\u0627\u0641\u0634\u0627\u0631 \u0633\u0641\u0644\u06cc"
    ],
    "name:swe_x_preferred":[
        "Chah\u0101r Afsh\u0101r-e Sofl\u00e1"
    ],
    "wof:name":"Chahar Afshar-e Sofla",
    "wof:placetype":"locality"
},
  "geometry": {"coordinates":[47.795,34.278],"type":"Point"}
}