{
  "type": "Feature",
  "properties": {
    "gn:admin1_code":"11",
    "gn:asciiname":"Lur",
    "gn:country_code":"IR",
    "gn:dem":348,
    "gn:feature_class":"P",
    "gn:feature_code":"PPL",
    "gn:name":"L\u016br",
    "gn:population":0,
    "gn:timezone":"Asia/Tehran",
    "iso:country":"IR",
    "name:fas_x_preferred":[
        "\u0644\u0648\u0631"
    ],
    "name:fas_x_variant":[
        "L\u016br"
    ],
    "wof:name":"Lur",
    "wof:placetype":"locality"
},
  "geometry": {"coordinates":[57.4596,26.8792],"type":"Point"}
}