{
  "type": "Feature",
  "properties": {
    "gn:admin1_code":"35.0",
    "gn:asciiname":"Izad Kheyl",
    "gn:country_code":"IR",
    "gn:dem":-19,
    "gn:feature_class":"P",
    "gn:feature_code":"PPL",
    "gn:name":"\u012azad Kheyl",
    "gn:population":0,
    "gn:timezone":"Asia/Tehran",
    "iso:country":"IR",
    "name:ceb_x_preferred":[
        "\u012azad Kheyl"
    ],
    "name:fas_x_preferred":[
        "\u064a\u0632\u064e\u062f\u06cc \u062e\u0650\u064a\u0644"
    ],
    "name:fas_x_variant":[
        "\u012azad\u012b Kheyl",
        "\u012azad Kheyl",
        "\u0627\u064a\u0632\u062f \u062e\u064a\u0644",
        "\u0627\u06cc\u0632\u062f\u062e\u06cc\u0644"
    ],
    "name:swe_x_preferred":[
        "\u012azad Kheyl"
    ],
    "wof:name":"Izad Kheyl",
    "wof:placetype":"locality"
},
  "geometry": {"coordinates":[52.94365,36.70491],"type":"Point"}
}