{
  "type": "Feature",
  "properties": {
    "gn:admin1_code":"44.0",
    "gn:asciiname":"Saburi",
    "gn:country_code":"IR",
    "gn:dem":1283,
    "gn:feature_class":"P",
    "gn:feature_code":"PPL",
    "gn:name":"\u015eab\u016br\u012b",
    "gn:population":0,
    "gn:timezone":"Asia/Tehran",
    "iso:country":"IR",
    "name:fas_x_preferred":[
        "\u0635\u0628\u0648\u0631\u06cc"
    ],
    "name:fas_x_variant":[
        "\u015eab\u016br\u012b"
    ],
    "wof:name":"Saburi",
    "wof:placetype":"locality"
},
  "geometry": {"coordinates":[50.94926,35.79464],"type":"Point"}
}