{
  "type": "Feature",
  "properties": {
    "gn:admin1_code":"44.0",
    "gn:asciiname":"Saburi",
    "gn:country_code":"IR",
    "gn:dem":1283,
    "gn:feature_class":"P",
    "gn:feature_code":"PPL",
    "gn:name":"\u015eab\u016br\u012b",
    "gn:population":0,
    "gn:timezone":"Asia/Tehran",
    "iso:country":"IR",
    "name:est_x_preferred":[
        "Saburi"
    ],
    "name:fas_x_preferred":[
        "\u0635\u0628\u0648\u0631\u06cc"
    ],
    "name:fas_x_variant":[
        "\u015eab\u016br\u012b"
    ],
    "name:fra_x_preferred":[
        "Saburi"
    ],
    "name:hye_x_preferred":[
        "\u054d\u0561\u0562\u0578\u0582\u057c\u056b"
    ],
    "name:pol_x_preferred":[
        "Saburi"
    ],
    "name:spa_x_preferred":[
        "Saburi"
    ],
    "name:ukr_x_preferred":[
        "\u0421\u0430\u0431\u0443\u0440\u0456"
    ],
    "name:urd_x_preferred":[
        "\u0635\u0628\u0631\u06cc"
    ],
    "name:vol_x_preferred":[
        "Saburi"
    ],
    "wof:name":"Saburi",
    "wof:placetype":"locality"
},
  "geometry": {"coordinates":[50.94926,35.79464],"type":"Point"}
}