{
  "type": "Feature",
  "properties": {
    "gn:admin1_code":"33",
    "gn:asciiname":"Cheshmeh Vazan",
    "gn:country_code":"IR",
    "gn:dem":1523,
    "gn:feature_class":"P",
    "gn:feature_code":"PPL",
    "gn:name":"Cheshmeh Vaz\u0101n",
    "gn:population":0,
    "gn:timezone":"Asia/Tehran",
    "iso:country":"IR",
    "name:fas_x_preferred":[
        "\u0686\u0634\u0645\u0647 \u0648\u0632\u0627\u0646"
    ],
    "name:fas_x_variant":[
        "Cheshmeh Vaz\u0101n"
    ],
    "wof:name":"Cheshmeh Vazan",
    "wof:placetype":"locality"
},
  "geometry": {"coordinates":[47.00276,38.41198],"type":"Point"}
}