{
  "type": "Feature",
  "properties": {
    "gn:admin1_code":"25",
    "gn:asciiname":"Hajjaji",
    "gn:country_code":"IR",
    "gn:dem":1145,
    "gn:feature_class":"P",
    "gn:feature_code":"PPL",
    "gn:name":"\u1e28ajj\u0101j\u012b",
    "gn:population":0,
    "gn:timezone":"Asia/Tehran",
    "iso:country":"IR",
    "name:fas_x_preferred":[
        "\u062d\u062c\u0627\u062c\u06cc"
    ],
    "name:fas_x_variant":[
        "\u1e28ajj\u0101j\u012b"
    ],
    "wof:name":"Hajjaji",
    "wof:placetype":"locality"
},
  "geometry": {"coordinates":[54.17408,36.06321],"type":"Point"}
}