{
  "type": "Feature",
  "properties": {
    "gn:admin1_code":"23",
    "gn:asciiname":"Cheshmeh Khani-ye Sofla",
    "gn:country_code":"IR",
    "gn:dem":1972,
    "gn:feature_class":"P",
    "gn:feature_code":"PPL",
    "gn:name":"Cheshmeh Kh\u0101n\u012b-ye Sofl\u00e1",
    "gn:population":0,
    "gn:timezone":"Asia/Tehran",
    "iso:country":"IR",
    "name:ara_x_preferred":[
        "\u062a\u0634\u0634\u0645\u0629 \u062e\u0627\u0646\u064a \u0633\u0641\u0644\u064a"
    ],
    "name:fas_x_preferred":[
        "Cheshmeh Kh\u0101n\u012b-ye Sofl\u00e1"
    ],
    "name:fas_x_variant":[
        "\u0686\u0634\u0645\u0647 \u062e\u0627\u0646\u06cc \u0633\u0641\u0644\u06cc"
    ],
    "name:und_x_variant":[
        "Cheshmeh Kh\u0101n\u012b",
        "Chashmeh Kh\u0101n\u012b",
        "\u0686\u0634\u0645\u0647 \u062e\u0627\u0646\u06cc \u0633\u0641\u0644\u06cc"
    ],
    "wof:name":"Cheshmeh Khani-ye Sofla",
    "wof:placetype":"locality"
},
  "geometry": {"coordinates":[48.20397,34.03325],"type":"Point"}
}