{
  "type": "Feature",
  "properties": {
    "gn:admin1_code":"29",
    "gn:asciiname":"Mangol",
    "gn:country_code":"IR",
    "gn:dem":694,
    "gn:feature_class":"P",
    "gn:feature_code":"PPL",
    "gn:name":"Mangol",
    "gn:population":0,
    "gn:timezone":"Asia/Tehran",
    "iso:country":"IR",
    "name:ceb_x_preferred":[
        "Mangol"
    ],
    "name:fas_x_preferred":[
        "\u0645\u064e\u0646\u06af\u064f\u0644"
    ],
    "name:fas_x_variant":[
        "\u0645\u064e\u0646\u06af\u064e\u0644"
    ],
    "name:swe_x_preferred":[
        "Mangol"
    ],
    "name:und_x_variant":[
        "Mangal"
    ],
    "wof:name":"Mangol",
    "wof:placetype":"locality"
},
  "geometry": {"coordinates":[58.81667,26.85],"type":"Point"}
}