{
  "type": "Feature",
  "properties": {
    "gn:admin1_code":"28.0",
    "gn:asciiname":"Chandabeh",
    "gn:country_code":"IR",
    "gn:dem":2238,
    "gn:feature_class":"P",
    "gn:feature_code":"PPL",
    "gn:name":"Chand\u0101beh",
    "gn:population":0,
    "gn:timezone":"Asia/Tehran",
    "iso:country":"IR",
    "name:fas_x_preferred":[
        "Chand\u0101beh"
    ],
    "wof:name":"Chandabeh",
    "wof:placetype":"locality"
},
  "geometry": {"coordinates":[52.66667,32.78333],"type":"Point"}
}