{
  "type": "Feature",
  "properties": {
    "gn:admin1_code":"4.0",
    "gn:asciiname":"Mohammadabad-e Boru'i",
    "gn:country_code":"IR",
    "gn:dem":1786,
    "gn:feature_class":"P",
    "gn:feature_code":"PPL",
    "gn:name":"Mo\u1e29ammad\u0101b\u0101d-e Bor\u016b\u2019\u012b",
    "gn:population":0,
    "gn:timezone":"Asia/Tehran",
    "iso:country":"IR",
    "name:fas_x_preferred":[
        "Mo\u1e29ammad\u0101b\u0101d-e Bor\u016b\u2019\u012b"
    ],
    "wof:name":"Mohammadabad-e Boru'i",
    "wof:placetype":"locality"
},
  "geometry": {"coordinates":[60.46666999999999,29.43333],"type":"Point"}
}