{
  "type": "Feature",
  "properties": {
    "gn:admin1_code":"29",
    "gn:asciiname":"Kamargan-e Sinu",
    "gn:country_code":"IR",
    "gn:dem":2374,
    "gn:feature_class":"P",
    "gn:feature_code":"PPL",
    "gn:name":"Kamarg\u0101n-e S\u012bn\u016b",
    "gn:population":0,
    "gn:timezone":"Asia/Tehran",
    "iso:country":"IR",
    "name:fas_x_preferred":[
        "Kamarg\u0101n-e S\u012bn\u016b"
    ],
    "wof:name":"Kamargan-e Sinu",
    "wof:placetype":"locality"
},
  "geometry": {"coordinates":[55.30222,30.26667],"type":"Point"}
}