{
  "type": "Feature",
  "properties": {
    "gn:admin1_code":"4.0",
    "gn:asciiname":"Hasanabad-e Minu'i",
    "gn:country_code":"IR",
    "gn:dem":1606,
    "gn:feature_class":"P",
    "gn:feature_code":"PPL",
    "gn:name":"\u1e28asan\u0101b\u0101d-e M\u012bn\u016b\u2019\u012b",
    "gn:population":0,
    "gn:timezone":"Asia/Tehran",
    "iso:country":"IR",
    "name:fas_x_preferred":[
        "\u062d\u0633\u0646 \u0622\u0628\u0627\u062f \u0645\u06cc\u0646\u0648\u0626\u06cc"
    ],
    "name:fas_x_variant":[
        "\u1e28asan\u0101b\u0101d-e M\u012bn\u016b\u2019\u012b"
    ],
    "wof:name":"Hasanabad-e Minu'i",
    "wof:placetype":"locality"
},
  "geometry": {"coordinates":[60.53202,28.82962],"type":"Point"}
}