{
  "type": "Feature",
  "properties": {
    "gn:admin1_code":"32",
    "gn:asciiname":"Qeshlaq-e Aqa Khan-e Karamat",
    "gn:country_code":"IR",
    "gn:dem":101,
    "gn:feature_class":"P",
    "gn:feature_code":"PPL",
    "gn:name":"Qeshl\u0101q-e \u0100q\u0101 Kh\u0101n-e Kar\u0101mat",
    "gn:population":0,
    "gn:timezone":"Asia/Tehran",
    "iso:country":"IR",
    "name:fas_x_preferred":[
        "\u0642\u0650\u0634\u0644\u0627\u0642\u0650 \u0622\u0642\u0627 \u062e\u0627\u0646\u0650 \u0643\u064e\u0631\u0627\u0645\u064e\u062a"
    ],
    "name:fas_x_variant":[
        "Qeshl\u0101q-e \u0100q\u0101 Kh\u0101n-e Kar\u0101mat"
    ],
    "wof:name":"Qeshlaq-e Aqa Khan-e Karamat",
    "wof:placetype":"locality"
},
  "geometry": {"coordinates":[48.16667,39.48333],"type":"Point"}
}