{
  "type": "Feature",
  "properties": {
    "gn:admin1_code":"4.0",
    "gn:asciiname":"Deh-e Nur Mohammad",
    "gn:country_code":"IR",
    "gn:dem":486,
    "gn:feature_class":"P",
    "gn:feature_code":"PPL",
    "gn:name":"Deh-e N\u016br Mo\u1e29ammad",
    "gn:population":0,
    "gn:timezone":"Asia/Tehran",
    "iso:country":"IR",
    "name:fas_x_preferred":[
        "\u062f\u0647 \u0646\u0648\u0631 \u0645\u062d\u0645\u062f"
    ],
    "name:fas_x_variant":[
        "Deh-e N\u016br Mo\u1e29ammad"
    ],
    "wof:name":"Deh-e Nur Mohammad",
    "wof:placetype":"locality"
},
  "geometry": {"coordinates":[61.6111,30.9905],"type":"Point"}
}