{
  "type": "Feature",
  "properties": {
    "gn:admin1_code":"1.0",
    "gn:asciiname":"Taleqan",
    "gn:country_code":"IR",
    "gn:dem":1288,
    "gn:feature_class":"P",
    "gn:feature_code":"PPL",
    "gn:name":"\u0162\u0101leq\u0101n",
    "gn:population":0,
    "gn:timezone":"Asia/Tehran",
    "iso:country":"IR",
    "name:ara_x_preferred":[
        "\u0637\u0627\u0644\u0642\u0627\u0646"
    ],
    "name:aze_x_preferred":[
        "Taliqan"
    ],
    "name:fas_x_preferred":[
        "\u0637\u0627\u0644\u0642\u0627\u0646"
    ],
    "name:fas_x_variant":[
        "\u0162\u0101leq\u0101n"
    ],
    "name:fra_x_preferred":[
        "Tal\u00e9ghan"
    ],
    "name:glk_x_preferred":[
        "\u062a\u0627\u0644\u06a9\u0627\u0646"
    ],
    "name:ita_x_preferred":[
        "Taleqan"
    ],
    "name:mlg_x_preferred":[
        "Taleqan"
    ],
    "name:msa_x_preferred":[
        "Taleqan"
    ],
    "name:pnb_x_preferred":[
        "\u0637\u0627\u0644\u0642\u0627\u0646"
    ],
    "name:pol_x_preferred":[
        "Taleghan"
    ],
    "name:rus_x_preferred":[
        "\u0422\u0430\u043b\u0435\u043a\u0430\u043d"
    ],
    "name:tur_x_preferred":[
        "Taligan"
    ],
    "name:urd_x_preferred":[
        "\u0637\u0627\u0644\u0642\u0627\u0646"
    ],
    "wof:name":"Taleqan",
    "wof:placetype":"locality"
},
  "geometry": {"coordinates":[45.4383,36.9962],"type":"Point"}
}