{
  "type": "Feature",
  "properties": {
    "gn:admin1_code":"37.0",
    "gn:asciiname":"Shahrak-e Jomhuri-ye Eslami",
    "gn:country_code":"IR",
    "gn:dem":128,
    "gn:feature_class":"P",
    "gn:feature_code":"PPL",
    "gn:name":"Shahrak-e Jomh\u016br\u012b-ye Esl\u0101m\u012b",
    "gn:population":0,
    "gn:timezone":"Asia/Tehran",
    "iso:country":"IR",
    "name:fas_x_preferred":[
        "\u0634\u0647\u0631\u06a9 \u062c\u0645\u0647\u0648\u0631\u06cc \u0627\u0633\u0644\u0627\u0645\u06cc"
    ],
    "name:und_x_variant":[
        "Shahrak-e Jomh\u016br\u012b-ye Esl\u0101m\u012b"
    ],
    "wof:name":"Shahrak-e Jomhuri-ye Eslami",
    "wof:placetype":"locality"
},
  "geometry": {"coordinates":[55.45871999999999,37.39203],"type":"Point"}
}