{
  "type": "Feature",
  "properties": {
    "gn:admin1_code":"16.0",
    "gn:asciiname":"Hoseynabad-e Zelleh Jub",
    "gn:country_code":"IR",
    "gn:dem":1881,
    "gn:feature_class":"P",
    "gn:feature_code":"PPL",
    "gn:name":"\u1e28oseyn\u0101b\u0101d-e Z\u0327elleh J\u016bb",
    "gn:population":0,
    "gn:timezone":"Asia/Tehran",
    "iso:country":"IR",
    "name:ceb_x_preferred":[
        "\u1e28oseyn\u0101b\u0101d-e Z\u0327elleh J\u016bb"
    ],
    "name:fas_x_preferred":[
        "\u062d\u064f\u0633\u0650\u064a\u0646\u0627\u0628\u0627\u062f\u0650 \u0632\u0650\u0644\u0650\u0647 \u062c\u0648"
    ],
    "name:fas_x_variant":[
        "\u062d\u064f\u0633\u0650\u064a\u0646\u0627\u0628\u0627\u062f\u0650 \u0632\u0650\u0644\u0650\u0647 \u062c\u0648\u0628",
        "\u062d\u0633\u06cc\u0646 \u0622\u0628\u0627\u062f \u0638\u0644\u0647 \u062c\u0648\u0628",
        "\u1e28oseyn\u0101b\u0101d-e Zeleh J\u016b",
        "\u1e28oseyn\u0101b\u0101d-e Z\u0327elleh J\u016bb",
        "\u062d\u0633\u06cc\u0646\u200c\u0622\u0628\u0627\u062f \u0638\u0644\u0647 \u062c\u0648\u0628"
    ],
    "name:swe_x_preferred":[
        "\u1e28oseyn\u0101b\u0101d-e Z\u0327elleh J\u016bb"
    ],
    "name:und_x_variant":[
        "\u1e28oseyn\u0101b\u0101d-e Zeleh J\u016bb"
    ],
    "wof:name":"Hoseynabad-e Zelleh Jub",
    "wof:placetype":"locality"
},
  "geometry": {"coordinates":[47.91255,35.05874],"type":"Point"}
}