{
  "type": "Feature",
  "properties": {
    "gn:admin1_code":"11",
    "gn:asciiname":"Chah Fa`leh-ye Sharqi",
    "gn:country_code":"IR",
    "gn:dem":19,
    "gn:feature_class":"P",
    "gn:feature_code":"PPL",
    "gn:name":"Ch\u0101h Fa\u2018leh-ye Sharq\u012b",
    "gn:population":0,
    "gn:timezone":"Asia/Tehran",
    "iso:country":"IR",
    "name:fas_x_preferred":[
        "\u0686\u0627\u0647 \u0641\u064e\u0639\u0644\u0650\u0647"
    ],
    "name:fas_x_variant":[
        "\u0686\u0627\u0647 \u0642\u064e\u0644\u0639\u0650\u0647",
        "\u0686\u0627\u0647 \u0641\u0639\u0644\u0647 \u0634\u0631\u0642\u06cc",
        "Ch\u0101h Fa\u2018leh",
        "Ch\u0101h Fa\u2018leh-ye Sharq\u012b"
    ],
    "name:und_x_variant":[
        "Ch\u0101h Qal\u2018eh"
    ],
    "wof:name":"Chah Fa`leh-ye Sharqi",
    "wof:placetype":"locality"
},
  "geometry": {"coordinates":[56.64125,27.36069],"type":"Point"}
}