{
  "type": "Feature",
  "properties": {
    "gn:admin1_code":"29",
    "gn:asciiname":"Maskun",
    "gn:country_code":"IR",
    "gn:dem":2113,
    "gn:feature_class":"P",
    "gn:feature_code":"PPL",
    "gn:name":"Mask\u016bn",
    "gn:population":0,
    "gn:timezone":"Asia/Tehran",
    "iso:country":"IR",
    "name:fas_x_preferred":[
        "\u0645\u0633\u06a9\u0648\u0646"
    ],
    "name:fas_x_variant":[
        "Mask\u016bn"
    ],
    "wof:name":"Maskun",
    "wof:placetype":"locality"
},
  "geometry": {"coordinates":[57.893,28.9475],"type":"Point"}
}