{
  "type": "Feature",
  "properties": {
    "gn:admin1_code":"33",
    "gn:asciiname":"Haft Cheshmeh",
    "gn:country_code":"IR",
    "gn:dem":2033,
    "gn:feature_class":"P",
    "gn:feature_code":"PPL",
    "gn:name":"Haft Cheshmeh",
    "gn:population":0,
    "gn:timezone":"Asia/Tehran",
    "iso:country":"IR",
    "name:azb_x_preferred":[
        "\u0647\u0641\u062a \u0686\u0634\u0645\u0647(\u0628\u0647\u0628\u0647\u0627\u0646)"
    ],
    "name:ceb_x_preferred":[
        "Haft Cheshmeh"
    ],
    "name:fas_x_preferred":[
        "\u0647\u0641\u062a \u0686\u0634\u0645\u0647"
    ],
    "name:fas_x_variant":[
        "\u0647\u0641\u062a\u200c\u0686\u0634\u0645\u0647"
    ],
    "name:swe_x_preferred":[
        "Haft Cheshmeh"
    ],
    "name:und_x_variant":[
        "Kafta-Chashme",
        "Hafta Chashmeh",
        "Haft Cheshmeh"
    ],
    "wof:name":"Haft Cheshmeh",
    "wof:placetype":"locality"
},
  "geometry": {"coordinates":[48.06293,37.73908],"type":"Point"}
}