{
  "type": "Feature",
  "properties": {
    "gn:admin1_code":"42",
    "gn:asciiname":"Miandehi",
    "gn:country_code":"IR",
    "gn:dem":1816,
    "gn:feature_class":"P",
    "gn:feature_code":"PPL",
    "gn:name":"M\u012b\u0101ndeh\u012b",
    "gn:population":0,
    "gn:timezone":"Asia/Tehran",
    "iso:country":"IR",
    "name:fas_x_preferred":[
        "\u0645\u06cc\u0627\u0646\u062f\u0647\u06cc"
    ],
    "name:fas_x_variant":[
        "M\u012b\u0101ndeh\u012b"
    ],
    "wof:name":"Miandehi",
    "wof:placetype":"locality"
},
  "geometry": {"coordinates":[59.5356,35.56348],"type":"Point"}
}