{
  "type": "Feature",
  "properties": {
    "gn:admin1_code":"23.0",
    "gn:asciiname":"Amirabad",
    "gn:country_code":"IR",
    "gn:dem":1307,
    "gn:feature_class":"P",
    "gn:feature_code":"PPL",
    "gn:name":"Am\u012br\u0101b\u0101d",
    "gn:population":0,
    "gn:timezone":"Asia/Tehran",
    "iso:country":"IR",
    "name:ara_x_preferred":[
        "\u0623\u0645\u064a\u0631 \u0623\u0628\u0627\u062f"
    ],
    "name:aze_x_preferred":[
        "\u018fmirabad"
    ],
    "name:ceb_x_preferred":[
        "Amirabad"
    ],
    "name:fas_x_preferred":[
        "\u0627\u064e\u0645\u064a\u0631\u0627\u0628\u0627\u062f\u0650 \u06af\u0648\u0631\u0643\u064e\u0634"
    ],
    "name:fas_x_variant":[
        "\u0627\u0645\u064a\u0631 \u0622\u0628\u0627\u062f",
        "Am\u012br\u0101b\u0101d-e G\u016brkash",
        "Am\u012br\u0101b\u0101d",
        "\u0627\u0645\u06cc\u0631\u0622\u0628\u0627\u062f"
    ],
    "name:mzn_x_preferred":[
        "\u0627\u0645\u06cc\u0631\u0622\u0628\u0627\u062f"
    ],
    "name:swe_x_preferred":[
        "Amirabad"
    ],
    "wof:name":"Amirabad",
    "wof:placetype":"locality"
},
  "geometry": {"coordinates":[48.9629,33.3816],"type":"Point"}
}