{
  "type": "Feature",
  "properties": {
    "gn:admin1_code":"4.0",
    "gn:asciiname":"Tolombeh-ye Zurabad",
    "gn:country_code":"IR",
    "gn:dem":1619,
    "gn:feature_class":"P",
    "gn:feature_code":"PPL",
    "gn:name":"Tolombeh-ye Z\u016br\u0101b\u0101d",
    "gn:population":0,
    "gn:timezone":"Asia/Tehran",
    "iso:country":"IR",
    "name:fas_x_preferred":[
        "Tolombeh-ye Z\u016br\u0101b\u0101d"
    ],
    "wof:name":"Tolombeh-ye Zurabad",
    "wof:placetype":"locality"
},
  "geometry": {"coordinates":[60.53111,28.79917],"type":"Point"}
}