{
  "type": "Feature",
  "properties": {
    "gn:admin1_code":"29",
    "gn:asciiname":"Kalatak",
    "gn:country_code":"IR",
    "gn:dem":436,
    "gn:feature_class":"P",
    "gn:feature_code":"PPL",
    "gn:name":"Kal\u0101tak",
    "gn:population":0,
    "gn:timezone":"Asia/Tehran",
    "iso:country":"IR",
    "name:fas_x_preferred":[
        "\u06a9\u0644\u0627\u062a\u06a9"
    ],
    "name:fas_x_variant":[
        "Kal\u0101tak"
    ],
    "wof:name":"Kalatak",
    "wof:placetype":"locality"
},
  "geometry": {"coordinates":[57.9891,27.8052],"type":"Point"}
}