{
  "type": "Feature",
  "properties": {
    "gn:admin1_code":"35.0",
    "gn:asciiname":"Sirgah",
    "gn:country_code":"IR",
    "gn:dem":1191,
    "gn:feature_class":"P",
    "gn:feature_code":"PPL",
    "gn:name":"S\u012brg\u0101h",
    "gn:population":0,
    "gn:timezone":"Asia/Tehran",
    "iso:country":"IR",
    "name:fas_x_preferred":[
        "\u0628\u064a\u0631\u06af\u0627\u0647"
    ],
    "name:fas_x_variant":[
        "Sh\u012brg\u0101h",
        "B\u012brg\u0101h",
        "\u0634\u06cc\u0631\u06af\u0627\u0647",
        "\u0633\u06cc\u0631\u06af\u0627\u0647"
    ],
    "name:und_x_variant":[
        "\u0634\u06cc\u0631\u06af\u0627\u0647",
        "S\u012brg\u0101h"
    ],
    "wof:name":"Sirgah",
    "wof:placetype":"locality"
},
  "geometry": {"coordinates":[51.25308,36.47533],"type":"Point"}
}