{
  "type": "Feature",
  "properties": {
    "gn:admin1_code":"7",
    "gn:asciiname":"Kuh-e Kolbeh",
    "gn:country_code":"IR",
    "gn:dem":2532,
    "gn:feature_class":"P",
    "gn:feature_code":"PPL",
    "gn:name":"K\u016bh-e Kolbeh",
    "gn:population":0,
    "gn:timezone":"Asia/Tehran",
    "iso:country":"IR",
    "name:fas_x_preferred":[
        "K\u016bh-e Kolbeh"
    ],
    "wof:name":"Kuh-e Kolbeh",
    "wof:placetype":"locality"
},
  "geometry": {"coordinates":[52.13889,30.21028],"type":"Point"}
}