{
  "type": "Feature",
  "properties": {
    "gn:admin1_code":"42.0",
    "gn:asciiname":"Cheshmeh Anjir",
    "gn:country_code":"IR",
    "gn:dem":825,
    "gn:feature_class":"P",
    "gn:feature_code":"PPL",
    "gn:name":"Cheshmeh Anj\u012br",
    "gn:population":0,
    "gn:timezone":"Asia/Tehran",
    "iso:country":"IR",
    "name:fas_x_preferred":[
        "\u0686\u0634\u0645\u0647 \u0627\u0646\u062c\u06cc\u0631"
    ],
    "name:fas_x_variant":[
        "Anj\u012br",
        "Cheshmeh Anj\u012br"
    ],
    "wof:name":"Cheshmeh Anjir",
    "wof:placetype":"locality"
},
  "geometry": {"coordinates":[61.1328,35.49165],"type":"Point"}
}