{
  "type": "Feature",
  "properties": {
    "gn:admin1_code":"4.0",
    "gn:asciiname":"Chut",
    "gn:country_code":"IR",
    "gn:dem":34,
    "gn:feature_class":"P",
    "gn:feature_code":"PPL",
    "gn:name":"Ch\u016bt",
    "gn:population":0,
    "gn:timezone":"Asia/Tehran",
    "iso:country":"IR",
    "name:fas_x_preferred":[
        "\u0686\u0648\u062a"
    ],
    "name:fas_x_variant":[
        "\u0686\u064f\u062a",
        "\u0634\u064f\u062a",
        "Ch\u016bt"
    ],
    "name:fra_x_preferred":[
        "Chut"
    ],
    "name:rus_x_preferred":[
        "\u0422\u044c\u044b\u0442"
    ],
    "name:und_x_variant":[
        "Shot",
        "Chot"
    ],
    "wof:name":"Chut",
    "wof:placetype":"locality"
},
  "geometry": {"coordinates":[61.38333000000001,25.66667],"type":"Point"}
}