{
  "type": "Feature",
  "properties": {
    "gn:admin1_code":"33",
    "gn:asciiname":"Siah Kalan",
    "gn:country_code":"IR",
    "gn:dem":2016,
    "gn:feature_class":"P",
    "gn:feature_code":"PPL",
    "gn:name":"S\u012bah Kal\u0101n",
    "gn:population":0,
    "gn:timezone":"Asia/Tehran",
    "iso:country":"IR",
    "name:fas_x_preferred":[
        "\u0633\u06cc\u0647 \u06a9\u0644\u0627\u0646"
    ],
    "name:fas_x_variant":[
        "S\u012b\u0101h Kal\u0101n",
        "S\u012bah Kal\u0101n"
    ],
    "name:und_x_variant":[
        "Siakh-Kulan",
        "Siahkuli\u0101n",
        "Siyah Kalan",
        "S\u012b\u0101h K\u016bly\u0101n"
    ],
    "wof:name":"Siah Kalan",
    "wof:placetype":"locality"
},
  "geometry": {"coordinates":[46.7407,38.613],"type":"Point"}
}