{
  "type": "Feature",
  "properties": {
    "gn:admin1_code":"15",
    "gn:asciiname":"Kala Par Siah",
    "gn:country_code":"IR",
    "gn:dem":717,
    "gn:feature_class":"P",
    "gn:feature_code":"PPL",
    "gn:name":"Kal\u0101 Par S\u012b\u0101h",
    "gn:population":0,
    "gn:timezone":"Asia/Tehran",
    "iso:country":"IR",
    "name:fas_x_preferred":[
        "Kal\u0101 Par S\u012b\u0101h"
    ],
    "name:fas_x_variant":[
        "\u06a9\u0644\u0627 \u067e\u0631 \u0633\u06cc\u0627\u0647"
    ],
    "wof:name":"Kala Par Siah",
    "wof:placetype":"locality"
},
  "geometry": {"coordinates":[49.67836,31.88256],"type":"Point"}
}