{
  "type": "Feature",
  "properties": {
    "gn:admin1_code":"5",
    "gn:asciiname":"Pir Sabz",
    "gn:country_code":"IR",
    "gn:dem":1248,
    "gn:feature_class":"P",
    "gn:feature_code":"PPL",
    "gn:name":"P\u012br Sabz",
    "gn:population":0,
    "gn:timezone":"Asia/Tehran",
    "iso:country":"IR",
    "name:fas_x_preferred":[
        "\u067e\u064a\u0631 \u0633\u0628\u0632"
    ],
    "name:fas_x_variant":[
        "P\u012br Sabz"
    ],
    "wof:name":"Pir Sabz",
    "wof:placetype":"locality"
},
  "geometry": {"coordinates":[50.9345,30.3819],"type":"Point"}
}