{
  "type": "Feature",
  "properties": {
    "gn:admin1_code":"33.0",
    "gn:asciiname":"Larijan-e Bala",
    "gn:country_code":"IR",
    "gn:dem":411,
    "gn:feature_class":"P",
    "gn:feature_code":"PPL",
    "gn:name":"L\u0101r\u012bj\u0101n-e B\u0101l\u0101",
    "gn:population":0,
    "gn:timezone":"Asia/Tehran",
    "iso:country":"IR",
    "name:fas_x_preferred":[
        "\u0644\u0627\u0631\u06cc\u062c\u0627\u0646 \u0628\u0627\u0644\u0627"
    ],
    "name:fas_x_variant":[
        "L\u0101r\u012bj\u0101n-e \u2018Oly\u0101",
        "L\u0101r\u012bj\u0101n-e B\u0101l\u0101"
    ],
    "wof:name":"Larijan-e Bala",
    "wof:placetype":"locality"
},
  "geometry": {"coordinates":[47.01600000000001,39.14],"type":"Point"}
}