{
  "type": "Feature",
  "properties": {
    "gn:admin1_code":"23",
    "gn:asciiname":"Zaran Cham Garmurt",
    "gn:country_code":"IR",
    "gn:dem":1083,
    "gn:feature_class":"P",
    "gn:feature_code":"PPL",
    "gn:name":"Z\u0101r\u0101n Cham Garm\u016brt",
    "gn:population":0,
    "gn:timezone":"Asia/Tehran",
    "iso:country":"IR",
    "name:fas_x_preferred":[
        "\u0632\u0631\u0648\u0627\u0646 \u0686\u0645"
    ],
    "name:fas_x_variant":[
        "Z\u016br\u0101ncham",
        "Zarav\u0101n Cham",
        "\u0632\u0627\u0631\u0627\u0646 \u0686\u0645 \u06af\u0631\u0645\u0648\u0631\u062a"
    ],
    "name:und_x_variant":[
        "Z\u0101r\u0101n Cham Garm\u016brt"
    ],
    "wof:name":"Zaran Cham Garmurt",
    "wof:placetype":"locality"
},
  "geometry": {"coordinates":[47.8206,33.6838],"type":"Point"}
}