{
  "type": "Feature",
  "properties": {
    "gn:admin1_code":"7",
    "gn:asciiname":"Tang-e Zard",
    "gn:country_code":"IR",
    "gn:dem":1370,
    "gn:feature_class":"P",
    "gn:feature_code":"PPL",
    "gn:name":"Tang-e Zard",
    "gn:population":0,
    "gn:timezone":"Asia/Tehran",
    "iso:country":"IR",
    "name:fas_x_preferred":[
        "\u062a\u0646\u06af \u0632\u0631\u062f"
    ],
    "name:msa_x_preferred":[
        "Tang-e Zard"
    ],
    "wof:name":"Tang-e Zard",
    "wof:placetype":"locality"
},
  "geometry": {"coordinates":[51.90825,29.53756],"type":"Point"}
}