{
  "type": "Feature",
  "properties": {
    "gn:admin1_code":"40.0",
    "gn:asciiname":"Bagh-e-Khan",
    "gn:country_code":"IR",
    "gn:dem":1302,
    "gn:feature_class":"P",
    "gn:feature_code":"PPL",
    "gn:name":"B\u0101gh-e-Kh\u0101n",
    "gn:population":0,
    "gn:timezone":"Asia/Tehran",
    "iso:country":"IR",
    "wof:name":"Bagh-e-Khan",
    "wof:placetype":"locality"
},
  "geometry": {"coordinates":[54.29444,31.84028],"type":"Point"}
}