{
  "type": "Feature",
  "properties": {
    "gn:admin1_code":"4.0",
    "gn:asciiname":"`Abdollahabad",
    "gn:country_code":"IR",
    "gn:dem":2010,
    "gn:feature_class":"P",
    "gn:feature_code":"PPL",
    "gn:name":"\u2018Abdoll\u0101h\u0101b\u0101d",
    "gn:population":0,
    "gn:timezone":"Asia/Tehran",
    "iso:country":"IR",
    "name:fas_x_preferred":[
        "\u2018Abdoll\u0101h\u0101b\u0101d"
    ],
    "wof:name":"`Abdollahabad",
    "wof:placetype":"locality"
},
  "geometry": {"coordinates":[60.52916999999999,29.34944],"type":"Point"}
}