{
  "type": "Feature",
  "properties": {
    "gn:admin1_code":"42",
    "gn:asciiname":"Dastgerdan",
    "gn:country_code":"IR",
    "gn:dem":941,
    "gn:feature_class":"P",
    "gn:feature_code":"PPL",
    "gn:name":"Dastgerd\u0101n",
    "gn:population":0,
    "gn:timezone":"Asia/Tehran",
    "iso:country":"IR",
    "name:fas_x_preferred":[
        "\u062f\u0633\u062a\u06af\u0631\u062f\u0627\u0646"
    ],
    "name:fas_x_variant":[
        "Dastgerd\u0101n"
    ],
    "wof:name":"Dastgerdan",
    "wof:placetype":"locality"
},
  "geometry": {"coordinates":[59.7448,36.2569],"type":"Point"}
}