{
  "type": "Feature",
  "properties": {
    "gn:admin1_code":"13",
    "gn:asciiname":"Gav Bandeh",
    "gn:country_code":"IR",
    "gn:dem":1307,
    "gn:feature_class":"P",
    "gn:feature_code":"PPL",
    "gn:name":"G\u0101v Bandeh",
    "gn:population":0,
    "gn:timezone":"Asia/Tehran",
    "iso:country":"IR",
    "name:fas_x_preferred":[
        "\u06af\u0627\u0648\u0628\u0646\u062f\u0647"
    ],
    "name:fas_x_variant":[
        "G\u0101v Bandeh"
    ],
    "name:und_x_variant":[
        "G\u0101w\u0101na",
        "G\u0101v\u0101neh",
        "G\u0101vbandel"
    ],
    "wof:name":"Gav Bandeh",
    "wof:placetype":"locality"
},
  "geometry": {"coordinates":[47.0604,34.4002],"type":"Point"}
}