{
  "type": "Feature",
  "properties": {
    "gn:admin1_code":"38.0",
    "gn:asciiname":"Alulak",
    "gn:country_code":"IR",
    "gn:dem":1793,
    "gn:feature_class":"P",
    "gn:feature_code":"PPL",
    "gn:name":"\u0100l\u016blak",
    "gn:population":0,
    "gn:timezone":"Asia/Tehran",
    "iso:country":"IR",
    "name:fas_x_preferred":[
        "\u0622\u0644\u0648\u0644\u0643"
    ],
    "name:fas_x_variant":[
        "\u0100l\u016blak"
    ],
    "wof:name":"Alulak",
    "wof:placetype":"locality"
},
  "geometry": {"coordinates":[50.028,36.4196],"type":"Point"}
}