{
  "type": "Feature",
  "properties": {
    "gn:admin1_code":"8",
    "gn:asciiname":"Lavandevil",
    "gn:country_code":"IR",
    "gn:dem":-18,
    "gn:feature_class":"P",
    "gn:feature_code":"PPL",
    "gn:name":"Lavandev\u012bl",
    "gn:population":0,
    "gn:timezone":"Asia/Tehran",
    "iso:country":"IR",
    "name:fas_x_preferred":[
        "\u0644\u0648\u0646\u062f\u0648\u06cc\u0644"
    ],
    "name:fas_x_variant":[
        "Lavandev\u012bl"
    ],
    "name:und_x_variant":[
        "B\u0101zar-e Lavandv\u012bl",
        "Lavandv\u012bl",
        "Landv\u012bl-e Sabal\u012b",
        "Lavandavil",
        "Lavandv\u012bl-e Sabal\u012b"
    ],
    "wof:name":"Lavandevil",
    "wof:placetype":"locality"
},
  "geometry": {"coordinates":[48.8707,38.3088],"type":"Point"}
}