{
  "type": "Feature",
  "properties": {
    "gn:admin1_code":"1.0",
    "gn:asciiname":"Hamran",
    "gn:country_code":"IR",
    "gn:dem":1186,
    "gn:feature_class":"P",
    "gn:feature_code":"PPL",
    "gn:name":"Hamr\u0101n",
    "gn:population":0,
    "gn:timezone":"Asia/Tehran",
    "iso:country":"IR",
    "name:azb_x_preferred":[
        "\u0647\u0645\u0631\u0627\u0646"
    ],
    "name:ceb_x_preferred":[
        "Hamr\u0101n"
    ],
    "name:ckb_x_preferred":[
        "\u06be\u06d5\u0645\u0631\u0627\u0646"
    ],
    "name:fas_x_preferred":[
        "\u0647\u0645\u0631\u0627\u0646"
    ],
    "name:fas_x_variant":[
        "Hamr\u0101n"
    ],
    "name:kur_x_preferred":[
        "Hemran"
    ],
    "name:msa_x_preferred":[
        "Hamran"
    ],
    "name:swe_x_preferred":[
        "Hamr\u0101n"
    ],
    "wof:name":"Hamran",
    "wof:placetype":"locality"
},
  "geometry": {"coordinates":[45.5555,36.2428],"type":"Point"}
}