{
  "type": "Feature",
  "properties": {
    "gn:admin1_code":"4.0",
    "gn:asciiname":"Gas Mazur",
    "gn:country_code":"IR",
    "gn:dem":1310,
    "gn:feature_class":"P",
    "gn:feature_code":"PPL",
    "gn:name":"Gas Maz\u016br",
    "gn:population":0,
    "gn:timezone":"Asia/Tehran",
    "iso:country":"IR",
    "name:fas_x_preferred":[
        "Gas Maz\u016br"
    ],
    "wof:name":"Gas Mazur",
    "wof:placetype":"locality"
},
  "geometry": {"coordinates":[60.52639,26.57222],"type":"Point"}
}