{
  "type": "Feature",
  "properties": {
    "gn:admin1_code":"11",
    "gn:asciiname":"Moharramabad",
    "gn:country_code":"IR",
    "gn:dem":873,
    "gn:feature_class":"P",
    "gn:feature_code":"PPL",
    "gn:name":"Mo\u1e29arram\u0101b\u0101d",
    "gn:population":0,
    "gn:timezone":"Asia/Tehran",
    "iso:country":"IR",
    "name:ceb_x_preferred":[
        "Mo\u1e29arram\u0101b\u0101d"
    ],
    "name:fas_x_preferred":[
        "\u0645\u062d\u0631\u0645 \u0622\u0628\u0627\u062f"
    ],
    "name:fas_x_variant":[
        "Shaqr\u016bd",
        "\u0634\u0642\u0631\u0648\u062f",
        "Mo\u1e29arram\u0101b\u0101d",
        "\u0645\u062d\u0631\u0645\u200c\u0622\u0628\u0627\u062f"
    ],
    "name:pol_x_preferred":[
        "Moharramabad"
    ],
    "name:swe_x_preferred":[
        "Mo\u1e29arram\u0101b\u0101d"
    ],
    "wof:name":"Moharramabad",
    "wof:placetype":"locality"
},
  "geometry": {"coordinates":[56.8003,27.8971],"type":"Point"}
}