{
  "type": "Feature",
  "properties": {
    "gn:admin1_code":"11.0",
    "gn:asciiname":"Darreh Hajji",
    "gn:country_code":"IR",
    "gn:dem":207,
    "gn:feature_class":"P",
    "gn:feature_code":"PPL",
    "gn:name":"Darreh \u1e28\u0101jj\u012b",
    "gn:population":0,
    "gn:timezone":"Asia/Tehran",
    "iso:country":"IR",
    "name:ceb_x_preferred":[
        "Darreh \u1e28\u0101jj\u012b"
    ],
    "name:fas_x_preferred":[
        "\u062f\u0631\u0647 \u062d\u0627\u062c\u06cc"
    ],
    "name:fas_x_variant":[
        "Darreh \u1e28\u0101jj\u012b"
    ],
    "name:msa_x_preferred":[
        "Darreh Hajji"
    ],
    "name:swe_x_preferred":[
        "Darreh \u1e28\u0101jj\u012b"
    ],
    "wof:name":"Darreh Hajji",
    "wof:placetype":"locality"
},
  "geometry": {"coordinates":[57.33447,27.20939000000001],"type":"Point"}
}