{
  "type": "Feature",
  "properties": {
    "gn:admin1_code":"15",
    "gn:asciiname":"Chulaki",
    "gn:country_code":"IR",
    "gn:dem":1094,
    "gn:feature_class":"P",
    "gn:feature_code":"PPL",
    "gn:name":"Ch\u016blak\u012b",
    "gn:population":0,
    "gn:timezone":"Asia/Tehran",
    "iso:country":"IR",
    "name:fas_x_preferred":[
        "Ch\u016blak\u012b"
    ],
    "name:vie_x_preferred":[
        "Chulaki"
    ],
    "wof:name":"Chulaki",
    "wof:placetype":"locality"
},
  "geometry": {"coordinates":[50.01194,31.85222000000001],"type":"Point"}
}