{
  "type": "Feature",
  "properties": {
    "gn:admin1_code":"33.0",
    "gn:asciiname":"Abkhvareh",
    "gn:country_code":"IR",
    "gn:dem":1755,
    "gn:feature_class":"P",
    "gn:feature_code":"PPL",
    "gn:name":"\u0100bkhv\u0101reh",
    "gn:population":0,
    "gn:timezone":"Asia/Tehran",
    "iso:country":"IR",
    "name:fas_x_preferred":[
        "\u0622\u0628\u062e\u0648\u0627\u0631\u0647"
    ],
    "name:fas_x_variant":[
        "\u0100b Khv\u0101reh",
        "\u0100bkhv\u0101reh"
    ],
    "name:und_x_variant":[
        "Avkh\u0101reh",
        "Abkh\u0101ra",
        "Avkhara",
        "\u0100bkh\u0101reh"
    ],
    "wof:name":"Abkhvareh",
    "wof:placetype":"locality"
},
  "geometry": {"coordinates":[46.5288,38.5147],"type":"Point"}
}