{
  "type": "Feature",
  "properties": {
    "gn:admin1_code":"5",
    "gn:asciiname":"Bajereh",
    "gn:country_code":"IR",
    "gn:dem":1292,
    "gn:feature_class":"P",
    "gn:feature_code":"PPL",
    "gn:name":"B\u0101jereh",
    "gn:population":0,
    "gn:timezone":"Asia/Tehran",
    "iso:country":"IR",
    "name:ara_x_preferred":[
        "\u0628\u0627\u062c\u0631\u0629"
    ],
    "name:ceb_x_preferred":[
        "B\u0101jereh"
    ],
    "name:fas_x_preferred":[
        "B\u0101jereh"
    ],
    "name:fas_x_variant":[
        "\u0628\u0627\u062c\u0631\u0647"
    ],
    "name:swe_x_preferred":[
        "B\u0101jereh"
    ],
    "name:und_x_variant":[
        "\u0628\u0627\u062c\u0631\u0647"
    ],
    "wof:name":"Bajereh",
    "wof:placetype":"locality"
},
  "geometry": {"coordinates":[50.13788,31.13154],"type":"Point"}
}