{
  "type": "Feature",
  "properties": {
    "gn:admin1_code":"15",
    "gn:asciiname":"Bard Zard",
    "gn:country_code":"IR",
    "gn:dem":837,
    "gn:feature_class":"P",
    "gn:feature_code":"PPL",
    "gn:name":"Bard Zard",
    "gn:population":0,
    "gn:timezone":"Asia/Tehran",
    "iso:country":"IR",
    "name:fas_x_preferred":[
        "\u0628\u0631\u062f \u0632\u0631\u062f"
    ],
    "wof:name":"Bard Zard",
    "wof:placetype":"locality"
},
  "geometry": {"coordinates":[49.93579,31.99503],"type":"Point"}
}