{
  "type": "Feature",
  "properties": {
    "gn:admin1_code":"43",
    "gn:asciiname":"Darparchin-e Bala",
    "gn:country_code":"IR",
    "gn:dem":1943,
    "gn:feature_class":"P",
    "gn:feature_code":"PPL",
    "gn:name":"Darparch\u012bn-e B\u0101l\u0101",
    "gn:population":0,
    "gn:timezone":"Asia/Tehran",
    "iso:country":"IR",
    "name:fas_x_preferred":[
        "Darparch\u012bn-e B\u0101l\u0101"
    ],
    "wof:name":"Darparchin-e Bala",
    "wof:placetype":"locality"
},
  "geometry": {"coordinates":[57.85,37.15],"type":"Point"}
}