{
  "type": "Feature",
  "properties": {
    "gn:admin1_code":"35.0",
    "gn:asciiname":"Bulideh",
    "gn:country_code":"IR",
    "gn:dem":18,
    "gn:feature_class":"P",
    "gn:feature_code":"PPL",
    "gn:name":"B\u016bl\u012bdeh",
    "gn:population":0,
    "gn:timezone":"Asia/Tehran",
    "iso:country":"IR",
    "name:fas_x_preferred":[
        "\u0628\u0648\u0644\u064a\u062f\u0647"
    ],
    "name:fas_x_variant":[
        "B\u016bl\u012bdeh"
    ],
    "wof:name":"Bulideh",
    "wof:placetype":"locality"
},
  "geometry": {"coordinates":[52.30687,36.5282],"type":"Point"}
}