{
  "type": "Feature",
  "properties": {
    "gn:admin1_code":"41",
    "gn:asciiname":"Ravash",
    "gn:country_code":"IR",
    "gn:dem":1499,
    "gn:feature_class":"P",
    "gn:feature_code":"PPL",
    "gn:name":"R\u0101vash",
    "gn:population":0,
    "gn:timezone":"Asia/Tehran",
    "iso:country":"IR",
    "name:fas_x_preferred":[
        "\u0631\u0627\u0648\u064e\u0634"
    ],
    "name:fas_x_variant":[
        "R\u0101vash"
    ],
    "name:und_x_variant":[
        "Raw\u0101sh"
    ],
    "wof:name":"Ravash",
    "wof:placetype":"locality"
},
  "geometry": {"coordinates":[59.08333,33.31667],"type":"Point"}
}