{
  "type": "Feature",
  "properties": {
    "gn:admin1_code":"8.0",
    "gn:asciiname":"Jur Lashkaj",
    "gn:country_code":"IR",
    "gn:dem":642,
    "gn:feature_class":"P",
    "gn:feature_code":"PPL",
    "gn:name":"J\u016br Lashkaj",
    "gn:population":0,
    "gn:timezone":"Asia/Tehran",
    "iso:country":"IR",
    "name:fas_x_preferred":[
        "\u0644\u0634 \u06a9\u062c"
    ],
    "name:fas_x_variant":[
        "\u062c\u0648\u0631 \u0644\u0634\u06a9\u062c"
    ],
    "name:und_x_variant":[
        "Lash Kaj",
        "J\u016br Lashkaj"
    ],
    "wof:name":"Jur Lashkaj",
    "wof:placetype":"locality"
},
  "geometry": {"coordinates":[49.95228,37.02284],"type":"Point"}
}