{
  "type": "Feature",
  "properties": {
    "gn:admin1_code":"8",
    "gn:asciiname":"Khorram Rud",
    "gn:country_code":"IR",
    "gn:dem":1384,
    "gn:feature_class":"P",
    "gn:feature_code":"PPL",
    "gn:name":"Khorram R\u016bd",
    "gn:population":0,
    "gn:timezone":"Asia/Tehran",
    "iso:country":"IR",
    "name:ceb_x_preferred":[
        "Khorram R\u016bd"
    ],
    "name:fas_x_preferred":[
        "Khorram R\u016bd"
    ],
    "name:fas_x_variant":[
        "\u062e\u0631\u0645 \u0631\u0648\u062f",
        "\u062e\u0631\u0645\u200c\u0631\u0648\u062f"
    ],
    "name:msa_x_preferred":[
        "Khorram Rud"
    ],
    "name:swe_x_preferred":[
        "Khorram R\u016bd"
    ],
    "name:ukr_x_preferred":[
        "\u0425\u043e\u0440\u0430\u043c-\u0420\u0443\u0434"
    ],
    "name:und_x_variant":[
        "Khorm\u0101r\u016bd",
        "Khurmahr\u016bd",
        "Khurumrud"
    ],
    "wof:name":"Khorram Rud",
    "wof:placetype":"locality"
},
  "geometry": {"coordinates":[49.94734,36.87616],"type":"Point"}
}