{
  "type": "Feature",
  "properties": {
    "gn:admin1_code":"32.0",
    "gn:asciiname":"Arallu-ye Kuchek",
    "gn:country_code":"IR",
    "gn:dem":1401,
    "gn:feature_class":"P",
    "gn:feature_code":"PPL",
    "gn:name":"\u0100r\u0101ll\u016b-ye K\u016bchek",
    "gn:population":0,
    "gn:timezone":"Asia/Tehran",
    "iso:country":"IR",
    "name:fas_x_preferred":[
        "\u0622\u0631\u0627\u0644\u0644\u0648\u06cc \u0643\u0648\u0686\u06a9"
    ],
    "name:fas_x_variant":[
        "\u0622\u0631\u0627\u0644\u0651\u0648\u06cc \u0643\u0648\u0686\u0650\u0643",
        "\u0100r\u0101ll\u016b-ye K\u016bchek",
        "\u0622\u0631\u0627\u0644\u0651\u0648"
    ],
    "name:und_x_variant":[
        "\u0100r\u0101ll\u016b"
    ],
    "wof:name":"Arallu-ye Kuchek",
    "wof:placetype":"locality"
},
  "geometry": {"coordinates":[48.418,38.1339],"type":"Point"}
}