{
  "type": "Feature",
  "properties": {
    "gn:admin1_code":"29.0",
    "gn:asciiname":"Deh-e Heydar",
    "gn:country_code":"IR",
    "gn:dem":920,
    "gn:feature_class":"P",
    "gn:feature_code":"PPLL",
    "gn:name":"Deh-e \u1e28eydar",
    "gn:population":0,
    "gn:timezone":"Asia/Tehran",
    "iso:country":"IR",
    "name:ara_x_preferred":[
        "\u062f\u0647 \u062d\u064a\u062f\u0631"
    ],
    "name:fas_x_preferred":[
        "\u062f\u0647 \u062d\u064a\u062f\u0631"
    ],
    "name:fas_x_variant":[
        "\u062f\u0647 \u062d\u06cc\u062f\u0631"
    ],
    "name:und_x_variant":[
        "Deh-e \u1e28eydar"
    ],
    "wof:name":"Deh-e Heydar",
    "wof:placetype":"locality"
},
  "geometry": {"coordinates":[58.8221,28.0809],"type":"Point"}
}