{
  "type": "Feature",
  "properties": {
    "gn:admin1_code":"7.0",
    "gn:asciiname":"Deh Gah",
    "gn:country_code":"IR",
    "gn:dem":1289,
    "gn:feature_class":"P",
    "gn:feature_code":"PPL",
    "gn:name":"Deh Gah",
    "gn:population":0,
    "gn:timezone":"Asia/Tehran",
    "iso:country":"IR",
    "name:fas_x_preferred":[
        "\u062f\u0647 \u06af\u0647"
    ],
    "name:fas_x_variant":[
        "\u062f\u0647\u200c\u06af\u0627\u0647"
    ],
    "name:msa_x_preferred":[
        "Deh Gah"
    ],
    "name:und_x_variant":[
        "\u062f\u0647 \u06af\u0647"
    ],
    "wof:name":"Deh Gah",
    "wof:placetype":"locality"
},
  "geometry": {"coordinates":[51.32249,30.50638],"type":"Point"}
}