{
  "type": "Feature",
  "properties": {
    "gn:admin1_code":"42.0",
    "gn:asciiname":"Kohneh Forud",
    "gn:country_code":"IR",
    "gn:dem":1460,
    "gn:feature_class":"P",
    "gn:feature_code":"PPL",
    "gn:name":"Kohneh For\u016bd",
    "gn:population":0,
    "gn:timezone":"Asia/Tehran",
    "iso:country":"IR",
    "name:fas_x_preferred":[
        "Kohneh For\u016bd"
    ],
    "name:fas_x_variant":[
        "\u06a9\u0647\u0646\u0647 \u0641\u0631\u0648\u062f"
    ],
    "name:und_x_variant":[
        "\u06a9\u0647\u0646\u0647 \u0641\u0631\u0648\u062f"
    ],
    "wof:name":"Kohneh Forud",
    "wof:placetype":"locality"
},
  "geometry": {"coordinates":[58.47704,37.0401],"type":"Point"}
}