{
  "type": "Feature",
  "properties": {
    "gn:admin1_code":"32",
    "gn:asciiname":"Miandaraq",
    "gn:country_code":"IR",
    "gn:dem":2002,
    "gn:feature_class":"P",
    "gn:feature_code":"PPLL",
    "gn:name":"M\u012b\u0101ndaraq",
    "gn:population":0,
    "gn:timezone":"Asia/Tehran",
    "iso:country":"IR",
    "name:fas_x_preferred":[
        "\u062a\u0642\u06cc \u0643\u0646\u062f\u06cc"
    ],
    "name:fas_x_variant":[
        "Taq\u012b Kand\u012b",
        "\u0645\u064a\u0627\u0646\u062f\u0631\u0642",
        "\u0645\u064a\u0627\u0646\u062f\u0631\u0642 \u0628\u0642\u06cc \u06a9\u0646\u062f\u06cc"
    ],
    "name:und_x_variant":[
        "M\u012b\u0101ndaraq",
        "M\u012b\u0101ndaraq Taq\u012b Kand\u012b"
    ],
    "wof:name":"Miandaraq",
    "wof:placetype":"locality"
},
  "geometry": {"coordinates":[47.9837,38.4132],"type":"Point"}
}