{
  "type": "Feature",
  "properties": {
    "gn:admin1_code":"42.0",
    "gn:asciiname":"Sowrand",
    "gn:country_code":"IR",
    "gn:dem":1914,
    "gn:feature_class":"P",
    "gn:feature_code":"PPL",
    "gn:name":"Sowrand",
    "gn:population":0,
    "gn:timezone":"Asia/Tehran",
    "iso:country":"IR",
    "name:ceb_x_preferred":[
        "Sowrand"
    ],
    "name:fas_x_preferred":[
        "\u0633\u0648\u0631\u0646\u062f"
    ],
    "name:swe_x_preferred":[
        "Sowrand"
    ],
    "name:und_x_variant":[
        "S\u016brnad",
        "S\u016brand"
    ],
    "wof:name":"Sowrand",
    "wof:placetype":"locality"
},
  "geometry": {"coordinates":[60.06815,33.32839],"type":"Point"}
}