{
  "type": "Feature",
  "properties": {
    "gn:admin1_code":"29.0",
    "gn:asciiname":"Aderenjan",
    "gn:country_code":"IR",
    "gn:dem":2284,
    "gn:feature_class":"P",
    "gn:feature_code":"PPLF",
    "gn:name":"\u0100derenj\u0101n",
    "gn:population":0,
    "gn:timezone":"Asia/Tehran",
    "iso:country":"IR",
    "name:fas_x_preferred":[
        "\u0100derenj\u0101n"
    ],
    "name:fas_x_variant":[
        "\u0622\u062f\u0631\u0646\u062c\u0627\u0646",
        "\u0627\u0630\u0631\u0646\u062c\u0627\u0646"
    ],
    "name:und_x_variant":[
        "Az\u0304arenj\u0101n"
    ],
    "wof:name":"Aderenjan",
    "wof:placetype":"locality"
},
  "geometry": {"coordinates":[56.4144,29.2995],"type":"Point"}
}