{
  "type": "Feature",
  "properties": {
    "gn:admin1_code":"15",
    "gn:asciiname":"Sepahdar",
    "gn:country_code":"IR",
    "gn:dem":495,
    "gn:feature_class":"P",
    "gn:feature_code":"PPL",
    "gn:name":"Sepahd\u0101r",
    "gn:population":0,
    "gn:timezone":"Asia/Tehran",
    "iso:country":"IR",
    "name:fas_x_preferred":[
        "\u0633\u0650\u067e\u064e\u0647\u062f\u0627\u0631"
    ],
    "name:fas_x_variant":[
        "\u0628\u064f\u0646\u0650\u06c0 \u0633\u0650\u067e\u064e\u0647\u062f\u0627\u0631",
        "Sepahd\u0101r"
    ],
    "name:und_x_variant":[
        "Boneh-ye Sepahd\u0101r",
        "Sip\u0101hd\u0101r"
    ],
    "wof:name":"Sepahdar",
    "wof:placetype":"locality"
},
  "geometry": {"coordinates":[48.28333,32.76667],"type":"Point"}
}