{
  "type": "Feature",
  "properties": {
    "gn:admin1_code":"7.0",
    "gn:asciiname":"`Aliabad-e Bala",
    "gn:country_code":"IR",
    "gn:dem":1593,
    "gn:feature_class":"P",
    "gn:feature_code":"PPL",
    "gn:name":"\u2018Al\u012b\u0101b\u0101d-e B\u0101l\u0101",
    "gn:population":0,
    "gn:timezone":"Asia/Tehran",
    "iso:country":"IR",
    "name:fas_x_preferred":[
        "\u2018Al\u012b\u0101b\u0101d-e B\u0101l\u0101"
    ],
    "name:und_x_variant":[
        "\u2018Ali Abad\u00e9 \u2018Olya"
    ],
    "wof:name":"`Aliabad-e Bala",
    "wof:placetype":"locality"
},
  "geometry": {"coordinates":[52.71666999999999,29.91667],"type":"Point"}
}