{
  "type": "Feature",
  "properties": {
    "gn:admin1_code":"15.0",
    "gn:asciiname":"Rusta-ye Darb",
    "gn:country_code":"IR",
    "gn:dem":831,
    "gn:feature_class":"P",
    "gn:feature_code":"PPL",
    "gn:name":"R\u016bst\u0101-ye Darb",
    "gn:population":0,
    "gn:timezone":"Asia/Tehran",
    "iso:country":"IR",
    "name:ara_x_preferred":[
        "\u062f\u0631\u0628"
    ],
    "name:fas_x_preferred":[
        "\u062f\u0631\u0628"
    ],
    "name:fas_x_variant":[
        "\u0631\u0648\u0633\u062a\u0627\u06cc \u062f\u0631\u0628",
        "\u062f\u0631\u0628 \u0627\u0628\u0648 \u0627\u0644\u0639\u0628\u0627\u0633"
    ],
    "name:und_x_variant":[
        "Darb",
        "\u062f\u0631\u0628",
        "R\u016bst\u0101-ye Darb",
        "Darb-e Ab\u016b ol \u2018Abb\u0101s"
    ],
    "wof:name":"Rusta-ye Darb",
    "wof:placetype":"locality"
},
  "geometry": {"coordinates":[49.94414,31.53545],"type":"Point"}
}