{
  "type": "Feature",
  "properties": {
    "gn:admin1_code":"36",
    "gn:asciiname":"Chohreh Tappeh",
    "gn:country_code":"IR",
    "gn:dem":1284,
    "gn:feature_class":"P",
    "gn:feature_code":"PPL",
    "gn:name":"Chohreh Tappeh",
    "gn:population":0,
    "gn:timezone":"Asia/Tehran",
    "iso:country":"IR",
    "name:fas_x_preferred":[
        "\u0686\u0647\u0631\u0647 \u062a\u067e\u0647"
    ],
    "name:fas_x_variant":[
        "\u0686\u0647\u0631 \u062a\u067e\u0651\u0647"
    ],
    "name:und_x_variant":[
        "Chohr Tappeh"
    ],
    "wof:name":"Chohreh Tappeh",
    "wof:placetype":"locality"
},
  "geometry": {"coordinates":[47.6827,36.75707],"type":"Point"}
}