{
  "type": "Feature",
  "properties": {
    "gn:admin1_code":"26",
    "gn:asciiname":"Qal`eh Sin",
    "gn:country_code":"IR",
    "gn:dem":915,
    "gn:feature_class":"P",
    "gn:feature_code":"PPL",
    "gn:name":"Qal\u2018eh S\u012bn",
    "gn:population":0,
    "gn:timezone":"Asia/Tehran",
    "iso:country":"IR",
    "name:fas_x_preferred":[
        "\u0642\u0644\u0639\u0647 \u0633\u064a\u0646"
    ],
    "name:fas_x_variant":[
        "Qal\u2018eh S\u012bn"
    ],
    "wof:name":"Qal`eh Sin",
    "wof:placetype":"locality"
},
  "geometry": {"coordinates":[51.681,35.309],"type":"Point"}
}