{
  "type": "Feature",
  "properties": {
    "gn:admin1_code":"40",
    "gn:asciiname":"Chah-e Khun",
    "gn:country_code":"IR",
    "gn:dem":2612,
    "gn:feature_class":"P",
    "gn:feature_code":"PPL",
    "gn:name":"Ch\u0101h-e Kh\u016bn",
    "gn:population":0,
    "gn:timezone":"Asia/Tehran",
    "iso:country":"IR",
    "name:fas_x_preferred":[
        "\u0686\u0627\u0647 \u062e\u0648\u0646"
    ],
    "name:fas_x_variant":[
        "Ch\u0101h-e Kh\u016bn"
    ],
    "name:und_x_variant":[
        "Ch\u0101h-i-Kh\u016bni"
    ],
    "wof:name":"Chah-e Khun",
    "wof:placetype":"locality"
},
  "geometry": {"coordinates":[54.76667,31.26667],"type":"Point"}
}