{
  "type": "Feature",
  "properties": {
    "gn:admin1_code":"40",
    "gn:asciiname":"Natkuh",
    "gn:country_code":"IR",
    "gn:dem":2293,
    "gn:feature_class":"P",
    "gn:feature_code":"PPL",
    "gn:name":"Natk\u016bh",
    "gn:population":0,
    "gn:timezone":"Asia/Tehran",
    "iso:country":"IR",
    "name:ara_x_preferred":[
        "\u0646\u062a\u06a9\u0648\u0629"
    ],
    "name:fas_x_preferred":[
        "\u0646\u064e\u062a\u0643\u0648\u0647"
    ],
    "name:fas_x_variant":[
        "\u0646\u064e\u062f \u0643\u0648\u0647",
        "Natk\u016bh",
        "\u0646\u062a\u06a9\u0648\u0647",
        "Nad K\u016bh"
    ],
    "name:und_x_variant":[
        "Nad K\u016bh",
        "\u0646\u062a\u06a9\u0648\u0647"
    ],
    "wof:name":"Natkuh",
    "wof:placetype":"locality"
},
  "geometry": {"coordinates":[55.89824,31.72719],"type":"Point"}
}