{
  "type": "Feature",
  "properties": {
    "gn:admin1_code":"4.0",
    "gn:asciiname":"Pachegi",
    "gn:country_code":"IR",
    "gn:dem":726,
    "gn:feature_class":"P",
    "gn:feature_code":"PPL",
    "gn:name":"Pacheg\u012b",
    "gn:population":0,
    "gn:timezone":"Asia/Tehran",
    "iso:country":"IR",
    "name:fas_x_preferred":[
        "Pacheg\u012b"
    ],
    "wof:name":"Pachegi",
    "wof:placetype":"locality"
},
  "geometry": {"coordinates":[60.71083,26.32111],"type":"Point"}
}