{
  "type": "Feature",
  "properties": {
    "gn:admin1_code":"8",
    "gn:asciiname":"Khotbeh Sara",
    "gn:country_code":"IR",
    "gn:dem":-8,
    "gn:feature_class":"P",
    "gn:feature_code":"PPL",
    "gn:name":"Kho\u0163beh Sar\u0101",
    "gn:population":0,
    "gn:timezone":"Asia/Tehran",
    "iso:country":"IR",
    "name:ceb_x_preferred":[
        "Kho\u0163beh Sar\u0101"
    ],
    "name:fas_x_preferred":[
        "\u062e\u0637\u0628\u0647 \u0633\u0631\u0627"
    ],
    "name:fas_x_variant":[
        "Kho\u0163beh Sar\u0101"
    ],
    "name:msa_x_preferred":[
        "Khotbeh Sara"
    ],
    "name:swe_x_preferred":[
        "Kho\u0163beh Sar\u0101"
    ],
    "name:ukr_x_preferred":[
        "\u0425\u043e\u0442\u0431\u0435-\u0421\u0430\u0440\u0430"
    ],
    "name:und_x_variant":[
        "Hata Basrah",
        "Seydg\u0101h-e Kho\u0163beh Sar\u0101"
    ],
    "wof:name":"Khotbeh Sara",
    "wof:placetype":"locality"
},
  "geometry": {"coordinates":[48.9107,38.0307],"type":"Point"}
}