{
  "type": "Feature",
  "properties": {
    "gn:admin1_code":"41",
    "gn:asciiname":"Gakrau",
    "gn:country_code":"IR",
    "gn:dem":2019,
    "gn:feature_class":"P",
    "gn:feature_code":"PPL",
    "gn:name":"Gakr\u0101u",
    "gn:population":0,
    "gn:timezone":"Asia/Tehran",
    "iso:country":"IR",
    "name:fas_x_preferred":[
        "Gakr\u0101u"
    ],
    "wof:name":"Gakrau",
    "wof:placetype":"locality"
},
  "geometry": {"coordinates":[59.53333000000001,32.13333],"type":"Point"}
}