{
  "type": "Feature",
  "properties": {
    "gn:admin1_code":"33",
    "gn:asciiname":"Aqdagh-e Bala",
    "gn:country_code":"IR",
    "gn:dem":1644,
    "gn:feature_class":"P",
    "gn:feature_code":"PPL",
    "gn:name":"\u0100qd\u0101gh-e B\u0101l\u0101",
    "gn:population":0,
    "gn:timezone":"Asia/Tehran",
    "iso:country":"IR",
    "name:fas_x_preferred":[
        "\u0622\u0642\u062f\u0627\u063a \u0628\u0627\u0644\u0627"
    ],
    "name:fas_x_variant":[
        "\u0100qd\u0101gh R\u016bd",
        "\u0100qd\u0101gh-e B\u0101l\u0101"
    ],
    "wof:name":"Aqdagh-e Bala",
    "wof:placetype":"locality"
},
  "geometry": {"coordinates":[47.0233,37.3589],"type":"Point"}
}