{
  "type": "Feature",
  "properties": {
    "gn:admin1_code":"15.0",
    "gn:asciiname":"Darreh Pidan",
    "gn:country_code":"IR",
    "gn:dem":414,
    "gn:feature_class":"P",
    "gn:feature_code":"PPL",
    "gn:name":"Darreh P\u012bd\u0101n",
    "gn:population":0,
    "gn:timezone":"Asia/Tehran",
    "iso:country":"IR",
    "wof:name":"Darreh Pidan",
    "wof:placetype":"locality"
},
  "geometry": {"coordinates":[49.71806,31.39],"type":"Point"}
}