{
  "type": "Feature",
  "properties": {
    "gn:admin1_code":"34.0",
    "gn:asciiname":"Cheshmeh Palang",
    "gn:country_code":"IR",
    "gn:dem":1011,
    "gn:feature_class":"P",
    "gn:feature_code":"PPL",
    "gn:name":"Cheshmeh Palang",
    "gn:population":0,
    "gn:timezone":"Asia/Tehran",
    "iso:country":"IR",
    "name:ara_x_preferred":[
        "\u062a\u0634\u0634\u0645\u0647\u0628\u0644\u0646\u063a"
    ],
    "name:fas_x_preferred":[
        "\u0686\u0634\u0645\u0647 \u067e\u0644\u0646\u06af"
    ],
    "name:fas_x_variant":[
        "\u0686\u0634\u0645\u0647 \u067e\u0644\u0646\u06af \u067e\u0627\u0626\u06cc\u0646",
        "\u063a\u0644\u0627\u0645 \u0628\u0644\u0627\u063a\u06cc",
        "\u0686\u0634\u0645\u0647\u200c\u067e\u0644\u0646\u06af"
    ],
    "name:und_x_variant":[
        "Cheshmeh Palang-e P\u0101\u2019\u012bn",
        "Ghol\u0101m Bol\u0101gh\u012b"
    ],
    "wof:name":"Cheshmeh Palang",
    "wof:placetype":"locality"
},
  "geometry": {"coordinates":[50.75248,34.98233],"type":"Point"}
}