{
  "type": "Feature",
  "properties": {
    "gn:admin1_code":"42",
    "gn:asciiname":"Dish Dish",
    "gn:country_code":"IR",
    "gn:dem":1203,
    "gn:feature_class":"P",
    "gn:feature_code":"PPL",
    "gn:name":"D\u012bsh D\u012bsh",
    "gn:population":0,
    "gn:timezone":"Asia/Tehran",
    "iso:country":"IR",
    "name:fas_x_preferred":[
        "\u062f\u06cc\u0634\u062f\u06cc\u0634"
    ],
    "name:fas_x_variant":[
        "D\u012bsh D\u012bsh",
        "D\u012bshd\u012bsh",
        "\u062f\u06cc\u0634 \u062f\u06cc\u0634"
    ],
    "wof:name":"Dish Dish",
    "wof:placetype":"locality"
},
  "geometry": {"coordinates":[59.05065,36.01104],"type":"Point"}
}