{
  "type": "Feature",
  "properties": {
    "gn:admin1_code":"35",
    "gn:asciiname":"Yolmeh Salian",
    "gn:country_code":"IR",
    "gn:dem":4,
    "gn:feature_class":"P",
    "gn:feature_code":"PPL",
    "gn:name":"Yolmeh S\u0101l\u012b\u0101n",
    "gn:population":0,
    "gn:timezone":"Asia/Tehran",
    "iso:country":"IR",
    "name:ara_x_preferred":[
        "\u064a\u0644\u0645\u0629 \u0633\u0627\u0644\u064a\u0627\u0646"
    ],
    "name:fas_x_preferred":[
        "\u064a\u064f\u0644\u0645\u0650\u0647 \u0633\u0627\u0644\u064a\u0627\u0646"
    ],
    "name:fas_x_variant":[
        "\u06cc\u0644\u0645\u0647\u200c\u0633\u0627\u0644\u06cc\u0627\u0646"
    ],
    "name:msa_x_preferred":[
        "Yolmeh Salian"
    ],
    "name:urd_x_preferred":[
        "\u06cc\u0648\u0644\u0645\u06cc\u06c1 \u0633\u0627\u0644\u0627\u0646"
    ],
    "wof:name":"Yolmeh Salian",
    "wof:placetype":"locality"
},
  "geometry": {"coordinates":[54.73333,37.13333],"type":"Point"}
}