{
  "type": "Feature",
  "properties": {
    "gn:admin1_code":"38.0",
    "gn:asciiname":"Ruch-e Sofla",
    "gn:country_code":"IR",
    "gn:dem":1881,
    "gn:feature_class":"P",
    "gn:feature_code":"PPL",
    "gn:name":"R\u016bch-e Sofl\u00e1",
    "gn:population":0,
    "gn:timezone":"Asia/Tehran",
    "iso:country":"IR",
    "name:fas_x_preferred":[
        "\u0631\u0648\u0686"
    ],
    "name:fas_x_variant":[
        "R\u016bch",
        "P\u0101\u2019\u012bn R\u016bch",
        "\u067e\u0627\u0626\u06cc\u0646 \u0631\u0648\u0686",
        "\u0631\u0648\u0686 \u0633\u0641\u0644\u06cc"
    ],
    "name:und_x_variant":[
        "\u067e\u0627\u0626\u06cc\u0646 \u0631\u0648\u0686",
        "R\u016bch-e Sofl\u00e1"
    ],
    "wof:name":"Ruch-e Sofla",
    "wof:placetype":"locality"
},
  "geometry": {"coordinates":[50.64581,36.37874],"type":"Point"}
}