{
  "type": "Feature",
  "properties": {
    "gn:admin1_code":"34.0",
    "gn:asciiname":"Qal`eh-ye Som-e Sami",
    "gn:country_code":"IR",
    "gn:dem":983,
    "gn:feature_class":"P",
    "gn:feature_code":"PPL",
    "gn:name":"Qal\u2018eh-ye Som-e S\u0101m\u012b",
    "gn:population":0,
    "gn:timezone":"Asia/Tehran",
    "iso:country":"IR",
    "name:fas_x_preferred":[
        "Qal\u2018eh-ye Som-e S\u0101m\u012b"
    ],
    "name:fas_x_variant":[
        "\u0642\u0644\u0639\u0647 \u0633\u0645 \u0633\u0627\u0645\u06cc"
    ],
    "wof:name":"Qal`eh-ye Som-e Sami",
    "wof:placetype":"locality"
},
  "geometry": {"coordinates":[50.35239,34.8855],"type":"Point"}
}