{
  "type": "Feature",
  "properties": {
    "gn:admin1_code":"33.0",
    "gn:asciiname":"Dash Qayah Bashi",
    "gn:country_code":"IR",
    "gn:dem":681,
    "gn:feature_class":"P",
    "gn:feature_code":"PPL",
    "gn:name":"D\u0101sh Qayah B\u0101sh\u012b",
    "gn:population":0,
    "gn:timezone":"Asia/Tehran",
    "iso:country":"IR",
    "name:aze_x_preferred":[
        "Da\u015fqayaba\u015f\u0131"
    ],
    "name:fas_x_preferred":[
        "\u062f\u0627\u0634 \u0642\u06cc\u0647 \u0628\u0627\u0634\u06cc"
    ],
    "name:fas_x_variant":[
        "D\u0101sh B\u0101shi",
        "D\u0101sh Qayah B\u0101sh\u012b",
        "\u062f\u0627\u0634 \u0642\u06cc\u0647\u200c\u0628\u0627\u0634\u06cc"
    ],
    "name:msa_x_preferred":[
        "Dash Qayah Bashi"
    ],
    "wof:name":"Dash Qayah Bashi",
    "wof:placetype":"locality"
},
  "geometry": {"coordinates":[47.2315,39.1163],"type":"Point"}
}