{
  "type": "Feature",
  "properties": {
    "gn:admin1_code":"15.0",
    "gn:asciiname":"Azadi",
    "gn:country_code":"IR",
    "gn:dem":20,
    "gn:feature_class":"P",
    "gn:feature_code":"PPL",
    "gn:name":"\u0100z\u0101d\u012b",
    "gn:population":0,
    "gn:timezone":"Asia/Tehran",
    "iso:country":"IR",
    "name:fas_x_preferred":[
        "\u0622\u0632\u0627\u062f\u06cc"
    ],
    "name:fas_x_variant":[
        "\u0100z\u0101d\u012b"
    ],
    "wof:name":"Azadi",
    "wof:placetype":"locality"
},
  "geometry": {"coordinates":[48.5214,31.4144],"type":"Point"}
}