{
  "type": "Feature",
  "properties": {
    "gn:admin1_code":"23",
    "gn:asciiname":"Haft Cheshmeh",
    "gn:country_code":"IR",
    "gn:dem":740,
    "gn:feature_class":"P",
    "gn:feature_code":"PPL",
    "gn:name":"Haft Cheshmeh",
    "gn:population":0,
    "gn:timezone":"Asia/Tehran",
    "iso:country":"IR",
    "name:fas_x_preferred":[
        "\u0647\u0641\u062a \u0686\u0634\u0645\u0647"
    ],
    "wof:name":"Haft Cheshmeh",
    "wof:placetype":"locality"
},
  "geometry": {"coordinates":[47.779,33.0595],"type":"Point"}
}