{
  "type": "Feature",
  "properties": {
    "gn:admin1_code":"15",
    "gn:asciiname":"Qajariyeh-ye Yek",
    "gn:country_code":"IR",
    "gn:dem":12,
    "gn:feature_class":"P",
    "gn:feature_code":"PPL",
    "gn:name":"Qajar\u012byeh-ye Yek",
    "gn:population":0,
    "gn:timezone":"Asia/Tehran",
    "iso:country":"IR",
    "name:ara_x_preferred":[
        "\u0642\u062c\u0631\u064a\u0629 \u0627\u0644\u0623\u0648\u0644\u0649"
    ],
    "name:azb_x_preferred":[
        "\u0642\u062c\u0631\u06cc\u0647 \u06cc\u0643(\u0627\u0647\u0648\u0627\u0632)"
    ],
    "name:ceb_x_preferred":[
        "Qajar\u012byeh-ye Yek"
    ],
    "name:fas_x_preferred":[
        "\u0642\u062c\u0631\u06cc\u0647 \u06cc\u06a9"
    ],
    "name:fas_x_variant":[
        "Qajar\u012byeh-ye Yek"
    ],
    "name:pol_x_preferred":[
        "Ghad\u017carije-je Jek"
    ],
    "name:und_x_variant":[
        "Qajar\u012byeh Yek"
    ],
    "wof:name":"Qajariyeh-ye Yek",
    "wof:placetype":"locality"
},
  "geometry": {"coordinates":[48.36937,31.03112],"type":"Point"}
}