{
  "type": "Feature",
  "properties": {
    "gn:admin1_code":"40",
    "gn:asciiname":"Kalbi",
    "gn:country_code":"IR",
    "gn:dem":2677,
    "gn:feature_class":"P",
    "gn:feature_code":"PPL",
    "gn:name":"Kalb\u012b",
    "gn:population":0,
    "gn:timezone":"Asia/Tehran",
    "iso:country":"IR",
    "name:fas_x_preferred":[
        "\u0643\u064e\u0644\u0648\u06cc"
    ],
    "name:fas_x_variant":[
        "Kalv\u012b",
        "Kalb\u012b",
        "\u06a9\u0644\u0628\u06cc",
        "\u06a9\u0627\u0628\u0639\u0644\u06cc",
        "Kalb\u2018al\u012b"
    ],
    "wof:name":"Kalbi",
    "wof:placetype":"locality"
},
  "geometry": {"coordinates":[54.04362,31.53231],"type":"Point"}
}