{
  "type": "Feature",
  "properties": {
    "gn:admin1_code":"29",
    "gn:asciiname":"Deh Now-ye Bala",
    "gn:country_code":"IR",
    "gn:dem":2378,
    "gn:feature_class":"P",
    "gn:feature_code":"PPL",
    "gn:name":"Deh Now-ye B\u0101l\u0101",
    "gn:population":0,
    "gn:timezone":"Asia/Tehran",
    "iso:country":"IR",
    "name:fas_x_preferred":[
        "\u062f\u0647 \u0646\u0648 \u0628\u0627\u0644\u0627"
    ],
    "name:fas_x_variant":[
        "Am\u012bn\u0101b\u0101d",
        "\u0627\u0645\u06cc\u0646 \u0622\u0628\u0627\u062f",
        "Deh Now-ye B\u0101l\u0101"
    ],
    "wof:name":"Deh Now-ye Bala",
    "wof:placetype":"locality"
},
  "geometry": {"coordinates":[57.31922,30.37947],"type":"Point"}
}