{
  "type": "Feature",
  "properties": {
    "gn:admin1_code":"42.0",
    "gn:asciiname":"Chah Ja`farzadeh-ye Miani",
    "gn:country_code":"IR",
    "gn:dem":1219,
    "gn:feature_class":"P",
    "gn:feature_code":"PPL",
    "gn:name":"Ch\u0101h Ja\u2018farz\u0101deh-ye M\u012b\u0101n\u012b",
    "gn:population":0,
    "gn:timezone":"Asia/Tehran",
    "iso:country":"IR",
    "name:fas_x_preferred":[
        "Ch\u0101h Ja\u2018farz\u0101deh-ye M\u012b\u0101n\u012b"
    ],
    "wof:name":"Chah Ja`farzadeh-ye Miani",
    "wof:placetype":"locality"
},
  "geometry": {"coordinates":[58.79971999999999,36.83417],"type":"Point"}
}