{
  "type": "Feature",
  "properties": {
    "gn:admin1_code":"39.0",
    "gn:asciiname":"Nabeh",
    "gn:country_code":"IR",
    "gn:dem":1842,
    "gn:feature_class":"P",
    "gn:feature_code":"PPL",
    "gn:name":"N\u0101beh",
    "gn:population":0,
    "gn:timezone":"Asia/Tehran",
    "iso:country":"IR",
    "name:fas_x_preferred":[
        "Qal\u2018eh Boland"
    ],
    "name:fas_x_variant":[
        "\u0642\u0644\u0639\u0647 \u0628\u0644\u0646\u062f",
        "\u0646\u0627\u0628\u0647"
    ],
    "name:und_x_variant":[
        "\u0642\u0644\u0639\u0647 \u0628\u0644\u0646\u062f",
        "N\u0101beh"
    ],
    "wof:name":"Nabeh",
    "wof:placetype":"locality"
},
  "geometry": {"coordinates":[50.24819,34.61465],"type":"Point"}
}