{
  "type": "Feature",
  "properties": {
    "gn:admin1_code":"28.0",
    "gn:asciiname":"Nasimabad-e Pa'in",
    "gn:country_code":"IR",
    "gn:dem":2048,
    "gn:feature_class":"P",
    "gn:feature_code":"PPL",
    "gn:name":"Nas\u012bm\u0101b\u0101d-e P\u0101\u2019\u012bn",
    "gn:population":0,
    "gn:timezone":"Asia/Tehran",
    "iso:country":"IR",
    "name:fas_x_preferred":[
        "Nas\u012bm\u0101b\u0101d-e P\u0101\u2019\u012bn"
    ],
    "name:fas_x_variant":[
        "\u0646\u0633\u06cc\u0645 \u0622\u0628\u0627\u062f \u067e\u0627\u0626\u06cc\u0646"
    ],
    "wof:name":"Nasimabad-e Pa'in",
    "wof:placetype":"locality"
},
  "geometry": {"coordinates":[50.94599,32.80821],"type":"Point"}
}