{
  "type": "Feature",
  "properties": {
    "gn:admin1_code":"13",
    "gn:asciiname":"Sahaz",
    "gn:country_code":"IR",
    "gn:dem":1495,
    "gn:feature_class":"P",
    "gn:feature_code":"PPL",
    "gn:name":"Sah\u0101z",
    "gn:population":0,
    "gn:timezone":"Asia/Tehran",
    "iso:country":"IR",
    "name:fas_x_preferred":[
        "\u0633\u0647\u0627\u0632"
    ],
    "name:fas_x_variant":[
        "S\u0101z",
        "Sah\u0101z"
    ],
    "wof:name":"Sahaz",
    "wof:placetype":"locality"
},
  "geometry": {"coordinates":[47.1479,34.6271],"type":"Point"}
}