{
  "type": "Feature",
  "properties": {
    "gn:admin1_code":"7.0",
    "gn:asciiname":"Shah -aleh",
    "gn:country_code":"IR",
    "gn:dem":1136,
    "gn:feature_class":"P",
    "gn:feature_code":"PPL",
    "gn:name":"Sh\u0101h -\u0101le\u1e29",
    "gn:population":0,
    "gn:timezone":"Asia/Tehran",
    "iso:country":"IR",
    "name:fas_x_preferred":[
        "Sh\u0101h -\u0101le\u1e29"
    ],
    "wof:name":"Shah -aleh",
    "wof:placetype":"locality"
},
  "geometry": {"coordinates":[51.55139000000001,29.85056],"type":"Point"}
}