{
  "type": "Feature",
  "properties": {
    "gn:admin1_code":"15.0",
    "gn:asciiname":"Hajji Ja`far",
    "gn:country_code":"IR",
    "gn:dem":6,
    "gn:feature_class":"P",
    "gn:feature_code":"PPLF",
    "gn:name":"H\u0101jj\u012b Ja\u2018far",
    "gn:population":0,
    "gn:timezone":"Asia/Tehran",
    "iso:country":"IR",
    "name:fas_x_preferred":[
        "\u062d\u0627\u062c\u0651\u06cc \u062c\u0639\u0641\u0631"
    ],
    "name:fas_x_variant":[
        "H\u0101j\u012b Ja\u2018far",
        "H\u0101jj\u012b Ja\u2018far"
    ],
    "wof:name":"Hajji Ja`far",
    "wof:placetype":"locality"
},
  "geometry": {"coordinates":[48.29644,30.36517000000001],"type":"Point"}
}