{
  "type": "Feature",
  "properties": {
    "gn:admin1_code":"8",
    "gn:asciiname":"Sipini Chal",
    "gn:country_code":"IR",
    "gn:dem":2256,
    "gn:feature_class":"P",
    "gn:feature_code":"PPLL",
    "gn:name":"S\u012bp\u012bn\u012b Ch\u0101l",
    "gn:population":0,
    "gn:timezone":"Asia/Tehran",
    "iso:country":"IR",
    "name:fas_x_preferred":[
        "\u0644\u0648\u0634\u0627 \u067e\u0634\u062a"
    ],
    "name:fas_x_variant":[
        "L\u016bsh\u0101 Posht",
        "\u0633\u06cc\u067e\u06cc\u0646\u06cc \u0686\u0627\u0644"
    ],
    "name:und_x_variant":[
        "S\u012bp\u012bn\u012b Ch\u0101l"
    ],
    "wof:name":"Sipini Chal",
    "wof:placetype":"locality"
},
  "geometry": {"coordinates":[48.67151,37.78375],"type":"Point"}
}