{
  "type": "Feature",
  "properties": {
    "gn:admin1_code":"29",
    "gn:asciiname":"Mirabad",
    "gn:country_code":"IR",
    "gn:dem":635,
    "gn:feature_class":"P",
    "gn:feature_code":"PPL",
    "gn:name":"M\u012br\u0101b\u0101d",
    "gn:population":0,
    "gn:timezone":"Asia/Tehran",
    "iso:country":"IR",
    "name:aze_x_preferred":[
        "Mirabad"
    ],
    "name:ceb_x_preferred":[
        "Mirabad"
    ],
    "name:fas_x_preferred":[
        "\u0645\u06cc\u0631 \u0622\u0628\u0627\u062f \u0627\u0645\u0627\u0645 \u0642\u0644\u06cc"
    ],
    "name:fas_x_variant":[
        "\u0645\u06cc\u0631 \u0622\u0628\u0627\u062f",
        "M\u012br\u0101b\u0101d-e Em\u0101m Qol\u012b",
        "\u0645\u06cc\u0631\u0622\u0628\u0627\u062f"
    ],
    "name:swe_x_preferred":[
        "Mirabad"
    ],
    "name:und_x_variant":[
        "M\u012br\u0101b\u0101d"
    ],
    "wof:name":"Mirabad",
    "wof:placetype":"locality"
},
  "geometry": {"coordinates":[58.9847,28.7431],"type":"Point"}
}