{
  "type": "Feature",
  "properties": {
    "gn:admin1_code":"23",
    "gn:asciiname":"Mohbatabad",
    "gn:country_code":"IR",
    "gn:dem":1701,
    "gn:feature_class":"P",
    "gn:feature_code":"PPL",
    "gn:name":"Mo\u1e29bat\u0101b\u0101d",
    "gn:population":0,
    "gn:timezone":"Asia/Tehran",
    "iso:country":"IR",
    "name:fas_x_preferred":[
        "\u062d\u062c\u062a \u0622\u0628\u0627\u062f"
    ],
    "name:fas_x_variant":[
        "\u1e28ojjat\u0101b\u0101d",
        "\u0645\u062d\u0628\u062a \u0622\u0628\u0627\u062f",
        "\u067e\u06cc\u0631\u0647 \u0622\u0628\u0627\u062f"
    ],
    "name:und_x_variant":[
        "Mo\u1e29bat\u0101b\u0101d",
        "P\u012breh\u0101b\u0101d"
    ],
    "wof:name":"Mohbatabad",
    "wof:placetype":"locality"
},
  "geometry": {"coordinates":[48.5999,33.4179],"type":"Point"}
}