{
  "type": "Feature",
  "properties": {
    "gn:admin1_code":"37",
    "gn:asciiname":"Seyyed Kalateh",
    "gn:country_code":"IR",
    "gn:dem":383,
    "gn:feature_class":"P",
    "gn:feature_code":"PPL",
    "gn:name":"Seyyed Kal\u0101teh",
    "gn:population":0,
    "gn:timezone":"Asia/Tehran",
    "iso:country":"IR",
    "name:fas_x_preferred":[
        "\u0633\u0650\u064a\u0650\u0651\u062f \u0643\u064e\u0644\u0627\u062a\u0650\u0647"
    ],
    "name:fas_x_variant":[
        "\u0633\u0650\u064a\u0644 \u0643\u064e\u0644\u0627",
        "\u0633\u062f\u0651 \u06a9\u0644\u0627\u062a\u0647",
        "Seyyed Kal\u0101teh",
        "Sadd-e Kal\u0101teh",
        "\u0633\u064a\u062f \u06a9\u0644\u0627\u062a\u0647"
    ],
    "name:und_x_variant":[
        "Seyl Kal\u0101",
        "Saiyid Qal\u2018eh"
    ],
    "wof:name":"Seyyed Kalateh",
    "wof:placetype":"locality"
},
  "geometry": {"coordinates":[55.10931,36.95608],"type":"Point"}
}