{
  "type": "Feature",
  "properties": {
    "gn:admin1_code":"33",
    "gn:asciiname":"Chakhmaq Bolagh-e Pa'in",
    "gn:country_code":"IR",
    "gn:dem":1853,
    "gn:feature_class":"P",
    "gn:feature_code":"PPL",
    "gn:name":"Chakhm\u0101q Bol\u0101gh-e P\u0101\u2019\u012bn",
    "gn:population":0,
    "gn:timezone":"Asia/Tehran",
    "iso:country":"IR",
    "name:fas_x_preferred":[
        "\u0686\u062e\u0645\u0627\u0642 \u0628\u0644\u0627\u063a \u067e\u0627\u0626\u06cc\u0646"
    ],
    "name:fas_x_variant":[
        "\u0686\u062e\u0645\u0627\u0642\u200c\u0628\u0644\u0627\u063a \u0633\u0641\u0644\u06cc"
    ],
    "name:msa_x_preferred":[
        "Chakhmaq Bolagh-e Sofla"
    ],
    "name:und_x_variant":[
        "Khom\u0101q Bol\u0101gh-e Ash\u0101qi",
        "Ch\u0101khm\u0101qbol\u0101q-e Sofl\u0101",
        "Chakhm\u0101q Bol\u0101gh-e Ash\u0101qi",
        "Chakhmakh-bulag-Ashagi",
        "Chakhm\u0101q Bol\u0101gh-e Sofl\u00e1",
        "Chakhm\u0101q Bol\u0101gh P\u0101\u2019\u012bn",
        "Chaqm\u0101q Bul\u0101gh Ash\u0101ghi",
        "Chakhm\u0101q Bol\u0101gh-e P\u0101\u2019\u012bn"
    ],
    "wof:name":"Chakhmaq Bolagh-e Pa'in",
    "wof:placetype":"locality"
},
  "geometry": {"coordinates":[46.7012,38.3929],"type":"Point"}
}