{
  "type": "Feature",
  "properties": {
    "gn:admin1_code":"43.0",
    "gn:asciiname":"`Emarat",
    "gn:country_code":"IR",
    "gn:dem":1244,
    "gn:feature_class":"P",
    "gn:feature_code":"PPL",
    "gn:name":"\u2018Em\u0101rat",
    "gn:population":0,
    "gn:timezone":"Asia/Tehran",
    "iso:country":"IR",
    "name:fas_x_preferred":[
        "\u2018Abb\u0101s\u0101b\u0101d"
    ],
    "name:fas_x_variant":[
        "\u2018Em\u0101rat",
        "\u0639\u0628\u0627\u0633 \u0622\u0628\u0627\u062f",
        "\u0639\u0645\u0627\u0631\u062a"
    ],
    "name:und_x_variant":[
        "\u0639\u0628\u0627\u0633 \u0622\u0628\u0627\u062f"
    ],
    "wof:name":"`Emarat",
    "wof:placetype":"locality"
},
  "geometry": {"coordinates":[56.74158000000001,37.32864],"type":"Point"}
}