{
  "type": "Feature",
  "properties": {
    "gn:admin1_code":"15",
    "gn:asciiname":"Porzinistan-e Gholam`ali",
    "gn:country_code":"IR",
    "gn:dem":75,
    "gn:feature_class":"P",
    "gn:feature_code":"PPL",
    "gn:name":"Porz\u012bn\u012bst\u0101n-e Ghol\u0101m\u2018al\u012b",
    "gn:population":0,
    "gn:timezone":"Asia/Tehran",
    "iso:country":"IR",
    "name:fas_x_preferred":[
        "\u0628\u0646\u0647 \u063a\u0644\u0627\u0645\u0639\u0644\u06cc"
    ],
    "name:fas_x_variant":[
        "Porzanast\u0101n",
        "Boneh-ye Ghol\u0101m\u2018al\u012b",
        "\u067e\u0631\u0632\u06cc\u0646\u06cc\u0633\u062a\u0627\u0646 \u063a\u0644\u0627\u0645\u0639\u0644\u06cc",
        "\u067e\u0631\u0632\u06cc\u0646\u0633\u062a\u0627\u0646"
    ],
    "name:und_x_variant":[
        "Ghol\u0101m\u2018al\u012b",
        "Porz\u012bn\u012bst\u0101n-e Ghol\u0101m\u2018al\u012b",
        "Porz\u012bnast\u0101n"
    ],
    "wof:name":"Porzinistan-e Gholam`ali",
    "wof:placetype":"locality"
},
  "geometry": {"coordinates":[48.7837,31.90992],"type":"Point"}
}