{
  "type": "Feature",
  "properties": {
    "gn:admin1_code":"4",
    "gn:asciiname":"Dabar",
    "gn:country_code":"IR",
    "gn:dem":623,
    "gn:feature_class":"P",
    "gn:feature_code":"PPL",
    "gn:name":"Dab\u0101r",
    "gn:population":0,
    "gn:timezone":"Asia/Tehran",
    "iso:country":"IR",
    "name:fas_x_preferred":[
        "\u062f\u0628\u0627\u0631"
    ],
    "name:fas_x_variant":[
        "Dab\u0101r",
        "\u062f\u0628 \u0628\u0627\u0631"
    ],
    "name:und_x_variant":[
        "Dab B\u0101r"
    ],
    "wof:name":"Dabar",
    "wof:placetype":"locality"
},
  "geometry": {"coordinates":[59.8289,26.3861],"type":"Point"}
}