{
  "type": "Feature",
  "properties": {
    "gn:admin1_code":"37.0",
    "gn:asciiname":"Chalejeh",
    "gn:country_code":"IR",
    "gn:dem":379,
    "gn:feature_class":"P",
    "gn:feature_code":"PPL",
    "gn:name":"Ch\u0101lejeh",
    "gn:population":0,
    "gn:timezone":"Asia/Tehran",
    "iso:country":"IR",
    "name:ceb_x_preferred":[
        "Ch\u0101lejeh"
    ],
    "name:fas_x_preferred":[
        "\u0686\u0627\u0644 \u062c\u0647"
    ],
    "name:fas_x_variant":[
        "Ch\u0101lejeh",
        "\u0686\u0627\u0644\u062c\u0647"
    ],
    "name:msa_x_preferred":[
        "Chalejeh"
    ],
    "name:swe_x_preferred":[
        "Ch\u0101lejeh"
    ],
    "wof:name":"Chalejeh",
    "wof:placetype":"locality"
},
  "geometry": {"coordinates":[55.54417,37.72874],"type":"Point"}
}