{
  "type": "Feature",
  "properties": {
    "gn:admin1_code":"3.0",
    "gn:asciiname":"Dowrak-e Sofla",
    "gn:country_code":"IR",
    "gn:dem":1600,
    "gn:feature_class":"P",
    "gn:feature_code":"PPL",
    "gn:name":"Dowrak-e Sofl\u00e1",
    "gn:population":0,
    "gn:timezone":"Asia/Tehran",
    "iso:country":"IR",
    "name:fas_x_preferred":[
        "Dowrak-e Sofl\u00e1"
    ],
    "name:fas_x_variant":[
        "\u062f\u0648\u0631\u06a9 \u0633\u0641\u0644\u06cc"
    ],
    "wof:name":"Dowrak-e Sofla",
    "wof:placetype":"locality"
},
  "geometry": {"coordinates":[50.0286,32.25919],"type":"Point"}
}