{
  "type": "Feature",
  "properties": {
    "gn:admin1_code":"42",
    "gn:asciiname":"Mowkuh",
    "gn:country_code":"IR",
    "gn:dem":1893,
    "gn:feature_class":"P",
    "gn:feature_code":"PPL",
    "gn:name":"Mowk\u016bh",
    "gn:population":0,
    "gn:timezone":"Asia/Tehran",
    "iso:country":"IR",
    "name:fas_x_preferred":[
        "Mowk\u016bh"
    ],
    "wof:name":"Mowkuh",
    "wof:placetype":"locality"
},
  "geometry": {"coordinates":[57.26639,33.61694],"type":"Point"}
}