{
  "type": "Feature",
  "properties": {
    "gn:admin1_code":"8",
    "gn:asciiname":"Gil-e Pardesar",
    "gn:country_code":"IR",
    "gn:dem":22,
    "gn:feature_class":"P",
    "gn:feature_code":"PPL",
    "gn:name":"G\u012bl-e Pardesar",
    "gn:population":0,
    "gn:timezone":"Asia/Tehran",
    "iso:country":"IR",
    "name:fas_x_preferred":[
        "G\u012bleh Pordesar"
    ],
    "name:fas_x_variant":[
        "\u06af\u06cc\u0644 \u067e\u0631\u062f\u0633\u0631",
        "\u06af\u06cc\u0644 \u067e\u0631\u062f\u0647 \u0633\u0631"
    ],
    "name:und_x_variant":[
        "Gulpardsar",
        "G\u012bl-e Pardesar",
        "Gul-Pardasar",
        "Gol Pardehsar",
        "Gol Pardsar",
        "G\u012bl-e Pardeh Sar"
    ],
    "wof:name":"Gil-e Pardesar",
    "wof:placetype":"locality"
},
  "geometry": {"coordinates":[49.66405,37.20876],"type":"Point"}
}