{
  "type": "Feature",
  "properties": {
    "gn:admin1_code":"8",
    "gn:asciiname":"Pa'in Lasak",
    "gn:country_code":"IR",
    "gn:dem":105,
    "gn:feature_class":"P",
    "gn:feature_code":"PPL",
    "gn:name":"P\u0101\u2019\u012bn L\u0101sak",
    "gn:population":0,
    "gn:timezone":"Asia/Tehran",
    "iso:country":"IR",
    "name:fas_x_preferred":[
        "\u0644\u0627\u0633\u06a9"
    ],
    "name:fas_x_variant":[
        "L\u0101sak",
        "\u067e\u0627\u06cc\u06cc\u0646 \u0644\u0627\u0633\u06a9"
    ],
    "name:und_x_variant":[
        "P\u0101\u2019\u012bn L\u0101sak"
    ],
    "wof:name":"Pa'in Lasak",
    "wof:placetype":"locality"
},
  "geometry": {"coordinates":[49.39733,37.0458],"type":"Point"}
}