{
  "type": "Feature",
  "properties": {
    "gn:admin1_code":"15",
    "gn:asciiname":"Al Jazayer",
    "gn:country_code":"IR",
    "gn:dem":52,
    "gn:feature_class":"P",
    "gn:feature_code":"PPL",
    "gn:name":"Al Jaz\u0101yer",
    "gn:population":0,
    "gn:timezone":"Asia/Tehran",
    "iso:country":"IR",
    "name:fas_x_preferred":[
        "\u0627\u0644\u062c\u0632\u0627\u06cc\u0631"
    ],
    "name:fas_x_variant":[
        "Al Jaz\u0101yer"
    ],
    "name:und_x_variant":[
        "\u2018Abd or Ra\u1e29\u012bm-e \u1e94omd\u012b"
    ],
    "wof:name":"Al Jazayer",
    "wof:placetype":"locality"
},
  "geometry": {"coordinates":[48.2894,32.0015],"type":"Point"}
}