{
  "type": "Feature",
  "properties": {
    "gn:admin1_code":"22",
    "gn:asciiname":"Boneh-ye Ahmad",
    "gn:country_code":"IR",
    "gn:dem":14,
    "gn:feature_class":"P",
    "gn:feature_code":"PPL",
    "gn:name":"Boneh-ye A\u1e29mad",
    "gn:population":0,
    "gn:timezone":"Asia/Tehran",
    "iso:country":"IR",
    "name:ara_x_preferred":[
        "\u0628\u0646\u0647\u200c\u0627\u062d\u0645\u062f"
    ],
    "name:fas_x_preferred":[
        "\u0628\u0646\u0647 \u0627\u062d\u0645\u062f"
    ],
    "name:fas_x_variant":[
        "\u0628\u064f\u0646\u0650\u0647 \u0627\u064e\u062d\u0645\u064e\u062f",
        "Boneh-ye A\u1e29mad",
        "\u0628\u0646\u0647\u200c\u0627\u062d\u0645\u062f"
    ],
    "name:msa_x_preferred":[
        "Boneh-ye Ahmad"
    ],
    "name:und_x_variant":[
        "Boneh A\u1e29mad"
    ],
    "wof:name":"Boneh-ye Ahmad",
    "wof:placetype":"locality"
},
  "geometry": {"coordinates":[50.2689,29.9845],"type":"Point"}
}