{
  "type": "Feature",
  "properties": {
    "gn:admin1_code":"16",
    "gn:asciiname":"Zangabad",
    "gn:country_code":"IR",
    "gn:dem":1795,
    "gn:feature_class":"P",
    "gn:feature_code":"PPL",
    "gn:name":"Zang\u0101b\u0101d",
    "gn:population":0,
    "gn:timezone":"Asia/Tehran",
    "iso:country":"IR",
    "name:fas_x_preferred":[
        "\u0632\u0646\u06af \u0622\u0628\u0627\u062f"
    ],
    "name:fas_x_variant":[
        "Zang\u0101b\u0101d"
    ],
    "wof:name":"Zangabad",
    "wof:placetype":"locality"
},
  "geometry": {"coordinates":[48.00375,35.13123],"type":"Point"}
}