{
  "type": "Feature",
  "properties": {
    "gn:admin1_code":"15",
    "gn:asciiname":"Chal Gura",
    "gn:country_code":"IR",
    "gn:dem":580,
    "gn:feature_class":"P",
    "gn:feature_code":"PPL",
    "gn:name":"Ch\u0101l G\u016br\u0101",
    "gn:population":0,
    "gn:timezone":"Asia/Tehran",
    "iso:country":"IR",
    "name:fas_x_preferred":[
        "Ch\u0101l G\u016br\u0101"
    ],
    "wof:name":"Chal Gura",
    "wof:placetype":"locality"
},
  "geometry": {"coordinates":[48.96667,32.43333],"type":"Point"}
}