{
  "type": "Feature",
  "properties": {
    "gn:admin1_code":"11",
    "gn:asciiname":"Now Kar",
    "gn:country_code":"IR",
    "gn:dem":661,
    "gn:feature_class":"P",
    "gn:feature_code":"PPL",
    "gn:name":"Now K\u0101r",
    "gn:population":0,
    "gn:timezone":"Asia/Tehran",
    "iso:country":"IR",
    "name:fas_x_preferred":[
        "\u0646\u0648 \u06a9\u0627\u0631"
    ],
    "name:fas_x_variant":[
        "Now K\u0101r"
    ],
    "wof:name":"Now Kar",
    "wof:placetype":"locality"
},
  "geometry": {"coordinates":[56.5223,27.7767],"type":"Point"}
}