{
  "type": "Feature",
  "properties": {
    "gn:admin1_code":"42",
    "gn:asciiname":"Sar Chel-e Bala",
    "gn:country_code":"IR",
    "gn:dem":1283,
    "gn:feature_class":"P",
    "gn:feature_code":"PPL",
    "gn:name":"Sar Chel-e B\u0101l\u0101",
    "gn:population":0,
    "gn:timezone":"Asia/Tehran",
    "iso:country":"IR",
    "name:fas_x_preferred":[
        "\u0633\u0631 \u0686\u0644 \u0628\u0627\u0644\u0627"
    ],
    "name:fas_x_variant":[
        "Sar Chel-e B\u0101l\u0101"
    ],
    "wof:name":"Sar Chel-e Bala",
    "wof:placetype":"locality"
},
  "geometry": {"coordinates":[59.50723000000001,35.11937],"type":"Point"}
}