{
  "type": "Feature",
  "properties": {
    "gn:admin1_code":"5.0",
    "gn:asciiname":"Dehdasht",
    "gn:country_code":"IR",
    "gn:dem":1139,
    "gn:feature_class":"P",
    "gn:feature_code":"PPL",
    "gn:name":"Dehdasht",
    "gn:population":0,
    "gn:timezone":"Asia/Tehran",
    "iso:country":"IR",
    "name:ara_x_preferred":[
        "\u062f\u0647\u062f\u0634\u062a"
    ],
    "name:ceb_x_preferred":[
        "Dehdasht"
    ],
    "name:fas_x_preferred":[
        "\u062f\u0647\u062f\u0634\u062a"
    ],
    "name:hin_x_preferred":[
        "\u0926\u0947\u0939 \u0926\u0936\u094d\u0924"
    ],
    "name:ita_x_preferred":[
        "Dehdasht"
    ],
    "name:mlg_x_preferred":[
        "Dehdasht"
    ],
    "name:pol_x_preferred":[
        "Dehdaszt"
    ],
    "name:rus_x_preferred":[
        "\u0414\u0435\u0445\u0434\u0435\u0448\u0442"
    ],
    "name:swe_x_preferred":[
        "Dehdasht"
    ],
    "name:tur_x_preferred":[
        "Dehde\u015ft"
    ],
    "name:urd_x_preferred":[
        "\u062f\u06c1\u062f\u0634\u062a"
    ],
    "name:zho_x_preferred":[
        "\u5eab\u8d6b\u5409\u76e7\u8036"
    ],
    "wof:name":"Dehdasht",
    "wof:placetype":"locality"
},
  "geometry": {"coordinates":[50.49869,31.01751],"type":"Point"}
}