{
  "type": "Feature",
  "properties": {
    "gn:admin1_code":"5.0",
    "gn:asciiname":"Dehdasht",
    "gn:country_code":"IR",
    "gn:dem":1139,
    "gn:feature_class":"P",
    "gn:feature_code":"PPL",
    "gn:name":"Dehdasht",
    "gn:population":0,
    "gn:timezone":"Asia/Tehran",
    "iso:country":"IR",
    "name:fas_x_preferred":[
        "\u062f\u0647\u062f\u0634\u062a"
    ],
    "wof:name":"Dehdasht",
    "wof:placetype":"locality"
},
  "geometry": {"coordinates":[50.49869,31.01751],"type":"Point"}
}