{
  "type": "Feature",
  "properties": {
    "gn:admin1_code":"37",
    "gn:asciiname":"Malashi",
    "gn:country_code":"IR",
    "gn:dem":349,
    "gn:feature_class":"P",
    "gn:feature_code":"PPL",
    "gn:name":"Mal\u0101sh\u012b",
    "gn:population":0,
    "gn:timezone":"Asia/Tehran",
    "iso:country":"IR",
    "name:ceb_x_preferred":[
        "Mal\u0101sh\u012b"
    ],
    "name:fas_x_preferred":[
        "Qorb\u0101n\u0101b\u0101d"
    ],
    "name:fas_x_variant":[
        "Mal\u0101sh\u012b",
        "\u0645\u0644\u0627\u0634\u06cc"
    ],
    "name:msa_x_preferred":[
        "Malashi"
    ],
    "name:swe_x_preferred":[
        "Mal\u0101sh\u012b"
    ],
    "wof:name":"Malashi",
    "wof:placetype":"locality"
},
  "geometry": {"coordinates":[55.36664,37.1069],"type":"Point"}
}