{
  "type": "Feature",
  "properties": {
    "gn:admin1_code":"7",
    "gn:asciiname":"Koreh Aqa'i",
    "gn:country_code":"IR",
    "gn:dem":399,
    "gn:feature_class":"P",
    "gn:feature_code":"PPL",
    "gn:name":"Koreh \u0100q\u0101\u2019\u012b",
    "gn:population":0,
    "gn:timezone":"Asia/Tehran",
    "iso:country":"IR",
    "name:fas_x_preferred":[
        "Ger\u012bn-e \u0100gh\u0101\u2019\u012b"
    ],
    "name:fas_x_variant":[
        "\u06a9\u0631\u0647 \u0622\u0642\u0627\u06cc\u06cc",
        "\u06af\u0631\u0647\u0646 \u0627\u063a\u0627\u06cc\u06cc"
    ],
    "name:und_x_variant":[
        "Garin Arabi",
        "Gerehn",
        "Gerehn \u2018Arab\u012b",
        "Koreh \u0100q\u0101\u2019\u012b",
        "Gerehn Agh\u0101\u2019\u012b"
    ],
    "wof:name":"Koreh Aqa'i",
    "wof:placetype":"locality"
},
  "geometry": {"coordinates":[53.42333000000001,27.32139],"type":"Point"}
}