{
  "type": "Feature",
  "properties": {
    "gn:admin1_code":"25.0",
    "gn:asciiname":"Sharifiyeh",
    "gn:country_code":"IR",
    "gn:dem":1121,
    "gn:feature_class":"P",
    "gn:feature_code":"PPLF",
    "gn:name":"Shar\u012bf\u012byeh",
    "gn:population":0,
    "gn:timezone":"Asia/Tehran",
    "iso:country":"IR",
    "name:fas_x_preferred":[
        "Shar\u012bf\u012byeh"
    ],
    "name:fas_x_variant":[
        "\u0634\u0631\u064a\u0641\u064a\u0647"
    ],
    "wof:name":"Sharifiyeh",
    "wof:placetype":"locality"
},
  "geometry": {"coordinates":[54.25498,35.98719000000001],"type":"Point"}
}