{
  "type": "Feature",
  "properties": {
    "gn:admin1_code":"41",
    "gn:asciiname":"Manzariyeh",
    "gn:country_code":"IR",
    "gn:dem":1567,
    "gn:feature_class":"P",
    "gn:feature_code":"PPL",
    "gn:name":"Manz\u0327ar\u012byeh",
    "gn:population":0,
    "gn:timezone":"Asia/Tehran",
    "iso:country":"IR",
    "name:ara_x_preferred":[
        "\u0645\u0646\u0638\u0631\u064a\u0647"
    ],
    "name:aze_x_preferred":[
        "M\u0259nz\u0259riyy\u0259"
    ],
    "name:fas_x_preferred":[
        "Manz\u0327ar\u012byeh"
    ],
    "name:fas_x_variant":[
        "\u0645\u0646\u0638\u0631\u064a\u0647",
        "\u0628\u0627\u063a \u0645\u0646\u0638\u0631\u064a\u0647",
        "\u0645\u0646\u0638\u0631\u06cc\u0647"
    ],
    "name:ita_x_preferred":[
        "Manzariyeh"
    ],
    "name:mlg_x_preferred":[
        "Manzariyeh"
    ],
    "name:rus_x_preferred":[
        "\u041c\u0435\u043d\u0437\u0435\u0440\u0438\u0439\u0435"
    ],
    "name:tur_x_preferred":[
        "Menzeriye"
    ],
    "name:und_x_variant":[
        "B\u0101gh-e Manz\u0327ar\u012byeh"
    ],
    "wof:name":"Manzariyeh",
    "wof:placetype":"locality"
},
  "geometry": {"coordinates":[59.19703000000001,32.83547],"type":"Point"}
}