{
  "type": "Feature",
  "properties": {
    "gn:admin1_code":"41",
    "gn:asciiname":"Manzariyeh",
    "gn:country_code":"IR",
    "gn:dem":1567,
    "gn:feature_class":"P",
    "gn:feature_code":"PPL",
    "gn:name":"Manz\u0327ar\u012byeh",
    "gn:population":0,
    "gn:timezone":"Asia/Tehran",
    "iso:country":"IR",
    "name:fas_x_preferred":[
        "Manz\u0327ar\u012byeh"
    ],
    "name:fas_x_variant":[
        "\u0645\u0646\u0638\u0631\u064a\u0647",
        "\u0628\u0627\u063a \u0645\u0646\u0638\u0631\u064a\u0647"
    ],
    "name:und_x_variant":[
        "\u0645\u0646\u0638\u0631\u064a\u0647",
        "B\u0101gh-e Manz\u0327ar\u012byeh"
    ],
    "wof:name":"Manzariyeh",
    "wof:placetype":"locality"
},
  "geometry": {"coordinates":[59.19703000000001,32.83547],"type":"Point"}
}