{
  "type": "Feature",
  "properties": {
    "gn:admin1_code":"16.0",
    "gn:asciiname":"Rezaabad",
    "gn:country_code":"IR",
    "gn:dem":1612,
    "gn:feature_class":"P",
    "gn:feature_code":"PPL",
    "gn:name":"Re\u1e95\u0101\u0101b\u0101d",
    "gn:population":0,
    "gn:timezone":"Asia/Tehran",
    "iso:country":"IR",
    "name:fas_x_preferred":[
        "\u0631\u0636\u0627 \u0622\u0628\u0627\u062f"
    ],
    "name:fas_x_variant":[
        "Re\u1e95\u0101\u0101b\u0101d",
        "\u0631\u0636\u0627\u0622\u0628\u0627\u062f"
    ],
    "wof:name":"Rezaabad",
    "wof:placetype":"locality"
},
  "geometry": {"coordinates":[47.90337,35.75955],"type":"Point"}
}