{
  "type": "Feature",
  "properties": {
    "gn:admin1_code":"41",
    "gn:asciiname":"Rohuzg",
    "gn:country_code":"IR",
    "gn:dem":1845,
    "gn:feature_class":"P",
    "gn:feature_code":"PPL",
    "gn:name":"Roh\u016bzg",
    "gn:population":0,
    "gn:timezone":"Asia/Tehran",
    "iso:country":"IR",
    "name:fas_x_preferred":[
        "Roh\u016bzg"
    ],
    "name:fas_x_variant":[
        "\u0631\u0647\u0631\u0632\u06af",
        "Ruh\u016bzg",
        "Roh\u016bq",
        "Reh\u012bzek",
        "Reh\u012bzeg",
        "\u0631\u0647\u0648\u0632\u06af"
    ],
    "name:und_x_variant":[
        "Reh\u012bzek",
        "Reh\u012bzeg",
        "Roh\u016bq",
        "Ruh\u016bzg",
        "Rohrozg",
        "\u0631\u0647\u0631\u0632\u06af"
    ],
    "wof:name":"Rohuzg",
    "wof:placetype":"locality"
},
  "geometry": {"coordinates":[59.29518,32.33474],"type":"Point"}
}