{
  "type": "Feature",
  "properties": {
    "gn:admin1_code":"4.0",
    "gn:asciiname":"Cheraghan",
    "gn:country_code":"IR",
    "gn:dem":416,
    "gn:feature_class":"P",
    "gn:feature_code":"PPL",
    "gn:name":"Cher\u0101gh\u0101n",
    "gn:population":0,
    "gn:timezone":"Asia/Tehran",
    "iso:country":"IR",
    "name:fas_x_preferred":[
        "Cher\u0101gh\u0101n"
    ],
    "name:fas_x_variant":[
        "Cher\u0101g\u0101h",
        "\u0686\u0631\u0627\u063a\u0627\u0646"
    ],
    "wof:name":"Cheraghan",
    "wof:placetype":"locality"
},
  "geometry": {"coordinates":[61.37846999999999,26.24799],"type":"Point"}
}