{
  "type": "Feature",
  "properties": {
    "gn:admin1_code":"28",
    "gn:asciiname":"Kal Cheshmeh",
    "gn:country_code":"IR",
    "gn:dem":1397,
    "gn:feature_class":"P",
    "gn:feature_code":"PPL",
    "gn:name":"Kal Cheshmeh",
    "gn:population":0,
    "gn:timezone":"Asia/Tehran",
    "iso:country":"IR",
    "name:fas_x_preferred":[
        "\u06a9\u0644 \u0686\u0634\u0645\u0647"
    ],
    "wof:name":"Kal Cheshmeh",
    "wof:placetype":"locality"
},
  "geometry": {"coordinates":[52.753,33.2916],"type":"Point"}
}