{
  "type": "Feature",
  "properties": {
    "gn:admin1_code":"28.0",
    "gn:asciiname":"Senjedcheh-ye Pa'in",
    "gn:country_code":"IR",
    "gn:dem":1756,
    "gn:feature_class":"P",
    "gn:feature_code":"PPL",
    "gn:name":"Senjedcheh-ye Pa\u2019\u012bn",
    "gn:population":0,
    "gn:timezone":"Asia/Tehran",
    "iso:country":"IR",
    "name:fas_x_preferred":[
        "Senjedcheh-ye Pa\u2019\u012bn"
    ],
    "name:fas_x_variant":[
        "\u0633\u0646\u062c\u062f\u0686\u0647 \u067e\u0627\u0626\u06cc\u0646"
    ],
    "wof:name":"Senjedcheh-ye Pa'in",
    "wof:placetype":"locality"
},
  "geometry": {"coordinates":[53.13782,32.96136],"type":"Point"}
}