{
  "type": "Feature",
  "properties": {
    "gn:admin1_code":"0",
    "gn:asciiname":"Mir Sevan",
    "gn:cc2":"IR",
    "gn:country_code":"IR",
    "gn:dem":2007,
    "gn:feature_class":"P",
    "gn:feature_code":"PPL",
    "gn:name":"M\u012br Sev\u0101n",
    "gn:population":0,
    "gn:timezone":"Asia/Tehran",
    "iso:country":"IR",
    "name:fas_x_preferred":[
        "M\u012br Sev\u0101n"
    ],
    "name:und_x_variant":[
        "M\u012brs\u012bvan",
        "M\u012br S\u012bwan"
    ],
    "wof:name":"Mir Sevan",
    "wof:placetype":"locality"
},
  "geometry": {"coordinates":[48.21667,34.03333],"type":"Point"}
}