{
  "type": "Feature",
  "properties": {
    "gn:admin1_code":"5",
    "gn:asciiname":"Bimenjgan",
    "gn:country_code":"IR",
    "gn:dem":689,
    "gn:feature_class":"P",
    "gn:feature_code":"PPL",
    "gn:name":"B\u012bmenjg\u0101n",
    "gn:population":0,
    "gn:timezone":"Asia/Tehran",
    "iso:country":"IR",
    "name:ceb_x_preferred":[
        "B\u012bmenjg\u0101n"
    ],
    "name:fas_x_preferred":[
        "\u0642\u064e\u0644\u0639\u0650\u06c0 \u0628\u0650\u0645\u064a\u0646 \u06af\u0648\u0646"
    ],
    "name:fas_x_variant":[
        "\u0628\u064a\u062f\u0650 \u0645\u064e\u0646\u062c\u0650\u06af\u0627\u0646",
        "\u0628\u064a\u0645\u064e\u0646\u062c\u0650\u06af\u064e\u0646",
        "B\u012bmenjg\u0101n",
        "\u0628\u064a\u0645\u0646\u062c\u06af\u0627\u0646",
        "\u0628\u06cc \u0645\u0646\u062c\u06af\u0627\u0646"
    ],
    "name:swe_x_preferred":[
        "B\u012bmenjg\u0101n"
    ],
    "name:und_x_variant":[
        "Qal\u2018eh-i-Bemingon",
        "B\u012bmanjegan",
        "B\u012bd-e Manjeg\u0101n",
        "Qal\u2018eh-ye Bem\u012bn G\u016bn",
        "\u0628\u064a\u0645\u0646\u062c\u06af\u0627\u0646"
    ],
    "wof:name":"Bimenjgan",
    "wof:placetype":"locality"
},
  "geometry": {"coordinates":[50.55631,30.70304],"type":"Point"}
}