{
  "type": "Feature",
  "properties": {
    "gn:admin1_code":"41",
    "gn:asciiname":"Zohri",
    "gn:country_code":"IR",
    "gn:dem":1760,
    "gn:feature_class":"P",
    "gn:feature_code":"PPL",
    "gn:name":"Zohr\u012b",
    "gn:population":0,
    "gn:timezone":"Asia/Tehran",
    "iso:country":"IR",
    "name:ceb_x_preferred":[
        "Zohr\u012b"
    ],
    "name:fas_x_preferred":[
        "\u0632\u0647\u0631\u06cc"
    ],
    "name:fas_x_variant":[
        "Zohr\u012b"
    ],
    "name:swe_x_preferred":[
        "Zohr\u012b"
    ],
    "name:und_x_variant":[
        "Zohreh"
    ],
    "wof:name":"Zohri",
    "wof:placetype":"locality"
},
  "geometry": {"coordinates":[59.51123000000001,31.99041],"type":"Point"}
}