{
  "type": "Feature",
  "properties": {
    "gn:admin1_code":"26.0",
    "gn:asciiname":"Baqershahr",
    "gn:country_code":"IR",
    "gn:dem":1023,
    "gn:feature_class":"P",
    "gn:feature_code":"PPL",
    "gn:name":"B\u0101qershahr",
    "gn:population":0,
    "gn:timezone":"Asia/Tehran",
    "iso:country":"IR",
    "name:fas_x_preferred":[
        "\u0628\u0627\u0642\u0650\u0631\u0627\u0628\u0627\u062f\u0650 \u0628\u0627\u0642\u0650\u0631\u064f\u0641"
    ],
    "name:fas_x_variant":[
        "\u0628\u0627\u0642\u0650\u0631 \u0622\u0628\u0627\u062f",
        "\u0628\u0627\u0642\u0631 \u0622\u0628\u0627\u062f \u0628\u0627\u0642\u0631\u0627\u0641",
        "B\u0101qer\u0101b\u0101d-e B\u0101qerof",
        "B\u0101qershahr",
        "\u0628\u0627\u0642\u0631\u0634\u0647\u0631"
    ],
    "name:und_x_variant":[
        "B\u0101qer\u0101b\u0101d"
    ],
    "wof:name":"Baqershahr",
    "wof:placetype":"locality"
},
  "geometry": {"coordinates":[51.4048,35.53164],"type":"Point"}
}