{
  "type": "Feature",
  "properties": {
    "gn:admin1_code":"43",
    "gn:asciiname":"Kalateh-ye Dahaneh Delbar",
    "gn:country_code":"IR",
    "gn:dem":984,
    "gn:feature_class":"P",
    "gn:feature_code":"PPL",
    "gn:name":"Kal\u0101teh-ye Dah\u0101neh Delbar",
    "gn:population":0,
    "gn:timezone":"Asia/Tehran",
    "iso:country":"IR",
    "name:fas_x_preferred":[
        "\u062f\u0647\u0646\u0647 \u062f\u0644\u0628\u0631"
    ],
    "name:fas_x_variant":[
        "\u06a9\u0644\u0627\u062a\u0647 \u062f\u0647\u0627\u0646\u0647 \u062f\u0644\u0628\u0631"
    ],
    "name:und_x_variant":[
        "Dahaneh-ye Delbar",
        "\u062f\u0647\u0646\u0647 \u062f\u0644\u0628\u0631",
        "Kal\u0101teh-ye Dah\u0101neh Delbar"
    ],
    "wof:name":"Kalateh-ye Dahaneh Delbar",
    "wof:placetype":"locality"
},
  "geometry": {"coordinates":[56.32294,36.97001],"type":"Point"}
}