{
  "type": "Feature",
  "properties": {
    "gn:admin1_code":"15",
    "gn:asciiname":"Koreyt-e Borumi",
    "gn:country_code":"IR",
    "gn:dem":21,
    "gn:feature_class":"P",
    "gn:feature_code":"PPL",
    "gn:name":"Koreyt-e Bor\u016bm\u012b",
    "gn:population":0,
    "gn:timezone":"Asia/Tehran",
    "iso:country":"IR",
    "name:ara_x_preferred":[
        "\u0643\u0631\u064a\u062a \u0628\u0631\u0648\u0645\u064a"
    ],
    "name:azb_x_preferred":[
        "\u0643\u0631\u06cc\u062a \u0628\u0631\u0648\u0645\u06cc(\u0627\u0647\u0648\u0627\u0632)"
    ],
    "name:fas_x_preferred":[
        "\u06a9\u0631\u06cc\u062a \u0628\u0631\u0648\u0645\u06cc"
    ],
    "name:fas_x_variant":[
        "Koreyt-e Bor\u016bm\u012b"
    ],
    "name:und_x_variant":[
        "Karet",
        "Koreyt",
        "Qarait",
        "Koreyt-e Do"
    ],
    "wof:name":"Koreyt-e Borumi",
    "wof:placetype":"locality"
},
  "geometry": {"coordinates":[48.81994,31.28126],"type":"Point"}
}