{
  "type": "Feature",
  "properties": {
    "gn:admin1_code":"8",
    "gn:asciiname":"Azgam",
    "gn:country_code":"IR",
    "gn:dem":-14,
    "gn:feature_class":"P",
    "gn:feature_code":"PPL",
    "gn:name":"Azgam",
    "gn:population":0,
    "gn:timezone":"Asia/Tehran",
    "iso:country":"IR",
    "name:ceb_x_preferred":[
        "Azgam"
    ],
    "name:fas_x_preferred":[
        "\u0627\u0632\u06af\u0645"
    ],
    "name:msa_x_preferred":[
        "Azgam"
    ],
    "name:swe_x_preferred":[
        "Azgam"
    ],
    "name:ukr_x_preferred":[
        "\u0410\u0437\u0491\u0430\u043c"
    ],
    "wof:name":"Azgam",
    "wof:placetype":"locality"
},
  "geometry": {"coordinates":[49.3436,37.3478],"type":"Point"}
}