{
  "type": "Feature",
  "properties": {
    "gn:admin1_code":"11",
    "gn:asciiname":"Salahu",
    "gn:country_code":"IR",
    "gn:dem":33,
    "gn:feature_class":"P",
    "gn:feature_code":"PPL",
    "gn:name":"\u015eal\u0101h\u016b",
    "gn:population":0,
    "gn:timezone":"Asia/Tehran",
    "iso:country":"IR",
    "name:fas_x_preferred":[
        "\u015eal\u0101h\u016b"
    ],
    "name:fas_x_variant":[
        "\u0635\u0644\u0627\u0647\u0648"
    ],
    "name:msa_x_preferred":[
        "Salahu"
    ],
    "wof:name":"Salahu",
    "wof:placetype":"locality"
},
  "geometry": {"coordinates":[58.87742,25.68254],"type":"Point"}
}