{
  "type": "Feature",
  "properties": {
    "gn:admin1_code":"42.0",
    "gn:asciiname":"Nowbahar",
    "gn:country_code":"IR",
    "gn:dem":1218,
    "gn:feature_class":"P",
    "gn:feature_code":"PPL",
    "gn:name":"Nowbah\u0101r",
    "gn:population":0,
    "gn:timezone":"Asia/Tehran",
    "iso:country":"IR",
    "name:fas_x_preferred":[
        "\u0646\u0648\u0628\u0647\u0627\u0631"
    ],
    "name:fas_x_variant":[
        "Nowb\u0101h\u0101r",
        "Nowbah\u0101r"
    ],
    "wof:name":"Nowbahar",
    "wof:placetype":"locality"
},
  "geometry": {"coordinates":[59.1162,35.98174],"type":"Point"}
}