{
  "type": "Feature",
  "properties": {
    "gn:admin1_code":"43.0",
    "gn:asciiname":"Qarah Meydan-e Bozorg",
    "gn:country_code":"IR",
    "gn:dem":630,
    "gn:feature_class":"P",
    "gn:feature_code":"PPL",
    "gn:name":"Qarah Meyd\u0101n-e Bozorg",
    "gn:population":0,
    "gn:timezone":"Asia/Tehran",
    "iso:country":"IR",
    "name:fas_x_preferred":[
        "\u0642\u0631\u0647 \u0645\u064a\u062f\u0627\u0646 \u0628\u0632\u0631\u06af"
    ],
    "name:und_x_variant":[
        "Qarah Meyd\u0101n-e Bozorg",
        "Qarah Meyd\u0101n"
    ],
    "wof:name":"Qarah Meydan-e Bozorg",
    "wof:placetype":"locality"
},
  "geometry": {"coordinates":[56.54087,37.68094],"type":"Point"}
}