{
  "type": "Feature",
  "properties": {
    "gn:admin1_code":"29",
    "gn:asciiname":"Mazra`eh-ye Sargari",
    "gn:country_code":"IR",
    "gn:dem":1343,
    "gn:feature_class":"P",
    "gn:feature_code":"PPLF",
    "gn:name":"Mazra\u2018eh-ye Sargar\u012b",
    "gn:population":0,
    "gn:timezone":"Asia/Tehran",
    "iso:country":"IR",
    "name:fas_x_preferred":[
        "\u0633\u0631\u06af\u0631\u06cc"
    ],
    "name:fas_x_variant":[
        "Sargar\u012b",
        "\u0645\u0632\u0631\u0639\u0647 \u0633\u0631\u06af\u0631\u06cc"
    ],
    "name:und_x_variant":[
        "Mazra\u2018eh-ye Sargar\u012b"
    ],
    "wof:name":"Mazra`eh-ye Sargari",
    "wof:placetype":"locality"
},
  "geometry": {"coordinates":[58.64629,28.36221],"type":"Point"}
}