{
  "type": "Feature",
  "properties": {
    "gn:admin1_code":"41",
    "gn:asciiname":"Jannatabad-e Galandar",
    "gn:country_code":"IR",
    "gn:dem":1846,
    "gn:feature_class":"P",
    "gn:feature_code":"PPL",
    "gn:name":"Jannat\u0101b\u0101d-e Galandar",
    "gn:population":0,
    "gn:timezone":"Asia/Tehran",
    "iso:country":"IR",
    "name:fas_x_preferred":[
        "\u06a9\u0644\u0627\u062a \u062c\u062f\u06cc\u062f"
    ],
    "name:fas_x_variant":[
        "Jannat\u0101b\u0101d",
        "Kalkast\u016bn",
        "Kal\u0101teh-ye Jad\u012bn",
        "Kal\u0101t-e Jad\u012bd",
        "\u062c\u0646\u062a \u0622\u0628\u0627\u062f \u06af\u0644\u0646\u062f\u0631",
        "\u062c\u0646\u062a \u0622\u0628\u0627\u062f"
    ],
    "name:und_x_variant":[
        "Kal\u0101teh Jad\u012bn",
        "Kal\u0101teh-ye Jad\u012bd",
        "Kal\u0101teh Jad\u012bd",
        "Jannat\u0101b\u0101d-e Galandar"
    ],
    "wof:name":"Jannatabad-e Galandar",
    "wof:placetype":"locality"
},
  "geometry": {"coordinates":[59.62921,32.41478],"type":"Point"}
}