{
  "type": "Feature",
  "properties": {
    "gn:admin1_code":"35.0",
    "gn:asciiname":"Pet Now",
    "gn:country_code":"IR",
    "gn:dem":1547,
    "gn:feature_class":"P",
    "gn:feature_code":"PPL",
    "gn:name":"Pet Now",
    "gn:population":0,
    "gn:timezone":"Asia/Tehran",
    "iso:country":"IR",
    "name:fas_x_preferred":[
        "\u067e\u0650\u062a \u0646\u064f\u0648"
    ],
    "wof:name":"Pet Now",
    "wof:placetype":"locality"
},
  "geometry": {"coordinates":[53.95028000000001,36.58222],"type":"Point"}
}