{
  "type": "Feature",
  "properties": {
    "gn:admin1_code":"3.0",
    "gn:asciiname":"`Algi-ye `Olya",
    "gn:country_code":"IR",
    "gn:dem":1951,
    "gn:feature_class":"P",
    "gn:feature_code":"PPL",
    "gn:name":"\u2018Alg\u012b-ye \u2018Oly\u0101",
    "gn:population":0,
    "gn:timezone":"Asia/Tehran",
    "iso:country":"IR",
    "name:fas_x_preferred":[
        "\u2018Alg\u012b-ye \u2018Oly\u0101"
    ],
    "name:fas_x_variant":[
        "\u0639\u0644\u06af\u06cc \u0639\u0644\u06cc\u0627"
    ],
    "wof:name":"`Algi-ye `Olya",
    "wof:placetype":"locality"
},
  "geometry": {"coordinates":[50.02216,32.30635],"type":"Point"}
}