{
  "type": "Feature",
  "properties": {
    "gn:admin1_code":"28.0",
    "gn:asciiname":"Khatunabad",
    "gn:country_code":"IR",
    "gn:dem":1556,
    "gn:feature_class":"P",
    "gn:feature_code":"PPL",
    "gn:name":"Kh\u0101t\u016bn\u0101b\u0101d",
    "gn:population":0,
    "gn:timezone":"Asia/Tehran",
    "iso:country":"IR",
    "name:fas_x_preferred":[
        "Kh\u0101t\u016bn\u0101b\u0101d"
    ],
    "name:fas_x_variant":[
        "\u062e\u0627\u062a\u0648\u0646 \u0622\u0628\u0627\u062f",
        "\u062e\u0627\u062a\u0648\u0646\u200c\u0622\u0628\u0627\u062f"
    ],
    "wof:name":"Khatunabad",
    "wof:placetype":"locality"
},
  "geometry": {"coordinates":[51.78895,32.66086],"type":"Point"}
}