{
  "type": "Feature",
  "properties": {
    "gn:admin1_code":"1",
    "gn:asciiname":"Kusalar-e Sofla",
    "gn:country_code":"IR",
    "gn:dem":1288,
    "gn:feature_class":"P",
    "gn:feature_code":"PPL",
    "gn:name":"K\u016bs\u0101l\u0101r-e Sofl\u00e1",
    "gn:population":0,
    "gn:timezone":"Asia/Tehran",
    "iso:country":"IR",
    "name:azb_x_preferred":[
        "\u0622\u0634\u0627\u063a\u06cc \u06a9\u0648\u0652\u0633\u0627\u0644\u0627\u0631(\u0642\u0648\u0634\u0627\u0686\u0627\u06cc)"
    ],
    "name:aze_x_preferred":[
        "A\u015fa\u011f\u0131 Kosalar"
    ],
    "name:ceb_x_preferred":[
        "K\u016bs\u0101l\u0101r-e Sofl\u00e1"
    ],
    "name:fas_x_preferred":[
        "\u06a9\u0648\u0633\u0627\u0644\u0627\u0631 \u0633\u0641\u0644\u06cc"
    ],
    "name:fas_x_variant":[
        "\u0643\u0648\u0633\u0647 \u0644\u0631 \u0633\u0641\u0644\u0649",
        "K\u016bsehlar-e Sofl\u00e1",
        "\u0643\u0648\u0633\u0650\u0647\u0644\u064e\u0631",
        "K\u016bs\u0101l\u0101r-e Sofl\u00e1",
        "\u06a9\u0648\u0633\u0647\u200c\u0644\u0631 \u0633\u0641\u0644\u06cc"
    ],
    "name:msa_x_preferred":[
        "Kusehlar-e Sofla"
    ],
    "name:swe_x_preferred":[
        "K\u016bs\u0101l\u0101r-e Sofl\u00e1"
    ],
    "name:und_x_variant":[
        "K\u016bsehlar"
    ],
    "wof:name":"Kusalar-e Sofla",
    "wof:placetype":"locality"
},
  "geometry": {"coordinates":[46.0605,37.0466],"type":"Point"}
}