{
  "type": "Feature",
  "properties": {
    "gn:admin1_code":"29",
    "gn:asciiname":"Gorgin",
    "gn:country_code":"IR",
    "gn:dem":1685,
    "gn:feature_class":"P",
    "gn:feature_code":"PPL",
    "gn:name":"Gorg\u012bn",
    "gn:population":0,
    "gn:timezone":"Asia/Tehran",
    "iso:country":"IR",
    "name:ara_x_preferred":[
        "\u063a\u0631\u063a\u064a\u0646"
    ],
    "name:fas_x_preferred":[
        "\u06af\u0631\u06af\u06cc\u0646"
    ],
    "name:fas_x_variant":[
        "Gorg\u012bn",
        "\u06a9\u0631\u06af\u06cc\u0646"
    ],
    "name:und_x_variant":[
        "Kirgin",
        "Karg\u012bn",
        "Kerg\u012bn"
    ],
    "wof:name":"Gorgin",
    "wof:placetype":"locality"
},
  "geometry": {"coordinates":[56.1787,28.7992],"type":"Point"}
}