{
  "type": "Feature",
  "properties": {
    "gn:admin1_code":"13",
    "gn:asciiname":"Kol Kol",
    "gn:country_code":"IR",
    "gn:dem":1862,
    "gn:feature_class":"P",
    "gn:feature_code":"PPL",
    "gn:name":"Kol Kol",
    "gn:population":0,
    "gn:timezone":"Asia/Tehran",
    "iso:country":"IR",
    "name:fas_x_preferred":[
        "\u06a9\u0644 \u06a9\u0644"
    ],
    "name:und_x_variant":[
        "Gol Gol",
        "Kulkul",
        "Kol Kol"
    ],
    "wof:name":"Kol Kol",
    "wof:placetype":"locality"
},
  "geometry": {"coordinates":[47.52689,34.98042],"type":"Point"}
}