{
  "type": "Feature",
  "properties": {
    "gn:admin1_code":"26.0",
    "gn:asciiname":"Dir Kaj",
    "gn:country_code":"IR",
    "gn:dem":858,
    "gn:feature_class":"P",
    "gn:feature_code":"PPL",
    "gn:name":"D\u012br K\u0101j",
    "gn:population":0,
    "gn:timezone":"Asia/Tehran",
    "iso:country":"IR",
    "name:und_x_variant":[
        "D\u012br K\u0101j"
    ],
    "wof:name":"Dir Kaj",
    "wof:placetype":"locality"
},
  "geometry": {"coordinates":[51.46917,35.15],"type":"Point"}
}