{
  "type": "Feature",
  "properties": {
    "gn:admin1_code":"29.0",
    "gn:asciiname":"Ab Yad-e Qahremani",
    "gn:country_code":"IR",
    "gn:dem":1871,
    "gn:feature_class":"P",
    "gn:feature_code":"PPL",
    "gn:name":"\u0100b Y\u0101d-e Qahrem\u0101n\u012b",
    "gn:population":0,
    "gn:timezone":"Asia/Tehran",
    "iso:country":"IR",
    "name:fas_x_preferred":[
        "\u0622\u0628 \u06cc\u0627\u062f \u0642\u0647\u0631\u0645\u0627\u0646\u06cc"
    ],
    "name:fas_x_variant":[
        "\u0100b B\u0101d-e Qahrem\u0101n\u012b",
        "\u0100b Y\u0101d-e Qahrem\u0101n\u012b",
        "\u0622\u0628\u0627\u062f \u0642\u0647\u0631\u0645\u0627\u0646",
        "\u0622\u0628\u0628\u0627\u062f \u0642\u0647\u0631\u0645\u0627\u0646\u06cc"
    ],
    "name:und_x_variant":[
        "\u0100b\u0101d-e Qahrem\u0101n",
        "\u0100bb\u0101d-e Qahrem\u0101n\u012b"
    ],
    "wof:name":"Ab Yad-e Qahremani",
    "wof:placetype":"locality"
},
  "geometry": {"coordinates":[56.2626,28.8267],"type":"Point"}
}