{
  "type": "Feature",
  "properties": {
    "gn:admin1_code":"33",
    "gn:asciiname":"Divrazm",
    "gn:country_code":"IR",
    "gn:dem":1611,
    "gn:feature_class":"P",
    "gn:feature_code":"PPL",
    "gn:name":"D\u012bvrazm",
    "gn:population":0,
    "gn:timezone":"Asia/Tehran",
    "iso:country":"IR",
    "name:fas_x_preferred":[
        "\u062f\u06cc\u0648\u0631\u0632\u0645"
    ],
    "name:fas_x_variant":[
        "D\u012bvrazm",
        "\u062f\u0648\u0647 \u0632\u06cc\u0645"
    ],
    "name:und_x_variant":[
        "Davehz\u012bm"
    ],
    "wof:name":"Divrazm",
    "wof:placetype":"locality"
},
  "geometry": {"coordinates":[46.3717,37.3233],"type":"Point"}
}