{
  "type": "Feature",
  "properties": {
    "gn:admin1_code":"29",
    "gn:asciiname":"Rahmatabad-e Kataki",
    "gn:country_code":"IR",
    "gn:dem":414,
    "gn:feature_class":"P",
    "gn:feature_code":"PPLF",
    "gn:name":"Ra\u1e29mat\u0101b\u0101d-e Katak\u012b",
    "gn:population":0,
    "gn:timezone":"Asia/Tehran",
    "iso:country":"IR",
    "name:fas_x_preferred":[
        "\u062d\u0633\u06cc\u0646 \u0622\u0628\u0627\u062f"
    ],
    "name:fas_x_variant":[
        "\u1e28oseyn\u0101b\u0101d",
        "\u0631\u062d\u0645\u062a \u0622\u0628\u0627\u062f \u06a9\u062a\u06a9\u06cc",
        "\u0631\u062d\u0645\u062a\u200c\u0622\u0628\u0627\u062f \u06a9\u062a\u06a9\u06cc"
    ],
    "name:und_x_variant":[
        "Ra\u1e29mat\u0101b\u0101d-e Katak\u012b"
    ],
    "wof:name":"Rahmatabad-e Kataki",
    "wof:placetype":"locality"
},
  "geometry": {"coordinates":[58.395,27.82425],"type":"Point"}
}