{
  "type": "Feature",
  "properties": {
    "gn:admin1_code":"41",
    "gn:asciiname":"Khurgaz",
    "gn:country_code":"IR",
    "gn:dem":1463,
    "gn:feature_class":"P",
    "gn:feature_code":"PPLL",
    "gn:name":"Kh\u016brgaz",
    "gn:population":0,
    "gn:timezone":"Asia/Tehran",
    "iso:country":"IR",
    "name:fas_x_preferred":[
        "\u062e\u0648\u0631\u06af\u0632"
    ],
    "name:fas_x_variant":[
        "Kh\u016brgaz",
        "\u062c\u0645\u062c\u0645\u0647"
    ],
    "name:und_x_variant":[
        "Jamjameh"
    ],
    "wof:name":"Khurgaz",
    "wof:placetype":"locality"
},
  "geometry": {"coordinates":[59.33554,31.53281],"type":"Point"}
}