{
  "type": "Feature",
  "properties": {
    "gn:admin1_code":"7",
    "gn:asciiname":"Gharbi",
    "gn:country_code":"IR",
    "gn:dem":1244,
    "gn:feature_class":"P",
    "gn:feature_code":"PPL",
    "gn:name":"Gharb\u012b",
    "gn:population":0,
    "gn:timezone":"Asia/Tehran",
    "iso:country":"IR",
    "name:fas_x_preferred":[
        "\u063a\u0631\u0628\u06cc"
    ],
    "name:fas_x_variant":[
        "Gharb\u012b"
    ],
    "name:msa_x_preferred":[
        "Gharbi"
    ],
    "wof:name":"Gharbi",
    "wof:placetype":"locality"
},
  "geometry": {"coordinates":[53.2455,28.939],"type":"Point"}
}