{
  "type": "Feature",
  "properties": {
    "gn:admin1_code":"23",
    "gn:asciiname":"Cheleh Ban",
    "gn:country_code":"IR",
    "gn:dem":1005,
    "gn:feature_class":"P",
    "gn:feature_code":"PPL",
    "gn:name":"Cheleh B\u0101n",
    "gn:population":0,
    "gn:timezone":"Asia/Tehran",
    "iso:country":"IR",
    "name:fas_x_preferred":[
        "\u0686\u0644\u0647 \u0628\u0627\u0646"
    ],
    "name:fas_x_variant":[
        "N\u016br\u2018al\u012b Chelehb\u0101n"
    ],
    "name:und_x_variant":[
        "Cheleh B\u0101n"
    ],
    "wof:name":"Cheleh Ban",
    "wof:placetype":"locality"
},
  "geometry": {"coordinates":[47.13945,33.41514],"type":"Point"}
}