{
  "type": "Feature",
  "properties": {
    "gn:admin1_code":"4",
    "gn:asciiname":"Anari",
    "gn:country_code":"IR",
    "gn:dem":1189,
    "gn:feature_class":"P",
    "gn:feature_code":"PPL",
    "gn:name":"An\u0101r\u012b",
    "gn:population":0,
    "gn:timezone":"Asia/Tehran",
    "iso:country":"IR",
    "name:fas_x_preferred":[
        "\u0627\u0646\u0627\u0631\u06cc"
    ],
    "name:fas_x_variant":[
        "An\u0101r\u012b"
    ],
    "wof:name":"Anari",
    "wof:placetype":"locality"
},
  "geometry": {"coordinates":[61.04571,27.05304000000001],"type":"Point"}
}