{
  "type": "Feature",
  "properties": {
    "gn:admin1_code":"33",
    "gn:asciiname":"Tarun",
    "gn:country_code":"IR",
    "gn:dem":1614,
    "gn:feature_class":"P",
    "gn:feature_code":"PPL",
    "gn:name":"\u0162\u0101r\u016bn",
    "gn:population":0,
    "gn:timezone":"Asia/Tehran",
    "iso:country":"IR",
    "name:fas_x_preferred":[
        "\u0637\u0627\u0631\u0648\u0646"
    ],
    "name:fas_x_variant":[
        "T\u0101r\u016bn",
        "\u0162\u0101r\u016bn"
    ],
    "name:msa_x_preferred":[
        "Tarun"
    ],
    "name:und_x_variant":[
        "\u0162\u0101rom",
        "\u0162\u0101r\u0101n"
    ],
    "wof:name":"Tarun",
    "wof:placetype":"locality"
},
  "geometry": {"coordinates":[47.871,37.7342],"type":"Point"}
}