{
  "type": "Feature",
  "properties": {
    "gn:admin1_code":"28.0",
    "gn:asciiname":"`Asgaran Karvan",
    "gn:country_code":"IR",
    "gn:dem":2143,
    "gn:feature_class":"P",
    "gn:feature_code":"PPL",
    "gn:name":"\u2018Asgar\u0101n Karvan",
    "gn:population":0,
    "gn:timezone":"Asia/Tehran",
    "iso:country":"IR",
    "name:fas_x_preferred":[
        "\u2018Asgar\u0101n"
    ],
    "name:fas_x_variant":[
        "\u2018Asgar\u0101n Karvan",
        "\u0639\u0633\u06af\u0631\u0627\u0646 \u06a9\u0631\u0648\u0646"
    ],
    "name:und_x_variant":[
        "\u2018Askar\u0101n",
        "\u0639\u0633\u06af\u0631\u0627\u0646 \u06a9\u0631\u0648\u0646"
    ],
    "wof:name":"`Asgaran Karvan",
    "wof:placetype":"locality"
},
  "geometry": {"coordinates":[50.85321,32.86427],"type":"Point"}
}