{
  "type": "Feature",
  "properties": {
    "gn:admin1_code":"37",
    "gn:asciiname":"Qaranjik-e Pur Arman",
    "gn:country_code":"IR",
    "gn:dem":-6,
    "gn:feature_class":"P",
    "gn:feature_code":"PPL",
    "gn:name":"Qaranj\u012bk-e P\u016br \u0100rm\u0101n",
    "gn:population":0,
    "gn:timezone":"Asia/Tehran",
    "iso:country":"IR",
    "name:ara_x_preferred":[
        "\u0642\u0631\u0646\u062c\u064a\u0643 \u0628\u0648\u0631 \u0627\u0645\u0627\u0646"
    ],
    "name:fas_x_preferred":[
        "Qaranj\u012bk-e P\u016br Am\u0101n"
    ],
    "name:fas_x_variant":[
        "\u0642\u0631\u0646\u062c\u064a\u06a9 \u067e\u0648\u0631 \u0627\u0645\u0627\u0646",
        "\u0642\u0631\u0646\u062c\u064a\u06a9 \u067e\u0648\u0631 \u0622\u0631\u0645\u0627\u0646",
        "\u0642\u0631\u0646\u062c\u06cc\u06a9\u200c\u067e\u0648\u0631\u0627\u0645\u0627\u0646"
    ],
    "name:msa_x_preferred":[
        "Qaranjik-e Pur Aman"
    ],
    "name:und_x_variant":[
        "Qaranj\u012bk-e L\u016br\u0101m\u0101n",
        "\u0642\u0631\u0646\u062c\u064a\u06a9 \u067e\u0648\u0631 \u0627\u0645\u0627\u0646",
        "Qaranj\u012bk-e P\u016br \u0100rm\u0101n"
    ],
    "wof:name":"Qaranjik-e Pur Arman",
    "wof:placetype":"locality"
},
  "geometry": {"coordinates":[54.54156,37.06603],"type":"Point"}
}