{
  "type": "Feature",
  "properties": {
    "gn:admin1_code":"29",
    "gn:asciiname":"Rulardu",
    "gn:country_code":"IR",
    "gn:dem":2066,
    "gn:feature_class":"P",
    "gn:feature_code":"PPL",
    "gn:name":"R\u016blard\u016b",
    "gn:population":0,
    "gn:timezone":"Asia/Tehran",
    "iso:country":"IR",
    "name:fas_x_preferred":[
        "\u0631\u0648\u0644\u0631\u062f\u0648"
    ],
    "name:fas_x_variant":[
        "R\u016blard\u016b"
    ],
    "wof:name":"Rulardu",
    "wof:placetype":"locality"
},
  "geometry": {"coordinates":[57.26104,30.51172],"type":"Point"}
}