{
  "type": "Feature",
  "properties": {
    "gn:admin1_code":"36",
    "gn:asciiname":"Chuljeh Qeshlaq",
    "gn:country_code":"IR",
    "gn:dem":1553,
    "gn:feature_class":"P",
    "gn:feature_code":"PPL",
    "gn:name":"Ch\u016bljeh Qeshl\u0101q",
    "gn:population":0,
    "gn:timezone":"Asia/Tehran",
    "iso:country":"IR",
    "name:fas_x_preferred":[
        "\u0686\u0644\u062c\u0647 \u0642\u0634\u0644\u0627\u0642"
    ],
    "name:fas_x_variant":[
        "\u0686\u0648\u0644\u0686\u0650\u0647 \u0642\u0650\u0634\u0644\u0627\u0642",
        "\u0686\u0648\u0644\u0686\u0650\u0647",
        "\u0686\u064f\u0644\u062f\u0698\u0650\u062e",
        "\u0686\u0648\u0644\u0650\u0647",
        "\u0686\u064f\u0648\u0644\u062c\u0650\u0647 \u0642\u0650\u0634\u0644\u0627\u0642",
        "\u0686\u064f\u0648\u0644\u0686\u0650\u0647 \u0642\u0650\u0634\u0644\u0627\u0642",
        "\u0686\u0648\u0644\u062c\u0650\u0647 \u0642\u0650\u0634\u0644\u0627\u0642",
        "\u0686\u064f\u0644\u062c\u064e\u0647 \u0642\u0650\u0634\u0644\u0627\u0642",
        "\u0686\u064f\u0651\u0644\u062c\u0650\u0647 \u063a\u0650\u0633\u0644\u064e\u063a",
        "Choljeh Qeshl\u0101q",
        "\u0686\u0648\u0644\u062c\u0647 \u0642\u0634\u0644\u0627\u0642"
    ],
    "name:und_x_variant":[
        "Chowlcheh Qeshl\u0101q",
        "Chooljeh Gheslagh",
        "Ch\u016bleh",
        "Ch\u016blcheh Qeshl\u0101q",
        "Choldzhekh",
        "Ch\u016blcheh",
        "Chowljeh Qeshl\u0101q",
        "Choljah Qeshl\u0101q",
        "Ch\u016bljeh Qeshl\u0101q"
    ],
    "wof:name":"Chuljeh Qeshlaq",
    "wof:placetype":"locality"
},
  "geometry": {"coordinates":[48.09399000000001,36.23533],"type":"Point"}
}