{
  "type": "Feature",
  "properties": {
    "gn:admin1_code":"5.0",
    "gn:asciiname":"`Avaz Khadir",
    "gn:country_code":"IR",
    "gn:dem":2293,
    "gn:feature_class":"P",
    "gn:feature_code":"PPL",
    "gn:name":"\u2018Ava\u1e95 Khad\u012br",
    "gn:population":0,
    "gn:timezone":"Asia/Tehran",
    "iso:country":"IR",
    "name:fas_x_preferred":[
        "\u0639\u0648\u0636 \u062e\u062f\u06cc\u0631"
    ],
    "name:fas_x_variant":[
        "\u0628\u0647\u0627\u0631\u0647 \u0645\u0644\u0647 \u0646\u0627\u0645\u062f\u0627\u0631\u0627\u0646 \u0639\u0648\u0636"
    ],
    "name:und_x_variant":[
        "\u2018Ava\u1e95 Khad\u012br",
        "Bah\u0101reh Meleh-ye N\u0101md\u0101r\u0101n-e \u2018Ava\u1e95"
    ],
    "wof:name":"`Avaz Khadir",
    "wof:placetype":"locality"
},
  "geometry": {"coordinates":[50.82724,31.03917],"type":"Point"}
}