{
  "type": "Feature",
  "properties": {
    "gn:admin1_code":"29",
    "gn:asciiname":"Bahaabad-e Sofla",
    "gn:country_code":"IR",
    "gn:dem":1721,
    "gn:feature_class":"P",
    "gn:feature_code":"PPL",
    "gn:name":"Bah\u0101\u0101b\u0101d-e Sofl\u00e1",
    "gn:population":0,
    "gn:timezone":"Asia/Tehran",
    "iso:country":"IR",
    "name:fas_x_preferred":[
        "Beh\u0101b\u0101d-e P\u0101\u2019\u012bn"
    ],
    "name:fas_x_variant":[
        "\u0628\u0647\u0627 \u0622\u0628\u0627\u062f \u0633\u0641\u0644\u06cc"
    ],
    "name:und_x_variant":[
        "Bah\u0101\u0101b\u0101d-e Sofl\u00e1"
    ],
    "wof:name":"Bahaabad-e Sofla",
    "wof:placetype":"locality"
},
  "geometry": {"coordinates":[55.56933000000001,29.55368],"type":"Point"}
}