{
  "type": "Feature",
  "properties": {
    "gn:country":"IR",
    "gn:fcode":"PPL",
    "gn:pop":36709,
    "iso:country":"IR",
    "name:ara_x_preferred":[
        "\u0627\u0642\u0628\u0627\u0644\u064a\u0629"
    ],
    "name:azb_x_preferred":[
        "\u0627\u0642\u0628\u0627\u0644\u06cc\u0647"
    ],
    "name:aze_x_preferred":[
        "\u0130qbaliy\u0259"
    ],
    "name:fas_x_preferred":[
        "\u0627\u0642\u0628\u0627\u0644\u064a\u0651\u0647"
    ],
    "name:fas_x_variant":[
        "Eqb\u0101l\u012byeh",
        "\u0627\u0642\u0628\u0627\u0644\u06cc\u0647"
    ],
    "name:hin_x_preferred":[
        "\u0907\u0915\u092c\u093e\u0932\u093f\u092f\u093e\u0939"
    ],
    "name:ita_x_preferred":[
        "Eqbaliyeh"
    ],
    "name:mlg_x_preferred":[
        "Eqbaliyeh"
    ],
    "name:pol_x_preferred":[
        "Eghbalije"
    ],
    "name:rus_x_preferred":[
        "\u0421\u043e\u043b\u044c\u0442\u0430\u043d\u0430\u0431\u0430\u0434"
    ],
    "name:tur_x_preferred":[
        "\u0130kbaliye"
    ],
    "name:urd_x_preferred":[
        "\u0627\u0642\u0628\u0627\u0644\u06cc\u06c1"
    ],
    "qs:name":"Eqb\u0101l\u012byeh",
    "qs:photos_9r":0,
    "qs:photos_sr":0,
    "qs:pop_sr":"7",
    "wd:wordcount":108,
    "wof:name":"Eqb\u0101l\u012byeh",
    "wof:placetype":"locality",
    "wof:population":36709
},
  "geometry": {"coordinates":[51.5358,35.3022],"type":"Point"}
}