{
  "type": "Feature",
  "properties": {
    "gn:country":"IR",
    "gn:fcode":"PPL",
    "gn:pop":36709,
    "iso:country":"IR",
    "name:fas_x_preferred":[
        "\u0627\u0642\u0628\u0627\u0644\u064a\u0651\u0647"
    ],
    "name:fas_x_variant":[
        "Eqb\u0101l\u012byeh"
    ],
    "qs:name":"Eqb\u0101l\u012byeh",
    "qs:photos_9r":0,
    "qs:photos_sr":0,
    "qs:pop_sr":"7",
    "wd:wordcount":108,
    "wof:name":"Eqb\u0101l\u012byeh",
    "wof:placetype":"locality",
    "wof:population":36709
},
  "geometry": {"coordinates":[51.5358,35.3022],"type":"Point"}
}