{
  "type": "Feature",
  "properties": {
    "gn:admin1_code":"26.0",
    "gn:asciiname":"Kureh Farangi",
    "gn:country_code":"IR",
    "gn:dem":1019,
    "gn:feature_class":"P",
    "gn:feature_code":"PPL",
    "gn:name":"K\u016breh Farang\u012b",
    "gn:population":0,
    "gn:timezone":"Asia/Tehran",
    "iso:country":"IR",
    "name:fas_x_preferred":[
        "\u06a9\u0648\u0631\u0647 \u0641\u0631\u0646\u06af\u06cc"
    ],
    "name:und_x_variant":[
        "K\u016breh Farang\u012b"
    ],
    "wof:name":"Kureh Farangi",
    "wof:placetype":"locality"
},
  "geometry": {"coordinates":[51.50674,35.55695],"type":"Point"}
}