{
  "type": "Feature",
  "properties": {
    "gn:admin1_code":"37",
    "gn:asciiname":"Kord Kuy",
    "gn:country_code":"IR",
    "gn:dem":-2,
    "gn:feature_class":"P",
    "gn:feature_code":"PPLA2",
    "gn:name":"Kord K\u016by",
    "gn:population":0,
    "gn:timezone":"Asia/Tehran",
    "iso:country":"IR",
    "name:ara_x_preferred":[
        "\u0643\u0631\u062f\u0643\u0648\u064a"
    ],
    "name:aze_x_preferred":[
        "K\u00fcrdk\u00f6y"
    ],
    "name:fas_x_preferred":[
        "\u0643\u0631\u062f\u0643\u0648\u06cc"
    ],
    "name:fas_x_variant":[
        "\u0643\u064f\u0631\u062f \u0643\u0648",
        "\u06a9\u0631\u062f \u06a9\u0648\u06cc",
        "\u06a9\u0631\u062f\u06a9\u0648\u06cc"
    ],
    "name:ita_x_preferred":[
        "Kordkuy"
    ],
    "name:mlg_x_preferred":[
        "Kordkuy"
    ],
    "name:msa_x_preferred":[
        "Kordkuy"
    ],
    "name:mzn_x_preferred":[
        "\u06a9\u0631\u062f\u06a9\u0648\u06cc"
    ],
    "name:pnb_x_preferred":[
        "\u06a9\u0631\u062f\u06a9\u0648\u06cc"
    ],
    "name:ron_x_preferred":[
        "Kordkuy"
    ],
    "name:rus_x_preferred":[
        "\u041a\u043e\u0440\u0434\u043a\u0443\u0439"
    ],
    "name:spa_x_preferred":[
        "Kordkuy"
    ],
    "name:tgk_x_preferred":[
        "\u041a\u0443\u0440\u0434\u043a\u04ef\u0439"
    ],
    "name:tur_x_preferred":[
        "K\u00fcrdk\u00f6y"
    ],
    "name:und_x_variant":[
        "Kurd K\u016bi",
        "Kord K\u016b",
        "Kord K\u016by"
    ],
    "name:zho_x_preferred":[
        "\u79d1\u723e\u5fb7\u5eab\u4f0a"
    ],
    "wof:name":"Kord Kuy",
    "wof:placetype":"locality"
},
  "geometry": {"coordinates":[54.11214,36.79307],"type":"Point"}
}