{
  "type": "Feature",
  "properties": {
    "gn:admin1_code":"37",
    "gn:asciiname":"Kord Kuy",
    "gn:country_code":"IR",
    "gn:dem":-2,
    "gn:feature_class":"P",
    "gn:feature_code":"PPLA2",
    "gn:name":"Kord K\u016by",
    "gn:population":0,
    "gn:timezone":"Asia/Tehran",
    "iso:country":"IR",
    "name:fas_x_preferred":[
        "\u0643\u0631\u062f\u0643\u0648\u06cc"
    ],
    "name:fas_x_variant":[
        "\u0643\u064f\u0631\u062f \u0643\u0648",
        "\u06a9\u0631\u062f \u06a9\u0648\u06cc"
    ],
    "name:und_x_variant":[
        "Kurd K\u016bi",
        "Kord K\u016b",
        "Kord K\u016by"
    ],
    "wof:name":"Kord Kuy",
    "wof:placetype":"locality"
},
  "geometry": {"coordinates":[54.11214,36.79307],"type":"Point"}
}