{
  "type": "Feature",
  "properties": {
    "gn:admin1_code":"4.0",
    "gn:asciiname":"Firuzeh'i",
    "gn:country_code":"IR",
    "gn:dem":480,
    "gn:feature_class":"P",
    "gn:feature_code":"PPL",
    "gn:name":"F\u012br\u016bzeh\u2019\u012b",
    "gn:population":0,
    "gn:timezone":"Asia/Tehran",
    "iso:country":"IR",
    "name:fas_x_preferred":[
        "\u0641\u06cc\u0631\u0648\u0632\u0647 \u0627\u06cc"
    ],
    "name:fas_x_variant":[
        "F\u012br\u016bzeh\u2019\u012b"
    ],
    "name:und_x_variant":[
        "F\u012br\u016bz\u0101b\u0101d"
    ],
    "wof:name":"Firuzeh'i",
    "wof:placetype":"locality"
},
  "geometry": {"coordinates":[61.4827,30.96202000000001],"type":"Point"}
}