{
  "type": "Feature",
  "properties": {
    "gn:admin1_code":"29.0",
    "gn:asciiname":"Tangaleh-ye Pa'in",
    "gn:country_code":"IR",
    "gn:dem":2313,
    "gn:feature_class":"P",
    "gn:feature_code":"PPL",
    "gn:name":"Tang\u0101leh-ye P\u0101\u2019\u012bn",
    "gn:population":0,
    "gn:timezone":"Asia/Tehran",
    "iso:country":"IR",
    "name:fas_x_preferred":[
        "\u062a\u0646\u06af\u0627\u0644\u0647"
    ],
    "name:fas_x_variant":[
        "Tang\u0101leh",
        "\u062a\u0646\u06af\u0627\u0644\u0647 \u067e\u0627\u0626\u064a\u0646"
    ],
    "name:und_x_variant":[
        "Tang\u0101leh-ye P\u0101\u2019\u012bn"
    ],
    "wof:name":"Tangaleh-ye Pa'in",
    "wof:placetype":"locality"
},
  "geometry": {"coordinates":[55.0695,30.4592],"type":"Point"}
}