{
  "type": "Feature",
  "properties": {
    "gn:admin1_code":"7",
    "gn:asciiname":"Mahmudabad-e Seh Dang",
    "gn:country_code":"IR",
    "gn:dem":1514,
    "gn:feature_class":"P",
    "gn:feature_code":"PPL",
    "gn:name":"Ma\u1e29m\u016bd\u0101b\u0101d-e Seh D\u0101ng",
    "gn:population":0,
    "gn:timezone":"Asia/Tehran",
    "iso:country":"IR",
    "name:fas_x_preferred":[
        "\u0645\u062d\u0645\u0648\u062f\u0622\u0628\u0627\u062f \u0633\u0647 \u062f\u0627\u0646\u06af"
    ],
    "name:fas_x_variant":[
        "Ma\u1e29m\u016bd\u0101b\u0101d-e Seh D\u0101ngeh",
        "Ma\u1e29m\u016bd\u0101b\u0101d-e Seh D\u0101ng"
    ],
    "name:und_x_variant":[
        "Mahmood Abade Seh Dangeh"
    ],
    "wof:name":"Mahmudabad-e Seh Dang",
    "wof:placetype":"locality"
},
  "geometry": {"coordinates":[52.7197,29.2567],"type":"Point"}
}