{
  "type": "Feature",
  "properties": {
    "gn:admin1_code":"32",
    "gn:asciiname":"Shayeq",
    "gn:country_code":"IR",
    "gn:dem":1950,
    "gn:feature_class":"P",
    "gn:feature_code":"PPL",
    "gn:name":"Sh\u0101yeq",
    "gn:population":0,
    "gn:timezone":"Asia/Tehran",
    "iso:country":"IR",
    "name:ceb_x_preferred":[
        "Sh\u0101yeq"
    ],
    "name:fas_x_preferred":[
        "\u0634\u0627\u064a\u0642"
    ],
    "name:fas_x_variant":[
        "Sh\u0101yeq",
        "\u0634\u0627\u06cc\u0642"
    ],
    "name:msa_x_preferred":[
        "Shayeq"
    ],
    "name:mzn_x_preferred":[
        "\u0634\u0627\u06cc\u0642"
    ],
    "name:swe_x_preferred":[
        "Sh\u0101yeq"
    ],
    "wof:name":"Shayeq",
    "wof:placetype":"locality"
},
  "geometry": {"coordinates":[47.9881,38.1418],"type":"Point"}
}