{
  "type": "Feature",
  "properties": {
    "gn:admin1_code":"4.0",
    "gn:asciiname":"Karuchindar",
    "gn:country_code":"IR",
    "gn:dem":719,
    "gn:feature_class":"P",
    "gn:feature_code":"PPLL",
    "gn:name":"Kar\u016bch\u012bndar",
    "gn:population":0,
    "gn:timezone":"Asia/Tehran",
    "iso:country":"IR",
    "name:fas_x_preferred":[
        "\u06a9\u0631\u0648\u0686\u064a\u0646\u062f\u0631"
    ],
    "name:fas_x_variant":[
        "\u06a9\u0648\u0686\u064a\u0646\u062f\u0631"
    ],
    "name:und_x_variant":[
        "Kar\u016bch\u012bndar",
        "K\u016bch\u012bndar"
    ],
    "wof:name":"Karuchindar",
    "wof:placetype":"locality"
},
  "geometry": {"coordinates":[59.63053000000001,26.86465],"type":"Point"}
}