{
  "type": "Feature",
  "properties": {
    "gn:admin1_code":"8",
    "gn:asciiname":"Ashkejan-e Pahlu",
    "gn:country_code":"IR",
    "gn:dem":141,
    "gn:feature_class":"P",
    "gn:feature_code":"PPL",
    "gn:name":"Ashkej\u0101n-e Pahl\u016b",
    "gn:population":0,
    "gn:timezone":"Asia/Tehran",
    "iso:country":"IR",
    "name:fas_x_preferred":[
        "Ashk-e Jah\u0101n Pahl\u016b"
    ],
    "name:fas_x_variant":[
        "\u0627\u0634\u06a9\u062c\u0627\u0646 \u067e\u0647\u0644\u0648",
        "\u067e\u0634\u062a\u0627\u0631 \u0633\u0631\u0627"
    ],
    "name:und_x_variant":[
        "Ashkej\u0101n-e Pahl\u016b",
        "Posht\u0101r Sar\u0101"
    ],
    "wof:name":"Ashkejan-e Pahlu",
    "wof:placetype":"locality"
},
  "geometry": {"coordinates":[49.85969,37.11803],"type":"Point"}
}