{
  "type": "Feature",
  "properties": {
    "gn:admin1_code":"32",
    "gn:asciiname":"Pusjin",
    "gn:country_code":"IR",
    "gn:dem":1465,
    "gn:feature_class":"P",
    "gn:feature_code":"PPL",
    "gn:name":"P\u016bsj\u012bn",
    "gn:population":0,
    "gn:timezone":"Asia/Tehran",
    "iso:country":"IR",
    "name:ceb_x_preferred":[
        "P\u016bsj\u012bn"
    ],
    "name:fas_x_preferred":[
        "\u0628\u0648\u0633\u062c\u064a\u0646"
    ],
    "name:fas_x_variant":[
        "\u067e\u0648\u0633\u062c\u064a\u0646",
        "B\u016bsj\u012bn",
        "P\u016bsj\u012bn",
        "\u0628\u0648\u0633\u200c\u062c\u06cc\u0646"
    ],
    "name:msa_x_preferred":[
        "Busjin"
    ],
    "name:mzn_x_preferred":[
        "\u0628\u0648\u0633\u200c\u062c\u06cc\u0646"
    ],
    "name:swe_x_preferred":[
        "P\u016bsj\u012bn"
    ],
    "wof:name":"Pusjin",
    "wof:placetype":"locality"
},
  "geometry": {"coordinates":[48.2826,38.0066],"type":"Point"}
}