{
  "type": "Feature",
  "properties": {
    "gn:admin1_code":"34",
    "gn:asciiname":"Mal Mir",
    "gn:country_code":"IR",
    "gn:dem":2085,
    "gn:feature_class":"P",
    "gn:feature_code":"PPL",
    "gn:name":"M\u0101l M\u012br",
    "gn:population":0,
    "gn:timezone":"Asia/Tehran",
    "iso:country":"IR",
    "name:ara_x_preferred":[
        "\u0645\u0627\u0644\u200c\u0645\u064a\u0631"
    ],
    "name:fas_x_preferred":[
        "\u0645\u0627\u0644\u0645\u06cc\u0631"
    ],
    "name:fas_x_variant":[
        "M\u0101l M\u012br",
        "M\u0101l-e M\u012br",
        "\u0645\u0627\u0644\u200c\u0645\u06cc\u0631"
    ],
    "name:msa_x_preferred":[
        "Mal Mir"
    ],
    "wof:name":"Mal Mir",
    "wof:placetype":"locality"
},
  "geometry": {"coordinates":[49.11827,33.75015],"type":"Point"}
}