{
  "type": "Feature",
  "properties": {
    "gn:admin1_code":"5.0",
    "gn:asciiname":"Jay Kharman",
    "gn:country_code":"IR",
    "gn:dem":1080,
    "gn:feature_class":"P",
    "gn:feature_code":"PPL",
    "gn:name":"J\u0101y Kharman",
    "gn:population":0,
    "gn:timezone":"Asia/Tehran",
    "iso:country":"IR",
    "name:fas_x_preferred":[
        "\u062c\u0627\u06cc \u062e\u0631\u0645\u0646"
    ],
    "name:und_x_variant":[
        "J\u0101y Kharman"
    ],
    "wof:name":"Jay Kharman",
    "wof:placetype":"locality"
},
  "geometry": {"coordinates":[50.41417,31.0068],"type":"Point"}
}