{
  "type": "Feature",
  "properties": {
    "gn:admin1_code":"7",
    "gn:asciiname":"Dehkadeh-ye `Ashayeri-ye Gow Kazemi",
    "gn:country_code":"IR",
    "gn:dem":1067,
    "gn:feature_class":"P",
    "gn:feature_code":"PPL",
    "gn:name":"Dehkadeh-ye \u2018Ash\u0101yer\u012b-ye Gow K\u0101z\u0327em\u012b",
    "gn:population":0,
    "gn:timezone":"Asia/Tehran",
    "iso:country":"IR",
    "name:fas_x_preferred":[
        "\u06af\u0648\u062f \u06a9\u0627\u0638\u0645\u06cc"
    ],
    "name:fas_x_variant":[
        "Gowd-e K\u0101z\u0327em\u012b",
        "\u062f\u0647\u06a9\u062f\u0647 \u0639\u0634\u0627\u06cc\u0631\u06cc \u06af\u0648 \u06a9\u0627\u0638\u0645\u06cc"
    ],
    "name:und_x_variant":[
        "Dehkadeh-ye \u2018Ash\u0101yer\u012b-ye Gow K\u0101z\u0327em\u012b"
    ],
    "wof:name":"Dehkadeh-ye `Ashayeri-ye Gow Kazemi",
    "wof:placetype":"locality"
},
  "geometry": {"coordinates":[53.77841,28.26976],"type":"Point"}
}