{
  "type": "Feature",
  "properties": {
    "gn:admin1_code":"33.0",
    "gn:asciiname":"Seyyedlar",
    "gn:country_code":"IR",
    "gn:dem":1011,
    "gn:feature_class":"P",
    "gn:feature_code":"PPL",
    "gn:name":"Seyyedlar",
    "gn:population":0,
    "gn:timezone":"Asia/Tehran",
    "iso:country":"IR",
    "name:fas_x_preferred":[
        "\u0633\u0650\u064a\u0650\u0651\u062f\u0644\u064e\u0631"
    ],
    "name:fas_x_variant":[
        "\u0633\u06cc\u062f\u0644\u0631"
    ],
    "wof:name":"Seyyedlar",
    "wof:placetype":"locality"
},
  "geometry": {"coordinates":[47.23667,38.97333],"type":"Point"}
}