{
  "type": "Feature",
  "properties": {
    "gn:admin1_code":"4.0",
    "gn:asciiname":"Javan Jah",
    "gn:country_code":"IR",
    "gn:dem":708,
    "gn:feature_class":"P",
    "gn:feature_code":"PPL",
    "gn:name":"Javan J\u0101h",
    "gn:population":0,
    "gn:timezone":"Asia/Tehran",
    "iso:country":"IR",
    "name:fas_x_preferred":[
        "\u062c\u0648\u0646 \u062c\u0627\u0647"
    ],
    "name:fas_x_variant":[
        "\u062c\u0648\u0627\u0646 \u0686\u0627\u0647"
    ],
    "name:und_x_variant":[
        "Javan J\u0101h",
        "Jav\u0101n Ch\u0101h"
    ],
    "wof:name":"Javan Jah",
    "wof:placetype":"locality"
},
  "geometry": {"coordinates":[59.2699,26.46979],"type":"Point"}
}