{
  "type": "Feature",
  "properties": {
    "gn:admin1_code":"35",
    "gn:asciiname":"Kuner",
    "gn:country_code":"IR",
    "gn:dem":-18,
    "gn:feature_class":"P",
    "gn:feature_code":"PPL",
    "gn:name":"K\u016bner",
    "gn:population":0,
    "gn:timezone":"Asia/Tehran",
    "iso:country":"IR",
    "name:ceb_x_preferred":[
        "K\u016bner"
    ],
    "name:fas_x_preferred":[
        "\u0643\u0648\u0646\u0631"
    ],
    "name:fas_x_variant":[
        "K\u016bner",
        "\u06a9\u0648\u0646\u0631"
    ],
    "name:mzn_x_preferred":[
        "\u06a9\u0648\u0646\u0631"
    ],
    "name:swe_x_preferred":[
        "K\u016bner"
    ],
    "wof:name":"Kuner",
    "wof:placetype":"locality"
},
  "geometry": {"coordinates":[52.57335,36.61494],"type":"Point"}
}