{
  "type": "Feature",
  "properties": {
    "gn:admin1_code":"15.0",
    "gn:asciiname":"Badilian",
    "gn:cc2":"IR",
    "gn:country_code":"IR",
    "gn:dem":60,
    "gn:feature_class":"P",
    "gn:feature_code":"PPL",
    "gn:name":"Bad\u012bl\u012b\u0101n",
    "gn:population":0,
    "gn:timezone":"Asia/Tehran",
    "iso:country":"IR",
    "name:und_x_variant":[
        "Bad\u012bley\u0101n",
        "Bad\u012bl\u012b"
    ],
    "wof:name":"Badilian",
    "wof:placetype":"locality"
},
  "geometry": {"coordinates":[48.56667,32.15],"type":"Point"}
}