{
  "type": "Feature",
  "properties": {
    "gn:admin1_code":"8",
    "gn:asciiname":"Changarian",
    "gn:country_code":"IR",
    "gn:dem":9,
    "gn:feature_class":"P",
    "gn:feature_code":"PPL",
    "gn:name":"Changar\u012b\u0101n",
    "gn:population":0,
    "gn:timezone":"Asia/Tehran",
    "iso:country":"IR",
    "name:fas_x_preferred":[
        "\u0686\u0646\u06af\u06cc\u0632\u06cc\u0627\u0646"
    ],
    "name:fas_x_variant":[
        "Changar\u012b\u0101n",
        "Chang\u012bz\u012b\u0101n",
        "\u0686\u0646\u06af\u0631\u06cc\u0627\u0646"
    ],
    "name:und_x_variant":[
        "Chingiran",
        "Changer\u012b\u0101n",
        "Changerey\u0101n"
    ],
    "wof:name":"Changarian",
    "wof:placetype":"locality"
},
  "geometry": {"coordinates":[49.16367,37.53476],"type":"Point"}
}