{
  "type": "Feature",
  "properties": {
    "gn:admin1_code":"26.0",
    "gn:asciiname":"Rusta-ye Fasli-ye Yurt Shah",
    "gn:country_code":"IR",
    "gn:dem":1253,
    "gn:elevation":"0.0",
    "gn:feature_class":"P",
    "gn:feature_code":"PPL",
    "gn:name":"R\u016bst\u0101-ye Fa\u015fl\u012b-ye Y\u016brt Sh\u0101h",
    "gn:population":0,
    "gn:timezone":"Asia/Tehran",
    "iso:country":"IR",
    "name:fas_x_preferred":[
        "\u064a\u0648\u0631\u062f\u0650\u0634\u0627\u0647\u0650 \u0628\u0627\u0644\u0627"
    ],
    "name:fas_x_variant":[
        "\u06cc\u0648\u0631\u062f\u0634\u0627 \u0628\u0627\u0644\u0627",
        "Y\u016brdesh\u0101h-e B\u0101l\u0101",
        "Y\u016brdsh\u0101-ye B\u0101l\u0101",
        "\u0631\u0648\u0633\u062a\u0627\u06cc \u0641\u0635\u0644\u06cc \u06cc\u0648\u0631\u062a \u0634\u0627\u0647",
        "\u064a\u0648\u0631\u062f\u0634\u0627\u062f"
    ],
    "name:und_x_variant":[
        "R\u016bst\u0101-ye Fa\u015fl\u012b-ye Y\u016brt Sh\u0101h",
        "Y\u016brdsh\u0101d"
    ],
    "wof:name":"Rusta-ye Fasli-ye Yurt Shah",
    "wof:placetype":"locality"
},
  "geometry": {"coordinates":[51.7887,35.6015],"type":"Point"}
}