{
  "type": "Feature",
  "properties": {
    "gn:admin1_code":"25",
    "gn:asciiname":"Kandu",
    "gn:country_code":"IR",
    "gn:dem":1081,
    "gn:feature_class":"P",
    "gn:feature_code":"PPL",
    "gn:name":"Kand\u016b",
    "gn:population":0,
    "gn:timezone":"Asia/Tehran",
    "iso:country":"IR",
    "name:fas_x_preferred":[
        "\u0643\u0646\u062f\u0648"
    ],
    "name:fas_x_variant":[
        "Kand\u016b",
        "\u0643\u0646\u062f\u0648 \u064a\u0648\u0633\u0641 \u0622\u0628\u0627\u062f"
    ],
    "name:und_x_variant":[
        "Kand\u016b Y\u016bsef\u0101b\u0101d"
    ],
    "wof:name":"Kandu",
    "wof:placetype":"locality"
},
  "geometry": {"coordinates":[53.49183000000001,35.53807000000001],"type":"Point"}
}