{
  "type": "Feature",
  "properties": {
    "gn:admin1_code":"38",
    "gn:asciiname":"Dizan",
    "gn:country_code":"IR",
    "gn:dem":1219,
    "gn:feature_class":"P",
    "gn:feature_code":"PPL",
    "gn:name":"D\u012bz\u0101n",
    "gn:population":0,
    "gn:timezone":"Asia/Tehran",
    "iso:country":"IR",
    "name:ara_x_preferred":[
        "\u062f\u064a\u0632\u0627\u0646"
    ],
    "name:fas_x_preferred":[
        "\u062f\u064a\u0632\u0627\u0646"
    ],
    "name:fas_x_variant":[
        "D\u012bz\u0101n",
        "\u062f\u06cc\u0632\u0627\u0646"
    ],
    "name:und_x_variant":[
        "Tez\u0101n"
    ],
    "wof:name":"Dizan",
    "wof:placetype":"locality"
},
  "geometry": {"coordinates":[49.88222,36.01651],"type":"Point"}
}