{
  "type": "Feature",
  "properties": {
    "gn:admin1_code":"15",
    "gn:asciiname":"Naft-e Sefid",
    "gn:country_code":"IR",
    "gn:dem":231,
    "gn:feature_class":"P",
    "gn:feature_code":"PPL",
    "gn:name":"Naft-e Sef\u012bd",
    "gn:population":0,
    "gn:timezone":"Asia/Tehran",
    "iso:country":"IR",
    "name:aze_x_preferred":[
        "N\u0259ft Sefid"
    ],
    "name:ceb_x_preferred":[
        "Naft Sef\u012bd"
    ],
    "name:fas_x_preferred":[
        "\u0646\u0641\u062a \u0633\u0641\u06cc\u062f"
    ],
    "name:fas_x_variant":[
        "Naft-e Sef\u012bd",
        "Naft Sef\u012bd"
    ],
    "name:swe_x_preferred":[
        "Naft Sef\u012bd"
    ],
    "name:und_x_variant":[
        "Naft Seq\u012bd",
        "Naft-e Saf\u012bd",
        "Nafte-e Sef\u012dd"
    ],
    "wof:name":"Naft-e Sefid",
    "wof:placetype":"locality"
},
  "geometry": {"coordinates":[49.28648,31.63472],"type":"Point"}
}