{
  "type": "Feature",
  "properties": {
    "gn:admin1_code":"8",
    "gn:asciiname":"Kalgu",
    "gn:country_code":"IR",
    "gn:dem":-11,
    "gn:feature_class":"P",
    "gn:feature_code":"PPL",
    "gn:name":"Kalg\u016b",
    "gn:population":0,
    "gn:timezone":"Asia/Tehran",
    "iso:country":"IR",
    "name:fas_x_preferred":[
        "\u06a9\u0644\u06af\u0648"
    ],
    "name:fas_x_variant":[
        "Kalg\u016b"
    ],
    "wof:name":"Kalgu",
    "wof:placetype":"locality"
},
  "geometry": {"coordinates":[49.3901,37.3266],"type":"Point"}
}