{
  "type": "Feature",
  "properties": {
    "gn:admin1_code":"7",
    "gn:asciiname":"Seyyed Ahmadi",
    "gn:country_code":"IR",
    "gn:dem":2357,
    "gn:feature_class":"P",
    "gn:feature_code":"PPL",
    "gn:name":"Seyyed A\u1e29mad\u012b",
    "gn:population":0,
    "gn:timezone":"Asia/Tehran",
    "iso:country":"IR",
    "name:fas_x_preferred":[
        "\u0633\u06cc\u062f \u0627\u062d\u0645\u062f\u06cc"
    ],
    "name:fas_x_variant":[
        "Seyyed A\u1e29mad\u012b",
        "\u0633\u06cc\u062f\u0627\u062d\u0645\u062f\u06cc"
    ],
    "name:msa_x_preferred":[
        "Seyyed Ahmadi"
    ],
    "wof:name":"Seyyed Ahmadi",
    "wof:placetype":"locality"
},
  "geometry": {"coordinates":[52.9208,30.6202],"type":"Point"}
}