{
  "type": "Feature",
  "properties": {
    "gn:admin1_code":"13",
    "gn:asciiname":"Sukhvor Morovvati",
    "gn:country_code":"IR",
    "gn:dem":1081,
    "gn:feature_class":"P",
    "gn:feature_code":"PPL",
    "gn:name":"S\u016bkhvor Morovvat\u012b",
    "gn:population":0,
    "gn:timezone":"Asia/Tehran",
    "iso:country":"IR",
    "name:fas_x_preferred":[
        "\u0633\u0648\u062e\u0648\u0631 \u0645\u0631\u0648\u0651\u062a\u06cc"
    ],
    "name:fas_x_variant":[
        "S\u016bkh\u016br-e Morovvat\u012b",
        "S\u016bkhvor Morovvat\u012b"
    ],
    "wof:name":"Sukhvor Morovvati",
    "wof:placetype":"locality"
},
  "geometry": {"coordinates":[46.13121,34.15085999999999],"type":"Point"}
}