{
  "type": "Feature",
  "properties": {
    "gn:admin1_code":"43",
    "gn:asciiname":"Takht",
    "gn:country_code":"IR",
    "gn:dem":1630,
    "gn:feature_class":"P",
    "gn:feature_code":"PPL",
    "gn:name":"Takht",
    "gn:population":0,
    "gn:timezone":"Asia/Tehran",
    "iso:country":"IR",
    "name:fas_x_preferred":[
        "\u062a\u062e\u062a"
    ],
    "wof:name":"Takht",
    "wof:placetype":"locality"
},
  "geometry": {"coordinates":[58.02712,37.68733],"type":"Point"}
}