{
  "type": "Feature",
  "properties": {
    "gn:admin1_code":"34.0",
    "gn:asciiname":"Ashtian",
    "gn:country_code":"IR",
    "gn:dem":2073,
    "gn:feature_class":"P",
    "gn:feature_code":"PPLA2",
    "gn:name":"\u0100sht\u012b\u0101n",
    "gn:population":0,
    "gn:timezone":"Asia/Tehran",
    "iso:country":"IR",
    "name:fas_x_preferred":[
        "\u0100sht\u012b\u0101n"
    ],
    "name:fas_x_variant":[
        "\u0622\u0634\u062a\u064a\u0627\u0646"
    ],
    "name:und_x_variant":[
        "Asht\u012byan",
        "\u0622\u0634\u062a\u064a\u0627\u0646"
    ],
    "wof:name":"Ashtian",
    "wof:placetype":"locality"
},
  "geometry": {"coordinates":[50.00608,34.52298],"type":"Point"}
}