{
  "type": "Feature",
  "properties": {
    "gn:admin1_code":"34.0",
    "gn:asciiname":"Ashtian",
    "gn:country_code":"IR",
    "gn:dem":2073,
    "gn:feature_class":"P",
    "gn:feature_code":"PPLA2",
    "gn:name":"\u0100sht\u012b\u0101n",
    "gn:population":0,
    "gn:timezone":"Asia/Tehran",
    "iso:country":"IR",
    "name:ara_x_preferred":[
        "\u0622\u0634\u062a\u064a\u0627\u0646"
    ],
    "name:aze_x_preferred":[
        "A\u015ftiyan"
    ],
    "name:epo_x_preferred":[
        "A\u015dtiano"
    ],
    "name:fas_x_preferred":[
        "\u0100sht\u012b\u0101n"
    ],
    "name:fas_x_variant":[
        "\u0622\u0634\u062a\u064a\u0627\u0646",
        "\u0622\u0634\u062a\u06cc\u0627\u0646"
    ],
    "name:fra_x_preferred":[
        "Achtian"
    ],
    "name:ita_x_preferred":[
        "Ashtian"
    ],
    "name:mlg_x_preferred":[
        "Ashtian"
    ],
    "name:pnb_x_preferred":[
        "\u0622\u0634\u062a\u06cc\u0627\u0646"
    ],
    "name:pol_x_preferred":[
        "Asztijan"
    ],
    "name:ron_x_preferred":[
        "Ashtiyan"
    ],
    "name:rus_x_preferred":[
        "\u0410\u0448\u0442\u0438\u0430\u043d"
    ],
    "name:tgk_x_preferred":[
        "\u041e\u0448\u0442\u0438\u0451\u043d"
    ],
    "name:tur_x_preferred":[
        "A\u015ftiyan"
    ],
    "name:ukr_x_preferred":[
        "\u0410\u0448\u0442\u0456\u0430\u043d"
    ],
    "name:und_x_variant":[
        "Asht\u012byan",
        "\u0622\u0634\u062a\u064a\u0627\u0646"
    ],
    "name:urd_x_preferred":[
        "\u0622\u0634\u062a\u06cc\u0627\u0646"
    ],
    "name:zho_x_preferred":[
        "\u963f\u4ec0\u63d0\u63da"
    ],
    "wof:name":"Ashtian",
    "wof:placetype":"locality"
},
  "geometry": {"coordinates":[50.00608,34.52298],"type":"Point"}
}