{
  "type": "Feature",
  "properties": {
    "gn:admin1_code":"10.0",
    "gn:asciiname":"Shan Kabud",
    "gn:country_code":"IR",
    "gn:dem":1390,
    "gn:feature_class":"P",
    "gn:feature_code":"PPL",
    "gn:name":"Sh\u0101n Kab\u016bd",
    "gn:population":0,
    "gn:timezone":"Asia/Tehran",
    "iso:country":"IR",
    "name:ceb_x_preferred":[
        "Sh\u0101n Kab\u016bd"
    ],
    "name:fas_x_preferred":[
        "\u0634\u0627\u0646 \u0643\u064e\u0628\u0648\u062f"
    ],
    "name:fas_x_variant":[
        "\u0634\u0627\u0646 \u06a9\u0628\u0648\u062f",
        "Sh\u0101n Kab\u016bd"
    ],
    "name:msa_x_preferred":[
        "Shan Kabud"
    ],
    "name:swe_x_preferred":[
        "Sh\u0101n Kab\u016bd"
    ],
    "wof:name":"Shan Kabud",
    "wof:placetype":"locality"
},
  "geometry": {"coordinates":[46.4653,33.5656],"type":"Point"}
}