{
  "type": "Feature",
  "properties": {
    "gn:admin1_code":"10",
    "gn:asciiname":"Belavah Tareh-ye Sofla",
    "gn:country_code":"IR",
    "gn:dem":923,
    "gn:feature_class":"P",
    "gn:feature_code":"PPL",
    "gn:name":"Bel\u0101vah Tareh-ye Sofl\u00e1",
    "gn:population":0,
    "gn:timezone":"Asia/Tehran",
    "iso:country":"IR",
    "name:fas_x_preferred":[
        "\u0628\u0644\u0627\u0648\u0647 \u062a\u0631\u0647 \u0633\u0641\u0644\u06cc"
    ],
    "name:fas_x_variant":[
        "Bel\u0101vah Tareh-ye Sofl\u00e1"
    ],
    "name:und_x_variant":[
        "Bel\u0101veh Tareh"
    ],
    "wof:name":"Belavah Tareh-ye Sofla",
    "wof:placetype":"locality"
},
  "geometry": {"coordinates":[46.8039,33.6668],"type":"Point"}
}