{
  "type": "Feature",
  "properties": {
    "gn:admin1_code":"7",
    "gn:asciiname":"Tall Mahtabi",
    "gn:country_code":"IR",
    "gn:dem":1583,
    "gn:feature_class":"P",
    "gn:feature_code":"PPL",
    "gn:name":"Tall Maht\u0101b\u012b",
    "gn:population":0,
    "gn:timezone":"Asia/Tehran",
    "iso:country":"IR",
    "name:fas_x_preferred":[
        "\u062a\u0644 \u0645\u0647\u062a\u0627\u0628\u06cc"
    ],
    "name:fas_x_variant":[
        "Tall Maht\u0101b\u012b"
    ],
    "name:msa_x_preferred":[
        "Tall Mahtabi"
    ],
    "wof:name":"Tall Mahtabi",
    "wof:placetype":"locality"
},
  "geometry": {"coordinates":[54.3074,29.2436],"type":"Point"}
}