{
  "type": "Feature",
  "properties": {
    "gn:admin1_code":"1",
    "gn:asciiname":"Shedi",
    "gn:country_code":"IR",
    "gn:dem":795,
    "gn:feature_class":"P",
    "gn:feature_code":"PPL",
    "gn:name":"Shed\u012b",
    "gn:population":0,
    "gn:timezone":"Asia/Tehran",
    "iso:country":"IR",
    "name:fas_x_preferred":[
        "\u0634\u0650\u062f\u06cc"
    ],
    "name:fas_x_variant":[
        "\u0634\u062f\u06cc",
        "Shed\u012b"
    ],
    "wof:name":"Shedi",
    "wof:placetype":"locality"
},
  "geometry": {"coordinates":[44.9305,39.507],"type":"Point"}
}