{
  "type": "Feature",
  "properties": {
    "iso:country":"IR",
    "name:ara_x_preferred":[
        "\u0646\u0648\u0634\u0647\u0631"
    ],
    "name:arz_x_preferred":[
        "\u0646\u0648\u0634\u0647\u0631"
    ],
    "name:aze_x_preferred":[
        "Nov\u015f\u0259hr"
    ],
    "name:ceb_x_preferred":[
        "Nowshahr"
    ],
    "name:deu_x_preferred":[
        "Nouschahr"
    ],
    "name:eng_x_preferred":[
        "Nowshahr"
    ],
    "name:fas_x_preferred":[
        "\u0646\u0648\u0634\u0647\u0631"
    ],
    "name:fra_x_preferred":[
        "Nowshahr"
    ],
    "name:hbs_x_preferred":[
        "Nov\u0161aher"
    ],
    "name:ita_x_preferred":[
        "Nushahr"
    ],
    "name:mlg_x_preferred":[
        "Nowshahr"
    ],
    "name:mzn_x_preferred":[
        "\u0646\u0648\u0634\u0647\u0631"
    ],
    "name:nld_x_preferred":[
        "Nowshahr"
    ],
    "name:nob_x_preferred":[
        "Noshahr"
    ],
    "name:pnb_x_preferred":[
        "\u0646\u0648\u0634\u06c1\u0631"
    ],
    "name:pol_x_preferred":[
        "Nouszahr"
    ],
    "name:ron_x_preferred":[
        "Nowshahr"
    ],
    "name:rus_x_preferred":[
        "\u041d\u043e\u0443\u0448\u0435\u0445\u0440"
    ],
    "name:spa_x_preferred":[
        "Nowshahr"
    ],
    "name:swe_x_preferred":[
        "Noshahr"
    ],
    "name:tgk_x_preferred":[
        "\u041d\u0430\u0432\u0448\u0430\u04b3\u0440"
    ],
    "name:tur_x_preferred":[
        "Nov\u015fehr"
    ],
    "name:und_x_variant":[
        "Bandar-e Now Shahr"
    ],
    "name:urd_x_preferred":[
        "\u0646\u0648\u0634\u06c1\u0631"
    ],
    "name:urd_x_variant":[
        "\u0646\u0648\u0634\u06be\u0631"
    ],
    "name:zho_x_preferred":[
        "\u7459\u6c99\u8d6b\u723e"
    ],
    "qs:gn_country":"IR",
    "qs:gn_fcode":"PPLA2",
    "qs:gn_pop":40000,
    "qs:name":"Now Shahr",
    "qs:name_adm0":"Iran",
    "qs:name_adm1":"Mazandaran",
    "qs:photos":0,
    "qs:photos_1k":0,
    "qs:photos_9k":1,
    "qs:photos_9r":1,
    "qs:photos_all":1,
    "qs:photos_sr":0,
    "qs:placetype":"Town",
    "qs:pop_sr":"7",
    "qs:woe_adm0":23424851,
    "wd:wordcount":508,
    "wof:name":"Now Shahr",
    "wof:placetype":"locality",
    "wof:population":40000
},
  "geometry": {"coordinates":[51.496,36.649],"type":"Point"}
}