{
  "type": "Feature",
  "properties": {
    "gn:admin1_code":"11",
    "gn:asciiname":"Darberkeh",
    "gn:country_code":"IR",
    "gn:dem":968,
    "gn:feature_class":"P",
    "gn:feature_code":"PPL",
    "gn:name":"Darberkeh",
    "gn:population":0,
    "gn:timezone":"Asia/Tehran",
    "iso:country":"IR",
    "name:fas_x_preferred":[
        "\u062f\u0631\u0628\u0631\u06a9\u0647"
    ],
    "wof:name":"Darberkeh",
    "wof:placetype":"locality"
},
  "geometry": {"coordinates":[56.6988,27.9277],"type":"Point"}
}