{
  "type": "Feature",
  "properties": {
    "gn:admin1_code":"37",
    "gn:asciiname":"Su Javal",
    "gn:country_code":"IR",
    "gn:dem":-22,
    "gn:feature_class":"P",
    "gn:feature_code":"PPL",
    "gn:name":"S\u016b Jav\u0101l",
    "gn:population":0,
    "gn:timezone":"Asia/Tehran",
    "iso:country":"IR",
    "name:fas_x_preferred":[
        "\u0633\u0648 \u062c\u064e\u0648\u0627\u0644"
    ],
    "wof:name":"Su Javal",
    "wof:placetype":"locality"
},
  "geometry": {"coordinates":[54.115,36.88361],"type":"Point"}
}