{
  "type": "Feature",
  "properties": {
    "gn:admin1_code":"7",
    "gn:asciiname":"Sheykh `Amer",
    "gn:country_code":"IR",
    "gn:dem":498,
    "gn:feature_class":"P",
    "gn:feature_code":"PPL",
    "gn:name":"Sheykh \u2018\u0100mer",
    "gn:population":0,
    "gn:timezone":"Asia/Tehran",
    "iso:country":"IR",
    "name:fas_x_preferred":[
        "\u0634\u06cc\u062e \u0639\u0627\u0645\u0631"
    ],
    "name:fas_x_variant":[
        "Sheykh \u2018\u0100mer"
    ],
    "name:und_x_variant":[
        "Shaikh \u2018Umar",
        "Sheykh \u2018Omar",
        "Sheykh \u0100mer\u012b"
    ],
    "wof:name":"Sheykh `Amer",
    "wof:placetype":"locality"
},
  "geometry": {"coordinates":[53.4004,27.4455],"type":"Point"}
}