{
  "type": "Feature",
  "properties": {
    "gn:admin1_code":"29",
    "gn:asciiname":"Kahnu",
    "gn:country_code":"IR",
    "gn:dem":635,
    "gn:feature_class":"P",
    "gn:feature_code":"PPL",
    "gn:name":"Kahn\u016b",
    "gn:population":0,
    "gn:timezone":"Asia/Tehran",
    "iso:country":"IR",
    "name:fas_x_preferred":[
        "Kahn\u016b"
    ],
    "wof:name":"Kahnu",
    "wof:placetype":"locality"
},
  "geometry": {"coordinates":[57.72722,28.59611],"type":"Point"}
}