{
  "type": "Feature",
  "properties": {
    "gn:admin1_code":"9",
    "gn:asciiname":"Chulak Qapanuri",
    "gn:country_code":"IR",
    "gn:dem":1548,
    "gn:feature_class":"P",
    "gn:feature_code":"PPL",
    "gn:name":"Ch\u016blak Qap\u0101n\u016br\u012b",
    "gn:population":0,
    "gn:timezone":"Asia/Tehran",
    "iso:country":"IR",
    "name:ceb_x_preferred":[
        "Ch\u016blak-e Qab\u0101n\u016br\u012b"
    ],
    "name:fas_x_preferred":[
        "\u0686\u0648\u0644\u06a9 \u0642\u067e\u0627\u0646\u0648\u0631\u06cc"
    ],
    "name:fas_x_variant":[
        "Ch\u016blak-e Qab\u0101n\u016br\u012b",
        "Ch\u016blak",
        "\u0686\u0648\u0644\u06a9 \u0642\u0628\u0627\u0646\u0648\u0631\u06cc"
    ],
    "name:msa_x_preferred":[
        "Chulak Qapanuri"
    ],
    "name:swe_x_preferred":[
        "Ch\u016blak-e Qab\u0101n\u016br\u012b"
    ],
    "name:und_x_variant":[
        "Ch\u016blak Qap\u0101n\u016br\u012b",
        "\u0686\u0648\u0644\u06a9 \u0642\u0628\u0627\u0646\u0648\u0631\u06cc"
    ],
    "wof:name":"Chulak Qapanuri",
    "wof:placetype":"locality"
},
  "geometry": {"coordinates":[48.30018,34.23467],"type":"Point"}
}