{
  "type": "Feature",
  "properties": {
    "gn:admin1_code":"1",
    "gn:asciiname":"Hajji Baghlu",
    "gn:country_code":"IR",
    "gn:dem":1288,
    "gn:feature_class":"P",
    "gn:feature_code":"PPL",
    "gn:name":"\u1e28\u0101jj\u012b B\u0101ghl\u016b",
    "gn:population":0,
    "gn:timezone":"Asia/Tehran",
    "iso:country":"IR",
    "name:azb_x_preferred":[
        "\u062d\u0627\u062c\u06cc \u0628\u0627\u063a\u0644\u0648"
    ],
    "name:aze_x_preferred":[
        "Hac\u0131 Ba\u011fl\u0131"
    ],
    "name:fas_x_preferred":[
        "\u062d\u0627\u062c\u0651\u06cc \u0628\u0627\u063a\u0644\u0648"
    ],
    "name:fas_x_variant":[
        "\u1e28\u0101jj\u012bb\u0101ghl\u016b",
        "\u1e28\u0101jj\u012b B\u0101ghl\u016b",
        "\u062d\u0627\u062c\u06cc\u200c\u0628\u0627\u063a\u0644\u0648"
    ],
    "name:msa_x_preferred":[
        "Hajji Baghlu"
    ],
    "wof:name":"Hajji Baghlu",
    "wof:placetype":"locality"
},
  "geometry": {"coordinates":[45.4442,37.0056],"type":"Point"}
}