{
  "type": "Feature",
  "properties": {
    "gn:admin1_code":"16",
    "gn:asciiname":"Karabad",
    "gn:country_code":"IR",
    "gn:dem":1234,
    "gn:feature_class":"P",
    "gn:feature_code":"PPL",
    "gn:name":"Kar\u0101b\u0101d",
    "gn:population":0,
    "gn:timezone":"Asia/Tehran",
    "iso:country":"IR",
    "name:ceb_x_preferred":[
        "Kar\u0101b\u0101d"
    ],
    "name:ckb_x_preferred":[
        "\u06a9\u06d5\u0695\u0627\u0648\u0627"
    ],
    "name:fas_x_preferred":[
        "\u0643\u0631 \u0622\u0628\u0627\u062f"
    ],
    "name:fas_x_variant":[
        "Kar\u0101b\u0101d",
        "\u06a9\u0631\u0622\u0628\u0627\u062f"
    ],
    "name:swe_x_preferred":[
        "Kar\u0101b\u0101d"
    ],
    "name:und_x_variant":[
        "Gar\u0101b\u0101d",
        "Karr\u0101b\u0101d",
        "Karr\u0101wa"
    ],
    "wof:name":"Karabad",
    "wof:placetype":"locality"
},
  "geometry": {"coordinates":[46.4238,35.2624],"type":"Point"}
}