{
  "type": "Feature",
  "properties": {
    "gn:admin1_code":"29",
    "gn:asciiname":"Deh Bala-ye Bid Khun",
    "gn:country_code":"IR",
    "gn:dem":2709,
    "gn:feature_class":"P",
    "gn:feature_code":"PPL",
    "gn:name":"Deh B\u0101l\u0101-ye B\u012bd Kh\u016bn",
    "gn:population":0,
    "gn:timezone":"Asia/Tehran",
    "iso:country":"IR",
    "name:fas_x_preferred":[
        "Dehb\u0101l\u0101-ye B\u012bdkh\u0101n"
    ],
    "name:fas_x_variant":[
        "Deh B\u0101l\u0101-ye B\u012bd Kh\u016bn",
        "\u062f\u0647 \u0628\u0627\u0644\u0627 \u0628\u064a\u062f \u062e\u0648\u0646"
    ],
    "name:und_x_variant":[
        "Deh-e B\u0101l\u0101",
        "Deh B\u0101l\u0101"
    ],
    "wof:name":"Deh Bala-ye Bid Khun",
    "wof:placetype":"locality"
},
  "geometry": {"coordinates":[56.50743000000001,29.61275],"type":"Point"}
}