{
  "type": "Feature",
  "properties": {
    "gn:admin1_code":"10",
    "gn:asciiname":"Damrud",
    "gn:country_code":"IR",
    "gn:dem":365,
    "gn:feature_class":"P",
    "gn:feature_code":"PPL",
    "gn:name":"Damr\u016bd",
    "gn:population":0,
    "gn:timezone":"Asia/Tehran",
    "iso:country":"IR",
    "name:fas_x_preferred":[
        "\u062f\u0645\u0631\u0648\u062f"
    ],
    "name:fas_x_variant":[
        "Damr\u016bd",
        "\u0645\u064e\u0631\u0648\u064e\u062f"
    ],
    "name:und_x_variant":[
        "Marvad"
    ],
    "wof:name":"Damrud",
    "wof:placetype":"locality"
},
  "geometry": {"coordinates":[47.8764,32.9207],"type":"Point"}
}