{
  "type": "Feature",
  "properties": {
    "gn:admin1_code":"7",
    "gn:asciiname":"Kohneh",
    "gn:country_code":"IR",
    "gn:dem":620,
    "gn:feature_class":"P",
    "gn:feature_code":"PPL",
    "gn:name":"Kohneh",
    "gn:population":0,
    "gn:timezone":"Asia/Tehran",
    "iso:country":"IR",
    "name:fas_x_preferred":[
        "\u06a9\u0647\u0646\u0647"
    ],
    "name:fas_x_variant":[
        "Kohneh \u2018Al\u012b\u0101b\u0101d"
    ],
    "name:msa_x_preferred":[
        "Kohneh"
    ],
    "name:und_x_variant":[
        "Kahneh \u2018Al\u012b\u0101b\u0101d",
        "\u2018Al\u012b\u0101b\u0101d",
        "Kahneh-ye \u2018Al\u012b\u0101b\u0101d",
        "\u2018Al\u012b\u0101b\u0101d-e Kohneh"
    ],
    "wof:name":"Kohneh",
    "wof:placetype":"locality"
},
  "geometry": {"coordinates":[54.7682,27.7842],"type":"Point"}
}