{
  "type": "Feature",
  "properties": {
    "gn:admin1_code":"36.0",
    "gn:asciiname":"Aq Bolagh",
    "gn:country_code":"IR",
    "gn:dem":2153,
    "gn:feature_class":"P",
    "gn:feature_code":"PPL",
    "gn:name":"\u0100q Bol\u0101gh",
    "gn:population":0,
    "gn:timezone":"Asia/Tehran",
    "iso:country":"IR",
    "name:fas_x_preferred":[
        "\u0622\u0642 \u0628\u064f\u0644\u0627\u063a"
    ],
    "name:fas_x_variant":[
        "\u0622\u0642\u0628\u0644\u0627\u063a",
        "\u0100t Bol\u0101gh",
        "\u0100q Bol\u0101gh",
        "\u0622\u062a \u0628\u064f\u0644\u0627\u063a",
        "\u062e\u064e\u0631\u0627\u0628\u0650\u0647 \u0622\u063a\u0628\u064f\u0644\u0627\u063a",
        "\u0100qbol\u0101gh",
        "\u0622\u0642 \u0628\u0644\u0627\u063a",
        "\u0622\u0642\u0628\u0644\u0627\u063a \u062d\u0648\u0645\u0647"
    ],
    "name:und_x_variant":[
        "Ak-Bulag",
        "\u0100qbul\u0101q",
        "Khar\u0101beh-e \u0100ghbol\u0101gh",
        "\u0100qbol\u0101gh \u1e28\u016bmeh"
    ],
    "wof:name":"Aq Bolagh",
    "wof:placetype":"locality"
},
  "geometry": {"coordinates":[48.06111,36.69688],"type":"Point"}
}