{
  "type": "Feature",
  "properties": {
    "gn:admin1_code":"32",
    "gn:asciiname":"Pir `Alilu",
    "gn:country_code":"IR",
    "gn:dem":1547,
    "gn:feature_class":"P",
    "gn:feature_code":"PPL",
    "gn:name":"P\u012br \u2018Al\u012bl\u016b",
    "gn:population":0,
    "gn:timezone":"Asia/Tehran",
    "iso:country":"IR",
    "name:fas_x_preferred":[
        "\u067e\u064a\u0631 \u0639\u064e\u0644\u06cc"
    ],
    "name:fas_x_variant":[
        "\u067e\u064a\u0631 \u0639\u0644\u06cc\u0644\u0648",
        "P\u012br \u2018Al\u012b",
        "P\u012br \u2018Al\u012bl\u016b"
    ],
    "wof:name":"Pir `Alilu",
    "wof:placetype":"locality"
},
  "geometry": {"coordinates":[48.1262,38.6709],"type":"Point"}
}