{
  "type": "Feature",
  "properties": {
    "gn:admin1_code":"29",
    "gn:asciiname":"Sibak-e Suran",
    "gn:country_code":"IR",
    "gn:dem":2498,
    "gn:feature_class":"P",
    "gn:feature_code":"PPL",
    "gn:name":"S\u012bbak-e S\u016br\u0101n",
    "gn:population":0,
    "gn:timezone":"Asia/Tehran",
    "iso:country":"IR",
    "name:fas_x_preferred":[
        "S\u012bbak-e S\u016br\u0101n"
    ],
    "wof:name":"Sibak-e Suran",
    "wof:placetype":"locality"
},
  "geometry": {"coordinates":[57.93333000000001,28.76667],"type":"Point"}
}