{
  "type": "Feature",
  "properties": {
    "gn:admin1_code":"29.0",
    "gn:asciiname":"Jahadabad",
    "gn:country_code":"IR",
    "gn:dem":2592,
    "gn:feature_class":"P",
    "gn:feature_code":"PPL",
    "gn:name":"Jah\u0101d\u0101b\u0101d",
    "gn:population":0,
    "gn:timezone":"Asia/Tehran",
    "iso:country":"IR",
    "name:fas_x_preferred":[
        "Kal\u016bk"
    ],
    "name:fas_x_variant":[
        "\u062c\u0647\u0627\u062f \u0622\u0628\u0627\u062f",
        "\u062c\u0647\u0627\u062f\u0622\u0628\u0627\u062f"
    ],
    "name:und_x_variant":[
        "Bon S\u0101rd\u016b\u2019\u012byeh",
        "Jah\u0101d\u0101b\u0101d"
    ],
    "wof:name":"Jahadabad",
    "wof:placetype":"locality"
},
  "geometry": {"coordinates":[57.34467,29.24025],"type":"Point"}
}