{
  "type": "Feature",
  "properties": {
    "gn:admin1_code":"16",
    "gn:asciiname":"Tazehabad-e Sarab",
    "gn:country_code":"IR",
    "gn:dem":1868,
    "gn:feature_class":"P",
    "gn:feature_code":"PPL",
    "gn:name":"T\u0101zeh\u0101b\u0101d-e Sar\u0101b",
    "gn:population":0,
    "gn:timezone":"Asia/Tehran",
    "iso:country":"IR",
    "name:fas_x_preferred":[
        "T\u0101zeh\u0101b\u0101d-e Sar\u0101b-e Qa\u1e29\u0163"
    ],
    "name:fas_x_variant":[
        "\u062a\u0627\u0632\u0647 \u0622\u0628\u0627\u062f \u0633\u0631\u0627\u0628 \u0642\u062d\u0637",
        "\u062a\u0627\u0632\u0647 \u0622\u0628\u0627\u062f \u0633\u0631\u0627\u0628",
        "\u062a\u0627\u0632\u0647\u200c\u0622\u0628\u0627\u062f \u0633\u0631\u0627\u0628 \u0642\u062d\u0637"
    ],
    "name:und_x_variant":[
        "T\u0101zeh\u0101wa",
        "T\u0101zeh\u0101b\u0101d-e Sar \u0100b Qa\u1e29\u0163",
        "T\u0101zeh \u0100veh",
        "\u062a\u0627\u0632\u0647 \u0622\u0628\u0627\u062f \u0633\u0631\u0627\u0628 \u0642\u062d\u0637",
        "T\u0101zeh\u0101b\u0101d-e Sar\u0101b"
    ],
    "wof:name":"Tazehabad-e Sarab",
    "wof:placetype":"locality"
},
  "geometry": {"coordinates":[47.56441,35.17968],"type":"Point"}
}