{
  "type": "Feature",
  "properties": {
    "gn:admin1_code":"4.0",
    "gn:asciiname":"`Iduabad",
    "gn:country_code":"IR",
    "gn:dem":1308,
    "gn:feature_class":"P",
    "gn:feature_code":"PPL",
    "gn:name":"\u2018\u012ad\u016b\u0101b\u0101d",
    "gn:population":0,
    "gn:timezone":"Asia/Tehran",
    "iso:country":"IR",
    "name:fas_x_preferred":[
        "\u2018\u012ad\u016b\u0101b\u0101d"
    ],
    "name:fas_x_variant":[
        "\u0639\u06cc\u062f\u0648 \u0622\u0628\u0627\u062f"
    ],
    "wof:name":"`Iduabad",
    "wof:placetype":"locality"
},
  "geometry": {"coordinates":[61.21696,28.91728],"type":"Point"}
}