{
  "type": "Feature",
  "properties": {
    "gn:admin1_code":"7",
    "gn:asciiname":"Mowruzeh",
    "gn:country_code":"IR",
    "gn:dem":1991,
    "gn:feature_class":"P",
    "gn:feature_code":"PPL",
    "gn:name":"Mowr\u016bzeh",
    "gn:population":0,
    "gn:timezone":"Asia/Tehran",
    "iso:country":"IR",
    "name:fas_x_preferred":[
        "\u0645\u0648\u0631\u0648\u0632\u0647"
    ],
    "name:fas_x_variant":[
        "Mowr\u016bz",
        "Nowr\u016bzeh",
        "Mowr\u016bzeh"
    ],
    "name:msa_x_preferred":[
        "Mowruzeh"
    ],
    "wof:name":"Mowruzeh",
    "wof:placetype":"locality"
},
  "geometry": {"coordinates":[52.0455,30.1795],"type":"Point"}
}