{
  "type": "Feature",
  "properties": {
    "gn:admin1_code":"35.0",
    "gn:asciiname":"Varand",
    "gn:country_code":"IR",
    "gn:dem":580,
    "gn:feature_class":"P",
    "gn:feature_code":"PPL",
    "gn:name":"Varand",
    "gn:population":0,
    "gn:timezone":"Asia/Tehran",
    "iso:country":"IR",
    "name:fas_x_preferred":[
        "\u0648\u0631\u0646\u062f"
    ],
    "name:fas_x_variant":[
        "\u0648\u0627\u0631\u0627\u0646\u062f"
    ],
    "name:hye_x_preferred":[
        "\u054e\u0561\u0580\u0561\u0576\u0564"
    ],
    "name:hyw_x_preferred":[
        "\u054e\u0561\u0580\u0561\u0576\u0564"
    ],
    "name:sco_x_preferred":[
        "Varand"
    ],
    "wof:name":"Varand",
    "wof:placetype":"locality"
},
  "geometry": {"coordinates":[53.20591,36.3664],"type":"Point"}
}