{
  "type": "Feature",
  "properties": {
    "gn:admin1_code":"29",
    "gn:asciiname":"Kalejak-e Sofla",
    "gn:country_code":"IR",
    "gn:dem":1156,
    "gn:feature_class":"P",
    "gn:feature_code":"PPL",
    "gn:name":"Kalejak-e Sofl\u00e1",
    "gn:population":0,
    "gn:timezone":"Asia/Tehran",
    "iso:country":"IR",
    "name:ara_x_preferred":[
        "\u062a\u0634\u0627\u0647 \u063a\u0631\u063a"
    ],
    "name:fas_x_preferred":[
        "\u0686\u0627\u0647 \u06af\u0631\u06af"
    ],
    "name:fas_x_variant":[
        "Ch\u0101h Gorg",
        "\u06a9\u0644\u062c\u06a9 \u0633\u0641\u0644\u06cc",
        "\u06a9\u0644\u062c\u06a9"
    ],
    "name:und_x_variant":[
        "Ch\u0101h Gol",
        "Ch\u0101h-e Gol",
        "Kalejak-e Sofl\u00e1",
        "Kalejak"
    ],
    "wof:name":"Kalejak-e Sofla",
    "wof:placetype":"locality"
},
  "geometry": {"coordinates":[58.37756,28.32845],"type":"Point"}
}