{
  "type": "Feature",
  "properties": {
    "gn:admin1_code":"16",
    "gn:asciiname":"Khandan Qoli",
    "gn:country_code":"IR",
    "gn:dem":1892,
    "gn:feature_class":"P",
    "gn:feature_code":"PPL",
    "gn:name":"Kh\u0101nd\u0101n Qol\u012b",
    "gn:population":0,
    "gn:timezone":"Asia/Tehran",
    "iso:country":"IR",
    "name:ara_x_preferred":[
        "\u062e\u0627\u0646\u062f\u0627\u0646 \u0642\u0644\u064a"
    ],
    "name:fas_x_preferred":[
        "\u062e\u0627\u0646\u062f\u0627\u0646 \u0642\u0644\u06cc"
    ],
    "name:fas_x_variant":[
        "Kh\u0101nd\u0101nqol\u012b",
        "Kh\u0101nd\u0101n Qol\u012b"
    ],
    "name:und_x_variant":[
        "Khan Qul\u012b",
        "Kh\u0101neh Qul\u012b",
        "Kh\u0101ned\u0101nqol\u012b"
    ],
    "wof:name":"Khandan Qoli",
    "wof:placetype":"locality"
},
  "geometry": {"coordinates":[47.42100000000001,35.69483],"type":"Point"}
}