{
  "type": "Feature",
  "properties": {
    "gn:admin1_code":"4.0",
    "gn:asciiname":"Hikan",
    "gn:country_code":"IR",
    "gn:dem":762,
    "gn:feature_class":"P",
    "gn:feature_code":"PPL",
    "gn:name":"H\u012bk\u0101n",
    "gn:population":0,
    "gn:timezone":"Asia/Tehran",
    "iso:country":"IR",
    "name:fas_x_preferred":[
        "\u0647\u06cc\u06a9\u0627\u0646"
    ],
    "name:fas_x_variant":[
        "H\u012bk\u0101n",
        "H\u012bsk\u0101n"
    ],
    "name:und_x_variant":[
        "H\u012bsk\u0101n"
    ],
    "wof:name":"Hikan",
    "wof:placetype":"locality"
},
  "geometry": {"coordinates":[59.22196,26.7175],"type":"Point"}
}