{
  "type": "Feature",
  "properties": {
    "gn:admin1_code":"4.0",
    "gn:asciiname":"Kahn-e Magar",
    "gn:country_code":"IR",
    "gn:dem":1248,
    "gn:feature_class":"P",
    "gn:feature_code":"PPL",
    "gn:name":"Kahn-e Mag\u0101r",
    "gn:population":0,
    "gn:timezone":"Asia/Tehran",
    "iso:country":"IR",
    "name:fas_x_preferred":[
        "\u06a9\u0647\u0645\u06af\u0627\u0631"
    ],
    "name:fas_x_variant":[
        "Kahmag\u0101r",
        "\u06a9\u0647\u0646 \u0645\u06af\u0627\u0631"
    ],
    "name:und_x_variant":[
        "K\u0101mg\u0101r",
        "Kahmgar",
        "K\u0101m\u0101g\u0101r",
        "Kahn-e Mag\u0101r"
    ],
    "wof:name":"Kahn-e Magar",
    "wof:placetype":"locality"
},
  "geometry": {"coordinates":[61.76300000000001,27.1228],"type":"Point"}
}