{
  "type": "Feature",
  "properties": {
    "gn:admin1_code":"29",
    "gn:asciiname":"Tabaq-e Namdad",
    "gn:country_code":"IR",
    "gn:dem":802,
    "gn:feature_class":"P",
    "gn:feature_code":"PPLL",
    "gn:name":"\u0162abaq-e Namd\u0101d",
    "gn:population":0,
    "gn:timezone":"Asia/Tehran",
    "iso:country":"IR",
    "name:fas_x_preferred":[
        "\u0637\u0628\u0642 \u0646\u0645\u062f\u0627\u062f"
    ],
    "name:fas_x_variant":[
        "Notarkan\u012b-ye N\u012bmd\u0101d",
        "\u0162abaq-e Namd\u0101d",
        "Notarkan\u012b N\u012bmd\u0101d",
        "Namd\u0101d"
    ],
    "name:und_x_variant":[
        "Tabak-e Yanomd\u0101d"
    ],
    "wof:name":"Tabaq-e Namdad",
    "wof:placetype":"locality"
},
  "geometry": {"coordinates":[58.90619,28.0049],"type":"Point"}
}