{
  "type": "Feature",
  "properties": {
    "gn:admin1_code":"41.0",
    "gn:asciiname":"Sulabast",
    "gn:country_code":"IR",
    "gn:dem":1610,
    "gn:feature_class":"P",
    "gn:feature_code":"PPL",
    "gn:name":"S\u016bl\u0101bast",
    "gn:population":0,
    "gn:timezone":"Asia/Tehran",
    "iso:country":"IR",
    "name:fas_x_preferred":[
        "\u0633\u0648\u0644\u0627\u0628\u0633\u062a"
    ],
    "name:fas_x_variant":[
        "Sul\u0101w\u0101s",
        "S\u016bl\u0101vas",
        "S\u016bl\u0101bast"
    ],
    "name:und_x_variant":[
        "Soolabast"
    ],
    "wof:name":"Sulabast",
    "wof:placetype":"locality"
},
  "geometry": {"coordinates":[60.3162,32.5378],"type":"Point"}
}