{
  "type": "Feature",
  "properties": {
    "gn:admin1_code":"15",
    "gn:asciiname":"Shur Tang",
    "gn:country_code":"IR",
    "gn:dem":718,
    "gn:feature_class":"P",
    "gn:feature_code":"PPL",
    "gn:name":"Sh\u016br Tang",
    "gn:population":0,
    "gn:timezone":"Asia/Tehran",
    "iso:country":"IR",
    "name:fas_x_preferred":[
        "Sh\u016br Tenag"
    ],
    "name:fas_x_variant":[
        "Sh\u016br Tang",
        "\u0634\u0648\u0631 \u062a\u0646\u06af"
    ],
    "name:und_x_variant":[
        "\u0634\u0648\u0631 \u062a\u0646\u06af"
    ],
    "wof:name":"Shur Tang",
    "wof:placetype":"locality"
},
  "geometry": {"coordinates":[49.76679,31.81113],"type":"Point"}
}