{
  "type": "Feature",
  "properties": {
    "gn:admin1_code":"23",
    "gn:asciiname":"Ja`farabad Miruk",
    "gn:country_code":"IR",
    "gn:dem":1632,
    "gn:feature_class":"P",
    "gn:feature_code":"PPL",
    "gn:name":"Ja\u2018far\u0101b\u0101d M\u012br\u016bk",
    "gn:population":0,
    "gn:timezone":"Asia/Tehran",
    "iso:country":"IR",
    "name:ara_x_preferred":[
        "\u0645\u0631\u0627\u062f\u0622\u0628\u0627\u062f \u0645\u064a\u0631\u0627\u062e\u0648\u0631"
    ],
    "name:ceb_x_preferred":[
        "Ja\u2018far\u0101b\u0101d M\u012br\u016bk"
    ],
    "name:fas_x_preferred":[
        "\u0645\u064f\u0631\u0627\u062f \u0622\u0628\u0627\u062f"
    ],
    "name:fas_x_variant":[
        "\u0645\u0631\u0627\u062f \u0622\u0628\u0627\u062f \u0645\u06cc\u0631 \u0622\u062e\u0648\u0631",
        "Mor\u0101d\u0101b\u0101d-e M\u012br\u0101kh\u016br",
        "\u062c\u0639\u0641\u0631 \u0622\u0628\u0627\u062f \u0645\u06cc\u0631\u0648\u06a9",
        "\u0645\u0631\u0627\u062f\u0622\u0628\u0627\u062f \u0645\u06cc\u0631\u0627\u062e\u0648\u0631"
    ],
    "name:swe_x_preferred":[
        "Ja\u2018far\u0101b\u0101d M\u012br\u016bk"
    ],
    "name:und_x_variant":[
        "Mor\u0101d\u0101b\u0101d",
        "Mor\u0101d\u0101b\u0101d-e M\u012br \u0100khowr"
    ],
    "wof:name":"Ja`farabad Miruk",
    "wof:placetype":"locality"
},
  "geometry": {"coordinates":[47.9894,33.949],"type":"Point"}
}