{
  "type": "Feature",
  "properties": {
    "gn:admin1_code":"37.0",
    "gn:asciiname":"Qarah Sar-e Bala",
    "gn:country_code":"IR",
    "gn:dem":356,
    "gn:feature_class":"P",
    "gn:feature_code":"PPL",
    "gn:name":"Qarah Sar-e B\u0101l\u0101",
    "gn:population":0,
    "gn:timezone":"Asia/Tehran",
    "iso:country":"IR",
    "name:ceb_x_preferred":[
        "Qarah Sar-e B\u0101l\u0101"
    ],
    "name:fas_x_preferred":[
        "Qarah Yasar-e B\u0101l\u0101"
    ],
    "name:fas_x_variant":[
        "Qareh Yasar-e B\u0101l\u0101",
        "\u0642\u0631\u0647 \u064a\u0633\u0631 \u0628\u0627\u0644\u0627",
        "\u0642\u0631\u0647 \u0633\u0631 \u0628\u0627\u0644\u0627",
        "\u0642\u0631\u0647\u200c\u06cc\u0633\u0631 \u0628\u0627\u0644\u0627"
    ],
    "name:msa_x_preferred":[
        "Qarah Yasar-e Bala"
    ],
    "name:swe_x_preferred":[
        "Qarah Sar-e B\u0101l\u0101"
    ],
    "wof:name":"Qarah Sar-e Bala",
    "wof:placetype":"locality"
},
  "geometry": {"coordinates":[55.73335,37.55078],"type":"Point"}
}