{
  "type": "Feature",
  "properties": {
    "gn:admin1_code":"11",
    "gn:asciiname":"Chari",
    "gn:country_code":"IR",
    "gn:dem":248,
    "gn:feature_class":"P",
    "gn:feature_code":"PPL",
    "gn:name":"Ch\u0101r\u012b",
    "gn:population":0,
    "gn:timezone":"Asia/Tehran",
    "iso:country":"IR",
    "name:ben_x_preferred":[
        "\u099a\u09be\u09b0\u09bf"
    ],
    "name:ceb_x_preferred":[
        "Chari"
    ],
    "name:fas_x_preferred":[
        "\u0686\u0627\u0631\u06cc"
    ],
    "name:fas_x_variant":[
        "Ch\u0101r\u012b"
    ],
    "name:fin_x_preferred":[
        "Chari"
    ],
    "name:hin_x_preferred":[
        "\u091a\u0930\u0940"
    ],
    "name:ita_x_preferred":[
        "Chari"
    ],
    "name:urd_x_preferred":[
        "\u0686\u0627\u0631\u06cc"
    ],
    "wof:name":"Chari",
    "wof:placetype":"locality"
},
  "geometry": {"coordinates":[55.84861,27.40167],"type":"Point"}
}