{
  "type": "Feature",
  "properties": {
    "gn:admin1_code":"4.0",
    "gn:asciiname":"Do Chahak",
    "gn:country_code":"IR",
    "gn:dem":385,
    "gn:feature_class":"P",
    "gn:feature_code":"PPLF",
    "gn:name":"Do Ch\u0101hak",
    "gn:population":0,
    "gn:timezone":"Asia/Tehran",
    "iso:country":"IR",
    "name:fas_x_preferred":[
        "\u062f\u0648 \u0686\u0627\u0647\u06a9"
    ],
    "name:und_x_variant":[
        "Do Ch\u0101hak"
    ],
    "wof:name":"Do Chahak",
    "wof:placetype":"locality"
},
  "geometry": {"coordinates":[59.09418,27.11188],"type":"Point"}
}