{
  "type": "Feature",
  "properties": {
    "gn:admin1_code":"35.0",
    "gn:asciiname":"Izva",
    "gn:country_code":"IR",
    "gn:dem":2389,
    "gn:feature_class":"P",
    "gn:feature_code":"PPL",
    "gn:name":"\u012azv\u0101",
    "gn:population":0,
    "gn:timezone":"Asia/Tehran",
    "iso:country":"IR",
    "name:fas_x_preferred":[
        "\u0627\u06cc\u0632\u0648\u0627"
    ],
    "name:fas_x_variant":[
        "\u012azv\u0101"
    ],
    "wof:name":"Izva",
    "wof:placetype":"locality"
},
  "geometry": {"coordinates":[52.00772,36.31339000000001],"type":"Point"}
}