{
  "type": "Feature",
  "properties": {
    "gn:admin1_code":"28.0",
    "gn:asciiname":"Qomishlu",
    "gn:country_code":"IR",
    "gn:dem":2139,
    "gn:feature_class":"P",
    "gn:feature_code":"PPL",
    "gn:name":"Qom\u012bshl\u016b",
    "gn:population":0,
    "gn:timezone":"Asia/Tehran",
    "iso:country":"IR",
    "name:fas_x_preferred":[
        "Qomeshl\u016b"
    ],
    "name:fas_x_variant":[
        "Qom\u012bshl\u016b",
        "\u0642\u0645\u06cc\u0634\u0644\u0648"
    ],
    "name:und_x_variant":[
        "Qam\u012bshl\u016b",
        "Qameshl\u016b",
        "\u0642\u0645\u06cc\u0634\u0644\u0648"
    ],
    "wof:name":"Qomishlu",
    "wof:placetype":"locality"
},
  "geometry": {"coordinates":[51.4693,32.0464],"type":"Point"}
}