{
  "type": "Feature",
  "properties": {
    "gn:admin1_code":"32.0",
    "gn:asciiname":"Qi Chaman",
    "gn:country_code":"IR",
    "gn:dem":2102,
    "gn:feature_class":"P",
    "gn:feature_code":"PPL",
    "gn:name":"Q\u012b Chaman",
    "gn:population":0,
    "gn:timezone":"Asia/Tehran",
    "iso:country":"IR",
    "name:ara_x_preferred":[
        "\u0642\u064a\u0629 \u062a\u0634\u0645\u0646"
    ],
    "name:ceb_x_preferred":[
        "Qarah Chaman"
    ],
    "name:fas_x_preferred":[
        "\u0642\u064a\u0647 \u0686\u0645\u0646"
    ],
    "name:fas_x_variant":[
        "\u0642\u0631\u0647 \u0686\u0645\u0646",
        "\u0642\u06cc \u0686\u0645\u0646",
        "\u0642\u06cc\u0647 \u0686\u0645\u0646"
    ],
    "name:msa_x_preferred":[
        "Qayeh Chaman"
    ],
    "name:swe_x_preferred":[
        "Qarah Chaman"
    ],
    "name:und_x_variant":[
        "Qareh Chaman",
        "Qayeh Chaman",
        "Qarah Chaman",
        "Q\u012b Chaman"
    ],
    "wof:name":"Qi Chaman",
    "wof:placetype":"locality"
},
  "geometry": {"coordinates":[48.51501,37.98886],"type":"Point"}
}