{
  "type": "Feature",
  "properties": {
    "gn:admin1_code":"3",
    "gn:asciiname":"Charkan",
    "gn:country_code":"IR",
    "gn:dem":1765,
    "gn:feature_class":"P",
    "gn:feature_code":"PPL",
    "gn:name":"Charkan",
    "gn:population":0,
    "gn:timezone":"Asia/Tehran",
    "iso:country":"IR",
    "name:fas_x_preferred":[
        "Cherk\u012bn"
    ],
    "name:fas_x_variant":[
        "\u0686\u0631\u0643\u064a\u0646",
        "\u0686\u0631\u06a9\u0646",
        "\u0686\u0631\u06af\u0646"
    ],
    "name:und_x_variant":[
        "\u0686\u0631\u0643\u064a\u0646",
        "Charkan",
        "Chergan"
    ],
    "wof:name":"Charkan",
    "wof:placetype":"locality"
},
  "geometry": {"coordinates":[50.7472,31.57954],"type":"Point"}
}