{
  "type": "Feature",
  "properties": {
    "gn:admin1_code":"8",
    "gn:asciiname":"Behdan",
    "gn:country_code":"IR",
    "gn:dem":41,
    "gn:feature_class":"P",
    "gn:feature_code":"PPL",
    "gn:name":"Behd\u0101n",
    "gn:population":0,
    "gn:timezone":"Asia/Tehran",
    "iso:country":"IR",
    "name:fas_x_preferred":[
        "Behd\u0101n"
    ],
    "name:fas_x_variant":[
        "Behd\u0101n-e P\u0101\u2019\u012bn",
        "Behd\u0101n-e B\u0101l\u0101",
        "\u0628\u0647\u062f\u0627\u0646"
    ],
    "name:und_x_variant":[
        "\u0628\u0647\u062f\u0627\u0646"
    ],
    "wof:name":"Behdan",
    "wof:placetype":"locality"
},
  "geometry": {"coordinates":[49.62234,37.17562],"type":"Point"}
}