{
  "type": "Feature",
  "properties": {
    "gn:admin1_code":"15.0",
    "gn:asciiname":"Chal Baraftab",
    "gn:country_code":"IR",
    "gn:dem":162,
    "gn:feature_class":"P",
    "gn:feature_code":"PPL",
    "gn:name":"Ch\u0101l Bar\u0101ft\u0101b",
    "gn:population":0,
    "gn:timezone":"Asia/Tehran",
    "iso:country":"IR",
    "name:fas_x_preferred":[
        "\u0686\u0627\u0644 \u0628\u0631\u0622\u0641\u062a\u0627\u0628"
    ],
    "wof:name":"Chal Baraftab",
    "wof:placetype":"locality"
},
  "geometry": {"coordinates":[48.91667,32.05],"type":"Point"}
}