{
  "type": "Feature",
  "properties": {
    "iso:country":"IR",
    "name:fas_x_preferred":[
        "\u0627\u0633\u062a\u062e\u0631 \u0633\u0631"
    ],
    "name:unk_x_variant":[
        "Estakhr Sar"
    ],
    "qs:gn_country":"IR",
    "qs:gn_fcode":"PPL",
    "qs:gn_pop":0,
    "qs:name":"Sakht Sar",
    "qs:name_adm0":"Iran",
    "qs:name_adm1":"Mazandaran",
    "qs:photos":48,
    "qs:photos_1k":10,
    "qs:photos_9k":1,
    "qs:photos_9r":2,
    "qs:photos_all":48,
    "qs:photos_sr":2,
    "qs:placetype":"Town",
    "qs:pop_sr":"0",
    "qs:woe_adm0":23424851,
    "wd:elevation":985.0,
    "wd:wordcount":1693,
    "wof:name":"Sakht Sar",
    "wof:placetype":"locality"
},
  "geometry": {"coordinates":[50.863,36.76332],"type":"Point"}
}