{
  "type": "Feature",
  "properties": {
    "gn:admin1_code":"7",
    "gn:asciiname":"Cheshmeh Dozdan",
    "gn:country_code":"IR",
    "gn:dem":1751,
    "gn:feature_class":"P",
    "gn:feature_code":"PPL",
    "gn:name":"Cheshmeh Dozd\u0101n",
    "gn:population":0,
    "gn:timezone":"Asia/Tehran",
    "iso:country":"IR",
    "name:fas_x_preferred":[
        "Cheshmeh Dozd\u0101n"
    ],
    "name:fas_x_variant":[
        "\u0686\u0634\u0645\u0647 \u062f\u0632\u062f\u0627\u0646"
    ],
    "name:und_x_variant":[
        "Chashmeh-e Dozd\u0101n",
        "\u0686\u0634\u0645\u0647 \u062f\u0632\u062f\u0627\u0646"
    ],
    "wof:name":"Cheshmeh Dozdan",
    "wof:placetype":"locality"
},
  "geometry": {"coordinates":[51.95679000000001,30.06331],"type":"Point"}
}