{
  "type": "Feature",
  "properties": {
    "gn:admin1_code":"13.0",
    "gn:asciiname":"Banehdar-e Bala",
    "gn:country_code":"IR",
    "gn:dem":930,
    "gn:feature_class":"P",
    "gn:feature_code":"PPL",
    "gn:name":"B\u0101nehd\u0101r-e B\u0101l\u0101",
    "gn:population":0,
    "gn:timezone":"Asia/Tehran",
    "iso:country":"IR",
    "name:fas_x_preferred":[
        "\u0628\u0627\u0646\u0647 \u062f\u0627\u0631 \u0628\u0627\u0644\u0627"
    ],
    "name:fas_x_variant":[
        "B\u0101nehd\u0101r-e B\u0101l\u0101"
    ],
    "wof:name":"Banehdar-e Bala",
    "wof:placetype":"locality"
},
  "geometry": {"coordinates":[45.9063,34.8887],"type":"Point"}
}