{
  "type": "Feature",
  "properties": {
    "gn:admin1_code":"41",
    "gn:asciiname":"Nughab",
    "gn:country_code":"IR",
    "gn:dem":1595,
    "gn:feature_class":"P",
    "gn:feature_code":"PPL",
    "gn:name":"N\u016bgh\u0101b",
    "gn:population":0,
    "gn:timezone":"Asia/Tehran",
    "iso:country":"IR",
    "name:fas_x_preferred":[
        "\u0646\u0648\u063a\u0627\u0628"
    ],
    "name:fas_x_variant":[
        "N\u016bgh\u0101b"
    ],
    "name:und_x_variant":[
        "Naugh\u0101b",
        "Nowgh\u0101b",
        "Nooghab",
        "N\u016bq\u0101b",
        "Nowq\u0101b"
    ],
    "wof:name":"Nughab",
    "wof:placetype":"locality"
},
  "geometry": {"coordinates":[59.91853,32.9808],"type":"Point"}
}