{
  "type": "Feature",
  "properties": {
    "gn:admin1_code":"37.0",
    "gn:asciiname":"Tappeh-ye Hajji Sari",
    "gn:country_code":"IR",
    "gn:dem":60,
    "gn:feature_class":"P",
    "gn:feature_code":"PPL",
    "gn:name":"Tappeh-ye \u1e28\u0101jj\u012b S\u0101r\u012b",
    "gn:population":0,
    "gn:timezone":"Asia/Tehran",
    "iso:country":"IR",
    "name:fas_x_preferred":[
        "\u062a\u067e\u0647 \u062d\u0627\u062c\u06cc \u0633\u0627\u0631\u06cc"
    ],
    "name:und_x_variant":[
        "Tappeh-ye \u1e28\u0101jj\u012b S\u0101r\u012b"
    ],
    "wof:name":"Tappeh-ye Hajji Sari",
    "wof:placetype":"locality"
},
  "geometry": {"coordinates":[55.26606999999999,37.17301],"type":"Point"}
}