{
  "type": "Feature",
  "properties": {
    "gn:admin1_code":"8",
    "gn:asciiname":"Barzeh Kuh",
    "gn:country_code":"IR",
    "gn:dem":2051,
    "gn:feature_class":"P",
    "gn:feature_code":"PPL",
    "gn:name":"Barzeh K\u016bh",
    "gn:population":0,
    "gn:timezone":"Asia/Tehran",
    "iso:country":"IR",
    "name:fas_x_preferred":[
        "\u0628\u0631\u0632\u0647 \u06a9\u0648\u0647"
    ],
    "name:fas_x_variant":[
        "Barzeh K\u016bh",
        "\u0628\u0631\u0632 \u06a9\u0648\u0647"
    ],
    "name:und_x_variant":[
        "Borz K\u016bh",
        "Barz K\u016bh"
    ],
    "wof:name":"Barzeh Kuh",
    "wof:placetype":"locality"
},
  "geometry": {"coordinates":[48.7782,37.5462],"type":"Point"}
}