{
  "type": "Feature",
  "properties": {
    "gn:admin1_code":"29",
    "gn:asciiname":"Baqerabad",
    "gn:country_code":"IR",
    "gn:dem":392,
    "gn:feature_class":"P",
    "gn:feature_code":"PPL",
    "gn:name":"B\u0101qer\u0101b\u0101d",
    "gn:population":0,
    "gn:timezone":"Asia/Tehran",
    "iso:country":"IR",
    "name:fas_x_preferred":[
        "\u0628\u0627\u0642\u0631 \u0622\u0628\u0627\u062f"
    ],
    "name:fas_x_variant":[
        "B\u0101qer\u0101b\u0101d",
        "\u0628\u0627\u0642\u0631\u0622\u0628\u0627\u062f"
    ],
    "wof:name":"Baqerabad",
    "wof:placetype":"locality"
},
  "geometry": {"coordinates":[58.59099000000001,27.79991],"type":"Point"}
}