{
  "type": "Feature",
  "properties": {
    "gn:admin1_code":"37",
    "gn:asciiname":"Ilvar-e Yek Dangeh",
    "gn:country_code":"IR",
    "gn:dem":-24,
    "gn:feature_class":"P",
    "gn:feature_code":"PPL",
    "gn:name":"\u012alv\u0101r-e Yek D\u0101ngeh",
    "gn:population":0,
    "gn:timezone":"Asia/Tehran",
    "iso:country":"IR",
    "name:fas_x_preferred":[
        "\u064a\u0644\u0648\u0627\u0631\u0650 \u064a\u0650\u0643 \u062f\u0627\u0646\u06af\u0650\u0647"
    ],
    "name:fas_x_variant":[
        "\u012alv\u0101r-e Yek D\u0101ngeh",
        "\u0627\u06cc\u0644\u0648\u0627\u0631 \u06cc\u06a9\u200c\u062f\u0627\u0646\u06af\u0647"
    ],
    "name:msa_x_preferred":[
        "Ilvar-e Yek Dangeh"
    ],
    "wof:name":"Ilvar-e Yek Dangeh",
    "wof:placetype":"locality"
},
  "geometry": {"coordinates":[54.15028,36.89972],"type":"Point"}
}