{
  "type": "Feature",
  "properties": {
    "gn:admin1_code":"35.0",
    "gn:asciiname":"Afrasiab Kola",
    "gn:country_code":"IR",
    "gn:dem":5,
    "gn:feature_class":"P",
    "gn:feature_code":"PPL",
    "gn:name":"Afr\u0101s\u012b\u0101b Kol\u0101",
    "gn:population":0,
    "gn:timezone":"Asia/Tehran",
    "iso:country":"IR",
    "name:fas_x_preferred":[
        "\u0627\u0641\u0631\u0627\u0633\u06cc\u0627\u0628 \u06a9\u0644\u0627"
    ],
    "name:fas_x_variant":[
        "Afr\u0101s\u012b\u0101b Kol\u0101"
    ],
    "wof:name":"Afrasiab Kola",
    "wof:placetype":"locality"
},
  "geometry": {"coordinates":[52.05801,36.5362],"type":"Point"}
}