{
  "type": "Feature",
  "properties": {
    "gn:admin1_code":"23",
    "gn:asciiname":"Gashur-e Qal`eh Mohammad",
    "gn:country_code":"IR",
    "gn:dem":1925,
    "gn:feature_class":"P",
    "gn:feature_code":"PPL",
    "gn:name":"Gash\u016br-e Qal`eh Mo\u1e29ammad",
    "gn:population":0,
    "gn:timezone":"Asia/Tehran",
    "iso:country":"IR",
    "name:fas_x_preferred":[
        "\u06af\u064e\u0634\u0648\u0631\u0650 \u0642\u064e\u0644\u0639\u0650\u0647 \u0645\u064f\u062d\u064e\u0645\u064e\u0651\u062f"
    ],
    "wof:name":"Gashur-e Qal`eh Mohammad",
    "wof:placetype":"locality"
},
  "geometry": {"coordinates":[47.71667,34.23333],"type":"Point"}
}