{
  "type": "Feature",
  "properties": {
    "gn:admin1_code":"4.0",
    "gn:asciiname":"Sanjerabad",
    "gn:country_code":"IR",
    "gn:dem":1119,
    "gn:feature_class":"P",
    "gn:feature_code":"PPL",
    "gn:name":"Sanjer\u0101b\u0101d",
    "gn:population":0,
    "gn:timezone":"Asia/Tehran",
    "iso:country":"IR",
    "name:fas_x_preferred":[
        "\u0633\u0646\u062c\u0631 \u0622\u0628\u0627\u062f"
    ],
    "name:und_x_variant":[
        "Sanjer\u0101b\u0101d"
    ],
    "wof:name":"Sanjerabad",
    "wof:placetype":"locality"
},
  "geometry": {"coordinates":[59.98779,29.86673],"type":"Point"}
}