{
  "type": "Feature",
  "properties": {
    "gn:admin1_code":"32",
    "gn:asciiname":"`Aruj Daghi",
    "gn:country_code":"IR",
    "gn:dem":700,
    "gn:feature_class":"P",
    "gn:feature_code":"PPL",
    "gn:name":"\u2018Ar\u016bj D\u0101gh\u012b",
    "gn:population":0,
    "gn:timezone":"Asia/Tehran",
    "iso:country":"IR",
    "name:fas_x_preferred":[
        "\u2018Ar\u016bj D\u0101gh\u012b"
    ],
    "name:fas_x_variant":[
        "\u0639\u064e\u0631\u0648\u062c \u062f\u0627\u063a\u06cc"
    ],
    "wof:name":"`Aruj Daghi",
    "wof:placetype":"locality"
},
  "geometry": {"coordinates":[48.25,39.01667],"type":"Point"}
}