{
  "type": "Feature",
  "properties": {
    "gn:admin1_code":"11",
    "gn:asciiname":"Ashuri",
    "gn:country_code":"IR",
    "gn:dem":23,
    "gn:feature_class":"P",
    "gn:feature_code":"PPL",
    "gn:name":"\u0100sh\u016br\u012b",
    "gn:population":0,
    "gn:timezone":"Asia/Tehran",
    "iso:country":"IR",
    "name:fas_x_preferred":[
        "\u0622\u0634\u0648\u0631\u06cc"
    ],
    "name:fas_x_variant":[
        "\u0100sh\u016br\u012b"
    ],
    "name:heb_x_preferred":[
        "\u05d0\u05d5\u05ea\u05d9\u05d5\u05ea \u05e1\u05ea\"\u05dd"
    ],
    "wof:name":"Ashuri",
    "wof:placetype":"locality"
},
  "geometry": {"coordinates":[57.154,26.9494],"type":"Point"}
}