{
  "type": "Feature",
  "properties": {
    "gn:admin1_code":"8.0",
    "gn:asciiname":"Qal`eh-ye Kul",
    "gn:country_code":"IR",
    "gn:dem":93,
    "gn:feature_class":"P",
    "gn:feature_code":"PPL",
    "gn:name":"Qal\u2018eh-ye K\u016bl",
    "gn:population":0,
    "gn:timezone":"Asia/Tehran",
    "iso:country":"IR",
    "name:fas_x_preferred":[
        "\u0642\u0644\u0639\u0647 \u06a9\u0648\u0644"
    ],
    "name:und_x_variant":[
        "Qal\u2018eh-ye K\u016bl"
    ],
    "wof:name":"Qal`eh-ye Kul",
    "wof:placetype":"locality"
},
  "geometry": {"coordinates":[49.11979,37.33155],"type":"Point"}
}