{
  "type": "Feature",
  "properties": {
    "gn:admin1_code":"42.0",
    "gn:asciiname":"Koshkak",
    "gn:country_code":"IR",
    "gn:dem":903,
    "gn:feature_class":"P",
    "gn:feature_code":"PPL",
    "gn:name":"Koshkak",
    "gn:population":0,
    "gn:timezone":"Asia/Tehran",
    "iso:country":"IR",
    "name:fas_x_preferred":[
        "\u06a9\u0634\u06a9\u06a9"
    ],
    "wof:name":"Koshkak",
    "wof:placetype":"locality"
},
  "geometry": {"coordinates":[60.7197,34.9237],"type":"Point"}
}