{
  "type": "Feature",
  "properties": {
    "gn:admin1_code":"7.0",
    "gn:asciiname":"Tashk",
    "gn:country_code":"IR",
    "gn:dem":1590,
    "gn:feature_class":"P",
    "gn:feature_code":"PPL",
    "gn:name":"\u0162ashk",
    "gn:population":0,
    "gn:timezone":"Asia/Tehran",
    "iso:country":"IR",
    "name:fas_x_preferred":[
        "\u0162ashk"
    ],
    "name:fas_x_variant":[
        "\u0637\u0634\u06a9"
    ],
    "name:msa_x_preferred":[
        "Tashk"
    ],
    "wof:name":"Tashk",
    "wof:placetype":"locality"
},
  "geometry": {"coordinates":[53.59917,29.82806],"type":"Point"}
}