{
  "type": "Feature",
  "properties": {
    "gn:admin1_code":"33.0",
    "gn:asciiname":"Abak",
    "gn:country_code":"IR",
    "gn:dem":1363,
    "gn:feature_class":"P",
    "gn:feature_code":"PPL",
    "gn:name":"Abak",
    "gn:population":0,
    "gn:timezone":"Asia/Tehran",
    "iso:country":"IR",
    "name:fas_x_preferred":[
        "\u0627\u0628\u0643"
    ],
    "name:fas_x_variant":[
        "\u0100bak"
    ],
    "wof:name":"Abak",
    "wof:placetype":"locality"
},
  "geometry": {"coordinates":[47.5672,37.4046],"type":"Point"}
}