{
  "type": "Feature",
  "properties": {
    "gn:admin1_code":"5",
    "gn:asciiname":"Puleh Mashemi",
    "gn:country_code":"IR",
    "gn:dem":1529,
    "gn:feature_class":"P",
    "gn:feature_code":"PPL",
    "gn:name":"P\u016bleh M\u0101shem\u012b",
    "gn:population":0,
    "gn:timezone":"Asia/Tehran",
    "iso:country":"IR",
    "name:fas_x_preferred":[
        "M\u0101shem\u012b-ye \u2018Oly\u0101"
    ],
    "name:fas_x_variant":[
        "\u0645\u0627\u0634\u0645\u06cc \u0639\u0644\u064a\u0627",
        "\u067e\u0648\u0644\u0647 \u0645\u0627\u0634\u0645\u06cc"
    ],
    "name:und_x_variant":[
        "\u0645\u0627\u0634\u0645\u06cc \u0639\u0644\u064a\u0627",
        "P\u016bleh M\u0101shem\u012b"
    ],
    "wof:name":"Puleh Mashemi",
    "wof:placetype":"locality"
},
  "geometry": {"coordinates":[50.70128,31.35237],"type":"Point"}
}