{
  "type": "Feature",
  "properties": {
    "gn:admin1_code":"35",
    "gn:asciiname":"Aneh",
    "gn:country_code":"IR",
    "gn:dem":1797,
    "gn:feature_class":"P",
    "gn:feature_code":"PPL",
    "gn:name":"Aneh",
    "gn:population":0,
    "gn:timezone":"Asia/Tehran",
    "iso:country":"IR",
    "name:ara_x_preferred":[
        "\u0623\u0646\u0647\u0629"
    ],
    "name:fas_x_preferred":[
        "\u0622\u0646\u0647\u0650\u0647"
    ],
    "name:fas_x_variant":[
        "\u0100nheh",
        "\u0627\u0646\u0647\u0647",
        "\u0627\u0646\u0647"
    ],
    "name:ukr_x_preferred":[
        "\u0410\u043d\u0433\u0435"
    ],
    "name:und_x_variant":[
        "Anheh",
        "Aneh"
    ],
    "wof:name":"Aneh",
    "wof:placetype":"locality"
},
  "geometry": {"coordinates":[52.18827,35.88746],"type":"Point"}
}