{
  "type": "Feature",
  "properties": {
    "gn:admin1_code":"42",
    "gn:asciiname":"Bongash",
    "gn:country_code":"IR",
    "gn:dem":1880,
    "gn:feature_class":"P",
    "gn:feature_code":"PPL",
    "gn:name":"Bongash",
    "gn:population":0,
    "gn:timezone":"Asia/Tehran",
    "iso:country":"IR",
    "name:fas_x_preferred":[
        "\u0628\u0646\u06af\u0634"
    ],
    "wof:name":"Bongash",
    "wof:placetype":"locality"
},
  "geometry": {"coordinates":[59.62051,35.53749000000001],"type":"Point"}
}