{
  "type": "Feature",
  "properties": {
    "gn:admin1_code":"3",
    "gn:asciiname":"Qal`eh Sukhteh",
    "gn:country_code":"IR",
    "gn:dem":2026,
    "gn:feature_class":"P",
    "gn:feature_code":"PPL",
    "gn:name":"Qal\u2018eh S\u016bkhteh",
    "gn:population":0,
    "gn:timezone":"Asia/Tehran",
    "iso:country":"IR",
    "name:fas_x_preferred":[
        "\u0642\u0644\u0639\u0647 \u0633\u0648\u062e\u062a\u0647"
    ],
    "name:fas_x_variant":[
        "Qal\u2018eh S\u016bkhteh",
        "\u0642\u064e\u0644\u0639\u0650\u06c0 \u0633\u0648\u062e\u062a\u0650\u0647",
        "\u0642\u064e\u0644\u0639\u0650\u0647 \u0633\u0648\u062e\u062a\u064e"
    ],
    "name:und_x_variant":[
        "Qal\u2018eh S\u016bkhta",
        "Qal\u2018eh-ye S\u016bkhteh"
    ],
    "wof:name":"Qal`eh Sukhteh",
    "wof:placetype":"locality"
},
  "geometry": {"coordinates":[51.12058,31.29737],"type":"Point"}
}