{
  "type": "Feature",
  "properties": {
    "gn:admin1_code":"9",
    "gn:asciiname":"`Eynabad",
    "gn:country_code":"IR",
    "gn:dem":1774,
    "gn:feature_class":"P",
    "gn:feature_code":"PPL",
    "gn:name":"\u2018Eyn\u0101b\u0101d",
    "gn:population":0,
    "gn:timezone":"Asia/Tehran",
    "iso:country":"IR",
    "name:fas_x_preferred":[
        "\u2018Eyn\u0101b\u0101d"
    ],
    "name:fas_x_variant":[
        "\u0639\u06cc\u0646 \u0622\u0628\u0627\u062f",
        "\u0642\u0644\u0639\u0647 \u0622\u0642\u0627 \u0628\u06cc\u06af \u0633\u0627\u0628\u0642",
        "\u0642\u0644\u0639\u0647 \u0622\u0642\u0627 \u0628\u06cc\u06a9",
        "\u0639\u06cc\u0646\u200c\u0622\u0628\u0627\u062f"
    ],
    "name:msa_x_preferred":[
        "Eynabad"
    ],
    "name:und_x_variant":[
        "Qal\u2018eh-ye \u0100q\u0101 Beyg-e S\u0101beq",
        "Qal\u2018eh-ye \u0100q\u0101 Beyk"
    ],
    "wof:name":"`Eynabad",
    "wof:placetype":"locality"
},
  "geometry": {"coordinates":[48.42613,34.55922],"type":"Point"}
}