{
  "type": "Feature",
  "properties": {
    "gn:admin1_code":"13",
    "gn:asciiname":"Murt-e Sabz",
    "gn:country_code":"IR",
    "gn:dem":867,
    "gn:feature_class":"P",
    "gn:feature_code":"PPL",
    "gn:name":"M\u016brt-e Sabz",
    "gn:population":0,
    "gn:timezone":"Asia/Tehran",
    "iso:country":"IR",
    "name:ara_x_preferred":[
        "\u0645\u0648\u0631\u062a\u200c\u0633\u0628\u0632"
    ],
    "name:ceb_x_preferred":[
        "M\u016brt-e Sabz"
    ],
    "name:fas_x_preferred":[
        "\u0645\u0648\u0631\u062a \u0633\u0628\u0632"
    ],
    "name:fas_x_variant":[
        "M\u016brt-e Sabz",
        "\u0645\u0648\u0631\u062a\u200c\u0633\u0628\u0632"
    ],
    "name:swe_x_preferred":[
        "M\u016brt-e Sabz"
    ],
    "wof:name":"Murt-e Sabz",
    "wof:placetype":"locality"
},
  "geometry": {"coordinates":[45.9127,34.0043],"type":"Point"}
}