{
  "type": "Feature",
  "properties": {
    "gn:admin1_code":"16",
    "gn:asciiname":"Navgaran",
    "gn:country_code":"IR",
    "gn:dem":2043,
    "gn:feature_class":"P",
    "gn:feature_code":"PPL",
    "gn:name":"N\u0101vgar\u0101n",
    "gn:population":0,
    "gn:timezone":"Asia/Tehran",
    "iso:country":"IR",
    "name:ara_x_preferred":[
        "\u0646\u0627\u0648\u063a\u0631\u0627\u0646"
    ],
    "name:ceb_x_preferred":[
        "Nowgar\u0101n"
    ],
    "name:fas_x_preferred":[
        "\u0646\u0648\u06af\u0631\u0627\u0646"
    ],
    "name:fas_x_variant":[
        "N\u0101vgar\u0101n",
        "Nowgar\u0101n",
        "\u0646\u0627\u0648\u06af\u0631\u0627\u0646"
    ],
    "name:swe_x_preferred":[
        "Nowgar\u0101n"
    ],
    "name:und_x_variant":[
        "Nau Gar\u0101n",
        "Now Gar\u0101n",
        "Namgaran"
    ],
    "wof:name":"Navgaran",
    "wof:placetype":"locality"
},
  "geometry": {"coordinates":[47.21102,35.46015],"type":"Point"}
}