{
  "type": "Feature",
  "properties": {
    "gn:admin1_code":"15",
    "gn:asciiname":"Hajji Nasrollah",
    "gn:country_code":"IR",
    "gn:dem":24,
    "gn:feature_class":"P",
    "gn:feature_code":"PPL",
    "gn:name":"\u1e28\u0101jj\u012b Na\u015froll\u0101h",
    "gn:population":0,
    "gn:timezone":"Asia/Tehran",
    "iso:country":"IR",
    "name:fas_x_preferred":[
        "\u1e28\u0101jj\u012b Na\u015froll\u0101h"
    ],
    "wof:name":"Hajji Nasrollah",
    "wof:placetype":"locality"
},
  "geometry": {"coordinates":[48.81944,31.55639],"type":"Point"}
}