{
  "type": "Feature",
  "properties": {
    "gn:admin1_code":"35.0",
    "gn:asciiname":"Gorg Taj",
    "gn:country_code":"IR",
    "gn:dem":678,
    "gn:feature_class":"P",
    "gn:feature_code":"PPL",
    "gn:name":"Gorg Taj",
    "gn:population":0,
    "gn:timezone":"Asia/Tehran",
    "iso:country":"IR",
    "name:fas_x_preferred":[
        "\u06af\u064f\u0631\u06af \u062a\u0627\u062c"
    ],
    "name:fas_x_variant":[
        "\u06af\u0631\u06af \u062a\u062c",
        "\u06af\u0631\u06af\u062a\u062c"
    ],
    "name:mzn_x_preferred":[
        "\u06af\u0631\u06af\u062a\u062c"
    ],
    "name:und_x_variant":[
        "Gorg T\u0101j",
        "\u06af\u0631\u06af \u062a\u062c",
        "Gorg Taj"
    ],
    "wof:name":"Gorg Taj",
    "wof:placetype":"locality"
},
  "geometry": {"coordinates":[53.57803000000001,36.54538],"type":"Point"}
}