{
  "type": "Feature",
  "properties": {
    "gn:admin1_code":"33",
    "gn:asciiname":"Qashuqchi",
    "gn:country_code":"IR",
    "gn:dem":1385,
    "gn:feature_class":"P",
    "gn:feature_code":"PPL",
    "gn:name":"Q\u0101sh\u016bqch\u012b",
    "gn:population":0,
    "gn:timezone":"Asia/Tehran",
    "iso:country":"IR",
    "name:fas_x_preferred":[
        "\u0642\u0627\u0634\u0648\u0642\u0686\u06cc"
    ],
    "name:fas_x_variant":[
        "Q\u0101sh\u016bqch\u012b",
        "\u0642\u0627\u0634\u0642\u0686\u06cc"
    ],
    "name:und_x_variant":[
        "Q\u0101shoqch\u012b"
    ],
    "wof:name":"Qashuqchi",
    "wof:placetype":"locality"
},
  "geometry": {"coordinates":[46.2978,37.047],"type":"Point"}
}