{
  "type": "Feature",
  "properties": {
    "gn:admin1_code":"23.0",
    "gn:asciiname":"Golsir",
    "gn:country_code":"IR",
    "gn:dem":1493,
    "gn:feature_class":"P",
    "gn:feature_code":"PPL",
    "gn:name":"Gols\u012br",
    "gn:population":0,
    "gn:timezone":"Asia/Tehran",
    "iso:country":"IR",
    "name:fas_x_preferred":[
        "\u06af\u064f\u0644\u0633\u064a\u0631"
    ],
    "name:fas_x_variant":[
        "Gols\u012br"
    ],
    "wof:name":"Golsir",
    "wof:placetype":"locality"
},
  "geometry": {"coordinates":[48.78333,33.23333],"type":"Point"}
}