{
  "type": "Feature",
  "properties": {
    "gn:admin1_code":"29",
    "gn:asciiname":"Ab Shuru'iyeh",
    "gn:country_code":"IR",
    "gn:dem":2112,
    "gn:feature_class":"P",
    "gn:feature_code":"PPL",
    "gn:name":"\u0100b Sh\u016br\u016b\u2019\u012byeh",
    "gn:population":0,
    "gn:timezone":"Asia/Tehran",
    "iso:country":"IR",
    "name:fas_x_preferred":[
        "\u0100b Sh\u016br\u016b\u2019\u012byeh"
    ],
    "wof:name":"Ab Shuru'iyeh",
    "wof:placetype":"locality"
},
  "geometry": {"coordinates":[57.28111,30.52278],"type":"Point"}
}