{
  "type": "Feature",
  "properties": {
    "gn:admin1_code":"7",
    "gn:asciiname":"Seh Chah-e Kuh Sorkh",
    "gn:country_code":"IR",
    "gn:dem":1813,
    "gn:feature_class":"P",
    "gn:feature_code":"PPL",
    "gn:name":"Seh Ch\u0101h-e K\u016bh Sorkh",
    "gn:population":0,
    "gn:timezone":"Asia/Tehran",
    "iso:country":"IR",
    "name:fas_x_preferred":[
        "Seh Ch\u0101h-e K\u016bh Sorkh"
    ],
    "wof:name":"Seh Chah-e Kuh Sorkh",
    "wof:placetype":"locality"
},
  "geometry": {"coordinates":[52.44611,29.0625],"type":"Point"}
}