{
  "type": "Feature",
  "properties": {
    "gn:admin1_code":"13",
    "gn:asciiname":"Chambatan-e Bala",
    "gn:country_code":"IR",
    "gn:dem":1279,
    "gn:feature_class":"P",
    "gn:feature_code":"PPL",
    "gn:name":"Chamba\u0163\u0101n-e B\u0101l\u0101",
    "gn:population":0,
    "gn:timezone":"Asia/Tehran",
    "iso:country":"IR",
    "name:fas_x_preferred":[
        "\u0686\u0645\u0628\u0637\u0627\u0646 \u0628\u0627\u0644\u0627"
    ],
    "name:fas_x_variant":[
        "Chamba\u0163\u0101n-e \u2018Oly\u0101",
        "Chamba\u0163\u0101n-e B\u0101l\u0101"
    ],
    "wof:name":"Chambatan-e Bala",
    "wof:placetype":"locality"
},
  "geometry": {"coordinates":[47.4623,34.3941],"type":"Point"}
}