{
  "type": "Feature",
  "properties": {
    "gn:admin1_code":"15",
    "gn:asciiname":"Shahrak-e Piruzi",
    "gn:country_code":"IR",
    "gn:dem":82,
    "gn:feature_class":"P",
    "gn:feature_code":"PPL",
    "gn:name":"Shahrak-e P\u012br\u016bz\u012b",
    "gn:population":0,
    "gn:timezone":"Asia/Tehran",
    "iso:country":"IR",
    "name:fas_x_preferred":[
        "\u0634\u0647\u0631\u06a9 \u067e\u06cc\u0631\u0648\u0632\u06cc"
    ],
    "name:fas_x_variant":[
        "Shahrak-e Behr\u016bz\u012b",
        "Shahrak-e P\u012br\u016bz\u012b",
        "\u0642\u0644\u0639\u0647 \u0631\u0628\u0639 \u0627\u0644\u0648\u06cc\u062e"
    ],
    "name:und_x_variant":[
        "Qal\u2018eh-ye Rob\u2018 ol V\u012bkh"
    ],
    "wof:name":"Shahrak-e Piruzi",
    "wof:placetype":"locality"
},
  "geometry": {"coordinates":[48.35336,32.24821],"type":"Point"}
}