{
  "type": "Feature",
  "properties": {
    "gn:admin1_code":"9",
    "gn:asciiname":"Deh Piaz",
    "gn:country_code":"IR",
    "gn:dem":1724,
    "gn:feature_class":"P",
    "gn:feature_code":"PPL",
    "gn:name":"Deh P\u012b\u0101z",
    "gn:population":0,
    "gn:timezone":"Asia/Tehran",
    "iso:country":"IR",
    "name:fas_x_preferred":[
        "\u062f\u0650\u0647 \u067e\u0650\u064a\u0627\u0632"
    ],
    "name:fas_x_variant":[
        "\u062f\u0650\u0647 \u067e\u064a\u0651\u0627\u0632",
        "Deh P\u012b\u0101z",
        "\u062f\u0647 \u067e\u06cc\u0627\u0632"
    ],
    "name:msa_x_preferred":[
        "Deh Piaz"
    ],
    "name:und_x_variant":[
        "Deh Pey\u0101z",
        "Deh P\u012by\u0101z"
    ],
    "wof:name":"Deh Piaz",
    "wof:placetype":"locality"
},
  "geometry": {"coordinates":[48.5148,34.88208],"type":"Point"}
}