{
  "type": "Feature",
  "properties": {
    "gn:admin1_code":"8.0",
    "gn:asciiname":"Bala Mahalleh-ye Diz Kuh",
    "gn:country_code":"IR",
    "gn:dem":265,
    "gn:feature_class":"P",
    "gn:feature_code":"PPL",
    "gn:name":"B\u0101l\u0101 Ma\u1e29alleh-ye D\u012bz K\u016bh",
    "gn:population":0,
    "gn:timezone":"Asia/Tehran",
    "iso:country":"IR",
    "name:fas_x_preferred":[
        "\u0628\u0627\u0644\u0627 \u0645\u062d\u0644\u0647 \u062f\u06cc\u0632 \u06a9\u0648\u0647"
    ],
    "name:und_x_variant":[
        "B\u0101l\u0101 Ma\u1e29alleh-ye D\u012bz K\u016bh"
    ],
    "wof:name":"Bala Mahalleh-ye Diz Kuh",
    "wof:placetype":"locality"
},
  "geometry": {"coordinates":[49.58175,37.0231],"type":"Point"}
}