{
  "type": "Feature",
  "properties": {
    "gn:admin1_code":"33",
    "gn:asciiname":"Ahmadabad",
    "gn:country_code":"IR",
    "gn:dem":1278,
    "gn:feature_class":"P",
    "gn:feature_code":"PPL",
    "gn:name":"A\u1e29mad\u0101b\u0101d",
    "gn:population":0,
    "gn:timezone":"Asia/Tehran",
    "iso:country":"IR",
    "name:fas_x_preferred":[
        "\u0627\u062d\u0645\u062f \u0622\u0628\u0627\u062f"
    ],
    "name:fas_x_variant":[
        "A\u1e29mad\u0101b\u0101d"
    ],
    "wof:name":"Ahmadabad",
    "wof:placetype":"locality"
},
  "geometry": {"coordinates":[45.9913,37.1792],"type":"Point"}
}