{
  "type": "Feature",
  "properties": {
    "gn:admin1_code":"23",
    "gn:asciiname":"Kalak Bisheh-ye Sofla",
    "gn:country_code":"IR",
    "gn:dem":1107,
    "gn:feature_class":"P",
    "gn:feature_code":"PPL",
    "gn:name":"Kalak B\u012bsheh-ye Sofl\u00e1",
    "gn:population":0,
    "gn:timezone":"Asia/Tehran",
    "iso:country":"IR",
    "name:fas_x_preferred":[
        "\u0643\u0650\u0644\u064e\u0643 \u0628\u064a\u0634\u0650\u06c0 \u0635\u0627\u062f\u0650\u0642"
    ],
    "name:fas_x_variant":[
        "\u06a9\u0644\u06a9 \u0628\u06cc\u0634\u0647 \u0633\u0641\u0644\u06cc",
        "Kelak B\u012bsheh-ye \u015e\u0101deq",
        "Kalak B\u012bsheh-ye Sofl\u00e1"
    ],
    "name:und_x_variant":[
        "Kelak B\u012bsheh-ye Seyyed Mo\u1e29ammad",
        "\u06a9\u0644\u06a9 \u0628\u064a\u0634\u0647 \u0633\u064a\u062f \u0645\u062d\u0645\u062f"
    ],
    "wof:name":"Kalak Bisheh-ye Sofla",
    "wof:placetype":"locality"
},
  "geometry": {"coordinates":[47.8947,33.2129],"type":"Point"}
}