{
  "type": "Feature",
  "properties": {
    "gn:admin1_code":"15",
    "gn:asciiname":"Kamar Deraz",
    "gn:country_code":"IR",
    "gn:dem":882,
    "gn:feature_class":"P",
    "gn:feature_code":"PPL",
    "gn:name":"Kamar Der\u0101z",
    "gn:population":0,
    "gn:timezone":"Asia/Tehran",
    "iso:country":"IR",
    "name:ceb_x_preferred":[
        "Kamar Der\u0101z"
    ],
    "name:fas_x_preferred":[
        "Kamar Der\u0101z"
    ],
    "name:fas_x_variant":[
        "\u06a9\u0645\u0631 \u062f\u0631\u0627\u0632",
        "\u06a9\u0645\u0631\u062f\u0631\u0627\u0632"
    ],
    "name:swe_x_preferred":[
        "Kamar Der\u0101z"
    ],
    "name:und_x_variant":[
        "Boneh-ye Kord",
        "Boneh-ye Kord\u012b",
        "\u06a9\u0645\u0631 \u062f\u0631\u0627\u0632"
    ],
    "wof:name":"Kamar Deraz",
    "wof:placetype":"locality"
},
  "geometry": {"coordinates":[49.8656,31.70116],"type":"Point"}
}