{
  "type": "Feature",
  "properties": {
    "gn:admin1_code":"26.0",
    "gn:asciiname":"Tutak",
    "gn:country_code":"IR",
    "gn:dem":1321,
    "gn:feature_class":"P",
    "gn:feature_code":"PPL",
    "gn:name":"T\u016btak",
    "gn:population":0,
    "gn:timezone":"Asia/Tehran",
    "iso:country":"IR",
    "name:fas_x_preferred":[
        "\u062a\u0648\u062a\u06a9"
    ],
    "name:fas_x_variant":[
        "T\u016btak"
    ],
    "name:urd_x_preferred":[
        "\u062a\u0648\u062a\u06a9"
    ],
    "wof:name":"Tutak",
    "wof:placetype":"locality"
},
  "geometry": {"coordinates":[51.6179,35.5733],"type":"Point"}
}