{
  "type": "Feature",
  "properties": {
    "gn:admin1_code":"8.0",
    "gn:asciiname":"Khosrow Kalayeh",
    "gn:country_code":"IR",
    "gn:dem":1450,
    "gn:feature_class":"P",
    "gn:feature_code":"PPL",
    "gn:name":"Khosrow Kal\u0101yeh",
    "gn:population":0,
    "gn:timezone":"Asia/Tehran",
    "iso:country":"IR",
    "name:fas_x_preferred":[
        "Khorsand Kal\u0101yeh"
    ],
    "name:fas_x_variant":[
        "\u062e\u0631\u0633\u0646\u062f \u06a9\u0644\u0627\u06cc\u0647",
        "\u062e\u0633\u0631\u0648 \u06a9\u0644\u0627\u06cc\u0647",
        "\u062e\u0648\u0631\u0633\u0646\u062f \u06a9\u0644\u0627\u06cc\u0647"
    ],
    "name:und_x_variant":[
        "\u062e\u0631\u0633\u0646\u062f \u06a9\u0644\u0627\u06cc\u0647",
        "Khosrow Kal\u0101yeh",
        "Khowrsand Kal\u0101yeh"
    ],
    "wof:name":"Khosrow Kalayeh",
    "wof:placetype":"locality"
},
  "geometry": {"coordinates":[50.22044,36.82485],"type":"Point"}
}