{
  "type": "Feature",
  "properties": {
    "gn:admin1_code":"23",
    "gn:asciiname":"Chaghalvandi",
    "gn:country_code":"IR",
    "gn:dem":1659,
    "gn:feature_class":"P",
    "gn:feature_code":"PPL",
    "gn:name":"Chaghalvand\u012b",
    "gn:population":0,
    "gn:timezone":"Asia/Tehran",
    "iso:country":"IR",
    "name:fas_x_preferred":[
        "\u0686\u063a\u0644\u0648\u0646\u062f\u06cc"
    ],
    "name:fas_x_variant":[
        "Chaghalvand\u012b"
    ],
    "name:und_x_variant":[
        "Chaqharvand",
        "Chagharvand",
        "Chaqalvand\u012b",
        "Chaqalwandi"
    ],
    "wof:name":"Chaghalvandi",
    "wof:placetype":"locality"
},
  "geometry": {"coordinates":[48.55974000000001,33.64755],"type":"Point"}
}