{
  "type": "Feature",
  "properties": {
    "gn:admin1_code":"37",
    "gn:asciiname":"Kangar",
    "gn:country_code":"IR",
    "gn:dem":100,
    "gn:feature_class":"P",
    "gn:feature_code":"PPL",
    "gn:name":"Kangar",
    "gn:population":0,
    "gn:timezone":"Asia/Tehran",
    "iso:country":"IR",
    "wof:name":"Kangar",
    "wof:placetype":"locality"
},
  "geometry": {"coordinates":[55.43333000000001,37.38333],"type":"Point"}
}