{
  "type": "Feature",
  "properties": {
    "gn:admin1_code":"37",
    "gn:asciiname":"Kangar",
    "gn:country_code":"IR",
    "gn:dem":100,
    "gn:feature_class":"P",
    "gn:feature_code":"PPL",
    "gn:name":"Kangar",
    "gn:population":0,
    "gn:timezone":"Asia/Tehran",
    "iso:country":"IR",
    "name:ara_x_preferred":[
        "\u0643\u0627\u0646\u062c\u0627\u0631"
    ],
    "name:bjn_x_preferred":[
        "Kangar"
    ],
    "name:bul_x_preferred":[
        "\u041a\u0430\u043d\u0433\u0430\u0440"
    ],
    "name:ceb_x_preferred":[
        "Kangar"
    ],
    "name:deu_x_preferred":[
        "Kangar"
    ],
    "name:epo_x_preferred":[
        "Kangar"
    ],
    "name:fas_x_preferred":[
        "\u06a9\u0646\u06af\u0631"
    ],
    "name:fin_x_preferred":[
        "Kangar"
    ],
    "name:fra_x_preferred":[
        "Kangar"
    ],
    "name:hin_x_preferred":[
        "\u0915\u0902\u0917\u093e\u0930"
    ],
    "name:ind_x_preferred":[
        "Kangar"
    ],
    "name:ita_x_preferred":[
        "Kangar"
    ],
    "name:jpn_x_preferred":[
        "\u30ab\u30f3\u30ac\u30fc"
    ],
    "name:kor_x_preferred":[
        "\uce89\uc544\ub974"
    ],
    "name:mkd_x_preferred":[
        "\u041a\u0430\u043d\u0433\u0430\u0440"
    ],
    "name:msa_x_preferred":[
        "Kangar"
    ],
    "name:nld_x_preferred":[
        "Kangar"
    ],
    "name:nor_x_preferred":[
        "Kangar"
    ],
    "name:pol_x_preferred":[
        "Kangar"
    ],
    "name:por_x_preferred":[
        "Kangar"
    ],
    "name:rus_x_preferred":[
        "\u041a\u0430\u043d\u0433\u0430\u0440"
    ],
    "name:spa_x_preferred":[
        "Kangar"
    ],
    "name:swe_x_preferred":[
        "Kangar"
    ],
    "name:tam_x_preferred":[
        "\u0b95\u0b99\u0bcd\u0b95\u0bbe\u0bb0\u0bcd"
    ],
    "name:tur_x_preferred":[
        "Kangar"
    ],
    "name:ukr_x_preferred":[
        "\u041a\u0430\u043d\u0433\u0430\u0440"
    ],
    "name:urd_x_preferred":[
        "\u06a9\u0627\u0646\u06af\u0631"
    ],
    "name:vie_x_preferred":[
        "Kangar"
    ],
    "name:war_x_preferred":[
        "Kangar"
    ],
    "name:zho_x_preferred":[
        "\u52a0\u592e"
    ],
    "wof:name":"Kangar",
    "wof:placetype":"locality"
},
  "geometry": {"coordinates":[55.43333000000001,37.38333],"type":"Point"}
}