{
  "type": "Feature",
  "properties": {
    "gn:admin1_code":"4",
    "gn:asciiname":"Do Dar",
    "gn:country_code":"IR",
    "gn:dem":13,
    "gn:feature_class":"P",
    "gn:feature_code":"PPL",
    "gn:name":"Do Dar",
    "gn:population":0,
    "gn:timezone":"Asia/Tehran",
    "iso:country":"IR",
    "name:fas_x_preferred":[
        "\u062f\u0648 \u062f\u0631"
    ],
    "name:und_x_variant":[
        "\u062f\u0648 \u062f\u0631"
    ],
    "wof:name":"Do Dar",
    "wof:placetype":"locality"
},
  "geometry": {"coordinates":[59.32924000000001,25.63931],"type":"Point"}
}