{
  "type": "Feature",
  "properties": {
    "gn:admin1_code":"7",
    "gn:asciiname":"Mobarakeh",
    "gn:country_code":"IR",
    "gn:dem":1645,
    "gn:feature_class":"P",
    "gn:feature_code":"PPL",
    "gn:name":"Mob\u0101rakeh",
    "gn:population":0,
    "gn:timezone":"Asia/Tehran",
    "iso:country":"IR",
    "name:fas_x_preferred":[
        "\u0645\u0628\u0627\u0631\u06a9\u0647"
    ],
    "name:fas_x_variant":[
        "Mob\u0101rakeh"
    ],
    "name:msa_x_preferred":[
        "Mobarakeh"
    ],
    "name:und_x_variant":[
        "Mub\u0101raksh\u0101h",
        "Mob\u0101rak Sh\u0101h"
    ],
    "wof:name":"Mobarakeh",
    "wof:placetype":"locality"
},
  "geometry": {"coordinates":[52.3807,29.9827],"type":"Point"}
}