{
  "type": "Feature",
  "properties": {
    "gn:admin1_code":"4.0",
    "gn:asciiname":"Hajj `Osman Bazar",
    "gn:country_code":"IR",
    "gn:dem":25,
    "gn:feature_class":"P",
    "gn:feature_code":"PPL",
    "gn:name":"\u1e28\u0101jj \u2018Os\u0304m\u0101n B\u0101z\u0101r",
    "gn:population":0,
    "gn:timezone":"Asia/Tehran",
    "iso:country":"IR",
    "name:fas_x_preferred":[
        "\u1e28\u0101jj \u2018Os\u0304m\u0101n B\u0101z\u0101r"
    ],
    "name:fas_x_variant":[
        "\u062d\u0627\u062c \u0639\u062b\u0645\u0627\u0646 \u0628\u0627\u0632\u0627\u0631"
    ],
    "wof:name":"Hajj `Osman Bazar",
    "wof:placetype":"locality"
},
  "geometry": {"coordinates":[61.2141,25.58286],"type":"Point"}
}