{
  "type": "Feature",
  "properties": {
    "gn:admin1_code":"42.0",
    "gn:asciiname":"Mazra`eh-ye Fakhrabad",
    "gn:country_code":"IR",
    "gn:dem":1322,
    "gn:feature_class":"P",
    "gn:feature_code":"PPLF",
    "gn:name":"Mazra\u2018eh-ye Fakhr\u0101b\u0101d",
    "gn:population":0,
    "gn:timezone":"Asia/Tehran",
    "iso:country":"IR",
    "name:fas_x_preferred":[
        "\u0645\u0632\u0631\u0639\u0647 \u0641\u062e\u0631 \u0622\u0628\u0627\u062f"
    ],
    "name:und_x_variant":[
        "Mazra\u2018eh-ye Fakhr\u0101b\u0101d"
    ],
    "wof:name":"Mazra`eh-ye Fakhrabad",
    "wof:placetype":"locality"
},
  "geometry": {"coordinates":[56.93899,36.4265],"type":"Point"}
}