{
  "type": "Feature",
  "properties": {
    "gn:admin1_code":"7",
    "gn:asciiname":"Benow",
    "gn:country_code":"IR",
    "gn:dem":643,
    "gn:feature_class":"P",
    "gn:feature_code":"PPLF",
    "gn:name":"Benow",
    "gn:population":0,
    "gn:timezone":"Asia/Tehran",
    "iso:country":"IR",
    "name:fas_x_preferred":[
        "\u0628\u0646\u0648"
    ],
    "name:und_x_variant":[
        "Kon\u0101rd\u0101n",
        "Ban\u016b",
        "Banoo",
        "Benow"
    ],
    "wof:name":"Benow",
    "wof:placetype":"locality"
},
  "geometry": {"coordinates":[53.9716,27.4979],"type":"Point"}
}