{
  "type": "Feature",
  "properties": {
    "gn:admin1_code":"8.0",
    "gn:asciiname":"Khatin Gorab",
    "gn:country_code":"IR",
    "gn:dem":13,
    "gn:feature_class":"P",
    "gn:feature_code":"PPL",
    "gn:name":"Kha\u0163\u012bn Gor\u0101b",
    "gn:population":0,
    "gn:timezone":"Asia/Tehran",
    "iso:country":"IR",
    "name:fas_x_preferred":[
        "\u062e\u0637\u06cc\u0628 \u06af\u0648\u0631\u0627\u0628"
    ],
    "name:fas_x_variant":[
        "Kha\u0163\u012bb G\u016br\u0101b",
        "\u062e\u0637\u06cc\u0646 \u06af\u0631\u0627\u0628",
        "\u062d\u0644\u0642\u0647 \u0633\u0628\u0632"
    ],
    "name:und_x_variant":[
        "Kha\u0163\u012bn Gor\u0101b",
        "\u1e28alqeh Sabz"
    ],
    "wof:name":"Khatin Gorab",
    "wof:placetype":"locality"
},
  "geometry": {"coordinates":[49.3557,37.24817],"type":"Point"}
}