{
  "type": "Feature",
  "properties": {
    "gn:admin1_code":"4.0",
    "gn:asciiname":"Deh-e `Isa Faqir",
    "gn:country_code":"IR",
    "gn:dem":488,
    "gn:feature_class":"P",
    "gn:feature_code":"PPL",
    "gn:name":"Deh-e \u2018\u012as\u00e1 Faq\u012br",
    "gn:population":0,
    "gn:timezone":"Asia/Tehran",
    "iso:country":"IR",
    "name:fas_x_preferred":[
        "\u062f\u0647 \u0639\u06cc\u0633\u06cc \u0641\u0642\u06cc\u0631"
    ],
    "name:fas_x_variant":[
        "\u2018\u012as\u00e1 Faq\u012br",
        "Deh-e \u2018\u012as\u00e1 Faq\u012br",
        "\u0639\u06cc\u0633\u06cc \u0641\u0642\u06cc\u0631"
    ],
    "wof:name":"Deh-e `Isa Faqir",
    "wof:placetype":"locality"
},
  "geometry": {"coordinates":[61.6406,30.9101],"type":"Point"}
}