{
  "type": "Feature",
  "properties": {
    "gn:admin1_code":"32",
    "gn:asciiname":"Qeshlaq-e Esma`il",
    "gn:country_code":"IR",
    "gn:dem":314,
    "gn:feature_class":"P",
    "gn:feature_code":"PPL",
    "gn:name":"Qeshl\u0101q-e Esm\u0101\u2018\u012bl",
    "gn:population":0,
    "gn:timezone":"Asia/Tehran",
    "iso:country":"IR",
    "name:fas_x_preferred":[
        "\u0642\u0634\u0644\u0627\u0642 \u0627\u0633\u0645\u0627\u0639\u06cc\u0644"
    ],
    "name:fas_x_variant":[
        "Qeshl\u0101q-e Esm\u0101\u2018\u012bl"
    ],
    "wof:name":"Qeshlaq-e Esma`il",
    "wof:placetype":"locality"
},
  "geometry": {"coordinates":[47.7321,39.3703],"type":"Point"}
}