{
  "type": "Feature",
  "properties": {
    "gn:admin1_code":"43",
    "gn:asciiname":"Pishandeh",
    "gn:country_code":"IR",
    "gn:dem":1239,
    "gn:feature_class":"P",
    "gn:feature_code":"PPL",
    "gn:name":"P\u012bshandeh",
    "gn:population":0,
    "gn:timezone":"Asia/Tehran",
    "iso:country":"IR",
    "name:ara_x_preferred":[
        "\u0628\u0634\u064a\u0646 \u062f\u0647"
    ],
    "name:fas_x_preferred":[
        "P\u012bshandeh"
    ],
    "name:fas_x_variant":[
        "\u067e\u06cc\u0634\u0646\u062f\u0647",
        "\u067e\u0634\u06cc\u0646 \u062f\u0647"
    ],
    "name:und_x_variant":[
        "Poshvandeh",
        "Pashvandeh",
        "Pash\u012bndeh",
        "Pashandeh"
    ],
    "wof:name":"Pishandeh",
    "wof:placetype":"locality"
},
  "geometry": {"coordinates":[57.06971,37.89444],"type":"Point"}
}