{
  "type": "Feature",
  "properties": {
    "gn:admin1_code":"29",
    "gn:asciiname":"Terezj",
    "gn:country_code":"IR",
    "gn:dem":1963,
    "gn:feature_class":"P",
    "gn:feature_code":"PPL",
    "gn:name":"Terezj",
    "gn:population":0,
    "gn:timezone":"Asia/Tehran",
    "iso:country":"IR",
    "name:fas_x_preferred":[
        "\u062a\u0631\u0632\u062c"
    ],
    "name:fas_x_variant":[
        "\u062a\u0632\u0631\u062c"
    ],
    "name:und_x_variant":[
        "\u0162ezerj",
        "T\u012bzrak",
        "Tezerj",
        "Terezj"
    ],
    "wof:name":"Terezj",
    "wof:placetype":"locality"
},
  "geometry": {"coordinates":[55.12833000000001,30.58056],"type":"Point"}
}