{
  "type": "Feature",
  "properties": {
    "gn:admin1_code":"22",
    "gn:asciiname":"Rusta-ye Salemabad",
    "gn:country_code":"IR",
    "gn:dem":8,
    "gn:feature_class":"P",
    "gn:feature_code":"PPL",
    "gn:name":"R\u016bst\u0101-ye S\u0101lem\u0101b\u0101d",
    "gn:population":0,
    "gn:timezone":"Asia/Tehran",
    "iso:country":"IR",
    "name:ceb_x_preferred":[
        "R\u016bst\u0101-ye S\u0101lem\u0101b\u0101d"
    ],
    "name:fas_x_preferred":[
        "\u0633\u0627\u0644\u0645 \u0622\u0628\u0627\u062f"
    ],
    "name:fas_x_variant":[
        "\u0633\u0627\u0644\u0650\u0645 \u0622\u0628\u0627\u062f\u0650\u0647",
        "\u0633\u064e\u0644\u064a\u0645 \u0622\u0628\u0627\u062f",
        "S\u0101lem\u0101b\u0101d",
        "\u0631\u0648\u0633\u062a\u0627\u06cc \u0633\u0627\u0644\u0645 \u0622\u0628\u0627\u062f",
        "\u0633\u0627\u0644\u0645\u200c\u0622\u0628\u0627\u062f"
    ],
    "name:msa_x_preferred":[
        "Salemabad"
    ],
    "name:swe_x_preferred":[
        "R\u016bst\u0101-ye S\u0101lem\u0101b\u0101d"
    ],
    "name:und_x_variant":[
        "Sal\u012bm \u0100b\u0101d",
        "S\u0101lem \u0100b\u0101deh",
        "Salim Abadeh",
        "R\u016bst\u0101-ye S\u0101lem\u0101b\u0101d"
    ],
    "wof:name":"Rusta-ye Salemabad",
    "wof:placetype":"locality"
},
  "geometry": {"coordinates":[51.12843,28.44322],"type":"Point"}
}