{
  "type": "Feature",
  "properties": {
    "gn:admin1_code":"37.0",
    "gn:asciiname":"Reza'i",
    "gn:country_code":"IR",
    "gn:dem":117,
    "gn:feature_class":"P",
    "gn:feature_code":"PPL",
    "gn:name":"Re\u1e95\u0101\u2019\u012b",
    "gn:population":0,
    "gn:timezone":"Asia/Tehran",
    "iso:country":"IR",
    "name:fas_x_preferred":[
        "\u0631\u0636\u0627\u06cc\u06cc"
    ],
    "name:fas_x_variant":[
        "\u0645\u0632\u0631\u0639\u0647 \u062d\u0627\u062c\u06cc \u0631\u0636\u0627\u06cc\u06cc"
    ],
    "name:und_x_variant":[
        "Re\u1e95\u0101\u2019\u012b",
        "Mazra\u2018eh-ye \u1e28\u0101jj\u012b-ye Re\u1e95\u0101\u2019\u012b"
    ],
    "wof:name":"Reza'i",
    "wof:placetype":"locality"
},
  "geometry": {"coordinates":[55.43623,37.34929],"type":"Point"}
}