{
  "type": "Feature",
  "properties": {
    "gn:admin1_code":"42",
    "gn:asciiname":"Pabaz",
    "gn:country_code":"IR",
    "gn:dem":1111,
    "gn:feature_class":"P",
    "gn:feature_code":"PPL",
    "gn:name":"P\u0101b\u0101z",
    "gn:population":0,
    "gn:timezone":"Asia/Tehran",
    "iso:country":"IR",
    "name:ceb_x_preferred":[
        "P\u0101 B\u0101z"
    ],
    "name:fas_x_preferred":[
        "\u067e\u0627\u0628\u0627\u0632"
    ],
    "name:fas_x_variant":[
        "P\u0101 yi B\u0101z",
        "P\u0101 B\u0101r"
    ],
    "name:swe_x_preferred":[
        "P\u0101 B\u0101z"
    ],
    "name:und_x_variant":[
        "P\u0101b\u0101z"
    ],
    "wof:name":"Pabaz",
    "wof:placetype":"locality"
},
  "geometry": {"coordinates":[58.32901,35.98842],"type":"Point"}
}