{
  "type": "Feature",
  "properties": {
    "gn:admin1_code":"37.0",
    "gn:asciiname":"Kotuk",
    "gn:country_code":"IR",
    "gn:dem":1417,
    "gn:feature_class":"P",
    "gn:feature_code":"PPL",
    "gn:name":"Kot\u016bk",
    "gn:population":0,
    "gn:timezone":"Asia/Tehran",
    "iso:country":"IR",
    "name:fas_x_preferred":[
        "Kot\u016bk"
    ],
    "name:und_x_variant":[
        "Kat\u016bk"
    ],
    "wof:name":"Kotuk",
    "wof:placetype":"locality"
},
  "geometry": {"coordinates":[55.24889,37.0225],"type":"Point"}
}