{
  "type": "Feature",
  "properties": {
    "gn:admin1_code":"28.0",
    "gn:asciiname":"Arjang",
    "gn:country_code":"IR",
    "gn:dem":2265,
    "gn:feature_class":"P",
    "gn:feature_code":"PPL",
    "gn:name":"Arjang",
    "gn:population":0,
    "gn:timezone":"Asia/Tehran",
    "iso:country":"IR",
    "name:fas_x_preferred":[
        "\u0627\u0631\u062c\u0646\u06af"
    ],
    "name:fas_x_variant":[
        "\u0627\u0631\u062c\u0646\u06a9"
    ],
    "name:und_x_variant":[
        "Arjanak"
    ],
    "wof:name":"Arjang",
    "wof:placetype":"locality"
},
  "geometry": {"coordinates":[50.17403,33.32789],"type":"Point"}
}