{
  "type": "Feature",
  "properties": {
    "gn:admin1_code":"11",
    "gn:asciiname":"Marong",
    "gn:country_code":"IR",
    "gn:dem":357,
    "gn:feature_class":"P",
    "gn:feature_code":"PPL",
    "gn:name":"Marong",
    "gn:population":0,
    "gn:timezone":"Asia/Tehran",
    "iso:country":"IR",
    "name:fas_x_preferred":[
        "\u0645\u0631\u0646\u06af"
    ],
    "wof:name":"Marong",
    "wof:placetype":"locality"
},
  "geometry": {"coordinates":[57.967,26.2256],"type":"Point"}
}