{
  "type": "Feature",
  "properties": {
    "gn:admin1_code":"13",
    "gn:asciiname":"Masgareh",
    "gn:country_code":"IR",
    "gn:dem":1273,
    "gn:feature_class":"P",
    "gn:feature_code":"PPL",
    "gn:name":"Masgareh",
    "gn:population":0,
    "gn:timezone":"Asia/Tehran",
    "iso:country":"IR",
    "name:fas_x_preferred":[
        "\u0645\u0633\u06af\u0631\u0647"
    ],
    "name:fra_x_preferred":[
        "Masgareh"
    ],
    "name:und_x_variant":[
        "Qal\u2018eh Mashkara",
        "Masgareh"
    ],
    "wof:name":"Masgareh",
    "wof:placetype":"locality"
},
  "geometry": {"coordinates":[47.1708,33.9471],"type":"Point"}
}