{
  "type": "Feature",
  "properties": {
    "gn:admin1_code":"33",
    "gn:asciiname":"Ushdelaq",
    "gn:country_code":"IR",
    "gn:dem":1363,
    "gn:feature_class":"P",
    "gn:feature_code":"PPL",
    "gn:name":"\u016ashdelaq",
    "gn:population":0,
    "gn:timezone":"Asia/Tehran",
    "iso:country":"IR",
    "name:ara_x_preferred":[
        "\u0623\u0634\u062f\u0644\u0642"
    ],
    "name:azb_x_preferred":[
        "\u0627\u0634\u062f\u0644\u0642"
    ],
    "name:fas_x_preferred":[
        "\u0627\u0648\u0634\u062f\u0644\u0642"
    ],
    "name:fas_x_variant":[
        "\u016ashdelaq",
        "\u0627\u0634\u062f\u0644\u0642"
    ],
    "name:msa_x_preferred":[
        "Oshdalaq"
    ],
    "name:und_x_variant":[
        "Uchky \u2018Uliya",
        "Uzhkyulya",
        "Ushtula",
        "Oshdelag"
    ],
    "wof:name":"Ushdelaq",
    "wof:placetype":"locality"
},
  "geometry": {"coordinates":[46.982,38.4542],"type":"Point"}
}