{
  "type": "Feature",
  "properties": {
    "gn:admin1_code":"33.0",
    "gn:asciiname":"Alanaq",
    "gn:country_code":"IR",
    "gn:dem":1813,
    "gn:feature_class":"P",
    "gn:feature_code":"PPL",
    "gn:name":"\u0100l\u0101naq",
    "gn:population":0,
    "gn:timezone":"Asia/Tehran",
    "iso:country":"IR",
    "name:ara_x_preferred":[
        "\u0623\u0644\u0627\u0646\u0642"
    ],
    "name:azb_x_preferred":[
        "\u0622\u0644\u0627\u0646\u0642"
    ],
    "name:fas_x_preferred":[
        "\u0622\u0644\u0627\u0646\u0642"
    ],
    "name:fas_x_variant":[
        "Al\u0101naq",
        "\u0100l\u0101naq"
    ],
    "name:msa_x_preferred":[
        "Alanaq"
    ],
    "name:tur_x_preferred":[
        "Alanak"
    ],
    "name:und_x_variant":[
        "Alana"
    ],
    "wof:name":"Alanaq",
    "wof:placetype":"locality"
},
  "geometry": {"coordinates":[46.715,38.0109],"type":"Point"}
}