{
  "type": "Feature",
  "properties": {
    "gn:admin1_code":"9",
    "gn:asciiname":"Chalboqa",
    "gn:country_code":"IR",
    "gn:dem":1946,
    "gn:feature_class":"P",
    "gn:feature_code":"PPL",
    "gn:name":"Ch\u0101lboq\u0101",
    "gn:population":0,
    "gn:timezone":"Asia/Tehran",
    "iso:country":"IR",
    "name:ceb_x_preferred":[
        "Ch\u0101l Boq\u0101"
    ],
    "name:fas_x_preferred":[
        "\u0686\u0627\u0644\u0628\u0642\u0627"
    ],
    "name:fas_x_variant":[
        "\u0686\u0627\u0644 \u0628\u0642\u0627",
        "Sh\u0101lbaq\u0101",
        "Ch\u0101l Boq\u0101"
    ],
    "name:msa_x_preferred":[
        "Chal Boqa"
    ],
    "name:swe_x_preferred":[
        "Ch\u0101l Boq\u0101"
    ],
    "name:und_x_variant":[
        "Ch\u0101l Bogh\u0101\u2019",
        "Ch\u0101b\u016bgha",
        "Ch\u0101lb\u016bgha",
        "Ch\u0101lboq\u0101"
    ],
    "wof:name":"Chalboqa",
    "wof:placetype":"locality"
},
  "geometry": {"coordinates":[48.92747,35.42019000000001],"type":"Point"}
}