{
  "type": "Feature",
  "properties": {
    "gn:admin1_code":"0",
    "gn:asciiname":"Rig Sohrabi",
    "gn:country_code":"IR",
    "gn:dem":371,
    "gn:feature_class":"P",
    "gn:feature_code":"PPL",
    "gn:name":"R\u012bg Sohr\u0101b\u012b",
    "gn:population":0,
    "gn:timezone":"Asia/Tehran",
    "iso:country":"IR",
    "name:fas_x_preferred":[
        "\u0631\u06cc\u06af \u0633\u0647\u0631\u0627\u0628\u06cc"
    ],
    "name:fas_x_variant":[
        "R\u012bg Sohr\u0101b\u012b"
    ],
    "wof:name":"Rig Sohrabi",
    "wof:placetype":"locality"
},
  "geometry": {"coordinates":[57.6251,27.4623],"type":"Point"}
}