{
  "type": "Feature",
  "properties": {
    "gn:admin1_code":"29",
    "gn:asciiname":"Shast Pich-e Sofla",
    "gn:country_code":"IR",
    "gn:dem":2151,
    "gn:feature_class":"P",
    "gn:feature_code":"PPL",
    "gn:name":"Sha\u015ft P\u012bch-e Sofl\u00e1",
    "gn:population":0,
    "gn:timezone":"Asia/Tehran",
    "iso:country":"IR",
    "name:fas_x_preferred":[
        "\u0634\u0635\u062a \u067e\u06cc\u0686 \u0633\u0641\u0644\u06cc"
    ],
    "name:fas_x_variant":[
        "Sha\u015ft P\u012bch-e Sofl\u00e1"
    ],
    "wof:name":"Shast Pich-e Sofla",
    "wof:placetype":"locality"
},
  "geometry": {"coordinates":[56.853,29.1645],"type":"Point"}
}