{
  "type": "Feature",
  "properties": {
    "gn:admin1_code":"15",
    "gn:asciiname":"Beyt-e `Obeyd",
    "gn:country_code":"IR",
    "gn:dem":6,
    "gn:feature_class":"P",
    "gn:feature_code":"PPL",
    "gn:name":"Beyt-e \u2018Obeyd",
    "gn:population":0,
    "gn:timezone":"Asia/Tehran",
    "iso:country":"IR",
    "name:fas_x_preferred":[
        "Beyt-e \u2018Obeyd"
    ],
    "wof:name":"Beyt-e `Obeyd",
    "wof:placetype":"locality"
},
  "geometry": {"coordinates":[48.63333,30.68333],"type":"Point"}
}