{
  "type": "Feature",
  "properties": {
    "gn:admin1_code":"1",
    "gn:asciiname":"Mateh Kharpeh",
    "gn:country_code":"IR",
    "gn:dem":1838,
    "gn:feature_class":"P",
    "gn:feature_code":"PPL",
    "gn:name":"M\u0101teh Kharpeh",
    "gn:population":0,
    "gn:timezone":"Asia/Tehran",
    "iso:country":"IR",
    "name:fas_x_preferred":[
        "M\u0101teh Kharpeh"
    ],
    "name:fas_x_variant":[
        "M\u0101teh Kharbeh",
        "\u0645\u0627\u062a\u0647 \u062e\u0631\u067e\u0647"
    ],
    "name:und_x_variant":[
        "\u0645\u0627\u062a\u0647 \u062e\u0631\u067e\u0647"
    ],
    "wof:name":"Mateh Kharpeh",
    "wof:placetype":"locality"
},
  "geometry": {"coordinates":[44.5583,38.1235],"type":"Point"}
}