{
  "type": "Feature",
  "properties": {
    "gn:admin1_code":"8.0",
    "gn:asciiname":"Aghuz Chaleh",
    "gn:country_code":"IR",
    "gn:dem":715,
    "gn:feature_class":"P",
    "gn:feature_code":"PPL",
    "gn:name":"\u0100gh\u016bz Ch\u0101leh",
    "gn:population":0,
    "gn:timezone":"Asia/Tehran",
    "iso:country":"IR",
    "name:fas_x_preferred":[
        "\u0100gh\u016bz Ch\u0101leh"
    ],
    "name:fas_x_variant":[
        "\u0622\u063a\u0648\u0632 \u0686\u0627\u0644\u0647"
    ],
    "wof:name":"Aghuz Chaleh",
    "wof:placetype":"locality"
},
  "geometry": {"coordinates":[49.56813,36.81478],"type":"Point"}
}