{
  "type": "Feature",
  "properties": {
    "gn:admin1_code":"1",
    "gn:asciiname":"Hajji Ahmad Kandi",
    "gn:country_code":"IR",
    "gn:dem":1007,
    "gn:feature_class":"P",
    "gn:feature_code":"PPL",
    "gn:name":"\u1e28\u0101jj\u012b A\u1e29mad Kand\u012b",
    "gn:population":0,
    "gn:timezone":"Asia/Tehran",
    "iso:country":"IR",
    "name:ara_x_preferred":[
        "\u062d\u0627\u062c\u064a\u0627\u062d\u0645\u062f\u0643\u0646\u062f\u064a"
    ],
    "name:aze_x_preferred":[
        "Hac\u0131 \u018fhm\u0259d k\u0259ndi"
    ],
    "name:ceb_x_preferred":[
        "\u1e28\u0101jj\u012b A\u1e29mad Kand\u012b"
    ],
    "name:fas_x_preferred":[
        "\u062d\u0627\u062c\u06cc \u0627\u062d\u0645\u062f \u06a9\u0646\u062f\u06cc"
    ],
    "name:fas_x_variant":[
        "\u1e28\u0101jj\u012b A\u1e29mad Kand\u012b",
        "\u062d\u0627\u062c\u06cc\u200c\u0627\u062d\u0645\u062f\u06a9\u0646\u062f\u06cc"
    ],
    "name:msa_x_preferred":[
        "Hajji Ahmad Kandi"
    ],
    "name:swe_x_preferred":[
        "\u1e28\u0101jj\u012b A\u1e29mad Kand\u012b"
    ],
    "name:und_x_variant":[
        "\u1e28\u0101j\u012b A\u1e29mad Kand\u012b"
    ],
    "wof:name":"Hajji Ahmad Kandi",
    "wof:placetype":"locality"
},
  "geometry": {"coordinates":[45.1493,38.8601],"type":"Point"}
}