{
  "type": "Feature",
  "properties": {
    "gn:admin1_code":"8",
    "gn:asciiname":"Zanburchal",
    "gn:country_code":"IR",
    "gn:dem":583,
    "gn:feature_class":"P",
    "gn:feature_code":"PPL",
    "gn:name":"Zanb\u016brch\u0101l",
    "gn:population":0,
    "gn:timezone":"Asia/Tehran",
    "iso:country":"IR",
    "name:fas_x_preferred":[
        "Zanb\u016brch\u0101l"
    ],
    "wof:name":"Zanburchal",
    "wof:placetype":"locality"
},
  "geometry": {"coordinates":[48.72972,37.81861],"type":"Point"}
}