{
  "type": "Feature",
  "properties": {
    "gn:admin1_code":"7",
    "gn:asciiname":"Burenjan",
    "gn:country_code":"IR",
    "gn:dem":1726,
    "gn:feature_class":"P",
    "gn:feature_code":"PPL",
    "gn:name":"B\u016brenj\u0101n",
    "gn:population":0,
    "gn:timezone":"Asia/Tehran",
    "iso:country":"IR",
    "name:fas_x_preferred":[
        "B\u016brenj\u0101n"
    ],
    "name:fas_x_variant":[
        "\u0628\u0648\u0631\u0646\u062c\u0627\u0646"
    ],
    "name:und_x_variant":[
        "Burinjun",
        "\u0628\u0648\u0631\u0646\u062c\u0627\u0646"
    ],
    "wof:name":"Burenjan",
    "wof:placetype":"locality"
},
  "geometry": {"coordinates":[51.9787,29.48888],"type":"Point"}
}