{
  "type": "Feature",
  "properties": {
    "gn:admin1_code":"35.0",
    "gn:asciiname":"Kari Kesh",
    "gn:country_code":"IR",
    "gn:dem":265,
    "gn:feature_class":"P",
    "gn:feature_code":"PPL",
    "gn:name":"Kar\u012b Kesh",
    "gn:population":0,
    "gn:timezone":"Asia/Tehran",
    "iso:country":"IR",
    "name:ceb_x_preferred":[
        "Kar\u012b Kesh"
    ],
    "name:fas_x_preferred":[
        "P\u012b\u0101z Kesh"
    ],
    "name:fas_x_variant":[
        "\u067e\u06cc\u0627\u0632 \u06a9\u0634",
        "\u06a9\u0631\u06cc \u06a9\u0634",
        "\u067e\u06cc\u0627\u0632\u06a9\u0634"
    ],
    "name:swe_x_preferred":[
        "Kar\u012b Kesh"
    ],
    "name:und_x_variant":[
        "\u067e\u06cc\u0627\u0632 \u06a9\u0634",
        "Kar\u012b Kesh"
    ],
    "wof:name":"Kari Kesh",
    "wof:placetype":"locality"
},
  "geometry": {"coordinates":[50.70002,36.81801],"type":"Point"}
}