{
  "type": "Feature",
  "properties": {
    "gn:admin1_code":"37",
    "gn:asciiname":"Duji Owdak",
    "gn:country_code":"IR",
    "gn:dem":49,
    "gn:feature_class":"P",
    "gn:feature_code":"PPL",
    "gn:name":"D\u016bj\u012b Owdak",
    "gn:population":0,
    "gn:timezone":"Asia/Tehran",
    "iso:country":"IR",
    "name:fas_x_preferred":[
        "D\u016bj\u012b Owdak"
    ],
    "name:fas_x_variant":[
        "\u062f\u0648\u062c\u06cc \u0627\u0648\u062f\u06a9"
    ],
    "wof:name":"Duji Owdak",
    "wof:placetype":"locality"
},
  "geometry": {"coordinates":[54.77486999999999,37.00576],"type":"Point"}
}