{
  "type": "Feature",
  "properties": {
    "gn:admin1_code":"35",
    "gn:asciiname":"Pa'in Marzbal",
    "gn:country_code":"IR",
    "gn:dem":44,
    "gn:feature_class":"P",
    "gn:feature_code":"PPL",
    "gn:name":"P\u0101\u2019\u012bn Marzb\u0101l",
    "gn:population":0,
    "gn:timezone":"Asia/Tehran",
    "iso:country":"IR",
    "name:fas_x_preferred":[
        "\u067e\u0627\u0626\u064a\u0646 \u0645\u0631\u0632\u0628\u0627\u0644"
    ],
    "name:fas_x_variant":[
        "P\u0101\u2019\u012bn Marzb\u0101l"
    ],
    "name:und_x_variant":[
        "\u067e\u0627\u0626\u064a\u0646 \u0645\u064e\u0631\u0632\u0628\u0627\u0644"
    ],
    "wof:name":"Pa'in Marzbal",
    "wof:placetype":"locality"
},
  "geometry": {"coordinates":[52.65118,36.41276],"type":"Point"}
}