{
  "type": "Feature",
  "properties": {
    "gn:admin1_code":"4.0",
    "gn:asciiname":"Mirch",
    "gn:country_code":"IR",
    "gn:dem":816,
    "gn:feature_class":"P",
    "gn:feature_code":"PPL",
    "gn:name":"M\u012brch",
    "gn:population":0,
    "gn:timezone":"Asia/Tehran",
    "iso:country":"IR",
    "name:fas_x_preferred":[
        "M\u012brch"
    ],
    "name:hin_x_preferred":[
        "\u092e\u093f\u0930\u094d\u091a"
    ],
    "wof:name":"Mirch",
    "wof:placetype":"locality"
},
  "geometry": {"coordinates":[60.72556,26.46972],"type":"Point"}
}