{
  "type": "Feature",
  "properties": {
    "gn:admin1_code":"34",
    "gn:asciiname":"Varkbar",
    "gn:country_code":"IR",
    "gn:dem":2100,
    "gn:feature_class":"P",
    "gn:feature_code":"PPL",
    "gn:name":"Varkb\u0101r",
    "gn:population":0,
    "gn:timezone":"Asia/Tehran",
    "iso:country":"IR",
    "name:fas_x_preferred":[
        "\u0648\u0631\u0643\u0628\u0627\u0631"
    ],
    "name:fas_x_variant":[
        "Varkb\u0101r-e \u2018Oly\u0101",
        "Varkb\u0101r"
    ],
    "name:und_x_variant":[
        "Warkb\u0101r"
    ],
    "wof:name":"Varkbar",
    "wof:placetype":"locality"
},
  "geometry": {"coordinates":[49.5748,35.31874000000001],"type":"Point"}
}