{
  "type": "Feature",
  "properties": {
    "gn:admin1_code":"7.0",
    "gn:asciiname":"Rashidabad",
    "gn:country_code":"IR",
    "gn:dem":1087,
    "gn:feature_class":"P",
    "gn:feature_code":"PPL",
    "gn:name":"Rash\u012bd\u0101b\u0101d",
    "gn:population":0,
    "gn:timezone":"Asia/Tehran",
    "iso:country":"IR",
    "name:fas_x_preferred":[
        "\u0631\u0634\u06cc\u062f \u0622\u0628\u0627\u062f"
    ],
    "name:fas_x_variant":[
        "Rash\u012bd\u0101b\u0101d"
    ],
    "wof:name":"Rashidabad",
    "wof:placetype":"locality"
},
  "geometry": {"coordinates":[54.3074,28.7805],"type":"Point"}
}