{
  "type": "Feature",
  "properties": {
    "gn:admin1_code":"29.0",
    "gn:asciiname":"Borjabad `Ashayeri",
    "gn:country_code":"IR",
    "gn:dem":1817,
    "gn:feature_class":"P",
    "gn:feature_code":"PPL",
    "gn:name":"Borj\u0101b\u0101d \u2018Ash\u0101yer\u012b",
    "gn:population":0,
    "gn:timezone":"Asia/Tehran",
    "iso:country":"IR",
    "name:fas_x_preferred":[
        "\u0628\u0631\u062c \u0622\u0628\u0627\u062f \u0639\u0634\u0627\u06cc\u0631\u06cc"
    ],
    "name:und_x_variant":[
        "Borj\u0101b\u0101d \u2018Ash\u0101yer\u012b"
    ],
    "wof:name":"Borjabad `Ashayeri",
    "wof:placetype":"locality"
},
  "geometry": {"coordinates":[55.75175,29.49322],"type":"Point"}
}