{
  "type": "Feature",
  "properties": {
    "gn:admin1_code":"29",
    "gn:asciiname":"Chah-e `Alam",
    "gn:country_code":"IR",
    "gn:dem":389,
    "gn:feature_class":"P",
    "gn:feature_code":"PPLF",
    "gn:name":"Ch\u0101h-e \u2018Alam",
    "gn:population":0,
    "gn:timezone":"Asia/Tehran",
    "iso:country":"IR",
    "name:fas_x_preferred":[
        "\u0686\u0627\u0647 \u0627\u0639\u0644\u0645"
    ],
    "name:fas_x_variant":[
        "Ch\u0101h-e A\u2018lam",
        "\u0686\u0627\u0647 \u0639\u0644\u0645"
    ],
    "name:und_x_variant":[
        "Ch\u0101h-e \u2018Alam"
    ],
    "wof:name":"Chah-e `Alam",
    "wof:placetype":"locality"
},
  "geometry": {"coordinates":[58.80453000000001,27.77088],"type":"Point"}
}