{
  "type": "Feature",
  "properties": {
    "gn:admin1_code":"4",
    "gn:asciiname":"Na`luki",
    "gn:country_code":"IR",
    "gn:dem":390,
    "gn:feature_class":"P",
    "gn:feature_code":"PPL",
    "gn:name":"Na\u2018l\u016bk\u012b",
    "gn:population":0,
    "gn:timezone":"Asia/Tehran",
    "iso:country":"IR",
    "name:ara_x_preferred":[
        "\u0646\u0644\u0648\u0643\u064a"
    ],
    "name:fas_x_preferred":[
        "\u0646\u0648\u0631 \u0622\u0628\u0627\u062f \u0646\u0644\u0648\u06a9\u06cc"
    ],
    "name:fas_x_variant":[
        "N\u016br\u0101b\u0101d-e Nal\u016bk\u012b",
        "\u0646\u0639\u0644\u0648\u06a9\u06cc",
        "\u0646\u0644\u0648\u06a9\u06cc"
    ],
    "name:und_x_variant":[
        "Na\u2018l\u016bk\u012b",
        "Nal\u016bk\u012b"
    ],
    "wof:name":"Na`luki",
    "wof:placetype":"locality"
},
  "geometry": {"coordinates":[59.40194,27.07912],"type":"Point"}
}