{
  "type": "Feature",
  "properties": {
    "gn:admin1_code":"34",
    "gn:asciiname":"Qalavar-e Bala",
    "gn:country_code":"IR",
    "gn:dem":1487,
    "gn:feature_class":"P",
    "gn:feature_code":"PPL",
    "gn:name":"Qal\u0101var-e B\u0101l\u0101",
    "gn:population":0,
    "gn:timezone":"Asia/Tehran",
    "iso:country":"IR",
    "name:fas_x_preferred":[
        "\u0642\u0644\u0627\u0648\u0631 \u0628\u0627\u0644\u0627"
    ],
    "name:fas_x_variant":[
        "Qal\u0101var-e B\u0101l\u0101"
    ],
    "wof:name":"Qalavar-e Bala",
    "wof:placetype":"locality"
},
  "geometry": {"coordinates":[50.5985,33.9136],"type":"Point"}
}