{
  "type": "Feature",
  "properties": {
    "gn:admin1_code":"38",
    "gn:asciiname":"Hoseynabad-e Kord",
    "gn:country_code":"IR",
    "gn:dem":1183,
    "gn:feature_class":"P",
    "gn:feature_code":"PPL",
    "gn:name":"\u1e28oseyn\u0101b\u0101d-e Kord",
    "gn:population":0,
    "gn:timezone":"Asia/Tehran",
    "iso:country":"IR",
    "name:ara_x_preferred":[
        "\u062d\u0633\u064a\u0646 \u0623\u0628\u0627\u062f \u06a9\u0631\u062f"
    ],
    "name:fas_x_preferred":[
        "\u1e28oseyn\u0101b\u0101d"
    ],
    "name:fas_x_variant":[
        "\u1e28oseyn\u0101b\u0101d-e Kord",
        "\u062d\u0633\u064a\u0646 \u0622\u0628\u0627\u062f \u0643\u0631\u062f",
        "\u062d\u0633\u06cc\u0646 \u0622\u0628\u0627\u062f",
        "\u062d\u0633\u06cc\u0646\u200c\u0622\u0628\u0627\u062f \u06a9\u0631\u062f"
    ],
    "wof:name":"Hoseynabad-e Kord",
    "wof:placetype":"locality"
},
  "geometry": {"coordinates":[50.4924,36.0034],"type":"Point"}
}