{
  "type": "Feature",
  "properties": {
    "gn:admin1_code":"23",
    "gn:asciiname":"Pelkan-e `Olya",
    "gn:country_code":"IR",
    "gn:dem":1773,
    "gn:feature_class":"P",
    "gn:feature_code":"PPL",
    "gn:name":"Pelk\u0101n-e \u2018Oly\u0101",
    "gn:population":0,
    "gn:timezone":"Asia/Tehran",
    "iso:country":"IR",
    "name:fas_x_preferred":[
        "\u067e\u0644\u0643\u0627\u0646 \u0639\u0644\u064a\u0627"
    ],
    "name:fas_x_variant":[
        "Pellehk\u0101n-e B\u0101l\u0101",
        "\u0100b Sardeh-ye Sofl\u00e1",
        "Palk\u0101n-e \u2018Oly\u0101",
        "Palk\u0101n-e \u2018Al\u0101\u2019\u012bn",
        "Pelk\u0101n-e \u2018Oly\u0101"
    ],
    "wof:name":"Pelkan-e `Olya",
    "wof:placetype":"locality"
},
  "geometry": {"coordinates":[48.62666,33.78375],"type":"Point"}
}