{
  "type": "Feature",
  "properties": {
    "gn:admin1_code":"28.0",
    "gn:asciiname":"Gol Shahr",
    "gn:country_code":"IR",
    "gn:dem":1616,
    "gn:feature_class":"P",
    "gn:feature_code":"PPL",
    "gn:name":"Gol Shahr",
    "gn:population":0,
    "gn:timezone":"Asia/Tehran",
    "iso:country":"IR",
    "wof:name":"Gol Shahr",
    "wof:placetype":"locality"
},
  "geometry": {"coordinates":[51.45,32.61667],"type":"Point"}
}