{
  "type": "Feature",
  "properties": {
    "gn:admin1_code":"15.0",
    "gn:asciiname":"Na`l-e Kanan",
    "gn:country_code":"IR",
    "gn:dem":974,
    "gn:feature_class":"P",
    "gn:feature_code":"PPL",
    "gn:name":"Na\u2018l-e Kan\u0101n",
    "gn:population":0,
    "gn:timezone":"Asia/Tehran",
    "iso:country":"IR",
    "name:fas_x_preferred":[
        "Na\u2018l-e Kan\u0101n"
    ],
    "name:fas_x_variant":[
        "\u0646\u0639\u0644 \u06a9\u0646\u0627\u0646"
    ],
    "name:und_x_variant":[
        "\u0646\u0639\u0644 \u06a9\u0646\u0627\u0646"
    ],
    "wof:name":"Na`l-e Kanan",
    "wof:placetype":"locality"
},
  "geometry": {"coordinates":[50.17949,31.74278],"type":"Point"}
}