{
  "type": "Feature",
  "properties": {
    "gn:admin1_code":"8.0",
    "gn:asciiname":"Eshkolak",
    "gn:country_code":"IR",
    "gn:dem":58,
    "gn:feature_class":"P",
    "gn:feature_code":"PPL",
    "gn:name":"Eshkolak",
    "gn:population":0,
    "gn:timezone":"Asia/Tehran",
    "iso:country":"IR",
    "name:fas_x_preferred":[
        "\u0627\u0634\u06a9\u0644\u06a9"
    ],
    "name:fas_x_variant":[
        "\u0644\u0634\u06a9\u0644\u06a9"
    ],
    "name:und_x_variant":[
        "Lashkalak"
    ],
    "wof:name":"Eshkolak",
    "wof:placetype":"locality"
},
  "geometry": {"coordinates":[50.33401,37.03016],"type":"Point"}
}