{
  "type": "Feature",
  "properties": {
    "gn:admin1_code":"15.0",
    "gn:asciiname":"Abeleh",
    "gn:country_code":"IR",
    "gn:dem":377,
    "gn:feature_class":"P",
    "gn:feature_code":"PPL",
    "gn:name":"\u0100beleh",
    "gn:population":0,
    "gn:timezone":"Asia/Tehran",
    "iso:country":"IR",
    "wof:name":"Abeleh",
    "wof:placetype":"locality"
},
  "geometry": {"coordinates":[49.21667,32.06667],"type":"Point"}
}