{
  "type": "Feature",
  "properties": {
    "gn:admin1_code":"4",
    "gn:asciiname":"Niazabad",
    "gn:country_code":"IR",
    "gn:dem":1443,
    "gn:feature_class":"P",
    "gn:feature_code":"PPL",
    "gn:name":"N\u012b\u0101z\u0101b\u0101d",
    "gn:population":0,
    "gn:timezone":"Asia/Tehran",
    "iso:country":"IR",
    "name:fas_x_preferred":[
        "\u0646\u06cc\u0627\u0632 \u0622\u0628\u0627\u062f"
    ],
    "name:fas_x_variant":[
        "N\u012b\u0101z\u0101b\u0101d"
    ],
    "wof:name":"Niazabad",
    "wof:placetype":"locality"
},
  "geometry": {"coordinates":[60.41956,28.94256],"type":"Point"}
}