{
  "type": "Feature",
  "properties": {
    "gn:admin1_code":"22",
    "gn:asciiname":"Bana-ye Hadi",
    "gn:country_code":"IR",
    "gn:dem":753,
    "gn:feature_class":"P",
    "gn:feature_code":"PPL",
    "gn:name":"Ban\u0101-ye H\u0101d\u012b",
    "gn:population":0,
    "gn:timezone":"Asia/Tehran",
    "iso:country":"IR",
    "name:fas_x_preferred":[
        "\u0628\u064e\u0646\u0627\u06cc \u0647\u0627\u062f\u06cc"
    ],
    "name:fas_x_variant":[
        "Ban\u0101-ye H\u0101d\u012b"
    ],
    "wof:name":"Bana-ye Hadi",
    "wof:placetype":"locality"
},
  "geometry": {"coordinates":[52.12389,27.95111],"type":"Point"}
}