{
  "type": "Feature",
  "properties": {
    "gn:admin1_code":"4.0",
    "gn:asciiname":"Dastshuk",
    "gn:country_code":"IR",
    "gn:dem":1126,
    "gn:feature_class":"P",
    "gn:feature_code":"PPL",
    "gn:name":"Dastsh\u016bk",
    "gn:population":0,
    "gn:timezone":"Asia/Tehran",
    "iso:country":"IR",
    "name:fas_x_preferred":[
        "\u062f\u0634\u062a\u0648\u06a9"
    ],
    "name:fas_x_variant":[
        "Dasht\u016bk",
        "\u062f\u0633\u062a\u0634\u0648\u06a9"
    ],
    "name:und_x_variant":[
        "Dashtkooh",
        "Dashtak",
        "Dashtok",
        "Dastsh\u016bk"
    ],
    "wof:name":"Dastshuk",
    "wof:placetype":"locality"
},
  "geometry": {"coordinates":[62.09995,27.23042],"type":"Point"}
}