{
  "type": "Feature",
  "properties": {
    "gn:admin1_code":"8",
    "gn:asciiname":"Chaykhansar",
    "gn:country_code":"IR",
    "gn:dem":-1,
    "gn:feature_class":"P",
    "gn:feature_code":"PPL",
    "gn:name":"Ch\u0101ykh\u0101nsar",
    "gn:population":0,
    "gn:timezone":"Asia/Tehran",
    "iso:country":"IR",
    "name:fas_x_preferred":[
        "Ch\u0101kh\u0101nesar"
    ],
    "name:fas_x_variant":[
        "Ch\u0101kh\u0101nehsar",
        "\u0686\u0627\u062e\u0627\u0646\u0647 \u0633\u0631",
        "\u0686\u0627\u06cc\u062e\u0627\u0646\u0633\u0631"
    ],
    "name:und_x_variant":[
        "Chakh\u0101n\u012b",
        "Chakh\u0101n\u012b Sar",
        "\u0686\u0627\u062e\u0627\u0646\u0647 \u0633\u0631",
        "Ch\u0101ykh\u0101nsar"
    ],
    "wof:name":"Chaykhansar",
    "wof:placetype":"locality"
},
  "geometry": {"coordinates":[50.4486,37.03849],"type":"Point"}
}