{
  "type": "Feature",
  "properties": {
    "gn:admin1_code":"23",
    "gn:asciiname":"Monar",
    "gn:country_code":"IR",
    "gn:dem":960,
    "gn:feature_class":"P",
    "gn:feature_code":"PPL",
    "gn:name":"Mon\u0101r",
    "gn:population":0,
    "gn:timezone":"Asia/Tehran",
    "iso:country":"IR",
    "name:fas_x_preferred":[
        "\u0645\u0646\u0627\u0631"
    ],
    "name:fas_x_variant":[
        "\u0645\u0646\u0627\u0631 \u0633\u0627\u0637\u0631\u0648\u0646\u062f",
        "Mon\u0101r",
        "Men\u0101r-e Sa\u0163orvand",
        "\u0639\u0644\u06cc \u0639\u0633\u06af\u0631"
    ],
    "name:und_x_variant":[
        "\u2018Al\u012b \u2018Asgar"
    ],
    "wof:name":"Monar",
    "wof:placetype":"locality"
},
  "geometry": {"coordinates":[47.26227,33.41511],"type":"Point"}
}