{
  "type": "Feature",
  "properties": {
    "gn:admin1_code":"16",
    "gn:asciiname":"Nabiabad",
    "gn:country_code":"IR",
    "gn:dem":1906,
    "gn:feature_class":"P",
    "gn:feature_code":"PPL",
    "gn:name":"Nab\u012b\u0101b\u0101d",
    "gn:population":0,
    "gn:timezone":"Asia/Tehran",
    "iso:country":"IR",
    "name:fas_x_preferred":[
        "\u0646\u0628\u06cc \u0622\u0628\u0627\u062f"
    ],
    "name:fas_x_variant":[
        "Nab\u012b\u0101b\u0101d",
        "\u0646\u0628\u06cc\u200c\u0622\u0628\u0627\u062f"
    ],
    "name:mzn_x_preferred":[
        "\u0646\u0628\u06cc\u200c\u0622\u0628\u0627\u062f"
    ],
    "name:und_x_variant":[
        "Ney\u0101b\u0101d",
        "Nay\u0101b\u0101d"
    ],
    "wof:name":"Nabiabad",
    "wof:placetype":"locality"
},
  "geometry": {"coordinates":[47.42366,35.10604],"type":"Point"}
}