{
  "type": "Feature",
  "properties": {
    "gn:admin1_code":"35.0",
    "gn:asciiname":"Siah Lash",
    "gn:country_code":"IR",
    "gn:dem":17,
    "gn:feature_class":"P",
    "gn:feature_code":"PPL",
    "gn:name":"S\u012b\u0101h Lash",
    "gn:population":0,
    "gn:timezone":"Asia/Tehran",
    "iso:country":"IR",
    "name:fas_x_preferred":[
        "\u0633\u06cc\u0627\u0647 \u0644\u0634"
    ],
    "name:fas_x_variant":[
        "S\u012b\u0101h Lash"
    ],
    "wof:name":"Siah Lash",
    "wof:placetype":"locality"
},
  "geometry": {"coordinates":[52.24801,36.507],"type":"Point"}
}