{
  "type": "Feature",
  "properties": {
    "gn:admin1_code":"26.0",
    "gn:asciiname":"Qal`eh-ye Salariyeh",
    "gn:country_code":"IR",
    "gn:dem":824,
    "gn:feature_class":"P",
    "gn:feature_code":"PPL",
    "gn:name":"Qal\u2018eh-ye S\u0101l\u0101r\u012byeh",
    "gn:population":0,
    "gn:timezone":"Asia/Tehran",
    "iso:country":"IR",
    "name:fas_x_preferred":[
        "\u0642\u064e\u0644\u0639\u0650\u06c0 \u0633\u0627\u0644\u0627\u0631\u064a\u0650\u0651\u0647"
    ],
    "name:fas_x_variant":[
        "Qal\u2018eh-ye S\u0101l\u0101r\u012byeh"
    ],
    "wof:name":"Qal`eh-ye Salariyeh",
    "wof:placetype":"locality"
},
  "geometry": {"coordinates":[51.58333,35.11667],"type":"Point"}
}