{
  "type": "Feature",
  "properties": {
    "gn:admin1_code":"10.0",
    "gn:asciiname":"Golzar-e Haddad",
    "gn:country_code":"IR",
    "gn:dem":1214,
    "gn:feature_class":"P",
    "gn:feature_code":"PPL",
    "gn:name":"Golz\u0101r-e \u1e28add\u0101d",
    "gn:population":0,
    "gn:timezone":"Asia/Tehran",
    "iso:country":"IR",
    "name:ceb_x_preferred":[
        "Golz\u0101r-e \u1e28add\u0101d"
    ],
    "name:fas_x_preferred":[
        "\u06af\u0644\u0632\u0627\u0631 \u062d\u062f\u0651\u0627\u062f"
    ],
    "name:fas_x_variant":[
        "Golz\u0101r-e \u1e28add\u0101d",
        "\u06af\u0644\u0632\u0627\u0631 \u062d\u062f\u0627\u062f"
    ],
    "name:msa_x_preferred":[
        "Golzar-e Haddad"
    ],
    "name:swe_x_preferred":[
        "Golz\u0101r-e \u1e28add\u0101d"
    ],
    "wof:name":"Golzar-e Haddad",
    "wof:placetype":"locality"
},
  "geometry": {"coordinates":[46.3468,33.7164],"type":"Point"}
}