{
  "type": "Feature",
  "properties": {
    "gn:admin1_code":"29.0",
    "gn:asciiname":"Firuzabad",
    "gn:country_code":"IR",
    "gn:dem":1950,
    "gn:feature_class":"P",
    "gn:feature_code":"PPL",
    "gn:name":"F\u012br\u016bz\u0101b\u0101d",
    "gn:population":0,
    "gn:timezone":"Asia/Tehran",
    "iso:country":"IR",
    "name:fas_x_preferred":[
        "F\u012br\u016bz\u0101b\u0101d"
    ],
    "wof:name":"Firuzabad",
    "wof:placetype":"locality"
},
  "geometry": {"coordinates":[56.69139000000001,28.98194],"type":"Point"}
}