{
  "type": "Feature",
  "properties": {
    "gn:admin1_code":"8.0",
    "gn:asciiname":"Bala Galayeh",
    "gn:country_code":"IR",
    "gn:dem":1876,
    "gn:feature_class":"P",
    "gn:feature_code":"PPL",
    "gn:name":"B\u0101l\u0101 Gal\u0101yeh",
    "gn:population":0,
    "gn:timezone":"Asia/Tehran",
    "iso:country":"IR",
    "name:fas_x_preferred":[
        "\u06af\u0644\u0627\u06cc\u0647 \u06a9\u0648\u0686\u06a9"
    ],
    "name:fas_x_variant":[
        "\u0628\u0627\u0644\u0627 \u06af\u0644\u0627\u06cc\u0647"
    ],
    "name:und_x_variant":[
        "Gal\u0101yeh-ye K\u016bchak",
        "B\u0101l\u0101 Gal\u0101yeh"
    ],
    "wof:name":"Bala Galayeh",
    "wof:placetype":"locality"
},
  "geometry": {"coordinates":[50.22973,36.76511],"type":"Point"}
}