{
  "type": "Feature",
  "properties": {
    "gn:admin1_code":"23",
    "gn:asciiname":"Qata`at",
    "gn:country_code":"IR",
    "gn:dem":1977,
    "gn:feature_class":"P",
    "gn:feature_code":"PPL",
    "gn:name":"Qa\u0163a\u2018\u0101t",
    "gn:population":0,
    "gn:timezone":"Asia/Tehran",
    "iso:country":"IR",
    "name:fas_x_preferred":[
        "\u0642\u0637\u0639\u0627\u062a"
    ],
    "name:fas_x_variant":[
        "Qa\u0163a\u2018\u0101t"
    ],
    "name:und_x_variant":[
        "Qa\u0163a\u2018\u0101t Qeshl\u0101q"
    ],
    "wof:name":"Qata`at",
    "wof:placetype":"locality"
},
  "geometry": {"coordinates":[49.3979,33.61603],"type":"Point"}
}