{
  "type": "Feature",
  "properties": {
    "gn:admin1_code":"42.0",
    "gn:asciiname":"Dars Akhund",
    "gn:country_code":"IR",
    "gn:dem":1373,
    "gn:feature_class":"P",
    "gn:feature_code":"PPL",
    "gn:name":"Dars \u0100kh\u016bnd",
    "gn:population":0,
    "gn:timezone":"Asia/Tehran",
    "iso:country":"IR",
    "name:fas_x_preferred":[
        "\u062f\u0631\u0633 \u0622\u062e\u0648\u0646\u062f"
    ],
    "name:fas_x_variant":[
        "Dars \u0100kh\u016bnd"
    ],
    "name:und_x_variant":[
        "Dars-e \u0100khvond",
        "Dan\u0101n-i-S\u0101khu",
        "Dah\u0101neh-ye S\u0101kh\u016b"
    ],
    "wof:name":"Dars Akhund",
    "wof:placetype":"locality"
},
  "geometry": {"coordinates":[60.6152,35.6482],"type":"Point"}
}