{
  "type": "Feature",
  "properties": {
    "gn:admin1_code":"40.0",
    "gn:asciiname":"Mazra`eh-ye Khalil-e Pa'in",
    "gn:country_code":"IR",
    "gn:dem":1576,
    "gn:feature_class":"P",
    "gn:feature_code":"PPL",
    "gn:name":"Mazra\u2018eh-ye Khal\u012bl-e P\u0101\u2019\u012bn",
    "gn:population":0,
    "gn:timezone":"Asia/Tehran",
    "iso:country":"IR",
    "name:fas_x_preferred":[
        "\u0645\u064e\u0632\u0631\u064e\u0639\u0650\u06c0 \u062e\u064e\u0644\u064a\u0644\u0650 \u067e\u0627\u0626\u064a\u0646"
    ],
    "name:fas_x_variant":[
        "Mazra\u2018eh-ye Khal\u012bl-e P\u0101\u2019\u012bn"
    ],
    "wof:name":"Mazra`eh-ye Khalil-e Pa'in",
    "wof:placetype":"locality"
},
  "geometry": {"coordinates":[53.88444000000001,31.915],"type":"Point"}
}