{
  "type": "Feature",
  "properties": {
    "gn:admin1_code":"8",
    "gn:asciiname":"Nowbijar Mahalleh",
    "gn:country_code":"IR",
    "gn:dem":-20,
    "gn:feature_class":"P",
    "gn:feature_code":"PPL",
    "gn:name":"Nowb\u012bj\u0101r Ma\u1e29alleh",
    "gn:population":0,
    "gn:timezone":"Asia/Tehran",
    "iso:country":"IR",
    "name:fas_x_preferred":[
        "\u0646\u0648\u0628\u06cc\u062c\u0627\u0631 \u0645\u062d\u0644\u0647"
    ],
    "name:fas_x_variant":[
        "\u0646\u0648\u0628\u06cc\u062c\u0627\u0631 \u0645\u062d\u0644\u0647 \u0645\u062d\u0633\u0646 \u0622\u0628\u0627\u062f"
    ],
    "name:und_x_variant":[
        "Nowb\u012bj\u0101r Ma\u1e29alleh",
        "Nowb\u012bj\u0101r Ma\u1e29alleh-ye Mo\u1e29sen\u0101b\u0101d"
    ],
    "wof:name":"Nowbijar Mahalleh",
    "wof:placetype":"locality"
},
  "geometry": {"coordinates":[49.9323,37.3923],"type":"Point"}
}