{
  "type": "Feature",
  "properties": {
    "gn:admin1_code":"1.0",
    "gn:asciiname":"Kani Shinkan",
    "gn:country_code":"IR",
    "gn:dem":1418,
    "gn:feature_class":"P",
    "gn:feature_code":"PPL",
    "gn:name":"K\u0101n\u012b Sh\u012bnk\u0101n",
    "gn:population":0,
    "gn:timezone":"Asia/Tehran",
    "iso:country":"IR",
    "name:fas_x_preferred":[
        "\u06a9\u0627\u0646\u06cc \u0634\u06cc\u0646\u06a9\u0627\u0646"
    ],
    "name:fas_x_variant":[
        "K\u0101n\u012b Sh\u012bnk\u0101n"
    ],
    "wof:name":"Kani Shinkan",
    "wof:placetype":"locality"
},
  "geometry": {"coordinates":[45.2875,36.5004],"type":"Point"}
}