{
  "type": "Feature",
  "properties": {
    "gn:admin1_code":"13",
    "gn:asciiname":"Golah Jar",
    "gn:country_code":"IR",
    "gn:dem":1263,
    "gn:feature_class":"P",
    "gn:feature_code":"PPL",
    "gn:name":"Golah J\u0101r",
    "gn:population":0,
    "gn:timezone":"Asia/Tehran",
    "iso:country":"IR",
    "name:fas_x_preferred":[
        "\u06af\u0644\u0647 \u062c\u0627\u0631"
    ],
    "name:fas_x_variant":[
        "Golah J\u0101r"
    ],
    "wof:name":"Golah Jar",
    "wof:placetype":"locality"
},
  "geometry": {"coordinates":[47.3355,34.1856],"type":"Point"}
}