{
  "type": "Feature",
  "properties": {
    "gn:admin1_code":"11",
    "gn:asciiname":"Dahaneh-ye Palangi",
    "gn:country_code":"IR",
    "gn:dem":1113,
    "gn:feature_class":"P",
    "gn:feature_code":"PPL",
    "gn:name":"Dahaneh-ye Palang\u012b",
    "gn:population":0,
    "gn:timezone":"Asia/Tehran",
    "iso:country":"IR",
    "name:fas_x_preferred":[
        "\u062f\u0647\u0646\u0647 \u067e\u0644\u0646\u06af\u06cc"
    ],
    "name:fas_x_variant":[
        "Dahaneh-ye Palang\u012b"
    ],
    "wof:name":"Dahaneh-ye Palangi",
    "wof:placetype":"locality"
},
  "geometry": {"coordinates":[56.0549,27.8927],"type":"Point"}
}