{
  "type": "Feature",
  "properties": {
    "gn:admin1_code":"15",
    "gn:asciiname":"Boneh-ye Hajat",
    "gn:country_code":"IR",
    "gn:dem":42,
    "gn:feature_class":"P",
    "gn:feature_code":"PPL",
    "gn:name":"Boneh-ye \u1e28\u0101j\u0101t",
    "gn:population":0,
    "gn:timezone":"Asia/Tehran",
    "iso:country":"IR",
    "name:fas_x_preferred":[
        "\u062e\u0648\u0632\u06cc\u0646\u0647 \u067e\u0627\u0626\u06cc\u0646"
    ],
    "name:fas_x_variant":[
        "Khowz\u012bneh-ye P\u0101\u2019\u012bn",
        "Khvoz\u012bneh-ye P\u0101\u2019\u012bn",
        "\u0628\u0646\u0647 \u062d\u0627\u062c\u0627\u062a"
    ],
    "name:und_x_variant":[
        "Khowz\u012bn\u0101 P\u0101\u2019\u012bn",
        "Boneh-ye \u1e28\u0101j\u0101t"
    ],
    "wof:name":"Boneh-ye Hajat",
    "wof:placetype":"locality"
},
  "geometry": {"coordinates":[48.5789,32.0345],"type":"Point"}
}