{
  "type": "Feature",
  "properties": {
    "gn:admin1_code":"7",
    "gn:asciiname":"Mehrabad-e Ja`fari",
    "gn:country_code":"IR",
    "gn:dem":1752,
    "gn:feature_class":"P",
    "gn:feature_code":"PPL",
    "gn:name":"Mehr\u0101b\u0101d-e Ja\u2018far\u012b",
    "gn:population":0,
    "gn:timezone":"Asia/Tehran",
    "iso:country":"IR",
    "name:fas_x_preferred":[
        "\u062c\u0639\u0641\u0631 \u0622\u0628\u0627\u062f"
    ],
    "name:fas_x_variant":[
        "Ja\u2018far\u0101b\u0101d",
        "\u0645\u0647\u0631 \u0622\u0628\u0627\u062f \u062c\u0639\u0641\u0631\u06cc",
        "\u0628\u0646\u06a9\u0648\u06cc \u062c\u0639\u0641\u0631\u06cc"
    ],
    "name:und_x_variant":[
        "Mehr\u0101b\u0101d-e Ja\u2018far\u012b",
        "Bank\u016b-ye Ja\u2018far\u012b"
    ],
    "wof:name":"Mehrabad-e Ja`fari",
    "wof:placetype":"locality"
},
  "geometry": {"coordinates":[53.2232,29.4521],"type":"Point"}
}