{
  "type": "Feature",
  "properties": {
    "gn:admin1_code":"11",
    "gn:asciiname":"Kalateh-ye Guni",
    "gn:country_code":"IR",
    "gn:dem":1179,
    "gn:feature_class":"P",
    "gn:feature_code":"PPL",
    "gn:name":"Kal\u0101teh-ye G\u016bn\u012b",
    "gn:population":0,
    "gn:timezone":"Asia/Tehran",
    "iso:country":"IR",
    "name:fas_x_preferred":[
        "\u06a9\u0644\u0627\u062a\u0647 \u06af\u0648\u0646\u06cc"
    ],
    "name:fas_x_variant":[
        "Kal\u0101teh-ye G\u016bn\u012b"
    ],
    "wof:name":"Kalateh-ye Guni",
    "wof:placetype":"locality"
},
  "geometry": {"coordinates":[56.1305,27.88],"type":"Point"}
}