{
  "type": "Feature",
  "properties": {
    "gn:admin1_code":"4",
    "gn:asciiname":"Rah Sebil",
    "gn:country_code":"IR",
    "gn:dem":744,
    "gn:feature_class":"P",
    "gn:feature_code":"PPL",
    "gn:name":"R\u0101h Seb\u012bl",
    "gn:population":0,
    "gn:timezone":"Asia/Tehran",
    "iso:country":"IR",
    "name:fas_x_preferred":[
        "R\u0101h Seb\u012bl"
    ],
    "wof:name":"Rah Sebil",
    "wof:placetype":"locality"
},
  "geometry": {"coordinates":[59.65,26.61667000000001],"type":"Point"}
}