{
  "type": "Feature",
  "properties": {
    "gn:admin1_code":"28",
    "gn:asciiname":"Shahrak-e Shahid Qujani",
    "gn:country_code":"IR",
    "gn:dem":1727,
    "gn:feature_class":"P",
    "gn:feature_code":"PPL",
    "gn:name":"Shahrak-e Shah\u012bd Q\u016bj\u0101n\u012b",
    "gn:population":0,
    "gn:timezone":"Asia/Tehran",
    "iso:country":"IR",
    "name:fas_x_preferred":[
        "\u0634\u0647\u0631\u0643 \u0634\u0647\u06cc\u062f \u0642\u0648\u0686\u0627\u0646\u06cc"
    ],
    "name:fas_x_variant":[
        "Shahrak-e Shah\u012bd Q\u016bch\u0101n\u012b",
        "\u0634\u0647\u0631\u0643 \u0634\u0647\u06cc\u062f \u0642\u0648\u062c\u0627\u0646\u06cc"
    ],
    "name:und_x_variant":[
        "Shahrak-e Shah\u012bd Q\u016bj\u0101n\u012b"
    ],
    "wof:name":"Shahrak-e Shahid Qujani",
    "wof:placetype":"locality"
},
  "geometry": {"coordinates":[51.40226,33.15867],"type":"Point"}
}