{
  "type": "Feature",
  "properties": {
    "gn:admin1_code":"34",
    "gn:asciiname":"Hasanabad",
    "gn:country_code":"IR",
    "gn:dem":1359,
    "gn:feature_class":"P",
    "gn:feature_code":"PPL",
    "gn:name":"\u1e28asan\u0101b\u0101d",
    "gn:population":0,
    "gn:timezone":"Asia/Tehran",
    "iso:country":"IR",
    "name:fas_x_preferred":[
        "\u062d\u0633\u0646 \u0622\u0628\u0627\u062f \u0634\u064a\u0631 \u0645\u062d\u0645\u062f"
    ],
    "name:fas_x_variant":[
        "\u1e28asan\u0101b\u0101d-e Sh\u012br Mo\u1e29ammad",
        "\u062d\u0633\u0646 \u0622\u0628\u0627\u062f"
    ],
    "name:und_x_variant":[
        "Husain\u0101b\u0101d",
        "\u1e28asan\u0101b\u0101d"
    ],
    "wof:name":"Hasanabad",
    "wof:placetype":"locality"
},
  "geometry": {"coordinates":[50.1389,35.0528],"type":"Point"}
}