{
  "type": "Feature",
  "properties": {
    "gn:admin1_code":"15",
    "gn:asciiname":"Sarimeh",
    "gn:country_code":"IR",
    "gn:dem":24,
    "gn:feature_class":"P",
    "gn:feature_code":"PPL",
    "gn:name":"Sar\u012bmeh",
    "gn:population":0,
    "gn:timezone":"Asia/Tehran",
    "iso:country":"IR",
    "name:fas_x_preferred":[
        "\u0633\u0631\u06cc\u0645\u0647"
    ],
    "name:fas_x_variant":[
        "Sar\u012bmeh"
    ],
    "wof:name":"Sarimeh",
    "wof:placetype":"locality"
},
  "geometry": {"coordinates":[48.84722,31.71323],"type":"Point"}
}