{
  "type": "Feature",
  "properties": {
    "gn:admin1_code":"1",
    "gn:asciiname":"Lakabad",
    "gn:country_code":"IR",
    "gn:dem":1724,
    "gn:feature_class":"P",
    "gn:feature_code":"PPL",
    "gn:name":"Lak\u0101b\u0101d",
    "gn:population":0,
    "gn:timezone":"Asia/Tehran",
    "iso:country":"IR",
    "name:ara_x_preferred":[
        "\u0644\u0643 \u0622\u0628\u0627\u062f"
    ],
    "name:fas_x_preferred":[
        "\u0644\u06a9 \u0622\u0628\u0627\u062f"
    ],
    "name:fas_x_variant":[
        "Lak\u0101b\u0101d",
        "\u0644\u06a9\u200c\u0622\u0628\u0627\u062f"
    ],
    "name:urd_x_preferred":[
        "\u0644\u0627\u06a9 \u0622\u0628\u0627\u062f"
    ],
    "wof:name":"Lakabad",
    "wof:placetype":"locality"
},
  "geometry": {"coordinates":[44.5671,38.0477],"type":"Point"}
}