{
  "type": "Feature",
  "properties": {
    "gn:admin1_code":"41",
    "gn:asciiname":"Kalateh-ye Hoseynabad",
    "gn:country_code":"IR",
    "gn:dem":1858,
    "gn:feature_class":"P",
    "gn:feature_code":"PPL",
    "gn:name":"Kal\u0101teh-ye \u1e28oseyn\u0101b\u0101d",
    "gn:population":0,
    "gn:timezone":"Asia/Tehran",
    "iso:country":"IR",
    "name:fas_x_preferred":[
        "\u1e28oseyn\u0101b\u0101d"
    ],
    "name:fas_x_variant":[
        "\u062d\u0633\u064a\u0646 \u0622\u0628\u0627\u062f",
        "Kal\u0101teh-ye \u1e28oseyn\u0101b\u0101d",
        "Kal\u0101teh Husain\u0101b\u0101d",
        "Husain\u0101b\u0101d",
        "\u06a9\u0644\u0627\u062a\u0647 \u062d\u0633\u064a\u0646 \u0622\u0628\u0627\u062f"
    ],
    "name:und_x_variant":[
        "Kal\u0101teh-ye \u1e28oseyn\u0101b\u0101d",
        "Hosein Abad Barakooh",
        "Kal\u0101teh Husain\u0101b\u0101d",
        "Husain\u0101b\u0101d",
        "\u062d\u0633\u064a\u0646 \u0622\u0628\u0627\u062f"
    ],
    "wof:name":"Kalateh-ye Hoseynabad",
    "wof:placetype":"locality"
},
  "geometry": {"coordinates":[59.10773,32.72187],"type":"Point"}
}