{
  "type": "Feature",
  "properties": {
    "gn:admin1_code":"32.0",
    "gn:asciiname":"Chenar",
    "gn:country_code":"IR",
    "gn:dem":678,
    "gn:feature_class":"P",
    "gn:feature_code":"PPL",
    "gn:name":"Chen\u0101r",
    "gn:population":0,
    "gn:timezone":"Asia/Tehran",
    "iso:country":"IR",
    "name:fas_x_preferred":[
        "\u0686\u0646\u0627\u0631"
    ],
    "name:fas_x_variant":[
        "Chen\u0101r"
    ],
    "name:nld_x_preferred":[
        "Chenar"
    ],
    "wof:name":"Chenar",
    "wof:placetype":"locality"
},
  "geometry": {"coordinates":[47.8625,39.1212],"type":"Point"}
}