{
  "type": "Feature",
  "properties": {
    "gn:admin1_code":"34",
    "gn:asciiname":"Horrabad",
    "gn:country_code":"IR",
    "gn:dem":1684,
    "gn:feature_class":"P",
    "gn:feature_code":"PPL",
    "gn:name":"\u1e28orr\u0101b\u0101d",
    "gn:population":0,
    "gn:timezone":"Asia/Tehran",
    "iso:country":"IR",
    "name:fas_x_preferred":[
        "\u062d\u064f\u0631 \u0622\u0628\u0627\u062f"
    ],
    "name:fas_x_variant":[
        "\u1e28or\u0101b\u0101d",
        "\u1e28orr\u0101b\u0101d",
        "\u062d\u0631 \u0622\u0628\u0627\u062f"
    ],
    "name:und_x_variant":[
        "Hur\u0101b\u0101d",
        "\u1e28orr\u0101b\u0101d",
        "\u062d\u0631 \u0622\u0628\u0627\u062f"
    ],
    "wof:name":"Horrabad",
    "wof:placetype":"locality"
},
  "geometry": {"coordinates":[49.69797,34.34528],"type":"Point"}
}