{
  "type": "Feature",
  "properties": {
    "gn:admin1_code":"16",
    "gn:asciiname":"Cheraghabad",
    "gn:country_code":"IR",
    "gn:dem":1886,
    "gn:feature_class":"P",
    "gn:feature_code":"PPL",
    "gn:name":"Cher\u0101gh\u0101b\u0101d",
    "gn:population":0,
    "gn:timezone":"Asia/Tehran",
    "iso:country":"IR",
    "name:fas_x_preferred":[
        "\u0686\u0631\u0627\u063a \u0622\u0628\u0627\u062f"
    ],
    "name:fas_x_variant":[
        "Cher\u0101gh\u0101b\u0101d"
    ],
    "name:und_x_variant":[
        "Chiragh\u0101b\u0101d"
    ],
    "wof:name":"Cheraghabad",
    "wof:placetype":"locality"
},
  "geometry": {"coordinates":[47.32285,35.21686],"type":"Point"}
}