{
  "type": "Feature",
  "properties": {
    "gn:admin1_code":"37",
    "gn:asciiname":"Shirang-e Sofla",
    "gn:country_code":"IR",
    "gn:dem":83,
    "gn:feature_class":"P",
    "gn:feature_code":"PPL",
    "gn:name":"Sh\u012brang-e Sofl\u00e1",
    "gn:population":0,
    "gn:timezone":"Asia/Tehran",
    "iso:country":"IR",
    "name:fas_x_preferred":[
        "Sh\u012brang-e Sofl\u00e1"
    ],
    "name:fas_x_variant":[
        "Sh\u012brang-e P\u0101\u2019\u012bn",
        "\u0634\u06cc\u0631\u0646\u06af \u0633\u0641\u0644\u06cc"
    ],
    "name:und_x_variant":[
        "\u0634\u06cc\u0631\u0646\u06af \u0633\u0641\u0644\u06cc"
    ],
    "wof:name":"Shirang-e Sofla",
    "wof:placetype":"locality"
},
  "geometry": {"coordinates":[54.71911,36.95449],"type":"Point"}
}