{
  "type": "Feature",
  "properties": {
    "gn:admin1_code":"13",
    "gn:asciiname":"Shahid Davud Hadian",
    "gn:country_code":"IR",
    "gn:dem":1521,
    "gn:feature_class":"P",
    "gn:feature_code":"PPL",
    "gn:name":"Shah\u012bd D\u0101v\u016bd H\u0101d\u012b\u0101n",
    "gn:population":0,
    "gn:timezone":"Asia/Tehran",
    "iso:country":"IR",
    "name:fas_x_preferred":[
        "\u0634\u0647\u06cc\u062f \u062f\u0627\u0648\u062f \u0647\u0627\u062f\u06cc\u0627\u0646"
    ],
    "name:fas_x_variant":[
        "Sar\u0101b Qanbar-e Shah\u012bd H\u0101d\u012b\u0101n",
        "Shah\u012bd D\u0101v\u016bd H\u0101d\u012b\u0101n"
    ],
    "name:und_x_variant":[
        "Sar\u0101b Qanbar",
        "Shah\u012bd D\u0101v\u016bd H\u0101d\u012b\u0101n"
    ],
    "wof:name":"Shahid Davud Hadian",
    "wof:placetype":"locality"
},
  "geometry": {"coordinates":[46.2931,34.0428],"type":"Point"}
}