{
  "type": "Feature",
  "properties": {
    "gn:admin1_code":"1",
    "gn:asciiname":"Goladur",
    "gn:country_code":"IR",
    "gn:dem":1759,
    "gn:feature_class":"P",
    "gn:feature_code":"PPL",
    "gn:name":"Golad\u016br",
    "gn:population":0,
    "gn:timezone":"Asia/Tehran",
    "iso:country":"IR",
    "name:aze_x_preferred":[
        "G\u00fcl\u0259dur"
    ],
    "name:ceb_x_preferred":[
        "Golad\u016br"
    ],
    "name:fas_x_preferred":[
        "\u06af\u0644\u062f\u0648\u0631"
    ],
    "name:fas_x_variant":[
        "Golad\u016br"
    ],
    "name:msa_x_preferred":[
        "Goladur"
    ],
    "name:swe_x_preferred":[
        "Golad\u016br"
    ],
    "wof:name":"Goladur",
    "wof:placetype":"locality"
},
  "geometry": {"coordinates":[44.6462,38.7594],"type":"Point"}
}