{
  "type": "Feature",
  "properties": {
    "gn:admin1_code":"32",
    "gn:asciiname":"Mowlan-e Sofla",
    "gn:cc2":"IR",
    "gn:country_code":"IR",
    "gn:dem":1917,
    "gn:feature_class":"P",
    "gn:feature_code":"PPL",
    "gn:name":"Mowl\u0101n-e Sofl\u00e1",
    "gn:population":0,
    "gn:timezone":"Asia/Tehran",
    "iso:country":"IR",
    "name:fas_x_preferred":[
        "\u0645\u064f\u0648\u0644\u0627\u0646\u0650 \u0633\u064f\u0641\u0644\u064e\u0649"
    ],
    "name:fas_x_variant":[
        "\u0633\u0648\u0644\u0627\u0646",
        "Mowl\u0101n-e Sofl\u00e1"
    ],
    "name:und_x_variant":[
        "S\u016bl\u0101n"
    ],
    "wof:name":"Mowlan-e Sofla",
    "wof:placetype":"locality"
},
  "geometry": {"coordinates":[48.35139,37.99389],"type":"Point"}
}