{
  "type": "Feature",
  "properties": {
    "gn:admin1_code":"7.0",
    "gn:asciiname":"Tang-e Chowgan-e `Olya-ye Darreh Shuri",
    "gn:country_code":"IR",
    "gn:dem":846,
    "gn:feature_class":"P",
    "gn:feature_code":"PPL",
    "gn:name":"Tang-e Chowg\u0101n-e \u2018Oly\u0101-ye Darreh Sh\u016br\u012b",
    "gn:population":0,
    "gn:timezone":"Asia/Tehran",
    "iso:country":"IR",
    "name:fas_x_preferred":[
        "Tang-e Chowg\u0101n-e \u2018Oly\u0101-ye Darreh Sh\u016br\u012b"
    ],
    "name:fas_x_variant":[
        "\u062a\u0646\u06af \u0686\u0648\u06af\u0627\u0646 \u0639\u0644\u06cc\u0627 \u062f\u0631\u0647 \u0634\u0648\u0631\u06cc"
    ],
    "wof:name":"Tang-e Chowgan-e `Olya-ye Darreh Shuri",
    "wof:placetype":"locality"
},
  "geometry": {"coordinates":[51.5936,29.78698],"type":"Point"}
}