{
  "type": "Feature",
  "properties": {
    "gn:admin1_code":"35.0",
    "gn:asciiname":"Kaseh Gar Mahalleh",
    "gn:country_code":"IR",
    "gn:dem":-13,
    "gn:feature_class":"P",
    "gn:feature_code":"PPL",
    "gn:name":"K\u0101seh Gar Ma\u1e29alleh",
    "gn:population":0,
    "gn:timezone":"Asia/Tehran",
    "iso:country":"IR",
    "name:ceb_x_preferred":[
        "K\u0101seh Gar Ma\u1e29alleh"
    ],
    "name:fas_x_preferred":[
        "K\u0101seh Gar Ma\u1e29alleh"
    ],
    "name:fas_x_variant":[
        "\u06a9\u0627\u0633\u0647 \u06af\u0631 \u0645\u062d\u0644\u0647",
        "\u06a9\u0627\u0633\u0647\u200c\u06af\u0631\u0645\u062d\u0644\u0647"
    ],
    "name:swe_x_preferred":[
        "K\u0101seh Gar Ma\u1e29alleh"
    ],
    "wof:name":"Kaseh Gar Mahalleh",
    "wof:placetype":"locality"
},
  "geometry": {"coordinates":[50.81842,36.8356],"type":"Point"}
}