{
  "type": "Feature",
  "properties": {
    "gn:admin1_code":"23.0",
    "gn:asciiname":"Mantaqeh-ye Jazestan",
    "gn:country_code":"IR",
    "gn:dem":1071,
    "gn:feature_class":"P",
    "gn:feature_code":"PPL",
    "gn:name":"Man\u0163aqeh-ye J\u0101zest\u0101n",
    "gn:population":0,
    "gn:timezone":"Asia/Tehran",
    "iso:country":"IR",
    "name:fas_x_preferred":[
        "\u062c\u0627\u0632\u0633\u062a\u0627\u0646"
    ],
    "name:fas_x_variant":[
        "J\u0101zest\u0101n",
        "\u0645\u0646\u0637\u0642\u0647 \u062c\u0627\u0632\u0633\u062a\u0627\u0646"
    ],
    "name:und_x_variant":[
        "Man\u0163aqeh-ye J\u0101zest\u0101n"
    ],
    "wof:name":"Mantaqeh-ye Jazestan",
    "wof:placetype":"locality"
},
  "geometry": {"coordinates":[48.6845,33.1654],"type":"Point"}
}