{
  "type": "Feature",
  "properties": {
    "gn:admin1_code":"32",
    "gn:asciiname":"Aghcheh Kohol",
    "gn:country_code":"IR",
    "gn:dem":1906,
    "gn:feature_class":"P",
    "gn:feature_code":"PPL",
    "gn:name":"\u0100ghcheh Kohol",
    "gn:population":0,
    "gn:timezone":"Asia/Tehran",
    "iso:country":"IR",
    "name:fas_x_preferred":[
        "\u0622\u063a\u0686\u0647 \u06a9\u0647\u0644"
    ],
    "name:fas_x_variant":[
        "\u0100ghcheh Kohol",
        "\u0622\u063a\u062c\u0647 \u06a9\u0647\u0644",
        "\u0622\u063a\u0686\u0647\u200c\u06a9\u0647\u0644"
    ],
    "name:msa_x_preferred":[
        "Aghcheh Kohol"
    ],
    "name:und_x_variant":[
        "\u0100ghcheh Kahal",
        "\u0100ghjeh Kohol"
    ],
    "wof:name":"Aghcheh Kohol",
    "wof:placetype":"locality"
},
  "geometry": {"coordinates":[48.30638,37.89143],"type":"Point"}
}