{
  "type": "Feature",
  "properties": {
    "gn:admin1_code":"15.0",
    "gn:asciiname":"Gonjeh",
    "gn:country_code":"IR",
    "gn:dem":103,
    "gn:feature_class":"P",
    "gn:feature_code":"PPL",
    "gn:name":"Gonjeh",
    "gn:population":0,
    "gn:timezone":"Asia/Tehran",
    "iso:country":"IR",
    "name:fas_x_preferred":[
        "\u06af\u0646\u062c\u0647"
    ],
    "name:und_x_variant":[
        "Konjeh",
        "Gonjeh"
    ],
    "wof:name":"Gonjeh",
    "wof:placetype":"locality"
},
  "geometry": {"coordinates":[48.27242,32.37401],"type":"Point"}
}