{
  "type": "Feature",
  "properties": {
    "gn:admin1_code":"32",
    "gn:asciiname":"Dagermandaraq",
    "gn:country_code":"IR",
    "gn:dem":1325,
    "gn:feature_class":"P",
    "gn:feature_code":"PPL",
    "gn:name":"Dagerm\u0101ndaraq",
    "gn:population":0,
    "gn:timezone":"Asia/Tehran",
    "iso:country":"IR",
    "name:azb_x_preferred":[
        "\u062f\u0647\u200c\u06cc\u06cc\u0631\u0645\u0627\u0646 \u062f\u0631\u0647(\u0646\u0645\u06cc\u0646)"
    ],
    "name:ceb_x_preferred":[
        "Dagerm\u0101ndaraq"
    ],
    "name:fas_x_preferred":[
        "\u062f\u06af\u0631\u0645\u0627\u0646\u062f\u0631\u0642"
    ],
    "name:fas_x_variant":[
        "Dagerm\u0101ndaraq"
    ],
    "name:msa_x_preferred":[
        "Dagermandaraq"
    ],
    "name:mzn_x_preferred":[
        "\u062f\u06af\u0631\u0645\u0627\u0646\u062f\u0631\u0642"
    ],
    "name:swe_x_preferred":[
        "Dagerm\u0101ndaraq"
    ],
    "wof:name":"Dagermandaraq",
    "wof:placetype":"locality"
},
  "geometry": {"coordinates":[48.5482,38.3341],"type":"Point"}
}