{
  "type": "Feature",
  "properties": {
    "gn:admin1_code":"15",
    "gn:asciiname":"Shahrak-e Motahhari",
    "gn:country_code":"IR",
    "gn:dem":89,
    "gn:feature_class":"P",
    "gn:feature_code":"PPL",
    "gn:name":"Shahrak-e Mo\u0163ahhar\u012b",
    "gn:population":0,
    "gn:timezone":"Asia/Tehran",
    "iso:country":"IR",
    "name:fas_x_preferred":[
        "Shahrak-e \u0100yatoll\u0101h Montaz\u0327er\u012b"
    ],
    "name:fas_x_variant":[
        "\u0634\u0647\u0631\u06a9 \u0645\u0637\u0647\u0631\u06cc",
        "\u0632\u0631\u0627\u0639\u06cc \u0634\u0648\u0634",
        "\u0634\u0647\u0631\u06a9 \u0648\u062d\u062f\u062a",
        "\u0634\u0647\u0631\u06a9 \u0634\u0647\u06cc\u062f \u0645\u062d\u0645\u062f \u0645\u0646\u062a\u0638\u0631\u06cc"
    ],
    "name:und_x_variant":[
        "Shahrak-e Mo\u0163ahhar\u012b",
        "Qal\u2018eh-ye Rob Kov\u012bkh",
        "Kov\u012bkh",
        "Shahrak-e \u0100yatoll\u0101h Mo\u0163ahhar\u012b",
        "Zer\u0101\u2018\u012b-ye Sh\u016bsh",
        "Shahrak-e Va\u1e29dat",
        "Shahrak-e Shah\u012bd Mo\u1e29ammad Montaz\u0327er\u012b"
    ],
    "wof:name":"Shahrak-e Motahhari",
    "wof:placetype":"locality"
},
  "geometry": {"coordinates":[48.3841,32.26908],"type":"Point"}
}