{
  "type": "Feature",
  "properties": {
    "gn:admin1_code":"4.0",
    "gn:asciiname":"Lagharzehi",
    "gn:country_code":"IR",
    "gn:dem":268,
    "gn:feature_class":"P",
    "gn:feature_code":"PPL",
    "gn:name":"L\u0101gharzeh\u012b",
    "gn:population":0,
    "gn:timezone":"Asia/Tehran",
    "iso:country":"IR",
    "name:fas_x_preferred":[
        "L\u0101gharzeh\u012b"
    ],
    "wof:name":"Lagharzehi",
    "wof:placetype":"locality"
},
  "geometry": {"coordinates":[61.01667,25.45],"type":"Point"}
}