{
  "type": "Feature",
  "properties": {
    "gn:admin1_code":"37",
    "gn:asciiname":"Qarah Tappeh-ye Sheykh",
    "gn:country_code":"IR",
    "gn:dem":151,
    "gn:feature_class":"P",
    "gn:feature_code":"PPL",
    "gn:name":"Qarah Tappeh-ye Sheykh",
    "gn:population":0,
    "gn:timezone":"Asia/Tehran",
    "iso:country":"IR",
    "name:fas_x_preferred":[
        "\u0642\u0631\u0647 \u062a\u067e\u0647 \u0634\u06cc\u062e"
    ],
    "name:und_x_variant":[
        "Qareh Tappeh-ye Sheykh",
        "Qarah Tappeh-ye Sheykh"
    ],
    "wof:name":"Qarah Tappeh-ye Sheykh",
    "wof:placetype":"locality"
},
  "geometry": {"coordinates":[55.46769000000001,37.47145],"type":"Point"}
}