{
  "type": "Feature",
  "properties": {
    "gn:admin1_code":"42",
    "gn:asciiname":"`Aliabad",
    "gn:country_code":"IR",
    "gn:dem":1172,
    "gn:feature_class":"P",
    "gn:feature_code":"PPL",
    "gn:name":"\u2018Al\u012b\u0101b\u0101d",
    "gn:population":0,
    "gn:timezone":"Asia/Tehran",
    "iso:country":"IR",
    "name:deu_x_preferred":[
        "Aliabad-e Shahid"
    ],
    "name:fas_x_preferred":[
        "\u2018Al\u012b\u0101b\u0101d-e Sh\u0101hm\u012br"
    ],
    "name:fas_x_variant":[
        "\u0639\u0644\u06cc \u0622\u0628\u0627\u062f",
        "\u0639\u0644\u06cc \u0622\u0628\u0627\u062f \u0634\u0647\u06cc\u062f",
        "\u0639\u0644\u06cc\u200c\u0622\u0628\u0627\u062f \u0634\u0647\u06cc\u062f"
    ],
    "name:und_x_variant":[
        "\u2018Al\u012b\u0101b\u0101d",
        "\u2018Al\u012b\u0101b\u0101d-e Shah\u012bd"
    ],
    "wof:name":"`Aliabad",
    "wof:placetype":"locality"
},
  "geometry": {"coordinates":[58.87622,36.10603],"type":"Point"}
}