{
  "type": "Feature",
  "properties": {
    "gn:admin1_code":"15",
    "gn:asciiname":"Dabiyeh",
    "gn:country_code":"IR",
    "gn:dem":9,
    "gn:feature_class":"P",
    "gn:feature_code":"PPL",
    "gn:name":"Dab\u012byeh",
    "gn:population":0,
    "gn:timezone":"Asia/Tehran",
    "iso:country":"IR",
    "name:fas_x_preferred":[
        "\u062f\u0628\u06cc\u0647"
    ],
    "name:fas_x_variant":[
        "Dab\u012byeh"
    ],
    "wof:name":"Dabiyeh",
    "wof:placetype":"locality"
},
  "geometry": {"coordinates":[47.9154,31.7491],"type":"Point"}
}