{
  "type": "Feature",
  "properties": {
    "gn:admin1_code":"33",
    "gn:asciiname":"Alilu",
    "gn:country_code":"IR",
    "gn:dem":1773,
    "gn:feature_class":"P",
    "gn:feature_code":"PPL",
    "gn:name":"\u0100l\u012bl\u016b",
    "gn:population":0,
    "gn:timezone":"Asia/Tehran",
    "iso:country":"IR",
    "name:fas_x_preferred":[
        "\u0100lel\u016b"
    ],
    "name:fas_x_variant":[
        "\u0100l\u012bl\u016b",
        "\u0622\u0644\u06cc\u0644\u0648",
        "\u0622\u0644\u0644\u0648"
    ],
    "name:und_x_variant":[
        "\u0622\u0644\u06cc\u0644\u0648"
    ],
    "wof:name":"Alilu",
    "wof:placetype":"locality"
},
  "geometry": {"coordinates":[46.6064,37.1973],"type":"Point"}
}