{
  "type": "Feature",
  "properties": {
    "gn:admin1_code":"29",
    "gn:asciiname":"Vakilabad",
    "gn:country_code":"IR",
    "gn:dem":818,
    "gn:feature_class":"P",
    "gn:feature_code":"PPL",
    "gn:name":"Vak\u012bl\u0101b\u0101d",
    "gn:population":0,
    "gn:timezone":"Asia/Tehran",
    "iso:country":"IR",
    "name:aze_x_preferred":[
        "V\u0259kilabad"
    ],
    "name:fas_x_preferred":[
        "\u0648\u06a9\u06cc\u0644 \u0622\u0628\u0627\u062f"
    ],
    "name:fas_x_variant":[
        "Vak\u012bl\u0101b\u0101d",
        "\u062f\u0647 \u0646\u0648",
        "\u062f\u0647\u0646\u0648 \u0648\u06a9\u06cc\u0644 \u0622\u0628\u0627\u062f"
    ],
    "name:und_x_variant":[
        "Deh Now",
        "Deh-e Now",
        "Dehnow-ye Vak\u012bl\u0101b\u0101d"
    ],
    "wof:name":"Vakilabad",
    "wof:placetype":"locality"
},
  "geometry": {"coordinates":[58.61697,28.98172000000001],"type":"Point"}
}