{
  "type": "Feature",
  "properties": {
    "gn:admin1_code":"37",
    "gn:asciiname":"Geri Dowji",
    "gn:country_code":"IR",
    "gn:dem":15,
    "gn:feature_class":"P",
    "gn:feature_code":"PPL",
    "gn:name":"Ger\u012b Dowj\u012b",
    "gn:population":0,
    "gn:timezone":"Asia/Tehran",
    "iso:country":"IR",
    "name:ara_x_preferred":[
        "\u063a\u0631\u064a \u062f\u0648\u062c\u064a"
    ],
    "name:fas_x_preferred":[
        "Ger\u012b"
    ],
    "name:fas_x_variant":[
        "\u06af\u0631\u06cc",
        "\u06af\u0631\u06cc \u062f\u0648\u062c\u06cc",
        "\u06af\u0631\u06cc\u200c\u062f\u0648\u062c\u06cc"
    ],
    "name:msa_x_preferred":[
        "Geri Doveji"
    ],
    "name:und_x_variant":[
        "Ger\u012b Dovej\u012b",
        "Ger\u012b Dowj\u012b"
    ],
    "wof:name":"Geri Dowji",
    "wof:placetype":"locality"
},
  "geometry": {"coordinates":[54.72637,37.08009000000001],"type":"Point"}
}