{
  "type": "Feature",
  "properties": {
    "gn:admin1_code":"33",
    "gn:asciiname":"Dulan",
    "gn:country_code":"IR",
    "gn:dem":1510,
    "gn:feature_class":"P",
    "gn:feature_code":"PPL",
    "gn:name":"D\u016bl\u0101n",
    "gn:population":0,
    "gn:timezone":"Asia/Tehran",
    "iso:country":"IR",
    "name:fas_x_preferred":[
        "\u062f\u0648\u0644\u0627\u0646"
    ],
    "name:fas_x_variant":[
        "D\u016bl\u0101n"
    ],
    "name:fra_x_preferred":[
        "Dulan"
    ],
    "name:heb_x_preferred":[
        "\u05d3\u05d5\u05dc\u05d0\u05df"
    ],
    "name:hin_x_preferred":[
        "\u0921\u0941\u0932\u093e\u0928"
    ],
    "name:hun_x_preferred":[
        "Dulan"
    ],
    "name:ind_x_preferred":[
        "Dulan"
    ],
    "name:ita_x_preferred":[
        "Dulan"
    ],
    "name:jpn_x_preferred":[
        "\u90fd\u862d"
    ],
    "name:kor_x_preferred":[
        "\ub458\ub780"
    ],
    "name:msa_x_preferred":[
        "Dulan"
    ],
    "name:nld_x_preferred":[
        "Dulan"
    ],
    "name:pol_x_preferred":[
        "Dulan"
    ],
    "name:por_x_preferred":[
        "Dulan"
    ],
    "name:rus_x_preferred":[
        "\u0414\u0443\u043b\u0430\u043d"
    ],
    "name:swe_x_preferred":[
        "Dulan"
    ],
    "name:tur_x_preferred":[
        "Dulan"
    ],
    "name:ukr_x_preferred":[
        "\u0414\u0443\u043b\u0430\u043d\u044c"
    ],
    "name:urd_x_preferred":[
        "\u062f\u0648\u0644\u0627\u0646"
    ],
    "name:vie_x_preferred":[
        "\u0110\u00f4 Lan"
    ],
    "name:zho_cn_x_preferred":[
        "\u90fd\u5170"
    ],
    "name:zho_tw_x_preferred":[
        "\u90fd\u862d"
    ],
    "wof:name":"Dulan",
    "wof:placetype":"locality"
},
  "geometry": {"coordinates":[47.13559,38.95848],"type":"Point"}
}