{
  "type": "Feature",
  "properties": {
    "gn:admin1_code":"33",
    "gn:asciiname":"Dulan",
    "gn:country_code":"IR",
    "gn:dem":1510,
    "gn:feature_class":"P",
    "gn:feature_code":"PPL",
    "gn:name":"D\u016bl\u0101n",
    "gn:population":0,
    "gn:timezone":"Asia/Tehran",
    "iso:country":"IR",
    "name:fas_x_preferred":[
        "D\u016bl\u0101n"
    ],
    "name:fas_x_variant":[
        "\u062f\u0648\u0644\u0627\u0646"
    ],
    "wof:name":"Dulan",
    "wof:placetype":"locality"
},
  "geometry": {"coordinates":[47.13559,38.95848],"type":"Point"}
}