{
  "type": "Feature",
  "properties": {
    "gn:admin1_code":"4.0",
    "gn:asciiname":"Hajj `Abdollah",
    "gn:country_code":"IR",
    "gn:dem":484,
    "gn:feature_class":"P",
    "gn:feature_code":"PPL",
    "gn:name":"\u1e28\u0101jj \u2018Abdoll\u0101h",
    "gn:population":0,
    "gn:timezone":"Asia/Tehran",
    "iso:country":"IR",
    "name:fas_x_preferred":[
        "\u062d\u0627\u062c \u0639\u0628\u062f\u0627\u0644\u0644\u0647"
    ],
    "name:fas_x_variant":[
        "\u1e28\u0101jj \u2018Abdoll\u0101h"
    ],
    "wof:name":"Hajj `Abdollah",
    "wof:placetype":"locality"
},
  "geometry": {"coordinates":[61.7408,31.0936],"type":"Point"}
}