{
  "type": "Feature",
  "properties": {
    "gn:admin1_code":"16.0",
    "gn:asciiname":"Kupich-e Sofla",
    "gn:country_code":"IR",
    "gn:dem":1461,
    "gn:feature_class":"P",
    "gn:feature_code":"PPL",
    "gn:name":"K\u016bp\u012bch-e Sofl\u00e1",
    "gn:population":0,
    "gn:timezone":"Asia/Tehran",
    "iso:country":"IR",
    "name:ara_x_preferred":[
        "\u0643\u0648\u0628\u064a\u062a\u0634 \u0627\u0644\u0633\u0641\u0644\u064a"
    ],
    "name:ceb_x_preferred":[
        "K\u016bp\u012bch-e Sofl\u00e1"
    ],
    "name:ckb_x_preferred":[
        "\u06a9\u06d5\u0648\u067e\u06ce\u0686 \u062e\u0648\u0627\u0631\u0648\u0648"
    ],
    "name:fas_x_preferred":[
        "\u06a9\u0648\u067e\u06cc\u0686 \u0633\u0641\u0644\u06cc"
    ],
    "name:fas_x_variant":[
        "K\u016bp\u012bch-e Sofl\u00e1"
    ],
    "name:swe_x_preferred":[
        "K\u016bp\u012bch-e Sofl\u00e1"
    ],
    "wof:name":"Kupich-e Sofla",
    "wof:placetype":"locality"
},
  "geometry": {"coordinates":[45.8448,36.0169],"type":"Point"}
}