{
  "type": "Feature",
  "properties": {
    "gn:admin1_code":"43",
    "gn:asciiname":"Khvosh-e Pa'in",
    "gn:country_code":"IR",
    "gn:dem":1101,
    "gn:feature_class":"P",
    "gn:feature_code":"PPL",
    "gn:name":"Khvosh-e P\u0101\u2019\u012bn",
    "gn:population":0,
    "gn:timezone":"Asia/Tehran",
    "iso:country":"IR",
    "name:fas_x_preferred":[
        "Khvosh-e P\u0101\u2019\u012bn"
    ],
    "name:fas_x_variant":[
        "\u062e\u0648\u0634 \u067e\u0627\u0626\u06cc\u0646"
    ],
    "name:und_x_variant":[
        "Khowsh P\u0101\u2019\u012bn",
        "K\u016bshk P\u0101\u012bn",
        "K\u016bshk-e P\u0101\u2019\u012bn",
        "K\u016bshk"
    ],
    "wof:name":"Khvosh-e Pa'in",
    "wof:placetype":"locality"
},
  "geometry": {"coordinates":[57.33373,37.12523],"type":"Point"}
}