{
  "type": "Feature",
  "properties": {
    "gn:admin1_code":"16",
    "gn:asciiname":"Kurdarreh",
    "gn:country_code":"IR",
    "gn:dem":1678,
    "gn:feature_class":"P",
    "gn:feature_code":"PPL",
    "gn:name":"K\u016brdarreh",
    "gn:population":0,
    "gn:timezone":"Asia/Tehran",
    "iso:country":"IR",
    "name:ceb_x_preferred":[
        "K\u016brdarreh"
    ],
    "name:ckb_x_preferred":[
        "\u06a9\u06c6\u0631\u06cc\u06d5\u0631\u06d5"
    ],
    "name:fas_x_preferred":[
        "\u0643\u0648\u0631\u062f\u0631\u0651\u0647"
    ],
    "name:fas_x_variant":[
        "\u0643\u0648\u0631\u0650\u0647 \u062f\u0631\u0647",
        "K\u016brdarreh",
        "\u06a9\u0648\u0631\u0647\u200c\u062f\u0631\u0647"
    ],
    "name:swe_x_preferred":[
        "K\u016brdarreh"
    ],
    "name:und_x_variant":[
        "Kh\u016breh Darreh",
        "K\u016breh Darreh"
    ],
    "wof:name":"Kurdarreh",
    "wof:placetype":"locality"
},
  "geometry": {"coordinates":[46.4311,35.4634],"type":"Point"}
}