{
  "type": "Feature",
  "properties": {
    "gn:admin1_code":"5",
    "gn:asciiname":"Sar Asiab",
    "gn:country_code":"IR",
    "gn:dem":1673,
    "gn:feature_class":"P",
    "gn:feature_code":"PPL",
    "gn:name":"Sar \u0100s\u012b\u0101b",
    "gn:population":0,
    "gn:timezone":"Asia/Tehran",
    "iso:country":"IR",
    "name:fas_x_preferred":[
        "Sar \u0100s\u012b\u0101b"
    ],
    "name:fas_x_variant":[
        "\u0633\u0631 \u0622\u0633\u064a\u0627\u0628",
        "\u0633\u0631\u0622\u0633\u06cc\u0627\u0628"
    ],
    "wof:name":"Sar Asiab",
    "wof:placetype":"locality"
},
  "geometry": {"coordinates":[51.31602,30.91641],"type":"Point"}
}