{
  "type": "Feature",
  "properties": {
    "gn:admin1_code":"33",
    "gn:asciiname":"Kargan-e Qadim",
    "gn:country_code":"IR",
    "gn:dem":1950,
    "gn:feature_class":"P",
    "gn:feature_code":"PPL",
    "gn:name":"Karg\u0101n-e Qad\u012bm",
    "gn:population":0,
    "gn:timezone":"Asia/Tehran",
    "iso:country":"IR",
    "name:ara_x_preferred":[
        "\u0643\u0631\u063a\u0627\u0646 \u0627\u0644\u0642\u062f\u064a\u0645"
    ],
    "name:ceb_x_preferred":[
        "Karg\u0101n-e Qad\u012bm"
    ],
    "name:fas_x_preferred":[
        "\u06a9\u0631\u06af\u0627\u0646"
    ],
    "name:fas_x_variant":[
        "Karg\u0101n-e Qad\u012bm",
        "Karg\u0101n",
        "\u06a9\u0631\u06af\u0627\u0646 \u0642\u062f\u06cc\u0645"
    ],
    "name:msa_x_preferred":[
        "Kargan-e Qadim"
    ],
    "name:swe_x_preferred":[
        "Karg\u0101n-e Qad\u012bm"
    ],
    "name:tur_x_preferred":[
        "Kergan"
    ],
    "name:und_x_variant":[
        "Karkan",
        "Gorg\u0101n"
    ],
    "wof:name":"Kargan-e Qadim",
    "wof:placetype":"locality"
},
  "geometry": {"coordinates":[46.7055,37.8608],"type":"Point"}
}