{
  "type": "Feature",
  "properties": {
    "gn:admin1_code":"40",
    "gn:asciiname":"Haznak",
    "gn:country_code":"IR",
    "gn:dem":2239,
    "gn:feature_class":"P",
    "gn:feature_code":"PPL",
    "gn:name":"Haznak",
    "gn:population":0,
    "gn:timezone":"Asia/Tehran",
    "iso:country":"IR",
    "name:fas_x_preferred":[
        "\u0647\u064e\u0632\u0646\u064e\u0643"
    ],
    "wof:name":"Haznak",
    "wof:placetype":"locality"
},
  "geometry": {"coordinates":[53.86666999999999,31.73333],"type":"Point"}
}