{
  "type": "Feature",
  "properties": {
    "gn:admin1_code":"22",
    "gn:asciiname":"Rusta-ye Soheyli",
    "gn:country_code":"IR",
    "gn:dem":14,
    "gn:feature_class":"P",
    "gn:feature_code":"PPL",
    "gn:name":"R\u016bst\u0101-ye Soheyl\u012b",
    "gn:population":0,
    "gn:timezone":"Asia/Tehran",
    "iso:country":"IR",
    "name:ara_x_preferred":[
        "\u0633\u0647\u064a\u0644\u064a"
    ],
    "name:fas_x_preferred":[
        "\u0633\u0647\u064a\u0644\u06cc"
    ],
    "name:fas_x_variant":[
        "Soheyl\u012b",
        "\u0631\u0648\u0633\u062a\u0627\u06cc \u0633\u0647\u06cc\u0644\u06cc",
        "\u0633\u0647\u06cc\u0644\u06cc"
    ],
    "name:msa_x_preferred":[
        "Soheyli"
    ],
    "name:und_x_variant":[
        "Suhaili",
        "R\u016bst\u0101-ye Soheyl\u012b"
    ],
    "wof:name":"Rusta-ye Soheyli",
    "wof:placetype":"locality"
},
  "geometry": {"coordinates":[51.0184,29.2358],"type":"Point"}
}