{
  "type": "Feature",
  "properties": {
    "gn:admin1_code":"1",
    "gn:asciiname":"Khederabad",
    "gn:country_code":"IR",
    "gn:dem":1226,
    "gn:feature_class":"P",
    "gn:feature_code":"PPL",
    "gn:name":"Kheder\u0101b\u0101d",
    "gn:population":0,
    "gn:timezone":"Asia/Tehran",
    "iso:country":"IR",
    "name:fas_x_preferred":[
        "\u062e\u062f\u0631 \u0622\u0628\u0627\u062f"
    ],
    "name:fas_x_variant":[
        "Kheder\u0101b\u0101d R\u016by\u0101n",
        "Kheder\u0101b\u0101d"
    ],
    "name:und_x_variant":[
        "Khedr \u0100b\u0101d"
    ],
    "wof:name":"Khederabad",
    "wof:placetype":"locality"
},
  "geometry": {"coordinates":[45.3505,36.4389],"type":"Point"}
}