{
  "type": "Feature",
  "properties": {
    "gn:admin1_code":"43",
    "gn:asciiname":"Aba-Kurban",
    "gn:country_code":"IR",
    "gn:dem":875,
    "gn:feature_class":"P",
    "gn:feature_code":"PPL",
    "gn:name":"Aba-Kurban",
    "gn:population":0,
    "gn:timezone":"Asia/Tehran",
    "iso:country":"IR",
    "wof:name":"Aba-Kurban",
    "wof:placetype":"locality"
},
  "geometry": {"coordinates":[56.61666999999999,38.18333],"type":"Point"}
}