{
  "type": "Feature",
  "properties": {
    "gn:admin1_code":"5.0",
    "gn:asciiname":"Tall-e Boland",
    "gn:country_code":"IR",
    "gn:dem":1395,
    "gn:feature_class":"P",
    "gn:feature_code":"PPL",
    "gn:name":"Tall-e Boland",
    "gn:population":0,
    "gn:timezone":"Asia/Tehran",
    "iso:country":"IR",
    "name:fas_x_preferred":[
        "\u062a\u0644 \u0628\u0644\u0646\u062f"
    ],
    "wof:name":"Tall-e Boland",
    "wof:placetype":"locality"
},
  "geometry": {"coordinates":[50.58129,31.37843],"type":"Point"}
}