{
  "type": "Feature",
  "properties": {
    "gn:admin1_code":"8.0",
    "gn:asciiname":"Tirin",
    "gn:country_code":"IR",
    "gn:dem":1447,
    "gn:feature_class":"P",
    "gn:feature_code":"PPL",
    "gn:name":"T\u012br\u012bn",
    "gn:population":0,
    "gn:timezone":"Asia/Tehran",
    "iso:country":"IR",
    "name:fas_x_preferred":[
        "\u062a\u06cc\u0631\u06cc\u0646"
    ],
    "name:fas_x_variant":[
        "\u062a\u0645\u0631\u06cc\u0646"
    ],
    "name:und_x_variant":[
        "T\u012br\u012bn",
        "Tamr\u012bn"
    ],
    "wof:name":"Tirin",
    "wof:placetype":"locality"
},
  "geometry": {"coordinates":[49.97487,37.01807],"type":"Point"}
}