{
  "type": "Feature",
  "properties": {
    "gn:admin1_code":"1.0",
    "gn:asciiname":"Kani Kowtar",
    "gn:country_code":"IR",
    "gn:dem":1646,
    "gn:feature_class":"P",
    "gn:feature_code":"PPL",
    "gn:name":"K\u0101n\u012b Kowtar",
    "gn:population":0,
    "gn:timezone":"Asia/Tehran",
    "iso:country":"IR",
    "name:azb_x_preferred":[
        "\u06a9\u0627\u0646\u06cc \u06a9\u0648\u062a\u0631(\u0633\u0648\u06cc\u0648\u0642\u200c\u0628\u0648\u0644\u0627\u0642)"
    ],
    "name:ceb_x_preferred":[
        "K\u0101n\u012b Kowtar"
    ],
    "name:ckb_x_preferred":[
        "\u06a9\u0627\u0646\u06cc \u06a9\u06d5\u0648\u062a\u06d5\u0631"
    ],
    "name:fas_x_preferred":[
        "\u06a9\u0627\u0646\u06cc \u06a9\u0648\u062a\u0631"
    ],
    "name:fas_x_variant":[
        "\u0643\u0627\u0646\u06cc \u0643\u064f\u0648\u062a\u064e\u0631",
        "K\u0101n\u012b Kowtar",
        "\u06a9\u0627\u0646\u06cc\u200c\u06a9\u0648\u062a\u0631"
    ],
    "name:msa_x_preferred":[
        "Kani Kowtar"
    ],
    "name:swe_x_preferred":[
        "K\u0101n\u012b Kowtar"
    ],
    "wof:name":"Kani Kowtar",
    "wof:placetype":"locality"
},
  "geometry": {"coordinates":[45.9887,36.7043],"type":"Point"}
}