{
  "type": "Feature",
  "properties": {
    "gn:admin1_code":"1",
    "gn:asciiname":"Tazeh Kand-e Qaterchi",
    "gn:country_code":"IR",
    "gn:dem":1359,
    "gn:feature_class":"P",
    "gn:feature_code":"PPL",
    "gn:name":"T\u0101zeh Kand-e Q\u0101\u0163erch\u012b",
    "gn:population":0,
    "gn:timezone":"Asia/Tehran",
    "iso:country":"IR",
    "name:fas_x_preferred":[
        "\u062a\u0627\u0632\u0650\u0647 \u0643\u064e\u0646\u062f\u0650 \u0642\u0627\u0637\u0650\u0631\u0686\u06cc"
    ],
    "name:fas_x_variant":[
        "\u062a\u0627\u0632\u0647 \u06a9\u0646\u062f \u0642\u0627\u0637\u0631\u0686\u06cc",
        "T\u0101zeh Kand-e Q\u0101\u0163erch\u012b"
    ],
    "wof:name":"Tazeh Kand-e Qaterchi",
    "wof:placetype":"locality"
},
  "geometry": {"coordinates":[44.9751,37.6628],"type":"Point"}
}