{
  "type": "Feature",
  "properties": {
    "gn:admin1_code":"7",
    "gn:asciiname":"Gerdkhun",
    "gn:country_code":"IR",
    "gn:dem":1479,
    "gn:feature_class":"P",
    "gn:feature_code":"PPL",
    "gn:name":"Gerdkh\u016bn",
    "gn:population":0,
    "gn:timezone":"Asia/Tehran",
    "iso:country":"IR",
    "name:fas_x_preferred":[
        "\u06af\u0644 \u062e\u0648\u0646"
    ],
    "name:fas_x_variant":[
        "Gol Kh\u016bn",
        "\u06af\u0631\u062f\u062e\u0648\u0646"
    ],
    "name:und_x_variant":[
        "Gel Kh\u016bn",
        "Gerkh\u016bn-e Sh\u016bb\u0101z\u0101r",
        "Gerdkh\u016bn"
    ],
    "wof:name":"Gerdkhun",
    "wof:placetype":"locality"
},
  "geometry": {"coordinates":[52.6584,29.5426],"type":"Point"}
}