{
  "type": "Feature",
  "properties": {
    "gn:admin1_code":"41",
    "gn:asciiname":"Mehdiabad",
    "gn:country_code":"IR",
    "gn:dem":2014,
    "gn:feature_class":"P",
    "gn:feature_code":"PPL",
    "gn:name":"Mehd\u012b\u0101b\u0101d",
    "gn:population":0,
    "gn:timezone":"Asia/Tehran",
    "iso:country":"IR",
    "name:fas_x_preferred":[
        "Mehd\u012b\u0101b\u0101d"
    ],
    "wof:name":"Mehdiabad",
    "wof:placetype":"locality"
},
  "geometry": {"coordinates":[59.87361,32.83583],"type":"Point"}
}