{
  "type": "Feature",
  "properties": {
    "gn:admin1_code":"8",
    "gn:asciiname":"Kord Mahalleh",
    "gn:country_code":"IR",
    "gn:dem":87,
    "gn:feature_class":"P",
    "gn:feature_code":"PPL",
    "gn:name":"Kord Ma\u1e29alleh",
    "gn:population":0,
    "gn:timezone":"Asia/Tehran",
    "iso:country":"IR",
    "name:fas_x_preferred":[
        "\u06a9\u0631\u062f \u0645\u062d\u0644\u0647"
    ],
    "name:fas_x_variant":[
        "Kord Ma\u1e29alleh",
        "\u06a9\u0631\u062f\u0645\u062d\u0644\u0647"
    ],
    "name:msa_x_preferred":[
        "Kord Mahalleh"
    ],
    "name:ukr_x_preferred":[
        "\u041a\u043e\u0440\u0434-\u041c\u0430\u0445\u0430\u043b\u0435"
    ],
    "wof:name":"Kord Mahalleh",
    "wof:placetype":"locality"
},
  "geometry": {"coordinates":[49.28212,37.16866],"type":"Point"}
}