{
  "type": "Feature",
  "properties": {
    "gn:admin1_code":"26",
    "gn:asciiname":"Kushkak-e Bala",
    "gn:country_code":"IR",
    "gn:dem":1168,
    "gn:feature_class":"P",
    "gn:feature_code":"PPL",
    "gn:name":"K\u016bshkak-e B\u0101l\u0101",
    "gn:population":0,
    "gn:timezone":"Asia/Tehran",
    "iso:country":"IR",
    "name:fas_x_preferred":[
        "\u0643\u0648\u0634\u0643\u06a9"
    ],
    "name:fas_x_variant":[
        "K\u016bshkak",
        "\u06a9\u0648\u0634\u06a9\u06a9 \u0628\u0627\u0644\u0627"
    ],
    "name:und_x_variant":[
        "K\u016bshkak-e B\u0101l\u0101"
    ],
    "wof:name":"Kushkak-e Bala",
    "wof:placetype":"locality"
},
  "geometry": {"coordinates":[50.9096,35.6871],"type":"Point"}
}