{
  "type": "Feature",
  "properties": {
    "gn:admin1_code":"28",
    "gn:asciiname":"Soheyl Chah Kharbozeh",
    "gn:country_code":"IR",
    "gn:dem":1446,
    "gn:feature_class":"P",
    "gn:feature_code":"PPL",
    "gn:name":"Soheyl Ch\u0101h Kharbozeh",
    "gn:population":0,
    "gn:timezone":"Asia/Tehran",
    "iso:country":"IR",
    "name:fas_x_preferred":[
        "\u0633\u0647\u06cc\u0644 \u0686\u0627\u0647 \u062e\u0631\u0628\u0632\u0647"
    ],
    "name:fas_x_variant":[
        "Soheyl Ch\u0101h Kharbozeh"
    ],
    "wof:name":"Soheyl Chah Kharbozeh",
    "wof:placetype":"locality"
},
  "geometry": {"coordinates":[53.7968,33.4349],"type":"Point"}
}