{
  "type": "Feature",
  "properties": {
    "gn:admin1_code":"9",
    "gn:asciiname":"Khigan",
    "gn:country_code":"IR",
    "gn:dem":1768,
    "gn:feature_class":"P",
    "gn:feature_code":"PPL",
    "gn:name":"Kh\u012bg\u0101n",
    "gn:population":0,
    "gn:timezone":"Asia/Tehran",
    "iso:country":"IR",
    "name:fas_x_preferred":[
        "\u062e\u06cc\u06af\u0627\u0646"
    ],
    "name:fas_x_variant":[
        "\u062e\u0650\u06af\u064e\u0646",
        "\u062e\u0650\u064a\u06af\u0627\u0646",
        "Kh\u012bg\u0101n"
    ],
    "name:und_x_variant":[
        "Khegan",
        "Kheyg\u0101n"
    ],
    "wof:name":"Khigan",
    "wof:placetype":"locality"
},
  "geometry": {"coordinates":[49.03201,35.31769],"type":"Point"}
}