{
  "type": "Feature",
  "properties": {
    "gn:admin1_code":"1.0",
    "gn:asciiname":"Bardpahn",
    "gn:country_code":"IR",
    "gn:dem":1805,
    "gn:feature_class":"P",
    "gn:feature_code":"PPL",
    "gn:name":"Bardpahn",
    "gn:population":0,
    "gn:timezone":"Asia/Tehran",
    "iso:country":"IR",
    "name:fas_x_preferred":[
        "\u0628\u0631\u062f\u067e\u0647\u0646"
    ],
    "name:und_x_variant":[
        "Bardeh Pahn",
        "Bardpahn"
    ],
    "wof:name":"Bardpahn",
    "wof:placetype":"locality"
},
  "geometry": {"coordinates":[45.3597,36.1917],"type":"Point"}
}