{
  "type": "Feature",
  "properties": {
    "gn:admin1_code":"25",
    "gn:asciiname":"Tash-e `Olya",
    "gn:country_code":"IR",
    "gn:dem":2273,
    "gn:feature_class":"P",
    "gn:feature_code":"PPL",
    "gn:name":"T\u0101sh-e \u2018Oly\u0101",
    "gn:population":0,
    "gn:timezone":"Asia/Tehran",
    "iso:country":"IR",
    "name:fas_x_preferred":[
        "T\u0101sh-e \u2018Oly\u0101"
    ],
    "name:fas_x_variant":[
        "\u062a\u0627\u0634\u0650 \u0628\u0627\u0644\u0627",
        "\u062a\u0627\u0634",
        "\u062a\u0627\u0634 \u0639\u0644\u06cc\u0627",
        "T\u0101sh-e B\u0101l\u0101"
    ],
    "name:und_x_variant":[
        "T\u0101sh"
    ],
    "wof:name":"Tash-e `Olya",
    "wof:placetype":"locality"
},
  "geometry": {"coordinates":[54.67968000000001,36.56574000000001],"type":"Point"}
}