{
  "type": "Feature",
  "properties": {
    "gn:admin1_code":"16.0",
    "gn:asciiname":"Tazehabad-e Majidkhani",
    "gn:country_code":"IR",
    "gn:dem":2000,
    "gn:feature_class":"P",
    "gn:feature_code":"PPL",
    "gn:name":"T\u0101zeh\u0101b\u0101d-e Maj\u012bdkh\u0101n\u012b",
    "gn:population":0,
    "gn:timezone":"Asia/Tehran",
    "iso:country":"IR",
    "name:fas_x_preferred":[
        "\u062a\u0627\u0632\u0650\u0647\u0627\u0628\u0627\u062f\u0650 \u0627\u064e\u0645\u064a\u0646"
    ],
    "name:fas_x_variant":[
        "T\u0101zeh\u0101b\u0101d-e Mo\u1e29ammad-e Am\u012bn",
        "\u062a\u0627\u0632\u0647 \u0622\u0628\u0627\u062f \u0645\u062d\u0645\u0651\u062f \u0627\u0645\u06cc\u0646",
        "T\u0101zeh\u0101b\u0101d-e Am\u012bn",
        "Maj\u012bd Kh\u0101n",
        "\u0645\u062c\u06cc\u062f \u062e\u0627\u0646",
        "T\u0101zeh\u0101b\u0101d-e Maj\u012bdkh\u0101n\u012b",
        "\u062a\u0627\u0632\u0647 \u0622\u0628\u0627\u062f \u0645\u062c\u064a\u062f\u062e\u0627\u0646\u06cc"
    ],
    "name:und_x_variant":[
        "\u0645\u062c\u06cc\u062f \u062e\u0627\u0646"
    ],
    "wof:name":"Tazehabad-e Majidkhani",
    "wof:placetype":"locality"
},
  "geometry": {"coordinates":[46.9232,35.81046],"type":"Point"}
}