{
  "type": "Feature",
  "properties": {
    "gn:admin1_code":"4.0",
    "gn:asciiname":"Aparing",
    "gn:country_code":"IR",
    "gn:dem":603,
    "gn:feature_class":"P",
    "gn:feature_code":"PPLL",
    "gn:name":"\u0100p\u0101r\u012bng",
    "gn:population":0,
    "gn:timezone":"Asia/Tehran",
    "iso:country":"IR",
    "name:fas_x_preferred":[
        "\u0622\u067e\u0627\u0631\u064a\u0646\u06af"
    ],
    "name:und_x_variant":[
        "\u0100p\u0101r\u012bng"
    ],
    "wof:name":"Aparing",
    "wof:placetype":"locality"
},
  "geometry": {"coordinates":[59.57402,26.9093],"type":"Point"}
}