{
  "type": "Feature",
  "properties": {
    "gn:admin1_code":"13",
    "gn:asciiname":"Tazehabad-e `Azizi",
    "gn:country_code":"IR",
    "gn:dem":1604,
    "gn:feature_class":"P",
    "gn:feature_code":"PPL",
    "gn:name":"T\u0101zeh\u0101b\u0101d-e \u2018Az\u012bz\u012b",
    "gn:population":0,
    "gn:timezone":"Asia/Tehran",
    "iso:country":"IR",
    "name:fas_x_preferred":[
        "\u062a\u0627\u0632\u0647 \u0622\u0628\u0627\u062f \u0639\u0632\u064a\u0632\u06cc"
    ],
    "name:fas_x_variant":[
        "T\u0101zeh\u0101b\u0101d-e \u2018Az\u012bz\u012b"
    ],
    "wof:name":"Tazehabad-e `Azizi",
    "wof:placetype":"locality"
},
  "geometry": {"coordinates":[46.3473,34.7113],"type":"Point"}
}