{
  "type": "Feature",
  "properties": {
    "gn:admin1_code":"1.0",
    "gn:asciiname":"Shivehju",
    "gn:country_code":"IR",
    "gn:dem":1283,
    "gn:feature_class":"P",
    "gn:feature_code":"PPL",
    "gn:name":"Sh\u012bvehj\u016b",
    "gn:population":0,
    "gn:timezone":"Asia/Tehran",
    "iso:country":"IR",
    "name:ceb_x_preferred":[
        "Sh\u012bvehj\u016b"
    ],
    "name:ckb_x_preferred":[
        "\u0634\u06cc\u0648\u06d5\u062c\u06c6"
    ],
    "name:fas_x_preferred":[
        "\u0634\u06cc\u0648\u0647 \u062c\u0648"
    ],
    "name:fas_x_variant":[
        "Sh\u012bvehj\u016b",
        "\u0634\u06cc\u0648\u0647\u200c\u062c\u0648"
    ],
    "name:kur_x_preferred":[
        "\u015e\u00eeweco"
    ],
    "name:msa_x_preferred":[
        "Shivehju"
    ],
    "name:swe_x_preferred":[
        "Sh\u012bvehj\u016b"
    ],
    "wof:name":"Shivehju",
    "wof:placetype":"locality"
},
  "geometry": {"coordinates":[45.4855,36.351],"type":"Point"}
}