{
  "type": "Feature",
  "properties": {
    "gn:admin1_code":"33",
    "gn:asciiname":"Hajj Khalil",
    "gn:country_code":"IR",
    "gn:dem":1985,
    "gn:feature_class":"P",
    "gn:feature_code":"PPL",
    "gn:name":"\u1e28\u0101jj Khal\u012bl",
    "gn:population":0,
    "gn:timezone":"Asia/Tehran",
    "iso:country":"IR",
    "name:fas_x_preferred":[
        "\u062d\u0627\u062c\u06cc \u062e\u0644\u064a\u0644"
    ],
    "name:fas_x_variant":[
        "\u1e28\u0101jj\u012b Khal\u012bl",
        "\u062d\u0627\u062c \u062e\u0644\u06cc\u0644"
    ],
    "name:und_x_variant":[
        "\u1e28\u0101jj Khal\u012bl"
    ],
    "wof:name":"Hajj Khalil",
    "wof:placetype":"locality"
},
  "geometry": {"coordinates":[48.03483,37.81578],"type":"Point"}
}