{
  "type": "Feature",
  "properties": {
    "gn:admin1_code":"3",
    "gn:asciiname":"Seyfabad",
    "gn:country_code":"IR",
    "gn:dem":2292,
    "gn:feature_class":"P",
    "gn:feature_code":"PPL",
    "gn:name":"Seyf\u0101b\u0101d",
    "gn:population":0,
    "gn:timezone":"Asia/Tehran",
    "iso:country":"IR",
    "name:fas_x_preferred":[
        "Seyf\u0101b\u0101d"
    ],
    "name:fas_x_variant":[
        "\u0633\u064a\u0641 \u0622\u0628\u0627\u062f"
    ],
    "name:und_x_variant":[
        "\u0633\u064a\u0641 \u0622\u0628\u0627\u062f"
    ],
    "wof:name":"Seyfabad",
    "wof:placetype":"locality"
},
  "geometry": {"coordinates":[50.89932,31.90059],"type":"Point"}
}