{
  "type": "Feature",
  "properties": {
    "gn:admin1_code":"4",
    "gn:asciiname":"Kasrshib",
    "gn:country_code":"IR",
    "gn:dem":911,
    "gn:feature_class":"P",
    "gn:feature_code":"PPL",
    "gn:name":"Kasrsh\u012bb",
    "gn:population":0,
    "gn:timezone":"Asia/Tehran",
    "iso:country":"IR",
    "name:fas_x_preferred":[
        "Kasrsh\u012bb"
    ],
    "name:fas_x_variant":[
        "\u06a9\u0633\u0631\u0634\u06cc\u0628"
    ],
    "wof:name":"Kasrshib",
    "wof:placetype":"locality"
},
  "geometry": {"coordinates":[60.83013,26.42415],"type":"Point"}
}