{
  "type": "Feature",
  "properties": {
    "gn:admin1_code":"35.0",
    "gn:asciiname":"Pahnedar",
    "gn:country_code":"IR",
    "gn:dem":763,
    "gn:feature_class":"P",
    "gn:feature_code":"PPL",
    "gn:name":"Pahnedar",
    "gn:population":0,
    "gn:timezone":"Asia/Tehran",
    "iso:country":"IR",
    "name:fas_x_preferred":[
        "\u067e\u0647\u0646\u062f\u0631"
    ],
    "name:fas_x_variant":[
        "\u067e\u064e\u0647\u0646 \u062f\u064e\u0631"
    ],
    "name:und_x_variant":[
        "Pahn Dar",
        "Pahnedar"
    ],
    "wof:name":"Pahnedar",
    "wof:placetype":"locality"
},
  "geometry": {"coordinates":[53.24195,36.16799],"type":"Point"}
}