{
  "type": "Feature",
  "properties": {
    "gn:admin1_code":"33",
    "gn:asciiname":"Gezafer",
    "gn:country_code":"IR",
    "gn:dem":1178,
    "gn:feature_class":"P",
    "gn:feature_code":"PPL",
    "gn:name":"Gez\u0101fer",
    "gn:population":0,
    "gn:timezone":"Asia/Tehran",
    "iso:country":"IR",
    "name:fas_x_preferred":[
        "\u06af\u0650\u0632\u0627\u0641\u0650\u0631"
    ],
    "name:fas_x_variant":[
        "\u06af\u0632\u0627\u0641\u0631",
        "Gez\u0101fer"
    ],
    "wof:name":"Gezafer",
    "wof:placetype":"locality"
},
  "geometry": {"coordinates":[45.4012,38.4501],"type":"Point"}
}