{
  "type": "Feature",
  "properties": {
    "gn:admin1_code":"13",
    "gn:asciiname":"Khan Jamal Panahi-ye `Olya",
    "gn:country_code":"IR",
    "gn:dem":1778,
    "gn:feature_class":"P",
    "gn:feature_code":"PPL",
    "gn:name":"Kh\u0101n Jam\u0101l Pan\u0101h\u012b-ye \u2018Oly\u0101",
    "gn:population":0,
    "gn:timezone":"Asia/Tehran",
    "iso:country":"IR",
    "name:ceb_x_preferred":[
        "Kh\u0101n Jam\u0101l-e Pan\u0101h\u012b"
    ],
    "name:fas_x_preferred":[
        "\u062e\u0627\u0646 \u062c\u0645\u0627\u0644 \u067e\u0646\u0627\u0647\u06cc"
    ],
    "name:fas_x_variant":[
        "Kh\u0101njam\u0101l-e Pan\u0101h\u012b",
        "Kh\u0101n Jam\u0101l-e Pan\u0101h\u012b",
        "\u062e\u0627\u0646 \u062c\u0645\u0627\u0644 \u067e\u0646\u0627\u0647\u06cc \u0639\u0644\u06cc\u0627",
        "\u062e\u0627\u0646\u062c\u0645\u0627\u0644 \u067e\u0646\u0627\u0647\u06cc"
    ],
    "name:swe_x_preferred":[
        "Kh\u0101n Jam\u0101l-e Pan\u0101h\u012b"
    ],
    "name:und_x_variant":[
        "Kh\u0101n Jam\u0101l Pan\u0101h\u012b-ye \u2018Oly\u0101"
    ],
    "wof:name":"Khan Jamal Panahi-ye `Olya",
    "wof:placetype":"locality"
},
  "geometry": {"coordinates":[47.63695,34.91864],"type":"Point"}
}