{
  "type": "Feature",
  "properties": {
    "gn:admin1_code":"11.0",
    "gn:asciiname":"Chahu Saheli",
    "gn:country_code":"IR",
    "gn:dem":8,
    "gn:feature_class":"P",
    "gn:feature_code":"PPL",
    "gn:name":"Ch\u0101h\u016b S\u0101\u1e29el\u012b",
    "gn:population":0,
    "gn:timezone":"Asia/Tehran",
    "iso:country":"IR",
    "name:fas_x_preferred":[
        "\u0686\u0627\u0647\u0648 \u0633\u0627\u062d\u0644\u06cc"
    ],
    "name:fas_x_variant":[
        "Ch\u0101h\u016b S\u0101\u1e29el\u012b",
        "\u0639\u0627\u064a\u0634\u0647 \u0622\u0628\u0627\u062f"
    ],
    "name:und_x_variant":[
        "\u2018\u0100\u012bsheh\u0101b\u0101d"
    ],
    "wof:name":"Chahu Saheli",
    "wof:placetype":"locality"
},
  "geometry": {"coordinates":[55.4779,26.6893],"type":"Point"}
}