{
  "type": "Feature",
  "properties": {
    "gn:admin1_code":"8",
    "gn:asciiname":"Navan",
    "gn:cc2":"IR",
    "gn:country_code":"IR",
    "gn:dem":14,
    "gn:feature_class":"P",
    "gn:feature_code":"PPL",
    "gn:name":"N\u0101v\u0101n",
    "gn:population":0,
    "gn:timezone":"Asia/Tehran",
    "iso:country":"IR",
    "name:ara_x_preferred":[
        "\u0646\u0627\u0641\u0627\u0646"
    ],
    "name:bul_x_preferred":[
        "\u041d\u0430\u0432\u0430\u043d"
    ],
    "name:cat_x_preferred":[
        "Navan"
    ],
    "name:ceb_x_preferred":[
        "Navan"
    ],
    "name:ces_x_preferred":[
        "Navan"
    ],
    "name:cym_x_preferred":[
        "Navan"
    ],
    "name:dan_x_preferred":[
        "Navan"
    ],
    "name:deu_x_preferred":[
        "Navan"
    ],
    "name:ell_x_preferred":[
        "\u039d\u03b1\u03b2\u03ac\u03bd"
    ],
    "name:eus_x_preferred":[
        "Navan"
    ],
    "name:fas_x_preferred":[
        "N\u0101v\u0101n"
    ],
    "name:fas_x_variant":[
        "\u0646\u0627\u0648\u0627\u0646"
    ],
    "name:fra_x_preferred":[
        "Navan"
    ],
    "name:gle_x_preferred":[
        "An Uaimh"
    ],
    "name:glg_x_preferred":[
        "Navan"
    ],
    "name:glv_x_preferred":[
        "Yn Ooive"
    ],
    "name:heb_x_preferred":[
        "\u05e0\u05d0\u05d1\u05d0\u05df"
    ],
    "name:ind_x_preferred":[
        "Navan"
    ],
    "name:ita_x_preferred":[
        "Navan"
    ],
    "name:jpn_x_preferred":[
        "\u30ca\u30f4\u30a1\u30f3"
    ],
    "name:kat_x_preferred":[
        "\u10dc\u10d0\u10d5\u10d0\u10dc\u10d8"
    ],
    "name:lit_x_preferred":[
        "Navanas"
    ],
    "name:mkd_x_preferred":[
        "\u041d\u0430\u0432\u0430\u043d"
    ],
    "name:nld_x_preferred":[
        "Navan"
    ],
    "name:nno_x_preferred":[
        "Navan"
    ],
    "name:nor_x_preferred":[
        "Navan"
    ],
    "name:pol_x_preferred":[
        "Navan"
    ],
    "name:por_x_preferred":[
        "Navan"
    ],
    "name:rus_x_preferred":[
        "\u0410\u043d-\u0423\u0430\u0432\u044c"
    ],
    "name:slk_x_preferred":[
        "Navan"
    ],
    "name:spa_x_preferred":[
        "Navan"
    ],
    "name:srp_x_preferred":[
        "\u041d\u0430\u0432\u0430\u043d"
    ],
    "name:swe_x_preferred":[
        "Navan"
    ],
    "name:ukr_x_preferred":[
        "\u041d\u0430\u0432\u0430\u043d"
    ],
    "name:und_x_variant":[
        "Nawan"
    ],
    "name:urd_x_preferred":[
        "\u0646\u0627\u0648\u06cc\u0646"
    ],
    "wof:name":"Navan",
    "wof:placetype":"locality"
},
  "geometry": {"coordinates":[48.91028,37.83028],"type":"Point"}
}