{
  "type": "Feature",
  "properties": {
    "gn:admin1_code":"8",
    "gn:asciiname":"Navan",
    "gn:cc2":"IR",
    "gn:country_code":"IR",
    "gn:dem":14,
    "gn:feature_class":"P",
    "gn:feature_code":"PPL",
    "gn:name":"N\u0101v\u0101n",
    "gn:population":0,
    "gn:timezone":"Asia/Tehran",
    "iso:country":"IR",
    "name:fas_x_preferred":[
        "N\u0101v\u0101n"
    ],
    "name:und_x_variant":[
        "Nawan"
    ],
    "wof:name":"Navan",
    "wof:placetype":"locality"
},
  "geometry": {"coordinates":[48.91028,37.83028],"type":"Point"}
}