{
  "type": "Feature",
  "properties": {
    "gn:admin1_code":"25",
    "gn:asciiname":"Parpa-ye Bala",
    "gn:country_code":"IR",
    "gn:dem":1866,
    "gn:feature_class":"P",
    "gn:feature_code":"PPL",
    "gn:name":"Parp\u0101-ye B\u0101l\u0101",
    "gn:population":0,
    "gn:timezone":"Asia/Tehran",
    "iso:country":"IR",
    "name:fas_x_preferred":[
        "\u067e\u0631\u067e\u0627\u06cc \u0628\u0627\u0644\u0627"
    ],
    "name:fas_x_variant":[
        "\u067e\u064e\u0631\u064a\u0627",
        "\u067e\u064e\u0631\u064a\u0651\u0627",
        "Parp\u0101-ye B\u0101l\u0101"
    ],
    "name:und_x_variant":[
        "Par\u012b\u0101",
        "Par\u012by\u0101"
    ],
    "wof:name":"Parpa-ye Bala",
    "wof:placetype":"locality"
},
  "geometry": {"coordinates":[53.92513,35.76300000000001],"type":"Point"}
}