{
  "type": "Feature",
  "properties": {
    "gn:admin1_code":"15.0",
    "gn:asciiname":"Matu'i",
    "gn:country_code":"IR",
    "gn:dem":159,
    "gn:feature_class":"P",
    "gn:feature_code":"PPL",
    "gn:name":"Mat\u016b\u2019\u012b",
    "gn:population":0,
    "gn:timezone":"Asia/Tehran",
    "iso:country":"IR",
    "name:fas_x_preferred":[
        "Mat\u016b\u2019\u012b"
    ],
    "name:fas_x_variant":[
        "\u0645\u062a\u0648\u0626\u06cc"
    ],
    "wof:name":"Matu'i",
    "wof:placetype":"locality"
},
  "geometry": {"coordinates":[49.59455,31.24246],"type":"Point"}
}