{
  "type": "Feature",
  "properties": {
    "gn:admin1_code":"29",
    "gn:asciiname":"Behjerd",
    "gn:country_code":"IR",
    "gn:dem":2301,
    "gn:feature_class":"P",
    "gn:feature_code":"PPLF",
    "gn:name":"Behjerd",
    "gn:population":0,
    "gn:timezone":"Asia/Tehran",
    "iso:country":"IR",
    "name:ara_x_preferred":[
        "\u0628\u0647\u062c\u0631\u062f \u0627\u0644\u0639\u0644\u064a\u0627"
    ],
    "name:fas_x_preferred":[
        "\u0628\u0647\u062c\u0631\u062f \u0639\u0644\u06cc\u0627"
    ],
    "name:fas_x_variant":[
        "Behjerd-e \u2018Oly\u0101",
        "\u0628\u0647\u062c\u0631\u062f",
        "\u0628\u0647\u062c\u0631\u062f \u0633\u0641\u0644\u06cc"
    ],
    "name:und_x_variant":[
        "Behjerd-e Sofl\u00e1"
    ],
    "wof:name":"Behjerd",
    "wof:placetype":"locality"
},
  "geometry": {"coordinates":[56.4516,29.2972],"type":"Point"}
}