{
  "type": "Feature",
  "properties": {
    "gn:admin1_code":"23",
    "gn:asciiname":"Cham Murt",
    "gn:country_code":"IR",
    "gn:dem":914,
    "gn:feature_class":"P",
    "gn:feature_code":"PPL",
    "gn:name":"Cham M\u016brt",
    "gn:population":0,
    "gn:timezone":"Asia/Tehran",
    "iso:country":"IR",
    "name:fas_x_preferred":[
        "\u0686\u0645 \u0645\u0648\u0631\u062a"
    ],
    "name:fas_x_variant":[
        "Cham-e M\u016brd"
    ],
    "name:und_x_variant":[
        "Jadsir",
        "Cham M\u016brt"
    ],
    "wof:name":"Cham Murt",
    "wof:placetype":"locality"
},
  "geometry": {"coordinates":[47.9649,33.4176],"type":"Point"}
}