{
  "type": "Feature",
  "properties": {
    "gn:admin1_code":"41.0",
    "gn:asciiname":"Kaffaz-e Sofla",
    "gn:country_code":"IR",
    "gn:dem":1492,
    "gn:feature_class":"P",
    "gn:feature_code":"PPL",
    "gn:name":"Kaff\u0101z-e Sofl\u00e1",
    "gn:population":0,
    "gn:timezone":"Asia/Tehran",
    "iso:country":"IR",
    "name:ceb_x_preferred":[
        "Kaff\u0101z-e Sofl\u00e1"
    ],
    "name:fas_x_preferred":[
        "\u06a9\u0641\u0651\u0627\u0632 \u0633\u0641\u0644\u06cc"
    ],
    "name:fas_x_variant":[
        "Kaf\u0101z",
        "Kaff\u0101z-e Sofl\u00e1",
        "Kaf\u0101s",
        "\u06a9\u0641\u0627\u0632"
    ],
    "name:swe_x_preferred":[
        "Kaff\u0101z-e Sofl\u00e1"
    ],
    "name:und_x_variant":[
        "Kaf\u0101s"
    ],
    "wof:name":"Kaffaz-e Sofla",
    "wof:placetype":"locality"
},
  "geometry": {"coordinates":[60.37300000000001,32.5477],"type":"Point"}
}