{
  "type": "Feature",
  "properties": {
    "gn:admin1_code":"23",
    "gn:asciiname":"Bagh",
    "gn:country_code":"IR",
    "gn:dem":1325,
    "gn:feature_class":"P",
    "gn:feature_code":"PPL",
    "gn:name":"B\u0101gh",
    "gn:population":0,
    "gn:timezone":"Asia/Tehran",
    "iso:country":"IR",
    "name:fas_x_preferred":[
        "\u0628\u0627\u063a"
    ],
    "name:fas_x_variant":[
        "B\u0101gh"
    ],
    "wof:name":"Bagh",
    "wof:placetype":"locality"
},
  "geometry": {"coordinates":[48.7267,33.0664],"type":"Point"}
}