{
  "type": "Feature",
  "properties": {
    "gn:admin1_code":"42",
    "gn:asciiname":"Yulqoli",
    "gn:country_code":"IR",
    "gn:dem":661,
    "gn:feature_class":"P",
    "gn:feature_code":"PPL",
    "gn:name":"Y\u016blqol\u012b",
    "gn:population":0,
    "gn:timezone":"Asia/Tehran",
    "iso:country":"IR",
    "name:fas_x_preferred":[
        "Y\u016blqol\u012b"
    ],
    "name:fas_x_variant":[
        "\u06cc\u0648\u0644\u0642\u0644\u06cc",
        "\u06cc\u0648\u0644 \u0642\u0648\u0646\u0644\u06cc"
    ],
    "name:und_x_variant":[
        "Y\u016bl Qownl\u012b"
    ],
    "wof:name":"Yulqoli",
    "wof:placetype":"locality"
},
  "geometry": {"coordinates":[59.79403000000001,37.0931],"type":"Point"}
}