{
  "type": "Feature",
  "properties": {
    "gn:admin1_code":"32.0",
    "gn:asciiname":"Shataji",
    "gn:country_code":"IR",
    "gn:dem":2070,
    "gn:feature_class":"P",
    "gn:feature_code":"PPL",
    "gn:name":"Shataj\u012b",
    "gn:population":0,
    "gn:timezone":"Asia/Tehran",
    "iso:country":"IR",
    "name:fas_x_preferred":[
        "\u0634\u062a\u062c\u06cc"
    ],
    "name:und_x_variant":[
        "Shataj\u012b"
    ],
    "wof:name":"Shataji",
    "wof:placetype":"locality"
},
  "geometry": {"coordinates":[48.67957,37.97755],"type":"Point"}
}