{
  "type": "Feature",
  "properties": {
    "gn:admin1_code":"4",
    "gn:asciiname":"Kalateh-ye Hoseyn Khan",
    "gn:country_code":"IR",
    "gn:dem":1088,
    "gn:feature_class":"P",
    "gn:feature_code":"PPL",
    "gn:name":"Kal\u0101teh-ye \u1e28oseyn Kh\u0101n",
    "gn:population":0,
    "gn:timezone":"Asia/Tehran",
    "iso:country":"IR",
    "name:fas_x_preferred":[
        "\u06a9\u0644\u0627\u062a\u0647 \u062d\u0633\u064a\u0646 \u062e\u0627\u0646"
    ],
    "name:fas_x_variant":[
        "Kal\u0101teh-ye \u1e28oseyn Kh\u0101n"
    ],
    "wof:name":"Kalateh-ye Hoseyn Khan",
    "wof:placetype":"locality"
},
  "geometry": {"coordinates":[60.49031,30.84499000000001],"type":"Point"}
}