{
  "type": "Feature",
  "properties": {
    "gn:admin1_code":"23",
    "gn:asciiname":"Sayehbaneh",
    "gn:cc2":"IR",
    "gn:country_code":"IR",
    "gn:dem":1511,
    "gn:feature_class":"P",
    "gn:feature_code":"PPL",
    "gn:name":"S\u0101yehb\u0101neh",
    "gn:population":0,
    "gn:timezone":"Asia/Tehran",
    "iso:country":"IR",
    "name:fas_x_preferred":[
        "S\u0101yehb\u0101neh"
    ],
    "name:und_x_variant":[
        "S\u0101yb\u0101neh",
        "S\u0101yeb\u0101neh"
    ],
    "wof:name":"Sayehbaneh",
    "wof:placetype":"locality"
},
  "geometry": {"coordinates":[48.79194,33.82694],"type":"Point"}
}