{
  "type": "Feature",
  "properties": {
    "gn:admin1_code":"10",
    "gn:asciiname":"Kalateh-ye Halilan",
    "gn:country_code":"IR",
    "gn:dem":1114,
    "gn:feature_class":"P",
    "gn:feature_code":"PPL",
    "gn:name":"Kal\u0101teh-ye Hal\u012bl\u0101n",
    "gn:population":0,
    "gn:timezone":"Asia/Tehran",
    "iso:country":"IR",
    "name:fas_x_preferred":[
        "\u0643\u064e\u0644\u0627\u062a\u0650\u0647"
    ],
    "name:fas_x_variant":[
        "\u06a9\u0644\u0627\u062a\u0647",
        "Kal\u0101teh",
        "\u06a9\u0644\u0627\u062a\u0647 \u0647\u0644\u06cc\u0644\u0627\u0646"
    ],
    "name:und_x_variant":[
        "Kal\u0101teh-ye Hal\u012bl\u0101n"
    ],
    "wof:name":"Kalateh-ye Halilan",
    "wof:placetype":"locality"
},
  "geometry": {"coordinates":[47.0468,33.7607],"type":"Point"}
}