{
  "type": "Feature",
  "properties": {
    "gn:admin1_code":"22",
    "gn:asciiname":"Gureh",
    "gn:country_code":"IR",
    "gn:dem":44,
    "gn:feature_class":"P",
    "gn:feature_code":"PPL",
    "gn:name":"G\u016breh",
    "gn:population":0,
    "gn:timezone":"Asia/Tehran",
    "iso:country":"IR",
    "name:fas_x_preferred":[
        "\u06af\u064f\u0631\u0650\u0647"
    ],
    "name:fas_x_variant":[
        "\u06af\u064f\u0631\u064e\u0651\u0647",
        "\u06af\u064f\u0631\u0650\u0651\u0647",
        "\u06af\u0648\u0631\u0647",
        "G\u016breh"
    ],
    "name:und_x_variant":[
        "Gorrah",
        "Gorreh",
        "Gurreh",
        "Goreh"
    ],
    "wof:name":"Gureh",
    "wof:placetype":"locality"
},
  "geometry": {"coordinates":[50.4513,29.8998],"type":"Point"}
}