{
  "type": "Feature",
  "properties": {
    "gn:admin1_code":"32",
    "gn:asciiname":"Tazeh Kand",
    "gn:country_code":"IR",
    "gn:dem":1237,
    "gn:feature_class":"P",
    "gn:feature_code":"PPL",
    "gn:name":"T\u0101zeh Kand",
    "gn:population":0,
    "gn:timezone":"Asia/Tehran",
    "iso:country":"IR",
    "name:ara_x_preferred":[
        "\u062a\u0627\u0632\u0647 \u0643\u0646\u062f \u0644\u0646\u063a\u0627\u0646"
    ],
    "name:azb_x_preferred":[
        "\u062a\u0632\u0647 \u06a9\u0646\u062f"
    ],
    "name:fas_x_preferred":[
        "\u062a\u0627\u0632\u0650\u0647 \u0643\u064e\u0646\u062f\u0650 \u0644\u064e\u0646\u06af\u0627\u0646"
    ],
    "name:fas_x_variant":[
        "\u062a\u0627\u0632\u0647 \u06a9\u0646\u062f",
        "T\u0101zeh Kand-e Lang\u0101n",
        "T\u0101zeh Kand",
        "\u062a\u0627\u0632\u0647\u200c\u06a9\u0646\u062f \u0644\u0646\u06af\u0627\u0646"
    ],
    "name:msa_x_preferred":[
        "Tazeh Kand-e Langan"
    ],
    "wof:name":"Tazeh Kand",
    "wof:placetype":"locality"
},
  "geometry": {"coordinates":[47.9676,38.9619],"type":"Point"}
}