{
  "type": "Feature",
  "properties": {
    "gn:admin1_code":"15",
    "gn:asciiname":"Laderazi",
    "gn:country_code":"IR",
    "gn:dem":262,
    "gn:feature_class":"P",
    "gn:feature_code":"PPL",
    "gn:name":"L\u0101der\u0101z\u012b",
    "gn:population":0,
    "gn:timezone":"Asia/Tehran",
    "iso:country":"IR",
    "name:fas_x_preferred":[
        "\u0644\u0627\u062f\u0631\u0627\u0632\u06cc"
    ],
    "name:fas_x_variant":[
        "L\u0101der\u0101z\u012b"
    ],
    "name:und_x_variant":[
        "Cheshmeh \u2018Al\u012b M\u016bchk\u0101n",
        "Chahsmen Ali",
        "Chashmeh-i-\u2018Ali",
        "Cheshmeh \u2018Al\u012b"
    ],
    "name:urd_x_preferred":[
        "\u0644\u0627\u0688\u06cc\u0631\u0627\u0632\u06cc"
    ],
    "wof:name":"Laderazi",
    "wof:placetype":"locality"
},
  "geometry": {"coordinates":[49.19215,32.07812],"type":"Point"}
}