{
  "type": "Feature",
  "properties": {
    "gn:admin1_code":"35.0",
    "gn:asciiname":"Makarud",
    "gn:country_code":"IR",
    "gn:dem":-3,
    "gn:feature_class":"P",
    "gn:feature_code":"PPL",
    "gn:name":"Makar\u016bd",
    "gn:population":0,
    "gn:timezone":"Asia/Tehran",
    "iso:country":"IR",
    "name:ceb_x_preferred":[
        "Mak\u0101 R\u016bd"
    ],
    "name:fas_x_preferred":[
        "\u0645\u06a9\u0631\u0648\u062f"
    ],
    "name:fas_x_variant":[
        "Mak R\u016bd",
        "Mak\u0101 R\u016bd",
        "\u0645\u0643\u0627 \u0631\u0648\u062f"
    ],
    "name:swe_x_preferred":[
        "Mak\u0101 R\u016bd"
    ],
    "name:und_x_variant":[
        "Mak\u0101 R\u016bd",
        "\u0645\u0643\u0627 \u0631\u0648\u062f",
        "Makar\u016bd"
    ],
    "wof:name":"Makarud",
    "wof:placetype":"locality"
},
  "geometry": {"coordinates":[51.003,36.74249],"type":"Point"}
}