{
  "type": "Feature",
  "properties": {
    "gn:admin1_code":"15",
    "gn:asciiname":"Gobeyr-e Do",
    "gn:country_code":"IR",
    "gn:dem":23,
    "gn:feature_class":"P",
    "gn:feature_code":"PPL",
    "gn:name":"Gobeyr-e Do",
    "gn:population":0,
    "gn:timezone":"Asia/Tehran",
    "iso:country":"IR",
    "name:ara_x_preferred":[
        "\u063a\u0628\u064a\u0631 \u0627\u0644\u062b\u0627\u0646\u064a"
    ],
    "name:azb_x_preferred":[
        "\u06af\u0628\u06cc\u0631\u062f\u0648"
    ],
    "name:ceb_x_preferred":[
        "Gobeyr-e Do"
    ],
    "name:fas_x_preferred":[
        "\u06af\u0628\u06cc\u0631 \u062f\u0648"
    ],
    "name:swe_x_preferred":[
        "Gobeyr-e Do"
    ],
    "name:und_x_variant":[
        "K\u016bt al Qubair",
        "Gobeyr-e Dovvom",
        "Gobeyr-e Bozorq"
    ],
    "wof:name":"Gobeyr-e Do",
    "wof:placetype":"locality"
},
  "geometry": {"coordinates":[48.77488,31.46998],"type":"Point"}
}