{
  "type": "Feature",
  "properties": {
    "gn:admin1_code":"16.0",
    "gn:asciiname":"Vatreh Zamin",
    "gn:country_code":"IR",
    "gn:dem":1887,
    "gn:feature_class":"P",
    "gn:feature_code":"PPL",
    "gn:name":"Vatreh Zam\u012bn",
    "gn:population":0,
    "gn:timezone":"Asia/Tehran",
    "iso:country":"IR",
    "name:ckb_x_preferred":[
        "\u0641\u062a\u0631\u06d5 \u0632\u06d5\u0648\u06cc"
    ],
    "name:fas_x_preferred":[
        "\u0641\u0637\u0631\u0647 \u0632\u0645\u064a\u0646"
    ],
    "name:fas_x_variant":[
        "\u0648\u062a\u0631\u0647 \u0632\u0645\u06cc\u0646",
        "Fe\u0163reh Zam\u012bn",
        "Vatreh Zam\u012bn",
        "\u0641\u0637\u0631\u0647 \u0632\u0645\u06cc\u0646"
    ],
    "name:kur_x_preferred":[
        "Fitre Zew\u00ee"
    ],
    "wof:name":"Vatreh Zamin",
    "wof:placetype":"locality"
},
  "geometry": {"coordinates":[46.7072,35.3021],"type":"Point"}
}