{
  "type": "Feature",
  "properties": {
    "gn:admin1_code":"8.0",
    "gn:asciiname":"Siah Barg",
    "gn:country_code":"IR",
    "gn:dem":1577,
    "gn:feature_class":"P",
    "gn:feature_code":"PPL",
    "gn:name":"S\u012b\u0101h Barg",
    "gn:population":0,
    "gn:timezone":"Asia/Tehran",
    "iso:country":"IR",
    "name:fas_x_preferred":[
        "S\u012b\u0101h Barg"
    ],
    "name:fas_x_variant":[
        "\u0633\u06cc\u0627\u0647 \u0628\u0631\u06af"
    ],
    "name:und_x_variant":[
        "\u0633\u06cc\u0627\u0647 \u0628\u0631\u06af"
    ],
    "wof:name":"Siah Barg",
    "wof:placetype":"locality"
},
  "geometry": {"coordinates":[50.13952000000001,36.81672],"type":"Point"}
}