{
  "type": "Feature",
  "properties": {
    "gn:admin1_code":"11",
    "gn:asciiname":"Konar Zard",
    "gn:country_code":"IR",
    "gn:dem":244,
    "gn:feature_class":"P",
    "gn:feature_code":"PPL",
    "gn:name":"Kon\u0101r Zard",
    "gn:population":0,
    "gn:timezone":"Asia/Tehran",
    "iso:country":"IR",
    "name:ara_x_preferred":[
        "\u0643\u0646\u0627\u0631 \u0632\u0631\u062f"
    ],
    "name:ceb_x_preferred":[
        "Kon\u0101r Zard"
    ],
    "name:fas_x_preferred":[
        "\u0643\u064e\u0646\u0627\u0631\u0650 \u0632\u064e\u0631\u062f"
    ],
    "name:fas_x_variant":[
        "\u0643\u064f\u0646\u0627\u0631\u0650 \u0632\u064e\u0631\u062f",
        "Kon\u0101r Zard",
        "\u0643\u0646\u0627\u0631 \u0632\u0631\u062f",
        "\u06a9\u0646\u0627\u0631\u0632\u0631\u062f"
    ],
    "name:msa_x_preferred":[
        "Konar Zard"
    ],
    "name:swe_x_preferred":[
        "Kon\u0101r Zard"
    ],
    "name:und_x_variant":[
        "Kan\u0101r-e Zard",
        "Kon\u0101r-e Zard"
    ],
    "wof:name":"Konar Zard",
    "wof:placetype":"locality"
},
  "geometry": {"coordinates":[54.67863000000001,27.04446],"type":"Point"}
}