{
  "type": "Feature",
  "properties": {
    "gn:admin1_code":"23",
    "gn:asciiname":"Shah Qoliabad",
    "gn:country_code":"IR",
    "gn:dem":1634,
    "gn:feature_class":"P",
    "gn:feature_code":"PPL",
    "gn:name":"Sh\u0101h Qol\u012b\u0101b\u0101d",
    "gn:population":0,
    "gn:timezone":"Asia/Tehran",
    "iso:country":"IR",
    "name:ara_x_preferred":[
        "\u0634\u0627\u0629 \u0642\u0644\u064a\u0622\u0628\u0627\u062f"
    ],
    "name:fas_x_preferred":[
        "\u0634\u0627\u0647 \u0642\u0644\u06cc"
    ],
    "name:fas_x_variant":[
        "\u0634\u0627\u0647 \u0642\u0644\u06cc \u0622\u0628\u0627\u062f",
        "Sh\u0101h Qol\u012b",
        "Sh\u0101h Qol\u012b\u0101b\u0101d",
        "\u0634\u0627\u0647 \u0642\u0644\u06cc\u200c\u0622\u0628\u0627\u062f"
    ],
    "wof:name":"Shah Qoliabad",
    "wof:placetype":"locality"
},
  "geometry": {"coordinates":[47.9021,33.9118],"type":"Point"}
}