{
  "type": "Feature",
  "properties": {
    "gn:admin1_code":"42",
    "gn:asciiname":"Lakhi",
    "gn:country_code":"IR",
    "gn:dem":928,
    "gn:feature_class":"P",
    "gn:feature_code":"PPL",
    "gn:name":"L\u0101kh\u012b",
    "gn:population":0,
    "gn:timezone":"Asia/Tehran",
    "iso:country":"IR",
    "name:fas_x_preferred":[
        "Kal\u0101teh-ye Lokh\u012b"
    ],
    "name:fas_x_variant":[
        "\u06a9\u0644\u0627\u062a\u0647 \u0644\u062e\u06cc",
        "\u0644\u0627\u062e\u06cc",
        "\u06a9\u0644\u0627\u062a\u0647 \u0644\u0627\u062e\u06cc \u062c\u062f\u06cc\u062f"
    ],
    "name:und_x_variant":[
        "\u06a9\u0644\u0627\u062a\u0647 \u0644\u062e\u06cc",
        "L\u0101kh\u012b",
        "Kal\u0101teh-ye L\u0101kh\u012b-e Jad\u012bd"
    ],
    "wof:name":"Lakhi",
    "wof:placetype":"locality"
},
  "geometry": {"coordinates":[59.60249,34.10765],"type":"Point"}
}