{
  "type": "Feature",
  "properties": {
    "gn:admin1_code":"8.0",
    "gn:asciiname":"Lumeh Vasht",
    "gn:country_code":"IR",
    "gn:dem":1632,
    "gn:feature_class":"P",
    "gn:feature_code":"PPLL",
    "gn:name":"L\u016bmeh Vasht",
    "gn:population":0,
    "gn:timezone":"Asia/Tehran",
    "iso:country":"IR",
    "name:fas_x_preferred":[
        "\u0644\u0648\u0645\u0647 \u062f\u0634\u062a"
    ],
    "name:fas_x_variant":[
        "L\u016bmeh Dasht",
        "\u0644\u0648\u0645\u0647 \u0648\u0634\u062a"
    ],
    "name:msa_x_preferred":[
        "Lumeh Dasht"
    ],
    "name:ukr_x_preferred":[
        "\u041b\u0443\u043c\u0435-\u0414\u0435\u0448\u0442"
    ],
    "name:und_x_variant":[
        "L\u016bmeh Vasht"
    ],
    "wof:name":"Lumeh Vasht",
    "wof:placetype":"locality"
},
  "geometry": {"coordinates":[48.80937,37.61684],"type":"Point"}
}