{
  "type": "Feature",
  "properties": {
    "gn:admin1_code":"5.0",
    "gn:asciiname":"Shilabdan",
    "gn:country_code":"IR",
    "gn:dem":1092,
    "gn:feature_class":"P",
    "gn:feature_code":"PPL",
    "gn:name":"Sh\u012bl\u0101bd\u0101n",
    "gn:population":0,
    "gn:timezone":"Asia/Tehran",
    "iso:country":"IR",
    "name:fas_x_preferred":[
        "\u0634\u06cc\u0644\u0627\u0628\u062f\u0627\u0646"
    ],
    "name:und_x_variant":[
        "Sh\u012bl\u0101bd\u0101n"
    ],
    "wof:name":"Shilabdan",
    "wof:placetype":"locality"
},
  "geometry": {"coordinates":[50.25688,31.0011],"type":"Point"}
}