{
  "type": "Feature",
  "properties": {
    "gn:admin1_code":"5",
    "gn:asciiname":"Sar Ab Biz-e Pa'in",
    "gn:country_code":"IR",
    "gn:dem":888,
    "gn:feature_class":"P",
    "gn:feature_code":"PPL",
    "gn:name":"Sar \u0100b B\u012bz-e P\u0101\u2019\u012bn",
    "gn:population":0,
    "gn:timezone":"Asia/Tehran",
    "iso:country":"IR",
    "name:fas_x_preferred":[
        "Sar \u0100b B\u012bz-e P\u0101\u2019\u012bn"
    ],
    "name:fas_x_variant":[
        "\u0633\u0631 \u0622\u0628 \u0628\u064a\u0632 \u067e\u0627\u0626\u064a\u0646"
    ],
    "wof:name":"Sar Ab Biz-e Pa'in",
    "wof:placetype":"locality"
},
  "geometry": {"coordinates":[51.08621,30.39375],"type":"Point"}
}