{
  "type": "Feature",
  "properties": {
    "gn:admin1_code":"15",
    "gn:asciiname":"Shahid ol Hoda",
    "gn:country_code":"IR",
    "gn:dem":67,
    "gn:feature_class":"P",
    "gn:feature_code":"PPL",
    "gn:name":"Shah\u012bd ol Hod\u0101",
    "gn:population":0,
    "gn:timezone":"Asia/Tehran",
    "iso:country":"IR",
    "name:fas_x_preferred":[
        "\u0639\u0644\u0645 \u0627\u0644\u0647\u062f\u06cc"
    ],
    "name:fas_x_variant":[
        "\u2018Alam ol Hod\u00e1",
        "\u0634\u0647\u06cc\u062f \u0627\u0644\u0647\u062f\u0627",
        "\u0628\u06cc\u062a \u0639\u06cc\u0633\u06cc",
        "\u0634\u06cc\u062e \u0639\u06cc\u0633\u06cc"
    ],
    "name:und_x_variant":[
        "Sheykh \u2018\u012as\u00e1",
        "Shah\u012bd ol Hod\u0101",
        "Beyt-e \u2018\u012as\u00e1"
    ],
    "wof:name":"Shahid ol Hoda",
    "wof:placetype":"locality"
},
  "geometry": {"coordinates":[48.2737,32.13347],"type":"Point"}
}