{
  "type": "Feature",
  "properties": {
    "gn:admin1_code":"35.0",
    "gn:asciiname":"Hashtal",
    "gn:country_code":"IR",
    "gn:dem":46,
    "gn:feature_class":"P",
    "gn:feature_code":"PPL",
    "gn:name":"Hashtal",
    "gn:population":0,
    "gn:timezone":"Asia/Tehran",
    "iso:country":"IR",
    "name:fas_x_preferred":[
        "\u0647\u064e\u0634\u062a\u064e\u0644\u0650 \u067e\u0627\u0626\u064a\u0646"
    ],
    "name:fas_x_variant":[
        "Hashtal-e P\u0101\u2019\u012bn",
        "\u0647\u0634\u062a\u0644"
    ],
    "wof:name":"Hashtal",
    "wof:placetype":"locality"
},
  "geometry": {"coordinates":[52.42542,36.49732],"type":"Point"}
}