{
  "type": "Feature",
  "properties": {
    "gn:admin1_code":"42",
    "gn:asciiname":"Deh-e Hajji",
    "gn:country_code":"IR",
    "gn:dem":1110,
    "gn:feature_class":"P",
    "gn:feature_code":"PPL",
    "gn:name":"Deh-e \u1e28\u0101jj\u012b",
    "gn:population":0,
    "gn:timezone":"Asia/Tehran",
    "iso:country":"IR",
    "name:fas_x_preferred":[
        "\u062f\u0647 \u062d\u0627\u062c\u06cc"
    ],
    "name:fas_x_variant":[
        "Deh-e \u1e28\u0101jj\u012b"
    ],
    "wof:name":"Deh-e Hajji",
    "wof:placetype":"locality"
},
  "geometry": {"coordinates":[58.64702,36.15587],"type":"Point"}
}