{
  "type": "Feature",
  "properties": {
    "gn:admin1_code":"8",
    "gn:asciiname":"Soleyman Zamin",
    "gn:country_code":"IR",
    "gn:dem":142,
    "gn:feature_class":"P",
    "gn:feature_code":"PPL",
    "gn:name":"Soleym\u0101n Zam\u012bn",
    "gn:population":0,
    "gn:timezone":"Asia/Tehran",
    "iso:country":"IR",
    "name:fas_x_preferred":[
        "Soleym\u0101n Zam\u012bn"
    ],
    "wof:name":"Soleyman Zamin",
    "wof:placetype":"locality"
},
  "geometry": {"coordinates":[49.15389,37.26722],"type":"Point"}
}