{
  "type": "Feature",
  "properties": {
    "gn:admin1_code":"4.0",
    "gn:asciiname":"Deh-e Khiari",
    "gn:country_code":"IR",
    "gn:dem":477,
    "gn:feature_class":"P",
    "gn:feature_code":"PPL",
    "gn:name":"Deh-e Kh\u012b\u0101r\u012b",
    "gn:population":0,
    "gn:timezone":"Asia/Tehran",
    "iso:country":"IR",
    "name:fas_x_preferred":[
        "\u062f\u0647 \u062e\u06cc\u0627\u0631\u06cc"
    ],
    "name:fas_x_variant":[
        "Deh-e Kh\u012b\u0101r\u012b"
    ],
    "wof:name":"Deh-e Khiari",
    "wof:placetype":"locality"
},
  "geometry": {"coordinates":[61.34829000000001,30.90117],"type":"Point"}
}