{
  "type": "Feature",
  "properties": {
    "gn:admin1_code":"28.0",
    "gn:asciiname":"`Eshratabad",
    "gn:country_code":"IR",
    "gn:dem":2039,
    "gn:feature_class":"P",
    "gn:feature_code":"PPL",
    "gn:name":"\u2018Eshrat\u0101b\u0101d",
    "gn:population":0,
    "gn:timezone":"Asia/Tehran",
    "iso:country":"IR",
    "name:fas_x_preferred":[
        "\u0639\u0634\u0631\u062a \u0622\u0628\u0627\u062f"
    ],
    "name:fas_x_variant":[
        "\u2018Eshrat\u0101b\u0101d"
    ],
    "wof:name":"`Eshratabad",
    "wof:placetype":"locality"
},
  "geometry": {"coordinates":[52.9552,32.6865],"type":"Point"}
}