{
  "type": "Feature",
  "properties": {
    "gn:admin1_code":"15.0",
    "gn:asciiname":"Asbah-e Do",
    "gn:country_code":"IR",
    "gn:dem":25,
    "gn:feature_class":"P",
    "gn:feature_code":"PPL",
    "gn:name":"A\u015fba\u1e29-e Do",
    "gn:population":0,
    "gn:timezone":"Asia/Tehran",
    "iso:country":"IR",
    "name:fas_x_preferred":[
        "\u0627\u0635\u0628\u062d \u062f\u0648"
    ],
    "name:fas_x_variant":[
        "A\u015fba\u1e29-e Do"
    ],
    "name:und_x_variant":[
        "A\u015fba\u1e29",
        "A\u015fb\u0101\u1e29d\u016b",
        "A\u015fja-e Do"
    ],
    "wof:name":"Asbah-e Do",
    "wof:placetype":"locality"
},
  "geometry": {"coordinates":[48.827,31.5454],"type":"Point"}
}