{
  "type": "Feature",
  "properties": {
    "gn:admin1_code":"28.0",
    "gn:asciiname":"Hoseynabad-e Qohab",
    "gn:country_code":"IR",
    "gn:dem":1529,
    "gn:feature_class":"P",
    "gn:feature_code":"PPL",
    "gn:name":"\u1e28oseyn\u0101b\u0101d-e Qoh\u0101b",
    "gn:population":0,
    "gn:timezone":"Asia/Tehran",
    "iso:country":"IR",
    "name:fas_x_preferred":[
        "\u1e28oseyn\u0101b\u0101d-e Qoh\u0101b"
    ],
    "name:fas_x_variant":[
        "\u062d\u0633\u06cc\u0646 \u0622\u0628\u0627\u062f \u0642\u0647\u0627\u0628"
    ],
    "name:und_x_variant":[
        "\u062d\u0633\u06cc\u0646 \u0622\u0628\u0627\u062f \u0642\u0647\u0627\u0628"
    ],
    "wof:name":"Hoseynabad-e Qohab",
    "wof:placetype":"locality"
},
  "geometry": {"coordinates":[51.93234,32.62897],"type":"Point"}
}