{
  "type": "Feature",
  "properties": {
    "gn:admin1_code":"11.0",
    "gn:asciiname":"Dezhgan",
    "gn:country_code":"IR",
    "gn:dem":42,
    "gn:feature_class":"P",
    "gn:feature_code":"PPL",
    "gn:name":"Dezhg\u0101n",
    "gn:population":0,
    "gn:timezone":"Asia/Tehran",
    "iso:country":"IR",
    "name:fas_x_preferred":[
        "\u062f\u0698\u06af\u0627\u0646"
    ],
    "name:fas_x_variant":[
        "Dezhg\u0101n"
    ],
    "wof:name":"Dezhgan",
    "wof:placetype":"locality"
},
  "geometry": {"coordinates":[55.278,26.8971],"type":"Point"}
}