{
  "type": "Feature",
  "properties": {
    "gn:admin1_code":"5.0",
    "gn:asciiname":"Chelleh Pun",
    "gn:country_code":"IR",
    "gn:dem":1235,
    "gn:feature_class":"P",
    "gn:feature_code":"PPL",
    "gn:name":"Chelleh P\u016bn",
    "gn:population":0,
    "gn:timezone":"Asia/Tehran",
    "iso:country":"IR",
    "name:fas_x_preferred":[
        "\u0686\u0644\u0647 \u067e\u0648\u0646"
    ],
    "name:und_x_variant":[
        "Chelleh P\u016bn"
    ],
    "wof:name":"Chelleh Pun",
    "wof:placetype":"locality"
},
  "geometry": {"coordinates":[50.6426,31.39578],"type":"Point"}
}