{
  "type": "Feature",
  "properties": {
    "gn:admin1_code":"38",
    "gn:asciiname":"Bakandi",
    "gn:country_code":"IR",
    "gn:dem":1309,
    "gn:feature_class":"P",
    "gn:feature_code":"PPL",
    "gn:name":"Bakand\u012b",
    "gn:population":0,
    "gn:timezone":"Asia/Tehran",
    "iso:country":"IR",
    "name:fas_x_preferred":[
        "\u0628\u0643\u0646\u062f\u06cc"
    ],
    "name:fas_x_variant":[
        "Beyg Kand\u012b",
        "Bakand\u012b",
        "\u0628\u06a9 \u0643\u0646\u062f\u06cc"
    ],
    "name:und_x_variant":[
        "Bak Kand\u012b",
        "Beg Kand\u012b",
        "Bikandi"
    ],
    "wof:name":"Bakandi",
    "wof:placetype":"locality"
},
  "geometry": {"coordinates":[49.57264,36.38955],"type":"Point"}
}