{
  "type": "Feature",
  "properties": {
    "gn:admin1_code":"4.0",
    "gn:asciiname":"Kal Shab-e Ravan",
    "gn:country_code":"IR",
    "gn:dem":1594,
    "gn:feature_class":"P",
    "gn:feature_code":"PPL",
    "gn:name":"Kal Shab-e Rav\u0101n",
    "gn:population":0,
    "gn:timezone":"Asia/Tehran",
    "iso:country":"IR",
    "name:fas_x_preferred":[
        "\u06a9\u0644 \u0634\u0628 \u0631\u0648\u0627\u0646"
    ],
    "name:und_x_variant":[
        "Kal Shab-e Rav\u0101n"
    ],
    "wof:name":"Kal Shab-e Ravan",
    "wof:placetype":"locality"
},
  "geometry": {"coordinates":[61.282,27.57237000000001],"type":"Point"}
}