{
  "type": "Feature",
  "properties": {
    "gn:admin1_code":"29",
    "gn:asciiname":"Chahar Taq",
    "gn:country_code":"IR",
    "gn:dem":2816,
    "gn:feature_class":"P",
    "gn:feature_code":"PPL",
    "gn:name":"Chah\u0101r \u0162\u0101q",
    "gn:population":0,
    "gn:timezone":"Asia/Tehran",
    "iso:country":"IR",
    "name:ara_x_preferred":[
        "\u062a\u0634\u0647\u0627\u0631\u0637\u0627\u0642"
    ],
    "name:fas_x_preferred":[
        "\u0686\u0647\u0627\u0631 \u0637\u0627\u0642"
    ],
    "name:fas_x_variant":[
        "Chah\u0101r \u0162\u0101q",
        "\u0686\u0647\u0627\u0631\u0637\u0627\u0642"
    ],
    "name:und_x_variant":[
        "Chah\u0101r V\u0101g",
        "Cheh\u0101r",
        "Cheh\u0101r Taq"
    ],
    "wof:name":"Chahar Taq",
    "wof:placetype":"locality"
},
  "geometry": {"coordinates":[57.1332,29.5071],"type":"Point"}
}