{
  "type": "Feature",
  "properties": {
    "gn:admin1_code":"5",
    "gn:asciiname":"Darreh Sendan",
    "gn:country_code":"IR",
    "gn:dem":1219,
    "gn:feature_class":"P",
    "gn:feature_code":"PPL",
    "gn:name":"Darreh Send\u0101n",
    "gn:population":0,
    "gn:timezone":"Asia/Tehran",
    "iso:country":"IR",
    "name:fas_x_preferred":[
        "Darreh Send\u0101n"
    ],
    "name:fas_x_variant":[
        "\u062f\u0631\u0647 \u0633\u0646\u062f\u0627\u0646"
    ],
    "wof:name":"Darreh Sendan",
    "wof:placetype":"locality"
},
  "geometry": {"coordinates":[50.13294000000001,31.10532000000001],"type":"Point"}
}