{
  "type": "Feature",
  "properties": {
    "gn:admin1_code":"29",
    "gn:asciiname":"Farahabad",
    "gn:country_code":"IR",
    "gn:dem":582,
    "gn:feature_class":"P",
    "gn:feature_code":"PPL",
    "gn:name":"Fara\u1e29\u0101b\u0101d",
    "gn:population":0,
    "gn:timezone":"Asia/Tehran",
    "iso:country":"IR",
    "name:fas_x_preferred":[
        "Fara\u1e29\u0101b\u0101d"
    ],
    "wof:name":"Farahabad",
    "wof:placetype":"locality"
},
  "geometry": {"coordinates":[57.44556,27.90889],"type":"Point"}
}