{
  "type": "Feature",
  "properties": {
    "gn:admin1_code":"7",
    "gn:asciiname":"Jowhari",
    "gn:country_code":"IR",
    "gn:dem":188,
    "gn:feature_class":"P",
    "gn:feature_code":"PPL",
    "gn:name":"Jowhar\u012b",
    "gn:population":0,
    "gn:timezone":"Asia/Tehran",
    "iso:country":"IR",
    "name:ara_x_preferred":[
        "\u062c\u0648\u0647\u0631\u064a"
    ],
    "name:fas_x_preferred":[
        "\u062c\u0648\u0647\u0631\u06cc"
    ],
    "name:fas_x_variant":[
        "Jowhar\u012b"
    ],
    "name:msa_x_preferred":[
        "Jowhari"
    ],
    "wof:name":"Jowhari",
    "wof:placetype":"locality"
},
  "geometry": {"coordinates":[52.2583,28.1467],"type":"Point"}
}