{
  "type": "Feature",
  "properties": {
    "gn:admin1_code":"15",
    "gn:asciiname":"Hasasaneh-ye Pa'in",
    "gn:country_code":"IR",
    "gn:dem":11,
    "gn:feature_class":"P",
    "gn:feature_code":"PPL",
    "gn:name":"\u1e28as\u0101saneh-ye P\u0101\u2019\u012bn",
    "gn:population":0,
    "gn:timezone":"Asia/Tehran",
    "iso:country":"IR",
    "name:fas_x_preferred":[
        "\u1e28as\u0101saneh-ye P\u0101\u2019\u012bn"
    ],
    "wof:name":"Hasasaneh-ye Pa'in",
    "wof:placetype":"locality"
},
  "geometry": {"coordinates":[48.02861,31.49444],"type":"Point"}
}