{
  "type": "Feature",
  "properties": {
    "gn:admin1_code":"16.0",
    "gn:asciiname":"Hoseynabad-e Kangar",
    "gn:country_code":"IR",
    "gn:dem":2181,
    "gn:feature_class":"P",
    "gn:feature_code":"PPL",
    "gn:name":"\u1e28oseyn\u0101b\u0101d-e Kangar",
    "gn:population":0,
    "gn:timezone":"Asia/Tehran",
    "iso:country":"IR",
    "name:ceb_x_preferred":[
        "\u1e28oseyn\u0101b\u0101d-e Kangareh"
    ],
    "name:fas_x_preferred":[
        "\u062d\u0633\u06cc\u0646 \u0622\u0628\u0627\u062f \u06a9\u0646\u06af\u0631\u0647"
    ],
    "name:fas_x_variant":[
        "\u1e28oseyn\u0101b\u0101d-e Kangareh",
        "\u062d\u0633\u06cc\u0646 \u0622\u0628\u0627\u062f \u06a9\u0646\u06af\u0631",
        "\u062d\u0633\u06cc\u0646\u200c\u0622\u0628\u0627\u062f \u06a9\u0646\u06af\u0631\u0647"
    ],
    "name:swe_x_preferred":[
        "\u1e28oseyn\u0101b\u0101d-e Kangareh"
    ],
    "name:und_x_variant":[
        "\u1e28oseyn\u0101b\u0101d-e Kangar"
    ],
    "wof:name":"Hoseynabad-e Kangar",
    "wof:placetype":"locality"
},
  "geometry": {"coordinates":[47.56991,35.10377],"type":"Point"}
}