{
  "type": "Feature",
  "properties": {
    "gn:admin1_code":"8",
    "gn:asciiname":"Halu Sara",
    "gn:country_code":"IR",
    "gn:dem":55,
    "gn:feature_class":"P",
    "gn:feature_code":"PPL",
    "gn:name":"Hal\u016b Sar\u0101",
    "gn:population":0,
    "gn:timezone":"Asia/Tehran",
    "iso:country":"IR",
    "name:ara_x_preferred":[
        "\u0628\u0627\u064a\u064a\u0646 \u0647\u0644\u0648\u0633\u0631\u0627"
    ],
    "name:fas_x_preferred":[
        "Hal\u016b Sar\u0101-ye P\u0101\u2019\u012bn"
    ],
    "name:fas_x_variant":[
        "\u0647\u0644\u0648 \u0633\u0631\u0627",
        "\u067e\u0627\u0626\u06cc\u0646 \u0647\u0644\u0648 \u0633\u0631\u0627",
        "\u067e\u0627\u06cc\u06cc\u0646 \u0647\u0644\u0648\u0633\u0631\u0627"
    ],
    "name:msa_x_preferred":[
        "Pain Halu Sara"
    ],
    "name:ukr_x_preferred":[
        "\u041f\u0430\u0457\u043d-\u0413\u043e\u043b\u044e-\u0421\u0430\u0440\u0430"
    ],
    "name:und_x_variant":[
        "Hal\u016b Sar\u0101",
        "P\u0101\u2019\u012bn Hal\u016b Sar\u0101"
    ],
    "wof:name":"Halu Sara",
    "wof:placetype":"locality"
},
  "geometry": {"coordinates":[50.26451,37.04376],"type":"Point"}
}