{
  "type": "Feature",
  "properties": {
    "gn:admin1_code":"29.0",
    "gn:asciiname":"Hasanabad-e Vakareh",
    "gn:country_code":"IR",
    "gn:dem":758,
    "gn:feature_class":"P",
    "gn:feature_code":"PPL",
    "gn:name":"\u1e28asan\u0101b\u0101d-e Vakareh",
    "gn:population":0,
    "gn:timezone":"Asia/Tehran",
    "iso:country":"IR",
    "name:fas_x_preferred":[
        "\u062d\u0633\u0646 \u0622\u0628\u0627\u062f\u062f\u0647 \u06a9\u0648\u0631\u0647"
    ],
    "name:fas_x_variant":[
        "Hasan\u0101b\u0101d",
        "\u062d\u0633\u0646 \u0622\u0628\u0627\u062f \u0648\u06a9\u0631\u0647",
        "\u062d\u0633\u0646 \u0622\u0628\u0627\u062f\u062f\u0647 \u06a9\u0631\u0647",
        "\u062d\u0633\u0646 \u0622\u0628\u0627\u062f\u0647 \u06a9\u0631\u0647"
    ],
    "name:und_x_variant":[
        "\u1e28asan\u0101b\u0101ddeh K\u016breh",
        "\u1e28asan\u0101b\u0101d-e Vakareh",
        "\u1e28asan\u0101b\u0101ddeh Kareh",
        "\u1e28asan\u0101b\u0101deh-e Kareh"
    ],
    "wof:name":"Hasanabad-e Vakareh",
    "wof:placetype":"locality"
},
  "geometry": {"coordinates":[58.70915,28.94204],"type":"Point"}
}