{
  "type": "Feature",
  "properties": {
    "gn:admin1_code":"15.0",
    "gn:asciiname":"Magrian-e Yek",
    "gn:country_code":"IR",
    "gn:dem":34,
    "gn:feature_class":"P",
    "gn:feature_code":"PPL",
    "gn:name":"Magr\u012b\u0101n-e Yek",
    "gn:population":0,
    "gn:timezone":"Asia/Tehran",
    "iso:country":"IR",
    "name:fas_x_preferred":[
        "\u0645\u06af\u0631\u06cc\u0627\u0646 \u06cc\u06a9"
    ],
    "name:fas_x_variant":[
        "Magr\u012b\u0101n-e Yek"
    ],
    "wof:name":"Magrian-e Yek",
    "wof:placetype":"locality"
},
  "geometry": {"coordinates":[48.453,31.7478],"type":"Point"}
}