{
  "type": "Feature",
  "properties": {
    "gn:admin1_code":"10",
    "gn:asciiname":"Delgosha",
    "gn:country_code":"IR",
    "gn:dem":1397,
    "gn:feature_class":"P",
    "gn:feature_code":"PPL",
    "gn:name":"Delgosh\u0101",
    "gn:population":0,
    "gn:timezone":"Asia/Tehran",
    "iso:country":"IR",
    "name:ara_x_preferred":[
        "\u062f\u0644\u063a\u0634\u0627"
    ],
    "name:aze_x_preferred":[
        "Dilgu\u015fa"
    ],
    "name:ceb_x_preferred":[
        "Delgosh\u0101"
    ],
    "name:fas_x_preferred":[
        "\u062f\u0644\u06a9\u0634\u0627\u062f"
    ],
    "name:fas_x_variant":[
        "\u062f\u0644\u06af\u0634\u0627"
    ],
    "name:ita_x_preferred":[
        "Delgosha"
    ],
    "name:mlg_x_preferred":[
        "Delgosha"
    ],
    "name:msa_x_preferred":[
        "Delgosha"
    ],
    "name:pol_x_preferred":[
        "Delgosza"
    ],
    "name:rus_x_preferred":[
        "\u0414\u0435\u043b\u044c\u0433\u043e\u0448\u0430"
    ],
    "name:swe_x_preferred":[
        "Delgosh\u0101"
    ],
    "name:tur_x_preferred":[
        "Dilgu\u015fa"
    ],
    "name:und_x_variant":[
        "Delkash\u0101d"
    ],
    "wof:name":"Delgosha",
    "wof:placetype":"locality"
},
  "geometry": {"coordinates":[46.5948,33.4057],"type":"Point"}
}