{
  "type": "Feature",
  "properties": {
    "gn:admin1_code":"10",
    "gn:asciiname":"Delgosha",
    "gn:country_code":"IR",
    "gn:dem":1397,
    "gn:feature_class":"P",
    "gn:feature_code":"PPL",
    "gn:name":"Delgosh\u0101",
    "gn:population":0,
    "gn:timezone":"Asia/Tehran",
    "iso:country":"IR",
    "name:fas_x_preferred":[
        "\u062f\u0644\u06a9\u0634\u0627\u062f"
    ],
    "name:fas_x_variant":[
        "\u062f\u0644\u06af\u0634\u0627"
    ],
    "name:und_x_variant":[
        "Delkash\u0101d",
        "Delgosh\u0101"
    ],
    "wof:name":"Delgosha",
    "wof:placetype":"locality"
},
  "geometry": {"coordinates":[46.5948,33.4057],"type":"Point"}
}