{
  "type": "Feature",
  "properties": {
    "gn:admin1_code":"5",
    "gn:asciiname":"Tang-e Alak",
    "gn:country_code":"IR",
    "gn:dem":1994,
    "gn:feature_class":"P",
    "gn:feature_code":"PPL",
    "gn:name":"Tang-e \u0100lak",
    "gn:population":0,
    "gn:timezone":"Asia/Tehran",
    "iso:country":"IR",
    "name:fas_x_preferred":[
        "Tang-e \u0100lak"
    ],
    "name:fas_x_variant":[
        "Tang \u0100lak",
        "\u062a\u0646\u06af \u0622\u0644\u06a9"
    ],
    "wof:name":"Tang-e Alak",
    "wof:placetype":"locality"
},
  "geometry": {"coordinates":[50.86215,31.07346],"type":"Point"}
}