{
  "type": "Feature",
  "properties": {
    "gn:admin1_code":"35.0",
    "gn:asciiname":"Kuseh Raz",
    "gn:country_code":"IR",
    "gn:dem":6,
    "gn:feature_class":"P",
    "gn:feature_code":"PPL",
    "gn:name":"K\u016bseh Raz",
    "gn:population":0,
    "gn:timezone":"Asia/Tehran",
    "iso:country":"IR",
    "name:fas_x_preferred":[
        "\u0643\u0648\u0633\u0647 \u0631\u0632"
    ],
    "name:fas_x_variant":[
        "K\u016bseh Raz"
    ],
    "wof:name":"Kuseh Raz",
    "wof:placetype":"locality"
},
  "geometry": {"coordinates":[52.2573,36.53401],"type":"Point"}
}