{
  "type": "Feature",
  "properties": {
    "gn:admin1_code":"4.0",
    "gn:asciiname":"Kandez",
    "gn:country_code":"IR",
    "gn:dem":989,
    "gn:feature_class":"P",
    "gn:feature_code":"PPL",
    "gn:name":"Kandez",
    "gn:population":0,
    "gn:timezone":"Asia/Tehran",
    "iso:country":"IR",
    "name:fas_x_preferred":[
        "\u06a9\u0646\u062f\u0632"
    ],
    "name:und_x_variant":[
        "Kandaz",
        "Kondowz",
        "Kandez",
        "\u06a9\u0646\u062f\u0632"
    ],
    "wof:name":"Kandez",
    "wof:placetype":"locality"
},
  "geometry": {"coordinates":[61.38279,26.65112],"type":"Point"}
}