{
  "type": "Feature",
  "properties": {
    "gn:admin1_code":"7.0",
    "gn:asciiname":"`Arabuyeh",
    "gn:country_code":"IR",
    "gn:dem":1885,
    "gn:feature_class":"P",
    "gn:feature_code":"PPL",
    "gn:name":"\u2018Arab\u016byeh",
    "gn:population":0,
    "gn:timezone":"Asia/Tehran",
    "iso:country":"IR",
    "name:fas_x_preferred":[
        "\u0639\u0631\u0628\u0648\u06cc\u0647"
    ],
    "name:fas_x_variant":[
        "\u2018Arab\u016b",
        "\u2018Arab\u016byeh"
    ],
    "name:msa_x_preferred":[
        "Arabuyeh"
    ],
    "name:und_x_variant":[
        "Araboo",
        "\u2018Arbeh",
        "\u2018Arab\u012b"
    ],
    "wof:name":"`Arabuyeh",
    "wof:placetype":"locality"
},
  "geometry": {"coordinates":[54.5724,29.032],"type":"Point"}
}