{
  "type": "Feature",
  "properties": {
    "gn:admin1_code":"1",
    "gn:asciiname":"Shiveh",
    "gn:country_code":"IR",
    "gn:dem":2125,
    "gn:feature_class":"P",
    "gn:feature_code":"PPL",
    "gn:name":"Sh\u012bveh",
    "gn:population":0,
    "gn:timezone":"Asia/Tehran",
    "iso:country":"IR",
    "name:fas_x_preferred":[
        "\u0634\u06cc\u0648\u0647"
    ],
    "name:fas_x_variant":[
        "Sh\u012bveh",
        "\u06cc\u06cc\u0644\u0627\u0642 \u0634\u06cc\u0648\u0647"
    ],
    "wof:name":"Shiveh",
    "wof:placetype":"locality"
},
  "geometry": {"coordinates":[44.4718,38.0899],"type":"Point"}
}