{
  "type": "Feature",
  "properties": {
    "gn:admin1_code":"34",
    "gn:asciiname":"Saqarjuq",
    "gn:country_code":"IR",
    "gn:dem":1957,
    "gn:feature_class":"P",
    "gn:feature_code":"PPL",
    "gn:name":"Saqarj\u016bq",
    "gn:population":0,
    "gn:timezone":"Asia/Tehran",
    "iso:country":"IR",
    "name:fas_x_preferred":[
        "\u0633\u064e\u0642\u064e\u0631\u062c\u0648\u0642"
    ],
    "wof:name":"Saqarjuq",
    "wof:placetype":"locality"
},
  "geometry": {"coordinates":[49.88333,34.53333],"type":"Point"}
}