{
  "type": "Feature",
  "properties": {
    "gn:admin1_code":"28",
    "gn:asciiname":"Zarg",
    "gn:country_code":"IR",
    "gn:dem":1124,
    "gn:feature_class":"P",
    "gn:feature_code":"PPL",
    "gn:name":"Zarg",
    "gn:population":0,
    "gn:timezone":"Asia/Tehran",
    "iso:country":"IR",
    "name:fas_x_preferred":[
        "\u0632\u064e\u0631\u06af"
    ],
    "wof:name":"Zarg",
    "wof:placetype":"locality"
},
  "geometry": {"coordinates":[51.75,33.78333],"type":"Point"}
}