{
  "type": "Feature",
  "properties": {
    "gn:admin1_code":"16",
    "gn:asciiname":"Qomchoqay",
    "gn:country_code":"IR",
    "gn:dem":1598,
    "gn:feature_class":"P",
    "gn:feature_code":"PPL",
    "gn:name":"Qomchoq\u0101y",
    "gn:population":0,
    "gn:timezone":"Asia/Tehran",
    "iso:country":"IR",
    "name:fas_x_preferred":[
        "\u0642\u0645 \u0686\u0642\u0627"
    ],
    "name:fas_x_variant":[
        "Qomchoq\u0101y",
        "Qom Choq\u0101",
        "\u0642\u0645\u0686\u0642\u0627\u06cc"
    ],
    "name:und_x_variant":[
        "Qamcheq\u0101y"
    ],
    "wof:name":"Qomchoqay",
    "wof:placetype":"locality"
},
  "geometry": {"coordinates":[47.62504000000001,36.1669],"type":"Point"}
}