{
  "type": "Feature",
  "properties": {
    "gn:admin1_code":"13",
    "gn:asciiname":"Gakiyeh",
    "gn:country_code":"IR",
    "gn:dem":1318,
    "gn:feature_class":"P",
    "gn:feature_code":"PPL",
    "gn:name":"G\u0101k\u012byeh",
    "gn:population":0,
    "gn:timezone":"Asia/Tehran",
    "iso:country":"IR",
    "name:fas_x_preferred":[
        "\u06af\u0627\u06a9\u06cc\u0651\u0647"
    ],
    "name:fas_x_variant":[
        "G\u0101k\u012byeh"
    ],
    "name:und_x_variant":[
        "Gak\u012ba",
        "G\u0101keyeh"
    ],
    "wof:name":"Gakiyeh",
    "wof:placetype":"locality"
},
  "geometry": {"coordinates":[46.9612,34.575],"type":"Point"}
}