{
  "type": "Feature",
  "properties": {
    "gn:admin1_code":"15",
    "gn:asciiname":"Bakhtegan",
    "gn:country_code":"IR",
    "gn:dem":830,
    "gn:feature_class":"P",
    "gn:feature_code":"PPL",
    "gn:name":"Bakhteg\u0101n",
    "gn:population":0,
    "gn:timezone":"Asia/Tehran",
    "iso:country":"IR",
    "name:fas_x_preferred":[
        "Bakhteg\u0101n-e \u2018Oly\u0101"
    ],
    "name:fas_x_variant":[
        "Bakhteg\u0101n",
        "\u0628\u062e\u062a\u06af\u0627\u0646"
    ],
    "wof:name":"Bakhtegan",
    "wof:placetype":"locality"
},
  "geometry": {"coordinates":[49.94393,31.54331],"type":"Point"}
}