{
  "type": "Feature",
  "properties": {
    "gn:admin1_code":"4.0",
    "gn:asciiname":"Nikkan",
    "gn:country_code":"IR",
    "gn:dem":1078,
    "gn:feature_class":"P",
    "gn:feature_code":"PPL",
    "gn:name":"N\u012bkk\u0101n",
    "gn:population":0,
    "gn:timezone":"Asia/Tehran",
    "iso:country":"IR",
    "name:fas_x_preferred":[
        "\u0646\u064a\u0643\u0651\u0627\u0646"
    ],
    "name:fas_x_variant":[
        "\u0646\u0650\u0643\u0627\u0646",
        "N\u012bkk\u0101n"
    ],
    "name:und_x_variant":[
        "Nek\u0101n"
    ],
    "wof:name":"Nikkan",
    "wof:placetype":"locality"
},
  "geometry": {"coordinates":[62.35,27.11667000000001],"type":"Point"}
}