{
  "type": "Feature",
  "properties": {
    "gn:admin1_code":"11.0",
    "gn:asciiname":"Mahraq Sheykh",
    "gn:cc2":"IR",
    "gn:country_code":"IR",
    "gn:dem":19,
    "gn:feature_class":"P",
    "gn:feature_code":"PPL",
    "gn:name":"Ma\u1e29raq Sheykh",
    "gn:population":0,
    "gn:timezone":"Asia/Tehran",
    "iso:country":"IR",
    "name:fas_x_preferred":[
        "\u0645\u064e\u062d\u0631\u064e\u0642 \u0634\u0650\u064a\u062e"
    ],
    "name:fas_x_variant":[
        "\u0645\u0650\u0647\u0631\u0650 \u0634\u0650\u064a\u062e",
        "Ma\u1e29raq Sheykh"
    ],
    "name:und_x_variant":[
        "Mehr-e Sheykh"
    ],
    "wof:name":"Mahraq Sheykh",
    "wof:placetype":"locality"
},
  "geometry": {"coordinates":[56.98333,27.21667],"type":"Point"}
}