{
  "type": "Feature",
  "properties": {
    "gn:admin1_code":"44",
    "gn:asciiname":"Aznaq",
    "gn:country_code":"IR",
    "gn:dem":1517,
    "gn:feature_class":"P",
    "gn:feature_code":"PPL",
    "gn:name":"Aznaq",
    "gn:population":0,
    "gn:timezone":"Asia/Tehran",
    "iso:country":"IR",
    "name:ceb_x_preferred":[
        "Aznaq"
    ],
    "name:fas_x_preferred":[
        "\u0627\u0632\u0646\u0642"
    ],
    "name:msa_x_preferred":[
        "Aznaq"
    ],
    "name:swe_x_preferred":[
        "Aznaq"
    ],
    "wof:name":"Aznaq",
    "wof:placetype":"locality"
},
  "geometry": {"coordinates":[50.8183,35.975],"type":"Point"}
}