{
  "type": "Feature",
  "properties": {
    "gn:admin1_code":"3",
    "gn:asciiname":"Qal`eh Darvish",
    "gn:country_code":"IR",
    "gn:dem":1818,
    "gn:feature_class":"P",
    "gn:feature_code":"PPL",
    "gn:name":"Qal\u2018eh Darv\u012bsh",
    "gn:population":0,
    "gn:timezone":"Asia/Tehran",
    "iso:country":"IR",
    "name:fas_x_preferred":[
        "\u0642\u064e\u0644\u0639\u0650\u06c0 \u062f\u064e\u0631\u0648\u064a\u0634"
    ],
    "name:fas_x_variant":[
        "Qal\u2018eh Darv\u012bsh",
        "\u0642\u0644\u0639\u0647 \u062f\u0631\u0648\u064a\u0634"
    ],
    "name:und_x_variant":[
        "Ghal\u2018eh Darvish",
        "Qal\u2018eh-ye Darv\u012bsh"
    ],
    "wof:name":"Qal`eh Darvish",
    "wof:placetype":"locality"
},
  "geometry": {"coordinates":[50.51318,32.10777],"type":"Point"}
}