{
  "type": "Feature",
  "properties": {
    "gn:admin1_code":"28.0",
    "gn:asciiname":"Shahedan-e Pa'in",
    "gn:country_code":"IR",
    "gn:dem":1774,
    "gn:feature_class":"P",
    "gn:feature_code":"PPL",
    "gn:name":"Sh\u0101hed\u0101n-e P\u0101\u2019\u012bn",
    "gn:population":0,
    "gn:timezone":"Asia/Tehran",
    "iso:country":"IR",
    "wof:name":"Shahedan-e Pa'in",
    "wof:placetype":"locality"
},
  "geometry": {"coordinates":[51.19417,32.66556],"type":"Point"}
}