{
  "type": "Feature",
  "properties": {
    "gn:admin1_code":"33",
    "gn:asciiname":"Yaddi Bolagh",
    "gn:country_code":"IR",
    "gn:dem":1496,
    "gn:elevation":"0.0",
    "gn:feature_class":"P",
    "gn:feature_code":"PPL",
    "gn:name":"Yadd\u012b Bol\u0101gh",
    "gn:population":0,
    "gn:timezone":"Asia/Tehran",
    "iso:country":"IR",
    "name:fas_x_preferred":[
        "\u06cc\u062f\u06cc \u0628\u0644\u0627\u063a"
    ],
    "name:fas_x_variant":[
        "Yadd\u012b Bol\u0101gh",
        "\u06cc\u062f\u06cc\u200c\u0628\u0644\u0627\u063a"
    ],
    "wof:name":"Yaddi Bolagh",
    "wof:placetype":"locality"
},
  "geometry": {"coordinates":[47.2998,38.9486],"type":"Point"}
}