{
  "type": "Feature",
  "properties": {
    "gn:admin1_code":"22",
    "gn:asciiname":"Ehsham-e Gankhiki",
    "gn:country_code":"IR",
    "gn:dem":21,
    "gn:feature_class":"P",
    "gn:feature_code":"PPL",
    "gn:name":"E\u1e29sh\u0101m-e Gankh\u012bk\u012b",
    "gn:population":0,
    "gn:timezone":"Asia/Tehran",
    "iso:country":"IR",
    "name:fas_x_preferred":[
        "\u0627\u0650\u062d\u0634\u0627\u0645\u0650 \u06af\u064e\u0646\u062e\u064a\u0643\u06cc"
    ],
    "name:fas_x_variant":[
        "E\u1e29sh\u0101m-e Gankh\u012bk\u012b"
    ],
    "wof:name":"Ehsham-e Gankhiki",
    "wof:placetype":"locality"
},
  "geometry": {"coordinates":[51.93333,27.96667],"type":"Point"}
}