{
  "type": "Feature",
  "properties": {
    "gn:admin1_code":"29.0",
    "gn:asciiname":"Deh Shur",
    "gn:country_code":"IR",
    "gn:dem":382,
    "gn:feature_class":"P",
    "gn:feature_code":"PPL",
    "gn:name":"Deh Sh\u016br",
    "gn:population":0,
    "gn:timezone":"Asia/Tehran",
    "iso:country":"IR",
    "name:fas_x_preferred":[
        "\u062f\u0647 \u0634\u0648\u0631"
    ],
    "name:fas_x_variant":[
        "Deh Sh\u016br"
    ],
    "wof:name":"Deh Shur",
    "wof:placetype":"locality"
},
  "geometry": {"coordinates":[57.4883,27.4538],"type":"Point"}
}