{
  "type": "Feature",
  "properties": {
    "gn:admin1_code":"7",
    "gn:asciiname":"Darengun",
    "gn:country_code":"IR",
    "gn:dem":1843,
    "gn:feature_class":"P",
    "gn:feature_code":"PPL",
    "gn:name":"D\u0101reng\u016bn",
    "gn:population":0,
    "gn:timezone":"Asia/Tehran",
    "iso:country":"IR",
    "name:fas_x_preferred":[
        "\u062f\u0627\u0631\u0646\u06af\u0648\u0646"
    ],
    "name:fas_x_variant":[
        "D\u0101renj\u0101n",
        "\u062f\u0627\u0631\u0646\u062c\u0627\u0646",
        "D\u0101reng\u016bn"
    ],
    "name:und_x_variant":[
        "D\u0101reng\u0101n",
        "Darinj\u0101n",
        "D\u0101renj\u0101n-e S\u012b\u0101kh"
    ],
    "wof:name":"Darengun",
    "wof:placetype":"locality"
},
  "geometry": {"coordinates":[52.33600000000001,29.4088],"type":"Point"}
}