{
  "type": "Feature",
  "properties": {
    "gn:admin1_code":"16",
    "gn:asciiname":"Bowdela",
    "gn:country_code":"IR",
    "gn:dem":1880,
    "gn:feature_class":"P",
    "gn:feature_code":"PPL",
    "gn:name":"Bowdel\u0101",
    "gn:population":0,
    "gn:timezone":"Asia/Tehran",
    "iso:country":"IR",
    "name:ara_x_preferred":[
        "\u0628\u0648\u062f\u0644\u0627"
    ],
    "name:ceb_x_preferred":[
        "Bowdel\u0101"
    ],
    "name:fas_x_preferred":[
        "\u0628\u0648\u062f\u0644\u0627"
    ],
    "name:fas_x_variant":[
        "\u0645\u064f\u0634\u064a\u0631 \u0622\u0628\u0627\u062f",
        "\u0639\u064e\u0628\u062f \u0627\u0644\u0644\u064e\u0651\u0647",
        "Bowdel\u0101"
    ],
    "name:swe_x_preferred":[
        "Bowdel\u0101"
    ],
    "name:und_x_variant":[
        "Mosh\u012br\u0101b\u0101d",
        "B\u016bdl\u0101",
        "Ubaidullah",
        "\u2018Abdoll\u0101h"
    ],
    "wof:name":"Bowdela",
    "wof:placetype":"locality"
},
  "geometry": {"coordinates":[47.57194000000001,35.53975],"type":"Point"}
}