{
  "type": "Feature",
  "properties": {
    "gn:admin1_code":"33",
    "gn:asciiname":"Marv Dizaj",
    "gn:country_code":"IR",
    "gn:dem":1693,
    "gn:feature_class":"P",
    "gn:feature_code":"PPL",
    "gn:name":"Marv D\u012bzaj",
    "gn:population":0,
    "gn:timezone":"Asia/Tehran",
    "iso:country":"IR",
    "name:ceb_x_preferred":[
        "Marv D\u012bzaj"
    ],
    "name:fas_x_preferred":[
        "\u0645\u0631\u0648 \u062f\u06cc\u0632\u062c"
    ],
    "name:fas_x_variant":[
        "Mor\u016b D\u012bzaj",
        "Marv D\u012bzaj",
        "\u0645\u0631\u0648\u062f\u06cc\u0632\u062c"
    ],
    "name:msa_x_preferred":[
        "Marv Dizaj"
    ],
    "name:swe_x_preferred":[
        "Marv D\u012bzaj"
    ],
    "name:und_x_variant":[
        "Marow D\u012bzaj",
        "Morovu D\u012bzeh",
        "Marov D\u012bzeh",
        "Marovu-Diza",
        "M\u0101rov\u012b D\u012bzeh",
        "M\u0101rv\u012b D\u012bzeh"
    ],
    "wof:name":"Marv Dizaj",
    "wof:placetype":"locality"
},
  "geometry": {"coordinates":[46.069,38.2937],"type":"Point"}
}