{
  "type": "Feature",
  "properties": {
    "gn:admin1_code":"33.0",
    "gn:asciiname":"Luti Qeran",
    "gn:country_code":"IR",
    "gn:dem":1280,
    "gn:feature_class":"P",
    "gn:feature_code":"PPLF",
    "gn:name":"L\u016bt\u012b Qer\u0101n",
    "gn:population":0,
    "gn:timezone":"Asia/Tehran",
    "iso:country":"IR",
    "name:fas_x_preferred":[
        "\u0644\u0648\u062a\u06cc \u0642\u0631\u0627\u0646"
    ],
    "name:und_x_variant":[
        "L\u016bt\u012b Qer\u0101n"
    ],
    "wof:name":"Luti Qeran",
    "wof:placetype":"locality"
},
  "geometry": {"coordinates":[45.70149,38.54783],"type":"Point"}
}