{
  "type": "Feature",
  "properties": {
    "gn:admin1_code":"23",
    "gn:asciiname":"Mian Kharan",
    "gn:country_code":"IR",
    "gn:dem":1612,
    "gn:feature_class":"P",
    "gn:feature_code":"PPL",
    "gn:name":"M\u012b\u0101n Khar\u0101n",
    "gn:population":0,
    "gn:timezone":"Asia/Tehran",
    "iso:country":"IR",
    "name:ceb_x_preferred":[
        "M\u012b\u0101n Khar\u0101n"
    ],
    "name:fas_x_preferred":[
        "\u0645\u06cc\u0627\u0646 \u062e\u0631\u0627\u0646"
    ],
    "name:fas_x_variant":[
        "M\u012b\u0101n Khar\u0101n"
    ],
    "name:swe_x_preferred":[
        "M\u012b\u0101n Khar\u0101n"
    ],
    "name:und_x_variant":[
        "Miy\u0101n Khar\u0101n",
        "Mey\u0101n Khar\u0101n"
    ],
    "wof:name":"Mian Kharan",
    "wof:placetype":"locality"
},
  "geometry": {"coordinates":[48.2338,33.8923],"type":"Point"}
}