{
  "type": "Feature",
  "properties": {
    "gn:admin1_code":"32",
    "gn:asciiname":"Sarilar",
    "gn:country_code":"IR",
    "gn:dem":779,
    "gn:feature_class":"P",
    "gn:feature_code":"PPL",
    "gn:name":"S\u0101r\u012blar",
    "gn:population":0,
    "gn:timezone":"Asia/Tehran",
    "iso:country":"IR",
    "name:ara_x_preferred":[
        "\u0633\u0627\u0631\u064a\u0644\u0627\u0631"
    ],
    "name:fas_x_preferred":[
        "\u0633\u0627\u0631\u06cc \u0644\u0631"
    ],
    "name:fas_x_variant":[
        "S\u0101r\u012blar",
        "\u0633\u0627\u0631\u06cc \u0644\u0627\u0631"
    ],
    "name:msa_x_preferred":[
        "Sarilar"
    ],
    "wof:name":"Sarilar",
    "wof:placetype":"locality"
},
  "geometry": {"coordinates":[47.7398,39.0382],"type":"Point"}
}