{
  "type": "Feature",
  "properties": {
    "gn:admin1_code":"35.0",
    "gn:asciiname":"Ashkalam",
    "gn:country_code":"IR",
    "gn:dem":592,
    "gn:feature_class":"P",
    "gn:feature_code":"PPL",
    "gn:name":"Ashkalam",
    "gn:population":0,
    "gn:timezone":"Asia/Tehran",
    "iso:country":"IR",
    "name:fas_x_preferred":[
        "R\u0101shkalam"
    ],
    "name:fas_x_variant":[
        "\u0631\u0627\u0634\u06a9\u0644\u0645",
        "\u0627\u0634\u06a9\u0644\u0645"
    ],
    "name:und_x_variant":[
        "\u0631\u0627\u0634\u06a9\u0644\u0645",
        "Ashkalam"
    ],
    "wof:name":"Ashkalam",
    "wof:placetype":"locality"
},
  "geometry": {"coordinates":[50.94624,36.69485],"type":"Point"}
}