{
  "type": "Feature",
  "properties": {
    "gn:admin1_code":"29",
    "gn:asciiname":"Deh-e Morteza",
    "gn:country_code":"IR",
    "gn:dem":2917,
    "gn:feature_class":"P",
    "gn:feature_code":"PPL",
    "gn:name":"Deh-e Morte\u1e95\u00e1",
    "gn:population":0,
    "gn:timezone":"Asia/Tehran",
    "iso:country":"IR",
    "name:fas_x_preferred":[
        "\u062f\u0647 \u0645\u0631\u062a\u0636\u06cc"
    ],
    "name:fas_x_variant":[
        "Deh-e Morte\u1e95\u00e1"
    ],
    "name:und_x_variant":[
        "Deh Morte\u1e95\u00e1",
        "Deh Murteza"
    ],
    "wof:name":"Deh-e Morteza",
    "wof:placetype":"locality"
},
  "geometry": {"coordinates":[57.1954,29.5181],"type":"Point"}
}