{
  "type": "Feature",
  "properties": {
    "gn:admin1_code":"13",
    "gn:asciiname":"Sang Dar Meydan-e `Olya",
    "gn:country_code":"IR",
    "gn:dem":660,
    "gn:feature_class":"P",
    "gn:feature_code":"PPL",
    "gn:name":"Sang Dar Meyd\u0101n-e \u2018Oly\u0101",
    "gn:population":0,
    "gn:timezone":"Asia/Tehran",
    "iso:country":"IR",
    "name:fas_x_preferred":[
        "\u0633\u0646\u06af \u062f\u0631 \u0645\u06cc\u062f\u0627\u0646 \u0639\u0644\u06cc\u0627"
    ],
    "name:fas_x_variant":[
        "Sang Dar Meyd\u0101n-e \u2018Oly\u0101"
    ],
    "wof:name":"Sang Dar Meydan-e `Olya",
    "wof:placetype":"locality"
},
  "geometry": {"coordinates":[45.86994,34.34738],"type":"Point"}
}