{
  "type": "Feature",
  "properties": {
    "gn:admin1_code":"40",
    "gn:asciiname":"Aminabad-e Shavvaz",
    "gn:country_code":"IR",
    "gn:dem":2268,
    "gn:feature_class":"P",
    "gn:feature_code":"PPL",
    "gn:name":"Am\u012bn\u0101b\u0101d-e Shavv\u0101z",
    "gn:population":0,
    "gn:timezone":"Asia/Tehran",
    "iso:country":"IR",
    "name:fas_x_preferred":[
        "\u0627\u0645\u06cc\u0646 \u0622\u0628\u0627\u062f \u0634\u0648\u0651\u0627\u0632"
    ],
    "name:fas_x_variant":[
        "Am\u012bn\u0101b\u0101d-e Shavv\u0101z"
    ],
    "wof:name":"Aminabad-e Shavvaz",
    "wof:placetype":"locality"
},
  "geometry": {"coordinates":[53.6466,31.7185],"type":"Point"}
}