{
  "type": "Feature",
  "properties": {
    "gn:admin1_code":"29",
    "gn:asciiname":"Gowdab",
    "gn:country_code":"IR",
    "gn:dem":634,
    "gn:feature_class":"P",
    "gn:feature_code":"PPL",
    "gn:name":"Gowd\u0101b",
    "gn:population":0,
    "gn:timezone":"Asia/Tehran",
    "iso:country":"IR",
    "name:fas_x_preferred":[
        "\u06af\u0648\u062f \u0622\u0628"
    ],
    "name:fas_x_variant":[
        "Gowd\u0101b"
    ],
    "wof:name":"Gowdab",
    "wof:placetype":"locality"
},
  "geometry": {"coordinates":[58.62388000000001,27.98336],"type":"Point"}
}