{
  "type": "Feature",
  "properties": {
    "gn:admin1_code":"7.0",
    "gn:asciiname":"Kal Hasinak",
    "gn:country_code":"IR",
    "gn:dem":1689,
    "gn:feature_class":"P",
    "gn:feature_code":"PPL",
    "gn:name":"Kal \u1e28as\u012bnak",
    "gn:population":0,
    "gn:timezone":"Asia/Tehran",
    "iso:country":"IR",
    "name:fas_x_preferred":[
        "Kal Has\u012bnak"
    ],
    "name:fas_x_variant":[
        "\u06a9\u0644 \u0647\u0633\u06cc\u0646\u06a9",
        "\u06a9\u0644 \u062d\u0633\u06cc\u0646\u06a9",
        "\u06af\u0631\u062f \u06a9\u0644 \u062d\u0633\u06cc\u0646\u06a9"
    ],
    "name:und_x_variant":[
        "Kal \u1e28as\u012bnak",
        "Gerd Kal \u1e28as\u012bnak"
    ],
    "wof:name":"Kal Hasinak",
    "wof:placetype":"locality"
},
  "geometry": {"coordinates":[51.49419,30.3862],"type":"Point"}
}