{
  "type": "Feature",
  "properties": {
    "gn:admin1_code":"16",
    "gn:asciiname":"Takht",
    "gn:country_code":"IR",
    "gn:dem":1873,
    "gn:feature_class":"P",
    "gn:feature_code":"PPL",
    "gn:name":"Takht",
    "gn:population":0,
    "gn:timezone":"Asia/Tehran",
    "iso:country":"IR",
    "name:fas_x_preferred":[
        "\u062a\u062e\u062a \u0639\u0644\u064a\u0627"
    ],
    "name:fas_x_variant":[
        "\u062a\u064e\u062e\u062a \u0627\u064f\u0644\u064a\u064e",
        "\u062a\u062e\u062a",
        "\u062a\u064e\u0686\u062a",
        "Takht-e \u2018Oly\u0101"
    ],
    "name:und_x_variant":[
        "Takht Olya",
        "Tacht",
        "Takht"
    ],
    "wof:name":"Takht",
    "wof:placetype":"locality"
},
  "geometry": {"coordinates":[47.63076,35.88793],"type":"Point"}
}