{
  "type": "Feature",
  "properties": {
    "gn:admin1_code":"36",
    "gn:asciiname":"Kanavand",
    "gn:country_code":"IR",
    "gn:dem":1485,
    "gn:feature_class":"P",
    "gn:feature_code":"PPL",
    "gn:name":"Kan\u0101vand",
    "gn:population":0,
    "gn:timezone":"Asia/Tehran",
    "iso:country":"IR",
    "name:fas_x_preferred":[
        "\u0643\u0646\u0627\u0648\u0646\u062f"
    ],
    "name:fas_x_variant":[
        "\u0643\u0650\u0646\u0627\u0648\u064e\u0646\u062f",
        "\u0643\u064e\u0646\u0648\u064e\u0646\u062f",
        "Kan\u0101vand"
    ],
    "name:und_x_variant":[
        "Ken\u0101vand",
        "Kanvand",
        "Kanawand"
    ],
    "wof:name":"Kanavand",
    "wof:placetype":"locality"
},
  "geometry": {"coordinates":[48.23428,36.80435],"type":"Point"}
}