{
  "type": "Feature",
  "properties": {
    "gn:admin1_code":"26",
    "gn:asciiname":"Lowbar",
    "gn:cc2":"IR",
    "gn:country_code":"IR",
    "gn:dem":2089,
    "gn:feature_class":"P",
    "gn:feature_code":"PPL",
    "gn:name":"Lowbar",
    "gn:population":0,
    "gn:timezone":"Asia/Tehran",
    "iso:country":"IR",
    "name:fas_x_preferred":[
        "\u0644\u064f\u0648\u0628\u064e\u0631"
    ],
    "name:und_x_variant":[
        "Luber",
        "Lowbar"
    ],
    "wof:name":"Lowbar",
    "wof:placetype":"locality"
},
  "geometry": {"coordinates":[52.09111,35.70667],"type":"Point"}
}