{
  "type": "Feature",
  "properties": {
    "gn:admin1_code":"25",
    "gn:asciiname":"Berom",
    "gn:country_code":"IR",
    "gn:dem":1094,
    "gn:feature_class":"P",
    "gn:feature_code":"PPL",
    "gn:name":"Berom",
    "gn:population":0,
    "gn:timezone":"Asia/Tehran",
    "iso:country":"IR",
    "name:fas_x_preferred":[
        "\u0628\u0631\u0645"
    ],
    "name:fra_x_preferred":[
        "Birom"
    ],
    "wof:name":"Berom",
    "wof:placetype":"locality"
},
  "geometry": {"coordinates":[54.42100000000001,36.14347],"type":"Point"}
}