{
  "type": "Feature",
  "properties": {
    "gn:admin1_code":"13",
    "gn:asciiname":"Anjab",
    "gn:country_code":"IR",
    "gn:dem":1606,
    "gn:feature_class":"P",
    "gn:feature_code":"PPL",
    "gn:name":"Anj\u0101b",
    "gn:population":0,
    "gn:timezone":"Asia/Tehran",
    "iso:country":"IR",
    "name:fas_x_preferred":[
        "\u0627\u0646\u062c\u0627\u0628"
    ],
    "name:fas_x_variant":[
        "Anj\u0101b"
    ],
    "wof:name":"Anjab",
    "wof:placetype":"locality"
},
  "geometry": {"coordinates":[47.24635,33.96365],"type":"Point"}
}