{
  "type": "Feature",
  "properties": {
    "gn:admin1_code":"29",
    "gn:asciiname":"Sohrabi-ye Parig",
    "gn:country_code":"IR",
    "gn:dem":640,
    "gn:feature_class":"P",
    "gn:feature_code":"PPL",
    "gn:name":"Sohr\u0101b\u012b-ye P\u0101r\u012bg",
    "gn:population":0,
    "gn:timezone":"Asia/Tehran",
    "iso:country":"IR",
    "name:fas_x_preferred":[
        "\u067e\u0627\u0631\u06cc\u0646\u06af \u0633\u0647\u0631\u0627\u0628\u06cc"
    ],
    "name:fas_x_variant":[
        "P\u0101r\u012bng-e Sohr\u0101b\u012b",
        "\u0633\u0647\u0631\u0627\u0628\u06cc \u067e\u0627\u0631\u06cc\u06af",
        "\u0645\u0648\u062a\u0648\u0631\u0647\u0627\u06cc \u067e\u0627\u0631\u06cc\u06a9 \u0627\u0645\u06cc\u0631\u06cc"
    ],
    "name:und_x_variant":[
        "Sohr\u0101b\u012b-ye P\u0101r\u012bg",
        "Mowtowrh\u0101-ye P\u0101r\u012bk Am\u012br\u012b"
    ],
    "wof:name":"Sohrabi-ye Parig",
    "wof:placetype":"locality"
},
  "geometry": {"coordinates":[57.3202,28.1387],"type":"Point"}
}