{
  "type": "Feature",
  "properties": {
    "gn:admin1_code":"35.0",
    "gn:asciiname":"Takish",
    "gn:country_code":"IR",
    "gn:dem":76,
    "gn:feature_class":"P",
    "gn:feature_code":"PPL",
    "gn:name":"Tak\u012bsh",
    "gn:population":0,
    "gn:timezone":"Asia/Tehran",
    "iso:country":"IR",
    "name:fas_x_preferred":[
        "Sar Kalleh Ch\u0101y"
    ],
    "name:fas_x_variant":[
        "\u0633\u0631 \u06a9\u0644\u0647 \u0686\u0627\u06cc",
        "\u062a\u06a9\u064a\u0634"
    ],
    "name:und_x_variant":[
        "Tak\u012bsh"
    ],
    "wof:name":"Takish",
    "wof:placetype":"locality"
},
  "geometry": {"coordinates":[50.78342,36.78422],"type":"Point"}
}