{
  "type": "Feature",
  "properties": {
    "gn:admin1_code":"40.0",
    "gn:asciiname":"Shahriari-ye `Olya",
    "gn:country_code":"IR",
    "gn:dem":1745,
    "gn:feature_class":"P",
    "gn:feature_code":"PPL",
    "gn:name":"Shahr\u012b\u0101r\u012b-ye \u2018Olya",
    "gn:population":0,
    "gn:timezone":"Asia/Tehran",
    "iso:country":"IR",
    "name:fas_x_preferred":[
        "Shahr\u012b\u0101r\u012b-ye \u2018Olya"
    ],
    "name:fas_x_variant":[
        "\u0634\u0647\u0631\u06cc\u0627\u0631\u06cc \u0639\u0644\u06cc\u0627"
    ],
    "name:und_x_variant":[
        "Shahr\u012by\u0101r\u012b"
    ],
    "wof:name":"Shahriari-ye `Olya",
    "wof:placetype":"locality"
},
  "geometry": {"coordinates":[54.31365,29.68658],"type":"Point"}
}