{
  "type": "Feature",
  "properties": {
    "gn:admin1_code":"1",
    "gn:asciiname":"Gerd-e Kashan",
    "gn:country_code":"IR",
    "gn:dem":1468,
    "gn:feature_class":"P",
    "gn:feature_code":"PPL",
    "gn:name":"Gerd-e K\u0101sh\u0101n",
    "gn:population":0,
    "gn:timezone":"Asia/Tehran",
    "iso:country":"IR",
    "name:azb_x_preferred":[
        "\u06af\u0631\u062f\u06a9\u0627\u0634\u0627\u0646"
    ],
    "name:aze_x_preferred":[
        "G\u0259rd-i K\u0259\u015fan"
    ],
    "name:ceb_x_preferred":[
        "Gerd-e K\u0101sh\u0101n"
    ],
    "name:fas_x_preferred":[
        "\u06af\u0631\u062f \u06a9\u0627\u0634\u0627\u0646"
    ],
    "name:fas_x_variant":[
        "Gerd-e K\u0101sh\u0101n",
        "\u06af\u0631\u062f\u06a9\u0627\u0634\u0627\u0646"
    ],
    "name:msa_x_preferred":[
        "Gerd-e Kashan"
    ],
    "name:swe_x_preferred":[
        "Gerd-e K\u0101sh\u0101n"
    ],
    "wof:name":"Gerd-e Kashan",
    "wof:placetype":"locality"
},
  "geometry": {"coordinates":[45.1576,37.0811],"type":"Point"}
}