{
  "type": "Feature",
  "properties": {
    "gn:admin1_code":"38",
    "gn:asciiname":"Valazjerd",
    "gn:country_code":"IR",
    "gn:dem":1244,
    "gn:feature_class":"P",
    "gn:feature_code":"PPL",
    "gn:name":"Val\u0101zjerd",
    "gn:population":0,
    "gn:timezone":"Asia/Tehran",
    "iso:country":"IR",
    "name:fas_x_preferred":[
        "Vel\u0101zjerd"
    ],
    "name:fas_x_variant":[
        "Val\u0101zjerd",
        "\u0648\u0644\u0627\u0632\u062c\u0631\u062f"
    ],
    "name:und_x_variant":[
        "W\u0101l\u0101zird",
        "Val\u0101zjerd",
        "\u0648\u0644\u0627\u0632\u062c\u0631\u062f"
    ],
    "wof:name":"Valazjerd",
    "wof:placetype":"locality"
},
  "geometry": {"coordinates":[49.77394,35.99825999999999],"type":"Point"}
}