{
  "type": "Feature",
  "properties": {
    "gn:admin1_code":"15.0",
    "gn:asciiname":"Abu Sokheyl",
    "gn:country_code":"IR",
    "gn:dem":8,
    "gn:feature_class":"P",
    "gn:feature_code":"PPL",
    "gn:name":"Ab\u016b Sokheyl",
    "gn:population":0,
    "gn:timezone":"Asia/Tehran",
    "iso:country":"IR",
    "name:fas_x_preferred":[
        "Ab\u016b Sokheyl"
    ],
    "wof:name":"Abu Sokheyl",
    "wof:placetype":"locality"
},
  "geometry": {"coordinates":[47.89472,31.59639],"type":"Point"}
}