{
  "type": "Feature",
  "properties": {
    "gn:admin1_code":"1",
    "gn:asciiname":"Qeshlaq-e Khanjar",
    "gn:country_code":"IR",
    "gn:dem":1278,
    "gn:feature_class":"P",
    "gn:feature_code":"PPL",
    "gn:name":"Qeshl\u0101q-e Khanjar",
    "gn:population":0,
    "gn:timezone":"Asia/Tehran",
    "iso:country":"IR",
    "name:fas_x_preferred":[
        "\u062e\u064e\u0646\u062c\u064e\u0631 \u0642\u0650\u0634\u0644\u0627\u0642\u06cc"
    ],
    "name:fas_x_variant":[
        "\u0642\u0634\u0644\u0627\u0642 \u062e\u0646\u062c\u0631",
        "Khanjar Qeshl\u0101q\u012b",
        "Qeshl\u0101q-e Khanjar"
    ],
    "wof:name":"Qeshlaq-e Khanjar",
    "wof:placetype":"locality"
},
  "geometry": {"coordinates":[45.216,37.477],"type":"Point"}
}