{
  "type": "Feature",
  "properties": {
    "gn:admin1_code":"28",
    "gn:asciiname":"Parzegan-e `Olya",
    "gn:country_code":"IR",
    "gn:dem":2503,
    "gn:feature_class":"P",
    "gn:feature_code":"PPL",
    "gn:name":"Parzeg\u0101n-e \u2018Oly\u0101",
    "gn:population":0,
    "gn:timezone":"Asia/Tehran",
    "iso:country":"IR",
    "name:fas_x_preferred":[
        "Parzehg\u0101n-e \u2018Oly\u0101"
    ],
    "name:fas_x_variant":[
        "Parzeg\u0101n-e \u2018Oly\u0101",
        "\u067e\u0631\u0632\u06af\u0627\u0646 \u0639\u0644\u06cc\u0627"
    ],
    "wof:name":"Parzegan-e `Olya",
    "wof:placetype":"locality"
},
  "geometry": {"coordinates":[50.33621,32.69792],"type":"Point"}
}