{
  "type": "Feature",
  "properties": {
    "gn:admin1_code":"9",
    "gn:asciiname":"Kand Bolaghi",
    "gn:country_code":"IR",
    "gn:dem":1844,
    "gn:feature_class":"P",
    "gn:feature_code":"PPL",
    "gn:name":"Kand Bol\u0101gh\u012b",
    "gn:population":0,
    "gn:timezone":"Asia/Tehran",
    "iso:country":"IR",
    "name:fas_x_preferred":[
        "\u0643\u0646\u062f \u0628\u0644\u0627\u063a\u06cc"
    ],
    "name:fas_x_variant":[
        "Kand-e Bol\u0101q\u012b",
        "Kand-e Bol\u0101gh\u012b"
    ],
    "name:und_x_variant":[
        "Gonbad Bolaghi",
        "Kand Bul\u0101khe",
        "Kand Bol\u0101gh\u012b"
    ],
    "wof:name":"Kand Bolaghi",
    "wof:placetype":"locality"
},
  "geometry": {"coordinates":[48.32275,35.43009],"type":"Point"}
}