{
  "type": "Feature",
  "properties": {
    "gn:admin1_code":"15.0",
    "gn:asciiname":"Kut-e Navaser",
    "gn:country_code":"IR",
    "gn:dem":16,
    "gn:feature_class":"P",
    "gn:feature_code":"PPL",
    "gn:name":"K\u016bt-e Nav\u0101\u015fer",
    "gn:population":0,
    "gn:timezone":"Asia/Tehran",
    "iso:country":"IR",
    "name:azb_x_preferred":[
        "\u0643\u0648\u062a \u0646\u0648\u0627\u0635\u0631(\u0627\u0647\u0648\u0627\u0632)"
    ],
    "name:fas_x_preferred":[
        "K\u016bt on Nav\u0101\u015fer"
    ],
    "name:fas_x_variant":[
        "\u06a9\u0648\u062a \u0627\u0644\u0646\u0648\u0627\u0635\u0631",
        "\u06a9\u0648\u062a \u0646\u0648\u0627\u0635\u0631"
    ],
    "name:und_x_variant":[
        "\u06a9\u0648\u062a \u0627\u0644\u0646\u0648\u0627\u0635\u0631",
        "K\u016bt-e Nav\u0101\u015fer"
    ],
    "wof:name":"Kut-e Navaser",
    "wof:placetype":"locality"
},
  "geometry": {"coordinates":[48.66038,31.22259],"type":"Point"}
}