{
  "type": "Feature",
  "properties": {
    "gn:admin1_code":"40",
    "gn:asciiname":"Malvand",
    "gn:country_code":"IR",
    "gn:dem":1298,
    "gn:feature_class":"P",
    "gn:feature_code":"PPL",
    "gn:name":"Malvand",
    "gn:population":0,
    "gn:timezone":"Asia/Tehran",
    "iso:country":"IR",
    "name:fas_x_preferred":[
        "\u0645\u0644\u0648\u0646\u062f"
    ],
    "name:und_x_variant":[
        "\u0645\u0644\u0648\u0646\u062f"
    ],
    "wof:name":"Malvand",
    "wof:placetype":"locality"
},
  "geometry": {"coordinates":[57.03281,33.92725],"type":"Point"}
}