{
  "type": "Feature",
  "properties": {
    "gn:admin1_code":"37",
    "gn:asciiname":"Kasgan Qujaq",
    "gn:country_code":"IR",
    "gn:dem":76,
    "gn:feature_class":"P",
    "gn:feature_code":"PPL",
    "gn:name":"Kasgan Q\u016bjaq",
    "gn:population":0,
    "gn:timezone":"Asia/Tehran",
    "iso:country":"IR",
    "name:ara_x_preferred":[
        "\u0643\u0631\u0646\u062f"
    ],
    "name:fas_x_preferred":[
        "Q\u016bjoqlar"
    ],
    "name:fas_x_variant":[
        "\u0642\u062c\u0642 \u0644\u0631",
        "\u06a9\u0633\u06af\u0646 \u0642\u0648\u062c\u0642",
        "\u06a9\u0633\u06a9\u0646 \u0642\u0648\u062c\u0642",
        "\u06a9\u0631\u0646\u062f"
    ],
    "name:msa_x_preferred":[
        "Kerend"
    ],
    "name:und_x_variant":[
        "Qojoqlar",
        "\u0642\u062c\u0642 \u0644\u0631",
        "Kasgan Q\u016bjaq",
        "Kaskan Q\u016bjaq"
    ],
    "wof:name":"Kasgan Qujaq",
    "wof:placetype":"locality"
},
  "geometry": {"coordinates":[55.301,37.37831],"type":"Point"}
}