{
  "type": "Feature",
  "properties": {
    "gn:admin1_code":"35.0",
    "gn:asciiname":"Sang Sarlingeh",
    "gn:country_code":"IR",
    "gn:dem":-22,
    "gn:feature_class":"P",
    "gn:feature_code":"PPL",
    "gn:name":"Sang Sarl\u012bngeh",
    "gn:population":0,
    "gn:timezone":"Asia/Tehran",
    "iso:country":"IR",
    "name:fas_x_preferred":[
        "Sang Sarl\u012bngeh"
    ],
    "name:fas_x_variant":[
        "\u0633\u0646\u06af \u0633\u0631\u0644\u06cc\u0646\u06af\u0647"
    ],
    "wof:name":"Sang Sarlingeh",
    "wof:placetype":"locality"
},
  "geometry": {"coordinates":[52.98569000000001,36.7268],"type":"Point"}
}