{
  "type": "Feature",
  "properties": {
    "gn:admin1_code":"15",
    "gn:asciiname":"Jassaniyeh-ye Bozorg",
    "gn:country_code":"IR",
    "gn:dem":22,
    "gn:feature_class":"P",
    "gn:feature_code":"PPL",
    "gn:name":"Jass\u0101n\u012byeh-ye Bozorg",
    "gn:population":0,
    "gn:timezone":"Asia/Tehran",
    "iso:country":"IR",
    "name:ara_x_preferred":[
        "\u062c\u0633\u0627\u0646\u064a\u0629 \u0627\u0644\u0643\u0628\u064a\u0631\u0629"
    ],
    "name:azb_x_preferred":[
        "\u062c\u0633\u0627\u0646\u06cc\u0647 \u0628\u0632\u0631\u06af"
    ],
    "name:fas_x_preferred":[
        "\u062c\u0633\u0627\u0646\u06cc\u0647 \u0628\u0632\u0631\u06af"
    ],
    "name:fas_x_variant":[
        "Jass\u0101n\u012byeh-ye Bozorg"
    ],
    "name:und_x_variant":[
        "Loveym\u012b",
        "Jass\u0101n\u012byeh",
        "Lov\u012bm\u012b",
        "Luwaimi",
        "Yassan\u012beh",
        "Yass\u0101n\u012byeh",
        "Les\u0101n\u012byeh"
    ],
    "name:urd_x_preferred":[
        "\u062c\u0633\u0627\u0646\u064a\u06c1 \u0628\u0632\u0631\u06af"
    ],
    "wof:name":"Jassaniyeh-ye Bozorg",
    "wof:placetype":"locality"
},
  "geometry": {"coordinates":[48.74891,31.41797],"type":"Point"}
}