{
  "type": "Feature",
  "properties": {
    "gn:admin1_code":"26.0",
    "gn:asciiname":"Kabirabad",
    "gn:country_code":"IR",
    "gn:dem":998,
    "gn:feature_class":"P",
    "gn:feature_code":"PPL",
    "gn:name":"Kab\u012br\u0101b\u0101d",
    "gn:population":0,
    "gn:timezone":"Asia/Tehran",
    "iso:country":"IR",
    "name:ceb_x_preferred":[
        "Kab\u012br\u0101b\u0101d"
    ],
    "name:fas_x_preferred":[
        "\u0643\u0628\u064a\u0631 \u0622\u0628\u0627\u062f"
    ],
    "name:fas_x_variant":[
        "Kab\u012br\u0101b\u0101d",
        "\u06a9\u0628\u06cc\u0631\u0622\u0628\u0627\u062f"
    ],
    "name:swe_x_preferred":[
        "Kab\u012br\u0101b\u0101d"
    ],
    "wof:name":"Kabirabad",
    "wof:placetype":"locality"
},
  "geometry": {"coordinates":[51.3291,35.5021],"type":"Point"}
}