{
  "type": "Feature",
  "properties": {
    "gn:admin1_code":"15",
    "gn:asciiname":"Qal`eh-ye Seyyed",
    "gn:country_code":"IR",
    "gn:dem":207,
    "gn:feature_class":"P",
    "gn:feature_code":"PPL",
    "gn:name":"Qal\u2018eh-ye Seyyed",
    "gn:population":0,
    "gn:timezone":"Asia/Tehran",
    "iso:country":"IR",
    "name:fas_x_preferred":[
        "Qal\u2018eh-ye Seyyed"
    ],
    "name:fas_x_variant":[
        "\u0642\u0644\u0639\u0647 \u0633\u06cc\u0651\u062f"
    ],
    "wof:name":"Qal`eh-ye Seyyed",
    "wof:placetype":"locality"
},
  "geometry": {"coordinates":[49.6569,31.25873],"type":"Point"}
}