{
  "type": "Feature",
  "properties": {
    "gn:admin1_code":"29.0",
    "gn:asciiname":"Sahmabad",
    "gn:country_code":"IR",
    "gn:dem":2073,
    "gn:feature_class":"P",
    "gn:feature_code":"PPL",
    "gn:name":"Sahm\u0101b\u0101d",
    "gn:population":0,
    "gn:timezone":"Asia/Tehran",
    "iso:country":"IR",
    "name:ceb_x_preferred":[
        "Qal\u2018eh-ye Salm\u0101b\u0101d"
    ],
    "name:fas_x_preferred":[
        "\u0633\u0647\u0645 \u0622\u0628\u0627\u062f"
    ],
    "name:fas_x_variant":[
        "Sahm\u0101b\u0101d",
        "\u0633\u0647\u0645\u200c\u0622\u0628\u0627\u062f"
    ],
    "name:swe_x_preferred":[
        "Qal\u2018eh-ye Salm\u0101b\u0101d"
    ],
    "name:ukr_x_preferred":[
        "\u0421\u0430\u0433\u043c\u0430\u0431\u0430\u0434"
    ],
    "name:urd_x_preferred":[
        "\u0633\u06c1\u0645 \u0622\u0628\u0627\u062f"
    ],
    "wof:name":"Sahmabad",
    "wof:placetype":"locality"
},
  "geometry": {"coordinates":[55.5006,30.3819],"type":"Point"}
}