{
  "type": "Feature",
  "properties": {
    "gn:admin1_code":"13",
    "gn:asciiname":"Kashanbeh-ye Lak",
    "gn:country_code":"IR",
    "gn:dem":1494,
    "gn:feature_class":"P",
    "gn:feature_code":"PPL",
    "gn:name":"K\u0101shanbeh-ye Lak",
    "gn:population":0,
    "gn:timezone":"Asia/Tehran",
    "iso:country":"IR",
    "name:ceb_x_preferred":[
        "K\u0101shanbeh-ye Lak"
    ],
    "name:fas_x_preferred":[
        "\u06a9\u0627\u0634\u0646\u0628\u0647 \u0644\u06a9"
    ],
    "name:fas_x_variant":[
        "K\u0101shanbeh-ye Lak",
        "\u06a9\u0627\u0634\u0646\u0628\u0647\u200c\u0644\u06a9"
    ],
    "name:swe_x_preferred":[
        "K\u0101shanbeh-ye Lak"
    ],
    "wof:name":"Kashanbeh-ye Lak",
    "wof:placetype":"locality"
},
  "geometry": {"coordinates":[46.6428,34.2905],"type":"Point"}
}