{
  "type": "Feature",
  "properties": {
    "gn:admin1_code":"4.0",
    "gn:asciiname":"Shahrak",
    "gn:country_code":"IR",
    "gn:dem":1316,
    "gn:feature_class":"P",
    "gn:feature_code":"PPL",
    "gn:name":"Shahrak",
    "gn:population":0,
    "gn:timezone":"Asia/Tehran",
    "iso:country":"IR",
    "name:fas_x_preferred":[
        "\u0634\u0647\u0631\u06a9"
    ],
    "name:msa_x_preferred":[
        "Shahrak"
    ],
    "name:rus_x_preferred":[
        "\u0428\u0430\u0445\u0440\u0430\u043a"
    ],
    "name:tgk_x_preferred":[
        "\u04b6\u0430\u043c\u043e\u0430\u0442\u0438 \u0428\u0430\u04b3\u0440\u0430\u043a"
    ],
    "name:urd_x_preferred":[
        "\u0634\u0627\u06c1\u0631\u06a9"
    ],
    "wof:name":"Shahrak",
    "wof:placetype":"locality"
},
  "geometry": {"coordinates":[60.73961,27.91997000000001],"type":"Point"}
}