{
  "type": "Feature",
  "properties": {
    "gn:admin1_code":"4.0",
    "gn:asciiname":"Shahrak",
    "gn:country_code":"IR",
    "gn:dem":1316,
    "gn:feature_class":"P",
    "gn:feature_code":"PPL",
    "gn:name":"Shahrak",
    "gn:population":0,
    "gn:timezone":"Asia/Tehran",
    "iso:country":"IR",
    "name:fas_x_preferred":[
        "\u0634\u0647\u0631\u06a9"
    ],
    "wof:name":"Shahrak",
    "wof:placetype":"locality"
},
  "geometry": {"coordinates":[60.73961,27.91997000000001],"type":"Point"}
}