{
  "type": "Feature",
  "properties": {
    "gn:admin1_code":"42",
    "gn:asciiname":"Kalateh-ye Navaleh",
    "gn:country_code":"IR",
    "gn:dem":1640,
    "gn:feature_class":"P",
    "gn:feature_code":"PPL",
    "gn:name":"Kal\u0101teh-ye Nav\u0101leh",
    "gn:population":0,
    "gn:timezone":"Asia/Tehran",
    "iso:country":"IR",
    "name:fas_x_preferred":[
        "\u0646\u0648\u0627\u0644\u0647"
    ],
    "name:fas_x_variant":[
        "Nav\u0101leh",
        "\u06a9\u0644\u0627\u062a\u0647 \u0646\u0648\u0627\u0644\u0647"
    ],
    "name:und_x_variant":[
        "Kal\u0101teh-ye Nav\u0101leh"
    ],
    "wof:name":"Kalateh-ye Navaleh",
    "wof:placetype":"locality"
},
  "geometry": {"coordinates":[59.84393000000001,35.13059000000001],"type":"Point"}
}