{
  "type": "Feature",
  "properties": {
    "gn:admin1_code":"33",
    "gn:asciiname":"Neycharan",
    "gn:country_code":"IR",
    "gn:dem":1888,
    "gn:feature_class":"P",
    "gn:feature_code":"PPL",
    "gn:name":"Neychar\u0101n",
    "gn:population":0,
    "gn:timezone":"Asia/Tehran",
    "iso:country":"IR",
    "name:ceb_x_preferred":[
        "Neychar\u0101n"
    ],
    "name:fas_x_preferred":[
        "\u0646\u06cc\u0686\u0631\u0627\u0646"
    ],
    "name:fas_x_variant":[
        "Neychar\u0101n"
    ],
    "name:msa_x_preferred":[
        "Neycharan"
    ],
    "name:swe_x_preferred":[
        "Neychar\u0101n"
    ],
    "name:und_x_variant":[
        "Let\u012by\u0101r\u0101n",
        "Naychar\u0101n",
        "Letiaran",
        "Letyaran"
    ],
    "wof:name":"Neycharan",
    "wof:placetype":"locality"
},
  "geometry": {"coordinates":[46.6083,38.3545],"type":"Point"}
}