{
  "type": "Feature",
  "properties": {
    "gn:admin1_code":"11",
    "gn:asciiname":"Hurmudar",
    "gn:country_code":"IR",
    "gn:dem":87,
    "gn:feature_class":"P",
    "gn:feature_code":"PPL",
    "gn:name":"H\u016brm\u016bdar",
    "gn:population":0,
    "gn:timezone":"Asia/Tehran",
    "iso:country":"IR",
    "name:fas_x_preferred":[
        "\u0647\u0631\u0645\u0648\u062f\u0631"
    ],
    "name:fas_x_variant":[
        "\u0647\u0650\u0631\u0645\u064f\u0651\u062f\u064e\u0631 \u0628\u064e\u0644\u064e",
        "\u062e\u0648\u064f\u0631\u0645\u0650\u0647\u062f\u0627\u0646\u0650 \u0628\u0627\u0644\u0627",
        "H\u016brm\u016bdar",
        "\u0647\u0648\u0631\u0645\u0648\u062f\u0631",
        "Herm\u016bdar"
    ],
    "name:und_x_variant":[
        "Khvormehd\u0101n-e B\u0101l\u0101",
        "Hermoodar Bala",
        "H\u016brm\u016brd",
        "Hurm\u016bdar B\u0101la"
    ],
    "wof:name":"Hurmudar",
    "wof:placetype":"locality"
},
  "geometry": {"coordinates":[56.31375,27.31699],"type":"Point"}
}