{
  "type": "Feature",
  "properties": {
    "gn:admin1_code":"33",
    "gn:asciiname":"Tappeh-ye Esma`ilabad",
    "gn:country_code":"IR",
    "gn:dem":1290,
    "gn:feature_class":"P",
    "gn:feature_code":"PPL",
    "gn:name":"Tappeh-ye Esm\u0101\u2018\u012bl\u0101b\u0101d",
    "gn:population":0,
    "gn:timezone":"Asia/Tehran",
    "iso:country":"IR",
    "name:fas_x_preferred":[
        "\u062a\u067e\u0651\u0647 \u0627\u0633\u0645\u0627\u0639\u06cc\u0644 \u0622\u0628\u0627\u062f"
    ],
    "name:fas_x_variant":[
        "Tappeh-ye Esm\u0101\u2018\u012bl\u0101b\u0101d"
    ],
    "wof:name":"Tappeh-ye Esma`ilabad",
    "wof:placetype":"locality"
},
  "geometry": {"coordinates":[46.118,37.0908],"type":"Point"}
}