{
  "type": "Feature",
  "properties": {
    "gn:admin1_code":"15",
    "gn:asciiname":"Seri-ye Yek",
    "gn:country_code":"IR",
    "gn:dem":31,
    "gn:feature_class":"P",
    "gn:feature_code":"PPL",
    "gn:name":"Ser\u012b-ye Yek",
    "gn:population":0,
    "gn:timezone":"Asia/Tehran",
    "iso:country":"IR",
    "name:ceb_x_preferred":[
        "Ser\u012b-ye Yek"
    ],
    "name:fas_x_preferred":[
        "\u0633\u0631\u06cc \u06cc\u06a9"
    ],
    "name:fas_x_variant":[
        "Ser\u012b Yek-e Zarr\u016bk",
        "Ser\u012b-ye Yek",
        "\u0633\u0631\u06cc \u06cc\u06a9 \u0632\u0631\u0648\u06a9"
    ],
    "name:swe_x_preferred":[
        "Ser\u012b-ye Yek"
    ],
    "wof:name":"Seri-ye Yek",
    "wof:placetype":"locality"
},
  "geometry": {"coordinates":[48.69175,31.74097],"type":"Point"}
}