{
  "type": "Feature",
  "properties": {
    "gn:admin1_code":"29.0",
    "gn:asciiname":"Rostamabad-e Chah Narenj",
    "gn:country_code":"IR",
    "gn:dem":665,
    "gn:feature_class":"P",
    "gn:feature_code":"PPL",
    "gn:name":"Rostam\u0101b\u0101d-e Ch\u0101h N\u0101renj",
    "gn:population":0,
    "gn:timezone":"Asia/Tehran",
    "iso:country":"IR",
    "name:fas_x_preferred":[
        "\u0631\u0633\u062a\u0645 \u0622\u0628\u0627\u062f \u0686\u0627\u0647 \u0646\u0627\u0631\u0646\u062c"
    ],
    "name:und_x_variant":[
        "Rostam\u0101b\u0101d-e Ch\u0101h N\u0101renj"
    ],
    "wof:name":"Rostamabad-e Chah Narenj",
    "wof:placetype":"locality"
},
  "geometry": {"coordinates":[57.35716,28.202],"type":"Point"}
}