{
  "type": "Feature",
  "properties": {
    "gn:admin1_code":"37",
    "gn:asciiname":"Turang Tappeh",
    "gn:country_code":"IR",
    "gn:dem":15,
    "gn:feature_class":"P",
    "gn:feature_code":"PPL",
    "gn:name":"T\u016brang Tappeh",
    "gn:population":0,
    "gn:timezone":"Asia/Tehran",
    "iso:country":"IR",
    "name:fas_x_preferred":[
        "\u062a\u0648\u0631\u0646\u06af \u062a\u067e\u0651\u0647"
    ],
    "name:fas_x_variant":[
        "T\u016brang Tappeh"
    ],
    "name:und_x_variant":[
        "K\u016br\u0101n Tappeh"
    ],
    "wof:name":"Turang Tappeh",
    "wof:placetype":"locality"
},
  "geometry": {"coordinates":[54.58837,36.9371],"type":"Point"}
}