{
  "type": "Feature",
  "properties": {
    "gn:admin1_code":"16",
    "gn:asciiname":"Divandarreh",
    "gn:country_code":"IR",
    "gn:dem":1838,
    "gn:feature_class":"P",
    "gn:feature_code":"PPLA2",
    "gn:name":"D\u012bv\u0101ndarreh",
    "gn:population":0,
    "gn:timezone":"Asia/Tehran",
    "iso:country":"IR",
    "name:fas_x_preferred":[
        "\u062f\u064a\u0648\u0627\u0646\u062f\u0631\u0647"
    ],
    "name:und_x_variant":[
        "D\u012bvan Darra",
        "D\u012bw\u0101n Darreh",
        "D\u012bv\u0101ndarreh"
    ],
    "wof:name":"Divandarreh",
    "wof:placetype":"locality"
},
  "geometry": {"coordinates":[47.0239,35.9139],"type":"Point"}
}