{
  "type": "Feature",
  "properties": {
    "gn:admin1_code":"16",
    "gn:asciiname":"Divandarreh",
    "gn:country_code":"IR",
    "gn:dem":1838,
    "gn:feature_class":"P",
    "gn:feature_code":"PPLA2",
    "gn:name":"D\u012bv\u0101ndarreh",
    "gn:population":0,
    "gn:timezone":"Asia/Tehran",
    "iso:country":"IR",
    "name:ara_x_preferred":[
        "\u062f\u064a\u0648\u0627\u0646\u062f\u0631\u0647"
    ],
    "name:aze_x_preferred":[
        "Divand\u0259r\u0259"
    ],
    "name:ckb_x_preferred":[
        "\u062f\u06cc\u0648\u0627\u0646\u062f\u06d5\u0631\u06d5"
    ],
    "name:epo_x_preferred":[
        "Divandere"
    ],
    "name:fas_x_preferred":[
        "\u062f\u064a\u0648\u0627\u0646\u062f\u0631\u0647"
    ],
    "name:fas_x_variant":[
        "\u062f\u06cc\u0648\u0627\u0646\u062f\u0631\u0647"
    ],
    "name:ita_x_preferred":[
        "Diwandarreh"
    ],
    "name:kur_x_preferred":[
        "D\u00eewandere"
    ],
    "name:mlg_x_preferred":[
        "Divandarreh"
    ],
    "name:pnb_x_preferred":[
        "\u062f\u06cc\u0648\u0627\u0646\u062f\u0631\u06c1"
    ],
    "name:pol_x_preferred":[
        "Diwandarre"
    ],
    "name:rus_x_preferred":[
        "\u0414\u0438\u0432\u0430\u043d\u0434\u0435\u0440\u0435"
    ],
    "name:tur_x_preferred":[
        "Divandere"
    ],
    "name:und_x_variant":[
        "D\u012bvan Darra",
        "D\u012bw\u0101n Darreh",
        "D\u012bv\u0101ndarreh"
    ],
    "name:zho_x_preferred":[
        "\u8fea\u842c\u9054\u96f7"
    ],
    "wof:name":"Divandarreh",
    "wof:placetype":"locality"
},
  "geometry": {"coordinates":[47.0239,35.9139],"type":"Point"}
}