{
  "type": "Feature",
  "properties": {
    "gn:admin1_code":"7.0",
    "gn:asciiname":"Qal`eh Sefid",
    "gn:country_code":"IR",
    "gn:dem":2051,
    "gn:feature_class":"P",
    "gn:feature_code":"PPL",
    "gn:name":"Qal\u2018eh Sef\u012bd",
    "gn:population":0,
    "gn:timezone":"Asia/Tehran",
    "iso:country":"IR",
    "name:fas_x_preferred":[
        "Qal\u2018eh Sef\u012bd"
    ],
    "name:fas_x_variant":[
        "\u0642\u0644\u0639\u0647 \u0633\u0641\u06cc\u062f"
    ],
    "name:und_x_variant":[
        "\u0642\u0644\u0639\u0647 \u0633\u0641\u06cc\u062f"
    ],
    "wof:name":"Qal`eh Sefid",
    "wof:placetype":"locality"
},
  "geometry": {"coordinates":[51.71025,30.31058],"type":"Point"}
}