{
  "type": "Feature",
  "properties": {
    "gn:admin1_code":"41",
    "gn:asciiname":"Owjad",
    "gn:country_code":"IR",
    "gn:dem":2133,
    "gn:feature_class":"P",
    "gn:feature_code":"PPL",
    "gn:name":"Owj\u0101d",
    "gn:population":0,
    "gn:timezone":"Asia/Tehran",
    "iso:country":"IR",
    "name:ara_x_preferred":[
        "\u0623\u0648\u062c\u0627\u062f"
    ],
    "name:fas_x_preferred":[
        "\u0627\u0648\u062c\u0627\u062f"
    ],
    "name:fas_x_variant":[
        "Owj\u0101d"
    ],
    "name:und_x_variant":[
        "\u016aj\u0101d",
        "Aujad"
    ],
    "wof:name":"Owjad",
    "wof:placetype":"locality"
},
  "geometry": {"coordinates":[59.57471999999999,33.2972],"type":"Point"}
}