{
  "type": "Feature",
  "properties": {
    "gn:admin1_code":"32",
    "gn:asciiname":"Khan Mohammad",
    "gn:country_code":"IR",
    "gn:dem":785,
    "gn:feature_class":"P",
    "gn:feature_code":"PPL",
    "gn:name":"Kh\u0101n Mo\u1e29ammad",
    "gn:population":0,
    "gn:timezone":"Asia/Tehran",
    "iso:country":"IR",
    "name:fas_x_preferred":[
        "\u062e\u0627\u0646 \u0645\u064f\u062d\u064e\u0645\u064e\u0651\u062f\u0644\u0648"
    ],
    "name:fas_x_variant":[
        "\u062e\u0627\u0646 \u0645\u062d\u0645\u062f",
        "Kh\u0101n Mo\u1e29ammadl\u016b",
        "Kh\u0101n Mo\u1e29ammad"
    ],
    "wof:name":"Khan Mohammad",
    "wof:placetype":"locality"
},
  "geometry": {"coordinates":[47.8077,39.1414],"type":"Point"}
}