{
  "type": "Feature",
  "properties": {
    "gn:admin1_code":"35.0",
    "gn:asciiname":"Limakdeh",
    "gn:country_code":"IR",
    "gn:dem":1728,
    "gn:feature_class":"P",
    "gn:feature_code":"PPL",
    "gn:name":"L\u012bm\u0101kdeh",
    "gn:population":0,
    "gn:timezone":"Asia/Tehran",
    "iso:country":"IR",
    "name:fas_x_preferred":[
        "\u0644\u064a\u0645\u0627\u0643\u062f\u0647"
    ],
    "name:fas_x_variant":[
        "L\u012bm\u0101k Deh",
        "\u0644\u06cc\u0645\u0627\u06a9 \u062f\u0647"
    ],
    "name:und_x_variant":[
        "\u0644\u06cc\u0645\u0627\u06a9 \u062f\u0647",
        "L\u012bm\u0101kdeh"
    ],
    "wof:name":"Limakdeh",
    "wof:placetype":"locality"
},
  "geometry": {"coordinates":[50.57588,36.7956],"type":"Point"}
}