{
  "type": "Feature",
  "properties": {
    "gn:admin1_code":"5",
    "gn:asciiname":"Jalil",
    "gn:country_code":"IR",
    "gn:dem":2022,
    "gn:feature_class":"P",
    "gn:feature_code":"PPL",
    "gn:name":"Jal\u012bl",
    "gn:population":0,
    "gn:timezone":"Asia/Tehran",
    "iso:country":"IR",
    "name:aze_x_preferred":[
        "C\u0259lil"
    ],
    "name:deu_x_preferred":[
        "Jalil"
    ],
    "name:fas_x_preferred":[
        "Jal\u012bl"
    ],
    "name:rus_x_preferred":[
        "\u0414\u0436\u0430\u043b\u0438\u043b\u044c"
    ],
    "wof:name":"Jalil",
    "wof:placetype":"locality"
},
  "geometry": {"coordinates":[51.29972,30.63528],"type":"Point"}
}