{
  "type": "Feature",
  "properties": {
    "gn:admin1_code":"11",
    "gn:asciiname":"Pakam-e Bala",
    "gn:country_code":"IR",
    "gn:dem":1098,
    "gn:feature_class":"P",
    "gn:feature_code":"PPL",
    "gn:name":"P\u0101kam-e B\u0101l\u0101",
    "gn:population":0,
    "gn:timezone":"Asia/Tehran",
    "iso:country":"IR",
    "name:fas_x_preferred":[
        "\u067e\u0627\u0643\u0645"
    ],
    "name:fas_x_variant":[
        "\u067e\u0627\u0643\u064e\u0645\u0650 \u0645\u0627\u0634\u0627\u0631\u06cc",
        "\u067e\u0627\u0643\u0645 \u0628\u0627\u0644\u0627",
        "P\u0101kam",
        "P\u0101kam-e B\u0101l\u0101"
    ],
    "name:und_x_variant":[
        "P\u0101kam-e M\u0101sh\u0101r\u012b"
    ],
    "wof:name":"Pakam-e Bala",
    "wof:placetype":"locality"
},
  "geometry": {"coordinates":[56.5813,27.8166],"type":"Point"}
}