{
  "type": "Feature",
  "properties": {
    "gn:admin1_code":"13",
    "gn:asciiname":"Gabri",
    "gn:country_code":"IR",
    "gn:dem":1275,
    "gn:feature_class":"P",
    "gn:feature_code":"PPL",
    "gn:name":"Gabr\u012b",
    "gn:population":0,
    "gn:timezone":"Asia/Tehran",
    "iso:country":"IR",
    "name:deu_x_preferred":[
        "Gabri"
    ],
    "name:fas_x_preferred":[
        "Gabr\u012b"
    ],
    "wof:name":"Gabri",
    "wof:placetype":"locality"
},
  "geometry": {"coordinates":[47.3275,34.18778],"type":"Point"}
}