{
  "type": "Feature",
  "properties": {
    "gn:admin1_code":"42",
    "gn:asciiname":"Gandavak",
    "gn:country_code":"IR",
    "gn:dem":932,
    "gn:feature_class":"P",
    "gn:feature_code":"PPL",
    "gn:name":"Gandavak",
    "gn:population":0,
    "gn:timezone":"Asia/Tehran",
    "iso:country":"IR",
    "name:ceb_x_preferred":[
        "Gandavak"
    ],
    "name:fas_x_preferred":[
        "\u06af\u0646\u062f\u0648\u06a9"
    ],
    "name:fas_x_variant":[
        "Gevand\u016bk",
        "\u06af\u0648\u0646\u062f\u0648\u06a9"
    ],
    "wof:name":"Gandavak",
    "wof:placetype":"locality"
},
  "geometry": {"coordinates":[59.67887,36.3428],"type":"Point"}
}