{
  "type": "Feature",
  "properties": {
    "gn:admin1_code":"15.0",
    "gn:asciiname":"Chidak",
    "gn:country_code":"IR",
    "gn:dem":1910,
    "gn:feature_class":"P",
    "gn:feature_code":"PPL",
    "gn:name":"Ch\u012bd\u0101k",
    "gn:population":0,
    "gn:timezone":"Asia/Tehran",
    "iso:country":"IR",
    "name:fas_x_preferred":[
        "\u0686\u064a\u062f\u0627\u0643"
    ],
    "name:und_x_variant":[
        "Ch\u012bd\u0101k",
        "\u0686\u064a\u062f\u0627\u0643"
    ],
    "wof:name":"Chidak",
    "wof:placetype":"locality"
},
  "geometry": {"coordinates":[50.21333,31.91889],"type":"Point"}
}