{
  "type": "Feature",
  "properties": {
    "gn:admin1_code":"5",
    "gn:asciiname":"Leh Howz",
    "gn:country_code":"IR",
    "gn:dem":1641,
    "gn:feature_class":"P",
    "gn:feature_code":"PPL",
    "gn:name":"Leh \u1e28ow\u1e95",
    "gn:population":0,
    "gn:timezone":"Asia/Tehran",
    "iso:country":"IR",
    "name:fas_x_preferred":[
        "Leh \u1e28ow\u1e95"
    ],
    "name:fas_x_variant":[
        "\u0644\u0647 \u062d\u0648\u0636"
    ],
    "wof:name":"Leh Howz",
    "wof:placetype":"locality"
},
  "geometry": {"coordinates":[50.47914,31.24216],"type":"Point"}
}