{
  "type": "Feature",
  "properties": {
    "gn:admin1_code":"1",
    "gn:asciiname":"Darzi Vali",
    "gn:country_code":"IR",
    "gn:dem":1537,
    "gn:feature_class":"P",
    "gn:feature_code":"PPL",
    "gn:name":"Darz\u012b Val\u012b",
    "gn:population":0,
    "gn:timezone":"Asia/Tehran",
    "iso:country":"IR",
    "name:fas_x_preferred":[
        "\u062f\u0631\u0632\u06cc \u0648\u0644\u06cc"
    ],
    "name:fas_x_variant":[
        "Darz\u012b Val\u012b"
    ],
    "wof:name":"Darzi Vali",
    "wof:placetype":"locality"
},
  "geometry": {"coordinates":[46.3911,36.4607],"type":"Point"}
}