{
  "type": "Feature",
  "properties": {
    "gn:admin1_code":"5",
    "gn:asciiname":"Ghurak-e Miani",
    "gn:country_code":"IR",
    "gn:dem":916,
    "gn:feature_class":"P",
    "gn:feature_code":"PPL",
    "gn:name":"Gh\u016brak-e M\u012b\u0101n\u012b",
    "gn:population":0,
    "gn:timezone":"Asia/Tehran",
    "iso:country":"IR",
    "name:fas_x_preferred":[
        "\u063a\u0648\u0631\u064e\u0643\u0650 \u0645\u064a\u0627\u0646\u06cc"
    ],
    "name:fas_x_variant":[
        "Gh\u016brak-e M\u012b\u0101n\u012b"
    ],
    "wof:name":"Ghurak-e Miani",
    "wof:placetype":"locality"
},
  "geometry": {"coordinates":[51.16667,30.26667],"type":"Point"}
}