{
  "type": "Feature",
  "properties": {
    "gn:admin1_code":"33",
    "gn:asciiname":"Zonuzaq",
    "gn:country_code":"IR",
    "gn:dem":1890,
    "gn:feature_class":"P",
    "gn:feature_code":"PPL",
    "gn:name":"Zon\u016bzaq",
    "gn:population":0,
    "gn:timezone":"Asia/Tehran",
    "iso:country":"IR",
    "name:fas_x_preferred":[
        "\u0632\u064e\u0646\u064f\u0651\u0632\u064e\u063a"
    ],
    "name:fas_x_variant":[
        "\u0632\u0646\u0648\u0632\u0642",
        "\u0632\u064f\u0646\u0648\u0632\u064e\u0642",
        "Zon\u016bzaq",
        "\u0632\u064f\u0646\u0648\u0632\u0627\u062e"
    ],
    "name:und_x_variant":[
        "Zanoozagh",
        "Zunuzakh",
        "Zunusakh",
        "Zon\u016bz\u0101kh"
    ],
    "wof:name":"Zonuzaq",
    "wof:placetype":"locality"
},
  "geometry": {"coordinates":[45.8526,38.5922],"type":"Point"}
}