{
  "type": "Feature",
  "properties": {
    "gn:admin1_code":"16",
    "gn:asciiname":"Galan",
    "gn:country_code":"IR",
    "gn:dem":1711,
    "gn:feature_class":"P",
    "gn:feature_code":"PPL",
    "gn:name":"Gal\u0101n",
    "gn:population":0,
    "gn:timezone":"Asia/Tehran",
    "iso:country":"IR",
    "name:ceb_x_preferred":[
        "Galan"
    ],
    "name:deu_x_preferred":[
        "Galan"
    ],
    "name:fas_x_preferred":[
        "\u06af\u0644\u0627\u0646"
    ],
    "name:fas_x_variant":[
        "Gal\u0101n"
    ],
    "name:fra_x_preferred":[
        "Galan"
    ],
    "name:ita_x_preferred":[
        "Galan"
    ],
    "name:nld_x_preferred":[
        "Galan"
    ],
    "name:swe_x_preferred":[
        "Galan"
    ],
    "name:ukr_x_preferred":[
        "\u0413\u0430\u043b\u0430\u043d"
    ],
    "name:und_x_variant":[
        "Gul\u0101n",
        "K\u016bl\u0101n",
        "Gol\u0101n"
    ],
    "wof:name":"Galan",
    "wof:placetype":"locality"
},
  "geometry": {"coordinates":[46.4366,35.4306],"type":"Point"}
}