{
  "type": "Feature",
  "properties": {
    "gn:admin1_code":"4",
    "gn:asciiname":"Shahr-e Deraz",
    "gn:country_code":"IR",
    "gn:dem":1248,
    "gn:feature_class":"P",
    "gn:feature_code":"PPL",
    "gn:name":"Shahr-e Der\u0101z",
    "gn:population":0,
    "gn:timezone":"Asia/Tehran",
    "iso:country":"IR",
    "name:fas_x_preferred":[
        "\u0634\u0647\u0631 \u062f\u0631\u0627\u0632"
    ],
    "name:fas_x_variant":[
        "Shahr-e Der\u0101z"
    ],
    "wof:name":"Shahr-e Deraz",
    "wof:placetype":"locality"
},
  "geometry": {"coordinates":[61.7697,27.0939],"type":"Point"}
}