{
  "type": "Feature",
  "properties": {
    "gn:admin1_code":"33",
    "gn:asciiname":"Kalankash",
    "gn:country_code":"IR",
    "gn:dem":1615,
    "gn:feature_class":"P",
    "gn:feature_code":"PPL",
    "gn:name":"Kal\u0101nkash",
    "gn:population":0,
    "gn:timezone":"Asia/Tehran",
    "iso:country":"IR",
    "name:ceb_x_preferred":[
        "Kal\u0101nkash"
    ],
    "name:fas_x_preferred":[
        "\u06a9\u0644\u0627\u0646\u06a9\u0634"
    ],
    "name:fas_x_variant":[
        "Kal\u0101nkash"
    ],
    "name:msa_x_preferred":[
        "Kalankash"
    ],
    "name:swe_x_preferred":[
        "Kal\u0101nkash"
    ],
    "name:und_x_variant":[
        "Kolankesh",
        "Kal\u0101nkesh",
        "Kelen-ki",
        "Kal\u0101nkish"
    ],
    "wof:name":"Kalankash",
    "wof:placetype":"locality"
},
  "geometry": {"coordinates":[46.09888,38.29037],"type":"Point"}
}