{
  "type": "Feature",
  "properties": {
    "gn:admin1_code":"29.0",
    "gn:asciiname":"Tall-e Kushk",
    "gn:country_code":"IR",
    "gn:dem":1879,
    "gn:feature_class":"P",
    "gn:feature_code":"PPL",
    "gn:name":"Tall-e K\u016bshk",
    "gn:population":0,
    "gn:timezone":"Asia/Tehran",
    "iso:country":"IR",
    "name:fas_x_preferred":[
        "Tall-e K\u016bshk"
    ],
    "name:fas_x_variant":[
        "\u062a\u0644 \u06a9\u0648\u0634\u06a9"
    ],
    "name:msa_x_preferred":[
        "Tall-e Kushk"
    ],
    "wof:name":"Tall-e Kushk",
    "wof:placetype":"locality"
},
  "geometry": {"coordinates":[56.26667,28.83333],"type":"Point"}
}