{
  "type": "Feature",
  "properties": {
    "gn:admin1_code":"7",
    "gn:asciiname":"Qanat-e Now",
    "gn:country_code":"IR",
    "gn:dem":2224,
    "gn:feature_class":"P",
    "gn:feature_code":"PPL",
    "gn:name":"Qan\u0101t-e Now",
    "gn:population":0,
    "gn:timezone":"Asia/Tehran",
    "iso:country":"IR",
    "name:fas_x_preferred":[
        "\u0642\u0646\u0627\u062a \u0646\u0648"
    ],
    "name:fas_x_variant":[
        "Qan\u0101t-e Now"
    ],
    "name:und_x_variant":[
        "Qan\u0101t-i-Nau"
    ],
    "wof:name":"Qanat-e Now",
    "wof:placetype":"locality"
},
  "geometry": {"coordinates":[53.3194,30.4215],"type":"Point"}
}