{
  "type": "Feature",
  "properties": {
    "gn:admin1_code":"28",
    "gn:asciiname":"Varposht",
    "gn:country_code":"IR",
    "gn:dem":2000,
    "gn:feature_class":"P",
    "gn:feature_code":"PPL",
    "gn:name":"Varposht",
    "gn:population":0,
    "gn:timezone":"Asia/Tehran",
    "iso:country":"IR",
    "name:fas_x_preferred":[
        "\u0648\u0631\u067e\u0634\u062a"
    ],
    "name:und_x_variant":[
        "Var Posht",
        "Khar\u0101 Posht",
        "Varposht",
        "Khar Posht"
    ],
    "wof:name":"Varposht",
    "wof:placetype":"locality"
},
  "geometry": {"coordinates":[52.9395,32.739],"type":"Point"}
}