{
  "type": "Feature",
  "properties": {
    "gn:admin1_code":"23",
    "gn:asciiname":"Dar Mar",
    "gn:country_code":"IR",
    "gn:dem":1002,
    "gn:feature_class":"P",
    "gn:feature_code":"PPL",
    "gn:name":"Dar Mar",
    "gn:population":0,
    "gn:timezone":"Asia/Tehran",
    "iso:country":"IR",
    "name:fas_x_preferred":[
        "\u062f\u0631\u0645\u0631"
    ],
    "wof:name":"Dar Mar",
    "wof:placetype":"locality"
},
  "geometry": {"coordinates":[47.7438,33.3018],"type":"Point"}
}