{
  "type": "Feature",
  "properties": {
    "gn:admin1_code":"36.0",
    "gn:asciiname":"Ahmad Kandi",
    "gn:country_code":"IR",
    "gn:dem":1924,
    "gn:feature_class":"P",
    "gn:feature_code":"PPL",
    "gn:name":"A\u1e29mad Kand\u012b",
    "gn:population":0,
    "gn:timezone":"Asia/Tehran",
    "iso:country":"IR",
    "name:fas_x_preferred":[
        "\u0627\u062d\u0645\u062f \u0643\u0646\u062f\u06cc"
    ],
    "name:fas_x_variant":[
        "A\u1e29mad Kand\u012b"
    ],
    "name:und_x_variant":[
        "Akhmadkandi"
    ],
    "wof:name":"Ahmad Kandi",
    "wof:placetype":"locality"
},
  "geometry": {"coordinates":[48.3307,36.5004],"type":"Point"}
}