{
  "type": "Feature",
  "properties": {
    "gn:admin1_code":"15",
    "gn:asciiname":"Khozeyyer",
    "gn:country_code":"IR",
    "gn:dem":44,
    "gn:feature_class":"P",
    "gn:feature_code":"PPL",
    "gn:name":"Kho\u1e95eyyer",
    "gn:population":0,
    "gn:timezone":"Asia/Tehran",
    "iso:country":"IR",
    "name:fas_x_preferred":[
        "Kho\u1e95eyyer"
    ],
    "wof:name":"Khozeyyer",
    "wof:placetype":"locality"
},
  "geometry": {"coordinates":[48.59278,31.95833],"type":"Point"}
}