{
  "type": "Feature",
  "properties": {
    "gn:admin1_code":"28",
    "gn:asciiname":"Khuygan",
    "gn:country_code":"IR",
    "gn:dem":2211,
    "gn:feature_class":"P",
    "gn:feature_code":"PPL",
    "gn:name":"Kh\u016byg\u0101n",
    "gn:population":0,
    "gn:timezone":"Asia/Tehran",
    "iso:country":"IR",
    "name:fas_x_preferred":[
        "Kh\u016byg\u0101n"
    ],
    "name:fas_x_variant":[
        "Kh\u016byg\u0101n-e P\u0101\u2019\u012bn",
        "Khvoyj\u0101n",
        "Kh\u016byg\u0101n-e Sofl\u00e1",
        "Khoij\u0101n",
        "\u062e\u0648\u06cc\u06af\u0627\u0646"
    ],
    "name:und_x_variant":[
        "\u062e\u0648\u06cc\u06af\u0627\u0646"
    ],
    "wof:name":"Khuygan",
    "wof:placetype":"locality"
},
  "geometry": {"coordinates":[50.37536,32.83215999999999],"type":"Point"}
}