{
  "type": "Feature",
  "properties": {
    "gn:admin1_code":"22",
    "gn:asciiname":"Mazra`eh-ye Zendan",
    "gn:country_code":"IR",
    "gn:dem":10,
    "gn:feature_class":"P",
    "gn:feature_code":"PPL",
    "gn:name":"Mazra\u2018eh-ye Zend\u0101n",
    "gn:population":0,
    "gn:timezone":"Asia/Tehran",
    "iso:country":"IR",
    "name:fas_x_preferred":[
        "\u0632\u0650\u0646\u062f\u0627\u0646"
    ],
    "name:fas_x_variant":[
        "Zend\u0101n",
        "\u0645\u0632\u0631\u0639\u0647 \u0632\u0646\u062f\u0627\u0646"
    ],
    "name:und_x_variant":[
        "Zind\u0101n",
        "Mazra\u2018eh-ye Zend\u0101n"
    ],
    "wof:name":"Mazra`eh-ye Zendan",
    "wof:placetype":"locality"
},
  "geometry": {"coordinates":[50.98523,29.22871],"type":"Point"}
}