{
  "type": "Feature",
  "properties": {
    "gn:admin1_code":"4.0",
    "gn:asciiname":"Sekandar",
    "gn:country_code":"IR",
    "gn:dem":920,
    "gn:feature_class":"P",
    "gn:feature_code":"PPL",
    "gn:name":"Sekandar",
    "gn:population":0,
    "gn:timezone":"Asia/Tehran",
    "iso:country":"IR",
    "name:fas_x_preferred":[
        "\u0633\u06a9\u0646\u062f\u0631"
    ],
    "name:fas_x_variant":[
        "\u012arafsh\u0101n",
        "\u0627\u06cc\u0631\u0627\u0641\u0634\u0627\u0646"
    ],
    "name:und_x_variant":[
        "S\u012bkandar",
        "Qal\u2018eyh-ye \u012arafsh\u0101n",
        "Eskandar",
        "Sekandar"
    ],
    "wof:name":"Sekandar",
    "wof:placetype":"locality"
},
  "geometry": {"coordinates":[61.932,26.6868],"type":"Point"}
}