{
  "type": "Feature",
  "properties": {
    "gn:admin1_code":"3",
    "gn:asciiname":"Sini",
    "gn:country_code":"IR",
    "gn:dem":1867,
    "gn:feature_class":"P",
    "gn:feature_code":"PPL",
    "gn:name":"S\u012bn\u012b",
    "gn:population":0,
    "gn:timezone":"Asia/Tehran",
    "iso:country":"IR",
    "name:bel_x_preferred":[
        "\u0421\u0456\u043d\u0456"
    ],
    "name:bpy_x_preferred":[
        "\u09b8\u09bf\u09a8\u09bf"
    ],
    "name:cat_x_preferred":[
        "Sini"
    ],
    "name:ceb_x_preferred":[
        "Sini"
    ],
    "name:deu_x_preferred":[
        "Sini"
    ],
    "name:fas_x_preferred":[
        "\u0633\u064a\u0646\u06cc"
    ],
    "name:fas_x_variant":[
        "S\u012bn\u012b"
    ],
    "name:fin_x_preferred":[
        "Sini"
    ],
    "name:fra_x_preferred":[
        "Sini"
    ],
    "name:ita_x_preferred":[
        "Sini"
    ],
    "name:nld_x_preferred":[
        "Sini"
    ],
    "name:swe_x_preferred":[
        "Sini"
    ],
    "wof:name":"Sini",
    "wof:placetype":"locality"
},
  "geometry": {"coordinates":[51.04618,31.55657],"type":"Point"}
}