{
  "type": "Feature",
  "properties": {
    "gn:admin1_code":"4",
    "gn:asciiname":"`Abdolvahed",
    "gn:country_code":"IR",
    "gn:dem":1383,
    "gn:feature_class":"P",
    "gn:feature_code":"PPL",
    "gn:name":"\u2018Abdolv\u0101\u1e29ed",
    "gn:population":0,
    "gn:timezone":"Asia/Tehran",
    "iso:country":"IR",
    "name:fas_x_preferred":[
        "\u0639\u0628\u062f\u0627\u0644\u0648\u0627\u062d\u062f"
    ],
    "name:fas_x_variant":[
        "\u2018Abdolv\u0101\u1e29ed"
    ],
    "wof:name":"`Abdolvahed",
    "wof:placetype":"locality"
},
  "geometry": {"coordinates":[60.33359,29.091],"type":"Point"}
}