{
  "type": "Feature",
  "properties": {
    "gn:admin1_code":"4",
    "gn:asciiname":"Sahtavan",
    "gn:country_code":"IR",
    "gn:dem":775,
    "gn:feature_class":"P",
    "gn:feature_code":"PPL",
    "gn:name":"Sahtav\u0101n",
    "gn:population":0,
    "gn:timezone":"Asia/Tehran",
    "iso:country":"IR",
    "name:fas_x_preferred":[
        "\u0633\u0647\u062a\u0648\u0627\u0646"
    ],
    "name:fas_x_variant":[
        "Sahtav\u0101n"
    ],
    "wof:name":"Sahtavan",
    "wof:placetype":"locality"
},
  "geometry": {"coordinates":[60.0037,26.3458],"type":"Point"}
}