{
  "type": "Feature",
  "properties": {
    "gn:admin1_code":"1.0",
    "gn:asciiname":"Pa Qal`eh",
    "gn:country_code":"IR",
    "gn:dem":1484,
    "gn:feature_class":"P",
    "gn:feature_code":"PPL",
    "gn:name":"P\u0101 Qal\u2018eh",
    "gn:population":0,
    "gn:timezone":"Asia/Tehran",
    "iso:country":"IR",
    "name:fas_x_preferred":[
        "\u067e\u0627 \u0642\u0644\u0639\u0647"
    ],
    "name:fas_x_variant":[
        "P\u0101 Qal\u2018eh"
    ],
    "wof:name":"Pa Qal`eh",
    "wof:placetype":"locality"
},
  "geometry": {"coordinates":[45.0325,36.9925],"type":"Point"}
}