{
  "type": "Feature",
  "properties": {
    "gn:admin1_code":"29",
    "gn:asciiname":"Mohammadabad-e Geluski",
    "gn:country_code":"IR",
    "gn:dem":803,
    "gn:feature_class":"P",
    "gn:feature_code":"PPL",
    "gn:name":"Mo\u1e29ammad\u0101b\u0101d-e Gel\u016bsk\u012b",
    "gn:population":0,
    "gn:timezone":"Asia/Tehran",
    "iso:country":"IR",
    "name:fas_x_preferred":[
        "Kel\u016bsk\u012b"
    ],
    "name:fas_x_variant":[
        "\u0645\u062d\u0645\u062f \u0622\u0628\u0627\u062f \u06af\u0644\u0648\u0633\u06a9\u06cc"
    ],
    "name:und_x_variant":[
        "Mo\u1e29ammad\u0101b\u0101d-e Gel\u016bsk\u012b",
        "Mo\u1e29ammad\u0101b\u0101d-e Kal\u016bk\u012b",
        "Mo\u1e29ammad\u0101b\u0101d",
        "Mo\u1e29ammad\u0101b\u0101d-e Kel\u016bsk\u012b"
    ],
    "wof:name":"Mohammadabad-e Geluski",
    "wof:placetype":"locality"
},
  "geometry": {"coordinates":[58.63944,28.96],"type":"Point"}
}