{
  "type": "Feature",
  "properties": {
    "gn:admin1_code":"28.0",
    "gn:asciiname":"Khuya",
    "gn:country_code":"IR",
    "gn:dem":1517,
    "gn:feature_class":"P",
    "gn:feature_code":"PPLF",
    "gn:name":"Kh\u016by\u0101",
    "gn:population":0,
    "gn:timezone":"Asia/Tehran",
    "iso:country":"IR",
    "name:fas_x_preferred":[
        "\u062e\u0648\u064a\u0627"
    ],
    "name:und_x_variant":[
        "Kh\u016by\u0101"
    ],
    "wof:name":"Khuya",
    "wof:placetype":"locality"
},
  "geometry": {"coordinates":[52.0725,32.54806],"type":"Point"}
}