{
  "type": "Feature",
  "properties": {
    "gn:admin1_code":"40",
    "gn:asciiname":"Sharifabad",
    "gn:country_code":"IR",
    "gn:dem":1955,
    "gn:feature_class":"P",
    "gn:feature_code":"PPL",
    "gn:name":"Shar\u012bf\u0101b\u0101d",
    "gn:population":0,
    "gn:timezone":"Asia/Tehran",
    "iso:country":"IR",
    "name:fas_x_preferred":[
        "\u0634\u0631\u06cc\u0641 \u0622\u0628\u0627\u062f"
    ],
    "name:fas_x_variant":[
        "Shar\u012bf\u0101b\u0101d"
    ],
    "wof:name":"Sharifabad",
    "wof:placetype":"locality"
},
  "geometry": {"coordinates":[53.8598,31.4046],"type":"Point"}
}