{
  "type": "Feature",
  "properties": {
    "gn:admin1_code":"35.0",
    "gn:asciiname":"Seraj Mahalleh",
    "gn:country_code":"IR",
    "gn:dem":79,
    "gn:feature_class":"P",
    "gn:feature_code":"PPL",
    "gn:name":"Ser\u0101j Ma\u1e29alleh",
    "gn:population":0,
    "gn:timezone":"Asia/Tehran",
    "iso:country":"IR",
    "name:fas_x_preferred":[
        "\u0633\u064e\u0631\u0627\u062c \u0645\u064e\u062d\u064e\u0644\u0650\u0651\u0647"
    ],
    "name:fas_x_variant":[
        "Ser\u0101j Ma\u1e29alleh",
        "\u0633\u0631\u0627\u062c \u0645\u062d\u0644\u0647"
    ],
    "name:und_x_variant":[
        "Sar\u0101j Ma\u1e29alleh",
        "\u0633\u0631\u0627\u062c \u0645\u062d\u0644\u0647"
    ],
    "wof:name":"Seraj Mahalleh",
    "wof:placetype":"locality"
},
  "geometry": {"coordinates":[53.74949,36.71267],"type":"Point"}
}