{
  "type": "Feature",
  "properties": {
    "gn:admin1_code":"41",
    "gn:asciiname":"Mirkhan",
    "gn:country_code":"IR",
    "gn:dem":1815,
    "gn:feature_class":"P",
    "gn:feature_code":"PPL",
    "gn:name":"M\u012brkh\u0101n",
    "gn:population":0,
    "gn:timezone":"Asia/Tehran",
    "iso:country":"IR",
    "name:fas_x_preferred":[
        "\u0645\u06cc\u063a\u0627\u0646"
    ],
    "name:fas_x_variant":[
        "M\u012bgh\u0101n",
        "\u0645\u06cc\u0631\u062e\u0627\u0646"
    ],
    "name:und_x_variant":[
        "M\u012brkh\u0101n",
        "M\u012br Kh\u016bn",
        "M\u012br Kh\u0101n"
    ],
    "wof:name":"Mirkhan",
    "wof:placetype":"locality"
},
  "geometry": {"coordinates":[59.7758,32.3987],"type":"Point"}
}