{
  "type": "Feature",
  "properties": {
    "gn:admin1_code":"13",
    "gn:asciiname":"Shahgodar-e Mohammad",
    "gn:cc2":"IR",
    "gn:country_code":"IR",
    "gn:dem":1352,
    "gn:feature_class":"P",
    "gn:feature_code":"PPL",
    "gn:name":"Sh\u0101hgod\u0101r-e Mo\u1e29ammad",
    "gn:population":0,
    "gn:timezone":"Asia/Tehran",
    "iso:country":"IR",
    "name:ceb_x_preferred":[
        "Sh\u0101hgod\u0101r-e Mo\u1e29ammad"
    ],
    "name:fas_x_preferred":[
        "Sh\u0101hgod\u0101r-e Mo\u1e29ammad"
    ],
    "name:fas_x_variant":[
        "\u0634\u0627\u0647\u200c\u06af\u062f\u0627\u0631\u0645\u062d\u0645\u062f"
    ],
    "name:swe_x_preferred":[
        "Sh\u0101hgod\u0101r-e Mo\u1e29ammad"
    ],
    "name:und_x_variant":[
        "Ban\u0101vech",
        "Sh\u0101h Goz\u0101r"
    ],
    "wof:name":"Shahgodar-e Mohammad",
    "wof:placetype":"locality"
},
  "geometry": {"coordinates":[46.25528,34.68111],"type":"Point"}
}