{
  "type": "Feature",
  "properties": {
    "gn:admin1_code":"25",
    "gn:asciiname":"Rudbar",
    "gn:country_code":"IR",
    "gn:dem":1558,
    "gn:feature_class":"P",
    "gn:feature_code":"PPL",
    "gn:name":"R\u016bdb\u0101r",
    "gn:population":0,
    "gn:timezone":"Asia/Tehran",
    "iso:country":"IR",
    "name:fas_x_preferred":[
        "\u0631\u0648\u062f\u0628\u0627\u0631"
    ],
    "name:fas_x_variant":[
        "R\u016bdb\u0101r"
    ],
    "wof:name":"Rudbar",
    "wof:placetype":"locality"
},
  "geometry": {"coordinates":[53.14116,35.89091],"type":"Point"}
}