{
  "type": "Feature",
  "properties": {
    "gn:admin1_code":"25",
    "gn:asciiname":"Rudbar",
    "gn:country_code":"IR",
    "gn:dem":1558,
    "gn:feature_class":"P",
    "gn:feature_code":"PPL",
    "gn:name":"R\u016bdb\u0101r",
    "gn:population":0,
    "gn:timezone":"Asia/Tehran",
    "iso:country":"IR",
    "name:ara_x_preferred":[
        "\u0631\u0648\u062f\u0628\u0627\u0631"
    ],
    "name:aze_x_preferred":[
        "Rudbar"
    ],
    "name:ceb_x_preferred":[
        "Khal\u012bl\u0101b\u0101d"
    ],
    "name:deu_x_preferred":[
        "Rudbar"
    ],
    "name:fas_x_preferred":[
        "\u0631\u0648\u062f\u0628\u0627\u0631"
    ],
    "name:fas_x_variant":[
        "R\u016bdb\u0101r"
    ],
    "name:fra_x_preferred":[
        "Roudbar"
    ],
    "name:ita_x_preferred":[
        "Rudbar"
    ],
    "name:mlg_x_preferred":[
        "Rudbar"
    ],
    "name:msa_x_preferred":[
        "Rudbar"
    ],
    "name:pnb_x_preferred":[
        "\u0631\u0648\u062f\u0628\u0627\u0631"
    ],
    "name:pol_x_preferred":[
        "Rudbar"
    ],
    "name:ron_x_preferred":[
        "Roudbar"
    ],
    "name:rus_x_preferred":[
        "\u0420\u0443\u0434\u0431\u0430\u0440"
    ],
    "name:tgk_x_preferred":[
        "\u0420\u04ef\u0434\u0431\u043e\u0440"
    ],
    "name:tur_x_preferred":[
        "Rudbar"
    ],
    "name:zho_x_preferred":[
        "\u9b6f\u5fb7\u5df4\u723e"
    ],
    "wof:name":"Rudbar",
    "wof:placetype":"locality"
},
  "geometry": {"coordinates":[53.14116,35.89091],"type":"Point"}
}