{
  "type": "Feature",
  "properties": {
    "gn:admin1_code":"15",
    "gn:asciiname":"Shekar Ab",
    "gn:country_code":"IR",
    "gn:dem":501,
    "gn:feature_class":"P",
    "gn:feature_code":"PPL",
    "gn:name":"Shekar \u0100b",
    "gn:population":0,
    "gn:timezone":"Asia/Tehran",
    "iso:country":"IR",
    "name:fas_x_preferred":[
        "\u0634\u06a9\u0631 \u0622\u0628"
    ],
    "name:fas_x_variant":[
        "Shekar \u0100b"
    ],
    "wof:name":"Shekar Ab",
    "wof:placetype":"locality"
},
  "geometry": {"coordinates":[49.17321,32.45517],"type":"Point"}
}