{
  "type": "Feature",
  "properties": {
    "gn:admin1_code":"1",
    "gn:asciiname":"Dizaj-e Arik",
    "gn:country_code":"IR",
    "gn:dem":1128,
    "gn:feature_class":"P",
    "gn:feature_code":"PPL",
    "gn:name":"D\u012bzaj-e Ar\u012bk",
    "gn:population":0,
    "gn:timezone":"Asia/Tehran",
    "iso:country":"IR",
    "name:aze_x_preferred":[
        "Dizac-i Herik"
    ],
    "name:ceb_x_preferred":[
        "D\u012bzaj-e Ar\u012bk"
    ],
    "name:fas_x_preferred":[
        "D\u012bzaj-e Her\u012bk"
    ],
    "name:fas_x_variant":[
        "D\u012bzaj-e Ar\u012bk",
        "\u062f\u06cc\u0632\u062c \u0627\u0631\u06cc\u06a9",
        "\u062f\u06cc\u0632\u062c \u0647\u0631\u06cc\u06a9"
    ],
    "name:msa_x_preferred":[
        "Dizaj-e Herik"
    ],
    "name:swe_x_preferred":[
        "D\u012bzaj-e Ar\u012bk"
    ],
    "name:und_x_variant":[
        "\u062f\u06cc\u0632\u062c \u0627\u0631\u06cc\u06a9"
    ],
    "wof:name":"Dizaj-e Arik",
    "wof:placetype":"locality"
},
  "geometry": {"coordinates":[44.9691,38.5247],"type":"Point"}
}