{
  "type": "Feature",
  "properties": {
    "gn:admin1_code":"28.0",
    "gn:asciiname":"Qal`eh Shah",
    "gn:country_code":"IR",
    "gn:dem":1618,
    "gn:feature_class":"P",
    "gn:feature_code":"PPL",
    "gn:name":"Qal\u2018eh Sh\u0101h",
    "gn:population":0,
    "gn:timezone":"Asia/Tehran",
    "iso:country":"IR",
    "name:fas_x_preferred":[
        "Qal\u2018eh Sh\u0101h"
    ],
    "name:und_x_variant":[
        "Qal\u2018eh-ye Sh\u0101h"
    ],
    "wof:name":"Qal`eh Shah",
    "wof:placetype":"locality"
},
  "geometry": {"coordinates":[51.43917,32.62667],"type":"Point"}
}