{
  "type": "Feature",
  "properties": {
    "gn:admin1_code":"28",
    "gn:asciiname":"Sahruyeh",
    "gn:country_code":"IR",
    "gn:dem":1252,
    "gn:feature_class":"P",
    "gn:feature_code":"PPL",
    "gn:name":"Sahr\u016byeh",
    "gn:population":0,
    "gn:timezone":"Asia/Tehran",
    "iso:country":"IR",
    "name:fas_x_preferred":[
        "\u0633\u0647\u0631\u0648\u06cc\u0647"
    ],
    "name:fas_x_variant":[
        "Sahr\u016byeh"
    ],
    "name:und_x_variant":[
        "Sohr\u016b\u2018\u012byeh"
    ],
    "wof:name":"Sahruyeh",
    "wof:placetype":"locality"
},
  "geometry": {"coordinates":[52.4565,33.3476],"type":"Point"}
}