{
  "type": "Feature",
  "properties": {
    "gn:admin1_code":"41.0",
    "gn:asciiname":"Qasemabad-e Pa'in",
    "gn:country_code":"IR",
    "gn:dem":1622,
    "gn:feature_class":"P",
    "gn:feature_code":"PPL",
    "gn:name":"Q\u0101sem\u0101b\u0101d-e P\u0101\u2019\u012bn",
    "gn:population":0,
    "gn:timezone":"Asia/Tehran",
    "iso:country":"IR",
    "name:fas_x_preferred":[
        "Q\u0101sem\u0101b\u0101d-e P\u0101\u2019\u012bn"
    ],
    "wof:name":"Qasemabad-e Pa'in",
    "wof:placetype":"locality"
},
  "geometry": {"coordinates":[60.45,32.55],"type":"Point"}
}