{
  "type": "Feature",
  "properties": {
    "gn:admin1_code":"28.0",
    "gn:asciiname":"Mazra`eh Malek",
    "gn:country_code":"IR",
    "gn:dem":2111,
    "gn:feature_class":"P",
    "gn:feature_code":"PPL",
    "gn:name":"Mazra\u2018eh Malek",
    "gn:population":0,
    "gn:timezone":"Asia/Tehran",
    "iso:country":"IR",
    "name:fas_x_preferred":[
        "\u0645\u0632\u0631\u0639\u0647 \u0645\u0644\u06a9"
    ],
    "name:fas_x_variant":[
        "Mazra\u2018eh-ye Malek",
        "Mazra\u2018eh Malek"
    ],
    "wof:name":"Mazra`eh Malek",
    "wof:placetype":"locality"
},
  "geometry": {"coordinates":[52.708,32.7202],"type":"Point"}
}