{
  "type": "Feature",
  "properties": {
    "gn:admin1_code":"13",
    "gn:asciiname":"Kangarban-e Bala",
    "gn:country_code":"IR",
    "gn:dem":1348,
    "gn:feature_class":"P",
    "gn:feature_code":"PPL",
    "gn:name":"Kangarb\u0101n-e B\u0101l\u0101",
    "gn:population":0,
    "gn:timezone":"Asia/Tehran",
    "iso:country":"IR",
    "name:fas_x_preferred":[
        "\u06a9\u0646\u06af\u0631\u0628\u0627\u0646 \u0628\u0627\u0644\u0627"
    ],
    "name:fas_x_variant":[
        "Kangarb\u0101n-e \u2018Oly\u00e1",
        "Kangarb\u0101n-e B\u0101l\u0101"
    ],
    "name:und_x_variant":[
        "Kangarb\u0101n",
        "Kankarb\u0101n-e B\u0101l\u0101"
    ],
    "wof:name":"Kangarban-e Bala",
    "wof:placetype":"locality"
},
  "geometry": {"coordinates":[46.7685,34.3663],"type":"Point"}
}