{
  "type": "Feature",
  "properties": {
    "gn:admin1_code":"29.0",
    "gn:asciiname":"Gozabad",
    "gn:country_code":"IR",
    "gn:dem":1657,
    "gn:feature_class":"P",
    "gn:feature_code":"PPLF",
    "gn:name":"Goz\u0101b\u0101d",
    "gn:population":0,
    "gn:timezone":"Asia/Tehran",
    "iso:country":"IR",
    "name:fas_x_preferred":[
        "Goz\u0101b\u0101d"
    ],
    "name:fas_x_variant":[
        "\u06af\u0632 \u0622\u0628\u0627\u062f"
    ],
    "wof:name":"Gozabad",
    "wof:placetype":"locality"
},
  "geometry": {"coordinates":[56.54592,30.21303],"type":"Point"}
}