{
  "type": "Feature",
  "properties": {
    "gn:admin1_code":"4",
    "gn:asciiname":"Habudan",
    "gn:country_code":"IR",
    "gn:dem":1282,
    "gn:feature_class":"P",
    "gn:feature_code":"PPL",
    "gn:name":"Hab\u016bd\u0101n",
    "gn:population":0,
    "gn:timezone":"Asia/Tehran",
    "iso:country":"IR",
    "name:fas_x_preferred":[
        "\u0647\u0628\u0648\u062f\u0627\u0646"
    ],
    "name:fas_x_variant":[
        "Hab\u016bd\u0101n"
    ],
    "wof:name":"Habudan",
    "wof:placetype":"locality"
},
  "geometry": {"coordinates":[60.22561,26.53902],"type":"Point"}
}