{
  "type": "Feature",
  "properties": {
    "gn:admin1_code":"4.0",
    "gn:asciiname":"Tall",
    "gn:country_code":"IR",
    "gn:dem":1255,
    "gn:feature_class":"P",
    "gn:feature_code":"PPL",
    "gn:name":"Tall",
    "gn:population":0,
    "gn:timezone":"Asia/Tehran",
    "iso:country":"IR",
    "name:ara_x_preferred":[
        "\u0637\u0648\u064a\u0644"
    ],
    "name:ceb_x_preferred":[
        "Tall"
    ],
    "name:deu_x_preferred":[
        "Tall"
    ],
    "name:fas_x_preferred":[
        "\u062a\u0644"
    ],
    "name:fra_x_preferred":[
        "Tall"
    ],
    "name:rus_x_preferred":[
        "\u0422\u043e\u043b\u043b"
    ],
    "name:swe_x_preferred":[
        "Tall"
    ],
    "wof:name":"Tall",
    "wof:placetype":"locality"
},
  "geometry": {"coordinates":[61.78518,27.16904000000001],"type":"Point"}
}