{
  "type": "Feature",
  "properties": {
    "gn:admin1_code":"33",
    "gn:asciiname":"Gonbadan",
    "gn:country_code":"IR",
    "gn:dem":1668,
    "gn:feature_class":"P",
    "gn:feature_code":"PPL",
    "gn:name":"Gonbad\u0101n",
    "gn:population":0,
    "gn:timezone":"Asia/Tehran",
    "iso:country":"IR",
    "name:azb_x_preferred":[
        "\u06af\u0646\u0628\u062f\u0627\u0646"
    ],
    "name:fas_x_preferred":[
        "\u06af\u0646\u0628\u062f\u0627\u0646"
    ],
    "name:fas_x_variant":[
        "Gonbad\u0101n"
    ],
    "name:msa_x_preferred":[
        "Gonbadan"
    ],
    "wof:name":"Gonbadan",
    "wof:placetype":"locality"
},
  "geometry": {"coordinates":[47.5935,37.8965],"type":"Point"}
}