{
  "type": "Feature",
  "properties": {
    "gn:admin1_code":"35.0",
    "gn:asciiname":"Hari Kandeh-e Bala",
    "gn:country_code":"IR",
    "gn:dem":14,
    "gn:feature_class":"P",
    "gn:feature_code":"PPL",
    "gn:name":"Har\u012b Kandeh-e B\u0101l\u0101",
    "gn:population":0,
    "gn:timezone":"Asia/Tehran",
    "iso:country":"IR",
    "name:fas_x_preferred":[
        "Har\u012b Kandeh-e B\u0101l\u0101"
    ],
    "name:fas_x_variant":[
        "\u0647\u0631\u06cc \u0643\u0646\u062f\u0647 \u0628\u0627\u0644\u0627"
    ],
    "wof:name":"Hari Kandeh-e Bala",
    "wof:placetype":"locality"
},
  "geometry": {"coordinates":[52.725,36.48998],"type":"Point"}
}