{
  "type": "Feature",
  "properties": {
    "gn:admin1_code":"43",
    "gn:asciiname":"Cherrik",
    "gn:country_code":"IR",
    "gn:dem":994,
    "gn:feature_class":"P",
    "gn:feature_code":"PPL",
    "gn:name":"Cherr\u012bk",
    "gn:population":0,
    "gn:timezone":"Asia/Tehran",
    "iso:country":"IR",
    "name:fas_x_preferred":[
        "Cherr\u012bk"
    ],
    "name:fas_x_variant":[
        "\u0686\u0631\u06cc\u06a9"
    ],
    "name:und_x_variant":[
        "Cherik",
        "Charr\u012bk",
        "Cherak",
        "\u0686\u0631\u06cc\u06a9"
    ],
    "wof:name":"Cherrik",
    "wof:placetype":"locality"
},
  "geometry": {"coordinates":[57.11896,37.58012],"type":"Point"}
}