{
  "type": "Feature",
  "properties": {
    "gn:admin1_code":"23",
    "gn:asciiname":"Qal`eh Mohammad",
    "gn:country_code":"IR",
    "gn:dem":1862,
    "gn:feature_class":"P",
    "gn:feature_code":"PPL",
    "gn:name":"Qal\u2018eh Mo\u1e29ammad",
    "gn:population":0,
    "gn:timezone":"Asia/Tehran",
    "iso:country":"IR",
    "name:fas_x_preferred":[
        "\u0642\u064e\u0644\u0639\u0650\u0647 \u0645\u064f\u062d\u064e\u0645\u064e\u0651\u062f"
    ],
    "name:fas_x_variant":[
        "\u0643\u0650\u0634\u0648\u064e\u0631 \u0642\u064e\u0644\u0639\u0650\u0647 \u0645\u064f\u062d\u064e\u0645\u064e\u0651\u062f",
        "\u0642\u064f\u0644\u0627 \u0645\u064f\u062d\u064e\u0645\u064e\u0651\u062f",
        "\u0642\u064e\u0644\u0639\u0650\u06c0 \u0645\u064f\u062d\u064e\u0645\u064e\u0651\u062f",
        "\u0642\u0644\u0639\u0647 \u0645\u062d\u0645\u0651\u062f",
        "Qal\u2018eh Mo\u1e29ammad",
        "Gash\u016br-e Qal\u2018eh Mo\u1e29ammad",
        "\u06af\u064e\u0634\u0648\u0631\u0650 \u0642\u064e\u0644\u0639\u0650\u0647 \u0645\u064f\u062d\u064e\u0645\u064e\u0651\u062f"
    ],
    "name:und_x_variant":[
        "Kal\u0101m-i- Ahmad",
        "Qal\u2018eh-ye Mo\u1e29ammad",
        "Qol\u0101 Mo\u1e29ammad",
        "Keshvar Qal\u2018eh Mo\u1e29ammad"
    ],
    "wof:name":"Qal`eh Mohammad",
    "wof:placetype":"locality"
},
  "geometry": {"coordinates":[47.7214,34.2322],"type":"Point"}
}