{
  "type": "Feature",
  "properties": {
    "gn:admin1_code":"15",
    "gn:asciiname":"Shahrak-e Azadi",
    "gn:country_code":"IR",
    "gn:dem":116,
    "gn:feature_class":"P",
    "gn:feature_code":"PPL",
    "gn:name":"Shahrak-e \u0100z\u0101d\u012b",
    "gn:population":0,
    "gn:timezone":"Asia/Tehran",
    "iso:country":"IR",
    "name:fas_x_preferred":[
        "\u0634\u0647\u0631\u06a9 \u0622\u0632\u0627\u062f\u06cc"
    ],
    "name:fas_x_variant":[
        "Shahrak-e \u0100z\u0101d\u012b",
        "\u0634\u0647\u0631\u06a9 \u0628\u0627\u0628\u06a9"
    ],
    "name:und_x_variant":[
        "Shahrak-e B\u0101bak"
    ],
    "wof:name":"Shahrak-e Azadi",
    "wof:placetype":"locality"
},
  "geometry": {"coordinates":[48.25176,32.40408],"type":"Point"}
}