{
  "type": "Feature",
  "properties": {
    "gn:admin1_code":"40.0",
    "gn:asciiname":"Azmighan",
    "gn:country_code":"IR",
    "gn:dem":956,
    "gn:feature_class":"P",
    "gn:feature_code":"PPL",
    "gn:name":"Azm\u012bgh\u0101n",
    "gn:population":0,
    "gn:timezone":"Asia/Tehran",
    "iso:country":"IR",
    "name:ceb_x_preferred":[
        "Azm\u012bgh\u0101n"
    ],
    "name:fas_x_preferred":[
        "Az\u0304m\u012bgh\u0101n"
    ],
    "name:fas_x_variant":[
        "\u0627\u0630\u0645\u064a\u063a\u0627\u0646",
        "Ezm\u012bq\u0101n",
        "\u0627\u0632\u0645\u064a\u063a\u0627\u0646",
        "\u0627\u0632\u0645\u06cc\u063a\u0627\u0646"
    ],
    "name:swe_x_preferred":[
        "Azm\u012bgh\u0101n"
    ],
    "wof:name":"Azmighan",
    "wof:placetype":"locality"
},
  "geometry": {"coordinates":[56.89196999999999,33.8257],"type":"Point"}
}