{
  "type": "Feature",
  "properties": {
    "gn:admin1_code":"1",
    "gn:asciiname":"Chir Kord",
    "gn:country_code":"IR",
    "gn:dem":1601,
    "gn:feature_class":"P",
    "gn:feature_code":"PPL",
    "gn:name":"Ch\u012br Kord",
    "gn:population":0,
    "gn:timezone":"Asia/Tehran",
    "iso:country":"IR",
    "name:fas_x_preferred":[
        "Ch\u012br"
    ],
    "name:fas_x_variant":[
        "Ch\u012br Kord",
        "\u0686\u06cc\u0631 \u06a9\u0631\u062f"
    ],
    "wof:name":"Chir Kord",
    "wof:placetype":"locality"
},
  "geometry": {"coordinates":[44.8152,38.8798],"type":"Point"}
}