{
  "type": "Feature",
  "properties": {
    "gn:admin1_code":"15",
    "gn:asciiname":"Pian-e Sofla",
    "gn:country_code":"IR",
    "gn:dem":837,
    "gn:feature_class":"P",
    "gn:feature_code":"PPL",
    "gn:name":"P\u012b\u0101n-e Sofl\u00e1",
    "gn:population":0,
    "gn:timezone":"Asia/Tehran",
    "iso:country":"IR",
    "name:azb_x_preferred":[
        "\u067e\u06cc\u0627\u0646 \u0633\u0641\u0644\u06cc(\u0627\u06cc\u0630\u0647)"
    ],
    "name:ceb_x_preferred":[
        "P\u012b\u0101n-e P\u0101\u2018\u012bn"
    ],
    "name:fas_x_preferred":[
        "P\u012b\u0101n-e Sofl\u00e1"
    ],
    "name:fas_x_variant":[
        "P\u012b\u0101n-e P\u0101\u2018\u012bn",
        "\u067e\u06cc\u0627\u0646 \u067e\u0627\u0626\u06cc\u0646",
        "\u067e\u06cc\u0627\u0646 \u0633\u0641\u0644\u06cc"
    ],
    "name:swe_x_preferred":[
        "P\u012b\u0101n-e P\u0101\u2018\u012bn"
    ],
    "name:und_x_variant":[
        "\u067e\u06cc\u0627\u0646 \u067e\u0627\u0626\u06cc\u0646"
    ],
    "wof:name":"Pian-e Sofla",
    "wof:placetype":"locality"
},
  "geometry": {"coordinates":[49.79702,31.96742],"type":"Point"}
}