{
  "type": "Feature",
  "properties": {
    "gn:admin1_code":"3",
    "gn:asciiname":"Enkak",
    "gn:country_code":"IR",
    "gn:dem":1444,
    "gn:feature_class":"P",
    "gn:feature_code":"PPL",
    "gn:name":"Enkak",
    "gn:population":0,
    "gn:timezone":"Asia/Tehran",
    "iso:country":"IR",
    "name:fas_x_preferred":[
        "\u012anekek"
    ],
    "name:fas_x_variant":[
        "\u0627\u0646\u06af\u06a9",
        "\u0627\u0646\u06a9\u06a9",
        "\u0627\u06cc\u0646\u06a9\u06a9"
    ],
    "name:und_x_variant":[
        "Enekek",
        "\u012anekak",
        "Engak",
        "\u0627\u0646\u06af\u06a9",
        "Enkak"
    ],
    "wof:name":"Enkak",
    "wof:placetype":"locality"
},
  "geometry": {"coordinates":[50.97062,31.27234],"type":"Point"}
}