{
  "type": "Feature",
  "properties": {
    "gn:admin1_code":"1",
    "gn:asciiname":"Mahmud Aghol",
    "gn:country_code":"IR",
    "gn:dem":1482,
    "gn:feature_class":"P",
    "gn:feature_code":"PPL",
    "gn:name":"Ma\u1e29m\u016bd \u0100ghol",
    "gn:population":0,
    "gn:timezone":"Asia/Tehran",
    "iso:country":"IR",
    "name:azb_x_preferred":[
        "\u0645\u0627\u062d\u0645\u0648\u062f\u0627\u063a\u0648\u0644\u06cc"
    ],
    "name:aze_x_preferred":[
        "Mahmuda\u011f\u0131l\u0131"
    ],
    "name:fas_x_preferred":[
        "\u0645\u064e\u062d\u0645\u0648\u062f \u0622\u063a\u0644\u06cc"
    ],
    "name:fas_x_variant":[
        "\u0645\u062d\u0645\u0648\u062f \u0622\u063a\u0644",
        "Ma\u1e29m\u016bd \u0100ghl\u012b",
        "Ma\u1e29m\u016bd \u0100ghol",
        "\u0645\u062d\u0645\u0648\u062f\u0627\u063a\u0644\u06cc"
    ],
    "name:msa_x_preferred":[
        "Mahmud Aghli"
    ],
    "wof:name":"Mahmud Aghol",
    "wof:placetype":"locality"
},
  "geometry": {"coordinates":[44.6783,39.3845],"type":"Point"}
}