{
  "type": "Feature",
  "properties": {
    "gn:admin1_code":"1",
    "gn:asciiname":"Beyk Jan",
    "gn:country_code":"IR",
    "gn:dem":924,
    "gn:feature_class":"P",
    "gn:feature_code":"PPL",
    "gn:name":"Beyk J\u0101n",
    "gn:population":0,
    "gn:timezone":"Asia/Tehran",
    "iso:country":"IR",
    "name:fas_x_preferred":[
        "\u0628\u064a\u0633\u062a\u0627\u0646"
    ],
    "name:fas_x_variant":[
        "\u0628\u06cc\u06a9 \u062c\u0627\u0646",
        "B\u0101yj\u0101n",
        "Beyk J\u0101n",
        "\u0628\u0627\u064a\u062c\u0627\u0646 \u06af\u064e\u0686\u0644\u064e\u0631\u0627\u062a",
        "\u0628\u0650\u064a\u06af\u062c\u0627\u0646",
        "\u0628\u0627\u064a\u062c\u0627\u0646\u0650 \u06af\u0650\u0686\u0644\u064e\u0631\u0627\u062a",
        "\u0628\u0627\u064a\u062c\u0627\u0646"
    ],
    "name:und_x_variant":[
        "B\u0101yj\u0101n Gachlar\u0101t",
        "Beygj\u0101n",
        "Beistan",
        "B\u0101yj\u0101n-e Gechlar\u0101t",
        "B\u012bst\u0101n",
        "\u0628\u0627\u064a\u062c\u0627\u0646"
    ],
    "wof:name":"Beyk Jan",
    "wof:placetype":"locality"
},
  "geometry": {"coordinates":[45.2627,39.0823],"type":"Point"}
}