{
  "type": "Feature",
  "properties": {
    "gn:admin1_code":"11",
    "gn:asciiname":"Takhteh Maram",
    "gn:country_code":"IR",
    "gn:dem":432,
    "gn:feature_class":"P",
    "gn:feature_code":"PPL",
    "gn:name":"Takhteh M\u0101r\u0101m",
    "gn:population":0,
    "gn:timezone":"Asia/Tehran",
    "iso:country":"IR",
    "name:fas_x_preferred":[
        "\u062a\u064e\u062e\u062a\u0650\u0647 \u0645\u0627\u0631\u0627\u0645"
    ],
    "name:fas_x_variant":[
        "Takhteh M\u0101r\u0101m"
    ],
    "wof:name":"Takhteh Maram",
    "wof:placetype":"locality"
},
  "geometry": {"coordinates":[55.88028000000001,27.7175],"type":"Point"}
}