{
  "type": "Feature",
  "properties": {
    "gn:admin1_code":"5",
    "gn:asciiname":"Sar Sureh",
    "gn:country_code":"IR",
    "gn:dem":842,
    "gn:feature_class":"P",
    "gn:feature_code":"PPL",
    "gn:name":"Sar S\u016breh",
    "gn:population":0,
    "gn:timezone":"Asia/Tehran",
    "iso:country":"IR",
    "name:fas_x_preferred":[
        "\u0633\u0631 \u0633\u0648\u0631\u0647"
    ],
    "name:fas_x_variant":[
        "Sar S\u016breh"
    ],
    "wof:name":"Sar Sureh",
    "wof:placetype":"locality"
},
  "geometry": {"coordinates":[50.29371,30.97842],"type":"Point"}
}