{
  "type": "Feature",
  "properties": {
    "gn:admin1_code":"16.0",
    "gn:asciiname":"Halu",
    "gn:country_code":"IR",
    "gn:dem":1350,
    "gn:feature_class":"P",
    "gn:feature_code":"PPL",
    "gn:name":"H\u0101l\u016b",
    "gn:population":0,
    "gn:timezone":"Asia/Tehran",
    "iso:country":"IR",
    "name:ara_x_preferred":[
        "\u0647\u0644\u0648"
    ],
    "name:ceb_x_preferred":[
        "H\u0101l\u016b"
    ],
    "name:ckb_x_preferred":[
        "\u06be\u06d5\u06b5\u06c6"
    ],
    "name:fas_x_preferred":[
        "\u0647\u0627\u0644\u0648"
    ],
    "name:fas_x_variant":[
        "H\u0101l\u016b",
        "\u0647\u0644\u0648"
    ],
    "name:swe_x_preferred":[
        "H\u0101l\u016b"
    ],
    "wof:name":"Halu",
    "wof:placetype":"locality"
},
  "geometry": {"coordinates":[45.6747,36.1051],"type":"Point"}
}