{
  "type": "Feature",
  "properties": {
    "gn:admin1_code":"32",
    "gn:asciiname":"Surkha Kandi",
    "gn:country_code":"IR",
    "gn:dem":116,
    "gn:feature_class":"P",
    "gn:feature_code":"PPL",
    "gn:name":"S\u016brkh\u0101 Kand\u012b",
    "gn:population":0,
    "gn:timezone":"Asia/Tehran",
    "iso:country":"IR",
    "name:fas_x_preferred":[
        "\u0633\u0648\u0631\u062e\u0627 \u0643\u064e\u0646\u062f\u06cc"
    ],
    "name:fas_x_variant":[
        "S\u016brkh\u0101 Kand\u012b"
    ],
    "wof:name":"Surkha Kandi",
    "wof:placetype":"locality"
},
  "geometry": {"coordinates":[47.55556,39.50444],"type":"Point"}
}