{
  "type": "Feature",
  "properties": {
    "gn:admin1_code":"32",
    "gn:asciiname":"Hajji Nosrat",
    "gn:country_code":"IR",
    "gn:dem":307,
    "gn:feature_class":"P",
    "gn:feature_code":"PPL",
    "gn:name":"\u1e28\u0101jj\u012b No\u015frat",
    "gn:population":0,
    "gn:timezone":"Asia/Tehran",
    "iso:country":"IR",
    "name:fas_x_preferred":[
        "\u062d\u0627\u062c\u06cc \u0646\u0635\u0631\u062a"
    ],
    "name:fas_x_variant":[
        "\u1e28\u0101jj\u012b No\u015frat"
    ],
    "name:und_x_variant":[
        "\u1e28\u0101jj\u012b No\u015frat"
    ],
    "wof:name":"Hajji Nosrat",
    "wof:placetype":"locality"
},
  "geometry": {"coordinates":[47.5009,39.3518],"type":"Point"}
}