{
  "type": "Feature",
  "properties": {
    "gn:admin1_code":"4.0",
    "gn:asciiname":"Khvajeh Mahmudi",
    "gn:country_code":"IR",
    "gn:dem":483,
    "gn:feature_class":"P",
    "gn:feature_code":"PPL",
    "gn:name":"Khv\u0101jeh Ma\u1e29m\u016bd\u012b",
    "gn:population":0,
    "gn:timezone":"Asia/Tehran",
    "iso:country":"IR",
    "name:fas_x_preferred":[
        "\u062e\u0648\u0627\u062c\u0647 \u0645\u062d\u0645\u0648\u062f\u06cc"
    ],
    "name:fas_x_variant":[
        "Khv\u0101jeh Ma\u1e29m\u016bd\u012b"
    ],
    "wof:name":"Khvajeh Mahmudi",
    "wof:placetype":"locality"
},
  "geometry": {"coordinates":[61.5543,31.0965],"type":"Point"}
}