{
  "type": "Feature",
  "properties": {
    "gn:admin1_code":"11.0",
    "gn:asciiname":"Jumahalleh-ye Talvar",
    "gn:country_code":"IR",
    "gn:dem":18,
    "gn:feature_class":"P",
    "gn:feature_code":"PPL",
    "gn:name":"J\u016bma\u1e29alleh-ye T\u0101lv\u0101r",
    "gn:population":0,
    "gn:timezone":"Asia/Tehran",
    "iso:country":"IR",
    "name:fas_x_preferred":[
        "\u062c\u0648\u0645\u062d\u0644\u0647 \u062a\u0627\u0644\u0648\u0627\u0631"
    ],
    "name:und_x_variant":[
        "J\u016bma\u1e29alleh-ye T\u0101lv\u0101r"
    ],
    "wof:name":"Jumahalleh-ye Talvar",
    "wof:placetype":"locality"
},
  "geometry": {"coordinates":[57.1155,26.941],"type":"Point"}
}