{
  "type": "Feature",
  "properties": {
    "gn:admin1_code":"23",
    "gn:asciiname":"Rahimabad",
    "gn:country_code":"IR",
    "gn:dem":1651,
    "gn:feature_class":"P",
    "gn:feature_code":"PPL",
    "gn:name":"Ra\u1e29\u012bm\u0101b\u0101d",
    "gn:population":0,
    "gn:timezone":"Asia/Tehran",
    "iso:country":"IR",
    "name:fas_x_preferred":[
        "\u062d\u064f\u0633\u0650\u064a\u0646\u0627\u0628\u0627\u062f\u0650 \u0627\u064e\u0645\u064a\u0631\u06cc"
    ],
    "name:fas_x_variant":[
        "\u062d\u064f\u0633\u0650\u064a\u0646\u062c\u0627\u0646",
        "\u062d\u0633\u06cc\u0646 \u0622\u0628\u0627\u062f",
        "\u1e28oseyn\u0101b\u0101d-e Am\u012br\u012b",
        "\u1e28oseyn\u0101b\u0101d",
        "\u0631\u062d\u06cc\u0645 \u0622\u0628\u0627\u062f"
    ],
    "name:und_x_variant":[
        "\u1e28oseynj\u0101n",
        "Ra\u1e29\u012bm\u0101b\u0101d"
    ],
    "wof:name":"Rahimabad",
    "wof:placetype":"locality"
},
  "geometry": {"coordinates":[48.26147,33.9031],"type":"Point"}
}