{
  "type": "Feature",
  "properties": {
    "gn:admin1_code":"29.0",
    "gn:asciiname":"`Aliabad-e Jar",
    "gn:country_code":"IR",
    "gn:dem":1724,
    "gn:feature_class":"P",
    "gn:feature_code":"PPL",
    "gn:name":"\u2018Al\u012b\u0101b\u0101d-e Jar",
    "gn:population":0,
    "gn:timezone":"Asia/Tehran",
    "iso:country":"IR",
    "name:fas_x_preferred":[
        "\u2018Al\u012b\u0101b\u0101d-e Jar"
    ],
    "name:und_x_variant":[
        "\u2019Al\u012b\u0101b\u0101d-e Jahr"
    ],
    "wof:name":"`Aliabad-e Jar",
    "wof:placetype":"locality"
},
  "geometry": {"coordinates":[56.89861,30.44944000000001],"type":"Point"}
}