{
  "type": "Feature",
  "properties": {
    "gn:admin1_code":"38",
    "gn:asciiname":"Garmarud-e Sofla",
    "gn:country_code":"IR",
    "gn:dem":1281,
    "gn:elevation":"0.0",
    "gn:feature_class":"P",
    "gn:feature_code":"PPL",
    "gn:name":"Garm\u0101r\u016bd-e Sofl\u00e1",
    "gn:population":0,
    "gn:timezone":"Asia/Tehran",
    "iso:country":"IR",
    "name:fas_x_preferred":[
        "\u06af\u0631\u0645\u0627\u0631\u0648\u062f \u067e\u0627\u0626\u06cc\u0646"
    ],
    "name:fas_x_variant":[
        "\u06af\u0631\u0645\u0627\u0631\u0648\u062f \u0633\u0641\u0644\u06cc"
    ],
    "name:und_x_variant":[
        "Garm\u0101r\u016bd-e P\u0101\u2019\u012bn",
        "Garm\u0101r\u016bd-e Sofl\u00e1"
    ],
    "wof:name":"Garmarud-e Sofla",
    "wof:placetype":"locality"
},
  "geometry": {"coordinates":[50.38368,36.46245],"type":"Point"}
}