{
  "type": "Feature",
  "properties": {
    "gn:admin1_code":"29",
    "gn:asciiname":"Pa Deh",
    "gn:country_code":"IR",
    "gn:dem":2795,
    "gn:feature_class":"P",
    "gn:feature_code":"PPL",
    "gn:name":"P\u0101 Deh",
    "gn:population":0,
    "gn:timezone":"Asia/Tehran",
    "iso:country":"IR",
    "name:fas_x_preferred":[
        "\u067e\u0627 \u062f\u0650\u0647"
    ],
    "name:fas_x_variant":[
        "P\u0101 Deh"
    ],
    "name:und_x_variant":[
        "Padou"
    ],
    "wof:name":"Pa Deh",
    "wof:placetype":"locality"
},
  "geometry": {"coordinates":[57.58333,29.36667000000001],"type":"Point"}
}