{
  "type": "Feature",
  "properties": {
    "gn:admin1_code":"42",
    "gn:asciiname":"Aghuyeh",
    "gn:country_code":"IR",
    "gn:dem":1417,
    "gn:feature_class":"P",
    "gn:feature_code":"PPL",
    "gn:name":"\u0100gh\u016byeh",
    "gn:population":0,
    "gn:timezone":"Asia/Tehran",
    "iso:country":"IR",
    "name:fas_x_preferred":[
        "\u0622\u063a\u0648\u06cc\u0647"
    ],
    "name:fas_x_variant":[
        "\u0100gh\u016byeh"
    ],
    "wof:name":"Aghuyeh",
    "wof:placetype":"locality"
},
  "geometry": {"coordinates":[59.20575,35.30468],"type":"Point"}
}