{
  "type": "Feature",
  "properties": {
    "gn:admin1_code":"1.0",
    "gn:asciiname":"Gurangah",
    "gn:country_code":"IR",
    "gn:dem":1289,
    "gn:feature_class":"P",
    "gn:feature_code":"PPL",
    "gn:name":"G\u016br\u0101ngah",
    "gn:population":0,
    "gn:timezone":"Asia/Tehran",
    "iso:country":"IR",
    "name:fas_x_preferred":[
        "\u06af\u0648\u0631\u0627\u0646\u06af\u0647"
    ],
    "name:fas_x_variant":[
        "G\u016br\u0101ngah"
    ],
    "wof:name":"Gurangah",
    "wof:placetype":"locality"
},
  "geometry": {"coordinates":[45.4842,36.2076],"type":"Point"}
}