{
  "type": "Feature",
  "properties": {
    "gn:admin1_code":"4.0",
    "gn:asciiname":"Manesh",
    "gn:country_code":"IR",
    "gn:dem":1440,
    "gn:feature_class":"P",
    "gn:feature_code":"PPLF",
    "gn:name":"M\u0101nesh",
    "gn:population":0,
    "gn:timezone":"Asia/Tehran",
    "iso:country":"IR",
    "name:fas_x_preferred":[
        "\u0645\u0627\u0646\u0634"
    ],
    "name:fas_x_variant":[
        "M\u0101nesh"
    ],
    "wof:name":"Manesh",
    "wof:placetype":"locality"
},
  "geometry": {"coordinates":[61.31289,27.40234],"type":"Point"}
}