{
  "type": "Feature",
  "properties": {
    "gn:admin1_code":"25.0",
    "gn:asciiname":"Ab-e Garm",
    "gn:cc2":"IR",
    "gn:country_code":"IR",
    "gn:dem":1319,
    "gn:feature_class":"P",
    "gn:feature_code":"PPL",
    "gn:name":"\u0100b-e Garm",
    "gn:population":0,
    "gn:timezone":"Asia/Tehran",
    "iso:country":"IR",
    "name:fas_x_preferred":[
        "\u0622\u0628\u0650 \u06af\u064e\u0631\u0645"
    ],
    "name:fas_x_variant":[
        "\u0100b-e Garm"
    ],
    "name:und_x_variant":[
        "\u0100b-i-Garm"
    ],
    "wof:name":"Ab-e Garm",
    "wof:placetype":"locality"
},
  "geometry": {"coordinates":[53.68333000000001,35.55],"type":"Point"}
}