{
  "type": "Feature",
  "properties": {
    "gn:admin1_code":"29",
    "gn:asciiname":"Sang Siah",
    "gn:country_code":"IR",
    "gn:dem":2570,
    "gn:feature_class":"P",
    "gn:feature_code":"PPL",
    "gn:name":"Sang S\u012b\u0101h",
    "gn:population":0,
    "gn:timezone":"Asia/Tehran",
    "iso:country":"IR",
    "name:fas_x_preferred":[
        "\u0633\u0646\u06af \u0633\u06cc\u0627\u0647"
    ],
    "name:fas_x_variant":[
        "Sang S\u012b\u0101h"
    ],
    "wof:name":"Sang Siah",
    "wof:placetype":"locality"
},
  "geometry": {"coordinates":[56.1056,29.8117],"type":"Point"}
}