{
  "type": "Feature",
  "properties": {
    "gn:admin1_code":"28",
    "gn:asciiname":"Komeshcheh",
    "gn:country_code":"IR",
    "gn:dem":2026,
    "gn:feature_class":"P",
    "gn:feature_code":"PPL",
    "gn:name":"Komeshcheh",
    "gn:population":0,
    "gn:timezone":"Asia/Tehran",
    "iso:country":"IR",
    "name:fas_x_preferred":[
        "\u06a9\u0645\u0634\u0686\u0647"
    ],
    "name:und_x_variant":[
        "Komshecheh",
        "Komeshcheh"
    ],
    "wof:name":"Komeshcheh",
    "wof:placetype":"locality"
},
  "geometry": {"coordinates":[52.0554,33.231],"type":"Point"}
}