{
  "type": "Feature",
  "properties": {
    "gn:admin1_code":"29.0",
    "gn:asciiname":"Kahur Zard",
    "gn:country_code":"IR",
    "gn:dem":628,
    "gn:feature_class":"P",
    "gn:feature_code":"PPLL",
    "gn:name":"Kah\u016br Zard",
    "gn:population":0,
    "gn:timezone":"Asia/Tehran",
    "iso:country":"IR",
    "name:fas_x_preferred":[
        "\u06a9\u0647\u0648\u0631 \u0632\u0631\u062f"
    ],
    "name:und_x_variant":[
        "Kah\u016br Zard"
    ],
    "wof:name":"Kahur Zard",
    "wof:placetype":"locality"
},
  "geometry": {"coordinates":[58.53525,28.05841],"type":"Point"}
}