{
  "type": "Feature",
  "properties": {
    "gn:admin1_code":"42",
    "gn:asciiname":"Deh-e Now Khalaj",
    "gn:country_code":"IR",
    "gn:dem":1171,
    "gn:feature_class":"P",
    "gn:feature_code":"PPL",
    "gn:name":"Deh-e Now Khalaj",
    "gn:population":0,
    "gn:timezone":"Asia/Tehran",
    "iso:country":"IR",
    "name:fas_x_preferred":[
        "\u062f\u0647 \u0646\u0648 \u062e\u0644\u062c"
    ],
    "name:und_x_variant":[
        "Dehnow-e Khalaj",
        "Deh Now-ye Khalaj",
        "Deh-e Now Khalaj"
    ],
    "wof:name":"Deh-e Now Khalaj",
    "wof:placetype":"locality"
},
  "geometry": {"coordinates":[58.57885,36.2886],"type":"Point"}
}