{
  "type": "Feature",
  "properties": {
    "gn:admin1_code":"8",
    "gn:asciiname":"Gereh Mar",
    "gn:country_code":"IR",
    "gn:dem":1461,
    "gn:feature_class":"P",
    "gn:feature_code":"PPL",
    "gn:name":"Gereh M\u0101r",
    "gn:population":0,
    "gn:timezone":"Asia/Tehran",
    "iso:country":"IR",
    "name:fas_x_preferred":[
        "\u0643\u0628\u0648\u062f \u0645\u0647\u0631"
    ],
    "name:fas_x_variant":[
        "\u0643\u0648\u0631\u0627\u0645\u0627\u0631",
        "Kab\u016bd Mehr",
        "K\u016br\u0101m\u0101r",
        "\u06af\u0631\u0647 \u0645\u0627\u0631",
        "\u06a9\u0628\u0648\u062f\u0645\u0647\u0631"
    ],
    "name:msa_x_preferred":[
        "Kabud Mehr"
    ],
    "name:ukr_x_preferred":[
        "\u041a\u0430\u0431\u0443\u0434\u043c\u0435\u0445\u0440"
    ],
    "name:und_x_variant":[
        "Gereh M\u0101r"
    ],
    "wof:name":"Gereh Mar",
    "wof:placetype":"locality"
},
  "geometry": {"coordinates":[48.64754,37.87267],"type":"Point"}
}