{
  "type": "Feature",
  "properties": {
    "gn:admin1_code":"34",
    "gn:asciiname":"Qal`eh-ye Dizijan",
    "gn:country_code":"IR",
    "gn:dem":1961,
    "gn:feature_class":"P",
    "gn:feature_code":"PPL",
    "gn:name":"Qal\u2018eh-ye D\u012bz\u012bj\u0101n",
    "gn:population":0,
    "gn:timezone":"Asia/Tehran",
    "iso:country":"IR",
    "name:fas_x_preferred":[
        "\u0642\u0644\u0639\u0647 \u062f\u06cc\u0632\u06cc\u062c\u0627\u0646"
    ],
    "name:fas_x_variant":[
        "\u0642\u064e\u0644\u0639\u0650\u0647 \u062f\u064a\u0632\u06cc \u062c\u0627\u0646",
        "Qal\u2018eh-ye D\u012bz\u012bj\u0101n"
    ],
    "name:und_x_variant":[
        "Ghal\u2018eh Dizijan",
        "Qal\u2018eh D\u012bz\u012b J\u0101n"
    ],
    "wof:name":"Qal`eh-ye Dizijan",
    "wof:placetype":"locality"
},
  "geometry": {"coordinates":[49.53815,33.87168],"type":"Point"}
}