{
  "type": "Feature",
  "properties": {
    "gn:admin1_code":"8.0",
    "gn:asciiname":"Gavakedeh",
    "gn:country_code":"IR",
    "gn:dem":-19,
    "gn:feature_class":"P",
    "gn:feature_code":"PPL",
    "gn:name":"G\u0101vakedeh",
    "gn:population":0,
    "gn:timezone":"Asia/Tehran",
    "iso:country":"IR",
    "name:fas_x_preferred":[
        "\u06af\u0627\u0648\u06a9 \u062f\u0647"
    ],
    "name:fas_x_variant":[
        "G\u0101v Kadeh",
        "\u06af\u0627\u0648\u06a9\u062f\u0647",
        "\u06af\u06cc\u0627\u0647 \u06a9\u0648",
        "\u06af\u06cc\u0627\u0647 \u06a9\u0648\u0647"
    ],
    "name:und_x_variant":[
        "K\u0101vak Deh",
        "Esl\u0101m\u0101b\u0101d",
        "G\u0101vakedeh",
        "G\u0101vak Deh",
        "G\u012b\u0101h K\u016b",
        "G\u012b\u0101h K\u016bh",
        "G\u012blk\u016b"
    ],
    "wof:name":"Gavakedeh",
    "wof:placetype":"locality"
},
  "geometry": {"coordinates":[49.3449,37.3669],"type":"Point"}
}