{
  "type": "Feature",
  "properties": {
    "gn:admin1_code":"10.0",
    "gn:asciiname":"Khuran-e Sofla",
    "gn:country_code":"IR",
    "gn:dem":1191,
    "gn:feature_class":"P",
    "gn:feature_code":"PPL",
    "gn:name":"Kh\u016br\u0101n-e Sofl\u00e1",
    "gn:population":0,
    "gn:timezone":"Asia/Tehran",
    "iso:country":"IR",
    "name:ara_x_preferred":[
        "\u062e\u0648\u0631\u0627\u0646 \u0633\u0641\u0644\u064a"
    ],
    "name:ceb_x_preferred":[
        "Kh\u016br\u0101n-e Sofl\u00e1"
    ],
    "name:fas_x_preferred":[
        "\u062e\u0648\u0631\u0627\u0646 \u0633\u0641\u0644\u0649"
    ],
    "name:fas_x_variant":[
        "Kh\u016br\u0101n-e Sofl\u00e1",
        "\u062e\u0648\u0631\u0627\u0646 \u0633\u0641\u0644\u06cc"
    ],
    "name:msa_x_preferred":[
        "Khuran-e Sofla"
    ],
    "name:swe_x_preferred":[
        "Kh\u016br\u0101n-e Sofl\u00e1"
    ],
    "wof:name":"Khuran-e Sofla",
    "wof:placetype":"locality"
},
  "geometry": {"coordinates":[46.2426,33.8295],"type":"Point"}
}