{
  "type": "Feature",
  "properties": {
    "gn:admin1_code":"36",
    "gn:asciiname":"Kordnab",
    "gn:country_code":"IR",
    "gn:dem":1990,
    "gn:feature_class":"P",
    "gn:feature_code":"PPL",
    "gn:name":"Kordn\u0101b",
    "gn:population":0,
    "gn:timezone":"Asia/Tehran",
    "iso:country":"IR",
    "name:azb_x_preferred":[
        "\u06a9\u0631\u062f\u0647 \u0646\u0627\u0628"
    ],
    "name:fas_x_preferred":[
        "\u0643\u0631\u062f\u0647 \u0646\u0627\u0628"
    ],
    "name:fas_x_variant":[
        "Kordeh N\u0101b",
        "\u06a9\u0631\u062f\u0646\u0627\u0628",
        "\u06a9\u0631\u062f\u0647 \u0646\u0627\u0628"
    ],
    "name:und_x_variant":[
        "Kardahn\u0101b",
        "Gerdeh N\u0101b",
        "Karkhina",
        "Kordn\u0101b",
        "Kordeh Nof Eskand",
        "Kordeh Now"
    ],
    "wof:name":"Kordnab",
    "wof:placetype":"locality"
},
  "geometry": {"coordinates":[48.77411,36.6259],"type":"Point"}
}