{
  "type": "Feature",
  "properties": {
    "gn:admin1_code":"41",
    "gn:asciiname":"Band Darreh",
    "gn:country_code":"IR",
    "gn:dem":1715,
    "gn:feature_class":"P",
    "gn:feature_code":"PPL",
    "gn:name":"Band Darreh",
    "gn:population":0,
    "gn:timezone":"Asia/Tehran",
    "iso:country":"IR",
    "name:und_x_variant":[
        "Band-i-Darreh",
        "Band Darreh"
    ],
    "wof:name":"Band Darreh",
    "wof:placetype":"locality"
},
  "geometry": {"coordinates":[59.21666999999999,32.81667],"type":"Point"}
}