{
  "type": "Feature",
  "properties": {
    "gn:admin1_code":"1.0",
    "gn:asciiname":"Qazantah",
    "gn:country_code":"IR",
    "gn:dem":1398,
    "gn:feature_class":"P",
    "gn:feature_code":"PPL",
    "gn:name":"Q\u0101z\u0101nt\u0101h",
    "gn:population":0,
    "gn:timezone":"Asia/Tehran",
    "iso:country":"IR",
    "name:fas_x_preferred":[
        "\u0642\u0627\u0632\u0627\u0646\u062a\u0627\u0647"
    ],
    "name:fas_x_variant":[
        "Q\u0101z\u0101nt\u0101h"
    ],
    "wof:name":"Qazantah",
    "wof:placetype":"locality"
},
  "geometry": {"coordinates":[45.9751,36.3465],"type":"Point"}
}