{
  "type": "Feature",
  "properties": {
    "gn:admin1_code":"26",
    "gn:asciiname":"Shushabad",
    "gn:country_code":"IR",
    "gn:dem":972,
    "gn:feature_class":"P",
    "gn:feature_code":"PPL",
    "gn:name":"Sh\u016bsh\u0101b\u0101d",
    "gn:population":0,
    "gn:timezone":"Asia/Tehran",
    "iso:country":"IR",
    "name:fas_x_preferred":[
        "\u0634\u0648\u0634 \u0622\u0628\u0627\u062f"
    ],
    "name:fas_x_variant":[
        "Sh\u016bsh\u0101b\u0101d",
        "\u0634\u0648\u0634\u200c\u0622\u0628\u0627\u062f"
    ],
    "wof:name":"Shushabad",
    "wof:placetype":"locality"
},
  "geometry": {"coordinates":[51.7343,35.3646],"type":"Point"}
}