{
  "type": "Feature",
  "properties": {
    "gn:admin1_code":"15",
    "gn:asciiname":"Sadat-e Ja`uleh",
    "gn:country_code":"IR",
    "gn:dem":30,
    "gn:feature_class":"P",
    "gn:feature_code":"PPL",
    "gn:name":"S\u0101d\u0101t-e Ja\u2018\u016bleh",
    "gn:population":0,
    "gn:timezone":"Asia/Tehran",
    "iso:country":"IR",
    "name:ara_x_preferred":[
        "\u0633\u064a\u062f \u0646\u0628\u064a"
    ],
    "name:azb_x_preferred":[
        "\u0633\u06cc\u062f\u0646\u0628\u06cc(\u0627\u0647\u0648\u0627\u0632)"
    ],
    "name:ceb_x_preferred":[
        "Seyyed Nab\u012b"
    ],
    "name:fas_x_preferred":[
        "\u0633\u06cc\u0651\u062f \u0646\u0628\u06cc"
    ],
    "name:fas_x_variant":[
        "Seyyed Nab\u012b",
        "\u0633\u0627\u062f\u0627\u062a \u062c\u0639\u0648\u0644\u0647",
        "\u0633\u06cc\u062f\u0646\u0628\u06cc"
    ],
    "name:swe_x_preferred":[
        "Seyyed Nab\u012b"
    ],
    "name:und_x_variant":[
        "S\u0101d\u0101t-e Ja\u2018\u016bleh"
    ],
    "wof:name":"Sadat-e Ja`uleh",
    "wof:placetype":"locality"
},
  "geometry": {"coordinates":[48.6741,31.7388],"type":"Point"}
}