{
  "type": "Feature",
  "properties": {
    "gn:admin1_code":"43.0",
    "gn:asciiname":"Hajji Gald Akhund",
    "gn:country_code":"IR",
    "gn:dem":769,
    "gn:feature_class":"P",
    "gn:feature_code":"PPL",
    "gn:name":"\u1e28\u0101jj\u012b Gald \u0100kh\u016bnd",
    "gn:population":0,
    "gn:timezone":"Asia/Tehran",
    "iso:country":"IR",
    "name:fas_x_preferred":[
        "\u1e28\u0101jj\u012b Gald \u0100kh\u016bnd"
    ],
    "name:fas_x_variant":[
        "\u062d\u0627\u062c\u06cc \u06af\u0644\u062f \u0622\u062e\u0648\u0646\u062f"
    ],
    "name:und_x_variant":[
        "\u062d\u0627\u062c\u06cc \u06af\u0644\u062f \u0622\u062e\u0648\u0646\u062f"
    ],
    "wof:name":"Hajji Gald Akhund",
    "wof:placetype":"locality"
},
  "geometry": {"coordinates":[56.70847,37.95507],"type":"Point"}
}