{
  "type": "Feature",
  "properties": {
    "gn:admin1_code":"8",
    "gn:asciiname":"Dargah",
    "gn:country_code":"IR",
    "gn:dem":-16,
    "gn:feature_class":"P",
    "gn:feature_code":"PPL",
    "gn:name":"Darg\u0101h",
    "gn:population":0,
    "gn:timezone":"Asia/Tehran",
    "iso:country":"IR",
    "name:fas_x_preferred":[
        "Darg\u0101h-e B\u0101l\u0101"
    ],
    "name:fas_x_variant":[
        "Darg\u0101h",
        "\u062f\u0631\u06af\u0627\u0647"
    ],
    "name:und_x_variant":[
        "Dehgah",
        "Darg\u0101h",
        "\u062f\u0631\u06af\u0627\u0647"
    ],
    "wof:name":"Dargah",
    "wof:placetype":"locality"
},
  "geometry": {"coordinates":[50.01743,37.30883],"type":"Point"}
}