{
  "type": "Feature",
  "properties": {
    "gn:admin1_code":"42",
    "gn:asciiname":"Mushak",
    "gn:country_code":"IR",
    "gn:dem":1934,
    "gn:feature_class":"P",
    "gn:feature_code":"PPL",
    "gn:name":"M\u016bshak",
    "gn:population":0,
    "gn:timezone":"Asia/Tehran",
    "iso:country":"IR",
    "name:fas_x_preferred":[
        "\u0645\u0648\u0634\u06a9"
    ],
    "name:fas_x_variant":[
        "M\u016bshak"
    ],
    "wof:name":"Mushak",
    "wof:placetype":"locality"
},
  "geometry": {"coordinates":[58.54235,35.50697],"type":"Point"}
}