{
  "type": "Feature",
  "properties": {
    "gn:admin1_code":"37.0",
    "gn:asciiname":"Qarah Gol-e Takht-e Vasat",
    "gn:country_code":"IR",
    "gn:dem":121,
    "gn:feature_class":"P",
    "gn:feature_code":"PPL",
    "gn:name":"Qarah Gol-e Takht-e Vasa\u0163",
    "gn:population":0,
    "gn:timezone":"Asia/Tehran",
    "iso:country":"IR",
    "name:ceb_x_preferred":[
        "Qarah Gol-e Takht-e Vasa\u0163"
    ],
    "name:fas_x_preferred":[
        "\u0642\u064e\u0631\u064e\u0647 \u06af\u064f\u0644\u0650 \u062a\u064e\u062e\u062a\u0650\u06c0 \u0648\u064e\u0633\u064e\u0637"
    ],
    "name:fas_x_variant":[
        "\u0642\u0631\u0647 \u06af\u0644 \u062a\u062e\u062a \u0648\u0633\u0637",
        "Qarah Gol-e Takhteh-ye Vasa\u0163",
        "Qarah Gol-e Takht-e Vasa\u0163",
        "\u0642\u0631\u0647\u200c\u06af\u0644 \u062a\u062e\u062a\u0647 \u0648\u0633\u0637"
    ],
    "name:msa_x_preferred":[
        "Qarah Gol-e Takhteh-ye Vasat"
    ],
    "name:swe_x_preferred":[
        "Qarah Gol-e Takht-e Vasa\u0163"
    ],
    "wof:name":"Qarah Gol-e Takht-e Vasat",
    "wof:placetype":"locality"
},
  "geometry": {"coordinates":[55.61454000000001,37.9248],"type":"Point"}
}