{
  "type": "Feature",
  "properties": {
    "gn:admin1_code":"35.0",
    "gn:asciiname":"Kafarat",
    "gn:country_code":"IR",
    "gn:dem":1229,
    "gn:feature_class":"P",
    "gn:feature_code":"PPL",
    "gn:name":"Kafar\u0101t",
    "gn:population":0,
    "gn:timezone":"Asia/Tehran",
    "iso:country":"IR",
    "name:ceb_x_preferred":[
        "Kafar\u0101t"
    ],
    "name:fas_x_preferred":[
        "\u0643\u064e\u0641\u0631\u0627\u062a"
    ],
    "name:fas_x_variant":[
        "Kafar\u0101t",
        "\u0643\u0641\u0631\u0627\u062a",
        "\u06a9\u0641\u0631\u0627\u062a"
    ],
    "name:swe_x_preferred":[
        "Kafar\u0101t"
    ],
    "name:und_x_variant":[
        "Kafr\u0101t",
        "\u0643\u0641\u0631\u0627\u062a"
    ],
    "wof:name":"Kafarat",
    "wof:placetype":"locality"
},
  "geometry": {"coordinates":[53.61247,36.41726],"type":"Point"}
}