{
  "type": "Feature",
  "properties": {
    "gn:admin1_code":"28",
    "gn:asciiname":"Kareh Dan",
    "gn:country_code":"IR",
    "gn:dem":2223,
    "gn:feature_class":"P",
    "gn:feature_code":"PPL",
    "gn:name":"Kareh D\u0101n",
    "gn:population":0,
    "gn:timezone":"Asia/Tehran",
    "iso:country":"IR",
    "name:fas_x_preferred":[
        "Kareh D\u0101n"
    ],
    "name:fas_x_variant":[
        "\u06a9\u0631\u0647 \u062f\u0627\u0646",
        "\u0643\u064e\u0647\u064e\u0631\u062f\u0627\u0646",
        "\u06a9\u0631\u0647\u200c\u062f\u0627\u0646"
    ],
    "name:und_x_variant":[
        "Kahred\u0101n",
        "\u06a9\u0631\u0647 \u062f\u0627\u0646",
        "Kahard\u0101n"
    ],
    "wof:name":"Kareh Dan",
    "wof:placetype":"locality"
},
  "geometry": {"coordinates":[51.73049,30.86782],"type":"Point"}
}