{
  "type": "Feature",
  "properties": {
    "gn:admin1_code":"35.0",
    "gn:asciiname":"Bazar Sarreh",
    "gn:country_code":"IR",
    "gn:dem":1245,
    "gn:feature_class":"P",
    "gn:feature_code":"PPL",
    "gn:name":"B\u0101z\u0101r Sarreh",
    "gn:population":0,
    "gn:timezone":"Asia/Tehran",
    "iso:country":"IR",
    "name:ara_x_preferred":[
        "\u0628\u0627\u0632\u0627\u0631\u0633\u0631"
    ],
    "name:ceb_x_preferred":[
        "B\u0101z\u0101r Sar"
    ],
    "name:fas_x_preferred":[
        "B\u0101z\u0101r Sar"
    ],
    "name:fas_x_variant":[
        "\u0628\u0627\u0632\u0627\u0631 \u0633\u0631",
        "\u0628\u0627\u0632\u0627\u0631 \u0633\u0631\u0647",
        "\u0628\u0627\u0632\u0627\u0631\u0633\u0631"
    ],
    "name:swe_x_preferred":[
        "B\u0101z\u0101r Sar"
    ],
    "name:und_x_variant":[
        "B\u0101z\u0101r Sarreh"
    ],
    "wof:name":"Bazar Sarreh",
    "wof:placetype":"locality"
},
  "geometry": {"coordinates":[51.18696,36.55891],"type":"Point"}
}