{
  "type": "Feature",
  "properties": {
    "gn:admin1_code":"4",
    "gn:asciiname":"Sherkat-e Ta`avoni",
    "gn:country_code":"IR",
    "gn:dem":1425,
    "gn:feature_class":"P",
    "gn:feature_code":"PPL",
    "gn:name":"Sherkat-e Ta\u2018\u0101von\u012b",
    "gn:population":0,
    "gn:timezone":"Asia/Tehran",
    "iso:country":"IR",
    "name:fas_x_preferred":[
        "\u0634\u0631\u06a9\u062a \u062a\u0639\u0627\u0648\u0646\u06cc"
    ],
    "name:fas_x_variant":[
        "Sherkat-e Ta\u2018\u0101von\u012b"
    ],
    "wof:name":"Sherkat-e Ta`avoni",
    "wof:placetype":"locality"
},
  "geometry": {"coordinates":[60.31473,28.96533],"type":"Point"}
}