{
  "type": "Feature",
  "properties": {
    "gn:admin1_code":"4.0",
    "gn:asciiname":"Deh-e Shagol",
    "gn:country_code":"IR",
    "gn:dem":484,
    "gn:feature_class":"P",
    "gn:feature_code":"PPL",
    "gn:name":"Deh-e Sh\u0101gol",
    "gn:population":0,
    "gn:timezone":"Asia/Tehran",
    "iso:country":"IR",
    "name:fas_x_preferred":[
        "Deh-e Sh\u0101gol"
    ],
    "name:fas_x_variant":[
        "\u062f\u0647 \u0634\u0627\u06af\u0644"
    ],
    "wof:name":"Deh-e Shagol",
    "wof:placetype":"locality"
},
  "geometry": {"coordinates":[61.79705,31.12662000000001],"type":"Point"}
}