{
  "type": "Feature",
  "properties": {
    "gn:admin1_code":"43",
    "gn:asciiname":"Do Ab",
    "gn:country_code":"IR",
    "gn:dem":1521,
    "gn:feature_class":"P",
    "gn:feature_code":"PPL",
    "gn:name":"Do \u0100b",
    "gn:population":0,
    "gn:timezone":"Asia/Tehran",
    "iso:country":"IR",
    "name:ceb_x_preferred":[
        "Do Ab"
    ],
    "name:fas_x_preferred":[
        "Do \u0100b"
    ],
    "name:fas_x_variant":[
        "\u062f\u0648 \u0622\u0628",
        "\u062f\u0648\u0622\u0628"
    ],
    "name:swe_x_preferred":[
        "Do Ab"
    ],
    "name:und_x_variant":[
        "Dow\u0101b",
        "D\u016b\u0101b"
    ],
    "wof:name":"Do Ab",
    "wof:placetype":"locality"
},
  "geometry": {"coordinates":[58.02363,37.63304],"type":"Point"}
}