{
  "type": "Feature",
  "properties": {
    "gn:admin1_code":"29",
    "gn:asciiname":"Tigh Siah",
    "gn:country_code":"IR",
    "gn:dem":1555,
    "gn:feature_class":"P",
    "gn:feature_code":"PPL",
    "gn:name":"T\u012bgh S\u012b\u0101h",
    "gn:population":0,
    "gn:timezone":"Asia/Tehran",
    "iso:country":"IR",
    "name:fas_x_preferred":[
        "T\u012bgh S\u012b\u0101h"
    ],
    "name:fas_x_variant":[
        "\u062a\u064a\u063a \u0633\u064a\u0627\u0647"
    ],
    "wof:name":"Tigh Siah",
    "wof:placetype":"locality"
},
  "geometry": {"coordinates":[58.28751,28.4187],"type":"Point"}
}