{
  "type": "Feature",
  "properties": {
    "gn:admin1_code":"16.0",
    "gn:asciiname":"Mazujedar-e Sheykh `Abdollah",
    "gn:country_code":"IR",
    "gn:dem":1733,
    "gn:feature_class":"P",
    "gn:feature_code":"PPL",
    "gn:name":"Maz\u016bjed\u0101r-e Sheykh \u2018Abdoll\u0101h",
    "gn:population":0,
    "gn:timezone":"Asia/Tehran",
    "iso:country":"IR",
    "name:fas_x_preferred":[
        "\u0645\u0627\u0632\u0648\u062c\u062f\u0627\u0631 \u0634\u06cc\u062e \u0639\u0628\u062f\u0627\u0644\u0644\u0647"
    ],
    "name:fas_x_variant":[
        "Maz\u016bjed\u0101r-e Sheykh \u2018Abdoll\u0101h"
    ],
    "wof:name":"Mazujedar-e Sheykh `Abdollah",
    "wof:placetype":"locality"
},
  "geometry": {"coordinates":[46.3455,36.0019],"type":"Point"}
}