{
  "type": "Feature",
  "properties": {
    "gn:admin1_code":"40",
    "gn:asciiname":"Deh-e Shams od Din",
    "gn:country_code":"IR",
    "gn:dem":2388,
    "gn:feature_class":"P",
    "gn:feature_code":"PPL",
    "gn:name":"Deh-e Shams od D\u012bn",
    "gn:population":0,
    "gn:timezone":"Asia/Tehran",
    "iso:country":"IR",
    "name:fas_x_preferred":[
        "\u062f\u0650\u0647\u0650 \u0634\u064e\u0645\u0633 \u0627\u0644\u062f\u0651\u064a\u0646"
    ],
    "name:fas_x_variant":[
        "\u062f\u0650\u0647\u0650 \u0634\u064e\u0645\u0633\u0650\u062f \u062f\u064a\u0646",
        "\u062f\u0650\u0647 \u0634\u064e\u0645\u0633 \u0627\u0650\u062f \u062f\u064a\u0646",
        "Deh-e Shams od D\u012bn",
        "\u062f\u0647 \u0634\u0645\u0633 \u0627\u0644\u062f\u06cc\u0646",
        "Deh-e Shamsed D\u012bn",
        "Deh Shams ed D\u012bn"
    ],
    "wof:name":"Deh-e Shams od Din",
    "wof:placetype":"locality"
},
  "geometry": {"coordinates":[55.89742,31.76146],"type":"Point"}
}