{
  "type": "Feature",
  "properties": {
    "gn:admin1_code":"4.0",
    "gn:asciiname":"Kalleh Rahi",
    "gn:country_code":"IR",
    "gn:dem":18,
    "gn:feature_class":"P",
    "gn:feature_code":"PPL",
    "gn:name":"Kalleh R\u0101h\u012b",
    "gn:population":0,
    "gn:timezone":"Asia/Tehran",
    "iso:country":"IR",
    "name:fas_x_preferred":[
        "Kalleh R\u0101h\u012b"
    ],
    "name:fas_x_variant":[
        "\u06a9\u0644\u0647 \u0631\u0627\u0647\u06cc"
    ],
    "name:und_x_variant":[
        "\u06a9\u0644\u0647 \u0631\u0627\u0647\u06cc"
    ],
    "wof:name":"Kalleh Rahi",
    "wof:placetype":"locality"
},
  "geometry": {"coordinates":[61.28992,25.48025],"type":"Point"}
}