{
  "type": "Feature",
  "properties": {
    "gn:admin1_code":"23",
    "gn:asciiname":"Rezaabad-e Mian Volan",
    "gn:country_code":"IR",
    "gn:dem":1565,
    "gn:feature_class":"P",
    "gn:feature_code":"PPL",
    "gn:name":"Re\u1e95\u0101\u0101b\u0101d-e M\u012b\u0101n Vol\u0101n",
    "gn:population":0,
    "gn:timezone":"Asia/Tehran",
    "iso:country":"IR",
    "name:fas_x_preferred":[
        "\u0686\u0650\u0642\u0627\u0644\u064e\u0643\u0627\u0646"
    ],
    "name:fas_x_variant":[
        "\u0686\u063a\u0627\u0644 \u06a9\u0627\u0646",
        "Ch\u012b\u0101lek\u0101n",
        "Chagh\u0101l K\u0101n",
        "\u0631\u0636\u0627 \u0622\u0628\u0627\u062f \u0645\u06cc\u0627\u0646 \u0648\u0644\u0627\u0646"
    ],
    "name:und_x_variant":[
        "Chey\u0101lak\u0101n",
        "Cheq\u0101lak\u0101n",
        "Re\u1e95\u0101\u0101b\u0101d-e M\u012b\u0101n Vol\u0101n"
    ],
    "wof:name":"Rezaabad-e Mian Volan",
    "wof:placetype":"locality"
},
  "geometry": {"coordinates":[48.2385,33.8305],"type":"Point"}
}