{
  "type": "Feature",
  "properties": {
    "gn:admin1_code":"9",
    "gn:asciiname":"Ansar ol Emam",
    "gn:country_code":"IR",
    "gn:dem":1737,
    "gn:feature_class":"P",
    "gn:feature_code":"PPL",
    "gn:name":"An\u015f\u0101r ol Em\u0101m",
    "gn:population":0,
    "gn:timezone":"Asia/Tehran",
    "iso:country":"IR",
    "name:fas_x_preferred":[
        "\u064a\u064e\u0646\u06af\u064a\u062c\u0650\u0647"
    ],
    "name:fas_x_variant":[
        "An\u015f\u0101r ol Em\u0101m",
        "\u0627\u0646\u0635\u0627\u0631\u0627\u0644\u0627\u0645\u0627\u0645"
    ],
    "name:msa_x_preferred":[
        "Ansar ol Emam"
    ],
    "name:und_x_variant":[
        "Yang\u012bjeh"
    ],
    "wof:name":"Ansar ol Emam",
    "wof:placetype":"locality"
},
  "geometry": {"coordinates":[48.4908,34.8587],"type":"Point"}
}