{
  "type": "Feature",
  "properties": {
    "gn:admin1_code":"40",
    "gn:asciiname":"Mazra`eh-ye Hashtkuh",
    "gn:country_code":"IR",
    "gn:dem":1738,
    "gn:feature_class":"P",
    "gn:feature_code":"PPL",
    "gn:name":"Mazra\u2018eh-ye Hashtk\u016bh",
    "gn:population":0,
    "gn:timezone":"Asia/Tehran",
    "iso:country":"IR",
    "name:fas_x_preferred":[
        "\u0645\u064e\u0632\u0631\u064e\u0639\u0650\u06c0 \u0647\u064e\u0634\u062a\u0643\u0648\u0647"
    ],
    "name:fas_x_variant":[
        "Mazra\u2018eh-ye Hashtk\u016bh"
    ],
    "wof:name":"Mazra`eh-ye Hashtkuh",
    "wof:placetype":"locality"
},
  "geometry": {"coordinates":[53.91472,31.87417],"type":"Point"}
}