{
  "type": "Feature",
  "properties": {
    "gn:admin1_code":"23",
    "gn:asciiname":"Kamar Khan",
    "gn:country_code":"IR",
    "gn:dem":1185,
    "gn:feature_class":"P",
    "gn:feature_code":"PPL",
    "gn:name":"Kamar Kh\u0101n",
    "gn:population":0,
    "gn:timezone":"Asia/Tehran",
    "iso:country":"IR",
    "name:fas_x_preferred":[
        "\u0643\u064e\u0645\u064e\u0631 \u062e\u0627\u0646"
    ],
    "name:fas_x_variant":[
        "Kamar Kh\u0101n"
    ],
    "wof:name":"Kamar Khan",
    "wof:placetype":"locality"
},
  "geometry": {"coordinates":[47.16143,33.66645],"type":"Point"}
}