{
  "type": "Feature",
  "properties": {
    "gn:admin1_code":"42",
    "gn:asciiname":"Jalambadan",
    "gn:country_code":"IR",
    "gn:dem":1560,
    "gn:feature_class":"P",
    "gn:feature_code":"PPL",
    "gn:name":"Jalamb\u0101d\u0101n",
    "gn:population":0,
    "gn:timezone":"Asia/Tehran",
    "iso:country":"IR",
    "name:fas_x_preferred":[
        "Jalamb\u0101d\u0101n"
    ],
    "name:fas_x_variant":[
        "\u062c\u0644\u0645\u0628\u0627\u062f\u0627\u0646"
    ],
    "name:und_x_variant":[
        "Jolomb\u0101r\u0101n",
        "\u062c\u0644\u0645\u0628\u0627\u062f\u0627\u0646"
    ],
    "wof:name":"Jalambadan",
    "wof:placetype":"locality"
},
  "geometry": {"coordinates":[57.44234,36.47283],"type":"Point"}
}