{
  "type": "Feature",
  "properties": {
    "gn:admin1_code":"4.0",
    "gn:asciiname":"Koshan`al",
    "gn:country_code":"IR",
    "gn:dem":974,
    "gn:feature_class":"P",
    "gn:feature_code":"PPL",
    "gn:name":"Koshan\u2018al",
    "gn:population":0,
    "gn:timezone":"Asia/Tehran",
    "iso:country":"IR",
    "name:fas_x_preferred":[
        "\u06a9\u0634\u0646\u0639\u0644"
    ],
    "name:und_x_variant":[
        "Koshan\u2018al"
    ],
    "wof:name":"Koshan`al",
    "wof:placetype":"locality"
},
  "geometry": {"coordinates":[59.27549000000001,27.96385],"type":"Point"}
}