{
  "type": "Feature",
  "properties": {
    "gn:admin1_code":"33",
    "gn:asciiname":"Bali Qeshlaq",
    "gn:country_code":"IR",
    "gn:dem":1009,
    "gn:elevation":"0.0",
    "gn:feature_class":"P",
    "gn:feature_code":"PPL",
    "gn:name":"B\u0101l\u012b Qeshl\u0101q",
    "gn:population":0,
    "gn:timezone":"Asia/Tehran",
    "iso:country":"IR",
    "name:fas_x_preferred":[
        "\u0628\u0627\u0644\u06cc \u0642\u0634\u0644\u0627\u0642"
    ],
    "name:fas_x_variant":[
        "\u0622\u062a\u0645\u0650\u064a\u0627\u0646",
        "\u0622\u062a \u0645\u06cc\u0627\u0646",
        "B\u0101l\u012b Qeshl\u0101q",
        "\u0100t Mey\u0101n"
    ],
    "name:und_x_variant":[
        "\u0100tmey\u0101n"
    ],
    "wof:name":"Bali Qeshlaq",
    "wof:placetype":"locality"
},
  "geometry": {"coordinates":[47.4593,38.4852],"type":"Point"}
}