{
  "type": "Feature",
  "properties": {
    "gn:admin1_code":"8",
    "gn:asciiname":"Aghuzbon Kandeh Sar",
    "gn:country_code":"IR",
    "gn:dem":839,
    "gn:feature_class":"P",
    "gn:feature_code":"PPL",
    "gn:name":"\u0100gh\u016bzbon Kandeh Sar",
    "gn:population":0,
    "gn:timezone":"Asia/Tehran",
    "iso:country":"IR",
    "name:fas_x_preferred":[
        "\u0100gh\u016bzbon Kandeh"
    ],
    "name:fas_x_variant":[
        "\u0100gh\u016bzbon Kandeh Sar",
        "\u0622\u063a\u0648\u0632\u0628\u0646 \u06a9\u0646\u062f\u0647 \u0633\u0631",
        "\u0622\u063a\u0648\u0632\u0628\u0646 \u06a9\u0646\u062f \u0633\u0631",
        "\u0627\u063a\u0648\u0632\u0628\u0646 \u06a9\u0646\u062f\u0633\u0631"
    ],
    "name:msa_x_preferred":[
        "Aghuzbon Kand Sar"
    ],
    "name:ukr_x_preferred":[
        "\u0410\u0491\u0443\u0437\u0431\u043e\u043d-\u041a\u0430\u043d\u0434-\u0421\u0430\u0440"
    ],
    "name:und_x_variant":[
        "\u0622\u063a\u0648\u0632\u0628\u0646 \u06a9\u0646\u062f\u0647 \u0633\u0631",
        "\u0100gh\u016bzbon Kand-e Sar"
    ],
    "wof:name":"Aghuzbon Kandeh Sar",
    "wof:placetype":"locality"
},
  "geometry": {"coordinates":[50.2078,36.87994000000001],"type":"Point"}
}