{
  "type": "Feature",
  "properties": {
    "gn:admin1_code":"22",
    "gn:asciiname":"Qal`eh Sarhan",
    "gn:country_code":"IR",
    "gn:dem":12,
    "gn:feature_class":"P",
    "gn:feature_code":"PPL",
    "gn:name":"Qal\u2018eh Sarh\u0101n",
    "gn:population":0,
    "gn:timezone":"Asia/Tehran",
    "iso:country":"IR",
    "name:fas_x_preferred":[
        "\u0642\u0644\u0639\u0647 \u0633\u0631\u0647\u0627\u0646"
    ],
    "name:fas_x_variant":[
        "\u0633\u064e\u0631\u062d\u0627\u0646",
        "Qal\u2018eh Sarh\u0101n"
    ],
    "name:und_x_variant":[
        "Sar\u1e29\u0101n"
    ],
    "wof:name":"Qal`eh Sarhan",
    "wof:placetype":"locality"
},
  "geometry": {"coordinates":[50.8467,29.2802],"type":"Point"}
}