{
  "type": "Feature",
  "properties": {
    "gn:admin1_code":"32",
    "gn:asciiname":"Asb-e Marz",
    "gn:country_code":"IR",
    "gn:dem":1909,
    "gn:feature_class":"P",
    "gn:feature_code":"PPL",
    "gn:name":"Asb-e Marz",
    "gn:population":0,
    "gn:timezone":"Asia/Tehran",
    "iso:country":"IR",
    "name:fas_x_preferred":[
        "\u0627\u0633\u0628 \u0645\u0631\u0632"
    ],
    "wof:name":"Asb-e Marz",
    "wof:placetype":"locality"
},
  "geometry": {"coordinates":[48.0138,38.1583],"type":"Point"}
}