{
  "type": "Feature",
  "properties": {
    "gn:admin1_code":"4.0",
    "gn:asciiname":"Keksuch",
    "gn:country_code":"IR",
    "gn:dem":88,
    "gn:feature_class":"P",
    "gn:feature_code":"PPL",
    "gn:name":"Keks\u016bch",
    "gn:population":0,
    "gn:timezone":"Asia/Tehran",
    "iso:country":"IR",
    "name:fas_x_preferred":[
        "Keks\u016bch"
    ],
    "wof:name":"Keksuch",
    "wof:placetype":"locality"
},
  "geometry": {"coordinates":[61.61666999999999,25.76667],"type":"Point"}
}