{
  "type": "Feature",
  "properties": {
    "gn:admin1_code":"41",
    "gn:asciiname":"Esfij",
    "gn:country_code":"IR",
    "gn:dem":1049,
    "gn:feature_class":"P",
    "gn:feature_code":"PPL",
    "gn:name":"Esf\u012bj",
    "gn:population":0,
    "gn:timezone":"Asia/Tehran",
    "iso:country":"IR",
    "name:fas_x_preferred":[
        "Esf\u012bj"
    ],
    "name:und_x_variant":[
        "Aspich",
        "Asf\u012bch"
    ],
    "wof:name":"Esfij",
    "wof:placetype":"locality"
},
  "geometry": {"coordinates":[59.63333000000001,31.03333],"type":"Point"}
}