{
  "type": "Feature",
  "properties": {
    "gn:admin1_code":"15",
    "gn:asciiname":"Sofeyreh",
    "gn:country_code":"IR",
    "gn:dem":23,
    "gn:feature_class":"P",
    "gn:feature_code":"PPL",
    "gn:name":"\u015eofeyreh",
    "gn:population":0,
    "gn:timezone":"Asia/Tehran",
    "iso:country":"IR",
    "name:ara_x_preferred":[
        "\u0635\u0641\u064a\u0631\u0629"
    ],
    "name:azb_x_preferred":[
        "\u0635\u0641\u06cc\u0631\u0647(\u0627\u0647\u0648\u0627\u0632)"
    ],
    "name:ceb_x_preferred":[
        "\u015eofeyreh"
    ],
    "name:fas_x_preferred":[
        "\u0635\u0641\u06cc\u0631\u0647"
    ],
    "name:fas_x_variant":[
        "\u015eofeyreh"
    ],
    "name:swe_x_preferred":[
        "\u015eofeyreh"
    ],
    "name:und_x_variant":[
        "Safareh",
        "Safera"
    ],
    "wof:name":"Sofeyreh",
    "wof:placetype":"locality"
},
  "geometry": {"coordinates":[48.86549,31.27183],"type":"Point"}
}