{
  "type": "Feature",
  "properties": {
    "gn:admin1_code":"32",
    "gn:asciiname":"Valzir",
    "gn:country_code":"IR",
    "gn:dem":1926,
    "gn:feature_class":"P",
    "gn:feature_code":"PPL",
    "gn:name":"Valz\u012br",
    "gn:population":0,
    "gn:timezone":"Asia/Tehran",
    "iso:country":"IR",
    "name:fas_x_preferred":[
        "\u0648\u0644\u0647\u0632\u064a\u0631"
    ],
    "name:fas_x_variant":[
        "Valehz\u012br",
        "\u0648\u0644\u0632\u064a\u0631",
        "\u0648\u0644\u06cc \u0622\u0628\u0627\u062f \u0648\u0644\u0647 \u0632\u064a\u0631",
        "\u0648\u0644\u06cc \u0622\u0628\u0627\u062f"
    ],
    "name:und_x_variant":[
        "Valz\u012br",
        "Val\u012b\u0101b\u0101d Valeh Z\u012br",
        "Val\u012b\u0101b\u0101d"
    ],
    "wof:name":"Valzir",
    "wof:placetype":"locality"
},
  "geometry": {"coordinates":[47.6771,38.312],"type":"Point"}
}