{
  "type": "Feature",
  "properties": {
    "gn:admin1_code":"5",
    "gn:asciiname":"Sartuf",
    "gn:country_code":"IR",
    "gn:dem":570,
    "gn:feature_class":"P",
    "gn:feature_code":"PPL",
    "gn:name":"Sart\u016bf",
    "gn:population":0,
    "gn:timezone":"Asia/Tehran",
    "iso:country":"IR",
    "name:fas_x_preferred":[
        "Sar\u0163\u016bf"
    ],
    "name:fas_x_variant":[
        "\u0633\u0631\u0637\u0648\u0641",
        "\u0633\u0631\u062a\u0648\u0641"
    ],
    "name:und_x_variant":[
        "\u0633\u0631\u0637\u0648\u0641",
        "Sart\u016bf"
    ],
    "wof:name":"Sartuf",
    "wof:placetype":"locality"
},
  "geometry": {"coordinates":[50.01038,31.02094],"type":"Point"}
}