{
  "type": "Feature",
  "properties": {
    "gn:admin1_code":"33",
    "gn:asciiname":"Shur Del",
    "gn:country_code":"IR",
    "gn:dem":1694,
    "gn:feature_class":"P",
    "gn:feature_code":"PPL",
    "gn:name":"Sh\u016br Del",
    "gn:population":0,
    "gn:timezone":"Asia/Tehran",
    "iso:country":"IR",
    "name:ceb_x_preferred":[
        "Sh\u016br Del"
    ],
    "name:fas_x_preferred":[
        "\u0634\u0648\u0631 \u062f\u0644"
    ],
    "name:fas_x_variant":[
        "Sh\u016breh Del",
        "Sh\u016br Del",
        "\u0634\u0648\u0631\u0647\u200c\u062f\u0644"
    ],
    "name:msa_x_preferred":[
        "Shureh Del"
    ],
    "name:swe_x_preferred":[
        "Sh\u016br Del"
    ],
    "wof:name":"Shur Del",
    "wof:placetype":"locality"
},
  "geometry": {"coordinates":[47.6756,37.9167],"type":"Point"}
}