{
  "type": "Feature",
  "properties": {
    "gn:admin1_code":"43",
    "gn:asciiname":"Kalateh-ye Molla Veys",
    "gn:country_code":"IR",
    "gn:dem":1384,
    "gn:feature_class":"P",
    "gn:feature_code":"PPL",
    "gn:name":"Kal\u0101teh-ye Moll\u0101 Veys",
    "gn:population":0,
    "gn:timezone":"Asia/Tehran",
    "iso:country":"IR",
    "name:ceb_x_preferred":[
        "Kal\u0101teh-ye Moll\u0101 Veys"
    ],
    "name:fas_x_preferred":[
        "Kal\u0101teh-ye Moll\u0101v\u012bsh"
    ],
    "name:fas_x_variant":[
        "Kal\u0101teh-ye Moll\u0101 Veys",
        "\u06a9\u0644\u0627\u062a\u0647 \u0645\u0644\u0627 \u0648\u06cc\u0633",
        "\u0645\u0644\u0627 \u0648\u06cc\u0633",
        "\u0645\u0644\u0627\u0648\u06cc\u0633"
    ],
    "name:swe_x_preferred":[
        "Kal\u0101teh-ye Moll\u0101 Veys"
    ],
    "name:und_x_variant":[
        "Moll\u0101 Veys",
        "Kal\u0101teh-ye Moll\u0101 Veys",
        "\u06a9\u0644\u0627\u062a\u0647 \u0645\u0644\u0627 \u0648\u06cc\u0633"
    ],
    "wof:name":"Kalateh-ye Molla Veys",
    "wof:placetype":"locality"
},
  "geometry": {"coordinates":[56.85748,37.24741],"type":"Point"}
}