{
  "type": "Feature",
  "properties": {
    "gn:admin1_code":"33.0",
    "gn:asciiname":"Koman",
    "gn:country_code":"IR",
    "gn:dem":965,
    "gn:feature_class":"P",
    "gn:feature_code":"PPL",
    "gn:name":"Kom\u0101n",
    "gn:population":0,
    "gn:timezone":"Asia/Tehran",
    "iso:country":"IR",
    "name:fas_x_preferred":[
        "\u06af\u064f\u0645\u0627\u0646"
    ],
    "name:fas_x_variant":[
        "\u06a9\u0645\u0627\u0646",
        "Gom\u0101n",
        "Kom\u0101n"
    ],
    "wof:name":"Koman",
    "wof:placetype":"locality"
},
  "geometry": {"coordinates":[47.1463,39.0852],"type":"Point"}
}