{
  "type": "Feature",
  "properties": {
    "gn:admin1_code":"23",
    "gn:asciiname":"Gori Balmak",
    "gn:country_code":"IR",
    "gn:dem":755,
    "gn:feature_class":"P",
    "gn:feature_code":"PPL",
    "gn:name":"Gor\u012b Balmak",
    "gn:population":0,
    "gn:timezone":"Asia/Tehran",
    "iso:country":"IR",
    "name:fas_x_preferred":[
        "\u06af\u0631\u06cc \u0628\u0644\u0645\u06a9"
    ],
    "name:fas_x_variant":[
        "Gor\u012b Balmak"
    ],
    "wof:name":"Gori Balmak",
    "wof:placetype":"locality"
},
  "geometry": {"coordinates":[47.7323,33.075],"type":"Point"}
}