{
  "type": "Feature",
  "properties": {
    "gn:admin1_code":"22.0",
    "gn:asciiname":"Kaftaru",
    "gn:country_code":"IR",
    "gn:dem":958,
    "gn:feature_class":"P",
    "gn:feature_code":"PPL",
    "gn:name":"Kaft\u0101r\u016b",
    "gn:population":0,
    "gn:timezone":"Asia/Tehran",
    "iso:country":"IR",
    "name:ara_x_preferred":[
        "\u0643\u0641\u062a\u0631\u0648"
    ],
    "name:ceb_x_preferred":[
        "Kaft\u0101r\u016b"
    ],
    "name:fas_x_preferred":[
        "\u06a9\u0641\u062a\u0627\u0631\u0648"
    ],
    "name:fas_x_variant":[
        "\u06a9\u0641\u062a\u0631\u0648"
    ],
    "name:msa_x_preferred":[
        "Kaftaru"
    ],
    "name:swe_x_preferred":[
        "Kaft\u0101r\u016b"
    ],
    "name:und_x_variant":[
        "Kaft\u0101r\u016b"
    ],
    "wof:name":"Kaftaru",
    "wof:placetype":"locality"
},
  "geometry": {"coordinates":[51.67384000000001,29.1243],"type":"Point"}
}