{
  "type": "Feature",
  "properties": {
    "gn:admin1_code":"42",
    "gn:asciiname":"Kalateh-ye `Abdol",
    "gn:country_code":"IR",
    "gn:dem":1198,
    "gn:feature_class":"P",
    "gn:feature_code":"PPL",
    "gn:name":"Kal\u0101teh-ye \u2018Abdol",
    "gn:population":0,
    "gn:timezone":"Asia/Tehran",
    "iso:country":"IR",
    "name:fas_x_preferred":[
        "\u06a9\u0644\u0627\u062a\u0647 \u0639\u0628\u062f\u0644"
    ],
    "name:fas_x_variant":[
        "Kal\u0101teh-ye \u2018Abdol"
    ],
    "wof:name":"Kalateh-ye `Abdol",
    "wof:placetype":"locality"
},
  "geometry": {"coordinates":[59.3944,36.3489],"type":"Point"}
}