{
  "type": "Feature",
  "properties": {
    "gn:admin1_code":"7.0",
    "gn:asciiname":"Bagh Dasht",
    "gn:country_code":"IR",
    "gn:dem":775,
    "gn:feature_class":"P",
    "gn:feature_code":"PPL",
    "gn:name":"B\u0101gh Dasht",
    "gn:population":0,
    "gn:timezone":"Asia/Tehran",
    "iso:country":"IR",
    "name:fas_x_preferred":[
        "B\u0101gh Dasht"
    ],
    "name:fas_x_variant":[
        "\u0628\u0627\u063a \u062f\u0634\u062a"
    ],
    "name:msa_x_preferred":[
        "Bagh Dasht"
    ],
    "name:und_x_variant":[
        "B\u0101gh-i-Dash",
        "B\u0101gh D\u0101sh",
        "Bagh-e Dasht"
    ],
    "wof:name":"Bagh Dasht",
    "wof:placetype":"locality"
},
  "geometry": {"coordinates":[51.97396,29.22119],"type":"Point"}
}