{
  "type": "Feature",
  "properties": {
    "gn:admin1_code":"35.0",
    "gn:asciiname":"Pasha Kola",
    "gn:country_code":"IR",
    "gn:dem":10,
    "gn:feature_class":"P",
    "gn:feature_code":"PPL",
    "gn:name":"P\u0101sh\u0101 Kol\u0101",
    "gn:population":0,
    "gn:timezone":"Asia/Tehran",
    "iso:country":"IR",
    "name:fas_x_preferred":[
        "\u067e\u0627\u0634\u0627 \u0643\u0644\u0627"
    ],
    "name:fas_x_variant":[
        "P\u0101sh\u0101 Kol\u0101"
    ],
    "wof:name":"Pasha Kola",
    "wof:placetype":"locality"
},
  "geometry": {"coordinates":[52.35388,36.55056],"type":"Point"}
}