{
  "type": "Feature",
  "properties": {
    "gn:admin1_code":"25",
    "gn:asciiname":"Diz Chah",
    "gn:cc2":"IR",
    "gn:country_code":"IR",
    "gn:dem":1369,
    "gn:feature_class":"P",
    "gn:feature_code":"PPL",
    "gn:name":"D\u012bz Ch\u0101h",
    "gn:population":0,
    "gn:timezone":"Asia/Tehran",
    "iso:country":"IR",
    "name:fas_x_preferred":[
        "\u062f\u064a\u0632 \u0686\u0627\u0647"
    ],
    "name:fas_x_variant":[
        "\u062f\u064f\u0648 \u0686\u0627\u0647",
        "\u062f\u0650\u0632 \u0686\u0627\u0647",
        "D\u012bz Ch\u0101h"
    ],
    "name:und_x_variant":[
        "Do Ch\u0101h",
        "Dez Ch\u0101h"
    ],
    "wof:name":"Diz Chah",
    "wof:placetype":"locality"
},
  "geometry": {"coordinates":[55.78972,35.82528],"type":"Point"}
}