{
  "type": "Feature",
  "properties": {
    "gn:admin1_code":"33",
    "gn:asciiname":"Qater Gutran-e Sofla",
    "gn:country_code":"IR",
    "gn:dem":1732,
    "gn:feature_class":"P",
    "gn:feature_code":"PPL",
    "gn:name":"Q\u0101\u0163er G\u016btran-e Sofl\u00e1",
    "gn:population":0,
    "gn:timezone":"Asia/Tehran",
    "iso:country":"IR",
    "name:fas_x_preferred":[
        "\u0642\u0627\u0637\u0631 \u06af\u0648\u062a\u0631\u0646 \u0633\u0641\u0644\u06cc"
    ],
    "name:fas_x_variant":[
        "Q\u0101\u0163er G\u016btran-e Sofl\u00e1",
        "\u0642\u0627\u0637\u0631 \u06af\u0648\u062a\u0648\u0631\u0646 \u0633\u0641\u0644\u06cc"
    ],
    "name:und_x_variant":[
        "Q\u0101\u0163er G\u016bt\u016bran-e Sofl\u00e1"
    ],
    "wof:name":"Qater Gutran-e Sofla",
    "wof:placetype":"locality"
},
  "geometry": {"coordinates":[46.5079,37.337],"type":"Point"}
}