{
  "type": "Feature",
  "properties": {
    "gn:admin1_code":"36",
    "gn:asciiname":"Bijeqin",
    "gn:country_code":"IR",
    "gn:dem":1811,
    "gn:feature_class":"P",
    "gn:feature_code":"PPL",
    "gn:name":"B\u012bjeq\u012bn",
    "gn:population":0,
    "gn:timezone":"Asia/Tehran",
    "iso:country":"IR",
    "name:azb_x_preferred":[
        "\u0628\u06cc\u062c\u0642\u06cc\u0646"
    ],
    "name:fas_x_preferred":[
        "\u0628\u06cc\u062c\u0642\u06cc\u0646"
    ],
    "name:fas_x_variant":[
        "B\u012bjeq\u012bn"
    ],
    "name:und_x_variant":[
        "Bayjaq\u012bn",
        "Bidzhin",
        "B\u012bjg\u012bn",
        "Bijaq\u012bn"
    ],
    "wof:name":"Bijeqin",
    "wof:placetype":"locality"
},
  "geometry": {"coordinates":[48.70377,36.113],"type":"Point"}
}