{
  "type": "Feature",
  "properties": {
    "gn:admin1_code":"4.0",
    "gn:asciiname":"Deh-e Esma`il",
    "gn:country_code":"IR",
    "gn:dem":480,
    "gn:feature_class":"P",
    "gn:feature_code":"PPL",
    "gn:name":"Deh-e Esm\u0101\u2018\u012bl",
    "gn:population":0,
    "gn:timezone":"Asia/Tehran",
    "iso:country":"IR",
    "name:fas_x_preferred":[
        "\u062f\u0647 \u0627\u0633\u0645\u0627\u0639\u06cc\u0644"
    ],
    "name:fas_x_variant":[
        "Deh-e Esm\u0101\u2018\u012bl",
        "\u0627\u0633\u0645\u0627\u0639\u06cc\u0644 \u0639\u0644\u06cc"
    ],
    "name:und_x_variant":[
        "Esm\u0101\u2018\u012bl \u2018Al\u012b"
    ],
    "wof:name":"Deh-e Esma`il",
    "wof:placetype":"locality"
},
  "geometry": {"coordinates":[61.5965,31.1642],"type":"Point"}
}