{
  "type": "Feature",
  "properties": {
    "gn:admin1_code":"8",
    "gn:asciiname":"Nowsher",
    "gn:country_code":"IR",
    "gn:dem":-12,
    "gn:feature_class":"P",
    "gn:feature_code":"PPL",
    "gn:name":"Nowsher",
    "gn:population":0,
    "gn:timezone":"Asia/Tehran",
    "iso:country":"IR",
    "name:fas_x_preferred":[
        "\u0646\u0648\u0634\u0647\u0631"
    ],
    "name:fas_x_variant":[
        "\u0646\u0648\u0634\u0631"
    ],
    "name:msa_x_preferred":[
        "Nowsher"
    ],
    "name:ukr_x_preferred":[
        "\u041d\u043e\u0432\u0448\u0435\u0440"
    ],
    "name:und_x_variant":[
        "Nowshahr",
        "\u0646\u0648\u0634\u0647\u0631",
        "Nowsher"
    ],
    "wof:name":"Nowsher",
    "wof:placetype":"locality"
},
  "geometry": {"coordinates":[49.77898,37.36622],"type":"Point"}
}