{
  "type": "Feature",
  "properties": {
    "gn:admin1_code":"7",
    "gn:asciiname":"Hasanabad",
    "gn:country_code":"IR",
    "gn:dem":2038,
    "gn:feature_class":"P",
    "gn:feature_code":"PPLF",
    "gn:name":"\u1e28asan\u0101b\u0101d",
    "gn:population":0,
    "gn:timezone":"Asia/Tehran",
    "iso:country":"IR",
    "name:aze_x_preferred":[
        "H\u0259s\u0259nabad"
    ],
    "name:ceb_x_preferred":[
        "Hasanabad"
    ],
    "name:fas_x_preferred":[
        "\u062d\u0633\u0646 \u0622\u0628\u0627\u062f"
    ],
    "name:fas_x_variant":[
        "\u1e28asan\u0101b\u0101d",
        "\u062d\u0633\u0646\u200c\u0622\u0628\u0627\u062f"
    ],
    "name:ita_x_preferred":[
        "Hasanabad"
    ],
    "name:swe_x_preferred":[
        "Hasanabad"
    ],
    "name:und_x_variant":[
        "\u1e28asan\u0101b\u0101d-e Gh\u016br\u012b"
    ],
    "wof:name":"Hasanabad",
    "wof:placetype":"locality"
},
  "geometry": {"coordinates":[54.47283,29.27664],"type":"Point"}
}