{
  "type": "Feature",
  "properties": {
    "gn:admin1_code":"13.0",
    "gn:asciiname":"Bandareh",
    "gn:cc2":"IR",
    "gn:country_code":"IR",
    "gn:dem":1746,
    "gn:feature_class":"P",
    "gn:feature_code":"PPL",
    "gn:name":"Bandareh",
    "gn:population":0,
    "gn:timezone":"Asia/Tehran",
    "iso:country":"IR",
    "name:ceb_x_preferred":[
        "Bandareh"
    ],
    "name:ckb_x_preferred":[
        "\u0628\u0646\u062f\u06d5\u0631\u06d5"
    ],
    "name:fas_x_preferred":[
        "\u0628\u0646\u062f\u0631\u0647"
    ],
    "name:swe_x_preferred":[
        "Bandareh"
    ],
    "name:und_x_variant":[
        "Beyn Darreh",
        "Bandareh"
    ],
    "wof:name":"Bandareh",
    "wof:placetype":"locality"
},
  "geometry": {"coordinates":[46.35,35.01667],"type":"Point"}
}