{
  "type": "Feature",
  "properties": {
    "gn:admin1_code":"5.0",
    "gn:asciiname":"Cheshmeh Rizak",
    "gn:country_code":"IR",
    "gn:dem":2379,
    "gn:feature_class":"P",
    "gn:feature_code":"PPL",
    "gn:name":"Cheshmeh R\u012bzak",
    "gn:population":0,
    "gn:timezone":"Asia/Tehran",
    "iso:country":"IR",
    "name:fas_x_preferred":[
        "\u0686\u0634\u0645\u0647 \u0631\u06cc\u0632\u0643"
    ],
    "name:und_x_variant":[
        "Cheshmeh R\u012bzak"
    ],
    "wof:name":"Cheshmeh Rizak",
    "wof:placetype":"locality"
},
  "geometry": {"coordinates":[50.99743,31.14267000000001],"type":"Point"}
}