{
  "type": "Feature",
  "properties": {
    "gn:admin1_code":"15",
    "gn:asciiname":"Khur-e Dowraq",
    "gn:cc2":"IR",
    "gn:country_code":"IR",
    "gn:dem":6,
    "gn:feature_class":"P",
    "gn:feature_code":"PPL",
    "gn:name":"Kh\u016br-e Dowraq",
    "gn:population":0,
    "gn:timezone":"Asia/Tehran",
    "iso:country":"IR",
    "name:fas_x_preferred":[
        "Kh\u016br-e Dowraq"
    ],
    "name:und_x_variant":[
        "Khowr-e D\u016braq",
        "Kh\u016brd\u016braq"
    ],
    "wof:name":"Khur-e Dowraq",
    "wof:placetype":"locality"
},
  "geometry": {"coordinates":[48.73722,30.56139000000001],"type":"Point"}
}