{
  "type": "Feature",
  "properties": {
    "gn:admin1_code":"7",
    "gn:asciiname":"Pir Mohlat",
    "gn:country_code":"IR",
    "gn:dem":836,
    "gn:feature_class":"P",
    "gn:feature_code":"PPL",
    "gn:name":"P\u012br Mohlat",
    "gn:population":0,
    "gn:timezone":"Asia/Tehran",
    "iso:country":"IR",
    "name:fas_x_preferred":[
        "P\u012br Mohlat"
    ],
    "name:fas_x_variant":[
        "P\u012br Mo\u1e29\u012b",
        "\u067e\u06cc\u0631 \u0645\u0647\u0644\u062a"
    ],
    "wof:name":"Pir Mohlat",
    "wof:placetype":"locality"
},
  "geometry": {"coordinates":[51.53622,29.50186],"type":"Point"}
}