{
  "type": "Feature",
  "properties": {
    "gn:admin1_code":"9",
    "gn:asciiname":"Jowzan",
    "gn:country_code":"IR",
    "gn:dem":1889,
    "gn:feature_class":"P",
    "gn:feature_code":"PPL",
    "gn:name":"Jowz\u0101n",
    "gn:population":0,
    "gn:timezone":"Asia/Tehran",
    "iso:country":"IR",
    "name:fas_x_preferred":[
        "Jowz\u0101n"
    ],
    "name:fas_x_variant":[
        "\u062c\u0648\u0632\u0627\u0646"
    ],
    "name:msa_x_preferred":[
        "Jowzan"
    ],
    "name:und_x_variant":[
        "Za\u016bzan",
        "Ja\u016bz\u0101n",
        "\u062c\u0648\u0632\u0627\u0646"
    ],
    "wof:name":"Jowzan",
    "wof:placetype":"locality"
},
  "geometry": {"coordinates":[48.9632,34.25422],"type":"Point"}
}