{
  "type": "Feature",
  "properties": {
    "gn:admin1_code":"40",
    "gn:asciiname":"Harisk-e `Olya",
    "gn:country_code":"IR",
    "gn:dem":2216,
    "gn:feature_class":"P",
    "gn:feature_code":"PPL",
    "gn:name":"Har\u012bsk-e \u2018Oly\u0101",
    "gn:population":0,
    "gn:timezone":"Asia/Tehran",
    "iso:country":"IR",
    "name:fas_x_preferred":[
        "\u0647\u064e\u0631\u064a\u0633\u0643\u0650 \u0628\u0627\u0644\u0627"
    ],
    "name:fas_x_variant":[
        "Har\u012bsk-e \u2018Oly\u0101",
        "Har\u012bsk-e B\u0101l\u0101",
        "\u0647\u0631\u06cc\u0633\u06a9 \u0639\u0644\u06cc\u0627"
    ],
    "wof:name":"Harisk-e `Olya",
    "wof:placetype":"locality"
},
  "geometry": {"coordinates":[55.90062,31.70501],"type":"Point"}
}