{
  "type": "Feature",
  "properties": {
    "gn:admin1_code":"16.0",
    "gn:asciiname":"Asiab Jub",
    "gn:country_code":"IR",
    "gn:dem":1756,
    "gn:feature_class":"P",
    "gn:feature_code":"PPL",
    "gn:name":"\u0100s\u012b\u0101b J\u016bb",
    "gn:population":0,
    "gn:timezone":"Asia/Tehran",
    "iso:country":"IR",
    "name:fas_x_preferred":[
        "\u0622\u0633\u06cc\u0627\u0628 \u062c\u0648\u0628"
    ],
    "name:fas_x_variant":[
        "\u0100s\u012b\u0101b J\u016bb"
    ],
    "name:und_x_variant":[
        "Esh\u0101bj\u016b",
        "\u0100seyab J\u016b",
        "Ashi\u0101bju"
    ],
    "wof:name":"Asiab Jub",
    "wof:placetype":"locality"
},
  "geometry": {"coordinates":[47.51102,35.31779],"type":"Point"}
}