{
  "type": "Feature",
  "properties": {
    "gn:admin1_code":"13",
    "gn:asciiname":"Derkeh",
    "gn:cc2":"IR",
    "gn:country_code":"IR",
    "gn:dem":1305,
    "gn:feature_class":"P",
    "gn:feature_code":"PPL",
    "gn:name":"Derkeh",
    "gn:population":0,
    "gn:timezone":"Asia/Tehran",
    "iso:country":"IR",
    "name:und_x_variant":[
        "Perkeh",
        "Derkah",
        "Darakeh",
        "Darka"
    ],
    "wof:name":"Derkeh",
    "wof:placetype":"locality"
},
  "geometry": {"coordinates":[47.66889000000001,34.44806],"type":"Point"}
}