{
  "type": "Feature",
  "properties": {
    "gn:admin1_code":"5",
    "gn:asciiname":"Mazra`eh-ye Ab Bid",
    "gn:country_code":"IR",
    "gn:dem":467,
    "gn:feature_class":"P",
    "gn:feature_code":"PPLL",
    "gn:name":"Mazra\u2018eh-ye \u0100b B\u012bd",
    "gn:population":0,
    "gn:timezone":"Asia/Tehran",
    "iso:country":"IR",
    "name:fas_x_preferred":[
        "\u0646\u0635\u0631\u062a \u0622\u0628\u0627\u062f"
    ],
    "name:fas_x_variant":[
        "No\u015frat\u0101b\u0101d",
        "\u0645\u0632\u0631\u0639\u0647 \u0622\u0628 \u0628\u06cc\u062f"
    ],
    "name:und_x_variant":[
        "Mazra\u2018eh-ye \u0100b B\u012bd"
    ],
    "wof:name":"Mazra`eh-ye Ab Bid",
    "wof:placetype":"locality"
},
  "geometry": {"coordinates":[50.4842,30.4723],"type":"Point"}
}