{
  "type": "Feature",
  "properties": {
    "gn:admin1_code":"4",
    "gn:asciiname":"Chah-e Sizdah-e Aban",
    "gn:country_code":"IR",
    "gn:dem":1189,
    "gn:feature_class":"P",
    "gn:feature_code":"PPL",
    "gn:name":"Ch\u0101h-e S\u012bzdah-e \u0100b\u0101n",
    "gn:population":0,
    "gn:timezone":"Asia/Tehran",
    "iso:country":"IR",
    "name:fas_x_preferred":[
        "\u0686\u0627\u0647 \u0646\u06cc\u0627\u0632 \u0645\u062d\u0645\u0651\u062f"
    ],
    "name:fas_x_variant":[
        "Ch\u0101h-e N\u012b\u0101z Mo\u1e29ammad",
        "\u0686\u0627\u0647 \u0633\u06cc\u0632\u062f\u0647 \u0622\u0628\u0627\u0646",
        "\u0633\u06cc\u0632\u062f\u0647 \u0622\u0628\u0627\u0646"
    ],
    "name:und_x_variant":[
        "Ch\u0101h-e S\u012bzdah-e \u0100b\u0101n",
        "S\u012bzdah \u0100b\u0101n"
    ],
    "wof:name":"Chah-e Sizdah-e Aban",
    "wof:placetype":"locality"
},
  "geometry": {"coordinates":[61.85507,27.42306],"type":"Point"}
}