{
  "type": "Feature",
  "properties": {
    "gn:admin1_code":"0",
    "gn:asciiname":"Suran",
    "gn:country_code":"IR",
    "gn:dem":907,
    "gn:feature_class":"P",
    "gn:feature_code":"PPL",
    "gn:name":"S\u016br\u0101n",
    "gn:population":0,
    "gn:timezone":"Asia/Tehran",
    "iso:country":"IR",
    "name:ceb_x_preferred":[
        "Suran"
    ],
    "name:fas_x_preferred":[
        "\u0633\u0648\u0631\u0627\u0646"
    ],
    "name:fas_x_variant":[
        "S\u016br\u0101n"
    ],
    "name:fra_x_preferred":[
        "Suran"
    ],
    "name:kor_x_preferred":[
        "\uc218\ub780"
    ],
    "name:swe_x_preferred":[
        "Suran"
    ],
    "wof:name":"Suran",
    "wof:placetype":"locality"
},
  "geometry": {"coordinates":[48.25,38.96667],"type":"Point"}
}