{
  "type": "Feature",
  "properties": {
    "gn:admin1_code":"43",
    "gn:asciiname":"Kalateh-ye Mirza",
    "gn:country_code":"IR",
    "gn:dem":1317,
    "gn:feature_class":"P",
    "gn:feature_code":"PPL",
    "gn:name":"Kal\u0101teh-ye M\u012brz\u0101",
    "gn:population":0,
    "gn:timezone":"Asia/Tehran",
    "iso:country":"IR",
    "name:fas_x_preferred":[
        "Kal\u0101teh-ye M\u012brza \u2018Al\u012b Khoncheh"
    ],
    "name:fas_x_variant":[
        "Kal\u0101teh-ye M\u012brz\u0101 \u2018Al\u012b Khoncheh",
        "Kal\u0101teh-ye M\u012brz\u0101",
        "\u06a9\u0644\u0627\u062a\u0647 \u0645\u06cc\u0631\u0632\u0627 \u0639\u0644\u06cc \u062e\u0646\u0686\u0647",
        "\u06a9\u0644\u0627\u062a\u0647 \u0645\u06cc\u0631\u0632\u0627",
        "\u06a9\u0644\u0627\u062a\u0647 \u0639\u0644\u06cc \u062e\u0646\u0686\u0647"
    ],
    "name:und_x_variant":[
        "Kal\u0101teh-ye \u2018Al\u012b Khoncheh"
    ],
    "wof:name":"Kalateh-ye Mirza",
    "wof:placetype":"locality"
},
  "geometry": {"coordinates":[57.04611,38.05746],"type":"Point"}
}