{
  "type": "Feature",
  "properties": {
    "gn:admin1_code":"11",
    "gn:asciiname":"Sar-e Tall",
    "gn:cc2":"IR",
    "gn:country_code":"IR",
    "gn:dem":425,
    "gn:feature_class":"P",
    "gn:feature_code":"PPL",
    "gn:name":"Sar-e Tall",
    "gn:population":0,
    "gn:timezone":"Asia/Tehran",
    "iso:country":"IR",
    "name:fas_x_preferred":[
        "\u0633\u064e\u0631\u0650 \u062a\u064e\u0644\u0651"
    ],
    "name:fas_x_variant":[
        "\u0633\u064e\u0631\u0650 \u062a\u064f\u0644",
        "\u0633\u064e\u0631\u0650 \u062a\u064e\u0644",
        "\u0633\u064e\u0631 \u062a\u064e\u0644"
    ],
    "name:und_x_variant":[
        "Sar-e Tol",
        "Sar Tal",
        "Sar-e Tal",
        "Sar-e Tall"
    ],
    "wof:name":"Sar-e Tall",
    "wof:placetype":"locality"
},
  "geometry": {"coordinates":[55.07222,27.36639000000001],"type":"Point"}
}