{
  "type": "Feature",
  "properties": {
    "gn:admin1_code":"32.0",
    "gn:asciiname":"Dash Kasan",
    "gn:country_code":"IR",
    "gn:dem":1355,
    "gn:feature_class":"P",
    "gn:feature_code":"PPL",
    "gn:name":"D\u0101sh Kasan",
    "gn:population":0,
    "gn:timezone":"Asia/Tehran",
    "iso:country":"IR",
    "name:fas_x_preferred":[
        "\u062f\u0627\u0634 \u06a9\u0633\u0646"
    ],
    "name:fas_x_variant":[
        "D\u0101sh Kasan"
    ],
    "wof:name":"Dash Kasan",
    "wof:placetype":"locality"
},
  "geometry": {"coordinates":[48.2929,38.23],"type":"Point"}
}