{
  "type": "Feature",
  "properties": {
    "gn:admin1_code":"7",
    "gn:asciiname":"Seh Chah",
    "gn:country_code":"IR",
    "gn:dem":1183,
    "gn:feature_class":"P",
    "gn:feature_code":"PPL",
    "gn:name":"Seh Ch\u0101h",
    "gn:population":0,
    "gn:timezone":"Asia/Tehran",
    "iso:country":"IR",
    "name:fas_x_preferred":[
        "\u0633\u0647 \u0686\u0627\u0647"
    ],
    "name:fas_x_variant":[
        "Seh Ch\u0101h-e Baghal S\u012b\u0101h",
        "Seh Ch\u0101h",
        "\u0633\u0647\u200c\u0686\u0627\u0647"
    ],
    "name:msa_x_preferred":[
        "Seh Chah"
    ],
    "wof:name":"Seh Chah",
    "wof:placetype":"locality"
},
  "geometry": {"coordinates":[53.3394,28.7848],"type":"Point"}
}