{
  "type": "Feature",
  "properties": {
    "gn:admin1_code":"29",
    "gn:asciiname":"Kerkak",
    "gn:country_code":"IR",
    "gn:dem":609,
    "gn:feature_class":"P",
    "gn:feature_code":"PPLF",
    "gn:name":"Kerkak",
    "gn:population":0,
    "gn:timezone":"Asia/Tehran",
    "iso:country":"IR",
    "name:ceb_x_preferred":[
        "Kerkak"
    ],
    "name:fas_x_preferred":[
        "\u06a9\u0631\u06a9\u06a9"
    ],
    "name:swe_x_preferred":[
        "Kerkak"
    ],
    "wof:name":"Kerkak",
    "wof:placetype":"locality"
},
  "geometry": {"coordinates":[58.56061999999999,26.97853],"type":"Point"}
}