{
  "type": "Feature",
  "properties": {
    "gn:admin1_code":"8.0",
    "gn:asciiname":"Razan",
    "gn:country_code":"IR",
    "gn:dem":934,
    "gn:feature_class":"P",
    "gn:feature_code":"PPL",
    "gn:name":"R\u0101z\u0101n",
    "gn:population":0,
    "gn:timezone":"Asia/Tehran",
    "iso:country":"IR",
    "name:ara_x_preferred":[
        "\u0631\u0627\u0632\u0627\u0646"
    ],
    "name:azb_x_preferred":[
        "\u0631\u0632\u0646"
    ],
    "name:aze_x_preferred":[
        "R\u0259z\u0259n"
    ],
    "name:ceb_x_preferred":[
        "Razan"
    ],
    "name:fas_x_preferred":[
        "\u0631\u0627\u0632\u0627\u0646"
    ],
    "name:fas_x_variant":[
        "\u0631\u0632\u0646"
    ],
    "name:ita_x_preferred":[
        "Razan"
    ],
    "name:mlg_x_preferred":[
        "Razan"
    ],
    "name:msa_x_preferred":[
        "Razan"
    ],
    "name:pnb_x_preferred":[
        "\u0631\u0632\u0646"
    ],
    "name:rus_x_preferred":[
        "\u0420\u0435\u0437\u0435\u043d"
    ],
    "name:swe_x_preferred":[
        "Razan"
    ],
    "name:tur_x_preferred":[
        "Rezen"
    ],
    "name:und_x_variant":[
        "R\u0101z\u0101n"
    ],
    "wof:name":"Razan",
    "wof:placetype":"locality"
},
  "geometry": {"coordinates":[48.67059,37.84615],"type":"Point"}
}