{
  "type": "Feature",
  "properties": {
    "gn:admin1_code":"8.0",
    "gn:asciiname":"Razan",
    "gn:country_code":"IR",
    "gn:dem":934,
    "gn:feature_class":"P",
    "gn:feature_code":"PPL",
    "gn:name":"R\u0101z\u0101n",
    "gn:population":0,
    "gn:timezone":"Asia/Tehran",
    "iso:country":"IR",
    "name:fas_x_preferred":[
        "\u0631\u0627\u0632\u0627\u0646"
    ],
    "name:und_x_variant":[
        "R\u0101z\u0101n"
    ],
    "wof:name":"Razan",
    "wof:placetype":"locality"
},
  "geometry": {"coordinates":[48.67059,37.84615],"type":"Point"}
}