{
  "type": "Feature",
  "properties": {
    "gn:admin1_code":"4.0",
    "gn:asciiname":"Rashidabad",
    "gn:country_code":"IR",
    "gn:dem":681,
    "gn:feature_class":"P",
    "gn:feature_code":"PPLL",
    "gn:name":"Rash\u012bd\u0101b\u0101d",
    "gn:population":0,
    "gn:timezone":"Asia/Tehran",
    "iso:country":"IR",
    "name:fas_x_preferred":[
        "\u0631\u0634\u064a\u062f \u0622\u0628\u0627\u062f"
    ],
    "name:und_x_variant":[
        "Rash\u012bd\u0101b\u0101d"
    ],
    "wof:name":"Rashidabad",
    "wof:placetype":"locality"
},
  "geometry": {"coordinates":[59.81247,26.86115],"type":"Point"}
}