{
  "type": "Feature",
  "properties": {
    "gn:admin1_code":"4.0",
    "gn:asciiname":"Halur",
    "gn:country_code":"IR",
    "gn:dem":1609,
    "gn:feature_class":"P",
    "gn:feature_code":"PPL",
    "gn:name":"Hal\u016br",
    "gn:population":0,
    "gn:timezone":"Asia/Tehran",
    "iso:country":"IR",
    "name:fas_x_preferred":[
        "\u0647\u0644\u0648\u0631"
    ],
    "name:fas_x_variant":[
        "H\u0101l\u016br",
        "Hal\u016br"
    ],
    "wof:name":"Halur",
    "wof:placetype":"locality"
},
  "geometry": {"coordinates":[60.21308000000001,28.83517],"type":"Point"}
}