{
  "type": "Feature",
  "properties": {
    "gn:admin1_code":"40.0",
    "gn:asciiname":"Dashtabad",
    "gn:country_code":"IR",
    "gn:dem":2120,
    "gn:feature_class":"P",
    "gn:feature_code":"PPL",
    "gn:name":"Dasht\u0101b\u0101d",
    "gn:population":0,
    "gn:timezone":"Asia/Tehran",
    "iso:country":"IR",
    "name:fas_x_preferred":[
        "\u062f\u0634\u062a \u0622\u0628\u0627\u062f"
    ],
    "name:fas_x_variant":[
        "Dasht\u0101b\u0101d"
    ],
    "wof:name":"Dashtabad",
    "wof:placetype":"locality"
},
  "geometry": {"coordinates":[53.9975,31.3939],"type":"Point"}
}