{
  "type": "Feature",
  "properties": {
    "gn:admin1_code":"8",
    "gn:asciiname":"Khoshk Ab Sara",
    "gn:country_code":"IR",
    "gn:dem":1767,
    "gn:feature_class":"P",
    "gn:feature_code":"PPL",
    "gn:name":"Khoshk \u0100b Sar\u0101",
    "gn:population":0,
    "gn:timezone":"Asia/Tehran",
    "iso:country":"IR",
    "name:fas_x_preferred":[
        "\u06af\u0631\u062f \u067e\u0634\u062a\u0647 \u0633\u0631"
    ],
    "name:fas_x_variant":[
        "\u062e\u0634\u06a9 \u0622\u0628 \u0633\u0631\u0627"
    ],
    "name:und_x_variant":[
        "Gerd Poshteh Sar",
        "Khoshk \u0100b Sar\u0101"
    ],
    "wof:name":"Khoshk Ab Sara",
    "wof:placetype":"locality"
},
  "geometry": {"coordinates":[50.49858,36.88995],"type":"Point"}
}