{
  "type": "Feature",
  "properties": {
    "gn:admin1_code":"37.0",
    "gn:asciiname":"Bayjeq Tatar Qarahsu",
    "gn:country_code":"IR",
    "gn:dem":66,
    "gn:feature_class":"P",
    "gn:feature_code":"PPL",
    "gn:name":"B\u0101yjeq T\u0101t\u0101r Qarahs\u016b",
    "gn:population":0,
    "gn:timezone":"Asia/Tehran",
    "iso:country":"IR",
    "name:ceb_x_preferred":[
        "B\u0101yjeq"
    ],
    "name:fas_x_preferred":[
        "\u062a\u0627\u062a\u0627\u0631 \u0628\u0627\u064a\u062c\u0642"
    ],
    "name:fas_x_variant":[
        "B\u0101yjeq",
        "T\u0101t\u0101r B\u0101yjeq",
        "\u0628\u0627\u064a\u062c\u0642",
        "\u0628\u0627\u06cc\u062c\u0642 \u062a\u0627\u062a\u0627\u0631 \u0642\u0631\u0647 \u0633\u0648",
        "\u062a\u0627\u062a\u0627\u0631\u0628\u0627\u06cc\u062c\u0642"
    ],
    "name:msa_x_preferred":[
        "Tatar Bayjeq"
    ],
    "name:swe_x_preferred":[
        "B\u0101yjeq"
    ],
    "name:und_x_variant":[
        "\u0628\u0627\u064a\u062c\u0642",
        "B\u0101yjeq T\u0101t\u0101r Qarahs\u016b",
        "Y\u0101y\u1e29aq"
    ],
    "wof:name":"Bayjeq Tatar Qarahsu",
    "wof:placetype":"locality"
},
  "geometry": {"coordinates":[55.17015,37.16487],"type":"Point"}
}