{
  "type": "Feature",
  "properties": {
    "gn:admin1_code":"25",
    "gn:asciiname":"Zargar",
    "gn:country_code":"IR",
    "gn:dem":1400,
    "gn:feature_class":"P",
    "gn:feature_code":"PPL",
    "gn:name":"Zargar",
    "gn:population":0,
    "gn:timezone":"Asia/Tehran",
    "iso:country":"IR",
    "name:aze_x_preferred":[
        "Z\u0259rg\u0259r"
    ],
    "name:ceb_x_preferred":[
        "Zargar"
    ],
    "name:ckb_x_preferred":[
        "\u0632\u06d5\u0631\u06af\u06d5\u0631"
    ],
    "name:fas_x_preferred":[
        "\u0632\u0631\u06af\u0631"
    ],
    "name:swe_x_preferred":[
        "Zargar"
    ],
    "wof:name":"Zargar",
    "wof:placetype":"locality"
},
  "geometry": {"coordinates":[55.08719,36.58261],"type":"Point"}
}