{
  "type": "Feature",
  "properties": {
    "gn:admin1_code":"4.0",
    "gn:asciiname":"Chegerd",
    "gn:cc2":"IR",
    "gn:country_code":"IR",
    "gn:dem":862,
    "gn:feature_class":"P",
    "gn:feature_code":"PPL",
    "gn:name":"Chegerd",
    "gn:population":0,
    "gn:timezone":"Asia/Tehran",
    "iso:country":"IR",
    "name:und_x_variant":[
        "Chegart-e K\u0101sh\u0101n",
        "Chegard",
        "Chegerd"
    ],
    "wof:name":"Chegerd",
    "wof:placetype":"locality"
},
  "geometry": {"coordinates":[62.68666999999999,27.62306],"type":"Point"}
}