{
  "type": "Feature",
  "properties": {
    "gn:admin1_code":"32",
    "gn:asciiname":"Goli Bolagh-e Bala",
    "gn:country_code":"IR",
    "gn:dem":727,
    "gn:feature_class":"P",
    "gn:feature_code":"PPL",
    "gn:name":"Gol\u012b Bol\u0101gh-e B\u0101l\u0101",
    "gn:population":0,
    "gn:timezone":"Asia/Tehran",
    "iso:country":"IR",
    "name:ara_x_preferred":[
        "\u063a\u0644\u064a \u0628\u0644\u0627\u063a \u0627\u0644\u0639\u0644\u064a\u0627"
    ],
    "name:azb_x_preferred":[
        "\u06cc\u0648\u062e\u0627\u0631\u06cc \u06af\u0648\u0644\u0648 \u0628\u0648\u0644\u0627\u0642"
    ],
    "name:fas_x_preferred":[
        "\u06af\u064f\u0644\u06cc \u0628\u064f\u0644\u0627\u0642\u0650 \u0639\u064f\u0644\u064a\u0627"
    ],
    "name:fas_x_variant":[
        "\u06af\u0644\u06cc \u0628\u0644\u0627\u063a \u0628\u0627\u0644\u0627",
        "Gol\u012b Bol\u0101q-e \u2018Oly\u0101",
        "Gol\u012b Bol\u0101gh-e B\u0101l\u0101",
        "\u06af\u0644\u06cc \u0628\u0644\u0627\u063a \u0639\u0644\u06cc\u0627"
    ],
    "name:msa_x_preferred":[
        "Goli Bolagh-e Olya"
    ],
    "wof:name":"Goli Bolagh-e Bala",
    "wof:placetype":"locality"
},
  "geometry": {"coordinates":[48.0313,39.2137],"type":"Point"}
}