{
  "type": "Feature",
  "properties": {
    "gn:admin1_code":"23",
    "gn:asciiname":"Sharafabad-e Pa'in",
    "gn:country_code":"IR",
    "gn:dem":1502,
    "gn:feature_class":"P",
    "gn:feature_code":"PPL",
    "gn:name":"Sharaf\u0101b\u0101d-e P\u0101\u2019\u012bn",
    "gn:population":0,
    "gn:timezone":"Asia/Tehran",
    "iso:country":"IR",
    "name:fas_x_preferred":[
        "\u0634\u064e\u0631\u064e\u0641\u0627\u0628\u0627\u062f\u0650 \u067e\u0627\u0626\u064a\u0646"
    ],
    "name:fas_x_variant":[
        "\u0634\u0631\u0641 \u0622\u0628\u0627\u062f \u067e\u0627\u0626\u06cc\u0646"
    ],
    "name:und_x_variant":[
        "Sharaf\u0101b\u0101d-e P\u0101\u2019\u012bn"
    ],
    "wof:name":"Sharafabad-e Pa'in",
    "wof:placetype":"locality"
},
  "geometry": {"coordinates":[47.5514,34.1226],"type":"Point"}
}