{
  "type": "Feature",
  "properties": {
    "gn:admin1_code":"13",
    "gn:asciiname":"Shalan",
    "gn:country_code":"IR",
    "gn:dem":1018,
    "gn:feature_class":"P",
    "gn:feature_code":"PPL",
    "gn:name":"Sh\u0101l\u0101n",
    "gn:population":0,
    "gn:timezone":"Asia/Tehran",
    "iso:country":"IR",
    "name:fas_x_preferred":[
        "\u0634\u0627\u0644\u0627\u0646"
    ],
    "name:fas_x_variant":[
        "Sh\u0101l\u0101n"
    ],
    "wof:name":"Shalan",
    "wof:placetype":"locality"
},
  "geometry": {"coordinates":[45.99953,34.47905],"type":"Point"}
}