{
  "type": "Feature",
  "properties": {
    "gn:admin1_code":"15",
    "gn:asciiname":"Kal Mawait",
    "gn:country_code":"IR",
    "gn:dem":868,
    "gn:feature_class":"P",
    "gn:feature_code":"PPL",
    "gn:name":"Kal Mawait",
    "gn:population":0,
    "gn:timezone":"Asia/Tehran",
    "iso:country":"IR",
    "wof:name":"Kal Mawait",
    "wof:placetype":"locality"
},
  "geometry": {"coordinates":[49.85,31.65],"type":"Point"}
}