{
  "type": "Feature",
  "properties": {
    "gn:admin1_code":"5",
    "gn:asciiname":"Deh Kond",
    "gn:country_code":"IR",
    "gn:dem":751,
    "gn:feature_class":"P",
    "gn:feature_code":"PPL",
    "gn:name":"Deh Kond",
    "gn:population":0,
    "gn:timezone":"Asia/Tehran",
    "iso:country":"IR",
    "name:ara_x_preferred":[
        "\u062f\u0647 \u06a9\u0646\u062f"
    ],
    "name:ceb_x_preferred":[
        "Deh Kond"
    ],
    "name:fas_x_preferred":[
        "\u062f\u0650\u0647 \u0643\u064f\u0646\u062f\u0650\u0647"
    ],
    "name:fas_x_variant":[
        "\u062f\u0647 \u0643\u0646\u062f",
        "\u062f\u0647 \u06a9\u0646\u062f"
    ],
    "name:swe_x_preferred":[
        "Deh Kond"
    ],
    "name:und_x_variant":[
        "Deh Kondeh",
        "\u062f\u0647 \u0643\u0646\u062f",
        "Deh Kond"
    ],
    "wof:name":"Deh Kond",
    "wof:placetype":"locality"
},
  "geometry": {"coordinates":[51.21142,30.31615],"type":"Point"}
}