{
  "type": "Feature",
  "properties": {
    "gn:admin1_code":"34",
    "gn:asciiname":"Junak",
    "gn:country_code":"IR",
    "gn:dem":1263,
    "gn:feature_class":"P",
    "gn:feature_code":"PPL",
    "gn:name":"J\u016bnak",
    "gn:population":0,
    "gn:timezone":"Asia/Tehran",
    "iso:country":"IR",
    "name:fas_x_preferred":[
        "\u06af\u0648\u0646\u0627\u0628"
    ],
    "name:fas_x_variant":[
        "G\u016bn\u0101b",
        "\u062c\u0648\u0646\u06a9"
    ],
    "name:und_x_variant":[
        "J\u016bnak"
    ],
    "wof:name":"Junak",
    "wof:placetype":"locality"
},
  "geometry": {"coordinates":[50.2467,34.8714],"type":"Point"}
}