{
  "type": "Feature",
  "properties": {
    "gn:admin1_code":"43",
    "gn:asciiname":"Tavakkol Senjed",
    "gn:country_code":"IR",
    "gn:dem":1275,
    "gn:feature_class":"P",
    "gn:feature_code":"PPL",
    "gn:name":"Tavakkol Senjed",
    "gn:population":0,
    "gn:timezone":"Asia/Tehran",
    "iso:country":"IR",
    "name:fas_x_preferred":[
        "\u062a\u0648\u06a9\u0644 \u0633\u0646\u062c\u062f"
    ],
    "name:und_x_variant":[
        "\u062a\u0648\u06a9\u0644 \u0633\u0646\u062c\u062f"
    ],
    "wof:name":"Tavakkol Senjed",
    "wof:placetype":"locality"
},
  "geometry": {"coordinates":[57.55089,37.77096],"type":"Point"}
}