{
  "type": "Feature",
  "properties": {
    "gn:admin1_code":"4.0",
    "gn:asciiname":"Latarabad",
    "gn:cc2":"IR",
    "gn:country_code":"IR",
    "gn:dem":1495,
    "gn:feature_class":"P",
    "gn:feature_code":"PPL",
    "gn:name":"Latar\u0101b\u0101d",
    "gn:population":0,
    "gn:timezone":"Asia/Tehran",
    "iso:country":"IR",
    "name:fas_x_preferred":[
        "Latar\u0101b\u0101d"
    ],
    "name:und_x_variant":[
        "Latr \u0100b\u0101d"
    ],
    "wof:name":"Latarabad",
    "wof:placetype":"locality"
},
  "geometry": {"coordinates":[60.41944,29.20611],"type":"Point"}
}