{
  "type": "Feature",
  "properties": {
    "gn:admin1_code":"15.0",
    "gn:asciiname":"Dehliz-e Seh",
    "gn:country_code":"IR",
    "gn:dem":21,
    "gn:feature_class":"P",
    "gn:feature_code":"PPL",
    "gn:name":"Dehl\u012bz-e Seh",
    "gn:population":0,
    "gn:timezone":"Asia/Tehran",
    "iso:country":"IR",
    "name:fas_x_preferred":[
        "\u062f\u0647\u0644\u06cc\u0632 \u0633\u0647"
    ],
    "name:fas_x_variant":[
        "Dehl\u012bz-e Seh",
        "\u0633\u06cc\u062f \u0634\u0631\u06cc\u0641"
    ],
    "name:und_x_variant":[
        "Seyyed Shar\u012bf"
    ],
    "wof:name":"Dehliz-e Seh",
    "wof:placetype":"locality"
},
  "geometry": {"coordinates":[48.45938,31.38294],"type":"Point"}
}