{
  "type": "Feature",
  "properties": {
    "gn:admin1_code":"5.0",
    "gn:asciiname":"Darreh Bin",
    "gn:country_code":"IR",
    "gn:dem":1792,
    "gn:feature_class":"P",
    "gn:feature_code":"PPL",
    "gn:name":"Darreh B\u012bn",
    "gn:population":0,
    "gn:timezone":"Asia/Tehran",
    "iso:country":"IR",
    "name:fas_x_preferred":[
        "\u062f\u064e\u0631\u0650\u0651\u0647 \u0628\u064a\u0646"
    ],
    "wof:name":"Darreh Bin",
    "wof:placetype":"locality"
},
  "geometry": {"coordinates":[50.98222,30.92444],"type":"Point"}
}