{
  "type": "Feature",
  "properties": {
    "gn:admin1_code":"43",
    "gn:asciiname":"Kornan",
    "gn:country_code":"IR",
    "gn:dem":1987,
    "gn:feature_class":"P",
    "gn:feature_code":"PPL",
    "gn:name":"Korn\u0101n",
    "gn:population":0,
    "gn:timezone":"Asia/Tehran",
    "iso:country":"IR",
    "name:fas_x_preferred":[
        "Kowrn\u0101n"
    ],
    "name:fas_x_variant":[
        "Korn\u0101n",
        "\u06a9\u0631\u0646\u0627\u0646"
    ],
    "name:und_x_variant":[
        "Korn\u0101n",
        "K\u016brn\u0101n"
    ],
    "wof:name":"Kornan",
    "wof:placetype":"locality"
},
  "geometry": {"coordinates":[57.97377,37.00527],"type":"Point"}
}