{
  "type": "Feature",
  "properties": {
    "gn:admin1_code":"42.0",
    "gn:asciiname":"Chenarak",
    "gn:country_code":"IR",
    "gn:dem":970,
    "gn:feature_class":"P",
    "gn:feature_code":"PPL",
    "gn:name":"Chen\u0101rak",
    "gn:population":0,
    "gn:timezone":"Asia/Tehran",
    "iso:country":"IR",
    "name:fas_x_preferred":[
        "\u0686\u0646\u0627\u0631\u06a9"
    ],
    "name:fas_x_variant":[
        "Chen\u0101rak",
        "Chan\u0101rak"
    ],
    "wof:name":"Chenarak",
    "wof:placetype":"locality"
},
  "geometry": {"coordinates":[60.0475,36.2485],"type":"Point"}
}