{
  "type": "Feature",
  "properties": {
    "gn:admin1_code":"33",
    "gn:asciiname":"Bostanabad",
    "gn:country_code":"IR",
    "gn:dem":1725,
    "gn:feature_class":"P",
    "gn:feature_code":"PPLA2",
    "gn:name":"Bost\u0101n\u0101b\u0101d",
    "gn:population":0,
    "gn:timezone":"Asia/Tehran",
    "iso:country":"IR",
    "name:ara_x_preferred":[
        "\u0628\u0633\u062a\u0627\u0646 \u0622\u0628\u0627\u062f"
    ],
    "name:azb_x_preferred":[
        "\u0628\u0633\u062a\u0627\u0646\u200c\u0622\u0628\u0627\u062f"
    ],
    "name:aze_x_preferred":[
        "Bostanabad"
    ],
    "name:ceb_x_preferred":[
        "Bost\u0101n\u0101b\u0101d"
    ],
    "name:deu_x_preferred":[
        "Bostanabad"
    ],
    "name:fas_x_preferred":[
        "Bost\u0101n\u0101b\u0101d"
    ],
    "name:fas_x_variant":[
        "\u0628\u0633\u062a\u0627\u0646 \u0622\u0628\u0627\u062f",
        "\u0628\u0633\u062a\u0627\u0646\u200c\u0622\u0628\u0627\u062f"
    ],
    "name:ita_x_preferred":[
        "Bostanabad"
    ],
    "name:mlg_x_preferred":[
        "Bostanabad"
    ],
    "name:msa_x_preferred":[
        "Bostanabad"
    ],
    "name:pnb_x_preferred":[
        "\u0628\u0633\u062a\u0627\u0646 \u0622\u0628\u0627\u062f"
    ],
    "name:tur_x_preferred":[
        "Bostanabad"
    ],
    "name:urd_x_preferred":[
        "\u0628\u0633\u062a\u0627\u0646\u200c\u0622\u0628\u0627\u062f"
    ],
    "wof:name":"Bostanabad",
    "wof:placetype":"locality"
},
  "geometry": {"coordinates":[46.83542,37.84633],"type":"Point"}
}