{
  "type": "Feature",
  "properties": {
    "gn:admin1_code":"4.0",
    "gn:asciiname":"Konarak",
    "gn:country_code":"IR",
    "gn:dem":6,
    "gn:feature_class":"P",
    "gn:feature_code":"PPLA2",
    "gn:name":"Kon\u0101rak",
    "gn:population":0,
    "gn:timezone":"Asia/Tehran",
    "iso:country":"IR",
    "name:ara_x_preferred":[
        "\u0643\u0646\u0627\u0631\u0643"
    ],
    "name:aze_x_preferred":[
        "K\u00fcnar\u0259k"
    ],
    "name:ceb_x_preferred":[
        "Kon\u0101rak"
    ],
    "name:fas_x_preferred":[
        "\u06a9\u0646\u0627\u0631\u06a9"
    ],
    "name:fas_x_variant":[
        "Kon\u0101rak"
    ],
    "name:ita_x_preferred":[
        "Konarak"
    ],
    "name:mlg_x_preferred":[
        "Konarak"
    ],
    "name:rus_x_preferred":[
        "\u041a\u043e\u043d\u0430\u0440\u0435\u043a"
    ],
    "name:tur_x_preferred":[
        "Kunarek"
    ],
    "name:und_x_variant":[
        "Kun\u0101rak",
        "Ken\u0101rak",
        "K\u016bm\u0101rak",
        "Kunark"
    ],
    "wof:name":"Konarak",
    "wof:placetype":"locality"
},
  "geometry": {"coordinates":[60.3995,25.3604],"type":"Point"}
}