{
  "type": "Feature",
  "properties": {
    "gn:admin1_code":"10.0",
    "gn:asciiname":"Abtaf-e Sofla",
    "gn:country_code":"IR",
    "gn:dem":319,
    "gn:feature_class":"P",
    "gn:feature_code":"PPL",
    "gn:name":"\u0100b\u0163\u0101f-e Sofl\u00e1",
    "gn:population":0,
    "gn:timezone":"Asia/Tehran",
    "iso:country":"IR",
    "name:fas_x_preferred":[
        "\u0622\u0628 \u0637\u0627\u0641"
    ],
    "name:fas_x_variant":[
        "\u0100b\u0163\u0101f",
        "\u0622\u0628\u0637\u0627\u0641 \u0633\u0641\u0644\u06cc",
        "\u0627\u0628\u0637\u0627\u0641 \u0633\u0641\u0644\u06cc"
    ],
    "name:msa_x_preferred":[
        "Abtaf-e Sofla"
    ],
    "name:por_x_preferred":[
        "Abtaf-e Sofla"
    ],
    "name:und_x_variant":[
        "\u0100b\u0163\u0101f-e Sofl\u00e1"
    ],
    "wof:name":"Abtaf-e Sofla",
    "wof:placetype":"locality"
},
  "geometry": {"coordinates":[47.81222,32.64347],"type":"Point"}
}