{
  "type": "Feature",
  "properties": {
    "gn:admin1_code":"32.0",
    "gn:asciiname":"Qeshlaq-e Quzuqorqu",
    "gn:country_code":"IR",
    "gn:dem":1043,
    "gn:feature_class":"P",
    "gn:feature_code":"PPL",
    "gn:name":"Qeshl\u0101q-e Q\u016bz\u016bqorq\u016b",
    "gn:population":0,
    "gn:timezone":"Asia/Tehran",
    "iso:country":"IR",
    "name:fas_x_preferred":[
        "\u0642\u0634\u0644\u0627\u0642 \u0642\u0648\u0632\u0648\u0642\u0631\u0642\u0648"
    ],
    "name:und_x_variant":[
        "Qeshl\u0101q-e Q\u016bz\u016bqorq\u016b"
    ],
    "wof:name":"Qeshlaq-e Quzuqorqu",
    "wof:placetype":"locality"
},
  "geometry": {"coordinates":[47.69198,38.5672],"type":"Point"}
}