{
  "type": "Feature",
  "properties": {
    "gn:admin1_code":"13",
    "gn:asciiname":"Darreh Deraz",
    "gn:country_code":"IR",
    "gn:dem":1365,
    "gn:feature_class":"P",
    "gn:feature_code":"PPL",
    "gn:name":"Darreh Der\u0101z",
    "gn:population":0,
    "gn:timezone":"Asia/Tehran",
    "iso:country":"IR",
    "name:fas_x_preferred":[
        "\u062f\u0631\u0651\u0647 \u062f\u0631\u0627\u0632"
    ],
    "name:fas_x_variant":[
        "Darreh Dar\u012bsh",
        "Darreh Der\u0101z",
        "\u062f\u0631\u0647 \u062f\u0631\u0627\u0632"
    ],
    "wof:name":"Darreh Deraz",
    "wof:placetype":"locality"
},
  "geometry": {"coordinates":[47.0252,34.3414],"type":"Point"}
}