{
  "type": "Feature",
  "properties": {
    "gn:admin1_code":"42.0",
    "gn:asciiname":"Sa`dabad",
    "gn:country_code":"IR",
    "gn:dem":783,
    "gn:feature_class":"P",
    "gn:feature_code":"PPL",
    "gn:name":"Sa\u2018d\u0101b\u0101d",
    "gn:population":0,
    "gn:timezone":"Asia/Tehran",
    "iso:country":"IR",
    "name:fas_x_preferred":[
        "Sa\u2018d\u0101b\u0101d"
    ],
    "wof:name":"Sa`dabad",
    "wof:placetype":"locality"
},
  "geometry": {"coordinates":[60.82194000000001,34.81389],"type":"Point"}
}