{
  "type": "Feature",
  "properties": {
    "gn:admin1_code":"8",
    "gn:asciiname":"Meskin",
    "gn:country_code":"IR",
    "gn:dem":604,
    "gn:feature_class":"P",
    "gn:feature_code":"PPL",
    "gn:name":"Mesk\u012bn",
    "gn:population":0,
    "gn:timezone":"Asia/Tehran",
    "iso:country":"IR",
    "name:fas_x_preferred":[
        "\u0645\u0633\u06a9\u06cc\u0646"
    ],
    "name:fas_x_variant":[
        "Mesk\u012bn-e V\u012bznah",
        "Mesk\u012bn"
    ],
    "name:msa_x_preferred":[
        "Meskin"
    ],
    "name:ukr_x_preferred":[
        "\u041c\u0435\u0441\u043a\u0456\u043d"
    ],
    "wof:name":"Meskin",
    "wof:placetype":"locality"
},
  "geometry": {"coordinates":[48.753,38.2354],"type":"Point"}
}