{
  "type": "Feature",
  "properties": {
    "gn:admin1_code":"7",
    "gn:asciiname":"Puzeh Badi",
    "gn:country_code":"IR",
    "gn:dem":1618,
    "gn:feature_class":"P",
    "gn:feature_code":"PPL",
    "gn:name":"P\u016bzeh B\u0101d\u012b",
    "gn:population":0,
    "gn:timezone":"Asia/Tehran",
    "iso:country":"IR",
    "name:fas_x_preferred":[
        "P\u016bzeh B\u0101d\u012b"
    ],
    "wof:name":"Puzeh Badi",
    "wof:placetype":"locality"
},
  "geometry": {"coordinates":[52.43472,30.09861],"type":"Point"}
}