{
  "type": "Feature",
  "properties": {
    "gn:admin1_code":"36",
    "gn:asciiname":"Nahl",
    "gn:country_code":"IR",
    "gn:dem":1701,
    "gn:feature_class":"P",
    "gn:feature_code":"PPL",
    "gn:name":"Nahl",
    "gn:population":0,
    "gn:timezone":"Asia/Tehran",
    "iso:country":"IR",
    "name:fas_x_preferred":[
        "\u0646\u064e\u0647\u0644"
    ],
    "wof:name":"Nahl",
    "wof:placetype":"locality"
},
  "geometry": {"coordinates":[48.33333,36.86667],"type":"Point"}
}