{
  "type": "Feature",
  "properties": {
    "gn:admin1_code":"1",
    "gn:asciiname":"Hajj Baba-ye `Olya",
    "gn:country_code":"IR",
    "gn:dem":1889,
    "gn:feature_class":"P",
    "gn:feature_code":"PPL",
    "gn:name":"\u1e28\u0101jj B\u0101b\u0101-ye \u2018Oly\u0101",
    "gn:population":0,
    "gn:timezone":"Asia/Tehran",
    "iso:country":"IR",
    "name:fas_x_preferred":[
        "\u062d\u0627\u062c\u06cc \u0628\u0627\u0628\u0627 \u0639\u0644\u06cc\u0627"
    ],
    "name:fas_x_variant":[
        "\u1e28\u0101jj\u012b B\u0101b\u0101-ye \u2018Oly\u0101",
        "\u062d\u0627\u062c \u0628\u0627\u0628\u0627 \u0639\u0644\u06cc\u0627"
    ],
    "name:und_x_variant":[
        "\u1e28\u0101jj B\u0101b\u0101-ye \u2018Oly\u0101"
    ],
    "wof:name":"Hajj Baba-ye `Olya",
    "wof:placetype":"locality"
},
  "geometry": {"coordinates":[47.12126,36.34343],"type":"Point"}
}