{
  "type": "Feature",
  "properties": {
    "gn:admin1_code":"22.0",
    "gn:asciiname":"Nowshadi",
    "gn:country_code":"IR",
    "gn:dem":51,
    "gn:feature_class":"P",
    "gn:feature_code":"PPL",
    "gn:name":"Nowsh\u0101d\u012b",
    "gn:population":0,
    "gn:timezone":"Asia/Tehran",
    "iso:country":"IR",
    "name:ceb_x_preferred":[
        "Nowsh\u0101d\u012b"
    ],
    "name:fas_x_preferred":[
        "\u062e\u0636\u0631\u06cc"
    ],
    "name:fas_x_variant":[
        "\u0646\u0648\u0634\u0627\u062f\u06cc"
    ],
    "name:swe_x_preferred":[
        "Nowsh\u0101d\u012b"
    ],
    "name:und_x_variant":[
        "Khe\u1e95r\u012b",
        "Nowsh\u0101d\u012b"
    ],
    "wof:name":"Nowshadi",
    "wof:placetype":"locality"
},
  "geometry": {"coordinates":[51.2742,28.92235],"type":"Point"}
}