{
  "type": "Feature",
  "properties": {
    "gn:admin1_code":"40",
    "gn:asciiname":"Vakilabad",
    "gn:country_code":"IR",
    "gn:dem":789,
    "gn:feature_class":"P",
    "gn:feature_code":"PPL",
    "gn:name":"Vak\u012bl\u0101b\u0101d",
    "gn:population":0,
    "gn:timezone":"Asia/Tehran",
    "iso:country":"IR",
    "name:aze_x_preferred":[
        "V\u0259kilabad"
    ],
    "name:fas_x_preferred":[
        "Vak\u012bl\u0101b\u0101d"
    ],
    "name:fas_x_variant":[
        "\u0648\u06a9\u06cc\u0644 \u0622\u0628\u0627\u062f"
    ],
    "wof:name":"Vakilabad",
    "wof:placetype":"locality"
},
  "geometry": {"coordinates":[56.88314,34.30898],"type":"Point"}
}