{
  "type": "Feature",
  "properties": {
    "gn:admin1_code":"36",
    "gn:asciiname":"Qozalu",
    "gn:country_code":"IR",
    "gn:dem":2190,
    "gn:feature_class":"P",
    "gn:feature_code":"PPL",
    "gn:name":"Qozal\u016b",
    "gn:population":0,
    "gn:timezone":"Asia/Tehran",
    "iso:country":"IR",
    "name:fas_x_preferred":[
        "\u0642\u0648\u0632\u0644\u0648"
    ],
    "name:fas_x_variant":[
        "Q\u016bzl\u016b",
        "\u0642\u0632\u0644\u0648"
    ],
    "name:und_x_variant":[
        "Qozal\u016b"
    ],
    "wof:name":"Qozalu",
    "wof:placetype":"locality"
},
  "geometry": {"coordinates":[47.4196,36.70211],"type":"Point"}
}