{
  "type": "Feature",
  "properties": {
    "gn:admin1_code":"42.0",
    "gn:asciiname":"`Aliabad",
    "gn:country_code":"IR",
    "gn:dem":989,
    "gn:feature_class":"P",
    "gn:feature_code":"PPLL",
    "gn:name":"\u2018Al\u012b\u0101b\u0101d",
    "gn:population":0,
    "gn:timezone":"Asia/Tehran",
    "iso:country":"IR",
    "name:fas_x_preferred":[
        "Ch\u0101h-e \u2018Al\u012b"
    ],
    "name:fas_x_variant":[
        "\u0686\u0627\u0647 \u0639\u0644\u06cc",
        "\u0639\u0644\u06cc \u0622\u0628\u0627\u062f"
    ],
    "name:und_x_variant":[
        "\u0686\u0627\u0647 \u0639\u0644\u06cc",
        "\u2018Al\u012b\u0101b\u0101d"
    ],
    "wof:name":"`Aliabad",
    "wof:placetype":"locality"
},
  "geometry": {"coordinates":[58.34049,35.24168],"type":"Point"}
}