{
  "type": "Feature",
  "properties": {
    "gn:admin1_code":"0",
    "gn:asciiname":"Jahadabad",
    "gn:country_code":"IR",
    "gn:dem":335,
    "gn:feature_class":"P",
    "gn:feature_code":"PPL",
    "gn:name":"Jah\u0101d\u0101b\u0101d",
    "gn:population":0,
    "gn:timezone":"Asia/Tehran",
    "iso:country":"IR",
    "name:fas_x_preferred":[
        "\u062c\u0647\u0627\u062f \u0622\u0628\u0627\u062f"
    ],
    "name:fas_x_variant":[
        "Jah\u0101d\u0101b\u0101d"
    ],
    "wof:name":"Jahadabad",
    "wof:placetype":"locality"
},
  "geometry": {"coordinates":[57.5285,27.3514],"type":"Point"}
}