{
  "type": "Feature",
  "properties": {
    "gn:admin1_code":"5.0",
    "gn:asciiname":"Kareh Kareh",
    "gn:country_code":"IR",
    "gn:dem":1250,
    "gn:feature_class":"P",
    "gn:feature_code":"PPL",
    "gn:name":"Kareh Kareh",
    "gn:population":0,
    "gn:timezone":"Asia/Tehran",
    "iso:country":"IR",
    "name:fas_x_preferred":[
        "\u06a9\u0631\u0647 \u06a9\u0631\u0647"
    ],
    "wof:name":"Kareh Kareh",
    "wof:placetype":"locality"
},
  "geometry": {"coordinates":[50.44786,31.20254000000001],"type":"Point"}
}