{
  "type": "Feature",
  "properties": {
    "gn:admin1_code":"9",
    "gn:asciiname":"Pir Savaran",
    "gn:country_code":"IR",
    "gn:dem":2138,
    "gn:feature_class":"P",
    "gn:feature_code":"PPL",
    "gn:name":"P\u012br Sav\u0101r\u0101n",
    "gn:population":0,
    "gn:timezone":"Asia/Tehran",
    "iso:country":"IR",
    "name:fas_x_preferred":[
        "P\u012br Sav\u0101r\u0101n"
    ],
    "name:fas_x_variant":[
        "\u067e\u06cc\u0631 \u0633\u0648\u0627\u0631\u0627\u0646",
        "\u067e\u06cc\u0631\u0633\u0648\u0627\u0631\u0627\u0646"
    ],
    "name:msa_x_preferred":[
        "Pir Savaran"
    ],
    "name:und_x_variant":[
        "P\u012br Saw\u0101ran"
    ],
    "wof:name":"Pir Savaran",
    "wof:placetype":"locality"
},
  "geometry": {"coordinates":[48.7785,34.11805],"type":"Point"}
}