{
  "type": "Feature",
  "properties": {
    "gn:admin1_code":"15.0",
    "gn:asciiname":"Beyt-e Hasan-e Tayeb",
    "gn:country_code":"IR",
    "gn:dem":54,
    "gn:feature_class":"P",
    "gn:feature_code":"PPL",
    "gn:name":"Beyt-e \u1e28asan-e \u0162\u0101yeb",
    "gn:population":0,
    "gn:timezone":"Asia/Tehran",
    "iso:country":"IR",
    "name:fas_x_preferred":[
        "\u0634\u0647\u0631\u06a9 \u062d\u0633\u0646 \u0637\u06cc\u0628"
    ],
    "name:fas_x_variant":[
        "Shahrak-e \u1e28asan \u0162ayyeb",
        "\u0628\u06cc\u062a \u062d\u0633\u0646 \u0637\u0627\u06cc\u0628",
        "\u062d\u0633\u0646 \u062a\u0639\u06cc\u0628"
    ],
    "name:und_x_variant":[
        "Beyt-e \u1e28asan-e \u0162\u0101yeb",
        "\u1e28asan-e Ta\u2018yeb"
    ],
    "wof:name":"Beyt-e Hasan-e Tayeb",
    "wof:placetype":"locality"
},
  "geometry": {"coordinates":[48.2106,31.8805],"type":"Point"}
}