{
  "type": "Feature",
  "properties": {
    "gn:admin1_code":"4",
    "gn:asciiname":"Chah-e Din Mohammad",
    "gn:country_code":"IR",
    "gn:dem":1459,
    "gn:feature_class":"P",
    "gn:feature_code":"PPL",
    "gn:name":"Ch\u0101h-e D\u012bn Mo\u1e29ammad",
    "gn:population":0,
    "gn:timezone":"Asia/Tehran",
    "iso:country":"IR",
    "name:fas_x_preferred":[
        "\u0686\u0627\u0647 \u062f\u06cc\u0646 \u0645\u062d\u0645\u0651\u062f"
    ],
    "name:fas_x_variant":[
        "Ch\u0101h-e D\u012bn Mo\u1e29ammad"
    ],
    "wof:name":"Chah-e Din Mohammad",
    "wof:placetype":"locality"
},
  "geometry": {"coordinates":[60.39313000000001,28.62191],"type":"Point"}
}