{
  "type": "Feature",
  "properties": {
    "gn:admin1_code":"15",
    "gn:asciiname":"`Anafcheh",
    "gn:country_code":"IR",
    "gn:dem":27,
    "gn:feature_class":"P",
    "gn:feature_code":"PPL",
    "gn:name":"\u2018An\u0101fcheh",
    "gn:population":0,
    "gn:timezone":"Asia/Tehran",
    "iso:country":"IR",
    "name:ara_x_preferred":[
        "\u064a\u0643\u0627\u0648\u064a\u0629 \u0627\u0644\u0623\u0648\u0644\u0649"
    ],
    "name:azb_x_preferred":[
        "\u06cc\u06a9\u0627\u0648\u06cc\u0647 \u06cc\u06a9"
    ],
    "name:ceb_x_preferred":[
        "Yek\u0101v\u012byeh-ye Yek"
    ],
    "name:fas_x_preferred":[
        "\u06cc\u06a9\u0627\u0648\u06cc\u0647 \u06cc\u06a9"
    ],
    "name:fas_x_variant":[
        "Yek\u0101v\u012byeh-ye Yek",
        "\u0639\u0646\u0627\u0641\u0686\u0647"
    ],
    "name:swe_x_preferred":[
        "Yek\u0101v\u012byeh-ye Yek"
    ],
    "name:und_x_variant":[
        "Lek\u0101v\u012bgeh-ye Yek",
        "\u2018An\u0101fcheh",
        "\u2018An\u0101fjeh",
        "Anafijeh",
        "Shaikh \u2018Abb\u0101s",
        "Anaf\u012bjeh",
        "\u2018An\u0101qcheh"
    ],
    "name:urd_x_preferred":[
        "\u06cc\u06a9\u0627\u0648\u06cc\u06c1 \u06cc\u06a9"
    ],
    "wof:name":"`Anafcheh",
    "wof:placetype":"locality"
},
  "geometry": {"coordinates":[48.8356,31.6206],"type":"Point"}
}