{
  "type": "Feature",
  "properties": {
    "gn:admin1_code":"28.0",
    "gn:asciiname":"Bafran",
    "gn:country_code":"IR",
    "gn:dem":1483,
    "gn:feature_class":"P",
    "gn:feature_code":"PPL",
    "gn:name":"B\u0101fr\u0101n",
    "gn:population":0,
    "gn:timezone":"Asia/Tehran",
    "iso:country":"IR",
    "name:fas_x_preferred":[
        "B\u0101fr\u0101n"
    ],
    "name:fas_x_variant":[
        "\u0628\u0627\u0641\u0631\u0627\u0646"
    ],
    "name:und_x_variant":[
        "B\u0101far\u0101n",
        "B\u0101fr\u0101n Minar"
    ],
    "wof:name":"Bafran",
    "wof:placetype":"locality"
},
  "geometry": {"coordinates":[53.14194000000001,32.83774],"type":"Point"}
}