{
  "type": "Feature",
  "properties": {
    "gn:admin1_code":"35",
    "gn:asciiname":"Dowghanlu",
    "gn:country_code":"IR",
    "gn:dem":33,
    "gn:feature_class":"P",
    "gn:feature_code":"PPL",
    "gn:name":"Dowgh\u0101nl\u016b",
    "gn:population":0,
    "gn:timezone":"Asia/Tehran",
    "iso:country":"IR",
    "name:ceb_x_preferred":[
        "Dowgh\u0101nl\u016b"
    ],
    "name:fas_x_preferred":[
        "\u062f\u064f\u0648\u0642\u0627\u0646\u0644\u0648"
    ],
    "name:fas_x_variant":[
        "Dowgh\u0101nl\u016b",
        "Dowq\u0101nl\u016b",
        "\u062f\u0648\u063a\u0627\u0646\u0644\u0648",
        "\u062f\u0648\u0642\u0627\u0646\u0644\u0648"
    ],
    "name:swe_x_preferred":[
        "Dowgh\u0101nl\u016b"
    ],
    "name:und_x_variant":[
        "\u062f\u0648\u063a\u0627\u0646\u0644\u0648"
    ],
    "wof:name":"Dowghanlu",
    "wof:placetype":"locality"
},
  "geometry": {"coordinates":[53.27646,36.64536],"type":"Point"}
}