{
  "type": "Feature",
  "properties": {
    "gn:admin1_code":"13",
    "gn:asciiname":"Shahrokhabad",
    "gn:country_code":"IR",
    "gn:dem":1307,
    "gn:feature_class":"P",
    "gn:feature_code":"PPL",
    "gn:name":"Sh\u0101hrokh\u0101b\u0101d",
    "gn:population":0,
    "gn:timezone":"Asia/Tehran",
    "iso:country":"IR",
    "name:fas_x_preferred":[
        "\u0634\u0627\u0647\u0631\u062e \u0622\u0628\u0627\u062f"
    ],
    "name:fas_x_variant":[
        "Sh\u0101hrokh\u0101b\u0101d"
    ],
    "wof:name":"Shahrokhabad",
    "wof:placetype":"locality"
},
  "geometry": {"coordinates":[46.9332,34.4804],"type":"Point"}
}