{
  "type": "Feature",
  "properties": {
    "gn:admin1_code":"42",
    "gn:asciiname":"`Ali Beyk",
    "gn:country_code":"IR",
    "gn:dem":1018,
    "gn:feature_class":"P",
    "gn:feature_code":"PPL",
    "gn:name":"\u2018Al\u012b Beyk",
    "gn:population":0,
    "gn:timezone":"Asia/Tehran",
    "iso:country":"IR",
    "name:fas_x_preferred":[
        "\u2018Al\u012b Beyk"
    ],
    "name:fas_x_variant":[
        "\u2018Al\u012b Beyg",
        "\u0639\u0644\u06cc \u0628\u06cc\u06af",
        "\u0639\u0644\u06cc \u0628\u06cc\u06a9"
    ],
    "wof:name":"`Ali Beyk",
    "wof:placetype":"locality"
},
  "geometry": {"coordinates":[57.75899,35.29994],"type":"Point"}
}