{
  "type": "Feature",
  "properties": {
    "gn:admin1_code":"42",
    "gn:asciiname":"Shad Mianeh",
    "gn:country_code":"IR",
    "gn:dem":1187,
    "gn:feature_class":"P",
    "gn:feature_code":"PPL",
    "gn:name":"Sh\u0101d M\u012b\u0101neh",
    "gn:population":0,
    "gn:timezone":"Asia/Tehran",
    "iso:country":"IR",
    "name:fas_x_preferred":[
        "\u0634\u0627\u062f \u0645\u06cc\u0627\u0646\u0647"
    ],
    "name:fas_x_variant":[
        "Sh\u0101d Mehneh",
        "Sh\u0101d M\u012b\u0101neh"
    ],
    "wof:name":"Shad Mianeh",
    "wof:placetype":"locality"
},
  "geometry": {"coordinates":[58.9056,36.10199],"type":"Point"}
}