{
  "type": "Feature",
  "properties": {
    "gn:admin1_code":"29",
    "gn:asciiname":"Downgeh Nim",
    "gn:cc2":"IR",
    "gn:country_code":"IR",
    "gn:dem":1822,
    "gn:feature_class":"P",
    "gn:feature_code":"PPL",
    "gn:name":"Downgeh N\u012bm",
    "gn:population":0,
    "gn:timezone":"Asia/Tehran",
    "iso:country":"IR",
    "name:fas_x_preferred":[
        "Downgeh N\u012bm"
    ],
    "name:fas_x_variant":[
        "\u062f\u0627\u0646\u06af \u0646\u06cc\u0645"
    ],
    "name:und_x_variant":[
        "D\u0101ng-e N\u012bm",
        "D\u016bngeh N\u012bm"
    ],
    "wof:name":"Downgeh Nim",
    "wof:placetype":"locality"
},
  "geometry": {"coordinates":[57.32167,30.47806],"type":"Point"}
}