{
  "type": "Feature",
  "properties": {
    "gn:admin1_code":"44.0",
    "gn:asciiname":"Sijan",
    "gn:country_code":"IR",
    "gn:dem":2108,
    "gn:feature_class":"P",
    "gn:feature_code":"PPL",
    "gn:name":"S\u012bj\u0101n",
    "gn:population":0,
    "gn:timezone":"Asia/Tehran",
    "iso:country":"IR",
    "name:ceb_x_preferred":[
        "Sijan"
    ],
    "name:fas_x_preferred":[
        "\u0633\u064a\u062c\u0627\u0646"
    ],
    "name:fas_x_variant":[
        "S\u012bj\u0101n"
    ],
    "name:rus_x_preferred":[
        "\u0428\u0438\u044f\u043d"
    ],
    "name:swe_x_preferred":[
        "Sijan"
    ],
    "name:ukr_x_preferred":[
        "\u0428\u0438\u044f\u043d"
    ],
    "wof:name":"Sijan",
    "wof:placetype":"locality"
},
  "geometry": {"coordinates":[51.1493,35.9207],"type":"Point"}
}