{
  "type": "Feature",
  "properties": {
    "gn:admin1_code":"8",
    "gn:asciiname":"Bonyad-e Hayati",
    "gn:country_code":"IR",
    "gn:dem":534,
    "gn:feature_class":"P",
    "gn:feature_code":"PPL",
    "gn:name":"Bony\u0101d-e \u1e28ay\u0101t\u012b",
    "gn:population":0,
    "gn:timezone":"Asia/Tehran",
    "iso:country":"IR",
    "name:fas_x_preferred":[
        "\u0628\u0646\u06cc\u0627\u062f \u062d\u06cc\u0627\u0637\u06cc"
    ],
    "name:fas_x_variant":[
        "Bony\u0101d-e \u1e28ay\u0101t\u012b"
    ],
    "wof:name":"Bonyad-e Hayati",
    "wof:placetype":"locality"
},
  "geometry": {"coordinates":[48.7871,38.2703],"type":"Point"}
}