{
  "type": "Feature",
  "properties": {
    "gn:admin1_code":"29",
    "gn:asciiname":"Qannad",
    "gn:country_code":"IR",
    "gn:dem":864,
    "gn:feature_class":"P",
    "gn:feature_code":"PPL",
    "gn:name":"Qann\u0101d",
    "gn:population":0,
    "gn:timezone":"Asia/Tehran",
    "iso:country":"IR",
    "name:fas_x_preferred":[
        "Af\u1e95al\u0101b\u0101d"
    ],
    "name:fas_x_variant":[
        "\u0642\u0646\u0627\u062f",
        "\u0627\u0628\u0648 \u0627\u0644\u0641\u0636\u0644"
    ],
    "name:und_x_variant":[
        "Qann\u0101d",
        "Ab\u016b ol Fa\u1e95l"
    ],
    "wof:name":"Qannad",
    "wof:placetype":"locality"
},
  "geometry": {"coordinates":[58.5284,28.8717],"type":"Point"}
}