{
  "type": "Feature",
  "properties": {
    "gn:admin1_code":"4.0",
    "gn:asciiname":"Deh-e Reza",
    "gn:country_code":"IR",
    "gn:dem":477,
    "gn:feature_class":"P",
    "gn:feature_code":"PPL",
    "gn:name":"Deh-e Re\u1e95\u0101",
    "gn:population":0,
    "gn:timezone":"Asia/Tehran",
    "iso:country":"IR",
    "name:fas_x_preferred":[
        "\u062f\u0647 \u0631\u0636\u0627"
    ],
    "name:fas_x_variant":[
        "Deh-e Re\u1e95\u0101",
        "\u062f\u0647 \u0639\u0644\u06cc\u0631\u0636\u0627"
    ],
    "name:und_x_variant":[
        "Deh-e \u2018Al\u012bre\u1e95\u0101"
    ],
    "wof:name":"Deh-e Reza",
    "wof:placetype":"locality"
},
  "geometry": {"coordinates":[61.3547,30.8613],"type":"Point"}
}