{
  "type": "Feature",
  "properties": {
    "gn:admin1_code":"42",
    "gn:asciiname":"Fathabad",
    "gn:country_code":"IR",
    "gn:dem":1413,
    "gn:feature_class":"P",
    "gn:feature_code":"PPL",
    "gn:name":"Fat\u1e29\u0101b\u0101d",
    "gn:population":0,
    "gn:timezone":"Asia/Tehran",
    "iso:country":"IR",
    "name:ara_x_preferred":[
        "\u0641\u062a\u062d \u0623\u0628\u0627\u062f"
    ],
    "name:fas_x_preferred":[
        "Khanjar\u012b-ye B\u0101l\u0101"
    ],
    "name:fas_x_variant":[
        "Fat\u1e29\u0101b\u0101d",
        "\u0641\u062a\u062d \u0622\u0628\u0627\u062f",
        "\u0641\u062a\u062d\u200c\u0622\u0628\u0627\u062f"
    ],
    "name:mzn_x_preferred":[
        "\u0641\u062a\u062d\u200c\u0622\u0628\u0627\u062f"
    ],
    "wof:name":"Fathabad",
    "wof:placetype":"locality"
},
  "geometry": {"coordinates":[57.76798,35.42845],"type":"Point"}
}