{
  "type": "Feature",
  "properties": {
    "gn:admin1_code":"7.0",
    "gn:asciiname":"Ab Goshneh",
    "gn:country_code":"IR",
    "gn:dem":1325,
    "gn:feature_class":"P",
    "gn:feature_code":"PPL",
    "gn:name":"\u0100b Goshneh",
    "gn:population":0,
    "gn:timezone":"Asia/Tehran",
    "iso:country":"IR",
    "name:fas_x_preferred":[
        "\u0100b Goshneh"
    ],
    "name:fas_x_variant":[
        "\u0622\u0628 \u06af\u0634\u0646\u0647"
    ],
    "wof:name":"Ab Goshneh",
    "wof:placetype":"locality"
},
  "geometry": {"coordinates":[51.63169,30.08048],"type":"Point"}
}