{
  "type": "Feature",
  "properties": {
    "gn:admin1_code":"15",
    "gn:asciiname":"Chit Anbeh",
    "gn:country_code":"IR",
    "gn:dem":463,
    "gn:feature_class":"P",
    "gn:feature_code":"PPL",
    "gn:name":"Ch\u012bt Anbeh",
    "gn:population":0,
    "gn:timezone":"Asia/Tehran",
    "iso:country":"IR",
    "name:fas_x_preferred":[
        "Ch\u012bt Anb\u016bh"
    ],
    "name:fas_x_variant":[
        "Ch\u012bt Boneh",
        "\u0686\u06cc\u062a \u0628\u0646\u0647",
        "\u0686\u06cc\u062a \u0627\u0646\u0628\u0647",
        "\u0686\u06cc \u062a\u0645\u0628\u0647"
    ],
    "name:und_x_variant":[
        "Chitamba",
        "Ch\u012bt Anbeh",
        "Ch\u012btamb\u016b",
        "\u0686\u06cc\u062a \u0628\u0646\u0647",
        "Ch\u012b Tombeh"
    ],
    "wof:name":"Chit Anbeh",
    "wof:placetype":"locality"
},
  "geometry": {"coordinates":[49.80878,31.36855],"type":"Point"}
}