{
  "type": "Feature",
  "properties": {
    "gn:admin1_code":"41",
    "gn:asciiname":"Gusheh-ye Zanan",
    "gn:country_code":"IR",
    "gn:dem":1460,
    "gn:feature_class":"P",
    "gn:feature_code":"PPL",
    "gn:name":"G\u016bsheh-ye Zan\u0101n",
    "gn:population":0,
    "gn:timezone":"Asia/Tehran",
    "iso:country":"IR",
    "name:fas_x_preferred":[
        "\u06af\u0648\u0634\u0650\u06c0 \u0632\u064e\u0646\u0627\u0646"
    ],
    "name:fas_x_variant":[
        "G\u016bsheh-ye Zan\u0101n"
    ],
    "name:und_x_variant":[
        "Gusheh-i-Zan\u0101n",
        "G\u016bsheh-e Zan\u0101n"
    ],
    "wof:name":"Gusheh-ye Zanan",
    "wof:placetype":"locality"
},
  "geometry": {"coordinates":[58.85,32.36667],"type":"Point"}
}