{
  "type": "Feature",
  "properties": {
    "gn:admin1_code":"40",
    "gn:asciiname":"Masjed Dagh",
    "gn:country_code":"IR",
    "gn:dem":1765,
    "gn:feature_class":"P",
    "gn:feature_code":"PPL",
    "gn:name":"Masjed D\u0101gh",
    "gn:population":0,
    "gn:timezone":"Asia/Tehran",
    "iso:country":"IR",
    "name:fas_x_preferred":[
        "Masjed D\u0101gh"
    ],
    "name:und_x_variant":[
        "Masjedak",
        "Masjid D\u0101g",
        "Masjid D\u0101q"
    ],
    "wof:name":"Masjed Dagh",
    "wof:placetype":"locality"
},
  "geometry": {"coordinates":[54.35,29.68333],"type":"Point"}
}