{
  "type": "Feature",
  "properties": {
    "gn:admin1_code":"29",
    "gn:asciiname":"Bekakerah",
    "gn:country_code":"IR",
    "gn:dem":2086,
    "gn:feature_class":"P",
    "gn:feature_code":"PPLF",
    "gn:name":"Bek\u0101ker\u0101h",
    "gn:population":0,
    "gn:timezone":"Asia/Tehran",
    "iso:country":"IR",
    "name:fas_x_preferred":[
        "Beg\u0101ker\u0101h"
    ],
    "name:fas_x_variant":[
        "\u0628\u06a9\u0627\u06a9\u0631\u0627\u0647",
        "\u0645\u06cc\u0627\u0646\u062c\u0648\u0627",
        "\u0645\u06cc\u0627\u0646 \u062c\u0648\u0628"
    ],
    "name:und_x_variant":[
        "Bek\u0101ker\u0101h",
        "M\u012b\u0101njov\u0101",
        "M\u012b\u0101n J\u016bb"
    ],
    "wof:name":"Bekakerah",
    "wof:placetype":"locality"
},
  "geometry": {"coordinates":[58.09889,28.90528],"type":"Point"}
}