{
  "type": "Feature",
  "properties": {
    "gn:admin1_code":"15",
    "gn:asciiname":"Akivash",
    "gn:country_code":"IR",
    "gn:dem":36,
    "gn:feature_class":"P",
    "gn:feature_code":"PPL",
    "gn:name":"Ak\u012bvash",
    "gn:population":0,
    "gn:timezone":"Asia/Tehran",
    "iso:country":"IR",
    "name:fas_x_preferred":[
        "\u06a9\u06cc\u0648\u0634"
    ],
    "name:fas_x_variant":[
        "Sheykh Gev\u012bsh",
        "K\u012bvash",
        "\u0627\u06a9\u06cc\u0648\u0634"
    ],
    "name:und_x_variant":[
        "Ak\u012bvash"
    ],
    "wof:name":"Akivash",
    "wof:placetype":"locality"
},
  "geometry": {"coordinates":[48.41837,31.81361],"type":"Point"}
}