{
  "type": "Feature",
  "properties": {
    "gn:admin1_code":"33",
    "gn:asciiname":"Aq Darak",
    "gn:country_code":"IR",
    "gn:dem":1592,
    "gn:feature_class":"P",
    "gn:feature_code":"PPL",
    "gn:name":"\u0100q Darak",
    "gn:population":0,
    "gn:timezone":"Asia/Tehran",
    "iso:country":"IR",
    "name:fas_x_preferred":[
        "\u0622\u0642 \u062f\u0631\u0643"
    ],
    "name:fas_x_variant":[
        "\u0100q Darak"
    ],
    "wof:name":"Aq Darak",
    "wof:placetype":"locality"
},
  "geometry": {"coordinates":[47.4564,37.2798],"type":"Point"}
}