{
  "type": "Feature",
  "properties": {
    "gn:admin1_code":"9.0",
    "gn:asciiname":"`Abd ol Mow'men",
    "gn:country_code":"IR",
    "gn:dem":1822,
    "gn:feature_class":"P",
    "gn:feature_code":"PPL",
    "gn:name":"\u2018Abd ol Mow\u2019men",
    "gn:population":0,
    "gn:timezone":"Asia/Tehran",
    "iso:country":"IR",
    "name:fas_x_preferred":[
        "\u0639\u0628\u062f\u0644 \u0641\u0648\u0645\u0646"
    ],
    "name:fas_x_variant":[
        "\u2018Abd ol Mo\u2019men",
        "\u2018Abdol F\u016bman",
        "\u0639\u0628\u062f \u0627\u0644\u0645\u0648\u0645\u0646"
    ],
    "name:und_x_variant":[
        "Bounna",
        "\u2018Abd ol Mow\u2019men",
        "Abdul Momin"
    ],
    "wof:name":"`Abd ol Mow'men",
    "wof:placetype":"locality"
},
  "geometry": {"coordinates":[48.34939,35.4318],"type":"Point"}
}