{
  "type": "Feature",
  "properties": {
    "gn:admin1_code":"43",
    "gn:asciiname":"Sangsar",
    "gn:country_code":"IR",
    "gn:dem":1029,
    "gn:feature_class":"P",
    "gn:feature_code":"PPL",
    "gn:name":"Sangs\u0101r",
    "gn:population":0,
    "gn:timezone":"Asia/Ashgabat",
    "iso:country":"IR",
    "name:fas_x_preferred":[
        "Sangs\u0101r"
    ],
    "name:fas_x_variant":[
        "\u0633\u0646\u06af \u0633\u0627\u0631"
    ],
    "wof:name":"Sangsar",
    "wof:placetype":"locality"
},
  "geometry": {"coordinates":[56.97689,38.21119],"type":"Point"}
}