{
  "type": "Feature",
  "properties": {
    "gn:admin1_code":"9",
    "gn:asciiname":"Qal`eh-ye Ajal Beyg",
    "gn:country_code":"IR",
    "gn:dem":1740,
    "gn:feature_class":"P",
    "gn:feature_code":"PPL",
    "gn:name":"Qal\u2018eh-ye Ajal Beyg",
    "gn:population":0,
    "gn:timezone":"Asia/Tehran",
    "iso:country":"IR",
    "name:fas_x_preferred":[
        "\u0642\u064e\u0644\u0639\u0650\u06c0 \u0627\u064e\u062c\u064e\u0644 \u0628\u0650\u064a\u06af"
    ],
    "name:fas_x_variant":[
        "\u0642\u064e\u0644\u0639\u0650\u06c0 \u0627\u064e\u062c\u064e\u0644\u0628\u064e\u06af",
        "\u0642\u064e\u0644\u0639\u0650\u0647 \u0627\u064e\u062c\u064e\u0644 \u0628\u0650\u064a\u06af",
        "Qal\u2018eh-ye Ajal Beyg"
    ],
    "name:und_x_variant":[
        "Qal\u2018eh Ajal Beyg",
        "Qal\u2018eh-ye Ajal Beq",
        "Qal\u2018eh-ye Ajalbag"
    ],
    "wof:name":"Qal`eh-ye Ajal Beyg",
    "wof:placetype":"locality"
},
  "geometry": {"coordinates":[48.41222,34.55889000000001],"type":"Point"}
}