{
  "type": "Feature",
  "properties": {
    "gn:admin1_code":"40.0",
    "gn:asciiname":"Mehrabad",
    "gn:country_code":"IR",
    "gn:dem":1321,
    "gn:feature_class":"P",
    "gn:feature_code":"PPL",
    "gn:name":"Mehr\u0101b\u0101d",
    "gn:population":0,
    "gn:timezone":"Asia/Tehran",
    "iso:country":"IR",
    "name:fas_x_preferred":[
        "Mehr\u0101b\u0101d"
    ],
    "wof:name":"Mehrabad",
    "wof:placetype":"locality"
},
  "geometry": {"coordinates":[57.0475,33.93167],"type":"Point"}
}