{
  "type": "Feature",
  "properties": {
    "gn:admin1_code":"4",
    "gn:asciiname":"Abyazabad",
    "gn:country_code":"IR",
    "gn:dem":1566,
    "gn:feature_class":"P",
    "gn:feature_code":"PPL",
    "gn:name":"Aby\u0101\u1e95\u0101b\u0101d",
    "gn:population":0,
    "gn:timezone":"Asia/Tehran",
    "iso:country":"IR",
    "name:fas_x_preferred":[
        "\u0627\u0628\u06cc\u0627\u0636 \u0622\u0628\u0627\u062f"
    ],
    "name:fas_x_variant":[
        "Aby\u0101\u1e95\u0101b\u0101d"
    ],
    "wof:name":"Abyazabad",
    "wof:placetype":"locality"
},
  "geometry": {"coordinates":[60.50337,28.8108],"type":"Point"}
}