{
  "type": "Feature",
  "properties": {
    "gn:admin1_code":"23",
    "gn:asciiname":"Rashnu",
    "gn:country_code":"IR",
    "gn:dem":1094,
    "gn:feature_class":"P",
    "gn:feature_code":"PPL",
    "gn:name":"Rashn\u016b",
    "gn:population":0,
    "gn:timezone":"Asia/Tehran",
    "iso:country":"IR",
    "name:diq_x_preferred":[
        "Re\u015fn"
    ],
    "name:fas_x_preferred":[
        "\u0631\u064e\u0634\u0646\u0648"
    ],
    "name:fas_x_variant":[
        "\u0631\u064e\u0634\u0646\u0648\u062f\u06cc",
        "\u0631\u0634\u0646\u0648\u062f\u06cc",
        "Rashn\u016b",
        "Rashn\u016bd\u012b",
        "\u0631\u0634\u0646\u0648",
        "\u0631\u0634\u0646"
    ],
    "name:jpn_x_preferred":[
        "\u30e9\u30b7\u30e5\u30cc"
    ],
    "name:mkd_x_preferred":[
        "\u0420\u0430\u0448\u043d\u0443"
    ],
    "name:nno_x_preferred":[
        "Rashnu"
    ],
    "name:pol_x_preferred":[
        "Rasznu"
    ],
    "name:ron_x_preferred":[
        "Ra\u0219naw"
    ],
    "name:rus_x_preferred":[
        "\u0420\u0430\u0448\u043d\u0443"
    ],
    "name:und_x_variant":[
        "Shan\u016b"
    ],
    "wof:name":"Rashnu",
    "wof:placetype":"locality"
},
  "geometry": {"coordinates":[47.53254,33.27455],"type":"Point"}
}