{
  "type": "Feature",
  "properties": {
    "gn:admin1_code":"23",
    "gn:asciiname":"Rashnu",
    "gn:country_code":"IR",
    "gn:dem":1094,
    "gn:feature_class":"P",
    "gn:feature_code":"PPL",
    "gn:name":"Rashn\u016b",
    "gn:population":0,
    "gn:timezone":"Asia/Tehran",
    "iso:country":"IR",
    "name:fas_x_preferred":[
        "\u0631\u064e\u0634\u0646\u0648"
    ],
    "name:fas_x_variant":[
        "\u0631\u064e\u0634\u0646\u0648\u062f\u06cc",
        "\u0631\u0634\u0646\u0648\u062f\u06cc",
        "Rashn\u016b",
        "Rashn\u016bd\u012b",
        "\u0631\u0634\u0646\u0648"
    ],
    "name:und_x_variant":[
        "Shan\u016b"
    ],
    "wof:name":"Rashnu",
    "wof:placetype":"locality"
},
  "geometry": {"coordinates":[47.53254,33.27455],"type":"Point"}
}