{
  "type": "Feature",
  "properties": {
    "gn:admin1_code":"23",
    "gn:asciiname":"Shams`ali",
    "gn:country_code":"IR",
    "gn:dem":1177,
    "gn:feature_class":"P",
    "gn:feature_code":"PPL",
    "gn:name":"Shams\u2018al\u012b",
    "gn:population":0,
    "gn:timezone":"Asia/Tehran",
    "iso:country":"IR",
    "name:fas_x_preferred":[
        "\u0634\u064e\u0645\u0633\u0639\u064e\u0644\u06cc"
    ],
    "name:fas_x_variant":[
        "Shams\u2018al\u012b"
    ],
    "wof:name":"Shams`ali",
    "wof:placetype":"locality"
},
  "geometry": {"coordinates":[47.85,33.68333],"type":"Point"}
}