{
  "type": "Feature",
  "properties": {
    "gn:admin1_code":"1.0",
    "gn:asciiname":"Khezrabad",
    "gn:country_code":"IR",
    "gn:dem":1287,
    "gn:feature_class":"P",
    "gn:feature_code":"PPL",
    "gn:name":"Khe\u1e95r\u0101b\u0101d",
    "gn:population":0,
    "gn:timezone":"Asia/Tehran",
    "iso:country":"IR",
    "name:ara_x_preferred":[
        "\u062e\u0636\u0631 \u0623\u0628\u0627\u062f"
    ],
    "name:azb_x_preferred":[
        "\u062e\u0636\u0631\u0622\u0628\u0627\u062f"
    ],
    "name:aze_x_preferred":[
        "X\u0131z\u0131rabad"
    ],
    "name:ceb_x_preferred":[
        "Khe\u1e95r\u0101b\u0101d"
    ],
    "name:fas_x_preferred":[
        "\u062e\u0636\u0631 \u0622\u0628\u0627\u062f"
    ],
    "name:fas_x_variant":[
        "Khe\u1e95r\u0101b\u0101d",
        "\u062e\u0636\u0631\u0622\u0628\u0627\u062f"
    ],
    "name:mlg_x_preferred":[
        "Khezrabad"
    ],
    "name:swe_x_preferred":[
        "Khe\u1e95r\u0101b\u0101d"
    ],
    "wof:name":"Khezrabad",
    "wof:placetype":"locality"
},
  "geometry": {"coordinates":[46.0023,36.8967],"type":"Point"}
}