{
  "type": "Feature",
  "properties": {
    "gn:admin1_code":"15",
    "gn:asciiname":"Sar Taf",
    "gn:country_code":"IR",
    "gn:dem":510,
    "gn:feature_class":"P",
    "gn:feature_code":"PPL",
    "gn:name":"Sar T\u0101f",
    "gn:population":0,
    "gn:timezone":"Asia/Tehran",
    "iso:country":"IR",
    "name:fas_x_preferred":[
        "\u0633\u0631 \u062a\u0627\u0641"
    ],
    "name:fas_x_variant":[
        "Sar T\u0101f"
    ],
    "wof:name":"Sar Taf",
    "wof:placetype":"locality"
},
  "geometry": {"coordinates":[48.47418,32.81197],"type":"Point"}
}