{
  "type": "Feature",
  "properties": {
    "gn:admin1_code":"40",
    "gn:asciiname":"Hoseynabad-e Navvab",
    "gn:country_code":"IR",
    "gn:dem":2091,
    "gn:feature_class":"P",
    "gn:feature_code":"PPL",
    "gn:name":"\u1e28oseyn\u0101b\u0101d-e Navv\u0101b",
    "gn:population":0,
    "gn:timezone":"Asia/Tehran",
    "iso:country":"IR",
    "name:fas_x_preferred":[
        "\u062d\u0633\u06cc\u0646 \u0622\u0628\u0627\u062f \u0646\u0648\u0627\u0628"
    ],
    "name:fas_x_variant":[
        "\u1e28oseyn\u0101b\u0101d-e Navv\u0101b",
        "\u062d\u0633\u06cc\u0646\u200c\u0622\u0628\u0627\u062f \u0646\u0648\u0627\u0628"
    ],
    "wof:name":"Hoseynabad-e Navvab",
    "wof:placetype":"locality"
},
  "geometry": {"coordinates":[53.9967,31.6857],"type":"Point"}
}