{
  "type": "Feature",
  "properties": {
    "gn:admin1_code":"4.0",
    "gn:asciiname":"Tulegi Ab",
    "gn:cc2":"IR",
    "gn:country_code":"IR",
    "gn:dem":996,
    "gn:feature_class":"P",
    "gn:feature_code":"PPL",
    "gn:name":"T\u016bleg\u012b \u0100b",
    "gn:population":0,
    "gn:timezone":"Asia/Tehran",
    "iso:country":"IR",
    "name:fas_x_preferred":[
        "T\u016bleg\u012b \u0100b"
    ],
    "name:und_x_variant":[
        "T\u016bl\u012b \u0100b"
    ],
    "wof:name":"Tulegi Ab",
    "wof:placetype":"locality"
},
  "geometry": {"coordinates":[61.0375,26.53306],"type":"Point"}
}