{
  "type": "Feature",
  "properties": {
    "gn:admin1_code":"35.0",
    "gn:asciiname":"Chenar Bon",
    "gn:country_code":"IR",
    "gn:dem":1068,
    "gn:feature_class":"P",
    "gn:feature_code":"PPL",
    "gn:name":"Chen\u0101r Bon",
    "gn:population":0,
    "gn:timezone":"Asia/Tehran",
    "iso:country":"IR",
    "name:fas_x_preferred":[
        "\u0686\u0650\u0646\u0627\u0631 \u0628\u064f\u0646\u0650 \u0632\u0627\u0631\u0650\u0645 \u0631\u0648\u062f"
    ],
    "name:fas_x_variant":[
        "Chen\u0101r Bon-e Z\u0101rem R\u016bd",
        "Chen\u0101r Bon",
        "\u0686\u0646\u0627\u0631 \u0628\u0646",
        "\u0686\u0646\u0627\u0631\u0628\u0646"
    ],
    "name:mzn_x_preferred":[
        "\u0686\u0646\u0627\u0631\u0628\u0646"
    ],
    "name:und_x_variant":[
        "Chen\u0101r Bon",
        "\u0686\u0646\u0627\u0631 \u0628\u0646"
    ],
    "wof:name":"Chenar Bon",
    "wof:placetype":"locality"
},
  "geometry": {"coordinates":[53.73884,36.42756],"type":"Point"}
}