{
  "type": "Feature",
  "properties": {
    "gn:admin1_code":"28.0",
    "gn:asciiname":"Tolombeh-ye Semsar",
    "gn:country_code":"IR",
    "gn:dem":1774,
    "gn:feature_class":"P",
    "gn:feature_code":"PPL",
    "gn:name":"Tolombeh-ye Sems\u0101r",
    "gn:population":0,
    "gn:timezone":"Asia/Tehran",
    "iso:country":"IR",
    "name:fas_x_preferred":[
        "Tolombeh-ye Sems\u0101r"
    ],
    "wof:name":"Tolombeh-ye Semsar",
    "wof:placetype":"locality"
},
  "geometry": {"coordinates":[51.64111,32.37361],"type":"Point"}
}