{
  "type": "Feature",
  "properties": {
    "gn:admin1_code":"28",
    "gn:asciiname":"Qasr-e Cham",
    "gn:country_code":"IR",
    "gn:dem":1933,
    "gn:feature_class":"P",
    "gn:feature_code":"PPL",
    "gn:name":"Qa\u015fr-e Cham",
    "gn:population":0,
    "gn:timezone":"Asia/Tehran",
    "iso:country":"IR",
    "name:fas_x_preferred":[
        "Qa\u015fr-e Cham"
    ],
    "name:fas_x_variant":[
        "\u0642\u0635\u0631 \u0686\u0645",
        "\u0642\u0635\u0631\u0686\u0645"
    ],
    "name:und_x_variant":[
        "\u2018A\u015fr-e Sh\u0101m",
        "Qa\u015fr-e Jam",
        "Asricham"
    ],
    "wof:name":"Qasr-e Cham",
    "wof:placetype":"locality"
},
  "geometry": {"coordinates":[51.81555,31.88698],"type":"Point"}
}