{
  "type": "Feature",
  "properties": {
    "gn:admin1_code":"0",
    "gn:asciiname":"Kal Aman",
    "gn:country_code":"IR",
    "gn:dem":861,
    "gn:feature_class":"P",
    "gn:feature_code":"PPL",
    "gn:name":"Kal Am\u0101n",
    "gn:population":0,
    "gn:timezone":"Asia/Tehran",
    "iso:country":"IR",
    "name:fas_x_preferred":[
        "\u06a9\u0644 \u0627\u0645\u0627\u0646"
    ],
    "name:fas_x_variant":[
        "Kal Am\u0101n"
    ],
    "wof:name":"Kal Aman",
    "wof:placetype":"locality"
},
  "geometry": {"coordinates":[57.6179,26.9387],"type":"Point"}
}