{
  "type": "Feature",
  "properties": {
    "gn:admin1_code":"4.0",
    "gn:asciiname":"Mandilan",
    "gn:country_code":"IR",
    "gn:dem":486,
    "gn:feature_class":"P",
    "gn:feature_code":"PPL",
    "gn:name":"Mand\u012bl\u0101n",
    "gn:population":0,
    "gn:timezone":"Asia/Tehran",
    "iso:country":"IR",
    "name:fas_x_preferred":[
        "\u0645\u0646\u062f\u06cc\u0644\u0627\u0646"
    ],
    "name:fas_x_variant":[
        "Mand\u012bl\u0101n",
        "\u0645\u0646\u062f\u06cc\u0644\u0627\u0646 \u0628\u0627\u0644\u0627"
    ],
    "name:und_x_variant":[
        "Mand\u012bl\u0101n",
        "Mand\u012bl\u0101n-e B\u0101l\u0101"
    ],
    "wof:name":"Mandilan",
    "wof:placetype":"locality"
},
  "geometry": {"coordinates":[61.74746999999999,31.0372],"type":"Point"}
}