{
  "type": "Feature",
  "properties": {
    "gn:admin1_code":"1",
    "gn:asciiname":"Zel Keh-ye `Olya",
    "gn:country_code":"IR",
    "gn:dem":795,
    "gn:feature_class":"P",
    "gn:feature_code":"PPL",
    "gn:name":"Z\u0304el Keh-ye \u2018Oly\u0101",
    "gn:population":0,
    "gn:timezone":"Asia/Tehran",
    "iso:country":"IR",
    "name:fas_x_preferred":[
        "Z\u0304el Keh-ye \u2018Oly\u0101"
    ],
    "name:fas_x_variant":[
        "\u0630\u0644 \u06a9\u0647 \u0639\u0644\u06cc\u0627",
        "\u0630\u064a\u0644\u064e\u0643\u0650\u06c0 \u0639\u064f\u0644\u064a\u0627",
        "Z\u0304\u012blakeh-ye \u2018Oly\u0101"
    ],
    "wof:name":"Zel Keh-ye `Olya",
    "wof:placetype":"locality"
},
  "geometry": {"coordinates":[44.8109,39.6038],"type":"Point"}
}