{
  "type": "Feature",
  "properties": {
    "gn:admin1_code":"4.0",
    "gn:asciiname":"Buk",
    "gn:country_code":"IR",
    "gn:dem":1526,
    "gn:feature_class":"P",
    "gn:feature_code":"PPL",
    "gn:name":"B\u016bk",
    "gn:population":0,
    "gn:timezone":"Asia/Tehran",
    "iso:country":"IR",
    "name:bel_x_preferred":[
        "\u0411\u0443\u043a"
    ],
    "name:ceb_x_preferred":[
        "Buk"
    ],
    "name:deu_x_preferred":[
        "Buk"
    ],
    "name:epo_x_preferred":[
        "Buk"
    ],
    "name:est_x_preferred":[
        "Buk"
    ],
    "name:fas_x_preferred":[
        "\u0628\u0648\u06a9"
    ],
    "name:fas_x_variant":[
        "B\u016bk",
        "B\u016bg"
    ],
    "name:fra_x_preferred":[
        "Buk"
    ],
    "name:jav_x_preferred":[
        "Buk"
    ],
    "name:lav_x_preferred":[
        "Buka"
    ],
    "name:msa_x_preferred":[
        "Buk"
    ],
    "name:nld_x_preferred":[
        "Buk"
    ],
    "name:pol_x_preferred":[
        "Buk"
    ],
    "name:por_x_preferred":[
        "Buk"
    ],
    "name:ron_x_preferred":[
        "Buk"
    ],
    "name:rus_x_preferred":[
        "\u0411\u0443\u043a"
    ],
    "name:srp_x_preferred":[
        "\u0411\u0443\u043a"
    ],
    "name:szl_x_preferred":[
        "Buk"
    ],
    "name:ukr_x_preferred":[
        "\u0411\u0443\u043a"
    ],
    "name:und_x_variant":[
        "Bag"
    ],
    "name:vie_x_preferred":[
        "Buk"
    ],
    "wof:name":"Buk",
    "wof:placetype":"locality"
},
  "geometry": {"coordinates":[60.3976,28.16131],"type":"Point"}
}