{
  "type": "Feature",
  "properties": {
    "gn:admin1_code":"4.0",
    "gn:asciiname":"Buk",
    "gn:country_code":"IR",
    "gn:dem":1526,
    "gn:feature_class":"P",
    "gn:feature_code":"PPL",
    "gn:name":"B\u016bk",
    "gn:population":0,
    "gn:timezone":"Asia/Tehran",
    "iso:country":"IR",
    "name:fas_x_preferred":[
        "\u0628\u0648\u06a9"
    ],
    "name:fas_x_variant":[
        "B\u016bk",
        "B\u016bg"
    ],
    "name:und_x_variant":[
        "B\u016bg",
        "Bag"
    ],
    "wof:name":"Buk",
    "wof:placetype":"locality"
},
  "geometry": {"coordinates":[60.3976,28.16131],"type":"Point"}
}