{
  "type": "Feature",
  "properties": {
    "gn:admin1_code":"8",
    "gn:asciiname":"Larzideh",
    "gn:country_code":"IR",
    "gn:dem":1057,
    "gn:feature_class":"P",
    "gn:feature_code":"PPL",
    "gn:name":"Larz\u012bdeh",
    "gn:population":0,
    "gn:timezone":"Asia/Tehran",
    "iso:country":"IR",
    "name:fas_x_preferred":[
        "\u0644\u0631\u0632\u06cc\u062f\u0647"
    ],
    "name:fas_x_variant":[
        "Larz\u012bdeh"
    ],
    "wof:name":"Larzideh",
    "wof:placetype":"locality"
},
  "geometry": {"coordinates":[48.6773,37.6485],"type":"Point"}
}