{
  "type": "Feature",
  "properties": {
    "gn:admin1_code":"8.0",
    "gn:asciiname":"Khulak",
    "gn:country_code":"IR",
    "gn:dem":-22,
    "gn:feature_class":"P",
    "gn:feature_code":"PPL",
    "gn:name":"Kh\u016blak",
    "gn:population":0,
    "gn:timezone":"Asia/Tehran",
    "iso:country":"IR",
    "name:ceb_x_preferred":[
        "Kh\u016blak"
    ],
    "name:fas_x_preferred":[
        "Kh\u016blak"
    ],
    "name:fas_x_variant":[
        "\u062e\u0648\u0644\u06a9"
    ],
    "name:msa_x_preferred":[
        "Khulak"
    ],
    "name:swe_x_preferred":[
        "Kh\u016blak"
    ],
    "name:ukr_x_preferred":[
        "\u0425\u0443\u043b\u0430\u043a"
    ],
    "wof:name":"Khulak",
    "wof:placetype":"locality"
},
  "geometry": {"coordinates":[49.49961,37.4707],"type":"Point"}
}