{
  "type": "Feature",
  "properties": {
    "gn:admin1_code":"11",
    "gn:asciiname":"Khodadadi",
    "gn:country_code":"IR",
    "gn:dem":1747,
    "gn:feature_class":"P",
    "gn:feature_code":"PPL",
    "gn:name":"Khod\u0101d\u0101d\u012b",
    "gn:population":0,
    "gn:timezone":"Asia/Tehran",
    "iso:country":"IR",
    "name:fas_x_preferred":[
        "\u062e\u062f\u0627\u062f\u0627\u062f\u06cc"
    ],
    "name:fas_x_variant":[
        "Khod\u0101d\u0101d",
        "Khod\u0101d\u0101d\u012b"
    ],
    "wof:name":"Khodadadi",
    "wof:placetype":"locality"
},
  "geometry": {"coordinates":[55.7563,28.7022],"type":"Point"}
}