{
  "type": "Feature",
  "properties": {
    "gn:admin1_code":"8",
    "gn:asciiname":"Darreh Zalu-ye Bala",
    "gn:country_code":"IR",
    "gn:dem":10,
    "gn:feature_class":"P",
    "gn:feature_code":"PPL",
    "gn:name":"Darreh Z\u0101l\u016b-ye B\u0101l\u0101",
    "gn:population":0,
    "gn:timezone":"Asia/Tehran",
    "iso:country":"IR",
    "name:fas_x_preferred":[
        "\u067e\u0646\u0628\u0647 \u0686\u0644\u0641\u062a"
    ],
    "name:fas_x_variant":[
        "\u062f\u0631\u0647 \u0632\u0627\u0644\u0648 \u0628\u0627\u0644\u0627"
    ],
    "name:und_x_variant":[
        "Panbeh Chalaft",
        "Darreh Z\u0101l\u016b-ye B\u0101l\u0101"
    ],
    "wof:name":"Darreh Zalu-ye Bala",
    "wof:placetype":"locality"
},
  "geometry": {"coordinates":[48.94377,37.75493],"type":"Point"}
}