{
  "type": "Feature",
  "properties": {
    "gn:admin1_code":"35.0",
    "gn:asciiname":"Ahangar Kola",
    "gn:country_code":"IR",
    "gn:dem":49,
    "gn:feature_class":"P",
    "gn:feature_code":"PPL",
    "gn:name":"\u0100hangar Kol\u0101",
    "gn:population":0,
    "gn:timezone":"Asia/Tehran",
    "iso:country":"IR",
    "name:fas_x_preferred":[
        "\u0622\u0647\u0646\u06af\u0631 \u0643\u0644\u0627"
    ],
    "name:fas_x_variant":[
        "\u0622\u0647\u064e\u0646\u06af\u064e\u0631 \u0643\u064e\u0644\u0627",
        "\u0100hangar Kol\u0101"
    ],
    "name:und_x_variant":[
        "\u0100hangar Kal\u0101"
    ],
    "wof:name":"Ahangar Kola",
    "wof:placetype":"locality"
},
  "geometry": {"coordinates":[52.65486,36.40664],"type":"Point"}
}