{
  "type": "Feature",
  "properties": {
    "gn:admin1_code":"7",
    "gn:asciiname":"Irajabad",
    "gn:country_code":"IR",
    "gn:dem":1895,
    "gn:feature_class":"P",
    "gn:feature_code":"PPL",
    "gn:name":"\u012araj\u0101b\u0101d",
    "gn:population":0,
    "gn:timezone":"Asia/Tehran",
    "iso:country":"IR",
    "name:fas_x_preferred":[
        "\u012araj\u0101b\u0101d"
    ],
    "name:fas_x_variant":[
        "\u0627\u06cc\u0631\u062c\u200c\u0622\u0628\u0627\u062f"
    ],
    "wof:name":"Irajabad",
    "wof:placetype":"locality"
},
  "geometry": {"coordinates":[52.10722,30.46944],"type":"Point"}
}