{
  "type": "Feature",
  "properties": {
    "gn:admin1_code":"33",
    "gn:asciiname":"Owtu Kandi",
    "gn:country_code":"IR",
    "gn:dem":931,
    "gn:feature_class":"P",
    "gn:feature_code":"PPL",
    "gn:name":"Owt\u016b Kand\u012b",
    "gn:population":0,
    "gn:timezone":"Asia/Tehran",
    "iso:country":"IR",
    "name:fas_x_preferred":[
        "\u0627\u0648\u062a\u0648 \u0643\u0646\u062f\u06cc"
    ],
    "name:fas_x_variant":[
        "Owt\u016b Kand\u012b"
    ],
    "wof:name":"Owtu Kandi",
    "wof:placetype":"locality"
},
  "geometry": {"coordinates":[47.2091,39.0412],"type":"Point"}
}