{
  "type": "Feature",
  "properties": {
    "gn:admin1_code":"23.0",
    "gn:asciiname":"Deh Sefid-e Vosta",
    "gn:country_code":"IR",
    "gn:dem":1525,
    "gn:feature_class":"P",
    "gn:feature_code":"PPL",
    "gn:name":"Deh Sef\u012bd-e Vos\u0163\u00e1",
    "gn:population":0,
    "gn:timezone":"Asia/Tehran",
    "iso:country":"IR",
    "name:fas_x_preferred":[
        "\u062f\u0647 \u0633\u0641\u06cc\u062f \u0648\u0633\u0637\u06cc"
    ],
    "name:fas_x_variant":[
        "\u062f\u0647\u200c\u0633\u0641\u06cc\u062f \u0648\u0633\u0637\u06cc"
    ],
    "name:und_x_variant":[
        "Deh Sef\u012bd-e Vos\u0163\u00e1"
    ],
    "wof:name":"Deh Sefid-e Vosta",
    "wof:placetype":"locality"
},
  "geometry": {"coordinates":[48.5375,33.50249],"type":"Point"}
}