{
  "type": "Feature",
  "properties": {
    "gn:admin1_code":"23",
    "gn:asciiname":"Seyyed `Azim Beyg",
    "gn:country_code":"IR",
    "gn:dem":1293,
    "gn:feature_class":"P",
    "gn:feature_code":"PPL",
    "gn:name":"Seyyed \u2018Az\u0327\u012bm Beyg",
    "gn:population":0,
    "gn:timezone":"Asia/Tehran",
    "iso:country":"IR",
    "name:fas_x_preferred":[
        "\u0633\u0650\u064a\u0650\u0651\u062f \u0639\u064e\u0638\u064a\u0645 \u0628\u0650\u064a\u06af"
    ],
    "name:fas_x_variant":[
        "Seyyed \u2018Az\u0327\u012bm Beyg"
    ],
    "wof:name":"Seyyed `Azim Beyg",
    "wof:placetype":"locality"
},
  "geometry": {"coordinates":[47.51667,33.75],"type":"Point"}
}