{
  "type": "Feature",
  "properties": {
    "gn:admin1_code":"4.0",
    "gn:asciiname":"Kelinkan",
    "gn:country_code":"IR",
    "gn:dem":789,
    "gn:feature_class":"P",
    "gn:feature_code":"PPL",
    "gn:name":"Kel\u012bnk\u0101n",
    "gn:population":0,
    "gn:timezone":"Asia/Tehran",
    "iso:country":"IR",
    "name:fas_x_preferred":[
        "Kel\u012bnk\u0101n"
    ],
    "name:fas_x_variant":[
        "Kel\u012bng\u0101n",
        "Gel\u012bnk\u0101n",
        "\u06a9\u0644\u06cc\u0646\u06a9\u0627\u0646"
    ],
    "name:und_x_variant":[
        "Kolang\u0101n",
        "Kal\u012bngan"
    ],
    "wof:name":"Kelinkan",
    "wof:placetype":"locality"
},
  "geometry": {"coordinates":[61.12239,26.44441],"type":"Point"}
}