{
  "type": "Feature",
  "properties": {
    "gn:admin1_code":"33.0",
    "gn:asciiname":"Mahalleh-ye `Ayeblu",
    "gn:country_code":"IR",
    "gn:dem":1348,
    "gn:feature_class":"P",
    "gn:feature_code":"PPL",
    "gn:name":"Ma\u1e29alleh-ye \u2018Ayebl\u016b",
    "gn:population":0,
    "gn:timezone":"Asia/Tehran",
    "iso:country":"IR",
    "name:fas_x_preferred":[
        "\u0645\u062d\u0644\u0647 \u0639\u064a\u0628\u0644\u0648"
    ],
    "name:und_x_variant":[
        "Ma\u1e29alleh-ye \u2018Ayebl\u016b"
    ],
    "wof:name":"Mahalleh-ye `Ayeblu",
    "wof:placetype":"locality"
},
  "geometry": {"coordinates":[45.73941,38.15262],"type":"Point"}
}