{
  "type": "Feature",
  "properties": {
    "gn:admin1_code":"23",
    "gn:asciiname":"Ebrahimabad",
    "gn:country_code":"IR",
    "gn:dem":882,
    "gn:feature_class":"P",
    "gn:feature_code":"PPL",
    "gn:name":"Ebr\u0101h\u012bm\u0101b\u0101d",
    "gn:population":0,
    "gn:timezone":"Asia/Tehran",
    "iso:country":"IR",
    "name:ara_x_preferred":[
        "\u0623\u0628\u0631\u0627\u0647\u064a\u0645 \u0623\u0628\u0627\u062f"
    ],
    "name:fas_x_preferred":[
        "\u0627\u0628\u0631\u0627\u0647\u06cc\u0645 \u0622\u0628\u0627\u062f"
    ],
    "name:fas_x_variant":[
        "Ebr\u0101h\u012bm\u0101b\u0101d",
        "\u06a9\u0648\u0634\u06a9\u06cc \u0622\u0645\u06cc\u0631\u0627\u0646",
        "\u0627\u0628\u0631\u0627\u0647\u06cc\u0645\u200c\u0622\u0628\u0627\u062f"
    ],
    "name:und_x_variant":[
        "K\u016bshk\u012b-ye Am\u012br\u0101n"
    ],
    "wof:name":"Ebrahimabad",
    "wof:placetype":"locality"
},
  "geometry": {"coordinates":[47.956,33.375],"type":"Point"}
}