{
  "type": "Feature",
  "properties": {
    "gn:admin1_code":"37",
    "gn:asciiname":"Nowchaman",
    "gn:country_code":"IR",
    "gn:dem":303,
    "gn:feature_class":"P",
    "gn:feature_code":"PPL",
    "gn:name":"Nowchaman",
    "gn:population":0,
    "gn:timezone":"Asia/Tehran",
    "iso:country":"IR",
    "name:ara_x_preferred":[
        "\u0646\u0648\u062a\u0634\u0645\u0646"
    ],
    "name:fas_x_preferred":[
        "\u0646\u0648\u0686\u0645\u0646"
    ],
    "name:msa_x_preferred":[
        "Now Chaman"
    ],
    "wof:name":"Nowchaman",
    "wof:placetype":"locality"
},
  "geometry": {"coordinates":[54.30495,36.76533],"type":"Point"}
}