{
  "type": "Feature",
  "properties": {
    "gn:admin1_code":"13",
    "gn:asciiname":"Qurbaghestan-e Sofla",
    "gn:country_code":"IR",
    "gn:dem":1293,
    "gn:feature_class":"P",
    "gn:feature_code":"PPL",
    "gn:name":"Q\u016brb\u0101ghest\u0101n-e Sofl\u00e1",
    "gn:population":0,
    "gn:timezone":"Asia/Tehran",
    "iso:country":"IR",
    "name:ceb_x_preferred":[
        "Q\u016brb\u0101ghest\u0101n-e Sofl\u00e1"
    ],
    "name:fas_x_preferred":[
        "\u0642\u0648\u0631 \u0628\u0627\u063a\u0633\u062a\u0627\u0646 \u0633\u0641\u0644\u06cc"
    ],
    "name:fas_x_variant":[
        "Q\u016brb\u0101ghest\u0101n-e Sofl\u00e1",
        "\u0642\u0631\u0647 \u0628\u0627\u063a\u0633\u062a\u0627\u0646 \u0633\u0641\u0644\u06cc",
        "\u0642\u0648\u0631\u0628\u0627\u063a\u0633\u062a\u0627\u0646 \u0633\u0641\u0644\u06cc"
    ],
    "name:pol_x_preferred":[
        "Ghurbaghestan-e Sofla"
    ],
    "name:swe_x_preferred":[
        "Q\u016brb\u0101ghest\u0101n-e Sofl\u00e1"
    ],
    "name:und_x_variant":[
        "Qarbaghast\u0101n-e P\u0101\u2019\u012bn",
        "Gherbaghestan\u00e9 Sofl\u00e1",
        "Qarab\u0101ghest\u0101n-e P\u0101\u2019\u012bn",
        "Qorb\u0101ghest\u0101n-e P\u0101\u2019\u012bn",
        "Qarb\u0101ghest\u0101n-e P\u0101\u2019\u012bn",
        "Qorb\u0101ghest\u0101n",
        "Gurbaghistan",
        "Qarah B\u0101ghest\u0101n-e Sofl\u00e1"
    ],
    "wof:name":"Qurbaghestan-e Sofla",
    "wof:placetype":"locality"
},
  "geometry": {"coordinates":[47.2222,34.2477],"type":"Point"}
}