{
  "type": "Feature",
  "properties": {
    "iso:country":"IR",
    "name:ara_x_preferred":[
        "\u0633\u0644\u0645\u0627\u0633"
    ],
    "name:arm_x_preferred":[
        "\u054d\u0561\u056c\u0574\u0561\u057d\u057f"
    ],
    "name:azb_x_preferred":[
        "\u0633\u0644\u0645\u0627\u0633"
    ],
    "name:aze_x_preferred":[
        "Salmas"
    ],
    "name:ben_x_preferred":[
        "\u09b8\u09be\u09b2\u09ae\u09be\u09b8"
    ],
    "name:cat_x_preferred":[
        "Salmas"
    ],
    "name:chi_x_preferred":[
        "\u6c99\u8d6b\u666e\u723e"
    ],
    "name:ckb_x_preferred":[
        "\u0633\u06d5\u06b5\u0645\u0627\u0633"
    ],
    "name:dut_x_preferred":[
        "Salmas"
    ],
    "name:eng_x_preferred":[
        "Salmas"
    ],
    "name:epo_x_preferred":[
        "Selmas"
    ],
    "name:fas_x_preferred":[
        "Salm\u0101s"
    ],
    "name:fas_x_variant":[
        "\u0633\u0644\u0645\u0627\u0633"
    ],
    "name:fre_x_preferred":[
        "Salmas"
    ],
    "name:ger_x_preferred":[
        "Salamas"
    ],
    "name:hin_x_preferred":[
        "\u0938\u093e\u0932\u092e\u093e\u0938"
    ],
    "name:ita_x_preferred":[
        "Salmas"
    ],
    "name:jpn_x_preferred":[
        "\u30b5\u30eb\u30de\u30b9"
    ],
    "name:kur_x_preferred":[
        "Dilmaqan"
    ],
    "name:may_x_preferred":[
        "Salmas"
    ],
    "name:mlg_x_preferred":[
        "Salmas"
    ],
    "name:per_x_preferred":[
        "\u0633\u0644\u0645\u0627\u0633"
    ],
    "name:pnb_x_preferred":[
        "\u0633\u0644\u0645\u0627\u0633"
    ],
    "name:pol_x_preferred":[
        "Salmas"
    ],
    "name:rum_x_preferred":[
        "Salmas"
    ],
    "name:rus_x_preferred":[
        "\u0421\u0430\u043b\u043c\u0430\u0441"
    ],
    "name:swe_x_preferred":[
        "Salm\u0101s"
    ],
    "name:tgk_x_preferred":[
        "\u0421\u0430\u043b\u043c\u043e\u0441"
    ],
    "name:tur_x_preferred":[
        "Salmas"
    ],
    "name:unk_x_variant":[
        "Shapur"
    ],
    "name:urd_x_preferred":[
        "\u0633\u0644\u0645\u0627\u0633"
    ],
    "qs:gn_country":"IR",
    "qs:gn_fcode":"PPL",
    "qs:gn_pop":81606,
    "qs:name":"Shahpur",
    "qs:name_adm0":"Iran",
    "qs:name_adm1":"Azarbayjan-e Gharbi",
    "qs:photos":86,
    "qs:photos_1k":17,
    "qs:photos_9k":1,
    "qs:photos_9r":3,
    "qs:photos_all":86,
    "qs:photos_sr":3,
    "qs:placetype":"Town",
    "qs:pop_sr":"8",
    "qs:woe_adm0":23424851,
    "wof:name":"Shahpur",
    "wof:placetype":"locality",
    "wof:population":81606
},
  "geometry": {"coordinates":[44.7653,38.1973],"type":"Point"}
}