{
  "type": "Feature",
  "properties": {
    "iso:country":"IR",
    "name:ara_x_preferred":[
        "\u0633\u0644\u0645\u0627\u0633"
    ],
    "name:azb_x_preferred":[
        "\u0633\u0644\u0645\u0627\u0633"
    ],
    "name:aze_x_preferred":[
        "Salmas"
    ],
    "name:ben_x_preferred":[
        "\u09b8\u09be\u09b2\u09ae\u09be\u09b8"
    ],
    "name:cat_x_preferred":[
        "Salmas"
    ],
    "name:ceb_x_preferred":[
        "Salm\u0101s"
    ],
    "name:ckb_x_preferred":[
        "\u0633\u06d5\u06b5\u0645\u0627\u0633"
    ],
    "name:deu_x_preferred":[
        "Salamas"
    ],
    "name:ell_x_preferred":[
        "\u03a3\u03b1\u03bb\u03bc\u03ac\u03c2"
    ],
    "name:eng_x_preferred":[
        "Salmas"
    ],
    "name:epo_x_preferred":[
        "Selmas"
    ],
    "name:fas_x_preferred":[
        "Salm\u0101s"
    ],
    "name:fas_x_variant":[
        "\u0633\u0644\u0645\u0627\u0633"
    ],
    "name:fra_x_preferred":[
        "Salmas"
    ],
    "name:gle_x_preferred":[
        "Salmas"
    ],
    "name:heb_x_preferred":[
        "\u05e1\u05dc\u05de\u05d0\u05e1"
    ],
    "name:hin_x_preferred":[
        "\u0938\u093e\u0932\u092e\u093e\u0938"
    ],
    "name:hun_x_preferred":[
        "Szalm\u00e1sz"
    ],
    "name:hye_x_preferred":[
        "\u054d\u0561\u056c\u0574\u0561\u057d\u057f"
    ],
    "name:hyw_x_preferred":[
        "\u054d\u0561\u056c\u0574\u0561\u057d\u057f"
    ],
    "name:ind_x_preferred":[
        "Salmas"
    ],
    "name:ita_x_preferred":[
        "Salmas"
    ],
    "name:jpn_x_preferred":[
        "\u30b5\u30eb\u30de\u30b9"
    ],
    "name:kur_x_preferred":[
        "Dilmaqan"
    ],
    "name:mlg_x_preferred":[
        "Salmas"
    ],
    "name:msa_x_preferred":[
        "Salmas"
    ],
    "name:mzn_x_preferred":[
        "\u0633\u0644\u0645\u0627\u0633"
    ],
    "name:nan_x_preferred":[
        "Salmas"
    ],
    "name:nld_x_preferred":[
        "Salmas"
    ],
    "name:pnb_x_preferred":[
        "\u0633\u0644\u0645\u0627\u0633"
    ],
    "name:pol_x_preferred":[
        "Salmas"
    ],
    "name:ron_x_preferred":[
        "Salmas"
    ],
    "name:rus_x_preferred":[
        "\u0421\u0430\u043b\u043c\u0430\u0441"
    ],
    "name:rus_x_variant":[
        "\u0421\u0435\u043b\u044c\u043c\u0430\u0441"
    ],
    "name:swe_x_preferred":[
        "Salm\u0101s"
    ],
    "name:tgk_x_preferred":[
        "\u0421\u0430\u043b\u043c\u043e\u0441"
    ],
    "name:tur_x_preferred":[
        "Salmas"
    ],
    "name:und_x_variant":[
        "Shapur"
    ],
    "name:urd_x_preferred":[
        "\u0633\u0644\u0645\u0627\u0633"
    ],
    "name:zho_x_preferred":[
        "\u6c99\u8d6b\u666e\u723e"
    ],
    "qs:gn_country":"IR",
    "qs:gn_fcode":"PPL",
    "qs:gn_pop":81606,
    "qs:name":"Shahpur",
    "qs:name_adm0":"Iran",
    "qs:name_adm1":"Azarbayjan-e Gharbi",
    "qs:photos":86,
    "qs:photos_1k":17,
    "qs:photos_9k":1,
    "qs:photos_9r":3,
    "qs:photos_all":86,
    "qs:photos_sr":3,
    "qs:placetype":"Town",
    "qs:pop_sr":"8",
    "qs:woe_adm0":23424851,
    "wof:name":"Shahpur",
    "wof:placetype":"locality",
    "wof:population":81606
},
  "geometry": {"coordinates":[44.7653,38.1973],"type":"Point"}
}