{
  "type": "Feature",
  "properties": {
    "gn:admin1_code":"33.0",
    "gn:asciiname":"Heshmatabad",
    "gn:country_code":"IR",
    "gn:dem":2074,
    "gn:feature_class":"P",
    "gn:feature_code":"PPL",
    "gn:name":"\u1e28eshmat\u0101b\u0101d",
    "gn:population":0,
    "gn:timezone":"Asia/Tehran",
    "iso:country":"IR",
    "name:fas_x_preferred":[
        "\u062d\u0634\u0645\u062a \u0622\u0628\u0627\u062f"
    ],
    "name:fas_x_variant":[
        "\u1e28eshmat\u0101b\u0101d"
    ],
    "wof:name":"Heshmatabad",
    "wof:placetype":"locality"
},
  "geometry": {"coordinates":[46.48338,38.36847],"type":"Point"}
}