{
  "type": "Feature",
  "properties": {
    "gn:admin1_code":"10.0",
    "gn:asciiname":"Palangerd",
    "gn:country_code":"IR",
    "gn:dem":1137,
    "gn:feature_class":"P",
    "gn:feature_code":"PPL",
    "gn:name":"Palangerd",
    "gn:population":0,
    "gn:timezone":"Asia/Tehran",
    "iso:country":"IR",
    "name:ara_x_preferred":[
        "\u0628\u0644\u0646\u063a\u0631\u062f"
    ],
    "name:ceb_x_preferred":[
        "Palangerd"
    ],
    "name:fas_x_preferred":[
        "\u067e\u0644\u0646\u06af\u0631\u062f"
    ],
    "name:msa_x_preferred":[
        "Palangerd"
    ],
    "wof:name":"Palangerd",
    "wof:placetype":"locality"
},
  "geometry": {"coordinates":[46.2729,33.8416],"type":"Point"}
}