{
  "type": "Feature",
  "properties": {
    "gn:admin1_code":"7",
    "gn:asciiname":"Havayjan",
    "gn:country_code":"IR",
    "gn:dem":2013,
    "gn:feature_class":"P",
    "gn:feature_code":"PPL",
    "gn:name":"Hav\u0101yj\u0101n",
    "gn:population":0,
    "gn:timezone":"Asia/Tehran",
    "iso:country":"IR",
    "name:fas_x_preferred":[
        "\u0647\u0631\u0627\u06cc\u062c\u0627\u0646"
    ],
    "name:fas_x_variant":[
        "Har\u0101yj\u0101n-e B\u0101l\u0101",
        "Har\u0101yj\u0101n",
        "\u0647\u0648\u0627\u06cc\u062c\u0627\u0646"
    ],
    "name:msa_x_preferred":[
        "Harayjan"
    ],
    "name:und_x_variant":[
        "Har\u012bj\u0101n",
        "Hav\u0101yj\u0101n",
        "Har\u0101yj\u0101n-e \u2018Olya"
    ],
    "wof:name":"Havayjan",
    "wof:placetype":"locality"
},
  "geometry": {"coordinates":[52.0535,29.9986],"type":"Point"}
}