{
  "type": "Feature",
  "properties": {
    "gn:admin1_code":"26",
    "gn:asciiname":"Baba Yurd",
    "gn:country_code":"IR",
    "gn:dem":2500,
    "gn:feature_class":"P",
    "gn:feature_code":"PPL",
    "gn:name":"B\u0101b\u0101 Y\u016brd",
    "gn:population":0,
    "gn:timezone":"Asia/Tehran",
    "iso:country":"IR",
    "name:fas_x_preferred":[
        "\u0628\u0627\u0628\u0627 \u064a\u0648\u0631\u062f"
    ],
    "name:fas_x_variant":[
        "B\u0101b\u0101 Y\u016brd"
    ],
    "wof:name":"Baba Yurd",
    "wof:placetype":"locality"
},
  "geometry": {"coordinates":[52.94154,35.82354],"type":"Point"}
}