{
  "type": "Feature",
  "properties": {
    "gn:admin1_code":"28",
    "gn:asciiname":"Qurtan",
    "gn:country_code":"IR",
    "gn:dem":1482,
    "gn:feature_class":"P",
    "gn:feature_code":"PPL",
    "gn:name":"Q\u016brt\u0101n",
    "gn:population":0,
    "gn:timezone":"Asia/Tehran",
    "iso:country":"IR",
    "name:fas_x_preferred":[
        "\u0642\u0648\u0631\u062a\u0627\u0646"
    ],
    "name:fas_x_variant":[
        "Q\u016brt\u0101n"
    ],
    "name:und_x_variant":[
        "Ur\u016bn",
        "Ghoortan",
        "Qurt\u016bn"
    ],
    "wof:name":"Qurtan",
    "wof:placetype":"locality"
},
  "geometry": {"coordinates":[52.5592,32.4515],"type":"Point"}
}