{
  "type": "Feature",
  "properties": {
    "gn:admin1_code":"5",
    "gn:asciiname":"Qashkamari",
    "gn:country_code":"IR",
    "gn:dem":1500,
    "gn:feature_class":"P",
    "gn:feature_code":"PPL",
    "gn:name":"Q\u0101shkamar\u012b",
    "gn:population":0,
    "gn:timezone":"Asia/Tehran",
    "iso:country":"IR",
    "name:fas_x_preferred":[
        "Q\u0101shkamar\u012b"
    ],
    "name:fas_x_variant":[
        "\u0642\u0627\u0634 \u06a9\u0645\u0631\u06cc"
    ],
    "wof:name":"Qashkamari",
    "wof:placetype":"locality"
},
  "geometry": {"coordinates":[50.52256,31.06489],"type":"Point"}
}