{
  "type": "Feature",
  "properties": {
    "gn:admin1_code":"11",
    "gn:asciiname":"Sar Rig",
    "gn:cc2":"IR",
    "gn:country_code":"IR",
    "gn:dem":6,
    "gn:feature_class":"P",
    "gn:feature_code":"PPL",
    "gn:name":"Sar R\u012bg",
    "gn:population":0,
    "gn:timezone":"Asia/Tehran",
    "iso:country":"IR",
    "name:fas_x_preferred":[
        "\u0633\u064e\u0631 \u0631\u064a\u06af"
    ],
    "name:fas_x_variant":[
        "\u0633\u064e\u0631 \u0631\u064a\u06af\u0627\u0646",
        "Sar R\u012bg"
    ],
    "name:und_x_variant":[
        "Sar R\u012bg\u0101n"
    ],
    "wof:name":"Sar Rig",
    "wof:placetype":"locality"
},
  "geometry": {"coordinates":[56.90306,27.12444],"type":"Point"}
}