{
  "type": "Feature",
  "properties": {
    "gn:admin1_code":"23",
    "gn:asciiname":"Sabur",
    "gn:country_code":"IR",
    "gn:dem":1290,
    "gn:feature_class":"P",
    "gn:feature_code":"PPL",
    "gn:name":"\u015eab\u016br",
    "gn:population":0,
    "gn:timezone":"Asia/Tehran",
    "iso:country":"IR",
    "name:ceb_x_preferred":[
        "\u015eab\u016br"
    ],
    "name:fas_x_preferred":[
        "\u015eab\u016br"
    ],
    "name:fas_x_variant":[
        "\u0635\u0628\u0648\u0631"
    ],
    "name:swe_x_preferred":[
        "\u015eab\u016br"
    ],
    "name:und_x_variant":[
        "Sab\u016br\u012b"
    ],
    "wof:name":"Sabur",
    "wof:placetype":"locality"
},
  "geometry": {"coordinates":[48.2573,33.4108],"type":"Point"}
}