{
  "type": "Feature",
  "properties": {
    "gn:admin1_code":"8.0",
    "gn:asciiname":"Jirkuyeh-ye `Alam",
    "gn:country_code":"IR",
    "gn:dem":-15,
    "gn:feature_class":"P",
    "gn:feature_code":"PPL",
    "gn:name":"J\u012brk\u016byeh-ye \u2018Alam",
    "gn:population":0,
    "gn:timezone":"Asia/Tehran",
    "iso:country":"IR",
    "name:fas_x_preferred":[
        "J\u012brk\u016byeh-ye \u2018Alam"
    ],
    "name:fas_x_variant":[
        "\u062c\u06cc\u0631\u06a9\u0648\u06cc\u0647 \u0639\u0644\u0645"
    ],
    "name:und_x_variant":[
        "\u062c\u06cc\u0631\u06a9\u0648\u06cc\u0647 \u0639\u0644\u0645"
    ],
    "wof:name":"Jirkuyeh-ye `Alam",
    "wof:placetype":"locality"
},
  "geometry": {"coordinates":[49.782,37.38183],"type":"Point"}
}