{
  "type": "Feature",
  "properties": {
    "gn:admin1_code":"33.0",
    "gn:asciiname":"Avan Sar",
    "gn:country_code":"IR",
    "gn:dem":1710,
    "gn:feature_class":"P",
    "gn:feature_code":"PPL",
    "gn:name":"\u0100v\u0101n Sar",
    "gn:population":0,
    "gn:timezone":"Asia/Tehran",
    "iso:country":"IR",
    "name:azb_x_preferred":[
        "\u0622\u0648\u0627\u0646\u0633\u0631"
    ],
    "name:fas_x_preferred":[
        "\u0622\u0648\u0627\u0646 \u0633\u0631"
    ],
    "name:fas_x_variant":[
        "\u0100v\u0101n Sar",
        "\u0622\u0648\u0627\u0646\u0633\u0631"
    ],
    "name:msa_x_preferred":[
        "Avan Sar"
    ],
    "name:und_x_variant":[
        "Amvey"
    ],
    "wof:name":"Avan Sar",
    "wof:placetype":"locality"
},
  "geometry": {"coordinates":[46.43986,38.69559],"type":"Point"}
}