{
  "type": "Feature",
  "properties": {
    "gn:admin1_code":"8.0",
    "gn:asciiname":"Halu Sara-ye Bala",
    "gn:cc2":"IR",
    "gn:country_code":"IR",
    "gn:dem":77,
    "gn:feature_class":"P",
    "gn:feature_code":"PPL",
    "gn:name":"Hal\u016b Sar\u0101-ye B\u0101l\u0101",
    "gn:population":0,
    "gn:timezone":"Asia/Tehran",
    "iso:country":"IR",
    "name:fas_x_preferred":[
        "Hal\u016b Sar\u0101-ye B\u0101l\u0101"
    ],
    "name:und_x_variant":[
        "B\u0101b\u0101 Hol\u016b Sar\u0101"
    ],
    "wof:name":"Halu Sara-ye Bala",
    "wof:placetype":"locality"
},
  "geometry": {"coordinates":[50.235,37.0375],"type":"Point"}
}