{
  "type": "Feature",
  "properties": {
    "gn:admin1_code":"33",
    "gn:asciiname":"Qezel Qiyeh",
    "gn:country_code":"IR",
    "gn:dem":2110,
    "gn:feature_class":"P",
    "gn:feature_code":"PPL",
    "gn:name":"Qezel Q\u012byeh",
    "gn:population":0,
    "gn:timezone":"Asia/Tehran",
    "iso:country":"IR",
    "name:fas_x_preferred":[
        "\u0642\u0632\u0644 \u0642\u06cc\u0647"
    ],
    "name:und_x_variant":[
        "Qezel Qayeh",
        "Qezel Q\u012byeh"
    ],
    "wof:name":"Qezel Qiyeh",
    "wof:placetype":"locality"
},
  "geometry": {"coordinates":[47.5991,38.0637],"type":"Point"}
}