{
  "type": "Feature",
  "properties": {
    "gn:admin1_code":"32",
    "gn:asciiname":"Hamdollahabad",
    "gn:country_code":"IR",
    "gn:dem":31,
    "gn:feature_class":"P",
    "gn:feature_code":"PPL",
    "gn:name":"\u1e28amdoll\u0101h\u0101b\u0101d",
    "gn:population":0,
    "gn:timezone":"Asia/Tehran",
    "iso:country":"IR",
    "name:azb_x_preferred":[
        "\u062d\u0645\u062f\u0648\u0627\u0644\u0644\u0647 \u0622\u0628\u0627\u062f"
    ],
    "name:ceb_x_preferred":[
        "\u1e28amdoll\u0101h\u0101b\u0101d"
    ],
    "name:fas_x_preferred":[
        "\u1e28amdoll\u0101h\u0101b\u0101d"
    ],
    "name:fas_x_variant":[
        "\u062d\u064e\u0645\u062f\u064f\u0644\u0651\u0627\u0647 \u0622\u0628\u0627\u062f",
        "\u062d\u0645\u062f\u0627\u0644\u0647\u200c\u0622\u0628\u0627\u062f"
    ],
    "name:msa_x_preferred":[
        "Hamdollahabad"
    ],
    "name:mzn_x_preferred":[
        "\u062d\u0645\u062f\u0627\u0644\u0647\u200c\u0622\u0628\u0627\u062f"
    ],
    "name:swe_x_preferred":[
        "\u1e28amdoll\u0101h\u0101b\u0101d"
    ],
    "wof:name":"Hamdollahabad",
    "wof:placetype":"locality"
},
  "geometry": {"coordinates":[48.05,39.63333],"type":"Point"}
}