{
  "type": "Feature",
  "properties": {
    "gn:admin1_code":"1.0",
    "gn:asciiname":"Deh Mansur",
    "gn:country_code":"IR",
    "gn:dem":1284,
    "gn:feature_class":"P",
    "gn:feature_code":"PPL",
    "gn:name":"Deh Man\u015f\u016br",
    "gn:population":0,
    "gn:timezone":"Asia/Tehran",
    "iso:country":"IR",
    "name:fas_x_preferred":[
        "\u062f\u0650\u0647 \u0645\u064e\u0646\u0635\u0648\u0631"
    ],
    "name:fas_x_variant":[
        "\u062f\u0647 \u0645\u0646\u0635\u0648\u0631",
        "Deh Man\u015f\u016br"
    ],
    "wof:name":"Deh Mansur",
    "wof:placetype":"locality"
},
  "geometry": {"coordinates":[45.9897,36.9541],"type":"Point"}
}