{
  "type": "Feature",
  "properties": {
    "gn:admin1_code":"7",
    "gn:asciiname":"Mahalleh-ye Akbari",
    "gn:country_code":"IR",
    "gn:dem":2011,
    "gn:feature_class":"P",
    "gn:feature_code":"PPL",
    "gn:name":"Ma\u1e29alleh-ye Akbar\u012b",
    "gn:population":0,
    "gn:timezone":"Asia/Tehran",
    "iso:country":"IR",
    "name:ara_x_preferred":[
        "\u0645\u062d\u0644\u0629 \u0623\u06a9\u0628\u0631\u064a"
    ],
    "name:fas_x_preferred":[
        "\u0627\u06a9\u0628\u0631\u06cc"
    ],
    "name:fas_x_variant":[
        "Ma\u1e29alleh-ye Akbar\u012b",
        "Akbar\u012b",
        "\u0645\u062d\u0644\u0647 \u0627\u06a9\u0628\u0631\u06cc"
    ],
    "name:msa_x_preferred":[
        "Mahalleh-ye Akbari"
    ],
    "wof:name":"Mahalleh-ye Akbari",
    "wof:placetype":"locality"
},
  "geometry": {"coordinates":[53.8202,30.336],"type":"Point"}
}