{
  "type": "Feature",
  "properties": {
    "gn:admin1_code":"3.0",
    "gn:asciiname":"Kal Mishan",
    "gn:country_code":"IR",
    "gn:dem":1569,
    "gn:feature_class":"P",
    "gn:feature_code":"PPL",
    "gn:name":"Kal M\u012bsh\u0101n",
    "gn:population":0,
    "gn:timezone":"Asia/Tehran",
    "iso:country":"IR",
    "name:fas_x_preferred":[
        "Kal M\u012bsh\u0101n"
    ],
    "name:fas_x_variant":[
        "\u06a9\u0644 \u0645\u06cc\u0634\u0627\u0646"
    ],
    "name:und_x_variant":[
        "\u06a9\u0644 \u0645\u06cc\u0634\u0627\u0646"
    ],
    "wof:name":"Kal Mishan",
    "wof:placetype":"locality"
},
  "geometry": {"coordinates":[50.47389,31.66375],"type":"Point"}
}