{
  "type": "Feature",
  "properties": {
    "gn:admin1_code":"13",
    "gn:asciiname":"Qal`eh-ye Khoda Morovvat Khan",
    "gn:country_code":"IR",
    "gn:dem":1329,
    "gn:feature_class":"P",
    "gn:feature_code":"PPL",
    "gn:name":"Qal\u2018eh-ye Khod\u0101 Morovvat Kh\u0101n",
    "gn:population":0,
    "gn:timezone":"Asia/Tehran",
    "iso:country":"IR",
    "name:fas_x_preferred":[
        "\u0642\u0644\u0639\u0647 \u062e\u062f\u0627 \u0645\u0631\u0648\u0651\u062a \u062e\u0627\u0646"
    ],
    "name:fas_x_variant":[
        "Qal\u2018eh-ye Khod\u0101 Morovvatkh\u0101n",
        "Qal\u2018eh-ye Khod\u0101 Morovvat Kh\u0101n"
    ],
    "name:und_x_variant":[
        "Qal\u2018a Khamrud Khan",
        "Qal\u2018eh-ye Khod\u0101 Morovat Kh\u0101n",
        "Qal\u2018eh Khod\u0101 Morovvat Kh\u0101n",
        "Qal\u2018eh Khamrud Khan"
    ],
    "wof:name":"Qal`eh-ye Khoda Morovvat Khan",
    "wof:placetype":"locality"
},
  "geometry": {"coordinates":[46.5952,34.596],"type":"Point"}
}