{
  "type": "Feature",
  "properties": {
    "gn:admin1_code":"42",
    "gn:asciiname":"Shahr-e Kohneh",
    "gn:country_code":"IR",
    "gn:dem":1331,
    "gn:feature_class":"P",
    "gn:feature_code":"PPL",
    "gn:name":"Shahr-e Kohneh",
    "gn:population":0,
    "gn:timezone":"Asia/Tehran",
    "iso:country":"IR",
    "name:fas_x_preferred":[
        "\u0634\u0647\u0631 \u06a9\u0647\u0646\u0647"
    ],
    "wof:name":"Shahr-e Kohneh",
    "wof:placetype":"locality"
},
  "geometry": {"coordinates":[58.92719,35.82148],"type":"Point"}
}