{
  "type": "Feature",
  "properties": {
    "gn:admin1_code":"15.0",
    "gn:asciiname":"Takht-e Sabz",
    "gn:country_code":"IR",
    "gn:dem":1057,
    "gn:feature_class":"P",
    "gn:feature_code":"PPL",
    "gn:name":"Takht-e Sabz",
    "gn:population":0,
    "gn:timezone":"Asia/Tehran",
    "iso:country":"IR",
    "name:fas_x_preferred":[
        "\u062a\u062e\u062a \u0633\u0631"
    ],
    "name:fas_x_variant":[
        "\u062a\u062e\u062a \u0633\u0628\u0632"
    ],
    "name:und_x_variant":[
        "Takht-e Sar",
        "\u062a\u062e\u062a \u0633\u0631",
        "Takht-e Sabz-e Vos\u0163\u00e1",
        "Takht-e Sabz"
    ],
    "wof:name":"Takht-e Sabz",
    "wof:placetype":"locality"
},
  "geometry": {"coordinates":[49.69891,32.15805],"type":"Point"}
}