{
  "type": "Feature",
  "properties": {
    "gn:admin1_code":"35.0",
    "gn:asciiname":"`Afi",
    "gn:country_code":"IR",
    "gn:dem":38,
    "gn:feature_class":"P",
    "gn:feature_code":"PPL",
    "gn:name":"\u2018Af\u012b",
    "gn:population":0,
    "gn:timezone":"Asia/Tehran",
    "iso:country":"IR",
    "name:fas_x_preferred":[
        "\u0639\u064e\u0641\u06cc"
    ],
    "name:und_x_variant":[
        "\u2018Af\u012b"
    ],
    "wof:name":"`Afi",
    "wof:placetype":"locality"
},
  "geometry": {"coordinates":[53.60167,36.69],"type":"Point"}
}