{
  "type": "Feature",
  "properties": {
    "gn:admin1_code":"13",
    "gn:asciiname":"Puyan",
    "gn:country_code":"IR",
    "gn:dem":1759,
    "gn:feature_class":"P",
    "gn:feature_code":"PPL",
    "gn:name":"P\u016by\u0101n",
    "gn:population":0,
    "gn:timezone":"Asia/Tehran",
    "iso:country":"IR",
    "name:fas_x_preferred":[
        "\u067e\u0648\u06cc\u0627\u0646"
    ],
    "name:fas_x_variant":[
        "P\u016by\u0101n"
    ],
    "wof:name":"Puyan",
    "wof:placetype":"locality"
},
  "geometry": {"coordinates":[47.2939,34.7022],"type":"Point"}
}