{
  "type": "Feature",
  "properties": {
    "gn:admin1_code":"4.0",
    "gn:asciiname":"Alarri",
    "gn:country_code":"IR",
    "gn:dem":480,
    "gn:feature_class":"P",
    "gn:feature_code":"PPL",
    "gn:name":"Alarr\u012b",
    "gn:population":0,
    "gn:timezone":"Asia/Tehran",
    "iso:country":"IR",
    "name:fas_x_preferred":[
        "Alarr\u012b"
    ],
    "name:fas_x_variant":[
        "\u0627\u0644\u0631\u0651\u06cc",
        "Allar\u012b",
        "\u062f\u0647 \u0627\u0644\u0631\u06cc"
    ],
    "name:und_x_variant":[
        "Deh-e Alarr\u012b"
    ],
    "wof:name":"Alarri",
    "wof:placetype":"locality"
},
  "geometry": {"coordinates":[61.4203,31.0702],"type":"Point"}
}