{
  "type": "Feature",
  "properties": {
    "gn:admin1_code":"15.0",
    "gn:asciiname":"`Eyn ol Majbil",
    "gn:country_code":"IR",
    "gn:dem":68,
    "gn:feature_class":"P",
    "gn:feature_code":"PPL",
    "gn:name":"\u2018Eyn ol Majb\u012bl",
    "gn:population":0,
    "gn:timezone":"Asia/Tehran",
    "iso:country":"IR",
    "name:fas_x_preferred":[
        "\u0639\u06cc\u0646 \u0627\u0644\u0645\u062c\u06cc\u0628\u0644"
    ],
    "name:fas_x_variant":[
        "\u2018Eyn ol Mejbel",
        "\u2018Eyn ol Mej\u012bbel",
        "\u0639\u06cc\u0646 \u0627\u0644\u0645\u062c\u0628\u06cc\u0644"
    ],
    "name:und_x_variant":[
        "\u2018Eyn ol Mej\u012bl",
        "Mojeyyel",
        "Mojeybel",
        "\u2018Eyn ol Majb\u012bl"
    ],
    "wof:name":"`Eyn ol Majbil",
    "wof:placetype":"locality"
},
  "geometry": {"coordinates":[49.21957,31.37417],"type":"Point"}
}