{
  "type": "Feature",
  "properties": {
    "gn:admin1_code":"35",
    "gn:asciiname":"Owrim Rudbar",
    "gn:country_code":"IR",
    "gn:dem":1179,
    "gn:feature_class":"P",
    "gn:feature_code":"PPL",
    "gn:name":"Owr\u012bm R\u016bdb\u0101r",
    "gn:population":0,
    "gn:timezone":"Asia/Tehran",
    "iso:country":"IR",
    "name:ceb_x_preferred":[
        "Owr\u012bm R\u016bdb\u0101r"
    ],
    "name:fas_x_preferred":[
        "\u0648\u0631\u064a\u0645 \u0631\u0648\u062f\u0628\u0627\u0631"
    ],
    "name:fas_x_variant":[
        "\u0627\u0648\u0631\u064a\u0645 \u0631\u0648\u062f\u0628\u0627\u0631",
        "\u016ar\u012bm R\u016bdb\u0101r",
        "Owr\u012bm R\u016bdb\u0101r",
        "\u0627\u0648\u0631\u06cc\u0645\u200c\u0631\u0648\u062f\u0628\u0627\u0631"
    ],
    "name:swe_x_preferred":[
        "Owr\u012bm R\u016bdb\u0101r"
    ],
    "wof:name":"Owrim Rudbar",
    "wof:placetype":"locality"
},
  "geometry": {"coordinates":[53.00299,35.94709],"type":"Point"}
}