{
  "type": "Feature",
  "properties": {
    "gn:admin1_code":"37.0",
    "gn:asciiname":"Qamar Dowlatshahi",
    "gn:country_code":"IR",
    "gn:dem":116,
    "gn:feature_class":"P",
    "gn:feature_code":"PPL",
    "gn:name":"Qamar Dowlatsh\u0101h\u012b",
    "gn:population":0,
    "gn:timezone":"Asia/Tehran",
    "iso:country":"IR",
    "name:fas_x_preferred":[
        "\u0642\u0645\u0631 \u062f\u0648\u0644\u062a\u0634\u0627\u0647\u06cc"
    ],
    "name:und_x_variant":[
        "Qamar Dowlatsh\u0101h\u012b"
    ],
    "wof:name":"Qamar Dowlatshahi",
    "wof:placetype":"locality"
},
  "geometry": {"coordinates":[55.10158000000001,37.04102],"type":"Point"}
}