{
  "type": "Feature",
  "properties": {
    "gn:admin1_code":"29",
    "gn:asciiname":"Sohran-e Sofla",
    "gn:country_code":"IR",
    "gn:dem":508,
    "gn:feature_class":"P",
    "gn:feature_code":"PPL",
    "gn:name":"Sohr\u0101n-e Sofl\u00e1",
    "gn:population":0,
    "gn:timezone":"Asia/Tehran",
    "iso:country":"IR",
    "name:ceb_x_preferred":[
        "Sohr\u0101n-e Sofl\u00e1"
    ],
    "name:fas_x_preferred":[
        "\u0633\u0647\u0631\u0627\u0646 \u0633\u0641\u0644\u06cc"
    ],
    "name:fas_x_variant":[
        "Sohr\u0101n-e P\u0101\u2019\u012bn",
        "Sohr\u0101n-e Sofl\u00e1",
        "\u0633\u0647\u0631\u0627\u0646 \u0633\u0641\u0644\u06cc \u0633\u0647\u0631\u0648\u0646 \u067e\u0627\u06cc\u06cc\u0646"
    ],
    "name:swe_x_preferred":[
        "Sohr\u0101n-e Sofl\u00e1"
    ],
    "name:und_x_variant":[
        "Pa\u2019\u012bn Sahr\u016bn",
        "Sohr\u0101n",
        "P\u0101\u2019\u012bn Sahr\u0101n",
        "Sohr\u016bn",
        "P\u0101\u2019\u012bn Sohr\u016bn"
    ],
    "wof:name":"Sohran-e Sofla",
    "wof:placetype":"locality"
},
  "geometry": {"coordinates":[57.8451,28.122],"type":"Point"}
}