{
  "type": "Feature",
  "properties": {
    "gn:admin1_code":"11.0",
    "gn:asciiname":"Chah Lambur",
    "gn:country_code":"IR",
    "gn:dem":52,
    "gn:feature_class":"P",
    "gn:feature_code":"PPL",
    "gn:name":"Ch\u0101h Lamb\u016br",
    "gn:population":0,
    "gn:timezone":"Asia/Tehran",
    "iso:country":"IR",
    "name:fas_x_preferred":[
        "\u0686\u0627\u0647 \u0644\u0645\u0628\u0648\u0631"
    ],
    "name:und_x_variant":[
        "Ch\u0101h Lamb\u016br"
    ],
    "wof:name":"Chah Lambur",
    "wof:placetype":"locality"
},
  "geometry": {"coordinates":[55.9336,27.26554],"type":"Point"}
}