{
  "type": "Feature",
  "properties": {
    "gn:admin1_code":"16",
    "gn:asciiname":"Bian Darreh",
    "gn:country_code":"IR",
    "gn:dem":1736,
    "gn:feature_class":"P",
    "gn:feature_code":"PPL",
    "gn:name":"B\u012b\u0101n Darreh",
    "gn:population":0,
    "gn:timezone":"Asia/Tehran",
    "iso:country":"IR",
    "name:fas_x_preferred":[
        "\u0628\u064a\u0627\u0646 \u062f\u064e\u0631\u0650\u0651\u0647"
    ],
    "name:fas_x_variant":[
        "\u0628\u0650\u064a\u0627\u0646 \u062f\u064e\u0631\u0650\u0651\u0647",
        "\u0628\u064e\u064a\u0627\u0646 \u062f\u064e\u0631\u0650\u0651\u0647",
        "\u0628\u06cc\u0627\u0646 \u062f\u0631\u0651\u0647",
        "B\u012b\u0101n Darreh"
    ],
    "name:und_x_variant":[
        "Bey\u0101n Darreh",
        "Bay\u0101n Darreh"
    ],
    "wof:name":"Bian Darreh",
    "wof:placetype":"locality"
},
  "geometry": {"coordinates":[46.1558,35.9539],"type":"Point"}
}