{
  "type": "Feature",
  "properties": {
    "gn:admin1_code":"42",
    "gn:asciiname":"Rigi",
    "gn:country_code":"IR",
    "gn:dem":1431,
    "gn:feature_class":"P",
    "gn:feature_code":"PPL",
    "gn:name":"R\u012bg\u012b",
    "gn:population":0,
    "gn:timezone":"Asia/Tehran",
    "iso:country":"IR",
    "name:fas_x_preferred":[
        "\u0631\u06cc\u06af\u06cc"
    ],
    "name:fas_x_variant":[
        "R\u012bg\u012b"
    ],
    "wof:name":"Rigi",
    "wof:placetype":"locality"
},
  "geometry": {"coordinates":[58.72476,35.77512],"type":"Point"}
}