{
  "type": "Feature",
  "properties": {
    "gn:admin1_code":"28",
    "gn:asciiname":"Neshlaj",
    "gn:country_code":"IR",
    "gn:dem":1999,
    "gn:feature_class":"P",
    "gn:feature_code":"PPL",
    "gn:name":"Neshlaj",
    "gn:population":0,
    "gn:timezone":"Asia/Tehran",
    "iso:country":"IR",
    "name:fas_x_preferred":[
        "\u0646\u0634\u0644\u062c"
    ],
    "name:und_x_variant":[
        "Nashlaj",
        "Nishlak",
        "Neshlaj"
    ],
    "wof:name":"Neshlaj",
    "wof:placetype":"locality"
},
  "geometry": {"coordinates":[51.0734,33.9894],"type":"Point"}
}