{
  "type": "Feature",
  "properties": {
    "gn:admin1_code":"28.0",
    "gn:asciiname":"Keyhaniyeh",
    "gn:country_code":"IR",
    "gn:dem":1817,
    "gn:feature_class":"P",
    "gn:feature_code":"PPL",
    "gn:name":"Keyh\u0101n\u012byeh",
    "gn:population":0,
    "gn:timezone":"Asia/Tehran",
    "iso:country":"IR",
    "name:fas_x_preferred":[
        "\u06a9\u06cc\u0647\u0627\u0646\u06cc\u0647"
    ],
    "name:fas_x_variant":[
        "Keyh\u0101n\u012byeh"
    ],
    "wof:name":"Keyhaniyeh",
    "wof:placetype":"locality"
},
  "geometry": {"coordinates":[51.119,32.4484],"type":"Point"}
}