{
  "type": "Feature",
  "properties": {
    "gn:admin1_code":"42",
    "gn:asciiname":"Nahaldan",
    "gn:country_code":"IR",
    "gn:dem":1203,
    "gn:feature_class":"P",
    "gn:feature_code":"PPL",
    "gn:name":"Nah\u0101ld\u0101n",
    "gn:population":0,
    "gn:timezone":"Asia/Tehran",
    "iso:country":"IR",
    "name:fas_x_preferred":[
        "Nah\u0101ld\u0101n"
    ],
    "name:fas_x_variant":[
        "\u0646\u0647\u0627\u0644\u062f\u0627\u0646"
    ],
    "name:und_x_variant":[
        "\u0646\u0647\u0627\u0644\u062f\u0627\u0646"
    ],
    "wof:name":"Nahaldan",
    "wof:placetype":"locality"
},
  "geometry": {"coordinates":[56.85601,36.43248],"type":"Point"}
}