{
  "type": "Feature",
  "properties": {
    "gn:admin1_code":"11",
    "gn:asciiname":"Todruyeh",
    "gn:country_code":"IR",
    "gn:dem":390,
    "gn:feature_class":"P",
    "gn:feature_code":"PPL",
    "gn:name":"Todr\u016byeh",
    "gn:population":0,
    "gn:timezone":"Asia/Tehran",
    "iso:country":"IR",
    "name:ara_x_preferred":[
        "\u062a\u062f\u0631\u0648\u064a\u0647"
    ],
    "name:fas_x_preferred":[
        "\u062a\u064f\u062f\u0631\u0648\u064a\u0650\u0647"
    ],
    "name:fas_x_variant":[
        "\u062a\u0648\u062f\u064e\u0631\u0627\u0646",
        "\u062a\u064e\u062f\u0631\u064f\u0651\u064a\u0650\u0647",
        "Tadr\u016byeh",
        "\u062a\u064e\u062f\u0631\u0648\u064a\u0650\u0647",
        "Todr\u016byeh",
        "\u062a\u062f\u0631\u0648\u064a\u0647",
        "\u062a\u062f\u0631\u0648\u06cc\u0647"
    ],
    "name:msa_x_preferred":[
        "Todruyeh"
    ],
    "name:und_x_variant":[
        "Tudaru",
        "Tadrooyeh",
        "T\u016bdor\u0101n",
        "Todr\u016byeh",
        "Tudir\u0101n",
        "T\u016bdar\u0101n",
        "\u062a\u062f\u0631\u0648\u064a\u0647"
    ],
    "wof:name":"Todruyeh",
    "wof:placetype":"locality"
},
  "geometry": {"coordinates":[54.70948000000001,27.30262],"type":"Point"}
}