{
  "type": "Feature",
  "properties": {
    "gn:admin1_code":"42",
    "gn:asciiname":"Nahrabad",
    "gn:country_code":"IR",
    "gn:dem":1117,
    "gn:feature_class":"P",
    "gn:feature_code":"PPL",
    "gn:name":"Nahr\u0101b\u0101d",
    "gn:population":0,
    "gn:timezone":"Asia/Tehran",
    "iso:country":"IR",
    "name:ara_x_preferred":[
        "\u0646\u0647\u0631\u0622\u0628\u0627\u062f"
    ],
    "name:ceb_x_preferred":[
        "Nahr\u0101b\u0101d"
    ],
    "name:fas_x_preferred":[
        "\u0646\u0647\u0631 \u0622\u0628\u0627\u062f"
    ],
    "name:fas_x_variant":[
        "Nahr\u0101b\u0101d",
        "\u0646\u0647\u0631\u0622\u0628\u0627\u062f"
    ],
    "name:swe_x_preferred":[
        "Nahr\u0101b\u0101d"
    ],
    "wof:name":"Nahrabad",
    "wof:placetype":"locality"
},
  "geometry": {"coordinates":[59.19814,36.71353],"type":"Point"}
}