{
  "type": "Feature",
  "properties": {
    "gn:admin1_code":"7",
    "gn:asciiname":"Ayur",
    "gn:country_code":"IR",
    "gn:dem":1757,
    "gn:feature_class":"P",
    "gn:feature_code":"PPL",
    "gn:name":"Ay\u016br",
    "gn:population":0,
    "gn:timezone":"Asia/Tehran",
    "iso:country":"IR",
    "name:fas_x_preferred":[
        "\u0627\u06cc\u0648\u0631"
    ],
    "name:fas_x_variant":[
        "Ayy\u016br",
        "Ay\u016br"
    ],
    "name:msa_x_preferred":[
        "Ayur"
    ],
    "wof:name":"Ayur",
    "wof:placetype":"locality"
},
  "geometry": {"coordinates":[52.3879,29.4492],"type":"Point"}
}