{
  "type": "Feature",
  "properties": {
    "gn:admin1_code":"10.0",
    "gn:asciiname":"Ahuran",
    "gn:country_code":"IR",
    "gn:dem":1636,
    "gn:feature_class":"P",
    "gn:feature_code":"PPL",
    "gn:name":"Ah\u016br\u0101n",
    "gn:population":0,
    "gn:timezone":"Asia/Tehran",
    "iso:country":"IR",
    "name:fas_x_preferred":[
        "\u0627\u064e\u0647\u0648\u0631\u0627\u0646"
    ],
    "wof:name":"Ahuran",
    "wof:placetype":"locality"
},
  "geometry": {"coordinates":[47.31139,33.90694000000001],"type":"Point"}
}