{
  "type": "Feature",
  "properties": {
    "gn:admin1_code":"8",
    "gn:asciiname":"Mirak Mahalleh",
    "gn:country_code":"IR",
    "gn:dem":12,
    "gn:feature_class":"P",
    "gn:feature_code":"PPL",
    "gn:name":"M\u012brak Ma\u1e29alleh",
    "gn:population":0,
    "gn:timezone":"Asia/Tehran",
    "iso:country":"IR",
    "name:fas_x_preferred":[
        "M\u012brak Ma\u1e29alleh"
    ],
    "name:fas_x_variant":[
        "\u0645\u06cc\u0631\u06a9 \u0645\u062d\u0644\u0647"
    ],
    "wof:name":"Mirak Mahalleh",
    "wof:placetype":"locality"
},
  "geometry": {"coordinates":[50.30887,37.06647],"type":"Point"}
}