{
  "type": "Feature",
  "properties": {
    "gn:admin1_code":"10",
    "gn:asciiname":"Pakal Gadab",
    "gn:country_code":"IR",
    "gn:dem":1205,
    "gn:feature_class":"P",
    "gn:feature_code":"PPL",
    "gn:name":"P\u0101kal Gad\u0101b",
    "gn:population":0,
    "gn:timezone":"Asia/Tehran",
    "iso:country":"IR",
    "name:fas_x_preferred":[
        "\u067e\u0627\u06a9\u0644 \u06af\u062f\u0627\u0628"
    ],
    "name:fas_x_variant":[
        "P\u0101kal Gad\u0101b"
    ],
    "wof:name":"Pakal Gadab",
    "wof:placetype":"locality"
},
  "geometry": {"coordinates":[46.7406,33.4617],"type":"Point"}
}