{
  "type": "Feature",
  "properties": {
    "gn:admin1_code":"13",
    "gn:asciiname":"Varmaqan",
    "gn:country_code":"IR",
    "gn:dem":2088,
    "gn:feature_class":"P",
    "gn:feature_code":"PPL",
    "gn:name":"Varmaq\u0101n",
    "gn:population":0,
    "gn:timezone":"Asia/Tehran",
    "iso:country":"IR",
    "name:fas_x_preferred":[
        "\u0648\u0631\u0645\u063a\u0627\u0646"
    ],
    "name:fas_x_variant":[
        "Vazmak\u0101n",
        "Varmagh\u0101n",
        "\u0648\u0631\u0645\u0642\u0627\u0646"
    ],
    "name:und_x_variant":[
        "Varmaq\u0101n",
        "Warmaq\u0101n",
        "Varmak\u0101n"
    ],
    "wof:name":"Varmaqan",
    "wof:placetype":"locality"
},
  "geometry": {"coordinates":[47.70443,35.03166],"type":"Point"}
}