{
  "type": "Feature",
  "properties": {
    "gn:admin1_code":"1",
    "gn:asciiname":"Safakhaneh",
    "gn:country_code":"IR",
    "gn:dem":1637,
    "gn:feature_class":"P",
    "gn:feature_code":"PPL",
    "gn:name":"\u015eaf\u0101kh\u0101neh",
    "gn:population":0,
    "gn:timezone":"Asia/Tehran",
    "iso:country":"IR",
    "name:aze_x_preferred":[
        "S\u0259faxana"
    ],
    "name:ckb_x_preferred":[
        "\u0633\u06d5\u0641\u0627\u062e\u0627\u0646\u06d5"
    ],
    "name:fas_x_preferred":[
        "\u015eaf\u0101 Kh\u0101neh"
    ],
    "name:fas_x_variant":[
        "\u0635\u0641\u0627\u062e\u0627\u0646\u0647"
    ],
    "name:msa_x_preferred":[
        "Safa Khaneh"
    ],
    "name:und_x_variant":[
        "\u015eaf\u0101kh\u0101neh"
    ],
    "name:urd_x_preferred":[
        "\u0635\u0641\u0627 \u062e\u0627\u0646\u06c1"
    ],
    "wof:name":"Safakhaneh",
    "wof:placetype":"locality"
},
  "geometry": {"coordinates":[46.68879,36.44112],"type":"Point"}
}