{
  "type": "Feature",
  "properties": {
    "gn:admin1_code":"15",
    "gn:asciiname":"Melleh-ye Bakhtegan",
    "gn:country_code":"IR",
    "gn:dem":815,
    "gn:feature_class":"P",
    "gn:feature_code":"PPL",
    "gn:name":"Melleh-ye Bakhteg\u0101n",
    "gn:population":0,
    "gn:timezone":"Asia/Tehran",
    "iso:country":"IR",
    "name:fas_x_preferred":[
        "Bakhteg\u0101n-e Sofl\u00e1"
    ],
    "name:fas_x_variant":[
        "\u0645\u0644\u0647 \u0628\u062e\u062a\u06af\u0627\u0646"
    ],
    "name:und_x_variant":[
        "Melleh-ye Bakhteg\u0101n"
    ],
    "wof:name":"Melleh-ye Bakhtegan",
    "wof:placetype":"locality"
},
  "geometry": {"coordinates":[49.94127,31.54041],"type":"Point"}
}