{
  "type": "Feature",
  "properties": {
    "gn:admin1_code":"4.0",
    "gn:asciiname":"Dashtak",
    "gn:country_code":"IR",
    "gn:dem":487,
    "gn:feature_class":"P",
    "gn:feature_code":"PPL",
    "gn:name":"Dashtak",
    "gn:population":0,
    "gn:timezone":"Asia/Tehran",
    "iso:country":"IR",
    "name:ceb_x_preferred":[
        "Dashtak"
    ],
    "name:fas_x_preferred":[
        "\u062f\u0634\u062a\u06a9"
    ],
    "name:swe_x_preferred":[
        "Dashtak"
    ],
    "name:und_x_variant":[
        "Dastak-e Now"
    ],
    "wof:name":"Dashtak",
    "wof:placetype":"locality"
},
  "geometry": {"coordinates":[61.5539,30.8591],"type":"Point"}
}