{
  "type": "Feature",
  "properties": {
    "gn:admin1_code":"9",
    "gn:asciiname":"Deh Dalian",
    "gn:country_code":"IR",
    "gn:dem":1877,
    "gn:feature_class":"P",
    "gn:feature_code":"PPL",
    "gn:name":"Deh Dal\u012b\u0101n",
    "gn:population":0,
    "gn:timezone":"Asia/Tehran",
    "iso:country":"IR",
    "name:fas_x_preferred":[
        "\u062f\u0650\u0647 \u062f\u064e\u0644\u064a\u0627\u0646"
    ],
    "name:fas_x_variant":[
        "\u062f\u0650\u0647 \u062f\u0650\u0644\u064a\u0627\u0646",
        "Deh Dal\u012b\u0101n",
        "\u062f\u0647 \u062f\u0644\u06cc\u0627\u0646"
    ],
    "name:und_x_variant":[
        "Deh Dely\u0101n",
        "Deh Del\u012b\u0101n",
        "\u062f\u0647 \u062f\u0644\u06cc\u0627\u0646"
    ],
    "wof:name":"Deh Dalian",
    "wof:placetype":"locality"
},
  "geometry": {"coordinates":[48.71138,34.80482],"type":"Point"}
}