{
  "type": "Feature",
  "properties": {
    "gn:admin1_code":"28.0",
    "gn:asciiname":"Il-e Tayebi",
    "gn:country_code":"IR",
    "gn:dem":2418,
    "gn:feature_class":"P",
    "gn:feature_code":"PPL",
    "gn:name":"\u012al-e \u0162ayeb\u012b",
    "gn:population":0,
    "gn:timezone":"Asia/Tehran",
    "iso:country":"IR",
    "name:fas_x_preferred":[
        "\u012al-e \u0162ayeb\u012b"
    ],
    "name:fas_x_variant":[
        "\u0627\u06cc\u0644 \u0637\u06cc\u0628\u06cc"
    ],
    "wof:name":"Il-e Tayebi",
    "wof:placetype":"locality"
},
  "geometry": {"coordinates":[51.42908,31.25697000000001],"type":"Point"}
}