{
  "type": "Feature",
  "properties": {
    "gn:admin1_code":"15",
    "gn:asciiname":"Oseyfer",
    "gn:country_code":"IR",
    "gn:dem":6,
    "gn:feature_class":"P",
    "gn:feature_code":"PPL",
    "gn:name":"O\u015feyfer",
    "gn:population":0,
    "gn:timezone":"Asia/Tehran",
    "iso:country":"IR",
    "name:fas_x_preferred":[
        "\u0627\u0633\u06cc\u0641\u0631"
    ],
    "name:fas_x_variant":[
        "\u0627\u0635\u06cc\u0641\u0631"
    ],
    "name:und_x_variant":[
        "O\u015feyfer"
    ],
    "wof:name":"Oseyfer",
    "wof:placetype":"locality"
},
  "geometry": {"coordinates":[48.74331,30.65076],"type":"Point"}
}