{
  "type": "Feature",
  "properties": {
    "gn:admin1_code":"16.0",
    "gn:asciiname":"Jushan",
    "gn:country_code":"IR",
    "gn:dem":1651,
    "gn:feature_class":"P",
    "gn:feature_code":"PPL",
    "gn:name":"J\u016bshan",
    "gn:population":0,
    "gn:timezone":"Asia/Tehran",
    "iso:country":"IR",
    "name:fas_x_preferred":[
        "\u062c\u0648\u0634\u064e\u0646"
    ],
    "name:fas_x_variant":[
        "\u062c\u0648\u0634\u0646",
        "J\u016bshan"
    ],
    "wof:name":"Jushan",
    "wof:placetype":"locality"
},
  "geometry": {"coordinates":[46.2437,36.056],"type":"Point"}
}