{
  "type": "Feature",
  "properties": {
    "gn:admin1_code":"33",
    "gn:asciiname":"Bishak",
    "gn:country_code":"IR",
    "gn:dem":1614,
    "gn:feature_class":"P",
    "gn:feature_code":"PPL",
    "gn:name":"B\u012bshak",
    "gn:population":0,
    "gn:timezone":"Asia/Tehran",
    "iso:country":"IR",
    "name:fas_x_preferred":[
        "\u0628\u06cc\u0634\u06a9"
    ],
    "name:fas_x_variant":[
        "B\u012bshak"
    ],
    "name:und_x_variant":[
        "Besh Sh\u0101y",
        "Byshechay",
        "Besheshai"
    ],
    "wof:name":"Bishak",
    "wof:placetype":"locality"
},
  "geometry": {"coordinates":[46.7434,38.5104],"type":"Point"}
}