{
  "type": "Feature",
  "properties": {
    "gn:admin1_code":"15",
    "gn:asciiname":"Magarnat-e Do",
    "gn:country_code":"IR",
    "gn:dem":30,
    "gn:feature_class":"P",
    "gn:feature_code":"PPL",
    "gn:name":"Magarn\u0101t-e Do",
    "gn:population":0,
    "gn:timezone":"Asia/Tehran",
    "iso:country":"IR",
    "name:ceb_x_preferred":[
        "Magarn\u0101t-e Do"
    ],
    "name:fas_x_preferred":[
        "\u0645\u06af\u0631\u0646\u0627\u062a \u062f\u0648"
    ],
    "name:fas_x_variant":[
        "Magarn\u0101t-e Do"
    ],
    "name:swe_x_preferred":[
        "Magarn\u0101t-e Do"
    ],
    "name:und_x_variant":[
        "Jabb\u0101r"
    ],
    "wof:name":"Magarnat-e Do",
    "wof:placetype":"locality"
},
  "geometry": {"coordinates":[48.85503,31.8146],"type":"Point"}
}