{
  "type": "Feature",
  "properties": {
    "gn:admin1_code":"15.0",
    "gn:asciiname":"Pol-e Parzin",
    "gn:country_code":"IR",
    "gn:dem":467,
    "gn:feature_class":"P",
    "gn:feature_code":"PPL",
    "gn:name":"Pol-e Parz\u012bn",
    "gn:population":0,
    "gn:timezone":"Asia/Tehran",
    "iso:country":"IR",
    "name:fas_x_preferred":[
        "\u0645\u06cc\u0627\u0646\u067e\u0644\u0627\u0646"
    ],
    "name:fas_x_variant":[
        "M\u012b\u0101npal\u0101n",
        "\u067e\u0644 \u067e\u0631\u0632\u06cc\u0646",
        "\u0645\u06cc \u067e\u06cc\u0644\u0627\u0646",
        "\u0645\u06cc\u0627\u0646 \u067e\u064a\u0644\u0648\u0646"
    ],
    "name:und_x_variant":[
        "Pol-e Parz\u012bn",
        "Mey P\u012bl\u0101n",
        "M\u012b\u0101n Peyl\u016bn"
    ],
    "wof:name":"Pol-e Parzin",
    "wof:placetype":"locality"
},
  "geometry": {"coordinates":[48.85941,32.40702],"type":"Point"}
}