{
  "type": "Feature",
  "properties": {
    "gn:admin1_code":"42",
    "gn:asciiname":"Jeyran",
    "gn:country_code":"IR",
    "gn:dem":1183,
    "gn:feature_class":"P",
    "gn:feature_code":"PPL",
    "gn:name":"Jeyr\u0101n",
    "gn:population":0,
    "gn:timezone":"Asia/Tehran",
    "iso:country":"IR",
    "name:fas_x_preferred":[
        "\u062c\u06cc\u0631\u0627\u0646"
    ],
    "name:fas_x_variant":[
        "Jeyr\u0101n"
    ],
    "wof:name":"Jeyran",
    "wof:placetype":"locality"
},
  "geometry": {"coordinates":[58.88878,36.12839],"type":"Point"}
}