{
  "type": "Feature",
  "properties": {
    "gn:admin1_code":"4",
    "gn:asciiname":"Jishtegan-e Sofla",
    "gn:country_code":"IR",
    "gn:dem":1029,
    "gn:feature_class":"P",
    "gn:feature_code":"PPL",
    "gn:name":"J\u012bshteg\u0101n-e Sofl\u00e1",
    "gn:population":0,
    "gn:timezone":"Asia/Tehran",
    "iso:country":"IR",
    "name:fas_x_preferred":[
        "\u062c\u064a\u0634\u062a\u06af\u0627\u0646 \u0633\u0641\u0644\u06cc"
    ],
    "name:fas_x_variant":[
        "J\u012bshteg\u0101n-e Sofl\u00e1"
    ],
    "wof:name":"Jishtegan-e Sofla",
    "wof:placetype":"locality"
},
  "geometry": {"coordinates":[61.44439000000001,26.62335],"type":"Point"}
}