{
  "type": "Feature",
  "properties": {
    "gn:admin1_code":"1.0",
    "gn:asciiname":"Incheh Darrehsi",
    "gn:country_code":"IR",
    "gn:dem":958,
    "gn:feature_class":"P",
    "gn:feature_code":"PPL",
    "gn:name":"\u012ancheh Darrehs\u012b",
    "gn:population":0,
    "gn:timezone":"Asia/Tehran",
    "iso:country":"IR",
    "name:azb_x_preferred":[
        "\u0627\u06cc\u0646\u0686\u0647 \u062f\u0631\u0647\u200c\u0633\u06cc"
    ],
    "name:aze_x_preferred":[
        "\u0130nc\u0259d\u0259r\u0259si"
    ],
    "name:fas_x_preferred":[
        "\u064a\u0646\u0686\u0650\u0647 \u062f\u064e\u0631\u0650\u0651\u0647\u0633\u06cc"
    ],
    "name:fas_x_variant":[
        "\u0627\u06cc\u0646\u0686\u0647 \u062f\u0631\u0651\u0647 \u0633\u06cc",
        "\u012ancheh Darrehs\u012b",
        "\u064a\u0646\u0686\u0650\u0647 \u062f\u064e\u0631\u064e\u0651\u0647\u0633\u06cc",
        "\u0627\u06cc\u0646\u0686\u0647\u200c\u062f\u0631\u0647\u200c\u0633\u06cc"
    ],
    "name:msa_x_preferred":[
        "Incheh Darrehsi"
    ],
    "name:und_x_variant":[
        "\u012ancheh Darrahs\u012b"
    ],
    "wof:name":"Incheh Darrehsi",
    "wof:placetype":"locality"
},
  "geometry": {"coordinates":[45.2406,39.0728],"type":"Point"}
}