{
  "type": "Feature",
  "properties": {
    "gn:admin1_code":"29",
    "gn:asciiname":"Khukestan",
    "gn:country_code":"IR",
    "gn:dem":2673,
    "gn:feature_class":"P",
    "gn:feature_code":"PPL",
    "gn:name":"Kh\u016bkest\u0101n",
    "gn:population":0,
    "gn:timezone":"Asia/Tehran",
    "iso:country":"IR",
    "name:ceb_x_preferred":[
        "Kh\u016bkest\u0101n"
    ],
    "name:fas_x_preferred":[
        "Kh\u016bkest\u0101n"
    ],
    "name:fas_x_variant":[
        "Kh\u016bbest\u0101n",
        "\u062e\u0648\u0628\u0633\u062a\u0627\u0646",
        "\u062e\u0648\u06a9\u0633\u062a\u0627\u0646"
    ],
    "name:swe_x_preferred":[
        "Kh\u016bkest\u0101n"
    ],
    "wof:name":"Khukestan",
    "wof:placetype":"locality"
},
  "geometry": {"coordinates":[57.49394,29.14442],"type":"Point"}
}