{
  "type": "Feature",
  "properties": {
    "gn:admin1_code":"8.0",
    "gn:asciiname":"Gildeh-ye Bala",
    "gn:country_code":"IR",
    "gn:dem":44,
    "gn:feature_class":"P",
    "gn:feature_code":"PPL",
    "gn:name":"G\u012bldeh-ye B\u0101l\u0101",
    "gn:population":0,
    "gn:timezone":"Asia/Tehran",
    "iso:country":"IR",
    "name:ceb_x_preferred":[
        "G\u012bldeh"
    ],
    "name:fas_x_preferred":[
        "\u06af\u06cc\u0644\u062f\u0647"
    ],
    "name:fas_x_variant":[
        "K\u012bldeh",
        "G\u012bldeh",
        "\u06af\u06cc\u0644\u062f\u0647 \u0628\u0627\u0644\u0627"
    ],
    "name:msa_x_preferred":[
        "Gildeh"
    ],
    "name:ukr_x_preferred":[
        "\u0490\u0456\u043b\u044c\u0434\u0435\u0433"
    ],
    "name:und_x_variant":[
        "G\u012bldeh-ye B\u0101l\u0101"
    ],
    "wof:name":"Gildeh-ye Bala",
    "wof:placetype":"locality"
},
  "geometry": {"coordinates":[49.47837,37.13563],"type":"Point"}
}