{
  "type": "Feature",
  "properties": {
    "gn:admin1_code":"4.0",
    "gn:asciiname":"Shahvak",
    "gn:country_code":"IR",
    "gn:dem":46,
    "gn:feature_class":"P",
    "gn:feature_code":"PPL",
    "gn:name":"Sh\u0101hvak",
    "gn:population":0,
    "gn:timezone":"Asia/Tehran",
    "iso:country":"IR",
    "name:fas_x_preferred":[
        "Sh\u0101hak B\u0101z\u0101r"
    ],
    "name:fas_x_variant":[
        "Sh\u0101hvak",
        "\u0634\u0627\u0647\u0648\u06a9",
        "\u0634\u0627\u0647\u06a9 \u0628\u0627\u0632\u0627\u0631"
    ],
    "wof:name":"Shahvak",
    "wof:placetype":"locality"
},
  "geometry": {"coordinates":[61.01836,25.78668],"type":"Point"}
}