{
  "type": "Feature",
  "properties": {
    "gn:admin1_code":"42",
    "gn:asciiname":"Hasanabad-e Manqasali",
    "gn:country_code":"IR",
    "gn:dem":1096,
    "gn:feature_class":"P",
    "gn:feature_code":"PPL",
    "gn:name":"\u1e28asan\u0101b\u0101d-e Manqasal\u012b",
    "gn:population":0,
    "gn:timezone":"Asia/Tehran",
    "iso:country":"IR",
    "name:fas_x_preferred":[
        "\u1e28asan\u0101b\u0101d-e Manqasal\u012b"
    ],
    "wof:name":"Hasanabad-e Manqasali",
    "wof:placetype":"locality"
},
  "geometry": {"coordinates":[59.28278,36.63361],"type":"Point"}
}