{
  "type": "Feature",
  "properties": {
    "gn:admin1_code":"42",
    "gn:asciiname":"Kushk-e Mehdi",
    "gn:country_code":"IR",
    "gn:dem":993,
    "gn:feature_class":"P",
    "gn:feature_code":"PPL",
    "gn:name":"K\u016bshk-e Mehd\u012b",
    "gn:population":0,
    "gn:timezone":"Asia/Tehran",
    "iso:country":"IR",
    "name:fas_x_preferred":[
        "\u06a9\u0648\u0634\u06a9 \u0645\u0647\u062f\u06cc"
    ],
    "name:fas_x_variant":[
        "K\u016bshk-e Mehd\u012b"
    ],
    "name:und_x_variant":[
        "K\u016btoshk-e Mehd\u012b"
    ],
    "wof:name":"Kushk-e Mehdi",
    "wof:placetype":"locality"
},
  "geometry": {"coordinates":[59.5649,36.3903],"type":"Point"}
}