{
  "type": "Feature",
  "properties": {
    "gn:admin1_code":"8",
    "gn:asciiname":"Esma`il Gavabar-e Pa'in",
    "gn:country_code":"IR",
    "gn:dem":48,
    "gn:feature_class":"P",
    "gn:feature_code":"PPL",
    "gn:name":"Esm\u0101\u2018\u012bl Gav\u0101bar-e P\u0101\u2019\u012bn",
    "gn:population":0,
    "gn:timezone":"Asia/Tehran",
    "iso:country":"IR",
    "name:fas_x_preferred":[
        "Esm\u0101\u2018\u012bl Gav\u0101bar-e \u2018Oly\u0101"
    ],
    "name:fas_x_variant":[
        "Esm\u0101\u2018\u012bl Gav\u0101bar",
        "\u0627\u0633\u0645\u0627\u0639\u06cc\u0644 \u06af\u0648\u0627\u0628\u0631",
        "Esma\u2018\u012bl Gav\u0101bar",
        "\u0627\u0633\u0645\u0627\u0639\u06cc\u0644 \u06af\u0648\u0627\u0628\u0631 \u067e\u0627\u06cc\u06cc\u0646"
    ],
    "name:und_x_variant":[
        "Esm\u0101\u2018\u012bl Gav\u0101bar-e P\u0101\u2019\u012bn"
    ],
    "wof:name":"Esma`il Gavabar-e Pa'in",
    "wof:placetype":"locality"
},
  "geometry": {"coordinates":[50.23104,37.0536],"type":"Point"}
}