{
  "type": "Feature",
  "properties": {
    "gn:admin1_code":"29",
    "gn:asciiname":"Chilabad",
    "gn:country_code":"IR",
    "gn:dem":399,
    "gn:feature_class":"P",
    "gn:feature_code":"PPL",
    "gn:name":"Ch\u012bl\u0101b\u0101d",
    "gn:population":0,
    "gn:timezone":"Asia/Tehran",
    "iso:country":"IR",
    "name:fas_x_preferred":[
        "\u0686\u06cc\u0644 \u0622\u0628\u0627\u062f"
    ],
    "name:fas_x_variant":[
        "Ch\u012bl\u0101b\u0101d"
    ],
    "wof:name":"Chilabad",
    "wof:placetype":"locality"
},
  "geometry": {"coordinates":[57.8949,27.5087],"type":"Point"}
}