{
  "type": "Feature",
  "properties": {
    "gn:admin1_code":"35",
    "gn:asciiname":"Karnam-e Sofla",
    "gn:country_code":"IR",
    "gn:dem":961,
    "gn:feature_class":"P",
    "gn:feature_code":"PPL",
    "gn:name":"K\u0101rn\u0101m-e Sofl\u00e1",
    "gn:population":0,
    "gn:timezone":"Asia/Tehran",
    "iso:country":"IR",
    "name:ceb_x_preferred":[
        "K\u0101rn\u0101m-e Sofl\u00e1"
    ],
    "name:fas_x_preferred":[
        "\u0643\u0627\u0631 \u0646\u0627\u0645"
    ],
    "name:fas_x_variant":[
        "K\u0101rn\u0101m-e P\u0101\u2019\u012bn",
        "K\u0101r N\u0101m",
        "\u0643\u0627\u0631\u0646\u0627\u0645 \u067e\u0627\u0626\u06cc\u0646",
        "\u0643\u0627\u0631\u0646\u0627\u0645 \u0633\u0641\u0644\u06cc",
        "\u06a9\u0627\u0631\u0646\u0627\u0645"
    ],
    "name:mzn_x_preferred":[
        "\u06a9\u0627\u0631\u0646\u0627\u0645"
    ],
    "name:swe_x_preferred":[
        "K\u0101rn\u0101m-e Sofl\u00e1"
    ],
    "name:und_x_variant":[
        "\u0643\u0627\u0631\u0646\u0627\u0645 \u067e\u0627\u0626\u06cc\u0646",
        "Gorn\u0101m-e Sofl\u00e1",
        "\u06af\u064f\u0631\u0646\u0627\u0645\u0650 \u0633\u064f\u0641\u0644\u064e\u0649",
        "K\u0101rn\u0101m-e Sofl\u00e1"
    ],
    "wof:name":"Karnam-e Sofla",
    "wof:placetype":"locality"
},
  "geometry": {"coordinates":[53.42341,36.39448],"type":"Point"}
}