{
  "type": "Feature",
  "properties": {
    "gn:admin1_code":"35",
    "gn:asciiname":"Akhvor Kola",
    "gn:country_code":"IR",
    "gn:dem":13,
    "gn:feature_class":"P",
    "gn:feature_code":"PPL",
    "gn:name":"\u0100khvor Kol\u0101",
    "gn:population":0,
    "gn:timezone":"Asia/Tehran",
    "iso:country":"IR",
    "name:fas_x_preferred":[
        "\u0100khvor Kol\u0101"
    ],
    "name:fas_x_variant":[
        "\u0100khvor Sar",
        "\u0622\u062e\u0648\u0631 \u06a9\u0644\u0627",
        "\u0622\u062e\u0648\u0631 \u0633\u0631"
    ],
    "name:und_x_variant":[
        "\u0622\u062e\u0648\u0631 \u0633\u0631",
        "\u0622\u062e\u0648\u0631 \u06a9\u0644\u0627"
    ],
    "wof:name":"Akhvor Kola",
    "wof:placetype":"locality"
},
  "geometry": {"coordinates":[53.02226999999999,36.58414000000001],"type":"Point"}
}