{
  "type": "Feature",
  "properties": {
    "gn:admin1_code":"11.0",
    "gn:asciiname":"Mahkameh",
    "gn:country_code":"IR",
    "gn:dem":185,
    "gn:feature_class":"P",
    "gn:feature_code":"PPL",
    "gn:name":"Ma\u1e29kameh",
    "gn:population":0,
    "gn:timezone":"Asia/Tehran",
    "iso:country":"IR",
    "name:fas_x_preferred":[
        "\u0645\u064e\u062d\u0643\u064e\u0645\u0650\u0647"
    ],
    "name:und_x_variant":[
        "Ma\u1e29kameh"
    ],
    "wof:name":"Mahkameh",
    "wof:placetype":"locality"
},
  "geometry": {"coordinates":[57.18333000000001,27.44167],"type":"Point"}
}