{
  "type": "Feature",
  "properties": {
    "gn:admin1_code":"41.0",
    "gn:asciiname":"Achuni",
    "gn:country_code":"IR",
    "gn:dem":1500,
    "gn:feature_class":"P",
    "gn:feature_code":"PPL",
    "gn:name":"\u0100ch\u016bn\u012b",
    "gn:population":0,
    "gn:timezone":"Asia/Tehran",
    "iso:country":"IR",
    "name:fas_x_preferred":[
        "\u0100ch\u0101n\u012b"
    ],
    "name:fas_x_variant":[
        "\u0622\u0686\u0648\u0646\u06cc",
        "\u062c\u0627\u0646\u06cc",
        "\u0627\u0686\u0648\u0646\u06cc"
    ],
    "name:und_x_variant":[
        "Ach\u016bn\u012b",
        "\u0100ch\u016bn\u012b",
        "J\u0101n\u012b"
    ],
    "wof:name":"Achuni",
    "wof:placetype":"locality"
},
  "geometry": {"coordinates":[59.26546,33.97135],"type":"Point"}
}