{
  "type": "Feature",
  "properties": {
    "gn:admin1_code":"7",
    "gn:asciiname":"Kasjaghureh",
    "gn:country_code":"IR",
    "gn:dem":2205,
    "gn:feature_class":"P",
    "gn:feature_code":"PPL",
    "gn:name":"Kasj\u0101gh\u016breh",
    "gn:population":0,
    "gn:timezone":"Asia/Tehran",
    "iso:country":"IR",
    "name:fas_x_preferred":[
        "Kasj\u0101gh\u016breh"
    ],
    "wof:name":"Kasjaghureh",
    "wof:placetype":"locality"
},
  "geometry": {"coordinates":[52.34861,31.38],"type":"Point"}
}