{
  "type": "Feature",
  "properties": {
    "gn:admin1_code":"13",
    "gn:asciiname":"Haft Ashian",
    "gn:country_code":"IR",
    "gn:dem":1787,
    "gn:feature_class":"P",
    "gn:feature_code":"PPL",
    "gn:name":"Haft \u0100sh\u012b\u0101n",
    "gn:population":0,
    "gn:timezone":"Asia/Tehran",
    "iso:country":"IR",
    "name:fas_x_preferred":[
        "\u0647\u0641\u062a \u0622\u0634\u06cc\u0627\u0646"
    ],
    "name:fas_x_variant":[
        "Haft \u0100sh\u012b\u0101n"
    ],
    "name:und_x_variant":[
        "Haft\u0101s\u0101n",
        "Hafteh Sh\u012b\u0101n",
        "Haft Sh\u012b\u0101n"
    ],
    "wof:name":"Haft Ashian",
    "wof:placetype":"locality"
},
  "geometry": {"coordinates":[47.4579,34.9676],"type":"Point"}
}