{
  "type": "Feature",
  "properties": {
    "gn:admin1_code":"4.0",
    "gn:asciiname":"Zavar",
    "gn:country_code":"IR",
    "gn:dem":710,
    "gn:feature_class":"P",
    "gn:feature_code":"PPLL",
    "gn:name":"Zav\u0101r",
    "gn:population":0,
    "gn:timezone":"Asia/Tehran",
    "iso:country":"IR",
    "name:cat_x_preferred":[
        "Zavar"
    ],
    "name:ces_x_preferred":[
        "Zavar"
    ],
    "name:deu_x_preferred":[
        "Zavar"
    ],
    "name:epo_x_preferred":[
        "Zavar"
    ],
    "name:eus_x_preferred":[
        "Zavar"
    ],
    "name:fas_x_preferred":[
        "\u0632\u0648\u0627\u0631"
    ],
    "name:fra_x_preferred":[
        "Zavar"
    ],
    "name:hun_x_preferred":[
        "Zavar"
    ],
    "name:ita_x_preferred":[
        "Zavar"
    ],
    "name:msa_x_preferred":[
        "Zavar"
    ],
    "name:nld_x_preferred":[
        "Zavar"
    ],
    "name:por_x_preferred":[
        "Zavar"
    ],
    "name:ron_x_preferred":[
        "Zavar"
    ],
    "name:slk_x_preferred":[
        "Zavar"
    ],
    "name:spa_x_preferred":[
        "Zavar"
    ],
    "name:srp_x_preferred":[
        "\u0417\u0430\u0432\u0430\u0440"
    ],
    "name:und_x_variant":[
        "Zav\u0101r"
    ],
    "name:war_x_preferred":[
        "Zavar"
    ],
    "wof:name":"Zavar",
    "wof:placetype":"locality"
},
  "geometry": {"coordinates":[59.6258,26.57566],"type":"Point"}
}