{
  "type": "Feature",
  "properties": {
    "gn:admin1_code":"37",
    "gn:asciiname":"Khvojeh",
    "gn:country_code":"IR",
    "gn:dem":308,
    "gn:feature_class":"P",
    "gn:feature_code":"PPL",
    "gn:name":"Khvojeh",
    "gn:population":0,
    "gn:timezone":"Asia/Tehran",
    "iso:country":"IR",
    "name:fas_x_preferred":[
        "\u062e\u0648\u062c\u0647"
    ],
    "wof:name":"Khvojeh",
    "wof:placetype":"locality"
},
  "geometry": {"coordinates":[55.7249,37.6281],"type":"Point"}
}