{
  "type": "Feature",
  "properties": {
    "gn:admin1_code":"15",
    "gn:asciiname":"Seyyed Yusef",
    "gn:country_code":"IR",
    "gn:dem":0,
    "gn:feature_class":"P",
    "gn:feature_code":"PPL",
    "gn:name":"Seyyed Y\u016bsef",
    "gn:population":0,
    "gn:timezone":"Asia/Tehran",
    "iso:country":"IR",
    "name:ara_x_preferred":[
        "\u0633\u064a\u062f \u064a\u0648\u0633\u0641"
    ],
    "name:azb_x_preferred":[
        "\u0633\u06cc\u062f\u06cc\u0648\u0633\u0641(\u0627\u0647\u0648\u0627\u0632)"
    ],
    "name:fas_x_preferred":[
        "Seyyed Y\u016bsef"
    ],
    "name:fas_x_variant":[
        "\u0633\u06cc\u062f\u06cc\u0648\u0633\u0641"
    ],
    "wof:name":"Seyyed Yusef",
    "wof:placetype":"locality"
},
  "geometry": {"coordinates":[48.45,30.05],"type":"Point"}
}