{
  "type": "Feature",
  "properties": {
    "gn:admin1_code":"3",
    "gn:asciiname":"Faryab-e Dudrah",
    "gn:country_code":"IR",
    "gn:dem":1362,
    "gn:feature_class":"P",
    "gn:feature_code":"PPL",
    "gn:name":"F\u0101ry\u0101b-e D\u016bdr\u0101h",
    "gn:population":0,
    "gn:timezone":"Asia/Tehran",
    "iso:country":"IR",
    "name:fas_x_preferred":[
        "F\u0101ry\u0101b-e D\u016bder\u0101\u2019"
    ],
    "name:fas_x_variant":[
        "\u0641\u0627\u0631\u06cc\u0627\u0628 \u062f\u0648\u062f\u0631\u0627\u0647",
        "\u067e\u0627\u0631\u064a\u0627\u0628",
        "\u0641\u0627\u0631\u06cc\u0627\u0628"
    ],
    "name:und_x_variant":[
        "F\u0101ry\u0101b-e D\u016bdr\u0101h",
        "P\u0101ry\u0101b",
        "F\u0101ry\u0101b-e Jal\u0101leh",
        "F\u0101ry\u0101b"
    ],
    "wof:name":"Faryab-e Dudrah",
    "wof:placetype":"locality"
},
  "geometry": {"coordinates":[50.84479,31.30988],"type":"Point"}
}