{
  "type": "Feature",
  "properties": {
    "gn:admin1_code":"15.0",
    "gn:asciiname":"Beyt-e `Abd os Sadeh",
    "gn:country_code":"IR",
    "gn:dem":38,
    "gn:feature_class":"P",
    "gn:feature_code":"PPL",
    "gn:name":"Beyt-e \u2018Abd os S\u0101deh",
    "gn:population":0,
    "gn:timezone":"Asia/Tehran",
    "iso:country":"IR",
    "name:fas_x_preferred":[
        "\u0628\u06cc\u062a \u0639\u0628\u062f\u0627\u0644\u0633\u0627\u062f\u0647"
    ],
    "name:und_x_variant":[
        "Beyt-e \u2018Abd os S\u0101deh"
    ],
    "wof:name":"Beyt-e `Abd os Sadeh",
    "wof:placetype":"locality"
},
  "geometry": {"coordinates":[48.85411,31.88575],"type":"Point"}
}