{
  "type": "Feature",
  "properties": {
    "gn:admin1_code":"4",
    "gn:asciiname":"Bug",
    "gn:country_code":"IR",
    "gn:dem":1436,
    "gn:feature_class":"P",
    "gn:feature_code":"PPL",
    "gn:name":"B\u016bg",
    "gn:population":0,
    "gn:timezone":"Asia/Tehran",
    "iso:country":"IR",
    "name:fas_x_preferred":[
        "\u0628\u0648\u06af"
    ],
    "name:fas_x_variant":[
        "B\u016bg"
    ],
    "wof:name":"Bug",
    "wof:placetype":"locality"
},
  "geometry": {"coordinates":[61.10738000000001,28.02429],"type":"Point"}
}