{
  "type": "Feature",
  "properties": {
    "gn:admin1_code":"7",
    "gn:asciiname":"Dabbaghi",
    "gn:country_code":"IR",
    "gn:dem":853,
    "gn:feature_class":"P",
    "gn:feature_code":"PPL",
    "gn:name":"Dabb\u0101gh\u012b",
    "gn:population":0,
    "gn:timezone":"Asia/Tehran",
    "iso:country":"IR",
    "name:fas_x_preferred":[
        "\u062f\u0628\u0627\u063a\u06cc"
    ],
    "name:fas_x_variant":[
        "Dabb\u0101gh\u012b"
    ],
    "wof:name":"Dabbaghi",
    "wof:placetype":"locality"
},
  "geometry": {"coordinates":[54.2618,27.6531],"type":"Point"}
}