{
  "type": "Feature",
  "properties": {
    "gn:admin1_code":"32",
    "gn:asciiname":"Aq Bolagh-e Bala",
    "gn:country_code":"IR",
    "gn:dem":1774,
    "gn:feature_class":"P",
    "gn:feature_code":"PPL",
    "gn:name":"\u0100q Bol\u0101gh-e B\u0101l\u0101",
    "gn:population":0,
    "gn:timezone":"Asia/Tehran",
    "iso:country":"IR",
    "name:fas_x_preferred":[
        "\u0622\u063a \u0628\u064f\u0644\u0627\u063a\u0650 \u0628\u0627\u0644\u0627"
    ],
    "name:fas_x_variant":[
        "\u0622\u0642 \u0628\u0644\u0627\u063a \u0628\u0627\u0644\u0627",
        "\u0100gh Bol\u0101gh-e B\u0101l\u0101",
        "\u0100q Bol\u0101gh-e B\u0101l\u0101"
    ],
    "wof:name":"Aq Bolagh-e Bala",
    "wof:placetype":"locality"
},
  "geometry": {"coordinates":[48.2613,38.6442],"type":"Point"}
}