{
  "type": "Feature",
  "properties": {
    "gn:admin1_code":"28",
    "gn:asciiname":"Sivar",
    "gn:country_code":"IR",
    "gn:dem":2073,
    "gn:feature_class":"P",
    "gn:feature_code":"PPL",
    "gn:name":"S\u012bvar",
    "gn:population":0,
    "gn:timezone":"Asia/Tehran",
    "iso:country":"IR",
    "name:fas_x_preferred":[
        "S\u012bvar"
    ],
    "name:fas_x_variant":[
        "\u0633\u06cc\u0648\u0631"
    ],
    "wof:name":"Sivar",
    "wof:placetype":"locality"
},
  "geometry": {"coordinates":[51.41983,31.10243],"type":"Point"}
}