{
  "type": "Feature",
  "properties": {
    "gn:admin1_code":"28",
    "gn:asciiname":"Qal`eh Ekhlas",
    "gn:country_code":"IR",
    "gn:dem":2407,
    "gn:feature_class":"P",
    "gn:feature_code":"PPL",
    "gn:name":"Qal\u2018eh Ekhl\u0101\u015f",
    "gn:population":0,
    "gn:timezone":"Asia/Tehran",
    "iso:country":"IR",
    "name:fas_x_preferred":[
        "Qal\u2018eh Ekhl\u0101\u015f"
    ],
    "name:fas_x_variant":[
        "\u0642\u0644\u0639\u0647 \u0627\u062e\u0644\u0627\u0635"
    ],
    "name:und_x_variant":[
        "Ghal\u2018eh Ekhlas",
        "\u0642\u0644\u0639\u0647 \u0627\u062e\u0644\u0627\u0635"
    ],
    "wof:name":"Qal`eh Ekhlas",
    "wof:placetype":"locality"
},
  "geometry": {"coordinates":[49.99915,33.17394],"type":"Point"}
}