{
  "type": "Feature",
  "properties": {
    "gn:admin1_code":"7",
    "gn:asciiname":"Shahr-e Bala",
    "gn:country_code":"IR",
    "gn:dem":2162,
    "gn:feature_class":"P",
    "gn:feature_code":"PPL",
    "gn:name":"Shahr-e B\u0101l\u0101",
    "gn:population":0,
    "gn:timezone":"Asia/Tehran",
    "iso:country":"IR",
    "name:ara_x_preferred":[
        "\u0634\u0647\u0631\u0643 \u0634\u0647\u064a\u062f \u0645\u0637\u0647\u0631\u064a"
    ],
    "name:fas_x_preferred":[
        "Shahr-e B\u0101l\u0101"
    ],
    "name:fas_x_variant":[
        "\u0634\u0647\u0631 \u0628\u0627\u0644\u0627",
        "\u0634\u0647\u0631\u0643 \u0634\u0647\u06cc\u062f \u0645\u0637\u0647\u0651\u0631\u06cc",
        "\u0634\u0647\u0631\u06a9 \u0634\u0647\u06cc\u062f \u0645\u0637\u0647\u0631\u06cc"
    ],
    "name:msa_x_preferred":[
        "Shahrak-e Shahid Motahhari"
    ],
    "name:und_x_variant":[
        "Shahrak-e Shah\u012bd Mo\u0163ahhar\u012b"
    ],
    "wof:name":"Shahr-e Bala",
    "wof:placetype":"locality"
},
  "geometry": {"coordinates":[52.5644,30.471],"type":"Point"}
}