{
  "type": "Feature",
  "properties": {
    "gn:admin1_code":"32",
    "gn:asciiname":"Hashatjin",
    "gn:country_code":"IR",
    "gn:dem":1482,
    "gn:feature_class":"P",
    "gn:feature_code":"PPL",
    "gn:name":"Hashatj\u012bn",
    "gn:population":0,
    "gn:timezone":"Asia/Tehran",
    "iso:country":"IR",
    "name:ara_x_preferred":[
        "\u0647\u0634\u062c\u064a\u0646"
    ],
    "name:azb_x_preferred":[
        "\u0647\u0634\u062c\u06cc\u0646"
    ],
    "name:aze_x_preferred":[
        "H\u0259\u015fcin"
    ],
    "name:ceb_x_preferred":[
        "Hashatj\u012bn"
    ],
    "name:diq_x_preferred":[
        "H\u0131\u015fecin"
    ],
    "name:fas_x_preferred":[
        "Hashatj\u012bn"
    ],
    "name:fas_x_variant":[
        "\u0647\u0634\u062a\u062c\u06cc\u0646",
        "\u0647\u0634\u062c\u06cc\u0646"
    ],
    "name:mlg_x_preferred":[
        "Hashatjin"
    ],
    "name:msa_x_preferred":[
        "Hashatjin"
    ],
    "name:pol_x_preferred":[
        "Haszd\u017cin"
    ],
    "name:swe_x_preferred":[
        "Hashatj\u012bn"
    ],
    "name:tur_x_preferred":[
        "He\u015fecin"
    ],
    "name:und_x_variant":[
        "Shein",
        "Hesh\u012b\u012bn",
        "Shain",
        "Heshajeyn",
        "H\u012bshen",
        "Heshaj\u012bn"
    ],
    "name:urd_x_preferred":[
        "\u06c1\u0634\u062c\u06cc\u0646"
    ],
    "wof:name":"Hashatjin",
    "wof:placetype":"locality"
},
  "geometry": {"coordinates":[48.32155,37.36885],"type":"Point"}
}