{
  "type": "Feature",
  "properties": {
    "gn:admin1_code":"32",
    "gn:asciiname":"Asmarud",
    "gn:country_code":"IR",
    "gn:dem":1655,
    "gn:feature_class":"P",
    "gn:feature_code":"PPL",
    "gn:name":"Asmar\u016bd",
    "gn:population":0,
    "gn:timezone":"Asia/Tehran",
    "iso:country":"IR",
    "name:fas_x_preferred":[
        "\u0627\u0633\u0645\u0631\u0648\u062f"
    ],
    "name:fas_x_variant":[
        "Asmar\u016bd"
    ],
    "name:msa_x_preferred":[
        "Asmarud"
    ],
    "name:und_x_variant":[
        "Esmr\u016bd"
    ],
    "wof:name":"Asmarud",
    "wof:placetype":"locality"
},
  "geometry": {"coordinates":[48.33411,37.50918],"type":"Point"}
}