{
  "type": "Feature",
  "properties": {
    "gn:admin1_code":"28.0",
    "gn:asciiname":"Rezvanshahr",
    "gn:country_code":"IR",
    "gn:dem":1875,
    "gn:feature_class":"P",
    "gn:feature_code":"PPL",
    "gn:name":"Re\u1e95v\u0101nshahr",
    "gn:population":0,
    "gn:timezone":"Asia/Tehran",
    "iso:country":"IR",
    "name:fas_x_preferred":[
        "\u0631\u0636\u0648\u0627\u0646\u0634\u0647\u0631"
    ],
    "name:fas_x_variant":[
        "Re\u1e95v\u0101nshahr"
    ],
    "wof:name":"Rezvanshahr",
    "wof:placetype":"locality"
},
  "geometry": {"coordinates":[51.104,32.7055],"type":"Point"}
}