{
  "type": "Feature",
  "properties": {
    "gn:admin1_code":"8",
    "gn:asciiname":"Avvaleh Kari Nav",
    "gn:country_code":"IR",
    "gn:dem":47,
    "gn:feature_class":"P",
    "gn:feature_code":"PPL",
    "gn:name":"Avvaleh Kar\u012b N\u0101v",
    "gn:population":0,
    "gn:timezone":"Asia/Tehran",
    "iso:country":"IR",
    "name:ceb_x_preferred":[
        "K\u0101rband"
    ],
    "name:fas_x_preferred":[
        "\u06a9\u0627\u0631\u0628\u0646\u062f"
    ],
    "name:fas_x_variant":[
        "K\u0101rban",
        "K\u0101rband",
        "\u0627\u0648\u0644\u0647 \u06a9\u0631\u06cc \u0646\u0627\u0648"
    ],
    "name:msa_x_preferred":[
        "Karband"
    ],
    "name:swe_x_preferred":[
        "K\u0101rband"
    ],
    "name:ukr_x_preferred":[
        "\u041a\u0430\u0440\u0431\u0430\u043d\u0434"
    ],
    "name:und_x_variant":[
        "Avvaleh Kar\u012b N\u0101v"
    ],
    "wof:name":"Avvaleh Kari Nav",
    "wof:placetype":"locality"
},
  "geometry": {"coordinates":[48.93829,37.73632],"type":"Point"}
}