{
  "type": "Feature",
  "properties": {
    "gn:admin1_code":"36",
    "gn:asciiname":"Boyuk Qiyeh",
    "gn:country_code":"IR",
    "gn:dem":1769,
    "gn:feature_class":"P",
    "gn:feature_code":"PPL",
    "gn:name":"Boy\u016bk Q\u012byeh",
    "gn:population":0,
    "gn:timezone":"Asia/Tehran",
    "iso:country":"IR",
    "name:fas_x_preferred":[
        "\u0628\u064f\u064a\u0648\u0643 \u0642\u064a\u0650\u0651\u0647"
    ],
    "name:fas_x_variant":[
        "Boy\u016bk Q\u012byeh"
    ],
    "wof:name":"Boyuk Qiyeh",
    "wof:placetype":"locality"
},
  "geometry": {"coordinates":[48.31667,36.31667],"type":"Point"}
}