{
  "type": "Feature",
  "properties": {
    "gn:admin1_code":"44.0",
    "gn:asciiname":"Seyfdarak",
    "gn:country_code":"IR",
    "gn:dem":1767,
    "gn:feature_class":"P",
    "gn:feature_code":"PPL",
    "gn:name":"Seyfd\u0101rak",
    "gn:population":0,
    "gn:timezone":"Asia/Tehran",
    "iso:country":"IR",
    "name:fas_x_preferred":[
        "Sef\u012bd\u0101rak"
    ],
    "name:fas_x_variant":[
        "Sef\u012bdd\u0101rak",
        "\u0633\u0641\u064a\u062f\u062f\u0627\u0631\u06a9",
        "\u0633\u0641\u064a\u062f\u0627\u0631\u0643",
        "\u0633\u06cc\u0641\u062f\u0627\u0631\u06a9",
        "\u0633\u0641\u06cc\u062f\u0627\u0631\u06a9"
    ],
    "name:msa_x_preferred":[
        "Sefidarak"
    ],
    "name:und_x_variant":[
        "\u0633\u0641\u064a\u062f\u0627\u0631\u0643",
        "\u0633\u0641\u064a\u062f\u062f\u0627\u0631\u06a9",
        "Seyfd\u0101rak"
    ],
    "wof:name":"Seyfdarak",
    "wof:placetype":"locality"
},
  "geometry": {"coordinates":[50.72857,36.0515],"type":"Point"}
}