{
  "type": "Feature",
  "properties": {
    "gn:admin1_code":"43.0",
    "gn:asciiname":"Kalateh-ye Parman",
    "gn:country_code":"IR",
    "gn:dem":534,
    "gn:feature_class":"P",
    "gn:feature_code":"PPL",
    "gn:name":"Kal\u0101teh-ye Parman",
    "gn:population":0,
    "gn:timezone":"Asia/Tehran",
    "iso:country":"IR",
    "name:fas_x_preferred":[
        "\u06a9\u0644\u0627\u062a\u0647 \u067e\u0631\u0645\u0646"
    ],
    "name:und_x_variant":[
        "Kal\u0101teh-ye Parman"
    ],
    "wof:name":"Kalateh-ye Parman",
    "wof:placetype":"locality"
},
  "geometry": {"coordinates":[56.33586999999999,38.17027],"type":"Point"}
}