{
  "type": "Feature",
  "properties": {
    "gn:admin1_code":"7.0",
    "gn:asciiname":"Lay Jana",
    "gn:country_code":"IR",
    "gn:dem":1582,
    "gn:feature_class":"P",
    "gn:feature_code":"PPL",
    "gn:name":"L\u0101y Jan\u0101",
    "gn:population":0,
    "gn:timezone":"Asia/Tehran",
    "iso:country":"IR",
    "name:fas_x_preferred":[
        "\u0644\u0627\u06cc \u062c\u0646\u0627"
    ],
    "name:fas_x_variant":[
        "L\u0101-ye Han\u0101",
        "L\u0101y \u1e28an\u0101",
        "L\u0101y Jan\u0101",
        "\u0644\u0627\u06cc \u062d\u0646\u0627"
    ],
    "name:msa_x_preferred":[
        "Lay Hana"
    ],
    "wof:name":"Lay Jana",
    "wof:placetype":"locality"
},
  "geometry": {"coordinates":[54.2465,29.2064],"type":"Point"}
}