{
  "type": "Feature",
  "properties": {
    "gn:admin1_code":"7.0",
    "gn:asciiname":"`Alamdan-e Bala",
    "gn:country_code":"IR",
    "gn:dem":184,
    "gn:feature_class":"P",
    "gn:feature_code":"PPL",
    "gn:name":"\u2018Alamd\u0101n-e B\u0101l\u0101",
    "gn:population":0,
    "gn:timezone":"Asia/Tehran",
    "iso:country":"IR",
    "name:fas_x_preferred":[
        "\u0639\u0644\u0645\u062f\u0627\u0646 \u0628\u0627\u0644\u0627"
    ],
    "name:fas_x_variant":[
        "\u2018Alamd\u0101n-e \u2018Oly\u0101",
        "\u2018Alamd\u0101n-e B\u0101l\u0101"
    ],
    "wof:name":"`Alamdan-e Bala",
    "wof:placetype":"locality"
},
  "geometry": {"coordinates":[52.2456,28.1499],"type":"Point"}
}