{
  "type": "Feature",
  "properties": {
    "gn:admin1_code":"29",
    "gn:asciiname":"Dehdar-e Bidu",
    "gn:country_code":"IR",
    "gn:dem":421,
    "gn:feature_class":"P",
    "gn:feature_code":"PPL",
    "gn:name":"Dehdar-e B\u012bd\u016b",
    "gn:population":0,
    "gn:timezone":"Asia/Tehran",
    "iso:country":"IR",
    "name:fas_x_preferred":[
        "Dehdar-e B\u012bd\u016b"
    ],
    "wof:name":"Dehdar-e Bidu",
    "wof:placetype":"locality"
},
  "geometry": {"coordinates":[57.57556,27.19111],"type":"Point"}
}