{
  "type": "Feature",
  "properties": {
    "gn:admin1_code":"16",
    "gn:asciiname":"Bardrasheh",
    "gn:country_code":"IR",
    "gn:dem":1361,
    "gn:feature_class":"P",
    "gn:feature_code":"PPL",
    "gn:name":"Bardrasheh",
    "gn:population":0,
    "gn:timezone":"Asia/Tehran",
    "iso:country":"IR",
    "name:fas_x_preferred":[
        "\u0628\u0631\u062f\u0647 \u0631\u0634\u0647"
    ],
    "name:fas_x_variant":[
        "\u0628\u064e\u0631\u062f\u064e\u0647 \u0631\u064e\u0634\u064e\u0647",
        "\u0628\u0631\u062f\u0631\u0634\u0647"
    ],
    "name:und_x_variant":[
        "Bardah Rashah",
        "Bardeh Rasheh",
        "Bardrasheh"
    ],
    "wof:name":"Bardrasheh",
    "wof:placetype":"locality"
},
  "geometry": {"coordinates":[46.0914,35.5946],"type":"Point"}
}