{
  "type": "Feature",
  "properties": {
    "gn:admin1_code":"33",
    "gn:asciiname":"Cheraghlu",
    "gn:country_code":"IR",
    "gn:dem":1802,
    "gn:feature_class":"P",
    "gn:feature_code":"PPL",
    "gn:name":"Cher\u0101ghl\u016b",
    "gn:population":0,
    "gn:timezone":"Asia/Tehran",
    "iso:country":"IR",
    "name:fas_x_preferred":[
        "\u0686\u0631\u0627\u063a\u0644\u06cc"
    ],
    "name:fas_x_variant":[
        "Cher\u0101ghl\u016b",
        "Cher\u0101ghl\u012b",
        "\u0686\u0631\u0627\u063a\u0644\u0648"
    ],
    "name:msa_x_preferred":[
        "Cheraghlu"
    ],
    "wof:name":"Cheraghlu",
    "wof:placetype":"locality"
},
  "geometry": {"coordinates":[46.2402,38.3846],"type":"Point"}
}