{
  "type": "Feature",
  "properties": {
    "gn:admin1_code":"4",
    "gn:asciiname":"Hamzeh Jahan",
    "gn:country_code":"IR",
    "gn:dem":1185,
    "gn:feature_class":"P",
    "gn:feature_code":"PPL",
    "gn:name":"\u1e28amzeh Jah\u0101n",
    "gn:population":0,
    "gn:timezone":"Asia/Tehran",
    "iso:country":"IR",
    "name:fas_x_preferred":[
        "\u062d\u0645\u0632\u0647 \u062c\u0647\u0627\u0646"
    ],
    "name:fas_x_variant":[
        "\u1e28amzeh Jah\u0101n"
    ],
    "wof:name":"Hamzeh Jahan",
    "wof:placetype":"locality"
},
  "geometry": {"coordinates":[62.5942,26.8934],"type":"Point"}
}