{
  "type": "Feature",
  "properties": {
    "gn:admin1_code":"29.0",
    "gn:asciiname":"Dehgaran",
    "gn:country_code":"IR",
    "gn:dem":675,
    "gn:feature_class":"P",
    "gn:feature_code":"PPL",
    "gn:name":"Dehgar\u0101n",
    "gn:population":0,
    "gn:timezone":"Asia/Tehran",
    "iso:country":"IR",
    "name:fas_x_preferred":[
        "\u062f\u0647\u06af\u0631\u0627\u0646"
    ],
    "name:fas_x_variant":[
        "Deh Kar\u0101n",
        "Dehgar\u0101n"
    ],
    "wof:name":"Dehgaran",
    "wof:placetype":"locality"
},
  "geometry": {"coordinates":[57.8061,28.6711],"type":"Point"}
}