{
  "type": "Feature",
  "properties": {
    "gn:admin1_code":"13",
    "gn:asciiname":"Goleh Sorkheh",
    "gn:country_code":"IR",
    "gn:dem":1931,
    "gn:feature_class":"P",
    "gn:feature_code":"PPL",
    "gn:name":"Goleh Sorkheh",
    "gn:population":0,
    "gn:timezone":"Asia/Tehran",
    "iso:country":"IR",
    "name:ceb_x_preferred":[
        "Goleh Sorkheh"
    ],
    "name:fas_x_preferred":[
        "\u06af\u0644\u0647 \u0633\u0631\u062e\u0647"
    ],
    "name:fas_x_variant":[
        "\u06af\u0644 \u0633\u0631\u062e\u0647",
        "\u06af\u0644\u200c\u0633\u0631\u062e\u0647"
    ],
    "name:swe_x_preferred":[
        "Goleh Sorkheh"
    ],
    "name:und_x_variant":[
        "Qal\u2018eh-ye Sorkheh",
        "Gel-e Sorkheh",
        "Qal\u2018eh S\u016brkeh",
        "Gelah Sorkheh",
        "Gol Sorkheh",
        "Gel Sorkheh",
        "Goleh Sorkheh"
    ],
    "wof:name":"Goleh Sorkheh",
    "wof:placetype":"locality"
},
  "geometry": {"coordinates":[47.41613,35.03739],"type":"Point"}
}