{
  "type": "Feature",
  "properties": {
    "gn:admin1_code":"13",
    "gn:asciiname":"Takhtgah-e Safi Yar Soltan",
    "gn:country_code":"IR",
    "gn:dem":1429,
    "gn:feature_class":"P",
    "gn:feature_code":"PPL",
    "gn:name":"Takhtg\u0101h-e \u015eaf\u012b Y\u0101r Sol\u0163\u0101n",
    "gn:population":0,
    "gn:timezone":"Asia/Tehran",
    "iso:country":"IR",
    "name:ara_x_preferred":[
        "\u062a\u062e\u062a\u063a\u0627\u0629 \u0635\u0641\u064a\u0627\u0631 \u0633\u0644\u0637\u0627\u0646"
    ],
    "name:fas_x_preferred":[
        "\u062a\u062e\u062a\u06af\u0627\u0647 \u0635\u0641\u06cc \u06cc\u0627\u0631 \u0633\u0644\u0637\u0627\u0646"
    ],
    "name:fas_x_variant":[
        "Takhtg\u0101h-e \u015eaf\u012by\u0101r Sol\u0163\u0101n",
        "Takhtg\u0101h-e \u015eaf\u012b Y\u0101r Sol\u0163\u0101n",
        "\u062a\u062e\u062a\u06af\u0627\u0647 \u0635\u0641\u06cc\u0627\u0631 \u0633\u0644\u0637\u0627\u0646"
    ],
    "wof:name":"Takhtgah-e Safi Yar Soltan",
    "wof:placetype":"locality"
},
  "geometry": {"coordinates":[46.4435,34.4933],"type":"Point"}
}