{
  "type": "Feature",
  "properties": {
    "gn:admin1_code":"1.0",
    "gn:asciiname":"Mahall-e Ehdas-e Shahrak-e Shardari-ye Bukan",
    "gn:country_code":"IR",
    "gn:dem":1369,
    "gn:feature_class":"P",
    "gn:feature_code":"PPL",
    "gn:name":"Ma\u1e29all-e E\u1e29d\u0101s\u0304-e Shahrak-e Shard\u0101r\u012b-ye B\u016bk\u0101n",
    "gn:population":0,
    "gn:timezone":"Asia/Tehran",
    "iso:country":"IR",
    "name:fas_x_preferred":[
        "\u0645\u062d\u0644 \u0627\u062d\u062f\u0627\u062b \u0634\u0647\u0631\u06a9 \u0634\u0647\u0631\u062f\u0627\u0631\u06cc \u0628\u0648\u06a9\u0627\u0646"
    ],
    "name:fas_x_variant":[
        "Ma\u1e29all-e E\u1e29d\u0101s\u0304-e Shahrak-e Shard\u0101r\u012b-ye B\u016bk\u0101n"
    ],
    "wof:name":"Mahall-e Ehdas-e Shahrak-e Shardari-ye Bukan",
    "wof:placetype":"locality"
},
  "geometry": {"coordinates":[46.209,36.4853],"type":"Point"}
}