{
  "type": "Feature",
  "properties": {
    "gn:admin1_code":"7",
    "gn:asciiname":"Kal",
    "gn:country_code":"IR",
    "gn:dem":396,
    "gn:feature_class":"P",
    "gn:feature_code":"PPL",
    "gn:name":"K\u0101l",
    "gn:population":0,
    "gn:timezone":"Asia/Tehran",
    "iso:country":"IR",
    "name:bos_x_preferred":[
        "Kal"
    ],
    "name:ceb_x_preferred":[
        "Kal"
    ],
    "name:ces_x_preferred":[
        "Kal"
    ],
    "name:fas_x_preferred":[
        "\u06a9\u0627\u0644"
    ],
    "name:fas_x_variant":[
        "K\u0101l"
    ],
    "name:nld_x_preferred":[
        "Kal"
    ],
    "name:pol_x_preferred":[
        "Kal"
    ],
    "name:por_x_preferred":[
        "Kal"
    ],
    "name:slv_x_preferred":[
        "Kal"
    ],
    "name:swe_x_preferred":[
        "Kal"
    ],
    "name:tur_x_preferred":[
        "Kal"
    ],
    "name:uzb_x_preferred":[
        "Kal"
    ],
    "wof:name":"Kal",
    "wof:placetype":"locality"
},
  "geometry": {"coordinates":[53.8154,27.245],"type":"Point"}
}