{
  "type": "Feature",
  "properties": {
    "gn:admin1_code":"16.0",
    "gn:asciiname":"Ganjeh Nav",
    "gn:country_code":"IR",
    "gn:dem":1209,
    "gn:feature_class":"P",
    "gn:feature_code":"PPL",
    "gn:name":"Ganjeh N\u0101v",
    "gn:population":0,
    "gn:timezone":"Asia/Tehran",
    "iso:country":"IR",
    "name:fas_x_preferred":[
        "\u06af\u064e\u0646\u062c\u0650\u0647 \u0646\u0627\u0648"
    ],
    "name:fas_x_variant":[
        "Ganjeh N\u0101v"
    ],
    "wof:name":"Ganjeh Nav",
    "wof:placetype":"locality"
},
  "geometry": {"coordinates":[46.33333,35.18333],"type":"Point"}
}