{
  "type": "Feature",
  "properties": {
    "gn:admin1_code":"28",
    "gn:asciiname":"Tarqrud",
    "gn:country_code":"IR",
    "gn:dem":2052,
    "gn:feature_class":"P",
    "gn:feature_code":"PPL",
    "gn:name":"\u0162arqr\u016bd",
    "gn:population":0,
    "gn:timezone":"Asia/Tehran",
    "iso:country":"IR",
    "name:fas_x_preferred":[
        "\u0162arq"
    ],
    "name:fas_x_variant":[
        "\u0637\u0631\u0642",
        "\u0637\u0631\u0642\u0631\u0648\u062f"
    ],
    "name:und_x_variant":[
        "Tarkh",
        "\u0162arqr\u016bd"
    ],
    "wof:name":"Tarqrud",
    "wof:placetype":"locality"
},
  "geometry": {"coordinates":[51.79908,33.35353],"type":"Point"}
}