{
  "type": "Feature",
  "properties": {
    "gn:admin1_code":"1",
    "gn:asciiname":"Tazeh Kand-e Emam",
    "gn:country_code":"IR",
    "gn:dem":1279,
    "gn:feature_class":"P",
    "gn:feature_code":"PPL",
    "gn:name":"T\u0101zeh Kand-e Em\u0101m",
    "gn:population":0,
    "gn:timezone":"Asia/Tehran",
    "iso:country":"IR",
    "name:fas_x_preferred":[
        "\u062a\u0627\u0632\u0650\u0647 \u0643\u064e\u0646\u062f"
    ],
    "name:fas_x_variant":[
        "\u062a\u0627\u0632\u0647 \u06a9\u0646\u062f \u0627\u0645\u0627\u0645",
        "T\u0101zeh Kand",
        "T\u0101zeh Kand-e Em\u0101m"
    ],
    "wof:name":"Tazeh Kand-e Emam",
    "wof:placetype":"locality"
},
  "geometry": {"coordinates":[45.2477,37.4369],"type":"Point"}
}