{
  "type": "Feature",
  "properties": {
    "gn:admin1_code":"15.0",
    "gn:asciiname":"Manureh- ye Shay",
    "gn:country_code":"IR",
    "gn:dem":15,
    "gn:feature_class":"P",
    "gn:feature_code":"PPL",
    "gn:name":"Man\u016breh- ye Shay",
    "gn:population":0,
    "gn:timezone":"Asia/Tehran",
    "iso:country":"IR",
    "wof:name":"Manureh- ye Shay",
    "wof:placetype":"locality"
},
  "geometry": {"coordinates":[48.89056,30.78111],"type":"Point"}
}