{
  "type": "Feature",
  "properties": {
    "gn:admin1_code":"7",
    "gn:asciiname":"Bard-e Now",
    "gn:country_code":"IR",
    "gn:dem":1339,
    "gn:feature_class":"P",
    "gn:feature_code":"PPL",
    "gn:name":"Bard-e Now",
    "gn:population":0,
    "gn:timezone":"Asia/Tehran",
    "iso:country":"IR",
    "name:ara_x_preferred":[
        "\u0628\u0631\u062f\u0646\u0648"
    ],
    "name:fas_x_preferred":[
        "\u0628\u0631\u062f \u0646\u0648"
    ],
    "name:fas_x_variant":[
        "Bard\u016bnow",
        "\u0628\u0631\u062f\u0646\u0648"
    ],
    "name:msa_x_preferred":[
        "Bard-e Now"
    ],
    "wof:name":"Bard-e Now",
    "wof:placetype":"locality"
},
  "geometry": {"coordinates":[54.3898,28.8843],"type":"Point"}
}