{
  "type": "Feature",
  "properties": {
    "iso:country":"IR",
    "name:ara_x_preferred":[
        "\u0645\u0639\u0634\u0648\u0631"
    ],
    "name:azb_x_preferred":[
        "\u0628\u0646\u062f\u0631 \u0645\u0627\u0647\u0634\u0647\u0631"
    ],
    "name:aze_x_preferred":[
        "B\u0259nd\u0259r Mah\u015f\u0259hr"
    ],
    "name:bel_x_variant":[
        "\u041c\u0430\u0433\u0448\u0430\u0445\u0440"
    ],
    "name:ceb_x_preferred":[
        "Bandar-e M\u0101hshahr"
    ],
    "name:deu_x_preferred":[
        "Mahschahr"
    ],
    "name:ell_x_preferred":[
        "\u039c\u03c0\u03b1\u03bd\u03c4\u03ac\u03c1-\u03b5 \u039c\u03b1\u03c7\u03c3\u03ac\u03c7\u03c1"
    ],
    "name:eng_x_preferred":[
        "Bandar-e Mahshahr"
    ],
    "name:fas_x_preferred":[
        "\u0628\u0646\u062f\u0631 \u0645\u0627\u0647\u0634\u0647\u0631"
    ],
    "name:fas_x_variant":[
        "Markaz-e B\u0101rg\u012br\u012b-ye Bandar-e M\u0101h Shahr",
        "B\u0101r And\u0101z",
        "Bandar-e M\u0101hshahr"
    ],
    "name:fin_x_preferred":[
        "Bandar-e Mah\u0161ahr"
    ],
    "name:fra_x_preferred":[
        "Bandar-e Mahshahr"
    ],
    "name:hbs_x_preferred":[
        "Mah\u0161aher"
    ],
    "name:hin_x_preferred":[
        "\u092c\u0902\u0926\u0930-\u090f-\u092e\u093e\u0928\u0936\u0939\u0930"
    ],
    "name:ita_x_preferred":[
        "Mahshahr"
    ],
    "name:lit_x_preferred":[
        "Bandare Mah\u0161ahras"
    ],
    "name:lit_x_variant":[
        "Bender Mah\u0161ahras"
    ],
    "name:mlg_x_preferred":[
        "Bandar-e Mahshahr"
    ],
    "name:nld_x_preferred":[
        "Bandar-e Mahshahr"
    ],
    "name:nob_x_preferred":[
        "Bandar-e Mahshahr"
    ],
    "name:nor_x_preferred":[
        "Bandar-e Mahshahr"
    ],
    "name:pnb_x_preferred":[
        "\u0628\u0646\u062f\u0631 \u0645\u0627\u06c1 \u0634\u06c1\u0631"
    ],
    "name:pol_x_preferred":[
        "Bandar-e Mahszahr"
    ],
    "name:ron_x_preferred":[
        "Mahshahr"
    ],
    "name:rus_x_preferred":[
        "\u0411\u0435\u043d\u0434\u0435\u0440-\u041c\u0430\u0445\u0448\u0435\u0445\u0440"
    ],
    "name:swe_x_preferred":[
        "Bandar-e Mahshahr"
    ],
    "name:tgk_x_preferred":[
        "\u041c\u043e\u04b3\u0448\u0430\u04b3\u0440"
    ],
    "name:tur_x_preferred":[
        "Mah\u015fehr"
    ],
    "name:und_x_variant":[
        "M\u0101hshahr"
    ],
    "name:zho_x_preferred":[
        "\u99ac\u8d6b\u590f\u8d6b\u723e\u6e2f"
    ],
    "qs:gn_country":"IR",
    "qs:gn_fcode":"PPL",
    "qs:gn_pop":0,
    "qs:name":"Bandar-e Mahshahr",
    "qs:name_adm0":"Iran",
    "qs:name_adm1":"Khuzestan",
    "qs:photos":17,
    "qs:photos_1k":3,
    "qs:photos_9k":1,
    "qs:photos_9r":1,
    "qs:photos_all":17,
    "qs:photos_sr":1,
    "qs:placetype":"Town",
    "qs:pop_sr":"7",
    "qs:woe_adm0":23424851,
    "wd:wordcount":533,
    "wof:name":"Bandar-e Mahshahr",
    "wof:placetype":"locality"
},
  "geometry": {"coordinates":[49.1981,30.5588],"type":"Point"}
}