{
  "type": "Feature",
  "properties": {
    "gn:admin1_code":"11",
    "gn:asciiname":"Qalatu'iyeh",
    "gn:country_code":"IR",
    "gn:dem":1213,
    "gn:feature_class":"P",
    "gn:feature_code":"PPL",
    "gn:name":"Qal\u0101t\u016b\u2019\u012byeh",
    "gn:population":0,
    "gn:timezone":"Asia/Tehran",
    "iso:country":"IR",
    "name:fas_x_preferred":[
        "\u0642\u0644\u0627\u062a\u0648\u0626\u064a\u0647"
    ],
    "name:fas_x_variant":[
        "\u0642\u064e\u0644\u0627\u062a\u0648",
        "Qal\u0101t\u016b\u2019\u012byeh",
        "\u062a\u0646\u06af \u062f\u0648"
    ],
    "name:msa_x_preferred":[
        "Qalatuiyeh"
    ],
    "name:und_x_variant":[
        "Qal\u0101t\u016b",
        "Tang Do"
    ],
    "wof:name":"Qalatu'iyeh",
    "wof:placetype":"locality"
},
  "geometry": {"coordinates":[55.7123,28.4114],"type":"Point"}
}