{
  "type": "Feature",
  "properties": {
    "gn:admin1_code":"15",
    "gn:asciiname":"Rak`at-e Sofla",
    "gn:country_code":"IR",
    "gn:dem":839,
    "gn:feature_class":"P",
    "gn:feature_code":"PPL",
    "gn:name":"Rak\u2018at-e Sofl\u00e1",
    "gn:population":0,
    "gn:timezone":"Asia/Tehran",
    "iso:country":"IR",
    "name:fas_x_preferred":[
        "Rak\u2018at-e Sofl\u00e1"
    ],
    "name:fas_x_variant":[
        "\u0631\u06a9\u0639\u062a \u0633\u0641\u0644\u06cc"
    ],
    "name:und_x_variant":[
        "\u0631\u06a9\u0639\u062a \u0633\u0641\u0644\u06cc"
    ],
    "wof:name":"Rak`at-e Sofla",
    "wof:placetype":"locality"
},
  "geometry": {"coordinates":[50.1483,31.74996],"type":"Point"}
}