{
  "type": "Feature",
  "properties": {
    "gn:admin1_code":"23",
    "gn:asciiname":"Bajgiran",
    "gn:country_code":"IR",
    "gn:dem":1953,
    "gn:feature_class":"P",
    "gn:feature_code":"PPL",
    "gn:name":"B\u0101jg\u012br\u0101n",
    "gn:population":0,
    "gn:timezone":"Asia/Tehran",
    "iso:country":"IR",
    "name:fas_x_preferred":[
        "\u0628\u0627\u062c\u06af\u06cc\u0631\u0627\u0646"
    ],
    "name:fas_x_variant":[
        "B\u0101jg\u012br\u0101n"
    ],
    "name:und_x_variant":[
        "B\u0101jk\u012br\u0101n"
    ],
    "wof:name":"Bajgiran",
    "wof:placetype":"locality"
},
  "geometry": {"coordinates":[49.34259,33.66465],"type":"Point"}
}