{
  "type": "Feature",
  "properties": {
    "gn:admin1_code":"8",
    "gn:asciiname":"Solush",
    "gn:country_code":"IR",
    "gn:dem":6,
    "gn:feature_class":"P",
    "gn:feature_code":"PPL",
    "gn:name":"Sol\u016bsh",
    "gn:population":0,
    "gn:timezone":"Asia/Tehran",
    "iso:country":"IR",
    "name:fas_x_preferred":[
        "Sol\u016bsh"
    ],
    "name:fas_x_variant":[
        "\u0633\u0644\u0648\u0634"
    ],
    "name:und_x_variant":[
        "\u0633\u0644\u0648\u0634"
    ],
    "wof:name":"Solush",
    "wof:placetype":"locality"
},
  "geometry": {"coordinates":[50.17675,37.118],"type":"Point"}
}