{
  "type": "Feature",
  "properties": {
    "gn:admin1_code":"8",
    "gn:asciiname":"Solush",
    "gn:country_code":"IR",
    "gn:dem":6,
    "gn:feature_class":"P",
    "gn:feature_code":"PPL",
    "gn:name":"Sol\u016bsh",
    "gn:population":0,
    "gn:timezone":"Asia/Tehran",
    "iso:country":"IR",
    "name:ceb_x_preferred":[
        "Sol\u016bsh"
    ],
    "name:fas_x_preferred":[
        "Sol\u016bsh"
    ],
    "name:fas_x_variant":[
        "\u0633\u0644\u0648\u0634"
    ],
    "name:msa_x_preferred":[
        "Solush"
    ],
    "name:swe_x_preferred":[
        "Sol\u016bsh"
    ],
    "name:ukr_x_preferred":[
        "\u0421\u043e\u043b\u0443\u0448"
    ],
    "wof:name":"Solush",
    "wof:placetype":"locality"
},
  "geometry": {"coordinates":[50.17675,37.118],"type":"Point"}
}