{
  "type": "Feature",
  "properties": {
    "gn:admin1_code":"1.0",
    "gn:asciiname":"Qeshlaq-e Zeynal Kandi",
    "gn:country_code":"IR",
    "gn:dem":1284,
    "gn:feature_class":"P",
    "gn:feature_code":"PPL",
    "gn:name":"Qeshl\u0101q-e Zeyn\u0101l Kand\u012b",
    "gn:population":0,
    "gn:timezone":"Asia/Tehran",
    "iso:country":"IR",
    "name:azb_x_preferred":[
        "\u0642\u0634\u0644\u0627\u0642\u200c\u0632\u06cc\u0646\u0627\u0644\u200c\u06a9\u0646\u062f\u06cc(\u0642\u0648\u0634\u0627\u0686\u0627\u06cc)"
    ],
    "name:aze_x_preferred":[
        "Q\u0131\u015flaq-i Zeynalk\u0259ndi"
    ],
    "name:ceb_x_preferred":[
        "Qeshl\u0101q-e Zeyn\u0101l Kand\u012b"
    ],
    "name:fas_x_preferred":[
        "\u0642\u0634\u0644\u0627\u0642 \u0632\u06cc\u0646\u0627\u0644 \u06a9\u0646\u062f\u06cc"
    ],
    "name:fas_x_variant":[
        "Qeshl\u0101q-e Zeyn\u0101l Kand\u012b",
        "\u0642\u0634\u0644\u0627\u0642\u200c\u0632\u06cc\u0646\u0627\u0644\u200c\u06a9\u0646\u062f\u06cc"
    ],
    "name:msa_x_preferred":[
        "Qeshlaq-e Zeynal Kandi"
    ],
    "name:swe_x_preferred":[
        "Qeshl\u0101q-e Zeyn\u0101l Kand\u012b"
    ],
    "wof:name":"Qeshlaq-e Zeynal Kandi",
    "wof:placetype":"locality"
},
  "geometry": {"coordinates":[46.0048,36.9132],"type":"Point"}
}