{
  "type": "Feature",
  "properties": {
    "gn:admin1_code":"8",
    "gn:asciiname":"Sureh",
    "gn:country_code":"IR",
    "gn:dem":254,
    "gn:feature_class":"P",
    "gn:feature_code":"PPL",
    "gn:name":"S\u016breh",
    "gn:population":0,
    "gn:timezone":"Asia/Tehran",
    "iso:country":"IR",
    "name:fas_x_preferred":[
        "Kesht B\u012b"
    ],
    "name:fas_x_variant":[
        "\u0633\u0648\u0631\u0647",
        "\u06a9\u0634\u062a\u0645\u06cc"
    ],
    "name:und_x_variant":[
        "S\u016breh",
        "Keshtm\u012b"
    ],
    "wof:name":"Sureh",
    "wof:placetype":"locality"
},
  "geometry": {"coordinates":[48.809,37.82563],"type":"Point"}
}