{
  "type": "Feature",
  "properties": {
    "gn:admin1_code":"11.0",
    "gn:asciiname":"Palangan",
    "gn:country_code":"IR",
    "gn:dem":163,
    "gn:feature_class":"P",
    "gn:feature_code":"PPL",
    "gn:name":"Palang\u0101n",
    "gn:population":0,
    "gn:timezone":"Asia/Tehran",
    "iso:country":"IR",
    "name:fas_x_preferred":[
        "\u067e\u0644\u0646\u06af\u0627\u0646"
    ],
    "name:msa_x_preferred":[
        "Palangan"
    ],
    "name:und_x_variant":[
        "Palang\u0101n"
    ],
    "wof:name":"Palangan",
    "wof:placetype":"locality"
},
  "geometry": {"coordinates":[57.20762,27.30499],"type":"Point"}
}