{
  "type": "Feature",
  "properties": {
    "gn:admin1_code":"9",
    "gn:asciiname":"Saray-e Juq",
    "gn:country_code":"IR",
    "gn:dem":1974,
    "gn:feature_class":"P",
    "gn:feature_code":"PPL",
    "gn:name":"Sar\u0101y-e J\u016bq",
    "gn:population":0,
    "gn:timezone":"Asia/Tehran",
    "iso:country":"IR",
    "name:fas_x_preferred":[
        "\u0633\u0631\u0627\u064a\u062c\u0648\u0642"
    ],
    "name:fas_x_variant":[
        "Sar\u0101yjoq",
        "Sar\u0101yj\u016bq",
        "\u0633\u0631\u0627\u06cc \u062c\u0648\u0642"
    ],
    "name:und_x_variant":[
        "Saraj\u016bkh",
        "Sar\u0101y-e J\u016bq"
    ],
    "wof:name":"Saray-e Juq",
    "wof:placetype":"locality"
},
  "geometry": {"coordinates":[47.96155,35.42862],"type":"Point"}
}