{
  "type": "Feature",
  "properties": {
    "gn:admin1_code":"23",
    "gn:asciiname":"Shuleh",
    "gn:country_code":"IR",
    "gn:dem":1190,
    "gn:feature_class":"P",
    "gn:feature_code":"PPL",
    "gn:name":"Sh\u016bleh",
    "gn:population":0,
    "gn:timezone":"Asia/Tehran",
    "iso:country":"IR",
    "name:fas_x_preferred":[
        "\u0634\u0648\u0644\u0647"
    ],
    "name:fas_x_variant":[
        "\u0634\u0648\u0644 \u0622\u0628\u0627\u062f",
        "\u0634\u064f\u0651\u0644\u0650\u0647",
        "Sh\u016bleh"
    ],
    "name:und_x_variant":[
        "Sh\u016bl \u0100b\u0101d",
        "Shooleh"
    ],
    "wof:name":"Shuleh",
    "wof:placetype":"locality"
},
  "geometry": {"coordinates":[49.5648,32.72759],"type":"Point"}
}