{
  "type": "Feature",
  "properties": {
    "gn:admin1_code":"42",
    "gn:asciiname":"Mah Kariz",
    "gn:country_code":"IR",
    "gn:dem":1525,
    "gn:feature_class":"P",
    "gn:feature_code":"PPL",
    "gn:name":"M\u0101h K\u0101r\u012bz",
    "gn:population":0,
    "gn:timezone":"Asia/Tehran",
    "iso:country":"IR",
    "name:ara_x_preferred":[
        "\u0645\u0627\u0629 \u0643\u0627\u0631\u064a\u0632"
    ],
    "name:ceb_x_preferred":[
        "M\u0101h K\u0101r\u012bz"
    ],
    "name:fas_x_preferred":[
        "\u0645\u0627\u0647 \u06a9\u0627\u0631\u06cc\u0632"
    ],
    "name:fas_x_variant":[
        "M\u0101h K\u0101r\u012bz"
    ],
    "name:swe_x_preferred":[
        "M\u0101h K\u0101r\u012bz"
    ],
    "name:und_x_variant":[
        "Meh K\u0101r\u012bz"
    ],
    "wof:name":"Mah Kariz",
    "wof:placetype":"locality"
},
  "geometry": {"coordinates":[59.56298,35.8307],"type":"Point"}
}