{
  "type": "Feature",
  "properties": {
    "gn:admin1_code":"32.0",
    "gn:asciiname":"Jinqir Binehsi",
    "gn:country_code":"IR",
    "gn:dem":2006,
    "gn:feature_class":"P",
    "gn:feature_code":"PPL",
    "gn:name":"J\u012bnq\u012br B\u012bnehs\u012b",
    "gn:population":0,
    "gn:timezone":"Asia/Tehran",
    "iso:country":"IR",
    "name:fas_x_preferred":[
        "\u062c\u06cc\u0646\u0642\u06cc\u0631 \u0628\u06cc\u0646\u0647 \u0633\u06cc"
    ],
    "name:fas_x_variant":[
        "J\u012bnq\u012br B\u012bnehs\u012b"
    ],
    "wof:name":"Jinqir Binehsi",
    "wof:placetype":"locality"
},
  "geometry": {"coordinates":[48.0231,38.337],"type":"Point"}
}