{
  "type": "Feature",
  "properties": {
    "gn:admin1_code":"32",
    "gn:asciiname":"Qotur Bolagh",
    "gn:country_code":"IR",
    "gn:dem":702,
    "gn:feature_class":"P",
    "gn:feature_code":"PPL",
    "gn:name":"Qo\u0163\u016br Bol\u0101gh",
    "gn:population":0,
    "gn:timezone":"Asia/Tehran",
    "iso:country":"IR",
    "name:fas_x_preferred":[
        "\u0642\u0648\u062a\u0648\u0631 \u0628\u064f\u0644\u0627\u063a"
    ],
    "name:fas_x_variant":[
        "\u0642\u0637\u0648\u0631 \u0628\u0644\u0627\u063a",
        "Q\u016bt\u016br Bol\u0101gh",
        "Qo\u0163\u016br Bol\u0101gh"
    ],
    "name:und_x_variant":[
        "Qo\u0163\u016br Bol\u0101gh"
    ],
    "wof:name":"Qotur Bolagh",
    "wof:placetype":"locality"
},
  "geometry": {"coordinates":[47.9643,39.2233],"type":"Point"}
}