{
  "type": "Feature",
  "properties": {
    "gn:admin1_code":"33",
    "gn:asciiname":"Kalantar-e Sofla",
    "gn:country_code":"IR",
    "gn:dem":2138,
    "gn:feature_class":"P",
    "gn:feature_code":"PPL",
    "gn:name":"Kal\u0101ntar-e Sofl\u00e1",
    "gn:population":0,
    "gn:timezone":"Asia/Tehran",
    "iso:country":"IR",
    "name:fas_x_preferred":[
        "\u06a9\u0644\u0627\u0646\u062a\u0631"
    ],
    "name:fas_x_variant":[
        "Kal\u0101ntar-e Sofl\u00e1",
        "Kal\u0101ntar",
        "\u06a9\u0644\u0627\u0646\u062a\u0631 \u0633\u0641\u0644\u06cc",
        "\u06a9\u0644\u0627\u0646\u062a\u0631 \u067e\u0627\u067e\u0627\u0644\u0648",
        "\u06a9\u0644\u0627\u0646\u062a\u0631 \u063a\u0644\u0627\u0645",
        "\u06a9\u0644\u0627\u0646\u062a\u0631 \u0639\u0644\u064a\u0627"
    ],
    "name:und_x_variant":[
        "Kal\u0101ntar-e P\u0101p\u0101l\u016b",
        "Kal\u0101ntar-e Ghol\u0101m",
        "Kal\u0101ntar-e \u2018Oly\u0101"
    ],
    "wof:name":"Kalantar-e Sofla",
    "wof:placetype":"locality"
},
  "geometry": {"coordinates":[47.8239,38.0697],"type":"Point"}
}