{
  "type": "Feature",
  "properties": {
    "gn:admin1_code":"4.0",
    "gn:asciiname":"Nook Abad",
    "gn:country_code":"IR",
    "gn:dem":737,
    "gn:feature_class":"P",
    "gn:feature_code":"PPL",
    "gn:name":"Nook Abad",
    "gn:population":0,
    "gn:timezone":"Asia/Tehran",
    "iso:country":"IR",
    "name:fas_x_preferred":[
        "\u0646\u0648\u06a9 \u0622\u0628\u0627\u062f"
    ],
    "name:fas_x_variant":[
        "N\u016bk\u0101b\u0101d",
        "Nowk\u0101b\u0101d"
    ],
    "name:und_x_variant":[
        "Nowk\u0101b\u0101d"
    ],
    "wof:name":"Nook Abad",
    "wof:placetype":"locality"
},
  "geometry": {"coordinates":[60.88325,27.13088],"type":"Point"}
}