{
  "type": "Feature",
  "properties": {
    "gn:admin1_code":"33",
    "gn:asciiname":"Qarah Qayah",
    "gn:country_code":"IR",
    "gn:dem":583,
    "gn:feature_class":"P",
    "gn:feature_code":"PPL",
    "gn:name":"Qarah Qayah",
    "gn:population":0,
    "gn:timezone":"Asia/Tehran",
    "iso:country":"IR",
    "name:ara_x_preferred":[
        "\u0642\u0631\u0629 \u0642\u064a\u0629 \u0634\u0627\u06a9\u0631 \u0644\u0648"
    ],
    "name:ceb_x_preferred":[
        "Qarah Qayah"
    ],
    "name:fas_x_preferred":[
        "\u0642\u064e\u0631\u064e\u0647 \u0642\u064e\u064a\u064e\u06c0 \u0634\u064e\u0643\u064e\u0631\u0644\u0648"
    ],
    "name:fas_x_variant":[
        "\u0642\u0631\u0647 \u0642\u064a\u0647",
        "Qarah Qayah-ye Shakarl\u016b",
        "\u0642\u0631\u0647\u200c\u0642\u06cc\u0647 \u0634\u06a9\u0631\u0644\u0648"
    ],
    "name:msa_x_preferred":[
        "Qarah Qayah-ye Shakarlu"
    ],
    "name:swe_x_preferred":[
        "Qarah Qayah"
    ],
    "wof:name":"Qarah Qayah",
    "wof:placetype":"locality"
},
  "geometry": {"coordinates":[47.3357,39.1294],"type":"Point"}
}