{
  "type": "Feature",
  "properties": {
    "gn:admin1_code":"4",
    "gn:asciiname":"Allahabad",
    "gn:country_code":"IR",
    "gn:dem":1597,
    "gn:feature_class":"P",
    "gn:feature_code":"PPL",
    "gn:name":"All\u0101h\u0101b\u0101d",
    "gn:population":0,
    "gn:timezone":"Asia/Tehran",
    "iso:country":"IR",
    "name:fas_x_preferred":[
        "\u0627\u0644\u0644\u0651\u0647 \u0622\u0628\u0627\u062f"
    ],
    "name:fas_x_variant":[
        "All\u0101h\u0101b\u0101d"
    ],
    "wof:name":"Allahabad",
    "wof:placetype":"locality"
},
  "geometry": {"coordinates":[60.5179,28.7403],"type":"Point"}
}