{
  "type": "Feature",
  "properties": {
    "gn:admin1_code":"23",
    "gn:asciiname":"Chaqadun",
    "gn:country_code":"IR",
    "gn:dem":1559,
    "gn:feature_class":"P",
    "gn:feature_code":"PPL",
    "gn:name":"Chaq\u0101d\u016bn",
    "gn:population":0,
    "gn:timezone":"Asia/Tehran",
    "iso:country":"IR",
    "name:ara_x_preferred":[
        "\u062a\u0634\u063a\u0627\u062f\u0648\u0646"
    ],
    "name:ceb_x_preferred":[
        "Ch\u016bq\u0101d\u016bn"
    ],
    "name:fas_x_preferred":[
        "\u0686\u063a\u0627\u062f\u0648\u0646"
    ],
    "name:fas_x_variant":[
        "\u0686\u0648\u0642\u0627\u062f\u0648\u0646",
        "Chogh\u0101d\u016bn",
        "Ch\u016bq\u0101d\u016bn",
        "\u0686\u0642\u0627\u062f\u0648\u0646"
    ],
    "name:swe_x_preferred":[
        "Ch\u016bq\u0101d\u016bn"
    ],
    "name:und_x_variant":[
        "Ch\u016bgh\u0101d\u016bn",
        "Chaq\u0101d\u016bn"
    ],
    "wof:name":"Chaqadun",
    "wof:placetype":"locality"
},
  "geometry": {"coordinates":[49.16568,33.48836],"type":"Point"}
}