{
  "type": "Feature",
  "properties": {
    "gn:admin1_code":"29",
    "gn:asciiname":"Mohammadabad",
    "gn:country_code":"IR",
    "gn:dem":1672,
    "gn:feature_class":"P",
    "gn:feature_code":"PPLF",
    "gn:name":"Mo\u1e29ammad\u0101b\u0101d",
    "gn:population":0,
    "gn:timezone":"Asia/Tehran",
    "iso:country":"IR",
    "name:fas_x_preferred":[
        "Mo\u1e29ammad\u0101b\u0101d"
    ],
    "name:fas_x_variant":[
        "\u0645\u062d\u0645\u0651\u062f \u0622\u0628\u0627\u062f"
    ],
    "wof:name":"Mohammadabad",
    "wof:placetype":"locality"
},
  "geometry": {"coordinates":[56.61199000000001,30.24056],"type":"Point"}
}