{
  "type": "Feature",
  "properties": {
    "gn:admin1_code":"4.0",
    "gn:asciiname":"Rutak",
    "gn:country_code":"IR",
    "gn:dem":482,
    "gn:feature_class":"P",
    "gn:feature_code":"PPL",
    "gn:name":"R\u016btak",
    "gn:population":0,
    "gn:timezone":"Asia/Tehran",
    "iso:country":"IR",
    "name:fas_x_preferred":[
        "R\u016btak"
    ],
    "name:fas_x_variant":[
        "\u0631\u0648\u062a\u06a9"
    ],
    "name:und_x_variant":[
        "Zeyn od D\u012bn"
    ],
    "wof:name":"Rutak",
    "wof:placetype":"locality"
},
  "geometry": {"coordinates":[60.75828000000001,26.22325],"type":"Point"}
}