{
  "type": "Feature",
  "properties": {
    "gn:admin1_code":"13",
    "gn:asciiname":"Davaleh-ye Bergelah",
    "gn:country_code":"IR",
    "gn:dem":1426,
    "gn:feature_class":"P",
    "gn:feature_code":"PPL",
    "gn:name":"Dav\u0101leh-ye Bergelah",
    "gn:population":0,
    "gn:timezone":"Asia/Tehran",
    "iso:country":"IR",
    "name:fas_x_preferred":[
        "Dav\u0101leh-ye Bergelah"
    ],
    "wof:name":"Davaleh-ye Bergelah",
    "wof:placetype":"locality"
},
  "geometry": {"coordinates":[46.23333,34.76667],"type":"Point"}
}