{
  "type": "Feature",
  "properties": {
    "gn:admin1_code":"8",
    "gn:asciiname":"Siah Astalaskh-e Saqad ol Molk",
    "gn:cc2":"IR",
    "gn:country_code":"IR",
    "gn:dem":-21,
    "gn:feature_class":"P",
    "gn:feature_code":"PPL",
    "gn:name":"S\u012b\u0101h As\u0163alaskh-e S\u0304aqad ol Molk",
    "gn:population":0,
    "gn:timezone":"Asia/Tehran",
    "iso:country":"IR",
    "name:fas_x_preferred":[
        "S\u012b\u0101h As\u0163alaskh-e S\u0304aqad ol Molk"
    ],
    "name:und_x_variant":[
        "S\u012b\u0101h As\u0163alaskh"
    ],
    "wof:name":"Siah Astalaskh-e Saqad ol Molk",
    "wof:placetype":"locality"
},
  "geometry": {"coordinates":[49.75389000000001,37.41139],"type":"Point"}
}