{
  "type": "Feature",
  "properties": {
    "gn:admin1_code":"11.0",
    "gn:asciiname":"Do Bastu",
    "gn:country_code":"IR",
    "gn:dem":417,
    "gn:feature_class":"P",
    "gn:feature_code":"PPL",
    "gn:name":"Do Bast\u016b",
    "gn:population":0,
    "gn:timezone":"Asia/Tehran",
    "iso:country":"IR",
    "name:fas_x_preferred":[
        "D\u016bst\u016b"
    ],
    "name:fas_x_variant":[
        "\u062f\u0648\u0633\u062a\u0648",
        "\u062f\u0648 \u0628\u0633\u062a\u0648"
    ],
    "name:und_x_variant":[
        "Do Bast\u016b"
    ],
    "wof:name":"Do Bastu",
    "wof:placetype":"locality"
},
  "geometry": {"coordinates":[55.0348,27.17063],"type":"Point"}
}