{
  "type": "Feature",
  "properties": {
    "gn:admin1_code":"42.0",
    "gn:asciiname":"Chah-e Samad-e Pa'in",
    "gn:country_code":"IR",
    "gn:dem":885,
    "gn:feature_class":"P",
    "gn:feature_code":"PPLL",
    "gn:name":"Ch\u0101h-e \u015eamad-e P\u0101\u2019\u012bn",
    "gn:population":0,
    "gn:timezone":"Asia/Tehran",
    "iso:country":"IR",
    "name:fas_x_preferred":[
        "\u0686\u0627\u0647 \u0635\u0645\u062f \u067e\u0627\u0626\u064a\u0646"
    ],
    "name:fas_x_variant":[
        "\u0686\u0627\u0647 \u0639\u0645\u064a\u0642 \u0635\u0645\u062f \u067e\u0627\u0626\u064a\u0646"
    ],
    "name:und_x_variant":[
        "Ch\u0101h-e \u015eamad-e P\u0101\u2019\u012bn",
        "Ch\u0101h-e \u2018Am\u012bq \u015eamad-e P\u0101\u2019\u012bn"
    ],
    "wof:name":"Chah-e Samad-e Pa'in",
    "wof:placetype":"locality"
},
  "geometry": {"coordinates":[58.69411,34.9831],"type":"Point"}
}