{
  "type": "Feature",
  "properties": {
    "gn:admin1_code":"1",
    "gn:asciiname":"Gabakh Bolagh",
    "gn:country_code":"IR",
    "gn:dem":1824,
    "gn:feature_class":"P",
    "gn:feature_code":"PPL",
    "gn:name":"G\u0101b\u0101kh Bol\u0101gh",
    "gn:population":0,
    "gn:timezone":"Asia/Tehran",
    "iso:country":"IR",
    "name:fas_x_preferred":[
        "\u0642\u0627\u0628\u0627\u062e \u0628\u064f\u0644\u0627\u063a"
    ],
    "name:fas_x_variant":[
        "\u06af\u0627\u0628\u0627\u062e \u0628\u0644\u0627\u063a",
        "Q\u0101b\u0101kh Bol\u0101gh",
        "G\u0101b\u0101kh Bol\u0101gh"
    ],
    "wof:name":"Gabakh Bolagh",
    "wof:placetype":"locality"
},
  "geometry": {"coordinates":[44.8289,39.0285],"type":"Point"}
}