{
  "type": "Feature",
  "properties": {
    "gn:admin1_code":"22",
    "gn:asciiname":"Bohr",
    "gn:country_code":"IR",
    "gn:dem":43,
    "gn:feature_class":"P",
    "gn:feature_code":"PPL",
    "gn:name":"Bohr",
    "gn:population":0,
    "gn:timezone":"Asia/Tehran",
    "iso:country":"IR",
    "name:ara_x_preferred":[
        "\u0628\u0647\u0631"
    ],
    "name:ceb_x_preferred":[
        "Bohr"
    ],
    "name:fas_x_preferred":[
        "\u0628\u0647\u0631"
    ],
    "name:fas_x_variant":[
        "\u0628\u0627\u0631"
    ],
    "name:msa_x_preferred":[
        "Bohr"
    ],
    "name:swe_x_preferred":[
        "Bohr"
    ],
    "name:und_x_variant":[
        "B\u0101r",
        "Bohr"
    ],
    "wof:name":"Bohr",
    "wof:placetype":"locality"
},
  "geometry": {"coordinates":[50.8994,29.5225],"type":"Point"}
}