{
  "type": "Feature",
  "properties": {
    "gn:admin1_code":"15",
    "gn:asciiname":"Seyreh",
    "gn:country_code":"IR",
    "gn:dem":15,
    "gn:feature_class":"P",
    "gn:feature_code":"PPL",
    "gn:name":"\u015eeyreh",
    "gn:population":0,
    "gn:timezone":"Asia/Tehran",
    "iso:country":"IR",
    "name:ara_x_preferred":[
        "\u0635\u064a\u0631\u0629"
    ],
    "name:azb_x_preferred":[
        "\u0635\u06cc\u0631\u0647(\u0627\u0647\u0648\u0627\u0632)"
    ],
    "name:ceb_x_preferred":[
        "\u015eeyreh"
    ],
    "name:fas_x_preferred":[
        "\u0635\u06cc\u0631\u0647"
    ],
    "name:fas_x_variant":[
        "\u015eeyreh"
    ],
    "name:swe_x_preferred":[
        "\u015eeyreh"
    ],
    "name:und_x_variant":[
        "Sirah",
        "Seyareh",
        "Sereh",
        "Seyreh"
    ],
    "wof:name":"Seyreh",
    "wof:placetype":"locality"
},
  "geometry": {"coordinates":[48.3727,31.0679],"type":"Point"}
}