{
  "type": "Feature",
  "properties": {
    "gn:admin1_code":"7.0",
    "gn:asciiname":"Konardan",
    "gn:country_code":"IR",
    "gn:dem":753,
    "gn:feature_class":"P",
    "gn:feature_code":"PPL",
    "gn:name":"Kon\u0101rd\u0101n",
    "gn:population":0,
    "gn:timezone":"Asia/Tehran",
    "iso:country":"IR",
    "name:fas_x_preferred":[
        "Kon\u0101rd\u0101n"
    ],
    "name:fas_x_variant":[
        "\u06a9\u0646\u0627\u0631\u062f\u0627\u0646"
    ],
    "name:msa_x_preferred":[
        "Konardan"
    ],
    "name:und_x_variant":[
        "\u06a9\u0646\u0627\u0631\u062f\u0627\u0646"
    ],
    "wof:name":"Konardan",
    "wof:placetype":"locality"
},
  "geometry": {"coordinates":[51.91231,29.04516],"type":"Point"}
}