{
  "type": "Feature",
  "properties": {
    "gn:admin1_code":"35.0",
    "gn:asciiname":"Kalnow-ye Sofla",
    "gn:country_code":"IR",
    "gn:dem":1184,
    "gn:feature_class":"P",
    "gn:feature_code":"PPL",
    "gn:name":"Kalnow-ye Sofl\u00e1",
    "gn:population":0,
    "gn:timezone":"Asia/Tehran",
    "iso:country":"IR",
    "name:fas_x_preferred":[
        "Kalenow-ye P\u0101\u2019\u012bn"
    ],
    "name:fas_x_variant":[
        "\u0643\u0644\u0646\u0648\u06cc \u067e\u0627\u0626\u064a\u0646",
        "\u06a9\u0644\u0646\u0648 \u0633\u0641\u0644\u06cc",
        "\u06a9\u0644\u0646\u0648 \u067e\u0627\u0626\u064a\u0646"
    ],
    "name:und_x_variant":[
        "Kalnow-ye Sofl\u00e1",
        "Kalnow-ye P\u0101\u2019\u012bn"
    ],
    "wof:name":"Kalnow-ye Sofla",
    "wof:placetype":"locality"
},
  "geometry": {"coordinates":[51.25738,36.51126],"type":"Point"}
}