{
  "type": "Feature",
  "properties": {
    "gn:admin1_code":"41.0",
    "gn:asciiname":"Avich",
    "gn:country_code":"IR",
    "gn:dem":1705,
    "gn:feature_class":"P",
    "gn:feature_code":"PPL",
    "gn:name":"\u0100v\u012bch",
    "gn:population":0,
    "gn:timezone":"Asia/Tehran",
    "iso:country":"IR",
    "name:fas_x_preferred":[
        "\u0622\u0648\u06cc\u0686"
    ],
    "name:fas_x_variant":[
        "\u0100v\u012bch"
    ],
    "name:und_x_variant":[
        "\u0100v\u012bz",
        "\u0100vach",
        "\u0100v\u012bsh",
        "Av\u012beh",
        "\u0100v\u012bj"
    ],
    "wof:name":"Avich",
    "wof:placetype":"locality"
},
  "geometry": {"coordinates":[59.02871999999999,33.54478],"type":"Point"}
}