{
  "type": "Feature",
  "properties": {
    "gn:admin1_code":"9",
    "gn:asciiname":"Lak Lak",
    "gn:country_code":"IR",
    "gn:dem":1531,
    "gn:feature_class":"P",
    "gn:feature_code":"PPL",
    "gn:name":"Lak Lak",
    "gn:population":0,
    "gn:timezone":"Asia/Tehran",
    "iso:country":"IR",
    "name:fas_x_preferred":[
        "\u0644\u06a9 \u0644\u06a9"
    ],
    "wof:name":"Lak Lak",
    "wof:placetype":"locality"
},
  "geometry": {"coordinates":[47.94433,34.66809],"type":"Point"}
}