{
  "type": "Feature",
  "properties": {
    "gn:admin1_code":"4.0",
    "gn:asciiname":"Deh-e Jangi Khan",
    "gn:country_code":"IR",
    "gn:dem":484,
    "gn:feature_class":"P",
    "gn:feature_code":"PPL",
    "gn:name":"Deh-e Jang\u012b Kh\u0101n",
    "gn:population":0,
    "gn:timezone":"Asia/Tehran",
    "iso:country":"IR",
    "name:fas_x_preferred":[
        "Deh-e Jang\u012b Kh\u0101n"
    ],
    "name:fas_x_variant":[
        "Jang\u012bkh\u016bn",
        "\u062f\u0647 \u062c\u0646\u06af\u06cc \u062e\u0627\u0646"
    ],
    "name:und_x_variant":[
        "\u062f\u0647 \u062c\u0646\u06af\u06cc \u062e\u0627\u0646"
    ],
    "wof:name":"Deh-e Jangi Khan",
    "wof:placetype":"locality"
},
  "geometry": {"coordinates":[61.77157,31.09691],"type":"Point"}
}