{
  "type": "Feature",
  "properties": {
    "gn:admin1_code":"35",
    "gn:asciiname":"Sangar",
    "gn:country_code":"IR",
    "gn:dem":1063,
    "gn:feature_class":"P",
    "gn:feature_code":"PPLF",
    "gn:name":"Sangar",
    "gn:population":0,
    "gn:timezone":"Asia/Tehran",
    "iso:country":"IR",
    "name:fas_x_preferred":[
        "\u0633\u0646\u06af\u0631"
    ],
    "name:und_x_variant":[
        "\u0633\u0646\u06af\u0631",
        "Sangar"
    ],
    "wof:name":"Sangar",
    "wof:placetype":"locality"
},
  "geometry": {"coordinates":[53.60795,36.40069],"type":"Point"}
}