{
  "type": "Feature",
  "properties": {
    "gn:admin1_code":"34",
    "gn:asciiname":"Kabud Kamar",
    "gn:country_code":"IR",
    "gn:dem":1744,
    "gn:feature_class":"P",
    "gn:feature_code":"PPL",
    "gn:name":"Kab\u016bd Kamar",
    "gn:population":0,
    "gn:timezone":"Asia/Tehran",
    "iso:country":"IR",
    "name:ceb_x_preferred":[
        "Kab\u016bd Kamar"
    ],
    "name:fas_x_preferred":[
        "\u06a9\u0628\u0648\u062f \u06a9\u0645\u0631"
    ],
    "name:fas_x_variant":[
        "Kab\u016bd Kamar"
    ],
    "name:swe_x_preferred":[
        "Kab\u016bd Kamar"
    ],
    "name:ukr_x_preferred":[
        "\u041a\u0430\u0431\u0443\u0434-\u041a\u0430\u043c\u0430\u0440"
    ],
    "name:und_x_variant":[
        "Kukmar"
    ],
    "wof:name":"Kabud Kamar",
    "wof:placetype":"locality"
},
  "geometry": {"coordinates":[49.97507,35.43646],"type":"Point"}
}