{
  "type": "Feature",
  "properties": {
    "gn:admin1_code":"29",
    "gn:asciiname":"Chah Chupan",
    "gn:country_code":"IR",
    "gn:dem":532,
    "gn:feature_class":"P",
    "gn:feature_code":"PPL",
    "gn:name":"Ch\u0101h Ch\u016bp\u0101n",
    "gn:population":0,
    "gn:timezone":"Asia/Tehran",
    "iso:country":"IR",
    "name:fas_x_preferred":[
        "\u0686\u0627\u0647 \u0686\u0648\u067e\u0627\u0646"
    ],
    "name:fas_x_variant":[
        "Ch\u0101h Ch\u016bp\u0101n"
    ],
    "wof:name":"Chah Chupan",
    "wof:placetype":"locality"
},
  "geometry": {"coordinates":[57.44600000000001,27.8827],"type":"Point"}
}