{
  "type": "Feature",
  "properties": {
    "gn:admin1_code":"15.0",
    "gn:asciiname":"Bahmanabad",
    "gn:country_code":"IR",
    "gn:dem":813,
    "gn:feature_class":"P",
    "gn:feature_code":"PPL",
    "gn:name":"Bahman\u0101b\u0101d",
    "gn:population":0,
    "gn:timezone":"Asia/Tehran",
    "iso:country":"IR",
    "name:fas_x_preferred":[
        "Bahman\u0101b\u0101d"
    ],
    "name:fas_x_variant":[
        "\u0628\u0647\u0645\u0646 \u0622\u0628\u0627\u062f"
    ],
    "name:und_x_variant":[
        "\u0628\u0647\u0645\u0646 \u0622\u0628\u0627\u062f"
    ],
    "wof:name":"Bahmanabad",
    "wof:placetype":"locality"
},
  "geometry": {"coordinates":[49.53239,32.20022],"type":"Point"}
}