{
  "type": "Feature",
  "properties": {
    "gn:admin1_code":"11",
    "gn:asciiname":"Kamkorukhan",
    "gn:cc2":"IR",
    "gn:country_code":"IR",
    "gn:dem":586,
    "gn:feature_class":"P",
    "gn:feature_code":"PPL",
    "gn:name":"Kamkor\u016bkh\u0101n",
    "gn:population":0,
    "gn:timezone":"Asia/Tehran",
    "iso:country":"IR",
    "name:fas_x_preferred":[
        "Kamkor\u016bkh\u0101n"
    ],
    "name:und_x_variant":[
        "\u0100b K\u0101sh"
    ],
    "wof:name":"Kamkorukhan",
    "wof:placetype":"locality"
},
  "geometry": {"coordinates":[58.18333000000001,26.23333],"type":"Point"}
}