{
  "type": "Feature",
  "properties": {
    "gn:admin1_code":"15",
    "gn:asciiname":"Karim Musa",
    "gn:country_code":"IR",
    "gn:dem":753,
    "gn:feature_class":"P",
    "gn:feature_code":"PPL",
    "gn:name":"Kar\u012bm M\u016bs\u00e1",
    "gn:population":0,
    "gn:timezone":"Asia/Tehran",
    "iso:country":"IR",
    "name:ara_x_preferred":[
        "\u0643\u0631\u064a\u0645 \u0645\u0648\u0633\u0649"
    ],
    "name:fas_x_preferred":[
        "Kar\u012bm M\u016bs\u00e1"
    ],
    "name:fas_x_variant":[
        "\u06a9\u0631\u06cc\u0645 \u0645\u0648\u0633\u06cc",
        "\u06a9\u0631\u06cc\u0645\u200c\u0645\u0648\u0633\u06cc"
    ],
    "name:ita_x_preferred":[
        "Karim Musa"
    ],
    "name:und_x_variant":[
        "\u06a9\u0631\u06cc\u0645 \u0645\u0648\u0633\u06cc"
    ],
    "wof:name":"Karim Musa",
    "wof:placetype":"locality"
},
  "geometry": {"coordinates":[49.50678,32.20522],"type":"Point"}
}