{
  "type": "Feature",
  "properties": {
    "gn:admin1_code":"29",
    "gn:asciiname":"Seyf",
    "gn:country_code":"IR",
    "gn:dem":1458,
    "gn:feature_class":"P",
    "gn:feature_code":"PPL",
    "gn:name":"Seyf",
    "gn:population":0,
    "gn:timezone":"Asia/Tehran",
    "iso:country":"IR",
    "name:fas_x_preferred":[
        "\u0635\u0641\u06cc \u0622\u0628\u0627\u062f"
    ],
    "name:fas_x_variant":[
        "\u015eaf\u012b\u0101b\u0101d"
    ],
    "name:und_x_variant":[
        "Saf\u012bel"
    ],
    "wof:name":"Seyf",
    "wof:placetype":"locality"
},
  "geometry": {"coordinates":[55.8457,30.4416],"type":"Point"}
}