{
  "type": "Feature",
  "properties": {
    "gn:admin1_code":"8.0",
    "gn:asciiname":"Seyqalan Rudbar",
    "gn:country_code":"IR",
    "gn:dem":-20,
    "gn:feature_class":"P",
    "gn:feature_code":"PPL",
    "gn:name":"\u015eeyqal\u0101n R\u016bdb\u0101r",
    "gn:population":0,
    "gn:timezone":"Asia/Tehran",
    "iso:country":"IR",
    "name:fas_x_preferred":[
        "\u015eeyqal\u0101n R\u016bdb\u0101r"
    ],
    "name:fas_x_variant":[
        "\u0635\u06cc\u0642\u0644\u0627\u0646 \u0631\u0648\u062f\u0628\u0627\u0631"
    ],
    "name:und_x_variant":[
        "\u0635\u06cc\u0642\u0644\u0627\u0646 \u0631\u0648\u062f\u0628\u0627\u0631"
    ],
    "wof:name":"Seyqalan Rudbar",
    "wof:placetype":"locality"
},
  "geometry": {"coordinates":[49.54316,37.33294],"type":"Point"}
}