{
  "type": "Feature",
  "properties": {
    "gn:admin1_code":"35",
    "gn:asciiname":"Pachi",
    "gn:country_code":"IR",
    "gn:dem":1089,
    "gn:feature_class":"P",
    "gn:feature_code":"PPL",
    "gn:name":"P\u0101ch\u012b",
    "gn:population":0,
    "gn:timezone":"Asia/Tehran",
    "iso:country":"IR",
    "name:ceb_x_preferred":[
        "Pachi"
    ],
    "name:fas_x_preferred":[
        "\u067e\u0627\u0686\u06cc"
    ],
    "name:fas_x_variant":[
        "\u067e\u0627\u062c\u06cc",
        "P\u0101ch\u012b"
    ],
    "name:swe_x_preferred":[
        "Pachi"
    ],
    "name:und_x_variant":[
        "P\u0101j\u012b"
    ],
    "wof:name":"Pachi",
    "wof:placetype":"locality"
},
  "geometry": {"coordinates":[53.27303000000001,36.08387000000001],"type":"Point"}
}