{
  "type": "Feature",
  "properties": {
    "gn:admin1_code":"42",
    "gn:asciiname":"Motor Ab-e Golshanabad",
    "gn:country_code":"IR",
    "gn:dem":1437,
    "gn:feature_class":"P",
    "gn:feature_code":"PPL",
    "gn:name":"Motor \u0100b-e Golshan\u0101b\u0101d",
    "gn:population":0,
    "gn:timezone":"Asia/Tehran",
    "iso:country":"IR",
    "name:fas_x_preferred":[
        "Motor \u0100b-e Golshan\u0101b\u0101d"
    ],
    "wof:name":"Motor Ab-e Golshanabad",
    "wof:placetype":"locality"
},
  "geometry": {"coordinates":[58.61611,36.80056],"type":"Point"}
}