{
  "type": "Feature",
  "properties": {
    "gn:admin1_code":"22",
    "gn:asciiname":"Qal`eh-ye Seyyed",
    "gn:country_code":"IR",
    "gn:dem":7,
    "gn:feature_class":"P",
    "gn:feature_code":"PPL",
    "gn:name":"Qal\u2018eh-ye Seyyed",
    "gn:population":0,
    "gn:timezone":"Asia/Tehran",
    "iso:country":"IR",
    "name:fas_x_preferred":[
        "\u0642\u064e\u0644\u0639\u0650\u06c0 \u0633\u0650\u064a\u0650\u0651\u062f"
    ],
    "name:fas_x_variant":[
        "Qal\u2018eh-ye Seyyed"
    ],
    "wof:name":"Qal`eh-ye Seyyed",
    "wof:placetype":"locality"
},
  "geometry": {"coordinates":[50.56444000000001,29.59694],"type":"Point"}
}