{
  "type": "Feature",
  "properties": {
    "gn:admin1_code":"13",
    "gn:asciiname":"Qeshlaq-e Namdar",
    "gn:country_code":"IR",
    "gn:dem":1289,
    "gn:feature_class":"P",
    "gn:feature_code":"PPL",
    "gn:name":"Qeshlaq-e Namdar",
    "gn:population":0,
    "gn:timezone":"Asia/Tehran",
    "iso:country":"IR",
    "wof:name":"Qeshlaq-e Namdar",
    "wof:placetype":"locality"
},
  "geometry": {"coordinates":[46.1219,34.0667],"type":"Point"}
}