{
  "type": "Feature",
  "properties": {
    "gn:admin1_code":"29.0",
    "gn:asciiname":"Deh-e Sheykh",
    "gn:country_code":"IR",
    "gn:dem":639,
    "gn:feature_class":"P",
    "gn:feature_code":"PPL",
    "gn:name":"Deh-e Sheykh",
    "gn:population":0,
    "gn:timezone":"Asia/Tehran",
    "iso:country":"IR",
    "name:fas_x_preferred":[
        "\u062f\u0647 \u0634\u06cc\u062e"
    ],
    "wof:name":"Deh-e Sheykh",
    "wof:placetype":"locality"
},
  "geometry": {"coordinates":[57.7472,28.6169],"type":"Point"}
}