{
  "type": "Feature",
  "properties": {
    "gn:admin1_code":"42",
    "gn:asciiname":"Char Takab",
    "gn:country_code":"IR",
    "gn:dem":1707,
    "gn:feature_class":"P",
    "gn:feature_code":"PPL",
    "gn:name":"Ch\u0101r Tak\u0101b",
    "gn:population":0,
    "gn:timezone":"Asia/Tehran",
    "iso:country":"IR",
    "name:ara_x_preferred":[
        "\u062a\u0634\u0647\u0627\u0631\u062a\u0643\u0627\u0628"
    ],
    "name:ceb_x_preferred":[
        "Ch\u0101r Tak\u0101b"
    ],
    "name:fas_x_preferred":[
        "\u0686\u0647\u0627\u0631 \u062a\u06a9\u0627\u0628"
    ],
    "name:fas_x_variant":[
        "Chah\u0101r Tak\u0101b",
        "\u0686\u0627\u0631 \u062a\u06a9\u0627\u0628",
        "\u0686\u0647\u0627\u0631\u062a\u06a9\u0627\u0628"
    ],
    "name:swe_x_preferred":[
        "Ch\u0101r Tak\u0101b"
    ],
    "name:und_x_variant":[
        "Chah\u0101r \u0162\u0101q",
        "Cheh\u0101r T\u0101gu",
        "Ch\u0101r Tak\u0101b"
    ],
    "wof:name":"Char Takab",
    "wof:placetype":"locality"
},
  "geometry": {"coordinates":[59.88803000000001,35.4986],"type":"Point"}
}