{
  "type": "Feature",
  "properties": {
    "gn:admin1_code":"29",
    "gn:asciiname":"Kahnuj",
    "gn:country_code":"IR",
    "gn:dem":271,
    "gn:feature_class":"P",
    "gn:feature_code":"PPL",
    "gn:name":"Kahn\u016bj",
    "gn:population":0,
    "gn:timezone":"Asia/Tehran",
    "iso:country":"IR",
    "name:ara_x_preferred":[
        "\u0643\u0647\u0646\u0648\u062c"
    ],
    "name:aze_x_preferred":[
        "K\u0259hnuc"
    ],
    "name:epo_x_preferred":[
        "Kahnu\u011d"
    ],
    "name:fas_x_preferred":[
        "Kahn\u016bj"
    ],
    "name:fas_x_variant":[
        "\u06a9\u0647\u0646\u0648\u062c"
    ],
    "name:ita_x_preferred":[
        "Kahnuj"
    ],
    "name:mlg_x_preferred":[
        "Kahnuj"
    ],
    "name:rus_x_preferred":[
        "\u041a\u0435\u0445\u043d\u0443\u0434\u0436"
    ],
    "name:tgk_x_preferred":[
        "\u041a\u0430\u04b3\u043d\u04ef\u04b7"
    ],
    "name:tur_x_preferred":[
        "Kahnuj"
    ],
    "wof:name":"Kahnuj",
    "wof:placetype":"locality"
},
  "geometry": {"coordinates":[58.10471999999999,30.06361],"type":"Point"}
}