{
  "type": "Feature",
  "properties": {
    "gn:admin1_code":"29",
    "gn:asciiname":"Kahnuj",
    "gn:country_code":"IR",
    "gn:dem":271,
    "gn:feature_class":"P",
    "gn:feature_code":"PPL",
    "gn:name":"Kahn\u016bj",
    "gn:population":0,
    "gn:timezone":"Asia/Tehran",
    "iso:country":"IR",
    "name:fas_x_preferred":[
        "Kahn\u016bj"
    ],
    "wof:name":"Kahnuj",
    "wof:placetype":"locality"
},
  "geometry": {"coordinates":[58.10471999999999,30.06361],"type":"Point"}
}