{
  "type": "Feature",
  "properties": {
    "gn:admin1_code":"5",
    "gn:asciiname":"Ab Zahli-e Tarza'i",
    "gn:country_code":"IR",
    "gn:dem":1802,
    "gn:feature_class":"P",
    "gn:feature_code":"PPL",
    "gn:name":"\u0100b Zahl\u012b-e T\u0101r\u1e95\u0101\u2019\u012b",
    "gn:population":0,
    "gn:timezone":"Asia/Tehran",
    "iso:country":"IR",
    "name:fas_x_preferred":[
        "\u0100bz\u0101l\u012b-e K\u016bchak"
    ],
    "name:fas_x_variant":[
        "\u0622\u0628 \u0632\u0647\u0644\u06cc \u062a\u0627\u0631\u0636\u0627\u06cc\u06cc"
    ],
    "name:und_x_variant":[
        "\u0100b Zahl\u012b-e T\u0101r\u1e95\u0101\u2019\u012b"
    ],
    "wof:name":"Ab Zahli-e Tarza'i",
    "wof:placetype":"locality"
},
  "geometry": {"coordinates":[50.6623,31.17923],"type":"Point"}
}