{
  "type": "Feature",
  "properties": {
    "gn:admin1_code":"35.0",
    "gn:asciiname":"Banafsheh Deh",
    "gn:country_code":"IR",
    "gn:dem":1147,
    "gn:feature_class":"P",
    "gn:feature_code":"PPL",
    "gn:name":"Banafsheh Deh",
    "gn:population":0,
    "gn:timezone":"Asia/Tehran",
    "iso:country":"IR",
    "name:fas_x_preferred":[
        "\u0628\u0646\u0641\u0634\u0647 \u062f\u0647"
    ],
    "wof:name":"Banafsheh Deh",
    "wof:placetype":"locality"
},
  "geometry": {"coordinates":[51.24711,36.50395],"type":"Point"}
}