{
  "type": "Feature",
  "properties": {
    "gn:admin1_code":"36",
    "gn:asciiname":"Aznab",
    "gn:country_code":"IR",
    "gn:dem":1726,
    "gn:feature_class":"P",
    "gn:feature_code":"PPL",
    "gn:name":"Azn\u0101b",
    "gn:population":0,
    "gn:timezone":"Asia/Tehran",
    "iso:country":"IR",
    "name:fas_x_preferred":[
        "\u0627\u0632\u0646\u0627\u0628"
    ],
    "name:fas_x_variant":[
        "Azn\u0101b"
    ],
    "name:und_x_variant":[
        "Ezn\u0101b",
        "Aznau",
        "Aznow",
        "Az\u0304n\u016b",
        "Arb\u0101b"
    ],
    "wof:name":"Aznab",
    "wof:placetype":"locality"
},
  "geometry": {"coordinates":[49.21527,36.05578],"type":"Point"}
}