{
  "type": "Feature",
  "properties": {
    "gn:admin1_code":"33",
    "gn:asciiname":"Davah Yataqi-ye Kuranlu",
    "gn:country_code":"IR",
    "gn:dem":2041,
    "gn:feature_class":"P",
    "gn:feature_code":"PPL",
    "gn:name":"Davah Y\u0101t\u0101q\u012b-ye K\u016br\u0101nl\u016b",
    "gn:population":0,
    "gn:timezone":"Asia/Tehran",
    "iso:country":"IR",
    "name:ceb_x_preferred":[
        "Davah T\u0101q\u012b"
    ],
    "name:fas_x_preferred":[
        "\u062f\u0648\u0647 \u064a\u0627\u062a\u0627\u0642\u06cc"
    ],
    "name:fas_x_variant":[
        "\u062f\u0648\u0647 \u062a\u0627\u0642\u06cc",
        "Davah Y\u0101t\u0101q\u012b",
        "Davah T\u0101q\u012b",
        "\u062f\u0648\u0647 \u06cc\u0627\u062a\u0627\u0642\u06cc \u06a9\u0648\u0631\u0627\u0646\u0644\u0648",
        "\u062f\u0648\u0647\u200c\u06cc\u0627\u062a\u0627\u0642\u06cc"
    ],
    "name:msa_x_preferred":[
        "Davah Yataqi"
    ],
    "name:swe_x_preferred":[
        "Davah T\u0101q\u012b"
    ],
    "name:und_x_variant":[
        "Davah Y\u0101t\u0101q\u012b-ye K\u016br\u0101nl\u016b"
    ],
    "wof:name":"Davah Yataqi-ye Kuranlu",
    "wof:placetype":"locality"
},
  "geometry": {"coordinates":[47.31459,36.94491],"type":"Point"}
}