{
  "type": "Feature",
  "properties": {
    "gn:admin1_code":"41",
    "gn:asciiname":"Givak-e Pa'in",
    "gn:country_code":"IR",
    "gn:dem":1944,
    "gn:feature_class":"P",
    "gn:feature_code":"PPL",
    "gn:name":"G\u012bvak-e P\u0101\u2019\u012bn",
    "gn:population":0,
    "gn:timezone":"Asia/Tehran",
    "iso:country":"IR",
    "name:fas_x_preferred":[
        "Givak Pa\u2019in"
    ],
    "name:fas_x_variant":[
        "G\u012bvak-e P\u0101\u2019\u012bn",
        "\u06af\u064a\u0648\u06a9 \u067e\u0627\u0626\u064a\u0646",
        "Gey\u016bk Sofl\u00e1",
        "\u06af\u064a\u0648\u06a9 \u0633\u0641\u0644\u06cc"
    ],
    "name:und_x_variant":[
        "G\u012bvak-e Sofl\u00e1"
    ],
    "wof:name":"Givak-e Pa'in",
    "wof:placetype":"locality"
},
  "geometry": {"coordinates":[59.12401,32.79443],"type":"Point"}
}