{
  "type": "Feature",
  "properties": {
    "gn:admin1_code":"42",
    "gn:asciiname":"Khowrestaneh",
    "gn:country_code":"IR",
    "gn:dem":1187,
    "gn:feature_class":"P",
    "gn:feature_code":"PPL",
    "gn:name":"Khowrest\u0101neh",
    "gn:population":0,
    "gn:timezone":"Asia/Tehran",
    "iso:country":"IR",
    "name:fas_x_preferred":[
        "\u062e\u0648\u0631\u0633\u062a\u0627\u0646\u0647"
    ],
    "name:fas_x_variant":[
        "Khor\u0101s\u0101nak",
        "\u062e\u0631\u0627\u0633\u0627\u0646\u06a9"
    ],
    "name:und_x_variant":[
        "Khowrest\u0101neh"
    ],
    "wof:name":"Khowrestaneh",
    "wof:placetype":"locality"
},
  "geometry": {"coordinates":[59.38293,36.64476],"type":"Point"}
}