{
  "type": "Feature",
  "properties": {
    "gn:admin1_code":"36",
    "gn:asciiname":"Siakhman",
    "gn:country_code":"IR",
    "gn:dem":1780,
    "gn:feature_class":"P",
    "gn:feature_code":"PPL",
    "gn:name":"Siakhman",
    "gn:population":0,
    "gn:timezone":"Asia/Tehran",
    "iso:country":"IR",
    "name:azb_x_preferred":[
        "\u0633\u06cc\u0627\u0645\u0627\u0646"
    ],
    "name:ceb_x_preferred":[
        "Siakhman"
    ],
    "name:fas_x_preferred":[
        "\u0633\u06cc\u0627\u0645\u0627\u0646"
    ],
    "name:fas_x_variant":[
        "S\u012b\u0101m\u0101n"
    ],
    "name:swe_x_preferred":[
        "Siakhman"
    ],
    "name:und_x_variant":[
        "Sey\u0101m\u0101n",
        "S\u012b\u0101hm\u0101n"
    ],
    "wof:name":"Siakhman",
    "wof:placetype":"locality"
},
  "geometry": {"coordinates":[48.56542,36.21496],"type":"Point"}
}