{
  "type": "Feature",
  "properties": {
    "gn:admin1_code":"13",
    "gn:asciiname":"Beyuleh",
    "gn:country_code":"IR",
    "gn:dem":1179,
    "gn:feature_class":"P",
    "gn:feature_code":"PPL",
    "gn:name":"Bey\u016bleh",
    "gn:population":0,
    "gn:timezone":"Asia/Tehran",
    "iso:country":"IR",
    "name:fas_x_preferred":[
        "\u0628\u064a\u0644\u0648\u0644\u0647"
    ],
    "name:fas_x_variant":[
        "Bey\u016bleh"
    ],
    "wof:name":"Beyuleh",
    "wof:placetype":"locality"
},
  "geometry": {"coordinates":[46.3355,34.8387],"type":"Point"}
}