{
  "type": "Feature",
  "properties": {
    "gn:admin1_code":"15",
    "gn:asciiname":"Tall-e Asvad",
    "gn:country_code":"IR",
    "gn:dem":27,
    "gn:feature_class":"P",
    "gn:feature_code":"PPL",
    "gn:name":"Tall-e Asvad",
    "gn:population":0,
    "gn:timezone":"Asia/Tehran",
    "iso:country":"IR",
    "name:fas_x_preferred":[
        "\u062a\u0644 \u0627\u0633\u0648\u062f"
    ],
    "name:und_x_variant":[
        "Tel Aswad",
        "Tal Asvad",
        "Tal-e-Asvad",
        "Tall-e Asvad"
    ],
    "wof:name":"Tall-e Asvad",
    "wof:placetype":"locality"
},
  "geometry": {"coordinates":[49.33875,30.97041],"type":"Point"}
}