{
  "type": "Feature",
  "properties": {
    "gn:admin1_code":"41",
    "gn:asciiname":"Seyyedan",
    "gn:country_code":"IR",
    "gn:dem":1472,
    "gn:feature_class":"P",
    "gn:feature_code":"PPL",
    "gn:name":"Seyyed\u0101n",
    "gn:population":0,
    "gn:timezone":"Asia/Tehran",
    "iso:country":"IR",
    "name:fas_x_preferred":[
        "Seyyed\u0101n"
    ],
    "name:fas_x_variant":[
        "\u0633\u06cc\u062f\u0627\u0646",
        "S\u012bdu",
        "Seyd\u016bn",
        "Seyd\u016b"
    ],
    "name:und_x_variant":[
        "S\u012bdu",
        "Seyd\u016bn",
        "Seyd\u016b",
        "\u0633\u06cc\u062f\u0627\u0646"
    ],
    "wof:name":"Seyyedan",
    "wof:placetype":"locality"
},
  "geometry": {"coordinates":[58.82679,32.34967],"type":"Point"}
}