{
  "type": "Feature",
  "properties": {
    "gn:admin1_code":"7",
    "gn:asciiname":"Dowrag",
    "gn:country_code":"IR",
    "gn:dem":1263,
    "gn:feature_class":"P",
    "gn:feature_code":"PPL",
    "gn:name":"Dowrag",
    "gn:population":0,
    "gn:timezone":"Asia/Tehran",
    "iso:country":"IR",
    "name:fas_x_preferred":[
        "Dorag-e Cheshmeh Kon\u0101r\u012b"
    ],
    "name:fas_x_variant":[
        "\u062f\u0648\u0631\u06af",
        "\u062f\u0648\u0631\u06af \u0686\u0634\u0645\u0647 \u06a9\u0646\u0627\u0631\u06cc"
    ],
    "name:und_x_variant":[
        "Dowrag-e Cheshmeh Kon\u0101r\u012b"
    ],
    "wof:name":"Dowrag",
    "wof:placetype":"locality"
},
  "geometry": {"coordinates":[51.47782,30.30664],"type":"Point"}
}