{
  "type": "Feature",
  "properties": {
    "gn:admin1_code":"5.0",
    "gn:asciiname":"Tang Sangari",
    "gn:country_code":"IR",
    "gn:dem":2316,
    "gn:feature_class":"P",
    "gn:feature_code":"PPL",
    "gn:name":"Tang Sangar\u012b",
    "gn:population":0,
    "gn:timezone":"Asia/Tehran",
    "iso:country":"IR",
    "name:fas_x_preferred":[
        "Tang Sangar\u012b"
    ],
    "name:fas_x_variant":[
        "\u062a\u0646\u06af \u0633\u0646\u06af\u0631\u06cc"
    ],
    "name:und_x_variant":[
        "\u062a\u0646\u06af \u0633\u0646\u06af\u0631\u06cc"
    ],
    "wof:name":"Tang Sangari",
    "wof:placetype":"locality"
},
  "geometry": {"coordinates":[51.06999,31.02357],"type":"Point"}
}