{
  "type": "Feature",
  "properties": {
    "gn:admin1_code":"1",
    "gn:asciiname":"`Oliar Kandi",
    "gn:country_code":"IR",
    "gn:dem":1309,
    "gn:feature_class":"P",
    "gn:feature_code":"PPL",
    "gn:name":"\u2018Ol\u012b\u0101r Kand\u012b",
    "gn:population":0,
    "gn:timezone":"Asia/Tehran",
    "iso:country":"IR",
    "name:fas_x_preferred":[
        "\u0639\u0644\u06cc\u0627\u0631 \u06a9\u0646\u062f\u06cc"
    ],
    "name:fas_x_variant":[
        "\u2018Ol\u012b\u0101r Kand\u012b"
    ],
    "wof:name":"`Oliar Kandi",
    "wof:placetype":"locality"
},
  "geometry": {"coordinates":[46.2366,36.9251],"type":"Point"}
}