{
  "type": "Feature",
  "properties": {
    "gn:admin1_code":"8",
    "gn:asciiname":"Mahraman",
    "gn:country_code":"IR",
    "gn:dem":114,
    "gn:feature_class":"P",
    "gn:feature_code":"PPL",
    "gn:name":"Ma\u1e29ram\u0101n",
    "gn:population":0,
    "gn:timezone":"Asia/Tehran",
    "iso:country":"IR",
    "name:ceb_x_preferred":[
        "Ma\u1e29ram\u0101n"
    ],
    "name:fas_x_preferred":[
        "\u0645\u062d\u0631\u0645\u0627\u0646"
    ],
    "name:fas_x_variant":[
        "Ma\u1e29ram\u0101n"
    ],
    "name:msa_x_preferred":[
        "Mahraman"
    ],
    "name:swe_x_preferred":[
        "Ma\u1e29ram\u0101n"
    ],
    "name:ukr_x_preferred":[
        "\u041c\u0430\u0445\u0440\u0430\u043c\u0430\u043d"
    ],
    "wof:name":"Mahraman",
    "wof:placetype":"locality"
},
  "geometry": {"coordinates":[49.36869,37.08219],"type":"Point"}
}