{
  "type": "Feature",
  "properties": {
    "gn:admin1_code":"11",
    "gn:asciiname":"Mashahran",
    "gn:country_code":"IR",
    "gn:dem":13,
    "gn:feature_class":"P",
    "gn:feature_code":"PPL",
    "gn:name":"M\u0101shahr\u0101n",
    "gn:population":0,
    "gn:timezone":"Asia/Tehran",
    "iso:country":"IR",
    "name:fas_x_preferred":[
        "\u0645\u0627\u0634\u0647\u0631\u0627\u0646"
    ],
    "name:fas_x_variant":[
        "\u0645\u0627\u0634\u0647\u0631\u0627\u0646 \u0646\u0648",
        "M\u0101h Shahr\u0101n",
        "M\u0101shahr\u0101n-e Now"
    ],
    "name:und_x_variant":[
        "M\u0101shahr\u0101n",
        "M\u0101shehr\u0101n",
        "Espeng\u0101n",
        "Espang\u0101n"
    ],
    "wof:name":"Mashahran",
    "wof:placetype":"locality"
},
  "geometry": {"coordinates":[56.9622,27.1522],"type":"Point"}
}