{
  "type": "Feature",
  "properties": {
    "gn:admin1_code":"4.0",
    "gn:asciiname":"Gattig",
    "gn:country_code":"IR",
    "gn:dem":735,
    "gn:feature_class":"P",
    "gn:feature_code":"PPL",
    "gn:name":"Gatt\u012bg",
    "gn:population":0,
    "gn:timezone":"Asia/Tehran",
    "iso:country":"IR",
    "name:fas_x_preferred":[
        "Gatt\u012bg"
    ],
    "wof:name":"Gattig",
    "wof:placetype":"locality"
},
  "geometry": {"coordinates":[60.71222,26.09389],"type":"Point"}
}