{
  "type": "Feature",
  "properties": {
    "gn:admin1_code":"42.0",
    "gn:asciiname":"Chah-e Barandaz",
    "gn:country_code":"IR",
    "gn:dem":1163,
    "gn:feature_class":"P",
    "gn:feature_code":"PPL",
    "gn:name":"Ch\u0101h-e B\u0101r\u0101nd\u0101z",
    "gn:population":0,
    "gn:timezone":"Asia/Tehran",
    "iso:country":"IR",
    "name:fas_x_preferred":[
        "\u0686\u0627\u0647 \u0628\u0627\u0631\u0627\u0646\u062f\u0627\u0632"
    ],
    "name:und_x_variant":[
        "Ch\u0101h-e B\u0101r\u0101nd\u0101z"
    ],
    "wof:name":"Chah-e Barandaz",
    "wof:placetype":"locality"
},
  "geometry": {"coordinates":[57.18015,35.40912],"type":"Point"}
}