{
  "type": "Feature",
  "properties": {
    "gn:admin1_code":"11",
    "gn:asciiname":"Malu",
    "gn:country_code":"IR",
    "gn:dem":9,
    "gn:feature_class":"P",
    "gn:feature_code":"PPL",
    "gn:name":"Mal\u016b",
    "gn:population":0,
    "gn:timezone":"Asia/Tehran",
    "iso:country":"IR",
    "name:cat_x_preferred":[
        "Malu"
    ],
    "name:ell_x_preferred":[
        "\u039c\u03b1\u03bb\u03bf\u03cd"
    ],
    "name:fas_x_preferred":[
        "\u0645\u0648\u0644\u0648"
    ],
    "name:fas_x_variant":[
        "\u0645\u0644\u0648",
        "\u0628\u0646\u062f\u0631 \u0645\u0644\u0648"
    ],
    "name:fra_x_preferred":[
        "Malu"
    ],
    "name:hrv_x_preferred":[
        "Malu"
    ],
    "name:new_x_preferred":[
        "\u092e\u093e\u0932\u0941"
    ],
    "name:und_x_variant":[
        "M\u016bl\u016b",
        "Mal\u016b",
        "Bandar-e Mal\u016b"
    ],
    "wof:name":"Malu",
    "wof:placetype":"locality"
},
  "geometry": {"coordinates":[54.72922,26.51828],"type":"Point"}
}