{
  "type": "Feature",
  "properties": {
    "gn:admin1_code":"4.0",
    "gn:asciiname":"Bitab",
    "gn:country_code":"IR",
    "gn:dem":555,
    "gn:feature_class":"P",
    "gn:feature_code":"PPL",
    "gn:name":"B\u012bt\u0101b",
    "gn:population":0,
    "gn:timezone":"Asia/Tehran",
    "iso:country":"IR",
    "name:fas_x_preferred":[
        "\u0628\u06cc\u062a\u0627\u0628"
    ],
    "name:fas_x_variant":[
        "Poty\u0101b",
        "B\u012bt\u0101b",
        "\u0628\u06cc\u200c\u062a\u0627\u0628"
    ],
    "wof:name":"Bitab",
    "wof:placetype":"locality"
},
  "geometry": {"coordinates":[60.7051,26.1413],"type":"Point"}
}