{
  "type": "Feature",
  "properties": {
    "gn:admin1_code":"28.0",
    "gn:asciiname":"Qal`eh-ye Chum",
    "gn:country_code":"IR",
    "gn:dem":1557,
    "gn:feature_class":"P",
    "gn:feature_code":"PPL",
    "gn:name":"Qal\u2018eh-ye Ch\u016bm",
    "gn:population":0,
    "gn:timezone":"Asia/Tehran",
    "iso:country":"IR",
    "name:fas_x_preferred":[
        "Ch\u016bm"
    ],
    "name:fas_x_variant":[
        "\u0686\u0648\u0645",
        "\u0642\u0644\u0639\u0647 \u0686\u0648\u0645"
    ],
    "name:und_x_variant":[
        "\u0686\u0648\u0645",
        "Qal\u2018eh-e Ch\u016bm",
        "Qal\u2018eh-ye Ch\u016bm"
    ],
    "wof:name":"Qal`eh-ye Chum",
    "wof:placetype":"locality"
},
  "geometry": {"coordinates":[51.76392,32.58215999999999],"type":"Point"}
}