{
  "type": "Feature",
  "properties": {
    "gn:admin1_code":"23",
    "gn:asciiname":"Dar Balut",
    "gn:cc2":"IR",
    "gn:country_code":"IR",
    "gn:dem":2033,
    "gn:feature_class":"P",
    "gn:feature_code":"PPL",
    "gn:name":"D\u0101r Bal\u016b\u0163",
    "gn:population":0,
    "gn:timezone":"Asia/Tehran",
    "iso:country":"IR",
    "name:fas_x_preferred":[
        "\u062f\u0627\u0631 \u0628\u064e\u0644\u0648\u0637"
    ],
    "name:fas_x_variant":[
        "\u062f\u064e\u0631\u0650\u0651\u0647 \u0628\u064e\u0644\u0648\u0637\u0650\u0647",
        "\u062f\u0627\u0631 \u0628\u064e\u0644\u0651\u0648\u0637",
        "\u062f\u064e\u0631\u0650\u0651\u0647 \u0628\u064e\u0644\u0648\u0637",
        "\u062f\u064e\u0631\u0650\u0651\u0647 \u0628\u064e\u0644\u0651\u0648\u062a\u0650\u0647",
        "D\u0101r Bal\u016b\u0163",
        "\u062f\u0627\u0631\u0628\u0644\u0648\u0637"
    ],
    "name:und_x_variant":[
        "D\u0101r Ball\u016b\u0163",
        "Darreh Bal\u016b\u0163",
        "Darreh Bal\u016b\u0163eh",
        "Darreh Ball\u016bteh"
    ],
    "wof:name":"Dar Balut",
    "wof:placetype":"locality"
},
  "geometry": {"coordinates":[48.57944000000001,33.70556],"type":"Point"}
}