{
  "type": "Feature",
  "properties": {
    "gn:admin1_code":"42.0",
    "gn:asciiname":"Abgahi-ye Pa'in",
    "gn:country_code":"IR",
    "gn:dem":1492,
    "gn:feature_class":"P",
    "gn:feature_code":"PPL",
    "gn:name":"\u0100bg\u0101h\u012b-ye P\u0101\u2019\u012bn",
    "gn:population":0,
    "gn:timezone":"Asia/Tehran",
    "iso:country":"IR",
    "name:fas_x_preferred":[
        "\u0622\u0628\u06af\u0627\u0647\u06cc \u067e\u0627\u06cc\u06cc\u0646"
    ],
    "name:und_x_variant":[
        "\u0100bg\u0101h\u012b-ye P\u0101\u2019\u012bn"
    ],
    "wof:name":"Abgahi-ye Pa'in",
    "wof:placetype":"locality"
},
  "geometry": {"coordinates":[59.05412,36.92023],"type":"Point"}
}