{
  "type": "Feature",
  "properties": {
    "gn:admin1_code":"8.0",
    "gn:asciiname":"Pileh Mahalleh",
    "gn:country_code":"IR",
    "gn:dem":225,
    "gn:feature_class":"P",
    "gn:feature_code":"PPL",
    "gn:name":"P\u012bleh Ma\u1e29alleh",
    "gn:population":0,
    "gn:timezone":"Asia/Tehran",
    "iso:country":"IR",
    "name:ceb_x_preferred":[
        "P\u012bleh Ma\u1e29alleh"
    ],
    "name:fas_x_preferred":[
        "P\u012bleh Ma\u1e29alleh"
    ],
    "name:fas_x_variant":[
        "\u067e\u06cc\u0644\u0647 \u0645\u062d\u0644\u0647"
    ],
    "name:msa_x_preferred":[
        "Pileh Mahalleh"
    ],
    "name:swe_x_preferred":[
        "P\u012bleh Ma\u1e29alleh"
    ],
    "name:ukr_x_preferred":[
        "\u041f\u0456\u043b\u0435-\u041c\u0430\u0445\u0430\u043b\u0435"
    ],
    "wof:name":"Pileh Mahalleh",
    "wof:placetype":"locality"
},
  "geometry": {"coordinates":[50.04833,37.07611],"type":"Point"}
}