{
  "type": "Feature",
  "properties": {
    "gn:admin1_code":"8.0",
    "gn:asciiname":"Pileh Mahalleh",
    "gn:country_code":"IR",
    "gn:dem":225,
    "gn:feature_class":"P",
    "gn:feature_code":"PPL",
    "gn:name":"P\u012bleh Ma\u1e29alleh",
    "gn:population":0,
    "gn:timezone":"Asia/Tehran",
    "iso:country":"IR",
    "name:fas_x_preferred":[
        "P\u012bleh Ma\u1e29alleh"
    ],
    "wof:name":"Pileh Mahalleh",
    "wof:placetype":"locality"
},
  "geometry": {"coordinates":[50.04833,37.07611],"type":"Point"}
}