{
  "type": "Feature",
  "properties": {
    "gn:admin1_code":"32",
    "gn:asciiname":"Owjur",
    "gn:country_code":"IR",
    "gn:dem":2049,
    "gn:feature_class":"P",
    "gn:feature_code":"PPL",
    "gn:name":"Owj\u016br",
    "gn:population":0,
    "gn:timezone":"Asia/Tehran",
    "iso:country":"IR",
    "name:fas_x_preferred":[
        "\u0627\u0648\u062c\u0648\u0631"
    ],
    "name:fas_x_variant":[
        "L\u016bj\u016br",
        "Owj\u016br"
    ],
    "wof:name":"Owjur",
    "wof:placetype":"locality"
},
  "geometry": {"coordinates":[47.9765,38.1678],"type":"Point"}
}