{
  "type": "Feature",
  "properties": {
    "gn:admin1_code":"28.0",
    "gn:asciiname":"Kondez",
    "gn:country_code":"IR",
    "gn:dem":1527,
    "gn:feature_class":"P",
    "gn:feature_code":"PPL",
    "gn:name":"Kondez",
    "gn:population":0,
    "gn:timezone":"Asia/Tehran",
    "iso:country":"IR",
    "name:fas_x_preferred":[
        "\u06a9\u0646\u062f\u0632"
    ],
    "wof:name":"Kondez",
    "wof:placetype":"locality"
},
  "geometry": {"coordinates":[51.94301,33.51713],"type":"Point"}
}