{
  "type": "Feature",
  "properties": {
    "gn:admin1_code":"3",
    "gn:asciiname":"Ma`mureh",
    "gn:country_code":"IR",
    "gn:dem":2240,
    "gn:feature_class":"P",
    "gn:feature_code":"PPL",
    "gn:name":"Ma\u2018m\u016breh",
    "gn:population":0,
    "gn:timezone":"Asia/Tehran",
    "iso:country":"IR",
    "name:fas_x_preferred":[
        "\u0645\u0639\u0645\u0648\u0631\u0647"
    ],
    "name:fas_x_variant":[
        "Ma\u2018m\u016breh",
        "\u0645\u064e\u0639\u0645\u0648\u0631\u064e\u0647"
    ],
    "name:und_x_variant":[
        "Ma\u2018m\u016brah"
    ],
    "wof:name":"Ma`mureh",
    "wof:placetype":"locality"
},
  "geometry": {"coordinates":[51.15418,31.89056],"type":"Point"}
}