{
  "type": "Feature",
  "properties": {
    "gn:admin1_code":"11",
    "gn:asciiname":"Golestan",
    "gn:country_code":"IR",
    "gn:dem":228,
    "gn:feature_class":"P",
    "gn:feature_code":"PPL",
    "gn:name":"Golest\u0101n",
    "gn:population":0,
    "gn:timezone":"Asia/Tehran",
    "iso:country":"IR",
    "name:fas_x_preferred":[
        "\u06af\u0644\u0633\u062a\u0627\u0646"
    ],
    "name:fas_x_variant":[
        "Golest\u0101n"
    ],
    "wof:name":"Golestan",
    "wof:placetype":"locality"
},
  "geometry": {"coordinates":[56.455,27.5587],"type":"Point"}
}