{
  "type": "Feature",
  "properties": {
    "gn:admin1_code":"28",
    "gn:asciiname":"Qafar",
    "gn:country_code":"IR",
    "gn:dem":2554,
    "gn:feature_class":"P",
    "gn:feature_code":"PPL",
    "gn:name":"Qafar",
    "gn:population":0,
    "gn:timezone":"Asia/Tehran",
    "iso:country":"IR",
    "name:ara_x_preferred":[
        "\u0642\u0641\u0631"
    ],
    "name:fas_x_preferred":[
        "\u0642\u0641\u0631"
    ],
    "name:und_x_variant":[
        "Ghafr",
        "Qafar",
        "\u0642\u0641\u0631"
    ],
    "wof:name":"Qafar",
    "wof:placetype":"locality"
},
  "geometry": {"coordinates":[50.43484,33.05077],"type":"Point"}
}