{
  "type": "Feature",
  "properties": {
    "gn:admin1_code":"1",
    "gn:asciiname":"Qezelcheh Gol",
    "gn:country_code":"IR",
    "gn:dem":1267,
    "gn:feature_class":"P",
    "gn:feature_code":"PPL",
    "gn:name":"Qezelcheh Gol",
    "gn:population":0,
    "gn:timezone":"Asia/Tehran",
    "iso:country":"IR",
    "name:ara_x_preferred":[
        "\u0642\u0632\u0644\u062c\u0647\u063a\u0644"
    ],
    "name:aze_x_preferred":[
        "Q\u0131z\u0131lcag\u00f6l"
    ],
    "name:fas_x_preferred":[
        "\u0642\u0632\u0644\u0686\u0647 \u06af\u0644"
    ],
    "name:fas_x_variant":[
        "\u0642\u0632\u0644\u062c\u0647\u200c\u06af\u0644"
    ],
    "name:msa_x_preferred":[
        "Qezeljeh Gol"
    ],
    "wof:name":"Qezelcheh Gol",
    "wof:placetype":"locality"
},
  "geometry": {"coordinates":[45.1608,38.9113],"type":"Point"}
}