{
  "type": "Feature",
  "properties": {
    "gn:admin1_code":"42.0",
    "gn:asciiname":"Khak Shur",
    "gn:country_code":"IR",
    "gn:dem":1540,
    "gn:feature_class":"P",
    "gn:feature_code":"PPL",
    "gn:name":"Kh\u0101k Sh\u016br",
    "gn:population":0,
    "gn:timezone":"Asia/Tehran",
    "iso:country":"IR",
    "name:fas_x_preferred":[
        "\u062e\u06a9 \u0634\u0648\u0631"
    ],
    "name:fas_x_variant":[
        "Kh\u0101k Sh\u016br",
        "\u062e\u0627\u06a9 \u0634\u0648\u0631"
    ],
    "name:msa_x_preferred":[
        "Khak Shur"
    ],
    "name:ukr_x_preferred":[
        "\u0425\u0430\u043a-\u0428\u0443\u0440"
    ],
    "wof:name":"Khak Shur",
    "wof:placetype":"locality"
},
  "geometry": {"coordinates":[60.09774,35.41319],"type":"Point"}
}