{
  "type": "Feature",
  "properties": {
    "gn:admin1_code":"38.0",
    "gn:asciiname":"Seyyedestan",
    "gn:country_code":"IR",
    "gn:dem":1297,
    "gn:feature_class":"P",
    "gn:feature_code":"PPL",
    "gn:name":"Seyyedest\u0101n",
    "gn:population":0,
    "gn:timezone":"Asia/Tehran",
    "iso:country":"IR",
    "name:fas_x_preferred":[
        "\u0633\u0650\u064a\u0650\u0651\u062f\u0650\u0633\u062a\u0627\u0646"
    ],
    "name:fas_x_variant":[
        "Seyyedest\u0101n"
    ],
    "wof:name":"Seyyedestan",
    "wof:placetype":"locality"
},
  "geometry": {"coordinates":[50.13333,36.23333],"type":"Point"}
}