{
  "type": "Feature",
  "properties": {
    "gn:admin1_code":"29",
    "gn:asciiname":"Dehnow-e Qahestan",
    "gn:country_code":"IR",
    "gn:dem":1985,
    "gn:feature_class":"P",
    "gn:feature_code":"PPL",
    "gn:name":"Dehnow-e Qahest\u0101n",
    "gn:population":0,
    "gn:timezone":"Asia/Tehran",
    "iso:country":"IR",
    "name:fas_x_preferred":[
        "\u062f\u0647 \u0646\u0648"
    ],
    "name:fas_x_variant":[
        "\u062f\u0647\u0646\u0648 \u0642\u0647\u0633\u062a\u0627\u0646",
        "\u062f\u0647\u0646\u0648"
    ],
    "name:und_x_variant":[
        "Deh-e Now",
        "\u062f\u0647 \u0646\u0648",
        "Dehnow-e Qahest\u0101n",
        "Dehnow"
    ],
    "wof:name":"Dehnow-e Qahestan",
    "wof:placetype":"locality"
},
  "geometry": {"coordinates":[55.80893,29.66388],"type":"Point"}
}