{
  "type": "Feature",
  "properties": {
    "gn:admin1_code":"7",
    "gn:asciiname":"Jadval-e Now",
    "gn:cc2":"IR",
    "gn:country_code":"IR",
    "gn:dem":1997,
    "gn:feature_class":"P",
    "gn:feature_code":"PPL",
    "gn:name":"Jadval-e Now",
    "gn:population":0,
    "gn:timezone":"Asia/Tehran",
    "iso:country":"IR",
    "name:fas_x_preferred":[
        "\u062c\u062f\u0648\u0644 \u0646\u0648"
    ],
    "name:und_x_variant":[
        "Qal\u2018eh-i-Nau",
        "Jadval-e Now"
    ],
    "wof:name":"Jadval-e Now",
    "wof:placetype":"locality"
},
  "geometry": {"coordinates":[52.12667,29.66611],"type":"Point"}
}