{
  "type": "Feature",
  "properties": {
    "gn:admin1_code":"43.0",
    "gn:asciiname":"Yan Cheshmeh",
    "gn:country_code":"IR",
    "gn:dem":970,
    "gn:feature_class":"P",
    "gn:feature_code":"PPL",
    "gn:name":"Y\u0101n Cheshmeh",
    "gn:population":0,
    "gn:timezone":"Asia/Tehran",
    "iso:country":"IR",
    "name:fas_x_preferred":[
        "\u06cc\u0627\u0646 \u0686\u0634\u0645\u0647"
    ],
    "name:fas_x_variant":[
        "\u06cc\u0627\u0646\u200c\u0686\u0634\u0645\u0647"
    ],
    "name:msa_x_preferred":[
        "Yan Cheshmeh"
    ],
    "name:und_x_variant":[
        "Y\u0101n Cheshmeh"
    ],
    "name:urd_x_preferred":[
        "\u06cc\u0646 \u0686\u0634\u0645\u06c1"
    ],
    "wof:name":"Yan Cheshmeh",
    "wof:placetype":"locality"
},
  "geometry": {"coordinates":[57.06451,37.79621],"type":"Point"}
}