{
  "type": "Feature",
  "properties": {
    "gn:admin1_code":"15",
    "gn:asciiname":"Rusta-ye Amir ol Mow'menin",
    "gn:country_code":"IR",
    "gn:dem":639,
    "gn:feature_class":"P",
    "gn:feature_code":"PPL",
    "gn:name":"R\u016bst\u0101-ye Am\u012br ol Mow\u2019men\u012bn",
    "gn:population":0,
    "gn:timezone":"Asia/Tehran",
    "iso:country":"IR",
    "name:fas_x_preferred":[
        "\u0627\u0645\u06cc\u0631 \u0627\u0644\u0645\u0624\u0645\u0646\u06cc\u0646"
    ],
    "name:fas_x_variant":[
        "Am\u012br ol Mo\u2019men\u012bn",
        "Am\u012br ol Mow\u2019men\u012bn",
        "\u0631\u0648\u0633\u062a\u0627\u06cc \u0627\u0645\u06cc\u0631\u0627\u0644\u0645\u0624\u0645\u0646\u06cc\u0646"
    ],
    "name:und_x_variant":[
        "R\u016bst\u0101-ye Am\u012br ol Mow\u2019men\u012bn"
    ],
    "wof:name":"Rusta-ye Amir ol Mow'menin",
    "wof:placetype":"locality"
},
  "geometry": {"coordinates":[49.46922,32.04502],"type":"Point"}
}