{
  "type": "Feature",
  "properties": {
    "gn:admin1_code":"13",
    "gn:asciiname":"Sahanleh",
    "gn:country_code":"IR",
    "gn:dem":1898,
    "gn:feature_class":"P",
    "gn:feature_code":"PPL",
    "gn:name":"Sah\u0101nleh",
    "gn:population":0,
    "gn:timezone":"Asia/Tehran",
    "iso:country":"IR",
    "name:fas_x_preferred":[
        "\u0633\u0647\u0646\u0644\u0647"
    ],
    "name:fas_x_variant":[
        "\u0633\u0647\u0627\u0646\u0644\u0647"
    ],
    "name:und_x_variant":[
        "Sah\u0101nleh"
    ],
    "name:urd_x_preferred":[
        "\u0633\u06c1\u0627\u0646\u0644\u06c1"
    ],
    "wof:name":"Sahanleh",
    "wof:placetype":"locality"
},
  "geometry": {"coordinates":[47.65551,34.83432],"type":"Point"}
}