{
  "type": "Feature",
  "properties": {
    "gn:admin1_code":"16.0",
    "gn:asciiname":"Kukh-e Rostam",
    "gn:country_code":"IR",
    "gn:dem":1226,
    "gn:elevation":"0.0",
    "gn:feature_class":"P",
    "gn:feature_code":"PPL",
    "gn:name":"K\u016bkh-e Rostam",
    "gn:population":0,
    "gn:timezone":"Asia/Tehran",
    "iso:country":"IR",
    "name:fas_x_preferred":[
        "\u0643\u0648\u062e\u0650 \u0631\u064f\u0633\u062a\u064e\u0645"
    ],
    "name:fas_x_variant":[
        "\u06a9\u0648\u062e \u0631\u0633\u062a\u0645",
        "K\u016bkh-e Rostam"
    ],
    "wof:name":"Kukh-e Rostam",
    "wof:placetype":"locality"
},
  "geometry": {"coordinates":[45.7388,35.9142],"type":"Point"}
}