{
  "type": "Feature",
  "properties": {
    "gn:admin1_code":"8.0",
    "gn:asciiname":"Khamir Mahalleh",
    "gn:country_code":"IR",
    "gn:dem":1678,
    "gn:feature_class":"P",
    "gn:feature_code":"PPL",
    "gn:name":"Kham\u012br Ma\u1e29alleh",
    "gn:population":0,
    "gn:timezone":"Asia/Tehran",
    "iso:country":"IR",
    "name:fas_x_preferred":[
        "\u062e\u0645\u064a\u0631 \u0645\u062d\u0644\u0647"
    ],
    "name:und_x_variant":[
        "Kham\u012br Ma\u1e29alleh"
    ],
    "wof:name":"Khamir Mahalleh",
    "wof:placetype":"locality"
},
  "geometry": {"coordinates":[50.31417,36.70327],"type":"Point"}
}