{
  "type": "Feature",
  "properties": {
    "gn:admin1_code":"40.0",
    "gn:asciiname":"Mazra`eh-ye Mian",
    "gn:country_code":"IR",
    "gn:dem":1901,
    "gn:feature_class":"P",
    "gn:feature_code":"PPL",
    "gn:name":"Mazra\u2018eh-ye M\u012b\u0101n",
    "gn:population":0,
    "gn:timezone":"Asia/Tehran",
    "iso:country":"IR",
    "name:fas_x_preferred":[
        "\u0645\u0632\u0631\u0639\u06c0 \u0645\u064a\u0627\u0646"
    ],
    "name:fas_x_variant":[
        "\u0645\u064e\u0632\u0631\u064e\u0639\u0650\u06c0 \u0645\u064a\u0627\u0646 \u0637\u0627\u062d\u0648\u0646\u0650\u0647",
        "Mazra\u2018eh-ye M\u012b\u0101n"
    ],
    "name:und_x_variant":[
        "Mazra\u2018eh-ye M\u012b\u0101n \u0162\u0101\u1e29\u016bneh"
    ],
    "wof:name":"Mazra`eh-ye Mian",
    "wof:placetype":"locality"
},
  "geometry": {"coordinates":[53.9417,31.8398],"type":"Point"}
}