{
  "type": "Feature",
  "properties": {
    "gn:admin1_code":"10",
    "gn:asciiname":"Kalajukheh",
    "gn:country_code":"IR",
    "gn:dem":1048,
    "gn:feature_class":"P",
    "gn:feature_code":"PPL",
    "gn:name":"Kal\u0101j\u016bkheh",
    "gn:population":0,
    "gn:timezone":"Asia/Tehran",
    "iso:country":"IR",
    "name:fas_x_preferred":[
        "Kal\u0101j\u016bkheh"
    ],
    "name:fas_x_variant":[
        "\u0643\u064e\u0644\u0627\u062c\u0648\u062e\u0650\u0647"
    ],
    "wof:name":"Kalajukheh",
    "wof:placetype":"locality"
},
  "geometry": {"coordinates":[47.43333,33.78333],"type":"Point"}
}