{
  "type": "Feature",
  "properties": {
    "gn:admin1_code":"35.0",
    "gn:asciiname":"Atar Kalleh",
    "gn:country_code":"IR",
    "gn:dem":1960,
    "gn:feature_class":"P",
    "gn:feature_code":"PPL",
    "gn:name":"Atar Kalleh",
    "gn:population":0,
    "gn:timezone":"Asia/Tehran",
    "iso:country":"IR",
    "name:fas_x_preferred":[
        "\u0627\u062a\u0631 \u06a9\u0644\u0647"
    ],
    "name:fas_x_variant":[
        "\u0627\u062a\u0631\u06a9\u0644\u0647"
    ],
    "wof:name":"Atar Kalleh",
    "wof:placetype":"locality"
},
  "geometry": {"coordinates":[52.95332,35.97304000000001],"type":"Point"}
}