{
  "type": "Feature",
  "properties": {
    "gn:admin1_code":"36.0",
    "gn:asciiname":"Alenjeh",
    "gn:country_code":"IR",
    "gn:dem":1924,
    "gn:feature_class":"P",
    "gn:feature_code":"PPL",
    "gn:name":"\u0100lenjeh",
    "gn:population":0,
    "gn:timezone":"Asia/Tehran",
    "iso:country":"IR",
    "name:azb_x_preferred":[
        "\u0627\u0644\u0646\u0686\u0647"
    ],
    "name:fas_x_preferred":[
        "\u0627\u064e\u0644\u0648\u0646\u062c\u0650\u0647"
    ],
    "name:fas_x_variant":[
        "\u0627\u0644\u0646\u062c\u0647",
        "\u0627\u064e\u0644\u064a\u0646\u062c\u0650\u0647",
        "Al\u016bnjeh",
        "\u0622\u0644\u0646\u062c\u0647",
        "\u0627\u0644\u0646\u0686\u0647"
    ],
    "name:und_x_variant":[
        "Alundzha",
        "Al\u012bnjeh",
        "Alunjeh",
        "Alenjeh",
        "\u0100lenjeh",
        "Alencheh"
    ],
    "wof:name":"Alenjeh",
    "wof:placetype":"locality"
},
  "geometry": {"coordinates":[48.39367,36.24063],"type":"Point"}
}