{
  "type": "Feature",
  "properties": {
    "gn:admin1_code":"38",
    "gn:asciiname":"Kolah Darreh",
    "gn:country_code":"IR",
    "gn:dem":1183,
    "gn:feature_class":"P",
    "gn:feature_code":"PPL",
    "gn:name":"Kolah Darreh",
    "gn:population":0,
    "gn:timezone":"Asia/Tehran",
    "iso:country":"IR",
    "name:fas_x_preferred":[
        "\u0643\u0644\u0647 \u062f\u0631\u0647"
    ],
    "name:und_x_variant":[
        "Kaleh Darreh",
        "Kol\u0101 Darreh",
        "Kulah Darreh",
        "Kolah Darreh"
    ],
    "wof:name":"Kolah Darreh",
    "wof:placetype":"locality"
},
  "geometry": {"coordinates":[50.1841,35.7583],"type":"Point"}
}