{
  "type": "Feature",
  "properties": {
    "gn:admin1_code":"15",
    "gn:asciiname":"Sureh",
    "gn:country_code":"IR",
    "gn:dem":1,
    "gn:feature_class":"P",
    "gn:feature_code":"PPL",
    "gn:name":"S\u016breh",
    "gn:population":0,
    "gn:timezone":"Asia/Tehran",
    "iso:country":"IR",
    "name:fas_x_preferred":[
        "\u0633\u0648\u0631\u0647"
    ],
    "name:und_x_variant":[
        "S\u016breh",
        "S\u016brah",
        "Sowreh"
    ],
    "wof:name":"Sureh",
    "wof:placetype":"locality"
},
  "geometry": {"coordinates":[48.13,30.4639],"type":"Point"}
}