{
  "type": "Feature",
  "properties": {
    "gn:admin1_code":"42",
    "gn:asciiname":"Dastjerd",
    "gn:country_code":"IR",
    "gn:dem":1216,
    "gn:feature_class":"P",
    "gn:feature_code":"PPL",
    "gn:name":"Dastjerd",
    "gn:population":0,
    "gn:timezone":"Asia/Tehran",
    "iso:country":"IR",
    "name:fas_x_preferred":[
        "\u062f\u0633\u062a\u062c\u0631\u062f \u0622\u0642\u0627 \u0628\u0632\u0631\u06af"
    ],
    "name:fas_x_variant":[
        "Dastjerd-e Aq\u0101 Bozorg",
        "Dastjerd-e \u0100q\u0101 Bozorg",
        "\u062f\u0633\u062a\u062c\u0631\u062f",
        "\u062f\u0633\u062a\u062c\u0631\u062f \u0622\u0642\u0627\u0628\u0632\u0631\u06af"
    ],
    "name:und_x_variant":[
        "Dastgerd",
        "Dashtjerd-e \u0100q\u0101 Bozorg",
        "Dastjerd"
    ],
    "wof:name":"Dastjerd",
    "wof:placetype":"locality"
},
  "geometry": {"coordinates":[58.97584000000001,36.07586],"type":"Point"}
}