{
  "type": "Feature",
  "properties": {
    "gn:admin1_code":"23",
    "gn:asciiname":"Marg Sar",
    "gn:country_code":"IR",
    "gn:dem":1806,
    "gn:feature_class":"P",
    "gn:feature_code":"PPL",
    "gn:name":"Marg Sar",
    "gn:population":0,
    "gn:timezone":"Asia/Tehran",
    "iso:country":"IR",
    "name:fas_x_preferred":[
        "\u0645\u0631\u06af \u0633\u0631"
    ],
    "name:fas_x_variant":[
        "\u0645\u064e\u0631\u06af\u0650 \u0633\u064e\u0631",
        "\u0645\u064e\u0631\u06af\u0650\u0647 \u0633\u064e\u0631",
        "Qal\u2018eh-ye Margsar",
        "\u0642\u064e\u0644\u0639\u06c0 \u0645\u0631\u06af\u0633\u0631",
        "\u0645\u0631\u06af\u062f\u0633\u0631"
    ],
    "name:und_x_variant":[
        "Marg-e Sar",
        "Margeh Sar",
        "Marg Sar",
        "Margadsar"
    ],
    "wof:name":"Marg Sar",
    "wof:placetype":"locality"
},
  "geometry": {"coordinates":[48.9235,33.0469],"type":"Point"}
}