{
  "type": "Feature",
  "properties": {
    "gn:admin1_code":"34",
    "gn:asciiname":"Fizyaneh-ye Sofla",
    "gn:country_code":"IR",
    "gn:dem":2039,
    "gn:feature_class":"P",
    "gn:feature_code":"PPL",
    "gn:name":"F\u012bzy\u0101neh-ye Sofl\u00e1",
    "gn:population":0,
    "gn:timezone":"Asia/Tehran",
    "iso:country":"IR",
    "name:fas_x_preferred":[
        "\u0641\u0650\u0632\u064a\u0627\u0646\u0650\u06c0 \u0633\u064f\u0641\u0644\u064e\u0649"
    ],
    "name:fas_x_variant":[
        "\u0641\u0650\u0632\u0627\u0646\u0650\u0647 \u067e\u0627\u0626\u064a\u0646",
        "\u0641\u0650\u0632\u0627\u0646\u0650\u06c0 \u067e\u0627\u0626\u064a\u0646",
        "\u0641\u0650\u064a\u0632\u064a\u0627\u0646\u0650\u0647\u0650 \u067e\u0627\u0626\u064a\u0646",
        "Fezy\u0101neh-ye Sofl\u00e1",
        "\u0641\u06cc\u0632\u06cc\u0627\u0646\u0647 \u0633\u0641\u0644\u06cc"
    ],
    "name:und_x_variant":[
        "Feyz\u012b\u0101neh-e P\u0101\u2019\u012bn",
        "Fez\u0101neh-ye P\u0101\u2019\u012bn",
        "Fez\u0101neh P\u0101\u2019\u012bn",
        "F\u012bzy\u0101neh-ye Sofl\u00e1"
    ],
    "wof:name":"Fizyaneh-ye Sofla",
    "wof:placetype":"locality"
},
  "geometry": {"coordinates":[49.24574000000001,33.68909],"type":"Point"}
}