{
  "type": "Feature",
  "properties": {
    "gn:admin1_code":"11",
    "gn:asciiname":"Rud-e Shur",
    "gn:country_code":"IR",
    "gn:dem":503,
    "gn:feature_class":"P",
    "gn:feature_code":"PPL",
    "gn:name":"R\u016bd-e Sh\u016br",
    "gn:population":0,
    "gn:timezone":"Asia/Tehran",
    "iso:country":"IR",
    "name:ara_x_preferred":[
        "\u0631\u0648\u062f\u0634\u0648\u0631"
    ],
    "name:fas_x_preferred":[
        "\u0631\u0648\u062f \u0634\u0648\u0631"
    ],
    "name:fas_x_variant":[
        "\u0634\u0648\u0631",
        "R\u016bd-e Sh\u016br",
        "\u0631\u0648\u062f\u0634\u0648\u0631"
    ],
    "name:msa_x_preferred":[
        "Rud-e Shur"
    ],
    "name:und_x_variant":[
        "Sh\u016br"
    ],
    "wof:name":"Rud-e Shur",
    "wof:placetype":"locality"
},
  "geometry": {"coordinates":[56.3257,27.6906],"type":"Point"}
}