{
  "type": "Feature",
  "properties": {
    "gn:admin1_code":"9",
    "gn:asciiname":"Farsafaj",
    "gn:country_code":"IR",
    "gn:dem":1620,
    "gn:feature_class":"P",
    "gn:feature_code":"PPL",
    "gn:name":"Farsafaj",
    "gn:population":0,
    "gn:timezone":"Asia/Tehran",
    "iso:country":"IR",
    "name:fas_x_preferred":[
        "\u0641\u064e\u0631\u0633\u064e\u0641\u064e\u062c"
    ],
    "wof:name":"Farsafaj",
    "wof:placetype":"locality"
},
  "geometry": {"coordinates":[48.285,34.48667],"type":"Point"}
}