{
  "type": "Feature",
  "properties": {
    "gn:admin1_code":"7",
    "gn:asciiname":"Gardan Tol",
    "gn:country_code":"IR",
    "gn:dem":787,
    "gn:feature_class":"P",
    "gn:feature_code":"PPL",
    "gn:name":"Gardan Tol",
    "gn:population":0,
    "gn:timezone":"Asia/Tehran",
    "iso:country":"IR",
    "name:fas_x_preferred":[
        "Gardaneh-ye Tol-e Bardang\u0101n"
    ],
    "name:fas_x_variant":[
        "\u06af\u0631\u062f\u0646 \u062a\u0644"
    ],
    "name:und_x_variant":[
        "Gardaneh-ye Tol Bardang\u0101n",
        "Gardan Tol",
        "\u06af\u0631\u062f\u0646 \u062a\u0644"
    ],
    "wof:name":"Gardan Tol",
    "wof:placetype":"locality"
},
  "geometry": {"coordinates":[51.34127,30.21743],"type":"Point"}
}