{
  "type": "Feature",
  "properties": {
    "gn:admin1_code":"7.0",
    "gn:asciiname":"Malekabad",
    "gn:country_code":"IR",
    "gn:dem":1606,
    "gn:feature_class":"P",
    "gn:feature_code":"PPL",
    "gn:name":"Malek\u0101b\u0101d",
    "gn:population":0,
    "gn:timezone":"Asia/Tehran",
    "iso:country":"IR",
    "name:fas_x_preferred":[
        "\u0645\u0644\u06a9 \u0622\u0628\u0627\u062f"
    ],
    "name:fas_x_variant":[
        "Molk\u0101b\u0101d",
        "\u0645\u0644\u06a9\u200c\u0622\u0628\u0627\u062f"
    ],
    "name:msa_x_preferred":[
        "Malekabad"
    ],
    "name:und_x_variant":[
        "Malek\u0101b\u0101d"
    ],
    "wof:name":"Malekabad",
    "wof:placetype":"locality"
},
  "geometry": {"coordinates":[52.5859,29.9971],"type":"Point"}
}