{
  "type": "Feature",
  "properties": {
    "gn:admin1_code":"7",
    "gn:asciiname":"Jowlani",
    "gn:country_code":"IR",
    "gn:dem":2435,
    "gn:feature_class":"P",
    "gn:feature_code":"PPLF",
    "gn:name":"Jowl\u0101n\u012b",
    "gn:population":0,
    "gn:timezone":"Asia/Tehran",
    "iso:country":"IR",
    "name:fas_x_preferred":[
        "\u062c\u0648\u0644\u0627\u0646\u06cc"
    ],
    "name:fas_x_variant":[
        "\u062c\u0648\u0644\u0627\u064a\u06cc"
    ],
    "name:und_x_variant":[
        "Jaul\u016bni",
        "Jowl\u0101n\u012b",
        "J\u016bl\u0101\u2019\u012b"
    ],
    "wof:name":"Jowlani",
    "wof:placetype":"locality"
},
  "geometry": {"coordinates":[53.44663000000001,30.54391],"type":"Point"}
}