{
  "type": "Feature",
  "properties": {
    "gn:admin1_code":"28",
    "gn:asciiname":"Mozaffarabad",
    "gn:country_code":"IR",
    "gn:dem":2283,
    "gn:feature_class":"P",
    "gn:feature_code":"PPL",
    "gn:name":"Moz\u0327affar\u0101b\u0101d",
    "gn:population":0,
    "gn:timezone":"Asia/Tehran",
    "iso:country":"IR",
    "name:fas_x_preferred":[
        "\u0645\u0638\u0641\u0631 \u0622\u0628\u0627\u062f"
    ],
    "name:fas_x_variant":[
        "Moz\u0327affar\u0101b\u0101d",
        "\u0645\u0638\u0641\u0631\u0622\u0628\u0627\u062f"
    ],
    "wof:name":"Mozaffarabad",
    "wof:placetype":"locality"
},
  "geometry": {"coordinates":[52.8472,32.7024],"type":"Point"}
}