{
  "type": "Feature",
  "properties": {
    "gn:admin1_code":"8",
    "gn:asciiname":"Sibleh",
    "gn:country_code":"IR",
    "gn:dem":2163,
    "gn:feature_class":"P",
    "gn:feature_code":"PPLL",
    "gn:name":"S\u012bbleh",
    "gn:population":0,
    "gn:timezone":"Asia/Tehran",
    "iso:country":"IR",
    "name:fas_x_preferred":[
        "\u0633\u0628\u0644\u0647"
    ],
    "name:fas_x_variant":[
        "\u0633\u06cc\u0628\u0644\u0647"
    ],
    "name:und_x_variant":[
        "Sableh",
        "S\u012bbleh"
    ],
    "wof:name":"Sibleh",
    "wof:placetype":"locality"
},
  "geometry": {"coordinates":[48.87583,37.20421],"type":"Point"}
}