{
  "type": "Feature",
  "properties": {
    "gn:admin1_code":"1",
    "gn:asciiname":"Yengejeh",
    "gn:cc2":"IR",
    "gn:country_code":"IR",
    "gn:dem":1880,
    "gn:feature_class":"P",
    "gn:feature_code":"PPL",
    "gn:name":"Yengejeh",
    "gn:population":0,
    "gn:timezone":"Asia/Tehran",
    "iso:country":"IR",
    "name:ceb_x_preferred":[
        "Yengejeh"
    ],
    "name:fas_x_preferred":[
        "\u064a\u0650\u0646\u0643\u0650\u062c\u0650\u0647"
    ],
    "name:fas_x_variant":[
        "\u064a\u0650\u0646\u06af\u0650\u062c\u0650\u0647",
        "\u06cc\u0646\u06af\u062c\u0647"
    ],
    "name:swe_x_preferred":[
        "Yengejeh"
    ],
    "name:und_x_variant":[
        "Yengije",
        "Yenkejeh",
        "Yengejeh"
    ],
    "wof:name":"Yengejeh",
    "wof:placetype":"locality"
},
  "geometry": {"coordinates":[44.65,38.26667],"type":"Point"}
}