{
  "type": "Feature",
  "properties": {
    "gn:admin1_code":"7",
    "gn:asciiname":"Chah-e Salaki",
    "gn:country_code":"IR",
    "gn:dem":1602,
    "gn:feature_class":"P",
    "gn:feature_code":"PPL",
    "gn:name":"Ch\u0101h-e S\u0101lak\u012b",
    "gn:population":0,
    "gn:timezone":"Asia/Tehran",
    "iso:country":"IR",
    "name:fas_x_preferred":[
        "\u0686\u0627\u0647 \u0633\u0627\u0644\u06a9\u06cc"
    ],
    "name:fas_x_variant":[
        "Ch\u0101h-e S\u0101lak\u012b"
    ],
    "wof:name":"Chah-e Salaki",
    "wof:placetype":"locality"
},
  "geometry": {"coordinates":[55.0726,28.8108],"type":"Point"}
}