{
  "type": "Feature",
  "properties": {
    "gn:admin1_code":"8",
    "gn:asciiname":"Darili Yurdi",
    "gn:country_code":"IR",
    "gn:dem":158,
    "gn:feature_class":"P",
    "gn:feature_code":"PPL",
    "gn:name":"Dar\u012bl\u012b Y\u016brd\u012b",
    "gn:population":0,
    "gn:timezone":"Asia/Tehran",
    "iso:country":"IR",
    "name:fas_x_preferred":[
        "\u062f\u0631\u06cc\u0644\u06cc \u06cc\u0648\u0631\u062f\u06cc"
    ],
    "name:fas_x_variant":[
        "Dar\u012bl\u012b Y\u016brd\u012b"
    ],
    "wof:name":"Darili Yurdi",
    "wof:placetype":"locality"
},
  "geometry": {"coordinates":[48.7991,38.2905],"type":"Point"}
}