{
  "type": "Feature",
  "properties": {
    "gn:admin1_code":"15.0",
    "gn:asciiname":"Dageh Meshki",
    "gn:country_code":"IR",
    "gn:dem":213,
    "gn:feature_class":"P",
    "gn:feature_code":"PPL",
    "gn:name":"Dageh Meshk\u012b",
    "gn:population":0,
    "gn:timezone":"Asia/Tehran",
    "iso:country":"IR",
    "name:fas_x_preferred":[
        "Dageh Meshg\u012b"
    ],
    "name:fas_x_variant":[
        "\u062f\u06af\u0647 \u0645\u0634\u06a9\u06cc"
    ],
    "name:und_x_variant":[
        "Dageh Meshk\u012b"
    ],
    "wof:name":"Dageh Meshki",
    "wof:placetype":"locality"
},
  "geometry": {"coordinates":[49.24277,32.16788],"type":"Point"}
}