{
  "type": "Feature",
  "properties": {
    "gn:admin1_code":"43.0",
    "gn:asciiname":"Bam-va-Safi Abad",
    "gn:country_code":"IR",
    "gn:dem":1127,
    "gn:feature_class":"P",
    "gn:feature_code":"PPL",
    "gn:name":"B\u0101m-va-Saf\u012b \u0100b\u0101d",
    "gn:population":0,
    "gn:timezone":"Asia/Tehran",
    "iso:country":"IR",
    "name:fas_x_preferred":[
        "B\u0101m-va-Saf\u012b \u0100b\u0101d"
    ],
    "wof:name":"Bam-va-Safi Abad",
    "wof:placetype":"locality"
},
  "geometry": {"coordinates":[57.72306,36.77111],"type":"Point"}
}