{
  "type": "Feature",
  "properties": {
    "gn:admin1_code":"33",
    "gn:asciiname":"Qarajeh Qayeh",
    "gn:country_code":"IR",
    "gn:dem":1677,
    "gn:feature_class":"P",
    "gn:feature_code":"PPL",
    "gn:name":"Qar\u0101jeh Qayeh",
    "gn:population":0,
    "gn:timezone":"Asia/Tehran",
    "iso:country":"IR",
    "name:fas_x_preferred":[
        "\u0642\u0631\u0627\u062c\u0647 \u0642\u06cc\u0647"
    ],
    "name:fas_x_variant":[
        "Qar\u0101jeh Qayeh"
    ],
    "wof:name":"Qarajeh Qayeh",
    "wof:placetype":"locality"
},
  "geometry": {"coordinates":[46.4058,37.2527],"type":"Point"}
}