{
  "type": "Feature",
  "properties": {
    "gn:admin1_code":"15.0",
    "gn:asciiname":"Keli Malek",
    "gn:country_code":"IR",
    "gn:dem":1284,
    "gn:feature_class":"P",
    "gn:feature_code":"PPL",
    "gn:name":"Kel\u012b Malek",
    "gn:population":0,
    "gn:timezone":"Asia/Tehran",
    "iso:country":"IR",
    "name:fas_x_preferred":[
        "Kel\u012b Malek"
    ],
    "name:fas_x_variant":[
        "\u06a9\u0644\u06cc \u0645\u0644\u06a9"
    ],
    "name:und_x_variant":[
        "\u06a9\u0644\u06cc \u0645\u0644\u06a9"
    ],
    "wof:name":"Keli Malek",
    "wof:placetype":"locality"
},
  "geometry": {"coordinates":[50.24462,31.71831],"type":"Point"}
}