{
  "type": "Feature",
  "properties": {
    "gn:admin1_code":"29.0",
    "gn:asciiname":"Agharku'iyeh",
    "gn:country_code":"IR",
    "gn:dem":1835,
    "gn:feature_class":"P",
    "gn:feature_code":"PPL",
    "gn:name":"Aghark\u016b\u2019\u012byeh",
    "gn:population":0,
    "gn:timezone":"Asia/Tehran",
    "iso:country":"IR",
    "name:fas_x_preferred":[
        "Aghark\u016b\u2019\u012byeh"
    ],
    "wof:name":"Agharku'iyeh",
    "wof:placetype":"locality"
},
  "geometry": {"coordinates":[56.09972,29.12111],"type":"Point"}
}