{
  "type": "Feature",
  "properties": {
    "gn:admin1_code":"15",
    "gn:asciiname":"Fereyduni",
    "gn:country_code":"IR",
    "gn:dem":822,
    "gn:feature_class":"P",
    "gn:feature_code":"PPL",
    "gn:name":"Fereyd\u016bn\u012b",
    "gn:population":0,
    "gn:timezone":"Asia/Tehran",
    "iso:country":"IR",
    "name:fas_x_preferred":[
        "Fereyd\u016bn\u012b"
    ],
    "name:fas_x_variant":[
        "\u0641\u0631\u06cc\u062f\u0648\u0646\u06cc"
    ],
    "name:und_x_variant":[
        "Fereidooni",
        "\u0641\u0631\u06cc\u062f\u0648\u0646\u06cc"
    ],
    "wof:name":"Fereyduni",
    "wof:placetype":"locality"
},
  "geometry": {"coordinates":[49.80188,31.68289],"type":"Point"}
}