{
  "type": "Feature",
  "properties": {
    "gn:admin1_code":"7.0",
    "gn:asciiname":"Legareh",
    "gn:country_code":"IR",
    "gn:dem":587,
    "gn:feature_class":"P",
    "gn:feature_code":"PPLL",
    "gn:name":"Leg\u0101reh",
    "gn:population":0,
    "gn:timezone":"Asia/Tehran",
    "iso:country":"IR",
    "name:fas_x_preferred":[
        "\u0644\u06af\u0627\u0631\u0647"
    ],
    "name:und_x_variant":[
        "Leg\u0101reh"
    ],
    "wof:name":"Legareh",
    "wof:placetype":"locality"
},
  "geometry": {"coordinates":[53.23834,27.7668],"type":"Point"}
}