{
  "type": "Feature",
  "properties": {
    "gn:admin1_code":"4.0",
    "gn:asciiname":"Sohrud",
    "gn:country_code":"IR",
    "gn:dem":330,
    "gn:feature_class":"P",
    "gn:feature_code":"PPL",
    "gn:name":"Sohr\u016bd",
    "gn:population":0,
    "gn:timezone":"Asia/Tehran",
    "iso:country":"IR",
    "name:fas_x_preferred":[
        "Sohr\u016bd"
    ],
    "wof:name":"Sohrud",
    "wof:placetype":"locality"
},
  "geometry": {"coordinates":[61.47528000000001,26.13556],"type":"Point"}
}