{
  "type": "Feature",
  "properties": {
    "gn:admin1_code":"8",
    "gn:asciiname":"Eshliki",
    "gn:cc2":"IR",
    "gn:country_code":"IR",
    "gn:dem":-13,
    "gn:feature_class":"P",
    "gn:feature_code":"PPL",
    "gn:name":"Eshl\u012bk\u012b",
    "gn:population":0,
    "gn:timezone":"Asia/Tehran",
    "iso:country":"IR",
    "name:fas_x_preferred":[
        "Eshl\u012bk\u012b"
    ],
    "name:und_x_variant":[
        "Ishlik",
        "\u012ash\u012bk\u012b",
        "Ishlyk"
    ],
    "wof:name":"Eshliki",
    "wof:placetype":"locality"
},
  "geometry": {"coordinates":[49.905,37.27833],"type":"Point"}
}