{
  "type": "Feature",
  "properties": {
    "gn:admin1_code":"15",
    "gn:asciiname":"Shahrak-e Ab va Khak",
    "gn:country_code":"IR",
    "gn:dem":34,
    "gn:feature_class":"P",
    "gn:feature_code":"PPL",
    "gn:name":"Shahrak-e \u0100b va Kh\u0101k",
    "gn:population":0,
    "gn:timezone":"Asia/Tehran",
    "iso:country":"IR",
    "name:fas_x_preferred":[
        "\u0632\u06cc\u062f\u0627\u0646"
    ],
    "name:fas_x_variant":[
        "Boneh-ye Zeyd\u0101n",
        "Zeyd\u0101n",
        "\u0634\u0647\u0631\u06a9 \u0622\u0628 \u0648 \u062e\u0627\u06a9"
    ],
    "name:und_x_variant":[
        "Sheykh Zeyd\u0101n",
        "Shahrak-e \u0100b va Kh\u0101k"
    ],
    "wof:name":"Shahrak-e Ab va Khak",
    "wof:placetype":"locality"
},
  "geometry": {"coordinates":[48.661,31.8785],"type":"Point"}
}