{
  "type": "Feature",
  "properties": {
    "gn:admin1_code":"1",
    "gn:asciiname":"Batchi",
    "gn:country_code":"IR",
    "gn:dem":1910,
    "gn:feature_class":"P",
    "gn:feature_code":"PPL",
    "gn:name":"Ba\u0163ch\u012b",
    "gn:population":0,
    "gn:timezone":"Asia/Tehran",
    "iso:country":"IR",
    "name:aze_x_preferred":[
        "Bat\u00e7\u0131"
    ],
    "name:fas_x_preferred":[
        "\u0628\u0637\u0686\u06cc"
    ],
    "name:fas_x_variant":[
        "Ba\u0163ch\u012b"
    ],
    "name:msa_x_preferred":[
        "Batchi"
    ],
    "wof:name":"Batchi",
    "wof:placetype":"locality"
},
  "geometry": {"coordinates":[44.7395,38.629],"type":"Point"}
}