{
  "type": "Feature",
  "properties": {
    "gn:admin1_code":"23",
    "gn:asciiname":"Keyanabad",
    "gn:country_code":"IR",
    "gn:dem":720,
    "gn:feature_class":"P",
    "gn:feature_code":"PPL",
    "gn:name":"Key\u0101n\u0101b\u0101d",
    "gn:population":0,
    "gn:timezone":"Asia/Tehran",
    "iso:country":"IR",
    "name:fas_x_preferred":[
        "\u067e\u064e\u0631\u0627\u0646 \u067e\u064e\u0631\u0648\u064a\u0632"
    ],
    "name:fas_x_variant":[
        "\u0627\u0633\u0644\u0627\u0645 \u0622\u0628\u0627\u062f \u067e\u0631\u0627\u0646 \u067e\u0631\u0648\u06cc\u0632",
        "Par\u0101n Parv\u012bz",
        "\u06a9\u06cc\u0627\u0646 \u0622\u0628\u0627\u062f"
    ],
    "name:und_x_variant":[
        "Esl\u0101m\u0101b\u0101d-e Par\u0101n Parv\u012bz",
        "Key\u0101n\u0101b\u0101d"
    ],
    "wof:name":"Keyanabad",
    "wof:placetype":"locality"
},
  "geometry": {"coordinates":[47.7427,33.2581],"type":"Point"}
}