{
  "type": "Feature",
  "properties": {
    "gn:admin1_code":"13",
    "gn:asciiname":"Khal Khal",
    "gn:country_code":"IR",
    "gn:dem":1338,
    "gn:feature_class":"P",
    "gn:feature_code":"PPL",
    "gn:name":"Kh\u0101l Kh\u0101l",
    "gn:population":0,
    "gn:timezone":"Asia/Tehran",
    "iso:country":"IR",
    "name:fas_x_preferred":[
        "\u062e\u0627\u0644 \u062e\u0627\u0644"
    ],
    "name:fas_x_variant":[
        "Kh\u0101l Kh\u0101l"
    ],
    "wof:name":"Khal Khal",
    "wof:placetype":"locality"
},
  "geometry": {"coordinates":[47.346,34.2802],"type":"Point"}
}