{
  "type": "Feature",
  "properties": {
    "gn:admin1_code":"22.0",
    "gn:asciiname":"Gonjeshki",
    "gn:country_code":"IR",
    "gn:dem":28,
    "gn:feature_class":"P",
    "gn:feature_code":"PPL",
    "gn:name":"Gonjeshk\u012b",
    "gn:population":0,
    "gn:timezone":"Asia/Tehran",
    "iso:country":"IR",
    "name:fas_x_preferred":[
        "\u06af\u0646\u062c\u0634\u06a9\u06cc"
    ],
    "name:fas_x_variant":[
        "Gonjeshk\u012b"
    ],
    "name:msa_x_preferred":[
        "Gonjeshki"
    ],
    "wof:name":"Gonjeshki",
    "wof:placetype":"locality"
},
  "geometry": {"coordinates":[50.628,29.6424],"type":"Point"}
}