{
  "type": "Feature",
  "properties": {
    "gn:admin1_code":"33",
    "gn:asciiname":"Shoja` Khanlu",
    "gn:country_code":"IR",
    "gn:dem":376,
    "gn:feature_class":"P",
    "gn:feature_code":"PPL",
    "gn:name":"Shoj\u0101\u2018 Kh\u0101nl\u016b",
    "gn:population":0,
    "gn:timezone":"Asia/Tehran",
    "iso:country":"IR",
    "name:fas_x_preferred":[
        "\u0634\u062c\u0627\u0639 \u062e\u0627\u0646\u0644\u0648"
    ],
    "name:fas_x_variant":[
        "Shoj\u0101\u2018 Kh\u0101nl\u016b"
    ],
    "wof:name":"Shoja` Khanlu",
    "wof:placetype":"locality"
},
  "geometry": {"coordinates":[47.1841,39.217],"type":"Point"}
}