{
  "type": "Feature",
  "properties": {
    "gn:admin1_code":"7",
    "gn:asciiname":"Hajjiabad-e Muzi",
    "gn:country_code":"IR",
    "gn:dem":815,
    "gn:feature_class":"P",
    "gn:feature_code":"PPL",
    "gn:name":"\u1e28\u0101jj\u012b\u0101b\u0101d-e M\u016bz\u012b",
    "gn:population":0,
    "gn:timezone":"Asia/Tehran",
    "iso:country":"IR",
    "name:fas_x_preferred":[
        "\u1e28\u0101jj\u012b\u0101b\u0101d-e M\u016bz\u012b"
    ],
    "name:fas_x_variant":[
        "\u1e28\u0101jj\u012b\u0101b\u0101d",
        "\u062d\u0627\u062c\u06cc \u0622\u0628\u0627\u062f \u0645\u0648\u0632\u06cc",
        "\u062d\u0627\u062c\u06cc\u200c\u0622\u0628\u0627\u062f \u0645\u0648\u0632\u06cc"
    ],
    "name:msa_x_preferred":[
        "Hajjiabad-e Muzi"
    ],
    "name:und_x_variant":[
        "\u062d\u0627\u062c\u06cc \u0622\u0628\u0627\u062f \u0645\u0648\u0632\u06cc"
    ],
    "wof:name":"Hajjiabad-e Muzi",
    "wof:placetype":"locality"
},
  "geometry": {"coordinates":[51.58391,29.7645],"type":"Point"}
}