{
  "type": "Feature",
  "properties": {
    "gn:admin1_code":"35.0",
    "gn:asciiname":"Lapu Sahra",
    "gn:country_code":"IR",
    "gn:dem":-24,
    "gn:feature_class":"P",
    "gn:feature_code":"PPL",
    "gn:name":"Lap\u016b \u015ea\u1e29r\u0101",
    "gn:population":0,
    "gn:timezone":"Asia/Tehran",
    "iso:country":"IR",
    "name:ceb_x_preferred":[
        "Lap\u016b \u015ea\u1e29r\u0101"
    ],
    "name:fas_x_preferred":[
        "Lap\u016b \u015ea\u1e29r\u0101"
    ],
    "name:fas_x_variant":[
        "\u0644\u067e\u0648 \u0635\u062d\u0631\u0627",
        "\u0644\u067e\u0648\u0635\u062d\u0631\u0627"
    ],
    "name:swe_x_preferred":[
        "Lap\u016b \u015ea\u1e29r\u0101"
    ],
    "name:urd_x_preferred":[
        "\u0644\u067e\u0648 \u0635\u062d\u0631\u0627\u0621"
    ],
    "wof:name":"Lapu Sahra",
    "wof:placetype":"locality"
},
  "geometry": {"coordinates":[52.82446,36.72605],"type":"Point"}
}