{
  "type": "Feature",
  "properties": {
    "gn:admin1_code":"1.0",
    "gn:asciiname":"Mam Heybeh",
    "gn:country_code":"IR",
    "gn:dem":1459,
    "gn:feature_class":"P",
    "gn:feature_code":"PPL",
    "gn:name":"M\u0101m Heybeh",
    "gn:population":0,
    "gn:timezone":"Asia/Tehran",
    "iso:country":"IR",
    "name:azb_x_preferred":[
        "\u0645\u0627\u0645 \u0647\u06cc\u0628\u0647"
    ],
    "name:aze_x_preferred":[
        "Mamheyb\u0259"
    ],
    "name:fas_x_preferred":[
        "\u0645\u0627\u0645 \u0647\u06cc\u0628\u0647"
    ],
    "name:fas_x_variant":[
        "M\u0101m Heybeh"
    ],
    "name:msa_x_preferred":[
        "Mam Heybeh"
    ],
    "wof:name":"Mam Heybeh",
    "wof:placetype":"locality"
},
  "geometry": {"coordinates":[45.349,36.5145],"type":"Point"}
}