{
  "type": "Feature",
  "properties": {
    "gn:admin1_code":"1.0",
    "gn:asciiname":"Berushkhvaran",
    "gn:country_code":"IR",
    "gn:dem":2395,
    "gn:feature_class":"P",
    "gn:feature_code":"PPL",
    "gn:name":"Ber\u016bshkhv\u0101r\u0101n",
    "gn:population":0,
    "gn:timezone":"Asia/Tehran",
    "iso:country":"IR",
    "name:fas_x_preferred":[
        "\u0628\u0631\u0648\u0634\u062e\u0648\u0627\u0631\u0627\u0646"
    ],
    "name:fas_x_variant":[
        "Ber\u016bshkhv\u0101r\u0101n"
    ],
    "wof:name":"Berushkhvaran",
    "wof:placetype":"locality"
},
  "geometry": {"coordinates":[44.4807,38.2775],"type":"Point"}
}