{
  "type": "Feature",
  "properties": {
    "gn:admin1_code":"10.0",
    "gn:asciiname":"Siah Gel",
    "gn:country_code":"IR",
    "gn:dem":883,
    "gn:feature_class":"P",
    "gn:feature_code":"PPL",
    "gn:name":"S\u012b\u0101h Gel",
    "gn:population":0,
    "gn:timezone":"Asia/Tehran",
    "iso:country":"IR",
    "name:ara_x_preferred":[
        "\u0633\u064a\u0627\u0629 \u063a\u0644"
    ],
    "name:fas_x_preferred":[
        "\u0633\u06cc\u0627\u0647 \u06af\u0644"
    ],
    "name:fas_x_variant":[
        "\u0633\u064a\u0627\u0647 \u0643\u064f\u0644",
        "S\u012b\u0101hgel",
        "S\u012b\u0101h Gel"
    ],
    "name:msa_x_preferred":[
        "Siah Gel"
    ],
    "name:und_x_variant":[
        "S\u012b\u0101h Kol"
    ],
    "wof:name":"Siah Gel",
    "wof:placetype":"locality"
},
  "geometry": {"coordinates":[46.0786,33.9112],"type":"Point"}
}