{
  "type": "Feature",
  "properties": {
    "gn:admin1_code":"4.0",
    "gn:asciiname":"Kahn",
    "gn:cc2":"IR",
    "gn:country_code":"IR",
    "gn:dem":149,
    "gn:feature_class":"P",
    "gn:feature_code":"PPL",
    "gn:name":"Kahn",
    "gn:population":0,
    "gn:timezone":"Asia/Tehran",
    "iso:country":"IR",
    "name:heb_x_preferred":[
        "\u05e7\u05d0\u05d4\u05df"
    ],
    "name:slv_x_preferred":[
        "Kahn"
    ],
    "name:und_x_variant":[
        "Kahn Bal\u016bch\u0101n\u012b",
        "Kohan Bal\u016bch\u0101n\u012b"
    ],
    "wof:name":"Kahn",
    "wof:placetype":"locality"
},
  "geometry": {"coordinates":[60.89444,25.94778],"type":"Point"}
}