{
  "type": "Feature",
  "properties": {
    "gn:admin1_code":"32.0",
    "gn:asciiname":"Khasteh Khuni",
    "gn:country_code":"IR",
    "gn:dem":1747,
    "gn:feature_class":"P",
    "gn:feature_code":"PPL",
    "gn:name":"Khasteh Kh\u016bn\u012b",
    "gn:population":0,
    "gn:timezone":"Asia/Tehran",
    "iso:country":"IR",
    "name:fas_x_preferred":[
        "\u062e\u0633\u062a\u0647 \u062e\u0648\u0646\u06cc"
    ],
    "name:und_x_variant":[
        "Khasteh Kh\u016bn\u012b"
    ],
    "wof:name":"Khasteh Khuni",
    "wof:placetype":"locality"
},
  "geometry": {"coordinates":[48.8521,37.3222],"type":"Point"}
}