{
  "type": "Feature",
  "properties": {
    "gn:admin1_code":"40",
    "gn:asciiname":"Jangal",
    "gn:country_code":"IR",
    "gn:dem":1997,
    "gn:feature_class":"P",
    "gn:feature_code":"PPL",
    "gn:name":"Jangal",
    "gn:population":0,
    "gn:timezone":"Asia/Tehran",
    "iso:country":"IR",
    "name:ara_x_preferred":[
        "\u062c\u0646\u063a\u0644"
    ],
    "name:aze_x_preferred":[
        "C\u0259ng\u0259l"
    ],
    "name:ceb_x_preferred":[
        "Jangal"
    ],
    "name:fas_x_preferred":[
        "\u062c\u064e\u0646\u06af\u064e\u0644\u0650 \u0639\u064e\u0644\u064a\u0631\u0650\u0636\u0627"
    ],
    "name:fas_x_variant":[
        "\u062c\u064e\u0646\u06af\u064e\u0644",
        "Jangal-e \u2018Al\u012bre\u1e95\u0101",
        "\u062c\u0646\u06af\u0644"
    ],
    "name:ita_x_preferred":[
        "Jangal"
    ],
    "name:mlg_x_preferred":[
        "Jangal"
    ],
    "name:swe_x_preferred":[
        "Jangal"
    ],
    "name:tur_x_preferred":[
        "Cengel"
    ],
    "wof:name":"Jangal",
    "wof:placetype":"locality"
},
  "geometry": {"coordinates":[55.96898,31.78446],"type":"Point"}
}