{
  "type": "Feature",
  "properties": {
    "gn:admin1_code":"8.0",
    "gn:asciiname":"Chamandan",
    "gn:country_code":"IR",
    "gn:dem":9,
    "gn:feature_class":"P",
    "gn:feature_code":"PPL",
    "gn:name":"Chamand\u0101n",
    "gn:population":0,
    "gn:timezone":"Asia/Tehran",
    "iso:country":"IR",
    "name:fas_x_preferred":[
        "\u0686\u0645\u0646\u062f\u0627\u0646"
    ],
    "name:msa_x_preferred":[
        "Chamandan"
    ],
    "name:ukr_x_preferred":[
        "\u0427\u0430\u043c\u0430\u043d\u0434\u0430\u043d"
    ],
    "name:und_x_variant":[
        "Chamand\u0101n"
    ],
    "wof:name":"Chamandan",
    "wof:placetype":"locality"
},
  "geometry": {"coordinates":[49.9633,37.1771],"type":"Point"}
}