{
  "type": "Feature",
  "properties": {
    "gn:admin1_code":"35.0",
    "gn:asciiname":"Bahmanan",
    "gn:country_code":"IR",
    "gn:dem":618,
    "gn:feature_class":"P",
    "gn:feature_code":"PPL",
    "gn:name":"Bahman\u0101n",
    "gn:population":0,
    "gn:timezone":"Asia/Tehran",
    "iso:country":"IR",
    "name:fas_x_preferred":[
        "\u0628\u0647\u0645\u0646\u0627\u0646"
    ],
    "name:fas_x_variant":[
        "Bahman\u0101n"
    ],
    "wof:name":"Bahmanan",
    "wof:placetype":"locality"
},
  "geometry": {"coordinates":[52.98318,36.22145],"type":"Point"}
}