{
  "type": "Feature",
  "properties": {
    "gn:admin1_code":"7",
    "gn:asciiname":"Dowbaran",
    "gn:country_code":"IR",
    "gn:dem":1112,
    "gn:feature_class":"P",
    "gn:feature_code":"PPL",
    "gn:name":"Dowbar\u0101n",
    "gn:population":0,
    "gn:timezone":"Asia/Tehran",
    "iso:country":"IR",
    "name:fas_x_preferred":[
        "Dowbar\u0101n"
    ],
    "name:fas_x_variant":[
        "D\u016bbor\u0101n",
        "\u062f\u0648\u0628\u0631\u0627\u0646"
    ],
    "name:und_x_variant":[
        "Dab\u012br\u0101n",
        "Dobor\u0101n",
        "Dowb\u0101n",
        "Dooban",
        "Dowbor\u0101n"
    ],
    "wof:name":"Dowbaran",
    "wof:placetype":"locality"
},
  "geometry": {"coordinates":[54.18796999999999,28.40612],"type":"Point"}
}