{
  "type": "Feature",
  "properties": {
    "gn:admin1_code":"5.0",
    "gn:asciiname":"Sar Tang",
    "gn:country_code":"IR",
    "gn:dem":1910,
    "gn:feature_class":"P",
    "gn:feature_code":"PPL",
    "gn:name":"Sar Tang",
    "gn:population":0,
    "gn:timezone":"Asia/Tehran",
    "iso:country":"IR",
    "name:ceb_x_preferred":[
        "Sar Tang"
    ],
    "name:fas_x_preferred":[
        "\u0633\u0631 \u062a\u0646\u06af"
    ],
    "name:fas_x_variant":[
        "\u0633\u0631\u062a\u0646\u06af"
    ],
    "name:swe_x_preferred":[
        "Sar Tang"
    ],
    "name:und_x_variant":[
        "\u0633\u0631 \u062a\u0646\u06af"
    ],
    "wof:name":"Sar Tang",
    "wof:placetype":"locality"
},
  "geometry": {"coordinates":[51.4374,30.72417],"type":"Point"}
}