{
  "type": "Feature",
  "properties": {
    "gn:admin1_code":"34",
    "gn:asciiname":"Khondab",
    "gn:country_code":"IR",
    "gn:dem":1695,
    "gn:feature_class":"P",
    "gn:feature_code":"PPLA2",
    "gn:name":"Khond\u0101b",
    "gn:population":0,
    "gn:timezone":"Asia/Tehran",
    "iso:country":"IR",
    "name:fas_x_preferred":[
        "\u062e\u0646\u062f\u0627\u0628"
    ],
    "name:fas_x_variant":[
        "\u062e\u0627\u0646\u062f\u0627\u0628",
        "Khond\u0101b"
    ],
    "name:und_x_variant":[
        "Kh\u0101nd\u0101b"
    ],
    "wof:name":"Khondab",
    "wof:placetype":"locality"
},
  "geometry": {"coordinates":[49.1841,34.3928],"type":"Point"}
}