{
  "type": "Feature",
  "properties": {
    "gn:admin1_code":"34",
    "gn:asciiname":"Khondab",
    "gn:country_code":"IR",
    "gn:dem":1695,
    "gn:feature_class":"P",
    "gn:feature_code":"PPLA2",
    "gn:name":"Khond\u0101b",
    "gn:population":0,
    "gn:timezone":"Asia/Tehran",
    "iso:country":"IR",
    "name:ara_x_preferred":[
        "\u062e\u0646\u062f\u0627\u0628"
    ],
    "name:aze_x_preferred":[
        "Xondab"
    ],
    "name:ceb_x_preferred":[
        "Khond\u0101b"
    ],
    "name:fas_x_preferred":[
        "\u062e\u0646\u062f\u0627\u0628"
    ],
    "name:fas_x_variant":[
        "\u062e\u0627\u0646\u062f\u0627\u0628",
        "Khond\u0101b"
    ],
    "name:glk_x_preferred":[
        "\u062e\u0646\u062f\u0627\u0628"
    ],
    "name:ita_x_preferred":[
        "Khondab"
    ],
    "name:mlg_x_preferred":[
        "Khondab"
    ],
    "name:rus_x_preferred":[
        "\u0425\u043e\u043d\u0434\u0430\u0431"
    ],
    "name:tur_x_preferred":[
        "Hondab"
    ],
    "name:und_x_variant":[
        "Kh\u0101nd\u0101b"
    ],
    "name:zho_x_preferred":[
        "\u6d2a\u9054\u535c"
    ],
    "wof:name":"Khondab",
    "wof:placetype":"locality"
},
  "geometry": {"coordinates":[49.1841,34.3928],"type":"Point"}
}