{
  "type": "Feature",
  "properties": {
    "gn:admin1_code":"42",
    "gn:asciiname":"Kalateh-ye `Abbas",
    "gn:country_code":"IR",
    "gn:dem":1698,
    "gn:feature_class":"P",
    "gn:feature_code":"PPL",
    "gn:name":"Kal\u0101teh-ye \u2018Abb\u0101s",
    "gn:population":0,
    "gn:timezone":"Asia/Tehran",
    "iso:country":"IR",
    "name:fas_x_preferred":[
        "\u06a9\u0644\u0627\u062a\u0647 \u0639\u0628\u0627\u0633"
    ],
    "name:fas_x_variant":[
        "Kal\u0101teh-ye \u2018Abb\u0101s"
    ],
    "wof:name":"Kalateh-ye `Abbas",
    "wof:placetype":"locality"
},
  "geometry": {"coordinates":[59.24132,35.46357000000001],"type":"Point"}
}