{
  "type": "Feature",
  "properties": {
    "gn:admin1_code":"28.0",
    "gn:asciiname":"Zarrin Shahr",
    "gn:country_code":"IR",
    "gn:dem":1705,
    "gn:feature_class":"P",
    "gn:feature_code":"PPLA2",
    "gn:name":"Zarr\u012bn Shahr",
    "gn:population":0,
    "gn:timezone":"Asia/Tehran",
    "iso:country":"IR",
    "name:fas_x_preferred":[
        "\u0632\u0631\u0651\u06cc\u0646 \u0634\u0647\u0631"
    ],
    "name:fas_x_variant":[
        "Zarr\u012bn Shahr"
    ],
    "name:und_x_variant":[
        "Qal\u2018eh R\u012bz",
        "R\u012bz",
        "R\u012bz-e Lanj\u0101n"
    ],
    "wof:name":"Zarrin Shahr",
    "wof:placetype":"locality"
},
  "geometry": {"coordinates":[51.3766,32.3897],"type":"Point"}
}