{
  "type": "Feature",
  "properties": {
    "gn:admin1_code":"28.0",
    "gn:asciiname":"Zarrin Shahr",
    "gn:country_code":"IR",
    "gn:dem":1705,
    "gn:feature_class":"P",
    "gn:feature_code":"PPLA2",
    "gn:name":"Zarr\u012bn Shahr",
    "gn:population":0,
    "gn:timezone":"Asia/Tehran",
    "iso:country":"IR",
    "name:ara_x_preferred":[
        "\u0632\u0631\u064a\u0646 \u0634\u0647\u0631"
    ],
    "name:aze_x_preferred":[
        "Z\u0259rrin\u015f\u0259hr"
    ],
    "name:ceb_x_preferred":[
        "Zarr\u012bn Shahr"
    ],
    "name:fas_x_preferred":[
        "\u0632\u0631\u0651\u06cc\u0646 \u0634\u0647\u0631"
    ],
    "name:fas_x_variant":[
        "Zarr\u012bn Shahr",
        "\u0632\u0631\u06cc\u0646\u200c\u0634\u0647\u0631"
    ],
    "name:fra_x_preferred":[
        "Zarrine-Chahr"
    ],
    "name:hin_x_preferred":[
        "\u091c\u093c\u0930\u094d\u0930\u0940\u0928\u0936\u0939\u0930"
    ],
    "name:ita_x_preferred":[
        "Zarrin Shahr"
    ],
    "name:mlg_x_preferred":[
        "Zarrin Shahr"
    ],
    "name:pol_x_preferred":[
        "Zarrinszahr"
    ],
    "name:por_x_preferred":[
        "Zarrinshahr"
    ],
    "name:ron_x_preferred":[
        "Zarrin Shahr"
    ],
    "name:rus_x_preferred":[
        "\u0417\u0435\u0440\u0440\u0438\u043d\u0448\u0435\u0445\u0440"
    ],
    "name:swe_x_preferred":[
        "Zarr\u012bn Shahr"
    ],
    "name:tur_x_preferred":[
        "Zerrin\u015fehr"
    ],
    "name:und_x_variant":[
        "Qal\u2018eh R\u012bz",
        "R\u012bz",
        "R\u012bz-e Lanj\u0101n"
    ],
    "name:urd_x_preferred":[
        "\u0632\u0631\u06cc\u0646\u200c\u0634\u06c1\u0631"
    ],
    "name:zho_x_preferred":[
        "\u624e\u6797\u6c99\u8d6b\u723e"
    ],
    "wof:name":"Zarrin Shahr",
    "wof:placetype":"locality"
},
  "geometry": {"coordinates":[51.3766,32.3897],"type":"Point"}
}