{
  "type": "Feature",
  "properties": {
    "gn:admin1_code":"8",
    "gn:asciiname":"Tanian",
    "gn:country_code":"IR",
    "gn:dem":2040,
    "gn:feature_class":"P",
    "gn:feature_code":"PPL",
    "gn:name":"Tan\u012b\u0101n",
    "gn:population":0,
    "gn:timezone":"Asia/Tehran",
    "iso:country":"IR",
    "name:fas_x_preferred":[
        "\u062a\u064e\u0646\u064a\u0627\u0646"
    ],
    "name:fas_x_variant":[
        "Tan\u012b\u0101n",
        "\u062a\u0646\u06cc\u0627\u0646"
    ],
    "name:msa_x_preferred":[
        "Tanian"
    ],
    "name:ukr_x_preferred":[
        "\u0422\u0430\u043d\u0456\u044f\u043d"
    ],
    "wof:name":"Tanian",
    "wof:placetype":"locality"
},
  "geometry": {"coordinates":[48.92417,37.29639],"type":"Point"}
}