{
  "type": "Feature",
  "properties": {
    "gn:admin1_code":"7",
    "gn:asciiname":"Dara Kuyeh",
    "gn:country_code":"IR",
    "gn:dem":1393,
    "gn:feature_class":"P",
    "gn:feature_code":"PPL",
    "gn:name":"D\u0101r\u0101 K\u016byeh",
    "gn:population":0,
    "gn:timezone":"Asia/Tehran",
    "iso:country":"IR",
    "name:fas_x_preferred":[
        "\u062f\u0627\u0631\u06a9\u0648\u06cc\u0647"
    ],
    "name:fas_x_variant":[
        "D\u0101rk\u016byeh",
        "\u062f\u0627\u0631\u0627 \u06a9\u0648\u06cc\u0647",
        "\u062f\u0627\u0631\u0627 \u06a9\u0627\u0646"
    ],
    "name:und_x_variant":[
        "Deh Kooyeh",
        "Dar\u0101ku",
        "D\u0101r\u0101kubeh",
        "D\u0101r\u0101 K\u016byeh",
        "D\u0101r\u0101 K\u0101n"
    ],
    "wof:name":"Dara Kuyeh",
    "wof:placetype":"locality"
},
  "geometry": {"coordinates":[54.18348,28.83877],"type":"Point"}
}