{
  "type": "Feature",
  "properties": {
    "gn:admin1_code":"41",
    "gn:asciiname":"Ebrahimabad",
    "gn:country_code":"IR",
    "gn:dem":1901,
    "gn:feature_class":"P",
    "gn:feature_code":"PPL",
    "gn:name":"Ebr\u0101h\u012bm\u0101b\u0101d",
    "gn:population":0,
    "gn:timezone":"Asia/Tehran",
    "iso:country":"IR",
    "name:ara_x_preferred":[
        "\u0623\u0628\u0631\u0627\u0647\u064a\u0645 \u0623\u0628\u0627\u062f"
    ],
    "name:fas_x_preferred":[
        "\u0627\u0628\u0631\u0627\u0647\u06cc\u0645 \u0622\u0628\u0627\u062f"
    ],
    "name:fas_x_variant":[
        "Ebr\u0101h\u012bm\u0101b\u0101d",
        "\u0627\u0628\u0631\u0627\u0647\u06cc\u0645\u200c\u0622\u0628\u0627\u062f"
    ],
    "name:und_x_variant":[
        "Ibr\u0101h\u012bm\u0101b\u0101d",
        "Ebrahim Abad Mo\u2019men Abad"
    ],
    "wof:name":"Ebrahimabad",
    "wof:placetype":"locality"
},
  "geometry": {"coordinates":[59.58824,32.84049],"type":"Point"}
}