{
  "type": "Feature",
  "properties": {
    "gn:admin1_code":"4.0",
    "gn:asciiname":"Kala Vachi",
    "gn:country_code":"IR",
    "gn:dem":749,
    "gn:feature_class":"P",
    "gn:feature_code":"PPL",
    "gn:name":"Kal\u0101 V\u0101ch\u012b",
    "gn:population":0,
    "gn:timezone":"Asia/Tehran",
    "iso:country":"IR",
    "wof:name":"Kala Vachi",
    "wof:placetype":"locality"
},
  "geometry": {"coordinates":[60.73944,26.44556],"type":"Point"}
}