{
  "type": "Feature",
  "properties": {
    "gn:admin1_code":"5",
    "gn:asciiname":"Dasht-e Qazi",
    "gn:country_code":"IR",
    "gn:dem":761,
    "gn:feature_class":"P",
    "gn:feature_code":"PPL",
    "gn:name":"Dasht-e Q\u0101\u1e95\u012b",
    "gn:population":0,
    "gn:timezone":"Asia/Tehran",
    "iso:country":"IR",
    "name:ceb_x_preferred":[
        "Dasht-e Q\u0101\u1e95\u012b"
    ],
    "name:fas_x_preferred":[
        "Dasht-e Q\u0101\u1e95\u012b"
    ],
    "name:fas_x_variant":[
        "\u062f\u0634\u062a \u0642\u0627\u0636\u06cc"
    ],
    "name:swe_x_preferred":[
        "Dasht-e Q\u0101\u1e95\u012b"
    ],
    "wof:name":"Dasht-e Qazi",
    "wof:placetype":"locality"
},
  "geometry": {"coordinates":[50.58909,30.96664],"type":"Point"}
}