{
  "type": "Feature",
  "properties": {
    "gn:admin1_code":"39",
    "gn:asciiname":"Varzaneh",
    "gn:country_code":"IR",
    "gn:dem":1566,
    "gn:feature_class":"P",
    "gn:feature_code":"PPL",
    "gn:name":"Varzaneh",
    "gn:population":0,
    "gn:timezone":"Asia/Tehran",
    "iso:country":"IR",
    "name:fas_x_preferred":[
        "\u0648\u0631\u0632\u0646\u0647"
    ],
    "name:und_x_variant":[
        "\u0648\u0631\u0632\u0646\u0647",
        "Varzaneh"
    ],
    "wof:name":"Varzaneh",
    "wof:placetype":"locality"
},
  "geometry": {"coordinates":[50.31509000000001,34.5651],"type":"Point"}
}