{
  "type": "Feature",
  "properties": {
    "gn:admin1_code":"0",
    "gn:asciiname":"Chah Hasan",
    "gn:country_code":"IR",
    "gn:dem":358,
    "gn:feature_class":"P",
    "gn:feature_code":"PPL",
    "gn:name":"Ch\u0101h \u1e28asan",
    "gn:population":0,
    "gn:timezone":"Asia/Tehran",
    "iso:country":"IR",
    "name:fas_x_preferred":[
        "\u0686\u0627\u0647 \u062d\u0633\u0646"
    ],
    "name:fas_x_variant":[
        "Ch\u0101h \u1e28asan"
    ],
    "wof:name":"Chah Hasan",
    "wof:placetype":"locality"
},
  "geometry": {"coordinates":[57.5663,27.4757],"type":"Point"}
}