{
  "type": "Feature",
  "properties": {
    "gn:admin1_code":"8.0",
    "gn:asciiname":"Kamdarz",
    "gn:country_code":"IR",
    "gn:dem":73,
    "gn:feature_class":"P",
    "gn:feature_code":"PPL",
    "gn:name":"Kamdarz",
    "gn:population":0,
    "gn:timezone":"Asia/Tehran",
    "iso:country":"IR",
    "name:fas_x_preferred":[
        "\u06a9\u0645\u062f\u0631\u0632"
    ],
    "wof:name":"Kamdarz",
    "wof:placetype":"locality"
},
  "geometry": {"coordinates":[49.05343,37.56265],"type":"Point"}
}