{
  "type": "Feature",
  "properties": {
    "gn:admin1_code":"29",
    "gn:asciiname":"Dar Maleki",
    "gn:country_code":"IR",
    "gn:dem":1028,
    "gn:feature_class":"P",
    "gn:feature_code":"PPL",
    "gn:name":"Dar Malek\u012b",
    "gn:population":0,
    "gn:timezone":"Asia/Tehran",
    "iso:country":"IR",
    "name:fas_x_preferred":[
        "\u062f\u0631\u0628 \u0645\u0644\u06a9\u06cc"
    ],
    "name:fas_x_variant":[
        "Darb-e Malek\u012b",
        "\u062f\u0631 \u0645\u0644\u06a9\u06cc"
    ],
    "name:und_x_variant":[
        "Derb-e Malek",
        "Darb-e Malek",
        "Darb Malek",
        "Dar Malek\u012b"
    ],
    "wof:name":"Dar Maleki",
    "wof:placetype":"locality"
},
  "geometry": {"coordinates":[58.24572,28.32591],"type":"Point"}
}