{
  "type": "Feature",
  "properties": {
    "gn:admin1_code":"32",
    "gn:asciiname":"Now Shahr",
    "gn:country_code":"IR",
    "gn:dem":1475,
    "gn:feature_class":"P",
    "gn:feature_code":"PPL",
    "gn:name":"Now Shahr",
    "gn:population":0,
    "gn:timezone":"Asia/Tehran",
    "iso:country":"IR",
    "name:ara_x_preferred":[
        "\u0646\u0648\u0634\u0647\u0631"
    ],
    "name:fas_x_preferred":[
        "\u0646\u064f\u0648 \u0634\u0627\u0631"
    ],
    "name:fas_x_variant":[
        "\u0646\u0648 \u0634\u0647\u0631",
        "\u0646\u0648\u0634\u0647\u0631"
    ],
    "name:msa_x_preferred":[
        "Now Shahr"
    ],
    "name:mzn_x_preferred":[
        "\u0646\u0648\u0634\u0647\u0631"
    ],
    "name:und_x_variant":[
        "Now Sh\u0101r",
        "Nushar",
        "Now Shahr"
    ],
    "wof:name":"Now Shahr",
    "wof:placetype":"locality"
},
  "geometry": {"coordinates":[48.4209,38.0884],"type":"Point"}
}