{
  "type": "Feature",
  "properties": {
    "gn:admin1_code":"15",
    "gn:asciiname":"Pol-e Bala Rud",
    "gn:country_code":"IR",
    "gn:dem":244,
    "gn:feature_class":"P",
    "gn:feature_code":"PPL",
    "gn:name":"Pol-e B\u0101l\u0101 R\u016bd",
    "gn:population":0,
    "gn:timezone":"Asia/Tehran",
    "iso:country":"IR",
    "name:ara_x_preferred":[
        "\u062c\u0633\u0631 \u0628\u0627\u0644\u0627\u0631\u0648\u062f"
    ],
    "name:azb_x_preferred":[
        "\u067e\u0644 \u0628\u0627\u0644\u0627\u0631\u0648\u062f(\u0627\u0646\u062f\u06cc\u0645\u0634\u06a9)"
    ],
    "name:fas_x_preferred":[
        "Pol-e B\u0101l\u0101 R\u016bd"
    ],
    "name:fas_x_variant":[
        "\u067e\u0644 \u0628\u0627\u0644\u0627\u0631\u0648\u062f"
    ],
    "wof:name":"Pol-e Bala Rud",
    "wof:placetype":"locality"
},
  "geometry": {"coordinates":[48.28333,32.58333],"type":"Point"}
}