{
  "type": "Feature",
  "properties": {
    "gn:admin1_code":"42",
    "gn:asciiname":"Hasanabad-e Bala",
    "gn:country_code":"IR",
    "gn:dem":1132,
    "gn:feature_class":"P",
    "gn:feature_code":"PPL",
    "gn:name":"\u1e28asan\u0101b\u0101d-e B\u0101l\u0101",
    "gn:population":0,
    "gn:timezone":"Asia/Tehran",
    "iso:country":"IR",
    "name:fas_x_preferred":[
        "\u062d\u0633\u0646 \u0622\u0628\u0627\u062f \u0628\u0627\u0644\u0627"
    ],
    "name:fas_x_variant":[
        "\u1e28asan\u0101b\u0101d-e B\u0101l\u0101"
    ],
    "wof:name":"Hasanabad-e Bala",
    "wof:placetype":"locality"
},
  "geometry": {"coordinates":[59.48726,35.01242],"type":"Point"}
}