{
  "type": "Feature",
  "properties": {
    "gn:admin1_code":"5",
    "gn:asciiname":"Badam Gerdaki",
    "gn:country_code":"IR",
    "gn:dem":1446,
    "gn:feature_class":"P",
    "gn:feature_code":"PPL",
    "gn:name":"B\u0101d\u0101m Gerdak\u012b",
    "gn:population":0,
    "gn:timezone":"Asia/Tehran",
    "iso:country":"IR",
    "name:fas_x_preferred":[
        "B\u0101d\u0101m Gerdak\u012b"
    ],
    "name:fas_x_variant":[
        "\u0628\u0627\u062f\u0627\u0645 \u06af\u0631\u062f\u06a9\u06cc"
    ],
    "wof:name":"Badam Gerdaki",
    "wof:placetype":"locality"
},
  "geometry": {"coordinates":[50.60362,31.17061],"type":"Point"}
}