{
  "type": "Feature",
  "properties": {
    "gn:admin1_code":"7.0",
    "gn:asciiname":"Shetvan",
    "gn:country_code":"IR",
    "gn:dem":709,
    "gn:feature_class":"P",
    "gn:feature_code":"PPL",
    "gn:name":"Shetv\u0101n",
    "gn:population":0,
    "gn:timezone":"Asia/Tehran",
    "iso:country":"IR",
    "name:ara_x_preferred":[
        "\u0634\u062a\u0648\u0627\u0646"
    ],
    "name:fas_x_preferred":[
        "Shetv\u0101n"
    ],
    "name:fas_x_variant":[
        "\u0634\u062a\u0648\u0627\u0646",
        "\u0634\u062a \u0648\u0627\u0646"
    ],
    "name:msa_x_preferred":[
        "Shetvan"
    ],
    "name:und_x_variant":[
        "\u0634\u062a\u0648\u0627\u0646"
    ],
    "wof:name":"Shetvan",
    "wof:placetype":"locality"
},
  "geometry": {"coordinates":[55.46454,27.86989],"type":"Point"}
}