{
  "type": "Feature",
  "properties": {
    "iso:country":"IR",
    "name:ara_x_preferred":[
        "\u062a\u062c\u0631\u064a\u0634"
    ],
    "name:ast_x_preferred":[
        "Tajrish"
    ],
    "name:azb_x_preferred":[
        "\u062a\u062c\u0631\u06cc\u0634"
    ],
    "name:aze_x_preferred":[
        "T\u0259cri\u015f"
    ],
    "name:bel_x_preferred":[
        "\u0422\u0430\u0434\u0436\u0440\u044b\u0448"
    ],
    "name:bul_x_preferred":[
        "\u0422\u0430\u0434\u0436\u0440\u0438\u0448"
    ],
    "name:cat_x_preferred":[
        "Tajrish"
    ],
    "name:deu_x_preferred":[
        "Tadschrisch"
    ],
    "name:eng_x_preferred":[
        "Tajrish"
    ],
    "name:eus_x_preferred":[
        "Tajrix"
    ],
    "name:fas_x_preferred":[
        "\u062a\u062c\u0631\u06cc\u0634"
    ],
    "name:fas_x_variant":[
        "\u062a\u062c\u0631\u064a\u0634",
        "Tajr\u012bsh"
    ],
    "name:fra_x_preferred":[
        "Tajrish"
    ],
    "name:ita_x_preferred":[
        "Tajrish"
    ],
    "name:jpn_x_preferred":[
        "\u30bf\u30b8\u30e5\u30ea\u30b7\u30e5"
    ],
    "name:mzn_x_preferred":[
        "\u062a\u062c\u0631\u06cc\u0634"
    ],
    "name:nld_x_preferred":[
        "Tajrish"
    ],
    "name:rus_x_preferred":[
        "\u0422\u0430\u0434\u0436\u0440\u0438\u0448"
    ],
    "name:slv_x_preferred":[
        "Tajri\u0161"
    ],
    "name:swe_x_preferred":[
        "Tajrish"
    ],
    "name:tgk_x_preferred":[
        "\u0422\u0430\u04b7\u0440\u0438\u0448"
    ],
    "name:tur_x_preferred":[
        "Tecri\u015f"
    ],
    "name:urd_x_preferred":[
        "\u062a\u062c\u0631\u06cc\u0634"
    ],
    "name:zho_x_preferred":[
        "\u5854\u5b63\u91cc\u4ec0"
    ],
    "qs:gn_country":"IR",
    "qs:gn_fcode":"PPLX",
    "qs:gn_pop":0,
    "qs:name":"Tajrish",
    "qs:name_adm0":"Iran",
    "qs:name_adm1":"Tehran",
    "qs:photos":935,
    "qs:photos_1k":189,
    "qs:photos_9k":4,
    "qs:photos_9r":6,
    "qs:photos_all":935,
    "qs:photos_sr":10,
    "qs:placetype":"Town",
    "qs:pop_sr":"0",
    "qs:woe_adm0":23424851,
    "wd:wordcount":685,
    "wof:name":"Tajrish",
    "wof:placetype":"locality"
},
  "geometry": {"coordinates":[51.4256,35.8044],"type":"Point"}
}