{
  "type": "Feature",
  "properties": {
    "gn:admin1_code":"4.0",
    "gn:asciiname":"Bidi-ye Bala",
    "gn:country_code":"IR",
    "gn:dem":1842,
    "gn:feature_class":"P",
    "gn:feature_code":"PPL",
    "gn:name":"B\u012bd\u012b-ye B\u0101l\u0101",
    "gn:population":0,
    "gn:timezone":"Asia/Tehran",
    "iso:country":"IR",
    "name:fas_x_preferred":[
        "B\u012bd\u012b-ye B\u0101l\u0101"
    ],
    "wof:name":"Bidi-ye Bala",
    "wof:placetype":"locality"
},
  "geometry": {"coordinates":[60.71666999999999,29.35],"type":"Point"}
}