{
  "type": "Feature",
  "properties": {
    "gn:admin1_code":"13",
    "gn:asciiname":"Qeshlaq-e Sahanleh",
    "gn:country_code":"IR",
    "gn:dem":2029,
    "gn:feature_class":"P",
    "gn:feature_code":"PPL",
    "gn:name":"Qeshl\u0101q-e Sahanleh",
    "gn:population":0,
    "gn:timezone":"Asia/Tehran",
    "iso:country":"IR",
    "name:fas_x_preferred":[
        "\u0642\u0634\u0644\u0627\u0642 \u0633\u0647\u0646\u0644\u0647"
    ],
    "name:fas_x_variant":[
        "Qeshl\u0101q-e Sahanleh"
    ],
    "wof:name":"Qeshlaq-e Sahanleh",
    "wof:placetype":"locality"
},
  "geometry": {"coordinates":[47.63,34.8452],"type":"Point"}
}