{
  "type": "Feature",
  "properties": {
    "gn:admin1_code":"42",
    "gn:asciiname":"Deh Menar",
    "gn:country_code":"IR",
    "gn:dem":1646,
    "gn:feature_class":"P",
    "gn:feature_code":"PPL",
    "gn:name":"Deh Men\u0101r",
    "gn:population":0,
    "gn:timezone":"Asia/Tehran",
    "iso:country":"IR",
    "name:fas_x_preferred":[
        "\u062f\u0647 \u0645\u0646\u0627\u0631"
    ],
    "name:fas_x_variant":[
        "Deh Men\u0101r"
    ],
    "wof:name":"Deh Menar",
    "wof:placetype":"locality"
},
  "geometry": {"coordinates":[59.06100000000001,35.60731],"type":"Point"}
}