{
  "type": "Feature",
  "properties": {
    "gn:admin1_code":"8",
    "gn:asciiname":"Niasan",
    "gn:country_code":"IR",
    "gn:dem":1913,
    "gn:feature_class":"P",
    "gn:feature_code":"PPL",
    "gn:name":"N\u012b\u0101san",
    "gn:population":0,
    "gn:timezone":"Asia/Tehran",
    "iso:country":"IR",
    "name:fas_x_preferred":[
        "N\u012b\u0101s\u0101n"
    ],
    "name:fas_x_variant":[
        "N\u012b\u0101san",
        "\u0646\u06cc\u0627\u0633\u0646"
    ],
    "name:msa_x_preferred":[
        "Niasan"
    ],
    "name:ukr_x_preferred":[
        "\u041d\u0456\u044f\u0441\u0430\u043d"
    ],
    "name:und_x_variant":[
        "N\u012b\u0101s\u012bn"
    ],
    "wof:name":"Niasan",
    "wof:placetype":"locality"
},
  "geometry": {"coordinates":[50.30653,36.73136],"type":"Point"}
}