{
  "type": "Feature",
  "properties": {
    "gn:admin1_code":"4",
    "gn:asciiname":"Tarati",
    "gn:country_code":"IR",
    "gn:dem":150,
    "gn:feature_class":"P",
    "gn:feature_code":"PPL",
    "gn:name":"Tar\u0101t\u012b",
    "gn:population":0,
    "gn:timezone":"Asia/Tehran",
    "iso:country":"IR",
    "name:fas_x_preferred":[
        "Ter\u0101t\u012b"
    ],
    "name:fas_x_variant":[
        "Tar\u0101t\u012b",
        "\u062a\u0631\u0627\u062a\u06cc"
    ],
    "name:und_x_variant":[
        "Tarat\u012b",
        "Trati",
        "Tor\u0101t\u012b",
        "\u062a\u0631\u0627\u062a\u06cc"
    ],
    "name:urd_x_preferred":[
        "\u062a\u0631\u0627\u0679\u06cc"
    ],
    "wof:name":"Tarati",
    "wof:placetype":"locality"
},
  "geometry": {"coordinates":[59.65311,25.9765],"type":"Point"}
}