{
  "type": "Feature",
  "properties": {
    "gn:admin1_code":"7",
    "gn:asciiname":"Qeshlaq-e `Ashayeri-ye Gowd-e Gorazi",
    "gn:country_code":"IR",
    "gn:dem":669,
    "gn:feature_class":"P",
    "gn:feature_code":"PPLL",
    "gn:name":"Qeshl\u0101q-e \u2018Ash\u0101yer\u012b-ye Gowd-e Gor\u0101z\u012b",
    "gn:population":0,
    "gn:timezone":"Asia/Tehran",
    "iso:country":"IR",
    "name:fas_x_preferred":[
        "\u06af\u0648\u062f \u06af\u0631\u0627\u0632\u06cc"
    ],
    "name:fas_x_variant":[
        "Gowd-e Gor\u0101z\u012b",
        "\u0642\u0634\u0644\u0627\u0642 \u0639\u0634\u0627\u06cc\u0631\u06cc \u06af\u0648\u062f \u06af\u0631\u0627\u0632\u06cc"
    ],
    "name:und_x_variant":[
        "Qeshl\u0101q-e \u2018Ash\u0101yer\u012b-ye Gowd-e Gor\u0101z\u012b"
    ],
    "wof:name":"Qeshlaq-e `Ashayeri-ye Gowd-e Gorazi",
    "wof:placetype":"locality"
},
  "geometry": {"coordinates":[53.01781,28.26626],"type":"Point"}
}