{
  "type": "Feature",
  "properties": {
    "gn:admin1_code":"8",
    "gn:asciiname":"Siah Posht",
    "gn:country_code":"IR",
    "gn:dem":861,
    "gn:feature_class":"P",
    "gn:feature_code":"PPL",
    "gn:name":"S\u012b\u0101h Posht",
    "gn:population":0,
    "gn:timezone":"Asia/Tehran",
    "iso:country":"IR",
    "name:fas_x_preferred":[
        "\u0633\u06cc\u0627\u0647 \u067e\u0634\u062a"
    ],
    "name:fas_x_variant":[
        "S\u012b\u0101h Posht"
    ],
    "wof:name":"Siah Posht",
    "wof:placetype":"locality"
},
  "geometry": {"coordinates":[48.76949000000001,37.88548],"type":"Point"}
}