{
  "type": "Feature",
  "properties": {
    "gn:admin1_code":"29",
    "gn:asciiname":"Rudin",
    "gn:country_code":"IR",
    "gn:dem":2454,
    "gn:feature_class":"P",
    "gn:feature_code":"PPL",
    "gn:name":"R\u016bd\u012bn",
    "gn:population":0,
    "gn:timezone":"Asia/Tehran",
    "iso:country":"IR",
    "name:ara_x_preferred":[
        "\u0631\u0648\u062f\u064a\u0646"
    ],
    "name:deu_x_preferred":[
        "Rudin"
    ],
    "name:fas_x_preferred":[
        "Zand\u016b\u2019\u012byeh"
    ],
    "name:fas_x_variant":[
        "\u0631\u0648\u062f\u06cc\u0646",
        "\u0645\u062d\u0645\u0648\u062f \u0622\u0628\u0627\u062f \u0631\u0648\u062f\u06cc\u0646"
    ],
    "name:fra_x_preferred":[
        "Roudine"
    ],
    "name:hun_x_preferred":[
        "Rugyin"
    ],
    "name:hye_x_preferred":[
        "\u054c\u0578\u0582\u0564\u056b\u0576"
    ],
    "name:pan_x_preferred":[
        "\u0a30\u0a42\u0a26\u0a3f\u0a28"
    ],
    "name:pnb_x_preferred":[
        "\u0631\u0648\u062f\u0646"
    ],
    "name:pol_x_preferred":[
        "Rudin"
    ],
    "name:rus_x_preferred":[
        "\u0420\u0443\u0434\u0438\u043d"
    ],
    "name:und_x_variant":[
        "R\u016bd\u012bn",
        "Ma\u1e29m\u016bd\u0101b\u0101d-e R\u016bd\u012bn"
    ],
    "wof:name":"Rudin",
    "wof:placetype":"locality"
},
  "geometry": {"coordinates":[55.94585,30.02706],"type":"Point"}
}