{
  "type": "Feature",
  "properties": {
    "gn:admin1_code":"26",
    "gn:asciiname":"Qal`eh Cheh",
    "gn:country_code":"IR",
    "gn:dem":965,
    "gn:feature_class":"P",
    "gn:feature_code":"PPL",
    "gn:name":"Qal\u2018eh Cheh",
    "gn:population":0,
    "gn:timezone":"Asia/Tehran",
    "iso:country":"IR",
    "name:fas_x_preferred":[
        "\u0642\u0644\u0639\u0647 \u0686\u0647"
    ],
    "name:fas_x_variant":[
        "Qal\u2018eh Cheh"
    ],
    "wof:name":"Qal`eh Cheh",
    "wof:placetype":"locality"
},
  "geometry": {"coordinates":[51.6863,35.3637],"type":"Point"}
}