{
  "type": "Feature",
  "properties": {
    "gn:admin1_code":"23.0",
    "gn:asciiname":"Shahid Chamran-e Seh",
    "gn:country_code":"IR",
    "gn:dem":1252,
    "gn:feature_class":"P",
    "gn:feature_code":"PPL",
    "gn:name":"Shah\u012bd Chamr\u0101n-e Seh",
    "gn:population":0,
    "gn:timezone":"Asia/Tehran",
    "iso:country":"IR",
    "name:fas_x_preferred":[
        "Shah\u012bd Chamr\u0101n-e Seh"
    ],
    "name:fas_x_variant":[
        "\u0634\u0647\u06cc\u062f \u0686\u0645\u0631\u0627\u0646 \u0633\u0647"
    ],
    "name:und_x_variant":[
        "\u0634\u0647\u06cc\u062f \u0686\u0645\u0631\u0627\u0646 \u0633\u0647"
    ],
    "wof:name":"Shahid Chamran-e Seh",
    "wof:placetype":"locality"
},
  "geometry": {"coordinates":[48.06742,33.21022],"type":"Point"}
}