{
  "type": "Feature",
  "properties": {
    "gn:admin1_code":"13",
    "gn:asciiname":"Dangi-ye `Abbas",
    "gn:country_code":"IR",
    "gn:dem":1194,
    "gn:feature_class":"P",
    "gn:feature_code":"PPL",
    "gn:name":"Dang\u012b-ye \u2018Abb\u0101s",
    "gn:population":0,
    "gn:timezone":"Asia/Tehran",
    "iso:country":"IR",
    "name:fas_x_preferred":[
        "\u062f\u0646\u06af\u06cc \u0639\u0628\u0627\u0633"
    ],
    "name:fas_x_variant":[
        "Deng\u012b-ye \u2018Abb\u0101s D\u0101reh Zard",
        "Dang\u012b-ye \u2018Abb\u0101s"
    ],
    "wof:name":"Dangi-ye `Abbas",
    "wof:placetype":"locality"
},
  "geometry": {"coordinates":[46.0105,34.6322],"type":"Point"}
}