{
  "type": "Feature",
  "properties": {
    "gn:admin1_code":"8.0",
    "gn:asciiname":"Gilavandan",
    "gn:country_code":"IR",
    "gn:dem":15,
    "gn:feature_class":"P",
    "gn:feature_code":"PPL",
    "gn:name":"G\u012bl\u0101vand\u0101n",
    "gn:population":0,
    "gn:timezone":"Asia/Tehran",
    "iso:country":"IR",
    "name:fas_x_preferred":[
        "K\u012bl\u0101vand\u0101n"
    ],
    "name:fas_x_variant":[
        "\u06af\u06cc\u0644\u0627\u0648\u0646\u062f\u0627\u0646"
    ],
    "name:msa_x_preferred":[
        "Gilavandan"
    ],
    "name:ukr_x_preferred":[
        "\u0490\u0456\u043b\u044f\u0432\u0430\u043d\u0434\u0430\u043d"
    ],
    "name:und_x_variant":[
        "G\u012bl\u0101vand\u0101n"
    ],
    "wof:name":"Gilavandan",
    "wof:placetype":"locality"
},
  "geometry": {"coordinates":[49.74842,37.21508],"type":"Point"}
}