{
  "type": "Feature",
  "properties": {
    "gn:admin1_code":"7",
    "gn:asciiname":"Sar Astaneh",
    "gn:country_code":"IR",
    "gn:dem":1647,
    "gn:feature_class":"P",
    "gn:feature_code":"PPL",
    "gn:name":"Sar \u0100st\u0101neh",
    "gn:population":0,
    "gn:timezone":"Asia/Tehran",
    "iso:country":"IR",
    "name:fas_x_preferred":[
        "Sar \u0100st\u0101neh"
    ],
    "name:fas_x_variant":[
        "\u0633\u0631 \u0622\u0633\u062a\u0627\u0646\u0647"
    ],
    "wof:name":"Sar Astaneh",
    "wof:placetype":"locality"
},
  "geometry": {"coordinates":[51.14325,30.59266],"type":"Point"}
}