{
  "type": "Feature",
  "properties": {
    "gn:admin1_code":"37",
    "gn:asciiname":"Qolmas",
    "gn:country_code":"IR",
    "gn:dem":-21,
    "gn:feature_class":"P",
    "gn:feature_code":"PPL",
    "gn:name":"Qolmas",
    "gn:population":0,
    "gn:timezone":"Asia/Tehran",
    "iso:country":"IR",
    "name:ceb_x_preferred":[
        "Qolmas"
    ],
    "name:fas_x_preferred":[
        "\u0642\u0644\u0645\u0633"
    ],
    "name:msa_x_preferred":[
        "Qolmas"
    ],
    "name:swe_x_preferred":[
        "Qolmas"
    ],
    "wof:name":"Qolmas",
    "wof:placetype":"locality"
},
  "geometry": {"coordinates":[54.24712,37.12624],"type":"Point"}
}