{
  "type": "Feature",
  "properties": {
    "gn:admin1_code":"32",
    "gn:asciiname":"Gazvar-e `Olya",
    "gn:country_code":"IR",
    "gn:dem":1638,
    "gn:feature_class":"P",
    "gn:feature_code":"PPL",
    "gn:name":"Gazvar-e \u2018Oly\u0101",
    "gn:population":0,
    "gn:timezone":"Asia/Tehran",
    "iso:country":"IR",
    "name:fas_x_preferred":[
        "\u06af\u0632\u0648\u0631 \u0639\u0644\u06cc\u0627"
    ],
    "name:fas_x_variant":[
        "\u06a9\u0632\u0648\u0632 \u0639\u0644\u064a\u0627",
        "Gazvar-e \u2018Oly\u0101",
        "Kazvaz-e \u2018Oly\u0101"
    ],
    "name:msa_x_preferred":[
        "Gazvar-e Olya"
    ],
    "name:und_x_variant":[
        "Gaz\u016br-e \u2018Oly\u0101"
    ],
    "wof:name":"Gazvar-e `Olya",
    "wof:placetype":"locality"
},
  "geometry": {"coordinates":[48.31857,37.84159],"type":"Point"}
}