{
  "type": "Feature",
  "properties": {
    "gn:admin1_code":"11",
    "gn:asciiname":"Kiseh'i",
    "gn:country_code":"IR",
    "gn:dem":1244,
    "gn:feature_class":"P",
    "gn:feature_code":"PPL",
    "gn:name":"K\u012bseh\u2019\u012b",
    "gn:population":0,
    "gn:timezone":"Asia/Tehran",
    "iso:country":"IR",
    "name:fas_x_preferred":[
        "\u06a9\u06cc\u0633\u0647 \u0627\u06cc"
    ],
    "name:fas_x_variant":[
        "K\u012bseh\u2019\u012b"
    ],
    "wof:name":"Kiseh'i",
    "wof:placetype":"locality"
},
  "geometry": {"coordinates":[57.8525,26.7483],"type":"Point"}
}