{
  "type": "Feature",
  "properties": {
    "gn:admin1_code":"33",
    "gn:asciiname":"Gaviran",
    "gn:country_code":"IR",
    "gn:dem":1957,
    "gn:feature_class":"P",
    "gn:feature_code":"PPL",
    "gn:name":"Gav\u012br\u0101n",
    "gn:population":0,
    "gn:timezone":"Asia/Tehran",
    "iso:country":"IR",
    "name:fas_x_preferred":[
        "Gav\u012br\u0101n"
    ],
    "wof:name":"Gaviran",
    "wof:placetype":"locality"
},
  "geometry": {"coordinates":[46.86667,38.91667],"type":"Point"}
}