{
  "type": "Feature",
  "properties": {
    "gn:admin1_code":"41",
    "gn:asciiname":"Narmenj",
    "gn:country_code":"IR",
    "gn:dem":1643,
    "gn:feature_class":"P",
    "gn:feature_code":"PPL",
    "gn:name":"N\u0101rmenj",
    "gn:population":0,
    "gn:timezone":"Asia/Tehran",
    "iso:country":"IR",
    "name:fas_x_preferred":[
        "N\u0101rmenj"
    ],
    "name:fas_x_variant":[
        "\u0646\u0627\u0631\u0645\u0646\u062c"
    ],
    "name:und_x_variant":[
        "\u0646\u0627\u0631\u0645\u0646\u062c"
    ],
    "wof:name":"Narmenj",
    "wof:placetype":"locality"
},
  "geometry": {"coordinates":[59.13363,32.83798],"type":"Point"}
}