{
  "type": "Feature",
  "properties": {
    "gn:admin1_code":"15",
    "gn:asciiname":"Mansuriyeh-ye Do",
    "gn:country_code":"IR",
    "gn:dem":27,
    "gn:feature_class":"P",
    "gn:feature_code":"PPL",
    "gn:name":"Man\u015f\u016br\u012byeh-ye Do",
    "gn:population":0,
    "gn:timezone":"Asia/Tehran",
    "iso:country":"IR",
    "name:ara_x_preferred":[
        "\u0645\u0646\u0635\u0648\u0631\u064a\u0629 \u0627\u0644\u062b\u0627\u0646\u064a\u0629"
    ],
    "name:azb_x_preferred":[
        "\u0645\u0646\u0635\u0648\u0631\u06cc\u0647 \u062f\u0648(\u0627\u0647\u0648\u0627\u0632)"
    ],
    "name:ceb_x_preferred":[
        "Man\u015f\u016br\u012byeh-ye Do"
    ],
    "name:fas_x_preferred":[
        "\u0645\u0646\u0635\u0648\u0631\u06cc\u0647 \u062f\u0648"
    ],
    "name:fas_x_variant":[
        "Man\u015f\u016br\u012byeh-ye Do"
    ],
    "name:swe_x_preferred":[
        "Man\u015f\u016br\u012byeh-ye Do"
    ],
    "wof:name":"Mansuriyeh-ye Do",
    "wof:placetype":"locality"
},
  "geometry": {"coordinates":[48.86961,31.50542],"type":"Point"}
}