{
  "type": "Feature",
  "properties": {
    "gn:admin1_code":"4",
    "gn:asciiname":"Maskan",
    "gn:country_code":"IR",
    "gn:dem":947,
    "gn:feature_class":"P",
    "gn:feature_code":"PPL",
    "gn:name":"Maskan",
    "gn:population":0,
    "gn:timezone":"Asia/Tehran",
    "iso:country":"IR",
    "name:ceb_x_preferred":[
        "Maskan"
    ],
    "name:fas_x_preferred":[
        "\u0645\u0633\u06a9\u0646"
    ],
    "name:swe_x_preferred":[
        "Maskan"
    ],
    "wof:name":"Maskan",
    "wof:placetype":"locality"
},
  "geometry": {"coordinates":[60.76115,26.92185],"type":"Point"}
}