{
  "type": "Feature",
  "properties": {
    "gn:admin1_code":"8",
    "gn:asciiname":"Fishom",
    "gn:country_code":"IR",
    "gn:dem":242,
    "gn:feature_class":"P",
    "gn:feature_code":"PPLL",
    "gn:name":"F\u012bshom",
    "gn:population":0,
    "gn:timezone":"Asia/Tehran",
    "iso:country":"IR",
    "name:ceb_x_preferred":[
        "F\u012bshom"
    ],
    "name:fas_x_preferred":[
        "Qas\u012bm"
    ],
    "name:fas_x_variant":[
        "\u0641\u06cc\u0634\u0645"
    ],
    "name:msa_x_preferred":[
        "Fishom"
    ],
    "name:swe_x_preferred":[
        "F\u012bshom"
    ],
    "name:ukr_x_preferred":[
        "\u0424\u0456\u0448\u043e\u043c"
    ],
    "wof:name":"Fishom",
    "wof:placetype":"locality"
},
  "geometry": {"coordinates":[49.4812,36.8421],"type":"Point"}
}