{
  "type": "Feature",
  "properties": {
    "gn:admin1_code":"11.0",
    "gn:asciiname":"Chira",
    "gn:country_code":"IR",
    "gn:dem":30,
    "gn:feature_class":"P",
    "gn:feature_code":"PPL",
    "gn:name":"Ch\u012br\u0101",
    "gn:population":0,
    "gn:timezone":"Asia/Tehran",
    "iso:country":"IR",
    "name:fas_x_preferred":[
        "\u0686\u064a\u0631\u0627"
    ],
    "name:und_x_variant":[
        "Ch\u012br\u0101"
    ],
    "wof:name":"Chira",
    "wof:placetype":"locality"
},
  "geometry": {"coordinates":[56.04194,26.81056],"type":"Point"}
}