{
  "type": "Feature",
  "properties": {
    "gn:admin1_code":"1",
    "gn:asciiname":"Shekar Bolaghi",
    "gn:country_code":"IR",
    "gn:dem":1805,
    "gn:feature_class":"P",
    "gn:feature_code":"PPL",
    "gn:name":"Shekar Bol\u0101gh\u012b",
    "gn:population":0,
    "gn:timezone":"Asia/Tehran",
    "iso:country":"IR",
    "name:fas_x_preferred":[
        "Shekar Bol\u0101gh\u012b"
    ],
    "name:fas_x_variant":[
        "\u0634\u06a9\u0631 \u0628\u0644\u0627\u063a\u06cc"
    ],
    "wof:name":"Shekar Bolaghi",
    "wof:placetype":"locality"
},
  "geometry": {"coordinates":[44.7724,38.934],"type":"Point"}
}