{
  "type": "Feature",
  "properties": {
    "gn:admin1_code":"29",
    "gn:asciiname":"Najafabad",
    "gn:country_code":"IR",
    "gn:dem":1749,
    "gn:feature_class":"P",
    "gn:feature_code":"PPL",
    "gn:name":"Najaf\u0101b\u0101d",
    "gn:population":0,
    "gn:timezone":"Asia/Tehran",
    "iso:country":"IR",
    "name:ara_x_preferred":[
        "\u0646\u062c\u0641 \u0622\u0628\u0627\u062f"
    ],
    "name:arz_x_preferred":[
        "\u0646\u062c\u0641 \u0622\u0628\u0627\u062f"
    ],
    "name:azb_x_preferred":[
        "\u0646\u062c\u0641\u200c\u0622\u0628\u0627\u062f"
    ],
    "name:aze_x_preferred":[
        "N\u0259c\u0259fabad"
    ],
    "name:ceb_x_preferred":[
        "Najaf\u0101b\u0101d"
    ],
    "name:epo_x_preferred":[
        "Na\u011dafabad"
    ],
    "name:fas_x_preferred":[
        "Najaf\u0101b\u0101d"
    ],
    "name:fas_x_variant":[
        "\u0646\u062c\u0641\u200c\u0622\u0628\u0627\u062f"
    ],
    "name:fin_x_preferred":[
        "Najafabad"
    ],
    "name:fra_x_preferred":[
        "Nadjafabad"
    ],
    "name:hin_x_preferred":[
        "\u0928\u091c\u092b\u093e\u092c\u093e\u0926"
    ],
    "name:ita_x_preferred":[
        "Najafabad"
    ],
    "name:mlg_x_preferred":[
        "Najafabad"
    ],
    "name:mzn_x_preferred":[
        "\u0646\u062c\u0641\u200c\u0622\u0628\u0627\u062f"
    ],
    "name:oss_x_preferred":[
        "\u041d\u0430\u0434\u0436\u0430\u0444\u0430\u0431\u0430\u0434"
    ],
    "name:pnb_x_preferred":[
        "\u0646\u062c\u0641 \u0622\u0628\u0627\u062f"
    ],
    "name:pol_x_preferred":[
        "Nad\u017cafabad"
    ],
    "name:por_x_preferred":[
        "Najafabad"
    ],
    "name:ron_x_preferred":[
        "Najafabad"
    ],
    "name:rus_x_preferred":[
        "\u041d\u0435\u0434\u0436\u0435\u0444\u0430\u0431\u0430\u0434"
    ],
    "name:swe_x_preferred":[
        "Najafabad"
    ],
    "name:tgk_x_preferred":[
        "\u041d\u0430\u04b7\u0430\u0444\u043e\u0431\u043e\u0434"
    ],
    "name:tur_x_preferred":[
        "Necefabad"
    ],
    "name:urd_x_preferred":[
        "\u0646\u062c\u0641 \u0622\u0628\u0627\u062f"
    ],
    "name:war_x_preferred":[
        "Najafabad"
    ],
    "name:zho_x_preferred":[
        "\u7d0d\u5091\u6cd5\u5df4\u5fb7"
    ],
    "wof:name":"Najafabad",
    "wof:placetype":"locality"
},
  "geometry": {"coordinates":[56.93611,30.24556],"type":"Point"}
}