{
  "type": "Feature",
  "properties": {
    "gn:admin1_code":"29",
    "gn:asciiname":"Najafabad",
    "gn:country_code":"IR",
    "gn:dem":1749,
    "gn:feature_class":"P",
    "gn:feature_code":"PPL",
    "gn:name":"Najaf\u0101b\u0101d",
    "gn:population":0,
    "gn:timezone":"Asia/Tehran",
    "iso:country":"IR",
    "name:fas_x_preferred":[
        "Najaf\u0101b\u0101d"
    ],
    "wof:name":"Najafabad",
    "wof:placetype":"locality"
},
  "geometry": {"coordinates":[56.93611,30.24556],"type":"Point"}
}