{
  "type": "Feature",
  "properties": {
    "gn:admin1_code":"36",
    "gn:asciiname":"Shaqaqi-ye Jezla",
    "gn:country_code":"IR",
    "gn:dem":657,
    "gn:feature_class":"P",
    "gn:feature_code":"PPL",
    "gn:name":"Shaq\u0101q\u012b-ye Jezl\u0101",
    "gn:population":0,
    "gn:timezone":"Asia/Tehran",
    "iso:country":"IR",
    "name:azb_x_preferred":[
        "\u0634\u0642\u0627\u0642\u06cc \u062c\u0632\u0644\u0627"
    ],
    "name:ceb_x_preferred":[
        "Shaq\u0101q\u012b-ye Jezl\u0101"
    ],
    "name:fas_x_preferred":[
        "\u0634\u0642\u0627\u0642\u06cc \u062c\u0632\u0644\u0627"
    ],
    "name:fas_x_variant":[
        "Shaq\u0101q\u012b-ye Jezl\u0101",
        "\u0642\u0634\u0644\u0627\u0642 \u062c\u0632\u0644\u0627"
    ],
    "name:swe_x_preferred":[
        "Shaq\u0101q\u012b-ye Jezl\u0101"
    ],
    "name:und_x_variant":[
        "Qeshl\u0101q-e Jezl\u0101"
    ],
    "wof:name":"Shaqaqi-ye Jezla",
    "wof:placetype":"locality"
},
  "geometry": {"coordinates":[48.74422,36.97529],"type":"Point"}
}