{
  "type": "Feature",
  "properties": {
    "gn:admin1_code":"29",
    "gn:asciiname":"Ker",
    "gn:country_code":"IR",
    "gn:dem":2515,
    "gn:feature_class":"P",
    "gn:feature_code":"PPL",
    "gn:name":"Ker",
    "gn:population":0,
    "gn:timezone":"Asia/Tehran",
    "iso:country":"IR",
    "wof:name":"Ker",
    "wof:placetype":"locality"
},
  "geometry": {"coordinates":[57.91667,28.91667],"type":"Point"}
}