{
  "type": "Feature",
  "properties": {
    "gn:admin1_code":"0",
    "gn:asciiname":"Mansurabad",
    "gn:country_code":"IR",
    "gn:dem":2385,
    "gn:feature_class":"P",
    "gn:feature_code":"PPL",
    "gn:name":"Man\u015f\u016br\u0101b\u0101d",
    "gn:population":0,
    "gn:timezone":"Asia/Tehran",
    "iso:country":"IR",
    "name:fas_x_preferred":[
        "\u0645\u064e\u0646\u0635\u0648\u0631 \u0622\u0628\u0627\u062f"
    ],
    "name:fas_x_variant":[
        "Man\u015f\u016br\u0101b\u0101d"
    ],
    "wof:name":"Mansurabad",
    "wof:placetype":"locality"
},
  "geometry": {"coordinates":[55.83333,31.46667],"type":"Point"}
}