{
  "type": "Feature",
  "properties": {
    "gn:admin1_code":"8",
    "gn:asciiname":"Shahran",
    "gn:country_code":"IR",
    "gn:dem":197,
    "gn:feature_class":"P",
    "gn:feature_code":"PPL",
    "gn:name":"Shahr\u0101n",
    "gn:population":0,
    "gn:timezone":"Asia/Tehran",
    "iso:country":"IR",
    "name:fas_x_preferred":[
        "Shahr\u0101n"
    ],
    "name:fas_x_variant":[
        "\u0634\u0647\u0631\u0627\u0646"
    ],
    "name:und_x_variant":[
        "Sh\u0101r\u0101n",
        "Shiaran",
        "\u0634\u0647\u0631\u0627\u0646"
    ],
    "wof:name":"Shahran",
    "wof:placetype":"locality"
},
  "geometry": {"coordinates":[49.56035,36.93774000000001],"type":"Point"}
}