{
  "type": "Feature",
  "properties": {
    "gn:admin1_code":"8.0",
    "gn:asciiname":"Garmavar",
    "gn:country_code":"IR",
    "gn:dem":1188,
    "gn:feature_class":"P",
    "gn:feature_code":"PPL",
    "gn:name":"Garm\u0101var",
    "gn:population":0,
    "gn:timezone":"Asia/Tehran",
    "iso:country":"IR",
    "name:ceb_x_preferred":[
        "Garm\u0101var"
    ],
    "name:fas_x_preferred":[
        "Garm\u0101var"
    ],
    "name:fas_x_variant":[
        "\u06af\u0631\u0645\u0627\u0648\u0631"
    ],
    "name:msa_x_preferred":[
        "Garmavar"
    ],
    "name:swe_x_preferred":[
        "Garm\u0101var"
    ],
    "name:ukr_x_preferred":[
        "\u0490\u044f\u0440\u043c\u0430\u0432\u0430\u0440"
    ],
    "name:und_x_variant":[
        "\u06af\u0631\u0645\u0627\u0648\u0631"
    ],
    "wof:name":"Garmavar",
    "wof:placetype":"locality"
},
  "geometry": {"coordinates":[50.0255,36.86013],"type":"Point"}
}