{
  "type": "Feature",
  "properties": {
    "gn:admin1_code":"35",
    "gn:asciiname":"Kolkat",
    "gn:country_code":"IR",
    "gn:dem":1371,
    "gn:feature_class":"P",
    "gn:feature_code":"PPL",
    "gn:name":"Kolkat",
    "gn:population":0,
    "gn:timezone":"Asia/Tehran",
    "iso:country":"IR",
    "name:fas_x_preferred":[
        "\u0643\u0644\u0643\u062a"
    ],
    "name:und_x_variant":[
        "\u0643\u0644\u0643\u062a",
        "Kolkat"
    ],
    "wof:name":"Kolkat",
    "wof:placetype":"locality"
},
  "geometry": {"coordinates":[53.97568,36.63165],"type":"Point"}
}