{
  "type": "Feature",
  "properties": {
    "gn:admin1_code":"4",
    "gn:asciiname":"Jagan",
    "gn:country_code":"IR",
    "gn:dem":831,
    "gn:feature_class":"P",
    "gn:feature_code":"PPL",
    "gn:name":"Jag\u0101n",
    "gn:population":0,
    "gn:timezone":"Asia/Tehran",
    "iso:country":"IR",
    "name:fas_x_preferred":[
        "\u062c\u064e\u06af\u0627\u0646"
    ],
    "name:fas_x_variant":[
        "Jag\u0101n"
    ],
    "name:hye_x_preferred":[
        "\u054b\u0561\u0563\u0561\u0576"
    ],
    "name:tam_x_preferred":[
        "\u0b9c\u0bc6\u0b95\u0ba9\u0bcd"
    ],
    "wof:name":"Jagan",
    "wof:placetype":"locality"
},
  "geometry": {"coordinates":[58.93333000000001,26.63333],"type":"Point"}
}