{
  "type": "Feature",
  "properties": {
    "gn:admin1_code":"1",
    "gn:asciiname":"Galeh Khar",
    "gn:country_code":"IR",
    "gn:dem":1869,
    "gn:feature_class":"P",
    "gn:feature_code":"PPL",
    "gn:name":"Galeh Khar",
    "gn:population":0,
    "gn:timezone":"Asia/Tehran",
    "iso:country":"IR",
    "name:fas_x_preferred":[
        "\u06af\u0644\u0647 \u062e\u0631"
    ],
    "name:fas_x_variant":[
        "\u06af\u064e\u0644\u0650\u0651\u0647 \u062e\u064e\u0631"
    ],
    "name:und_x_variant":[
        "Galleh Khar",
        "Galeh Khar"
    ],
    "wof:name":"Galeh Khar",
    "wof:placetype":"locality"
},
  "geometry": {"coordinates":[44.7239,37.9506],"type":"Point"}
}