{
  "type": "Feature",
  "properties": {
    "gn:admin1_code":"4.0",
    "gn:asciiname":"Towlagrud",
    "gn:country_code":"IR",
    "gn:dem":72,
    "gn:feature_class":"P",
    "gn:feature_code":"PPL",
    "gn:name":"Towlagr\u016bd",
    "gn:population":0,
    "gn:timezone":"Asia/Tehran",
    "iso:country":"IR",
    "name:ara_x_preferred":[
        "\u062a\u0648\u0644\u0643 \u0631\u0648\u062f"
    ],
    "name:fas_x_preferred":[
        "Towlak R\u016bd"
    ],
    "name:fas_x_variant":[
        "\u062a\u0648\u0644\u06a9 \u0631\u0648\u062f",
        "\u062a\u0648\u0644\u06af\u0631\u0648\u062f"
    ],
    "name:und_x_variant":[
        "Towlagr\u016bd"
    ],
    "wof:name":"Towlagrud",
    "wof:placetype":"locality"
},
  "geometry": {"coordinates":[60.79555,25.77866],"type":"Point"}
}