{
  "type": "Feature",
  "properties": {
    "gn:admin1_code":"8",
    "gn:asciiname":"Nasir Mahalleh",
    "gn:country_code":"IR",
    "gn:dem":100,
    "gn:feature_class":"P",
    "gn:feature_code":"PPL",
    "gn:name":"Na\u015f\u012br Ma\u1e29alleh",
    "gn:population":0,
    "gn:timezone":"Asia/Tehran",
    "iso:country":"IR",
    "name:fas_x_preferred":[
        "\u0646\u0635\u06cc\u0631 \u0645\u062d\u0644\u0647"
    ],
    "name:fas_x_variant":[
        "Na\u015f\u012br Ma\u1e29alleh",
        "\u0646\u0635\u06cc\u0631\u0645\u062d\u0644\u0647"
    ],
    "name:msa_x_preferred":[
        "Nasir Mahalleh"
    ],
    "name:ukr_x_preferred":[
        "\u041d\u0430\u0441\u0456\u0440-\u041c\u0430\u0445\u0430\u043b\u0435"
    ],
    "name:und_x_variant":[
        "Nasir-Magala"
    ],
    "wof:name":"Nasir Mahalleh",
    "wof:placetype":"locality"
},
  "geometry": {"coordinates":[49.34351,37.11918],"type":"Point"}
}