{
  "type": "Feature",
  "properties": {
    "gn:admin1_code":"35.0",
    "gn:asciiname":"Surmeshk",
    "gn:country_code":"IR",
    "gn:dem":1524,
    "gn:feature_class":"P",
    "gn:feature_code":"PPL",
    "gn:name":"S\u016brmeshk",
    "gn:population":0,
    "gn:timezone":"Asia/Tehran",
    "iso:country":"IR",
    "name:fas_x_preferred":[
        "S\u016brmeshk"
    ],
    "name:fas_x_variant":[
        "\u0633\u0648\u0631\u0645\u0634\u06a9",
        "\u0633\u0631\u0645\u0634\u06a9"
    ],
    "name:und_x_variant":[
        "Sarmeshk"
    ],
    "wof:name":"Surmeshk",
    "wof:placetype":"locality"
},
  "geometry": {"coordinates":[50.53713,36.76782],"type":"Point"}
}