{
  "type": "Feature",
  "properties": {
    "gn:admin1_code":"33",
    "gn:asciiname":"Kechi Qeshlaqi",
    "gn:country_code":"IR",
    "gn:dem":320,
    "gn:feature_class":"P",
    "gn:feature_code":"PPL",
    "gn:name":"Kech\u012b Qeshl\u0101q\u012b",
    "gn:population":0,
    "gn:timezone":"Asia/Tehran",
    "iso:country":"IR",
    "name:fas_x_preferred":[
        "\u06af\u0650\u0686\u06cc \u0642\u0650\u0634\u0644\u0627\u0642\u06cc"
    ],
    "name:fas_x_variant":[
        "\u06a9\u0686\u06cc \u0642\u0634\u0644\u0627\u0642\u06cc",
        "Gech\u012b Qeshl\u0101q\u012b",
        "Kech\u012b Qeshl\u0101q\u012b"
    ],
    "wof:name":"Kechi Qeshlaqi",
    "wof:placetype":"locality"
},
  "geometry": {"coordinates":[47.448,39.3184],"type":"Point"}
}