{
  "type": "Feature",
  "properties": {
    "gn:admin1_code":"41",
    "gn:asciiname":"Bavik",
    "gn:country_code":"IR",
    "gn:dem":2018,
    "gn:feature_class":"P",
    "gn:feature_code":"PPL",
    "gn:name":"Bav\u012bk",
    "gn:population":0,
    "gn:timezone":"Asia/Tehran",
    "iso:country":"IR",
    "name:fas_x_preferred":[
        "\u0628\u0648\u06cc\u06a9"
    ],
    "name:fas_x_variant":[
        "Bav\u012bk",
        "\u0628\u0648\u06cc\u06a9 \u0648\u0633\u0637\u06cc"
    ],
    "name:und_x_variant":[
        "B\u0101w\u012bk",
        "Bav\u012bk-e Vos\u0163\u00e1"
    ],
    "wof:name":"Bavik",
    "wof:placetype":"locality"
},
  "geometry": {"coordinates":[59.45358,33.2685],"type":"Point"}
}