{
  "type": "Feature",
  "properties": {
    "gn:admin1_code":"33",
    "gn:asciiname":"Dulab-e Kavanlu",
    "gn:country_code":"IR",
    "gn:dem":436,
    "gn:feature_class":"P",
    "gn:feature_code":"PPL",
    "gn:name":"D\u016bl\u0101b-e Kav\u0101nl\u016b",
    "gn:population":0,
    "gn:timezone":"Asia/Tehran",
    "iso:country":"IR",
    "name:fas_x_preferred":[
        "D\u016bl\u0101b-e Kav\u0101nl\u016b"
    ],
    "wof:name":"Dulab-e Kavanlu",
    "wof:placetype":"locality"
},
  "geometry": {"coordinates":[46.65,38.93333],"type":"Point"}
}