{
  "type": "Feature",
  "properties": {
    "gn:admin1_code":"35",
    "gn:asciiname":"Sorkh Garbuh",
    "gn:country_code":"IR",
    "gn:dem":1905,
    "gn:feature_class":"P",
    "gn:feature_code":"PPL",
    "gn:name":"Sorkh Garb\u016bh",
    "gn:population":0,
    "gn:timezone":"Asia/Tehran",
    "iso:country":"IR",
    "name:ara_x_preferred":[
        "\u0633\u0631\u062e \u063a\u0631\u064a\u0648\u0629"
    ],
    "name:ceb_x_preferred":[
        "Sorkh Geryeh"
    ],
    "name:fas_x_preferred":[
        "Sorkh Ger\u012bveh"
    ],
    "name:fas_x_variant":[
        "\u0633\u0631\u062e \u06af\u0631\u064a\u0647",
        "\u0633\u0631\u062e \u06af\u0631\u064a\u0648\u0647",
        "\u0633\u0631\u062e \u06af\u0631\u0628\u0648\u0647",
        "\u06af\u0631\u0628\u0648\u0647",
        "\u0633\u0631\u062e\u200c\u06af\u0631\u06cc\u0648\u0647"
    ],
    "name:swe_x_preferred":[
        "Sorkh Geryeh"
    ],
    "name:und_x_variant":[
        "Sorkh Geryeh",
        "Sorkh Ch\u0101r\u012b",
        "Surkhchari",
        "\u0633\u0631\u062e \u06af\u0631\u064a\u0648\u0647",
        "\u0633\u0631\u062e \u06af\u0631\u064a\u0647",
        "Sorkh Garb\u016bh",
        "Garb\u016bh"
    ],
    "wof:name":"Sorkh Garbuh",
    "wof:placetype":"locality"
},
  "geometry": {"coordinates":[54.05183,36.56259],"type":"Point"}
}