{
  "type": "Feature",
  "properties": {
    "gn:admin1_code":"13",
    "gn:asciiname":"Sar Asiab",
    "gn:country_code":"IR",
    "gn:dem":1357,
    "gn:feature_class":"P",
    "gn:feature_code":"PPL",
    "gn:name":"Sar \u0100s\u012b\u0101b",
    "gn:population":0,
    "gn:timezone":"Asia/Tehran",
    "iso:country":"IR",
    "name:fas_x_preferred":[
        "\u0633\u0631 \u0622\u0633\u06cc\u0627\u0628"
    ],
    "name:fas_x_variant":[
        "Sar \u0100s\u012b\u0101b",
        "\u0633\u0631\u0622\u0633\u06cc\u0627\u0628"
    ],
    "name:und_x_variant":[
        "Sar As\u012by\u0101b",
        "Sar Asey\u0101b"
    ],
    "wof:name":"Sar Asiab",
    "wof:placetype":"locality"
},
  "geometry": {"coordinates":[46.4114,34.4279],"type":"Point"}
}