{
  "type": "Feature",
  "properties": {
    "gn:admin1_code":"1.0",
    "gn:asciiname":"Nowbar",
    "gn:country_code":"IR",
    "gn:dem":1568,
    "gn:feature_class":"P",
    "gn:feature_code":"PPL",
    "gn:name":"Nowb\u0101r",
    "gn:population":0,
    "gn:timezone":"Asia/Tehran",
    "iso:country":"IR",
    "name:fas_x_preferred":[
        "\u0646\u064f\u0648\u0628\u0627\u0631"
    ],
    "name:fas_x_variant":[
        "\u0646\u0648\u0628\u0627\u0631",
        "Nowb\u0101r"
    ],
    "wof:name":"Nowbar",
    "wof:placetype":"locality"
},
  "geometry": {"coordinates":[46.0141,36.535],"type":"Point"}
}