{
  "type": "Feature",
  "properties": {
    "gn:admin1_code":"11",
    "gn:asciiname":"Dar Khizu",
    "gn:country_code":"IR",
    "gn:dem":404,
    "gn:feature_class":"P",
    "gn:feature_code":"PPL",
    "gn:name":"Dar Kh\u012bz\u016b",
    "gn:population":0,
    "gn:timezone":"Asia/Tehran",
    "iso:country":"IR",
    "name:fas_x_preferred":[
        "\u062f\u064e\u0631 \u062e\u064a\u0632\u0648"
    ],
    "name:fas_x_variant":[
        "Dar Kh\u012bz\u016b"
    ],
    "wof:name":"Dar Khizu",
    "wof:placetype":"locality"
},
  "geometry": {"coordinates":[56.39917,27.62167],"type":"Point"}
}