{
  "type": "Feature",
  "properties": {
    "gn:admin1_code":"13",
    "gn:asciiname":"Posht Tang-e Ezhdeha",
    "gn:country_code":"IR",
    "gn:dem":1611,
    "gn:feature_class":"P",
    "gn:feature_code":"PPL",
    "gn:name":"Posht Tang-e Ezhdeh\u0101",
    "gn:population":0,
    "gn:timezone":"Asia/Tehran",
    "iso:country":"IR",
    "name:fas_x_preferred":[
        "Posht Tang-e Ezhdeh\u0101"
    ],
    "wof:name":"Posht Tang-e Ezhdeha",
    "wof:placetype":"locality"
},
  "geometry": {"coordinates":[46.43944000000001,34.65194],"type":"Point"}
}