{
  "type": "Feature",
  "properties": {
    "gn:admin1_code":"15.0",
    "gn:asciiname":"Shahrak-e Davvar",
    "gn:country_code":"IR",
    "gn:dem":72,
    "gn:feature_class":"P",
    "gn:feature_code":"PPL",
    "gn:name":"Shahrak-e Davv\u0101r",
    "gn:population":0,
    "gn:timezone":"Asia/Tehran",
    "iso:country":"IR",
    "name:fas_x_preferred":[
        "\u0634\u0647\u0631\u06a9 \u062f\u0648\u0651\u0627\u0631"
    ],
    "name:fas_x_variant":[
        "Shahrak-e Davv\u0101r"
    ],
    "wof:name":"Shahrak-e Davvar",
    "wof:placetype":"locality"
},
  "geometry": {"coordinates":[48.2307,32.1988],"type":"Point"}
}