{
  "type": "Feature",
  "properties": {
    "gn:admin1_code":"28",
    "gn:asciiname":"Boltaq",
    "gn:country_code":"IR",
    "gn:dem":2403,
    "gn:feature_class":"P",
    "gn:feature_code":"PPL",
    "gn:name":"Bol\u0163\u0101q",
    "gn:population":0,
    "gn:timezone":"Asia/Tehran",
    "iso:country":"IR",
    "name:ara_x_preferred":[
        "\u0628\u0644\u0637\u0627\u0642"
    ],
    "name:fas_x_preferred":[
        "Bol\u0163\u0101q"
    ],
    "name:fas_x_variant":[
        "\u0628\u0644\u0637\u0627\u0642"
    ],
    "name:und_x_variant":[
        "Baltagh",
        "Bal\u0163\u0101q"
    ],
    "wof:name":"Boltaq",
    "wof:placetype":"locality"
},
  "geometry": {"coordinates":[49.99583,33.15501],"type":"Point"}
}