{
  "type": "Feature",
  "properties": {
    "gn:admin1_code":"29",
    "gn:asciiname":"Deh-e Tak",
    "gn:country_code":"IR",
    "gn:dem":1861,
    "gn:feature_class":"P",
    "gn:feature_code":"PPLF",
    "gn:name":"Deh-e Tak",
    "gn:population":0,
    "gn:timezone":"Asia/Tehran",
    "iso:country":"IR",
    "name:fas_x_preferred":[
        "\u062f\u0647 \u062a\u06a9"
    ],
    "name:fas_x_variant":[
        "\u1e28oseyn\u0101b\u0101d"
    ],
    "name:und_x_variant":[
        "Deh Tark",
        "Deh Tak",
        "Deh-e Tak"
    ],
    "wof:name":"Deh-e Tak",
    "wof:placetype":"locality"
},
  "geometry": {"coordinates":[56.15279,30.60833],"type":"Point"}
}