{
  "type": "Feature",
  "properties": {
    "gn:admin1_code":"43.0",
    "gn:asciiname":"Qezel",
    "gn:country_code":"IR",
    "gn:dem":688,
    "gn:feature_class":"P",
    "gn:feature_code":"PPL",
    "gn:name":"Qezel",
    "gn:population":0,
    "gn:timezone":"Asia/Tehran",
    "iso:country":"IR",
    "name:fas_x_preferred":[
        "\u0642\u0632\u0644"
    ],
    "wof:name":"Qezel",
    "wof:placetype":"locality"
},
  "geometry": {"coordinates":[56.4666,38.17806],"type":"Point"}
}