{
  "type": "Feature",
  "properties": {
    "gn:admin1_code":"23",
    "gn:asciiname":"Vali Asr",
    "gn:country_code":"IR",
    "gn:dem":765,
    "gn:feature_class":"P",
    "gn:feature_code":"PPL",
    "gn:name":"Val\u012b A\u015fr",
    "gn:population":0,
    "gn:timezone":"Asia/Tehran",
    "iso:country":"IR",
    "name:fas_x_preferred":[
        "\u0648\u0644\u06cc\u0639\u0635\u0631"
    ],
    "name:fas_x_variant":[
        "\u0648\u0644\u06cc \u0639\u0635\u0631"
    ],
    "name:und_x_variant":[
        "Val\u012b\u2018a\u015fr",
        "Val\u012b A\u015fr"
    ],
    "wof:name":"Vali Asr",
    "wof:placetype":"locality"
},
  "geometry": {"coordinates":[47.7233,33.0902],"type":"Point"}
}