{
  "type": "Feature",
  "properties": {
    "gn:admin1_code":"13.0",
    "gn:asciiname":"Seh Cheshmeh",
    "gn:country_code":"IR",
    "gn:dem":1389,
    "gn:feature_class":"P",
    "gn:feature_code":"PPL",
    "gn:name":"Seh Cheshmeh",
    "gn:population":0,
    "gn:timezone":"Asia/Tehran",
    "iso:country":"IR",
    "name:ceb_x_preferred":[
        "Seh Cheshmeh"
    ],
    "name:fas_x_preferred":[
        "\u0633\u0647 \u0686\u0634\u0645\u0647"
    ],
    "name:swe_x_preferred":[
        "Seh Cheshmeh"
    ],
    "wof:name":"Seh Cheshmeh",
    "wof:placetype":"locality"
},
  "geometry": {"coordinates":[47.0893,34.4682],"type":"Point"}
}