{
  "type": "Feature",
  "properties": {
    "gn:admin1_code":"4.0",
    "gn:asciiname":"Deh-e Habil",
    "gn:country_code":"IR",
    "gn:dem":482,
    "gn:feature_class":"P",
    "gn:feature_code":"PPL",
    "gn:name":"Deh-e H\u0101b\u012bl",
    "gn:population":0,
    "gn:timezone":"Asia/Tehran",
    "iso:country":"IR",
    "name:fas_x_preferred":[
        "\u062f\u0647 \u0647\u0627\u0628\u06cc\u0644"
    ],
    "name:fas_x_variant":[
        "Deh-e H\u0101b\u012bl",
        "\u0627\u0628\u06cc\u0644"
    ],
    "name:und_x_variant":[
        "Ab\u012bl"
    ],
    "wof:name":"Deh-e Habil",
    "wof:placetype":"locality"
},
  "geometry": {"coordinates":[61.582,31.1095],"type":"Point"}
}