{
  "type": "Feature",
  "properties": {
    "gn:admin1_code":"32.0",
    "gn:asciiname":"Savlehsar",
    "gn:country_code":"IR",
    "gn:dem":1724,
    "gn:feature_class":"P",
    "gn:feature_code":"PPL",
    "gn:name":"S\u0101vlehsar",
    "gn:population":0,
    "gn:timezone":"Asia/Tehran",
    "iso:country":"IR",
    "name:fas_x_preferred":[
        "\u0633\u0627\u0648\u0644\u0647 \u0633\u0631"
    ],
    "name:und_x_variant":[
        "S\u0101vlehsar"
    ],
    "wof:name":"Savlehsar",
    "wof:placetype":"locality"
},
  "geometry": {"coordinates":[48.85637,37.32114],"type":"Point"}
}