{
  "type": "Feature",
  "properties": {
    "gn:admin1_code":"44",
    "gn:asciiname":"Chahar Dangeh",
    "gn:country_code":"IR",
    "gn:dem":1251,
    "gn:feature_class":"P",
    "gn:feature_code":"PPL",
    "gn:name":"Chah\u0101r D\u0101ngeh",
    "gn:population":0,
    "gn:timezone":"Asia/Tehran",
    "iso:country":"IR",
    "name:fas_x_preferred":[
        "\u0686\u0647\u0627\u0631 \u062f\u0627\u0646\u06af\u0647"
    ],
    "name:fas_x_variant":[
        "Chah\u0101r D\u0101ngeh",
        "\u0686\u0647\u0627\u0631 \u0628\u0627\u063a"
    ],
    "name:und_x_variant":[
        "Chah\u0101r B\u0101gh"
    ],
    "wof:name":"Chahar Dangeh",
    "wof:placetype":"locality"
},
  "geometry": {"coordinates":[50.8481,35.8389],"type":"Point"}
}