{
  "type": "Feature",
  "properties": {
    "gn:admin1_code":"1",
    "gn:asciiname":"Qurmish",
    "gn:country_code":"IR",
    "gn:dem":1441,
    "gn:feature_class":"P",
    "gn:feature_code":"PPL",
    "gn:name":"Q\u016brm\u012bsh",
    "gn:population":0,
    "gn:timezone":"Asia/Tehran",
    "iso:country":"IR",
    "name:fas_x_preferred":[
        "\u0642\u0648\u0631\u0645\u06cc\u0634"
    ],
    "name:fas_x_variant":[
        "Qowrm\u012bsh",
        "Q\u016brm\u012bsh"
    ],
    "name:und_x_variant":[
        "Kurmish",
        "Gharmish",
        "Qorm\u012bsh"
    ],
    "wof:name":"Qurmish",
    "wof:placetype":"locality"
},
  "geometry": {"coordinates":[46.2789,36.6457],"type":"Point"}
}