{
  "type": "Feature",
  "properties": {
    "gn:admin1_code":"29",
    "gn:asciiname":"La Khurin",
    "gn:country_code":"IR",
    "gn:dem":2242,
    "gn:feature_class":"P",
    "gn:feature_code":"PPLF",
    "gn:name":"L\u0101 Kh\u016br\u012bn",
    "gn:population":0,
    "gn:timezone":"Asia/Tehran",
    "iso:country":"IR",
    "name:fas_x_preferred":[
        "\u0644\u0627 \u062e\u0648\u0631\u06cc\u0646"
    ],
    "name:fas_x_variant":[
        "L\u0101y Kh\u016br\u012bn",
        "L\u0101 Kh\u016br\u012bn",
        "\u0644\u0627\u06cc \u062e\u0648\u0631\u06cc\u0646"
    ],
    "wof:name":"La Khurin",
    "wof:placetype":"locality"
},
  "geometry": {"coordinates":[55.3691,30.2291],"type":"Point"}
}