{
  "type": "Feature",
  "properties": {
    "gn:admin1_code":"26",
    "gn:asciiname":"Akramabad-e Kianpur",
    "gn:country_code":"IR",
    "gn:dem":1236,
    "gn:feature_class":"P",
    "gn:feature_code":"PPL",
    "gn:name":"Akram\u0101b\u0101d-e K\u012b\u0101np\u016br",
    "gn:population":0,
    "gn:timezone":"Asia/Tehran",
    "iso:country":"IR",
    "name:fas_x_preferred":[
        "\u0627\u064e\u0643\u0631\u064e\u0645\u0627\u0628\u0627\u062f\u0650 \u0643\u064a\u0627\u0646\u067e\u0648\u0631"
    ],
    "name:fas_x_variant":[
        "\u0627\u0643\u0631\u0645 \u0622\u0628\u0627\u062f \u0643\u064a\u0627\u0646\u067e\u0648\u0631",
        "Akram\u0101b\u0101d-e K\u012b\u0101np\u016br",
        "\u0627\u06a9\u0631\u0645\u200c\u0622\u0628\u0627\u062f \u06a9\u06cc\u0627\u0646\u200c\u067e\u0648\u0631"
    ],
    "wof:name":"Akramabad-e Kianpur",
    "wof:placetype":"locality"
},
  "geometry": {"coordinates":[50.6805,35.5509],"type":"Point"}
}