{
  "type": "Feature",
  "properties": {
    "gn:admin1_code":"42",
    "gn:asciiname":"Yek Lengeh",
    "gn:country_code":"IR",
    "gn:dem":1537,
    "gn:feature_class":"P",
    "gn:feature_code":"PPL",
    "gn:name":"Yek Lengeh",
    "gn:population":0,
    "gn:timezone":"Asia/Tehran",
    "iso:country":"IR",
    "name:ceb_x_preferred":[
        "Yek Lengeh"
    ],
    "name:fas_x_preferred":[
        "\u06cc\u06a9 \u0644\u0646\u06af\u0647"
    ],
    "name:swe_x_preferred":[
        "Yek Lengeh"
    ],
    "name:urd_x_preferred":[
        "\u06cc\u06a9 \u0644\u06cc\u0646\u06af\u06c1"
    ],
    "wof:name":"Yek Lengeh",
    "wof:placetype":"locality"
},
  "geometry": {"coordinates":[59.13077,35.72285],"type":"Point"}
}