{
  "type": "Feature",
  "properties": {
    "gn:admin1_code":"35.0",
    "gn:asciiname":"Halu Sara",
    "gn:country_code":"IR",
    "gn:dem":649,
    "gn:feature_class":"P",
    "gn:feature_code":"PPL",
    "gn:name":"Hal\u016b Sar\u0101",
    "gn:population":0,
    "gn:timezone":"Asia/Tehran",
    "iso:country":"IR",
    "name:fas_x_preferred":[
        "Hal\u016b Sar\u0101"
    ],
    "name:fas_x_variant":[
        "\u0647\u0644\u0648 \u0633\u0631\u0627"
    ],
    "wof:name":"Halu Sara",
    "wof:placetype":"locality"
},
  "geometry": {"coordinates":[50.62652,36.87785],"type":"Point"}
}