{
  "type": "Feature",
  "properties": {
    "gn:admin1_code":"33.0",
    "gn:asciiname":"Aruq",
    "gn:country_code":"IR",
    "gn:dem":1302,
    "gn:feature_class":"P",
    "gn:feature_code":"PPL",
    "gn:name":"\u0100r\u016bq",
    "gn:population":0,
    "gn:timezone":"Asia/Tehran",
    "iso:country":"IR",
    "name:fas_x_preferred":[
        "\u0100r\u016bq"
    ],
    "name:fas_x_variant":[
        "\u0622\u0631\u0648\u0642"
    ],
    "name:msa_x_preferred":[
        "Aruq"
    ],
    "wof:name":"Aruq",
    "wof:placetype":"locality"
},
  "geometry": {"coordinates":[46.14604,37.13718],"type":"Point"}
}