{
  "type": "Feature",
  "properties": {
    "gn:admin1_code":"29.0",
    "gn:asciiname":"Ashub-e Sofla",
    "gn:country_code":"IR",
    "gn:dem":2277,
    "gn:feature_class":"P",
    "gn:feature_code":"PPL",
    "gn:name":"\u0100sh\u016bb-e Sofl\u00e1",
    "gn:population":0,
    "gn:timezone":"Asia/Tehran",
    "iso:country":"IR",
    "name:fas_x_preferred":[
        "\u0622\u0634\u0648\u0626\u06cc\u0647"
    ],
    "name:fas_x_variant":[
        "\u0100sh\u016b\u2019\u012byeh",
        "\u0622\u0634\u0648\u0628 \u0633\u0641\u0644\u06cc"
    ],
    "name:und_x_variant":[
        "\u0100sh\u016bb-e Sofl\u00e1"
    ],
    "wof:name":"Ashub-e Sofla",
    "wof:placetype":"locality"
},
  "geometry": {"coordinates":[55.06031,30.39791],"type":"Point"}
}