{
  "type": "Feature",
  "properties": {
    "gn:admin1_code":"13",
    "gn:asciiname":"Baba Jani-ye Abu Dajaneh",
    "gn:country_code":"IR",
    "gn:dem":913,
    "gn:feature_class":"P",
    "gn:feature_code":"PPL",
    "gn:name":"B\u0101b\u0101 J\u0101n\u012b-ye Ab\u016b Daj\u0101neh",
    "gn:population":0,
    "gn:timezone":"Asia/Tehran",
    "iso:country":"IR",
    "name:fas_x_preferred":[
        "\u0628\u0627\u0628\u0627\u062c\u0627\u0646\u06cc \u0627\u0628\u0648 \u062f\u062c\u0627\u0646\u0647"
    ],
    "name:fas_x_variant":[
        "B\u0101b\u0101 J\u0101n\u012b-ye \u2018Abd ol Mo\u1e29ammad",
        "B\u0101b\u0101 J\u0101n\u012b-ye Ab\u016b Daj\u0101neh"
    ],
    "name:und_x_variant":[
        "B\u0101b\u0101 J\u0101n\u012b"
    ],
    "wof:name":"Baba Jani-ye Abu Dajaneh",
    "wof:placetype":"locality"
},
  "geometry": {"coordinates":[45.97512,34.4768],"type":"Point"}
}