{
  "type": "Feature",
  "properties": {
    "gn:admin1_code":"34",
    "gn:asciiname":"Dowlatabad",
    "gn:country_code":"IR",
    "gn:dem":1707,
    "gn:feature_class":"P",
    "gn:feature_code":"PPL",
    "gn:name":"Dowlat\u0101b\u0101d",
    "gn:population":0,
    "gn:timezone":"Asia/Tehran",
    "iso:country":"IR",
    "name:fas_x_preferred":[
        "Dowlat\u0101b\u0101d"
    ],
    "name:fas_x_variant":[
        "\u062f\u0648\u0644\u062a \u0622\u0628\u0627\u062f"
    ],
    "name:und_x_variant":[
        "Daulat\u0101b\u0101d",
        "\u062f\u0648\u0644\u062a \u0622\u0628\u0627\u062f"
    ],
    "wof:name":"Dowlatabad",
    "wof:placetype":"locality"
},
  "geometry": {"coordinates":[49.62421,34.40327],"type":"Point"}
}