{
  "type": "Feature",
  "properties": {
    "gn:admin1_code":"1.0",
    "gn:asciiname":"Eynehchi",
    "gn:country_code":"IR",
    "gn:dem":1753,
    "gn:feature_class":"P",
    "gn:feature_code":"PPL",
    "gn:name":"Eynehch\u012b",
    "gn:population":0,
    "gn:timezone":"Asia/Tehran",
    "iso:country":"IR",
    "name:ara_x_preferred":[
        "\u0623\u0648\u064a\u0646\u0629 \u062a\u0634\u064a"
    ],
    "name:aze_x_preferred":[
        "\u0130yn\u0259\u00e7i"
    ],
    "name:ceb_x_preferred":[
        "Eynehch\u012b"
    ],
    "name:fas_x_preferred":[
        "\u0627\u06cc\u0646\u0647 \u0686\u06cc"
    ],
    "name:fas_x_variant":[
        "\u016aynehch\u012b",
        "\u0648\u064a\u0646\u0650\u0647\u0686\u06cc",
        "Eynehch\u012b",
        "\u0627\u0648\u06cc\u0646\u0647\u200c\u0686\u06cc"
    ],
    "name:msa_x_preferred":[
        "Uynehchi"
    ],
    "name:swe_x_preferred":[
        "Eynehch\u012b"
    ],
    "wof:name":"Eynehchi",
    "wof:placetype":"locality"
},
  "geometry": {"coordinates":[46.3657,36.5805],"type":"Point"}
}