{
  "type": "Feature",
  "properties": {
    "gn:admin1_code":"16",
    "gn:asciiname":"sawan",
    "gn:country_code":"IR",
    "gn:dem":1603,
    "gn:feature_class":"P",
    "gn:feature_code":"PPL",
    "gn:name":"\u0633\u0627\u0648\u0627\u0646",
    "gn:population":0,
    "gn:timezone":"Asia/Tehran",
    "iso:country":"IR",
    "name:ara_x_preferred":[
        "\u0633\u0627\u0648\u0627\u0646"
    ],
    "name:fas_x_preferred":[
        "S\u0101v\u0101n"
    ],
    "name:fas_x_variant":[
        "\u0633\u0627\u0648\u0627\u0646"
    ],
    "name:mal_x_preferred":[
        "\u0d38\u0d3e\u0d35\u0d7b"
    ],
    "name:pan_x_preferred":[
        "\u0a38\u0a3e\u0a35\u0a23"
    ],
    "name:tam_x_preferred":[
        "\u0b9a\u0bbe\u0bb5\u0ba9\u0bcd"
    ],
    "name:urd_x_preferred":[
        "\u0633\u0627\u0648\u0646"
    ],
    "wof:name":"sawan",
    "wof:placetype":"locality"
},
  "geometry": {"coordinates":[45.9059,36.0734],"type":"Point"}
}