{
  "type": "Feature",
  "properties": {
    "gn:admin1_code":"15.0",
    "gn:asciiname":"Abuk Baryeh",
    "gn:country_code":"IR",
    "gn:dem":12,
    "gn:feature_class":"P",
    "gn:feature_code":"PPL",
    "gn:name":"Ab\u016bk Baryeh",
    "gn:population":0,
    "gn:timezone":"Asia/Tehran",
    "iso:country":"IR",
    "name:ara_x_preferred":[
        "\u0623\u0628\u0648 \u0643\u0628\u064a\u0631\u0629"
    ],
    "name:azb_x_preferred":[
        "\u0627\u0628\u0648\u06a9\u0628\u0631\u06cc\u0647"
    ],
    "name:ceb_x_preferred":[
        "Ab\u016b Kab\u012breh"
    ],
    "name:fas_x_preferred":[
        "Ab\u016b Kab\u012breh"
    ],
    "name:fas_x_variant":[
        "Ab\u016b Kab\u012br\u012b",
        "\u0627\u0628\u0648 \u06a9\u0628\u06cc\u0631\u0647",
        "\u0627\u0628\u0648\u06a9 \u0628\u0631\u06cc\u0647",
        "\u0627\u0628\u0648\u06a9\u0628\u0631\u06cc\u0647"
    ],
    "name:swe_x_preferred":[
        "Ab\u016b Kab\u012breh"
    ],
    "name:und_x_variant":[
        "Ab\u016b Kab\u012br\u012byeh",
        "Ab\u016bk Baryeh"
    ],
    "wof:name":"Abuk Baryeh",
    "wof:placetype":"locality"
},
  "geometry": {"coordinates":[48.92356,31.1203],"type":"Point"}
}