{
  "type": "Feature",
  "properties": {
    "gn:admin1_code":"22",
    "gn:asciiname":"Chahleh",
    "gn:country_code":"IR",
    "gn:dem":42,
    "gn:feature_class":"P",
    "gn:feature_code":"PPL",
    "gn:name":"Chahleh",
    "gn:population":0,
    "gn:timezone":"Asia/Tehran",
    "iso:country":"IR",
    "name:ara_x_preferred":[
        "\u062a\u0634\u0647\u0644\u0629"
    ],
    "name:ceb_x_preferred":[
        "Chahleh"
    ],
    "name:fas_x_preferred":[
        "\u0686\u0647\u0644\u0647"
    ],
    "name:msa_x_preferred":[
        "Chahleh"
    ],
    "name:swe_x_preferred":[
        "Chahleh"
    ],
    "wof:name":"Chahleh",
    "wof:placetype":"locality"
},
  "geometry": {"coordinates":[51.2434,28.7068],"type":"Point"}
}