{
  "type": "Feature",
  "properties": {
    "gn:admin1_code":"29.0",
    "gn:asciiname":"Mazra`eh-ye Dehnow",
    "gn:country_code":"IR",
    "gn:dem":582,
    "gn:feature_class":"P",
    "gn:feature_code":"PPLF",
    "gn:name":"Mazra\u2018eh-ye Dehnow",
    "gn:population":0,
    "gn:timezone":"Asia/Tehran",
    "iso:country":"IR",
    "name:fas_x_preferred":[
        "\u0645\u0632\u0631\u0639\u0647 \u062f\u0647\u0646\u0648"
    ],
    "name:und_x_variant":[
        "Mazra\u2018eh-ye Dehnow"
    ],
    "wof:name":"Mazra`eh-ye Dehnow",
    "wof:placetype":"locality"
},
  "geometry": {"coordinates":[58.50471999999999,28.01705],"type":"Point"}
}