{
  "type": "Feature",
  "properties": {
    "gn:admin1_code":"8",
    "gn:asciiname":"Hasan Vareh",
    "gn:country_code":"IR",
    "gn:dem":-21,
    "gn:feature_class":"P",
    "gn:feature_code":"PPL",
    "gn:name":"\u1e28asan V\u0101reh",
    "gn:population":0,
    "gn:timezone":"Asia/Tehran",
    "iso:country":"IR",
    "name:fas_x_preferred":[
        "\u1e28asan V\u0101reh"
    ],
    "wof:name":"Hasan Vareh",
    "wof:placetype":"locality"
},
  "geometry": {"coordinates":[50.42861,37.05722],"type":"Point"}
}