{
  "type": "Feature",
  "properties": {
    "gn:admin1_code":"13",
    "gn:asciiname":"Jelugireh-ye `Olya",
    "gn:country_code":"IR",
    "gn:dem":1311,
    "gn:feature_class":"P",
    "gn:feature_code":"PPL",
    "gn:name":"Jel\u016bg\u012breh-ye \u2018Oly\u0101",
    "gn:population":0,
    "gn:timezone":"Asia/Tehran",
    "iso:country":"IR",
    "name:fas_x_preferred":[
        "\u062c\u0644\u0648\u06af\u06cc\u0631\u0647 \u0639\u0644\u06cc\u0627"
    ],
    "name:fas_x_variant":[
        "Jelog\u012breh-ye \u2018Oly\u0101",
        "Jel\u016bg\u012breh-ye \u2018Oly\u0101"
    ],
    "wof:name":"Jelugireh-ye `Olya",
    "wof:placetype":"locality"
},
  "geometry": {"coordinates":[46.8417,34.5833],"type":"Point"}
}