{
  "type": "Feature",
  "properties": {
    "gn:admin1_code":"23",
    "gn:asciiname":"Pashkaleh-ye Pa'in",
    "gn:country_code":"IR",
    "gn:dem":1497,
    "gn:feature_class":"P",
    "gn:feature_code":"PPL",
    "gn:name":"Pashkaleh-ye P\u0101\u2019\u012bn",
    "gn:population":0,
    "gn:timezone":"Asia/Tehran",
    "iso:country":"IR",
    "name:fas_x_preferred":[
        "\u067e\u064e\u0634\u0643\u064e\u0644\u0650\u06c0 \u067e\u0627\u0626\u064a\u0646"
    ],
    "name:fas_x_variant":[
        "Pashkaleh-ye P\u0101\u2019\u012bn"
    ],
    "wof:name":"Pashkaleh-ye Pa'in",
    "wof:placetype":"locality"
},
  "geometry": {"coordinates":[47.53167,34.13222],"type":"Point"}
}