{
  "type": "Feature",
  "properties": {
    "gn:admin1_code":"13",
    "gn:asciiname":"Do Cheqa",
    "gn:country_code":"IR",
    "gn:dem":1319,
    "gn:feature_class":"P",
    "gn:feature_code":"PPL",
    "gn:name":"Do Cheqa",
    "gn:population":0,
    "gn:timezone":"Asia/Tehran",
    "iso:country":"IR",
    "name:fas_x_preferred":[
        "\u0645\u0648 \u0645\u0647 \u0627\u06cc"
    ],
    "name:fas_x_variant":[
        "Do Cheq\u0101 \u2018Az\u012bz"
    ],
    "name:und_x_variant":[
        "D\u0101ch\u012ba",
        "D\u016bch\u012ba",
        "Mowm\u2019\u012b",
        "Do Ch\u012ba",
        "Mow\u2019men\u012b",
        "Do Cheqa",
        "Dowcheq\u0101 \u2018Az\u012bz",
        "M\u016bmeh\u2019\u012b"
    ],
    "wof:name":"Do Cheqa",
    "wof:placetype":"locality"
},
  "geometry": {"coordinates":[46.6098,34.0206],"type":"Point"}
}