{
  "type": "Feature",
  "properties": {
    "gn:admin1_code":"34",
    "gn:asciiname":"Qeshlaq Shahid",
    "gn:country_code":"IR",
    "gn:dem":2014,
    "gn:feature_class":"P",
    "gn:feature_code":"PPL",
    "gn:name":"Qeshl\u0101q Shah\u012bd",
    "gn:population":0,
    "gn:timezone":"Asia/Tehran",
    "iso:country":"IR",
    "name:fas_x_preferred":[
        "\u0634\u0647\u064a\u062f"
    ],
    "name:fas_x_variant":[
        "\u0642\u0634\u0644\u0627\u0642 \u0634\u0647\u064a\u062f",
        "Shah\u012bd"
    ],
    "name:und_x_variant":[
        "Gheshlagh Shahid",
        "Qeshl\u0101q Shah\u012bd"
    ],
    "wof:name":"Qeshlaq Shahid",
    "wof:placetype":"locality"
},
  "geometry": {"coordinates":[49.1464,34.3002],"type":"Point"}
}