{
  "type": "Feature",
  "properties": {
    "gn:admin1_code":"4.0",
    "gn:asciiname":"Shahrak-e Dasht-e Varmal",
    "gn:country_code":"IR",
    "gn:dem":478,
    "gn:feature_class":"P",
    "gn:feature_code":"PPL",
    "gn:name":"Shahrak-e Dasht-e Varm\u0101l",
    "gn:population":0,
    "gn:timezone":"Asia/Tehran",
    "iso:country":"IR",
    "name:fas_x_preferred":[
        "\u0634\u0647\u0631\u06a9 \u062f\u0634\u062a \u0648\u0631\u0645\u0627\u0644"
    ],
    "name:fas_x_variant":[
        "Shahrak-e Dasht-e Varm\u0101l"
    ],
    "wof:name":"Shahrak-e Dasht-e Varmal",
    "wof:placetype":"locality"
},
  "geometry": {"coordinates":[61.325,30.74119],"type":"Point"}
}