{
  "type": "Feature",
  "properties": {
    "gn:admin1_code":"22",
    "gn:asciiname":"Jabrani",
    "gn:country_code":"IR",
    "gn:dem":9,
    "gn:feature_class":"P",
    "gn:feature_code":"PPL",
    "gn:name":"Jabr\u0101n\u012b",
    "gn:population":0,
    "gn:timezone":"Asia/Tehran",
    "iso:country":"IR",
    "name:ara_x_preferred":[
        "\u062c\u0628\u0631\u0627\u0646\u064a"
    ],
    "name:ceb_x_preferred":[
        "Jabr\u0101n\u012b"
    ],
    "name:fas_x_preferred":[
        "\u062c\u064e\u0628\u0631\u0627\u0646\u0626 \u0628\u0627\u0644\u0627"
    ],
    "name:fas_x_variant":[
        "Jabr\u0101\u2019\u012b-ye B\u0101l\u0101",
        "Jabr\u0101n\u012b-ye B\u0101l\u0101",
        "\u062c\u0628\u0631\u0627\u0626\u06cc \u0628\u0627\u0644\u0627",
        "\u062c\u0628\u0631\u0627\u0646\u06cc"
    ],
    "name:msa_x_preferred":[
        "Jabrani"
    ],
    "name:swe_x_preferred":[
        "Jabr\u0101n\u012b"
    ],
    "name:urd_x_preferred":[
        "\u062c\u0628\u0631\u0627\u0646\u06cc"
    ],
    "wof:name":"Jabrani",
    "wof:placetype":"locality"
},
  "geometry": {"coordinates":[51.80242,27.85221],"type":"Point"}
}