{
  "type": "Feature",
  "properties": {
    "gn:admin1_code":"38.0",
    "gn:asciiname":"Salkh",
    "gn:country_code":"IR",
    "gn:dem":2771,
    "gn:feature_class":"P",
    "gn:feature_code":"PPL",
    "gn:name":"Salkh",
    "gn:population":0,
    "gn:timezone":"Asia/Tehran",
    "iso:country":"IR",
    "name:fas_x_preferred":[
        "\u0633\u0644\u062e"
    ],
    "name:fas_x_variant":[
        "\u0633\u0644\u06a9"
    ],
    "name:und_x_variant":[
        "Salkh",
        "Salk"
    ],
    "wof:name":"Salkh",
    "wof:placetype":"locality"
},
  "geometry": {"coordinates":[50.1205,36.6705],"type":"Point"}
}