{
  "type": "Feature",
  "properties": {
    "gn:admin1_code":"28.0",
    "gn:asciiname":"Mazra`eh-ye Heydarabad",
    "gn:country_code":"IR",
    "gn:dem":1005,
    "gn:feature_class":"P",
    "gn:feature_code":"PPLF",
    "gn:name":"Mazra\u2018eh-ye \u1e28eydar\u0101b\u0101d",
    "gn:population":0,
    "gn:timezone":"Asia/Tehran",
    "iso:country":"IR",
    "name:fas_x_preferred":[
        "\u0645\u0632\u0631\u0639\u0647 \u062d\u064a\u062f\u0631 \u0622\u0628\u0627\u062f"
    ],
    "name:und_x_variant":[
        "Mazra\u2018eh-ye \u1e28eydar\u0101b\u0101d"
    ],
    "wof:name":"Mazra`eh-ye Heydarabad",
    "wof:placetype":"locality"
},
  "geometry": {"coordinates":[51.97162,33.68495],"type":"Point"}
}