{
  "type": "Feature",
  "properties": {
    "gn:admin1_code":"28",
    "gn:asciiname":"Darreh Tang Ab",
    "gn:country_code":"IR",
    "gn:dem":2208,
    "gn:feature_class":"P",
    "gn:feature_code":"PPL",
    "gn:name":"Darreh Tang \u0100b",
    "gn:population":0,
    "gn:timezone":"Asia/Tehran",
    "iso:country":"IR",
    "name:fas_x_preferred":[
        "Darreh Tang \u0100b"
    ],
    "wof:name":"Darreh Tang Ab",
    "wof:placetype":"locality"
},
  "geometry": {"coordinates":[51.71972,31.86639000000001],"type":"Point"}
}