{
  "type": "Feature",
  "properties": {
    "gn:admin1_code":"34",
    "gn:asciiname":"Deh-e Namak",
    "gn:country_code":"IR",
    "gn:dem":1666,
    "gn:feature_class":"P",
    "gn:feature_code":"PPL",
    "gn:name":"Deh-e Namak",
    "gn:population":0,
    "gn:timezone":"Asia/Tehran",
    "iso:country":"IR",
    "name:ara_x_preferred":[
        "\u062f\u0647 \u0646\u0645\u0643"
    ],
    "name:fas_x_preferred":[
        "\u062f\u0647 \u0646\u0645\u06a9"
    ],
    "name:ukr_x_preferred":[
        "\u0414\u0435\u0433-\u0435 \u041d\u0430\u043c\u0430\u043a"
    ],
    "wof:name":"Deh-e Namak",
    "wof:placetype":"locality"
},
  "geometry": {"coordinates":[49.8704,34.24157],"type":"Point"}
}