{
  "type": "Feature",
  "properties": {
    "gn:admin1_code":"40",
    "gn:asciiname":"Kushk",
    "gn:country_code":"IR",
    "gn:dem":1578,
    "gn:feature_class":"P",
    "gn:feature_code":"PPL",
    "gn:name":"K\u016bshk",
    "gn:population":0,
    "gn:timezone":"Asia/Tehran",
    "iso:country":"IR",
    "name:fas_x_preferred":[
        "\u0643\u0648\u0634\u06a9"
    ],
    "name:fas_x_variant":[
        "K\u016bshk"
    ],
    "wof:name":"Kushk",
    "wof:placetype":"locality"
},
  "geometry": {"coordinates":[54.38632,30.0872],"type":"Point"}
}