{
  "type": "Feature",
  "properties": {
    "gn:admin1_code":"25",
    "gn:asciiname":"Chah Vahab-e Bala",
    "gn:country_code":"IR",
    "gn:dem":1345,
    "gn:feature_class":"P",
    "gn:feature_code":"PPL",
    "gn:name":"Ch\u0101h Vah\u0101b-e B\u0101l\u0101",
    "gn:population":0,
    "gn:timezone":"Asia/Tehran",
    "iso:country":"IR",
    "name:fas_x_preferred":[
        "Ch\u0101h-e B\u0101b-e B\u0101l\u0101"
    ],
    "name:fas_x_variant":[
        "Ch\u0101h Vah\u0101b",
        "\u0686\u0627\u0647 \u0628\u0627\u0628 \u0628\u0627\u0644\u0627",
        "\u0686\u0627\u0647 \u0648\u0647\u0627\u0628 \u0628\u0627\u0644\u0627"
    ],
    "name:und_x_variant":[
        "\u0686\u0627\u0647 \u0628\u0627\u0628 \u0628\u0627\u0644\u0627",
        "Ch\u0101h Vah\u0101b-e B\u0101l\u0101"
    ],
    "wof:name":"Chah Vahab-e Bala",
    "wof:placetype":"locality"
},
  "geometry": {"coordinates":[57.10323,35.52677],"type":"Point"}
}