{
  "type": "Feature",
  "properties": {
    "gn:admin1_code":"4",
    "gn:asciiname":"Vosh Kushi",
    "gn:country_code":"IR",
    "gn:dem":1248,
    "gn:feature_class":"P",
    "gn:feature_code":"PPL",
    "gn:name":"Vosh K\u016bsh\u012b",
    "gn:population":0,
    "gn:timezone":"Asia/Tehran",
    "iso:country":"IR",
    "name:fas_x_preferred":[
        "\u0648\u0634 \u06a9\u0648\u0634\u06cc"
    ],
    "name:fas_x_variant":[
        "Vosh K\u016bsh\u012b"
    ],
    "wof:name":"Vosh Kushi",
    "wof:placetype":"locality"
},
  "geometry": {"coordinates":[60.96574,27.68943],"type":"Point"}
}