{
  "type": "Feature",
  "properties": {
    "gn:admin1_code":"1",
    "gn:asciiname":"Barun",
    "gn:country_code":"IR",
    "gn:dem":1777,
    "gn:feature_class":"P",
    "gn:feature_code":"PPL",
    "gn:name":"B\u0101r\u016bn",
    "gn:population":0,
    "gn:timezone":"Asia/Tehran",
    "iso:country":"IR",
    "name:fas_x_preferred":[
        "B\u0101r\u016bn"
    ],
    "name:fas_x_variant":[
        "\u0628\u0627\u0631\u0648\u0646"
    ],
    "name:und_x_variant":[
        "\u0628\u0627\u0631\u0648\u0646"
    ],
    "wof:name":"Barun",
    "wof:placetype":"locality"
},
  "geometry": {"coordinates":[44.4683,39.1919],"type":"Point"}
}