{
  "type": "Feature",
  "properties": {
    "gn:admin1_code":"7",
    "gn:asciiname":"Shah Gharib",
    "gn:country_code":"IR",
    "gn:dem":918,
    "gn:feature_class":"P",
    "gn:feature_code":"PPL",
    "gn:name":"Sh\u0101h Ghar\u012bb",
    "gn:population":0,
    "gn:timezone":"Asia/Tehran",
    "iso:country":"IR",
    "name:fas_x_preferred":[
        "\u0634\u0627\u0647 \u063a\u0631\u06cc\u0628"
    ],
    "name:fas_x_variant":[
        "Sh\u0101h Ghar\u012bb",
        "\u0627\u0645\u0627\u0645\u0632\u0627\u062f\u0647 \u0634\u0627\u0647 \u063a\u0631\u06cc\u0628"
    ],
    "name:msa_x_preferred":[
        "Emamzadeh Shah Gharib"
    ],
    "name:und_x_variant":[
        "Em\u0101mz\u0101deh Sh\u0101h-e Ghar\u012bb"
    ],
    "wof:name":"Shah Gharib",
    "wof:placetype":"locality"
},
  "geometry": {"coordinates":[53.88474,28.24079],"type":"Point"}
}