{
  "type": "Feature",
  "properties": {
    "gn:admin1_code":"42.0",
    "gn:asciiname":"Baz Qand",
    "gn:country_code":"IR",
    "gn:dem":1542,
    "gn:feature_class":"P",
    "gn:feature_code":"PPL",
    "gn:name":"B\u0101z Qand",
    "gn:population":0,
    "gn:timezone":"Asia/Tehran",
    "iso:country":"IR",
    "name:fas_x_preferred":[
        "B\u0101z Qand"
    ],
    "name:fas_x_variant":[
        "\u0628\u0627\u0632 \u0642\u0646\u062f"
    ],
    "name:und_x_variant":[
        "\u0628\u0627\u0632 \u0642\u0646\u062f"
    ],
    "wof:name":"Baz Qand",
    "wof:placetype":"locality"
},
  "geometry": {"coordinates":[57.68662,36.41034000000001],"type":"Point"}
}