{
  "type": "Feature",
  "properties": {
    "gn:admin1_code":"33",
    "gn:asciiname":"Chupanlar-e Sardarlu",
    "gn:country_code":"IR",
    "gn:dem":1963,
    "gn:feature_class":"P",
    "gn:feature_code":"PPL",
    "gn:name":"Ch\u016bp\u0101nl\u0101r-e Sard\u0101rl\u016b",
    "gn:population":0,
    "gn:timezone":"Asia/Tehran",
    "iso:country":"IR",
    "name:fas_x_preferred":[
        "\u0686\u0648\u067e\u0627\u0646\u0644\u0627\u0631"
    ],
    "name:fas_x_variant":[
        "Ch\u016bp\u0101nl\u0101r-e Sard\u0101rl\u016b",
        "Ch\u016bp\u0101nl\u0101r",
        "\u0686\u0648\u067e\u0627\u0646\u0644\u0627\u0631 \u0633\u0631\u062f\u0627\u0631\u0644\u0648",
        "\u0686\u0648\u0628\u0627\u0646\u0644\u0627\u0631 \u0633\u0631\u062f\u0627\u0631\u0644\u0648"
    ],
    "name:msa_x_preferred":[
        "Chubanlar-e Sardarlu"
    ],
    "name:und_x_variant":[
        "Chob\u0101nl\u0101r Sard\u0101rl\u016b",
        "Chobanar",
        "Ch\u016bp\u0101nl\u0101r Sard\u0101rl\u016b",
        "Ch\u016bb\u0101nl\u0101r-e Sard\u0101rl\u016b"
    ],
    "wof:name":"Chupanlar-e Sardarlu",
    "wof:placetype":"locality"
},
  "geometry": {"coordinates":[46.7542,38.3732],"type":"Point"}
}