{
  "type": "Feature",
  "properties": {
    "gn:admin1_code":"43",
    "gn:asciiname":"Chahar Borj",
    "gn:country_code":"IR",
    "gn:dem":1058,
    "gn:feature_class":"P",
    "gn:feature_code":"PPL",
    "gn:name":"Chah\u0101r Borj",
    "gn:population":0,
    "gn:timezone":"Asia/Tehran",
    "iso:country":"IR",
    "name:fas_x_preferred":[
        "Chah\u0101r Borj"
    ],
    "name:fas_x_variant":[
        "\u0686\u0647\u0627\u0631 \u0628\u0631\u062c"
    ],
    "name:und_x_variant":[
        "Cheh\u0101r Burj",
        "\u0686\u0647\u0627\u0631 \u0628\u0631\u062c"
    ],
    "wof:name":"Chahar Borj",
    "wof:placetype":"locality"
},
  "geometry": {"coordinates":[57.19281,37.12122],"type":"Point"}
}