{
  "type": "Feature",
  "properties": {
    "gn:admin1_code":"43",
    "gn:asciiname":"Chahar Borj",
    "gn:country_code":"IR",
    "gn:dem":1058,
    "gn:feature_class":"P",
    "gn:feature_code":"PPL",
    "gn:name":"Chah\u0101r Borj",
    "gn:population":0,
    "gn:timezone":"Asia/Tehran",
    "iso:country":"IR",
    "name:ara_x_preferred":[
        "\u062a\u0634\u0647\u0627\u0631\u0628\u0631\u062c"
    ],
    "name:azb_x_preferred":[
        "\u0686\u0647\u0627\u0631\u0628\u0631\u062c"
    ],
    "name:aze_x_preferred":[
        "\u00c7arburc"
    ],
    "name:ceb_x_preferred":[
        "Chah\u0101r Borj-e Qad\u012bm"
    ],
    "name:ckb_x_preferred":[
        "\u0686\u0648\u0627\u0631\u0628\u0648\u0631\u062c"
    ],
    "name:fas_x_preferred":[
        "Chah\u0101r Borj"
    ],
    "name:fas_x_variant":[
        "\u0686\u0647\u0627\u0631 \u0628\u0631\u062c",
        "\u0686\u0647\u0627\u0631\u0628\u0631\u062c"
    ],
    "name:kur_x_preferred":[
        "\u00c7ar Burc"
    ],
    "name:mlg_x_preferred":[
        "Chahar Borj"
    ],
    "name:msa_x_preferred":[
        "Chahar Borj"
    ],
    "name:swe_x_preferred":[
        "Chah\u0101r Borj-e Qad\u012bm"
    ],
    "name:tur_x_preferred":[
        "\u00c7eharbur\u00e7"
    ],
    "name:und_x_variant":[
        "Cheh\u0101r Burj",
        "\u0686\u0647\u0627\u0631 \u0628\u0631\u062c"
    ],
    "name:urd_x_preferred":[
        "\u0686\u06c1\u0627\u0631\u0628\u0631\u062c"
    ],
    "wof:name":"Chahar Borj",
    "wof:placetype":"locality"
},
  "geometry": {"coordinates":[57.19281,37.12122],"type":"Point"}
}