{
  "type": "Feature",
  "properties": {
    "gn:admin1_code":"32",
    "gn:asciiname":"Hajji Norush Kandi",
    "gn:country_code":"IR",
    "gn:dem":803,
    "gn:feature_class":"P",
    "gn:feature_code":"PPL",
    "gn:name":"\u1e28\u0101jj\u012b Nor\u016bsh Kand\u012b",
    "gn:population":0,
    "gn:timezone":"Asia/Tehran",
    "iso:country":"IR",
    "name:ara_x_preferred":[
        "\u062d\u0627\u062c\u064a \u0646\u0648\u0631\u0634 \u06a9\u0646\u062f\u064a"
    ],
    "name:fas_x_preferred":[
        "\u062d\u0627\u062c\u0651\u06cc \u0646\u064f\u0648\u0631\u0648\u0634 \u0643\u064e\u0646\u062f\u06cc"
    ],
    "name:fas_x_variant":[
        "\u062d\u0627\u062c\u06cc \u0646\u0631\u0648\u0634 \u0643\u0646\u062f\u06cc",
        "\u1e28\u0101jj\u012b Nowr\u016bsh Kand\u012b",
        "\u1e28\u0101jj\u012b Nor\u016bsh Kand\u012b",
        "\u062d\u0627\u062c\u06cc \u0646\u0648\u0631\u0634 \u06a9\u0646\u062f\u06cc"
    ],
    "name:msa_x_preferred":[
        "Hajji Nowrush Kandi"
    ],
    "wof:name":"Hajji Norush Kandi",
    "wof:placetype":"locality"
},
  "geometry": {"coordinates":[47.6907,39.2198],"type":"Point"}
}