{
  "type": "Feature",
  "properties": {
    "gn:admin1_code":"13",
    "gn:asciiname":"Naqsheh",
    "gn:country_code":"IR",
    "gn:dem":1311,
    "gn:feature_class":"P",
    "gn:feature_code":"PPL",
    "gn:name":"Naqsheh",
    "gn:population":0,
    "gn:timezone":"Asia/Tehran",
    "iso:country":"IR",
    "wof:name":"Naqsheh",
    "wof:placetype":"locality"
},
  "geometry": {"coordinates":[46.87806,34.47972],"type":"Point"}
}