{
  "type": "Feature",
  "properties": {
    "gn:admin1_code":"41",
    "gn:asciiname":"Posuch",
    "gn:country_code":"IR",
    "gn:dem":1802,
    "gn:feature_class":"P",
    "gn:feature_code":"PPL",
    "gn:name":"Pos\u016bch",
    "gn:population":0,
    "gn:timezone":"Asia/Tehran",
    "iso:country":"IR",
    "name:ara_x_preferred":[
        "\u0628\u0633\u0648\u062c"
    ],
    "name:fas_x_preferred":[
        "Pos\u016bch"
    ],
    "name:fas_x_variant":[
        "\u067e\u0633\u0648\u0686",
        "P\u016bch",
        "Pos\u016bj",
        "Pas\u016bj",
        "Pas\u016bch",
        "Seyyed\u0101b\u0101d",
        "\u067e\u0633\u0648\u062c"
    ],
    "name:und_x_variant":[
        "Seyyed\u0101b\u0101d",
        "Pas\u016bch",
        "Pas\u016bj",
        "P\u016bch",
        "Pos\u016bj",
        "Pasuk",
        "\u067e\u0633\u0648\u0686"
    ],
    "wof:name":"Posuch",
    "wof:placetype":"locality"
},
  "geometry": {"coordinates":[59.30067,33.01387],"type":"Point"}
}