{
  "type": "Feature",
  "properties": {
    "gn:admin1_code":"35.0",
    "gn:asciiname":"Mian Galleh",
    "gn:country_code":"IR",
    "gn:dem":27,
    "gn:feature_class":"P",
    "gn:feature_code":"PPL",
    "gn:name":"M\u012b\u0101n Galleh",
    "gn:population":0,
    "gn:timezone":"Asia/Tehran",
    "iso:country":"IR",
    "name:fas_x_preferred":[
        "\u0645\u064a\u0627\u0646 \u06af\u064f\u0644\u0650\u0647"
    ],
    "name:fas_x_variant":[
        "\u0645\u0650\u064a\u0627\u0646 \u06af\u064e\u0644\u0650\u0651\u0647",
        "M\u012b\u0101n Goleh",
        "M\u012b\u0101n Galleh",
        "\u0645\u064a\u0627\u0646 \u06af\u0644\u0647"
    ],
    "name:und_x_variant":[
        "M\u012b\u0101n Galleh",
        "Mey\u0101n Galleh",
        "\u0645\u064a\u0627\u0646 \u06af\u0644\u0647"
    ],
    "wof:name":"Mian Galleh",
    "wof:placetype":"locality"
},
  "geometry": {"coordinates":[53.32872,36.67204],"type":"Point"}
}