{
  "type": "Feature",
  "properties": {
    "gn:admin1_code":"16",
    "gn:asciiname":"Khusheh Darreh",
    "gn:country_code":"IR",
    "gn:dem":1664,
    "gn:feature_class":"P",
    "gn:feature_code":"PPL",
    "gn:name":"Kh\u016bsheh Darreh",
    "gn:population":0,
    "gn:timezone":"Asia/Tehran",
    "iso:country":"IR",
    "name:fas_x_preferred":[
        "\u062e\u0648\u0634\u0647 \u062f\u0631\u0651\u0647"
    ],
    "name:fas_x_variant":[
        "Kh\u016bsheh Darreh"
    ],
    "name:und_x_variant":[
        "Vasheh Darreh",
        "Khoosheh Dareh Khor Khoreh"
    ],
    "wof:name":"Khusheh Darreh",
    "wof:placetype":"locality"
},
  "geometry": {"coordinates":[46.3739,35.9051],"type":"Point"}
}