{
  "type": "Feature",
  "properties": {
    "gn:admin1_code":"22",
    "gn:asciiname":"Gurak Khowrshidi",
    "gn:country_code":"IR",
    "gn:dem":10,
    "gn:feature_class":"P",
    "gn:feature_code":"PPL",
    "gn:name":"G\u016brak Khowrsh\u012bd\u012b",
    "gn:population":0,
    "gn:timezone":"Asia/Tehran",
    "iso:country":"IR",
    "name:fas_x_preferred":[
        "\u062e\u0648\u0631\u0634\u06cc\u062f\u06cc"
    ],
    "name:fas_x_variant":[
        "\u062e\u064f\u0631\u0634\u064a\u062f\u06cc",
        "Khowrsh\u012bd\u012b",
        "Khvorsh\u012bd\u012b",
        "\u06af\u0648\u0631\u06a9 \u062e\u0648\u0631\u0634\u06cc\u062f\u06cc"
    ],
    "name:und_x_variant":[
        "Khorsh\u012bd\u012b",
        "G\u016brak Khowrsh\u012bd\u012b"
    ],
    "wof:name":"Gurak Khowrshidi",
    "wof:placetype":"locality"
},
  "geometry": {"coordinates":[51.04722,28.94736],"type":"Point"}
}