{
  "type": "Feature",
  "properties": {
    "gn:admin1_code":"42.0",
    "gn:asciiname":"Deh-e Borzu",
    "gn:country_code":"IR",
    "gn:dem":1466,
    "gn:feature_class":"P",
    "gn:feature_code":"PPL",
    "gn:name":"Deh-e Borz\u016b",
    "gn:population":0,
    "gn:timezone":"Asia/Tehran",
    "iso:country":"IR",
    "name:ara_x_preferred":[
        "\u062f\u0629 \u0628\u0631\u0632\u0648"
    ],
    "name:fas_x_preferred":[
        "\u062f\u0647 \u0628\u0631\u0632\u0648"
    ],
    "name:fas_x_variant":[
        "Deh Borz\u016b",
        "Deh-e Borz\u016b"
    ],
    "wof:name":"Deh-e Borzu",
    "wof:placetype":"locality"
},
  "geometry": {"coordinates":[60.11825,35.1261],"type":"Point"}
}