{
  "type": "Feature",
  "properties": {
    "gn:admin1_code":"42",
    "gn:asciiname":"Borj",
    "gn:country_code":"IR",
    "gn:dem":1271,
    "gn:feature_class":"P",
    "gn:feature_code":"PPL",
    "gn:name":"Borj",
    "gn:population":0,
    "gn:timezone":"Asia/Tehran",
    "iso:country":"IR",
    "name:fas_x_preferred":[
        "\u0628\u0631\u062c"
    ],
    "wof:name":"Borj",
    "wof:placetype":"locality"
},
  "geometry": {"coordinates":[58.99145,36.12257],"type":"Point"}
}