{
  "type": "Feature",
  "properties": {
    "gn:admin1_code":"9",
    "gn:asciiname":"Yalfan",
    "gn:country_code":"IR",
    "gn:dem":1986,
    "gn:feature_class":"P",
    "gn:feature_code":"PPL",
    "gn:name":"Yalf\u0101n",
    "gn:population":0,
    "gn:timezone":"Asia/Tehran",
    "iso:country":"IR",
    "name:ceb_x_preferred":[
        "Yalf\u0101n"
    ],
    "name:fas_x_preferred":[
        "Yalf\u0101n"
    ],
    "name:fas_x_variant":[
        "\u06cc\u0644\u0641\u0627\u0646"
    ],
    "name:msa_x_preferred":[
        "Yalfan"
    ],
    "name:swe_x_preferred":[
        "Yalf\u0101n"
    ],
    "name:und_x_variant":[
        "Yalp\u0101n"
    ],
    "name:urd_x_preferred":[
        "\u06cc\u0644\u0641\u0627\u0646"
    ],
    "wof:name":"Yalfan",
    "wof:placetype":"locality"
},
  "geometry": {"coordinates":[48.6109,34.73647],"type":"Point"}
}