{
  "type": "Feature",
  "properties": {
    "gn:admin1_code":"8.0",
    "gn:asciiname":"Sadat Mahalleh",
    "gn:country_code":"IR",
    "gn:dem":-22,
    "gn:feature_class":"P",
    "gn:feature_code":"PPL",
    "gn:name":"S\u0101d\u0101t Ma\u1e29alleh",
    "gn:population":0,
    "gn:timezone":"Asia/Tehran",
    "iso:country":"IR",
    "name:fas_x_preferred":[
        "S\u0101d\u0101t Ma\u1e29alleh"
    ],
    "name:fas_x_variant":[
        "\u0633\u0627\u062f\u0627\u062a \u0645\u062d\u0644\u0647",
        "\u0647\u0646\u062f \u062e\u0627\u0644\u0647",
        "\u0633\u0627\u062f\u0627\u062a\u200c\u0645\u062d\u0644\u0647"
    ],
    "name:msa_x_preferred":[
        "Sadat Mahalleh"
    ],
    "name:ukr_x_preferred":[
        "\u0421\u0430\u0434\u0430\u0442-\u041c\u0430\u0445\u0430\u043b\u0435"
    ],
    "name:und_x_variant":[
        "Hend Kh\u0101leh"
    ],
    "name:urd_x_preferred":[
        "\u0633\u0627\u062f\u0627\u062a \u0645\u062d\u0644\u06c1"
    ],
    "wof:name":"Sadat Mahalleh",
    "wof:placetype":"locality"
},
  "geometry": {"coordinates":[49.44363,37.35602],"type":"Point"}
}