{
  "type": "Feature",
  "properties": {
    "gn:admin1_code":"32",
    "gn:asciiname":"Aghguni",
    "gn:country_code":"IR",
    "gn:dem":1549,
    "gn:feature_class":"P",
    "gn:feature_code":"PPL",
    "gn:name":"\u0100ghg\u016bn\u012b",
    "gn:population":0,
    "gn:timezone":"Asia/Tehran",
    "iso:country":"IR",
    "name:fas_x_preferred":[
        "\u0622\u0642 \u06af\u0648\u0646\u06cc"
    ],
    "name:fas_x_variant":[
        "\u0622\u063a\u06af\u0648\u0646\u06cc",
        "\u0100q G\u016bn\u012b",
        "\u0100ghg\u016bn\u012b",
        "\u0622\u0642\u200c\u06af\u0648\u0646\u06cc"
    ],
    "name:msa_x_preferred":[
        "Aq Guni"
    ],
    "wof:name":"Aghguni",
    "wof:placetype":"locality"
},
  "geometry": {"coordinates":[48.2596,38.0917],"type":"Point"}
}