{
  "type": "Feature",
  "properties": {
    "gn:admin1_code":"1.0",
    "gn:asciiname":"Kanurcheh",
    "gn:country_code":"IR",
    "gn:dem":1729,
    "gn:feature_class":"P",
    "gn:feature_code":"PPL",
    "gn:name":"Kan\u016brcheh",
    "gn:population":0,
    "gn:timezone":"Asia/Tehran",
    "iso:country":"IR",
    "name:fas_x_preferred":[
        "\u06a9\u0646\u0648\u0631\u0686\u0647"
    ],
    "name:fas_x_variant":[
        "Kan\u016brcheh"
    ],
    "wof:name":"Kanurcheh",
    "wof:placetype":"locality"
},
  "geometry": {"coordinates":[45.6791,36.1819],"type":"Point"}
}