{
  "type": "Feature",
  "properties": {
    "gn:admin1_code":"8",
    "gn:asciiname":"Gagireh-ye Posht",
    "gn:country_code":"IR",
    "gn:dem":1557,
    "gn:feature_class":"P",
    "gn:feature_code":"PPL",
    "gn:name":"G\u0101g\u012breh-ye Posht",
    "gn:population":0,
    "gn:timezone":"Asia/Tehran",
    "iso:country":"IR",
    "name:fas_x_preferred":[
        "\u06af\u0627\u06af\u0648\u0631 \u067e\u0634\u062a"
    ],
    "name:fas_x_variant":[
        "G\u0101g\u016br Posht",
        "\u06af\u0627\u06af\u06cc\u0631\u0647 \u067e\u0634\u062a"
    ],
    "name:und_x_variant":[
        "G\u0101g\u012breh-ye Posht"
    ],
    "wof:name":"Gagireh-ye Posht",
    "wof:placetype":"locality"
},
  "geometry": {"coordinates":[48.9758,37.34433],"type":"Point"}
}