{
  "type": "Feature",
  "properties": {
    "gn:admin1_code":"1.0",
    "gn:asciiname":"Babur-e `Ajam",
    "gn:country_code":"IR",
    "gn:dem":978,
    "gn:feature_class":"P",
    "gn:feature_code":"PPL",
    "gn:name":"B\u0101b\u016br-e \u2018Ajam",
    "gn:population":0,
    "gn:timezone":"Asia/Tehran",
    "iso:country":"IR",
    "name:fas_x_preferred":[
        "\u0628\u0627\u0628\u0648\u0631 \u0639\u064e\u062c\u064e\u0645"
    ],
    "name:fas_x_variant":[
        "\u0628\u0627\u0628\u0648\u0631 \u0639\u062c\u0645",
        "B\u0101b\u016br \u2018Ajam",
        "\u0628\u0627\u0628\u0648\u0631",
        "\u0628\u0627\u0628\u0627\u0631",
        "B\u0101b\u016br-e \u2018Ajam",
        "\u0628\u0627\u0628\u0650\u0631",
        "\u0628\u064e\u0628\u064f\u0651\u0631 \u0627\u064e\u062c\u064e\u0645"
    ],
    "name:und_x_variant":[
        "B\u0101ber",
        "B\u0101b\u0101r",
        "Baboor Ajam",
        "B\u0101b\u016br"
    ],
    "wof:name":"Babur-e `Ajam",
    "wof:placetype":"locality"
},
  "geometry": {"coordinates":[44.7528,39.3076],"type":"Point"}
}