{
  "type": "Feature",
  "properties": {
    "gn:admin1_code":"11",
    "gn:asciiname":"Sar Chahan",
    "gn:country_code":"IR",
    "gn:dem":56,
    "gn:feature_class":"P",
    "gn:feature_code":"PPL",
    "gn:name":"Sar Ch\u0101h\u0101n",
    "gn:population":0,
    "gn:timezone":"Asia/Tehran",
    "iso:country":"IR",
    "name:fas_x_preferred":[
        "\u0633\u0631 \u0686\u0627\u0647\u0627\u0646"
    ],
    "name:fas_x_variant":[
        "Sar Ch\u0101h\u0101n"
    ],
    "wof:name":"Sar Chahan",
    "wof:placetype":"locality"
},
  "geometry": {"coordinates":[56.6392,27.5097],"type":"Point"}
}