{
  "type": "Feature",
  "properties": {
    "gn:admin1_code":"11",
    "gn:asciiname":"Mazgerd",
    "gn:country_code":"IR",
    "gn:dem":896,
    "gn:feature_class":"P",
    "gn:feature_code":"PPL",
    "gn:name":"M\u0101zgerd",
    "gn:population":0,
    "gn:timezone":"Asia/Tehran",
    "iso:country":"IR",
    "name:fas_x_preferred":[
        "\u0645\u0632\u0627\u06af\u0631\u062f"
    ],
    "name:fas_x_variant":[
        "\u0645\u0627\u0631\u06af\u064e\u0632",
        "\u0645\u0627\u0632\u06af\u0631\u062f",
        "Maz\u0101gerd",
        "M\u0101zgerd"
    ],
    "name:und_x_variant":[
        "M\u0101rgaz"
    ],
    "wof:name":"Mazgerd",
    "wof:placetype":"locality"
},
  "geometry": {"coordinates":[56.9591,27.9882],"type":"Point"}
}