{
  "type": "Feature",
  "properties": {
    "gn:admin1_code":"42.0",
    "gn:asciiname":"Kalateh-ye Hajji Farhad",
    "gn:country_code":"IR",
    "gn:dem":890,
    "gn:feature_class":"P",
    "gn:feature_code":"PPL",
    "gn:name":"Kal\u0101teh-ye \u1e28\u0101jj\u012b Farh\u0101d",
    "gn:population":0,
    "gn:timezone":"Asia/Tehran",
    "iso:country":"IR",
    "name:fas_x_preferred":[
        "Kal\u0101teh-ye Farh\u0101d\u012b"
    ],
    "name:fas_x_variant":[
        "\u06a9\u0644\u0627\u062a\u0647 \u0641\u0631\u0647\u0627\u062f\u06cc",
        "\u06a9\u0644\u0627\u062a\u0647 \u062d\u0627\u062c\u06cc \u0641\u0631\u0647\u0627\u062f"
    ],
    "name:und_x_variant":[
        "Kal\u0101teh-ye \u1e28\u0101jj\u012b Farh\u0101d"
    ],
    "wof:name":"Kalateh-ye Hajji Farhad",
    "wof:placetype":"locality"
},
  "geometry": {"coordinates":[57.83331,34.52670999999999],"type":"Point"}
}