{
  "type": "Feature",
  "properties": {
    "gn:admin1_code":"42",
    "gn:asciiname":"Sardaq",
    "gn:country_code":"IR",
    "gn:dem":812,
    "gn:feature_class":"P",
    "gn:feature_code":"PPL",
    "gn:name":"Sardaq",
    "gn:population":0,
    "gn:timezone":"Asia/Tehran",
    "iso:country":"IR",
    "name:ara_x_preferred":[
        "\u0633\u0631\u062f\u0642"
    ],
    "name:fas_x_preferred":[
        "\u0633\u0631\u062f\u0642"
    ],
    "name:und_x_variant":[
        "Zardak",
        "Sardaq"
    ],
    "wof:name":"Sardaq",
    "wof:placetype":"locality"
},
  "geometry": {"coordinates":[58.11483000000001,34.7865],"type":"Point"}
}