{
  "type": "Feature",
  "properties": {
    "gn:admin1_code":"13",
    "gn:asciiname":"Shisheh Rah",
    "gn:country_code":"IR",
    "gn:dem":629,
    "gn:feature_class":"P",
    "gn:feature_code":"PPL",
    "gn:name":"Sh\u012bsheh R\u0101h",
    "gn:population":0,
    "gn:timezone":"Asia/Tehran",
    "iso:country":"IR",
    "name:fas_x_preferred":[
        "\u0634\u06cc\u0634\u0647 \u0631\u0627\u0647"
    ],
    "name:fas_x_variant":[
        "Sh\u012bsheh R\u0101h"
    ],
    "name:und_x_variant":[
        "Shesh R\u0101h"
    ],
    "wof:name":"Shisheh Rah",
    "wof:placetype":"locality"
},
  "geometry": {"coordinates":[45.84361,34.37547],"type":"Point"}
}