{
  "type": "Feature",
  "properties": {
    "gn:admin1_code":"15",
    "gn:asciiname":"Roqayyeh",
    "gn:country_code":"IR",
    "gn:dem":72,
    "gn:feature_class":"P",
    "gn:feature_code":"PPL",
    "gn:name":"Roqayyeh",
    "gn:population":0,
    "gn:timezone":"Asia/Tehran",
    "iso:country":"IR",
    "name:fas_x_preferred":[
        "\u0631\u0642\u06cc\u0647"
    ],
    "name:fas_x_variant":[
        "\u062f\u0648\u0627\u0631",
        "\u0634\u0647\u0631\u06a9 \u062f\u0648\u0651\u0627\u0631",
        "\u0630\u0628\u0647"
    ],
    "name:und_x_variant":[
        "Davv\u0101r",
        "Shahrak-e Davv\u0101r",
        "Z\u0304obeh"
    ],
    "wof:name":"Roqayyeh",
    "wof:placetype":"locality"
},
  "geometry": {"coordinates":[48.23051,32.1989],"type":"Point"}
}