{
  "type": "Feature",
  "properties": {
    "gn:admin1_code":"11.0",
    "gn:asciiname":"Lakhsa'i",
    "gn:country_code":"IR",
    "gn:dem":31,
    "gn:feature_class":"P",
    "gn:feature_code":"PPL",
    "gn:name":"Lakhs\u0101\u2019\u012b",
    "gn:population":0,
    "gn:timezone":"Asia/Tehran",
    "iso:country":"IR",
    "name:fas_x_preferred":[
        "\u0644\u064e\u062e\u0633\u0627\u0626\u06cc"
    ],
    "name:fas_x_variant":[
        "\u0644\u064e\u062e\u0633\u0627",
        "Lakhs\u0101\u2019\u012b"
    ],
    "name:und_x_variant":[
        "Lakhs\u0101"
    ],
    "wof:name":"Lakhsa'i",
    "wof:placetype":"locality"
},
  "geometry": {"coordinates":[57.03917,27.21556],"type":"Point"}
}