{
  "type": "Feature",
  "properties": {
    "gn:admin1_code":"40",
    "gn:asciiname":"Gazizat",
    "gn:country_code":"IR",
    "gn:dem":1987,
    "gn:feature_class":"P",
    "gn:feature_code":"PPL",
    "gn:name":"G\u0101z\u012bz\u0101t",
    "gn:population":0,
    "gn:timezone":"Asia/Tehran",
    "iso:country":"IR",
    "name:und_x_variant":[
        "G\u0101z\u012bz\u0101t"
    ],
    "wof:name":"Gazizat",
    "wof:placetype":"locality"
},
  "geometry": {"coordinates":[54.08299,31.29969],"type":"Point"}
}