{
  "type": "Feature",
  "properties": {
    "gn:admin1_code":"42",
    "gn:asciiname":"Buzhabad",
    "gn:country_code":"IR",
    "gn:dem":1494,
    "gn:feature_class":"P",
    "gn:feature_code":"PPL",
    "gn:name":"B\u016bzh\u0101b\u0101d",
    "gn:population":0,
    "gn:timezone":"Asia/Tehran",
    "iso:country":"IR",
    "name:ceb_x_preferred":[
        "B\u016bzh\u0101b\u0101d"
    ],
    "name:fas_x_preferred":[
        "\u0628\u0648\u0698 \u0622\u0628\u0627\u062f"
    ],
    "name:fas_x_variant":[
        "B\u016bzh\u0101b\u0101d",
        "\u0628\u0648\u0698\u0622\u0628\u0627\u062f"
    ],
    "name:fra_x_preferred":[
        "Buzhabad"
    ],
    "name:swe_x_preferred":[
        "B\u016bzh\u0101b\u0101d"
    ],
    "wof:name":"Buzhabad",
    "wof:placetype":"locality"
},
  "geometry": {"coordinates":[58.95179,36.22867],"type":"Point"}
}