{
  "type": "Feature",
  "properties": {
    "gn:admin1_code":"5",
    "gn:asciiname":"Emamzadeh `Abdollah",
    "gn:country_code":"IR",
    "gn:dem":2051,
    "gn:feature_class":"P",
    "gn:feature_code":"PPL",
    "gn:name":"Em\u0101mz\u0101deh \u2018Abdoll\u0101h",
    "gn:population":0,
    "gn:timezone":"Asia/Tehran",
    "iso:country":"IR",
    "name:fas_x_preferred":[
        "\u0627\u0650\u0645\u0627\u0645\u0632\u0627\u062f\u0650\u0647 \u0639\u064e\u0628\u062f \u0627\u0644\u0644\u064e\u0651\u0647"
    ],
    "name:fas_x_variant":[
        "Em\u0101mz\u0101deh \u2018Abdoll\u0101h"
    ],
    "wof:name":"Emamzadeh `Abdollah",
    "wof:placetype":"locality"
},
  "geometry": {"coordinates":[51.66667,30.58333],"type":"Point"}
}