{
  "type": "Feature",
  "properties": {
    "gn:admin1_code":"29",
    "gn:asciiname":"Baq Karteh",
    "gn:country_code":"IR",
    "gn:dem":1271,
    "gn:feature_class":"P",
    "gn:feature_code":"PPL",
    "gn:name":"Baq Karteh",
    "gn:population":0,
    "gn:timezone":"Asia/Tehran",
    "iso:country":"IR",
    "name:fas_x_preferred":[
        "\u06af\u06cc\u0648\u062f\u0641\u062a"
    ],
    "name:fas_x_variant":[
        "G\u012bvdaft",
        "\u0628\u0642 \u06a9\u0631\u062a\u0647"
    ],
    "wof:name":"Baq Karteh",
    "wof:placetype":"locality"
},
  "geometry": {"coordinates":[57.0627,28.2912],"type":"Point"}
}