{
  "type": "Feature",
  "properties": {
    "gn:admin1_code":"41",
    "gn:asciiname":"Dorakhsh",
    "gn:country_code":"IR",
    "gn:dem":1992,
    "gn:feature_class":"P",
    "gn:feature_code":"PPL",
    "gn:name":"Dorakhsh",
    "gn:population":0,
    "gn:timezone":"Asia/Tehran",
    "iso:country":"IR",
    "name:fas_x_preferred":[
        "\u062f\u0631\u062e\u0634"
    ],
    "name:und_x_variant":[
        "Duruksh",
        "D\u016br\u016bkhsh",
        "Durakan",
        "Dorokhsh",
        "Dorakhsh"
    ],
    "wof:name":"Dorakhsh",
    "wof:placetype":"locality"
},
  "geometry": {"coordinates":[59.71162,33.16259],"type":"Point"}
}