{
  "type": "Feature",
  "properties": {
    "gn:admin1_code":"23",
    "gn:asciiname":"Hoseyvand",
    "gn:country_code":"IR",
    "gn:dem":1142,
    "gn:feature_class":"P",
    "gn:feature_code":"PPL",
    "gn:name":"\u1e28oseyvand",
    "gn:population":0,
    "gn:timezone":"Asia/Tehran",
    "iso:country":"IR",
    "name:ara_x_preferred":[
        "\u062d\u0633\u064a\u0648\u0646\u062f"
    ],
    "name:ceb_x_preferred":[
        "\u1e28oseyvand"
    ],
    "name:fas_x_preferred":[
        "\u1e28oseynvand"
    ],
    "name:fas_x_variant":[
        "\u062d\u0633\u064a\u0646 \u0648\u0646\u062f",
        "\u062d\u0633\u06cc\u0648\u0646\u062f"
    ],
    "name:swe_x_preferred":[
        "\u1e28oseyvand"
    ],
    "name:und_x_variant":[
        "\u062d\u0633\u064a\u0646 \u0648\u0646\u062f",
        "\u1e28oseyvand"
    ],
    "wof:name":"Hoseyvand",
    "wof:placetype":"locality"
},
  "geometry": {"coordinates":[48.0388,33.5647],"type":"Point"}
}