{
  "type": "Feature",
  "properties": {
    "gn:admin1_code":"44.0",
    "gn:asciiname":"Shahrak-e Shahid Beheshti",
    "gn:country_code":"IR",
    "gn:dem":1229,
    "gn:feature_class":"P",
    "gn:feature_code":"PPL",
    "gn:name":"Shahrak-e Shah\u012bd Behesht\u012b",
    "gn:population":0,
    "gn:timezone":"Asia/Tehran",
    "iso:country":"IR",
    "name:fas_x_preferred":[
        "Shahrak-e Behesht\u012b"
    ],
    "name:fas_x_variant":[
        "\u0634\u0647\u0631\u06a9 \u0628\u0647\u0634\u062a\u06cc",
        "\u0634\u0647\u0631\u06a9 \u0634\u0647\u06cc\u062f \u0628\u0647\u0634\u062a\u06cc",
        "\u0646\u0638\u0631 \u0622\u0628\u0627\u062f"
    ],
    "name:und_x_variant":[
        "Shahrak-e Shah\u012bd Behesht\u012b",
        "Naz\u0327ar\u0101b\u0101d"
    ],
    "wof:name":"Shahrak-e Shahid Beheshti",
    "wof:placetype":"locality"
},
  "geometry": {"coordinates":[50.57691,36.01664],"type":"Point"}
}