{
  "type": "Feature",
  "properties": {
    "gn:admin1_code":"13",
    "gn:asciiname":"Ja`farabad",
    "gn:country_code":"IR",
    "gn:dem":1382,
    "gn:feature_class":"P",
    "gn:feature_code":"PPL",
    "gn:name":"Ja\u2018far\u0101b\u0101d",
    "gn:population":0,
    "gn:timezone":"Asia/Tehran",
    "iso:country":"IR",
    "name:fas_x_preferred":[
        "\u062c\u0639\u0641\u0631 \u0622\u0628\u0627\u062f"
    ],
    "name:fas_x_variant":[
        "Ja\u2018far\u0101b\u0101d"
    ],
    "name:und_x_variant":[
        "Ja\u2018far\u0101b\u0101d"
    ],
    "wof:name":"Ja`farabad",
    "wof:placetype":"locality"
},
  "geometry": {"coordinates":[47.09005,34.30087],"type":"Point"}
}