{
  "type": "Feature",
  "properties": {
    "gn:admin1_code":"7",
    "gn:asciiname":"Tall-e Gar",
    "gn:country_code":"IR",
    "gn:dem":872,
    "gn:feature_class":"P",
    "gn:feature_code":"PPL",
    "gn:name":"Tall-e Gar",
    "gn:population":0,
    "gn:timezone":"Asia/Tehran",
    "iso:country":"IR",
    "name:fas_x_preferred":[
        "\u062a\u0644 \u06af\u0631"
    ],
    "name:und_x_variant":[
        "Tol-e Gar",
        "Tall-e Gar",
        "\u062a\u0644 \u06af\u0631"
    ],
    "wof:name":"Tall-e Gar",
    "wof:placetype":"locality"
},
  "geometry": {"coordinates":[51.47322,30.28035],"type":"Point"}
}