{
  "type": "Feature",
  "properties": {
    "gn:admin1_code":"28",
    "gn:asciiname":"Nir",
    "gn:country_code":"IR",
    "gn:dem":1847,
    "gn:feature_class":"P",
    "gn:feature_code":"PPL",
    "gn:name":"N\u012br",
    "gn:population":0,
    "gn:timezone":"Asia/Tehran",
    "iso:country":"IR",
    "name:fas_x_preferred":[
        "N\u012byeh"
    ],
    "name:fas_x_variant":[
        "\u0646\u06cc\u0647",
        "\u0646\u064a\u0631"
    ],
    "name:pol_x_preferred":[
        "Nije"
    ],
    "name:und_x_variant":[
        "Neyeh",
        "N\u012br"
    ],
    "wof:name":"Nir",
    "wof:placetype":"locality"
},
  "geometry": {"coordinates":[51.86968,33.34565],"type":"Point"}
}