{
  "type": "Feature",
  "properties": {
    "gn:admin1_code":"33",
    "gn:asciiname":"Hasratan",
    "gn:country_code":"IR",
    "gn:dem":255,
    "gn:feature_class":"P",
    "gn:feature_code":"PPL",
    "gn:name":"\u1e28asrat\u0101n",
    "gn:population":0,
    "gn:timezone":"Asia/Tehran",
    "iso:country":"IR",
    "name:ceb_x_preferred":[
        "\u1e28asrat\u0101n"
    ],
    "name:fas_x_preferred":[
        "\u062d\u064e\u0633\u0631\u064e\u062a\u0627\u0646"
    ],
    "name:fas_x_variant":[
        "\u1e28asrat\u0101n",
        "\u062d\u0633\u0631\u062a\u0627\u0646"
    ],
    "name:msa_x_preferred":[
        "Hasratan"
    ],
    "name:swe_x_preferred":[
        "\u1e28asrat\u0101n"
    ],
    "wof:name":"Hasratan",
    "wof:placetype":"locality"
},
  "geometry": {"coordinates":[47.155,39.27556],"type":"Point"}
}