{
  "type": "Feature",
  "properties": {
    "gn:admin1_code":"15.0",
    "gn:asciiname":"`Arab Rashed",
    "gn:country_code":"IR",
    "gn:dem":56,
    "gn:feature_class":"P",
    "gn:feature_code":"PPL",
    "gn:name":"\u2018Arab R\u0101shed",
    "gn:population":0,
    "gn:timezone":"Asia/Tehran",
    "iso:country":"IR",
    "name:fas_x_preferred":[
        "\u0639\u0631\u0628 \u0631\u0627\u0634\u062f"
    ],
    "name:fas_x_variant":[
        "\u2018Arab R\u0101shed"
    ],
    "name:und_x_variant":[
        "\u2018Arbr\u0101shed"
    ],
    "wof:name":"`Arab Rashed",
    "wof:placetype":"locality"
},
  "geometry": {"coordinates":[49.2286,31.29904],"type":"Point"}
}