{
  "type": "Feature",
  "properties": {
    "gn:admin1_code":"1",
    "gn:asciiname":"Abajalu-ye `Olya",
    "gn:country_code":"IR",
    "gn:dem":1287,
    "gn:feature_class":"P",
    "gn:feature_code":"PPL",
    "gn:name":"Ab\u0101jal\u016b-ye \u2018Oly\u0101",
    "gn:population":0,
    "gn:timezone":"Asia/Tehran",
    "iso:country":"IR",
    "name:fas_x_preferred":[
        "\u0622\u0628\u0627\u062c\u0627\u0644\u0648\u06cc \u0639\u064f\u0644\u064a\u0627"
    ],
    "name:fas_x_variant":[
        "\u0627\u0628\u0627\u062c\u0644\u0648\u06cc \u0639\u0644\u06cc\u0627",
        "\u0100b\u0101j\u0101l\u016b-ye \u2018oly\u0101",
        "Ab\u0101jal\u016b-ye \u2018Oly\u0101"
    ],
    "wof:name":"Abajalu-ye `Olya",
    "wof:placetype":"locality"
},
  "geometry": {"coordinates":[45.1504,37.7273],"type":"Point"}
}