{
  "type": "Feature",
  "properties": {
    "gn:admin1_code":"29",
    "gn:asciiname":"Tigugan",
    "gn:country_code":"IR",
    "gn:dem":1061,
    "gn:feature_class":"P",
    "gn:feature_code":"PPL",
    "gn:name":"T\u012bg\u016bgan",
    "gn:population":0,
    "gn:timezone":"Asia/Tehran",
    "iso:country":"IR",
    "name:fas_x_preferred":[
        "\u062a\u06cc\u06af\u0648\u06af\u0646"
    ],
    "name:und_x_variant":[
        "T\u012bg\u016bgan"
    ],
    "wof:name":"Tigugan",
    "wof:placetype":"locality"
},
  "geometry": {"coordinates":[58.18794000000001,26.93135],"type":"Point"}
}