{
  "type": "Feature",
  "properties": {
    "gn:admin1_code":"23",
    "gn:asciiname":"Gaver",
    "gn:country_code":"IR",
    "gn:dem":1119,
    "gn:feature_class":"P",
    "gn:feature_code":"PPL",
    "gn:name":"G\u0101ver",
    "gn:population":0,
    "gn:timezone":"Asia/Tehran",
    "iso:country":"IR",
    "name:fas_x_preferred":[
        "\u06af\u0627\u0648\u0631\u0647"
    ],
    "name:fas_x_variant":[
        "G\u0101vrah",
        "\u06af\u0627\u0648\u0631",
        "\u06af\u0627\u0631\u0647"
    ],
    "name:und_x_variant":[
        "G\u0101ver",
        "G\u0101reh"
    ],
    "wof:name":"Gaver",
    "wof:placetype":"locality"
},
  "geometry": {"coordinates":[48.5615,33.2018],"type":"Point"}
}