{
  "type": "Feature",
  "properties": {
    "gn:admin1_code":"15",
    "gn:asciiname":"Cham",
    "gn:country_code":"IR",
    "gn:dem":628,
    "gn:feature_class":"P",
    "gn:feature_code":"PPL",
    "gn:name":"Cham",
    "gn:population":0,
    "gn:timezone":"Asia/Tehran",
    "iso:country":"IR",
    "name:als_x_preferred":[
        "Cham"
    ],
    "name:cat_x_preferred":[
        "Txam"
    ],
    "name:ceb_x_preferred":[
        "Cham"
    ],
    "name:ces_x_preferred":[
        "Cham"
    ],
    "name:deu_x_preferred":[
        "Cham"
    ],
    "name:epo_x_preferred":[
        "Cham"
    ],
    "name:est_x_preferred":[
        "Cham"
    ],
    "name:eus_x_preferred":[
        "Cham"
    ],
    "name:fas_x_preferred":[
        "\u0686\u0645"
    ],
    "name:fra_x_preferred":[
        "Cham"
    ],
    "name:ind_x_preferred":[
        "Cham"
    ],
    "name:ita_x_preferred":[
        "Cham"
    ],
    "name:lmo_x_preferred":[
        "Cham"
    ],
    "name:nld_x_preferred":[
        "Cham"
    ],
    "name:pol_x_preferred":[
        "Cham"
    ],
    "name:por_x_preferred":[
        "Cham"
    ],
    "name:ron_x_preferred":[
        "Cham"
    ],
    "name:slk_x_preferred":[
        "Cham"
    ],
    "name:spa_x_preferred":[
        "Cham"
    ],
    "name:swe_x_preferred":[
        "Cham"
    ],
    "name:und_x_variant":[
        "\u0686\u0645"
    ],
    "name:vie_x_preferred":[
        "Ch\u00e0m"
    ],
    "name:vol_x_preferred":[
        "Cham"
    ],
    "wof:name":"Cham",
    "wof:placetype":"locality"
},
  "geometry": {"coordinates":[50.02085,31.93312],"type":"Point"}
}