{
  "type": "Feature",
  "properties": {
    "gn:admin1_code":"15",
    "gn:asciiname":"Cham",
    "gn:country_code":"IR",
    "gn:dem":628,
    "gn:feature_class":"P",
    "gn:feature_code":"PPL",
    "gn:name":"Cham",
    "gn:population":0,
    "gn:timezone":"Asia/Tehran",
    "iso:country":"IR",
    "name:fas_x_preferred":[
        "\u0686\u0645"
    ],
    "name:und_x_variant":[
        "\u0686\u0645"
    ],
    "wof:name":"Cham",
    "wof:placetype":"locality"
},
  "geometry": {"coordinates":[50.02085,31.93312],"type":"Point"}
}