{
  "type": "Feature",
  "properties": {
    "gn:admin1_code":"3",
    "gn:asciiname":"Sang Shir",
    "gn:country_code":"IR",
    "gn:dem":2273,
    "gn:feature_class":"P",
    "gn:feature_code":"PPL",
    "gn:name":"Sang Sh\u012br",
    "gn:population":0,
    "gn:timezone":"Asia/Tehran",
    "iso:country":"IR",
    "name:fas_x_preferred":[
        "Sang Sh\u012br"
    ],
    "name:fas_x_variant":[
        "\u0633\u064e\u0646\u06af \u0634\u064a\u0631"
    ],
    "wof:name":"Sang Shir",
    "wof:placetype":"locality"
},
  "geometry": {"coordinates":[50.23278,32.52472],"type":"Point"}
}