{
  "type": "Feature",
  "properties": {
    "gn:admin1_code":"7.0",
    "gn:asciiname":"Khongeh Savar",
    "gn:country_code":"IR",
    "gn:dem":760,
    "gn:feature_class":"P",
    "gn:feature_code":"PPL",
    "gn:name":"Khongeh Sav\u0101r",
    "gn:population":0,
    "gn:timezone":"Asia/Tehran",
    "iso:country":"IR",
    "name:fas_x_preferred":[
        "Khongeh Sav\u0101r"
    ],
    "name:fas_x_variant":[
        "\u062e\u0646\u06af\u0647 \u0633\u0648\u0627\u0631"
    ],
    "wof:name":"Khongeh Savar",
    "wof:placetype":"locality"
},
  "geometry": {"coordinates":[51.82465,29.11913],"type":"Point"}
}