{
  "type": "Feature",
  "properties": {
    "gn:admin1_code":"8",
    "gn:asciiname":"Eshkum Dakeh",
    "gn:country_code":"IR",
    "gn:dem":-17,
    "gn:feature_class":"P",
    "gn:feature_code":"PPL",
    "gn:name":"Eshk\u016bm Dakeh",
    "gn:population":0,
    "gn:timezone":"Asia/Tehran",
    "iso:country":"IR",
    "name:fas_x_preferred":[
        "Eshk\u016bm Dehk\u0101"
    ],
    "name:fas_x_variant":[
        "Eshk\u016bm Dakeh",
        "\u0627\u0634\u06a9\u0648\u0645 \u062f\u06a9\u0647"
    ],
    "name:und_x_variant":[
        "Eshk\u016bm Dakeh",
        "Eshk\u016bmdakeh",
        "Eshm\u0101n Dehg\u0101h",
        "\u0627\u0634\u06a9\u0648\u0645 \u062f\u06a9\u0647",
        "Sham\u0101n Dehg\u0101h",
        "\u0627\u0634\u0645\u0627\u0646 \u062f\u0647\u06af\u0627\u0647"
    ],
    "wof:name":"Eshkum Dakeh",
    "wof:placetype":"locality"
},
  "geometry": {"coordinates":[49.99616,37.36417],"type":"Point"}
}