{
  "type": "Feature",
  "properties": {
    "gn:admin1_code":"5.0",
    "gn:asciiname":"Chahar Rah",
    "gn:country_code":"IR",
    "gn:dem":2218,
    "gn:feature_class":"P",
    "gn:feature_code":"PPL",
    "gn:name":"Chah\u0101r R\u0101h",
    "gn:population":0,
    "gn:timezone":"Asia/Tehran",
    "iso:country":"IR",
    "name:fas_x_preferred":[
        "\u0686\u0647\u0627\u0631 \u0631\u0627\u0647"
    ],
    "name:und_x_variant":[
        "Chah\u0101r R\u0101h"
    ],
    "wof:name":"Chahar Rah",
    "wof:placetype":"locality"
},
  "geometry": {"coordinates":[50.84583,31.08781],"type":"Point"}
}