{
  "type": "Feature",
  "properties": {
    "gn:admin1_code":"8",
    "gn:asciiname":"Pa'in Mahalleh-ye Gildeh",
    "gn:country_code":"IR",
    "gn:dem":-13,
    "gn:feature_class":"P",
    "gn:feature_code":"PPL",
    "gn:name":"P\u0101\u2019\u012bn Ma\u1e29alleh-ye G\u012bldeh",
    "gn:population":0,
    "gn:timezone":"Asia/Tehran",
    "iso:country":"IR",
    "name:ara_x_preferred":[
        "\u0628\u0627\u064a\u064a\u0646 \u0645\u062d\u0644\u0629 \u063a\u0644\u064a\u062f\u0629"
    ],
    "name:fas_x_preferred":[
        "G\u012bldeh-e P\u0101\u2019\u012bn Ma\u1e29alleh"
    ],
    "name:fas_x_variant":[
        "\u067e\u0627\u0626\u06cc\u0646 \u0645\u062d\u0644\u0647 \u06af\u06cc\u0644\u062f\u0647",
        "\u067e\u0627\u06cc\u06cc\u0646\u200c\u0645\u062d\u0644\u0647 \u06af\u06cc\u0644\u062f\u0647"
    ],
    "name:msa_x_preferred":[
        "Pain Mahalleh-ye Gildeh"
    ],
    "name:por_x_preferred":[
        "Pain Mahalleh-ye Gildeh"
    ],
    "name:ukr_x_preferred":[
        "\u041f\u0430\u0457\u043d-\u041c\u0430\u0445\u0430\u043b\u0435-\u0490\u0456\u043b\u044c\u0434\u0435"
    ],
    "name:und_x_variant":[
        "P\u0101\u2019\u012bn Ma\u1e29alleh-ye G\u012bldeh",
        "P\u0101\u2019\u012bn Ma\u1e29alleh-ye Geldeh",
        "G\u012bldeh-e P\u0101\u2019\u012bn"
    ],
    "wof:name":"Pa'in Mahalleh-ye Gildeh",
    "wof:placetype":"locality"
},
  "geometry": {"coordinates":[50.10344,37.35615],"type":"Point"}
}