{
  "type": "Feature",
  "properties": {
    "gn:admin1_code":"8",
    "gn:asciiname":"Pa'in Mahalleh-ye Gildeh",
    "gn:country_code":"IR",
    "gn:dem":-13,
    "gn:feature_class":"P",
    "gn:feature_code":"PPL",
    "gn:name":"P\u0101\u2019\u012bn Ma\u1e29alleh-ye G\u012bldeh",
    "gn:population":0,
    "gn:timezone":"Asia/Tehran",
    "iso:country":"IR",
    "name:fas_x_preferred":[
        "G\u012bldeh-e P\u0101\u2019\u012bn Ma\u1e29alleh"
    ],
    "name:fas_x_variant":[
        "\u067e\u0627\u0626\u06cc\u0646 \u0645\u062d\u0644\u0647 \u06af\u06cc\u0644\u062f\u0647"
    ],
    "name:und_x_variant":[
        "P\u0101\u2019\u012bn Ma\u1e29alleh-ye G\u012bldeh",
        "P\u0101\u2019\u012bn Ma\u1e29alleh-ye Geldeh",
        "G\u012bldeh-e P\u0101\u2019\u012bn"
    ],
    "wof:name":"Pa'in Mahalleh-ye Gildeh",
    "wof:placetype":"locality"
},
  "geometry": {"coordinates":[50.10344,37.35615],"type":"Point"}
}