{
  "type": "Feature",
  "properties": {
    "gn:admin1_code":"15",
    "gn:asciiname":"Tang-e Ta`ak",
    "gn:country_code":"IR",
    "gn:dem":368,
    "gn:feature_class":"P",
    "gn:feature_code":"PPL",
    "gn:name":"Tang-e T\u0101\u2018ak",
    "gn:population":0,
    "gn:timezone":"Asia/Tehran",
    "iso:country":"IR",
    "name:fas_x_preferred":[
        "Tang-e \u0162\u0101hak"
    ],
    "name:fas_x_variant":[
        "\u062a\u0646\u06af \u062a\u0627\u0639\u06a9",
        "\u062a\u0644\u0648\u06a9",
        "\u062a\u0646\u06af \u0637\u0627\u0647\u06a9"
    ],
    "name:und_x_variant":[
        "Tang-e T\u0101\u2018ak",
        "Tal\u016bk"
    ],
    "wof:name":"Tang-e Ta`ak",
    "wof:placetype":"locality"
},
  "geometry": {"coordinates":[49.22611,32.28964000000001],"type":"Point"}
}