{
  "type": "Feature",
  "properties": {
    "gn:admin1_code":"15",
    "gn:asciiname":"Sar Darreh",
    "gn:country_code":"IR",
    "gn:dem":739,
    "gn:feature_class":"P",
    "gn:feature_code":"PPL",
    "gn:name":"Sar Darreh",
    "gn:population":0,
    "gn:timezone":"Asia/Tehran",
    "iso:country":"IR",
    "wof:name":"Sar Darreh",
    "wof:placetype":"locality"
},
  "geometry": {"coordinates":[50.14778,31.73444000000001],"type":"Point"}
}