{
  "type": "Feature",
  "properties": {
    "gn:admin1_code":"1",
    "gn:asciiname":"Pileh Savar",
    "gn:cc2":"IR",
    "gn:country_code":"IR",
    "gn:dem":862,
    "gn:feature_class":"P",
    "gn:feature_code":"PPL",
    "gn:name":"P\u012bleh Sav\u0101r",
    "gn:population":0,
    "gn:timezone":"Asia/Tehran",
    "iso:country":"IR",
    "name:azb_x_preferred":[
        "\u067e\u06cc\u0644\u0647 \u0633\u0648\u0648\u0627\u0631"
    ],
    "name:aze_x_preferred":[
        "Bil\u0259suvar"
    ],
    "name:ceb_x_preferred":[
        "P\u012bleh Sav\u0101r"
    ],
    "name:fas_x_preferred":[
        "\u067e\u064a\u0644\u0650\u0647 \u0633\u064e\u0648\u0627\u0631"
    ],
    "name:fas_x_variant":[
        "P\u012bleh Sav\u0101r",
        "\u067e\u06cc\u0644\u0647\u200c\u0633\u0648\u0627\u0631"
    ],
    "name:msa_x_preferred":[
        "Pileh Savar"
    ],
    "name:swe_x_preferred":[
        "P\u012bleh Sav\u0101r"
    ],
    "name:und_x_variant":[
        "Razvaliny Pilesevar"
    ],
    "wof:name":"Pileh Savar",
    "wof:placetype":"locality"
},
  "geometry": {"coordinates":[45.02861,39.20028],"type":"Point"}
}