{
  "type": "Feature",
  "properties": {
    "gn:admin1_code":"33",
    "gn:asciiname":"Dizaj Sheykh Marjan",
    "gn:country_code":"IR",
    "gn:dem":1378,
    "gn:feature_class":"P",
    "gn:feature_code":"PPL",
    "gn:name":"D\u012bzaj Sheykh Marj\u0101n",
    "gn:population":0,
    "gn:timezone":"Asia/Tehran",
    "iso:country":"IR",
    "name:fas_x_preferred":[
        "\u062f\u064a\u0632\u0650\u0647"
    ],
    "name:fas_x_variant":[
        "\u062f\u06cc\u0632\u062c \u0634\u06cc\u062e \u0645\u0631\u062c\u0627\u0646",
        "D\u012bzaj-e Sheykh Marj\u0101n",
        "\u062f\u064a\u0632\u064e\u062c\u0650 \u0634\u0650\u064a\u062e \u0645\u064e\u0631\u062c\u0627\u0646",
        "\u062f\u064a\u0632\u064e\u062c \u0634\u0650\u064a\u062e \u0645\u064e\u0631\u062c\u0627\u0646"
    ],
    "name:und_x_variant":[
        "Diza",
        "D\u012bzaj Sheykh Marj\u0101n",
        "Dizaj Sheikh Marjan",
        "D\u012bzeh"
    ],
    "wof:name":"Dizaj Sheykh Marjan",
    "wof:placetype":"locality"
},
  "geometry": {"coordinates":[45.3853,38.3086],"type":"Point"}
}