{
  "type": "Feature",
  "properties": {
    "gn:admin1_code":"8",
    "gn:asciiname":"Shesh Arestan",
    "gn:country_code":"IR",
    "gn:dem":101,
    "gn:feature_class":"P",
    "gn:feature_code":"PPL",
    "gn:name":"Shesh \u0100rest\u0101n",
    "gn:population":0,
    "gn:timezone":"Asia/Tehran",
    "iso:country":"IR",
    "name:fas_x_preferred":[
        "Sh\u012bsh\u0101rest\u0101n"
    ],
    "name:fas_x_variant":[
        "Shesh \u0100rest\u0101n",
        "\u0634\u0634 \u0622\u0631\u0627\u0633\u062a\u0627\u0646",
        "\u0634\u06cc \u0634\u0627\u0631\u0633\u062a\u0627\u0646"
    ],
    "name:und_x_variant":[
        "\u0634\u0634 \u0622\u0631\u0627\u0633\u062a\u0627\u0646"
    ],
    "wof:name":"Shesh Arestan",
    "wof:placetype":"locality"
},
  "geometry": {"coordinates":[50.1724,37.05232],"type":"Point"}
}