{
  "type": "Feature",
  "properties": {
    "gn:admin1_code":"8.0",
    "gn:asciiname":"Yasan",
    "gn:country_code":"IR",
    "gn:dem":1357,
    "gn:feature_class":"P",
    "gn:feature_code":"PPL",
    "gn:name":"Yasan",
    "gn:population":0,
    "gn:timezone":"Asia/Tehran",
    "iso:country":"IR",
    "name:fas_x_preferred":[
        "\u06cc\u0633\u0646"
    ],
    "name:msa_x_preferred":[
        "Yasan"
    ],
    "name:ukr_x_preferred":[
        "\u042f\u0441\u0430\u043d"
    ],
    "name:und_x_variant":[
        "\u06cc\u0633\u0646"
    ],
    "name:urd_x_preferred":[
        "\u06cc\u0633\u0646"
    ],
    "wof:name":"Yasan",
    "wof:placetype":"locality"
},
  "geometry": {"coordinates":[50.05709,36.80605],"type":"Point"}
}