{
  "type": "Feature",
  "properties": {
    "gn:admin1_code":"4.0",
    "gn:asciiname":"Deh-e Musa Kukan",
    "gn:country_code":"IR",
    "gn:dem":482,
    "gn:feature_class":"P",
    "gn:feature_code":"PPL",
    "gn:name":"Deh-e M\u016bs\u00e1 K\u016bk\u0101n",
    "gn:population":0,
    "gn:timezone":"Asia/Tehran",
    "iso:country":"IR",
    "name:fas_x_preferred":[
        "\u062f\u0647 \u0645\u0648\u0633\u06cc \u06a9\u0648\u06a9\u0627\u0646"
    ],
    "name:fas_x_variant":[
        "Deh-e M\u016bs\u00e1 K\u016bk\u0101n",
        "\u0645\u0648\u0633\u06cc \u06a9\u0648\u0647\u06a9\u0646"
    ],
    "name:und_x_variant":[
        "M\u016bs\u00e1 K\u016bhkan"
    ],
    "wof:name":"Deh-e Musa Kukan",
    "wof:placetype":"locality"
},
  "geometry": {"coordinates":[61.73893,31.12404],"type":"Point"}
}