{
  "type": "Feature",
  "properties": {
    "gn:admin1_code":"16",
    "gn:asciiname":"Dowlatabad-e Kurkureh",
    "gn:country_code":"IR",
    "gn:dem":1813,
    "gn:feature_class":"P",
    "gn:feature_code":"PPL",
    "gn:name":"Dowlat\u0101b\u0101d-e K\u016brk\u016breh",
    "gn:population":0,
    "gn:timezone":"Asia/Tehran",
    "iso:country":"IR",
    "name:fas_x_preferred":[
        "\u062f\u0648\u0644\u062a \u0622\u0628\u0627\u062f \u06a9\u0648\u0631 \u06a9\u0648\u0631\u0647"
    ],
    "name:fas_x_variant":[
        "Dowlat\u0101b\u0101d K\u016brk\u016breh",
        "Dowlat\u0101b\u0101d-e K\u016brk\u016breh",
        "\u062f\u0648\u0644\u062a \u0622\u0628\u0627\u062f"
    ],
    "name:und_x_variant":[
        "Khor Khowreh",
        "Dowlat\u0101b\u0101d-e Karkareh",
        "Khvor Khvoreh",
        "Dowlat\u0101b\u0101d-e Khorkoreh",
        "Khor Kurreh",
        "Dowlat\u0101b\u0101d"
    ],
    "wof:name":"Dowlatabad-e Kurkureh",
    "wof:placetype":"locality"
},
  "geometry": {"coordinates":[47.11763,35.30377],"type":"Point"}
}