{
  "type": "Feature",
  "properties": {
    "gn:admin1_code":"28",
    "gn:asciiname":"Nesar-e Eskandari",
    "gn:country_code":"IR",
    "gn:dem":2150,
    "gn:feature_class":"P",
    "gn:feature_code":"PPL",
    "gn:name":"Nes\u0101r-e Eskandar\u012b",
    "gn:population":0,
    "gn:timezone":"Asia/Tehran",
    "iso:country":"IR",
    "name:ara_x_preferred":[
        "\u0646\u0633\u0627\u0631 \u0627\u0633\u0643\u0646\u062f\u0631\u064a"
    ],
    "name:fas_x_preferred":[
        "Nes\u0101r-e Eskandar\u012b"
    ],
    "name:fas_x_variant":[
        "\u0646\u0633\u0627\u0631 \u0627\u0633\u06a9\u0646\u062f\u0631\u06cc"
    ],
    "name:und_x_variant":[
        "Eskandar\u012b-ye Nes\u0101\u2018",
        "Nes\u0101r",
        "Nis\u0101r",
        "\u0646\u0633\u0627\u0631 \u0627\u0633\u06a9\u0646\u062f\u0631\u06cc"
    ],
    "wof:name":"Nesar-e Eskandari",
    "wof:placetype":"locality"
},
  "geometry": {"coordinates":[50.42426,32.81768],"type":"Point"}
}