{
  "type": "Feature",
  "properties": {
    "gn:admin1_code":"28.0",
    "gn:asciiname":"Shahrak-e Hadi Kal",
    "gn:country_code":"IR",
    "gn:dem":1558,
    "gn:feature_class":"P",
    "gn:feature_code":"PPL",
    "gn:name":"Shahrak-e H\u0101d\u012b Kal",
    "gn:population":0,
    "gn:timezone":"Asia/Tehran",
    "iso:country":"IR",
    "name:fas_x_preferred":[
        "H\u0101d\u012b Kal"
    ],
    "name:fas_x_variant":[
        "\u0634\u0647\u0631\u06a9 \u0647\u0627\u062f\u06cc \u06a9\u0644",
        "\u0647\u0627\u062f\u06cc \u06a9\u0644"
    ],
    "name:und_x_variant":[
        "H\u0101d\u012b Koll",
        "Shahrak-e H\u0101d\u012b Kal"
    ],
    "wof:name":"Shahrak-e Hadi Kal",
    "wof:placetype":"locality"
},
  "geometry": {"coordinates":[51.70912,32.72953],"type":"Point"}
}