{
  "type": "Feature",
  "properties": {
    "gn:admin1_code":"33",
    "gn:asciiname":"Morad Khan Kandi",
    "gn:country_code":"IR",
    "gn:dem":1928,
    "gn:feature_class":"P",
    "gn:feature_code":"PPL",
    "gn:name":"Mor\u0101d Kh\u0101n Kand\u012b",
    "gn:population":0,
    "gn:timezone":"Asia/Tehran",
    "iso:country":"IR",
    "name:fas_x_preferred":[
        "\u0645\u0631\u0627\u062f \u062e\u0627\u0646 \u0643\u0646\u062f\u06cc"
    ],
    "name:fas_x_variant":[
        "Mor\u0101dkh\u0101n Kand\u012b",
        "Mor\u0101d Kh\u0101n Kand\u012b"
    ],
    "wof:name":"Morad Khan Kandi",
    "wof:placetype":"locality"
},
  "geometry": {"coordinates":[47.3175,36.9826],"type":"Point"}
}