{
  "type": "Feature",
  "properties": {
    "gn:admin1_code":"23",
    "gn:asciiname":"`Aliabad",
    "gn:country_code":"IR",
    "gn:dem":2127,
    "gn:feature_class":"P",
    "gn:feature_code":"PPL",
    "gn:name":"\u2018Al\u012b\u0101b\u0101d",
    "gn:population":0,
    "gn:timezone":"Asia/Tehran",
    "iso:country":"IR",
    "name:fas_x_preferred":[
        "\u2018Al\u012b\u0101b\u0101d"
    ],
    "name:fas_x_variant":[
        "\u0639\u0644\u06cc \u0622\u0628\u0627\u062f",
        "\u06a9\u06cc\u0648\u0631\u0632 \u0627\u0645\u06cc\u0631 \u0622\u0628\u0627\u062f"
    ],
    "name:und_x_variant":[
        "\u0639\u0644\u06cc \u0622\u0628\u0627\u062f",
        "K\u012bvarz-e Am\u012br\u0101b\u0101d"
    ],
    "wof:name":"`Aliabad",
    "wof:placetype":"locality"
},
  "geometry": {"coordinates":[49.71285,33.15162],"type":"Point"}
}