{
  "type": "Feature",
  "properties": {
    "gn:admin1_code":"25",
    "gn:asciiname":"Qatik",
    "gn:country_code":"IR",
    "gn:dem":1597,
    "gn:feature_class":"P",
    "gn:feature_code":"PPL",
    "gn:name":"Qat\u012bk",
    "gn:population":0,
    "gn:timezone":"Asia/Tehran",
    "iso:country":"IR",
    "name:fas_x_preferred":[
        "\u0642\u062a\u06cc\u06a9"
    ],
    "name:fas_x_variant":[
        "Qat\u012bk",
        "\u0642\u06cc\u0637\u06a9"
    ],
    "name:und_x_variant":[
        "Q\u012b\u0163ak"
    ],
    "wof:name":"Qatik",
    "wof:placetype":"locality"
},
  "geometry": {"coordinates":[53.72225,35.61282999999999],"type":"Point"}
}