{
  "type": "Feature",
  "properties": {
    "gn:admin1_code":"23",
    "gn:asciiname":"Nurabad Nadar",
    "gn:country_code":"IR",
    "gn:dem":1583,
    "gn:feature_class":"P",
    "gn:feature_code":"PPL",
    "gn:name":"N\u016br\u0101b\u0101d Nadar",
    "gn:population":0,
    "gn:timezone":"Asia/Tehran",
    "iso:country":"IR",
    "name:fas_x_preferred":[
        "N\u016br\u0101b\u0101d"
    ],
    "name:fas_x_variant":[
        "\u0646\u0648\u0631 \u0622\u0628\u0627\u062f",
        "\u0646\u0648\u0631 \u0622\u0628\u0627\u062f \u0646\u062f\u0631"
    ],
    "name:und_x_variant":[
        "N\u016br\u0101b\u0101d Nadar"
    ],
    "wof:name":"Nurabad Nadar",
    "wof:placetype":"locality"
},
  "geometry": {"coordinates":[48.26311,33.84624],"type":"Point"}
}