{
  "type": "Feature",
  "properties": {
    "gn:admin1_code":"26.0",
    "gn:asciiname":"Razkan",
    "gn:country_code":"IR",
    "gn:dem":1116,
    "gn:feature_class":"P",
    "gn:feature_code":"PPL",
    "gn:name":"Razk\u0101n",
    "gn:population":0,
    "gn:timezone":"Asia/Tehran",
    "iso:country":"IR",
    "name:fas_x_preferred":[
        "\u0632\u0631\u0643\u0627\u0646"
    ],
    "name:fas_x_variant":[
        "Razk\u0101n",
        "Qal\u2018eh-ye Razak\u0101n",
        "\u0631\u0632\u0643\u0627\u0646",
        "\u0642\u064e\u0644\u0639\u0650\u06c0 \u0631\u064e\u0632\u064e\u0643\u0627\u0646",
        "Zark\u0101n"
    ],
    "wof:name":"Razkan",
    "wof:placetype":"locality"
},
  "geometry": {"coordinates":[51.1005,35.6259],"type":"Point"}
}