{
  "type": "Feature",
  "properties": {
    "gn:admin1_code":"15.0",
    "gn:asciiname":"`Abd ol Emam Feysali",
    "gn:country_code":"IR",
    "gn:dem":1,
    "gn:feature_class":"P",
    "gn:feature_code":"PPL",
    "gn:name":"\u2018Abd ol Em\u0101m Fey\u015fal\u012b",
    "gn:population":0,
    "gn:timezone":"Asia/Tehran",
    "iso:country":"IR",
    "name:fas_x_preferred":[
        "\u0639\u0628\u062f\u0627\u0644\u0627\u0645\u0627\u0645 \u0641\u06cc\u0635\u0644\u06cc"
    ],
    "name:fas_x_variant":[
        "\u2018Abd ol Em\u0101m-e Fey\u015fal"
    ],
    "name:und_x_variant":[
        "Raddeh-ye Omm ol Qa\u015fab",
        "Abd ol Em\u0101m Feysal\u012b",
        "\u2018Abd ol Em\u0101m Fey\u015fal\u012b"
    ],
    "wof:name":"`Abd ol Emam Feysali",
    "wof:placetype":"locality"
},
  "geometry": {"coordinates":[48.20039000000001,30.34827],"type":"Point"}
}