{
  "type": "Feature",
  "properties": {
    "gn:admin1_code":"7",
    "gn:asciiname":"Badamu",
    "gn:country_code":"IR",
    "gn:dem":2071,
    "gn:feature_class":"P",
    "gn:feature_code":"PPL",
    "gn:name":"B\u0101d\u0101m\u016b",
    "gn:population":0,
    "gn:timezone":"Asia/Tehran",
    "iso:country":"IR",
    "name:fas_x_preferred":[
        "\u0628\u0627\u062f\u0627\u0645\u0648"
    ],
    "name:fas_x_variant":[
        "B\u0101d\u0101m\u016b"
    ],
    "name:msa_x_preferred":[
        "Badamu"
    ],
    "wof:name":"Badamu",
    "wof:placetype":"locality"
},
  "geometry": {"coordinates":[54.5754,29.0936],"type":"Point"}
}