{
  "type": "Feature",
  "properties": {
    "gn:admin1_code":"1",
    "gn:asciiname":"Qand Qoli",
    "gn:country_code":"IR",
    "gn:dem":2080,
    "gn:feature_class":"P",
    "gn:feature_code":"PPL",
    "gn:name":"Qand Qol\u012b",
    "gn:population":0,
    "gn:timezone":"Asia/Tehran",
    "iso:country":"IR",
    "name:ara_x_preferred":[
        "\u0642\u0646\u062f\u062e\u0644\u064a"
    ],
    "name:aze_x_preferred":[
        "Q\u0259ndxili"
    ],
    "name:fas_x_preferred":[
        "Qand Qol\u012b"
    ],
    "name:fas_x_variant":[
        "\u0642\u064e\u0646\u062f \u062e\u0650\u0644\u06cc",
        "Qand Khel\u012b",
        "\u0642\u0646\u062f \u0642\u0644\u06cc",
        "\u0642\u0646\u062f\u062e\u0644\u06cc"
    ],
    "name:msa_x_preferred":[
        "Qand Kheli"
    ],
    "name:und_x_variant":[
        "\u0642\u0646\u062f \u0642\u0644\u06cc"
    ],
    "wof:name":"Qand Qoli",
    "wof:placetype":"locality"
},
  "geometry": {"coordinates":[44.2562,39.3222],"type":"Point"}
}