{
  "type": "Feature",
  "properties": {
    "gn:admin1_code":"3.0",
    "gn:asciiname":"Golabi-ye Pa`in",
    "gn:country_code":"IR",
    "gn:dem":1815,
    "gn:feature_class":"P",
    "gn:feature_code":"PPL",
    "gn:name":"Gol\u0101b\u012b-ye P\u0101\u2018\u012bn",
    "gn:population":0,
    "gn:timezone":"Asia/Tehran",
    "iso:country":"IR",
    "name:fas_x_preferred":[
        "Gol\u0101b\u012b-ye P\u0101\u2018\u012bn"
    ],
    "name:fas_x_variant":[
        "\u06af\u0644\u0627\u0628\u06cc \u067e\u0627\u0626\u06cc\u0646"
    ],
    "wof:name":"Golabi-ye Pa`in",
    "wof:placetype":"locality"
},
  "geometry": {"coordinates":[51.2259,31.2926],"type":"Point"}
}