{
  "type": "Feature",
  "properties": {
    "gn:admin1_code":"33",
    "gn:asciiname":"Qal`eh Joq",
    "gn:country_code":"IR",
    "gn:dem":1060,
    "gn:feature_class":"P",
    "gn:feature_code":"PPL",
    "gn:name":"Qal\u2018eh Joq",
    "gn:population":0,
    "gn:timezone":"Asia/Tehran",
    "iso:country":"IR",
    "name:fas_x_preferred":[
        "Qeshl\u0101q-e Qal\u2018ehj\u012bq"
    ],
    "name:fas_x_variant":[
        "\u0642\u0644\u0639\u0647 \u062c\u0642",
        "\u0642\u0644\u0639\u0647 \u062c\u0648\u0642",
        "\u0642\u0634\u0644\u0627\u0642 \u0642\u0644\u0639\u0647 \u062c\u06cc\u0642"
    ],
    "name:und_x_variant":[
        "Qal\u2018eh Joq",
        "Qal\u2018eh J\u016bq",
        "Qeshl\u0101q-e Qal\u2018eh J\u012bq"
    ],
    "wof:name":"Qal`eh Joq",
    "wof:placetype":"locality"
},
  "geometry": {"coordinates":[47.44688,38.56991],"type":"Point"}
}