{
  "type": "Feature",
  "properties": {
    "gn:admin1_code":"5",
    "gn:asciiname":"Dam Tang-e Chahen",
    "gn:country_code":"IR",
    "gn:dem":974,
    "gn:feature_class":"P",
    "gn:feature_code":"PPL",
    "gn:name":"Dam Tang-e Ch\u0101hen",
    "gn:population":0,
    "gn:timezone":"Asia/Tehran",
    "iso:country":"IR",
    "name:fas_x_preferred":[
        "Damtang-e Sh\u0101h\u012bn"
    ],
    "name:fas_x_variant":[
        "Dam Tang-e Ch\u0101hen",
        "\u062f\u0645 \u062a\u0646\u06af \u0686\u0627\u0647\u0646"
    ],
    "wof:name":"Dam Tang-e Chahen",
    "wof:placetype":"locality"
},
  "geometry": {"coordinates":[50.29836,30.99764],"type":"Point"}
}