{
  "type": "Feature",
  "properties": {
    "gn:admin1_code":"23",
    "gn:asciiname":"Sarab-e Sheykh `Ali",
    "gn:country_code":"IR",
    "gn:dem":1698,
    "gn:feature_class":"P",
    "gn:feature_code":"PPL",
    "gn:name":"Sar\u0101b-e Sheykh \u2018\u0100l\u012b",
    "gn:population":0,
    "gn:timezone":"Asia/Tehran",
    "iso:country":"IR",
    "name:fas_x_preferred":[
        "\u0633\u0631\u0627\u0628 \u0634\u06cc\u062e \u0639\u0627\u0644\u06cc"
    ],
    "name:fas_x_variant":[
        "Sar\u0101b-e Sheykh \u2018\u0100l\u012b"
    ],
    "name:und_x_variant":[
        "Sar\u0101b Shaikh \u2018Ali"
    ],
    "wof:name":"Sarab-e Sheykh `Ali",
    "wof:placetype":"locality"
},
  "geometry": {"coordinates":[48.05,33.8966],"type":"Point"}
}