{
  "type": "Feature",
  "properties": {
    "gn:admin1_code":"11",
    "gn:asciiname":"Pol-e Sharqi",
    "gn:country_code":"IR",
    "gn:dem":9,
    "gn:feature_class":"P",
    "gn:feature_code":"PPL",
    "gn:name":"Pol-e Sharq\u012b",
    "gn:population":0,
    "gn:timezone":"Asia/Tehran",
    "iso:country":"IR",
    "name:fas_x_preferred":[
        "\u067e\u0647\u0644"
    ],
    "name:fas_x_variant":[
        "Pol-e Sharq\u012b",
        "\u067e\u064f\u0644\u0650 \u0634\u064e\u0631\u0642\u06cc",
        "\u067e\u0644 \u0634\u0631\u0642\u06cc"
    ],
    "name:msa_x_preferred":[
        "Pol-e Sharqi"
    ],
    "name:und_x_variant":[
        "Pahel"
    ],
    "wof:name":"Pol-e Sharqi",
    "wof:placetype":"locality"
},
  "geometry": {"coordinates":[55.7394,27.009],"type":"Point"}
}