{
  "type": "Feature",
  "properties": {
    "gn:admin1_code":"7",
    "gn:asciiname":"Ab Bid",
    "gn:country_code":"IR",
    "gn:dem":1453,
    "gn:feature_class":"P",
    "gn:feature_code":"PPL",
    "gn:name":"\u0100b B\u012bd",
    "gn:population":0,
    "gn:timezone":"Asia/Tehran",
    "iso:country":"IR",
    "name:fas_x_preferred":[
        "\u0100b B\u012bd"
    ],
    "name:fas_x_variant":[
        "\u0100b B\u012bd-e Lalah",
        "\u0622\u0628 \u0628\u06cc\u062f",
        "\u0622\u0628\u200c\u0628\u06cc\u062f"
    ],
    "wof:name":"Ab Bid",
    "wof:placetype":"locality"
},
  "geometry": {"coordinates":[51.73437,30.16812],"type":"Point"}
}