{
  "type": "Feature",
  "properties": {
    "gn:admin1_code":"29",
    "gn:asciiname":"Darreh Kordi",
    "gn:country_code":"IR",
    "gn:dem":2412,
    "gn:feature_class":"P",
    "gn:feature_code":"PPL",
    "gn:name":"Darreh Kord\u012b",
    "gn:population":0,
    "gn:timezone":"Asia/Tehran",
    "iso:country":"IR",
    "name:fas_x_preferred":[
        "\u062f\u0631\u0651\u0647 \u06a9\u0631\u062f\u06cc"
    ],
    "name:und_x_variant":[
        "Borz",
        "Barz",
        "Burz",
        "Bowrz",
        "Darreh Kord\u012b"
    ],
    "wof:name":"Darreh Kordi",
    "wof:placetype":"locality"
},
  "geometry": {"coordinates":[55.4164,30.3973],"type":"Point"}
}