{
  "type": "Feature",
  "properties": {
    "gn:admin1_code":"29",
    "gn:asciiname":"Chaman Rang",
    "gn:country_code":"IR",
    "gn:dem":2493,
    "gn:feature_class":"P",
    "gn:feature_code":"PPL",
    "gn:name":"Chaman Rang",
    "gn:population":0,
    "gn:timezone":"Asia/Tehran",
    "iso:country":"IR",
    "name:fas_x_preferred":[
        "\u0686\u0645\u0646 \u0631\u0646\u06af"
    ],
    "name:und_x_variant":[
        "Chamanrang",
        "Chaman Rang",
        "Rang"
    ],
    "wof:name":"Chaman Rang",
    "wof:placetype":"locality"
},
  "geometry": {"coordinates":[56.66596,29.59135],"type":"Point"}
}