{
  "type": "Feature",
  "properties": {
    "gn:admin1_code":"28",
    "gn:asciiname":"Mashhad Kaveh",
    "gn:country_code":"IR",
    "gn:dem":2110,
    "gn:feature_class":"P",
    "gn:feature_code":"PPL",
    "gn:name":"Mashhad K\u0101veh",
    "gn:population":0,
    "gn:timezone":"Asia/Tehran",
    "iso:country":"IR",
    "name:fas_x_preferred":[
        "Mashhad K\u0101veh"
    ],
    "name:fas_x_variant":[
        "\u0645\u0634\u0647\u062f \u06a9\u0627\u0648\u0647"
    ],
    "name:und_x_variant":[
        "Mashhad-e K\u0101veh",
        "Mashhad",
        "\u0645\u0634\u0647\u062f \u06a9\u0627\u0648\u0647"
    ],
    "wof:name":"Mashhad Kaveh",
    "wof:placetype":"locality"
},
  "geometry": {"coordinates":[50.52099000000001,32.72456],"type":"Point"}
}