{
  "type": "Feature",
  "properties": {
    "gn:admin1_code":"35",
    "gn:asciiname":"Duna-ye `Olya",
    "gn:country_code":"IR",
    "gn:dem":2484,
    "gn:feature_class":"P",
    "gn:feature_code":"PPL",
    "gn:name":"D\u016bn\u0101-ye \u2018Oly\u0101",
    "gn:population":0,
    "gn:timezone":"Asia/Tehran",
    "iso:country":"IR",
    "name:fas_x_preferred":[
        "\u062f\u0648\u0646\u0627\u06cc \u0628\u0627\u0644\u0627"
    ],
    "name:fas_x_variant":[
        "\u062f\u0648\u0646\u0627",
        "\u062f\u0648\u0646\u0627\u06cc \u0639\u0644\u06cc\u0627",
        "D\u016bn\u0101-ye B\u0101l\u0101"
    ],
    "name:und_x_variant":[
        "D\u016bn\u0101",
        "D\u016bn\u0101-ye \u2018Oly\u0101"
    ],
    "wof:name":"Duna-ye `Olya",
    "wof:placetype":"locality"
},
  "geometry": {"coordinates":[51.37217,36.19574],"type":"Point"}
}