{
  "type": "Feature",
  "properties": {
    "gn:admin1_code":"8",
    "gn:asciiname":"Kalanglash",
    "gn:country_code":"IR",
    "gn:dem":1608,
    "gn:feature_class":"P",
    "gn:feature_code":"PPL",
    "gn:name":"Kalanglash",
    "gn:population":0,
    "gn:timezone":"Asia/Tehran",
    "iso:country":"IR",
    "name:fas_x_preferred":[
        "\u06a9\u0644\u0646\u06af\u0634"
    ],
    "name:fas_x_variant":[
        "\u06a9\u0644\u0646\u06a9\u0644\u0634"
    ],
    "name:und_x_variant":[
        "Kalangash",
        "\u06a9\u0644\u0646\u06af\u0634",
        "Kalanglash"
    ],
    "wof:name":"Kalanglash",
    "wof:placetype":"locality"
},
  "geometry": {"coordinates":[49.76202,36.82575],"type":"Point"}
}