{
  "type": "Feature",
  "properties": {
    "gn:admin1_code":"11",
    "gn:asciiname":"Zevr",
    "gn:country_code":"IR",
    "gn:dem":42,
    "gn:feature_class":"P",
    "gn:feature_code":"PPL",
    "gn:name":"Zevr",
    "gn:population":0,
    "gn:timezone":"Asia/Tehran",
    "iso:country":"IR",
    "name:fas_x_preferred":[
        "\u0632\u0650\u0648\u0631"
    ],
    "wof:name":"Zevr",
    "wof:placetype":"locality"
},
  "geometry": {"coordinates":[58.11666999999999,25.91667],"type":"Point"}
}