{
  "type": "Feature",
  "properties": {
    "gn:admin1_code":"7",
    "gn:asciiname":"Kalatu",
    "gn:country_code":"IR",
    "gn:dem":655,
    "gn:feature_class":"P",
    "gn:feature_code":"PPL",
    "gn:name":"Kal\u0101t\u016b",
    "gn:population":0,
    "gn:timezone":"Asia/Tehran",
    "iso:country":"IR",
    "name:fas_x_preferred":[
        "\u06a9\u0644\u0627\u062a\u0648"
    ],
    "name:fas_x_variant":[
        "Kal\u0101t\u016bn",
        "Kal\u0101t\u016b",
        "\u06a9\u0644\u0627\u062a\u0648\u0646"
    ],
    "name:msa_x_preferred":[
        "Kalatun"
    ],
    "wof:name":"Kalatu",
    "wof:placetype":"locality"
},
  "geometry": {"coordinates":[51.374,29.6388],"type":"Point"}
}