{
  "type": "Feature",
  "properties": {
    "gn:admin1_code":"38",
    "gn:asciiname":"Zajkan-e Sofla",
    "gn:country_code":"IR",
    "gn:dem":1325,
    "gn:feature_class":"P",
    "gn:feature_code":"PPL",
    "gn:name":"Z\u0101jk\u0101n-e Sofl\u00e1",
    "gn:population":0,
    "gn:timezone":"Asia/Tehran",
    "iso:country":"IR",
    "name:fas_x_preferred":[
        "\u0632\u0627\u062c \u0643\u0627\u0646 \u067e\u0627\u0626\u064a\u0646"
    ],
    "name:fas_x_variant":[
        "Z\u0101j K\u0101n-e P\u0101\u2019\u012bn",
        "\u0632\u0627\u062c\u06a9\u0627\u0646 \u0633\u0641\u0644\u06cc"
    ],
    "name:und_x_variant":[
        "Zadzhkan-Sufla",
        "Z\u0101jk\u0101n Sufla",
        "Z\u0101chg\u0101n-e Sofl\u00e1",
        "Z\u0101chk\u0101n-e Sofl\u00e1",
        "Z\u0101jk\u0101n-e Sofl\u00e1"
    ],
    "wof:name":"Zajkan-e Sofla",
    "wof:placetype":"locality"
},
  "geometry": {"coordinates":[49.42545,36.33831],"type":"Point"}
}