{
  "type": "Feature",
  "properties": {
    "gn:admin1_code":"1",
    "gn:asciiname":"Alakabad",
    "gn:country_code":"IR",
    "gn:dem":1872,
    "gn:feature_class":"P",
    "gn:feature_code":"PPL",
    "gn:name":"\u0100lak\u0101b\u0101d",
    "gn:population":0,
    "gn:timezone":"Asia/Tehran",
    "iso:country":"IR",
    "name:fas_x_preferred":[
        "\u0622\u0644\u06a9\u0627\u0628\u0627\u062f"
    ],
    "name:fas_x_variant":[
        "Alak\u0101b\u0101d",
        "\u0100lak\u0101b\u0101d"
    ],
    "name:und_x_variant":[
        "\u0100lamk\u0101b\u0101d"
    ],
    "wof:name":"Alakabad",
    "wof:placetype":"locality"
},
  "geometry": {"coordinates":[45.05,37.0488],"type":"Point"}
}