{
  "type": "Feature",
  "properties": {
    "gn:admin1_code":"33",
    "gn:asciiname":"Kandovan",
    "gn:country_code":"IR",
    "gn:dem":2224,
    "gn:feature_class":"P",
    "gn:feature_code":"PPL",
    "gn:name":"Kandov\u0101n",
    "gn:population":0,
    "gn:timezone":"Asia/Tehran",
    "iso:country":"IR",
    "name:ara_x_preferred":[
        "\u0643\u0627\u0646\u062f\u0648\u0641\u0627\u0646"
    ],
    "name:azb_x_preferred":[
        "\u06af\u0648\u0646\u062f\u0648\u063a\u0627\u0646"
    ],
    "name:aze_x_preferred":[
        "K\u0259nduvan"
    ],
    "name:bul_x_preferred":[
        "\u041a\u0430\u043d\u0434\u043e\u0432\u0430\u043d"
    ],
    "name:deu_x_preferred":[
        "Kandovan"
    ],
    "name:fas_x_preferred":[
        "\u06a9\u0646\u062f\u0648\u0627\u0646"
    ],
    "name:fas_x_variant":[
        "Kanv\u0101n"
    ],
    "name:fra_x_preferred":[
        "Kandovan"
    ],
    "name:hye_x_preferred":[
        "\u0554\u0561\u0576\u0564\u0578\u057e\u0561\u0576"
    ],
    "name:jpn_x_preferred":[
        "\u30ab\u30f3\u30c9\u30f4\u30a1\u30f3"
    ],
    "name:mkd_x_preferred":[
        "\u041a\u0430\u043d\u0434\u043e\u0432\u0430\u043d"
    ],
    "name:rus_x_preferred":[
        "\u041a\u0430\u043d\u0434\u043e\u0432\u0430\u043d"
    ],
    "name:und_x_variant":[
        "Kandov\u0101n",
        "Kandav\u0101n",
        "Kandkh\u0101n"
    ],
    "name:vie_x_preferred":[
        "Kandovan"
    ],
    "wof:name":"Kandovan",
    "wof:placetype":"locality"
},
  "geometry": {"coordinates":[46.2487,37.7949],"type":"Point"}
}