{
  "type": "Feature",
  "properties": {
    "gn:admin1_code":"33",
    "gn:asciiname":"Kandovan",
    "gn:country_code":"IR",
    "gn:dem":2224,
    "gn:feature_class":"P",
    "gn:feature_code":"PPL",
    "gn:name":"Kandov\u0101n",
    "gn:population":0,
    "gn:timezone":"Asia/Tehran",
    "iso:country":"IR",
    "name:fas_x_preferred":[
        "\u06a9\u0646\u062f\u0648\u0627\u0646"
    ],
    "name:fas_x_variant":[
        "Kanv\u0101n"
    ],
    "name:und_x_variant":[
        "Kandov\u0101n",
        "Kandav\u0101n",
        "Kandkh\u0101n"
    ],
    "wof:name":"Kandovan",
    "wof:placetype":"locality"
},
  "geometry": {"coordinates":[46.2487,37.7949],"type":"Point"}
}