{
  "type": "Feature",
  "properties": {
    "gn:admin1_code":"11.0",
    "gn:asciiname":"Pazard",
    "gn:country_code":"IR",
    "gn:dem":22,
    "gn:feature_class":"P",
    "gn:feature_code":"PPL",
    "gn:name":"P\u0101zard",
    "gn:population":0,
    "gn:timezone":"Asia/Tehran",
    "iso:country":"IR",
    "name:fas_x_preferred":[
        "\u067e\u0627\u0632\u0631\u062f"
    ],
    "name:fas_x_variant":[
        "Kang\u0101n-e Na\u015fr\u012b",
        "\u06a9\u0646\u06af\u0627\u0646 \u0646\u0635\u0631\u06cc",
        "P\u0101zard"
    ],
    "name:msa_x_preferred":[
        "Pazard"
    ],
    "wof:name":"Pazard",
    "wof:placetype":"locality"
},
  "geometry": {"coordinates":[57.4891,25.8586],"type":"Point"}
}