{
  "type": "Feature",
  "properties": {
    "gn:admin1_code":"32",
    "gn:asciiname":"Owch Darreh",
    "gn:country_code":"IR",
    "gn:dem":639,
    "gn:feature_class":"P",
    "gn:feature_code":"PPL",
    "gn:name":"Owch Darreh",
    "gn:population":0,
    "gn:timezone":"Asia/Tehran",
    "iso:country":"IR",
    "name:fas_x_preferred":[
        "\u0648\u0686 \u062f\u064e\u0631\u064e\u0642"
    ],
    "name:fas_x_variant":[
        "\u0627\u0648\u0686 \u062f\u0631\u0647",
        "\u016ach Daraq",
        "\u0648\u0686 \u062f\u064e\u0631\u0650\u0651\u0647"
    ],
    "name:und_x_variant":[
        "\u016ach Darreh",
        "Owch Darreh"
    ],
    "wof:name":"Owch Darreh",
    "wof:placetype":"locality"
},
  "geometry": {"coordinates":[48.0667,39.212],"type":"Point"}
}