{
  "type": "Feature",
  "properties": {
    "gn:admin1_code":"10.0",
    "gn:asciiname":"Shalibeh Sarkheh",
    "gn:country_code":"IR",
    "gn:dem":262,
    "gn:feature_class":"P",
    "gn:feature_code":"PPL",
    "gn:name":"Shal\u012bbeh Sarkheh",
    "gn:population":0,
    "gn:timezone":"Asia/Tehran",
    "iso:country":"IR",
    "name:fas_x_preferred":[
        "Shal\u012bbeh Sarkheh"
    ],
    "name:fas_x_variant":[
        "\u0634\u064e\u0644\u064a\u0628\u0650\u0647 \u0633\u064e\u0631\u062e\u0650\u0647"
    ],
    "wof:name":"Shalibeh Sarkheh",
    "wof:placetype":"locality"
},
  "geometry": {"coordinates":[47.98333,32.45],"type":"Point"}
}