{
  "type": "Feature",
  "properties": {
    "gn:admin1_code":"7",
    "gn:asciiname":"Bondareh",
    "gn:country_code":"IR",
    "gn:dem":1374,
    "gn:feature_class":"P",
    "gn:feature_code":"PPL",
    "gn:name":"Bondareh",
    "gn:population":0,
    "gn:timezone":"Asia/Tehran",
    "iso:country":"IR",
    "name:fas_x_preferred":[
        "\u0628\u0646 \u062f\u0631\u0651\u0647"
    ],
    "name:fas_x_variant":[
        "\u0628\u0646\u062f\u0631\u0647"
    ],
    "name:und_x_variant":[
        "Bon Darreh",
        "Bondareh"
    ],
    "wof:name":"Bondareh",
    "wof:placetype":"locality"
},
  "geometry": {"coordinates":[51.46986,30.36887],"type":"Point"}
}