{
  "type": "Feature",
  "properties": {
    "gn:admin1_code":"42.0",
    "gn:asciiname":"Kalateh-ye Hajj Molla",
    "gn:country_code":"IR",
    "gn:dem":1161,
    "gn:feature_class":"P",
    "gn:feature_code":"PPL",
    "gn:name":"Kal\u0101teh-ye \u1e28\u0101jj Moll\u0101",
    "gn:population":0,
    "gn:timezone":"Asia/Tehran",
    "iso:country":"IR",
    "name:fas_x_preferred":[
        "Kal\u0101teh-ye \u1e28\u0101jj Moll\u0101"
    ],
    "name:fas_x_variant":[
        "\u06a9\u0644\u0627\u062a\u0647 \u062d\u0627\u062c \u0645\u0644\u0627"
    ],
    "wof:name":"Kalateh-ye Hajj Molla",
    "wof:placetype":"locality"
},
  "geometry": {"coordinates":[58.34148,36.09416],"type":"Point"}
}