{
  "type": "Feature",
  "properties": {
    "gn:admin1_code":"4.0",
    "gn:asciiname":"Gazdivan",
    "gn:country_code":"IR",
    "gn:dem":1247,
    "gn:feature_class":"P",
    "gn:feature_code":"PPL",
    "gn:name":"Gazd\u012bv\u0101n",
    "gn:population":0,
    "gn:timezone":"Asia/Tehran",
    "iso:country":"IR",
    "name:fas_x_preferred":[
        "Gazd\u012bv\u0101n"
    ],
    "name:fas_x_variant":[
        "\u06af\u0632\u062f\u06cc\u0648\u0627\u0646"
    ],
    "wof:name":"Gazdivan",
    "wof:placetype":"locality"
},
  "geometry": {"coordinates":[60.75,27.86667000000001],"type":"Point"}
}