{
  "type": "Feature",
  "properties": {
    "gn:admin1_code":"4.0",
    "gn:asciiname":"Kalateh-ye `Omar",
    "gn:country_code":"IR",
    "gn:dem":1218,
    "gn:feature_class":"P",
    "gn:feature_code":"PPL",
    "gn:name":"Kal\u0101teh-ye \u2018Omar",
    "gn:population":0,
    "gn:timezone":"Asia/Tehran",
    "iso:country":"IR",
    "name:fas_x_preferred":[
        "\u06a9\u0644\u0627\u062a\u0647 \u0639\u0645\u0631"
    ],
    "name:fas_x_variant":[
        "Kal\u0101teh-ye \u2018Omar"
    ],
    "wof:name":"Kalateh-ye `Omar",
    "wof:placetype":"locality"
},
  "geometry": {"coordinates":[60.5484,30.7328],"type":"Point"}
}