{
  "type": "Feature",
  "properties": {
    "gn:admin1_code":"4.0",
    "gn:asciiname":"Deh-e Khaderi",
    "gn:country_code":"IR",
    "gn:dem":484,
    "gn:feature_class":"P",
    "gn:feature_code":"PPL",
    "gn:name":"Deh-e Khader\u012b",
    "gn:population":0,
    "gn:timezone":"Asia/Tehran",
    "iso:country":"IR",
    "name:fas_x_preferred":[
        "Deh-e Khader\u012b"
    ],
    "name:fas_x_variant":[
        "\u062f\u0647 \u062e\u062f\u0631\u06cc"
    ],
    "wof:name":"Deh-e Khaderi",
    "wof:placetype":"locality"
},
  "geometry": {"coordinates":[61.7865,31.0965],"type":"Point"}
}