{
  "type": "Feature",
  "properties": {
    "gn:admin1_code":"39.0",
    "gn:asciiname":"Shahrak-e Qods",
    "gn:country_code":"IR",
    "gn:dem":984,
    "gn:feature_class":"P",
    "gn:feature_code":"PPL",
    "gn:name":"Shahrak-e Qods",
    "gn:population":0,
    "gn:timezone":"Asia/Tehran",
    "iso:country":"IR",
    "name:fas_x_preferred":[
        "\u0634\u0647\u0631\u06a9 \u0642\u062f\u0633"
    ],
    "wof:name":"Shahrak-e Qods",
    "wof:placetype":"locality"
},
  "geometry": {"coordinates":[50.83382,34.60193],"type":"Point"}
}