{
  "type": "Feature",
  "properties": {
    "gn:admin1_code":"44",
    "gn:asciiname":"Qeshlaq-e Mohammadlu",
    "gn:country_code":"IR",
    "gn:dem":1183,
    "gn:feature_class":"P",
    "gn:feature_code":"PPL",
    "gn:name":"Qeshl\u0101q-e Mo\u1e29ammadl\u016b",
    "gn:population":0,
    "gn:timezone":"Asia/Tehran",
    "iso:country":"IR",
    "name:fas_x_preferred":[
        "\u0642\u0650\u0634\u0644\u0627\u0642\u0650 \u0645\u064f\u062d\u064e\u0645\u064e\u0651\u062f\u06cc"
    ],
    "name:fas_x_variant":[
        "\u0642\u0650\u0634\u0644\u0627\u0642\u0650 \u0645\u064f\u062d\u064e\u0645\u064e\u0651\u062f \u0639\u064e\u0644\u06cc",
        "\u0642\u0634\u0644\u0627\u0642 \u0645\u062d\u0645\u0651\u062f\u0644\u0648",
        "Qeshl\u0101q-e Mo\u1e29ammad\u012b",
        "Qeshl\u0101q-e Mo\u1e29ammadl\u016b"
    ],
    "name:und_x_variant":[
        "Qishl\u0101q Muhammad \u2018Ali",
        "Qeshl\u0101q-e Mo\u1e29ammad \u2018Al\u012b"
    ],
    "wof:name":"Qeshlaq-e Mohammadlu",
    "wof:placetype":"locality"
},
  "geometry": {"coordinates":[50.5279,35.7997],"type":"Point"}
}