{
  "type": "Feature",
  "properties": {
    "gn:admin1_code":"29",
    "gn:asciiname":"Jushir",
    "gn:country_code":"IR",
    "gn:dem":2604,
    "gn:feature_class":"P",
    "gn:feature_code":"PPL",
    "gn:name":"J\u016bsh\u012br",
    "gn:population":0,
    "gn:timezone":"Asia/Tehran",
    "iso:country":"IR",
    "name:fas_x_preferred":[
        "J\u016bsh\u012br"
    ],
    "wof:name":"Jushir",
    "wof:placetype":"locality"
},
  "geometry": {"coordinates":[56.63333000000001,29.38333],"type":"Point"}
}