{
  "type": "Feature",
  "properties": {
    "gn:admin1_code":"42.0",
    "gn:asciiname":"Cheshmeh Sar",
    "gn:country_code":"IR",
    "gn:dem":2174,
    "gn:feature_class":"P",
    "gn:feature_code":"PPL",
    "gn:name":"Cheshmeh S\u0101r",
    "gn:population":0,
    "gn:timezone":"Asia/Tehran",
    "iso:country":"IR",
    "name:fas_x_preferred":[
        "Cheshmeh S\u0101r"
    ],
    "name:fas_x_variant":[
        "\u0686\u0634\u0645\u0647\u200c\u0633\u0631"
    ],
    "name:mzn_x_preferred":[
        "\u0686\u0634\u0645\u0647\u200c\u0633\u0631"
    ],
    "wof:name":"Cheshmeh Sar",
    "wof:placetype":"locality"
},
  "geometry": {"coordinates":[57.01667,36.53278],"type":"Point"}
}