{
  "type": "Feature",
  "properties": {
    "gn:admin1_code":"4.0",
    "gn:asciiname":"Chokat",
    "gn:cc2":"IR",
    "gn:country_code":"IR",
    "gn:dem":36,
    "gn:feature_class":"P",
    "gn:feature_code":"PPL",
    "gn:name":"Chokat",
    "gn:population":0,
    "gn:timezone":"Asia/Tehran",
    "iso:country":"IR",
    "name:und_x_variant":[
        "Ch\u016bk\u0101t Dard",
        "Chauk\u0101t",
        "Chuk\u0101t",
        "Ch\u016bg\u0101t",
        "Chokat"
    ],
    "wof:name":"Chokat",
    "wof:placetype":"locality"
},
  "geometry": {"coordinates":[61.05611,25.60806],"type":"Point"}
}