{
  "type": "Feature",
  "properties": {
    "gn:admin1_code":"4.0",
    "gn:asciiname":"Gaze'i",
    "gn:country_code":"IR",
    "gn:dem":50,
    "gn:feature_class":"P",
    "gn:feature_code":"PPL",
    "gn:name":"Gaze\u2019\u012b",
    "gn:population":0,
    "gn:timezone":"Asia/Tehran",
    "iso:country":"IR",
    "name:fas_x_preferred":[
        "Gaze\u2019\u012b"
    ],
    "name:und_x_variant":[
        "Gazeh\u012b",
        "Gaz\u0101n\u012b",
        "Gaz\u2019\u012b"
    ],
    "wof:name":"Gaze'i",
    "wof:placetype":"locality"
},
  "geometry": {"coordinates":[60.96556,25.80639],"type":"Point"}
}