{
  "type": "Feature",
  "properties": {
    "gn:admin1_code":"7",
    "gn:asciiname":"Ab Chenaru",
    "gn:country_code":"IR",
    "gn:dem":1066,
    "gn:feature_class":"P",
    "gn:feature_code":"PPL",
    "gn:name":"\u0100b Chen\u0101r\u016b",
    "gn:population":0,
    "gn:timezone":"Asia/Tehran",
    "iso:country":"IR",
    "name:fas_x_preferred":[
        "\u0622\u0628 \u0686\u0646\u0627\u0631\u0648"
    ],
    "name:fas_x_variant":[
        "\u0100b Chen\u0101r",
        "\u0100b Chen\u0101r\u016b"
    ],
    "wof:name":"Ab Chenaru",
    "wof:placetype":"locality"
},
  "geometry": {"coordinates":[52.6149,28.5541],"type":"Point"}
}