{
  "type": "Feature",
  "properties": {
    "gn:admin1_code":"7",
    "gn:asciiname":"Mahalleh-ye Kal Mohseni",
    "gn:country_code":"IR",
    "gn:dem":407,
    "gn:feature_class":"P",
    "gn:feature_code":"PPL",
    "gn:name":"Ma\u1e29alleh-ye Kal Mo\u1e29sen\u012b",
    "gn:population":0,
    "gn:timezone":"Asia/Tehran",
    "iso:country":"IR",
    "name:fas_x_preferred":[
        "\u06a9\u0644 \u0645\u062d\u0633\u0646\u06cc"
    ],
    "name:fas_x_variant":[
        "Kal Mo\u1e29sen\u012b",
        "\u0645\u062d\u0644\u0647 \u06a9\u0644 \u0645\u062d\u0633\u0646\u06cc",
        "\u06a9\u0631\u0628\u0644\u0627\u0626\u06cc \u0645\u062d\u0633\u0646\u06cc"
    ],
    "name:und_x_variant":[
        "Ma\u1e29alleh-ye Kal Mo\u1e29sen\u012b",
        "Karbal\u0101\u2019\u012b Mo\u1e29sen\u012b"
    ],
    "wof:name":"Mahalleh-ye Kal Mohseni",
    "wof:placetype":"locality"
},
  "geometry": {"coordinates":[53.2354,27.333],"type":"Point"}
}