{
  "type": "Feature",
  "properties": {
    "gn:admin1_code":"23",
    "gn:asciiname":"Chal Kal-e `Olya",
    "gn:country_code":"IR",
    "gn:dem":704,
    "gn:feature_class":"P",
    "gn:feature_code":"PPL",
    "gn:name":"Ch\u0101l Kal-e \u2018Oly\u0101",
    "gn:population":0,
    "gn:timezone":"Asia/Tehran",
    "iso:country":"IR",
    "name:fas_x_preferred":[
        "\u0686\u0627\u0644 \u062e\u0627\u0644"
    ],
    "name:fas_x_variant":[
        "\u0686\u0627\u0644 \u06af\u064e\u0644\u0650 \u0639\u064f\u0644\u064a\u0627",
        "Ch\u0101l Kal-e \u2018Oly\u0101",
        "Ch\u0101lkal-e \u2018Oly\u0101",
        "\u0686\u0627\u0644 \u06a9\u0644 \u0639\u0644\u06cc\u0627"
    ],
    "name:und_x_variant":[
        "Ch\u0101l Kh\u0101l",
        "Ch\u0101l Gal-e \u2018Oly\u0101"
    ],
    "wof:name":"Chal Kal-e `Olya",
    "wof:placetype":"locality"
},
  "geometry": {"coordinates":[47.7958,33.0652],"type":"Point"}
}