{
  "type": "Feature",
  "properties": {
    "gn:admin1_code":"1",
    "gn:asciiname":"Nestan",
    "gn:country_code":"IR",
    "gn:dem":1420,
    "gn:feature_class":"P",
    "gn:feature_code":"PPL",
    "gn:name":"Nest\u0101n",
    "gn:population":0,
    "gn:timezone":"Asia/Tehran",
    "iso:country":"IR",
    "name:azb_x_preferred":[
        "\u0646\u0633\u062a\u0627\u0646"
    ],
    "name:ceb_x_preferred":[
        "Nest\u0101n"
    ],
    "name:ckb_x_preferred":[
        "\u0646\u0633\u062a\u0627\u0646"
    ],
    "name:fas_x_preferred":[
        "\u0646\u064a\u0633\u062a\u0627\u0646"
    ],
    "name:fas_x_variant":[
        "\u0646\u0650\u064a\u0650\u0633\u062a\u0627\u0646",
        "\u0646\u0633\u062a\u0627\u0646",
        "Neyest\u0101n",
        "Nest\u0101n",
        "\u0646\u0650\u0633\u062a\u0627\u0646"
    ],
    "name:kur_x_preferred":[
        "Nistan"
    ],
    "name:msa_x_preferred":[
        "Nestan"
    ],
    "name:swe_x_preferred":[
        "Nest\u0101n"
    ],
    "name:und_x_variant":[
        "N\u012bst\u0101n"
    ],
    "wof:name":"Nestan",
    "wof:placetype":"locality"
},
  "geometry": {"coordinates":[45.6302,36.2839],"type":"Point"}
}