{
  "type": "Feature",
  "properties": {
    "gn:admin1_code":"15",
    "gn:asciiname":"Jiri-ye Sofla",
    "gn:country_code":"IR",
    "gn:dem":13,
    "gn:feature_class":"P",
    "gn:feature_code":"PPL",
    "gn:name":"J\u012br\u012b-ye Sofl\u00e1",
    "gn:population":0,
    "gn:timezone":"Asia/Tehran",
    "iso:country":"IR",
    "name:ceb_x_preferred":[
        "J\u012br\u012b-ye Sofl\u00e1"
    ],
    "name:fas_x_preferred":[
        "\u062c\u06cc\u0631\u06cc \u0633\u0641\u0644\u06cc"
    ],
    "name:fas_x_variant":[
        "J\u012br\u012b-ye Sofl\u00e1"
    ],
    "name:swe_x_preferred":[
        "J\u012br\u012b-ye Sofl\u00e1"
    ],
    "wof:name":"Jiri-ye Sofla",
    "wof:placetype":"locality"
},
  "geometry": {"coordinates":[49.7118,30.4261],"type":"Point"}
}