{
  "type": "Feature",
  "properties": {
    "gn:admin1_code":"13",
    "gn:asciiname":"Mulanabad",
    "gn:country_code":"IR",
    "gn:dem":1728,
    "gn:feature_class":"P",
    "gn:feature_code":"PPL",
    "gn:name":"M\u016bl\u0101n\u0101b\u0101d",
    "gn:population":0,
    "gn:timezone":"Asia/Tehran",
    "iso:country":"IR",
    "name:fas_x_preferred":[
        "\u0645\u0648\u0644\u0627\u0646 \u0622\u0628\u0627\u062f"
    ],
    "name:fas_x_variant":[
        "M\u016bl\u0101n\u0101b\u0101d"
    ],
    "wof:name":"Mulanabad",
    "wof:placetype":"locality"
},
  "geometry": {"coordinates":[47.3716,34.8572],"type":"Point"}
}