{
  "type": "Feature",
  "properties": {
    "gn:admin1_code":"5.0",
    "gn:asciiname":"Chal Baniu",
    "gn:country_code":"IR",
    "gn:dem":2143,
    "gn:feature_class":"P",
    "gn:feature_code":"PPL",
    "gn:name":"Ch\u0101l Ban\u012b\u016b",
    "gn:population":0,
    "gn:timezone":"Asia/Tehran",
    "iso:country":"IR",
    "name:fas_x_preferred":[
        "\u0686\u0627\u0644 \u0628\u0646\u06cc\u0648"
    ],
    "name:und_x_variant":[
        "Ch\u0101l Ban\u012b\u016b"
    ],
    "wof:name":"Chal Baniu",
    "wof:placetype":"locality"
},
  "geometry": {"coordinates":[51.55838,30.52263],"type":"Point"}
}