{
  "type": "Feature",
  "properties": {
    "gn:admin1_code":"23",
    "gn:asciiname":"Titkan",
    "gn:country_code":"IR",
    "gn:dem":1443,
    "gn:feature_class":"P",
    "gn:feature_code":"PPL",
    "gn:name":"T\u012btk\u0101n",
    "gn:population":0,
    "gn:timezone":"Asia/Tehran",
    "iso:country":"IR",
    "name:ara_x_preferred":[
        "\u062a\u064a\u062a\u06a9\u0627\u0646"
    ],
    "name:ceb_x_preferred":[
        "T\u012btkan"
    ],
    "name:fas_x_preferred":[
        "\u067e\u064e\u0632\u0646\u064e\u0648\u064a\u062f"
    ],
    "name:fas_x_variant":[
        "Baznav\u012bd",
        "\u0628\u0632\u0646\u0648\u064a\u062f",
        "\u062a\u06cc\u062a\u06a9\u0627\u0646",
        "\u062a\u064a\u062a\u064e\u0643",
        "\u062a\u064a\u062a\u064e\u0643\u064e\u0646",
        "\u062a\u064a\u062a\u0643\u064e\u0646"
    ],
    "name:swe_x_preferred":[
        "T\u012btkan"
    ],
    "name:und_x_variant":[
        "Paznav\u012bd",
        "T\u012btk\u0101n",
        "T\u012btakan",
        "T\u012btak"
    ],
    "wof:name":"Titkan",
    "wof:placetype":"locality"
},
  "geometry": {"coordinates":[49.64252000000001,32.89735],"type":"Point"}
}