{
  "type": "Feature",
  "properties": {
    "gn:admin1_code":"28.0",
    "gn:asciiname":"Garafshan",
    "gn:country_code":"IR",
    "gn:dem":1635,
    "gn:feature_class":"P",
    "gn:feature_code":"PPL",
    "gn:name":"Gar\u0101fsh\u0101n",
    "gn:population":0,
    "gn:timezone":"Asia/Tehran",
    "iso:country":"IR",
    "name:fas_x_preferred":[
        "Gar\u0101fsh\u0101n"
    ],
    "name:fas_x_variant":[
        "Karafsh\u0101n",
        "\u06af\u0631\u0627\u0641\u0634\u0627\u0646"
    ],
    "name:und_x_variant":[
        "Karabsh\u0101n"
    ],
    "wof:name":"Garafshan",
    "wof:placetype":"locality"
},
  "geometry": {"coordinates":[51.55124,32.45174],"type":"Point"}
}