{
  "type": "Feature",
  "properties": {
    "gn:admin1_code":"23",
    "gn:asciiname":"Godar-e Mahmudvand",
    "gn:country_code":"IR",
    "gn:dem":1007,
    "gn:feature_class":"P",
    "gn:feature_code":"PPL",
    "gn:name":"God\u0101r-e Ma\u1e29m\u016bdvand",
    "gn:population":0,
    "gn:timezone":"Asia/Tehran",
    "iso:country":"IR",
    "name:fas_x_preferred":[
        "\u0645\u064e\u062d\u0645\u0648\u062f\u0648\u064e\u0646\u062f"
    ],
    "name:fas_x_variant":[
        "God\u0101r-e Ma\u1e29m\u016bd",
        "Ma\u1e29m\u016bdvand",
        "\u06af\u062f\u0627\u0631 \u0645\u062d\u0645\u0648\u062f",
        "\u06af\u062f\u0627\u0631 \u0645\u062d\u0645\u0648\u062f\u0648\u0646\u062f"
    ],
    "name:und_x_variant":[
        "God\u0101r-e Ma\u1e29m\u016bdvand",
        "\u06af\u062f\u0627\u0631 \u0645\u062d\u0645\u0648\u062f"
    ],
    "wof:name":"Godar-e Mahmudvand",
    "wof:placetype":"locality"
},
  "geometry": {"coordinates":[48.03312,33.49023],"type":"Point"}
}