{
  "type": "Feature",
  "properties": {
    "gn:admin1_code":"28",
    "gn:asciiname":"Jaq Jaq",
    "gn:cc2":"IR",
    "gn:country_code":"IR",
    "gn:dem":2587,
    "gn:feature_class":"P",
    "gn:feature_code":"PPL",
    "gn:name":"Jaq Jaq",
    "gn:population":0,
    "gn:timezone":"Asia/Tehran",
    "iso:country":"IR",
    "name:und_x_variant":[
        "Jaghjagh",
        "Jaq Jaq"
    ],
    "wof:name":"Jaq Jaq",
    "wof:placetype":"locality"
},
  "geometry": {"coordinates":[50.10389,32.87083],"type":"Point"}
}