{
  "type": "Feature",
  "properties": {
    "gn:admin1_code":"15.0",
    "gn:asciiname":"Tang-e Palangi",
    "gn:country_code":"IR",
    "gn:dem":1000,
    "gn:feature_class":"P",
    "gn:feature_code":"PPL",
    "gn:name":"Tang-e Palang\u012b",
    "gn:population":0,
    "gn:timezone":"Asia/Tehran",
    "iso:country":"IR",
    "name:fas_x_preferred":[
        "Tang-e Palang\u012b"
    ],
    "name:fas_x_variant":[
        "\u062a\u0646\u06af \u067e\u0644\u0646\u06af\u06cc"
    ],
    "name:und_x_variant":[
        "\u062a\u0646\u06af \u067e\u0644\u0646\u06af\u06cc"
    ],
    "wof:name":"Tang-e Palangi",
    "wof:placetype":"locality"
},
  "geometry": {"coordinates":[49.90293,31.69477],"type":"Point"}
}