{
  "type": "Feature",
  "properties": {
    "gn:admin1_code":"23",
    "gn:asciiname":"Lasur-e Sofla",
    "gn:country_code":"IR",
    "gn:dem":1700,
    "gn:feature_class":"P",
    "gn:feature_code":"PPL",
    "gn:name":"L\u0101s\u016br-e Sofl\u00e1",
    "gn:population":0,
    "gn:timezone":"Asia/Tehran",
    "iso:country":"IR",
    "name:fas_x_preferred":[
        "\u0633\u064a\u0631\u0647 \u0633\u0641\u0644\u0649"
    ],
    "name:fas_x_variant":[
        "S\u012breh-ye P\u0101\u2019\u012bn",
        "S\u012breh-ye Sofl\u00e1",
        "\u0644\u0627\u0633\u0648\u0631 \u0633\u0641\u0644\u06cc"
    ],
    "name:und_x_variant":[
        "L\u0101s\u016br-e Sofl\u00e1"
    ],
    "wof:name":"Lasur-e Sofla",
    "wof:placetype":"locality"
},
  "geometry": {"coordinates":[49.1624,33.41858],"type":"Point"}
}