{
  "type": "Feature",
  "properties": {
    "gn:admin1_code":"28",
    "gn:asciiname":"Shast Mahan",
    "gn:country_code":"IR",
    "gn:dem":1876,
    "gn:feature_class":"P",
    "gn:feature_code":"PPL",
    "gn:name":"Sha\u015ft M\u0101h\u0101n",
    "gn:population":0,
    "gn:timezone":"Asia/Tehran",
    "iso:country":"IR",
    "name:fas_x_preferred":[
        "\u0634\u0635\u062a \u0645\u0627\u0647\u0627\u0646"
    ],
    "name:fas_x_variant":[
        "\u0645\u064e\u0632\u0631\u064e\u0639\u0650\u06c0 \u0627\u064e\u0645\u064a\u0631 \u062e\u0627\u0646",
        "\u0645\u064e\u0632\u0631\u064e\u0639\u0650\u0647 \u0627\u064e\u0645\u064a\u0631 \u062e\u0627\u0646",
        "Sha\u015ft M\u0101h\u0101n"
    ],
    "name:und_x_variant":[
        "Mazra\u2018eh-ye Am\u012br Kh\u0101n",
        "Mazra\u2018eh Am\u012br Kh\u0101n"
    ],
    "wof:name":"Shast Mahan",
    "wof:placetype":"locality"
},
  "geometry": {"coordinates":[53.0411,32.5396],"type":"Point"}
}