{
  "type": "Feature",
  "properties": {
    "gn:admin1_code":"42",
    "gn:asciiname":"Mast `Ali",
    "gn:country_code":"IR",
    "gn:dem":1653,
    "gn:feature_class":"P",
    "gn:feature_code":"PPL",
    "gn:name":"Mast \u2018Al\u012b",
    "gn:population":0,
    "gn:timezone":"Asia/Tehran",
    "iso:country":"IR",
    "name:fas_x_preferred":[
        "\u0645\u0633\u062a \u0639\u0644\u06cc"
    ],
    "name:fas_x_variant":[
        "Mast \u2018Al\u012b",
        "\u0645\u0633\u062a\u200c\u0639\u0644\u06cc"
    ],
    "wof:name":"Mast `Ali",
    "wof:placetype":"locality"
},
  "geometry": {"coordinates":[59.274,35.58294],"type":"Point"}
}