{
  "type": "Feature",
  "properties": {
    "gn:admin1_code":"37",
    "gn:asciiname":"Parsah Su",
    "gn:country_code":"IR",
    "gn:dem":161,
    "gn:feature_class":"P",
    "gn:feature_code":"PPL",
    "gn:name":"Parsah S\u016b",
    "gn:population":0,
    "gn:timezone":"Asia/Tehran",
    "iso:country":"IR",
    "name:ceb_x_preferred":[
        "Sh\u0101h\u0101b\u0101d-e Parsah S\u016b"
    ],
    "name:fas_x_preferred":[
        "Sh\u0101h\u0101b\u0101d-e Parsah S\u016b"
    ],
    "name:fas_x_variant":[
        "Parsah S\u016b",
        "\u0634\u0627\u0647 \u0622\u0628\u0627\u062f \u067e\u0631\u0633\u0647 \u0633\u0648",
        "\u067e\u0631\u0633\u0647 \u0633\u0648",
        "\u067e\u0631\u0633\u0647\u200c\u0633\u0648"
    ],
    "name:msa_x_preferred":[
        "Parsah Su"
    ],
    "name:swe_x_preferred":[
        "Sh\u0101h\u0101b\u0101d-e Parsah S\u016b"
    ],
    "name:und_x_variant":[
        "Porsesu",
        "Por S\u016bs\u016b",
        "\u0634\u0627\u0647 \u0622\u0628\u0627\u062f \u067e\u0631\u0633\u0647 \u0633\u0648"
    ],
    "wof:name":"Parsah Su",
    "wof:placetype":"locality"
},
  "geometry": {"coordinates":[55.39358000000001,37.24891],"type":"Point"}
}