{
  "type": "Feature",
  "properties": {
    "iso:country":"IR",
    "name:ara_x_preferred":[
        "\u062c\u0648\u0627\u0646\u0631\u0648\u062f"
    ],
    "name:aze_x_preferred":[
        "Cavanrud"
    ],
    "name:cat_x_preferred":[
        "Javanrud"
    ],
    "name:ckb_x_preferred":[
        "\u062c\u0648\u0627\u0646\u0695\u06c6"
    ],
    "name:eng_x_preferred":[
        "Javanrud"
    ],
    "name:fas_x_preferred":[
        "\u062c\u0648\u0627\u0646\u0631\u0648\u062f"
    ],
    "name:fra_x_preferred":[
        "Javanroud"
    ],
    "name:ita_x_preferred":[
        "Javanrud"
    ],
    "name:kur_x_preferred":[
        "Ciwanro"
    ],
    "name:mlg_x_preferred":[
        "Javanrud"
    ],
    "name:nld_x_preferred":[
        "Javanrud"
    ],
    "name:pnb_x_preferred":[
        "\u062c\u0648\u0627\u0646\u0631\u0648\u062f"
    ],
    "name:ron_x_preferred":[
        "Javanroud"
    ],
    "name:ron_x_variant":[
        "Akbarabad"
    ],
    "name:rus_x_preferred":[
        "\u0414\u0436\u0430\u0432\u0430\u043d\u0440\u0443\u0434"
    ],
    "name:spa_x_preferred":[
        "Yavanrud"
    ],
    "name:spa_x_variant":[
        "Javanrood"
    ],
    "name:tgk_x_preferred":[
        "\u04b6\u0430\u0432\u043e\u043d\u0440\u04ef\u0434"
    ],
    "name:tur_x_preferred":[
        "Cevanrud"
    ],
    "name:unk_x_variant":[
        "Qal`a J\u016banr\u016bd"
    ],
    "name:urd_x_preferred":[
        "\u062c\u0648\u0627\u0646\u0631\u0648\u062f"
    ],
    "name:urd_x_variant":[
        "\u062c\u0627\u0648\u0627\u0646\u0631\u0648\u062f"
    ],
    "qs:gn_country":"IR",
    "qs:gn_fcode":"PPL",
    "qs:gn_pop":38657,
    "qs:name":"Javanrud",
    "qs:name_adm0":"Iran",
    "qs:name_adm1":"Kermanshah",
    "qs:photos":0,
    "qs:photos_1k":0,
    "qs:photos_9k":0,
    "qs:photos_9r":0,
    "qs:photos_all":0,
    "qs:photos_sr":0,
    "qs:placetype":"Town",
    "qs:pop_sr":"7",
    "qs:woe_adm0":23424851,
    "wd:wordcount":130,
    "wof:name":"Javanrud",
    "wof:placetype":"locality",
    "wof:population":38657
},
  "geometry": {"coordinates":[46.51722,34.79611],"type":"Point"}
}