{
  "type": "Feature",
  "properties": {
    "gn:admin1_code":"8.0",
    "gn:asciiname":"Shirin Anareh",
    "gn:country_code":"IR",
    "gn:dem":176,
    "gn:feature_class":"P",
    "gn:feature_code":"PPL",
    "gn:name":"Sh\u012br\u012bn An\u0101reh",
    "gn:population":0,
    "gn:timezone":"Asia/Tehran",
    "iso:country":"IR",
    "name:fas_x_preferred":[
        "Sh\u012br\u012bn An\u0101reh"
    ],
    "wof:name":"Shirin Anareh",
    "wof:placetype":"locality"
},
  "geometry": {"coordinates":[49.71222,37.0475],"type":"Point"}
}