{
  "type": "Feature",
  "properties": {
    "gn:admin1_code":"13",
    "gn:asciiname":"Azreh-ye Mohammad Khan",
    "gn:country_code":"IR",
    "gn:dem":1422,
    "gn:feature_class":"P",
    "gn:feature_code":"PPL",
    "gn:name":"Azreh-ye Mo\u1e29ammad Kh\u0101n",
    "gn:population":0,
    "gn:timezone":"Asia/Tehran",
    "iso:country":"IR",
    "name:fas_x_preferred":[
        "Azreh-ye Mo\u1e29ammad Kh\u0101n"
    ],
    "wof:name":"Azreh-ye Mohammad Khan",
    "wof:placetype":"locality"
},
  "geometry": {"coordinates":[46.81667,34.41667],"type":"Point"}
}