{
  "type": "Feature",
  "properties": {
    "gn:admin1_code":"43",
    "gn:asciiname":"Tuqqeh Chenar",
    "gn:country_code":"IR",
    "gn:dem":721,
    "gn:feature_class":"P",
    "gn:feature_code":"PPL",
    "gn:name":"\u0162\u016bqqeh Chen\u0101r",
    "gn:population":0,
    "gn:timezone":"Asia/Tehran",
    "iso:country":"IR",
    "name:fas_x_preferred":[
        "Toqqeh Chen\u0101r"
    ],
    "name:fas_x_variant":[
        "\u0637\u0648\u0642\u0647 \u0686\u0646\u0627\u0631",
        "\u0162\u016bqqeh Chen\u0101r"
    ],
    "name:und_x_variant":[
        "\u0162\u016bqqeh Chen\u0101r",
        "\u0637\u0648\u0642\u0647 \u0686\u0646\u0627\u0631"
    ],
    "wof:name":"Tuqqeh Chenar",
    "wof:placetype":"locality"
},
  "geometry": {"coordinates":[57.11103000000001,37.71982],"type":"Point"}
}