{
  "type": "Feature",
  "properties": {
    "gn:admin1_code":"34",
    "gn:asciiname":"Kheyrabad",
    "gn:country_code":"IR",
    "gn:dem":1680,
    "gn:feature_class":"P",
    "gn:feature_code":"PPL",
    "gn:name":"Kheyr\u0101b\u0101d",
    "gn:population":0,
    "gn:timezone":"Asia/Tehran",
    "iso:country":"IR",
    "name:aze_x_preferred":[
        "Xeyrabad"
    ],
    "name:fas_x_preferred":[
        "\u062e\u064e\u064a\u0631 \u0622\u0628\u0627\u062f"
    ],
    "name:fas_x_variant":[
        "Kheyr\u0101b\u0101d",
        "\u062e\u064a\u0631 \u0622\u0628\u0627\u062f",
        "\u062e\u06cc\u0631\u0622\u0628\u0627\u062f"
    ],
    "name:und_x_variant":[
        "Kha\u012br\u0101b\u0101d",
        "\u062e\u064a\u0631 \u0622\u0628\u0627\u062f"
    ],
    "wof:name":"Kheyrabad",
    "wof:placetype":"locality"
},
  "geometry": {"coordinates":[50.00966,34.13953],"type":"Point"}
}