{
  "type": "Feature",
  "properties": {
    "gn:admin1_code":"13",
    "gn:asciiname":"Kal Godar",
    "gn:country_code":"IR",
    "gn:dem":1868,
    "gn:feature_class":"P",
    "gn:feature_code":"PPL",
    "gn:name":"Kal God\u0101r",
    "gn:population":0,
    "gn:timezone":"Asia/Tehran",
    "iso:country":"IR",
    "name:fas_x_preferred":[
        "\u06a9\u0644 \u06af\u062f\u0627\u0631"
    ],
    "name:fas_x_variant":[
        "Kal God\u0101r",
        "\u06a9\u0644\u200c\u06af\u062f\u0627\u0631"
    ],
    "wof:name":"Kal Godar",
    "wof:placetype":"locality"
},
  "geometry": {"coordinates":[47.72258,34.60807],"type":"Point"}
}