{
  "type": "Feature",
  "properties": {
    "gn:admin1_code":"1",
    "gn:asciiname":"Zanjireh",
    "gn:country_code":"IR",
    "gn:dem":1545,
    "gn:feature_class":"P",
    "gn:feature_code":"PPL",
    "gn:name":"Zanj\u012breh",
    "gn:population":0,
    "gn:timezone":"Asia/Tehran",
    "iso:country":"IR",
    "name:fas_x_preferred":[
        "\u0632\u064e\u0646\u062c\u064a\u0631\u0650\u0647"
    ],
    "name:fas_x_variant":[
        "\u0632\u0646\u062c\u06cc\u0631\u0647",
        "Zanj\u012breh"
    ],
    "wof:name":"Zanjireh",
    "wof:placetype":"locality"
},
  "geometry": {"coordinates":[44.8602,38.9959],"type":"Point"}
}