{
  "type": "Feature",
  "properties": {
    "gn:admin1_code":"8.0",
    "gn:asciiname":"Barz`alam",
    "gn:country_code":"IR",
    "gn:dem":16,
    "gn:feature_class":"P",
    "gn:feature_code":"PPL",
    "gn:name":"Barz\u2018\u0101lam",
    "gn:population":0,
    "gn:timezone":"Asia/Tehran",
    "iso:country":"IR",
    "name:fas_x_preferred":[
        "\u0628\u0631\u0632\u0639\u0627\u0644\u0645"
    ],
    "name:fas_x_variant":[
        "\u0628\u0648\u0632\u0639\u0627\u0644\u0645"
    ],
    "name:und_x_variant":[
        "Barz\u2018\u0101lam",
        "B\u016bz\u2018\u0101lam"
    ],
    "wof:name":"Barz`alam",
    "wof:placetype":"locality"
},
  "geometry": {"coordinates":[49.93923,37.16978],"type":"Point"}
}