{
  "type": "Feature",
  "properties": {
    "gn:admin1_code":"5",
    "gn:asciiname":"Darreh Darreh",
    "gn:country_code":"IR",
    "gn:dem":825,
    "gn:feature_class":"P",
    "gn:feature_code":"PPL",
    "gn:name":"Darreh Darreh",
    "gn:population":0,
    "gn:timezone":"Asia/Tehran",
    "iso:country":"IR",
    "name:fas_x_preferred":[
        "\u062f\u064e\u0631\u0650\u0651\u0647 \u062f\u064e\u0631\u0650\u0651\u0647"
    ],
    "wof:name":"Darreh Darreh",
    "wof:placetype":"locality"
},
  "geometry": {"coordinates":[51.18861,30.25389],"type":"Point"}
}