{
  "type": "Feature",
  "properties": {
    "gn:admin1_code":"4.0",
    "gn:asciiname":"Lechvi",
    "gn:country_code":"IR",
    "gn:dem":485,
    "gn:feature_class":"P",
    "gn:feature_code":"PPL",
    "gn:name":"Lechv\u012b",
    "gn:population":0,
    "gn:timezone":"Asia/Tehran",
    "iso:country":"IR",
    "name:fas_x_preferred":[
        "\u0644\u0686\u0648\u06cc"
    ],
    "name:fas_x_variant":[
        "Lechv\u012b"
    ],
    "wof:name":"Lechvi",
    "wof:placetype":"locality"
},
  "geometry": {"coordinates":[61.5862,30.9092],"type":"Point"}
}