{
  "type": "Feature",
  "properties": {
    "gn:admin1_code":"42.0",
    "gn:asciiname":"Gholamreza Nami",
    "gn:country_code":"IR",
    "gn:dem":348,
    "gn:feature_class":"P",
    "gn:feature_code":"PPL",
    "gn:name":"Ghol\u0101mre\u1e95\u0101 N\u0101m\u012b",
    "gn:population":0,
    "gn:timezone":"Asia/Tehran",
    "iso:country":"IR",
    "name:fas_x_preferred":[
        "Ghol\u0101mre\u1e95\u0101 N\u0101m\u012b"
    ],
    "wof:name":"Gholamreza Nami",
    "wof:placetype":"locality"
},
  "geometry": {"coordinates":[60.98333,36.41667],"type":"Point"}
}