{
  "type": "Feature",
  "properties": {
    "gn:admin1_code":"16.0",
    "gn:asciiname":"Mohammad `Aliabad",
    "gn:country_code":"IR",
    "gn:dem":1586,
    "gn:elevation":"0.0",
    "gn:feature_class":"P",
    "gn:feature_code":"PPL",
    "gn:name":"Mo\u1e29ammad \u2018Al\u012b\u0101b\u0101d",
    "gn:population":0,
    "gn:timezone":"Asia/Tehran",
    "iso:country":"IR",
    "name:fas_x_preferred":[
        "\u0645\u064f\u062d\u064e\u0645\u064e\u0651\u062f \u0639\u064e\u0644\u06cc \u0622\u0628\u0627\u062f"
    ],
    "name:fas_x_variant":[
        "\u0645\u062d\u0645\u0651\u062f \u0639\u0644\u06cc \u0622\u0628\u0627\u062f",
        "Mo\u1e29ammad \u2018Al\u012b\u0101b\u0101d"
    ],
    "wof:name":"Mohammad `Aliabad",
    "wof:placetype":"locality"
},
  "geometry": {"coordinates":[45.9113,35.881],"type":"Point"}
}