{
  "type": "Feature",
  "properties": {
    "gn:admin1_code":"42",
    "gn:asciiname":"Kalateh-ye Malu",
    "gn:country_code":"IR",
    "gn:dem":1475,
    "gn:feature_class":"P",
    "gn:feature_code":"PPL",
    "gn:name":"Kal\u0101teh-ye Mal\u016b",
    "gn:population":0,
    "gn:timezone":"Asia/Tehran",
    "iso:country":"IR",
    "name:fas_x_preferred":[
        "\u06a9\u0644\u0627\u062a\u0647 \u0645\u0644\u0648"
    ],
    "name:fas_x_variant":[
        "Kal\u0101teh-ye Mal\u016b"
    ],
    "wof:name":"Kalateh-ye Malu",
    "wof:placetype":"locality"
},
  "geometry": {"coordinates":[58.56253,36.84335],"type":"Point"}
}