{
  "type": "Feature",
  "properties": {
    "gn:admin1_code":"38",
    "gn:asciiname":"Hajji `Arab",
    "gn:country_code":"IR",
    "gn:dem":1657,
    "gn:feature_class":"P",
    "gn:feature_code":"PPL",
    "gn:name":"\u1e28\u0101jj\u012b \u2018Arab",
    "gn:population":0,
    "gn:timezone":"Asia/Tehran",
    "iso:country":"IR",
    "name:ara_x_preferred":[
        "\u062d\u0627\u062c\u064a \u0639\u0631\u0628"
    ],
    "name:fas_x_preferred":[
        "\u062d\u0627\u062c\u06cc \u0639\u0631\u0628"
    ],
    "name:fas_x_variant":[
        "\u1e28\u0101jj\u012b \u2018Arab"
    ],
    "name:und_x_variant":[
        "H\u0101ji \u2018Arab"
    ],
    "wof:name":"Hajji `Arab",
    "wof:placetype":"locality"
},
  "geometry": {"coordinates":[49.74633,35.59326],"type":"Point"}
}