{
  "type": "Feature",
  "properties": {
    "gn:admin1_code":"15",
    "gn:asciiname":"Lashgargah",
    "gn:country_code":"IR",
    "gn:dem":423,
    "gn:feature_class":"P",
    "gn:feature_code":"PPL",
    "gn:name":"Lashgarg\u0101h",
    "gn:population":0,
    "gn:timezone":"Asia/Tehran",
    "iso:country":"IR",
    "name:fas_x_preferred":[
        "Lashgarg\u0101h"
    ],
    "name:fas_x_variant":[
        "\u0644\u0634\u06af\u0631\u06af\u0627\u0647"
    ],
    "name:und_x_variant":[
        "\u0644\u0634\u06af\u0631\u06af\u0627\u0647"
    ],
    "wof:name":"Lashgargah",
    "wof:placetype":"locality"
},
  "geometry": {"coordinates":[49.59983,31.96978],"type":"Point"}
}