{
  "type": "Feature",
  "properties": {
    "gn:admin1_code":"33",
    "gn:asciiname":"Hajjilar Qeshlaqi",
    "gn:country_code":"IR",
    "gn:dem":1274,
    "gn:elevation":"0.0",
    "gn:feature_class":"P",
    "gn:feature_code":"PPL",
    "gn:name":"\u1e28\u0101jj\u012bl\u0101r Qeshl\u0101q\u012b",
    "gn:population":0,
    "gn:timezone":"Asia/Tehran",
    "iso:country":"IR",
    "name:fas_x_preferred":[
        "\u0642\u0634\u0644\u0627\u0642 \u062d\u0627\u062c\u06cc\u0644\u0631"
    ],
    "name:fas_x_variant":[
        "Qeshl\u0101q-e \u1e28\u0101jj\u012bl\u0101r",
        "Qeshl\u0101q-e \u1e28\u0101jj\u012blar",
        "\u062d\u0627\u062c\u06cc \u0644\u0627\u0631 \u0642\u0634\u0644\u0627\u0642\u06cc",
        "\u0642\u0634\u0644\u0627\u0642 \u062d\u0627\u062c\u06cc\u0644\u0627\u0631"
    ],
    "name:und_x_variant":[
        "\u1e28\u0101jj\u012bl\u0101r Qeshl\u0101q\u012b"
    ],
    "wof:name":"Hajjilar Qeshlaqi",
    "wof:placetype":"locality"
},
  "geometry": {"coordinates":[47.36815,38.44734],"type":"Point"}
}