{
  "type": "Feature",
  "properties": {
    "gn:admin1_code":"8",
    "gn:asciiname":"Tamchal",
    "gn:country_code":"IR",
    "gn:dem":-12,
    "gn:feature_class":"P",
    "gn:feature_code":"PPL",
    "gn:name":"Tamch\u0101l",
    "gn:population":0,
    "gn:timezone":"Asia/Tehran",
    "iso:country":"IR",
    "name:ara_x_preferred":[
        "\u062a\u0645\u062a\u0634\u0627\u0644"
    ],
    "name:ceb_x_preferred":[
        "Tamch\u0101l"
    ],
    "name:fas_x_preferred":[
        "Tamch\u0101l"
    ],
    "name:fas_x_variant":[
        "\u062a\u0645 \u0686\u0627\u0644",
        "\u062a\u0645\u0686\u0627\u0644"
    ],
    "name:msa_x_preferred":[
        "Tamchal"
    ],
    "name:por_x_preferred":[
        "Tamchal"
    ],
    "name:swe_x_preferred":[
        "Tamch\u0101l"
    ],
    "name:ukr_x_preferred":[
        "\u0422\u0430\u043c\u0447\u0430\u043b\u044c"
    ],
    "name:und_x_variant":[
        "Yatamchal",
        "T\u012bmch\u0101l",
        "Tem\u012bch\u0101l",
        "Tomchal"
    ],
    "wof:name":"Tamchal",
    "wof:placetype":"locality"
},
  "geometry": {"coordinates":[49.95827,37.31043],"type":"Point"}
}