{
  "type": "Feature",
  "properties": {
    "gn:admin1_code":"28.0",
    "gn:asciiname":"Mahalleh-ye Yazdabad",
    "gn:country_code":"IR",
    "gn:dem":1608,
    "gn:feature_class":"P",
    "gn:feature_code":"PPL",
    "gn:name":"Ma\u1e29alleh-ye Yazd\u0101b\u0101d",
    "gn:population":0,
    "gn:timezone":"Asia/Tehran",
    "iso:country":"IR",
    "name:fas_x_preferred":[
        "Yazd\u0101b\u0101d"
    ],
    "name:fas_x_variant":[
        "\u06cc\u0632\u062f \u0622\u0628\u0627\u062f",
        "\u0645\u062d\u0644\u0647 \u06cc\u0632\u062f \u0622\u0628\u0627\u062f"
    ],
    "name:und_x_variant":[
        "Yezd\u0101b\u0101d",
        "\u06cc\u0632\u062f \u0622\u0628\u0627\u062f",
        "Ma\u1e29alleh-ye Yazd\u0101b\u0101d"
    ],
    "wof:name":"Mahalleh-ye Yazdabad",
    "wof:placetype":"locality"
},
  "geometry": {"coordinates":[51.57466,32.59267],"type":"Point"}
}