{
  "type": "Feature",
  "properties": {
    "gn:admin1_code":"42",
    "gn:asciiname":"Deh Bar",
    "gn:country_code":"IR",
    "gn:dem":1626,
    "gn:feature_class":"P",
    "gn:feature_code":"PPL",
    "gn:name":"Deh B\u0101r",
    "gn:population":0,
    "gn:timezone":"Asia/Tehran",
    "iso:country":"IR",
    "name:fas_x_preferred":[
        "\u062f\u0647 \u0628\u0627\u0631"
    ],
    "name:fas_x_variant":[
        "Dehb\u0101r",
        "Deh B\u0101r",
        "\u0686\u0634\u0645\u0647 \u067e\u0648\u0646\u0647"
    ],
    "name:und_x_variant":[
        "Dahb\u0101r"
    ],
    "wof:name":"Deh Bar",
    "wof:placetype":"locality"
},
  "geometry": {"coordinates":[59.2881,36.2509],"type":"Point"}
}