{
  "type": "Feature",
  "properties": {
    "gn:admin1_code":"15",
    "gn:asciiname":"Nahirat",
    "gn:country_code":"IR",
    "gn:dem":9,
    "gn:feature_class":"P",
    "gn:feature_code":"PPL",
    "gn:name":"Nah\u012br\u0101t",
    "gn:population":0,
    "gn:timezone":"Asia/Tehran",
    "iso:country":"IR",
    "name:azb_x_preferred":[
        "\u0646\u0647\u06cc\u0631\u0627\u062a"
    ],
    "name:ceb_x_preferred":[
        "Nah\u012br\u0101t"
    ],
    "name:fas_x_preferred":[
        "\u0646\u0647\u06cc\u0631\u0627\u062a"
    ],
    "name:fas_x_variant":[
        "Nah\u012br\u0101t"
    ],
    "name:swe_x_preferred":[
        "Nah\u012br\u0101t"
    ],
    "wof:name":"Nahirat",
    "wof:placetype":"locality"
},
  "geometry": {"coordinates":[47.9946,31.5654],"type":"Point"}
}