{
  "type": "Feature",
  "properties": {
    "gn:admin1_code":"32",
    "gn:asciiname":"Qasem Qeshlaq",
    "gn:country_code":"IR",
    "gn:dem":1422,
    "gn:feature_class":"P",
    "gn:feature_code":"PPL",
    "gn:name":"Q\u0101sem Qeshl\u0101q",
    "gn:population":0,
    "gn:timezone":"Asia/Tehran",
    "iso:country":"IR",
    "name:fas_x_preferred":[
        "\u0642\u0627\u0633\u0645 \u0642\u0634\u0644\u0627\u0642"
    ],
    "name:fas_x_variant":[
        "\u062d\u0627\u062c\u0651\u06cc \u0633\u064e\u0644\u064a\u0645\u0650 \u0642\u0650\u0634\u0644\u0627\u0642\u06cc",
        "Q\u0101sem Qeshl\u0101q"
    ],
    "name:und_x_variant":[
        "\u1e28\u0101jj\u012b Sal\u012bm-e Qeshl\u0101q\u012b"
    ],
    "wof:name":"Qasem Qeshlaq",
    "wof:placetype":"locality"
},
  "geometry": {"coordinates":[48.1962,38.1717],"type":"Point"}
}