{
  "type": "Feature",
  "properties": {
    "gn:admin1_code":"28",
    "gn:asciiname":"Tudeshgchu",
    "gn:country_code":"IR",
    "gn:dem":2078,
    "gn:feature_class":"P",
    "gn:feature_code":"PPL",
    "gn:name":"T\u016bdeshgch\u016b",
    "gn:population":0,
    "gn:timezone":"Asia/Tehran",
    "iso:country":"IR",
    "name:fas_x_preferred":[
        "\u062a\u0648\u062f\u0634\u06af \u0686\u0648"
    ],
    "name:fas_x_variant":[
        "T\u016bdeshkech\u016b",
        "T\u016bdeshgch\u016b"
    ],
    "name:und_x_variant":[
        "Toodeshkjooyeh",
        "T\u016bdashk Cheh",
        "T\u016bdeshkch\u016b"
    ],
    "wof:name":"Tudeshgchu",
    "wof:placetype":"locality"
},
  "geometry": {"coordinates":[52.6824,32.7332],"type":"Point"}
}