{
  "type": "Feature",
  "properties": {
    "gn:admin1_code":"29",
    "gn:asciiname":"Kerdabad",
    "gn:country_code":"IR",
    "gn:dem":1822,
    "gn:feature_class":"P",
    "gn:feature_code":"PPL",
    "gn:name":"Kerd\u0101b\u0101d",
    "gn:population":0,
    "gn:timezone":"Asia/Tehran",
    "iso:country":"IR",
    "name:fas_x_preferred":[
        "Kerd\u0101b\u0101d"
    ],
    "wof:name":"Kerdabad",
    "wof:placetype":"locality"
},
  "geometry": {"coordinates":[56.96139,30.54944],"type":"Point"}
}