{
  "type": "Feature",
  "properties": {
    "gn:admin1_code":"28.0",
    "gn:asciiname":"Shahrak-e Sherkat-e Gaz",
    "gn:country_code":"IR",
    "gn:dem":1609,
    "gn:feature_class":"P",
    "gn:feature_code":"PPL",
    "gn:name":"Shahrak-e Sherkat-e G\u0101z",
    "gn:population":0,
    "gn:timezone":"Asia/Tehran",
    "iso:country":"IR",
    "name:fas_x_preferred":[
        "\u0634\u0647\u0631\u06a9 \u0634\u0631\u06a9\u062a \u06af\u0627\u0632"
    ],
    "name:fas_x_variant":[
        "Shahrak-e Sherkat-e G\u0101z"
    ],
    "wof:name":"Shahrak-e Sherkat-e Gaz",
    "wof:placetype":"locality"
},
  "geometry": {"coordinates":[51.4911,32.5858],"type":"Point"}
}