{
  "type": "Feature",
  "properties": {
    "gn:admin1_code":"33",
    "gn:asciiname":"Sormalu",
    "gn:country_code":"IR",
    "gn:dem":1284,
    "gn:feature_class":"P",
    "gn:feature_code":"PPL",
    "gn:name":"Sormal\u016b",
    "gn:population":0,
    "gn:timezone":"Asia/Tehran",
    "iso:country":"IR",
    "name:fas_x_preferred":[
        "\u0633\u0631\u0645\u0644\u0648"
    ],
    "name:fas_x_variant":[
        "Sormal\u016b",
        "\u0633\u0631\u0645\u0647 \u0644\u0648"
    ],
    "name:und_x_variant":[
        "Sormehl\u016b"
    ],
    "wof:name":"Sormalu",
    "wof:placetype":"locality"
},
  "geometry": {"coordinates":[46.0521,37.11267],"type":"Point"}
}