{
  "type": "Feature",
  "properties": {
    "gn:admin1_code":"33",
    "gn:asciiname":"Mohsenabad",
    "gn:country_code":"IR",
    "gn:dem":1681,
    "gn:feature_class":"P",
    "gn:feature_code":"PPL",
    "gn:name":"Mo\u1e29sen\u0101b\u0101d",
    "gn:population":0,
    "gn:timezone":"Asia/Tehran",
    "iso:country":"IR",
    "name:fas_x_preferred":[
        "Mo\u1e29sen\u0101b\u0101d"
    ],
    "wof:name":"Mohsenabad",
    "wof:placetype":"locality"
},
  "geometry": {"coordinates":[47.41667,37.85],"type":"Point"}
}