{
  "type": "Feature",
  "properties": {
    "gn:admin1_code":"4.0",
    "gn:asciiname":"Deh-e Hajji Shah Nazar",
    "gn:country_code":"IR",
    "gn:dem":483,
    "gn:feature_class":"P",
    "gn:feature_code":"PPL",
    "gn:name":"Deh-e \u1e28\u0101jj\u012b Sh\u0101h Naz\u0327ar",
    "gn:population":0,
    "gn:timezone":"Asia/Tehran",
    "iso:country":"IR",
    "name:fas_x_preferred":[
        "\u062f\u0647 \u062d\u0627\u062c\u06cc \u0634\u0627\u0647 \u0646\u0638\u0631"
    ],
    "name:fas_x_variant":[
        "Deh-e \u1e28\u0101jj\u012b Sh\u0101h Naz\u0327ar"
    ],
    "wof:name":"Deh-e Hajji Shah Nazar",
    "wof:placetype":"locality"
},
  "geometry": {"coordinates":[61.7142,31.0887],"type":"Point"}
}