{
  "type": "Feature",
  "properties": {
    "gn:admin1_code":"29",
    "gn:asciiname":"Jambur",
    "gn:country_code":"IR",
    "gn:dem":769,
    "gn:feature_class":"P",
    "gn:feature_code":"PPL",
    "gn:name":"Jamb\u016br",
    "gn:population":0,
    "gn:timezone":"Asia/Tehran",
    "iso:country":"IR",
    "name:fas_x_preferred":[
        "\u062c\u0645\u0628\u0648\u0631"
    ],
    "name:fas_x_variant":[
        "Jamb\u016br"
    ],
    "name:ind_x_preferred":[
        "Jambur"
    ],
    "wof:name":"Jambur",
    "wof:placetype":"locality"
},
  "geometry": {"coordinates":[58.7037,28.14905],"type":"Point"}
}