{
  "type": "Feature",
  "properties": {
    "gn:admin1_code":"11",
    "gn:asciiname":"Badafshan-e Pa'in",
    "gn:country_code":"IR",
    "gn:dem":719,
    "gn:feature_class":"P",
    "gn:feature_code":"PPL",
    "gn:name":"B\u0101dafsh\u0101n-e P\u0101\u2019\u012bn",
    "gn:population":0,
    "gn:timezone":"Asia/Tehran",
    "iso:country":"IR",
    "name:fas_x_preferred":[
        "\u0628\u0627\u062f\u0627\u0641\u0634\u0627\u0646 \u067e\u0627\u0626\u064a\u0646"
    ],
    "name:fas_x_variant":[
        "\u06af\u0627\u0634\u0648 \u067e\u0627\u0626\u064a\u0646",
        "B\u0101dafsh\u0101n-e P\u0101\u2019\u012bn",
        "\u0628\u0627\u062f\u0627\u0641\u0634\u0627\u0646 \u067e\u0627\u06cc\u06cc\u0646"
    ],
    "name:msa_x_preferred":[
        "Badafshan-e Pain"
    ],
    "name:und_x_variant":[
        "G\u0101sh\u016b P\u0101\u2019\u012bn"
    ],
    "wof:name":"Badafshan-e Pa'in",
    "wof:placetype":"locality"
},
  "geometry": {"coordinates":[57.1556,27.5667],"type":"Point"}
}