{
  "type": "Feature",
  "properties": {
    "gn:admin1_code":"29",
    "gn:asciiname":"Qal`eh Abuzar",
    "gn:country_code":"IR",
    "gn:dem":2053,
    "gn:feature_class":"P",
    "gn:feature_code":"PPL",
    "gn:name":"Qal\u2018eh Ab\u016bz\u0304ar",
    "gn:population":0,
    "gn:timezone":"Asia/Tehran",
    "iso:country":"IR",
    "name:fas_x_preferred":[
        "\u0627\u0628\u0648\u0630\u0631"
    ],
    "name:fas_x_variant":[
        "Ab\u016bz\u0304ar",
        "\u0642\u0644\u0639\u0647 \u0627\u0628\u0648\u0630\u0631"
    ],
    "name:und_x_variant":[
        "Qal\u2018eh Ab\u016bz\u0304ar"
    ],
    "wof:name":"Qal`eh Abuzar",
    "wof:placetype":"locality"
},
  "geometry": {"coordinates":[55.9778,28.8275],"type":"Point"}
}