{
  "type": "Feature",
  "properties": {
    "gn:admin1_code":"28",
    "gn:asciiname":"Shahrak-e Shahid Modarres",
    "gn:country_code":"IR",
    "gn:dem":1579,
    "gn:feature_class":"P",
    "gn:feature_code":"PPL",
    "gn:name":"Shahrak-e Shah\u012bd Modarres",
    "gn:population":0,
    "gn:timezone":"Asia/Tehran",
    "iso:country":"IR",
    "name:fas_x_preferred":[
        "\u0634\u0647\u0631\u0643 \u0634\u0647\u06cc\u062f \u0645\u062f\u0631\u0633"
    ],
    "name:fas_x_variant":[
        "Shahrak-e Shah\u012bd Modarres"
    ],
    "wof:name":"Shahrak-e Shahid Modarres",
    "wof:placetype":"locality"
},
  "geometry": {"coordinates":[52.0298,32.423],"type":"Point"}
}