{
  "type": "Feature",
  "properties": {
    "gn:admin1_code":"7",
    "gn:asciiname":"Chah Anjir",
    "gn:country_code":"IR",
    "gn:dem":1925,
    "gn:feature_class":"P",
    "gn:feature_code":"PPL",
    "gn:name":"Ch\u0101h Anj\u012br",
    "gn:population":0,
    "gn:timezone":"Asia/Tehran",
    "iso:country":"IR",
    "name:fas_x_preferred":[
        "\u0686\u0627\u0647 \u0627\u0646\u062c\u06cc\u0631"
    ],
    "name:fas_x_variant":[
        "Ch\u0101h Anj\u012br",
        "\u0686\u0627\u0647 \u0627\u0646\u062c\u06cc\u0631 \u0639\u0644\u06cc\u0627"
    ],
    "name:msa_x_preferred":[
        "Chah Anjir-e Olya"
    ],
    "name:und_x_variant":[
        "Ch\u0101h Anj\u012br-e \u2018Oly\u0101"
    ],
    "wof:name":"Chah Anjir",
    "wof:placetype":"locality"
},
  "geometry": {"coordinates":[54.49800000000001,29.0352],"type":"Point"}
}