{
  "type": "Feature",
  "properties": {
    "gn:admin1_code":"5",
    "gn:asciiname":"Pak",
    "gn:country_code":"IR",
    "gn:dem":1757,
    "gn:feature_class":"P",
    "gn:feature_code":"PPL",
    "gn:name":"P\u0101k",
    "gn:population":0,
    "gn:timezone":"Asia/Tehran",
    "iso:country":"IR",
    "name:bos_x_preferred":[
        "Pak"
    ],
    "name:deu_x_preferred":[
        "Pak"
    ],
    "name:est_x_preferred":[
        "Pak"
    ],
    "name:fas_x_preferred":[
        "\u067e\u0627\u0643"
    ],
    "name:fin_x_preferred":[
        "Pak"
    ],
    "name:hat_x_preferred":[
        "Pak"
    ],
    "name:hrv_x_preferred":[
        "Pak"
    ],
    "name:hun_x_preferred":[
        "Pak"
    ],
    "name:kur_x_preferred":[
        "Pak"
    ],
    "name:nor_x_preferred":[
        "Pak"
    ],
    "name:pol_x_preferred":[
        "Pak"
    ],
    "name:rus_x_preferred":[
        "\u041f\u0430\u043a"
    ],
    "name:slv_x_preferred":[
        "Pak"
    ],
    "name:ukr_x_preferred":[
        "\u041f\u0430\u043a"
    ],
    "name:und_x_variant":[
        "P\u0101k"
    ],
    "wof:name":"Pak",
    "wof:placetype":"locality"
},
  "geometry": {"coordinates":[51.23333,31.05],"type":"Point"}
}