{
  "type": "Feature",
  "properties": {
    "gn:admin1_code":"42",
    "gn:asciiname":"Hodk",
    "gn:country_code":"IR",
    "gn:dem":1343,
    "gn:feature_class":"P",
    "gn:feature_code":"PPL",
    "gn:name":"Hodk",
    "gn:population":0,
    "gn:timezone":"Asia/Tehran",
    "iso:country":"IR",
    "name:fas_x_preferred":[
        "\u0647\u062f\u06a9"
    ],
    "wof:name":"Hodk",
    "wof:placetype":"locality"
},
  "geometry": {"coordinates":[57.94318000000001,35.37896],"type":"Point"}
}