{
  "type": "Feature",
  "properties": {
    "gn:admin1_code":"29",
    "gn:asciiname":"Posht Kuh-e Khar Posht",
    "gn:country_code":"IR",
    "gn:dem":675,
    "gn:feature_class":"P",
    "gn:feature_code":"PPL",
    "gn:name":"Posht K\u016bh-e Khar Posht",
    "gn:population":0,
    "gn:timezone":"Asia/Tehran",
    "iso:country":"IR",
    "name:fas_x_preferred":[
        "\u067e\u0634\u062a \u06a9\u0648\u0647 \u062e\u0631 \u067e\u0634\u062a"
    ],
    "name:fas_x_variant":[
        "Posht K\u016bh-e Khar Posht"
    ],
    "name:und_x_variant":[
        "Khar Posht"
    ],
    "wof:name":"Posht Kuh-e Khar Posht",
    "wof:placetype":"locality"
},
  "geometry": {"coordinates":[57.9172,28.4872],"type":"Point"}
}