{
  "type": "Feature",
  "properties": {
    "gn:admin1_code":"1.0",
    "gn:asciiname":"Shameh Sheykheh",
    "gn:country_code":"IR",
    "gn:dem":1657,
    "gn:feature_class":"P",
    "gn:feature_code":"PPL",
    "gn:name":"Shameh Sheykheh",
    "gn:population":0,
    "gn:timezone":"Asia/Tehran",
    "iso:country":"IR",
    "name:azb_x_preferred":[
        "\u0634\u0645\u0647 \u0634\u064a\u062e\u0647"
    ],
    "name:fas_x_preferred":[
        "\u0634\u0645\u0647 \u0634\u06cc\u062e\u0647"
    ],
    "name:fas_x_variant":[
        "\u0634\u0645\u0647\u200c\u0634\u06cc\u062e\u0647"
    ],
    "name:msa_x_preferred":[
        "Shameh Sheykheh"
    ],
    "wof:name":"Shameh Sheykheh",
    "wof:placetype":"locality"
},
  "geometry": {"coordinates":[45.4279,36.2201],"type":"Point"}
}