{
  "type": "Feature",
  "properties": {
    "gn:admin1_code":"42.0",
    "gn:asciiname":"Chah-e Velayati",
    "gn:country_code":"IR",
    "gn:dem":1203,
    "gn:feature_class":"P",
    "gn:feature_code":"PPL",
    "gn:name":"Ch\u0101h-e Vel\u0101yat\u012b",
    "gn:population":0,
    "gn:timezone":"Asia/Tehran",
    "iso:country":"IR",
    "name:fas_x_preferred":[
        "Ch\u0101h-e Vel\u0101yat\u012b"
    ],
    "wof:name":"Chah-e Velayati",
    "wof:placetype":"locality"
},
  "geometry": {"coordinates":[60.19083000000001,35.49583],"type":"Point"}
}