{
  "type": "Feature",
  "properties": {
    "gn:admin1_code":"32",
    "gn:asciiname":"Yuriq",
    "gn:country_code":"IR",
    "gn:dem":1415,
    "gn:feature_class":"P",
    "gn:feature_code":"PPL",
    "gn:name":"Y\u016br\u012bq",
    "gn:population":0,
    "gn:timezone":"Asia/Tehran",
    "iso:country":"IR",
    "name:fas_x_preferred":[
        "\u06cc\u0648\u0631\u06cc\u0642"
    ],
    "name:fas_x_variant":[
        "\u012avr\u012bq",
        "Y\u016br\u012bq"
    ],
    "wof:name":"Yuriq",
    "wof:placetype":"locality"
},
  "geometry": {"coordinates":[48.5254,38.1721],"type":"Point"}
}