{
  "type": "Feature",
  "properties": {
    "gn:admin1_code":"28",
    "gn:asciiname":"Mazra`eh-ye Bala",
    "gn:country_code":"IR",
    "gn:dem":2262,
    "gn:feature_class":"P",
    "gn:feature_code":"PPL",
    "gn:name":"Mazra\u2018eh-ye B\u0101l\u0101",
    "gn:population":0,
    "gn:timezone":"Asia/Tehran",
    "iso:country":"IR",
    "name:fas_x_preferred":[
        "\u0645\u0632\u0631\u0639\u0647 \u0628\u0627\u0644\u0627"
    ],
    "name:fas_x_variant":[
        "Mazra\u2018eh-ye B\u0101l\u0101"
    ],
    "wof:name":"Mazra`eh-ye Bala",
    "wof:placetype":"locality"
},
  "geometry": {"coordinates":[52.5977,32.7995],"type":"Point"}
}