{
  "type": "Feature",
  "properties": {
    "gn:admin1_code":"43",
    "gn:asciiname":"Hesar-e Pahlavanlu",
    "gn:country_code":"IR",
    "gn:dem":1351,
    "gn:feature_class":"P",
    "gn:feature_code":"PPL",
    "gn:name":"\u1e28e\u015f\u0101r-e Pahlav\u0101nl\u016b",
    "gn:population":0,
    "gn:timezone":"Asia/Tehran",
    "iso:country":"IR",
    "name:fas_x_preferred":[
        "\u1e28e\u015f\u0101r-e Gel\u012b\u0101n"
    ],
    "name:fas_x_variant":[
        "\u1e28e\u015f\u0101r-e Pahlav\u0101nl\u016b",
        "\u062d\u0635\u0627\u0631 \u067e\u0647\u0644\u0648\u0627\u0646\u0644\u0648"
    ],
    "name:und_x_variant":[
        "\u1e28e\u015f\u0101r-e Pahlev\u0101nl\u016b",
        "\u1e28e\u015f\u0101r-e Pahlav\u0101nl\u016b"
    ],
    "wof:name":"Hesar-e Pahlavanlu",
    "wof:placetype":"locality"
},
  "geometry": {"coordinates":[57.89266,37.23216],"type":"Point"}
}