{
  "type": "Feature",
  "properties": {
    "gn:admin1_code":"37.0",
    "gn:asciiname":"Koveyt Mahalleh",
    "gn:country_code":"IR",
    "gn:dem":119,
    "gn:feature_class":"P",
    "gn:feature_code":"PPL",
    "gn:name":"Koveyt Ma\u1e29alleh",
    "gn:population":0,
    "gn:timezone":"Asia/Tehran",
    "iso:country":"IR",
    "name:fas_x_preferred":[
        "\u06a9\u0648\u06cc\u062a \u0645\u062d\u0644\u0647"
    ],
    "name:fas_x_variant":[
        "\u06a9\u0648\u0641\u06cc\u062a \u0645\u062d\u0644\u0647",
        "\u06a9\u0648\u06cc\u062a\u200c\u0645\u062d\u0644\u0647"
    ],
    "name:msa_x_preferred":[
        "Koveyt Mahalleh"
    ],
    "name:und_x_variant":[
        "Koveyt Ma\u1e29alleh",
        "K\u016bfeyt Ma\u1e29alleh"
    ],
    "wof:name":"Koveyt Mahalleh",
    "wof:placetype":"locality"
},
  "geometry": {"coordinates":[55.35969,37.24527],"type":"Point"}
}