{
  "type": "Feature",
  "properties": {
    "gn:admin1_code":"40",
    "gn:asciiname":"Mazra`eh-ye `Ali",
    "gn:country_code":"IR",
    "gn:dem":2591,
    "gn:feature_class":"P",
    "gn:feature_code":"PPL",
    "gn:name":"Mazra\u2018eh-ye \u2018Al\u012b",
    "gn:population":0,
    "gn:timezone":"Asia/Tehran",
    "iso:country":"IR",
    "name:fas_x_preferred":[
        "\u0645\u0632\u0631\u0639\u0647 \u0639\u0644\u06cc"
    ],
    "name:fas_x_variant":[
        "Mazra\u2018eh-ye \u2018Al\u012b"
    ],
    "wof:name":"Mazra`eh-ye `Ali",
    "wof:placetype":"locality"
},
  "geometry": {"coordinates":[54.04835,31.52143],"type":"Point"}
}