{
  "type": "Feature",
  "properties": {
    "gn:admin1_code":"41",
    "gn:asciiname":"Mansurabad",
    "gn:country_code":"IR",
    "gn:dem":1919,
    "gn:feature_class":"P",
    "gn:feature_code":"PPL",
    "gn:name":"Man\u015f\u016br\u0101b\u0101d",
    "gn:population":0,
    "gn:timezone":"Asia/Tehran",
    "iso:country":"IR",
    "name:aze_x_preferred":[
        "M\u0259nsurabad"
    ],
    "name:fas_x_preferred":[
        "Man\u015f\u016br\u0101b\u0101d"
    ],
    "name:fas_x_variant":[
        "\u0645\u0646\u0635\u0648\u0631 \u0622\u0628\u0627\u062f",
        "\u0645\u0646\u0635\u0648\u0631\u0622\u0628\u0627\u062f"
    ],
    "wof:name":"Mansurabad",
    "wof:placetype":"locality"
},
  "geometry": {"coordinates":[59.42813,32.21629],"type":"Point"}
}