{
  "type": "Feature",
  "properties": {
    "gn:admin1_code":"1",
    "gn:asciiname":"Oruj Kandi",
    "gn:country_code":"IR",
    "gn:dem":2027,
    "gn:feature_class":"P",
    "gn:feature_code":"PPL",
    "gn:name":"Or\u016bj Kand\u012b",
    "gn:population":0,
    "gn:timezone":"Asia/Tehran",
    "iso:country":"IR",
    "name:fas_x_preferred":[
        "\u0627\u064f\u0631\u0648\u062c \u0643\u064e\u0646\u062f\u06cc"
    ],
    "name:fas_x_variant":[
        "Or\u016bj Kand\u012b",
        "\u0627\u0631\u0648\u062c \u06a9\u0646\u062f\u06cc"
    ],
    "name:und_x_variant":[
        "\u0627\u0631\u0648\u062c \u06a9\u0646\u062f\u06cc"
    ],
    "wof:name":"Oruj Kandi",
    "wof:placetype":"locality"
},
  "geometry": {"coordinates":[44.2252,39.2646],"type":"Point"}
}