{
  "type": "Feature",
  "properties": {
    "gn:admin1_code":"42.0",
    "gn:asciiname":"Samghan",
    "gn:country_code":"IR",
    "gn:dem":1014,
    "gn:feature_class":"P",
    "gn:feature_code":"PPL",
    "gn:name":"S\u0101mgh\u0101n",
    "gn:population":0,
    "gn:timezone":"Asia/Tehran",
    "iso:country":"IR",
    "name:ara_x_preferred":[
        "\u0633\u0627\u0645\u063a\u0627\u0646"
    ],
    "name:ceb_x_preferred":[
        "S\u0101mgh\u0101n"
    ],
    "name:fas_x_preferred":[
        "S\u0101mgh\u0101n"
    ],
    "name:fas_x_variant":[
        "\u0633\u0627\u0645\u063a\u0627\u0646",
        "\u0633\u0627\u0645\u0642\u0627\u0646"
    ],
    "name:swe_x_preferred":[
        "S\u0101mgh\u0101n"
    ],
    "name:und_x_variant":[
        "\u0633\u0627\u0645\u063a\u0627\u0646",
        "S\u0101mq\u0101n"
    ],
    "wof:name":"Samghan",
    "wof:placetype":"locality"
},
  "geometry": {"coordinates":[57.08492,36.80692],"type":"Point"}
}