{
  "type": "Feature",
  "properties": {
    "gn:admin1_code":"41.0",
    "gn:asciiname":"Poreng",
    "gn:country_code":"IR",
    "gn:dem":1520,
    "gn:feature_class":"P",
    "gn:feature_code":"PPL",
    "gn:name":"Poreng",
    "gn:population":0,
    "gn:timezone":"Asia/Tehran",
    "iso:country":"IR",
    "name:fas_x_preferred":[
        "\u067e\u0631\u0646\u06af"
    ],
    "name:fas_x_variant":[
        "P\u016breng"
    ],
    "wof:name":"Poreng",
    "wof:placetype":"locality"
},
  "geometry": {"coordinates":[60.066,32.452],"type":"Point"}
}