{
  "type": "Feature",
  "properties": {
    "gn:admin1_code":"29",
    "gn:asciiname":"Halq Chah Sard",
    "gn:country_code":"IR",
    "gn:dem":2359,
    "gn:feature_class":"P",
    "gn:feature_code":"PPL",
    "gn:name":"\u1e28alq Ch\u0101h Sard",
    "gn:population":0,
    "gn:timezone":"Asia/Tehran",
    "iso:country":"IR",
    "name:fas_x_preferred":[
        "\u062d\u0644\u0642 \u0686\u0627\u0647 \u0633\u0631\u062f"
    ],
    "name:fas_x_variant":[
        "\u0686\u0646\u0627\u0644 \u0622\u0628\u0627\u062f",
        "\u062e\u0627\u0644\u0635\u0647 \u062f\u064a\u0648\u0627\u0646\u06cc"
    ],
    "name:und_x_variant":[
        "Kh\u0101leseh-Ye-D\u012bv\u0101n\u012b",
        "Kh\u0101le\u015feh D\u012bv\u0101n\u012b",
        "\u1e28alq Ch\u0101h Sard",
        "Chen\u0101l\u0101b\u0101d"
    ],
    "wof:name":"Halq Chah Sard",
    "wof:placetype":"locality"
},
  "geometry": {"coordinates":[57.073,29.6917],"type":"Point"}
}