{
  "type": "Feature",
  "properties": {
    "gn:admin1_code":"7",
    "gn:asciiname":"Hezargun",
    "gn:country_code":"IR",
    "gn:dem":1075,
    "gn:feature_class":"P",
    "gn:feature_code":"PPL",
    "gn:name":"Hez\u0101rg\u016bn",
    "gn:population":0,
    "gn:timezone":"Asia/Tehran",
    "iso:country":"IR",
    "name:fas_x_preferred":[
        "\u0647\u0632\u0627\u0631\u06af\u0648\u0646"
    ],
    "name:fas_x_variant":[
        "Hez\u0101rg\u016bn"
    ],
    "wof:name":"Hezargun",
    "wof:placetype":"locality"
},
  "geometry": {"coordinates":[53.1499,28.8322],"type":"Point"}
}