{
  "type": "Feature",
  "properties": {
    "gn:admin1_code":"7",
    "gn:asciiname":"Deh Bal",
    "gn:cc2":"IR",
    "gn:country_code":"IR",
    "gn:dem":1740,
    "gn:feature_class":"P",
    "gn:feature_code":"PPL",
    "gn:name":"Deh B\u0101l",
    "gn:population":0,
    "gn:timezone":"Asia/Tehran",
    "iso:country":"IR",
    "name:ara_x_preferred":[
        "\u062f\u0629 \u0628\u0627\u0644"
    ],
    "name:fas_x_preferred":[
        "Deh B\u0101l"
    ],
    "name:fas_x_variant":[
        "\u062f\u0647 \u0628\u0627\u0644"
    ],
    "name:und_x_variant":[
        "Deh B\u0101n"
    ],
    "wof:name":"Deh Bal",
    "wof:placetype":"locality"
},
  "geometry": {"coordinates":[52.40472000000001,29.42278],"type":"Point"}
}