{
  "type": "Feature",
  "properties": {
    "gn:admin1_code":"34",
    "gn:asciiname":"Eyvand-e Bala",
    "gn:country_code":"IR",
    "gn:dem":2150,
    "gn:feature_class":"P",
    "gn:feature_code":"PPL",
    "gn:name":"Eyvand-e B\u0101l\u0101",
    "gn:population":0,
    "gn:timezone":"Asia/Tehran",
    "iso:country":"IR",
    "name:fas_x_preferred":[
        "\u0627\u064a\u0648\u0646\u062f \u0639\u0644\u064a\u0627"
    ],
    "name:fas_x_variant":[
        "Eyvand-e \u2018Oly\u0101",
        "\u0627\u06cc\u0648\u0646\u062f \u0628\u0627\u0644\u0627"
    ],
    "name:und_x_variant":[
        "\u012avand",
        "Eyvand",
        "Eyvand-e B\u0101l\u0101"
    ],
    "wof:name":"Eyvand-e Bala",
    "wof:placetype":"locality"
},
  "geometry": {"coordinates":[49.4279,34.21649],"type":"Point"}
}