{
  "type": "Feature",
  "properties": {
    "gn:admin1_code":"4.0",
    "gn:asciiname":"Shahryanch",
    "gn:country_code":"IR",
    "gn:dem":1182,
    "gn:feature_class":"P",
    "gn:feature_code":"PPL",
    "gn:name":"Shahry\u0101nch",
    "gn:population":0,
    "gn:timezone":"Asia/Tehran",
    "iso:country":"IR",
    "name:fas_x_preferred":[
        "\u0634\u0647\u0631\u064a\u0627\u0646\u0686"
    ],
    "name:fas_x_variant":[
        "Shahry\u0101nch",
        "Shahriy\u0101naj",
        "Shahr\u012b\u0101naj",
        "Shahr\u012b\u0101nach"
    ],
    "name:und_x_variant":[
        "Shahjonj"
    ],
    "wof:name":"Shahryanch",
    "wof:placetype":"locality"
},
  "geometry": {"coordinates":[60.5157,26.61997],"type":"Point"}
}