{
  "type": "Feature",
  "properties": {
    "gn:admin1_code":"33",
    "gn:asciiname":"Urta Qeshlaq",
    "gn:country_code":"IR",
    "gn:dem":1819,
    "gn:feature_class":"P",
    "gn:feature_code":"PPL",
    "gn:name":"\u016art\u0101 Qeshl\u0101q",
    "gn:population":0,
    "gn:timezone":"Asia/Tehran",
    "iso:country":"IR",
    "name:fas_x_preferred":[
        "\u016art\u0101 Qeshl\u0101q"
    ],
    "name:fas_x_variant":[
        "\u0627\u0648\u0631\u062a\u0627 \u0642\u0634\u0644\u0627\u0642",
        "\u0627\u0648\u0631\u062a\u0627 \u0642\u0634\u0644\u0627\u0642 \u0633\u0641\u0644\u06cc"
    ],
    "name:und_x_variant":[
        "\u0627\u0648\u0631\u062a\u0627 \u0642\u0634\u0644\u0627\u0642",
        "\u016art\u0101 Qeshl\u0101q-e Sofl\u00e1"
    ],
    "wof:name":"Urta Qeshlaq",
    "wof:placetype":"locality"
},
  "geometry": {"coordinates":[46.5193,37.0413],"type":"Point"}
}