{
  "type": "Feature",
  "properties": {
    "gn:admin1_code":"35.0",
    "gn:asciiname":"Shahrak-e Sefid Kuhak",
    "gn:country_code":"IR",
    "gn:dem":733,
    "gn:feature_class":"P",
    "gn:feature_code":"PPL",
    "gn:name":"Shahrak-e Sef\u012bd K\u016bhak",
    "gn:population":0,
    "gn:timezone":"Asia/Tehran",
    "iso:country":"IR",
    "name:fas_x_preferred":[
        "K\u016bshk"
    ],
    "name:fas_x_variant":[
        "\u06a9\u0648\u0634\u06a9",
        "\u0634\u0647\u0631\u06a9 \u0633\u0641\u06cc\u062f \u06a9\u0648\u0647\u06a9"
    ],
    "name:und_x_variant":[
        "\u06a9\u0648\u0634\u06a9",
        "Shahrak-e Sef\u012bd K\u016bhak"
    ],
    "wof:name":"Shahrak-e Sefid Kuhak",
    "wof:placetype":"locality"
},
  "geometry": {"coordinates":[51.31059000000001,36.4424],"type":"Point"}
}