{
  "type": "Feature",
  "properties": {
    "gn:admin1_code":"23.0",
    "gn:asciiname":"Qal`eh Khalileh",
    "gn:country_code":"IR",
    "gn:dem":2443,
    "gn:feature_class":"P",
    "gn:feature_code":"PPL",
    "gn:name":"Qal\u2018eh Khal\u012bleh",
    "gn:population":0,
    "gn:timezone":"Asia/Tehran",
    "iso:country":"IR",
    "name:fas_x_preferred":[
        "Qal\u2018eh Khal\u012bleh"
    ],
    "name:fas_x_variant":[
        "\u0642\u0644\u0639\u0647 \u062e\u0644\u06cc\u0644\u0647"
    ],
    "wof:name":"Qal`eh Khalileh",
    "wof:placetype":"locality"
},
  "geometry": {"coordinates":[49.88512,33.25005],"type":"Point"}
}