{
  "type": "Feature",
  "properties": {
    "gn:admin1_code":"7",
    "gn:asciiname":"Hoseynabad",
    "gn:country_code":"IR",
    "gn:dem":1382,
    "gn:feature_class":"P",
    "gn:feature_code":"PPL",
    "gn:name":"\u1e28oseyn\u0101b\u0101d",
    "gn:population":0,
    "gn:timezone":"Asia/Tehran",
    "iso:country":"IR",
    "name:aze_x_preferred":[
        "H\u00fcseynabad"
    ],
    "name:ceb_x_preferred":[
        "Hoseynabad"
    ],
    "name:fas_x_preferred":[
        "\u062d\u0633\u06cc\u0646 \u0622\u0628\u0627\u062f"
    ],
    "name:fas_x_variant":[
        "\u1e28oseyn\u0101b\u0101d",
        "\u062d\u0633\u06cc\u0646\u200c\u0622\u0628\u0627\u062f"
    ],
    "name:mzn_x_preferred":[
        "\u062d\u0633\u06cc\u0646\u200c\u0622\u0628\u0627\u062f"
    ],
    "name:swe_x_preferred":[
        "Hoseynabad"
    ],
    "wof:name":"Hoseynabad",
    "wof:placetype":"locality"
},
  "geometry": {"coordinates":[54.0292,28.92721],"type":"Point"}
}