{
  "type": "Feature",
  "properties": {
    "gn:admin1_code":"8",
    "gn:asciiname":"Asyehvaseh",
    "gn:country_code":"IR",
    "gn:dem":1961,
    "gn:feature_class":"P",
    "gn:feature_code":"PPL",
    "gn:name":"Asyehvaseh",
    "gn:population":0,
    "gn:timezone":"Asia/Tehran",
    "iso:country":"IR",
    "name:fas_x_preferred":[
        "\u0627\u064e\u0633\u064a\u0650\u0647\u0648\u064e\u0633\u0650\u0647"
    ],
    "wof:name":"Asyehvaseh",
    "wof:placetype":"locality"
},
  "geometry": {"coordinates":[48.84444000000001,37.39194000000001],"type":"Point"}
}