{
  "type": "Feature",
  "properties": {
    "gn:admin1_code":"42.0",
    "gn:asciiname":"Dahaneh-ye Chahal",
    "gn:country_code":"IR",
    "gn:dem":956,
    "gn:feature_class":"P",
    "gn:feature_code":"PPL",
    "gn:name":"Dahaneh-ye Chahal",
    "gn:population":0,
    "gn:timezone":"Asia/Tehran",
    "iso:country":"IR",
    "name:ceb_x_preferred":[
        "Dahaneh-ye Chahal"
    ],
    "name:fas_x_preferred":[
        "Q\u0101sem\u0101b\u0101d"
    ],
    "name:fas_x_variant":[
        "\u062f\u0647\u0646\u0647 \u0686\u0647\u0644"
    ],
    "name:swe_x_preferred":[
        "Dahaneh-ye Chahal"
    ],
    "name:und_x_variant":[
        "Dahaneh-ye Jahl"
    ],
    "wof:name":"Dahaneh-ye Chahal",
    "wof:placetype":"locality"
},
  "geometry": {"coordinates":[60.22375,35.95188],"type":"Point"}
}