{
  "type": "Feature",
  "properties": {
    "gn:admin1_code":"42.0",
    "gn:asciiname":"Bashirabad",
    "gn:country_code":"IR",
    "gn:dem":1246,
    "gn:feature_class":"P",
    "gn:feature_code":"PPL",
    "gn:name":"Bash\u012br\u0101b\u0101d",
    "gn:population":0,
    "gn:timezone":"Asia/Tehran",
    "iso:country":"IR",
    "name:fas_x_preferred":[
        "\u0628\u0634\u06cc\u0631 \u0622\u0628\u0627\u062f"
    ],
    "name:fas_x_variant":[
        "Cheshmeh-ye Jowhar B\u012bsh\u012br\u0101b\u0101d",
        "Bash\u012br\u0101b\u0101d",
        "\u0628\u0634\u06cc\u0631\u0622\u0628\u0627\u062f"
    ],
    "name:und_x_variant":[
        "Cheshmeh-ye Jowhar Sh\u012br\u0101b\u0101d"
    ],
    "wof:name":"Bashirabad",
    "wof:placetype":"locality"
},
  "geometry": {"coordinates":[60.7031,35.4473],"type":"Point"}
}