{
  "type": "Feature",
  "properties": {
    "gn:admin1_code":"7",
    "gn:asciiname":"Mafiabad",
    "gn:country_code":"IR",
    "gn:dem":486,
    "gn:feature_class":"P",
    "gn:feature_code":"PPL",
    "gn:name":"M\u0101f\u012b\u0101b\u0101d",
    "gn:population":0,
    "gn:timezone":"Asia/Tehran",
    "iso:country":"IR",
    "name:fas_x_preferred":[
        "\u0645\u0627\u0641\u06cc \u0622\u0628\u0627\u062f"
    ],
    "name:fas_x_variant":[
        "M\u0101f\u012b\u0101b\u0101d"
    ],
    "name:und_x_variant":[
        "Ma\u2018\u0101f\u012b\u0101b\u0101d"
    ],
    "wof:name":"Mafiabad",
    "wof:placetype":"locality"
},
  "geometry": {"coordinates":[51.35,29.5508],"type":"Point"}
}