{
  "type": "Feature",
  "properties": {
    "gn:admin1_code":"42",
    "gn:asciiname":"Kalateh-ye Baftiha",
    "gn:country_code":"IR",
    "gn:dem":1323,
    "gn:feature_class":"P",
    "gn:feature_code":"PPL",
    "gn:name":"Kal\u0101teh-ye B\u0101ft\u012bh\u0101",
    "gn:population":0,
    "gn:timezone":"Asia/Tehran",
    "iso:country":"IR",
    "name:fas_x_preferred":[
        "\u06a9\u0644\u0627\u062a\u0647 \u0628\u0627\u0641\u062a\u06cc\u0647\u0627"
    ],
    "name:fas_x_variant":[
        "Kal\u0101teh-ye B\u0101ft\u012bh\u0101"
    ],
    "wof:name":"Kalateh-ye Baftiha",
    "wof:placetype":"locality"
},
  "geometry": {"coordinates":[59.20091,35.24096],"type":"Point"}
}