{
  "type": "Feature",
  "properties": {
    "gn:admin1_code":"29",
    "gn:asciiname":"Bandavan-e Variz",
    "gn:country_code":"IR",
    "gn:dem":2370,
    "gn:feature_class":"P",
    "gn:feature_code":"PPL",
    "gn:name":"Bandav\u0101n-e V\u0101r\u012bz",
    "gn:population":0,
    "gn:timezone":"Asia/Tehran",
    "iso:country":"IR",
    "name:fas_x_preferred":[
        "Bandeb\u0101n"
    ],
    "name:fas_x_variant":[
        "\u0628\u0646\u062f\u0648\u0627\u0646 \u0648\u0627\u0631\u064a\u0632",
        "\u0628\u0646\u062f\u0648\u0627\u0646",
        "\u0628\u0646\u0648\u0646"
    ],
    "name:und_x_variant":[
        "Bandav\u0101n",
        "Bandav\u0101n-e V\u0101r\u012bz",
        "Ban\u016bn"
    ],
    "wof:name":"Bandavan-e Variz",
    "wof:placetype":"locality"
},
  "geometry": {"coordinates":[55.41904,30.38218],"type":"Point"}
}