{
  "type": "Feature",
  "properties": {
    "gn:admin1_code":"28",
    "gn:asciiname":"Kerch",
    "gn:cc2":"IR",
    "gn:country_code":"IR",
    "gn:dem":2191,
    "gn:feature_class":"P",
    "gn:feature_code":"PPL",
    "gn:name":"Kerch",
    "gn:population":0,
    "gn:timezone":"Asia/Tehran",
    "iso:country":"IR",
    "name:ara_x_preferred":[
        "\u06a9\u0631\u062a\u0634"
    ],
    "name:fas_x_preferred":[
        "\u06a9\u0631\u0686"
    ],
    "name:fas_x_variant":[
        "\u062a\u06cc \u06a9\u0631\u062a"
    ],
    "name:und_x_variant":[
        "K\u012brch",
        "Tey Karat"
    ],
    "wof:name":"Kerch",
    "wof:placetype":"locality"
},
  "geometry": {"coordinates":[50.08972,33.21278],"type":"Point"}
}