{
  "type": "Feature",
  "properties": {
    "gn:admin1_code":"7",
    "gn:asciiname":"Nurabad",
    "gn:country_code":"IR",
    "gn:dem":1317,
    "gn:feature_class":"P",
    "gn:feature_code":"PPL",
    "gn:name":"N\u016br\u0101b\u0101d",
    "gn:population":0,
    "gn:timezone":"Asia/Tehran",
    "iso:country":"IR",
    "name:fas_x_preferred":[
        "\u0646\u0648\u0631 \u0622\u0628\u0627\u062f"
    ],
    "name:fas_x_variant":[
        "N\u016br\u0101b\u0101d-e H\u0101rom",
        "N\u016br\u0101b\u0101d"
    ],
    "wof:name":"Nurabad",
    "wof:placetype":"locality"
},
  "geometry": {"coordinates":[53.73754,28.90478],"type":"Point"}
}