{
  "type": "Feature",
  "properties": {
    "gn:admin1_code":"33",
    "gn:asciiname":"Korokchi",
    "gn:country_code":"IR",
    "gn:dem":1425,
    "gn:feature_class":"P",
    "gn:feature_code":"PPL",
    "gn:name":"Korokch\u012b",
    "gn:population":0,
    "gn:timezone":"Asia/Tehran",
    "iso:country":"IR",
    "name:fas_x_preferred":[
        "\u06a9\u0631\u06a9\u0686\u06cc"
    ],
    "name:fas_x_variant":[
        "Korokch\u012b"
    ],
    "wof:name":"Korokchi",
    "wof:placetype":"locality"
},
  "geometry": {"coordinates":[47.5166,37.3527],"type":"Point"}
}