{
  "type": "Feature",
  "properties": {
    "gn:admin1_code":"35.0",
    "gn:asciiname":"Ashgeh Tochal",
    "gn:country_code":"IR",
    "gn:dem":2199,
    "gn:feature_class":"P",
    "gn:feature_code":"PPL",
    "gn:name":"Ashgeh Toch\u0101l",
    "gn:population":0,
    "gn:timezone":"Asia/Tehran",
    "iso:country":"IR",
    "name:fas_x_preferred":[
        "Ashgeh Toch\u0101l"
    ],
    "name:fas_x_variant":[
        "\u0627\u0634\u06af\u0647 \u062a\u0686\u0627\u0644",
        "\u0627\u0634\u06a9\u0647 \u062a\u0686\u0627\u0644"
    ],
    "name:und_x_variant":[
        "\u0627\u0634\u06af\u0647 \u062a\u0686\u0627\u0644",
        "Ashkeh Toch\u0101l"
    ],
    "wof:name":"Ashgeh Tochal",
    "wof:placetype":"locality"
},
  "geometry": {"coordinates":[50.52901,36.82794000000001],"type":"Point"}
}