{
  "type": "Feature",
  "properties": {
    "gn:admin1_code":"4",
    "gn:asciiname":"Piruq",
    "gn:cc2":"IR",
    "gn:country_code":"IR",
    "gn:dem":945,
    "gn:feature_class":"P",
    "gn:feature_code":"PPL",
    "gn:name":"P\u012br\u016bq",
    "gn:population":0,
    "gn:timezone":"Asia/Tehran",
    "iso:country":"IR",
    "name:fas_x_preferred":[
        "P\u012br\u016bq"
    ],
    "name:und_x_variant":[
        "Pir\u016bgh"
    ],
    "wof:name":"Piruq",
    "wof:placetype":"locality"
},
  "geometry": {"coordinates":[59.78333000000001,26.61667000000001],"type":"Point"}
}