{
  "type": "Feature",
  "properties": {
    "gn:admin1_code":"7",
    "gn:asciiname":"Qal`eh-ye Hajji Mohammad Shaf",
    "gn:country_code":"IR",
    "gn:dem":2246,
    "gn:feature_class":"P",
    "gn:feature_code":"PPL",
    "gn:name":"Qal\u2018eh-ye \u1e28\u0101jj\u012b Mo\u1e29ammad Shaf",
    "gn:population":0,
    "gn:timezone":"Asia/Tehran",
    "iso:country":"IR",
    "name:fas_x_preferred":[
        "Qal\u2018eh-ye \u1e28\u0101jj\u012b Mo\u1e29ammad Shaf"
    ],
    "name:und_x_variant":[
        "Qal\u2018eh Haji Muhammad Shaf\u012b\u2018",
        "Qal\u2018eh-ye \u1e28\u0101jj\u012b Shaf"
    ],
    "wof:name":"Qal`eh-ye Hajji Mohammad Shaf",
    "wof:placetype":"locality"
},
  "geometry": {"coordinates":[53.33333,30.05],"type":"Point"}
}