{
  "type": "Feature",
  "properties": {
    "gn:admin1_code":"15",
    "gn:asciiname":"Cheft",
    "gn:country_code":"IR",
    "gn:dem":861,
    "gn:feature_class":"P",
    "gn:feature_code":"PPL",
    "gn:name":"Cheft",
    "gn:population":0,
    "gn:timezone":"Asia/Tehran",
    "iso:country":"IR",
    "wof:name":"Cheft",
    "wof:placetype":"locality"
},
  "geometry": {"coordinates":[49.71667,32.005],"type":"Point"}
}