{
  "type": "Feature",
  "properties": {
    "gn:admin1_code":"29",
    "gn:asciiname":"Chenaran",
    "gn:country_code":"IR",
    "gn:dem":2405,
    "gn:feature_class":"P",
    "gn:feature_code":"PPL",
    "gn:name":"Chen\u0101r\u0101n",
    "gn:population":0,
    "gn:timezone":"Asia/Tehran",
    "iso:country":"IR",
    "name:ara_x_preferred":[
        "\u062a\u0634\u0646\u0627\u0631\u0627\u0646"
    ],
    "name:azb_x_preferred":[
        "\u0686\u06cc\u0646\u0627\u0631\u0627\u0646"
    ],
    "name:aze_x_preferred":[
        "\u00c7inaran"
    ],
    "name:ben_x_preferred":[
        "\u099a\u09c7\u09a8\u09be\u09b0\u09be\u09a8"
    ],
    "name:fas_x_preferred":[
        "\u0686\u0646\u0627\u0631\u0627\u0646"
    ],
    "name:fas_x_variant":[
        "Chen\u0101r\u0101n"
    ],
    "name:fra_x_preferred":[
        "Tchenaran"
    ],
    "name:ita_x_preferred":[
        "Chenaran"
    ],
    "name:mlg_x_preferred":[
        "Chenaran"
    ],
    "name:pnb_x_preferred":[
        "\u0686\u0646\u0627\u0631\u0627\u0646"
    ],
    "name:ron_x_preferred":[
        "Chenaran"
    ],
    "name:tgk_x_preferred":[
        "\u0427\u0438\u043d\u0430\u0440\u043e\u043d"
    ],
    "name:tur_x_preferred":[
        "\u00c7inaran"
    ],
    "name:urd_x_preferred":[
        "\u0686\u0646\u0627\u0631\u0627\u0646"
    ],
    "wof:name":"Chenaran",
    "wof:placetype":"locality"
},
  "geometry": {"coordinates":[57.0322,28.5151],"type":"Point"}
}