{
  "type": "Feature",
  "properties": {
    "gn:admin1_code":"29",
    "gn:asciiname":"Tafazzolabad",
    "gn:country_code":"IR",
    "gn:dem":1710,
    "gn:feature_class":"P",
    "gn:feature_code":"PPL",
    "gn:name":"Tafa\u1e95\u1e95ol\u0101b\u0101d",
    "gn:population":0,
    "gn:timezone":"Asia/Tehran",
    "iso:country":"IR",
    "name:fas_x_preferred":[
        "\u062a\u0641\u0636\u0644 \u0622\u0628\u0627\u062f"
    ],
    "name:fas_x_variant":[
        "Tafa\u1e95\u1e95ol\u0101b\u0101d"
    ],
    "wof:name":"Tafazzolabad",
    "wof:placetype":"locality"
},
  "geometry": {"coordinates":[55.8086,29.2492],"type":"Point"}
}