{
  "type": "Feature",
  "properties": {
    "gn:admin1_code":"44",
    "gn:asciiname":"Ekhvaniyeh",
    "gn:country_code":"IR",
    "gn:dem":1353,
    "gn:feature_class":"P",
    "gn:feature_code":"PPL",
    "gn:name":"Ekhv\u0101n\u012byeh",
    "gn:population":0,
    "gn:timezone":"Asia/Tehran",
    "iso:country":"IR",
    "name:und_x_variant":[
        "Akhav\u0101n\u012byeh",
        "Ekhv\u0101n\u012byeh"
    ],
    "wof:name":"Ekhvaniyeh",
    "wof:placetype":"locality"
},
  "geometry": {"coordinates":[50.48278,35.68917000000001],"type":"Point"}
}