{
  "type": "Feature",
  "properties": {
    "gn:admin1_code":"43",
    "gn:asciiname":"Jajarm",
    "gn:country_code":"IR",
    "gn:dem":933,
    "gn:feature_class":"P",
    "gn:feature_code":"PPLA2",
    "gn:name":"J\u0101jarm",
    "gn:population":0,
    "gn:timezone":"Asia/Tehran",
    "iso:country":"IR",
    "name:fas_x_preferred":[
        "J\u0101jarm"
    ],
    "name:fas_x_variant":[
        "\u062c\u0627\u062c\u0631\u0645"
    ],
    "name:und_x_variant":[
        "\u062c\u0627\u062c\u0631\u0645"
    ],
    "wof:name":"Jajarm",
    "wof:placetype":"locality"
},
  "geometry": {"coordinates":[56.38005,36.95012],"type":"Point"}
}