{
  "type": "Feature",
  "properties": {
    "gn:admin1_code":"32.0",
    "gn:asciiname":"Qeshlaq-e Hajji `Isa",
    "gn:country_code":"IR",
    "gn:dem":149,
    "gn:feature_class":"P",
    "gn:feature_code":"PPL",
    "gn:name":"Qeshl\u0101q-e \u1e28\u0101jj\u012b \u2018\u012as\u00e1",
    "gn:population":0,
    "gn:timezone":"Asia/Tehran",
    "iso:country":"IR",
    "name:fas_x_preferred":[
        "\u0642\u0634\u0644\u0627\u0642 \u062d\u0627\u062c\u06cc \u0639\u06cc\u0633\u06cc"
    ],
    "name:fas_x_variant":[
        "Qeshl\u0101q-e \u1e28\u0101jj\u012b \u2018\u012as\u00e1"
    ],
    "wof:name":"Qeshlaq-e Hajji `Isa",
    "wof:placetype":"locality"
},
  "geometry": {"coordinates":[48.1489,39.4328],"type":"Point"}
}