{
  "type": "Feature",
  "properties": {
    "gn:admin1_code":"7",
    "gn:asciiname":"Jannat Shahr",
    "gn:country_code":"IR",
    "gn:dem":1155,
    "gn:feature_class":"P",
    "gn:feature_code":"PPL",
    "gn:name":"Jannat Shahr",
    "gn:population":0,
    "gn:timezone":"Asia/Tehran",
    "iso:country":"IR",
    "name:fas_x_preferred":[
        "\u062c\u0646\u062a \u0634\u0647\u0631"
    ],
    "wof:name":"Jannat Shahr",
    "wof:placetype":"locality"
},
  "geometry": {"coordinates":[54.6859,28.6528],"type":"Point"}
}