{
  "type": "Feature",
  "properties": {
    "gn:admin1_code":"7",
    "gn:asciiname":"Jannat Shahr",
    "gn:country_code":"IR",
    "gn:dem":1155,
    "gn:feature_class":"P",
    "gn:feature_code":"PPL",
    "gn:name":"Jannat Shahr",
    "gn:population":0,
    "gn:timezone":"Asia/Tehran",
    "iso:country":"IR",
    "name:ara_x_preferred":[
        "\u062c\u0646\u062a \u0634\u0647\u0631"
    ],
    "name:aze_x_preferred":[
        "C\u0259nn\u0259t\u015f\u0259hr"
    ],
    "name:ceb_x_preferred":[
        "Jannat Shahr"
    ],
    "name:fas_x_preferred":[
        "\u062c\u0646\u062a \u0634\u0647\u0631"
    ],
    "name:fas_x_variant":[
        "\u062c\u0646\u062a\u200c\u0634\u0647\u0631"
    ],
    "name:ita_x_preferred":[
        "Jannatshahr"
    ],
    "name:mlg_x_preferred":[
        "Jannat Shahr"
    ],
    "name:msa_x_preferred":[
        "Jannat Shahr"
    ],
    "name:rus_x_preferred":[
        "\u0414\u0436\u0435\u043d\u043d\u0435\u0442\u0448\u0435\u0445\u0440"
    ],
    "name:swe_x_preferred":[
        "Jannat Shahr"
    ],
    "name:tur_x_preferred":[
        "Cennet\u015fehr"
    ],
    "name:urd_x_preferred":[
        "\u062c\u0646\u062a\u200c\u0634\u06c1\u0631"
    ],
    "name:zho_x_preferred":[
        "\u5360\u7d0d\u7279"
    ],
    "wof:name":"Jannat Shahr",
    "wof:placetype":"locality"
},
  "geometry": {"coordinates":[54.6859,28.6528],"type":"Point"}
}