{
  "type": "Feature",
  "properties": {
    "gn:admin1_code":"15",
    "gn:asciiname":"Shajarat",
    "gn:country_code":"IR",
    "gn:dem":47,
    "gn:feature_class":"P",
    "gn:feature_code":"PPL",
    "gn:name":"Shajar\u0101t",
    "gn:population":0,
    "gn:timezone":"Asia/Tehran",
    "iso:country":"IR",
    "name:aze_x_preferred":[
        "\u015e\u00fcceyrat"
    ],
    "name:ceb_x_preferred":[
        "Shajar\u012by\u0101t"
    ],
    "name:fas_x_preferred":[
        "\u0634\u062c\u0631\u06cc\u0651\u0627\u062a"
    ],
    "name:fas_x_variant":[
        "Shaj\u012br\u0101t",
        "Shajar\u012by\u0101t",
        "\u0634\u062c\u0631\u0627\u062a",
        "\u0634\u062c\u06cc\u0631\u0627\u062a"
    ],
    "name:swe_x_preferred":[
        "Shajar\u012by\u0101t"
    ],
    "name:und_x_variant":[
        "Shajeyr\u0101t",
        "Shajar\u0101t"
    ],
    "wof:name":"Shajarat",
    "wof:placetype":"locality"
},
  "geometry": {"coordinates":[49.0849,31.70845],"type":"Point"}
}