{
  "type": "Feature",
  "properties": {
    "gn:admin1_code":"7.0",
    "gn:asciiname":"Seyfabad-e Kohneh",
    "gn:country_code":"IR",
    "gn:dem":871,
    "gn:feature_class":"P",
    "gn:feature_code":"PPL",
    "gn:name":"Seyf\u0101b\u0101d-e Kohneh",
    "gn:population":0,
    "gn:timezone":"Asia/Tehran",
    "iso:country":"IR",
    "name:fas_x_preferred":[
        "Seyf\u0101b\u0101d-e Kohneh"
    ],
    "name:fas_x_variant":[
        "\u0633\u06cc\u0641 \u0622\u0628\u0627\u062f \u06a9\u0647\u0646\u0647"
    ],
    "name:und_x_variant":[
        "\u0633\u06cc\u0641 \u0622\u0628\u0627\u062f \u06a9\u0647\u0646\u0647"
    ],
    "wof:name":"Seyfabad-e Kohneh",
    "wof:placetype":"locality"
},
  "geometry": {"coordinates":[51.70203,29.5127],"type":"Point"}
}