{
  "type": "Feature",
  "properties": {
    "gn:admin1_code":"42",
    "gn:asciiname":"Dandaneh",
    "gn:country_code":"IR",
    "gn:dem":1048,
    "gn:feature_class":"P",
    "gn:feature_code":"PPL",
    "gn:name":"Dand\u0101neh",
    "gn:population":0,
    "gn:timezone":"Asia/Tehran",
    "iso:country":"IR",
    "name:fas_x_preferred":[
        "\u062f\u0646\u062f\u0627\u0646\u0647"
    ],
    "name:fas_x_variant":[
        "Dand\u0101neh"
    ],
    "wof:name":"Dandaneh",
    "wof:placetype":"locality"
},
  "geometry": {"coordinates":[59.44738,36.55486],"type":"Point"}
}