{
  "type": "Feature",
  "properties": {
    "gn:admin1_code":"11.0",
    "gn:asciiname":"Tang Ashkan",
    "gn:country_code":"IR",
    "gn:dem":641,
    "gn:feature_class":"P",
    "gn:feature_code":"PPL",
    "gn:name":"Tang Ashkan",
    "gn:population":0,
    "gn:timezone":"Asia/Tehran",
    "iso:country":"IR",
    "name:fas_x_preferred":[
        "\u062a\u0646\u06af \u0627\u0634\u06a9\u0646"
    ],
    "wof:name":"Tang Ashkan",
    "wof:placetype":"locality"
},
  "geometry": {"coordinates":[55.72973,27.3795],"type":"Point"}
}