{
  "type": "Feature",
  "properties": {
    "gn:admin1_code":"29",
    "gn:asciiname":"Bizhanabad-e `Olya",
    "gn:country_code":"IR",
    "gn:dem":456,
    "gn:feature_class":"P",
    "gn:feature_code":"PPL",
    "gn:name":"B\u012bzhan\u0101b\u0101d-e \u2018Oly\u0101",
    "gn:population":0,
    "gn:timezone":"Asia/Tehran",
    "iso:country":"IR",
    "name:fas_x_preferred":[
        "\u0628\u06cc\u0698\u0646 \u0622\u0628\u0627\u062f \u0639\u0644\u06cc\u0627"
    ],
    "name:fas_x_variant":[
        "B\u012bzhan\u0101b\u0101d-e \u2018Oly\u0101"
    ],
    "wof:name":"Bizhanabad-e `Olya",
    "wof:placetype":"locality"
},
  "geometry": {"coordinates":[58.01696999999999,27.95125],"type":"Point"}
}