{
  "type": "Feature",
  "properties": {
    "gn:admin1_code":"15",
    "gn:asciiname":"Sur-e Meqdad",
    "gn:country_code":"IR",
    "gn:dem":54,
    "gn:feature_class":"P",
    "gn:feature_code":"PPL",
    "gn:name":"S\u016br-e Meqd\u0101d",
    "gn:population":0,
    "gn:timezone":"Asia/Tehran",
    "iso:country":"IR",
    "name:ceb_x_preferred":[
        "S\u016br-e Meghd\u0101d"
    ],
    "name:fas_x_preferred":[
        "\u0633\u0648\u0631 \u0645\u063a\u062f\u0627\u062f"
    ],
    "name:fas_x_variant":[
        "S\u016br-e Meqd\u0101d",
        "S\u016br-e Meghd\u0101d",
        "\u0633\u0648\u0631 \u0645\u0642\u062f\u0627\u062f",
        "\u0633\u0648\u0631\u0645\u0642\u062f\u0627\u062f"
    ],
    "name:swe_x_preferred":[
        "S\u016br-e Meghd\u0101d"
    ],
    "name:und_x_variant":[
        "Var-e Meqd\u0101d",
        "S\u016br-e Moqd\u0101d",
        "S\u016bd Moghd\u0101d"
    ],
    "wof:name":"Sur-e Meqdad",
    "wof:placetype":"locality"
},
  "geometry": {"coordinates":[49.89315,30.52654],"type":"Point"}
}