{
  "type": "Feature",
  "properties": {
    "gn:admin1_code":"35.0",
    "gn:asciiname":"Fil",
    "gn:country_code":"IR",
    "gn:dem":2487,
    "gn:feature_class":"P",
    "gn:feature_code":"PPL",
    "gn:name":"F\u012bl",
    "gn:population":0,
    "gn:timezone":"Asia/Tehran",
    "iso:country":"IR",
    "name:cat_x_preferred":[
        "Fil"
    ],
    "name:ceb_x_preferred":[
        "Fil"
    ],
    "name:dan_x_preferred":[
        "Fil"
    ],
    "name:fas_x_preferred":[
        "\u0641\u06cc\u0644"
    ],
    "name:fas_x_variant":[
        "F\u012bl",
        "Fey\u016bl",
        "\u0641\u06cc\u0648\u0644",
        "\u0641\u06cc\u067e\u0648\u0644"
    ],
    "name:fra_x_preferred":[
        "Fil"
    ],
    "name:nno_x_preferred":[
        "Fil"
    ],
    "name:oci_x_preferred":[
        "Fil"
    ],
    "name:swe_x_preferred":[
        "Fil"
    ],
    "name:tur_x_preferred":[
        "Fil"
    ],
    "name:und_x_variant":[
        "Feyp\u016bl"
    ],
    "name:uzb_x_preferred":[
        "Fil"
    ],
    "wof:name":"Fil",
    "wof:placetype":"locality"
},
  "geometry": {"coordinates":[52.03613,36.17833],"type":"Point"}
}