{
  "type": "Feature",
  "properties": {
    "gn:admin1_code":"42",
    "gn:asciiname":"Narmad",
    "gn:country_code":"IR",
    "gn:dem":1036,
    "gn:feature_class":"P",
    "gn:feature_code":"PPL",
    "gn:name":"N\u0101rmad",
    "gn:population":0,
    "gn:timezone":"Asia/Tehran",
    "iso:country":"IR",
    "name:fas_x_preferred":[
        "N\u0101rmad"
    ],
    "name:guj_x_preferred":[
        "\u0aa8\u0ab0\u0acd\u0aae\u0aa6"
    ],
    "name:hin_x_preferred":[
        "\u0928\u0930\u094d\u092e\u0926"
    ],
    "name:ukr_x_preferred":[
        "\u041d\u0430\u0440\u043c\u0430\u0434\u0430\u0448\u0430\u043d\u043a\u0430\u0440 \u0414\u0430\u0432\u0435"
    ],
    "wof:name":"Narmad",
    "wof:placetype":"locality"
},
  "geometry": {"coordinates":[59.71028,36.44611],"type":"Point"}
}