{
  "type": "Feature",
  "properties": {
    "gn:admin1_code":"33",
    "gn:asciiname":"Qarajeh Arbat",
    "gn:country_code":"IR",
    "gn:dem":1214,
    "gn:feature_class":"P",
    "gn:feature_code":"PPL",
    "gn:name":"Qar\u0101jeh Arb\u0101\u0163",
    "gn:population":0,
    "gn:timezone":"Asia/Tehran",
    "iso:country":"IR",
    "name:fas_x_preferred":[
        "\u0642\u0631\u0627\u062c\u0647 \u0627\u0631\u0628\u0627\u0637"
    ],
    "name:fas_x_variant":[
        "Qar\u0101jeh Arb\u0101\u0163"
    ],
    "wof:name":"Qarajeh Arbat",
    "wof:placetype":"locality"
},
  "geometry": {"coordinates":[47.8509,37.2958],"type":"Point"}
}