{
  "type": "Feature",
  "properties": {
    "gn:admin1_code":"42.0",
    "gn:asciiname":"Estajrud",
    "gn:country_code":"IR",
    "gn:dem":1554,
    "gn:feature_class":"P",
    "gn:feature_code":"PPL",
    "gn:name":"Estajr\u016bd",
    "gn:population":0,
    "gn:timezone":"Asia/Tehran",
    "iso:country":"IR",
    "name:ara_x_preferred":[
        "\u0627\u0633\u062a\u062c\u0631\u0648\u062f"
    ],
    "name:ceb_x_preferred":[
        "Estajr\u016bd"
    ],
    "name:fas_x_preferred":[
        "\u0627\u0633\u062a\u062c\u0631\u0648\u062f"
    ],
    "name:fas_x_variant":[
        "Estajr\u016bd",
        "Esfahr\u016bd"
    ],
    "name:swe_x_preferred":[
        "Estajr\u016bd"
    ],
    "wof:name":"Estajrud",
    "wof:placetype":"locality"
},
  "geometry": {"coordinates":[60.09401999999999,35.06576],"type":"Point"}
}