{
  "type": "Feature",
  "properties": {
    "gn:admin1_code":"11",
    "gn:asciiname":"Bagh-e Keshavarzi",
    "gn:country_code":"IR",
    "gn:dem":36,
    "gn:feature_class":"P",
    "gn:feature_code":"PPL",
    "gn:name":"B\u0101gh-e Kesh\u0101varz\u012b",
    "gn:population":0,
    "gn:timezone":"Asia/Tehran",
    "iso:country":"IR",
    "name:fas_x_preferred":[
        "\u0628\u0627\u063a\u0650 \u0643\u0650\u0634\u0627\u0648\u064e\u0631\u0632\u06cc"
    ],
    "name:fas_x_variant":[
        "B\u0101gh-e Kesh\u0101varz\u012b"
    ],
    "wof:name":"Bagh-e Keshavarzi",
    "wof:placetype":"locality"
},
  "geometry": {"coordinates":[57.01917,27.28306],"type":"Point"}
}