{
  "type": "Feature",
  "properties": {
    "gn:admin1_code":"22.0",
    "gn:asciiname":"Mantaqeh-ye Lavar",
    "gn:country_code":"IR",
    "gn:dem":899,
    "gn:feature_class":"P",
    "gn:feature_code":"PPL",
    "gn:name":"Man\u0163aqeh-ye L\u0101var",
    "gn:population":0,
    "gn:timezone":"Asia/Tehran",
    "iso:country":"IR",
    "name:fas_x_preferred":[
        "\u0645\u0646\u0637\u0642\u0647 \u0644\u0627\u0648\u0631"
    ],
    "name:und_x_variant":[
        "Man\u0163aqeh-ye L\u0101var"
    ],
    "wof:name":"Mantaqeh-ye Lavar",
    "wof:placetype":"locality"
},
  "geometry": {"coordinates":[52.55294,27.61905],"type":"Point"}
}