{
  "type": "Feature",
  "properties": {
    "gn:admin1_code":"13",
    "gn:asciiname":"Molla Karamineh-e Shah Mar",
    "gn:country_code":"IR",
    "gn:dem":865,
    "gn:feature_class":"P",
    "gn:feature_code":"PPL",
    "gn:name":"Moll\u0101 Karam\u012bneh-e Sh\u0101h M\u0101r",
    "gn:population":0,
    "gn:timezone":"Asia/Tehran",
    "iso:country":"IR",
    "name:fas_x_preferred":[
        "\u0645\u0644\u0627 \u06a9\u0631\u0645\u064a\u0646\u0647 \u0634\u0627\u0647 \u0645\u0627\u0631"
    ],
    "name:fas_x_variant":[
        "Moll\u0101 Karam\u012bneh-e Sh\u0101h M\u0101r"
    ],
    "wof:name":"Molla Karamineh-e Shah Mar",
    "wof:placetype":"locality"
},
  "geometry": {"coordinates":[45.99100000000001,34.699],"type":"Point"}
}