{
  "type": "Feature",
  "properties": {
    "gn:admin1_code":"11",
    "gn:asciiname":"Darg Benzu",
    "gn:country_code":"IR",
    "gn:dem":1453,
    "gn:feature_class":"P",
    "gn:feature_code":"PPL",
    "gn:name":"Darg Benz\u016b",
    "gn:population":0,
    "gn:timezone":"Asia/Tehran",
    "iso:country":"IR",
    "name:fas_x_preferred":[
        "\u0628\u0650\u0646\u0632"
    ],
    "name:fas_x_variant":[
        "\u0628\u064f\u0632",
        "\u0628\u064f\u0646\u064e\u0632",
        "\u062f\u0631\u06af \u0628\u0646\u0632\u0648",
        "Darg Benz\u016b"
    ],
    "name:und_x_variant":[
        "Bonaz",
        "Boz",
        "Benz"
    ],
    "wof:name":"Darg Benzu",
    "wof:placetype":"locality"
},
  "geometry": {"coordinates":[57.7544,26.8074],"type":"Point"}
}