{
  "type": "Feature",
  "properties": {
    "gn:admin1_code":"35.0",
    "gn:asciiname":"Lowzeh Sara",
    "gn:country_code":"IR",
    "gn:dem":565,
    "gn:feature_class":"P",
    "gn:feature_code":"PPL",
    "gn:name":"Lowzeh Sar\u0101",
    "gn:population":0,
    "gn:timezone":"Asia/Tehran",
    "iso:country":"IR",
    "name:fas_x_preferred":[
        "\u0644\u0648\u0632\u0647 \u0633\u0631\u0627"
    ],
    "name:fas_x_variant":[
        "Lowzeh Sar\u0101"
    ],
    "wof:name":"Lowzeh Sara",
    "wof:placetype":"locality"
},
  "geometry": {"coordinates":[50.69495,36.77728],"type":"Point"}
}