{
  "type": "Feature",
  "properties": {
    "gn:admin1_code":"22.0",
    "gn:asciiname":"Gudari",
    "gn:country_code":"IR",
    "gn:dem":41,
    "gn:feature_class":"P",
    "gn:feature_code":"PPL",
    "gn:name":"G\u016bdar\u012b",
    "gn:population":0,
    "gn:timezone":"Asia/Tehran",
    "iso:country":"IR",
    "name:cat_x_preferred":[
        "Gudari"
    ],
    "name:ceb_x_preferred":[
        "Gudari"
    ],
    "name:eus_x_preferred":[
        "Gudari"
    ],
    "name:fas_x_preferred":[
        "\u06af\u0648\u062f\u0631\u06cc"
    ],
    "name:fas_x_variant":[
        "G\u016bdar\u012b"
    ],
    "name:spa_x_preferred":[
        "Gudari"
    ],
    "name:swe_x_preferred":[
        "Gudari"
    ],
    "wof:name":"Gudari",
    "wof:placetype":"locality"
},
  "geometry": {"coordinates":[50.5008,29.7916],"type":"Point"}
}