{
  "type": "Feature",
  "properties": {
    "gn:admin1_code":"7.0",
    "gn:asciiname":"Anarak",
    "gn:country_code":"IR",
    "gn:dem":1587,
    "gn:feature_class":"P",
    "gn:feature_code":"PPL",
    "gn:name":"An\u0101rak",
    "gn:population":0,
    "gn:timezone":"Asia/Tehran",
    "iso:country":"IR",
    "name:ara_x_preferred":[
        "\u0623\u0646\u0627\u0631\u0643"
    ],
    "name:fas_x_preferred":[
        "\u0627\u0646\u0627\u0631\u06a9"
    ],
    "name:fas_x_variant":[
        "N\u0101rak",
        "An\u0101rak"
    ],
    "name:msa_x_preferred":[
        "Anarak"
    ],
    "wof:name":"Anarak",
    "wof:placetype":"locality"
},
  "geometry": {"coordinates":[53.2404,29.7932],"type":"Point"}
}