{
  "type": "Feature",
  "properties": {
    "gn:admin1_code":"42",
    "gn:asciiname":"Khorram Beg",
    "gn:country_code":"IR",
    "gn:dem":1174,
    "gn:feature_class":"P",
    "gn:feature_code":"PPL",
    "gn:name":"Khorram Beg",
    "gn:population":0,
    "gn:timezone":"Asia/Tehran",
    "iso:country":"IR",
    "name:fas_x_preferred":[
        "\u062e\u0631\u0645 \u0628\u06af"
    ],
    "wof:name":"Khorram Beg",
    "wof:placetype":"locality"
},
  "geometry": {"coordinates":[58.8084,36.16758],"type":"Point"}
}