{
  "type": "Feature",
  "properties": {
    "gn:admin1_code":"8.0",
    "gn:asciiname":"Sukhteh Kosh",
    "gn:country_code":"IR",
    "gn:dem":1787,
    "gn:feature_class":"P",
    "gn:feature_code":"PPL",
    "gn:name":"S\u016bkhteh Kosh",
    "gn:population":0,
    "gn:timezone":"Asia/Tehran",
    "iso:country":"IR",
    "name:fas_x_preferred":[
        "S\u016bkhteh Kosh"
    ],
    "name:fas_x_variant":[
        "\u0633\u0648\u062e\u062a\u0647 \u06a9\u0634"
    ],
    "name:msa_x_preferred":[
        "Sukhteh Kosh"
    ],
    "name:ukr_x_preferred":[
        "\u0421\u0443\u0445\u0442\u0435-\u041a\u043e\u0448"
    ],
    "wof:name":"Sukhteh Kosh",
    "wof:placetype":"locality"
},
  "geometry": {"coordinates":[50.21654,36.77245],"type":"Point"}
}