{
  "type": "Feature",
  "properties": {
    "gn:admin1_code":"42",
    "gn:asciiname":"Tandok",
    "gn:country_code":"IR",
    "gn:dem":1779,
    "gn:feature_class":"P",
    "gn:feature_code":"PPL",
    "gn:name":"Tandok",
    "gn:population":0,
    "gn:timezone":"Asia/Tehran",
    "iso:country":"IR",
    "name:fas_x_preferred":[
        "\u062a\u0646\u062f\u0648\u06a9"
    ],
    "name:fas_x_variant":[
        "Tond\u016bk",
        "\u062a\u0646\u062f\u06a9"
    ],
    "name:und_x_variant":[
        "Tondok"
    ],
    "wof:name":"Tandok",
    "wof:placetype":"locality"
},
  "geometry": {"coordinates":[57.7799,35.81286],"type":"Point"}
}