{
  "type": "Feature",
  "properties": {
    "gn:admin1_code":"15",
    "gn:asciiname":"Tarkab",
    "gn:country_code":"IR",
    "gn:dem":787,
    "gn:feature_class":"P",
    "gn:feature_code":"PPL",
    "gn:name":"Tark\u0101b",
    "gn:population":0,
    "gn:timezone":"Asia/Tehran",
    "iso:country":"IR",
    "name:fas_x_preferred":[
        "Tark\u0101b"
    ],
    "name:fas_x_variant":[
        "Tarak\u0101b",
        "\u062a\u0631\u06a9\u0627\u0628"
    ],
    "name:und_x_variant":[
        "Tarakow"
    ],
    "wof:name":"Tarkab",
    "wof:placetype":"locality"
},
  "geometry": {"coordinates":[49.77436,31.71063],"type":"Point"}
}