{
  "type": "Feature",
  "properties": {
    "gn:admin1_code":"7",
    "gn:asciiname":"Deh Kohneh",
    "gn:country_code":"IR",
    "gn:dem":487,
    "gn:feature_class":"P",
    "gn:feature_code":"PPL",
    "gn:name":"Deh Kohneh",
    "gn:population":0,
    "gn:timezone":"Asia/Tehran",
    "iso:country":"IR",
    "name:ara_x_preferred":[
        "\u062f\u0647 \u06a9\u0647\u0646\u0647"
    ],
    "name:fas_x_preferred":[
        "\u062f\u0647 \u06a9\u0647\u0646\u0647"
    ],
    "name:fas_x_variant":[
        "\u062f\u0647\u200c\u06a9\u0647\u0646\u0647"
    ],
    "name:msa_x_preferred":[
        "Deh Kohneh"
    ],
    "wof:name":"Deh Kohneh",
    "wof:placetype":"locality"
},
  "geometry": {"coordinates":[53.3583,27.4686],"type":"Point"}
}