{
  "type": "Feature",
  "properties": {
    "gn:admin1_code":"1",
    "gn:asciiname":"Qalat",
    "gn:country_code":"IR",
    "gn:dem":1563,
    "gn:feature_class":"P",
    "gn:feature_code":"PPL",
    "gn:name":"Qal\u0101t",
    "gn:population":0,
    "gn:timezone":"Asia/Tehran",
    "iso:country":"IR",
    "name:cat_x_preferred":[
        "Qalat"
    ],
    "name:ceb_x_preferred":[
        "Qalat"
    ],
    "name:fas_x_preferred":[
        "\u0642\u0644\u0627\u062a"
    ],
    "name:fas_x_variant":[
        "Qal\u0101t",
        "\u06a9\u0644\u0627\u062a"
    ],
    "name:nno_x_preferred":[
        "Qalat"
    ],
    "name:pol_x_preferred":[
        "Kalat"
    ],
    "name:rus_x_preferred":[
        "\u041a\u0430\u043b\u0430\u0442"
    ],
    "name:swe_x_preferred":[
        "Qalat"
    ],
    "name:ukr_x_preferred":[
        "\u041a\u0430\u043b\u0430\u0442"
    ],
    "name:urd_x_preferred":[
        "\u0642\u0644\u0627\u062a"
    ],
    "wof:name":"Qalat",
    "wof:placetype":"locality"
},
  "geometry": {"coordinates":[45.4041,36.5043],"type":"Point"}
}