{
  "type": "Feature",
  "properties": {
    "gn:admin1_code":"33",
    "gn:asciiname":"Chahar Khanevar",
    "gn:country_code":"IR",
    "gn:dem":1827,
    "gn:feature_class":"P",
    "gn:feature_code":"PPL",
    "gn:name":"Chah\u0101r Kh\u0101nev\u0101r",
    "gn:population":0,
    "gn:timezone":"Asia/Tehran",
    "iso:country":"IR",
    "name:fas_x_preferred":[
        "\u0686\u0647\u0627\u0631 \u062e\u0627\u0646\u0648\u0627\u0631"
    ],
    "name:fas_x_variant":[
        "Chah\u0101r Kh\u0101nev\u0101r"
    ],
    "wof:name":"Chahar Khanevar",
    "wof:placetype":"locality"
},
  "geometry": {"coordinates":[47.9611,37.6325],"type":"Point"}
}