{
  "type": "Feature",
  "properties": {
    "gn:admin1_code":"26.0",
    "gn:asciiname":"Kordabad",
    "gn:country_code":"IR",
    "gn:dem":1163,
    "gn:feature_class":"P",
    "gn:feature_code":"PPL",
    "gn:name":"Kord\u0101b\u0101d",
    "gn:population":0,
    "gn:timezone":"Asia/Tehran",
    "iso:country":"IR",
    "name:fas_x_preferred":[
        "\u06a9\u0631\u062f \u0622\u0628\u0627\u062f"
    ],
    "name:fas_x_variant":[
        "Kord\u0101b\u0101d",
        "\u06a9\u0631\u062f\u0622\u0628\u0627\u062f"
    ],
    "wof:name":"Kordabad",
    "wof:placetype":"locality"
},
  "geometry": {"coordinates":[50.97895,35.66226],"type":"Point"}
}