{
  "type": "Feature",
  "properties": {
    "gn:admin1_code":"8",
    "gn:asciiname":"Ayurni",
    "gn:country_code":"IR",
    "gn:dem":703,
    "gn:feature_class":"P",
    "gn:feature_code":"PPL",
    "gn:name":"Ay\u016brn\u012b",
    "gn:population":0,
    "gn:timezone":"Asia/Tehran",
    "iso:country":"IR",
    "name:fas_x_preferred":[
        "\u0627\u06cc\u0648\u0631\u0646\u06cc"
    ],
    "name:fas_x_variant":[
        "Ay\u016brn\u012b-ye V\u012bznah",
        "Ay\u016brn\u012b"
    ],
    "wof:name":"Ayurni",
    "wof:placetype":"locality"
},
  "geometry": {"coordinates":[48.778,38.2466],"type":"Point"}
}