{
  "type": "Feature",
  "properties": {
    "gn:admin1_code":"16.0",
    "gn:asciiname":"Owghal",
    "gn:country_code":"IR",
    "gn:dem":1541,
    "gn:feature_class":"P",
    "gn:feature_code":"PPL",
    "gn:name":"Owghal",
    "gn:population":0,
    "gn:timezone":"Asia/Tehran",
    "iso:country":"IR",
    "name:fas_x_preferred":[
        "\u0627\u0648\u063a\u0644"
    ],
    "wof:name":"Owghal",
    "wof:placetype":"locality"
},
  "geometry": {"coordinates":[45.662,36.0254],"type":"Point"}
}