{
  "type": "Feature",
  "properties": {
    "gn:admin1_code":"11",
    "gn:asciiname":"Kuh Dazan",
    "gn:country_code":"IR",
    "gn:dem":323,
    "gn:feature_class":"P",
    "gn:feature_code":"PPL",
    "gn:name":"K\u016bh D\u0101z\u0101n",
    "gn:population":0,
    "gn:timezone":"Asia/Tehran",
    "iso:country":"IR",
    "name:ara_x_preferred":[
        "\u0643\u0648\u0647 \u062f\u0627\u0632\u0627\u0646"
    ],
    "name:ceb_x_preferred":[
        "K\u016bh D\u0101z\u0101n"
    ],
    "name:fas_x_preferred":[
        "\u0643\u0648\u0647 \u062f\u0627\u0632\u0627\u0646"
    ],
    "name:fas_x_variant":[
        "K\u016bh D\u0101z\u0101n",
        "\u06a9\u0648\u0647 \u062f\u0627\u0632\u0627\u0646"
    ],
    "name:msa_x_preferred":[
        "Kuh Dazan"
    ],
    "name:swe_x_preferred":[
        "K\u016bh D\u0101z\u0101n"
    ],
    "wof:name":"Kuh Dazan",
    "wof:placetype":"locality"
},
  "geometry": {"coordinates":[56.81361,27.6375],"type":"Point"}
}