{
  "type": "Feature",
  "properties": {
    "gn:admin1_code":"42.0",
    "gn:asciiname":"Taqiabad",
    "gn:country_code":"IR",
    "gn:dem":691,
    "gn:feature_class":"P",
    "gn:feature_code":"PPL",
    "gn:name":"Taq\u012b\u0101b\u0101d",
    "gn:population":0,
    "gn:timezone":"Asia/Tehran",
    "iso:country":"IR",
    "name:fas_x_preferred":[
        "\u062a\u0642\u06cc \u0622\u0628\u0627\u062f"
    ],
    "name:fas_x_variant":[
        "Taq\u012b\u0101b\u0101d",
        "\u062a\u0642\u06cc\u200c\u0622\u0628\u0627\u062f"
    ],
    "name:und_x_variant":[
        "Mamn\u016b\u2018eh"
    ],
    "wof:name":"Taqiabad",
    "wof:placetype":"locality"
},
  "geometry": {"coordinates":[60.1717,36.5978],"type":"Point"}
}