{
  "type": "Feature",
  "properties": {
    "gn:admin1_code":"35.0",
    "gn:asciiname":"Bab-e Rubar",
    "gn:country_code":"IR",
    "gn:dem":2170,
    "gn:feature_class":"P",
    "gn:feature_code":"PPL",
    "gn:name":"B\u0101b-e R\u016bb\u0101r",
    "gn:population":0,
    "gn:timezone":"Asia/Tehran",
    "iso:country":"IR",
    "name:fas_x_preferred":[
        "\u0628\u0627\u0628 \u0631\u0648\u062f\u0628\u0627\u0631"
    ],
    "name:fas_x_variant":[
        "B\u0101b R\u016bdb\u0101r",
        "\u0628\u0627\u0628 \u0631\u0648\u0628\u0627\u0631"
    ],
    "name:und_x_variant":[
        "B\u0101b-e R\u016bb\u0101r"
    ],
    "wof:name":"Bab-e Rubar",
    "wof:placetype":"locality"
},
  "geometry": {"coordinates":[51.01162,36.49874000000001],"type":"Point"}
}