{
  "type": "Feature",
  "properties": {
    "gn:admin1_code":"4",
    "gn:asciiname":"Kurdan",
    "gn:country_code":"IR",
    "gn:dem":616,
    "gn:feature_class":"P",
    "gn:feature_code":"PPL",
    "gn:name":"K\u016brd\u0101n",
    "gn:population":0,
    "gn:timezone":"Asia/Tehran",
    "iso:country":"IR",
    "name:fas_x_preferred":[
        "\u06a9\u0648\u0631\u062f\u0627\u0646"
    ],
    "name:fas_x_variant":[
        "K\u016brd\u0101n",
        "\u06a9\u0647\u0646\u0627\u0646 \u06a9\u0648\u0631\u062f\u0627\u0646"
    ],
    "name:und_x_variant":[
        "Kahn\u0101n-e K\u016brd\u0101n"
    ],
    "wof:name":"Kurdan",
    "wof:placetype":"locality"
},
  "geometry": {"coordinates":[59.05951999999999,26.78415],"type":"Point"}
}