{
  "type": "Feature",
  "properties": {
    "gn:admin1_code":"15",
    "gn:asciiname":"Qebleh'i-ye Sofla",
    "gn:country_code":"IR",
    "gn:dem":287,
    "gn:feature_class":"P",
    "gn:feature_code":"PPL",
    "gn:name":"Qebleh\u2019\u012b-ye Sofl\u00e1",
    "gn:population":0,
    "gn:timezone":"Asia/Tehran",
    "iso:country":"IR",
    "name:fas_x_preferred":[
        "\u0642\u0628\u0644\u0647\u06cc \u067e\u0627\u0626\u06cc\u0646"
    ],
    "name:fas_x_variant":[
        "Qebleh\u2019\u012b-ye P\u0101\u2019\u012bn",
        "Qebleh\u012b-ye P\u0101\u2019\u012bn",
        "\u0642\u0628\u0644\u0647 \u0627\u06cc \u0633\u0641\u0644\u06cc"
    ],
    "name:und_x_variant":[
        "Qebleh E\u012b P\u0101\u2019\u012bn",
        "Qebleh\u2019\u012b-ye Sofl\u00e1"
    ],
    "wof:name":"Qebleh'i-ye Sofla",
    "wof:placetype":"locality"
},
  "geometry": {"coordinates":[49.1353,32.07947],"type":"Point"}
}