{
  "type": "Feature",
  "properties": {
    "gn:admin1_code":"1.0",
    "gn:asciiname":"Qamtareh",
    "gn:country_code":"IR",
    "gn:dem":1834,
    "gn:feature_class":"P",
    "gn:feature_code":"PPL",
    "gn:name":"Qam\u0163areh",
    "gn:population":0,
    "gn:timezone":"Asia/Tehran",
    "iso:country":"IR",
    "name:azb_x_preferred":[
        "\u0642\u0645\u0637\u0631\u0647(\u0633\u0648\u06cc\u0648\u0642\u200c\u0628\u0648\u0644\u0627\u0642)"
    ],
    "name:aze_x_preferred":[
        "Q\u0259mtar\u0259"
    ],
    "name:ceb_x_preferred":[
        "Qam\u0163areh"
    ],
    "name:ckb_x_preferred":[
        "\u0642\u06d5\u0645\u062a\u06d5\u0631\u06ce"
    ],
    "name:fas_x_preferred":[
        "\u0642\u064e\u0645\u0637\u064e\u0631\u0650\u0647"
    ],
    "name:fas_x_variant":[
        "\u0642\u0645\u0637\u0631\u0647",
        "Qam\u0163areh"
    ],
    "name:msa_x_preferred":[
        "Qamtareh"
    ],
    "name:swe_x_preferred":[
        "Qam\u0163areh"
    ],
    "wof:name":"Qamtareh",
    "wof:placetype":"locality"
},
  "geometry": {"coordinates":[45.9113,36.7171],"type":"Point"}
}