{
  "type": "Feature",
  "properties": {
    "gn:admin1_code":"1.0",
    "gn:asciiname":"Qamtareh",
    "gn:country_code":"IR",
    "gn:dem":1834,
    "gn:feature_class":"P",
    "gn:feature_code":"PPL",
    "gn:name":"Qam\u0163areh",
    "gn:population":0,
    "gn:timezone":"Asia/Tehran",
    "iso:country":"IR",
    "name:fas_x_preferred":[
        "\u0642\u064e\u0645\u0637\u064e\u0631\u0650\u0647"
    ],
    "name:fas_x_variant":[
        "\u0642\u0645\u0637\u0631\u0647",
        "Qam\u0163areh"
    ],
    "wof:name":"Qamtareh",
    "wof:placetype":"locality"
},
  "geometry": {"coordinates":[45.9113,36.7171],"type":"Point"}
}