{
  "type": "Feature",
  "properties": {
    "gn:admin1_code":"4",
    "gn:asciiname":"Nosratabad-e Bala",
    "gn:cc2":"IR",
    "gn:country_code":"IR",
    "gn:dem":1114,
    "gn:feature_class":"P",
    "gn:feature_code":"PPL",
    "gn:name":"No\u015frat\u0101b\u0101d-e B\u0101l\u0101",
    "gn:population":0,
    "gn:timezone":"Asia/Tehran",
    "iso:country":"IR",
    "name:fas_x_preferred":[
        "No\u015frat\u0101b\u0101d-e B\u0101l\u0101"
    ],
    "name:und_x_variant":[
        "No\u015frat\u0101b\u0101d"
    ],
    "wof:name":"Nosratabad-e Bala",
    "wof:placetype":"locality"
},
  "geometry": {"coordinates":[59.98333,29.88333],"type":"Point"}
}