{
  "type": "Feature",
  "properties": {
    "gn:admin1_code":"33",
    "gn:asciiname":"Tazeh Kand-e `Isa Khani",
    "gn:country_code":"IR",
    "gn:dem":1283,
    "gn:feature_class":"P",
    "gn:feature_code":"PPL",
    "gn:name":"T\u0101zeh Kand-e \u2018\u012as\u00e1 Kh\u0101n\u012b",
    "gn:population":0,
    "gn:timezone":"Asia/Tehran",
    "iso:country":"IR",
    "name:ara_x_preferred":[
        "\u062e\u0627\u0646\u0629 \u0628\u0631\u0642 \u0639\u064a\u0633\u064a \u062e\u0627\u0646\u064a"
    ],
    "name:fas_x_preferred":[
        "\u062a\u0627\u0632\u0647 \u06a9\u0646\u062f \u0639\u06cc\u0633\u06cc \u062e\u0627\u0646\u06cc"
    ],
    "name:fas_x_variant":[
        "\u2018\u012as\u00e1 Kh\u0101n\u012b",
        "T\u0101zeh Kand-e \u2018\u012as\u00e1 Kh\u0101n\u012b",
        "\u062e\u0627\u0646\u0647 \u0628\u0631\u0642 \u0639\u06cc\u0633\u06cc \u062e\u0627\u0646\u06cc",
        "\u062e\u0627\u0646\u0647\u200c\u0628\u0631\u0642 \u0639\u06cc\u0633\u06cc\u200c\u062e\u0627\u0646\u06cc"
    ],
    "name:msa_x_preferred":[
        "Khaneh-ye Barq-e Isa Khani"
    ],
    "name:und_x_variant":[
        "Kh\u0101neh-ye Barq-e \u2018\u012as\u00e1 Kh\u0101n\u012b"
    ],
    "wof:name":"Tazeh Kand-e `Isa Khani",
    "wof:placetype":"locality"
},
  "geometry": {"coordinates":[46.0108,37.3069],"type":"Point"}
}