{
  "type": "Feature",
  "properties": {
    "gn:admin1_code":"5",
    "gn:asciiname":"Sar Bisheh-ye Sofla",
    "gn:country_code":"IR",
    "gn:dem":1629,
    "gn:feature_class":"P",
    "gn:feature_code":"PPL",
    "gn:name":"Sar B\u012bsheh-ye Sofl\u00e1",
    "gn:population":0,
    "gn:timezone":"Asia/Tehran",
    "iso:country":"IR",
    "name:fas_x_preferred":[
        "Sar B\u012bsheh-ye Sofl\u00e1"
    ],
    "name:fas_x_variant":[
        "\u0633\u0631 \u0628\u06cc\u0634\u0647 \u0633\u0641\u0644\u06cc",
        "\u0633\u0631\u0628\u06cc\u0634\u0647 \u0633\u0641\u0644\u06cc"
    ],
    "wof:name":"Sar Bisheh-ye Sofla",
    "wof:placetype":"locality"
},
  "geometry": {"coordinates":[50.34303,31.26771],"type":"Point"}
}