{
  "type": "Feature",
  "properties": {
    "gn:admin1_code":"9",
    "gn:asciiname":"Kaslan Qiyeh",
    "gn:country_code":"IR",
    "gn:dem":2124,
    "gn:feature_class":"P",
    "gn:feature_code":"PPL",
    "gn:name":"Kasl\u0101n Q\u012byeh",
    "gn:population":0,
    "gn:timezone":"Asia/Tehran",
    "iso:country":"IR",
    "name:fas_x_preferred":[
        "\u06a9\u0633\u0644\u0627\u0646 \u0642\u06cc\u0647"
    ],
    "name:fas_x_variant":[
        "Kasl\u0101n Qayeh"
    ],
    "name:und_x_variant":[
        "Kar\u0101sangiyeh",
        "Kasl\u0101nqayah",
        "Kaslan Fih",
        "Kasl\u0101n Q\u012byeh"
    ],
    "wof:name":"Kaslan Qiyeh",
    "wof:placetype":"locality"
},
  "geometry": {"coordinates":[48.18532,35.19363],"type":"Point"}
}