{
  "type": "Feature",
  "properties": {
    "gn:admin1_code":"8",
    "gn:asciiname":"Vardum",
    "gn:country_code":"IR",
    "gn:dem":50,
    "gn:feature_class":"P",
    "gn:feature_code":"PPL",
    "gn:name":"Vard\u016bm",
    "gn:population":0,
    "gn:timezone":"Asia/Tehran",
    "iso:country":"IR",
    "name:fas_x_preferred":[
        "\u0648\u0634\u0645\u0647 \u0633\u0631\u0627"
    ],
    "name:fas_x_variant":[
        "Voshmeh Sar\u0101",
        "\u0648\u0631\u062f\u0648\u0645"
    ],
    "name:msa_x_preferred":[
        "Vardum"
    ],
    "name:ukr_x_preferred":[
        "\u0412\u0430\u0440\u0434\u0443\u043c"
    ],
    "name:und_x_variant":[
        "Vard\u016bm"
    ],
    "wof:name":"Vardum",
    "wof:placetype":"locality"
},
  "geometry": {"coordinates":[49.15416,37.34015],"type":"Point"}
}