{
  "type": "Feature",
  "properties": {
    "gn:admin1_code":"29",
    "gn:asciiname":"Seyyedabad",
    "gn:country_code":"IR",
    "gn:dem":658,
    "gn:feature_class":"P",
    "gn:feature_code":"PPL",
    "gn:name":"Seyyed\u0101b\u0101d",
    "gn:population":0,
    "gn:timezone":"Asia/Tehran",
    "iso:country":"IR",
    "name:aze_x_preferred":[
        "Seyidabad"
    ],
    "name:fas_x_preferred":[
        "\u0633\u06cc\u062f \u0622\u0628\u0627\u062f"
    ],
    "name:fas_x_variant":[
        "Seyyed\u0101b\u0101d-e P\u0101\u2019\u012bn",
        "Seyyed\u0101b\u0101d",
        "\u0633\u0639\u06cc\u062f \u0622\u0628\u0627\u062f \u0633\u0641\u0644\u06cc",
        "\u0633\u06cc\u062f\u0622\u0628\u0627\u062f"
    ],
    "name:und_x_variant":[
        "Sa\u2018\u012bd\u0101b\u0101d",
        "Saiyid\u0101b\u0101d",
        "Sa\u2018\u012bd\u0101b\u0101d-e \u2018Oly\u0101",
        "Sa\u2018\u012bd\u0101b\u0101d-e Sofl\u0101",
        "Sa\u2018\u012bd\u0101b\u0101d-e Sofl\u00e1"
    ],
    "wof:name":"Seyyedabad",
    "wof:placetype":"locality"
},
  "geometry": {"coordinates":[57.4745,28.1941],"type":"Point"}
}