{
  "type": "Feature",
  "properties": {
    "gn:admin1_code":"7",
    "gn:asciiname":"Chah Bidu",
    "gn:country_code":"IR",
    "gn:dem":465,
    "gn:feature_class":"P",
    "gn:feature_code":"PPL",
    "gn:name":"Ch\u0101h B\u012bd\u016b",
    "gn:population":0,
    "gn:timezone":"Asia/Tehran",
    "iso:country":"IR",
    "name:fas_x_preferred":[
        "\u0686\u0627\u0647 \u0628\u06cc\u062f\u0648"
    ],
    "name:fas_x_variant":[
        "Ch\u0101h-e B\u012bd\u016b",
        "Ch\u0101h B\u012bd\u016b",
        "\u0628\u06cc\u062f\u0648"
    ],
    "name:msa_x_preferred":[
        "Chah Bidu"
    ],
    "name:und_x_variant":[
        "Chah Bidoo",
        "Ch\u0101h-i-B\u012bdu"
    ],
    "wof:name":"Chah Bidu",
    "wof:placetype":"locality"
},
  "geometry": {"coordinates":[52.6268,27.7054],"type":"Point"}
}