{
  "type": "Feature",
  "properties": {
    "gn:admin1_code":"36",
    "gn:asciiname":"Chuzuk",
    "gn:country_code":"IR",
    "gn:dem":1751,
    "gn:feature_class":"P",
    "gn:feature_code":"PPL",
    "gn:name":"Ch\u016bz\u016bk",
    "gn:population":0,
    "gn:timezone":"Asia/Tehran",
    "iso:country":"IR",
    "name:azb_x_preferred":[
        "\u0686\u0648\u0632\u06a9"
    ],
    "name:fas_x_preferred":[
        "\u0686\u0648\u0632\u064e\u0643"
    ],
    "name:fas_x_variant":[
        "\u0686\u0648\u0632\u0648\u0643",
        "\u062c\u0648\u0631\u064e\u0643",
        "\u062c\u0648\u0631\u064a\u0643",
        "\u0686\u0648\u0632\u064f\u0643",
        "\u0686\u0648\u0632\u06a9",
        "Ch\u016bzak",
        "\u0686\u0648\u0632\u0648\u06a9"
    ],
    "name:und_x_variant":[
        "J\u016brak",
        "Ch\u016bz\u016bk",
        "J\u016br\u012bk",
        "Chizuk",
        "Ch\u016bzok"
    ],
    "wof:name":"Chuzuk",
    "wof:placetype":"locality"
},
  "geometry": {"coordinates":[48.43353,36.30174],"type":"Point"}
}