{
  "type": "Feature",
  "properties": {
    "gn:admin1_code":"35.0",
    "gn:asciiname":"Shegta",
    "gn:country_code":"IR",
    "gn:dem":181,
    "gn:feature_class":"P",
    "gn:feature_code":"PPL",
    "gn:name":"Shegt\u0101",
    "gn:population":0,
    "gn:timezone":"Asia/Tehran",
    "iso:country":"IR",
    "name:ceb_x_preferred":[
        "Shegt\u0101"
    ],
    "name:fas_x_preferred":[
        "\u0634\u0650\u0643\u062a\u0627"
    ],
    "name:fas_x_variant":[
        "\u0634\u0650\u0643\u0650\u062a\u0627",
        "\u0634\u06af\u062a\u0627",
        "Shekt\u0101",
        "Shegt\u0101",
        "\u0634\u06a9\u062a\u0627"
    ],
    "name:mzn_x_preferred":[
        "\u0634\u06a9\u062a\u0627"
    ],
    "name:swe_x_preferred":[
        "Shegt\u0101"
    ],
    "name:und_x_variant":[
        "Sheket\u0101"
    ],
    "wof:name":"Shegta",
    "wof:placetype":"locality"
},
  "geometry": {"coordinates":[53.07865,36.46752],"type":"Point"}
}