{
  "type": "Feature",
  "properties": {
    "gn:admin1_code":"29",
    "gn:asciiname":"Hoseynabad",
    "gn:country_code":"IR",
    "gn:dem":1761,
    "gn:feature_class":"P",
    "gn:feature_code":"PPL",
    "gn:name":"\u1e28oseyn\u0101b\u0101d",
    "gn:population":0,
    "gn:timezone":"Asia/Tehran",
    "iso:country":"IR",
    "name:aze_x_preferred":[
        "H\u00fcseynabad"
    ],
    "name:ceb_x_preferred":[
        "Hoseynabad"
    ],
    "name:fas_x_preferred":[
        "\u062d\u0633\u06cc\u0646 \u0622\u0628\u0627\u062f"
    ],
    "name:fas_x_variant":[
        "\u1e28oseyn\u0101b\u0101d",
        "\u062d\u0633\u06cc\u0646\u200c\u0622\u0628\u0627\u062f"
    ],
    "name:mzn_x_preferred":[
        "\u062d\u0633\u06cc\u0646\u200c\u0622\u0628\u0627\u062f"
    ],
    "name:swe_x_preferred":[
        "Hoseynabad"
    ],
    "name:und_x_variant":[
        "\u1e28oseyn\u0101b\u0101d Kh\u0101n",
        "\u1e28oseyn\u0101b\u0101d-e Zang\u012b\u0101b\u0101d",
        "Husain\u0101b\u0101d",
        "\u1e28oseyn\u0101b\u0101d-e B\u012bglar B\u012bg\u012b",
        "Hosein Abad Zangi Abad",
        "\u1e28oseyn\u0101b\u0101d-e Kh\u0101n"
    ],
    "wof:name":"Hoseynabad",
    "wof:placetype":"locality"
},
  "geometry": {"coordinates":[56.9802,30.4216],"type":"Point"}
}