{
  "type": "Feature",
  "properties": {
    "gn:admin1_code":"29",
    "gn:asciiname":"Kesht",
    "gn:cc2":"IR",
    "gn:country_code":"IR",
    "gn:dem":2418,
    "gn:feature_class":"P",
    "gn:feature_code":"PPL",
    "gn:name":"Kesht",
    "gn:population":0,
    "gn:timezone":"Asia/Tehran",
    "iso:country":"IR",
    "name:und_x_variant":[
        "Kesht-e Jab\u0101l B\u0101rez",
        "Kashit Jabalbarez",
        "Kesht"
    ],
    "wof:name":"Kesht",
    "wof:placetype":"locality"
},
  "geometry": {"coordinates":[57.97639,28.76972],"type":"Point"}
}