{
  "type": "Feature",
  "properties": {
    "gn:admin1_code":"1.0",
    "gn:asciiname":"Guranabad-e Qazi",
    "gn:country_code":"IR",
    "gn:dem":1326,
    "gn:feature_class":"P",
    "gn:feature_code":"PPL",
    "gn:name":"G\u016br\u0101n\u0101b\u0101d-e Q\u0101\u1e95\u012b",
    "gn:population":0,
    "gn:timezone":"Asia/Tehran",
    "iso:country":"IR",
    "name:fas_x_preferred":[
        "\u06af\u0648\u0631\u0627\u0646 \u0622\u0628\u0627\u062f \u0642\u0627\u0636\u06cc"
    ],
    "name:fas_x_variant":[
        "G\u016br\u0101n\u0101b\u0101d-e Q\u0101\u1e95\u012b"
    ],
    "wof:name":"Guranabad-e Qazi",
    "wof:placetype":"locality"
},
  "geometry": {"coordinates":[45.3301,36.9699],"type":"Point"}
}