{
  "type": "Feature",
  "properties": {
    "gn:admin1_code":"13",
    "gn:asciiname":"Sameleh-ye Sofla",
    "gn:country_code":"IR",
    "gn:dem":1586,
    "gn:feature_class":"P",
    "gn:feature_code":"PPL",
    "gn:name":"S\u0101meleh-ye Sofl\u00e1",
    "gn:population":0,
    "gn:timezone":"Asia/Tehran",
    "iso:country":"IR",
    "name:ceb_x_preferred":[
        "S\u0101meleh-ye Sofl\u00e1"
    ],
    "name:fas_x_preferred":[
        "\u0633\u0627\u0645\u0644\u0647 \u0633\u0641\u0644\u06cc"
    ],
    "name:fas_x_variant":[
        "\u0633\u0627\u0645\u0650\u0644\u0650\u06c0 \u0633\u064f\u0641\u0644\u064e\u0649",
        "\u0633\u0627\u0645\u0650\u0644\u0650\u0647",
        "S\u0101meleh-ye Sofl\u00e1"
    ],
    "name:swe_x_preferred":[
        "S\u0101meleh-ye Sofl\u00e1"
    ],
    "name:und_x_variant":[
        "S\u0101meleh"
    ],
    "wof:name":"Sameleh-ye Sofla",
    "wof:placetype":"locality"
},
  "geometry": {"coordinates":[47.3073,34.0206],"type":"Point"}
}