{
  "type": "Feature",
  "properties": {
    "gn:admin1_code":"35",
    "gn:asciiname":"Valam",
    "gn:country_code":"IR",
    "gn:dem":836,
    "gn:feature_class":"P",
    "gn:feature_code":"PPL",
    "gn:name":"Valam",
    "gn:population":0,
    "gn:timezone":"Asia/Tehran",
    "iso:country":"IR",
    "name:fas_x_preferred":[
        "\u0648\u0644\u0645"
    ],
    "name:und_x_variant":[
        "\u0648\u0644\u0645",
        "Valam"
    ],
    "wof:name":"Valam",
    "wof:placetype":"locality"
},
  "geometry": {"coordinates":[53.64113,36.59095],"type":"Point"}
}