{
  "type": "Feature",
  "properties": {
    "gn:admin1_code":"28.0",
    "gn:asciiname":"Pir Arzancheh",
    "gn:country_code":"IR",
    "gn:dem":1874,
    "gn:feature_class":"P",
    "gn:feature_code":"PPL",
    "gn:name":"P\u012br Arz\u0101ncheh",
    "gn:population":0,
    "gn:timezone":"Asia/Tehran",
    "iso:country":"IR",
    "name:fas_x_preferred":[
        "\u067e\u06cc\u0631 \u0627\u0631\u0632\u0627\u0646\u0686\u0647"
    ],
    "name:fas_x_variant":[
        "P\u012br\u0101zd\u0101neh",
        "P\u012br Arz\u0101ncheh"
    ],
    "name:und_x_variant":[
        "P\u012br Arz\u0101njeh"
    ],
    "wof:name":"Pir Arzancheh",
    "wof:placetype":"locality"
},
  "geometry": {"coordinates":[52.9893,32.7361],"type":"Point"}
}