{
  "type": "Feature",
  "properties": {
    "gn:admin1_code":"4.0",
    "gn:asciiname":"Deh-e Faqir Qasem",
    "gn:country_code":"IR",
    "gn:dem":478,
    "gn:feature_class":"P",
    "gn:feature_code":"PPL",
    "gn:name":"Deh-e Faq\u012br Q\u0101sem",
    "gn:population":0,
    "gn:timezone":"Asia/Tehran",
    "iso:country":"IR",
    "name:fas_x_preferred":[
        "\u062f\u0647 \u0641\u0642\u06cc\u0631 \u0642\u0627\u0633\u0645"
    ],
    "name:fas_x_variant":[
        "Deh-e Faq\u012br Q\u0101sem"
    ],
    "wof:name":"Deh-e Faqir Qasem",
    "wof:placetype":"locality"
},
  "geometry": {"coordinates":[61.41801,30.83605],"type":"Point"}
}