{
  "type": "Feature",
  "properties": {
    "gn:admin1_code":"39.0",
    "gn:asciiname":"Shahrak-e Mehdiyeh",
    "gn:country_code":"IR",
    "gn:dem":922,
    "gn:feature_class":"P",
    "gn:feature_code":"PPL",
    "gn:name":"Shahrak-e Mehd\u012byeh",
    "gn:population":0,
    "gn:timezone":"Asia/Tehran",
    "iso:country":"IR",
    "name:fas_x_preferred":[
        "\u0634\u0647\u0631\u06a9 \u0645\u0647\u062f\u06cc\u0647"
    ],
    "name:und_x_variant":[
        "Shahrak-e Mehd\u012byeh"
    ],
    "wof:name":"Shahrak-e Mehdiyeh",
    "wof:placetype":"locality"
},
  "geometry": {"coordinates":[50.86339,34.68028],"type":"Point"}
}