{
  "type": "Feature",
  "properties": {
    "gn:admin1_code":"42.0",
    "gn:asciiname":"Gardaneh Ma`sumabad",
    "gn:country_code":"IR",
    "gn:dem":763,
    "gn:feature_class":"P",
    "gn:feature_code":"PPL",
    "gn:name":"Gardaneh Ma\u2018\u015f\u016bm\u0101b\u0101d",
    "gn:population":0,
    "gn:timezone":"Asia/Tehran",
    "iso:country":"IR",
    "name:fas_x_preferred":[
        "\u06af\u0631\u062f\u0646\u0647 \u0645\u0639\u0635\u0648\u0645 \u0622\u0628\u0627\u062f"
    ],
    "name:fas_x_variant":[
        "Gardaneh Ma\u2018\u015f\u016bm\u0101b\u0101d"
    ],
    "name:und_x_variant":[
        "Gardaneh"
    ],
    "wof:name":"Gardaneh Ma`sumabad",
    "wof:placetype":"locality"
},
  "geometry": {"coordinates":[60.96995,35.0704],"type":"Point"}
}