{
  "type": "Feature",
  "properties": {
    "gn:admin1_code":"11.0",
    "gn:asciiname":"Shahdadi",
    "gn:country_code":"IR",
    "gn:dem":64,
    "gn:feature_class":"P",
    "gn:feature_code":"PPL",
    "gn:name":"Shahd\u0101d\u012b",
    "gn:population":0,
    "gn:timezone":"Asia/Tehran",
    "iso:country":"IR",
    "name:fas_x_preferred":[
        "\u0634\u0647\u062f\u0627\u062f\u06cc"
    ],
    "name:fas_x_variant":[
        "Shahd\u0101d\u012b"
    ],
    "wof:name":"Shahdadi",
    "wof:placetype":"locality"
},
  "geometry": {"coordinates":[57.18076,27.07599],"type":"Point"}
}