{
  "type": "Feature",
  "properties": {
    "gn:admin1_code":"35",
    "gn:asciiname":"Donyak",
    "gn:country_code":"IR",
    "gn:dem":-1,
    "gn:feature_class":"P",
    "gn:feature_code":"PPL",
    "gn:name":"Donyak",
    "gn:population":0,
    "gn:timezone":"Asia/Tehran",
    "iso:country":"IR",
    "name:fas_x_preferred":[
        "D\u012bnak"
    ],
    "name:fas_x_variant":[
        "Dan\u012bk",
        "\u062f\u064e\u0646\u064a\u0643",
        "\u062f\u0646\u06cc\u06a9",
        "\u062f\u064a\u0646\u0643"
    ],
    "name:und_x_variant":[
        "Donyak"
    ],
    "wof:name":"Donyak",
    "wof:placetype":"locality"
},
  "geometry": {"coordinates":[53.04904000000001,36.62678],"type":"Point"}
}