{
  "type": "Feature",
  "properties": {
    "gn:admin1_code":"36",
    "gn:asciiname":"Espas",
    "gn:country_code":"IR",
    "gn:dem":1656,
    "gn:feature_class":"P",
    "gn:feature_code":"PPL",
    "gn:name":"Esp\u0101s",
    "gn:population":0,
    "gn:timezone":"Asia/Tehran",
    "iso:country":"IR",
    "name:arg_x_preferred":[
        "Espans"
    ],
    "name:bug_x_preferred":[
        "Espas"
    ],
    "name:cat_x_preferred":[
        "Espans"
    ],
    "name:ceb_x_preferred":[
        "Espas"
    ],
    "name:eus_x_preferred":[
        "Espas"
    ],
    "name:fas_x_preferred":[
        "\u0627\u0633\u067e\u0627\u0633"
    ],
    "name:fas_x_variant":[
        "Esp\u0101s"
    ],
    "name:fra_x_preferred":[
        "Espas"
    ],
    "name:hun_x_preferred":[
        "Espas"
    ],
    "name:ita_x_preferred":[
        "Espas"
    ],
    "name:lat_x_preferred":[
        "Espas"
    ],
    "name:lin_x_preferred":[
        "http://en.wikipedia.org/wiki/Espas,_Zanjan"
    ],
    "name:mlg_x_preferred":[
        "Espas"
    ],
    "name:msa_x_preferred":[
        "Espas"
    ],
    "name:nld_x_preferred":[
        "Espas"
    ],
    "name:oci_x_preferred":[
        "Espans"
    ],
    "name:pms_x_preferred":[
        "Espas"
    ],
    "name:pol_x_preferred":[
        "Espas"
    ],
    "name:por_x_preferred":[
        "Espas"
    ],
    "name:ron_x_preferred":[
        "Espas"
    ],
    "name:rus_x_preferred":[
        "\u042d\u0441\u043f\u0430\u0441"
    ],
    "name:slk_x_preferred":[
        "Espas"
    ],
    "name:spa_x_preferred":[
        "Espas"
    ],
    "name:srp_x_preferred":[
        "\u0415\u0441\u043f\u0430"
    ],
    "name:swe_x_preferred":[
        "Espas"
    ],
    "name:ukr_x_preferred":[
        "\u0415\u0441\u043f\u0430\u0441"
    ],
    "name:und_x_variant":[
        "\u012asb\u0101z",
        "Ispas"
    ],
    "name:vie_x_preferred":[
        "Espas"
    ],
    "name:vol_x_preferred":[
        "Espas"
    ],
    "name:war_x_preferred":[
        "Espas"
    ],
    "name:zho_x_preferred":[
        "\u57c3\u65af\u5e15"
    ],
    "wof:name":"Espas",
    "wof:placetype":"locality"
},
  "geometry": {"coordinates":[49.10609,36.16244],"type":"Point"}
}