{
  "type": "Feature",
  "properties": {
    "gn:admin1_code":"36",
    "gn:asciiname":"Espas",
    "gn:country_code":"IR",
    "gn:dem":1656,
    "gn:feature_class":"P",
    "gn:feature_code":"PPL",
    "gn:name":"Esp\u0101s",
    "gn:population":0,
    "gn:timezone":"Asia/Tehran",
    "iso:country":"IR",
    "name:fas_x_preferred":[
        "\u0627\u0633\u067e\u0627\u0633"
    ],
    "name:fas_x_variant":[
        "Esp\u0101s"
    ],
    "name:lin_x_preferred":[
        "http://en.wikipedia.org/wiki/Espas,_Zanjan"
    ],
    "name:und_x_variant":[
        "\u012asb\u0101z",
        "Ispas"
    ],
    "wof:name":"Espas",
    "wof:placetype":"locality"
},
  "geometry": {"coordinates":[49.10609,36.16244],"type":"Point"}
}