{
  "type": "Feature",
  "properties": {
    "gn:admin1_code":"29",
    "gn:asciiname":"Karimabad-e Gavkhaneh",
    "gn:country_code":"IR",
    "gn:dem":1715,
    "gn:feature_class":"P",
    "gn:feature_code":"PPLF",
    "gn:name":"Kar\u012bm\u0101b\u0101d-e G\u0101vkh\u0101neh",
    "gn:population":0,
    "gn:timezone":"Asia/Tehran",
    "iso:country":"IR",
    "name:fas_x_preferred":[
        "Kar\u012bm\u0101b\u0101d-e G\u0101vkh\u0101neh"
    ],
    "name:fas_x_variant":[
        "\u06a9\u0631\u06cc\u0645 \u0622\u0628\u0627\u062f \u06af\u0627\u0648\u062e\u0627\u0646\u0647",
        "Kar\u012bm\u0101b\u0101d"
    ],
    "name:und_x_variant":[
        "Kar\u012bm\u0101b\u0101d",
        "\u06a9\u0631\u06cc\u0645 \u0622\u0628\u0627\u062f \u06af\u0627\u0648\u062e\u0627\u0646\u0647"
    ],
    "wof:name":"Karimabad-e Gavkhaneh",
    "wof:placetype":"locality"
},
  "geometry": {"coordinates":[56.79663000000001,30.52939000000001],"type":"Point"}
}