{
  "type": "Feature",
  "properties": {
    "gn:admin1_code":"42",
    "gn:asciiname":"Darzab",
    "gn:country_code":"IR",
    "gn:dem":1539,
    "gn:feature_class":"P",
    "gn:feature_code":"PPL",
    "gn:name":"Darz\u0101b",
    "gn:population":0,
    "gn:timezone":"Asia/Tehran",
    "iso:country":"IR",
    "name:ara_x_preferred":[
        "\u062f\u0631\u0632\u0627\u0628"
    ],
    "name:fas_x_preferred":[
        "Darz\u0101b"
    ],
    "name:fas_x_variant":[
        "\u062f\u0631\u0632\u0627\u0628",
        "Darz \u0100b"
    ],
    "wof:name":"Darzab",
    "wof:placetype":"locality"
},
  "geometry": {"coordinates":[58.16667,34.43482],"type":"Point"}
}