{
  "type": "Feature",
  "properties": {
    "gn:admin1_code":"42.0",
    "gn:asciiname":"Qal`eh Now-e `Olya",
    "gn:country_code":"IR",
    "gn:dem":1429,
    "gn:feature_class":"P",
    "gn:feature_code":"PPL",
    "gn:name":"Qal\u2018eh Now-e \u2018Oly\u0101",
    "gn:population":0,
    "gn:timezone":"Asia/Tehran",
    "iso:country":"IR",
    "name:fas_x_preferred":[
        "Qal\u2018eh Now"
    ],
    "name:fas_x_variant":[
        "Qal\u2018eh-ye Now",
        "Qal\u2018eh-i-Nau",
        "Qal\u2018eh-ye Now \u2018\u014cly\u0101",
        "Qal\u2018eh-ye Now B\u0101l\u0101",
        "Qal\u2018eh-ye Now-ye \u2018Oly\u0101",
        "Qal\u2019eh Now-Ye-\u2019Oly\u0101",
        "\u0642\u0644\u0639\u0647 \u0646\u0648 \u0639\u0644\u064a\u0627",
        "Qal\u2018eh Now-e B\u0101l\u0101",
        "Qal\u2018eh Now-e \u2018Oly\u0101"
    ],
    "wof:name":"Qal`eh Now-e `Olya",
    "wof:placetype":"locality"
},
  "geometry": {"coordinates":[60.15885,35.09861],"type":"Point"}
}