{
  "type": "Feature",
  "properties": {
    "gn:admin1_code":"41",
    "gn:asciiname":"Khunik",
    "gn:country_code":"IR",
    "gn:dem":1834,
    "gn:feature_class":"P",
    "gn:feature_code":"PPLF",
    "gn:name":"Kh\u016bn\u012bk",
    "gn:population":0,
    "gn:timezone":"Asia/Tehran",
    "iso:country":"IR",
    "name:fas_x_preferred":[
        "Kh\u016bn\u012bk"
    ],
    "name:fas_x_variant":[
        "\u062e\u0648\u0646\u064a\u06a9"
    ],
    "name:und_x_variant":[
        "Khonik",
        "\u062e\u0648\u0646\u064a\u06a9"
    ],
    "wof:name":"Khunik",
    "wof:placetype":"locality"
},
  "geometry": {"coordinates":[59.3713,32.77428],"type":"Point"}
}