{
  "type": "Feature",
  "properties": {
    "gn:admin1_code":"13",
    "gn:asciiname":"Marjan",
    "gn:country_code":"IR",
    "gn:dem":623,
    "gn:feature_class":"P",
    "gn:feature_code":"PPL",
    "gn:name":"Marj\u0101n",
    "gn:population":0,
    "gn:timezone":"Asia/Tehran",
    "iso:country":"IR",
    "name:ceb_x_preferred":[
        "Marjan"
    ],
    "name:deu_x_preferred":[
        "Marjan"
    ],
    "name:fas_x_preferred":[
        "\u0645\u0631\u062c\u0627\u0646"
    ],
    "name:fas_x_variant":[
        "Marj\u0101n-e \u2018Al\u012bre\u1e95\u0101vand\u012b",
        "Marj\u0101n"
    ],
    "name:fra_x_preferred":[
        "Marjan"
    ],
    "name:swe_x_preferred":[
        "Marjan"
    ],
    "wof:name":"Marjan",
    "wof:placetype":"locality"
},
  "geometry": {"coordinates":[45.80497,34.26454],"type":"Point"}
}