{
  "type": "Feature",
  "properties": {
    "gn:admin1_code":"1.0",
    "gn:asciiname":"Kal Darreh",
    "gn:country_code":"IR",
    "gn:dem":1037,
    "gn:feature_class":"P",
    "gn:feature_code":"PPL",
    "gn:name":"K\u0101l Darreh",
    "gn:population":0,
    "gn:timezone":"Asia/Tehran",
    "iso:country":"IR",
    "name:fas_x_preferred":[
        "\u06a9\u0627\u0644 \u062f\u0631\u0651\u0647"
    ],
    "name:fas_x_variant":[
        "K\u0101l Darreh"
    ],
    "wof:name":"Kal Darreh",
    "wof:placetype":"locality"
},
  "geometry": {"coordinates":[45.5199,36.2216],"type":"Point"}
}