{
  "type": "Feature",
  "properties": {
    "gn:admin1_code":"34",
    "gn:asciiname":"Vafs",
    "gn:country_code":"IR",
    "gn:dem":2137,
    "gn:feature_class":"P",
    "gn:feature_code":"PPL",
    "gn:name":"Vafs",
    "gn:population":0,
    "gn:timezone":"Asia/Tehran",
    "iso:country":"IR",
    "name:aze_x_preferred":[
        "V\u0259fs"
    ],
    "name:fas_x_preferred":[
        "\u0648\u0641\u0633"
    ],
    "name:ukr_x_preferred":[
        "\u0412\u0430\u0444\u0441"
    ],
    "name:und_x_variant":[
        "Vabs",
        "Wa\u016bs",
        "Vafs"
    ],
    "wof:name":"Vafs",
    "wof:placetype":"locality"
},
  "geometry": {"coordinates":[49.38273,34.84846],"type":"Point"}
}