{
  "type": "Feature",
  "properties": {
    "gn:admin1_code":"7",
    "gn:asciiname":"Shah Rostam",
    "gn:country_code":"IR",
    "gn:dem":2364,
    "gn:feature_class":"P",
    "gn:feature_code":"PPL",
    "gn:name":"Sh\u0101h Rostam",
    "gn:population":0,
    "gn:timezone":"Asia/Tehran",
    "iso:country":"IR",
    "name:ara_x_preferred":[
        "\u0634\u0627\u0647 \u0631\u0633\u062a\u0645"
    ],
    "name:fas_x_preferred":[
        "\u0634\u0627\u0647 \u0631\u0633\u062a\u0645"
    ],
    "name:fas_x_variant":[
        "Sh\u0101h Rostam"
    ],
    "name:msa_x_preferred":[
        "Shah Rostam"
    ],
    "wof:name":"Shah Rostam",
    "wof:placetype":"locality"
},
  "geometry": {"coordinates":[53.543,30.299],"type":"Point"}
}