{
  "type": "Feature",
  "properties": {
    "gn:admin1_code":"42",
    "gn:asciiname":"Rud Ma`jan",
    "gn:country_code":"IR",
    "gn:dem":1729,
    "gn:feature_class":"P",
    "gn:feature_code":"PPL",
    "gn:name":"R\u016bd Ma\u2018jan",
    "gn:population":0,
    "gn:timezone":"Asia/Tehran",
    "iso:country":"IR",
    "name:fas_x_preferred":[
        "\u0631\u0648\u062f \u0645\u0639\u062c\u0646"
    ],
    "name:fas_x_variant":[
        "R\u016bd Ma\u2018jan"
    ],
    "name:und_x_variant":[
        "Zarmaj\u0101n",
        "R\u0101zmgah\u0101n",
        "R\u0101zmagh\u0101n"
    ],
    "wof:name":"Rud Ma`jan",
    "wof:placetype":"locality"
},
  "geometry": {"coordinates":[58.83283,35.44096],"type":"Point"}
}