{
  "type": "Feature",
  "properties": {
    "gn:admin1_code":"15",
    "gn:asciiname":"Darreh Kulak",
    "gn:country_code":"IR",
    "gn:dem":1147,
    "gn:feature_class":"P",
    "gn:feature_code":"PPL",
    "gn:name":"Darreh K\u016blak",
    "gn:population":0,
    "gn:timezone":"Asia/Tehran",
    "iso:country":"IR",
    "name:fas_x_preferred":[
        "Darreh K\u016blak"
    ],
    "wof:name":"Darreh Kulak",
    "wof:placetype":"locality"
},
  "geometry": {"coordinates":[50.19889000000001,31.69806],"type":"Point"}
}