{
  "type": "Feature",
  "properties": {
    "gn:admin1_code":"4.0",
    "gn:asciiname":"Chah-e Gaz",
    "gn:country_code":"IR",
    "gn:dem":636,
    "gn:feature_class":"P",
    "gn:feature_code":"PPLL",
    "gn:name":"Ch\u0101h-e Gaz",
    "gn:population":0,
    "gn:timezone":"Asia/Tehran",
    "iso:country":"IR",
    "name:fas_x_preferred":[
        "\u0686\u0627\u0647 \u06af\u0632"
    ],
    "name:und_x_variant":[
        "Ch\u0101h-e Gaz"
    ],
    "wof:name":"Chah-e Gaz",
    "wof:placetype":"locality"
},
  "geometry": {"coordinates":[59.67765,26.87173],"type":"Point"}
}