{
  "type": "Feature",
  "properties": {
    "gn:admin1_code":"1.0",
    "gn:asciiname":"Darageh-ye Oros Khan",
    "gn:country_code":"IR",
    "gn:dem":1282,
    "gn:elevation":"0.0",
    "gn:feature_class":"P",
    "gn:feature_code":"PPL",
    "gn:name":"Darageh-ye Oros Kh\u0101n",
    "gn:population":0,
    "gn:timezone":"Asia/Tehran",
    "iso:country":"IR",
    "name:azb_x_preferred":[
        "\u062f\u0631\u06af\u0647 \u0627\u0631\u0633\u062e\u0627\u0646"
    ],
    "name:aze_x_preferred":[
        "D\u0259r\u0259g\u0259h-i Oruzxan"
    ],
    "name:ceb_x_preferred":[
        "Darageh-ye Oros Kh\u0101n"
    ],
    "name:fas_x_preferred":[
        "\u062f\u064e\u0631\u064e\u0643\u0650\u06c0 \u0627\u064f\u0631\u064f\u0633 \u062e\u0627\u0646"
    ],
    "name:fas_x_variant":[
        "\u062f\u0631\u06af\u0647 \u0627\u0631\u0633 \u062e\u0627\u0646",
        "Darakeh-ye Oros Kh\u0101n",
        "Darageh-ye Oros Kh\u0101n",
        "\u062f\u0631\u06af\u0647\u200c\u0627\u0631\u0633\u062e\u0627\u0646"
    ],
    "name:msa_x_preferred":[
        "Darageh-ye Oros Khan"
    ],
    "name:swe_x_preferred":[
        "Darageh-ye Oros Kh\u0101n"
    ],
    "wof:name":"Darageh-ye Oros Khan",
    "wof:placetype":"locality"
},
  "geometry": {"coordinates":[45.578,36.9728],"type":"Point"}
}