{
  "type": "Feature",
  "properties": {
    "iso:country":"IR",
    "name:ara_x_preferred":[
        "\u0646\u0648\u0631\u0623\u0628\u0627\u062f"
    ],
    "name:aze_x_preferred":[
        "Nurabad"
    ],
    "name:ceb_x_preferred":[
        "N\u016br\u0101b\u0101d"
    ],
    "name:eng_x_preferred":[
        "Nurabad"
    ],
    "name:fas_x_preferred":[
        "\u0646\u0648\u0631\u0622\u0628\u0627\u062f"
    ],
    "name:fas_x_variant":[
        "\u0646\u0648\u0631 \u0622\u0628\u0627\u062f",
        "N\u016br\u0101b\u0101d"
    ],
    "name:fra_x_preferred":[
        "Nurabad"
    ],
    "name:hak_x_preferred":[
        "Nur\u00e2b\u00e2d"
    ],
    "name:ita_x_preferred":[
        "Nurabad"
    ],
    "name:mlg_x_preferred":[
        "Nurabad"
    ],
    "name:nld_x_preferred":[
        "Nurabad"
    ],
    "name:pol_x_preferred":[
        "Nurabad"
    ],
    "name:rus_x_preferred":[
        "\u041d\u0443\u0440\u0430\u0431\u0430\u0434"
    ],
    "name:swe_x_preferred":[
        "N\u016br\u0101b\u0101d"
    ],
    "name:tur_x_preferred":[
        "Nurabad"
    ],
    "name:ukr_x_preferred":[
        "\u041d\u0443\u0440\u0430\u0431\u0430\u0434"
    ],
    "name:zho_x_preferred":[
        "\u52aa\u62c9\u5df4\u5fb7"
    ],
    "qs:gn_country":"IR",
    "qs:gn_fcode":"PPL",
    "qs:gn_pop":73528,
    "qs:name":"Nurabad",
    "qs:name_adm0":"Iran",
    "qs:name_adm1":"Lorestan",
    "qs:photos":0,
    "qs:photos_1k":0,
    "qs:photos_9k":0,
    "qs:photos_9r":0,
    "qs:photos_all":0,
    "qs:photos_sr":0,
    "qs:placetype":"Town",
    "qs:pop_sr":"8",
    "qs:woe_adm0":23424851,
    "wd:wordcount":174,
    "wof:name":"Nurabad",
    "wof:placetype":"locality",
    "wof:population":73528
},
  "geometry": {"coordinates":[47.9725,34.0734],"type":"Point"}
}