{
  "type": "Feature",
  "properties": {
    "gn:admin1_code":"13.0",
    "gn:asciiname":"Gelal",
    "gn:country_code":"IR",
    "gn:dem":1262,
    "gn:feature_class":"P",
    "gn:feature_code":"PPL",
    "gn:name":"Gel\u0101l",
    "gn:population":0,
    "gn:timezone":"Asia/Tehran",
    "iso:country":"IR",
    "name:fas_x_preferred":[
        "\u06af\u0644\u0627\u0644"
    ],
    "name:fas_x_variant":[
        "Gel\u0101l"
    ],
    "wof:name":"Gelal",
    "wof:placetype":"locality"
},
  "geometry": {"coordinates":[46.3244,35.0437],"type":"Point"}
}