{
  "type": "Feature",
  "properties": {
    "gn:admin1_code":"36",
    "gn:asciiname":"Yakhiabad",
    "gn:country_code":"IR",
    "gn:dem":1555,
    "gn:feature_class":"P",
    "gn:feature_code":"PPL",
    "gn:name":"Yakhiabad",
    "gn:population":0,
    "gn:timezone":"Asia/Tehran",
    "iso:country":"IR",
    "name:fas_x_preferred":[
        "\u06cc\u062d\u06cc\u06cc \u0622\u0628\u0627\u062f"
    ],
    "name:fas_x_variant":[
        "Yahi\u0101b\u0101d",
        "Ya\u1e29y\u00e1\u0101b\u0101d"
    ],
    "wof:name":"Yakhiabad",
    "wof:placetype":"locality"
},
  "geometry": {"coordinates":[48.87288,36.71413],"type":"Point"}
}