{
  "type": "Feature",
  "properties": {
    "gn:admin1_code":"8",
    "gn:asciiname":"Suliveh Poshteh",
    "gn:country_code":"IR",
    "gn:dem":1283,
    "gn:feature_class":"P",
    "gn:feature_code":"PPL",
    "gn:name":"S\u016bl\u012bveh Poshteh",
    "gn:population":0,
    "gn:timezone":"Asia/Tehran",
    "iso:country":"IR",
    "name:fas_x_preferred":[
        "\u0633\u0648\u0644\u06cc\u0648\u0647 \u067e\u0634\u062a\u0647"
    ],
    "name:fas_x_variant":[
        "S\u016bl\u012bveh Poshteh"
    ],
    "wof:name":"Suliveh Poshteh",
    "wof:placetype":"locality"
},
  "geometry": {"coordinates":[49.06974,37.23481],"type":"Point"}
}