{
  "type": "Feature",
  "properties": {
    "gn:admin1_code":"41",
    "gn:asciiname":"Sarshabad",
    "gn:country_code":"IR",
    "gn:dem":2040,
    "gn:feature_class":"P",
    "gn:feature_code":"PPLF",
    "gn:name":"Sarsh\u0101b\u0101d",
    "gn:population":0,
    "gn:timezone":"Asia/Tehran",
    "iso:country":"IR",
    "name:fas_x_preferred":[
        "\u0633\u0631\u0634 \u0622\u0628\u0627\u062f"
    ],
    "name:fas_x_variant":[
        "Sarsh\u0101b\u0101d"
    ],
    "name:und_x_variant":[
        "Sash\u0101vard"
    ],
    "wof:name":"Sarshabad",
    "wof:placetype":"locality"
},
  "geometry": {"coordinates":[59.97344,32.70231],"type":"Point"}
}