{
  "type": "Feature",
  "properties": {
    "gn:admin1_code":"28",
    "gn:asciiname":"Qehyaz",
    "gn:cc2":"IR",
    "gn:country_code":"IR",
    "gn:dem":1456,
    "gn:feature_class":"P",
    "gn:feature_code":"PPL",
    "gn:name":"Qehy\u0101z",
    "gn:population":0,
    "gn:timezone":"Asia/Tehran",
    "iso:country":"IR",
    "name:fas_x_preferred":[
        "Qehy\u0101z"
    ],
    "name:und_x_variant":[
        "Kalt\u012b\u0101z",
        "Kehy\u0101z"
    ],
    "wof:name":"Qehyaz",
    "wof:placetype":"locality"
},
  "geometry": {"coordinates":[52.66721999999999,33.29417],"type":"Point"}
}