{
  "type": "Feature",
  "properties": {
    "gn:admin1_code":"33",
    "gn:asciiname":"Deylam Shah",
    "gn:country_code":"IR",
    "gn:dem":2143,
    "gn:elevation":"0.0",
    "gn:feature_class":"P",
    "gn:feature_code":"PPL",
    "gn:name":"Deylam Sh\u0101h",
    "gn:population":0,
    "gn:timezone":"Asia/Tehran",
    "iso:country":"IR",
    "name:fas_x_preferred":[
        "\u062f\u064a\u0644\u0645 \u0634\u0627\u0647"
    ],
    "name:fas_x_variant":[
        "\u062f\u06cc\u0644\u0645\u200c\u0634\u0627\u0647"
    ],
    "name:msa_x_preferred":[
        "Deylamshah"
    ],
    "name:und_x_variant":[
        "Deylam Sh\u0101h"
    ],
    "wof:name":"Deylam Shah",
    "wof:placetype":"locality"
},
  "geometry": {"coordinates":[47.3546,38.1435],"type":"Point"}
}