{
  "type": "Feature",
  "properties": {
    "gn:admin1_code":"7",
    "gn:asciiname":"Dudez",
    "gn:country_code":"IR",
    "gn:dem":1387,
    "gn:feature_class":"P",
    "gn:feature_code":"PPL",
    "gn:name":"D\u016bdez",
    "gn:population":0,
    "gn:timezone":"Asia/Tehran",
    "iso:country":"IR",
    "name:fas_x_preferred":[
        "D\u016bdez"
    ],
    "wof:name":"Dudez",
    "wof:placetype":"locality"
},
  "geometry": {"coordinates":[51.61667,30.31667],"type":"Point"}
}