{
  "type": "Feature",
  "properties": {
    "gn:admin1_code":"13",
    "gn:asciiname":"Kolah Deraz-e Javanmir",
    "gn:country_code":"IR",
    "gn:dem":1057,
    "gn:feature_class":"P",
    "gn:feature_code":"PPL",
    "gn:name":"Kol\u0101h Der\u0101z-e Jav\u0101nm\u012br",
    "gn:population":0,
    "gn:timezone":"Asia/Tehran",
    "iso:country":"IR",
    "name:fas_x_preferred":[
        "\u06a9\u0644\u0627\u0647 \u062f\u0631\u0627\u0632 \u062c\u0648\u0627\u0646\u0645\u06cc\u0631"
    ],
    "name:fas_x_variant":[
        "Kol\u0101h Der\u0101z-e Jav\u0101nm\u012br-e Sofl\u00e1",
        "Kol\u0101h Der\u0101z-e Jav\u0101nm\u012br"
    ],
    "name:und_x_variant":[
        "\u016aloyar"
    ],
    "wof:name":"Kolah Deraz-e Javanmir",
    "wof:placetype":"locality"
},
  "geometry": {"coordinates":[46.0554,34.0749],"type":"Point"}
}