{
  "type": "Feature",
  "properties": {
    "gn:admin1_code":"16",
    "gn:asciiname":"Belan",
    "gn:country_code":"IR",
    "gn:dem":1417,
    "gn:feature_class":"P",
    "gn:feature_code":"PPL",
    "gn:name":"Bel\u0101n",
    "gn:population":0,
    "gn:timezone":"Asia/Tehran",
    "iso:country":"IR",
    "name:fas_x_preferred":[
        "\u0628\u0650\u0644\u0627\u0646"
    ],
    "name:fas_x_variant":[
        "\u0628\u0644\u0627\u0646",
        "Bel\u0101n"
    ],
    "wof:name":"Belan",
    "wof:placetype":"locality"
},
  "geometry": {"coordinates":[46.9133,34.775],"type":"Point"}
}