{
  "type": "Feature",
  "properties": {
    "gn:admin1_code":"11",
    "gn:asciiname":"Naran",
    "gn:country_code":"IR",
    "gn:dem":56,
    "gn:feature_class":"P",
    "gn:feature_code":"PPL",
    "gn:name":"Naran",
    "gn:population":0,
    "gn:timezone":"Asia/Tehran",
    "iso:country":"IR",
    "name:fas_x_preferred":[
        "N\u0101r\u0101n"
    ],
    "name:fas_x_variant":[
        "\u0646\u0650\u0631\u064e\u0646"
    ],
    "name:und_x_variant":[
        "Neran",
        "Nehran"
    ],
    "wof:name":"Naran",
    "wof:placetype":"locality"
},
  "geometry": {"coordinates":[53.03,27.20667000000001],"type":"Point"}
}