{
  "type": "Feature",
  "properties": {
    "gn:admin1_code":"43.0",
    "gn:asciiname":"Kushkandar",
    "gn:country_code":"IR",
    "gn:dem":1625,
    "gn:feature_class":"P",
    "gn:feature_code":"PPL",
    "gn:name":"K\u016bshkandar",
    "gn:population":0,
    "gn:timezone":"Asia/Tehran",
    "iso:country":"IR",
    "name:ara_x_preferred":[
        "\u0643\u0648\u0634\u0643\u0646\u062f\u0631"
    ],
    "name:ceb_x_preferred":[
        "Koshkandar"
    ],
    "name:fas_x_preferred":[
        "K\u016bshkandar"
    ],
    "name:fas_x_variant":[
        "\u06a9\u0634\u06a9\u0646\u062f\u0631",
        "\u06a9\u0648\u0634\u06a9\u0646\u062f\u0631",
        "\u06a9\u0648\u0634\u0646\u062f\u0631"
    ],
    "name:swe_x_preferred":[
        "Koshkandar"
    ],
    "name:und_x_variant":[
        "K\u016bshk Andar",
        "Koshkandar",
        "\u06a9\u0634\u06a9\u0646\u062f\u0631",
        "K\u016bshandar"
    ],
    "wof:name":"Kushkandar",
    "wof:placetype":"locality"
},
  "geometry": {"coordinates":[57.91285,36.92284],"type":"Point"}
}