{
  "type": "Feature",
  "properties": {
    "gn:admin1_code":"5.0",
    "gn:asciiname":"Tarob",
    "gn:country_code":"IR",
    "gn:dem":1008,
    "gn:feature_class":"P",
    "gn:feature_code":"PPL",
    "gn:name":"T\u0101rob",
    "gn:population":0,
    "gn:timezone":"Asia/Tehran",
    "iso:country":"IR",
    "name:fas_x_preferred":[
        "\u0162\u0101rob"
    ],
    "name:fas_x_variant":[
        "\u0637\u0627\u0631\u0628",
        "\u062a\u0627\u0631\u0628"
    ],
    "name:und_x_variant":[
        "\u0162\u0101rb",
        "\u0637\u0627\u0631\u0628",
        "Torab",
        "T\u0101rob"
    ],
    "wof:name":"Tarob",
    "wof:placetype":"locality"
},
  "geometry": {"coordinates":[50.53663,31.0936],"type":"Point"}
}