{
  "type": "Feature",
  "properties": {
    "gn:admin1_code":"4",
    "gn:asciiname":"Bandini",
    "gn:country_code":"IR",
    "gn:dem":36,
    "gn:feature_class":"P",
    "gn:feature_code":"PPL",
    "gn:name":"B\u0101nd\u012bn\u012b",
    "gn:population":0,
    "gn:timezone":"Asia/Tehran",
    "iso:country":"IR",
    "name:deu_x_preferred":[
        "Bandini"
    ],
    "name:fas_x_preferred":[
        "Band\u012bn\u012b"
    ],
    "name:fas_x_variant":[
        "B\u0101nd\u012bn\u012b",
        "Band Bon\u012b",
        "Bandeyn\u012b",
        "\u0628\u0627\u0646\u062f\u06cc\u0646\u06cc"
    ],
    "name:fra_x_preferred":[
        "Bandini"
    ],
    "name:ita_x_preferred":[
        "Bandini"
    ],
    "name:mkd_x_preferred":[
        "\u0411\u0430\u043d\u0434\u0438\u043d\u0438"
    ],
    "name:nld_x_preferred":[
        "Bandini"
    ],
    "name:rus_x_preferred":[
        "\u0411\u0430\u043d\u0434\u0438\u043d\u0438"
    ],
    "name:slv_x_preferred":[
        "Bandini"
    ],
    "wof:name":"Bandini",
    "wof:placetype":"locality"
},
  "geometry": {"coordinates":[59.59589,25.5249],"type":"Point"}
}