{
  "type": "Feature",
  "properties": {
    "gn:admin1_code":"40",
    "gn:asciiname":"Sarneshin",
    "gn:country_code":"IR",
    "gn:dem":2413,
    "gn:feature_class":"P",
    "gn:feature_code":"PPL",
    "gn:name":"Sarnesh\u012bn",
    "gn:population":0,
    "gn:timezone":"Asia/Tehran",
    "iso:country":"IR",
    "name:fas_x_preferred":[
        "\u0633\u0631\u0646\u0634\u06cc\u0646"
    ],
    "name:fas_x_variant":[
        "Sarnesh\u012bn"
    ],
    "wof:name":"Sarneshin",
    "wof:placetype":"locality"
},
  "geometry": {"coordinates":[53.8128,31.6571],"type":"Point"}
}