{
  "type": "Feature",
  "properties": {
    "gn:admin1_code":"29",
    "gn:asciiname":"Navvab",
    "gn:country_code":"IR",
    "gn:dem":2220,
    "gn:feature_class":"P",
    "gn:feature_code":"PPL",
    "gn:name":"Navv\u0101b",
    "gn:population":0,
    "gn:timezone":"Asia/Tehran",
    "iso:country":"IR",
    "name:fas_x_preferred":[
        "Navv\u0101b"
    ],
    "wof:name":"Navvab",
    "wof:placetype":"locality"
},
  "geometry": {"coordinates":[57.21666999999999,29.05],"type":"Point"}
}