{
  "type": "Feature",
  "properties": {
    "gn:admin1_code":"3.0",
    "gn:asciiname":"Pol Rostam Beyg",
    "gn:country_code":"IR",
    "gn:dem":1475,
    "gn:feature_class":"P",
    "gn:feature_code":"PPL",
    "gn:name":"Pol Rostam Beyg",
    "gn:population":0,
    "gn:timezone":"Asia/Tehran",
    "iso:country":"IR",
    "name:fas_x_preferred":[
        "\u067e\u0644 \u0631\u0633\u062a\u0645 \u0628\u06cc\u06af"
    ],
    "name:und_x_variant":[
        "\u067e\u0644 \u0631\u0633\u062a\u0645 \u0628\u06cc\u06af"
    ],
    "wof:name":"Pol Rostam Beyg",
    "wof:placetype":"locality"
},
  "geometry": {"coordinates":[51.16721,31.16733],"type":"Point"}
}