{
  "type": "Feature",
  "properties": {
    "gn:admin1_code":"34",
    "gn:asciiname":"Kholuzin",
    "gn:country_code":"IR",
    "gn:dem":1651,
    "gn:feature_class":"P",
    "gn:feature_code":"PPL",
    "gn:name":"Khol\u016bz\u012bn",
    "gn:population":0,
    "gn:timezone":"Asia/Tehran",
    "iso:country":"IR",
    "name:ceb_x_preferred":[
        "Vezv\u0101naq"
    ],
    "name:fas_x_preferred":[
        "\u0648\u0632\u0648\u0627\u0646\u0642"
    ],
    "name:fas_x_variant":[
        "Vezv\u0101naq",
        "\u062e\u0644\u0648\u0632\u06cc\u0646"
    ],
    "name:swe_x_preferred":[
        "Vezv\u0101naq"
    ],
    "name:ukr_x_preferred":[
        "\u0412\u0435\u0437\u0432\u0430\u043d\u0430\u043a"
    ],
    "name:und_x_variant":[
        "Vazv\u0101naq",
        "Vazvangh",
        "Khol\u016bz\u012bn"
    ],
    "wof:name":"Kholuzin",
    "wof:placetype":"locality"
},
  "geometry": {"coordinates":[49.08713,34.53352],"type":"Point"}
}