{
  "type": "Feature",
  "properties": {
    "gn:admin1_code":"33",
    "gn:asciiname":"Gavashin",
    "gn:country_code":"IR",
    "gn:dem":1876,
    "gn:feature_class":"P",
    "gn:feature_code":"PPL",
    "gn:name":"Gav\u0101sh\u012bn",
    "gn:population":0,
    "gn:timezone":"Asia/Tehran",
    "iso:country":"IR",
    "name:fas_x_preferred":[
        "\u06af\u0648\u0627\u0634\u064a\u0646"
    ],
    "name:fas_x_variant":[
        "Gav\u0101sh\u012bn"
    ],
    "wof:name":"Gavashin",
    "wof:placetype":"locality"
},
  "geometry": {"coordinates":[47.5882,38.0186],"type":"Point"}
}