{
  "type": "Feature",
  "properties": {
    "gn:admin1_code":"29",
    "gn:asciiname":"Joznin Bolbolu",
    "gn:cc2":"IR",
    "gn:country_code":"IR",
    "gn:dem":569,
    "gn:feature_class":"P",
    "gn:feature_code":"PPL",
    "gn:name":"Jozn\u012bn Bolbol\u016b",
    "gn:population":0,
    "gn:timezone":"Asia/Tehran",
    "iso:country":"IR",
    "name:fas_x_preferred":[
        "Jozn\u012bn Bolbol\u016b"
    ],
    "name:und_x_variant":[
        "Jazfat\u012bn-e Bolbol\u016b"
    ],
    "wof:name":"Joznin Bolbolu",
    "wof:placetype":"locality"
},
  "geometry": {"coordinates":[57.65389,28.23889],"type":"Point"}
}