{
  "type": "Feature",
  "properties": {
    "gn:admin1_code":"23",
    "gn:asciiname":"Kuh Shurab",
    "gn:country_code":"IR",
    "gn:dem":1146,
    "gn:feature_class":"P",
    "gn:feature_code":"PPL",
    "gn:name":"K\u016bh Sh\u016br\u0101b",
    "gn:population":0,
    "gn:timezone":"Asia/Tehran",
    "iso:country":"IR",
    "name:fas_x_preferred":[
        "\u0643\u0648\u0631 \u0634\u0648\u0631\u0627\u0628\u0650 \u0639\u064e\u0644\u064a\u0634\u0627\u0647"
    ],
    "name:fas_x_variant":[
        "\u06a9\u0648\u0631 \u0634\u0648\u0631\u0622\u0628 \u0633\u0641\u0644\u06cc",
        "K\u016br Sh\u016br\u0101b-e \u2018Al\u012bsh\u0101h",
        "K\u016br Sh\u016br\u0101b-e Sofl\u00e1",
        "\u06a9\u0648\u0647 \u0634\u0648\u0631\u0627\u0628"
    ],
    "name:und_x_variant":[
        "K\u016bh Sh\u016br\u0101b"
    ],
    "wof:name":"Kuh Shurab",
    "wof:placetype":"locality"
},
  "geometry": {"coordinates":[47.8497,33.4693],"type":"Point"}
}