{
  "type": "Feature",
  "properties": {
    "gn:admin1_code":"15.0",
    "gn:asciiname":"Gavmishabad-e Gharbi",
    "gn:country_code":"IR",
    "gn:dem":119,
    "gn:feature_class":"P",
    "gn:feature_code":"PPL",
    "gn:name":"G\u0101vm\u012bsh\u0101b\u0101d-e Gharb\u012b",
    "gn:population":0,
    "gn:timezone":"Asia/Tehran",
    "iso:country":"IR",
    "name:fas_x_preferred":[
        "\u06af\u0627\u0648\u0645\u06cc\u0634 \u0622\u0628\u0627\u062f \u063a\u0631\u0628\u06cc"
    ],
    "name:fas_x_variant":[
        "G\u0101vm\u012bsh\u0101b\u0101d-e Gharb\u012b",
        "\u06af\u0627\u0648\u0645\u06cc\u0634 \u0622\u0628\u0627\u062f"
    ],
    "name:und_x_variant":[
        "G\u0101vm\u012bsh\u0101b\u0101d"
    ],
    "wof:name":"Gavmishabad-e Gharbi",
    "wof:placetype":"locality"
},
  "geometry": {"coordinates":[48.3668,32.3781],"type":"Point"}
}