{
  "type": "Feature",
  "properties": {
    "gn:admin1_code":"34",
    "gn:asciiname":"Maraq",
    "gn:country_code":"IR",
    "gn:dem":1622,
    "gn:feature_class":"P",
    "gn:feature_code":"PPL",
    "gn:name":"Maraq",
    "gn:population":0,
    "gn:timezone":"Asia/Tehran",
    "iso:country":"IR",
    "name:ceb_x_preferred":[
        "Maraq"
    ],
    "name:fas_x_preferred":[
        "\u0645\u064e\u0631\u063a"
    ],
    "name:fas_x_variant":[
        "\u0645\u064e\u0631\u064e\u0651\u0647",
        "\u0645\u064e\u0631\u0642",
        "\u0645\u064e\u0631\u064e\u0651\u0642",
        "\u0645\u0631\u0642"
    ],
    "name:swe_x_preferred":[
        "Maraq"
    ],
    "name:ukr_x_preferred":[
        "\u041c\u0430\u0440\u0430\u043a"
    ],
    "name:und_x_variant":[
        "Marq",
        "Marraq",
        "Margh",
        "Marrah",
        "\u0645\u0631\u0642",
        "Maraq"
    ],
    "wof:name":"Maraq",
    "wof:placetype":"locality"
},
  "geometry": {"coordinates":[49.95746,34.95435],"type":"Point"}
}