{
  "type": "Feature",
  "properties": {
    "gn:admin1_code":"29",
    "gn:asciiname":"Kalejak-e `Olya",
    "gn:country_code":"IR",
    "gn:dem":1186,
    "gn:feature_class":"P",
    "gn:feature_code":"PPL",
    "gn:name":"Kalejak-e \u2018Oly\u0101",
    "gn:population":0,
    "gn:timezone":"Asia/Tehran",
    "iso:country":"IR",
    "name:ara_x_preferred":[
        "\u0643\u0644\u062c\u0643"
    ],
    "name:ceb_x_preferred":[
        "Kalejak-e \u2018Oly\u0101"
    ],
    "name:fas_x_preferred":[
        "\u06a9\u0644\u062c\u06a9 \u0639\u0644\u06cc\u0627"
    ],
    "name:fas_x_variant":[
        "Kalejak-e \u2018Oly\u0101",
        "\u06a9\u0644\u062c\u06a9"
    ],
    "name:swe_x_preferred":[
        "Kalejak-e \u2018Oly\u0101"
    ],
    "name:und_x_variant":[
        "Kalejak"
    ],
    "wof:name":"Kalejak-e `Olya",
    "wof:placetype":"locality"
},
  "geometry": {"coordinates":[58.38152,28.33502],"type":"Point"}
}