{
  "type": "Feature",
  "properties": {
    "gn:admin1_code":"1",
    "gn:asciiname":"Qushabolagh",
    "gn:country_code":"IR",
    "gn:dem":2343,
    "gn:feature_class":"P",
    "gn:feature_code":"PPL",
    "gn:name":"Q\u016bsh\u0101bol\u0101gh",
    "gn:population":0,
    "gn:timezone":"Asia/Tehran",
    "iso:country":"IR",
    "name:fas_x_preferred":[
        "\u0642\u0648\u0634\u0647 \u0628\u0644\u0627\u063a"
    ],
    "name:fas_x_variant":[
        "Q\u016bsheh Bol\u0101gh",
        "\u0642\u0648\u0634\u0627\u0628\u0644\u0627\u063a"
    ],
    "name:und_x_variant":[
        "Q\u016bsh\u0101bol\u0101gh"
    ],
    "wof:name":"Qushabolagh",
    "wof:placetype":"locality"
},
  "geometry": {"coordinates":[47.24542,36.50445],"type":"Point"}
}