{
  "type": "Feature",
  "properties": {
    "gn:admin1_code":"36",
    "gn:asciiname":"Sohrin",
    "gn:country_code":"IR",
    "gn:dem":1864,
    "gn:feature_class":"P",
    "gn:feature_code":"PPL",
    "gn:name":"Sohr\u012bn",
    "gn:population":0,
    "gn:timezone":"Asia/Tehran",
    "iso:country":"IR",
    "name:fas_x_preferred":[
        "\u0633\u0647\u0631\u064a\u0646"
    ],
    "name:fas_x_variant":[
        "\u0630\u0648\u0643\u064e\u0631\u0627\u0626\u064a\u0646",
        "\u0633\u064f\u0647\u0631\u064a\u0646",
        "Mehr\u012bn",
        "\u0645\u0650\u0647\u0631\u064a\u0646",
        "Sohar\u012bn"
    ],
    "name:und_x_variant":[
        "Zokhrun",
        "Sohr\u012bn",
        "Z\u0304\u016bkar\u0101\u2019\u012bn",
        "Zukr\u0101\u012bn"
    ],
    "wof:name":"Sohrin",
    "wof:placetype":"locality"
},
  "geometry": {"coordinates":[48.41406,36.86381],"type":"Point"}
}