{
  "type": "Feature",
  "properties": {
    "gn:admin1_code":"42.0",
    "gn:asciiname":"Qal`eh Sorkh",
    "gn:country_code":"IR",
    "gn:dem":1066,
    "gn:feature_class":"P",
    "gn:feature_code":"PPL",
    "gn:name":"Qal\u2018eh Sorkh",
    "gn:population":0,
    "gn:timezone":"Asia/Tehran",
    "iso:country":"IR",
    "name:fas_x_preferred":[
        "Qal\u2018a Surkh"
    ],
    "name:fas_x_variant":[
        "Qal\u2018eh Surkh",
        "Qal\u2018eh-ye Sorkh",
        "\u0642\u0644\u0639\u0647 \u0633\u0631\u062e",
        "Qal\u2018eh Sorkh"
    ],
    "wof:name":"Qal`eh Sorkh",
    "wof:placetype":"locality"
},
  "geometry": {"coordinates":[60.353,35.40417],"type":"Point"}
}