{
  "type": "Feature",
  "properties": {
    "gn:admin1_code":"29",
    "gn:asciiname":"Mohammadabad-e Katagi",
    "gn:country_code":"IR",
    "gn:dem":420,
    "gn:feature_class":"P",
    "gn:feature_code":"PPL",
    "gn:name":"Mo\u1e29ammad\u0101b\u0101d-e Katag\u012b",
    "gn:population":0,
    "gn:timezone":"Asia/Tehran",
    "iso:country":"IR",
    "name:fas_x_preferred":[
        "\u0645\u062d\u0645\u062f \u0622\u0628\u0627\u062f \u06a9\u062a\u06af\u06cc"
    ],
    "name:fas_x_variant":[
        "Mo\u1e29ammad\u0101b\u0101d-e Katag\u012b"
    ],
    "wof:name":"Mohammadabad-e Katagi",
    "wof:placetype":"locality"
},
  "geometry": {"coordinates":[58.37379,27.83973],"type":"Point"}
}