{
  "type": "Feature",
  "properties": {
    "gn:admin1_code":"1",
    "gn:asciiname":"Quch`ali",
    "gn:country_code":"IR",
    "gn:dem":804,
    "gn:feature_class":"P",
    "gn:feature_code":"PPL",
    "gn:name":"Q\u016bch\u2018al\u012b",
    "gn:population":0,
    "gn:timezone":"Asia/Tehran",
    "iso:country":"IR",
    "name:fas_x_preferred":[
        "\u0642\u0648\u0686\u0639\u0644\u06cc"
    ],
    "name:fas_x_variant":[
        "\u0642\u0648\u0686\u0639\u064e\u0644\u06cc",
        "Q\u016bch\u2018al\u012b"
    ],
    "wof:name":"Quch`ali",
    "wof:placetype":"locality"
},
  "geometry": {"coordinates":[44.7436,39.6623],"type":"Point"}
}