{
  "type": "Feature",
  "properties": {
    "gn:admin1_code":"4.0",
    "gn:asciiname":"Deh-e Now-ye Milak",
    "gn:country_code":"IR",
    "gn:dem":490,
    "gn:feature_class":"P",
    "gn:feature_code":"PPL",
    "gn:name":"Deh-e Now-ye M\u012blak",
    "gn:population":0,
    "gn:timezone":"Asia/Tehran",
    "iso:country":"IR",
    "name:fas_x_preferred":[
        "\u062f\u0647 \u0646\u0648 \u0645\u0644\u06a9"
    ],
    "name:fas_x_variant":[
        "Deh Now-e \u2018Al\u012b Kh\u0101n",
        "\u062f\u0647 \u0646\u0648 \u0645\u06cc\u0644\u06a9",
        "\u062f\u0647\u0646\u0648 \u0639\u0644\u06cc \u062e\u0627\u0646"
    ],
    "name:und_x_variant":[
        "Dehnow \u2018Ali Khan",
        "Ali Khan",
        "Deh Now-e Malek",
        "Deh-e Now-ye M\u012blak",
        "Dehnow-ye \u2018Al\u012b Kh\u0101n"
    ],
    "wof:name":"Deh-e Now-ye Milak",
    "wof:placetype":"locality"
},
  "geometry": {"coordinates":[61.79144,30.98706],"type":"Point"}
}