{
  "type": "Feature",
  "properties": {
    "gn:admin1_code":"33",
    "gn:asciiname":"Qurkhowd",
    "gn:country_code":"IR",
    "gn:dem":2105,
    "gn:feature_class":"P",
    "gn:feature_code":"PPL",
    "gn:name":"Q\u016brkhowd",
    "gn:population":0,
    "gn:timezone":"Asia/Tehran",
    "iso:country":"IR",
    "name:fas_x_preferred":[
        "\u0642\u0648\u0631\u062e\u0648\u062f"
    ],
    "name:fas_x_variant":[
        "Q\u016brkh\u016bd"
    ],
    "name:und_x_variant":[
        "Q\u016brkhowd"
    ],
    "wof:name":"Qurkhowd",
    "wof:placetype":"locality"
},
  "geometry": {"coordinates":[47.6229,38.0525],"type":"Point"}
}