{
  "type": "Feature",
  "properties": {
    "gn:admin1_code":"39",
    "gn:asciiname":"Qomrud",
    "gn:country_code":"IR",
    "gn:dem":845,
    "gn:feature_class":"P",
    "gn:feature_code":"PPL",
    "gn:name":"Qomr\u016bd",
    "gn:population":0,
    "gn:timezone":"Asia/Tehran",
    "iso:country":"IR",
    "name:ceb_x_preferred":[
        "Qomr\u016bd"
    ],
    "name:fas_x_preferred":[
        "\u0642\u0645\u0631\u0648\u062f"
    ],
    "name:fas_x_variant":[
        "Qomr\u016bd"
    ],
    "name:swe_x_preferred":[
        "Qomr\u016bd"
    ],
    "name:und_x_variant":[
        "Qumr\u016bd"
    ],
    "wof:name":"Qomrud",
    "wof:placetype":"locality"
},
  "geometry": {"coordinates":[51.0717,34.7257],"type":"Point"}
}