{
  "type": "Feature",
  "properties": {
    "gn:admin1_code":"35.0",
    "gn:asciiname":"Khatib Mahalleh",
    "gn:country_code":"IR",
    "gn:dem":2025,
    "gn:feature_class":"P",
    "gn:feature_code":"PPL",
    "gn:name":"Kha\u0163\u012bb Ma\u1e29alleh",
    "gn:population":0,
    "gn:timezone":"Asia/Tehran",
    "iso:country":"IR",
    "name:fas_x_preferred":[
        "\u062e\u0637\u06cc\u0628 \u0645\u062d\u0644\u0647"
    ],
    "name:und_x_variant":[
        "Kha\u0163\u012bb Ma\u1e29alleh"
    ],
    "wof:name":"Khatib Mahalleh",
    "wof:placetype":"locality"
},
  "geometry": {"coordinates":[52.1843,36.28228],"type":"Point"}
}