{
  "type": "Feature",
  "properties": {
    "gn:admin1_code":"7",
    "gn:asciiname":"`Aliabad-e Fasarud",
    "gn:country_code":"IR",
    "gn:dem":1090,
    "gn:feature_class":"P",
    "gn:feature_code":"PPL",
    "gn:name":"\u2018Al\u012b\u0101b\u0101d-e Fas\u0101r\u016bd",
    "gn:population":0,
    "gn:timezone":"Asia/Tehran",
    "iso:country":"IR",
    "name:fas_x_preferred":[
        "\u0639\u0644\u06cc \u0622\u0628\u0627\u062f \u0641\u0633\u0627\u0631\u0648\u062f"
    ],
    "name:fas_x_variant":[
        "\u2018Al\u012b\u0101b\u0101d-e Fas\u0101r\u016bd"
    ],
    "wof:name":"`Aliabad-e Fasarud",
    "wof:placetype":"locality"
},
  "geometry": {"coordinates":[54.3363,28.7841],"type":"Point"}
}