{
  "type": "Feature",
  "properties": {
    "gn:admin1_code":"8.0",
    "gn:asciiname":"Kalfarud",
    "gn:country_code":"IR",
    "gn:dem":-9,
    "gn:feature_class":"P",
    "gn:feature_code":"PPL",
    "gn:name":"Kalf\u0101r\u016bd",
    "gn:population":0,
    "gn:timezone":"Asia/Tehran",
    "iso:country":"IR",
    "name:fas_x_preferred":[
        "Kalf\u0101r\u016bd"
    ],
    "name:fas_x_variant":[
        "\u06a9\u0644\u0641\u0627\u0631\u0648\u062f",
        "\u06a9\u0644\u0641\u0627 \u0631\u0648\u062f",
        "\u0644\u0645\u06cc\u0631 \u0633\u0641\u0644\u06cc",
        "\u0644\u0648\u0645\u0631",
        "\u0627\u0628\u0627\u062e\u0627\u0644\u0647"
    ],
    "name:und_x_variant":[
        "Kalf\u0101 R\u016bd",
        "Lam\u012br-e Sofl\u00e1",
        "L\u016bmar",
        "Ab\u0101kh\u0101leh"
    ],
    "wof:name":"Kalfarud",
    "wof:placetype":"locality"
},
  "geometry": {"coordinates":[48.97057,37.75673],"type":"Point"}
}