{
  "type": "Feature",
  "properties": {
    "gn:admin1_code":"4.0",
    "gn:asciiname":"Jarikeh",
    "gn:country_code":"IR",
    "gn:dem":503,
    "gn:feature_class":"P",
    "gn:feature_code":"PPL",
    "gn:name":"Jar\u012bkeh",
    "gn:population":0,
    "gn:timezone":"Asia/Tehran",
    "iso:country":"IR",
    "name:fas_x_preferred":[
        "\u062c\u0631\u06cc\u06a9\u0647"
    ],
    "name:fas_x_variant":[
        "Jar\u012bkeh"
    ],
    "wof:name":"Jarikeh",
    "wof:placetype":"locality"
},
  "geometry": {"coordinates":[61.761,30.814],"type":"Point"}
}