{
  "type": "Feature",
  "properties": {
    "gn:admin1_code":"28.0",
    "gn:asciiname":"Radan",
    "gn:country_code":"IR",
    "gn:dem":1563,
    "gn:feature_class":"P",
    "gn:feature_code":"PPL",
    "gn:name":"R\u0101d\u0101n",
    "gn:population":0,
    "gn:timezone":"Asia/Tehran",
    "iso:country":"IR",
    "name:ceb_x_preferred":[
        "Radan"
    ],
    "name:fas_x_preferred":[
        "\u0631\u0627\u062f\u0627\u0646"
    ],
    "name:swe_x_preferred":[
        "Radan"
    ],
    "wof:name":"Radan",
    "wof:placetype":"locality"
},
  "geometry": {"coordinates":[51.76667,32.64167],"type":"Point"}
}