{
  "type": "Feature",
  "properties": {
    "gn:admin1_code":"5.0",
    "gn:asciiname":"Kaleh-i-Aru",
    "gn:country_code":"IR",
    "gn:dem":667,
    "gn:feature_class":"P",
    "gn:feature_code":"PPL",
    "gn:name":"Kaleh-i-Aru",
    "gn:population":0,
    "gn:timezone":"Asia/Tehran",
    "iso:country":"IR",
    "name:fas_x_preferred":[
        "\u0622\u0631\u0648"
    ],
    "name:fas_x_variant":[
        "\u0100r\u016b"
    ],
    "wof:name":"Kaleh-i-Aru",
    "wof:placetype":"locality"
},
  "geometry": {"coordinates":[50.69085,30.59114000000001],"type":"Point"}
}