{
  "type": "Feature",
  "properties": {
    "gn:admin1_code":"7",
    "gn:asciiname":"Jowzjan",
    "gn:country_code":"IR",
    "gn:dem":1077,
    "gn:feature_class":"P",
    "gn:feature_code":"PPL",
    "gn:name":"Jowzj\u0101n",
    "gn:population":0,
    "gn:timezone":"Asia/Tehran",
    "iso:country":"IR",
    "name:ara_x_preferred":[
        "\u062c\u0648\u0632\u062c\u0627\u0646"
    ],
    "name:fas_x_preferred":[
        "\u062c\u0648\u0632\u062c\u0627\u0646"
    ],
    "name:fas_x_variant":[
        "Jowzj\u0101n"
    ],
    "name:msa_x_preferred":[
        "Jowzjan"
    ],
    "name:und_x_variant":[
        "Juzj\u016bn",
        "Jowz J\u0101n",
        "J\u016bz\u0101n"
    ],
    "wof:name":"Jowzjan",
    "wof:placetype":"locality"
},
  "geometry": {"coordinates":[54.4385,28.6793],"type":"Point"}
}