{
  "type": "Feature",
  "properties": {
    "gn:admin1_code":"8",
    "gn:asciiname":"Kord Sara Kuh-e Bala",
    "gn:country_code":"IR",
    "gn:dem":386,
    "gn:feature_class":"P",
    "gn:feature_code":"PPL",
    "gn:name":"Kord Sar\u0101 K\u016bh-e B\u0101l\u0101",
    "gn:population":0,
    "gn:timezone":"Asia/Tehran",
    "iso:country":"IR",
    "name:fas_x_preferred":[
        "Kord Sar\u0101 K\u016bh-e B\u0101l\u0101"
    ],
    "name:fas_x_variant":[
        "\u06a9\u0631\u062f \u0633\u0631\u0627 \u06a9\u0648\u0647 \u0628\u0627\u0644\u0627",
        "\u06a9\u0631\u062f\u0633\u0631\u0627\u06a9\u0648\u0647 \u0628\u0627\u0644\u0627"
    ],
    "name:msa_x_preferred":[
        "Kord Sara Kuh-e Bala"
    ],
    "name:und_x_variant":[
        "\u06a9\u0631\u062f \u0633\u0631\u0627 \u06a9\u0648\u0647 \u0628\u0627\u0644\u0627"
    ],
    "wof:name":"Kord Sara Kuh-e Bala",
    "wof:placetype":"locality"
},
  "geometry": {"coordinates":[50.10835,37.079],"type":"Point"}
}