{
  "type": "Feature",
  "properties": {
    "gn:admin1_code":"42",
    "gn:asciiname":"Jan Ahmad",
    "gn:country_code":"IR",
    "gn:dem":1933,
    "gn:feature_class":"P",
    "gn:feature_code":"PPL",
    "gn:name":"J\u0101n A\u1e29mad",
    "gn:population":0,
    "gn:timezone":"Asia/Tehran",
    "iso:country":"IR",
    "name:fas_x_preferred":[
        "\u062c\u0627\u0646 \u0627\u062d\u0645\u062f"
    ],
    "name:fas_x_variant":[
        "J\u0101n A\u1e29mad"
    ],
    "wof:name":"Jan Ahmad",
    "wof:placetype":"locality"
},
  "geometry": {"coordinates":[59.83053,33.34084],"type":"Point"}
}