{
  "type": "Feature",
  "properties": {
    "gn:admin1_code":"28.0",
    "gn:asciiname":"Mohsenabad",
    "gn:country_code":"IR",
    "gn:dem":1572,
    "gn:feature_class":"P",
    "gn:feature_code":"PPL",
    "gn:name":"Mo\u1e29sen\u0101b\u0101d",
    "gn:population":0,
    "gn:timezone":"Asia/Tehran",
    "iso:country":"IR",
    "name:fas_x_preferred":[
        "Mo\u1e29sen\u0101b\u0101d"
    ],
    "name:fas_x_variant":[
        "\u0100darmon\u0101\u0101b\u0101d",
        "\u0645\u062d\u0633\u0646 \u0622\u0628\u0627\u062f"
    ],
    "name:und_x_variant":[
        "\u0100darman\u0101b\u0101d",
        "\u0100darman\u0101\u0101b\u0101d",
        "Aderman\u0101b\u0101d"
    ],
    "wof:name":"Mohsenabad",
    "wof:placetype":"locality"
},
  "geometry": {"coordinates":[51.71191,32.82819],"type":"Point"}
}