{
  "type": "Feature",
  "properties": {
    "gn:admin1_code":"4.0",
    "gn:asciiname":"Kalpuregan",
    "gn:country_code":"IR",
    "gn:dem":1129,
    "gn:feature_class":"P",
    "gn:feature_code":"PPL",
    "gn:name":"Kalp\u016breg\u0101n",
    "gn:population":0,
    "gn:timezone":"Asia/Tehran",
    "iso:country":"IR",
    "name:fas_x_preferred":[
        "\u06a9\u0644\u067e\u0648\u0631\u06af\u0627\u0646"
    ],
    "name:fas_x_variant":[
        "Kalp\u016breh K\u0101n",
        "Kalp\u016breg\u0101n"
    ],
    "name:und_x_variant":[
        "Kolp\u016brg\u0101n",
        "Kalparkan",
        "Kalpoor Kan",
        "Kalparak"
    ],
    "wof:name":"Kalpuregan",
    "wof:placetype":"locality"
},
  "geometry": {"coordinates":[62.5395,27.2295],"type":"Point"}
}