{
  "type": "Feature",
  "properties": {
    "gn:admin1_code":"9",
    "gn:asciiname":"Mobarakabad",
    "gn:country_code":"IR",
    "gn:dem":1681,
    "gn:feature_class":"P",
    "gn:feature_code":"PPL",
    "gn:name":"Mob\u0101rak\u0101b\u0101d",
    "gn:population":0,
    "gn:timezone":"Asia/Tehran",
    "iso:country":"IR",
    "name:fas_x_preferred":[
        "Mob\u0101rak\u0101b\u0101d"
    ],
    "name:fas_x_variant":[
        "\u0645\u0628\u0627\u0631\u06a9 \u0622\u0628\u0627\u062f"
    ],
    "name:und_x_variant":[
        "\u0645\u0628\u0627\u0631\u06a9 \u0622\u0628\u0627\u062f"
    ],
    "wof:name":"Mobarakabad",
    "wof:placetype":"locality"
},
  "geometry": {"coordinates":[48.66433,34.40468],"type":"Point"}
}