{
  "type": "Feature",
  "properties": {
    "gn:admin1_code":"29",
    "gn:asciiname":"Korran",
    "gn:country_code":"IR",
    "gn:dem":1945,
    "gn:feature_class":"P",
    "gn:feature_code":"PPL",
    "gn:name":"Korr\u0101n",
    "gn:population":0,
    "gn:timezone":"Asia/Tehran",
    "iso:country":"IR",
    "name:fas_x_preferred":[
        "Korr\u0101n"
    ],
    "name:fas_x_variant":[
        "\u06a9\u0631\u0627\u0646",
        "Khorr\u0101n"
    ],
    "name:und_x_variant":[
        "Khorr\u0101n",
        "Kooran",
        "Khorram",
        "Khurram",
        "\u06a9\u0631\u0627\u0646"
    ],
    "wof:name":"Korran",
    "wof:placetype":"locality"
},
  "geometry": {"coordinates":[55.72943000000001,29.72107],"type":"Point"}
}