{
  "type": "Feature",
  "properties": {
    "gn:admin1_code":"33",
    "gn:asciiname":"Bolgan",
    "gn:country_code":"IR",
    "gn:dem":1795,
    "gn:feature_class":"P",
    "gn:feature_code":"PPL",
    "gn:name":"Bolg\u0101n",
    "gn:population":0,
    "gn:timezone":"Asia/Tehran",
    "iso:country":"IR",
    "name:fas_x_preferred":[
        "Bolq\u0101n"
    ],
    "name:fas_x_variant":[
        "Bolg\u0101n",
        "\u0628\u0644\u06af\u0627\u0646",
        "\u0628\u0644\u0642\u0627\u0646"
    ],
    "name:und_x_variant":[
        "\u0628\u0644\u06af\u0627\u0646"
    ],
    "wof:name":"Bolgan",
    "wof:placetype":"locality"
},
  "geometry": {"coordinates":[46.9672,37.2724],"type":"Point"}
}