{
  "type": "Feature",
  "properties": {
    "gn:admin1_code":"4.0",
    "gn:asciiname":"Deh-e Bozi",
    "gn:country_code":"IR",
    "gn:dem":479,
    "gn:feature_class":"P",
    "gn:feature_code":"PPL",
    "gn:name":"Deh-e Boz\u012b",
    "gn:population":0,
    "gn:timezone":"Asia/Tehran",
    "iso:country":"IR",
    "name:fas_x_preferred":[
        "Am\u012br\u0101b\u0101d-e Baz\u012b"
    ],
    "name:fas_x_variant":[
        "\u062f\u0647 \u0628\u0632\u06cc",
        "\u062f\u0647 \u0628\u0632\u06cc \u0633\u0641\u0644\u06cc",
        "\u062f\u0647 \u0628\u0632\u06cc \u0639\u0644\u06cc\u0627"
    ],
    "name:und_x_variant":[
        "Deh-e Boz\u012b",
        "\u062f\u0647 \u0628\u0632\u06cc",
        "Deh-e Boz\u012b-ye Sofl\u00e1",
        "Deh-e Boz\u012b-ye \u2018Oly\u0101",
        "Deh-e Bazz\u012b",
        "Deh Bazi",
        "Baz\u012b-ye P\u0101\u2019\u012bn"
    ],
    "wof:name":"Deh-e Bozi",
    "wof:placetype":"locality"
},
  "geometry": {"coordinates":[61.4858,31.16194],"type":"Point"}
}