{
  "type": "Feature",
  "properties": {
    "gn:admin1_code":"1",
    "gn:asciiname":"Kasian",
    "gn:country_code":"IR",
    "gn:dem":1125,
    "gn:feature_class":"P",
    "gn:feature_code":"PPL",
    "gn:name":"Kas\u012b\u0101n",
    "gn:population":0,
    "gn:timezone":"Asia/Tehran",
    "iso:country":"IR",
    "name:fas_x_preferred":[
        "\u06a9\u0633\u06cc\u0627\u0646"
    ],
    "name:fas_x_variant":[
        "Kas\u012b\u0101n"
    ],
    "wof:name":"Kasian",
    "wof:placetype":"locality"
},
  "geometry": {"coordinates":[44.9854,38.8937],"type":"Point"}
}