{
  "type": "Feature",
  "properties": {
    "gn:admin1_code":"15",
    "gn:asciiname":"Dinab",
    "gn:country_code":"IR",
    "gn:dem":884,
    "gn:feature_class":"P",
    "gn:feature_code":"PPL",
    "gn:name":"D\u012bn\u0101b",
    "gn:population":0,
    "gn:timezone":"Asia/Tehran",
    "iso:country":"IR",
    "name:fas_x_preferred":[
        "D\u012bn\u0101b"
    ],
    "wof:name":"Dinab",
    "wof:placetype":"locality"
},
  "geometry": {"coordinates":[49.7975,31.9375],"type":"Point"}
}