{
  "type": "Feature",
  "properties": {
    "gn:admin1_code":"8.0",
    "gn:asciiname":"Bajargah",
    "gn:country_code":"IR",
    "gn:dem":69,
    "gn:feature_class":"P",
    "gn:feature_code":"PPL",
    "gn:name":"Baj\u0101rg\u0101h",
    "gn:population":0,
    "gn:timezone":"Asia/Tehran",
    "iso:country":"IR",
    "name:fas_x_preferred":[
        "Baj\u0101rg\u0101h"
    ],
    "wof:name":"Bajargah",
    "wof:placetype":"locality"
},
  "geometry": {"coordinates":[49.53056,37.1125],"type":"Point"}
}