{
  "type": "Feature",
  "properties": {
    "gn:admin1_code":"4.0",
    "gn:asciiname":"Bazman",
    "gn:country_code":"IR",
    "gn:dem":964,
    "gn:feature_class":"P",
    "gn:feature_code":"PPL",
    "gn:name":"Bazm\u0101n",
    "gn:population":0,
    "gn:timezone":"Asia/Tehran",
    "iso:country":"IR",
    "name:ara_x_preferred":[
        "\u0628\u0632\u0645\u0627\u0646"
    ],
    "name:aze_x_preferred":[
        "B\u0259zman"
    ],
    "name:ceb_x_preferred":[
        "Bazm\u0101n"
    ],
    "name:fas_x_preferred":[
        "\u0628\u0632\u0645\u0627\u0646"
    ],
    "name:fas_x_variant":[
        "Bazm\u0101n"
    ],
    "name:ita_x_preferred":[
        "Bazman"
    ],
    "name:mlg_x_preferred":[
        "Bazman"
    ],
    "name:swe_x_preferred":[
        "Bazm\u0101n"
    ],
    "name:tur_x_preferred":[
        "Bezman"
    ],
    "wof:name":"Bazman",
    "wof:placetype":"locality"
},
  "geometry": {"coordinates":[60.18059,27.85637],"type":"Point"}
}