{
  "type": "Feature",
  "properties": {
    "gn:admin1_code":"29.0",
    "gn:asciiname":"Asiab-e Qazi",
    "gn:country_code":"IR",
    "gn:dem":2355,
    "gn:feature_class":"P",
    "gn:feature_code":"PPL",
    "gn:name":"\u0100s\u012b\u0101b-e Q\u0101\u1e95\u012b",
    "gn:population":0,
    "gn:timezone":"Asia/Tehran",
    "iso:country":"IR",
    "name:fas_x_preferred":[
        "\u0622\u0633\u06cc\u0627\u0628 \u0642\u0627\u0636\u06cc"
    ],
    "name:fas_x_variant":[
        "\u0100s\u012b\u0101b Q\u0101\u1e95\u012b",
        "\u0100s\u012b\u0101b-e Q\u0101\u1e95\u012b",
        "\u0637\u0627\u062d\u0648\u0646\u0647 \u0642\u0627\u0636\u06cc"
    ],
    "name:und_x_variant":[
        "\u0162\u0101h\u016bneh Q\u0101\u1e95\u012b",
        "\u0100s\u012by\u0101b-e Q\u0101z\u012b",
        "\u0100sey\u0101b-e Q\u0101z\u012b",
        "\u0162\u0101\u1e29\u016bneh-ye Q\u0101\u1e95\u012b"
    ],
    "wof:name":"Asiab-e Qazi",
    "wof:placetype":"locality"
},
  "geometry": {"coordinates":[56.4178,29.3497],"type":"Point"}
}