{
  "type": "Feature",
  "properties": {
    "gn:admin1_code":"9",
    "gn:asciiname":"Cheshmeh Qarah",
    "gn:country_code":"IR",
    "gn:dem":2107,
    "gn:feature_class":"P",
    "gn:feature_code":"PPL",
    "gn:name":"Cheshmeh Qarah",
    "gn:population":0,
    "gn:timezone":"Asia/Tehran",
    "iso:country":"IR",
    "name:fas_x_preferred":[
        "\u0686\u0634\u0645\u0647 \u0642\u0631\u0647"
    ],
    "wof:name":"Cheshmeh Qarah",
    "wof:placetype":"locality"
},
  "geometry": {"coordinates":[47.87107,34.90616],"type":"Point"}
}