{
  "type": "Feature",
  "properties": {
    "gn:admin1_code":"13.0",
    "gn:asciiname":"Makalani",
    "gn:country_code":"IR",
    "gn:dem":1546,
    "gn:feature_class":"P",
    "gn:feature_code":"PPL",
    "gn:name":"M\u0101kal\u0101n\u012b",
    "gn:population":0,
    "gn:timezone":"Asia/Tehran",
    "iso:country":"IR",
    "name:fas_x_preferred":[
        "M\u0101kal\u0101n\u012b"
    ],
    "wof:name":"Makalani",
    "wof:placetype":"locality"
},
  "geometry": {"coordinates":[46.58333,34.36667],"type":"Point"}
}