{
  "type": "Feature",
  "properties": {
    "gn:admin1_code":"33",
    "gn:asciiname":"Tokmeh Tappeh",
    "gn:country_code":"IR",
    "gn:dem":2113,
    "gn:feature_class":"P",
    "gn:feature_code":"PPL",
    "gn:name":"Tokmeh Tappeh",
    "gn:population":0,
    "gn:timezone":"Asia/Tehran",
    "iso:country":"IR",
    "name:fas_x_preferred":[
        "\u062a\u06a9\u0645\u0647 \u062a\u067e\u0647"
    ],
    "wof:name":"Tokmeh Tappeh",
    "wof:placetype":"locality"
},
  "geometry": {"coordinates":[46.88800000000001,37.0723],"type":"Point"}
}