{
  "type": "Feature",
  "properties": {
    "gn:admin1_code":"11",
    "gn:asciiname":"Sand",
    "gn:country_code":"IR",
    "gn:dem":10,
    "gn:feature_class":"P",
    "gn:feature_code":"PPL",
    "gn:name":"Sand",
    "gn:population":0,
    "gn:timezone":"Asia/Tehran",
    "iso:country":"IR",
    "name:fas_x_preferred":[
        "\u0633\u0646\u062f"
    ],
    "name:und_x_variant":[
        "\u0633\u0646\u062f",
        "Sand"
    ],
    "wof:name":"Sand",
    "wof:placetype":"locality"
},
  "geometry": {"coordinates":[58.25587,25.70075],"type":"Point"}
}