{
  "type": "Feature",
  "properties": {
    "gn:admin1_code":"4.0",
    "gn:asciiname":"Kahn-e Molla",
    "gn:country_code":"IR",
    "gn:dem":1156,
    "gn:feature_class":"P",
    "gn:feature_code":"PPL",
    "gn:name":"Kahn-e Moll\u0101",
    "gn:population":0,
    "gn:timezone":"Asia/Tehran",
    "iso:country":"IR",
    "name:fas_x_preferred":[
        "\u06a9\u0647\u0646 \u0645\u0644\u0651\u0627"
    ],
    "name:fas_x_variant":[
        "Kahn-e Moll\u0101"
    ],
    "name:und_x_variant":[
        "Kahn-e Moll",
        "Kahn Molla Zaboli"
    ],
    "wof:name":"Kahn-e Molla",
    "wof:placetype":"locality"
},
  "geometry": {"coordinates":[61.9452,27.3052],"type":"Point"}
}