{
  "type": "Feature",
  "properties": {
    "gn:admin1_code":"23",
    "gn:asciiname":"Qal`eh-ye Jahangir",
    "gn:country_code":"IR",
    "gn:dem":2040,
    "gn:feature_class":"P",
    "gn:feature_code":"PPL",
    "gn:name":"Qal\u2018eh-ye Jah\u0101ng\u012br",
    "gn:population":0,
    "gn:timezone":"Asia/Tehran",
    "iso:country":"IR",
    "name:fas_x_preferred":[
        "\u0642\u0644\u0639\u0647 \u062c\u0647\u0627\u0646\u06af\u06cc\u0631"
    ],
    "name:fas_x_variant":[
        "Qal\u2018eh-ye Jah\u0101ng\u012br"
    ],
    "name:und_x_variant":[
        "Qal\u2018eh Jangi",
        "Qal\u2018eh-ye Jang\u012b"
    ],
    "wof:name":"Qal`eh-ye Jahangir",
    "wof:placetype":"locality"
},
  "geometry": {"coordinates":[49.09658,33.61802],"type":"Point"}
}