{
  "type": "Feature",
  "properties": {
    "gn:admin1_code":"29",
    "gn:asciiname":"Sabz Gezi",
    "gn:country_code":"IR",
    "gn:dem":599,
    "gn:feature_class":"P",
    "gn:feature_code":"PPL",
    "gn:name":"Sabz Gez\u012b",
    "gn:population":0,
    "gn:timezone":"Asia/Tehran",
    "iso:country":"IR",
    "name:fas_x_preferred":[
        "\u0633\u0628\u0632 \u06af\u0632\u06cc"
    ],
    "name:fas_x_variant":[
        "Sabz Gez\u012b"
    ],
    "wof:name":"Sabz Gezi",
    "wof:placetype":"locality"
},
  "geometry": {"coordinates":[57.8927,28.3028],"type":"Point"}
}