{
  "type": "Feature",
  "properties": {
    "gn:admin1_code":"15",
    "gn:asciiname":"Ghafur",
    "gn:country_code":"IR",
    "gn:dem":65,
    "gn:feature_class":"P",
    "gn:feature_code":"PPL",
    "gn:name":"Ghaf\u016br",
    "gn:population":0,
    "gn:timezone":"Asia/Tehran",
    "iso:country":"IR",
    "name:fas_x_preferred":[
        "Ghaf\u016br"
    ],
    "wof:name":"Ghafur",
    "wof:placetype":"locality"
},
  "geometry": {"coordinates":[48.81667,32.15],"type":"Point"}
}