{
  "type": "Feature",
  "properties": {
    "gn:admin1_code":"35.0",
    "gn:asciiname":"Tilek",
    "gn:country_code":"IR",
    "gn:dem":1463,
    "gn:feature_class":"P",
    "gn:feature_code":"PPL",
    "gn:name":"T\u012blek",
    "gn:population":0,
    "gn:timezone":"Asia/Tehran",
    "iso:country":"IR",
    "name:fas_x_preferred":[
        "\u062a\u06cc\u0644\u06a9"
    ],
    "name:fas_x_variant":[
        "\u062a\u064a\u0644\u064e\u0643",
        "T\u012blek"
    ],
    "name:und_x_variant":[
        "T\u012blak"
    ],
    "wof:name":"Tilek",
    "wof:placetype":"locality"
},
  "geometry": {"coordinates":[53.58819,36.12665],"type":"Point"}
}