{
  "type": "Feature",
  "properties": {
    "gn:admin1_code":"35.0",
    "gn:asciiname":"Kachal Deh-e Pa'in",
    "gn:country_code":"IR",
    "gn:dem":77,
    "gn:feature_class":"P",
    "gn:feature_code":"PPL",
    "gn:name":"Kachal Deh-e P\u0101\u2019\u012bn",
    "gn:population":0,
    "gn:timezone":"Asia/Tehran",
    "iso:country":"IR",
    "name:fas_x_preferred":[
        "\u067e\u0627\u0626\u064a\u0646 \u0643\u0686\u0644 \u062f\u0647"
    ],
    "name:fas_x_variant":[
        "P\u0101\u2019\u012bn Kachal Deh",
        "\u06a9\u0686\u0644 \u062f\u0647 \u067e\u0627\u06cc\u06cc\u0646",
        "\u0643\u0686\u0644 \u062f\u0647"
    ],
    "name:und_x_variant":[
        "Kachal Deh-e P\u0101\u2019\u012bn",
        "Kachal Deh"
    ],
    "wof:name":"Kachal Deh-e Pa'in",
    "wof:placetype":"locality"
},
  "geometry": {"coordinates":[52.23877,36.45398],"type":"Point"}
}