{
  "type": "Feature",
  "properties": {
    "gn:admin1_code":"1",
    "gn:asciiname":"Shur Gel",
    "gn:country_code":"IR",
    "gn:dem":1522,
    "gn:feature_class":"P",
    "gn:feature_code":"PPL",
    "gn:name":"Sh\u016br Gel",
    "gn:population":0,
    "gn:timezone":"Asia/Tehran",
    "iso:country":"IR",
    "name:fas_x_preferred":[
        "\u0634\u0648\u0631 \u06af\u0650\u0644"
    ],
    "name:fas_x_variant":[
        "\u0634\u0648\u0631 \u06af\u064f\u0644",
        "\u0634\u0648\u0631 \u06af\u0644",
        "\u0634\u064f\u0651\u0631 \u06af\u0650\u0644",
        "Sh\u016br Gel"
    ],
    "name:und_x_variant":[
        "Sh\u016br Gol",
        "Shoor Gel"
    ],
    "wof:name":"Shur Gel",
    "wof:placetype":"locality"
},
  "geometry": {"coordinates":[44.841,38.0844],"type":"Point"}
}