{
  "type": "Feature",
  "properties": {
    "gn:admin1_code":"15",
    "gn:asciiname":"Helal",
    "gn:cc2":"IR",
    "gn:country_code":"IR",
    "gn:dem":94,
    "gn:feature_class":"P",
    "gn:feature_code":"PPL",
    "gn:name":"Hel\u0101l",
    "gn:population":0,
    "gn:timezone":"Asia/Tehran",
    "iso:country":"IR",
    "name:ara_x_preferred":[
        "\u0647\u0644\u0627\u0644"
    ],
    "name:fas_x_preferred":[
        "Hel\u0101l"
    ],
    "name:fas_x_variant":[
        "\u0647\u0644\u0627\u0644"
    ],
    "name:und_x_variant":[
        "Qal\u2018eh-ye N\u0101\u015fer",
        "Qal\u2018eh-ye Na\u015f\u012br"
    ],
    "wof:name":"Helal",
    "wof:placetype":"locality"
},
  "geometry": {"coordinates":[48.26667,32.28333],"type":"Point"}
}