{
  "type": "Feature",
  "properties": {
    "gn:admin1_code":"35.0",
    "gn:asciiname":"Rudbar Dasht",
    "gn:country_code":"IR",
    "gn:dem":160,
    "gn:feature_class":"P",
    "gn:feature_code":"PPL",
    "gn:name":"R\u016bdb\u0101r Dasht",
    "gn:population":0,
    "gn:timezone":"Asia/Tehran",
    "iso:country":"IR",
    "name:ara_x_preferred":[
        "\u0631\u0648\u062f\u0628\u0627\u0631\u062f\u0634\u062a"
    ],
    "name:ceb_x_preferred":[
        "R\u016bdb\u0101r Dasht"
    ],
    "name:fas_x_preferred":[
        "\u0631\u0648\u062f\u0628\u0627\u0631 \u062f\u0634\u062a"
    ],
    "name:fas_x_variant":[
        "R\u016bdb\u0101r Dasht",
        "\u0631\u0648\u062f\u0628\u0627\u0631\u062f\u0634\u062a"
    ],
    "name:swe_x_preferred":[
        "R\u016bdb\u0101r Dasht"
    ],
    "name:ukr_x_preferred":[
        "\u0420\u0443\u0434\u0431\u0430\u0440-\u0414\u0430\u0448\u0442"
    ],
    "wof:name":"Rudbar Dasht",
    "wof:placetype":"locality"
},
  "geometry": {"coordinates":[52.36128,36.42005],"type":"Point"}
}