{
  "type": "Feature",
  "properties": {
    "gn:admin1_code":"8.0",
    "gn:asciiname":"Jireh Mahalleh",
    "gn:country_code":"IR",
    "gn:dem":104,
    "gn:feature_class":"P",
    "gn:feature_code":"PPL",
    "gn:name":"J\u012breh Ma\u1e29alleh",
    "gn:population":0,
    "gn:timezone":"Asia/Tehran",
    "iso:country":"IR",
    "name:fas_x_preferred":[
        "\u062c\u06cc\u0631\u0647 \u0645\u062d\u0644\u0647"
    ],
    "name:und_x_variant":[
        "J\u012breh Ma\u1e29alleh"
    ],
    "wof:name":"Jireh Mahalleh",
    "wof:placetype":"locality"
},
  "geometry": {"coordinates":[49.3023,37.12255],"type":"Point"}
}