{
  "type": "Feature",
  "properties": {
    "gn:admin1_code":"28",
    "gn:asciiname":"Baz Bandeh",
    "gn:country_code":"IR",
    "gn:dem":1821,
    "gn:feature_class":"P",
    "gn:feature_code":"PPL",
    "gn:name":"B\u0101z Bandeh",
    "gn:population":0,
    "gn:timezone":"Asia/Tehran",
    "iso:country":"IR",
    "name:fas_x_preferred":[
        "\u0628\u0627\u0632 \u0628\u0646\u062f\u0647"
    ],
    "name:fas_x_variant":[
        "B\u0101zb\u0101n Deh",
        "B\u0101z Bandeh"
    ],
    "name:und_x_variant":[
        "W\u0101zbandeh",
        "V\u0101z Bandeh"
    ],
    "wof:name":"Baz Bandeh",
    "wof:placetype":"locality"
},
  "geometry": {"coordinates":[53.0961,32.6442],"type":"Point"}
}