{
  "type": "Feature",
  "properties": {
    "gn:admin1_code":"15.0",
    "gn:asciiname":"Seyyed Gharib",
    "gn:country_code":"IR",
    "gn:dem":3,
    "gn:feature_class":"P",
    "gn:feature_code":"PPL",
    "gn:name":"Seyyed Ghar\u012bb",
    "gn:population":0,
    "gn:timezone":"Asia/Tehran",
    "iso:country":"IR",
    "name:fas_x_preferred":[
        "\u0633\u06cc\u0651\u062f \u063a\u0631\u06cc\u0628"
    ],
    "name:fas_x_variant":[
        "Seyyed Ghar\u012bb"
    ],
    "wof:name":"Seyyed Gharib",
    "wof:placetype":"locality"
},
  "geometry": {"coordinates":[48.20069,30.35931],"type":"Point"}
}