{
  "type": "Feature",
  "properties": {
    "gn:admin1_code":"40",
    "gn:asciiname":"Mazra`eh-ye Rajab",
    "gn:country_code":"IR",
    "gn:dem":2469,
    "gn:feature_class":"P",
    "gn:feature_code":"PPL",
    "gn:name":"Mazra\u2018eh-ye Rajab",
    "gn:population":0,
    "gn:timezone":"Asia/Tehran",
    "iso:country":"IR",
    "name:fas_x_preferred":[
        "Mazra\u2018eh-ye Kh\u0101neh"
    ],
    "name:fas_x_variant":[
        "\u0645\u0632\u0631\u0639\u0647 \u0631\u062c\u0628"
    ],
    "name:und_x_variant":[
        "Mazra\u2018eh Kh\u0101neh",
        "Mazra\u2018eh-ye Rajab"
    ],
    "wof:name":"Mazra`eh-ye Rajab",
    "wof:placetype":"locality"
},
  "geometry": {"coordinates":[54.21849,31.46467],"type":"Point"}
}