{
  "type": "Feature",
  "properties": {
    "gn:admin1_code":"32",
    "gn:asciiname":"Bikhan",
    "gn:country_code":"IR",
    "gn:dem":1245,
    "gn:feature_class":"P",
    "gn:feature_code":"PPLL",
    "gn:name":"B\u012bkh\u0101n",
    "gn:population":0,
    "gn:timezone":"Asia/Tehran",
    "iso:country":"IR",
    "name:fas_x_preferred":[
        "\u0628\u06cc\u062e\u0627\u0646"
    ],
    "name:fas_x_variant":[
        "B\u012bkh\u0101n",
        "\u0628\u064a\u062e\u0627\u0646 \u0642\u0634\u0644\u0627\u0642\u06cc"
    ],
    "name:und_x_variant":[
        "B\u012bkh\u0101n Qeshl\u0101q\u012b"
    ],
    "wof:name":"Bikhan",
    "wof:placetype":"locality"
},
  "geometry": {"coordinates":[47.95885,38.58538],"type":"Point"}
}