{
  "type": "Feature",
  "properties": {
    "gn:admin1_code":"39.0",
    "gn:asciiname":"Aghlak",
    "gn:country_code":"IR",
    "gn:dem":1322,
    "gn:feature_class":"P",
    "gn:feature_code":"PPL",
    "gn:name":"Aghlak",
    "gn:population":0,
    "gn:timezone":"Asia/Tehran",
    "iso:country":"IR",
    "name:ceb_x_preferred":[
        "\u0100q\u0101 Lak"
    ],
    "name:fas_x_preferred":[
        "\u0100q\u0101 Lak"
    ],
    "name:fas_x_variant":[
        "\u0100gholak",
        "\u0622\u0642\u0627 \u0644\u06a9",
        "\u0627\u063a\u0644\u06a9",
        "\u0622\u063a\u0644\u06a9"
    ],
    "name:swe_x_preferred":[
        "\u0100q\u0101 Lak"
    ],
    "name:und_x_variant":[
        "\u0100qlak",
        "\u0100ghlak",
        "Aghelak",
        "\u0622\u0642\u0627 \u0644\u06a9",
        "Aghlak"
    ],
    "wof:name":"Aghlak",
    "wof:placetype":"locality"
},
  "geometry": {"coordinates":[50.32496,34.73403],"type":"Point"}
}