{
  "type": "Feature",
  "properties": {
    "gn:admin1_code":"41",
    "gn:asciiname":"Faratan",
    "gn:country_code":"IR",
    "gn:dem":1938,
    "gn:feature_class":"P",
    "gn:feature_code":"PPL",
    "gn:name":"Far\u0101t\u0101n",
    "gn:population":0,
    "gn:timezone":"Asia/Tehran",
    "iso:country":"IR",
    "name:fas_x_preferred":[
        "Far\u0101t\u0101n"
    ],
    "name:fas_x_variant":[
        "\u0641\u0631\u0627\u062a\u0627\u0646",
        "Fer\u0101t\u0101n",
        "Far\u0101\u0163\u016bn"
    ],
    "name:und_x_variant":[
        "Fer\u0101t\u0101n",
        "Far\u0101\u0163\u016bn",
        "\u0641\u0631\u0627\u062a\u0627\u0646"
    ],
    "wof:name":"Faratan",
    "wof:placetype":"locality"
},
  "geometry": {"coordinates":[59.37126,32.29323],"type":"Point"}
}