{
  "type": "Feature",
  "properties": {
    "gn:admin1_code":"33",
    "gn:asciiname":"Payam",
    "gn:country_code":"IR",
    "gn:dem":1815,
    "gn:feature_class":"P",
    "gn:feature_code":"PPL",
    "gn:name":"Pay\u0101m",
    "gn:population":0,
    "gn:timezone":"Asia/Tehran",
    "iso:country":"IR",
    "name:aze_x_preferred":[
        "Yam"
    ],
    "name:fas_x_preferred":[
        "\u067e\u064e\u064a\u0627\u0645"
    ],
    "name:fas_x_variant":[
        "\u067e\u06cc\u0627\u0645",
        "\u064a\u0627\u0645",
        "Pay\u0101m",
        "\u06cc\u0627\u0645"
    ],
    "name:msa_x_preferred":[
        "Piyam"
    ],
    "name:und_x_variant":[
        "Y\u0101m",
        "Piy\u0101m",
        "P\u012b\u0101m"
    ],
    "wof:name":"Payam",
    "wof:placetype":"locality"
},
  "geometry": {"coordinates":[45.8129,38.3557],"type":"Point"}
}