{
  "type": "Feature",
  "properties": {
    "gn:admin1_code":"7",
    "gn:asciiname":"Qal`eh Gachi",
    "gn:country_code":"IR",
    "gn:dem":1581,
    "gn:feature_class":"P",
    "gn:feature_code":"PPL",
    "gn:name":"Qal\u2018eh Gach\u012b",
    "gn:population":0,
    "gn:timezone":"Asia/Tehran",
    "iso:country":"IR",
    "name:fas_x_preferred":[
        "\u0642\u0644\u0639\u0647 \u06af\u0686\u06cc"
    ],
    "name:fas_x_variant":[
        "Qal\u2018eh Gach\u012b"
    ],
    "wof:name":"Qal`eh Gachi",
    "wof:placetype":"locality"
},
  "geometry": {"coordinates":[53.02261,29.59039000000001],"type":"Point"}
}