{
  "type": "Feature",
  "properties": {
    "gn:admin1_code":"8",
    "gn:asciiname":"Kil Kalayeh",
    "gn:country_code":"IR",
    "gn:dem":-17,
    "gn:feature_class":"P",
    "gn:feature_code":"PPL",
    "gn:name":"K\u012bl Kal\u0101yeh",
    "gn:population":0,
    "gn:timezone":"Asia/Tehran",
    "iso:country":"IR",
    "name:fas_x_preferred":[
        "G\u012bl Kal\u0101yeh"
    ],
    "name:fas_x_variant":[
        "\u06af\u06cc\u0644 \u06a9\u0644\u0627\u06cc\u0647",
        "\u06a9\u06cc\u0644 \u06a9\u0644\u0627\u06cc\u0647"
    ],
    "name:und_x_variant":[
        "Gel\u012b Kal\u0101yeh",
        "Gol-e Kalak",
        "K\u012bl Kal\u0101yeh"
    ],
    "wof:name":"Kil Kalayeh",
    "wof:placetype":"locality"
},
  "geometry": {"coordinates":[50.37773,37.08562],"type":"Point"}
}