{
  "type": "Feature",
  "properties": {
    "gn:admin1_code":"16",
    "gn:asciiname":"Aghcheh Gonbad",
    "gn:country_code":"IR",
    "gn:dem":1476,
    "gn:feature_class":"P",
    "gn:feature_code":"PPL",
    "gn:name":"\u0100ghcheh Gonbad",
    "gn:population":0,
    "gn:timezone":"Asia/Tehran",
    "iso:country":"IR",
    "name:ara_x_preferred":[
        "\u0623\u063a\u062a\u0634\u0629 \u063a\u0646\u0628\u062f"
    ],
    "name:azb_x_preferred":[
        "\u0622\u0642\u0686\u0647 \u06af\u0646\u0628\u062f"
    ],
    "name:ceb_x_preferred":[
        "\u0100ghcheh Gonbad"
    ],
    "name:fas_x_preferred":[
        "\u0622\u063a\u0686\u0647 \u06af\u0646\u0628\u062f"
    ],
    "name:fas_x_variant":[
        "\u0100ghjeh Kand",
        "\u0100ghcheh Gonbad"
    ],
    "name:und_x_variant":[
        "\u0100ghjeh Gonbad"
    ],
    "wof:name":"Aghcheh Gonbad",
    "wof:placetype":"locality"
},
  "geometry": {"coordinates":[47.83031,36.18698],"type":"Point"}
}