{
  "type": "Feature",
  "properties": {
    "gn:admin1_code":"15",
    "gn:asciiname":"Takht-e Jahangir",
    "gn:cc2":"IR",
    "gn:country_code":"IR",
    "gn:dem":209,
    "gn:feature_class":"P",
    "gn:feature_code":"PPL",
    "gn:name":"Takht-e Jah\u0101ng\u012br",
    "gn:population":0,
    "gn:timezone":"Asia/Tehran",
    "iso:country":"IR",
    "name:fas_x_preferred":[
        "Takht-e Jah\u0101ng\u012br"
    ],
    "name:und_x_variant":[
        "Takht-i-Jek\u0101ngir",
        "Takht-i-Jeh\u0101ng\u012br"
    ],
    "wof:name":"Takht-e Jahangir",
    "wof:placetype":"locality"
},
  "geometry": {"coordinates":[49.28333,31.63333],"type":"Point"}
}