{
  "type": "Feature",
  "properties": {
    "gn:admin1_code":"23",
    "gn:asciiname":"Chenar",
    "gn:country_code":"IR",
    "gn:dem":1609,
    "gn:feature_class":"P",
    "gn:feature_code":"PPL",
    "gn:name":"Chen\u0101r",
    "gn:population":0,
    "gn:timezone":"Asia/Tehran",
    "iso:country":"IR",
    "name:fas_x_preferred":[
        "\u0686\u0646\u0627\u0631"
    ],
    "name:fas_x_variant":[
        "Chen\u0101r",
        "\u0645\u06cc \u0648\u06a9"
    ],
    "name:und_x_variant":[
        "Mey Vak"
    ],
    "wof:name":"Chenar",
    "wof:placetype":"locality"
},
  "geometry": {"coordinates":[48.50407,33.18959],"type":"Point"}
}