{
  "type": "Feature",
  "properties": {
    "gn:admin1_code":"15",
    "gn:asciiname":"Ahmad-e Mavali",
    "gn:country_code":"IR",
    "gn:dem":14,
    "gn:feature_class":"P",
    "gn:feature_code":"PPL",
    "gn:name":"A\u1e29mad-e Mav\u0101l\u012b",
    "gn:population":0,
    "gn:timezone":"Asia/Tehran",
    "iso:country":"IR",
    "name:ceb_x_preferred":[
        "Sayy\u0101r A\u1e29mad\u0101b\u0101d"
    ],
    "name:fas_x_preferred":[
        "\u0633\u06cc\u0627\u0631 \u0627\u062d\u0645\u062f \u0622\u0628\u0627\u062f"
    ],
    "name:fas_x_variant":[
        "Sayy\u0101r-e Mov\u0101l\u012b",
        "Sayy\u0101r A\u1e29mad\u0101b\u0101d",
        "\u0627\u062d\u0645\u062f \u0645\u0648\u0627\u0644\u06cc",
        "\u0633\u06cc\u0627\u0631 \u0627\u062d\u0645\u062f\u0622\u0628\u0627\u062f"
    ],
    "name:swe_x_preferred":[
        "Sayy\u0101r A\u1e29mad\u0101b\u0101d"
    ],
    "name:und_x_variant":[
        "A\u1e29mad-e Mav\u0101l\u012b"
    ],
    "wof:name":"Ahmad-e Mavali",
    "wof:placetype":"locality"
},
  "geometry": {"coordinates":[48.2268,31.3982],"type":"Point"}
}