{
  "type": "Feature",
  "properties": {
    "gn:admin1_code":"10",
    "gn:asciiname":"Chaleh Siah",
    "gn:country_code":"IR",
    "gn:dem":702,
    "gn:feature_class":"P",
    "gn:feature_code":"PPL",
    "gn:name":"Ch\u0101leh S\u012b\u0101h",
    "gn:population":0,
    "gn:timezone":"Asia/Tehran",
    "iso:country":"IR",
    "name:ara_x_preferred":[
        "\u062a\u0634\u0627\u0644\u0629 \u0633\u064a\u0627\u0629"
    ],
    "name:fas_x_preferred":[
        "Ch\u0101leh S\u012b\u0101h"
    ],
    "name:fas_x_variant":[
        "\u0686\u0627\u0644\u0650\u0647 \u0633\u064a\u0627\u0647",
        "\u0686\u0627\u0644\u0647 \u0633\u06cc\u0627\u0647"
    ],
    "name:msa_x_preferred":[
        "Chaleh Siah"
    ],
    "wof:name":"Chaleh Siah",
    "wof:placetype":"locality"
},
  "geometry": {"coordinates":[47.33333,33.16667],"type":"Point"}
}