{
  "type": "Feature",
  "properties": {
    "gn:admin1_code":"38",
    "gn:asciiname":"Kingarin",
    "gn:country_code":"IR",
    "gn:dem":1235,
    "gn:feature_class":"P",
    "gn:feature_code":"PPL",
    "gn:name":"K\u012bngar\u012bn",
    "gn:population":0,
    "gn:timezone":"Asia/Tehran",
    "iso:country":"IR",
    "name:fas_x_preferred":[
        "Kangar\u012bn"
    ],
    "name:fas_x_variant":[
        "\u0643\u0646\u06af\u0631\u064a\u0646",
        "\u0643\u064a\u0646\u06af\u0631\u064a\u0646"
    ],
    "name:und_x_variant":[
        "\u0643\u0646\u06af\u0631\u064a\u0646",
        "K\u012bngar\u012bn"
    ],
    "wof:name":"Kingarin",
    "wof:placetype":"locality"
},
  "geometry": {"coordinates":[50.01005,36.57494000000001],"type":"Point"}
}