{
  "type": "Feature",
  "properties": {
    "gn:admin1_code":"11",
    "gn:asciiname":"Merd-e Now",
    "gn:country_code":"IR",
    "gn:dem":426,
    "gn:feature_class":"P",
    "gn:feature_code":"PPL",
    "gn:name":"Merd-e Now",
    "gn:population":0,
    "gn:timezone":"Asia/Tehran",
    "iso:country":"IR",
    "name:fas_x_preferred":[
        "\u0645\u064e\u0631\u062f\u0648\u0646\u064f\u0648"
    ],
    "name:fas_x_variant":[
        "\u0645\u0631\u062f \u0646\u0648"
    ],
    "name:und_x_variant":[
        "Merd\u016bn\u016b",
        "Mard\u016bnow",
        "Merd-e Now",
        "\u0645\u0631\u062f \u0646\u0648"
    ],
    "wof:name":"Merd-e Now",
    "wof:placetype":"locality"
},
  "geometry": {"coordinates":[54.46635,27.33013],"type":"Point"}
}