{
  "type": "Feature",
  "properties": {
    "gn:admin1_code":"42.0",
    "gn:asciiname":"Gol Gonbad",
    "gn:country_code":"IR",
    "gn:dem":1356,
    "gn:feature_class":"P",
    "gn:feature_code":"PPL",
    "gn:name":"Gol Gonbad",
    "gn:population":0,
    "gn:timezone":"Asia/Tehran",
    "iso:country":"IR",
    "name:ceb_x_preferred":[
        "Gol Gonbad"
    ],
    "name:fas_x_preferred":[
        "\u06af\u0644 \u06af\u0646\u0628\u062f"
    ],
    "name:fas_x_variant":[
        "Komb\u012b"
    ],
    "name:swe_x_preferred":[
        "Gol Gonbad"
    ],
    "name:und_x_variant":[
        "Komb\u012b",
        "Gol Gonbad",
        "\u06af\u0644 \u06af\u0646\u0628\u062f"
    ],
    "wof:name":"Gol Gonbad",
    "wof:placetype":"locality"
},
  "geometry": {"coordinates":[58.16648000000001,36.63925],"type":"Point"}
}