{
  "type": "Feature",
  "properties": {
    "gn:admin1_code":"26.0",
    "gn:asciiname":"Bagh Gol",
    "gn:country_code":"IR",
    "gn:dem":1989,
    "gn:feature_class":"P",
    "gn:feature_code":"PPL",
    "gn:name":"B\u0101gh Gol",
    "gn:population":0,
    "gn:timezone":"Asia/Tehran",
    "iso:country":"IR",
    "name:fas_x_preferred":[
        "\u0628\u0627\u063a \u06af\u0644"
    ],
    "name:fas_x_variant":[
        "B\u0101gh Gol"
    ],
    "name:und_x_variant":[
        "B\u0101gh-e Gol"
    ],
    "wof:name":"Bagh Gol",
    "wof:placetype":"locality"
},
  "geometry": {"coordinates":[51.49931,35.90782],"type":"Point"}
}