{
  "type": "Feature",
  "properties": {
    "gn:admin1_code":"11.0",
    "gn:asciiname":"Abgerd",
    "gn:country_code":"IR",
    "gn:dem":184,
    "gn:feature_class":"P",
    "gn:feature_code":"PPL",
    "gn:name":"\u0100bgerd",
    "gn:population":0,
    "gn:timezone":"Asia/Tehran",
    "iso:country":"IR",
    "name:fas_x_preferred":[
        "\u0622\u0628 \u06af\u0631\u062f"
    ],
    "name:fas_x_variant":[
        "\u0100b Gerd",
        "\u0622\u0628\u06af\u0631\u062f"
    ],
    "name:und_x_variant":[
        "\u0100bgerd"
    ],
    "wof:name":"Abgerd",
    "wof:placetype":"locality"
},
  "geometry": {"coordinates":[53.306,27.1373],"type":"Point"}
}