{
  "type": "Feature",
  "properties": {
    "gn:admin1_code":"35",
    "gn:asciiname":"Pa'in Karu Kola",
    "gn:country_code":"IR",
    "gn:dem":8,
    "gn:feature_class":"P",
    "gn:feature_code":"PPL",
    "gn:name":"P\u0101\u2019\u012bn Kar\u016b Kol\u0101",
    "gn:population":0,
    "gn:timezone":"Asia/Tehran",
    "iso:country":"IR",
    "name:fas_x_preferred":[
        "\u067e\u0627\u0626\u064a\u0646 \u0643\u0631\u0648 \u0643\u0644\u0627"
    ],
    "name:fas_x_variant":[
        "P\u0101\u2019\u012bn Kar\u016b Kol\u0101"
    ],
    "name:und_x_variant":[
        "\u067e\u0627\u0626\u064a\u0646 \u0643\u064e\u0631\u0648 \u0643\u064f\u0644\u0627"
    ],
    "wof:name":"Pa'in Karu Kola",
    "wof:placetype":"locality"
},
  "geometry": {"coordinates":[52.54904000000001,36.50242],"type":"Point"}
}