{
  "type": "Feature",
  "properties": {
    "gn:admin1_code":"41",
    "gn:asciiname":"Hoseynabad",
    "gn:country_code":"IR",
    "gn:dem":1765,
    "gn:feature_class":"P",
    "gn:feature_code":"PPL",
    "gn:name":"\u1e28oseyn\u0101b\u0101d",
    "gn:population":0,
    "gn:timezone":"Asia/Tehran",
    "iso:country":"IR",
    "name:fas_x_preferred":[
        "\u1e28oseyn\u0101b\u0101d"
    ],
    "name:fas_x_variant":[
        "\u062d\u0633\u064a\u0646 \u0622\u0628\u0627\u062f",
        "Husain\u0101b\u0101d",
        "\u062d\u0633\u064a\u0646 \u0622\u0628\u0627\u062f \u0627\u0628\u0648 \u0637\u0627\u0644\u0628"
    ],
    "name:und_x_variant":[
        "Hosein Abad Gheis Abad",
        "Husain\u0101b\u0101d",
        "\u062d\u0633\u064a\u0646 \u0622\u0628\u0627\u062f",
        "\u1e28oseyn\u0101b\u0101d-e Ab\u016b \u0162\u0101leb"
    ],
    "wof:name":"Hoseynabad",
    "wof:placetype":"locality"
},
  "geometry": {"coordinates":[59.28211,32.37167],"type":"Point"}
}