{
  "type": "Feature",
  "properties": {
    "gn:admin1_code":"10",
    "gn:asciiname":"Darreh Chini",
    "gn:country_code":"IR",
    "gn:dem":952,
    "gn:feature_class":"P",
    "gn:feature_code":"PPL",
    "gn:name":"Darreh Ch\u012bn\u012b",
    "gn:population":0,
    "gn:timezone":"Asia/Tehran",
    "iso:country":"IR",
    "name:ara_x_preferred":[
        "\u062f\u0631\u0629 \u062a\u0634\u0628\u064a"
    ],
    "name:fas_x_preferred":[
        "\u062f\u0631\u0651\u0647 \u0686\u067e\u06cc"
    ],
    "name:fas_x_variant":[
        "Darreh Chap\u012b",
        "\u062f\u0631\u0647 \u0686\u06cc\u0646\u06cc",
        "\u062f\u0631\u0647 \u0686\u067e\u06cc"
    ],
    "name:msa_x_preferred":[
        "Darreh Chapi"
    ],
    "name:und_x_variant":[
        "Darreh Ch\u012bn\u012b"
    ],
    "wof:name":"Darreh Chini",
    "wof:placetype":"locality"
},
  "geometry": {"coordinates":[46.878,33.6288],"type":"Point"}
}