{
  "type": "Feature",
  "properties": {
    "gn:admin1_code":"8",
    "gn:asciiname":"Darreh Khal",
    "gn:country_code":"IR",
    "gn:dem":1487,
    "gn:feature_class":"P",
    "gn:feature_code":"PPL",
    "gn:name":"Darreh Kh\u0101l",
    "gn:population":0,
    "gn:timezone":"Asia/Tehran",
    "iso:country":"IR",
    "name:fas_x_preferred":[
        "\u062f\u0631\u0647 \u062e\u0627\u0644"
    ],
    "name:fas_x_variant":[
        "Darreh Kh\u0101l"
    ],
    "name:und_x_variant":[
        "Darreh Kh\u0101l"
    ],
    "wof:name":"Darreh Khal",
    "wof:placetype":"locality"
},
  "geometry": {"coordinates":[48.87765,37.48398],"type":"Point"}
}