{
  "type": "Feature",
  "properties": {
    "gn:admin1_code":"28",
    "gn:asciiname":"Seftejan",
    "gn:country_code":"IR",
    "gn:dem":2234,
    "gn:feature_class":"P",
    "gn:feature_code":"PPL",
    "gn:name":"Seftej\u0101n",
    "gn:population":0,
    "gn:timezone":"Asia/Tehran",
    "iso:country":"IR",
    "name:ara_x_preferred":[
        "\u0633\u0641\u062a\u062c\u0627\u0646"
    ],
    "name:fas_x_preferred":[
        "Seftej\u0101n"
    ],
    "name:fas_x_variant":[
        "\u0633\u0641\u062a\u062c\u0627\u0646"
    ],
    "name:und_x_variant":[
        "S\u012bfatg\u016bn",
        "\u015eefatg\u016bn",
        "Seft J\u0101n"
    ],
    "wof:name":"Seftejan",
    "wof:placetype":"locality"
},
  "geometry": {"coordinates":[50.3566,32.9396],"type":"Point"}
}