{
  "type": "Feature",
  "properties": {
    "gn:admin1_code":"8.0",
    "gn:asciiname":"Mahalleh-ye Bisheh Sara",
    "gn:country_code":"IR",
    "gn:dem":66,
    "gn:feature_class":"P",
    "gn:feature_code":"PPL",
    "gn:name":"Ma\u1e29alleh-ye B\u012bsheh Sar\u0101",
    "gn:population":0,
    "gn:timezone":"Asia/Tehran",
    "iso:country":"IR",
    "name:fas_x_preferred":[
        "\u0645\u062d\u0644\u0647 \u0628\u06cc\u0634\u0647 \u0633\u0631\u0627"
    ],
    "name:und_x_variant":[
        "Ma\u1e29alleh-ye B\u012bsheh Sar\u0101"
    ],
    "wof:name":"Mahalleh-ye Bisheh Sara",
    "wof:placetype":"locality"
},
  "geometry": {"coordinates":[49.12389,37.4978],"type":"Point"}
}