{
  "type": "Feature",
  "properties": {
    "gn:admin1_code":"34",
    "gn:asciiname":"Morvarid Darreh",
    "gn:country_code":"IR",
    "gn:dem":2055,
    "gn:feature_class":"P",
    "gn:feature_code":"PPL",
    "gn:name":"Morv\u0101r\u012bd Darreh",
    "gn:population":0,
    "gn:timezone":"Asia/Tehran",
    "iso:country":"IR",
    "name:ceb_x_preferred":[
        "Morv\u0101r\u012bd Darreh"
    ],
    "name:fas_x_preferred":[
        "\u0645\u0631\u0648\u0627\u0631\u06cc\u062f \u062f\u0631\u0647"
    ],
    "name:fas_x_variant":[
        "Morv\u0101r\u012bd Darreh"
    ],
    "name:swe_x_preferred":[
        "Morv\u0101r\u012bd Darreh"
    ],
    "name:ukr_x_preferred":[
        "\u041c\u043e\u0440\u0432\u0430\u0440\u0456\u0434-\u0414\u0430\u0440\u0440\u0435"
    ],
    "name:und_x_variant":[
        "Morv\u0101r\u012bdar",
        "Morv\u0101r\u012bd"
    ],
    "wof:name":"Morvarid Darreh",
    "wof:placetype":"locality"
},
  "geometry": {"coordinates":[49.25017,33.97992],"type":"Point"}
}