{
  "type": "Feature",
  "properties": {
    "gn:admin1_code":"9.0",
    "gn:asciiname":"Pasragad Branch",
    "gn:country_code":"IR",
    "gn:dem":2010,
    "gn:elevation":"1000.0",
    "gn:feature_class":"P",
    "gn:feature_code":"PPL",
    "gn:name":"Pasragad Branch",
    "gn:population":787878,
    "gn:timezone":"Asia/Tehran",
    "iso:country":"IR",
    "wof:name":"Pasragad Branch",
    "wof:placetype":"locality",
    "wof:population":787878
},
  "geometry": {"coordinates":[48.47168,34.77772],"type":"Point"}
}