{
  "type": "Feature",
  "properties": {
    "gn:admin1_code":"1.0",
    "gn:asciiname":"Vadi Karan",
    "gn:country_code":"IR",
    "gn:dem":2269,
    "gn:feature_class":"P",
    "gn:feature_code":"PPL",
    "gn:name":"V\u0101d\u012b Kar\u0101n",
    "gn:population":0,
    "gn:timezone":"Asia/Tehran",
    "iso:country":"IR",
    "name:fas_x_preferred":[
        "\u0648\u0627\u062f\u06cc \u06a9\u0631\u0627\u0646"
    ],
    "name:fas_x_variant":[
        "V\u0101d\u012b Kar\u0101n"
    ],
    "wof:name":"Vadi Karan",
    "wof:placetype":"locality"
},
  "geometry": {"coordinates":[44.5652,37.9368],"type":"Point"}
}