{
  "type": "Feature",
  "properties": {
    "gn:admin1_code":"42.0",
    "gn:asciiname":"Sahel Borj",
    "gn:country_code":"IR",
    "gn:dem":1309,
    "gn:feature_class":"P",
    "gn:feature_code":"PPL",
    "gn:name":"S\u0101\u1e29el Borj",
    "gn:population":0,
    "gn:timezone":"Asia/Tehran",
    "iso:country":"IR",
    "name:fas_x_preferred":[
        "\u0633\u0627\u062d\u0644 \u0628\u0631\u062c"
    ],
    "name:fas_x_variant":[
        "S\u0101\u1e29el Borj"
    ],
    "name:urd_x_preferred":[
        "\u0633\u06c1\u06cc\u0644 \u0628\u0648\u0631\u062c"
    ],
    "wof:name":"Sahel Borj",
    "wof:placetype":"locality"
},
  "geometry": {"coordinates":[59.00658000000001,36.13033],"type":"Point"}
}