{
  "type": "Feature",
  "properties": {
    "gn:admin1_code":"29",
    "gn:asciiname":"Tolombeh-ye Razavi",
    "gn:country_code":"IR",
    "gn:dem":1723,
    "gn:feature_class":"P",
    "gn:feature_code":"PPL",
    "gn:name":"Tolombeh-ye Ra\u1e95av\u012b",
    "gn:population":0,
    "gn:timezone":"Asia/Tehran",
    "iso:country":"IR",
    "name:fas_x_preferred":[
        "Tolombeh-ye Ra\u1e95av\u012b"
    ],
    "wof:name":"Tolombeh-ye Razavi",
    "wof:placetype":"locality"
},
  "geometry": {"coordinates":[55.63333000000001,29.46667],"type":"Point"}
}