{
  "type": "Feature",
  "properties": {
    "gn:admin1_code":"29.0",
    "gn:asciiname":"Chah-e Asadollah",
    "gn:country_code":"IR",
    "gn:dem":400,
    "gn:feature_class":"P",
    "gn:feature_code":"PPL",
    "gn:name":"Ch\u0101h-e Asadoll\u0101h",
    "gn:population":0,
    "gn:timezone":"Asia/Tehran",
    "iso:country":"IR",
    "name:fas_x_preferred":[
        "\u0686\u0627\u0647 \u0627\u0633\u062f \u0627\u0644\u0644\u0647"
    ],
    "name:und_x_variant":[
        "Ch\u0101h-e Asadoll\u0101h"
    ],
    "wof:name":"Chah-e Asadollah",
    "wof:placetype":"locality"
},
  "geometry": {"coordinates":[58.58828000000001,27.19129],"type":"Point"}
}