{
  "type": "Feature",
  "properties": {
    "gn:admin1_code":"35.0",
    "gn:asciiname":"Khowsh Vash",
    "gn:country_code":"IR",
    "gn:dem":2417,
    "gn:feature_class":"P",
    "gn:feature_code":"PPL",
    "gn:name":"Khowsh V\u0101sh",
    "gn:population":0,
    "gn:timezone":"Asia/Tehran",
    "iso:country":"IR",
    "name:fas_x_preferred":[
        "\u062e\u0648\u0634 \u0648\u0627\u0634"
    ],
    "name:fas_x_variant":[
        "Khvosh V\u0101sh"
    ],
    "name:und_x_variant":[
        "Khowsh V\u0101sh"
    ],
    "wof:name":"Khowsh Vash",
    "wof:placetype":"locality"
},
  "geometry": {"coordinates":[52.22673,36.23971],"type":"Point"}
}