{
  "type": "Feature",
  "properties": {
    "gn:admin1_code":"40",
    "gn:asciiname":"Ja`farabad",
    "gn:country_code":"IR",
    "gn:dem":1330,
    "gn:feature_class":"P",
    "gn:feature_code":"PPLF",
    "gn:name":"Ja\u2018far\u0101b\u0101d",
    "gn:population":0,
    "gn:timezone":"Asia/Tehran",
    "iso:country":"IR",
    "name:fas_x_preferred":[
        "\u062c\u064e\u0639\u0641\u064e\u0631 \u0622\u0628\u0627\u062f"
    ],
    "name:fas_x_variant":[
        "\u062c\u064e\u0621\u0641\u064e\u0631 \u0627\u064e\u0628\u064e\u062f \u0628\u064e\u0647\u064e\u0628\u064e\u062f",
        "Ja\u2018far\u0101b\u0101d",
        "\u062c\u0639\u0641\u0631 \u0622\u0628\u0627\u062f",
        "Ja\u2019far Abad Bahabad"
    ],
    "name:und_x_variant":[
        "Ja\u2019far Abad Bahabad"
    ],
    "wof:name":"Ja`farabad",
    "wof:placetype":"locality"
},
  "geometry": {"coordinates":[55.95458000000001,32.04525],"type":"Point"}
}