{
  "type": "Feature",
  "properties": {
    "gn:admin1_code":"1.0",
    "gn:asciiname":"Bard-e Kur",
    "gn:country_code":"IR",
    "gn:dem":1456,
    "gn:feature_class":"P",
    "gn:feature_code":"PPL",
    "gn:name":"Bard-e K\u016br",
    "gn:population":0,
    "gn:timezone":"Asia/Tehran",
    "iso:country":"IR",
    "name:fas_x_preferred":[
        "\u0628\u0631\u062f \u06a9\u0648\u0631"
    ],
    "name:fas_x_variant":[
        "Bard-e K\u016br"
    ],
    "wof:name":"Bard-e Kur",
    "wof:placetype":"locality"
},
  "geometry": {"coordinates":[45.3389,36.5068],"type":"Point"}
}