{
  "type": "Feature",
  "properties": {
    "gn:admin1_code":"3",
    "gn:asciiname":"Moosa Abad",
    "gn:country_code":"IR",
    "gn:dem":2032,
    "gn:feature_class":"P",
    "gn:feature_code":"PPL",
    "gn:name":"Moosa Abad",
    "gn:population":0,
    "gn:timezone":"Asia/Tehran",
    "iso:country":"IR",
    "name:fas_x_preferred":[
        "\u0645\u0648\u0633\u06cc \u0622\u0628\u0627\u062f"
    ],
    "name:fas_x_variant":[
        "M\u016bs\u00e1\u0101b\u0101d",
        "\u0645\u064f\u0651\u0633\u064e \u0627\u064e\u0628\u064e\u062f",
        "\u0645\u0648\u0633\u064e\u0649",
        "\u0645\u0648\u0633\u0649 \u0622\u0628\u0627\u062f"
    ],
    "name:und_x_variant":[
        "M\u016bs\u00e1",
        "M\u016bs\u012b\u0101b\u0101d",
        "\u0645\u0648\u0633\u0649 \u0622\u0628\u0627\u062f"
    ],
    "wof:name":"Moosa Abad",
    "wof:placetype":"locality"
},
  "geometry": {"coordinates":[50.90268,32.09417],"type":"Point"}
}