{
  "type": "Feature",
  "properties": {
    "gn:admin1_code":"41.0",
    "gn:asciiname":"Kalat-e Mir",
    "gn:country_code":"IR",
    "gn:dem":1806,
    "gn:feature_class":"P",
    "gn:feature_code":"PPL",
    "gn:name":"Kal\u0101t-e M\u012br",
    "gn:population":0,
    "gn:timezone":"Asia/Tehran",
    "iso:country":"IR",
    "name:fas_x_preferred":[
        "Kal\u0101t-e M\u012br"
    ],
    "name:fas_x_variant":[
        "\u06a9\u0644\u0627\u062a \u0645\u064a\u0631",
        "\u06a9\u0644\u0627\u062a\u0647 \u0645\u064a\u0631"
    ],
    "name:und_x_variant":[
        "\u06a9\u0644\u0627\u062a \u0645\u064a\u0631",
        "Kal\u0101teh-ye M\u012br"
    ],
    "wof:name":"Kalat-e Mir",
    "wof:placetype":"locality"
},
  "geometry": {"coordinates":[59.3626,32.77916],"type":"Point"}
}