{
  "type": "Feature",
  "properties": {
    "gn:admin1_code":"41",
    "gn:asciiname":"Mazra`eh-ye Sinidar",
    "gn:country_code":"IR",
    "gn:dem":1582,
    "gn:feature_class":"P",
    "gn:feature_code":"PPL",
    "gn:name":"Mazra\u2018eh-ye S\u012bn\u012bdar",
    "gn:population":0,
    "gn:timezone":"Asia/Tehran",
    "iso:country":"IR",
    "name:fas_x_preferred":[
        "\u0633\u06cc\u0646\u06cc\u062f\u0631"
    ],
    "name:fas_x_variant":[
        "Sin\u012bdar",
        "S\u012bn\u012bdar",
        "\u0645\u0632\u0631\u0639\u0647 \u0633\u06cc\u0646\u06cc\u062f\u0631"
    ],
    "name:und_x_variant":[
        "S\u012bndar",
        "S\u012bnandar",
        "Mazra\u2018eh-ye S\u012bn\u012bdar"
    ],
    "wof:name":"Mazra`eh-ye Sinidar",
    "wof:placetype":"locality"
},
  "geometry": {"coordinates":[59.49112,33.63180999999999],"type":"Point"}
}