{
  "type": "Feature",
  "properties": {
    "gn:admin1_code":"13",
    "gn:asciiname":"Marjan Gomar",
    "gn:country_code":"IR",
    "gn:dem":659,
    "gn:feature_class":"P",
    "gn:feature_code":"PPL",
    "gn:name":"Marj\u0101n Gom\u0101r",
    "gn:population":0,
    "gn:timezone":"Asia/Tehran",
    "iso:country":"IR",
    "name:fas_x_preferred":[
        "\u0645\u0631\u062c\u0627\u0646 \u06af\u0645\u0627\u0631"
    ],
    "name:fas_x_variant":[
        "Gom\u0101r",
        "Marj\u0101n Gom\u0101r"
    ],
    "name:und_x_variant":[
        "Marj\u0101n-e Gom\u0101r"
    ],
    "wof:name":"Marjan Gomar",
    "wof:placetype":"locality"
},
  "geometry": {"coordinates":[45.8297,34.2336],"type":"Point"}
}