{
  "type": "Feature",
  "properties": {
    "gn:admin1_code":"29.0",
    "gn:asciiname":"Molla Hajji",
    "gn:country_code":"IR",
    "gn:dem":1705,
    "gn:feature_class":"P",
    "gn:feature_code":"PPL",
    "gn:name":"Moll\u0101 \u1e28\u0101jj\u012b",
    "gn:population":0,
    "gn:timezone":"Asia/Tehran",
    "iso:country":"IR",
    "name:fas_x_preferred":[
        "Moll\u0101 \u1e28\u0101jj\u012b"
    ],
    "name:fas_x_variant":[
        "\u0645\u0644\u0627 \u062d\u0627\u062c\u06cc"
    ],
    "wof:name":"Molla Hajji",
    "wof:placetype":"locality"
},
  "geometry": {"coordinates":[55.47308,29.53867],"type":"Point"}
}