{
  "type": "Feature",
  "properties": {
    "gn:admin1_code":"15.0",
    "gn:asciiname":"Zobeydi-ye Farahan",
    "gn:country_code":"IR",
    "gn:dem":115,
    "gn:feature_class":"P",
    "gn:feature_code":"PPL",
    "gn:name":"Zobeyd\u012b-ye Farah\u0101n",
    "gn:population":0,
    "gn:timezone":"Asia/Tehran",
    "iso:country":"IR",
    "name:fas_x_preferred":[
        "Zobeyd\u012b-ye Far\u0101h\u0101n\u012b"
    ],
    "name:fas_x_variant":[
        "\u0632\u0628\u06cc\u062f\u06cc \u0641\u0631\u0627\u0647\u0627\u0646\u06cc",
        "\u0632\u0628\u06cc\u062f\u06cc \u0641\u0631\u0647\u0627\u0646",
        "\u0628\u0646\u0647 \u0641\u0631\u0647\u0627\u0646"
    ],
    "name:und_x_variant":[
        "\u0632\u0628\u06cc\u062f\u06cc \u0641\u0631\u0627\u0647\u0627\u0646\u06cc",
        "Zobeyd\u012b-ye Farah\u0101n",
        "Boneh-ye Farah\u0101n"
    ],
    "wof:name":"Zobeydi-ye Farahan",
    "wof:placetype":"locality"
},
  "geometry": {"coordinates":[49.60037,31.1572],"type":"Point"}
}