{
  "type": "Feature",
  "properties": {
    "gn:admin1_code":"13",
    "gn:asciiname":"Maleh Amirkhan",
    "gn:country_code":"IR",
    "gn:dem":1561,
    "gn:feature_class":"P",
    "gn:feature_code":"PPL",
    "gn:name":"Maleh Am\u012brkh\u0101n",
    "gn:population":0,
    "gn:timezone":"Asia/Tehran",
    "iso:country":"IR",
    "name:fas_x_preferred":[
        "Maleh Am\u012brkh\u0101n"
    ],
    "wof:name":"Maleh Amirkhan",
    "wof:placetype":"locality"
},
  "geometry": {"coordinates":[46.43583,34.54611],"type":"Point"}
}