{
  "type": "Feature",
  "properties": {
    "gn:admin1_code":"5",
    "gn:asciiname":"Gowd-e Belkhi",
    "gn:country_code":"IR",
    "gn:dem":1684,
    "gn:feature_class":"P",
    "gn:feature_code":"PPL",
    "gn:name":"Gowd-e Belkh\u012b",
    "gn:population":0,
    "gn:timezone":"Asia/Tehran",
    "iso:country":"IR",
    "name:ara_x_preferred":[
        "\u063a\u0648\u062f \u0628\u0644\u0647\u064a"
    ],
    "name:fas_x_preferred":[
        "Gowd-e Belh\u012b"
    ],
    "name:fas_x_variant":[
        "Gowd-e D\u016bl",
        "\u06af\u0648\u062f \u0628\u0644\u0647\u06cc",
        "\u06af\u0648\u062f \u0628\u0644\u062e\u06cc",
        "\u06af\u0648\u062f\u0628\u0644\u0647\u06cc"
    ],
    "name:und_x_variant":[
        "\u06af\u0648\u062f \u0628\u0644\u0647\u06cc",
        "Gowd-e Belkh\u012b"
    ],
    "wof:name":"Gowd-e Belkhi",
    "wof:placetype":"locality"
},
  "geometry": {"coordinates":[51.49444,30.46229000000001],"type":"Point"}
}