{
  "type": "Feature",
  "properties": {
    "gn:admin1_code":"13",
    "gn:asciiname":"Cheshmeh Qal`eh",
    "gn:country_code":"IR",
    "gn:dem":1711,
    "gn:feature_class":"P",
    "gn:feature_code":"PPL",
    "gn:name":"Cheshmeh Qal\u2018eh",
    "gn:population":0,
    "gn:timezone":"Asia/Tehran",
    "iso:country":"IR",
    "name:fas_x_preferred":[
        "\u0686\u0634\u0645\u0647 \u0642\u0644\u0639\u0647"
    ],
    "name:fas_x_variant":[
        "Cheshmeh Qal\u2018eh"
    ],
    "wof:name":"Cheshmeh Qal`eh",
    "wof:placetype":"locality"
},
  "geometry": {"coordinates":[47.458,34.7983],"type":"Point"}
}