{
  "type": "Feature",
  "properties": {
    "gn:admin1_code":"11",
    "gn:asciiname":"Kar Gazi",
    "gn:country_code":"IR",
    "gn:dem":500,
    "gn:feature_class":"P",
    "gn:feature_code":"PPL",
    "gn:name":"K\u0101r Gaz\u012b",
    "gn:population":0,
    "gn:timezone":"Asia/Tehran",
    "iso:country":"IR",
    "name:ceb_x_preferred":[
        "K\u0101r Gaz\u012b"
    ],
    "name:fas_x_preferred":[
        "\u0643\u0631\u06af\u0632\u06cc"
    ],
    "name:fas_x_variant":[
        "\u06a9\u0627\u0631 \u06af\u0632\u06cc",
        "Korgaz\u012b",
        "K\u0101r Gaz\u012b",
        "\u06a9\u0631\u06af\u0632\u06cc"
    ],
    "name:msa_x_preferred":[
        "Kar Gazi"
    ],
    "name:swe_x_preferred":[
        "K\u0101r Gaz\u012b"
    ],
    "wof:name":"Kar Gazi",
    "wof:placetype":"locality"
},
  "geometry": {"coordinates":[57.1276,27.7831],"type":"Point"}
}