{
  "type": "Feature",
  "properties": {
    "gn:admin1_code":"15",
    "gn:asciiname":"Zavyeh-ye Hamudi",
    "gn:country_code":"IR",
    "gn:dem":95,
    "gn:feature_class":"P",
    "gn:feature_code":"PPL",
    "gn:name":"Z\u0101vyeh-ye \u1e28am\u016bd\u012b",
    "gn:population":0,
    "gn:timezone":"Asia/Tehran",
    "iso:country":"IR",
    "name:ceb_x_preferred":[
        "Z\u0101v\u012byeh \u1e28am\u016bd\u012b"
    ],
    "name:fas_x_preferred":[
        "\u0632\u0627\u0648\u06cc\u0647 \u062d\u0645\u0648\u062f\u06cc"
    ],
    "name:fas_x_variant":[
        "Z\u0101v\u012byeh \u1e28am\u016bd\u012b",
        "\u062c\u0648\u062f\u06cc"
    ],
    "name:swe_x_preferred":[
        "Z\u0101v\u012byeh \u1e28am\u016bd\u012b"
    ],
    "name:und_x_variant":[
        "Ham\u016bd\u012b",
        "Zav\u012byeh Hamood\u012b",
        "Zav\u012byeh",
        "Z\u0101veyeh-ye \u1e28am\u016bd\u012b",
        "Z\u0101vyeh-ye \u1e28am\u016bd\u012b",
        "J\u016bd\u012b"
    ],
    "wof:name":"Zavyeh-ye Hamudi",
    "wof:placetype":"locality"
},
  "geometry": {"coordinates":[48.32318,32.29555],"type":"Point"}
}