{
  "type": "Feature",
  "properties": {
    "gn:admin1_code":"4.0",
    "gn:asciiname":"Lashgaran",
    "gn:country_code":"IR",
    "gn:dem":1386,
    "gn:feature_class":"P",
    "gn:feature_code":"PPL",
    "gn:name":"Lashgar\u0101n",
    "gn:population":0,
    "gn:timezone":"Asia/Tehran",
    "iso:country":"IR",
    "name:fas_x_preferred":[
        "\u0644\u0634\u06af\u0631\u0627\u0646"
    ],
    "name:und_x_variant":[
        "Lashgar\u0101n"
    ],
    "wof:name":"Lashgaran",
    "wof:placetype":"locality"
},
  "geometry": {"coordinates":[61.92214,28.011],"type":"Point"}
}