{
  "type": "Feature",
  "properties": {
    "gn:admin1_code":"16.0",
    "gn:asciiname":"Qomchian",
    "gn:country_code":"IR",
    "gn:dem":1887,
    "gn:feature_class":"P",
    "gn:feature_code":"PPL",
    "gn:name":"Qomch\u012b\u0101n",
    "gn:population":0,
    "gn:timezone":"Asia/Tehran",
    "iso:country":"IR",
    "name:fas_x_preferred":[
        "\u0642\u064f\u0645\u0686\u064a\u0627\u0646"
    ],
    "name:fas_x_variant":[
        "\u0642\u0645\u0686\u06cc\u0627\u0646",
        "Qomch\u012b\u0101n"
    ],
    "wof:name":"Qomchian",
    "wof:placetype":"locality"
},
  "geometry": {"coordinates":[46.4322,35.7362],"type":"Point"}
}