{
  "type": "Feature",
  "properties": {
    "gn:admin1_code":"28.0",
    "gn:asciiname":"Mahalleh-ye Aghcheh Bodi",
    "gn:country_code":"IR",
    "gn:dem":1614,
    "gn:feature_class":"P",
    "gn:feature_code":"PPL",
    "gn:name":"Ma\u1e29alleh-ye \u0100ghcheh Bod\u012b",
    "gn:population":0,
    "gn:timezone":"Asia/Tehran",
    "iso:country":"IR",
    "name:fas_x_preferred":[
        "\u0100ghcheh Bod\u012b"
    ],
    "name:fas_x_variant":[
        "\u0622\u063a\u0686\u0647 \u0628\u062f\u06cc",
        "\u0645\u062d\u0644\u0647 \u0622\u063a\u0686\u0647 \u0628\u062f\u06cc"
    ],
    "name:und_x_variant":[
        "\u0100ghcheh Bo",
        "\u0622\u063a\u0686\u0647 \u0628\u062f\u06cc",
        "Ma\u1e29alleh-ye \u0100ghcheh Bod\u012b"
    ],
    "wof:name":"Mahalleh-ye Aghcheh Bodi",
    "wof:placetype":"locality"
},
  "geometry": {"coordinates":[51.53011,32.53682],"type":"Point"}
}