{
  "type": "Feature",
  "properties": {
    "gn:admin1_code":"7",
    "gn:asciiname":"Do Kuhak",
    "gn:country_code":"IR",
    "gn:dem":1787,
    "gn:feature_class":"P",
    "gn:feature_code":"PPL",
    "gn:name":"Do K\u016bhak",
    "gn:population":0,
    "gn:timezone":"Asia/Tehran",
    "iso:country":"IR",
    "name:fas_x_preferred":[
        "\u062f\u0648 \u06a9\u0648\u0647\u06a9"
    ],
    "name:fas_x_variant":[
        "Do K\u016bhak",
        "\u062f\u0648\u06a9\u0648\u0647\u06a9"
    ],
    "name:msa_x_preferred":[
        "Do Kuhak"
    ],
    "name:und_x_variant":[
        "D\u016bk\u016bhak",
        "Dow K\u016bhak",
        "D\u016bdehak"
    ],
    "wof:name":"Do Kuhak",
    "wof:placetype":"locality"
},
  "geometry": {"coordinates":[52.415,29.7922],"type":"Point"}
}