{
  "type": "Feature",
  "properties": {
    "gn:admin1_code":"7.0",
    "gn:asciiname":"Tarbor-e Lay Bisheh",
    "gn:country_code":"IR",
    "gn:dem":1610,
    "gn:feature_class":"P",
    "gn:feature_code":"PPL",
    "gn:name":"Tarbor-e L\u0101y B\u012bsheh",
    "gn:population":0,
    "gn:timezone":"Asia/Tehran",
    "iso:country":"IR",
    "name:fas_x_preferred":[
        "\u062a\u0631\u0628\u0631 \u0644\u0627\u06cc \u0628\u06cc\u0634\u0647"
    ],
    "name:fas_x_variant":[
        "Tarbor-e P\u0101\u2019\u012bn",
        "Tarbor-e L\u0101y B\u012bsheh"
    ],
    "name:msa_x_preferred":[
        "Tarbor-e Lay Bisheh"
    ],
    "wof:name":"Tarbor-e Lay Bisheh",
    "wof:placetype":"locality"
},
  "geometry": {"coordinates":[52.8996,29.6095],"type":"Point"}
}