{
  "type": "Feature",
  "properties": {
    "gn:admin1_code":"42",
    "gn:asciiname":"Bozmargi",
    "gn:country_code":"IR",
    "gn:dem":1060,
    "gn:feature_class":"P",
    "gn:feature_code":"PPL",
    "gn:name":"Bozmarg\u012b",
    "gn:population":0,
    "gn:timezone":"Asia/Tehran",
    "iso:country":"IR",
    "name:fas_x_preferred":[
        "\u0628\u0632\u0645\u0631\u06af\u06cc"
    ],
    "name:fas_x_variant":[
        "Bozmarg\u0101n",
        "Bozmarg\u012b",
        "\u0628\u0627\u0632\u0645\u0631\u06af\u0627\u0646"
    ],
    "wof:name":"Bozmargi",
    "wof:placetype":"locality"
},
  "geometry": {"coordinates":[59.40501,36.51591],"type":"Point"}
}