{
  "type": "Feature",
  "properties": {
    "gn:admin1_code":"22",
    "gn:asciiname":"Ashku",
    "gn:country_code":"IR",
    "gn:dem":5,
    "gn:feature_class":"P",
    "gn:feature_code":"PPLF",
    "gn:name":"Ashk\u016b",
    "gn:population":0,
    "gn:timezone":"Asia/Tehran",
    "iso:country":"IR",
    "name:fas_x_preferred":[
        "\u0627\u0634\u0643\u0648"
    ],
    "name:fas_x_variant":[
        "Ashk\u016bn",
        "Ashk\u016b",
        "\u0627\u0634\u0643\u0648\u0646"
    ],
    "name:und_x_variant":[
        "\u0627\u0634\u0643\u0648\u0646"
    ],
    "wof:name":"Ashku",
    "wof:placetype":"locality"
},
  "geometry": {"coordinates":[51.77523,27.84851],"type":"Point"}
}