{
  "type": "Feature",
  "properties": {
    "gn:admin1_code":"42",
    "gn:asciiname":"Taqiabad",
    "gn:country_code":"IR",
    "gn:dem":1195,
    "gn:feature_class":"P",
    "gn:feature_code":"PPL",
    "gn:name":"Taq\u012b\u0101b\u0101d",
    "gn:population":0,
    "gn:timezone":"Asia/Tehran",
    "iso:country":"IR",
    "name:fas_x_preferred":[
        "\u062a\u0642\u06cc \u0622\u0628\u0627\u062f"
    ],
    "name:fas_x_variant":[
        "Taq\u012b\u0101b\u0101d"
    ],
    "wof:name":"Taqiabad",
    "wof:placetype":"locality"
},
  "geometry": {"coordinates":[58.59419000000001,36.31101],"type":"Point"}
}