{
  "type": "Feature",
  "properties": {
    "gn:admin1_code":"11",
    "gn:asciiname":"Bagh Narges",
    "gn:country_code":"IR",
    "gn:dem":482,
    "gn:feature_class":"P",
    "gn:feature_code":"PPL",
    "gn:name":"B\u0101gh Narges",
    "gn:population":0,
    "gn:timezone":"Asia/Tehran",
    "iso:country":"IR",
    "name:ceb_x_preferred":[
        "B\u0101gh Narges"
    ],
    "name:fas_x_preferred":[
        "\u0628\u0627\u063a \u0646\u0631\u06af\u0633\u0627\u0646"
    ],
    "name:fas_x_variant":[
        "\u0628\u0627\u063a \u0646\u0631\u06af\u0633",
        "B\u0101gh Narges\u0101n",
        "B\u0101gh Narges"
    ],
    "name:msa_x_preferred":[
        "Bagh Narges"
    ],
    "name:swe_x_preferred":[
        "B\u0101gh Narges"
    ],
    "wof:name":"Bagh Narges",
    "wof:placetype":"locality"
},
  "geometry": {"coordinates":[57.2517,27.7889],"type":"Point"}
}