{
  "type": "Feature",
  "properties": {
    "gn:admin1_code":"15",
    "gn:asciiname":"Kowsareh",
    "gn:country_code":"IR",
    "gn:dem":306,
    "gn:feature_class":"P",
    "gn:feature_code":"PPL",
    "gn:name":"Kows\u0304areh",
    "gn:population":0,
    "gn:timezone":"Asia/Tehran",
    "iso:country":"IR",
    "name:ceb_x_preferred":[
        "Kows\u0304areh"
    ],
    "name:fas_x_preferred":[
        "\u06a9\u0648\u062b\u0631\u0647"
    ],
    "name:fas_x_variant":[
        "Kows\u0304ar",
        "Kows\u0304areh"
    ],
    "name:swe_x_preferred":[
        "Kows\u0304areh"
    ],
    "name:und_x_variant":[
        "Kowshareh",
        "Kows\u0101reh"
    ],
    "wof:name":"Kowsareh",
    "wof:placetype":"locality"
},
  "geometry": {"coordinates":[49.40542,31.98355],"type":"Point"}
}