{
  "type": "Feature",
  "properties": {
    "gn:admin1_code":"33",
    "gn:asciiname":"Chowlaqlu",
    "gn:country_code":"IR",
    "gn:dem":1387,
    "gn:feature_class":"P",
    "gn:feature_code":"PPL",
    "gn:name":"Chowl\u0101ql\u016b",
    "gn:population":0,
    "gn:timezone":"Asia/Tehran",
    "iso:country":"IR",
    "name:ceb_x_preferred":[
        "Chowl\u0101ql\u016b"
    ],
    "name:fas_x_preferred":[
        "\u0686\u0648\u0644\u0627\u0642\u0644\u0648"
    ],
    "name:fas_x_variant":[
        "Chol\u0101ql\u016b",
        "Chowl\u0101ql\u016b"
    ],
    "name:msa_x_preferred":[
        "Chowlaqlu"
    ],
    "name:swe_x_preferred":[
        "Chowl\u0101ql\u016b"
    ],
    "name:und_x_variant":[
        "Cholaghloo",
        "Chol\u0101kl\u016b",
        "Cholakhlu"
    ],
    "wof:name":"Chowlaqlu",
    "wof:placetype":"locality"
},
  "geometry": {"coordinates":[47.9061,37.2872],"type":"Point"}
}