{
  "type": "Feature",
  "properties": {
    "gn:admin1_code":"16",
    "gn:asciiname":"Kelucheh",
    "gn:country_code":"IR",
    "gn:dem":1757,
    "gn:feature_class":"P",
    "gn:feature_code":"PPL",
    "gn:name":"Kel\u016bcheh",
    "gn:population":0,
    "gn:timezone":"Asia/Tehran",
    "iso:country":"IR",
    "name:fas_x_preferred":[
        "\u06a9\u0644\u0648\u0686\u0647"
    ],
    "name:fas_x_variant":[
        "\u0643\u064f\u0644\u0686\u0650\u0647",
        "\u0643\u0648\u0644\u0686\u0627\u0647",
        "Kol\u016bcheh"
    ],
    "name:und_x_variant":[
        "Kel\u016bcheh",
        "Kolcheh",
        "K\u016blch\u0101h"
    ],
    "wof:name":"Kelucheh",
    "wof:placetype":"locality"
},
  "geometry": {"coordinates":[47.9154,35.62421],"type":"Point"}
}