{
  "type": "Feature",
  "properties": {
    "gn:admin1_code":"5.0",
    "gn:asciiname":"Genaveh",
    "gn:country_code":"IR",
    "gn:dem":2437,
    "gn:feature_class":"P",
    "gn:feature_code":"PPL",
    "gn:name":"Gen\u0101veh",
    "gn:population":0,
    "gn:timezone":"Asia/Tehran",
    "iso:country":"IR",
    "name:fas_x_preferred":[
        "Gan\u0101veh"
    ],
    "name:fas_x_variant":[
        "\u06af\u0646\u0627\u0648\u0647"
    ],
    "name:und_x_variant":[
        "Gen\u0101veh"
    ],
    "wof:name":"Genaveh",
    "wof:placetype":"locality"
},
  "geometry": {"coordinates":[50.66517,31.22256],"type":"Point"}
}