{
  "type": "Feature",
  "properties": {
    "gn:admin1_code":"16",
    "gn:asciiname":"Nanur",
    "gn:country_code":"IR",
    "gn:dem":1679,
    "gn:feature_class":"P",
    "gn:feature_code":"PPL",
    "gn:name":"Nan\u016br",
    "gn:population":0,
    "gn:timezone":"Asia/Tehran",
    "iso:country":"IR",
    "name:ara_x_preferred":[
        "\u0646\u0646\u0648\u0631"
    ],
    "name:ceb_x_preferred":[
        "Nan\u016br"
    ],
    "name:ckb_x_preferred":[
        "\u0646\u06d5\u0646\u06c6\u0631"
    ],
    "name:fas_x_preferred":[
        "\u0646\u064e\u0646\u0648\u0631"
    ],
    "name:fas_x_variant":[
        "\u0646\u064e\u0646\u064f\u0631",
        "\u067e\u064e\u0647\u0644\u064e\u0648\u06cc \u062f\u0650\u0698",
        "\u0646\u0646\u0648\u0631",
        "Nan\u016br"
    ],
    "name:swe_x_preferred":[
        "Nan\u016br"
    ],
    "name:und_x_variant":[
        "Pahlav\u012b Dezh",
        "Nanor"
    ],
    "wof:name":"Nanur",
    "wof:placetype":"locality"
},
  "geometry": {"coordinates":[46.0138,35.8647],"type":"Point"}
}