{
  "type": "Feature",
  "properties": {
    "gn:admin1_code":"5",
    "gn:asciiname":"Ab Mowrd",
    "gn:country_code":"IR",
    "gn:dem":1281,
    "gn:feature_class":"P",
    "gn:feature_code":"PPL",
    "gn:name":"\u0100b Mowrd",
    "gn:population":0,
    "gn:timezone":"Asia/Tehran",
    "iso:country":"IR",
    "name:fas_x_preferred":[
        "\u0622\u0628 \u0645\u0648\u0631\u062f"
    ],
    "name:fas_x_variant":[
        "\u0100b M\u016brd",
        "\u0100b Mowrd",
        "\u0627\u064e\u0628 \u0645\u064f\u0651\u0631\u062f",
        "\u0622\u0628 \u0645\u0648\u0631\u062f \u062f\u0645 \u0644\u0648\u062f\u0627\u0628"
    ],
    "name:und_x_variant":[
        "Ab Moord",
        "\u0100b Mowrd-e Dam L\u016bd\u0101b"
    ],
    "wof:name":"Ab Mowrd",
    "wof:placetype":"locality"
},
  "geometry": {"coordinates":[50.78948,31.00386],"type":"Point"}
}