{
  "type": "Feature",
  "properties": {
    "gn:admin1_code":"29",
    "gn:asciiname":"Ja`farabad-e Nuq",
    "gn:country_code":"IR",
    "gn:dem":1391,
    "gn:feature_class":"P",
    "gn:feature_code":"PPL",
    "gn:name":"Ja\u2018far\u0101b\u0101d-e N\u016bq",
    "gn:population":0,
    "gn:timezone":"Asia/Tehran",
    "iso:country":"IR",
    "name:fas_x_preferred":[
        "Ja\u2018far\u0101b\u0101d"
    ],
    "name:fas_x_variant":[
        "Ja\u2018far\u0101b\u0101d-e N\u016bq",
        "\u062c\u0639\u0641\u0631 \u0622\u0628\u0627\u062f \u0646\u0648\u0642",
        "Ja\u2018far Abad Noq"
    ],
    "wof:name":"Ja`farabad-e Nuq",
    "wof:placetype":"locality"
},
  "geometry": {"coordinates":[55.88389,30.72586],"type":"Point"}
}