{
  "type": "Feature",
  "properties": {
    "gn:admin1_code":"35.0",
    "gn:asciiname":"Mejlar",
    "gn:country_code":"IR",
    "gn:dem":672,
    "gn:feature_class":"P",
    "gn:feature_code":"PPL",
    "gn:name":"Mejl\u0101r",
    "gn:population":0,
    "gn:timezone":"Asia/Tehran",
    "iso:country":"IR",
    "name:ara_x_preferred":[
        "\u0645\u064a\u062c\u0644\u0627\u0631"
    ],
    "name:fas_x_preferred":[
        "\u0645\u064a\u062c\u0644\u0627\u0631"
    ],
    "name:fas_x_variant":[
        "Mejl\u0101r",
        "M\u012bjl\u0101r",
        "\u0645\u0650\u062c\u0650\u0644",
        "\u0645\u062c\u0644\u0627\u0631",
        "\u0645\u06cc\u062c\u0644\u0627\u0631"
    ],
    "name:und_x_variant":[
        "\u0645\u062c\u0644\u0627\u0631",
        "Mejel"
    ],
    "wof:name":"Mejlar",
    "wof:placetype":"locality"
},
  "geometry": {"coordinates":[51.2786,36.38106],"type":"Point"}
}