{
  "type": "Feature",
  "properties": {
    "gn:admin1_code":"11",
    "gn:asciiname":"Mardan",
    "gn:country_code":"IR",
    "gn:dem":331,
    "gn:feature_class":"P",
    "gn:feature_code":"PPL",
    "gn:name":"Mard\u0101n",
    "gn:population":0,
    "gn:timezone":"Asia/Tehran",
    "iso:country":"IR",
    "name:fas_x_preferred":[
        "\u0645\u064e\u0631\u062f\u0627\u0646"
    ],
    "name:fas_x_variant":[
        "Mard\u0101n"
    ],
    "wof:name":"Mardan",
    "wof:placetype":"locality"
},
  "geometry": {"coordinates":[54.00115,27.07006],"type":"Point"}
}