{
  "type": "Feature",
  "properties": {
    "gn:admin1_code":"7",
    "gn:asciiname":"Faryab",
    "gn:country_code":"IR",
    "gn:dem":1571,
    "gn:feature_class":"P",
    "gn:feature_code":"PPL",
    "gn:name":"F\u0101ry\u0101b",
    "gn:population":0,
    "gn:timezone":"Asia/Tehran",
    "iso:country":"IR",
    "name:fas_x_preferred":[
        "F\u0101ry\u0101b"
    ],
    "wof:name":"Faryab",
    "wof:placetype":"locality"
},
  "geometry": {"coordinates":[52.14222,29.39389000000001],"type":"Point"}
}