{
  "type": "Feature",
  "properties": {
    "gn:admin1_code":"13",
    "gn:asciiname":"Sarhal-e Shirazi",
    "gn:country_code":"IR",
    "gn:dem":955,
    "gn:feature_class":"P",
    "gn:feature_code":"PPL",
    "gn:name":"Sar\u1e29\u0101l-e Sh\u012br\u0101z\u012b",
    "gn:population":0,
    "gn:timezone":"Asia/Tehran",
    "iso:country":"IR",
    "name:fas_x_preferred":[
        "\u0633\u0631 \u062d\u0627\u0644 \u0634\u06cc\u0631\u0627\u0632\u06cc"
    ],
    "name:fas_x_variant":[
        "Sar\u1e29\u0101l-e Sh\u012br\u0101z\u012b"
    ],
    "wof:name":"Sarhal-e Shirazi",
    "wof:placetype":"locality"
},
  "geometry": {"coordinates":[45.909,34.0613],"type":"Point"}
}