{
  "type": "Feature",
  "properties": {
    "gn:admin1_code":"8",
    "gn:asciiname":"Sang Chub",
    "gn:country_code":"IR",
    "gn:dem":-16,
    "gn:feature_class":"P",
    "gn:feature_code":"PPL",
    "gn:name":"Sang Ch\u016bb",
    "gn:population":0,
    "gn:timezone":"Asia/Tehran",
    "iso:country":"IR",
    "name:fas_x_preferred":[
        "\u0633\u0646\u06af \u0686\u0648\u0628"
    ],
    "name:und_x_variant":[
        "Sang Ch\u016bb"
    ],
    "wof:name":"Sang Chub",
    "wof:placetype":"locality"
},
  "geometry": {"coordinates":[49.35731,37.35937],"type":"Point"}
}