{
  "type": "Feature",
  "properties": {
    "gn:admin1_code":"5",
    "gn:asciiname":"Sargordeh-ye Murd",
    "gn:country_code":"IR",
    "gn:dem":1287,
    "gn:feature_class":"P",
    "gn:feature_code":"PPL",
    "gn:name":"Sargordeh-ye M\u016brd",
    "gn:population":0,
    "gn:timezone":"Asia/Tehran",
    "iso:country":"IR",
    "name:fas_x_preferred":[
        "Sargordeh-ye M\u016brd"
    ],
    "name:fas_x_variant":[
        "\u0633\u0631\u06af\u0631\u062f\u0647 \u0645\u0648\u0631\u062f"
    ],
    "name:und_x_variant":[
        "\u0633\u0631\u06af\u0631\u062f\u0647 \u0645\u0648\u0631\u062f"
    ],
    "wof:name":"Sargordeh-ye Murd",
    "wof:placetype":"locality"
},
  "geometry": {"coordinates":[50.15173,31.05946],"type":"Point"}
}