{
  "type": "Feature",
  "properties": {
    "gn:admin1_code":"35.0",
    "gn:asciiname":"Larg Dasht",
    "gn:country_code":"IR",
    "gn:dem":377,
    "gn:feature_class":"P",
    "gn:feature_code":"PPL",
    "gn:name":"Larg Dasht",
    "gn:population":0,
    "gn:timezone":"Asia/Tehran",
    "iso:country":"IR",
    "name:fas_x_preferred":[
        "\u0644\u0631\u06af \u062f\u0634\u062a"
    ],
    "name:und_x_variant":[
        "Merg Dasht",
        "Larg Dasht"
    ],
    "wof:name":"Larg Dasht",
    "wof:placetype":"locality"
},
  "geometry": {"coordinates":[50.68249,36.86004000000001],"type":"Point"}
}