{
  "type": "Feature",
  "properties": {
    "gn:admin1_code":"33",
    "gn:asciiname":"Khalaj",
    "gn:country_code":"IR",
    "gn:dem":1883,
    "gn:feature_class":"P",
    "gn:feature_code":"PPL",
    "gn:name":"Khalaj",
    "gn:population":0,
    "gn:timezone":"Asia/Tehran",
    "iso:country":"IR",
    "name:azb_x_preferred":[
        "\u062e\u0644\u062c"
    ],
    "name:aze_x_preferred":[
        "X\u0259l\u0259c"
    ],
    "name:fas_x_preferred":[
        "\u062e\u0644\u062c"
    ],
    "name:msa_x_preferred":[
        "Khalaj"
    ],
    "name:und_x_variant":[
        "Kholash",
        "Khaiash",
        "Khoiash"
    ],
    "wof:name":"Khalaj",
    "wof:placetype":"locality"
},
  "geometry": {"coordinates":[47.0229,38.326],"type":"Point"}
}