{
  "type": "Feature",
  "properties": {
    "gn:admin1_code":"34",
    "gn:asciiname":"Kala",
    "gn:country_code":"IR",
    "gn:dem":2048,
    "gn:feature_class":"P",
    "gn:feature_code":"PPL",
    "gn:name":"Kal\u0101",
    "gn:population":0,
    "gn:timezone":"Asia/Tehran",
    "iso:country":"IR",
    "name:aze_x_preferred":[
        "Kala"
    ],
    "name:ben_x_preferred":[
        "\u0995\u09b2\u09be"
    ],
    "name:ceb_x_preferred":[
        "Kala"
    ],
    "name:ces_x_preferred":[
        "Kala"
    ],
    "name:deu_x_preferred":[
        "Kala"
    ],
    "name:est_x_preferred":[
        "Kala"
    ],
    "name:eus_x_preferred":[
        "Kala"
    ],
    "name:fas_x_preferred":[
        "Kal\u0101"
    ],
    "name:fas_x_variant":[
        "\u0643\u0644\u0627",
        "\u06a9\u0627\u0644\u0627"
    ],
    "name:fin_x_preferred":[
        "Kala"
    ],
    "name:fra_x_preferred":[
        "Kala"
    ],
    "name:ind_x_preferred":[
        "Kala"
    ],
    "name:ita_x_preferred":[
        "Kala"
    ],
    "name:lit_x_preferred":[
        "Kala"
    ],
    "name:nld_x_preferred":[
        "Kala"
    ],
    "name:pol_x_preferred":[
        "Kala"
    ],
    "name:por_x_preferred":[
        "Kala"
    ],
    "name:slv_x_preferred":[
        "Kala"
    ],
    "name:spa_x_preferred":[
        "Kala"
    ],
    "name:swe_x_preferred":[
        "Kala"
    ],
    "wof:name":"Kala",
    "wof:placetype":"locality"
},
  "geometry": {"coordinates":[49.72513,34.76229],"type":"Point"}
}