{
  "type": "Feature",
  "properties": {
    "gn:admin1_code":"34",
    "gn:asciiname":"Kala",
    "gn:country_code":"IR",
    "gn:dem":2048,
    "gn:feature_class":"P",
    "gn:feature_code":"PPL",
    "gn:name":"Kal\u0101",
    "gn:population":0,
    "gn:timezone":"Asia/Tehran",
    "iso:country":"IR",
    "name:fas_x_preferred":[
        "Kal\u0101"
    ],
    "name:fas_x_variant":[
        "\u0643\u0644\u0627"
    ],
    "name:und_x_variant":[
        "\u0643\u0644\u0627"
    ],
    "wof:name":"Kala",
    "wof:placetype":"locality"
},
  "geometry": {"coordinates":[49.72513,34.76229],"type":"Point"}
}