{
  "type": "Feature",
  "properties": {
    "gn:admin1_code":"0",
    "gn:asciiname":"Kownian",
    "gn:country_code":"IR",
    "gn:dem":499,
    "gn:feature_class":"P",
    "gn:feature_code":"PPL",
    "gn:name":"Kown\u012b\u0101n",
    "gn:population":0,
    "gn:timezone":"Asia/Tehran",
    "iso:country":"IR",
    "name:fas_x_preferred":[
        "\u06a9\u0648\u0646\u06cc\u0627\u0646"
    ],
    "name:fas_x_variant":[
        "Kown\u012b\u0101n"
    ],
    "wof:name":"Kownian",
    "wof:placetype":"locality"
},
  "geometry": {"coordinates":[57.4186,27.6397],"type":"Point"}
}