{
  "type": "Feature",
  "properties": {
    "gn:admin1_code":"1",
    "gn:asciiname":"Hajji Jafan",
    "gn:country_code":"IR",
    "gn:dem":2287,
    "gn:feature_class":"P",
    "gn:feature_code":"PPL",
    "gn:name":"\u1e28\u0101jj\u012b Jaf\u0101n",
    "gn:population":0,
    "gn:timezone":"Asia/Tehran",
    "iso:country":"IR",
    "name:aze_x_preferred":[
        "Hac\u0131cafan"
    ],
    "name:ceb_x_preferred":[
        "\u1e28\u0101jj\u012b Jaf\u0101n"
    ],
    "name:fas_x_preferred":[
        "\u1e28\u0101jj\u012b Jaf\u0101n"
    ],
    "name:fas_x_variant":[
        "\u062d\u0627\u062c\u06cc \u062c\u0641\u0627\u0646",
        "\u062d\u0627\u062c\u06cc\u200c\u062c\u0641\u0627\u0646"
    ],
    "name:msa_x_preferred":[
        "Hajji Jafan"
    ],
    "name:swe_x_preferred":[
        "\u1e28\u0101jj\u012b Jaf\u0101n"
    ],
    "wof:name":"Hajji Jafan",
    "wof:placetype":"locality"
},
  "geometry": {"coordinates":[44.4511,38.1351],"type":"Point"}
}