{
  "type": "Feature",
  "properties": {
    "gn:admin1_code":"29",
    "gn:asciiname":"Deyhurach",
    "gn:country_code":"IR",
    "gn:dem":596,
    "gn:feature_class":"P",
    "gn:feature_code":"PPL",
    "gn:name":"Deyh\u016brach",
    "gn:population":0,
    "gn:timezone":"Asia/Tehran",
    "iso:country":"IR",
    "name:fas_x_preferred":[
        "\u062f\u06cc \u0647\u0631\u062c"
    ],
    "name:fas_x_variant":[
        "\u062f\u06cc\u0647\u0648\u0631\u0686",
        "Deyh\u016brach"
    ],
    "name:und_x_variant":[
        "Dey Horj"
    ],
    "wof:name":"Deyhurach",
    "wof:placetype":"locality"
},
  "geometry": {"coordinates":[57.2931,27.6017],"type":"Point"}
}