{
  "type": "Feature",
  "properties": {
    "gn:admin1_code":"29",
    "gn:asciiname":"Mahmudiyeh Bahrami",
    "gn:country_code":"IR",
    "gn:dem":1505,
    "gn:feature_class":"P",
    "gn:feature_code":"PPL",
    "gn:name":"Ma\u1e29m\u016bd\u012byeh Bahr\u0101m\u012b",
    "gn:population":0,
    "gn:timezone":"Asia/Tehran",
    "iso:country":"IR",
    "name:fas_x_preferred":[
        "Ma\u1e29m\u016bd\u012byeh Bahr\u0101m\u012b"
    ],
    "name:fas_x_variant":[
        "Ma\u1e29m\u016bd\u012byeh",
        "\u0645\u062d\u0645\u0648\u062f\u06cc\u0647 \u0628\u0647\u0631\u0627\u0645\u06cc",
        "Mo\u1e29ammad\u012b",
        "Mahm\u016bdi"
    ],
    "wof:name":"Mahmudiyeh Bahrami",
    "wof:placetype":"locality"
},
  "geometry": {"coordinates":[56.03648000000001,30.54057],"type":"Point"}
}