{
  "type": "Feature",
  "properties": {
    "gn:admin1_code":"41",
    "gn:asciiname":"Chahkhu",
    "gn:country_code":"IR",
    "gn:dem":1714,
    "gn:feature_class":"P",
    "gn:feature_code":"PPL",
    "gn:name":"Ch\u0101hkh\u016b",
    "gn:population":0,
    "gn:timezone":"Asia/Tehran",
    "iso:country":"IR",
    "name:fas_x_preferred":[
        "\u0686\u0627\u0647\u062e\u0648"
    ],
    "name:fas_x_variant":[
        "Ch\u0101hkh\u016b"
    ],
    "wof:name":"Chahkhu",
    "wof:placetype":"locality"
},
  "geometry": {"coordinates":[60.07088,32.25684],"type":"Point"}
}