{
  "type": "Feature",
  "properties": {
    "gn:admin1_code":"29",
    "gn:asciiname":"Garmi",
    "gn:country_code":"IR",
    "gn:dem":2556,
    "gn:feature_class":"P",
    "gn:feature_code":"PPL",
    "gn:name":"Garm\u012b",
    "gn:population":0,
    "gn:timezone":"Asia/Tehran",
    "iso:country":"IR",
    "name:fas_x_preferred":[
        "\u06af\u0631\u0645\u06cc"
    ],
    "name:fas_x_variant":[
        "Garm\u012b"
    ],
    "wof:name":"Garmi",
    "wof:placetype":"locality"
},
  "geometry": {"coordinates":[55.2236,30.4125],"type":"Point"}
}