{
  "type": "Feature",
  "properties": {
    "gn:admin1_code":"33",
    "gn:asciiname":"Arbat",
    "gn:country_code":"IR",
    "gn:dem":1065,
    "gn:feature_class":"P",
    "gn:feature_code":"PPL",
    "gn:name":"Arb\u0101\u0163",
    "gn:population":0,
    "gn:timezone":"Asia/Tehran",
    "iso:country":"IR",
    "name:fas_x_preferred":[
        "\u0627\u0631\u0628\u0627\u0637"
    ],
    "name:fas_x_variant":[
        "Arb\u0101\u0163"
    ],
    "wof:name":"Arbat",
    "wof:placetype":"locality"
},
  "geometry": {"coordinates":[47.7843,37.4264],"type":"Point"}
}