{
  "type": "Feature",
  "properties": {
    "gn:admin1_code":"22.0",
    "gn:asciiname":"Gaz Khun",
    "gn:country_code":"IR",
    "gn:dem":18,
    "gn:feature_class":"P",
    "gn:feature_code":"PPL",
    "gn:name":"Gaz Kh\u016bn",
    "gn:population":0,
    "gn:timezone":"Asia/Tehran",
    "iso:country":"IR",
    "name:ara_x_preferred":[
        "\u063a\u0632\u062e\u0648\u0646"
    ],
    "name:fas_x_preferred":[
        "\u06af\u064e\u0633 \u062e\u0648\u0646"
    ],
    "name:fas_x_variant":[
        "\u06af\u0632 \u062e\u0648\u0646",
        "Gazkh\u016bn",
        "Gaz Kh\u016bn",
        "\u0643\u0650\u0632 \u062e\u0627\u0646",
        "\u06af\u0632\u062e\u0648\u0646"
    ],
    "name:msa_x_preferred":[
        "Gaz Khun"
    ],
    "name:und_x_variant":[
        "Gas Kh\u016bn",
        "Kez Kh\u0101n"
    ],
    "wof:name":"Gaz Khun",
    "wof:placetype":"locality"
},
  "geometry": {"coordinates":[51.5409,27.9384],"type":"Point"}
}