{
  "type": "Feature",
  "properties": {
    "gn:admin1_code":"42",
    "gn:asciiname":"Kalateh-ye Dahaneh",
    "gn:country_code":"IR",
    "gn:dem":1288,
    "gn:feature_class":"P",
    "gn:feature_code":"PPL",
    "gn:name":"Kal\u0101teh-ye Dahaneh",
    "gn:population":0,
    "gn:timezone":"Asia/Tehran",
    "iso:country":"IR",
    "name:ara_x_preferred":[
        "\u0643\u0644\u0627\u062a\u0629 \u062f\u0647\u0627\u0646\u0629"
    ],
    "name:fas_x_preferred":[
        "Kal\u0101teh-ye Dahaneh"
    ],
    "name:fas_x_variant":[
        "\u06a9\u0644\u0627\u062a\u0647 \u062f\u0647\u0646\u0647"
    ],
    "wof:name":"Kalateh-ye Dahaneh",
    "wof:placetype":"locality"
},
  "geometry": {"coordinates":[57.15917,33.91528],"type":"Point"}
}