{
  "type": "Feature",
  "properties": {
    "gn:admin1_code":"15",
    "gn:asciiname":"Emam Safi-ye Now",
    "gn:country_code":"IR",
    "gn:dem":79,
    "gn:feature_class":"P",
    "gn:feature_code":"PPL",
    "gn:name":"Em\u0101m \u015eaf\u012b-ye Now",
    "gn:population":0,
    "gn:timezone":"Asia/Tehran",
    "iso:country":"IR",
    "name:fas_x_preferred":[
        "Em\u0101m \u015eaf\u012b-ye Now"
    ],
    "wof:name":"Emam Safi-ye Now",
    "wof:placetype":"locality"
},
  "geometry": {"coordinates":[49.40917,31.44472],"type":"Point"}
}