{
  "type": "Feature",
  "properties": {
    "gn:admin1_code":"13",
    "gn:asciiname":"Darreh Yab",
    "gn:country_code":"IR",
    "gn:dem":641,
    "gn:feature_class":"P",
    "gn:feature_code":"PPL",
    "gn:name":"Darreh Y\u0101b",
    "gn:population":0,
    "gn:timezone":"Asia/Tehran",
    "iso:country":"IR",
    "name:fas_x_preferred":[
        "\u062f\u0631\u0651\u0647 \u06cc\u0627\u0628"
    ],
    "name:fas_x_variant":[
        "Darreh Y\u0101b",
        "\u062f\u0631\u0647\u200c\u06cc\u0627\u0628"
    ],
    "wof:name":"Darreh Yab",
    "wof:placetype":"locality"
},
  "geometry": {"coordinates":[46.028,34.9988],"type":"Point"}
}