{
  "type": "Feature",
  "properties": {
    "gn:admin1_code":"15.0",
    "gn:asciiname":"Yazab",
    "gn:country_code":"IR",
    "gn:dem":30,
    "gn:feature_class":"P",
    "gn:feature_code":"PPL",
    "gn:name":"Yaz\u0304\u0101b",
    "gn:population":0,
    "gn:timezone":"Asia/Tehran",
    "iso:country":"IR",
    "name:fas_x_preferred":[
        "Yaz \u0100b"
    ],
    "name:fas_x_variant":[
        "\u06cc\u0630\u0627\u0628"
    ],
    "name:und_x_variant":[
        "Yaz\u0304\u0101b"
    ],
    "wof:name":"Yazab",
    "wof:placetype":"locality"
},
  "geometry": {"coordinates":[48.68316,31.80587],"type":"Point"}
}