{
  "type": "Feature",
  "properties": {
    "gn:gn_country":"IR",
    "gn:gn_fcode":"PPL",
    "gn:gn_pop":40157,
    "gn:population":40157,
    "iso:country":"IR",
    "name:ara_x_preferred":[
        "\u0642\u0627\u064a\u0646"
    ],
    "name:arz_x_preferred":[
        "\u0642\u0627\u064a\u0646"
    ],
    "name:aze_x_preferred":[
        "Qain"
    ],
    "name:ben_x_preferred":[
        "\u0995\u09c1\u09af\u09bc\u09c7\u09a8"
    ],
    "name:dan_x_preferred":[
        "Qaen"
    ],
    "name:deu_x_preferred":[
        "Qaen"
    ],
    "name:ell_x_preferred":[
        "\u039a\u03b1\u03ad\u03bd"
    ],
    "name:eng_x_preferred":[
        "Qaen"
    ],
    "name:fas_x_preferred":[
        "Q\u0101\u2019en"
    ],
    "name:fas_x_variant":[
        "Q\u0101yen",
        "\u0642\u0627\u06cc\u0646",
        "\u0642\u0627\u0626\u0646"
    ],
    "name:fin_x_preferred":[
        "Qaen"
    ],
    "name:fra_x_preferred":[
        "Ghayen"
    ],
    "name:guj_x_preferred":[
        "\u0a95\u0acd\u0aaf\u0ac1\u0a8f\u0aa8"
    ],
    "name:hin_x_preferred":[
        "\u0915\u093c\u093e\u090f\u0928"
    ],
    "name:ind_x_preferred":[
        "Qaen"
    ],
    "name:ita_x_preferred":[
        "Qa'en"
    ],
    "name:jpn_x_preferred":[
        "\u30ab\u30a8\u30f3"
    ],
    "name:kan_x_preferred":[
        "\u0c95\u0ccd\u0caf\u0cc6\u0ca8\u0ccd"
    ],
    "name:kor_x_preferred":[
        "\ucfe0\uc5d4"
    ],
    "name:lav_x_preferred":[
        "Kajena"
    ],
    "name:lit_x_preferred":[
        "Kajenas"
    ],
    "name:mar_x_preferred":[
        "\u0915\u094d\u092f\u0942\u090f\u0928"
    ],
    "name:mlg_x_preferred":[
        "Qaen"
    ],
    "name:msa_x_preferred":[
        "Qaen"
    ],
    "name:nld_x_preferred":[
        "Qaen"
    ],
    "name:nob_x_preferred":[
        "Qaen"
    ],
    "name:pnb_x_preferred":[
        "\u0642\u0627\u06cc\u0646"
    ],
    "name:pol_x_preferred":[
        "Qaen"
    ],
    "name:por_x_preferred":[
        "Qaen"
    ],
    "name:rus_x_preferred":[
        "\u041a\u0430\u0439\u0435\u043d"
    ],
    "name:sin_x_preferred":[
        "\u0d9a\u0dd4\u0d85\u0dba\u0dd2\u0db1\u0dca"
    ],
    "name:spa_x_preferred":[
        "Qaen"
    ],
    "name:swe_x_preferred":[
        "Qayen"
    ],
    "name:tam_x_preferred":[
        "\u0b95\u0bbf\u0baf\u0bbe\u0ba9\u0bcd"
    ],
    "name:tel_x_preferred":[
        "\u0c15\u0c3e\u0c2f\u0c28\u0c4d"
    ],
    "name:tgk_x_preferred":[
        "\u049a\u043e\u0438\u043d"
    ],
    "name:tha_x_preferred":[
        "\u0e40\u0e04\u0e35\u0e22\u0e19"
    ],
    "name:tur_x_preferred":[
        "Gain"
    ],
    "name:ukr_x_preferred":[
        "\u041a\u0430\u0439\u0435\u043d"
    ],
    "name:unk_x_variant":[
        "Qa\u012bn"
    ],
    "name:urd_x_preferred":[
        "\u0642\u0627\u0626\u0646"
    ],
    "name:vie_x_preferred":[
        "Qaen"
    ],
    "name:zho_x_preferred":[
        "\u52a0\u5ef6"
    ],
    "qs_pg:aaroncc":"IR",
    "qs_pg:gn_country":"IR",
    "qs_pg:gn_fcode":"PPL",
    "qs_pg:gn_pop":40157,
    "qs_pg:name":"Q\u0101yen",
    "qs_pg:photos_9r":0,
    "qs_pg:photos_sr":0,
    "qs_pg:pop_sr":7,
    "qs_pg:qs_pg_placetype":"locality",
    "wof:name":"Q\u0101yen",
    "wof:placetype":"locality",
    "wof:population":40157
},
  "geometry": {"coordinates":[59.18439,33.72654],"type":"Point"}
}