{
  "type": "Feature",
  "properties": {
    "gn:admin1_code":"22",
    "gn:asciiname":"Kordevan",
    "gn:country_code":"IR",
    "gn:dem":97,
    "gn:feature_class":"P",
    "gn:feature_code":"PPL",
    "gn:name":"Kordev\u0101n",
    "gn:population":0,
    "gn:timezone":"Asia/Tehran",
    "iso:country":"IR",
    "name:fas_x_preferred":[
        "\u0643\u064f\u0631\u062f\u0650\u0648\u0627\u0646"
    ],
    "name:fas_x_variant":[
        "Kordev\u0101n"
    ],
    "wof:name":"Kordevan",
    "wof:placetype":"locality"
},
  "geometry": {"coordinates":[51.87333,28.21889],"type":"Point"}
}