{
  "type": "Feature",
  "properties": {
    "gn:admin1_code":"35",
    "gn:asciiname":"Gazna Sara",
    "gn:country_code":"IR",
    "gn:dem":2064,
    "gn:feature_class":"P",
    "gn:feature_code":"PPL",
    "gn:name":"Gazn\u0101 Sar\u0101",
    "gn:population":0,
    "gn:timezone":"Asia/Tehran",
    "iso:country":"IR",
    "name:fas_x_preferred":[
        "\u06af\u0632\u0646\u0627 \u0633\u0631\u0627"
    ],
    "name:fas_x_variant":[
        "\u06af\u0650\u0632\u0646\u0650\u0633\u0650\u0631\u064e",
        "Kazn\u0101 Sar\u0101",
        "Gazn\u0101 Sar\u0101"
    ],
    "name:und_x_variant":[
        "Geznesera",
        "Gazn\u0101 Sar\u0101"
    ],
    "wof:name":"Gazna Sara",
    "wof:placetype":"locality"
},
  "geometry": {"coordinates":[52.18953,36.28085],"type":"Point"}
}