{
  "type": "Feature",
  "properties": {
    "gn:admin1_code":"15.0",
    "gn:asciiname":"Ashkaf",
    "gn:country_code":"IR",
    "gn:dem":143,
    "gn:feature_class":"P",
    "gn:feature_code":"PPL",
    "gn:name":"Ashk\u0101f",
    "gn:population":0,
    "gn:timezone":"Asia/Tehran",
    "iso:country":"IR",
    "name:fas_x_preferred":[
        "\u0627\u0634\u06a9\u0627\u0641"
    ],
    "name:fas_x_variant":[
        "Ashk\u0101f"
    ],
    "wof:name":"Ashkaf",
    "wof:placetype":"locality"
},
  "geometry": {"coordinates":[49.8224,30.7035],"type":"Point"}
}