{
  "type": "Feature",
  "properties": {
    "gn:admin1_code":"4",
    "gn:asciiname":"Gat",
    "gn:country_code":"IR",
    "gn:dem":63,
    "gn:feature_class":"P",
    "gn:feature_code":"PPL",
    "gn:name":"Gat",
    "gn:population":0,
    "gn:timezone":"Asia/Tehran",
    "iso:country":"IR",
    "name:fas_x_preferred":[
        "\u06af\u062a"
    ],
    "wof:name":"Gat",
    "wof:placetype":"locality"
},
  "geometry": {"coordinates":[61.505,25.7934],"type":"Point"}
}