{
  "type": "Feature",
  "properties": {
    "gn:admin1_code":"5.0",
    "gn:asciiname":"Deli-ye Zila'i",
    "gn:country_code":"IR",
    "gn:dem":2312,
    "gn:feature_class":"P",
    "gn:feature_code":"PPL",
    "gn:name":"Del\u012b-ye Z\u012bl\u0101\u2019\u012b",
    "gn:population":0,
    "gn:timezone":"Asia/Tehran",
    "iso:country":"IR",
    "name:fas_x_preferred":[
        "Na\u015froll\u0101h\u0101b\u0101d"
    ],
    "name:fas_x_variant":[
        "\u0646\u0635\u0631 \u0627\u0644\u0644\u0651\u0647 \u0622\u0628\u0627\u062f",
        "\u062f\u0644\u06cc \u0632\u06cc\u0644\u0627\u0626\u06cc",
        "\u0645\u0648\u0631 \u0632\u0631\u062f \u062f\u0635\u0631\u0627\u0644\u0644\u0647"
    ],
    "name:und_x_variant":[
        "Del\u012b-ye Z\u012bl\u0101\u2019\u012b",
        "Mowr-e Zard Na\u015froll\u0101h"
    ],
    "wof:name":"Deli-ye Zila'i",
    "wof:placetype":"locality"
},
  "geometry": {"coordinates":[50.80589000000001,31.22293],"type":"Point"}
}