{
  "type": "Feature",
  "properties": {
    "gn:admin1_code":"7.0",
    "gn:asciiname":"Qeshlaq-e Halqeh Kahkumi",
    "gn:country_code":"IR",
    "gn:dem":1711,
    "gn:feature_class":"P",
    "gn:feature_code":"PPLL",
    "gn:name":"Qeshl\u0101q-e \u1e28alqeh Kahk\u016bm\u012b",
    "gn:population":0,
    "gn:timezone":"Asia/Tehran",
    "iso:country":"IR",
    "name:fas_x_preferred":[
        "\u0642\u0634\u0644\u0627\u0642 \u062d\u0644\u0642\u0647 \u06a9\u0647\u06a9\u0648\u0645\u06cc"
    ],
    "name:fas_x_variant":[
        "\u062d\u0644\u0642 \u06a9\u0647\u06a9\u0648\u0645\u06cc"
    ],
    "name:und_x_variant":[
        "Qeshl\u0101q-e \u1e28alqeh Kahk\u016bm\u012b",
        "\u1e28alaq-e Kahk\u016bm\u012b"
    ],
    "wof:name":"Qeshlaq-e Halqeh Kahkumi",
    "wof:placetype":"locality"
},
  "geometry": {"coordinates":[53.72039,28.42024],"type":"Point"}
}