{
  "type": "Feature",
  "properties": {
    "gn:admin1_code":"42.0",
    "gn:asciiname":"Mahalleh-ye Qal`eh Sakhteman",
    "gn:country_code":"IR",
    "gn:dem":961,
    "gn:feature_class":"P",
    "gn:feature_code":"PPL",
    "gn:name":"Ma\u1e29alleh-ye Qal\u2018eh S\u0101khtem\u0101n",
    "gn:population":0,
    "gn:timezone":"Asia/Tehran",
    "iso:country":"IR",
    "name:fas_x_preferred":[
        "\u0645\u062d\u0644\u0647 \u0642\u0644\u0639\u0647 \u0633\u0627\u062e\u062a\u0645\u0627\u0646"
    ],
    "name:und_x_variant":[
        "Ma\u1e29alleh-ye Qal\u2018eh S\u0101khtem\u0101n"
    ],
    "wof:name":"Mahalleh-ye Qal`eh Sakhteman",
    "wof:placetype":"locality"
},
  "geometry": {"coordinates":[59.67391,36.26295],"type":"Point"}
}