{
  "type": "Feature",
  "properties": {
    "gn:admin1_code":"8.0",
    "gn:asciiname":"Harzevil-e Pa'in",
    "gn:country_code":"IR",
    "gn:dem":442,
    "gn:feature_class":"P",
    "gn:feature_code":"PPL",
    "gn:name":"Harzev\u012bl-e P\u0101\u2019\u012bn",
    "gn:population":0,
    "gn:timezone":"Asia/Tehran",
    "iso:country":"IR",
    "name:fas_x_preferred":[
        "\u0647\u0631\u0632\u0648\u06cc\u0644 \u067e\u0627\u06cc\u06cc\u0646"
    ],
    "name:und_x_variant":[
        "Harzev\u012bl-e P\u0101\u2019\u012bn"
    ],
    "wof:name":"Harzevil-e Pa'in",
    "wof:placetype":"locality"
},
  "geometry": {"coordinates":[49.43095,36.7458],"type":"Point"}
}