{
  "type": "Feature",
  "properties": {
    "gn:admin1_code":"41.0",
    "gn:asciiname":"Do Rah",
    "gn:country_code":"IR",
    "gn:dem":1918,
    "gn:feature_class":"P",
    "gn:feature_code":"PPL",
    "gn:name":"Do Ra\u1e29",
    "gn:population":0,
    "gn:timezone":"Asia/Tehran",
    "iso:country":"IR",
    "name:ara_x_preferred":[
        "\u062f\u0648\u0631\u0627\u0647"
    ],
    "name:fas_x_preferred":[
        "Do Ra\u1e29"
    ],
    "name:fas_x_variant":[
        "\u062f\u0648\u0631\u0627\u0647"
    ],
    "name:msa_x_preferred":[
        "Do Rah"
    ],
    "name:und_x_variant":[
        "Do R\u016b"
    ],
    "wof:name":"Do Rah",
    "wof:placetype":"locality"
},
  "geometry": {"coordinates":[60.17417,32.08778],"type":"Point"}
}