{
  "type": "Feature",
  "properties": {
    "gn:admin1_code":"33",
    "gn:asciiname":"Aghbolagh",
    "gn:country_code":"IR",
    "gn:dem":1585,
    "gn:feature_class":"P",
    "gn:feature_code":"PPL",
    "gn:name":"\u0100ghbol\u0101gh",
    "gn:population":0,
    "gn:timezone":"Asia/Tehran",
    "iso:country":"IR",
    "name:fas_x_preferred":[
        "\u0100ghbol\u0101gh"
    ],
    "wof:name":"Aghbolagh",
    "wof:placetype":"locality"
},
  "geometry": {"coordinates":[46.35,38.03333],"type":"Point"}
}