{
  "type": "Feature",
  "properties": {
    "gn:admin1_code":"35.0",
    "gn:asciiname":"Eskandar Kola",
    "gn:country_code":"IR",
    "gn:dem":65,
    "gn:feature_class":"P",
    "gn:feature_code":"PPL",
    "gn:name":"Eskandar Kol\u0101",
    "gn:population":0,
    "gn:timezone":"Asia/Tehran",
    "iso:country":"IR",
    "name:fas_x_preferred":[
        "\u0627\u0650\u0633\u0643\u064e\u0646\u062f\u064e\u0631 \u0643\u064f\u0644\u0627"
    ],
    "name:fas_x_variant":[
        "Eskandar Kol\u0101",
        "\u0627\u0633\u06a9\u0646\u062f\u0631\u06a9\u0644\u0627"
    ],
    "name:und_x_variant":[
        "khiabane shaid fallah"
    ],
    "wof:name":"Eskandar Kola",
    "wof:placetype":"locality"
},
  "geometry": {"coordinates":[52.83634,36.45249],"type":"Point"}
}