{
  "type": "Feature",
  "properties": {
    "gn:admin1_code":"33",
    "gn:asciiname":"Osku",
    "gn:country_code":"IR",
    "gn:dem":1512,
    "gn:feature_class":"P",
    "gn:feature_code":"PPLA2",
    "gn:name":"Osk\u016b",
    "gn:population":0,
    "gn:timezone":"Asia/Tehran",
    "iso:country":"IR",
    "name:ara_x_preferred":[
        "\u0623\u0633\u0643\u0648"
    ],
    "name:azb_x_preferred":[
        "\u0627\u0648\u0633\u06a9\u0648"
    ],
    "name:aze_x_preferred":[
        "\u00dcsk\u00fc"
    ],
    "name:ceb_x_preferred":[
        "Osk\u016b"
    ],
    "name:deu_x_preferred":[
        "Osku"
    ],
    "name:fas_x_preferred":[
        "\u0627\u0633\u06a9\u0648"
    ],
    "name:fas_x_variant":[
        "Osk\u016b"
    ],
    "name:fin_x_preferred":[
        "Osku"
    ],
    "name:ita_x_preferred":[
        "Osku"
    ],
    "name:mlg_x_preferred":[
        "Osku"
    ],
    "name:msa_x_preferred":[
        "Osku"
    ],
    "name:pnb_x_preferred":[
        "\u0627\u0648\u0633\u06a9\u0648"
    ],
    "name:pol_x_preferred":[
        "Osku"
    ],
    "name:ron_x_preferred":[
        "Oskou"
    ],
    "name:tur_x_preferred":[
        "Osku"
    ],
    "name:und_x_variant":[
        "Yuzki",
        "Uzku"
    ],
    "name:urd_x_preferred":[
        "\u0627\u0633\u06a9\u0648"
    ],
    "name:zho_x_preferred":[
        "\u5967\u65af\u5eab"
    ],
    "wof:name":"Osku",
    "wof:placetype":"locality"
},
  "geometry": {"coordinates":[46.12258,37.91504000000001],"type":"Point"}
}