{
  "type": "Feature",
  "properties": {
    "gn:admin1_code":"33",
    "gn:asciiname":"Osku",
    "gn:country_code":"IR",
    "gn:dem":1512,
    "gn:feature_class":"P",
    "gn:feature_code":"PPLA2",
    "gn:name":"Osk\u016b",
    "gn:population":0,
    "gn:timezone":"Asia/Tehran",
    "iso:country":"IR",
    "name:fas_x_preferred":[
        "\u0627\u0633\u06a9\u0648"
    ],
    "name:fas_x_variant":[
        "Osk\u016b"
    ],
    "name:und_x_variant":[
        "Yuzki",
        "Uzku"
    ],
    "wof:name":"Osku",
    "wof:placetype":"locality"
},
  "geometry": {"coordinates":[46.12258,37.91504000000001],"type":"Point"}
}