{
  "type": "Feature",
  "properties": {
    "gn:admin1_code":"23",
    "gn:asciiname":"Golestanak",
    "gn:country_code":"IR",
    "gn:dem":1636,
    "gn:feature_class":"P",
    "gn:feature_code":"PPL",
    "gn:name":"Golest\u0101nak",
    "gn:population":0,
    "gn:timezone":"Asia/Tehran",
    "iso:country":"IR",
    "name:ara_x_preferred":[
        "\u063a\u0644\u0633\u062a\u0627\u0646\u0643"
    ],
    "name:ceb_x_preferred":[
        "Golest\u0101nak"
    ],
    "name:fas_x_preferred":[
        "\u06af\u064f\u0644\u0650\u0633\u062a\u0627\u0646\u064e\u0643"
    ],
    "name:fas_x_variant":[
        "\u06af\u064f\u0644\u0650\u0633\u062a\u0627\u0646",
        "\u06af\u0644\u0633\u062a\u0627\u0646\u06a9",
        "Golest\u0101nak",
        "Golest\u0101n"
    ],
    "name:swe_x_preferred":[
        "Golest\u0101nak"
    ],
    "wof:name":"Golestanak",
    "wof:placetype":"locality"
},
  "geometry": {"coordinates":[47.7236,34.0599],"type":"Point"}
}