{
  "type": "Feature",
  "properties": {
    "gn:admin1_code":"4",
    "gn:asciiname":"Daher",
    "gn:country_code":"IR",
    "gn:dem":1606,
    "gn:feature_class":"P",
    "gn:feature_code":"PPL",
    "gn:name":"D\u0101her",
    "gn:population":0,
    "gn:timezone":"Asia/Tehran",
    "iso:country":"IR",
    "name:deu_x_preferred":[
        "Daher"
    ],
    "name:fas_x_preferred":[
        "\u062f\u0627\u0647\u0631"
    ],
    "name:fas_x_variant":[
        "D\u0101her"
    ],
    "name:fra_x_preferred":[
        "Daher"
    ],
    "wof:name":"Daher",
    "wof:placetype":"locality"
},
  "geometry": {"coordinates":[60.18598000000001,29.01978],"type":"Point"}
}