{
  "type": "Feature",
  "properties": {
    "gn:admin1_code":"1",
    "gn:asciiname":"Aqajari",
    "gn:country_code":"IR",
    "gn:dem":1432,
    "gn:feature_class":"P",
    "gn:feature_code":"PPL",
    "gn:name":"\u0100q\u0101j\u0101r\u012b",
    "gn:population":0,
    "gn:timezone":"Asia/Tehran",
    "iso:country":"IR",
    "name:fas_x_preferred":[
        "\u0622\u0642\u0627 \u062c\u0627\u0631\u06cc"
    ],
    "name:fas_x_variant":[
        "\u0100q\u0101j\u0101r\u012b"
    ],
    "name:und_x_variant":[
        "\u0100gh\u0101jar\u012b"
    ],
    "wof:name":"Aqajari",
    "wof:placetype":"locality"
},
  "geometry": {"coordinates":[46.6139,36.577],"type":"Point"}
}