{
  "type": "Feature",
  "properties": {
    "gn:admin1_code":"4.0",
    "gn:asciiname":"Kahn-e Kureh",
    "gn:country_code":"IR",
    "gn:dem":907,
    "gn:feature_class":"P",
    "gn:feature_code":"PPL",
    "gn:name":"Kahn-e K\u016breh",
    "gn:population":0,
    "gn:timezone":"Asia/Tehran",
    "iso:country":"IR",
    "name:fas_x_preferred":[
        "Kahn-e K\u016breh"
    ],
    "name:fas_x_variant":[
        "\u06a9\u0647\u0646 \u06a9\u0648\u0631\u0647"
    ],
    "wof:name":"Kahn-e Kureh",
    "wof:placetype":"locality"
},
  "geometry": {"coordinates":[63.22991,27.13105],"type":"Point"}
}