{
  "type": "Feature",
  "properties": {
    "gn:admin1_code":"7",
    "gn:asciiname":"Fakhrabad-e `Olya",
    "gn:country_code":"IR",
    "gn:dem":1603,
    "gn:feature_class":"P",
    "gn:feature_code":"PPL",
    "gn:name":"Fakhr\u0101b\u0101d-e \u2018Oly\u0101",
    "gn:population":0,
    "gn:timezone":"Asia/Tehran",
    "iso:country":"IR",
    "name:fas_x_preferred":[
        "\u0641\u062e\u0631\u0622\u0628\u0627\u062f \u0639\u0644\u06cc\u0627"
    ],
    "name:fas_x_variant":[
        "Fakhr\u0101b\u0101d-e \u2018Olya",
        "Fakhr\u0101b\u0101d-e \u2018Oly\u0101",
        "Fakhr\u0101b\u0101d-e B\u0101l\u0101"
    ],
    "name:und_x_variant":[
        "Fakhr\u0101b\u0101d-e B\u0101l\u0101"
    ],
    "wof:name":"Fakhrabad-e `Olya",
    "wof:placetype":"locality"
},
  "geometry": {"coordinates":[52.7057,29.9812],"type":"Point"}
}