{
  "type": "Feature",
  "properties": {
    "gn:admin1_code":"25.0",
    "gn:asciiname":"Kalateh-ye Marri",
    "gn:country_code":"IR",
    "gn:dem":1300,
    "gn:feature_class":"P",
    "gn:feature_code":"PPL",
    "gn:name":"Kal\u0101teh-ye Marr\u012b",
    "gn:population":0,
    "gn:timezone":"Asia/Tehran",
    "iso:country":"IR",
    "name:fas_x_preferred":[
        "\u06a9\u0644\u0627\u062a\u0647 \u0645\u0631\u06cc"
    ],
    "name:fas_x_variant":[
        "\u0645\u064e\u0631\u06cc",
        "\u0645\u0631\u0651\u06cc"
    ],
    "name:und_x_variant":[
        "Kal\u0101teh-ye Marr\u012b",
        "Marr\u012b",
        "Mar\u012b"
    ],
    "wof:name":"Kalateh-ye Marri",
    "wof:placetype":"locality"
},
  "geometry": {"coordinates":[56.90583,35.39830999999999],"type":"Point"}
}