{
  "type": "Feature",
  "properties": {
    "gn:admin1_code":"34",
    "gn:asciiname":"Kalateh-ye Dahaneh-ye Ghar",
    "gn:country_code":"IR",
    "gn:dem":1375,
    "gn:feature_class":"P",
    "gn:feature_code":"PPL",
    "gn:name":"Kal\u0101teh-ye Dahaneh-ye Gh\u0101r",
    "gn:population":0,
    "gn:timezone":"Asia/Tehran",
    "iso:country":"IR",
    "name:fas_x_preferred":[
        "Kal\u0101teh-ye Dahaneh-ye Gh\u0101r"
    ],
    "wof:name":"Kalateh-ye Dahaneh-ye Ghar",
    "wof:placetype":"locality"
},
  "geometry": {"coordinates":[50.31667,35.38333],"type":"Point"}
}