{
  "type": "Feature",
  "properties": {
    "gn:admin1_code":"1",
    "gn:asciiname":"`Isalu-ye Zemi",
    "gn:country_code":"IR",
    "gn:dem":1294,
    "gn:feature_class":"P",
    "gn:feature_code":"PPL",
    "gn:name":"\u2018\u012as\u00e1l\u016b-ye Z\u0304em\u012b",
    "gn:population":0,
    "gn:timezone":"Asia/Tehran",
    "iso:country":"IR",
    "name:fas_x_preferred":[
        "\u0639\u06cc\u0633\u06cc \u0644\u0648 \u0630\u0645\u06cc"
    ],
    "name:fas_x_variant":[
        "\u0639\u064a\u0633\u064e\u0649\u0644\u0648\u06cc \u0630\u0650\u0645\u06cc",
        "\u2018\u012as\u00e1l\u016b-ye Z\u0304em\u012b"
    ],
    "wof:name":"`Isalu-ye Zemi",
    "wof:placetype":"locality"
},
  "geometry": {"coordinates":[45.1088,37.6837],"type":"Point"}
}