{
  "type": "Feature",
  "properties": {
    "gn:admin1_code":"35.0",
    "gn:asciiname":"Dar Mazar",
    "gn:country_code":"IR",
    "gn:dem":1465,
    "gn:feature_class":"P",
    "gn:feature_code":"PPL",
    "gn:name":"Dar Maz\u0101r",
    "gn:population":0,
    "gn:timezone":"Asia/Tehran",
    "iso:country":"IR",
    "name:fas_x_preferred":[
        "\u062f\u064e\u0631\u0645\u0650\u0632\u0627\u0631"
    ],
    "name:fas_x_variant":[
        "Dar Maz\u0101r",
        "\u062f\u0631 \u0645\u0632\u0627\u0631"
    ],
    "name:und_x_variant":[
        "Darmez\u0101r"
    ],
    "wof:name":"Dar Mazar",
    "wof:placetype":"locality"
},
  "geometry": {"coordinates":[53.85521,36.45605],"type":"Point"}
}