{
  "type": "Feature",
  "properties": {
    "gn:admin1_code":"42",
    "gn:asciiname":"Bazeh Kalagh",
    "gn:country_code":"IR",
    "gn:dem":1074,
    "gn:feature_class":"P",
    "gn:feature_code":"PPL",
    "gn:name":"B\u0101zeh Kal\u0101gh",
    "gn:population":0,
    "gn:timezone":"Asia/Tehran",
    "iso:country":"IR",
    "name:fas_x_preferred":[
        "\u0628\u0627\u0632\u0647 \u06a9\u0644\u0627\u063a"
    ],
    "name:fas_x_variant":[
        "B\u0101zeh Kal\u0101gh"
    ],
    "wof:name":"Bazeh Kalagh",
    "wof:placetype":"locality"
},
  "geometry": {"coordinates":[59.32713,36.57097],"type":"Point"}
}