{
  "type": "Feature",
  "properties": {
    "gn:admin1_code":"15",
    "gn:asciiname":"Kazem-e Heydar",
    "gn:cc2":"IR",
    "gn:country_code":"IR",
    "gn:dem":33,
    "gn:feature_class":"P",
    "gn:feature_code":"PPL",
    "gn:name":"K\u0101z\u0327em-e \u1e28eydar",
    "gn:population":0,
    "gn:timezone":"Asia/Tehran",
    "iso:country":"IR",
    "name:fas_x_preferred":[
        "K\u0101z\u0327em-e \u1e28eydar"
    ],
    "name:fas_x_variant":[
        "\u06a9\u0627\u0638\u0645 \u062d\u06cc\u062f\u0631"
    ],
    "name:und_x_variant":[
        "\u0162alayl\u012b"
    ],
    "wof:name":"Kazem-e Heydar",
    "wof:placetype":"locality"
},
  "geometry": {"coordinates":[48.63528,31.84833],"type":"Point"}
}