{
  "type": "Feature",
  "properties": {
    "gn:admin1_code":"1.0",
    "gn:asciiname":"Darageh-ye Lotfollah",
    "gn:country_code":"IR",
    "gn:dem":1281,
    "gn:elevation":"0.0",
    "gn:feature_class":"P",
    "gn:feature_code":"PPL",
    "gn:name":"Darageh-ye Lo\u0163foll\u0101h",
    "gn:population":0,
    "gn:timezone":"Asia/Tehran",
    "iso:country":"IR",
    "name:azb_x_preferred":[
        "\u062f\u0631\u06af\u0647 \u0644\u0637\u0641 \u0627\u0644\u0647"
    ],
    "name:aze_x_preferred":[
        "D\u0259r\u0259g\u0259h-i L\u00fctfullah"
    ],
    "name:ceb_x_preferred":[
        "Darageh-ye Lo\u0163foll\u0101h"
    ],
    "name:fas_x_preferred":[
        "\u062f\u064e\u0631\u064e\u0643\u0650\u06c0 \u0644\u064f\u0637\u0641 \u0627\u0644\u0644\u064e\u0651\u0647"
    ],
    "name:fas_x_variant":[
        "\u062f\u0631\u06af\u0647 \u0644\u0637\u0641 \u0627\u0644\u0644\u0647",
        "Darakeh-ye Lo\u0163foll\u0101h",
        "Darageh-ye Lo\u0163foll\u0101h",
        "\u062f\u0631\u06af\u0647\u200c\u0644\u0637\u0641\u200c\u0627\u0644\u0647"
    ],
    "name:msa_x_preferred":[
        "Darageh-ye Lotfollah"
    ],
    "name:swe_x_preferred":[
        "Darageh-ye Lo\u0163foll\u0101h"
    ],
    "wof:name":"Darageh-ye Lotfollah",
    "wof:placetype":"locality"
},
  "geometry": {"coordinates":[45.6271,36.9762],"type":"Point"}
}