{
  "type": "Feature",
  "properties": {
    "gn:admin1_code":"35.0",
    "gn:asciiname":"Teliran",
    "gn:country_code":"IR",
    "gn:dem":120,
    "gn:feature_class":"P",
    "gn:feature_code":"PPL",
    "gn:name":"Tel\u012br\u0101n",
    "gn:population":0,
    "gn:timezone":"Asia/Tehran",
    "iso:country":"IR",
    "name:ara_x_preferred":[
        "\u062a\u0644\u064a\u0631\u0627\u0646"
    ],
    "name:ceb_x_preferred":[
        "Tel\u012br\u0101n"
    ],
    "name:fas_x_preferred":[
        "\u062a\u0644\u064a\u0631\u0627\u0646"
    ],
    "name:fas_x_variant":[
        "Tel\u012br\u0101n",
        "\u062a\u0644\u06cc\u0631\u0627\u0646"
    ],
    "name:mzn_x_preferred":[
        "\u062a\u0644\u06cc\u0631\u0627\u0646"
    ],
    "name:swe_x_preferred":[
        "Tel\u012br\u0101n"
    ],
    "name:ukr_x_preferred":[
        "\u0422\u0435\u043b\u0456\u0440\u0430\u043d"
    ],
    "wof:name":"Teliran",
    "wof:placetype":"locality"
},
  "geometry": {"coordinates":[52.27889,36.42337],"type":"Point"}
}