{
  "type": "Feature",
  "properties": {
    "gn:admin1_code":"16",
    "gn:asciiname":"Darreh Tefi",
    "gn:country_code":"IR",
    "gn:dem":1318,
    "gn:feature_class":"P",
    "gn:feature_code":"PPL",
    "gn:name":"Darreh Tef\u012b",
    "gn:population":0,
    "gn:timezone":"Asia/Tehran",
    "iso:country":"IR",
    "name:fas_x_preferred":[
        "\u062f\u064e\u0631\u0650\u0651\u0647 \u062a\u0650\u0641\u06cc"
    ],
    "name:fas_x_variant":[
        "\u062f\u064e\u0631\u0650\u0651\u0647 \u062a\u064e\u0641\u06cc",
        "\u062f\u064e\u0631\u0650\u0651\u0647 \u062a\u064f\u0641\u06cc",
        "\u062f\u0631\u0651\u0647 \u062a\u0641\u06cc",
        "Darreh Tef\u012b",
        "\u062f\u064e\u0631\u0650\u0651\u0647 \u062a\u064e\u0642\u06cc"
    ],
    "name:und_x_variant":[
        "Darreh-ye Tef\u012b",
        "Darreh Tof\u012b",
        "Darreh Taf\u012b",
        "Darreh Taghi",
        "Darreh Tufi",
        "Darreh Taq\u012b"
    ],
    "wof:name":"Darreh Tefi",
    "wof:placetype":"locality"
},
  "geometry": {"coordinates":[46.0977,35.5372],"type":"Point"}
}