{
  "type": "Feature",
  "properties": {
    "gn:admin1_code":"7",
    "gn:asciiname":"Khong-e Taheri",
    "gn:country_code":"IR",
    "gn:dem":840,
    "gn:feature_class":"P",
    "gn:feature_code":"PPL",
    "gn:name":"Khong-e \u0162\u0101her\u012b",
    "gn:population":0,
    "gn:timezone":"Asia/Tehran",
    "iso:country":"IR",
    "name:fas_x_preferred":[
        "Khong-e \u0162\u0101her\u012b"
    ],
    "name:fas_x_variant":[
        "\u062e\u0646\u06af \u0637\u0627\u0647\u0631\u06cc"
    ],
    "name:und_x_variant":[
        "Khong \u0162\u0101her\u012b",
        "Khong",
        "\u062e\u0646\u06af \u0637\u0627\u0647\u0631\u06cc"
    ],
    "wof:name":"Khong-e Taheri",
    "wof:placetype":"locality"
},
  "geometry": {"coordinates":[51.43171,30.30112],"type":"Point"}
}