{
  "type": "Feature",
  "properties": {
    "gn:admin1_code":"10",
    "gn:asciiname":"Dam Samand",
    "gn:country_code":"IR",
    "gn:dem":1174,
    "gn:feature_class":"P",
    "gn:feature_code":"PPL",
    "gn:name":"Dam Samand",
    "gn:population":0,
    "gn:timezone":"Asia/Tehran",
    "iso:country":"IR",
    "name:fas_x_preferred":[
        "\u062f\u0645 \u0633\u0645\u0646\u062f"
    ],
    "wof:name":"Dam Samand",
    "wof:placetype":"locality"
},
  "geometry": {"coordinates":[47.1634,32.9873],"type":"Point"}
}