{
  "type": "Feature",
  "properties": {
    "gn:admin1_code":"7",
    "gn:asciiname":"Riz Ab",
    "gn:country_code":"IR",
    "gn:dem":1601,
    "gn:feature_class":"P",
    "gn:feature_code":"PPL",
    "gn:name":"R\u012bz \u0100b",
    "gn:population":0,
    "gn:timezone":"Asia/Tehran",
    "iso:country":"IR",
    "name:fas_x_preferred":[
        "\u0628\u0644\u0627\u06a9\u0633\u062a\u0648\u0646"
    ],
    "name:fas_x_variant":[
        "Bel\u0101kest\u016bn",
        "\u0631\u064a\u0632 \u0622\u0628",
        "\u0628\u0644\u0627\u06a9\u0633\u062a\u0648\u0646 \u0631\u064a\u0632 \u0622\u0628"
    ],
    "name:und_x_variant":[
        "R\u012bz \u0100b",
        "Bel\u0101kest\u016bn R\u012bz \u0100b"
    ],
    "wof:name":"Riz Ab",
    "wof:placetype":"locality"
},
  "geometry": {"coordinates":[55.01557,28.85262],"type":"Point"}
}