{
  "type": "Feature",
  "properties": {
    "gn:admin1_code":"29",
    "gn:asciiname":"Senjan-e Bala",
    "gn:country_code":"IR",
    "gn:dem":2612,
    "gn:feature_class":"P",
    "gn:feature_code":"PPL",
    "gn:name":"Senj\u0101n-e B\u0101l\u0101",
    "gn:population":0,
    "gn:timezone":"Asia/Tehran",
    "iso:country":"IR",
    "name:fas_x_preferred":[
        "\u0633\u0646\u062c\u0627\u0646 \u0628\u0627\u0644\u0627"
    ],
    "name:fas_x_variant":[
        "Sonj\u016b\u2019\u012byeh-ye B\u0101l\u0101",
        "Senj\u0101n-e B\u0101l\u0101"
    ],
    "name:und_x_variant":[
        "Senj\u0101n B\u0101l\u0101"
    ],
    "wof:name":"Senjan-e Bala",
    "wof:placetype":"locality"
},
  "geometry": {"coordinates":[56.1379,29.9558],"type":"Point"}
}