{
  "type": "Feature",
  "properties": {
    "gn:admin1_code":"15",
    "gn:asciiname":"Moslem Ebn-e `Aqil",
    "gn:country_code":"IR",
    "gn:dem":60,
    "gn:feature_class":"P",
    "gn:feature_code":"PPL",
    "gn:name":"Moslem Ebn-e \u2018Aq\u012bl",
    "gn:population":0,
    "gn:timezone":"Asia/Tehran",
    "iso:country":"IR",
    "name:fas_x_preferred":[
        "\u0634\u0627\u0647\u0648\u0631"
    ],
    "name:fas_x_variant":[
        "Moslem Ebn-e \u2018Aq\u012bl",
        "Sh\u0101v\u016br",
        "\u0634\u0627\u0648\u0648\u0631",
        "Sh\u0101h\u016br",
        "\u0645\u0633\u0644\u0645 \u0627\u0628\u0646 \u0639\u0642\u06cc\u0644",
        "\u0631\u0634\u06af \u0634\u0627\u0648\u0648\u0631"
    ],
    "name:und_x_variant":[
        "Rashk-e Sh\u0101hv\u0101r",
        "Shahvar",
        "Rashk-e Sh\u0101h\u016br",
        "Rashg-e Sh\u0101v\u016br"
    ],
    "wof:name":"Moslem Ebn-e `Aqil",
    "wof:placetype":"locality"
},
  "geometry": {"coordinates":[48.30404,32.05585],"type":"Point"}
}