{
  "type": "Feature",
  "properties": {
    "gn:admin1_code":"29",
    "gn:asciiname":"Jahan Jan",
    "gn:country_code":"IR",
    "gn:dem":2551,
    "gn:feature_class":"P",
    "gn:feature_code":"PPL",
    "gn:name":"Jah\u0101n J\u0101n",
    "gn:population":0,
    "gn:timezone":"Asia/Tehran",
    "iso:country":"IR",
    "name:fas_x_preferred":[
        "\u062c\u0647\u0627\u0646 \u062c\u0627\u0646"
    ],
    "name:fas_x_variant":[
        "Jah\u0101n J\u0101n"
    ],
    "wof:name":"Jahan Jan",
    "wof:placetype":"locality"
},
  "geometry": {"coordinates":[56.6408,29.3539],"type":"Point"}
}