{
  "type": "Feature",
  "properties": {
    "gn:admin1_code":"23",
    "gn:asciiname":"Darreh Bagh-e Dovvom",
    "gn:country_code":"IR",
    "gn:dem":946,
    "gn:feature_class":"P",
    "gn:feature_code":"PPL",
    "gn:name":"Darreh B\u0101gh-e Dovvom",
    "gn:population":0,
    "gn:timezone":"Asia/Tehran",
    "iso:country":"IR",
    "name:fas_x_preferred":[
        "\u062f\u064e\u0631\u0650\u0651\u0647 \u0628\u0627\u063a\u0650 \u062f\u064f\u0648\u064f\u0651\u0645"
    ],
    "wof:name":"Darreh Bagh-e Dovvom",
    "wof:placetype":"locality"
},
  "geometry": {"coordinates":[47.95,33.28333],"type":"Point"}
}