{
  "type": "Feature",
  "properties": {
    "gn:admin1_code":"29",
    "gn:asciiname":"Mohammadabad",
    "gn:country_code":"IR",
    "gn:dem":1965,
    "gn:feature_class":"P",
    "gn:feature_code":"PPL",
    "gn:name":"Mo\u1e29ammad\u0101b\u0101d",
    "gn:population":0,
    "gn:timezone":"Asia/Tehran",
    "iso:country":"IR",
    "name:ara_x_preferred":[
        "\u0645\u062d\u0645\u062f \u0623\u0628\u0627\u062f"
    ],
    "name:fas_x_preferred":[
        "\u0645\u062d\u0645\u062f \u0622\u0628\u0627\u062f"
    ],
    "name:fas_x_variant":[
        "Mo\u1e29ammad\u0101b\u0101d",
        "\u0645\u062d\u0645\u062f\u0622\u0628\u0627\u062f"
    ],
    "name:und_x_variant":[
        "Ma\u1e29m\u016bd\u0101b\u0101d"
    ],
    "wof:name":"Mohammadabad",
    "wof:placetype":"locality"
},
  "geometry": {"coordinates":[55.5595,30.2042],"type":"Point"}
}