{
  "type": "Feature",
  "properties": {
    "gn:admin1_code":"22",
    "gn:asciiname":"Hoseyn-e Za'eri",
    "gn:country_code":"IR",
    "gn:dem":30,
    "gn:feature_class":"P",
    "gn:feature_code":"PPL",
    "gn:name":"\u1e28oseyn-e Z\u0101\u2019er\u012b",
    "gn:population":0,
    "gn:timezone":"Asia/Tehran",
    "iso:country":"IR",
    "name:ara_x_preferred":[
        "\u062d\u0633\u064a\u0646 \u0632\u0627\u0626\u0631\u064a"
    ],
    "name:fas_x_preferred":[
        "\u062d\u0633\u064a\u0646 \u0632\u0627\u06cc\u0631\u06cc"
    ],
    "name:fas_x_variant":[
        "\u062d\u064f\u0633\u0641\u064a\u0646 \u0632\u0627\u0626\u0650\u0631\u06cc",
        "\u062d\u064f\u0633\u0650\u064a\u0646 \u0632\u0627\u0626\u0650\u0631\u06cc",
        "\u1e28oseyn-e Z\u0101\u2019er\u012b",
        "\u062d\u0633\u06cc\u0646\u200c\u0632\u0627\u0626\u0631\u06cc"
    ],
    "name:msa_x_preferred":[
        "Hoseyn-e Zaeri"
    ],
    "name:und_x_variant":[
        "Hasan Z\u012bri",
        "\u1e28osfyn Z\u0101\u2019er\u012b",
        "\u1e28oseyn Z\u0101\u2019er\u012b",
        "Hosein Za\u2019eri"
    ],
    "wof:name":"Hoseyn-e Za'eri",
    "wof:placetype":"locality"
},
  "geometry": {"coordinates":[51.4822,28.4725],"type":"Point"}
}