{
  "type": "Feature",
  "properties": {
    "gn:admin1_code":"42",
    "gn:asciiname":"Chahar Bagh",
    "gn:country_code":"IR",
    "gn:dem":1537,
    "gn:feature_class":"P",
    "gn:feature_code":"PPL",
    "gn:name":"Chah\u0101r B\u0101gh",
    "gn:population":0,
    "gn:timezone":"Asia/Tehran",
    "iso:country":"IR",
    "name:fas_x_preferred":[
        "\u0686\u0647\u0627\u0631 \u0628\u0627\u063a"
    ],
    "name:fas_x_variant":[
        "Chah\u0101r B\u0101gh"
    ],
    "wof:name":"Chahar Bagh",
    "wof:placetype":"locality"
},
  "geometry": {"coordinates":[58.55941,36.77092],"type":"Point"}
}