{
  "type": "Feature",
  "properties": {
    "gn:admin1_code":"33",
    "gn:asciiname":"Tazeh Kand-e Chelan",
    "gn:country_code":"IR",
    "gn:dem":1759,
    "gn:feature_class":"P",
    "gn:feature_code":"PPL",
    "gn:name":"T\u0101zeh Kand-e Chel\u0101n",
    "gn:population":0,
    "gn:timezone":"Asia/Tehran",
    "iso:country":"IR",
    "name:azb_x_preferred":[
        "\u062a\u0627\u0632\u0647\u200c\u06a9\u0646\u062f \u06af\u0644\u200c\u0686\u0648\u0627\u0646"
    ],
    "name:fas_x_preferred":[
        "\u062a\u0627\u0632\u0647 \u06a9\u0646\u062f \u0686\u0644\u0627\u0646"
    ],
    "name:fas_x_variant":[
        "T\u0101zeh Kand-e Chel\u0101n",
        "\u062a\u0627\u0632\u0647 \u06a9\u0646\u062f \u06af\u0644 \u0686\u0648\u0627\u0646",
        "\u062a\u0627\u0632\u0647\u200c\u06a9\u0646\u062f \u06af\u0644\u200c\u0686\u0648\u0627\u0646"
    ],
    "name:msa_x_preferred":[
        "Tazeh Kand-e Gol Chavan"
    ],
    "name:und_x_variant":[
        "T\u0101zeh Kand-e Gol Chav\u0101n"
    ],
    "wof:name":"Tazeh Kand-e Chelan",
    "wof:placetype":"locality"
},
  "geometry": {"coordinates":[46.5461,37.3343],"type":"Point"}
}