{
  "type": "Feature",
  "properties": {
    "gn:admin1_code":"0",
    "gn:asciiname":"Mehdiabad",
    "gn:cc2":"IR",
    "gn:country_code":"IR",
    "gn:dem":1224,
    "gn:feature_class":"P",
    "gn:feature_code":"PPL",
    "gn:name":"Mehd\u012b\u0101b\u0101d",
    "gn:population":0,
    "gn:timezone":"Asia/Tehran",
    "iso:country":"IR",
    "name:fas_x_preferred":[
        "\u0645\u0650\u0647\u062f\u06cc \u0622\u0628\u0627\u062f"
    ],
    "name:fas_x_variant":[
        "Mehd\u012b\u0101b\u0101d"
    ],
    "name:und_x_variant":[
        "Mur\u012b\u0101b\u0101d"
    ],
    "wof:name":"Mehdiabad",
    "wof:placetype":"locality"
},
  "geometry": {"coordinates":[54.43333000000001,31.88333],"type":"Point"}
}