{
  "type": "Feature",
  "properties": {
    "gn:admin1_code":"32",
    "gn:asciiname":"Van-e Bala",
    "gn:country_code":"IR",
    "gn:dem":894,
    "gn:feature_class":"P",
    "gn:feature_code":"PPL",
    "gn:name":"V\u0101n-e B\u0101l\u0101",
    "gn:population":0,
    "gn:timezone":"Asia/Tehran",
    "iso:country":"IR",
    "name:fas_x_preferred":[
        "\u0648\u0627\u0646\u0650 \u0639\u064f\u0644\u064a\u0627"
    ],
    "name:fas_x_variant":[
        "\u0648\u0627\u0646",
        "\u0648\u0627\u0646 \u0628\u0627\u0644\u0627",
        "V\u0101n-e \u2018Oly\u0101",
        "V\u0101n-e B\u0101l\u0101"
    ],
    "name:und_x_variant":[
        "V\u0101n"
    ],
    "wof:name":"Van-e Bala",
    "wof:placetype":"locality"
},
  "geometry": {"coordinates":[48.2926,39.0074],"type":"Point"}
}