{
  "type": "Feature",
  "properties": {
    "gn:admin1_code":"7",
    "gn:asciiname":"Kahnuyeh",
    "gn:country_code":"IR",
    "gn:dem":609,
    "gn:feature_class":"P",
    "gn:feature_code":"PPL",
    "gn:name":"Kahn\u016byeh",
    "gn:population":0,
    "gn:timezone":"Asia/Tehran",
    "iso:country":"IR",
    "name:fas_x_preferred":[
        "\u06a9\u0647\u0646\u0648\u06cc\u0647"
    ],
    "name:fas_x_variant":[
        "Kahn\u016byeh"
    ],
    "name:msa_x_preferred":[
        "Kahnuyeh"
    ],
    "name:und_x_variant":[
        "\u1e28ak\u016b",
        "Hakku"
    ],
    "wof:name":"Kahnuyeh",
    "wof:placetype":"locality"
},
  "geometry": {"coordinates":[53.27988000000001,28.05571],"type":"Point"}
}