{
  "type": "Feature",
  "properties": {
    "gn:admin1_code":"8.0",
    "gn:asciiname":"Sardarabad",
    "gn:country_code":"IR",
    "gn:dem":67,
    "gn:feature_class":"P",
    "gn:feature_code":"PPL",
    "gn:name":"Sard\u0101r\u0101b\u0101d",
    "gn:population":0,
    "gn:timezone":"Asia/Tehran",
    "iso:country":"IR",
    "name:fas_x_preferred":[
        "\u0633\u0631\u062f\u0627\u0631 \u0622\u0628\u0627\u062f"
    ],
    "name:fas_x_variant":[
        "\u0633\u0631\u062f\u0627\u0631\u0622\u0628\u0627\u062f"
    ],
    "name:msa_x_preferred":[
        "Sardarabad"
    ],
    "name:ukr_x_preferred":[
        "\u0421\u0430\u0440\u0434\u0430\u0440\u0430\u0431\u0430\u0434"
    ],
    "name:und_x_variant":[
        "Sard\u0101r\u0101b\u0101d",
        "Sad Sangar"
    ],
    "wof:name":"Sardarabad",
    "wof:placetype":"locality"
},
  "geometry": {"coordinates":[49.74551,37.11601],"type":"Point"}
}