{
  "type": "Feature",
  "properties": {
    "gn:admin1_code":"11",
    "gn:asciiname":"Bejtiyabi",
    "gn:country_code":"IR",
    "gn:dem":1221,
    "gn:feature_class":"P",
    "gn:feature_code":"PPL",
    "gn:name":"Bejt\u012by\u0101b\u012b",
    "gn:population":0,
    "gn:timezone":"Asia/Tehran",
    "iso:country":"IR",
    "name:fas_x_preferred":[
        "\u0628\u062c\u062a\u06cc\u06cc\u0627\u0628\u06cc"
    ],
    "name:fas_x_variant":[
        "Bejt\u012by\u0101b\u012b"
    ],
    "wof:name":"Bejtiyabi",
    "wof:placetype":"locality"
},
  "geometry": {"coordinates":[56.1494,27.8774],"type":"Point"}
}