{
  "type": "Feature",
  "properties": {
    "gn:admin1_code":"29.0",
    "gn:asciiname":"Fathiyeh",
    "gn:country_code":"IR",
    "gn:dem":699,
    "gn:feature_class":"P",
    "gn:feature_code":"PPL",
    "gn:name":"Fat\u1e29\u012byeh",
    "gn:population":0,
    "gn:timezone":"Asia/Tehran",
    "iso:country":"IR",
    "name:fas_x_preferred":[
        "\u0641\u062a\u062d\u06cc\u0647"
    ],
    "name:fas_x_variant":[
        "Fat\u1e29\u012byeh"
    ],
    "wof:name":"Fathiyeh",
    "wof:placetype":"locality"
},
  "geometry": {"coordinates":[58.8766,28.7554],"type":"Point"}
}