{
  "type": "Feature",
  "properties": {
    "gn:admin1_code":"9",
    "gn:asciiname":"Do Baraleh",
    "gn:country_code":"IR",
    "gn:dem":1801,
    "gn:feature_class":"P",
    "gn:feature_code":"PPL",
    "gn:name":"Do Bar\u0101leh",
    "gn:population":0,
    "gn:timezone":"Asia/Tehran",
    "iso:country":"IR",
    "name:fas_x_preferred":[
        "\u062f\u064f\u0648 \u0628\u064e\u0631\u0627\u0644\u0650\u0647"
    ],
    "name:fas_x_variant":[
        "\u062f\u064f\u0628\u0631\u0627\u0644\u064e",
        "\u062f\u0648\u0628\u0650\u0631\u0627\u0644\u0650\u0647",
        "Do Bar\u0101leh",
        "Dow Bar\u0101leh",
        "\u062f\u0648 \u0628\u0631\u0627\u0644\u0647"
    ],
    "name:und_x_variant":[
        "Dubar\u0101lah",
        "Dow Bar\u0101leh",
        "D\u016bber\u0101leh",
        "Dobr\u0101la",
        "\u062f\u0648 \u0628\u0631\u0627\u0644\u0647"
    ],
    "wof:name":"Do Baraleh",
    "wof:placetype":"locality"
},
  "geometry": {"coordinates":[48.03396,34.90217],"type":"Point"}
}