{
  "type": "Feature",
  "properties": {
    "gn:admin1_code":"5.0",
    "gn:asciiname":"Ahmad Salar",
    "gn:country_code":"IR",
    "gn:dem":1007,
    "gn:feature_class":"P",
    "gn:feature_code":"PPL",
    "gn:name":"A\u1e29mad S\u0101l\u0101r",
    "gn:population":0,
    "gn:timezone":"Asia/Tehran",
    "iso:country":"IR",
    "name:fas_x_preferred":[
        "A\u1e29mad S\u0101l\u0101r"
    ],
    "name:fas_x_variant":[
        "\u0627\u062d\u0645\u062f \u0633\u0627\u0644\u0627\u0631"
    ],
    "name:und_x_variant":[
        "\u0627\u062d\u0645\u062f \u0633\u0627\u0644\u0627\u0631"
    ],
    "wof:name":"Ahmad Salar",
    "wof:placetype":"locality"
},
  "geometry": {"coordinates":[50.55051,31.07938],"type":"Point"}
}