{
  "type": "Feature",
  "properties": {
    "gn:admin1_code":"29",
    "gn:asciiname":"Hanza Kuh",
    "gn:country_code":"IR",
    "gn:dem":2765,
    "gn:feature_class":"P",
    "gn:feature_code":"PPL",
    "gn:name":"Hanz\u0101 K\u016bh",
    "gn:population":0,
    "gn:timezone":"Asia/Tehran",
    "iso:country":"IR",
    "name:fas_x_preferred":[
        "Hanz\u0101 K\u016bh"
    ],
    "wof:name":"Hanza Kuh",
    "wof:placetype":"locality"
},
  "geometry": {"coordinates":[57.38333000000001,29.03333],"type":"Point"}
}