{
  "type": "Feature",
  "properties": {
    "gn:admin1_code":"33",
    "gn:asciiname":"Neshaq",
    "gn:country_code":"IR",
    "gn:dem":1830,
    "gn:feature_class":"P",
    "gn:feature_code":"PPL",
    "gn:name":"Neshaq",
    "gn:population":0,
    "gn:timezone":"Asia/Tehran",
    "iso:country":"IR",
    "name:azb_x_preferred":[
        "\u0646\u0634\u0642"
    ],
    "name:ceb_x_preferred":[
        "Neshaq"
    ],
    "name:fas_x_preferred":[
        "\u0646\u0634\u0642"
    ],
    "name:msa_x_preferred":[
        "Neshaq"
    ],
    "name:swe_x_preferred":[
        "Neshaq"
    ],
    "wof:name":"Neshaq",
    "wof:placetype":"locality"
},
  "geometry": {"coordinates":[47.664,37.6722],"type":"Point"}
}