{
  "type": "Feature",
  "properties": {
    "gn:admin1_code":"4",
    "gn:asciiname":"Chah-e Karam",
    "gn:country_code":"IR",
    "gn:dem":1197,
    "gn:feature_class":"P",
    "gn:feature_code":"PPL",
    "gn:name":"Ch\u0101h-e Karam",
    "gn:population":0,
    "gn:timezone":"Asia/Tehran",
    "iso:country":"IR",
    "name:fas_x_preferred":[
        "\u0686\u0627\u0647 \u06a9\u0631\u0645"
    ],
    "name:fas_x_variant":[
        "Ch\u0101h-e Karam"
    ],
    "wof:name":"Chah-e Karam",
    "wof:placetype":"locality"
},
  "geometry": {"coordinates":[61.7573,27.4253],"type":"Point"}
}