{
  "type": "Feature",
  "properties": {
    "gn:admin1_code":"32",
    "gn:asciiname":"Sharif Beyglu",
    "gn:country_code":"IR",
    "gn:dem":1403,
    "gn:feature_class":"P",
    "gn:feature_code":"PPL",
    "gn:name":"Shar\u012bf Beygl\u016b",
    "gn:population":0,
    "gn:timezone":"Asia/Tehran",
    "iso:country":"IR",
    "name:ara_x_preferred":[
        "\u0634\u0631\u064a\u0641 \u0628\u064a\u063a\u0644\u0648"
    ],
    "name:ceb_x_preferred":[
        "Shar\u012bf Beygl\u016b"
    ],
    "name:fas_x_preferred":[
        "\u0634\u0631\u064a\u0641 \u0628\u064a\u06af\u0644\u0648"
    ],
    "name:fas_x_variant":[
        "Shar\u012bf Beygl\u016b",
        "\u0634\u0631\u06cc\u0641\u200c\u0628\u06cc\u06af\u0644\u0648"
    ],
    "name:msa_x_preferred":[
        "Sharif Beyglu"
    ],
    "name:mzn_x_preferred":[
        "\u0634\u0631\u06cc\u0641\u200c\u0628\u06cc\u06af\u0644\u0648"
    ],
    "name:swe_x_preferred":[
        "Shar\u012bf Beygl\u016b"
    ],
    "wof:name":"Sharif Beyglu",
    "wof:placetype":"locality"
},
  "geometry": {"coordinates":[48.1836,38.5848],"type":"Point"}
}