{
  "type": "Feature",
  "properties": {
    "gn:admin1_code":"32",
    "gn:asciiname":"Lahrud",
    "gn:country_code":"IR",
    "gn:dem":1278,
    "gn:feature_class":"P",
    "gn:feature_code":"PPL",
    "gn:name":"L\u0101hr\u016bd",
    "gn:population":0,
    "gn:timezone":"Asia/Tehran",
    "iso:country":"IR",
    "name:ara_x_preferred":[
        "\u0644\u0627\u0647\u0631\u0648\u062f"
    ],
    "name:azb_x_preferred":[
        "\u0644\u0627\u0647\u0631\u0648\u062f"
    ],
    "name:aze_x_preferred":[
        "Lahrud"
    ],
    "name:ceb_x_preferred":[
        "L\u0101r\u012b"
    ],
    "name:diq_x_preferred":[
        "Lahrud"
    ],
    "name:fas_x_preferred":[
        "\u0644\u0627\u0631\u06cc"
    ],
    "name:fas_x_variant":[
        "Ser\u0101h\u012b",
        "Seh R\u0101h\u012b",
        "L\u0101hr\u016bd",
        "\u0644\u0627\u0647\u0631\u0648\u062f",
        "L\u0101r\u012b"
    ],
    "name:mlg_x_preferred":[
        "Lahrud"
    ],
    "name:msa_x_preferred":[
        "Lahrud"
    ],
    "name:pol_x_preferred":[
        "Lahrud"
    ],
    "name:swe_x_preferred":[
        "L\u0101r\u012b"
    ],
    "name:tur_x_preferred":[
        "Lahrud"
    ],
    "name:urd_x_preferred":[
        "\u0644\u0627\u06c1\u0631\u0648\u062f"
    ],
    "wof:name":"Lahrud",
    "wof:placetype":"locality"
},
  "geometry": {"coordinates":[47.83215,38.50886],"type":"Point"}
}