{
  "type": "Feature",
  "properties": {
    "gn:admin1_code":"42",
    "gn:asciiname":"Hasan Khordu",
    "gn:country_code":"IR",
    "gn:dem":1033,
    "gn:feature_class":"P",
    "gn:feature_code":"PPL",
    "gn:name":"\u1e28asan Khord\u016b",
    "gn:population":0,
    "gn:timezone":"Asia/Tehran",
    "iso:country":"IR",
    "name:ceb_x_preferred":[
        "\u1e28asan Khord\u016b"
    ],
    "name:fas_x_preferred":[
        "\u1e28asan Khord\u016b"
    ],
    "name:fas_x_variant":[
        "\u062d\u0633\u0646 \u062e\u0631\u062f\u0648"
    ],
    "name:swe_x_preferred":[
        "\u1e28asan Khord\u016b"
    ],
    "wof:name":"Hasan Khordu",
    "wof:placetype":"locality"
},
  "geometry": {"coordinates":[59.47917,36.44778],"type":"Point"}
}