{
  "type": "Feature",
  "properties": {
    "gn:admin1_code":"7",
    "gn:asciiname":"Charg",
    "gn:country_code":"IR",
    "gn:dem":1293,
    "gn:feature_class":"P",
    "gn:feature_code":"PPL",
    "gn:name":"Charg",
    "gn:population":0,
    "gn:timezone":"Asia/Tehran",
    "iso:country":"IR",
    "name:fas_x_preferred":[
        "\u0686\u0631\u06af"
    ],
    "name:und_x_variant":[
        "Cherg",
        "Charg"
    ],
    "wof:name":"Charg",
    "wof:placetype":"locality"
},
  "geometry": {"coordinates":[53.3536,28.9109],"type":"Point"}
}