{
  "type": "Feature",
  "properties": {
    "gn:admin1_code":"16",
    "gn:asciiname":"Hasanabad-e Qashoq",
    "gn:country_code":"IR",
    "gn:dem":1444,
    "gn:feature_class":"P",
    "gn:feature_code":"PPL",
    "gn:name":"\u1e28asan\u0101b\u0101d-e Q\u0101shoq",
    "gn:population":0,
    "gn:timezone":"Asia/Tehran",
    "iso:country":"IR",
    "name:fas_x_preferred":[
        "Q\u0101shoq"
    ],
    "name:fas_x_variant":[
        "\u062d\u0633\u0646 \u0622\u0628\u0627\u062f \u0642\u0627\u0634\u0642",
        "\u062d\u0633\u0646 \u0622\u0628\u0627\u062f"
    ],
    "name:und_x_variant":[
        "\u1e28asan\u0101b\u0101d-e Q\u0101shoq",
        "\u1e28asan\u0101b\u0101d"
    ],
    "wof:name":"Hasanabad-e Qashoq",
    "wof:placetype":"locality"
},
  "geometry": {"coordinates":[46.54714,36.38636],"type":"Point"}
}