{
  "type": "Feature",
  "properties": {
    "gn:admin1_code":"13",
    "gn:asciiname":"Qeshlaq",
    "gn:country_code":"IR",
    "gn:dem":1397,
    "gn:feature_class":"P",
    "gn:feature_code":"PPL",
    "gn:name":"Qeshl\u0101q",
    "gn:population":0,
    "gn:timezone":"Asia/Tehran",
    "iso:country":"IR",
    "name:fas_x_preferred":[
        "\u0642\u0634\u0644\u0627\u0642"
    ],
    "name:fas_x_variant":[
        "Qeshl\u0101q-e Bezn\u0101b\u0101d",
        "Qeshl\u0101q",
        "\u0642\u0634\u0644\u0627\u0642\u200c\u0628\u0632\u0646\u200c\u0622\u0628\u0627\u062f"
    ],
    "wof:name":"Qeshlaq",
    "wof:placetype":"locality"
},
  "geometry": {"coordinates":[47.4878,34.3546],"type":"Point"}
}