{
  "type": "Feature",
  "properties": {
    "gn:admin1_code":"33",
    "gn:asciiname":"Ahmadabad",
    "gn:country_code":"IR",
    "gn:dem":1765,
    "gn:feature_class":"P",
    "gn:feature_code":"PPL",
    "gn:name":"A\u1e29mad\u0101b\u0101d",
    "gn:population":0,
    "gn:timezone":"Asia/Tehran",
    "iso:country":"IR",
    "name:ara_x_preferred":[
        "\u0623\u062d\u0645\u062f \u0623\u0628\u0627\u062f"
    ],
    "name:azb_x_preferred":[
        "\u0627\u062d\u0645\u062f\u0622\u0628\u0627\u062f"
    ],
    "name:cat_x_preferred":[
        "Ahmadabad"
    ],
    "name:ceb_x_preferred":[
        "Ahmadabad"
    ],
    "name:fas_x_preferred":[
        "\u0627\u062d\u0645\u062f \u0622\u0628\u0627\u062f"
    ],
    "name:fas_x_variant":[
        "A\u1e29mad\u0101b\u0101d",
        "\u0627\u062d\u0645\u062f\u0622\u0628\u0627\u062f"
    ],
    "name:fra_x_preferred":[
        "Ahmadabad"
    ],
    "name:ita_x_preferred":[
        "Ahmadabad"
    ],
    "name:kat_x_preferred":[
        "\u10d0\u10f0\u10db\u10d0\u10d3\u10d0\u10d1\u10d0\u10d3\u10d8"
    ],
    "name:swe_x_preferred":[
        "Ahmadabad"
    ],
    "name:urd_x_preferred":[
        "\u0627\u062d\u0645\u062f \u0622\u0628\u0627\u062f"
    ],
    "name:vie_x_preferred":[
        "Ahmadabad"
    ],
    "wof:name":"Ahmadabad",
    "wof:placetype":"locality"
},
  "geometry": {"coordinates":[47.0042,37.6812],"type":"Point"}
}