{
  "type": "Feature",
  "properties": {
    "gn:admin1_code":"8",
    "gn:asciiname":"Kamchal",
    "gn:country_code":"IR",
    "gn:dem":671,
    "gn:feature_class":"P",
    "gn:feature_code":"PPLL",
    "gn:name":"Kamch\u0101l",
    "gn:population":0,
    "gn:timezone":"Asia/Tehran",
    "iso:country":"IR",
    "name:fas_x_preferred":[
        "\u06a9\u0645\u0686\u0627\u0644"
    ],
    "name:fas_x_variant":[
        "Kamch\u0101l"
    ],
    "wof:name":"Kamchal",
    "wof:placetype":"locality"
},
  "geometry": {"coordinates":[49.31604,37.05211],"type":"Point"}
}