{
  "type": "Feature",
  "properties": {
    "gn:admin1_code":"28",
    "gn:asciiname":"Murestan-e `Olya",
    "gn:country_code":"IR",
    "gn:dem":2634,
    "gn:feature_class":"P",
    "gn:feature_code":"PPL",
    "gn:name":"M\u016brest\u0101n-e \u2018Oly\u0101",
    "gn:population":0,
    "gn:timezone":"Asia/Tehran",
    "iso:country":"IR",
    "name:fas_x_preferred":[
        "M\u0101h\u016brest\u0101n-e B\u0101l\u0101"
    ],
    "name:fas_x_variant":[
        "M\u016brest\u0101n-e \u2018Oly\u0101",
        "\u0645\u0648\u0631\u0633\u062a\u0627\u0646 \u0639\u0644\u06cc\u0627",
        "\u0645\u0627\u0647\u0648\u0631\u0633\u062a\u0627\u0646 \u0639\u0644\u06cc\u0627"
    ],
    "name:und_x_variant":[
        "\u0645\u0648\u0631\u0633\u062a\u0627\u0646 \u0639\u0644\u06cc\u0627",
        "M\u0101h\u016brest\u0101n-e \u2018Oly\u0101"
    ],
    "wof:name":"Murestan-e `Olya",
    "wof:placetype":"locality"
},
  "geometry": {"coordinates":[49.93024000000001,33.09629],"type":"Point"}
}