{
  "type": "Feature",
  "properties": {
    "gn:admin1_code":"8",
    "gn:asciiname":"Rowshandeh",
    "gn:country_code":"IR",
    "gn:dem":14,
    "gn:feature_class":"P",
    "gn:feature_code":"PPL",
    "gn:name":"Rowshandeh",
    "gn:population":0,
    "gn:timezone":"Asia/Tehran",
    "iso:country":"IR",
    "name:fas_x_preferred":[
        "\u0631\u0648\u0634\u0646\u062f\u0647"
    ],
    "wof:name":"Rowshandeh",
    "wof:placetype":"locality"
},
  "geometry": {"coordinates":[49.14694,37.5467],"type":"Point"}
}