{
  "type": "Feature",
  "properties": {
    "gn:admin1_code":"28.0",
    "gn:asciiname":"Ashtian",
    "gn:country_code":"IR",
    "gn:dem":870,
    "gn:feature_class":"P",
    "gn:feature_code":"PPLF",
    "gn:name":"\u0100sht\u012b\u0101n",
    "gn:population":0,
    "gn:timezone":"Asia/Tehran",
    "iso:country":"IR",
    "name:fas_x_preferred":[
        "\u0100sht\u012b\u0101n"
    ],
    "name:fas_x_variant":[
        "\u0622\u0634\u062a\u064a\u0627\u0646",
        "\u0627\u0634\u062a\u06cc\u0627\u0646"
    ],
    "name:und_x_variant":[
        "\u0100sht\u012by\u0101n",
        "\u0100shtey\u0101n"
    ],
    "wof:name":"Ashtian",
    "wof:placetype":"locality"
},
  "geometry": {"coordinates":[54.29861999999999,33.62874],"type":"Point"}
}