{
  "type": "Feature",
  "properties": {
    "gn:admin1_code":"35",
    "gn:asciiname":"Borj-e Kheyl",
    "gn:country_code":"IR",
    "gn:dem":-11,
    "gn:feature_class":"P",
    "gn:feature_code":"PPL",
    "gn:name":"Borj-e Kheyl",
    "gn:population":0,
    "gn:timezone":"Asia/Tehran",
    "iso:country":"IR",
    "name:fas_x_preferred":[
        "\u0628\u0631\u062c \u062e\u064a\u0644"
    ],
    "wof:name":"Borj-e Kheyl",
    "wof:placetype":"locality"
},
  "geometry": {"coordinates":[52.76941,36.60397],"type":"Point"}
}