{
  "type": "Feature",
  "properties": {
    "gn:admin1_code":"33",
    "gn:asciiname":"Qarajeh",
    "gn:country_code":"IR",
    "gn:dem":1605,
    "gn:feature_class":"P",
    "gn:feature_code":"PPL",
    "gn:name":"Qar\u0101jeh",
    "gn:population":0,
    "gn:timezone":"Asia/Tehran",
    "iso:country":"IR",
    "name:fas_x_preferred":[
        "\u0642\u0631\u0627\u0686\u0647"
    ],
    "name:fas_x_variant":[
        "Qar\u0101cheh",
        "\u0642\u0631\u0627\u062c\u0647"
    ],
    "name:und_x_variant":[
        "Qar\u0101jeh"
    ],
    "wof:name":"Qarajeh",
    "wof:placetype":"locality"
},
  "geometry": {"coordinates":[46.9574,38.4114],"type":"Point"}
}