{
  "type": "Feature",
  "properties": {
    "gn:admin1_code":"32",
    "gn:asciiname":"Pir Bodaq",
    "gn:country_code":"IR",
    "gn:dem":1814,
    "gn:feature_class":"P",
    "gn:feature_code":"PPL",
    "gn:name":"P\u012br Bod\u0101q",
    "gn:population":0,
    "gn:timezone":"Asia/Tehran",
    "iso:country":"IR",
    "name:aze_x_preferred":[
        "Pirbida\u011f"
    ],
    "name:ceb_x_preferred":[
        "P\u012br Bod\u0101q"
    ],
    "name:fas_x_preferred":[
        "\u067e\u06cc\u0631 \u0628\u062f\u0627\u0642"
    ],
    "name:fas_x_variant":[
        "P\u012br Bod\u0101gh",
        "P\u012br Bod\u0101q",
        "\u067e\u06cc\u0631 \u0628\u0644\u0627\u063a",
        "\u067e\u06cc\u0631 \u0628\u062f\u0627\u063a",
        "\u067e\u06cc\u0631\u0628\u062f\u0627\u063a"
    ],
    "name:msa_x_preferred":[
        "Pir Bodagh"
    ],
    "name:mzn_x_preferred":[
        "\u067e\u06cc\u0631\u0628\u062f\u0627\u063a"
    ],
    "name:swe_x_preferred":[
        "P\u012br Bod\u0101q"
    ],
    "name:und_x_variant":[
        "P\u012br Bol\u0101gh"
    ],
    "wof:name":"Pir Bodaq",
    "wof:placetype":"locality"
},
  "geometry": {"coordinates":[48.13468,37.70383],"type":"Point"}
}