{
  "type": "Feature",
  "properties": {
    "gn:admin1_code":"4.0",
    "gn:asciiname":"Qaruki",
    "gn:country_code":"IR",
    "gn:dem":483,
    "gn:feature_class":"P",
    "gn:feature_code":"PPL",
    "gn:name":"Qar\u016bk\u012b",
    "gn:population":0,
    "gn:timezone":"Asia/Tehran",
    "iso:country":"IR",
    "name:fas_x_preferred":[
        "Qar\u016bk\u012b"
    ],
    "name:fas_x_variant":[
        "\u0642\u0631\u0648\u06a9\u06cc"
    ],
    "wof:name":"Qaruki",
    "wof:placetype":"locality"
},
  "geometry": {"coordinates":[61.75921999999999,31.12558],"type":"Point"}
}