{
  "type": "Feature",
  "properties": {
    "gn:admin1_code":"29.0",
    "gn:asciiname":"Mahva-ye Sofla",
    "gn:country_code":"IR",
    "gn:dem":2344,
    "gn:feature_class":"P",
    "gn:feature_code":"PPLF",
    "gn:name":"Mahv\u0101-ye Sofl\u00e1",
    "gn:population":0,
    "gn:timezone":"Asia/Tehran",
    "iso:country":"IR",
    "name:fas_x_preferred":[
        "\u0645\u0647\u0648\u0627 \u0633\u0641\u0644\u06cc"
    ],
    "name:fas_x_variant":[
        "\u0645\u0627\u0648\u0627\u06cc \u0633\u0641\u0644\u06cc"
    ],
    "name:und_x_variant":[
        "Mahv\u0101-ye Sofl\u00e1",
        "M\u0101v\u0101-ye Sofl\u00e1"
    ],
    "wof:name":"Mahva-ye Sofla",
    "wof:placetype":"locality"
},
  "geometry": {"coordinates":[54.87124,30.6545],"type":"Point"}
}