{
  "type": "Feature",
  "properties": {
    "gn:admin1_code":"15",
    "gn:asciiname":"Tak Ab",
    "gn:country_code":"IR",
    "gn:dem":472,
    "gn:feature_class":"P",
    "gn:feature_code":"PPL",
    "gn:name":"T\u0101k \u0100b",
    "gn:population":0,
    "gn:timezone":"Asia/Tehran",
    "iso:country":"IR",
    "name:fas_x_preferred":[
        "\u062a\u064e\u0644\u0643\u0627\u0628"
    ],
    "name:fas_x_variant":[
        "\u062a\u0627\u0643\u0627\u0628",
        "\u062a\u0627\u06af \u0622\u0628",
        "Talk\u0101b",
        "T\u0101g \u0100b",
        "\u062a\u0627\u06a9 \u0622\u0628",
        "\u062a\u0627\u06a9\u0627\u067e"
    ],
    "name:und_x_variant":[
        "T\u0101k\u0101b",
        "T\u0101k \u0100b",
        "T\u0101k\u0101p"
    ],
    "wof:name":"Tak Ab",
    "wof:placetype":"locality"
},
  "geometry": {"coordinates":[48.32721,32.79614],"type":"Point"}
}