{
  "type": "Feature",
  "properties": {
    "gn:admin1_code":"23",
    "gn:asciiname":"Bornabad",
    "gn:country_code":"IR",
    "gn:dem":1890,
    "gn:feature_class":"P",
    "gn:feature_code":"PPL",
    "gn:name":"Born\u0101b\u0101d",
    "gn:population":0,
    "gn:timezone":"Asia/Tehran",
    "iso:country":"IR",
    "name:fas_x_preferred":[
        "\u0628\u064e\u0631\u0646 \u0622\u0628\u0627\u062f"
    ],
    "name:fas_x_variant":[
        "\u0628\u064f\u0631\u0646 \u0622\u0628\u0627\u062f \u0628\u0627\u0644\u0627",
        "Born\u0101b\u0101d-e B\u0101l\u0101",
        "\u0628\u0631\u0646\u0627\u0628\u0627\u062f \u0628\u0627\u0644\u0627",
        "\u0628\u0631\u0646\u0627\u0628\u0627\u062f"
    ],
    "name:und_x_variant":[
        "Barn\u0101b\u0101d",
        "Born\u0101b\u0101d B\u0101l\u0101",
        "Born\u0101b\u0101d"
    ],
    "wof:name":"Bornabad",
    "wof:placetype":"locality"
},
  "geometry": {"coordinates":[49.54833,33.42144],"type":"Point"}
}