{
  "type": "Feature",
  "properties": {
    "gn:admin1_code":"15",
    "gn:asciiname":"Bard Gapi-ye Gonjeshgir",
    "gn:country_code":"IR",
    "gn:dem":859,
    "gn:feature_class":"P",
    "gn:feature_code":"PPL",
    "gn:name":"Bard Gap\u012b-ye Gonjeshg\u012br",
    "gn:population":0,
    "gn:timezone":"Asia/Tehran",
    "iso:country":"IR",
    "name:azb_x_preferred":[
        "\u0628\u0631\u062f\u06af\u067e\u06cc(\u0627\u06cc\u0630\u0647)"
    ],
    "name:fas_x_preferred":[
        "\u0628\u064e\u0631\u062f \u06af\u0650\u067e"
    ],
    "name:fas_x_variant":[
        "Bard Gap\u012b",
        "\u0628\u0631\u062f \u06af\u067e\u06cc",
        "\u0628\u0631\u062f \u06af\u067e\u06cc \u06af\u0646\u062c\u0634\u06af\u06cc\u0631",
        "\u0628\u0631\u062f\u06af\u067e\u06cc"
    ],
    "name:und_x_variant":[
        "Bard-i-Gappi",
        "Bard Gep",
        "\u0628\u0631\u062f \u06af\u067e\u06cc",
        "Bard Gap\u012b-ye Gonjeshg\u012br"
    ],
    "wof:name":"Bard Gapi-ye Gonjeshgir",
    "wof:placetype":"locality"
},
  "geometry": {"coordinates":[49.88999,31.81099],"type":"Point"}
}