{
  "type": "Feature",
  "properties": {
    "gn:admin1_code":"29",
    "gn:asciiname":"Gur",
    "gn:country_code":"IR",
    "gn:dem":1155,
    "gn:feature_class":"P",
    "gn:feature_code":"PPL",
    "gn:name":"G\u016br",
    "gn:population":0,
    "gn:timezone":"Asia/Tehran",
    "iso:country":"IR",
    "name:ceb_x_preferred":[
        "Gur"
    ],
    "name:deu_x_preferred":[
        "Gur"
    ],
    "name:fas_x_preferred":[
        "\u06af\u0648\u0631"
    ],
    "name:fas_x_variant":[
        "N\u016br\u0101b\u0101d",
        "\u0646\u0648\u0631 \u0622\u0628\u0627\u062f",
        "G\u016br"
    ],
    "name:fra_x_preferred":[
        "Gur"
    ],
    "name:pol_x_preferred":[
        "Gur"
    ],
    "name:rus_x_preferred":[
        "\u0413\u0443\u0440"
    ],
    "name:swe_x_preferred":[
        "Gur"
    ],
    "name:ukr_x_preferred":[
        "\u0413\u0443\u0440"
    ],
    "name:und_x_variant":[
        "Gow"
    ],
    "wof:name":"Gur",
    "wof:placetype":"locality"
},
  "geometry": {"coordinates":[57.8518,27.0613],"type":"Point"}
}