{
  "type": "Feature",
  "properties": {
    "gn:admin1_code":"35",
    "gn:asciiname":"Darupey",
    "gn:country_code":"IR",
    "gn:dem":200,
    "gn:feature_class":"P",
    "gn:feature_code":"PPL",
    "gn:name":"Dar\u016bpey",
    "gn:population":0,
    "gn:timezone":"Asia/Tehran",
    "iso:country":"IR",
    "name:fas_x_preferred":[
        "\u062f\u0631\u0648\u067e\u06cc"
    ],
    "name:fas_x_variant":[
        "\u062f\u064e\u0631\u064f\u0648 \u067e\u064e\u06cc",
        "\u062f\u064e\u0631\u064f\u0651\u067e\u0650\u06cc",
        "Dar\u016bpey"
    ],
    "name:und_x_variant":[
        "Daroopey",
        "Darow Pay"
    ],
    "wof:name":"Darupey",
    "wof:placetype":"locality"
},
  "geometry": {"coordinates":[53.14816999999999,36.45332],"type":"Point"}
}