{
  "type": "Feature",
  "properties": {
    "gn:admin1_code":"13.0",
    "gn:asciiname":"Shahrak-e Sisad Dastgah",
    "gn:country_code":"IR",
    "gn:dem":1542,
    "gn:feature_class":"P",
    "gn:feature_code":"PPL",
    "gn:name":"Shahrak-e S\u012b\u015fad Dastg\u0101h",
    "gn:population":0,
    "gn:timezone":"Asia/Tehran",
    "iso:country":"IR",
    "name:fas_x_preferred":[
        "\u0634\u0647\u0631\u06a9 \u0633\u06cc\u0635\u062f \u062f\u0633\u062a\u06af\u0627\u0647"
    ],
    "name:fas_x_variant":[
        "Shahrak-e S\u012b\u015fad Dastg\u0101h"
    ],
    "wof:name":"Shahrak-e Sisad Dastgah",
    "wof:placetype":"locality"
},
  "geometry": {"coordinates":[46.229,34.2815],"type":"Point"}
}