{
  "type": "Feature",
  "properties": {
    "gn:admin1_code":"35",
    "gn:asciiname":"Pa'in Sar Rost",
    "gn:country_code":"IR",
    "gn:dem":22,
    "gn:feature_class":"P",
    "gn:feature_code":"PPL",
    "gn:name":"P\u0101\u2019\u012bn Sar Rost",
    "gn:population":0,
    "gn:timezone":"Asia/Tehran",
    "iso:country":"IR",
    "name:fas_x_preferred":[
        "\u067e\u0627\u0626\u064a\u0646 \u0633\u0650\u0631\u0650\u0633\u062a"
    ],
    "name:fas_x_variant":[
        "P\u0101\u2019\u012bn Serest",
        "\u067e\u0627\u0626\u064a\u0646 \u0633\u0631 \u0631\u0633\u062a",
        "P\u0101\u2019\u012bn Sar Rost"
    ],
    "wof:name":"Pa'in Sar Rost",
    "wof:placetype":"locality"
},
  "geometry": {"coordinates":[52.67281,36.45582],"type":"Point"}
}