{
  "type": "Feature",
  "properties": {
    "gn:admin1_code":"22",
    "gn:asciiname":"Dobozeh",
    "gn:country_code":"IR",
    "gn:dem":670,
    "gn:feature_class":"P",
    "gn:feature_code":"PPL",
    "gn:name":"Dobozeh",
    "gn:population":0,
    "gn:timezone":"Asia/Tehran",
    "iso:country":"IR",
    "name:fas_x_preferred":[
        "\u062f\u0628\u0632\u0647"
    ],
    "name:fas_x_variant":[
        "\u062f\u064f\u0632\u0650\u0647",
        "\u062f\u0648\u0627\u0632\u062f\u0647 \u0627\u0631\u063a\u0648\u0646"
    ],
    "name:und_x_variant":[
        "Dozeh",
        "Dobozeh",
        "Dav\u0101zdah Argh\u016bn"
    ],
    "wof:name":"Dobozeh",
    "wof:placetype":"locality"
},
  "geometry": {"coordinates":[51.4247,29.1083],"type":"Point"}
}