{
  "type": "Feature",
  "properties": {
    "gn:admin1_code":"16.0",
    "gn:asciiname":"Bakerabad",
    "gn:country_code":"IR",
    "gn:dem":1958,
    "gn:feature_class":"P",
    "gn:feature_code":"PPL",
    "gn:name":"Baker\u0101b\u0101d",
    "gn:population":0,
    "gn:timezone":"Asia/Tehran",
    "iso:country":"IR",
    "name:ara_x_preferred":[
        "\u0628\u0643\u0631\u0622\u0628\u0627\u062f"
    ],
    "name:ceb_x_preferred":[
        "Baker\u0101b\u0101d"
    ],
    "name:fas_x_preferred":[
        "\u0628\u06a9\u0631 \u0622\u0628\u0627\u062f"
    ],
    "name:fas_x_variant":[
        "Baker\u0101b\u0101d",
        "\u0628\u06a9\u0631\u0622\u0628\u0627\u062f"
    ],
    "name:swe_x_preferred":[
        "Baker\u0101b\u0101d"
    ],
    "wof:name":"Bakerabad",
    "wof:placetype":"locality"
},
  "geometry": {"coordinates":[47.33179000000001,35.10739],"type":"Point"}
}