{
  "type": "Feature",
  "properties": {
    "gn:admin1_code":"7.0",
    "gn:asciiname":"Dindarlu",
    "gn:country_code":"IR",
    "gn:dem":1398,
    "gn:feature_class":"P",
    "gn:feature_code":"PPL",
    "gn:name":"D\u012bnd\u0101rl\u016b",
    "gn:population":0,
    "gn:timezone":"Asia/Tehran",
    "iso:country":"IR",
    "name:ara_x_preferred":[
        "\u062f\u064a\u0646\u062f\u0627\u0631\u0644\u0648"
    ],
    "name:fas_x_preferred":[
        "\u062f\u06cc\u0646\u062f\u0627\u0631\u0644\u0648"
    ],
    "name:fas_x_variant":[
        "D\u012bnd\u0101rl\u016b"
    ],
    "name:msa_x_preferred":[
        "Dindarlu"
    ],
    "name:und_x_variant":[
        "Dindarloo"
    ],
    "wof:name":"Dindarlu",
    "wof:placetype":"locality"
},
  "geometry": {"coordinates":[54.11786,28.92511],"type":"Point"}
}