{
  "type": "Feature",
  "properties": {
    "gn:admin1_code":"7",
    "gn:asciiname":"Mina",
    "gn:country_code":"IR",
    "gn:dem":543,
    "gn:feature_class":"P",
    "gn:feature_code":"PPL",
    "gn:name":"M\u012bn\u0101",
    "gn:population":0,
    "gn:timezone":"Asia/Tehran",
    "iso:country":"IR",
    "name:fas_x_preferred":[
        "\u0645\u06cc\u0646\u0627"
    ],
    "name:fas_x_variant":[
        "M\u012bn\u0101"
    ],
    "name:msa_x_preferred":[
        "Mina"
    ],
    "wof:name":"Mina",
    "wof:placetype":"locality"
},
  "geometry": {"coordinates":[53.166,27.7831],"type":"Point"}
}