{
  "type": "Feature",
  "properties": {
    "gn:admin1_code":"35",
    "gn:asciiname":"Varmatan",
    "gn:country_code":"IR",
    "gn:dem":11,
    "gn:feature_class":"P",
    "gn:feature_code":"PPL",
    "gn:name":"Varmat\u0101n",
    "gn:population":0,
    "gn:timezone":"Asia/Tehran",
    "iso:country":"IR",
    "name:ceb_x_preferred":[
        "Varmat\u0101n"
    ],
    "name:fas_x_preferred":[
        "\u0648\u064e\u0631\u0645\u064e\u062a\u0648\u0646"
    ],
    "name:fas_x_variant":[
        "Varmat\u016bn",
        "Varmat\u0101n",
        "\u0648\u0631\u0645\u062a\u0627\u0646",
        "\u0648\u0631\u0645\u062a\u0648\u0646"
    ],
    "name:mzn_x_preferred":[
        "\u0648\u0631\u0645\u062a\u0648\u0646"
    ],
    "name:swe_x_preferred":[
        "Varmat\u0101n"
    ],
    "wof:name":"Varmatan",
    "wof:placetype":"locality"
},
  "geometry": {"coordinates":[52.56511999999999,36.49451],"type":"Point"}
}