{
  "type": "Feature",
  "properties": {
    "gn:admin1_code":"16.0",
    "gn:asciiname":"Kandeh Sureh",
    "gn:country_code":"IR",
    "gn:dem":1584,
    "gn:feature_class":"P",
    "gn:feature_code":"PPL",
    "gn:name":"Kandeh S\u016breh",
    "gn:population":0,
    "gn:timezone":"Asia/Tehran",
    "iso:country":"IR",
    "name:fas_x_preferred":[
        "\u06a9\u0646\u062f\u0647 \u0633\u0648\u0631\u0647"
    ],
    "name:fas_x_variant":[
        "Kandeh S\u016breh"
    ],
    "wof:name":"Kandeh Sureh",
    "wof:placetype":"locality"
},
  "geometry": {"coordinates":[45.8022,35.8417],"type":"Point"}
}