{
  "type": "Feature",
  "properties": {
    "gn:admin1_code":"35.0",
    "gn:asciiname":"`Ali Kola-ye Ahi",
    "gn:country_code":"IR",
    "gn:dem":7,
    "gn:feature_class":"P",
    "gn:feature_code":"PPL",
    "gn:name":"\u2018Al\u012b Kol\u0101-ye \u0100h\u012b",
    "gn:population":0,
    "gn:timezone":"Asia/Tehran",
    "iso:country":"IR",
    "name:fas_x_preferred":[
        "\u0639\u0627\u0644\u06cc \u0643\u064f\u0644\u0627\u06cc \u0622\u0647\u06cc"
    ],
    "name:fas_x_variant":[
        "\u2018\u0100l\u012b Kol\u0101-ye \u0100h\u012b",
        "\u2018Al\u012b Kol\u0101-ye \u0100h\u012b",
        "\u0639\u0644\u06cc \u0643\u0644\u0627 \u0622\u0647\u06cc"
    ],
    "wof:name":"`Ali Kola-ye Ahi",
    "wof:placetype":"locality"
},
  "geometry": {"coordinates":[52.41909,36.55336],"type":"Point"}
}