{
  "type": "Feature",
  "properties": {
    "gn:admin1_code":"42",
    "gn:asciiname":"Kalateh-ye Asayeshk",
    "gn:country_code":"IR",
    "gn:dem":1024,
    "gn:feature_class":"P",
    "gn:feature_code":"PPL",
    "gn:name":"Kal\u0101teh-ye \u0100s\u0101yeshk",
    "gn:population":0,
    "gn:timezone":"Asia/Tehran",
    "iso:country":"IR",
    "name:fas_x_preferred":[
        "\u0100s\u0101sh\u012bk"
    ],
    "name:fas_x_variant":[
        "\u0622\u0633\u0627\u0634\u064a\u06a9",
        "\u06a9\u0644\u0627\u062a\u0647 \u0622\u0633\u0627\u0634\u064a\u06a9",
        "\u0622\u0633\u0627\u064a\u0634\u06a9"
    ],
    "name:und_x_variant":[
        "\u0100s\u0101yeshk",
        "Kal\u0101teh-ye \u0100s\u0101yeshk"
    ],
    "wof:name":"Kalateh-ye Asayeshk",
    "wof:placetype":"locality"
},
  "geometry": {"coordinates":[57.22098,34.02322],"type":"Point"}
}