{
  "type": "Feature",
  "properties": {
    "gn:admin1_code":"35.0",
    "gn:asciiname":"Dujman",
    "gn:country_code":"IR",
    "gn:dem":-20,
    "gn:feature_class":"P",
    "gn:feature_code":"PPL",
    "gn:name":"D\u016bjm\u0101n",
    "gn:population":0,
    "gn:timezone":"Asia/Tehran",
    "iso:country":"IR",
    "name:fas_x_preferred":[
        "\u062f\u0648\u062c\u0645\u0627\u0646"
    ],
    "name:fas_x_variant":[
        "D\u016bjm\u0101n"
    ],
    "wof:name":"Dujman",
    "wof:placetype":"locality"
},
  "geometry": {"coordinates":[51.37145,36.68655],"type":"Point"}
}