{
  "type": "Feature",
  "properties": {
    "gn:admin1_code":"34",
    "gn:asciiname":"Azad Marzabad",
    "gn:country_code":"IR",
    "gn:dem":1671,
    "gn:feature_class":"P",
    "gn:feature_code":"PPL",
    "gn:name":"\u0100z\u0101d Marz\u0101b\u0101d",
    "gn:population":0,
    "gn:timezone":"Asia/Tehran",
    "iso:country":"IR",
    "name:ara_x_preferred":[
        "\u0623\u0632\u0627\u062f \u0645\u0631\u0632 \u0623\u0628\u0627\u062f"
    ],
    "name:ceb_x_preferred":[
        "\u0100z\u0101d Marz\u0101b\u0101d"
    ],
    "name:fas_x_preferred":[
        "\u0100z\u0101d Marz\u0101b\u0101d"
    ],
    "name:fas_x_variant":[
        "\u0622\u0632\u0627\u062f \u0645\u0631\u0632 \u0622\u0628\u0627\u062f",
        "\u0627\u0632\u0627\u062f\u0645\u0631\u0632\u0622\u0628\u0627\u062f"
    ],
    "name:swe_x_preferred":[
        "\u0100z\u0101d Marz\u0101b\u0101d"
    ],
    "name:ukr_x_preferred":[
        "\u0410\u0437\u0430\u0434-\u041c\u0430\u0440\u0437\u0430\u0431\u0430\u0434"
    ],
    "name:und_x_variant":[
        "\u0622\u0632\u0627\u062f \u0645\u0631\u0632 \u0622\u0628\u0627\u062f"
    ],
    "wof:name":"Azad Marzabad",
    "wof:placetype":"locality"
},
  "geometry": {"coordinates":[49.70558,34.19326],"type":"Point"}
}