{
  "type": "Feature",
  "properties": {
    "gn:admin1_code":"1.0",
    "gn:asciiname":"Sustan-e `Olya",
    "gn:country_code":"IR",
    "gn:dem":1549,
    "gn:feature_class":"P",
    "gn:feature_code":"PPL",
    "gn:name":"S\u016bst\u0101n-e \u2018Oly\u0101",
    "gn:population":0,
    "gn:timezone":"Asia/Tehran",
    "iso:country":"IR",
    "name:fas_x_preferred":[
        "\u0633\u0648\u0633\u062a\u0627\u0646 \u0639\u0644\u06cc\u0627"
    ],
    "name:fas_x_variant":[
        "S\u016bst\u0101n-e \u2018Oly\u0101"
    ],
    "wof:name":"Sustan-e `Olya",
    "wof:placetype":"locality"
},
  "geometry": {"coordinates":[45.3828,36.4576],"type":"Point"}
}