{
  "type": "Feature",
  "properties": {
    "gn:admin1_code":"15.0",
    "gn:asciiname":"Sar Dali-ye Ja`far",
    "gn:country_code":"IR",
    "gn:dem":989,
    "gn:feature_class":"P",
    "gn:feature_code":"PPL",
    "gn:name":"Sar Dal\u012b-ye Ja\u2018far",
    "gn:population":0,
    "gn:timezone":"Asia/Tehran",
    "iso:country":"IR",
    "name:fas_x_preferred":[
        "Deh-e Ja\u2018far"
    ],
    "name:fas_x_variant":[
        "\u062f\u0647 \u062c\u0639\u0641\u0631",
        "\u0633\u0631 \u062f\u0644\u06cc \u062c\u0639\u0641\u0631",
        "\u0628\u0646\u0647 \u062c\u0639\u0641\u0631"
    ],
    "name:und_x_variant":[
        "Sar Dal\u012b-ye Ja\u2018far",
        "Boneh-ye Ja\u2018far"
    ],
    "wof:name":"Sar Dali-ye Ja`far",
    "wof:placetype":"locality"
},
  "geometry": {"coordinates":[49.72098,31.67868],"type":"Point"}
}