{
  "type": "Feature",
  "properties": {
    "gn:admin1_code":"8.0",
    "gn:asciiname":"Arbanab-e Pa'in",
    "gn:country_code":"IR",
    "gn:dem":2175,
    "gn:feature_class":"P",
    "gn:feature_code":"PPL",
    "gn:name":"Arban\u0101b-e P\u0101\u2019\u012bn",
    "gn:population":0,
    "gn:timezone":"Asia/Tehran",
    "iso:country":"IR",
    "name:fas_x_preferred":[
        "Arnab\u0101b-e P\u0101\u2018\u012bn"
    ],
    "name:fas_x_variant":[
        "\u0627\u0631\u0646\u0628\u0627\u0628 \u067e\u0627\u0626\u06cc\u0646",
        "\u0627\u0631\u0628\u0646\u0627\u0628 \u067e\u0627\u0626\u06cc\u0646"
    ],
    "name:und_x_variant":[
        "\u0627\u0631\u0646\u0628\u0627\u0628 \u067e\u0627\u0626\u06cc\u0646",
        "Arban\u0101b-e P\u0101\u2019\u012bn"
    ],
    "wof:name":"Arbanab-e Pa'in",
    "wof:placetype":"locality"
},
  "geometry": {"coordinates":[49.72482,36.88011],"type":"Point"}
}