{
  "type": "Feature",
  "properties": {
    "gn:admin1_code":"26",
    "gn:asciiname":"Pu'inak",
    "gn:country_code":"IR",
    "gn:dem":957,
    "gn:feature_class":"P",
    "gn:feature_code":"PPL",
    "gn:name":"P\u016b\u2019\u012bnak",
    "gn:population":0,
    "gn:timezone":"Asia/Tehran",
    "iso:country":"IR",
    "name:fas_x_preferred":[
        "P\u016b\u2019\u012bnak"
    ],
    "name:fas_x_variant":[
        "\u067e\u0648\u0626\u064a\u0646\u0643"
    ],
    "name:und_x_variant":[
        "\u067e\u0648\u0626\u064a\u0646\u0643"
    ],
    "wof:name":"Pu'inak",
    "wof:placetype":"locality"
},
  "geometry": {"coordinates":[51.6106,35.4026],"type":"Point"}
}