{
  "type": "Feature",
  "properties": {
    "gn:admin1_code":"36.0",
    "gn:asciiname":"Taskin",
    "gn:country_code":"IR",
    "gn:dem":2196,
    "gn:feature_class":"P",
    "gn:feature_code":"PPL",
    "gn:name":"Task\u012bn",
    "gn:population":0,
    "gn:timezone":"Asia/Tehran",
    "iso:country":"IR",
    "name:fas_x_preferred":[
        "\u062a\u0633\u06a9\u06cc\u0646"
    ],
    "name:und_x_variant":[
        "Task\u012bn"
    ],
    "wof:name":"Taskin",
    "wof:placetype":"locality"
},
  "geometry": {"coordinates":[48.78622,36.74791],"type":"Point"}
}