{
  "type": "Feature",
  "properties": {
    "gn:admin1_code":"13",
    "gn:asciiname":"Sameleh",
    "gn:country_code":"IR",
    "gn:dem":1819,
    "gn:feature_class":"P",
    "gn:feature_code":"PPL",
    "gn:name":"S\u0101meleh",
    "gn:population":0,
    "gn:timezone":"Asia/Tehran",
    "iso:country":"IR",
    "name:ceb_x_preferred":[
        "S\u0101meleh"
    ],
    "name:fas_x_preferred":[
        "\u0633\u0627\u0645\u0644\u0647"
    ],
    "name:fas_x_variant":[
        "S\u0101meleh"
    ],
    "name:und_x_variant":[
        "B\u0101qer\u0101b\u0101d S\u0101meleh",
        "B\u0101q\u012br\u0101b\u0101d",
        "S\u0101melah"
    ],
    "wof:name":"Sameleh",
    "wof:placetype":"locality"
},
  "geometry": {"coordinates":[47.1828,34.8916],"type":"Point"}
}