{
  "type": "Feature",
  "properties": {
    "gn:admin1_code":"13",
    "gn:asciiname":"Changizah",
    "gn:country_code":"IR",
    "gn:dem":2030,
    "gn:feature_class":"P",
    "gn:feature_code":"PPL",
    "gn:name":"Chang\u012bzah",
    "gn:population":0,
    "gn:timezone":"Asia/Tehran",
    "iso:country":"IR",
    "name:ceb_x_preferred":[
        "Chang\u012bzah"
    ],
    "name:fas_x_preferred":[
        "\u0686\u0646\u06af\u06cc\u0632\u0647"
    ],
    "name:fas_x_variant":[
        "Chang\u012bzah"
    ],
    "name:swe_x_preferred":[
        "Chang\u012bzah"
    ],
    "wof:name":"Changizah",
    "wof:placetype":"locality"
},
  "geometry": {"coordinates":[47.1366,34.8372],"type":"Point"}
}