{
  "type": "Feature",
  "properties": {
    "gn:admin1_code":"33",
    "gn:asciiname":"Sowma`eh",
    "gn:country_code":"IR",
    "gn:dem":1874,
    "gn:feature_class":"P",
    "gn:feature_code":"PPL",
    "gn:name":"\u015eowma\u2018eh",
    "gn:population":0,
    "gn:timezone":"Asia/Tehran",
    "iso:country":"IR",
    "name:fas_x_preferred":[
        "\u0635\u0648\u0645\u0639\u0647"
    ],
    "name:fas_x_variant":[
        "\u015eowme\u2018eh-ye Sang",
        "\u015eowma\u2018eh"
    ],
    "wof:name":"Sowma`eh",
    "wof:placetype":"locality"
},
  "geometry": {"coordinates":[47.0428,37.5718],"type":"Point"}
}