{
  "type": "Feature",
  "properties": {
    "gn:admin1_code":"23",
    "gn:asciiname":"Kalhu",
    "gn:country_code":"IR",
    "gn:dem":1059,
    "gn:feature_class":"P",
    "gn:feature_code":"PPL",
    "gn:name":"Kalh\u016b",
    "gn:population":0,
    "gn:timezone":"Asia/Tehran",
    "iso:country":"IR",
    "name:fas_x_preferred":[
        "\u06a9\u0644\u0647\u0648 \u0633\u0641\u0644\u06cc"
    ],
    "name:fas_x_variant":[
        "Koleh H\u016b-ye Sofl\u00e1",
        "\u06a9\u0644\u0647\u0648"
    ],
    "name:und_x_variant":[
        "Koleh H\u016b",
        "Kalh\u016b-ye Sofl\u00e1",
        "Kalh\u016b"
    ],
    "wof:name":"Kalhu",
    "wof:placetype":"locality"
},
  "geometry": {"coordinates":[47.81187,33.6652],"type":"Point"}
}