{
  "type": "Feature",
  "properties": {
    "gn:admin1_code":"26",
    "gn:asciiname":"Rasanan",
    "gn:country_code":"IR",
    "gn:dem":1901,
    "gn:feature_class":"P",
    "gn:feature_code":"PPL",
    "gn:name":"Rasan\u0101n",
    "gn:population":0,
    "gn:timezone":"Asia/Tehran",
    "iso:country":"IR",
    "name:ceb_x_preferred":[
        "Rasan\u0101n"
    ],
    "name:fas_x_preferred":[
        "\u0631\u0633\u0646\u0627\u0646"
    ],
    "name:fas_x_variant":[
        "Rasan\u0101n"
    ],
    "name:swe_x_preferred":[
        "Rasan\u0101n"
    ],
    "wof:name":"Rasanan",
    "wof:placetype":"locality"
},
  "geometry": {"coordinates":[51.7558,35.8022],"type":"Point"}
}