{
  "type": "Feature",
  "properties": {
    "gn:admin1_code":"41.0",
    "gn:asciiname":"Shurab",
    "gn:country_code":"IR",
    "gn:dem":1548,
    "gn:feature_class":"P",
    "gn:feature_code":"PPL",
    "gn:name":"Sh\u016br\u0101b",
    "gn:population":0,
    "gn:timezone":"Asia/Tehran",
    "iso:country":"IR",
    "name:ceb_x_preferred":[
        "Shurab"
    ],
    "name:fas_x_preferred":[
        "\u0634\u0648\u0631\u0627\u0628"
    ],
    "name:fas_x_variant":[
        "Sh\u016br\u0101b"
    ],
    "name:swe_x_preferred":[
        "Shurab"
    ],
    "wof:name":"Shurab",
    "wof:placetype":"locality"
},
  "geometry": {"coordinates":[60.10944,33.0554],"type":"Point"}
}