{
  "type": "Feature",
  "properties": {
    "gn:admin1_code":"33",
    "gn:asciiname":"Mahalleh-ye Qara Malek",
    "gn:country_code":"IR",
    "gn:dem":1343,
    "gn:feature_class":"P",
    "gn:feature_code":"PPL",
    "gn:name":"Ma\u1e29alleh-ye Qar\u0101 Malek",
    "gn:population":0,
    "gn:timezone":"Asia/Tehran",
    "iso:country":"IR",
    "name:fas_x_preferred":[
        "\u0642\u0631\u0647 \u0645\u0644\u06a9"
    ],
    "name:fas_x_variant":[
        "\u0645\u062d\u0644\u0647 \u0642\u0631\u0627 \u0645\u0644\u06a9",
        "\u0642\u0631\u0627\u0645\u0644\u06a9"
    ],
    "name:und_x_variant":[
        "Karamyalik",
        "Zamin Qara Melk",
        "Zam\u012bn Qar\u0101 Malek",
        "Qareh Malek",
        "Ma\u1e29alleh-ye Qar\u0101 Malek",
        "Qar\u0101malek"
    ],
    "wof:name":"Mahalleh-ye Qara Malek",
    "wof:placetype":"locality"
},
  "geometry": {"coordinates":[46.2196,38.0918],"type":"Point"}
}