{
  "type": "Feature",
  "properties": {
    "gn:admin1_code":"11",
    "gn:asciiname":"Baragan",
    "gn:country_code":"IR",
    "gn:dem":538,
    "gn:feature_class":"P",
    "gn:feature_code":"PPL",
    "gn:name":"Bar\u0101g\u0101n",
    "gn:population":0,
    "gn:timezone":"Asia/Tehran",
    "iso:country":"IR",
    "wof:name":"Baragan",
    "wof:placetype":"locality"
},
  "geometry": {"coordinates":[58.82056,26.44056],"type":"Point"}
}