{
  "type": "Feature",
  "properties": {
    "gn:admin1_code":"15",
    "gn:asciiname":"Saraj od Din",
    "gn:cc2":"IR",
    "gn:country_code":"IR",
    "gn:dem":76,
    "gn:feature_class":"P",
    "gn:feature_code":"PPL",
    "gn:name":"Sar\u0101j od D\u012bn",
    "gn:population":0,
    "gn:timezone":"Asia/Tehran",
    "iso:country":"IR",
    "name:fas_x_preferred":[
        "Sar\u0101j od D\u012bn"
    ],
    "name:und_x_variant":[
        "Kondek-e Yek",
        "Kondek-e Khanjar"
    ],
    "wof:name":"Saraj od Din",
    "wof:placetype":"locality"
},
  "geometry": {"coordinates":[49.36667,31.47306],"type":"Point"}
}