{
  "type": "Feature",
  "properties": {
    "gn:admin1_code":"35.0",
    "gn:asciiname":"Chopun Boneh",
    "gn:country_code":"IR",
    "gn:dem":-18,
    "gn:feature_class":"P",
    "gn:feature_code":"PPL",
    "gn:name":"Chop\u016bn Boneh",
    "gn:population":0,
    "gn:timezone":"Asia/Tehran",
    "iso:country":"IR",
    "name:fas_x_preferred":[
        "Chop\u016bn Boneh"
    ],
    "name:fas_x_variant":[
        "\u0686\u067e\u0648\u0646 \u0628\u0646\u0647"
    ],
    "wof:name":"Chopun Boneh",
    "wof:placetype":"locality"
},
  "geometry": {"coordinates":[52.70107,36.64722],"type":"Point"}
}