{
  "type": "Feature",
  "properties": {
    "gn:admin1_code":"8.0",
    "gn:asciiname":"Zileh Huni",
    "gn:country_code":"IR",
    "gn:dem":1815,
    "gn:feature_class":"P",
    "gn:feature_code":"PPL",
    "gn:name":"Z\u012bleh H\u016bn\u012b",
    "gn:population":0,
    "gn:timezone":"Asia/Tehran",
    "iso:country":"IR",
    "name:fas_x_preferred":[
        "\u062e\u0645\u0648\u0634\u062a"
    ],
    "name:fas_x_variant":[
        "Kham\u016bsht",
        "\u0632\u06cc\u0644\u0647 \u0647\u0648\u0646\u06cc"
    ],
    "name:und_x_variant":[
        "Z\u012bleh H\u016bn\u012b"
    ],
    "wof:name":"Zileh Huni",
    "wof:placetype":"locality"
},
  "geometry": {"coordinates":[48.6801,37.6691],"type":"Point"}
}