{
  "type": "Feature",
  "properties": {
    "gn:admin1_code":"35.0",
    "gn:asciiname":"Varpam",
    "gn:country_code":"IR",
    "gn:dem":1593,
    "gn:feature_class":"P",
    "gn:feature_code":"PPL",
    "gn:name":"Varp\u0101m",
    "gn:population":0,
    "gn:timezone":"Asia/Tehran",
    "iso:country":"IR",
    "name:ceb_x_preferred":[
        "Varp\u0101m"
    ],
    "name:fas_x_preferred":[
        "Varf\u0101m"
    ],
    "name:fas_x_variant":[
        "Varn\u0101m",
        "\u0648\u064e\u0631\u0646\u0627\u0645",
        "Varp\u0101m",
        "\u0648\u0631\u067e\u0627\u0645",
        "\u0648\u0631\u0641\u0627\u0645"
    ],
    "name:swe_x_preferred":[
        "Varp\u0101m"
    ],
    "name:und_x_variant":[
        "Varp\u0101m",
        "\u0648\u0631\u0641\u0627\u0645",
        "\u0648\u0631\u067e\u0627\u0645"
    ],
    "wof:name":"Varpam",
    "wof:placetype":"locality"
},
  "geometry": {"coordinates":[53.88856,36.48],"type":"Point"}
}