{
  "type": "Feature",
  "properties": {
    "gn:admin1_code":"35",
    "gn:asciiname":"Hari Kandeh-e Pa'in",
    "gn:country_code":"IR",
    "gn:dem":10,
    "gn:feature_class":"P",
    "gn:feature_code":"PPL",
    "gn:name":"Har\u012b Kandeh-e P\u0101\u2019\u012bn",
    "gn:population":0,
    "gn:timezone":"Asia/Tehran",
    "iso:country":"IR",
    "name:fas_x_preferred":[
        "\u0647\u064e\u0631\u06cc \u0643\u064e\u0646\u062f\u0650\u0647"
    ],
    "name:fas_x_variant":[
        "Har\u012b Kandeh",
        "Har\u012b Kandeh-e P\u0101\u2019\u012bn",
        "\u0647\u0631\u06cc \u0643\u0646\u062f\u0647 \u067e\u0627\u0626\u06cc\u0646",
        "\u0647\u0631\u06cc\u200c\u06a9\u0646\u062f\u0647"
    ],
    "name:mzn_x_preferred":[
        "\u0647\u0631\u06cc\u200c\u06a9\u0646\u062f\u0647"
    ],
    "wof:name":"Hari Kandeh-e Pa'in",
    "wof:placetype":"locality"
},
  "geometry": {"coordinates":[52.71805,36.49548],"type":"Point"}
}