{
  "type": "Feature",
  "properties": {
    "gn:admin1_code":"0",
    "gn:asciiname":"Morad Mardag",
    "gn:country_code":"IR",
    "gn:dem":1362,
    "gn:feature_class":"P",
    "gn:feature_code":"PPL",
    "gn:name":"Mor\u0101d Mardag",
    "gn:population":0,
    "gn:timezone":"Asia/Tehran",
    "iso:country":"IR",
    "name:fas_x_preferred":[
        "\u0645\u0631\u0627\u062f \u0645\u0631\u062f\u06af"
    ],
    "name:fas_x_variant":[
        "Mor\u0101d Mardag"
    ],
    "wof:name":"Morad Mardag",
    "wof:placetype":"locality"
},
  "geometry": {"coordinates":[57.8204,26.8453],"type":"Point"}
}