{
  "type": "Feature",
  "properties": {
    "gn:admin1_code":"15.0",
    "gn:asciiname":"Hoseyniyeh-ye Khezayer",
    "gn:country_code":"IR",
    "gn:dem":30,
    "gn:feature_class":"P",
    "gn:feature_code":"PPL",
    "gn:name":"\u1e28oseyn\u012byeh-ye Khe\u1e95ayer",
    "gn:population":0,
    "gn:timezone":"Asia/Tehran",
    "iso:country":"IR",
    "name:fas_x_preferred":[
        "\u062d\u0633\u06cc\u0646\u06cc\u0647 \u062e\u0632\u06cc\u0631"
    ],
    "name:fas_x_variant":[
        "\u1e28oseyn\u012byeh-ye Khaz\u012br",
        "\u1e28oseyn\u012byeh-ye Khe\u1e95ayer",
        "\u062d\u0633\u06cc\u0646\u06cc\u0647 \u062e\u0636\u06cc\u0631"
    ],
    "wof:name":"Hoseyniyeh-ye Khezayer",
    "wof:placetype":"locality"
},
  "geometry": {"coordinates":[49.4275,30.93764],"type":"Point"}
}