{
  "type": "Feature",
  "properties": {
    "gn:admin1_code":"33",
    "gn:asciiname":"Serajar",
    "gn:country_code":"IR",
    "gn:dem":564,
    "gn:feature_class":"P",
    "gn:feature_code":"PPL",
    "gn:name":"Ser\u0101jar",
    "gn:population":0,
    "gn:timezone":"Asia/Tehran",
    "iso:country":"IR",
    "name:fas_x_preferred":[
        "\u0633\u0648\u0631\u0627\u062c\u064e\u0631"
    ],
    "name:fas_x_variant":[
        "\u0633\u0631\u0627\u062c\u0631",
        "S\u016br\u0101jar",
        "Ser\u0101jar"
    ],
    "wof:name":"Serajar",
    "wof:placetype":"locality"
},
  "geometry": {"coordinates":[47.2489,39.1106],"type":"Point"}
}