{
  "type": "Feature",
  "properties": {
    "gn:admin1_code":"44",
    "gn:asciiname":"Dangizak",
    "gn:country_code":"IR",
    "gn:dem":1209,
    "gn:feature_class":"P",
    "gn:feature_code":"PPL",
    "gn:name":"Dang\u012bzak",
    "gn:population":0,
    "gn:timezone":"Asia/Tehran",
    "iso:country":"IR",
    "name:fas_x_preferred":[
        "\u062f\u0646\u06af\u064a\u0632\u06a9"
    ],
    "name:fas_x_variant":[
        "Dang\u012bzak",
        "\u062f\u0646\u06af\u06cc\u0632\u06a9"
    ],
    "name:msa_x_preferred":[
        "Dangizak"
    ],
    "name:rus_x_preferred":[
        "\u0414\u0435\u043d\u0433\u0438\u0437\u0435\u043a"
    ],
    "wof:name":"Dangizak",
    "wof:placetype":"locality"
},
  "geometry": {"coordinates":[50.6378,35.9301],"type":"Point"}
}