{
  "type": "Feature",
  "properties": {
    "gn:admin1_code":"29",
    "gn:asciiname":"Shekarabad",
    "gn:cc2":"IR",
    "gn:country_code":"IR",
    "gn:dem":416,
    "gn:feature_class":"P",
    "gn:feature_code":"PPL",
    "gn:name":"Shekar\u0101b\u0101d",
    "gn:population":0,
    "gn:timezone":"Asia/Tehran",
    "iso:country":"IR",
    "name:ara_x_preferred":[
        "\u0634\u0643\u0631 \u0623\u0628\u0627\u062f"
    ],
    "name:fas_x_preferred":[
        "Shekar\u0101b\u0101d"
    ],
    "name:fas_x_variant":[
        "\u0634\u06a9\u0631\u0622\u0628\u0627\u062f"
    ],
    "name:und_x_variant":[
        "Shokr\u0101b\u0101d"
    ],
    "wof:name":"Shekarabad",
    "wof:placetype":"locality"
},
  "geometry": {"coordinates":[57.37833000000001,27.65139000000001],"type":"Point"}
}