{
  "type": "Feature",
  "properties": {
    "gn:admin1_code":"15",
    "gn:asciiname":"Tang-e Div-e Kashgeli",
    "gn:country_code":"IR",
    "gn:dem":1117,
    "gn:feature_class":"P",
    "gn:feature_code":"PPL",
    "gn:name":"Tang-e D\u012bv-e K\u0101shgel\u012b",
    "gn:population":0,
    "gn:timezone":"Asia/Tehran",
    "iso:country":"IR",
    "name:fas_x_preferred":[
        "Tang-e D\u012bv-e K\u0101shgel\u012b"
    ],
    "wof:name":"Tang-e Div-e Kashgeli",
    "wof:placetype":"locality"
},
  "geometry": {"coordinates":[49.78389,32.04361],"type":"Point"}
}