{
  "type": "Feature",
  "properties": {
    "gn:admin1_code":"3",
    "gn:asciiname":"Darreh Shur",
    "gn:country_code":"IR",
    "gn:dem":981,
    "gn:feature_class":"P",
    "gn:feature_code":"PPL",
    "gn:name":"Darreh Sh\u016br",
    "gn:population":0,
    "gn:timezone":"Asia/Tehran",
    "iso:country":"IR",
    "name:fas_x_preferred":[
        "Darreh Sh\u016br"
    ],
    "name:fas_x_variant":[
        "Darreh S\u016br",
        "\u062f\u064e\u0631\u0650\u0651\u0647 \u0633\u0648\u0631",
        "\u062f\u0631\u0647 \u0634\u0648\u0631"
    ],
    "wof:name":"Darreh Shur",
    "wof:placetype":"locality"
},
  "geometry": {"coordinates":[50.42865,31.57973],"type":"Point"}
}