{
  "type": "Feature",
  "properties": {
    "gn:admin1_code":"33",
    "gn:asciiname":"Paralar",
    "gn:country_code":"IR",
    "gn:dem":1989,
    "gn:feature_class":"P",
    "gn:feature_code":"PPL",
    "gn:name":"P\u0101r\u0101l\u0101r",
    "gn:population":0,
    "gn:timezone":"Asia/Tehran",
    "iso:country":"IR",
    "name:ceb_x_preferred":[
        "P\u0101r\u0101l\u0101r"
    ],
    "name:fas_x_preferred":[
        "\u067e\u0627\u0631\u0627\u0644\u0627\u0631"
    ],
    "name:fas_x_variant":[
        "P\u0101r\u0101l\u0101r"
    ],
    "name:msa_x_preferred":[
        "Paralar"
    ],
    "name:swe_x_preferred":[
        "P\u0101r\u0101l\u0101r"
    ],
    "wof:name":"Paralar",
    "wof:placetype":"locality"
},
  "geometry": {"coordinates":[46.7315,37.1543],"type":"Point"}
}