{
  "type": "Feature",
  "properties": {
    "gn:admin1_code":"5",
    "gn:asciiname":"Tall Movizi",
    "gn:country_code":"IR",
    "gn:dem":776,
    "gn:feature_class":"P",
    "gn:feature_code":"PPL",
    "gn:name":"Tall Mov\u012bz\u012b",
    "gn:population":0,
    "gn:timezone":"Asia/Tehran",
    "iso:country":"IR",
    "name:fas_x_preferred":[
        "Tall Mov\u012bz\u012b"
    ],
    "name:fas_x_variant":[
        "\u062a\u0644 \u0645\u0648\u064a\u0632\u06cc"
    ],
    "name:und_x_variant":[
        "\u062a\u0644 \u0645\u0648\u064a\u0632\u06cc"
    ],
    "wof:name":"Tall Movizi",
    "wof:placetype":"locality"
},
  "geometry": {"coordinates":[51.1873,30.34294],"type":"Point"}
}