{
  "type": "Feature",
  "properties": {
    "gn:admin1_code":"29",
    "gn:asciiname":"Gowd Owrsu",
    "gn:country_code":"IR",
    "gn:dem":1613,
    "gn:feature_class":"P",
    "gn:feature_code":"PPL",
    "gn:name":"Gowd Owrs\u016b",
    "gn:population":0,
    "gn:timezone":"Asia/Tehran",
    "iso:country":"IR",
    "name:fas_x_preferred":[
        "Gowd Owrs\u016b"
    ],
    "wof:name":"Gowd Owrsu",
    "wof:placetype":"locality"
},
  "geometry": {"coordinates":[57.78333000000001,28.96667],"type":"Point"}
}