{
  "type": "Feature",
  "properties": {
    "gn:admin1_code":"33.0",
    "gn:asciiname":"Al Warka",
    "gn:country_code":"IR",
    "gn:dem":1541,
    "gn:feature_class":"P",
    "gn:feature_code":"PPL",
    "gn:name":"Al Warka",
    "gn:population":0,
    "gn:timezone":"Asia/Tehran",
    "iso:country":"IR",
    "wof:name":"Al Warka",
    "wof:placetype":"locality"
},
  "geometry": {"coordinates":[45.29333,38.35417],"type":"Point"}
}