{
  "type": "Feature",
  "properties": {
    "gn:admin1_code":"29",
    "gn:asciiname":"Sang Kar",
    "gn:country_code":"IR",
    "gn:dem":2558,
    "gn:feature_class":"P",
    "gn:feature_code":"PPL",
    "gn:name":"Sang K\u0101r",
    "gn:population":0,
    "gn:timezone":"Asia/Tehran",
    "iso:country":"IR",
    "name:ara_x_preferred":[
        "\u0634\u0646\u063a \u0643\u0631"
    ],
    "name:fas_x_preferred":[
        "\u0633\u0646\u06af \u06a9\u0627\u0631"
    ],
    "name:fas_x_variant":[
        "Sang K\u0101r",
        "\u0633\u0646\u06af \u06a9\u0631"
    ],
    "name:und_x_variant":[
        "Sang-e Kar",
        "Sangar"
    ],
    "wof:name":"Sang Kar",
    "wof:placetype":"locality"
},
  "geometry": {"coordinates":[56.6435,29.3554],"type":"Point"}
}