{
  "type": "Feature",
  "properties": {
    "gn:admin1_code":"11",
    "gn:asciiname":"Hesar",
    "gn:country_code":"IR",
    "gn:dem":29,
    "gn:feature_class":"P",
    "gn:feature_code":"PPL",
    "gn:name":"\u1e28e\u015f\u0101r",
    "gn:population":0,
    "gn:timezone":"Asia/Tehran",
    "iso:country":"IR",
    "name:fas_x_preferred":[
        "\u062d\u064e\u0635\u0627\u0631"
    ],
    "name:fas_x_variant":[
        "\u1e28e\u015f\u0101r",
        "\u062d\u0635\u0627\u0631"
    ],
    "name:msa_x_preferred":[
        "Hesar"
    ],
    "name:und_x_variant":[
        "\u1e28a\u015f\u0101r",
        "\u062d\u0635\u0627\u0631"
    ],
    "wof:name":"Hesar",
    "wof:placetype":"locality"
},
  "geometry": {"coordinates":[58.17385,25.79025],"type":"Point"}
}