{
  "type": "Feature",
  "properties": {
    "gn:admin1_code":"35.0",
    "gn:asciiname":"Chala Sar",
    "gn:country_code":"IR",
    "gn:dem":34,
    "gn:feature_class":"P",
    "gn:feature_code":"PPL",
    "gn:name":"Chal\u0101 Sar",
    "gn:population":0,
    "gn:timezone":"Asia/Tehran",
    "iso:country":"IR",
    "name:ceb_x_preferred":[
        "Chal\u0101 Sar"
    ],
    "name:fas_x_preferred":[
        "Chal\u0101 Sar"
    ],
    "name:fas_x_variant":[
        "\u0686\u0644\u0627 \u0633\u0631",
        "\u0686\u0644\u0627\u0633\u0631"
    ],
    "name:swe_x_preferred":[
        "Chal\u0101 Sar"
    ],
    "wof:name":"Chala Sar",
    "wof:placetype":"locality"
},
  "geometry": {"coordinates":[50.79059,36.80231],"type":"Point"}
}