{
  "type": "Feature",
  "properties": {
    "gn:admin1_code":"22.0",
    "gn:asciiname":"Dehnow",
    "gn:country_code":"IR",
    "gn:dem":10,
    "gn:feature_class":"P",
    "gn:feature_code":"PPL",
    "gn:name":"Dehnow",
    "gn:population":0,
    "gn:timezone":"Asia/Tehran",
    "iso:country":"IR",
    "name:fas_x_preferred":[
        "\u062f\u0647 \u0646\u0648"
    ],
    "wof:name":"Dehnow",
    "wof:placetype":"locality"
},
  "geometry": {"coordinates":[51.0326,28.898],"type":"Point"}
}