{
  "type": "Feature",
  "properties": {
    "gn:admin1_code":"35",
    "gn:asciiname":"Dehkhoda",
    "gn:country_code":"IR",
    "gn:dem":870,
    "gn:feature_class":"P",
    "gn:feature_code":"PPL",
    "gn:name":"Dehkhod\u0101",
    "gn:population":0,
    "gn:timezone":"Asia/Tehran",
    "iso:country":"IR",
    "name:fas_x_preferred":[
        "\u062f\u0647\u062e\u062f\u0627"
    ],
    "name:fas_x_variant":[
        "Dehkhod\u0101"
    ],
    "wof:name":"Dehkhoda",
    "wof:placetype":"locality"
},
  "geometry": {"coordinates":[53.04487,36.02338],"type":"Point"}
}