{
  "type": "Feature",
  "properties": {
    "gn:admin1_code":"42",
    "gn:asciiname":"Dust Mohammad Beyg",
    "gn:country_code":"IR",
    "gn:dem":844,
    "gn:feature_class":"P",
    "gn:feature_code":"PPL",
    "gn:name":"D\u016bst Mo\u1e29ammad Beyg",
    "gn:population":0,
    "gn:timezone":"Asia/Tehran",
    "iso:country":"IR",
    "name:fas_x_preferred":[
        "D\u016bst Mo\u1e29ammad Beyg"
    ],
    "name:fas_x_variant":[
        "\u062f\u0648\u0633\u062a \u0645\u062d\u0645\u062f \u0628\u06cc\u06af"
    ],
    "wof:name":"Dust Mohammad Beyg",
    "wof:placetype":"locality"
},
  "geometry": {"coordinates":[58.60323,37.66466],"type":"Point"}
}