{
  "type": "Feature",
  "properties": {
    "gn:admin1_code":"10",
    "gn:asciiname":"Rakas",
    "gn:country_code":"IR",
    "gn:dem":111,
    "gn:feature_class":"P",
    "gn:feature_code":"PPL",
    "gn:name":"Rak\u0101s",
    "gn:population":0,
    "gn:timezone":"Asia/Tehran",
    "iso:country":"IR",
    "name:fas_x_preferred":[
        "Rak\u0101s"
    ],
    "name:fas_x_variant":[
        "\u0631\u064e\u0643\u0627\u0633"
    ],
    "wof:name":"Rakas",
    "wof:placetype":"locality"
},
  "geometry": {"coordinates":[47.50278,32.48417],"type":"Point"}
}