{
  "type": "Feature",
  "properties": {
    "gn:admin1_code":"33",
    "gn:asciiname":"Fathollah Bolaghi",
    "gn:country_code":"IR",
    "gn:dem":1635,
    "gn:feature_class":"P",
    "gn:feature_code":"PPL",
    "gn:name":"Fat\u1e29oll\u0101h Bol\u0101gh\u012b",
    "gn:population":0,
    "gn:timezone":"Asia/Tehran",
    "iso:country":"IR",
    "name:fas_x_preferred":[
        "\u0641\u062a\u062d \ufdf2 \u0628\u0644\u0627\u063a\u06cc"
    ],
    "name:fas_x_variant":[
        "Fat\u1e29oll\u0101h Bol\u0101gh\u012b",
        "\u0641\u062a\u062d\u200c\u0627\u0644\u0647 \u0628\u0644\u0627\u063a\u06cc"
    ],
    "name:msa_x_preferred":[
        "Fathollah Bolaghi"
    ],
    "wof:name":"Fathollah Bolaghi",
    "wof:placetype":"locality"
},
  "geometry": {"coordinates":[46.50005,37.14198],"type":"Point"}
}