{
  "type": "Feature",
  "properties": {
    "gn:admin1_code":"7",
    "gn:asciiname":"Tir Afjan",
    "gn:country_code":"IR",
    "gn:dem":1226,
    "gn:feature_class":"P",
    "gn:feature_code":"PPL",
    "gn:name":"T\u012br Afj\u0101n",
    "gn:population":0,
    "gn:timezone":"Asia/Tehran",
    "iso:country":"IR",
    "name:fas_x_preferred":[
        "\u062a\u06cc\u0631 \u0627\u0641\u062c\u0627\u0646"
    ],
    "name:fas_x_variant":[
        "T\u012br Afj\u0101n",
        "\u062a\u06cc\u0631\u0627\u0641\u062c\u0627\u0646"
    ],
    "name:msa_x_preferred":[
        "Tir Afjan"
    ],
    "name:und_x_variant":[
        "T\u012bramj\u0101n"
    ],
    "wof:name":"Tir Afjan",
    "wof:placetype":"locality"
},
  "geometry": {"coordinates":[53.0169,28.7147],"type":"Point"}
}