{
  "type": "Feature",
  "properties": {
    "gn:admin1_code":"33.0",
    "gn:asciiname":"Chakheyrlu",
    "gn:country_code":"IR",
    "gn:dem":396,
    "gn:feature_class":"P",
    "gn:feature_code":"PPL",
    "gn:name":"Ch\u0101kheyrl\u016b",
    "gn:population":0,
    "gn:timezone":"Asia/Tehran",
    "iso:country":"IR",
    "name:fas_x_preferred":[
        "\u0686\u0627\u062e\u06cc\u0631\u0644\u0648"
    ],
    "name:fas_x_variant":[
        "Ch\u0101kheyrl\u016b"
    ],
    "wof:name":"Chakheyrlu",
    "wof:placetype":"locality"
},
  "geometry": {"coordinates":[47.4621,39.2506],"type":"Point"}
}