{
  "type": "Feature",
  "properties": {
    "gn:admin1_code":"5",
    "gn:asciiname":"Dishmuk",
    "gn:country_code":"IR",
    "gn:dem":1722,
    "gn:feature_class":"P",
    "gn:feature_code":"PPL",
    "gn:name":"D\u012bshm\u016bk",
    "gn:population":0,
    "gn:timezone":"Asia/Tehran",
    "iso:country":"IR",
    "name:fas_x_preferred":[
        "\u062f\u064a\u0634\u0645\u0648\u06a9"
    ],
    "name:fas_x_variant":[
        "\u062f\u064a\u0634\u0645\u064f\u0651\u0643",
        "D\u012bshmok",
        "D\u012bshm\u016bk",
        "\u062f\u06cc\u0634\u0645\u06a9"
    ],
    "name:und_x_variant":[
        "D\u012bshmook",
        "\u062f\u06cc\u0634\u0645\u06a9"
    ],
    "wof:name":"Dishmuk",
    "wof:placetype":"locality"
},
  "geometry": {"coordinates":[50.4011,31.29844000000001],"type":"Point"}
}