{
  "type": "Feature",
  "properties": {
    "gn:admin1_code":"37.0",
    "gn:asciiname":"Mazra`eh-ye Sazeman-e Mohammad Ja`fari",
    "gn:country_code":"IR",
    "gn:dem":47,
    "gn:feature_class":"P",
    "gn:feature_code":"PPLF",
    "gn:name":"Mazra\u2018eh-ye S\u0101zem\u0101n-e Mo\u1e29ammad Ja\u2018far\u012b",
    "gn:population":0,
    "gn:timezone":"Asia/Tehran",
    "iso:country":"IR",
    "name:fas_x_preferred":[
        "\u0645\u0632\u0631\u0639\u0647 \u0633\u0627\u0632\u0645\u0627\u0646 \u0645\u062d\u0645\u062f \u062c\u0639\u063a\u0631\u06cc"
    ],
    "name:und_x_variant":[
        "Mazra\u2018eh-ye S\u0101zem\u0101n-e Mo\u1e29ammad Ja\u2018far\u012b"
    ],
    "wof:name":"Mazra`eh-ye Sazeman-e Mohammad Ja`fari",
    "wof:placetype":"locality"
},
  "geometry": {"coordinates":[54.82305,37.00688],"type":"Point"}
}