{
  "type": "Feature",
  "properties": {
    "gn:admin1_code":"8",
    "gn:asciiname":"Khoshknowdahan",
    "gn:country_code":"IR",
    "gn:dem":45,
    "gn:feature_class":"P",
    "gn:feature_code":"PPL",
    "gn:name":"Khoshknowdah\u0101n",
    "gn:population":0,
    "gn:timezone":"Asia/Tehran",
    "iso:country":"IR",
    "name:fas_x_preferred":[
        "\u062e\u0634\u06a9\u0646\u0648\u062f\u0647\u0627\u0646"
    ],
    "name:fas_x_variant":[
        "Khoshknowdah\u0101n"
    ],
    "wof:name":"Khoshknowdahan",
    "wof:placetype":"locality"
},
  "geometry": {"coordinates":[49.2308,37.268],"type":"Point"}
}