{
  "type": "Feature",
  "properties": {
    "gn:admin1_code":"35.0",
    "gn:asciiname":"Khoshkeh Rud",
    "gn:country_code":"IR",
    "gn:dem":196,
    "gn:feature_class":"P",
    "gn:feature_code":"PPL",
    "gn:name":"Khoshkeh R\u016bd",
    "gn:population":0,
    "gn:timezone":"Asia/Tehran",
    "iso:country":"IR",
    "name:fas_x_preferred":[
        "Khomgard\u0101n"
    ],
    "name:fas_x_variant":[
        "\u062e\u0645\u06af\u0631\u062f\u0627\u0646",
        "\u062e\u0645 \u06af\u0631\u062f\u0646",
        "\u062e\u0634\u06a9\u0647 \u0631\u0648\u062f",
        "\u062e\u0645\u200c\u06af\u0631\u062f\u0646"
    ],
    "name:und_x_variant":[
        "Khom Gardan",
        "Khoshkeh R\u016bd"
    ],
    "wof:name":"Khoshkeh Rud",
    "wof:placetype":"locality"
},
  "geometry": {"coordinates":[50.85396,36.73092000000001],"type":"Point"}
}