{
  "type": "Feature",
  "properties": {
    "gn:admin1_code":"38",
    "gn:asciiname":"Darband",
    "gn:country_code":"IR",
    "gn:dem":1274,
    "gn:feature_class":"P",
    "gn:feature_code":"PPL",
    "gn:name":"Darband",
    "gn:population":0,
    "gn:timezone":"Asia/Tehran",
    "iso:country":"IR",
    "name:fas_x_preferred":[
        "\u062f\u0631\u0628\u0646\u062f"
    ],
    "name:und_x_variant":[
        "Darband"
    ],
    "wof:name":"Darband",
    "wof:placetype":"locality"
},
  "geometry": {"coordinates":[50.24762,36.58042],"type":"Point"}
}