{
  "type": "Feature",
  "properties": {
    "gn:admin1_code":"29.0",
    "gn:asciiname":"Ikmachi",
    "gn:country_code":"IR",
    "gn:dem":797,
    "gn:feature_class":"P",
    "gn:feature_code":"PPLL",
    "gn:name":"\u012akm\u0101ch\u012b",
    "gn:population":0,
    "gn:timezone":"Asia/Tehran",
    "iso:country":"IR",
    "name:fas_x_preferred":[
        "\u0627\u06cc\u06a9\u0645\u0627\u0686\u06cc"
    ],
    "name:und_x_variant":[
        "\u012akm\u0101ch\u012b"
    ],
    "wof:name":"Ikmachi",
    "wof:placetype":"locality"
},
  "geometry": {"coordinates":[58.89489,28.00639],"type":"Point"}
}