{
  "type": "Feature",
  "properties": {
    "gn:admin1_code":"8",
    "gn:asciiname":"Gol Bijar",
    "gn:country_code":"IR",
    "gn:dem":366,
    "gn:feature_class":"P",
    "gn:feature_code":"PPL",
    "gn:name":"Gol B\u012bj\u0101r",
    "gn:population":0,
    "gn:timezone":"Asia/Tehran",
    "iso:country":"IR",
    "name:fas_x_preferred":[
        "\u06af\u064f\u0644 \u0628\u064a\u062c\u0627\u0631"
    ],
    "name:fas_x_variant":[
        "Gol B\u012bj\u0101r"
    ],
    "name:und_x_variant":[
        "Kalabidzhar"
    ],
    "wof:name":"Gol Bijar",
    "wof:placetype":"locality"
},
  "geometry": {"coordinates":[49.73333,37.05],"type":"Point"}
}