{
  "type": "Feature",
  "properties": {
    "gn:admin1_code":"35",
    "gn:asciiname":"Vosta Kola",
    "gn:country_code":"IR",
    "gn:dem":89,
    "gn:feature_class":"P",
    "gn:feature_code":"PPL",
    "gn:name":"Vos\u0163\u00e1 Kol\u0101",
    "gn:population":0,
    "gn:timezone":"Asia/Tehran",
    "iso:country":"IR",
    "name:fas_x_preferred":[
        "\u0648\u0633\u0637\u0649 \u0643\u0644\u0627"
    ],
    "name:fas_x_variant":[
        "Vos\u0163\u00e1 Kol\u0101",
        "Vost\u0101 Kol\u0101",
        "Vost\u0101 Kal\u0101",
        "\u0648\u064f\u0633\u062a\u0627 \u0643\u064e\u0644\u0627",
        "\u0648\u064f\u0633\u062a\u0627 \u0643\u064f\u0644\u0627",
        "\u0648\u0633\u0637\u06cc\u200c\u06a9\u0644\u0627"
    ],
    "wof:name":"Vosta Kola",
    "wof:placetype":"locality"
},
  "geometry": {"coordinates":[52.493,36.386],"type":"Point"}
}