{
  "type": "Feature",
  "properties": {
    "gn:admin1_code":"36",
    "gn:asciiname":"Cheragh Hesari",
    "gn:country_code":"IR",
    "gn:dem":1949,
    "gn:feature_class":"P",
    "gn:feature_code":"PPL",
    "gn:name":"Cher\u0101gh \u1e28e\u015f\u0101r\u012b",
    "gn:population":0,
    "gn:timezone":"Asia/Tehran",
    "iso:country":"IR",
    "name:azb_x_preferred":[
        "\u0686\u0631\u0627\u063a \u062d\u0635\u0627\u0631\u06cc"
    ],
    "name:aze_x_preferred":[
        "\u00c7\u0131raq Hasar\u0131"
    ],
    "name:ceb_x_preferred":[
        "Cher\u0101gh \u1e28e\u015f\u0101r\u012b"
    ],
    "name:fas_x_preferred":[
        "\u0686\u0631\u0627\u063a \u062d\u0635\u0627\u0631\u06cc"
    ],
    "name:fas_x_variant":[
        "Cher\u0101gh \u1e28e\u015f\u0101r\u012b"
    ],
    "name:swe_x_preferred":[
        "Cher\u0101gh \u1e28e\u015f\u0101r\u012b"
    ],
    "name:und_x_variant":[
        "Chir\u0101gh Hisari",
        "Chirag-Khissari"
    ],
    "wof:name":"Cheragh Hesari",
    "wof:placetype":"locality"
},
  "geometry": {"coordinates":[48.42706,36.18583],"type":"Point"}
}