{
  "type": "Feature",
  "properties": {
    "gn:admin1_code":"29",
    "gn:asciiname":"Salaniabad",
    "gn:country_code":"IR",
    "gn:dem":530,
    "gn:feature_class":"P",
    "gn:feature_code":"PPL",
    "gn:name":"Sal\u0101n\u012b\u0101b\u0101d",
    "gn:population":0,
    "gn:timezone":"Asia/Tehran",
    "iso:country":"IR",
    "name:fas_x_preferred":[
        "Sal\u0101n\u012b\u0101b\u0101d"
    ],
    "wof:name":"Salaniabad",
    "wof:placetype":"locality"
},
  "geometry": {"coordinates":[57.41694,27.66333],"type":"Point"}
}