{
  "type": "Feature",
  "properties": {
    "gn:admin1_code":"13",
    "gn:asciiname":"Dashtelah-ye `Olya",
    "gn:country_code":"IR",
    "gn:dem":1284,
    "gn:feature_class":"P",
    "gn:feature_code":"PPL",
    "gn:name":"Dashtelah-ye \u2018Oly\u0101",
    "gn:population":0,
    "gn:timezone":"Asia/Tehran",
    "iso:country":"IR",
    "name:fas_x_preferred":[
        "\u062f\u0634\u062a \u0644\u0647 \u0639\u0644\u06cc\u0627"
    ],
    "name:fas_x_variant":[
        "Dashtelah-ye \u2018Oly\u0101"
    ],
    "wof:name":"Dashtelah-ye `Olya",
    "wof:placetype":"locality"
},
  "geometry": {"coordinates":[47.2979,34.1976],"type":"Point"}
}