{
  "type": "Feature",
  "properties": {
    "gn:admin1_code":"15",
    "gn:asciiname":"Abeleh-ye Rahmani",
    "gn:country_code":"IR",
    "gn:dem":745,
    "gn:feature_class":"P",
    "gn:feature_code":"PPL",
    "gn:name":"\u0100beleh-ye Ra\u1e29m\u0101n\u012b",
    "gn:population":0,
    "gn:timezone":"Asia/Tehran",
    "iso:country":"IR",
    "name:fas_x_preferred":[
        "\u0100beleh-ye Ra\u1e29m\u0101n\u012b"
    ],
    "wof:name":"Abeleh-ye Rahmani",
    "wof:placetype":"locality"
},
  "geometry": {"coordinates":[49.73333,31.81667],"type":"Point"}
}