{
  "type": "Feature",
  "properties": {
    "gn:admin1_code":"37",
    "gn:asciiname":"Qal`eh Qafeh-ye Pa'in",
    "gn:country_code":"IR",
    "gn:dem":1258,
    "gn:feature_class":"P",
    "gn:feature_code":"PPL",
    "gn:name":"Qal\u2018eh Q\u0101feh-ye P\u0101\u2019\u012bn",
    "gn:population":0,
    "gn:timezone":"Asia/Tehran",
    "iso:country":"IR",
    "name:fas_x_preferred":[
        "\u0642\u0644\u0639\u0647 \u0642\u0627\u0641\u0647 \u067e\u0627\u0626\u064a\u0646"
    ],
    "name:fas_x_variant":[
        "Qal\u2018eh Q\u0101feh-ye P\u0101\u2019\u012bn",
        "\u0642\u0644\u0639\u0647 \u0642\u0627\u0641\u0647",
        "\u0642\u0644\u0639\u0647 \u0642\u0627\u0641\u0647 \u067e\u0627\u06cc\u06cc\u0646"
    ],
    "name:msa_x_preferred":[
        "Qaleh Qafeh-ye Pain"
    ],
    "name:und_x_variant":[
        "Qal\u2018eh Q\u0101feh"
    ],
    "wof:name":"Qal`eh Qafeh-ye Pa'in",
    "wof:placetype":"locality"
},
  "geometry": {"coordinates":[55.48628000000001,37.0429],"type":"Point"}
}