{
  "type": "Feature",
  "properties": {
    "gn:admin1_code":"7",
    "gn:asciiname":"Fathabad",
    "gn:country_code":"IR",
    "gn:dem":831,
    "gn:feature_class":"P",
    "gn:feature_code":"PPL",
    "gn:name":"Fat\u1e29\u0101b\u0101d",
    "gn:population":0,
    "gn:timezone":"Asia/Tehran",
    "iso:country":"IR",
    "name:aze_x_preferred":[
        "F\u0259thabad"
    ],
    "name:ceb_x_preferred":[
        "Fathabad"
    ],
    "name:fas_x_preferred":[
        "Fat\u1e29\u0101b\u0101d"
    ],
    "name:fas_x_variant":[
        "\u0641\u062a\u062d\u200c\u0622\u0628\u0627\u062f"
    ],
    "name:swe_x_preferred":[
        "Fathabad"
    ],
    "wof:name":"Fathabad",
    "wof:placetype":"locality"
},
  "geometry": {"coordinates":[54.05,28.18333],"type":"Point"}
}