{
  "type": "Feature",
  "properties": {
    "gn:admin1_code":"26",
    "gn:asciiname":"Lasem Cheshmeh-ye Pa'in",
    "gn:country_code":"IR",
    "gn:dem":1889,
    "gn:feature_class":"P",
    "gn:feature_code":"PPL",
    "gn:name":"L\u0101sem Cheshmeh-ye P\u0101\u2019\u012bn",
    "gn:population":0,
    "gn:timezone":"Asia/Tehran",
    "iso:country":"IR",
    "name:fas_x_preferred":[
        "\u0644\u0627\u0633\u0645 \u0686\u0634\u0645\u0647 \u067e\u0627\u0626\u064a\u0646"
    ],
    "name:fas_x_variant":[
        "L\u0101sem Cheshmeh-ye P\u0101\u2019\u012bn",
        "\u0644\u0627\u0633\u0645 \u0686\u0634\u0645\u0647"
    ],
    "name:und_x_variant":[
        "L\u0101sem Cheshmeh",
        "Sa\u2018\u012bd\u0101b\u0101d"
    ],
    "wof:name":"Lasem Cheshmeh-ye Pa'in",
    "wof:placetype":"locality"
},
  "geometry": {"coordinates":[52.69998,35.73394000000001],"type":"Point"}
}