{
  "type": "Feature",
  "properties": {
    "gn:admin1_code":"7",
    "gn:asciiname":"Biadeh",
    "gn:country_code":"IR",
    "gn:dem":1083,
    "gn:feature_class":"P",
    "gn:feature_code":"PPL",
    "gn:name":"B\u012b\u0101deh",
    "gn:population":0,
    "gn:timezone":"Asia/Tehran",
    "iso:country":"IR",
    "name:ara_x_preferred":[
        "\u0628\u064a\u0627\u062f\u0629"
    ],
    "name:fas_x_preferred":[
        "\u0628\u06cc\u0627\u062f\u0647"
    ],
    "name:fas_x_variant":[
        "B\u012b\u0101deh"
    ],
    "name:msa_x_preferred":[
        "Biadeh"
    ],
    "name:und_x_variant":[
        "Biy\u0101deh"
    ],
    "wof:name":"Biadeh",
    "wof:placetype":"locality"
},
  "geometry": {"coordinates":[54.4599,28.6829],"type":"Point"}
}