{
  "type": "Feature",
  "properties": {
    "gn:admin1_code":"5",
    "gn:asciiname":"Darreh-ye `Alam Kal",
    "gn:country_code":"IR",
    "gn:dem":1685,
    "gn:feature_class":"P",
    "gn:feature_code":"PPL",
    "gn:name":"Darreh-ye \u2018Alam Kal",
    "gn:population":0,
    "gn:timezone":"Asia/Tehran",
    "iso:country":"IR",
    "name:fas_x_preferred":[
        "\u062f\u064e\u0631\u0650\u0651\u06c0 \u0639\u064e\u0644\u064e\u0645 \u0643\u064e\u0644"
    ],
    "name:fas_x_variant":[
        "Darreh-ye \u2018Alam Kal"
    ],
    "wof:name":"Darreh-ye `Alam Kal",
    "wof:placetype":"locality"
},
  "geometry": {"coordinates":[51.31278,30.7425],"type":"Point"}
}