{
  "type": "Feature",
  "properties": {
    "gn:admin1_code":"40",
    "gn:asciiname":"Chah-e Tum",
    "gn:country_code":"IR",
    "gn:dem":831,
    "gn:feature_class":"P",
    "gn:feature_code":"PPLL",
    "gn:name":"Ch\u0101h-e T\u016bm",
    "gn:population":0,
    "gn:timezone":"Asia/Tehran",
    "iso:country":"IR",
    "name:fas_x_preferred":[
        "Ch\u0101h-e T\u016bm"
    ],
    "name:fas_x_variant":[
        "\u0686\u0627\u0647 \u062a\u0648\u0645",
        "\u0686\u0627\u0647 \u062a\u0645"
    ],
    "name:und_x_variant":[
        "\u0686\u0627\u0647 \u062a\u0648\u0645",
        "Ch\u0101h-e Tam"
    ],
    "wof:name":"Chah-e Tum",
    "wof:placetype":"locality"
},
  "geometry": {"coordinates":[56.90746,34.78879000000001],"type":"Point"}
}