{
  "type": "Feature",
  "properties": {
    "gn:admin1_code":"33",
    "gn:asciiname":"Qurchi Kandi",
    "gn:country_code":"IR",
    "gn:dem":1522,
    "gn:feature_class":"P",
    "gn:feature_code":"PPL",
    "gn:name":"Q\u016brch\u012b Kand\u012b",
    "gn:population":0,
    "gn:timezone":"Asia/Tehran",
    "iso:country":"IR",
    "name:fas_x_preferred":[
        "\u06af\u0648\u0631\u0650\u0647\u062a\u06cc"
    ],
    "name:fas_x_variant":[
        "G\u016breht\u012b",
        "\u0642\u0648\u0631\u0686\u06cc \u06a9\u0646\u062f\u06cc",
        "\u06af\u0631\u062c\u06cc"
    ],
    "name:und_x_variant":[
        "Q\u016brch\u012b Kand\u012b",
        "Gorj\u012b"
    ],
    "wof:name":"Qurchi Kandi",
    "wof:placetype":"locality"
},
  "geometry": {"coordinates":[47.01429,38.40236],"type":"Point"}
}