{
  "type": "Feature",
  "properties": {
    "gn:admin1_code":"29.0",
    "gn:asciiname":"`Azizabad",
    "gn:country_code":"IR",
    "gn:dem":1668,
    "gn:feature_class":"P",
    "gn:feature_code":"PPL",
    "gn:name":"\u2018Az\u012bz\u0101b\u0101d",
    "gn:population":0,
    "gn:timezone":"Asia/Tehran",
    "iso:country":"IR",
    "name:fas_x_preferred":[
        "\u0639\u0632\u06cc\u0632 \u0622\u0628\u0627\u062f"
    ],
    "name:und_x_variant":[
        "\u2018Az\u012bz\u0101b\u0101d"
    ],
    "wof:name":"`Azizabad",
    "wof:placetype":"locality"
},
  "geometry": {"coordinates":[56.57076,30.75555],"type":"Point"}
}