{
  "type": "Feature",
  "properties": {
    "gn:admin1_code":"41",
    "gn:asciiname":"Zangu",
    "gn:country_code":"IR",
    "gn:dem":1379,
    "gn:feature_class":"P",
    "gn:feature_code":"PPL",
    "gn:name":"Zang\u016b",
    "gn:population":0,
    "gn:timezone":"Asia/Tehran",
    "iso:country":"IR",
    "name:fas_x_preferred":[
        "Tolombeh-ye Qohest\u0101n-e Zang\u016b"
    ],
    "name:fas_x_variant":[
        "\u0632\u0646\u06af\u0648"
    ],
    "name:und_x_variant":[
        "Qoht\u0101n",
        "Tolombeh-ye Qohest\u0101n",
        "Zang\u016b",
        "Zanak\u016b"
    ],
    "wof:name":"Zangu",
    "wof:placetype":"locality"
},
  "geometry": {"coordinates":[58.56573,33.77766],"type":"Point"}
}