{
  "type": "Feature",
  "properties": {
    "gn:admin1_code":"33",
    "gn:asciiname":"Gal",
    "gn:country_code":"IR",
    "gn:dem":1762,
    "gn:feature_class":"P",
    "gn:feature_code":"PPL",
    "gn:name":"G\u0101l",
    "gn:population":0,
    "gn:timezone":"Asia/Tehran",
    "iso:country":"IR",
    "name:cat_x_preferred":[
        "Gal"
    ],
    "name:ceb_x_preferred":[
        "Gal"
    ],
    "name:eus_x_preferred":[
        "Gal"
    ],
    "name:fas_x_preferred":[
        "\u06a9\u0644\u0648"
    ],
    "name:fas_x_variant":[
        "Gal\u016b",
        "Kal\u016b",
        "\u06af\u0627\u0644"
    ],
    "name:fin_x_preferred":[
        "Gal"
    ],
    "name:nds_x_preferred":[
        "Gal"
    ],
    "name:nld_x_preferred":[
        "Gal"
    ],
    "name:oci_x_preferred":[
        "Gal"
    ],
    "name:pol_x_preferred":[
        "Gal"
    ],
    "name:por_x_preferred":[
        "Gal"
    ],
    "name:rus_x_preferred":[
        "Gal"
    ],
    "name:slk_x_preferred":[
        "Gal"
    ],
    "name:spa_x_preferred":[
        "Gal"
    ],
    "name:srp_x_preferred":[
        "Gal"
    ],
    "name:swe_x_preferred":[
        "Gal"
    ],
    "name:und_x_variant":[
        "Gyal",
        "Gi\u0101l",
        "Galoo",
        "G\u0101l",
        "Galow",
        "Gey\u0101l"
    ],
    "wof:name":"Gal",
    "wof:placetype":"locality"
},
  "geometry": {"coordinates":[46.4352,38.6066],"type":"Point"}
}