{
  "type": "Feature",
  "properties": {
    "gn:admin1_code":"28.0",
    "gn:asciiname":"Qal`eh `Abdollah",
    "gn:country_code":"IR",
    "gn:dem":1514,
    "gn:feature_class":"P",
    "gn:feature_code":"PPL",
    "gn:name":"Qal\u2018eh \u2018Abdoll\u0101h",
    "gn:population":0,
    "gn:timezone":"Asia/Tehran",
    "iso:country":"IR",
    "name:fas_x_preferred":[
        "\u0642\u0644\u0639\u0647 \u0639\u0628\u062f \u0627\u0644\u0644\u0651\u0647"
    ],
    "name:fas_x_variant":[
        "Qal\u2018eh \u2018Abdoll\u0101h"
    ],
    "name:und_x_variant":[
        "Qal\u2018eh-ye \u2018Abdoll\u0101h",
        "Qal\u2018eh Abdullah"
    ],
    "wof:name":"Qal`eh `Abdollah",
    "wof:placetype":"locality"
},
  "geometry": {"coordinates":[52.121,32.5586],"type":"Point"}
}