{
  "type": "Feature",
  "properties": {
    "gn:admin1_code":"40",
    "gn:asciiname":"Chah-e Chabrzadan",
    "gn:country_code":"IR",
    "gn:dem":1955,
    "gn:feature_class":"P",
    "gn:feature_code":"PPL",
    "gn:name":"Ch\u0101h-e Chabrz\u0101d\u0101n",
    "gn:population":0,
    "gn:timezone":"Asia/Tehran",
    "iso:country":"IR",
    "name:fas_x_preferred":[
        "Ch\u0101h-e Chabrz\u0101d\u0101n"
    ],
    "name:und_x_variant":[
        "Ch\u0101h-i-Ghabarz\u0101d\u0101n"
    ],
    "wof:name":"Chah-e Chabrzadan",
    "wof:placetype":"locality"
},
  "geometry": {"coordinates":[54.35,31.23333],"type":"Point"}
}