{
  "type": "Feature",
  "properties": {
    "gn:admin1_code":"1",
    "gn:asciiname":"Ag Otluq",
    "gn:country_code":"IR",
    "gn:dem":841,
    "gn:feature_class":"P",
    "gn:feature_code":"PPL",
    "gn:name":"\u0100g Otl\u016bq",
    "gn:population":0,
    "gn:timezone":"Asia/Tehran",
    "iso:country":"IR",
    "name:fas_x_preferred":[
        "\u0622\u0642 \u0627\u062a\u0644\u0648\u0642"
    ],
    "name:fas_x_variant":[
        "\u0622\u063a\u064f\u062a\u0644\u0627\u0642",
        "\u0100ghotl\u0101q",
        "\u0100g Otl\u016bq"
    ],
    "wof:name":"Ag Otluq",
    "wof:placetype":"locality"
},
  "geometry": {"coordinates":[44.9625,39.3366],"type":"Point"}
}