{
  "type": "Feature",
  "properties": {
    "gn:admin1_code":"13",
    "gn:asciiname":"Qal`eh-ye Rashid ol Saltaneh",
    "gn:country_code":"IR",
    "gn:dem":1457,
    "gn:feature_class":"P",
    "gn:feature_code":"PPL",
    "gn:name":"Qal\u2018eh-ye Rash\u012bd ol Sal\u0163aneh",
    "gn:population":0,
    "gn:timezone":"Asia/Tehran",
    "iso:country":"IR",
    "name:fas_x_preferred":[
        "\u0642\u0644\u0639\u0647 \u0631\u0634\u06cc\u062f\u0627\u0644\u0633\u0644\u0637\u0646\u0647"
    ],
    "name:fas_x_variant":[
        "Qal\u2018eh-ye Rash\u012bd os Sal\u0163aneh",
        "Qal\u2018eh-ye Rash\u012bd ol Sal\u0163aneh"
    ],
    "wof:name":"Qal`eh-ye Rashid ol Saltaneh",
    "wof:placetype":"locality"
},
  "geometry": {"coordinates":[46.2781,34.4979],"type":"Point"}
}