{
  "type": "Feature",
  "properties": {
    "gn:admin1_code":"35.0",
    "gn:asciiname":"Shirdar Khal",
    "gn:country_code":"IR",
    "gn:dem":264,
    "gn:feature_class":"P",
    "gn:feature_code":"PPL",
    "gn:name":"Sh\u012brd\u0101r Kh\u0101l",
    "gn:population":0,
    "gn:timezone":"Asia/Tehran",
    "iso:country":"IR",
    "name:fas_x_preferred":[
        "\u0634\u064a\u0631\u062f\u0627\u0631 \u062e\u0627\u0644"
    ],
    "name:fas_x_variant":[
        "Sh\u012brd\u0101r Kh\u0101l"
    ],
    "wof:name":"Shirdar Khal",
    "wof:placetype":"locality"
},
  "geometry": {"coordinates":[52.41667,36.33333],"type":"Point"}
}