{
  "type": "Feature",
  "properties": {
    "gn:admin1_code":"25",
    "gn:asciiname":"Qarah Tappeh",
    "gn:country_code":"IR",
    "gn:dem":1613,
    "gn:feature_class":"P",
    "gn:feature_code":"PPL",
    "gn:name":"Qarah Tappeh",
    "gn:population":0,
    "gn:timezone":"Asia/Tehran",
    "iso:country":"IR",
    "name:ceb_x_preferred":[
        "Qarah Tappeh"
    ],
    "name:fas_x_preferred":[
        "\u0642\u0631\u0647 \u062a\u067e\u0647"
    ],
    "name:fas_x_variant":[
        "\u0642\u0631\u0647\u200c\u062a\u067e\u0647"
    ],
    "name:swe_x_preferred":[
        "Qarah Tappeh"
    ],
    "wof:name":"Qarah Tappeh",
    "wof:placetype":"locality"
},
  "geometry": {"coordinates":[55.13511999999999,36.71359],"type":"Point"}
}