{
  "type": "Feature",
  "properties": {
    "gn:admin1_code":"7",
    "gn:asciiname":"Nasirabad",
    "gn:country_code":"IR",
    "gn:dem":839,
    "gn:feature_class":"P",
    "gn:feature_code":"PPL",
    "gn:name":"Na\u015f\u012br\u0101b\u0101d",
    "gn:population":0,
    "gn:timezone":"Asia/Tehran",
    "iso:country":"IR",
    "name:fas_x_preferred":[
        "Na\u015f\u012br\u0101b\u0101d"
    ],
    "name:fas_x_variant":[
        "\u0646\u0635\u06cc\u0631 \u0622\u0628\u0627\u062f"
    ],
    "name:und_x_variant":[
        "\u0646\u0635\u06cc\u0631 \u0622\u0628\u0627\u062f"
    ],
    "wof:name":"Nasirabad",
    "wof:placetype":"locality"
},
  "geometry": {"coordinates":[51.70441,29.56977],"type":"Point"}
}