{
  "type": "Feature",
  "properties": {
    "gn:admin1_code":"5",
    "gn:asciiname":"Sar Tang",
    "gn:country_code":"IR",
    "gn:dem":1550,
    "gn:feature_class":"P",
    "gn:feature_code":"PPL",
    "gn:name":"Sar Tang",
    "gn:population":0,
    "gn:timezone":"Asia/Tehran",
    "iso:country":"IR",
    "name:fas_x_preferred":[
        "\u0633\u064e\u0631\u062a\u064e\u0646\u06af\u0650 \u067e\u0627\u0626\u064a\u0646"
    ],
    "name:fas_x_variant":[
        "\u0633\u064e\u0631\u062a\u064e\u0646\u06af\u0650 \u0633\u064f\u0641\u0644\u064e\u0649",
        "Sartang-e P\u0101\u2019\u012bn",
        "\u0633\u0631 \u062a\u0646\u06af"
    ],
    "name:und_x_variant":[
        "Sartang-e Sofl\u00e1",
        "Sar Tang",
        "\u0633\u0631 \u062a\u0646\u06af"
    ],
    "wof:name":"Sar Tang",
    "wof:placetype":"locality"
},
  "geometry": {"coordinates":[51.31689,30.88641],"type":"Point"}
}