{
  "type": "Feature",
  "properties": {
    "gn:admin1_code":"32",
    "gn:asciiname":"Qeshlaq-e Sadeq",
    "gn:country_code":"IR",
    "gn:dem":608,
    "gn:feature_class":"P",
    "gn:feature_code":"PPL",
    "gn:name":"Qeshl\u0101q-e \u015e\u0101deq",
    "gn:population":0,
    "gn:timezone":"Asia/Tehran",
    "iso:country":"IR",
    "name:fas_x_preferred":[
        "\u0642\u0634\u0644\u0627\u0642 \u0635\u0627\u062f\u0642"
    ],
    "name:fas_x_variant":[
        "Qeshl\u0101q-e \u015e\u0101deq"
    ],
    "wof:name":"Qeshlaq-e Sadeq",
    "wof:placetype":"locality"
},
  "geometry": {"coordinates":[47.6999,39.2448],"type":"Point"}
}