{
  "type": "Feature",
  "properties": {
    "gn:admin1_code":"36",
    "gn:asciiname":"Lardeh Shur",
    "gn:country_code":"IR",
    "gn:dem":1729,
    "gn:feature_class":"P",
    "gn:feature_code":"PPL",
    "gn:name":"Lardeh Sh\u016br",
    "gn:population":0,
    "gn:timezone":"Asia/Tehran",
    "iso:country":"IR",
    "name:azb_x_preferred":[
        "\u0644\u0631\u062f\u0647 \u0634\u0648\u0631"
    ],
    "name:ceb_x_preferred":[
        "Lardeh Sh\u016br"
    ],
    "name:fas_x_preferred":[
        "\u0644\u0631\u062f\u0647 \u0634\u0648\u0631"
    ],
    "name:fas_x_variant":[
        "Lardehsh\u016br",
        "Lardeh Sh\u016br"
    ],
    "name:swe_x_preferred":[
        "Lardeh Sh\u016br"
    ],
    "name:urd_x_preferred":[
        "\u0644\u0631\u062f\u06c1 \u0634\u0648\u0631"
    ],
    "wof:name":"Lardeh Shur",
    "wof:placetype":"locality"
},
  "geometry": {"coordinates":[47.39737,36.88838],"type":"Point"}
}