{
  "type": "Feature",
  "properties": {
    "gn:admin1_code":"7",
    "gn:asciiname":"Khodabakhsh",
    "gn:country_code":"IR",
    "gn:dem":1689,
    "gn:feature_class":"P",
    "gn:feature_code":"PPL",
    "gn:name":"Khod\u0101bakhsh",
    "gn:population":0,
    "gn:timezone":"Asia/Tehran",
    "iso:country":"IR",
    "name:fas_x_preferred":[
        "Khod\u0101bakhsh"
    ],
    "wof:name":"Khodabakhsh",
    "wof:placetype":"locality"
},
  "geometry": {"coordinates":[51.45778,30.34972],"type":"Point"}
}