{
  "type": "Feature",
  "properties": {
    "gn:admin1_code":"13",
    "gn:asciiname":"Kanjur-e `Olya",
    "gn:country_code":"IR",
    "gn:dem":1362,
    "gn:feature_class":"P",
    "gn:feature_code":"PPL",
    "gn:name":"Kanj\u016br-e \u2018Oly\u0101",
    "gn:population":0,
    "gn:timezone":"Asia/Tehran",
    "iso:country":"IR",
    "name:fas_x_preferred":[
        "\u06a9\u0646\u062c\u0648\u0631 \u0639\u0644\u06cc\u0627"
    ],
    "name:fas_x_variant":[
        "Kanj\u016br-e \u2018Oly\u0101"
    ],
    "name:und_x_variant":[
        "Kanj\u016br",
        "Kanj\u016br-e B\u0101l\u0101"
    ],
    "wof:name":"Kanjur-e `Olya",
    "wof:placetype":"locality"
},
  "geometry": {"coordinates":[47.1908,34.2441],"type":"Point"}
}