{
  "type": "Feature",
  "properties": {
    "gn:admin1_code":"41",
    "gn:asciiname":"Nosratabad",
    "gn:country_code":"IR",
    "gn:dem":771,
    "gn:feature_class":"P",
    "gn:feature_code":"PPL",
    "gn:name":"No\u015frat\u0101b\u0101d",
    "gn:population":0,
    "gn:timezone":"Asia/Tehran",
    "iso:country":"IR",
    "name:ara_x_preferred":[
        "\u0646\u0635\u0631\u062a \u0623\u0628\u0627\u062f"
    ],
    "name:azb_x_preferred":[
        "\u0646\u0648\u0635\u0631\u062a\u200c\u0622\u0628\u0627\u062f"
    ],
    "name:aze_x_preferred":[
        "N\u00fcsr\u0259tabad"
    ],
    "name:cat_x_preferred":[
        "Nosratabad"
    ],
    "name:ceb_x_preferred":[
        "No\u015frat\u0101b\u0101d"
    ],
    "name:fas_x_preferred":[
        "\u0646\u0635\u0631\u062a \u0622\u0628\u0627\u062f"
    ],
    "name:fas_x_variant":[
        "No\u015frat\u0101b\u0101d",
        "\u0646\u0635\u0631\u062a\u200c\u0622\u0628\u0627\u062f"
    ],
    "name:ita_x_preferred":[
        "Nosratabad"
    ],
    "name:mlg_x_preferred":[
        "Nosratabad"
    ],
    "name:tur_x_preferred":[
        "Nusretabad"
    ],
    "wof:name":"Nosratabad",
    "wof:placetype":"locality"
},
  "geometry": {"coordinates":[60.72579,31.46579],"type":"Point"}
}