{
  "type": "Feature",
  "properties": {
    "gn:admin1_code":"11",
    "gn:asciiname":"Chah Morgh",
    "gn:country_code":"IR",
    "gn:dem":1152,
    "gn:feature_class":"P",
    "gn:feature_code":"PPL",
    "gn:name":"Ch\u0101h Morgh",
    "gn:population":0,
    "gn:timezone":"Asia/Tehran",
    "iso:country":"IR",
    "name:fas_x_preferred":[
        "\u0686\u0627\u0647 \u0645\u0631\u063a"
    ],
    "name:fas_x_variant":[
        "Ch\u0101h Morgh"
    ],
    "name:msa_x_preferred":[
        "Chah Morgh"
    ],
    "wof:name":"Chah Morgh",
    "wof:placetype":"locality"
},
  "geometry": {"coordinates":[56.5736,27.9531],"type":"Point"}
}