{
  "type": "Feature",
  "properties": {
    "gn:admin1_code":"4.0",
    "gn:asciiname":"Kashkan Gitan",
    "gn:cc2":"IR",
    "gn:country_code":"IR",
    "gn:dem":1021,
    "gn:feature_class":"P",
    "gn:feature_code":"PPL",
    "gn:name":"Kashk\u0101n G\u012bt\u0101n",
    "gn:population":0,
    "gn:timezone":"Asia/Tehran",
    "iso:country":"IR",
    "name:fas_x_preferred":[
        "Kashk\u0101n G\u012bt\u0101n"
    ],
    "name:und_x_variant":[
        "Kashk\u0101n Kat\u0101n"
    ],
    "wof:name":"Kashkan Gitan",
    "wof:placetype":"locality"
},
  "geometry": {"coordinates":[60.65,26.61667000000001],"type":"Point"}
}