{
  "type": "Feature",
  "properties": {
    "gn:admin1_code":"5.0",
    "gn:asciiname":"Sartipabad",
    "gn:country_code":"IR",
    "gn:dem":2080,
    "gn:feature_class":"P",
    "gn:feature_code":"PPL",
    "gn:name":"Sart\u012bp\u0101b\u0101d",
    "gn:population":0,
    "gn:timezone":"Asia/Tehran",
    "iso:country":"IR",
    "name:fas_x_preferred":[
        "Sart\u012bp\u0101b\u0101d"
    ],
    "name:fas_x_variant":[
        "\u0633\u0631\u062a\u06cc\u067e \u0622\u0628\u0627\u062f"
    ],
    "name:und_x_variant":[
        "\u0633\u0631\u062a\u06cc\u067e \u0622\u0628\u0627\u062f"
    ],
    "wof:name":"Sartipabad",
    "wof:placetype":"locality"
},
  "geometry": {"coordinates":[51.30333,30.62297],"type":"Point"}
}