{
  "type": "Feature",
  "properties": {
    "gn:admin1_code":"26.0",
    "gn:asciiname":"`Aliabad-e Qeysari",
    "gn:country_code":"IR",
    "gn:dem":988,
    "gn:feature_class":"P",
    "gn:feature_code":"PPL",
    "gn:name":"\u2018Al\u012b\u0101b\u0101d-e Qey\u015far\u012b",
    "gn:population":0,
    "gn:timezone":"Asia/Tehran",
    "iso:country":"IR",
    "name:fas_x_preferred":[
        "\u0639\u064e\u0644\u06cc \u0622\u0628\u0627\u062f"
    ],
    "name:fas_x_variant":[
        "\u0639\u0644\u06cc \u0622\u0628\u0627\u062f \u0642\u064a\u0635\u0631\u06cc",
        "\u2018Al\u012b\u0101b\u0101d",
        "\u0639\u0644\u06cc \u0622\u0628\u0627\u062f \u0642\u064a\u0635\u0631\u06cc\u0647"
    ],
    "name:und_x_variant":[
        "\u2018Al\u012b\u0101b\u0101d-e Qey\u015far\u012b",
        "\u2018Al\u012b\u0101b\u0101d-e Qey\u015far\u012byeh"
    ],
    "wof:name":"`Aliabad-e Qeysari",
    "wof:placetype":"locality"
},
  "geometry": {"coordinates":[51.5889,35.49992],"type":"Point"}
}