{
  "type": "Feature",
  "properties": {
    "gn:admin1_code":"15",
    "gn:asciiname":"Jangeh",
    "gn:country_code":"IR",
    "gn:dem":1658,
    "gn:feature_class":"P",
    "gn:feature_code":"PPL",
    "gn:name":"Jangeh",
    "gn:population":0,
    "gn:timezone":"Asia/Tehran",
    "iso:country":"IR",
    "name:azb_x_preferred":[
        "\u062c\u0646\u06af\u0647(\u0627\u06cc\u0630\u0647)"
    ],
    "name:ceb_x_preferred":[
        "Jangeh"
    ],
    "name:fas_x_preferred":[
        "\u062c\u0646\u06af\u0647"
    ],
    "name:swe_x_preferred":[
        "Jangeh"
    ],
    "name:und_x_variant":[
        "Jang Gah",
        "Jangeh",
        "\u062c\u0646\u06af\u0647"
    ],
    "name:urd_x_preferred":[
        "\u062c\u0646\u06af\u06c1"
    ],
    "wof:name":"Jangeh",
    "wof:placetype":"locality"
},
  "geometry": {"coordinates":[49.96138,32.02868],"type":"Point"}
}