{
  "type": "Feature",
  "properties": {
    "gn:admin1_code":"28",
    "gn:asciiname":"Kashanak",
    "gn:country_code":"IR",
    "gn:dem":2233,
    "gn:feature_class":"P",
    "gn:feature_code":"PPL",
    "gn:name":"K\u0101sh\u0101nak",
    "gn:population":0,
    "gn:timezone":"Asia/Tehran",
    "iso:country":"IR",
    "name:fas_x_preferred":[
        "\u06a9\u0627\u0634\u0627\u0646\u06a9"
    ],
    "name:fas_x_variant":[
        "K\u0101sh\u0101nak"
    ],
    "name:und_x_variant":[
        "K\u0101sh\u0101vak"
    ],
    "wof:name":"Kashanak",
    "wof:placetype":"locality"
},
  "geometry": {"coordinates":[52.6095,33.1743],"type":"Point"}
}