{
  "type": "Feature",
  "properties": {
    "gn:admin1_code":"15",
    "gn:asciiname":"Sarkan",
    "gn:country_code":"IR",
    "gn:dem":724,
    "gn:feature_class":"P",
    "gn:feature_code":"PPL",
    "gn:name":"Sark\u0101n",
    "gn:population":0,
    "gn:timezone":"Asia/Tehran",
    "iso:country":"IR",
    "name:ara_x_preferred":[
        "\u0633\u0631\u0643\u0627\u0646"
    ],
    "name:aze_x_preferred":[
        "S\u0259rkan"
    ],
    "name:ceb_x_preferred":[
        "Sark\u0101n"
    ],
    "name:fas_x_preferred":[
        "Sark\u0101n"
    ],
    "name:fas_x_variant":[
        "\u0633\u0631\u06a9\u0627\u0646"
    ],
    "name:ita_x_preferred":[
        "Serkan"
    ],
    "name:mlg_x_preferred":[
        "Sarkan"
    ],
    "name:msa_x_preferred":[
        "Sarkan"
    ],
    "name:rus_x_preferred":[
        "\u0421\u0435\u0440\u043a\u0430\u043d"
    ],
    "name:swe_x_preferred":[
        "Sark\u0101n"
    ],
    "name:tur_x_preferred":[
        "Serkan"
    ],
    "name:zho_x_preferred":[
        "\u85a9\u723e\u574e"
    ],
    "wof:name":"Sarkan",
    "wof:placetype":"locality"
},
  "geometry": {"coordinates":[50.13556,31.74778],"type":"Point"}
}