{
  "type": "Feature",
  "properties": {
    "gn:admin1_code":"15",
    "gn:asciiname":"Sarkan",
    "gn:country_code":"IR",
    "gn:dem":724,
    "gn:feature_class":"P",
    "gn:feature_code":"PPL",
    "gn:name":"Sark\u0101n",
    "gn:population":0,
    "gn:timezone":"Asia/Tehran",
    "iso:country":"IR",
    "name:fas_x_preferred":[
        "Sark\u0101n"
    ],
    "wof:name":"Sarkan",
    "wof:placetype":"locality"
},
  "geometry": {"coordinates":[50.13556,31.74778],"type":"Point"}
}