{
  "type": "Feature",
  "properties": {
    "gn:admin1_code":"43",
    "gn:asciiname":"Kalateh-ye Jan",
    "gn:country_code":"IR",
    "gn:dem":1072,
    "gn:feature_class":"P",
    "gn:feature_code":"PPLF",
    "gn:name":"Kal\u0101teh-ye J\u0101n",
    "gn:population":0,
    "gn:timezone":"Asia/Tehran",
    "iso:country":"IR",
    "name:fas_x_preferred":[
        "Kal\u0101teh-ye J\u0101n"
    ],
    "name:fas_x_variant":[
        "\u06a9\u0644\u0627\u062a\u0647 \u062c\u0627\u0646"
    ],
    "name:und_x_variant":[
        "\u06a9\u0644\u0627\u062a\u0647 \u062c\u0627\u0646"
    ],
    "wof:name":"Kalateh-ye Jan",
    "wof:placetype":"locality"
},
  "geometry": {"coordinates":[56.70441,37.1031],"type":"Point"}
}