{
  "type": "Feature",
  "properties": {
    "gn:admin1_code":"15.0",
    "gn:asciiname":"Abu Sholug",
    "gn:cc2":"IR",
    "gn:country_code":"IR",
    "gn:dem":5,
    "gn:feature_class":"P",
    "gn:feature_code":"PPL",
    "gn:name":"Ab\u016b Shol\u016bg",
    "gn:population":0,
    "gn:timezone":"Asia/Tehran",
    "iso:country":"IR",
    "name:fas_x_preferred":[
        "Ab\u016b Shol\u016bg"
    ],
    "name:und_x_variant":[
        "Ab\u016b Chal\u0101k",
        "Ab\u016b Shal\u016bk"
    ],
    "wof:name":"Abu Sholug",
    "wof:placetype":"locality"
},
  "geometry": {"coordinates":[48.635,30.735],"type":"Point"}
}