{
  "type": "Feature",
  "properties": {
    "gn:admin1_code":"8",
    "gn:asciiname":"Kala Chay",
    "gn:country_code":"IR",
    "gn:dem":-18,
    "gn:feature_class":"P",
    "gn:feature_code":"PPL",
    "gn:name":"Kal\u0101 Ch\u0101y",
    "gn:population":0,
    "gn:timezone":"Asia/Tehran",
    "iso:country":"IR",
    "name:ara_x_preferred":[
        "\u0643\u0644\u0627\u062a\u0634\u0627\u064a"
    ],
    "name:aze_x_preferred":[
        "K\u0259la\u00e7ay"
    ],
    "name:fas_x_preferred":[
        "Kel\u0101 Ch\u0101y"
    ],
    "name:fas_x_variant":[
        "\u06a9\u0644\u0627 \u0686\u0627\u06cc",
        "\u06a9\u0644\u0627\u0686\u0627\u06cc"
    ],
    "name:glk_x_preferred":[
        "\u06a9\u0644\u0623\u0686\u0626\u0647"
    ],
    "name:ita_x_preferred":[
        "Kela Chay"
    ],
    "name:mlg_x_preferred":[
        "Kelachay"
    ],
    "name:msa_x_preferred":[
        "Kelachay"
    ],
    "name:mzn_x_preferred":[
        "\u06a9\u0644\u0627\u0686\u0627\u06cc"
    ],
    "name:tur_x_preferred":[
        "Kela\u00e7ay"
    ],
    "name:und_x_variant":[
        "Kala Cha",
        "Kal\u0101 Ch\u0101y"
    ],
    "wof:name":"Kala Chay",
    "wof:placetype":"locality"
},
  "geometry": {"coordinates":[50.39642,37.07961],"type":"Point"}
}