{
  "type": "Feature",
  "properties": {
    "gn:admin1_code":"33",
    "gn:asciiname":"Shah Mansur",
    "gn:country_code":"IR",
    "gn:dem":1771,
    "gn:feature_class":"P",
    "gn:feature_code":"PPL",
    "gn:name":"Sh\u0101h Man\u015f\u016br",
    "gn:population":0,
    "gn:timezone":"Asia/Tehran",
    "iso:country":"IR",
    "name:fas_x_preferred":[
        "\u0633\u0627\u0647 \u0645\u0646\u0635\u0648\u0631"
    ],
    "name:fas_x_variant":[
        "Seyah Man\u015f\u016br",
        "Sh\u0101h Man\u015f\u016br"
    ],
    "wof:name":"Shah Mansur",
    "wof:placetype":"locality"
},
  "geometry": {"coordinates":[47.9178,37.7964],"type":"Point"}
}