{
  "type": "Feature",
  "properties": {
    "gn:admin1_code":"41.0",
    "gn:asciiname":"Chah Boneh",
    "gn:country_code":"IR",
    "gn:dem":1331,
    "gn:feature_class":"P",
    "gn:feature_code":"PPLL",
    "gn:name":"Ch\u0101h Boneh",
    "gn:population":0,
    "gn:timezone":"Asia/Tehran",
    "iso:country":"IR",
    "name:fas_x_preferred":[
        "\u0686\u0627\u0647 \u0628\u0646\u0647"
    ],
    "name:und_x_variant":[
        "Ch\u0101h Boneh"
    ],
    "wof:name":"Chah Boneh",
    "wof:placetype":"locality"
},
  "geometry": {"coordinates":[58.51486,33.35242],"type":"Point"}
}