{
  "type": "Feature",
  "properties": {
    "gn:admin1_code":"42",
    "gn:asciiname":"Hesar Juq",
    "gn:country_code":"IR",
    "gn:dem":1206,
    "gn:feature_class":"P",
    "gn:feature_code":"PPL",
    "gn:name":"\u1e28e\u015f\u0101r J\u016bq",
    "gn:population":0,
    "gn:timezone":"Asia/Tehran",
    "iso:country":"IR",
    "name:ceb_x_preferred":[
        "\u1e28e\u015f\u0101r J\u016bq"
    ],
    "name:fas_x_preferred":[
        "\u062d\u0635\u0627\u0631 \u062c\u0648\u0642"
    ],
    "name:fas_x_variant":[
        "\u1e28e\u015f\u0101r J\u016bq",
        "\u062d\u0635\u0627\u0631\u062c\u0648\u0642"
    ],
    "name:swe_x_preferred":[
        "\u1e28e\u015f\u0101r J\u016bq"
    ],
    "wof:name":"Hesar Juq",
    "wof:placetype":"locality"
},
  "geometry": {"coordinates":[58.75176999999999,36.25298],"type":"Point"}
}