{
  "type": "Feature",
  "properties": {
    "gn:admin1_code":"4.0",
    "gn:asciiname":"Kanuk",
    "gn:country_code":"IR",
    "gn:dem":1224,
    "gn:feature_class":"P",
    "gn:feature_code":"PPL",
    "gn:name":"K\u0101n\u016bk",
    "gn:population":0,
    "gn:timezone":"Asia/Tehran",
    "iso:country":"IR",
    "name:fas_x_preferred":[
        "\u06a9\u0627\u0646\u0648\u06a9"
    ],
    "name:fas_x_variant":[
        "K\u0101n\u016bk"
    ],
    "wof:name":"Kanuk",
    "wof:placetype":"locality"
},
  "geometry": {"coordinates":[60.7902,29.8719],"type":"Point"}
}