{
  "type": "Feature",
  "properties": {
    "gn:admin1_code":"28.0",
    "gn:admin2_code":"449483.0",
    "gn:asciiname":"Nehsatabad",
    "gn:country_code":"IR",
    "gn:dem":2063,
    "gn:feature_class":"P",
    "gn:feature_code":"PPL",
    "gn:name":"Neh\u015fat\u0101b\u0101d",
    "gn:population":0,
    "gn:timezone":"Asia/Tehran",
    "iso:country":"IR",
    "name:fas_x_preferred":[
        "Neh\u015fat\u0101b\u0101d"
    ],
    "name:fas_x_variant":[
        "\u0646\u0647\u0635\u062a \u0622\u0628\u0627\u062f"
    ],
    "wof:name":"Nehsatabad",
    "wof:placetype":"locality"
},
  "geometry": {"coordinates":[51.65466,31.93252],"type":"Point"}
}