{
  "type": "Feature",
  "properties": {
    "gn:admin1_code":"33",
    "gn:asciiname":"Kola",
    "gn:country_code":"IR",
    "gn:dem":1372,
    "gn:feature_class":"P",
    "gn:feature_code":"PPL",
    "gn:name":"Kol\u0101",
    "gn:population":0,
    "gn:timezone":"Asia/Tehran",
    "iso:country":"IR",
    "name:fas_x_preferred":[
        "\u06a9\u0644\u0627"
    ],
    "name:fas_x_variant":[
        "K\u016bl\u0101",
        "Kol\u0101"
    ],
    "wof:name":"Kola",
    "wof:placetype":"locality"
},
  "geometry": {"coordinates":[47.5374,37.2544],"type":"Point"}
}