{
  "type": "Feature",
  "properties": {
    "gn:admin1_code":"7",
    "gn:asciiname":"Mohammad Qasemi",
    "gn:country_code":"IR",
    "gn:dem":514,
    "gn:feature_class":"P",
    "gn:feature_code":"PPL",
    "gn:name":"Mo\u1e29ammad Q\u0101sem\u012b",
    "gn:population":0,
    "gn:timezone":"Asia/Tehran",
    "iso:country":"IR",
    "name:fas_x_preferred":[
        "\u0645\u062d\u0645\u062f \u0642\u0627\u0633\u0645\u06cc"
    ],
    "name:fas_x_variant":[
        "Mo\u1e29ammad Q\u0101sem\u012b"
    ],
    "name:und_x_variant":[
        "Mohammad Ghasem"
    ],
    "wof:name":"Mohammad Qasemi",
    "wof:placetype":"locality"
},
  "geometry": {"coordinates":[53.5542,27.4006],"type":"Point"}
}