{
  "type": "Feature",
  "properties": {
    "gn:admin1_code":"42",
    "gn:asciiname":"Rivand",
    "gn:country_code":"IR",
    "gn:dem":958,
    "gn:feature_class":"P",
    "gn:feature_code":"PPL",
    "gn:name":"R\u012bvand",
    "gn:population":0,
    "gn:timezone":"Asia/Tehran",
    "iso:country":"IR",
    "name:fas_x_preferred":[
        "R\u012bvand"
    ],
    "name:fas_x_variant":[
        "\u0631\u06cc\u0648\u0646\u062f"
    ],
    "name:sco_x_preferred":[
        "Rivand"
    ],
    "name:und_x_variant":[
        "\u0631\u06cc\u0648\u0646\u062f"
    ],
    "wof:name":"Rivand",
    "wof:placetype":"locality"
},
  "geometry": {"coordinates":[57.33714000000001,36.23233],"type":"Point"}
}