{
  "type": "Feature",
  "properties": {
    "gn:admin1_code":"39.0",
    "gn:asciiname":"Vazir",
    "gn:country_code":"IR",
    "gn:dem":938,
    "gn:feature_class":"P",
    "gn:feature_code":"PPL",
    "gn:name":"Vaz\u012br",
    "gn:population":0,
    "gn:timezone":"Asia/Tehran",
    "iso:country":"IR",
    "name:fas_x_preferred":[
        "\u0648\u064e\u0632\u064a\u0631"
    ],
    "name:fas_x_variant":[
        "Vaz\u012br"
    ],
    "name:uzb_x_preferred":[
        "Vazir"
    ],
    "wof:name":"Vazir",
    "wof:placetype":"locality"
},
  "geometry": {"coordinates":[50.53306,34.81528],"type":"Point"}
}