{
  "type": "Feature",
  "properties": {
    "gn:admin1_code":"8",
    "gn:asciiname":"Poltadasht",
    "gn:country_code":"IR",
    "gn:dem":238,
    "gn:feature_class":"P",
    "gn:feature_code":"PPL",
    "gn:name":"Poltadasht",
    "gn:population":0,
    "gn:timezone":"Asia/Tehran",
    "iso:country":"IR",
    "name:fas_x_preferred":[
        "\u067e\u0644\u062a\u062f\u0634\u062a"
    ],
    "name:und_x_variant":[
        "Polo Dasht",
        "Poltadasht"
    ],
    "wof:name":"Poltadasht",
    "wof:placetype":"locality"
},
  "geometry": {"coordinates":[50.35346,37.01588],"type":"Point"}
}