{
  "type": "Feature",
  "properties": {
    "gn:admin1_code":"7.0",
    "gn:asciiname":"Angiz Jan",
    "gn:country_code":"IR",
    "gn:dem":2574,
    "gn:feature_class":"P",
    "gn:feature_code":"PPL",
    "gn:name":"Ang\u012bz J\u0101n",
    "gn:population":0,
    "gn:timezone":"Asia/Tehran",
    "iso:country":"IR",
    "name:fas_x_preferred":[
        "Ang\u012bz J\u0101n"
    ],
    "wof:name":"Angiz Jan",
    "wof:placetype":"locality"
},
  "geometry": {"coordinates":[51.8975,31.39472],"type":"Point"}
}