{
  "type": "Feature",
  "properties": {
    "gn:admin1_code":"15.0",
    "gn:asciiname":"Bagh-e Malek",
    "gn:country_code":"IR",
    "gn:dem":711,
    "gn:feature_class":"P",
    "gn:feature_code":"PPLA2",
    "gn:name":"B\u0101gh-e Malek",
    "gn:population":0,
    "gn:timezone":"Asia/Tehran",
    "iso:country":"IR",
    "name:fas_x_preferred":[
        "B\u0101gh-e Malek"
    ],
    "name:fas_x_variant":[
        "\u0628\u0627\u063a \u0645\u0644\u06a9"
    ],
    "name:und_x_variant":[
        "Bagh Malek",
        "Bagh-i-Malik",
        "\u0628\u0627\u063a \u0645\u0644\u06a9"
    ],
    "wof:name":"Bagh-e Malek",
    "wof:placetype":"locality"
},
  "geometry": {"coordinates":[49.88558,31.52398],"type":"Point"}
}