{
  "type": "Feature",
  "properties": {
    "gn:admin1_code":"15.0",
    "gn:asciiname":"Bagh-e Malek",
    "gn:country_code":"IR",
    "gn:dem":711,
    "gn:feature_class":"P",
    "gn:feature_code":"PPLA2",
    "gn:name":"B\u0101gh-e Malek",
    "gn:population":0,
    "gn:timezone":"Asia/Tehran",
    "iso:country":"IR",
    "name:ara_x_preferred":[
        "\u0628\u0627\u063a \u0645\u0644\u0643"
    ],
    "name:aze_x_preferred":[
        "Ba\u011f M\u0259lik"
    ],
    "name:ceb_x_preferred":[
        "B\u0101gh-e Malek"
    ],
    "name:deu_x_preferred":[
        "Baghmalek"
    ],
    "name:fas_x_preferred":[
        "B\u0101gh-e Malek"
    ],
    "name:fas_x_variant":[
        "\u0628\u0627\u063a \u0645\u0644\u06a9",
        "\u0628\u0627\u063a\u200c\u0645\u0644\u06a9"
    ],
    "name:ita_x_preferred":[
        "Baghmalek"
    ],
    "name:mlg_x_preferred":[
        "Bagh-e Malek"
    ],
    "name:rus_x_preferred":[
        "\u0411\u0430\u0433\u0435-\u041c\u0435\u043b\u0435\u043a"
    ],
    "name:swe_x_preferred":[
        "B\u0101gh-e Malek"
    ],
    "name:tur_x_preferred":[
        "Ba\u011f Melik"
    ],
    "name:und_x_variant":[
        "Bagh Malek",
        "Bagh-i-Malik"
    ],
    "name:urd_x_preferred":[
        "\u0628\u0627\u063a\u200c\u0645\u0644\u06a9"
    ],
    "wof:name":"Bagh-e Malek",
    "wof:placetype":"locality"
},
  "geometry": {"coordinates":[49.88558,31.52398],"type":"Point"}
}