{
  "type": "Feature",
  "properties": {
    "gn:admin1_code":"29",
    "gn:asciiname":"Jahanabad-e Chah-e `Ali Jan",
    "gn:country_code":"IR",
    "gn:dem":528,
    "gn:feature_class":"P",
    "gn:feature_code":"PPL",
    "gn:name":"Jah\u0101n\u0101b\u0101d-e Ch\u0101h-e \u2018Al\u012b J\u0101n",
    "gn:population":0,
    "gn:timezone":"Asia/Tehran",
    "iso:country":"IR",
    "name:fas_x_preferred":[
        "\u062c\u0647\u0627\u0646 \u0622\u0628\u0627\u062f \u0686\u0627\u0647 \u0639\u0644\u06cc \u062c\u0627\u0646"
    ],
    "name:fas_x_variant":[
        "Jah\u0101n\u0101b\u0101d-e Ch\u0101h-e \u2018Al\u012b J\u0101n"
    ],
    "wof:name":"Jahanabad-e Chah-e `Ali Jan",
    "wof:placetype":"locality"
},
  "geometry": {"coordinates":[59.25933000000001,28.74579],"type":"Point"}
}