{
  "type": "Feature",
  "properties": {
    "gn:admin1_code":"33",
    "gn:asciiname":"Derab",
    "gn:country_code":"IR",
    "gn:dem":2144,
    "gn:feature_class":"P",
    "gn:feature_code":"PPL",
    "gn:name":"Der\u0101b",
    "gn:population":0,
    "gn:timezone":"Asia/Tehran",
    "iso:country":"IR",
    "name:fas_x_preferred":[
        "\u062f\u0631\u0627\u0628"
    ],
    "name:fas_x_variant":[
        "Der\u0101b"
    ],
    "name:msa_x_preferred":[
        "Derab"
    ],
    "name:und_x_variant":[
        "Dar \u0100b"
    ],
    "wof:name":"Derab",
    "wof:placetype":"locality"
},
  "geometry": {"coordinates":[47.7469,38.017],"type":"Point"}
}