{
  "type": "Feature",
  "properties": {
    "gn:admin1_code":"23",
    "gn:asciiname":"Gol Darreh",
    "gn:country_code":"IR",
    "gn:dem":1613,
    "gn:feature_class":"P",
    "gn:feature_code":"PPL",
    "gn:name":"Gol Darreh",
    "gn:population":0,
    "gn:timezone":"Asia/Tehran",
    "iso:country":"IR",
    "name:ceb_x_preferred":[
        "Gol Darreh"
    ],
    "name:fas_x_preferred":[
        "\u06af\u064f\u0644 \u062f\u064e\u0631\u0650\u0651\u0647"
    ],
    "name:fas_x_variant":[
        "\u06af\u0644 \u062f\u0631\u0651\u0647"
    ],
    "name:swe_x_preferred":[
        "Gol Darreh"
    ],
    "wof:name":"Gol Darreh",
    "wof:placetype":"locality"
},
  "geometry": {"coordinates":[47.6665,34.1052],"type":"Point"}
}