{
  "type": "Feature",
  "properties": {
    "gn:admin1_code":"16.0",
    "gn:asciiname":"Ahu Tappeh",
    "gn:country_code":"IR",
    "gn:dem":1816,
    "gn:feature_class":"P",
    "gn:feature_code":"PPL",
    "gn:name":"\u0100h\u016b Tappeh",
    "gn:population":0,
    "gn:timezone":"Asia/Tehran",
    "iso:country":"IR",
    "name:fas_x_preferred":[
        "\u0622\u0647\u0648 \u062a\u064e\u067e\u0650\u0651\u0647"
    ],
    "name:fas_x_variant":[
        "\u0100h\u016b Tappeh",
        "\u0622\u0647\u0648 \u062a\u067e\u0647"
    ],
    "wof:name":"Ahu Tappeh",
    "wof:placetype":"locality"
},
  "geometry": {"coordinates":[48.00124,34.93787],"type":"Point"}
}