{
  "type": "Feature",
  "properties": {
    "gn:admin1_code":"11",
    "gn:asciiname":"Bahmani",
    "gn:country_code":"IR",
    "gn:dem":40,
    "gn:feature_class":"P",
    "gn:feature_code":"PPL",
    "gn:name":"Bahman\u012b",
    "gn:population":0,
    "gn:timezone":"Asia/Tehran",
    "iso:country":"IR",
    "name:ara_x_preferred":[
        "\u0628\u0647\u0645\u0646\u064a"
    ],
    "name:fas_x_preferred":[
        "\u0628\u064e\u0647\u0645\u064e\u0646\u0648"
    ],
    "name:fas_x_variant":[
        "Bahman\u012b",
        "\u0628\u0647\u0645\u0646\u06cc"
    ],
    "name:msa_x_preferred":[
        "Bahmani"
    ],
    "name:und_x_variant":[
        "Behmani",
        "Bahman\u016b",
        "\u0628\u0647\u0645\u0646\u06cc"
    ],
    "wof:name":"Bahmani",
    "wof:placetype":"locality"
},
  "geometry": {"coordinates":[54.16859,26.83768],"type":"Point"}
}