{
  "type": "Feature",
  "properties": {
    "gn:admin1_code":"37.0",
    "gn:asciiname":"Dadeli Ghazneyn",
    "gn:country_code":"IR",
    "gn:dem":440,
    "gn:feature_class":"P",
    "gn:feature_code":"PPL",
    "gn:name":"D\u0101del\u012b Ghazneyn",
    "gn:population":0,
    "gn:timezone":"Asia/Tehran",
    "iso:country":"IR",
    "name:fas_x_preferred":[
        "D\u0101dl\u012b-ye Qarneyn"
    ],
    "name:fas_x_variant":[
        "D\u0101dl\u012b-Ye-Ghazneyn",
        "\u062f\u0627\u062f\u0644\u06cc \u0642\u0631\u0646\u06cc\u0646",
        "\u062f\u0627\u062f\u0644\u06cc \u063a\u0632\u0646\u06cc\u0646",
        "\u062f\u0627\u062f\u0644\u06cc \u0642\u0632\u0646\u06cc\u0646"
    ],
    "name:msa_x_preferred":[
        "Dadli-ye Qazneyn"
    ],
    "name:und_x_variant":[
        "D\u0101del\u012b Ghazneyn"
    ],
    "wof:name":"Dadeli Ghazneyn",
    "wof:placetype":"locality"
},
  "geometry": {"coordinates":[56.06869,38.04077],"type":"Point"}
}