{
  "type": "Feature",
  "properties": {
    "gn:admin1_code":"35",
    "gn:asciiname":"Gerd Ab",
    "gn:country_code":"IR",
    "gn:dem":36,
    "gn:feature_class":"P",
    "gn:feature_code":"PPL",
    "gn:name":"Gerd \u0100b",
    "gn:population":0,
    "gn:timezone":"Asia/Tehran",
    "iso:country":"IR",
    "name:fas_x_preferred":[
        "Gerd \u0100b"
    ],
    "name:fas_x_variant":[
        "\u06af\u0631\u062f \u0622\u0628"
    ],
    "name:und_x_variant":[
        "Lang\u0101",
        "Gerd\u0101b Lang\u0101",
        "\u06af\u0631\u062f \u0622\u0628"
    ],
    "wof:name":"Gerd Ab",
    "wof:placetype":"locality"
},
  "geometry": {"coordinates":[51.11333,36.67621],"type":"Point"}
}