{
  "type": "Feature",
  "properties": {
    "gn:admin1_code":"26.0",
    "gn:asciiname":"Araj",
    "gn:country_code":"IR",
    "gn:dem":1568,
    "gn:feature_class":"P",
    "gn:feature_code":"PPL",
    "gn:name":"Ar\u0101j",
    "gn:population":0,
    "gn:timezone":"Asia/Tehran",
    "iso:country":"IR",
    "name:fas_x_preferred":[
        "\u0627\u064e\u0631\u0627\u062c"
    ],
    "name:fas_x_variant":[
        "Ar\u0101j"
    ],
    "wof:name":"Araj",
    "wof:placetype":"locality"
},
  "geometry": {"coordinates":[51.48806,35.80110999999999],"type":"Point"}
}