{
  "type": "Feature",
  "properties": {
    "gn:admin1_code":"29.0",
    "gn:asciiname":"Amirabad",
    "gn:country_code":"IR",
    "gn:dem":2113,
    "gn:feature_class":"P",
    "gn:feature_code":"PPLF",
    "gn:name":"Am\u012br\u0101b\u0101d",
    "gn:population":0,
    "gn:timezone":"Asia/Tehran",
    "iso:country":"IR",
    "name:ara_x_preferred":[
        "\u0623\u0645\u064a\u0631 \u0623\u0628\u0627\u062f"
    ],
    "name:aze_x_preferred":[
        "\u018fmirabad"
    ],
    "name:ceb_x_preferred":[
        "Amirabad"
    ],
    "name:fas_x_preferred":[
        "\u0627\u0645\u06cc\u0631 \u0622\u0628\u0627\u062f"
    ],
    "name:fas_x_variant":[
        "Am\u012br\u0101b\u0101d",
        "\u0627\u0645\u06cc\u0631 \u0622\u0628\u0627\u062f \u0627\u0645\u064a\u0631 \u0642\u0644\u06cc",
        "\u0627\u0645\u06cc\u0631\u0622\u0628\u0627\u062f"
    ],
    "name:mzn_x_preferred":[
        "\u0627\u0645\u06cc\u0631\u0622\u0628\u0627\u062f"
    ],
    "name:swe_x_preferred":[
        "Amirabad"
    ],
    "name:und_x_variant":[
        "Am\u012br\u0101b\u0101d-e \u0100m\u012br Qol\u012b"
    ],
    "wof:name":"Amirabad",
    "wof:placetype":"locality"
},
  "geometry": {"coordinates":[56.2189,29.3793],"type":"Point"}
}