{
  "type": "Feature",
  "properties": {
    "gn:admin1_code":"7.0",
    "gn:asciiname":"Abegarm",
    "gn:country_code":"IR",
    "gn:dem":1890,
    "gn:feature_class":"P",
    "gn:feature_code":"PPL",
    "gn:name":"\u0100begarm",
    "gn:population":0,
    "gn:timezone":"Asia/Tehran",
    "iso:country":"IR",
    "name:fas_x_preferred":[
        "\u0622\u0628\u06af\u0631\u0645"
    ],
    "name:und_x_variant":[
        "\u0100begarm"
    ],
    "wof:name":"Abegarm",
    "wof:placetype":"locality"
},
  "geometry": {"coordinates":[52.0614,30.0642],"type":"Point"}
}