{
  "type": "Feature",
  "properties": {
    "gn:admin1_code":"33",
    "gn:asciiname":"Bagh-e Ya`qub",
    "gn:country_code":"IR",
    "gn:dem":1687,
    "gn:feature_class":"P",
    "gn:feature_code":"PPL",
    "gn:name":"B\u0101gh-e Ya\u2018q\u016bb",
    "gn:population":0,
    "gn:timezone":"Asia/Tehran",
    "iso:country":"IR",
    "name:fas_x_preferred":[
        "\u0628\u0627\u063a \u064a\u0639\u0642\u0648\u0628"
    ],
    "name:fas_x_variant":[
        "B\u0101gh-e Ya\u2018q\u016bb"
    ],
    "name:und_x_variant":[
        "Payeh Gol",
        "B\u0101gh Ya\u2018q\u016bb",
        "Payagol"
    ],
    "wof:name":"Bagh-e Ya`qub",
    "wof:placetype":"locality"
},
  "geometry": {"coordinates":[46.4397,38.0074],"type":"Point"}
}