{
  "type": "Feature",
  "properties": {
    "gn:admin1_code":"35.0",
    "gn:asciiname":"Jisa-ye Bala",
    "gn:country_code":"IR",
    "gn:dem":38,
    "gn:feature_class":"P",
    "gn:feature_code":"PPL",
    "gn:name":"J\u012bs\u0101-ye B\u0101l\u0101",
    "gn:population":0,
    "gn:timezone":"Asia/Tehran",
    "iso:country":"IR",
    "name:fas_x_preferred":[
        "\u062c\u064a\u0633\u0627\u06cc \u0639\u0644\u064a\u0627"
    ],
    "name:fas_x_variant":[
        "J\u012bs\u0101-ye B\u0101l\u0101",
        "J\u012bs\u0101-ye \u2018Oly\u0101",
        "\u062c\u064a\u0633\u0627 \u0628\u0627\u0644\u0627",
        "\u062c\u064a\u0633\u0627 \u062e\u0636\u0631 \u0622\u0628\u0627\u062f",
        "\u062c\u06cc \u0633\u0627"
    ],
    "name:und_x_variant":[
        "J\u012bs\u0101-ye Kha\u1e95ar\u0101b\u0101d",
        "J\u012b S\u0101"
    ],
    "wof:name":"Jisa-ye Bala",
    "wof:placetype":"locality"
},
  "geometry": {"coordinates":[51.16069,36.67233],"type":"Point"}
}