{
  "type": "Feature",
  "properties": {
    "gn:admin1_code":"34",
    "gn:asciiname":"Khowrzan",
    "gn:country_code":"IR",
    "gn:dem":2213,
    "gn:feature_class":"P",
    "gn:feature_code":"PPL",
    "gn:name":"Khowrzan",
    "gn:population":0,
    "gn:timezone":"Asia/Tehran",
    "iso:country":"IR",
    "name:fas_x_preferred":[
        "\u062e\u0648\u0631\u0632\u0646 \u0639\u0644\u06cc\u0627"
    ],
    "name:fas_x_variant":[
        "Khvorz\u012bn",
        "Kh\u016brzen-e Qad\u012bm",
        "Kh\u016brz\u012bn",
        "\u062e\u0648\u0631\u0632\u0650\u0646\u0650 \u0642\u064e\u062f\u064a\u0645",
        "\u062e\u0648\u0631\u0632\u064a\u0646",
        "\u062e\u0648\u0631\u0632\u0646",
        "\u062e\u0648\u0631\u0632\u0627\u0646"
    ],
    "name:und_x_variant":[
        "Khowrzan-e \u2018Oly\u0101",
        "\u062e\u0648\u0631\u0632\u064a\u0646",
        "Khowrzan",
        "Khowrz\u0101n"
    ],
    "wof:name":"Khowrzan",
    "wof:placetype":"locality"
},
  "geometry": {"coordinates":[49.74575,33.98113],"type":"Point"}
}