{
  "type": "Feature",
  "properties": {
    "gn:admin1_code":"1",
    "gn:asciiname":"Almanabad",
    "gn:country_code":"IR",
    "gn:dem":1306,
    "gn:feature_class":"P",
    "gn:feature_code":"PPL",
    "gn:name":"\u0100lm\u0101n\u0101b\u0101d",
    "gn:population":0,
    "gn:timezone":"Asia/Tehran",
    "iso:country":"IR",
    "name:azb_x_preferred":[
        "\u0627\u0626\u0644\u0645\u0627\u0646 \u0622\u0628\u0627\u062f"
    ],
    "name:aze_x_preferred":[
        "Almanabad"
    ],
    "name:ceb_x_preferred":[
        "\u0100lm\u0101n\u0101b\u0101d"
    ],
    "name:fas_x_preferred":[
        "\u0100lm\u0101n\u0101b\u0101d"
    ],
    "name:fas_x_variant":[
        "\u0622\u0644\u0645\u0627\u0646 \u0622\u0628\u0627\u062f",
        "\u0627\u0644\u0645\u0627\u0646\u200c\u0622\u0628\u0627\u062f"
    ],
    "name:msa_x_preferred":[
        "Almanabad"
    ],
    "name:pol_x_preferred":[
        "Almanabad"
    ],
    "name:swe_x_preferred":[
        "\u0100lm\u0101n\u0101b\u0101d"
    ],
    "name:ukr_x_preferred":[
        "\u0410\u043b\u044c\u043c\u0430\u043d\u0430\u0431\u0430\u0434"
    ],
    "wof:name":"Almanabad",
    "wof:placetype":"locality"
},
  "geometry": {"coordinates":[45.1449,37.5549],"type":"Point"}
}