{
  "type": "Feature",
  "properties": {
    "gn:admin1_code":"23",
    "gn:asciiname":"Golah Veys",
    "gn:country_code":"IR",
    "gn:dem":1756,
    "gn:feature_class":"P",
    "gn:feature_code":"PPL",
    "gn:name":"Golah Veys",
    "gn:population":0,
    "gn:timezone":"Asia/Tehran",
    "iso:country":"IR",
    "name:ara_x_preferred":[
        "\u063a\u0644\u0629 \u0648\u064a\u0633"
    ],
    "name:fas_x_preferred":[
        "\u06af\u064f\u0644\u064e\u0647 \u0648\u0650\u064a\u0633"
    ],
    "name:fas_x_variant":[
        "\u06af\u0644\u0647 \u0648\u06cc\u0633"
    ],
    "wof:name":"Golah Veys",
    "wof:placetype":"locality"
},
  "geometry": {"coordinates":[47.7591,34.2431],"type":"Point"}
}