{
  "type": "Feature",
  "properties": {
    "gn:admin1_code":"5.0",
    "gn:asciiname":"Shahid Barvand",
    "gn:country_code":"IR",
    "gn:dem":2168,
    "gn:feature_class":"P",
    "gn:feature_code":"PPL",
    "gn:name":"Shah\u012bd Barvand",
    "gn:population":0,
    "gn:timezone":"Asia/Tehran",
    "iso:country":"IR",
    "name:fas_x_preferred":[
        "Shah\u012bd Barvand"
    ],
    "name:fas_x_variant":[
        "\u0634\u0647\u06cc\u062f \u0628\u0631\u0648\u0646\u062f"
    ],
    "name:und_x_variant":[
        "\u0634\u0647\u06cc\u062f \u0628\u0631\u0648\u0646\u062f"
    ],
    "wof:name":"Shahid Barvand",
    "wof:placetype":"locality"
},
  "geometry": {"coordinates":[51.01595,31.08264],"type":"Point"}
}