{
  "type": "Feature",
  "properties": {
    "gn:admin1_code":"26.0",
    "gn:asciiname":"Keshar-e Sofla",
    "gn:country_code":"IR",
    "gn:dem":1622,
    "gn:feature_class":"P",
    "gn:feature_code":"PPL",
    "gn:name":"Kesh\u0101r-e Sofl\u00e1",
    "gn:population":0,
    "gn:timezone":"Asia/Tehran",
    "iso:country":"IR",
    "name:fas_x_preferred":[
        "\u0643\u0634\u0627\u0631 \u067e\u0627\u0626\u064a\u0646"
    ],
    "name:fas_x_variant":[
        "Kesh\u0101r-e P\u0101\u2019\u012bn",
        "\u06a9\u0634\u0627\u0631 \u0633\u0641\u0644\u06cc"
    ],
    "name:und_x_variant":[
        "Kesh\u0101r-e Sofl\u00e1"
    ],
    "wof:name":"Keshar-e Sofla",
    "wof:placetype":"locality"
},
  "geometry": {"coordinates":[51.2442,35.8098],"type":"Point"}
}