{
  "type": "Feature",
  "properties": {
    "gn:admin1_code":"15",
    "gn:asciiname":"Tarveyd",
    "gn:country_code":"IR",
    "gn:dem":93,
    "gn:feature_class":"P",
    "gn:feature_code":"PPL",
    "gn:name":"Tarveyd",
    "gn:population":0,
    "gn:timezone":"Asia/Tehran",
    "iso:country":"IR",
    "wof:name":"Tarveyd",
    "wof:placetype":"locality"
},
  "geometry": {"coordinates":[48.15528,32.12444],"type":"Point"}
}