{
  "type": "Feature",
  "properties": {
    "gn:admin1_code":"41",
    "gn:asciiname":"Rameh",
    "gn:country_code":"IR",
    "gn:dem":1732,
    "gn:feature_class":"P",
    "gn:feature_code":"PPL",
    "gn:name":"Rameh",
    "gn:population":0,
    "gn:timezone":"Asia/Tehran",
    "iso:country":"IR",
    "wof:name":"Rameh",
    "wof:placetype":"locality"
},
  "geometry": {"coordinates":[59.58333,31.91667],"type":"Point"}
}