{
  "type": "Feature",
  "properties": {
    "gn:admin1_code":"15",
    "gn:asciiname":"Borj-e Yusefi",
    "gn:country_code":"IR",
    "gn:dem":150,
    "gn:feature_class":"P",
    "gn:feature_code":"PPL",
    "gn:name":"Borj-e Y\u016bsef\u012b",
    "gn:population":0,
    "gn:timezone":"Asia/Tehran",
    "iso:country":"IR",
    "name:azb_x_preferred":[
        "\u0628\u0631\u062c \u06cc\u0648\u0633\u0641\u06cc(\u0628\u0647\u0628\u0647\u0627\u0646)"
    ],
    "name:ceb_x_preferred":[
        "Borj-e Y\u016bsef\u012b"
    ],
    "name:fas_x_preferred":[
        "\u0628\u0631\u062c \u06cc\u0648\u0633\u0641\u06cc"
    ],
    "name:fas_x_variant":[
        "Borj-e Y\u016bsef\u012b"
    ],
    "name:swe_x_preferred":[
        "Borj-e Y\u016bsef\u012b"
    ],
    "name:und_x_variant":[
        "Borj Y\u016bsef\u012b",
        "Borj Y\u016bsof\u012b"
    ],
    "wof:name":"Borj-e Yusefi",
    "wof:placetype":"locality"
},
  "geometry": {"coordinates":[50.1773,30.3583],"type":"Point"}
}