{
  "type": "Feature",
  "properties": {
    "gn:admin1_code":"33",
    "gn:admin2_code":"449438",
    "gn:asciiname":"Miab",
    "gn:country_code":"IR",
    "gn:dem":2061,
    "gn:feature_class":"P",
    "gn:feature_code":"PPL",
    "gn:name":"M\u012b\u0101b",
    "gn:population":611,
    "gn:timezone":"Asia/Tehran",
    "iso:country":"IR",
    "name:azb_x_preferred":[
        "\u0645\u06cc\u0627\u0628"
    ],
    "name:fas_x_preferred":[
        "\u0645\u06cc\u0627\u0628"
    ],
    "name:fas_x_variant":[
        "M\u012b\u0101b",
        "\u0645\u06cc\u0627\u0648",
        "\u0645\u0650\u064a\u0627\u0628",
        "\u0645\u064a\u0651\u0627\u0628"
    ],
    "name:msa_x_preferred":[
        "Miab"
    ],
    "name:und_x_variant":[
        "M\u012by\u0101b",
        "Mey\u0101b"
    ],
    "wof:name":"Miab",
    "wof:placetype":"locality",
    "wof:population":611
},
  "geometry": {"coordinates":[45.8019,38.7011],"type":"Point"}
}