{
  "type": "Feature",
  "properties": {
    "gn:admin1_code":"15.0",
    "gn:asciiname":"Chalchalak",
    "gn:country_code":"IR",
    "gn:dem":829,
    "gn:feature_class":"P",
    "gn:feature_code":"PPL",
    "gn:name":"Chalchalak",
    "gn:population":0,
    "gn:timezone":"Asia/Tehran",
    "iso:country":"IR",
    "name:fas_x_preferred":[
        "\u0686\u0644\u0686\u0644\u06a9"
    ],
    "name:und_x_variant":[
        "\u0686\u0644\u0686\u0644\u06a9"
    ],
    "wof:name":"Chalchalak",
    "wof:placetype":"locality"
},
  "geometry": {"coordinates":[49.95057,31.5275],"type":"Point"}
}