{
  "type": "Feature",
  "properties": {
    "gn:admin1_code":"41.0",
    "gn:asciiname":"Chah Bunak",
    "gn:country_code":"IR",
    "gn:dem":1964,
    "gn:feature_class":"P",
    "gn:feature_code":"PPL",
    "gn:name":"Ch\u0101h B\u016bnak",
    "gn:population":0,
    "gn:timezone":"Asia/Tehran",
    "iso:country":"IR",
    "name:fas_x_preferred":[
        "\u0686\u0627\u0647 \u0628\u0648\u0646\u06a9"
    ],
    "name:fas_x_variant":[
        "\u0686\u0627\u0647 \u0628\u0648\u0646\u0627\u06a9"
    ],
    "name:und_x_variant":[
        "Ch\u0101h B\u016bnak",
        "Ch\u0101h B\u016bn\u0101k"
    ],
    "wof:name":"Chah Bunak",
    "wof:placetype":"locality"
},
  "geometry": {"coordinates":[59.68934,31.7927],"type":"Point"}
}