{
  "type": "Feature",
  "properties": {
    "gn:admin1_code":"29",
    "gn:asciiname":"Chehel Tokhm",
    "gn:country_code":"IR",
    "gn:dem":804,
    "gn:feature_class":"P",
    "gn:feature_code":"PPL",
    "gn:name":"Chehel Tokhm",
    "gn:population":0,
    "gn:timezone":"Asia/Tehran",
    "iso:country":"IR",
    "name:fas_x_preferred":[
        "\u0686\u0647\u0644 \u062a\u062e\u0645"
    ],
    "name:und_x_variant":[
        "Chahil Turkm",
        "Chehel Tokhm-e Bam",
        "Chehil Tukhm",
        "Chehel Tokhm"
    ],
    "wof:name":"Chehel Tokhm",
    "wof:placetype":"locality"
},
  "geometry": {"coordinates":[58.6494,28.9886],"type":"Point"}
}