{
  "type": "Feature",
  "properties": {
    "gn:admin1_code":"1",
    "gn:asciiname":"Hasel Qubi-ye Afshar",
    "gn:country_code":"IR",
    "gn:dem":1285,
    "gn:feature_class":"P",
    "gn:feature_code":"PPL",
    "gn:name":"\u1e28\u0101\u015fel Q\u016bb\u012b-ye Afsh\u0101r",
    "gn:population":0,
    "gn:timezone":"Asia/Tehran",
    "iso:country":"IR",
    "name:azb_x_preferred":[
        "\u062d\u0627\u0635\u0644\u200c\u0642\u0648\u0628\u06cc\u200c\u0627\u0641\u0634\u0627\u0631(\u0642\u0648\u0634\u0627\u0686\u0627\u06cc)"
    ],
    "name:aze_x_preferred":[
        "Hasilqubi-i \u018ff\u015far"
    ],
    "name:fas_x_preferred":[
        "\u062d\u0627\u0635\u0650\u0644 \u0642\u0648\u0626\u06cc"
    ],
    "name:fas_x_variant":[
        "\u062d\u0627\u0635\u0644 \u0642\u0648\u0628\u06cc \u0627\u0641\u0634\u0627\u0631",
        "\u062d\u0627\u0635\u0650\u0644 \u0642\u0648\u0621\u0626 \u0627\u064e\u0641\u0634\u0627\u0631",
        "\u1e28\u0101\u015fel Q\u016bb\u012b-ye Afsh\u0101r",
        "\u062d\u0627\u0635\u0644\u200c\u0642\u0648\u0628\u06cc\u200c\u0627\u0641\u0634\u0627\u0631"
    ],
    "name:msa_x_preferred":[
        "Hasel Qubi-ye Afshar"
    ],
    "name:und_x_variant":[
        "\u1e28\u0101\u015fel Q\u016b\u2019\u012b",
        "\u1e28\u0101\u015fel Q\u016b\u2019\u012b-ye Afsh\u0101r"
    ],
    "wof:name":"Hasel Qubi-ye Afshar",
    "wof:placetype":"locality"
},
  "geometry": {"coordinates":[45.9676,37.0286],"type":"Point"}
}