{
  "type": "Feature",
  "properties": {
    "gn:admin1_code":"42.0",
    "gn:asciiname":"Qal`eh Hammam",
    "gn:country_code":"IR",
    "gn:dem":1205,
    "gn:feature_class":"P",
    "gn:feature_code":"PPL",
    "gn:name":"Qal\u2018eh \u1e28amm\u0101m",
    "gn:population":0,
    "gn:timezone":"Asia/Tehran",
    "iso:country":"IR",
    "name:fas_x_preferred":[
        "\u0642\u0644\u0639\u0647 \u062d\u0645\u0651\u0627\u0645"
    ],
    "name:fas_x_variant":[
        "Qal\u2018eh \u1e28amm\u0101m"
    ],
    "wof:name":"Qal`eh Hammam",
    "wof:placetype":"locality"
},
  "geometry": {"coordinates":[60.7585,35.6387],"type":"Point"}
}