{
  "type": "Feature",
  "properties": {
    "gn:admin1_code":"15.0",
    "gn:asciiname":"Soveyseh-ye Seh",
    "gn:country_code":"IR",
    "gn:dem":13,
    "gn:feature_class":"P",
    "gn:feature_code":"PPL",
    "gn:name":"Soveyseh-ye Seh",
    "gn:population":0,
    "gn:timezone":"Asia/Tehran",
    "iso:country":"IR",
    "name:azb_x_preferred":[
        "\u0633\u0648\u06cc\u0633\u0647 \u0633\u0647(\u0627\u0647\u0648\u0627\u0632)"
    ],
    "name:fas_x_preferred":[
        "\u0633\u0648\u06cc\u0633\u0647 \u0633\u0647"
    ],
    "name:fas_x_variant":[
        "\u0633\u0648\u06cc\u0633\u0647 \u0632\u0628\u06cc\u0644\u0647"
    ],
    "name:und_x_variant":[
        "Soveyseh Zab\u012bleh"
    ],
    "wof:name":"Soveyseh-ye Seh",
    "wof:placetype":"locality"
},
  "geometry": {"coordinates":[48.60528,31.12927],"type":"Point"}
}