{
  "type": "Feature",
  "properties": {
    "gn:admin1_code":"42.0",
    "gn:asciiname":"Feyzabad",
    "gn:country_code":"IR",
    "gn:dem":965,
    "gn:feature_class":"P",
    "gn:feature_code":"PPL",
    "gn:name":"Fey\u1e95\u0101b\u0101d",
    "gn:population":0,
    "gn:timezone":"Asia/Tehran",
    "iso:country":"IR",
    "name:fas_x_preferred":[
        "Fey\u1e95\u0101b\u0101d"
    ],
    "name:fas_x_variant":[
        "Kal\u0101teh-ye Fey\u1e95\u0101b\u0101d",
        "\u0641\u06cc\u0636 \u0622\u0628\u0627\u062f",
        "\u0641\u06cc\u0636\u200c\u0622\u0628\u0627\u062f"
    ],
    "name:und_x_variant":[
        "\u0641\u06cc\u0636 \u0622\u0628\u0627\u062f"
    ],
    "wof:name":"Feyzabad",
    "wof:placetype":"locality"
},
  "geometry": {"coordinates":[56.7722,36.77361],"type":"Point"}
}