{
  "type": "Feature",
  "properties": {
    "gn:admin1_code":"16",
    "gn:asciiname":"Sianezar",
    "gn:country_code":"IR",
    "gn:dem":1729,
    "gn:feature_class":"P",
    "gn:feature_code":"PPL",
    "gn:name":"S\u012b\u0101nez\u0101r",
    "gn:population":0,
    "gn:timezone":"Asia/Tehran",
    "iso:country":"IR",
    "name:ara_x_preferred":[
        "\u0633\u064a\u0627\u0646\u0632\u0627\u0631"
    ],
    "name:ceb_x_preferred":[
        "S\u012b\u0101nez\u0101r"
    ],
    "name:ckb_x_preferred":[
        "\u0633\u06cc\u0627\u0646\u06d5\u0632\u0627\u0631"
    ],
    "name:fas_x_preferred":[
        "\u0633\u064a\u0627\u0647 \u0646\u0650\u0633\u0627\u0631"
    ],
    "name:fas_x_variant":[
        "\u0633\u06cc\u0627\u0646\u0632\u0627\u0631",
        "\u0633\u0650\u064a\u0627\u0646\u0632\u0627\u0631",
        "S\u012b\u0101nez\u0101r"
    ],
    "name:kur_x_preferred":[
        "Siyanezar"
    ],
    "name:swe_x_preferred":[
        "S\u012b\u0101nez\u0101r"
    ],
    "name:und_x_variant":[
        "Sey\u0101nz\u0101r",
        "S\u012b\u0101h Nes\u0101r",
        "S\u012b\u0101nz\u0101r",
        "S\u012b\u0101hnisar"
    ],
    "wof:name":"Sianezar",
    "wof:placetype":"locality"
},
  "geometry": {"coordinates":[46.2008,35.9507],"type":"Point"}
}