{
  "type": "Feature",
  "properties": {
    "gn:admin1_code":"42.0",
    "gn:asciiname":"Chah-e Nam Avar",
    "gn:country_code":"IR",
    "gn:dem":879,
    "gn:feature_class":"P",
    "gn:feature_code":"PPLL",
    "gn:name":"Ch\u0101h-e N\u0101m \u0100var",
    "gn:population":0,
    "gn:timezone":"Asia/Tehran",
    "iso:country":"IR",
    "name:fas_x_preferred":[
        "\u0686\u0627\u0647 \u0646\u0627\u0645 \u0622\u0648\u0631"
    ],
    "name:fas_x_variant":[
        "\u0686\u0627\u0647 \u0646\u0627\u0645 \u0622\u0648\u0631 \u0634\u0645\u0627\u0631\u0647 \u06f1"
    ],
    "name:und_x_variant":[
        "Ch\u0101h-e N\u0101m \u0100var",
        "Ch\u0101h-e N\u0101m \u0100var Shom\u0101reh Yek"
    ],
    "wof:name":"Chah-e Nam Avar",
    "wof:placetype":"locality"
},
  "geometry": {"coordinates":[58.71838,34.94273],"type":"Point"}
}