{
  "type": "Feature",
  "properties": {
    "gn:admin1_code":"8.0",
    "gn:asciiname":"Laman Gavabor",
    "gn:country_code":"IR",
    "gn:dem":1511,
    "gn:feature_class":"P",
    "gn:feature_code":"PPL",
    "gn:name":"Laman Gav\u0101bor",
    "gn:population":0,
    "gn:timezone":"Asia/Tehran",
    "iso:country":"IR",
    "name:fas_x_preferred":[
        "Laman Gav\u0101bor"
    ],
    "wof:name":"Laman Gavabor",
    "wof:placetype":"locality"
},
  "geometry": {"coordinates":[50.46667,36.93333],"type":"Point"}
}