{
  "type": "Feature",
  "properties": {
    "gn:admin1_code":"33",
    "gn:asciiname":"Eyvaraq",
    "gn:country_code":"IR",
    "gn:dem":1846,
    "gn:feature_class":"P",
    "gn:feature_code":"PPL",
    "gn:name":"Eyvaraq",
    "gn:population":0,
    "gn:timezone":"Asia/Tehran",
    "iso:country":"IR",
    "name:fas_x_preferred":[
        "\u0627\u06cc\u0648\u0631\u0642"
    ],
    "wof:name":"Eyvaraq",
    "wof:placetype":"locality"
},
  "geometry": {"coordinates":[47.5825,37.6531],"type":"Point"}
}