{
  "type": "Feature",
  "properties": {
    "gn:admin1_code":"13",
    "gn:asciiname":"Ruhollah",
    "gn:country_code":"IR",
    "gn:dem":1552,
    "gn:feature_class":"P",
    "gn:feature_code":"PPL",
    "gn:name":"R\u016b\u1e29oll\u0101h",
    "gn:population":0,
    "gn:timezone":"Asia/Tehran",
    "iso:country":"IR",
    "name:fas_x_preferred":[
        "\u0631\u0648\u062d \u0627\u0644\u0644\u0647"
    ],
    "name:fas_x_variant":[
        "R\u016b\u1e29oll\u0101h"
    ],
    "wof:name":"Ruhollah",
    "wof:placetype":"locality"
},
  "geometry": {"coordinates":[47.1785,34.6325],"type":"Point"}
}