{
  "type": "Feature",
  "properties": {
    "gn:admin1_code":"15",
    "gn:asciiname":"Hoseyn Ghalayem",
    "gn:country_code":"IR",
    "gn:dem":41,
    "gn:feature_class":"P",
    "gn:feature_code":"PPL",
    "gn:name":"\u1e28oseyn Ghalayem",
    "gn:population":0,
    "gn:timezone":"Asia/Tehran",
    "iso:country":"IR",
    "name:ceb_x_preferred":[
        "\u1e28oseyn Ghalayem"
    ],
    "name:fas_x_preferred":[
        "\u062d\u0633\u06cc\u0646 \u0642\u0644\u06cc\u0645"
    ],
    "name:fas_x_variant":[
        "Beyt-e Alv\u0101n",
        "\u0628\u06cc\u062a \u0627\u0644\u0648\u0627\u0646",
        "\u1e28oseyn Ghalayem",
        "\u062d\u0633\u06cc\u0646 \u063a\u0644\u06cc\u0645"
    ],
    "name:swe_x_preferred":[
        "\u1e28oseyn Ghalayem"
    ],
    "name:und_x_variant":[
        "\u1e28oseyn Qalayem"
    ],
    "wof:name":"Hoseyn Ghalayem",
    "wof:placetype":"locality"
},
  "geometry": {"coordinates":[48.39423,31.89662],"type":"Point"}
}