{
  "type": "Feature",
  "properties": {
    "gn:admin1_code":"35.0",
    "gn:asciiname":"Mahalleh-ye Mehdi Nasab",
    "gn:country_code":"IR",
    "gn:dem":-21,
    "gn:feature_class":"P",
    "gn:feature_code":"PPL",
    "gn:name":"Ma\u1e29alleh-ye Mehd\u012b Nasab",
    "gn:population":0,
    "gn:timezone":"Asia/Tehran",
    "iso:country":"IR",
    "name:fas_x_preferred":[
        "Ma\u1e29alleh-ye Mehd\u012b Nasab"
    ],
    "name:fas_x_variant":[
        "\u0645\u062d\u0644\u0647 \u0645\u0647\u062f\u06cc \u0646\u0633\u0628"
    ],
    "wof:name":"Mahalleh-ye Mehdi Nasab",
    "wof:placetype":"locality"
},
  "geometry": {"coordinates":[52.67537,36.69784],"type":"Point"}
}