{
  "type": "Feature",
  "properties": {
    "gn:admin1_code":"42",
    "gn:asciiname":"Hajjiabad",
    "gn:country_code":"IR",
    "gn:dem":1362,
    "gn:feature_class":"P",
    "gn:feature_code":"PPL",
    "gn:name":"\u1e28\u0101jj\u012b\u0101b\u0101d",
    "gn:population":0,
    "gn:timezone":"Asia/Tehran",
    "iso:country":"IR",
    "name:fas_x_preferred":[
        "\u1e28\u0101jj\u012b\u0101b\u0101d"
    ],
    "name:fas_x_variant":[
        "\u062d\u0627\u062c\u06cc \u0622\u0628\u0627\u062f",
        "\u062d\u0627\u062c\u06cc\u200c\u0622\u0628\u0627\u062f"
    ],
    "wof:name":"Hajjiabad",
    "wof:placetype":"locality"
},
  "geometry": {"coordinates":[59.35876,35.29388],"type":"Point"}
}