{
  "type": "Feature",
  "properties": {
    "gn:admin1_code":"4.0",
    "gn:asciiname":"Bani",
    "gn:country_code":"IR",
    "gn:dem":202,
    "gn:feature_class":"P",
    "gn:feature_code":"PPL",
    "gn:name":"B\u0101n\u012b",
    "gn:population":0,
    "gn:timezone":"Asia/Tehran",
    "iso:country":"IR",
    "name:fas_x_preferred":[
        "\u0628\u0627\u0646\u06cc"
    ],
    "name:und_x_variant":[
        "B\u0101n\u012b"
    ],
    "wof:name":"Bani",
    "wof:placetype":"locality"
},
  "geometry": {"coordinates":[59.42303,26.03875],"type":"Point"}
}