{
  "type": "Feature",
  "properties": {
    "gn:admin1_code":"44.0",
    "gn:asciiname":"Mahalleh-ye Larab",
    "gn:country_code":"IR",
    "gn:dem":2655,
    "gn:feature_class":"P",
    "gn:feature_code":"PPL",
    "gn:name":"Ma\u1e29alleh-ye L\u0101r\u0101b",
    "gn:population":0,
    "gn:timezone":"Asia/Tehran",
    "iso:country":"IR",
    "name:fas_x_preferred":[
        "\u0645\u062d\u0644\u0647 \u0644\u0627\u0631\u0627\u0628"
    ],
    "name:und_x_variant":[
        "Ma\u1e29alleh-ye L\u0101r\u0101b"
    ],
    "wof:name":"Mahalleh-ye Larab",
    "wof:placetype":"locality"
},
  "geometry": {"coordinates":[51.47292,36.02207],"type":"Point"}
}