{
  "type": "Feature",
  "properties": {
    "gn:admin1_code":"10.0",
    "gn:asciiname":"Sartang-e Sofla",
    "gn:country_code":"IR",
    "gn:dem":1020,
    "gn:feature_class":"P",
    "gn:feature_code":"PPL",
    "gn:name":"Sartang-e Sofl\u00e1",
    "gn:population":0,
    "gn:timezone":"Asia/Tehran",
    "iso:country":"IR",
    "name:fas_x_preferred":[
        "\u0633\u0631\u062a\u0646\u06af \u0633\u0641\u0644\u0649"
    ],
    "name:fas_x_variant":[
        "Sartang-e Sofl\u00e1"
    ],
    "wof:name":"Sartang-e Sofla",
    "wof:placetype":"locality"
},
  "geometry": {"coordinates":[46.1457,33.9134],"type":"Point"}
}