{
  "type": "Feature",
  "properties": {
    "gn:admin1_code":"34.0",
    "gn:asciiname":"Aqdash",
    "gn:country_code":"IR",
    "gn:dem":1901,
    "gn:feature_class":"P",
    "gn:feature_code":"PPL",
    "gn:name":"\u0100qd\u0101sh",
    "gn:population":0,
    "gn:timezone":"Asia/Tehran",
    "iso:country":"IR",
    "name:aze_x_preferred":[
        "A\u011fda\u015f"
    ],
    "name:ceb_x_preferred":[
        "A\u011fda\u015f"
    ],
    "name:deu_x_preferred":[
        "A\u011fda\u015f"
    ],
    "name:fas_x_preferred":[
        "\u0622\u0642\u062f\u0627\u0634"
    ],
    "name:fas_x_variant":[
        "\u0100qd\u0101sh",
        "\u0622\u063a\u200c\u062f\u0627\u0634"
    ],
    "name:hye_x_preferred":[
        "\u0531\u0572\u0564\u0561\u0577"
    ],
    "name:kat_x_preferred":[
        "\u10d0\u10e6\u10d3\u10d0\u10e8\u10d8"
    ],
    "name:nld_x_preferred":[
        "A\u011fda\u015f"
    ],
    "name:swe_x_preferred":[
        "A\u011fda\u015f"
    ],
    "wof:name":"Aqdash",
    "wof:placetype":"locality"
},
  "geometry": {"coordinates":[49.17092,34.24973],"type":"Point"}
}