{
  "type": "Feature",
  "properties": {
    "gn:admin1_code":"34.0",
    "gn:asciiname":"Aqdash",
    "gn:country_code":"IR",
    "gn:dem":1901,
    "gn:feature_class":"P",
    "gn:feature_code":"PPL",
    "gn:name":"\u0100qd\u0101sh",
    "gn:population":0,
    "gn:timezone":"Asia/Tehran",
    "iso:country":"IR",
    "name:fas_x_preferred":[
        "\u0622\u0642\u062f\u0627\u0634"
    ],
    "name:fas_x_variant":[
        "\u0100qd\u0101sh"
    ],
    "wof:name":"Aqdash",
    "wof:placetype":"locality"
},
  "geometry": {"coordinates":[49.17092,34.24973],"type":"Point"}
}