{
  "type": "Feature",
  "properties": {
    "gn:admin1_code":"11",
    "gn:asciiname":"Sarrik-e Mohammad Kamal Hoseyni",
    "gn:country_code":"IR",
    "gn:dem":60,
    "gn:feature_class":"P",
    "gn:feature_code":"PPL",
    "gn:name":"Sarr\u012bk-e Mo\u1e29ammad Kam\u0101l \u1e28oseyn\u012b",
    "gn:population":0,
    "gn:timezone":"Asia/Tehran",
    "iso:country":"IR",
    "name:fas_x_preferred":[
        "\u0633\u064e\u0631\u0651\u064a\u0643\u0650 \u0645\u064f\u062d\u064e\u0645\u064e\u0651\u062f \u0643\u064e\u0645\u0627\u0644 \u062d\u064f\u0633\u0650\u064a\u0646\u06cc"
    ],
    "name:fas_x_variant":[
        "Sarr\u012bk-e Mo\u1e29ammad Kam\u0101l \u1e28oseyn\u012b",
        "\u0633\u0631 \u0631\u06cc\u06af \u0633\u0648\u0645",
        "\u0633\u0631 \u0631\u06cc\u06af \u0633\u0647"
    ],
    "name:und_x_variant":[
        "Sar R\u012bg-e Sevvom",
        "Sar R\u012bg-e Seh"
    ],
    "wof:name":"Sarrik-e Mohammad Kamal Hoseyni",
    "wof:placetype":"locality"
},
  "geometry": {"coordinates":[56.2669,27.3034],"type":"Point"}
}