{
  "type": "Feature",
  "properties": {
    "gn:admin1_code":"29",
    "gn:asciiname":"Now Duzhu",
    "gn:cc2":"IR",
    "gn:country_code":"IR",
    "gn:dem":521,
    "gn:feature_class":"P",
    "gn:feature_code":"PPL",
    "gn:name":"Now D\u016bzh\u016b",
    "gn:population":0,
    "gn:timezone":"Asia/Tehran",
    "iso:country":"IR",
    "name:fas_x_preferred":[
        "Now D\u016bzh\u016b"
    ],
    "name:und_x_variant":[
        "Now Dezh"
    ],
    "wof:name":"Now Duzhu",
    "wof:placetype":"locality"
},
  "geometry": {"coordinates":[57.6375,27.26083],"type":"Point"}
}