{
  "type": "Feature",
  "properties": {
    "gn:admin1_code":"13",
    "gn:asciiname":"Gur-e Yahud",
    "gn:country_code":"IR",
    "gn:dem":1827,
    "gn:feature_class":"P",
    "gn:feature_code":"PPL",
    "gn:name":"G\u016br-e Yah\u016bd",
    "gn:population":0,
    "gn:timezone":"Asia/Tehran",
    "iso:country":"IR",
    "name:fas_x_preferred":[
        "G\u016br-e Yah\u016bd"
    ],
    "wof:name":"Gur-e Yahud",
    "wof:placetype":"locality"
},
  "geometry": {"coordinates":[47.58333,34.96667],"type":"Point"}
}