{
  "type": "Feature",
  "properties": {
    "gn:admin1_code":"7",
    "gn:asciiname":"Hakim Bashi-ye Hoseynabad",
    "gn:country_code":"IR",
    "gn:dem":767,
    "gn:feature_class":"P",
    "gn:feature_code":"PPL",
    "gn:name":"\u1e28ak\u012bm B\u0101sh\u012b-ye \u1e28oseyn\u0101b\u0101d",
    "gn:population":0,
    "gn:timezone":"Asia/Tehran",
    "iso:country":"IR",
    "name:fas_x_preferred":[
        "\u1e28ak\u012bm B\u0101sh\u012b-ye B\u0101l\u0101"
    ],
    "name:fas_x_variant":[
        "\u1e28ak\u012bm B\u0101sh\u012b-ye \u1e28oseyn\u0101b\u0101d",
        "\u062d\u06a9\u06cc\u0645 \u0628\u0627\u0634\u06cc \u062d\u0633\u06cc\u0646 \u0622\u0628\u0627\u062f",
        "\u062d\u06a9\u06cc\u0645\u200c\u0628\u0627\u0634\u06cc \u062d\u0633\u06cc\u0646\u200c\u0622\u0628\u0627\u062f"
    ],
    "name:msa_x_preferred":[
        "Hakim Bashi-ye Hoseynabad"
    ],
    "name:und_x_variant":[
        "Qal\u2018eh Hak\u012bm B\u0101shi B\u0101la",
        "\u1e28ak\u012bmb\u0101sh\u012b \u2018Oly\u0101",
        "Ne\u015ff-e M\u012b\u0101n",
        "\u1e28ak\u012bm B\u0101sh\u012b-ye \u1e28oseyn\u0101b\u0101d",
        "Qal\u2018eh-ye \u1e28ak\u012bm B\u0101sh\u012b",
        "\u062d\u06a9\u06cc\u0645 \u0628\u0627\u0634\u06cc \u062d\u0633\u06cc\u0646 \u0622\u0628\u0627\u062f"
    ],
    "wof:name":"Hakim Bashi-ye Hoseynabad",
    "wof:placetype":"locality"
},
  "geometry": {"coordinates":[51.53791,29.75437],"type":"Point"}
}