{
  "type": "Feature",
  "properties": {
    "gn:admin1_code":"1",
    "gn:asciiname":"Qeshlaq-e Bakhtiar",
    "gn:country_code":"IR",
    "gn:dem":1491,
    "gn:feature_class":"P",
    "gn:feature_code":"PPL",
    "gn:name":"Qeshl\u0101q-e Bakht\u012b\u0101r",
    "gn:population":0,
    "gn:timezone":"Asia/Tehran",
    "iso:country":"IR",
    "name:fas_x_preferred":[
        "Qeshl\u0101q-e Bakht\u012b\u0101r"
    ],
    "wof:name":"Qeshlaq-e Bakhtiar",
    "wof:placetype":"locality"
},
  "geometry": {"coordinates":[46.56667,36.75],"type":"Point"}
}