{
  "type": "Feature",
  "properties": {
    "gn:admin1_code":"35.0",
    "gn:asciiname":"Katu",
    "gn:country_code":"IR",
    "gn:dem":488,
    "gn:feature_class":"P",
    "gn:feature_code":"PPL",
    "gn:name":"Kat\u016b",
    "gn:population":0,
    "gn:timezone":"Asia/Tehran",
    "iso:country":"IR",
    "name:ceb_x_preferred":[
        "Katu"
    ],
    "name:deu_x_preferred":[
        "Katu"
    ],
    "name:fas_x_preferred":[
        "\u0643\u064e\u062a\u0648"
    ],
    "name:fas_x_variant":[
        "Kat\u016b"
    ],
    "name:fra_x_preferred":[
        "Katu"
    ],
    "name:hye_x_preferred":[
        "\u053f\u0561\u057f\u0578\u0582\u0576\u0565\u0580"
    ],
    "name:swe_x_preferred":[
        "Katu"
    ],
    "wof:name":"Katu",
    "wof:placetype":"locality"
},
  "geometry": {"coordinates":[52.86666999999999,36.28333],"type":"Point"}
}