{
  "type": "Feature",
  "properties": {
    "gn:admin1_code":"42",
    "gn:asciiname":"Hajji Jani",
    "gn:country_code":"IR",
    "gn:dem":1139,
    "gn:feature_class":"P",
    "gn:feature_code":"PPL",
    "gn:name":"\u1e28\u0101jj\u012b J\u0101n\u012b",
    "gn:population":0,
    "gn:timezone":"Asia/Tehran",
    "iso:country":"IR",
    "name:fas_x_preferred":[
        "Seb\u016bseh"
    ],
    "name:fas_x_variant":[
        "\u062d\u0627\u062c\u06cc \u062c\u0627\u0646\u06cc",
        "\u0633\u0628\u0648 \u0633\u0647"
    ],
    "name:und_x_variant":[
        "Ch\u0101h Tolombeh-ye \u2019\u0101jj\u012b J\u0101n\u012b Ch\u0101h",
        "\u1e28\u0101jj\u012b J\u0101n\u012b",
        "Sab\u016b Seh"
    ],
    "wof:name":"Hajji Jani",
    "wof:placetype":"locality"
},
  "geometry": {"coordinates":[59.18421,36.64914],"type":"Point"}
}