{
  "type": "Feature",
  "properties": {
    "gn:admin1_code":"26.0",
    "gn:asciiname":"Kalan",
    "gn:country_code":"IR",
    "gn:dem":2079,
    "gn:feature_class":"P",
    "gn:feature_code":"PPL",
    "gn:name":"Kal\u0101n",
    "gn:population":0,
    "gn:timezone":"Asia/Tehran",
    "iso:country":"IR",
    "name:fas_x_preferred":[
        "\u0643\u0644\u0627\u0646"
    ],
    "name:fas_x_variant":[
        "Kal\u0101n"
    ],
    "wof:name":"Kalan",
    "wof:placetype":"locality"
},
  "geometry": {"coordinates":[51.78992,35.80969],"type":"Point"}
}