{
  "type": "Feature",
  "properties": {
    "gn:admin1_code":"28",
    "gn:asciiname":"Khowshabad",
    "gn:country_code":"IR",
    "gn:dem":968,
    "gn:feature_class":"P",
    "gn:feature_code":"PPL",
    "gn:name":"Khowsh\u0101b\u0101d",
    "gn:population":0,
    "gn:timezone":"Asia/Tehran",
    "iso:country":"IR",
    "name:fas_x_preferred":[
        "\u062e\u0648\u0634 \u0622\u0628\u0627\u062f"
    ],
    "name:fas_x_variant":[
        "Khoshk\u0101b\u0101d",
        "\u062e\u0634\u06a9 \u0622\u0628\u0627\u062f",
        "\u062e\u0648\u0634\u200c\u0622\u0628\u0627\u062f"
    ],
    "name:und_x_variant":[
        "Khoshkb\u0101d",
        "Khosg\u0101b\u0101d",
        "Khowsh\u0101b\u0101d"
    ],
    "wof:name":"Khowshabad",
    "wof:placetype":"locality"
},
  "geometry": {"coordinates":[52.2405,33.5874],"type":"Point"}
}