{
  "type": "Feature",
  "properties": {
    "gn:admin1_code":"4",
    "gn:asciiname":"Samu'i",
    "gn:country_code":"IR",
    "gn:dem":1129,
    "gn:feature_class":"P",
    "gn:feature_code":"PPL",
    "gn:name":"Sam\u016b\u2019\u012b",
    "gn:population":0,
    "gn:timezone":"Asia/Tehran",
    "iso:country":"IR",
    "name:fas_x_preferred":[
        "\u0633\u0645\u0648\u0626\u06cc"
    ],
    "name:fas_x_variant":[
        "Sam\u016b\u2019\u012b"
    ],
    "wof:name":"Samu'i",
    "wof:placetype":"locality"
},
  "geometry": {"coordinates":[62.11600000000001,26.8394],"type":"Point"}
}