{
  "type": "Feature",
  "properties": {
    "gn:admin1_code":"0",
    "gn:asciiname":"Tappeh Gurestan",
    "gn:country_code":"IR",
    "gn:dem":1454,
    "gn:feature_class":"P",
    "gn:feature_code":"PPL",
    "gn:name":"Tappeh G\u016brest\u0101n",
    "gn:population":0,
    "gn:timezone":"Asia/Tehran",
    "iso:country":"IR",
    "name:fas_x_preferred":[
        "\u062a\u064e\u067e\u0650\u0651\u0647 \u06af\u0648\u0631\u0650\u0633\u062a\u0627\u0646"
    ],
    "name:fas_x_variant":[
        "Tappeh G\u016brest\u0101n"
    ],
    "wof:name":"Tappeh Gurestan",
    "wof:placetype":"locality"
},
  "geometry": {"coordinates":[48.63333,38.25],"type":"Point"}
}