{
  "type": "Feature",
  "properties": {
    "gn:admin1_code":"29",
    "gn:asciiname":"Kahnuj",
    "gn:country_code":"IR",
    "gn:dem":2838,
    "gn:feature_class":"P",
    "gn:feature_code":"PPL",
    "gn:name":"Kahn\u016bj",
    "gn:population":0,
    "gn:timezone":"Asia/Tehran",
    "iso:country":"IR",
    "name:ceb_x_preferred":[
        "Kahn\u016bj"
    ],
    "name:fas_x_preferred":[
        "Deh V\u0101l\u012b"
    ],
    "name:fas_x_variant":[
        "\u062f\u0647 \u0648\u0627\u0644\u06cc",
        "\u06a9\u0647\u0646\u0648\u062c"
    ],
    "name:und_x_variant":[
        "\u062f\u0647 \u0648\u0627\u0644\u06cc",
        "Kahn\u016bj"
    ],
    "wof:name":"Kahnuj",
    "wof:placetype":"locality"
},
  "geometry": {"coordinates":[57.32653000000001,29.19421],"type":"Point"}
}