{
  "type": "Feature",
  "properties": {
    "gn:admin1_code":"13",
    "gn:asciiname":"Kureh",
    "gn:country_code":"IR",
    "gn:dem":1824,
    "gn:feature_class":"P",
    "gn:feature_code":"PPL",
    "gn:name":"K\u016breh",
    "gn:population":0,
    "gn:timezone":"Asia/Tehran",
    "iso:country":"IR",
    "name:fas_x_preferred":[
        "\u06a9\u0648\u0631\u0647"
    ],
    "name:fas_x_variant":[
        "K\u016breh"
    ],
    "wof:name":"Kureh",
    "wof:placetype":"locality"
},
  "geometry": {"coordinates":[47.2304,34.7544],"type":"Point"}
}