{
  "type": "Feature",
  "properties": {
    "gn:admin1_code":"35.0",
    "gn:asciiname":"Limak",
    "gn:country_code":"IR",
    "gn:dem":56,
    "gn:feature_class":"P",
    "gn:feature_code":"PPL",
    "gn:name":"L\u012bm\u0101k",
    "gn:population":0,
    "gn:timezone":"Asia/Tehran",
    "iso:country":"IR",
    "name:fas_x_preferred":[
        "L\u012bm\u0101k"
    ],
    "name:fas_x_variant":[
        "\u0644\u06cc\u0645\u0627\u06a9"
    ],
    "name:und_x_variant":[
        "\u0644\u06cc\u0645\u0627\u06a9"
    ],
    "wof:name":"Limak",
    "wof:placetype":"locality"
},
  "geometry": {"coordinates":[50.73917,36.84031],"type":"Point"}
}