{
  "type": "Feature",
  "properties": {
    "gn:admin1_code":"29.0",
    "gn:asciiname":"Bagh-e Hoseyn Beyg",
    "gn:cc2":"IR",
    "gn:country_code":"IR",
    "gn:dem":1818,
    "gn:feature_class":"P",
    "gn:feature_code":"PPL",
    "gn:name":"B\u0101gh-e \u1e28oseyn Beyg",
    "gn:population":0,
    "gn:timezone":"Asia/Tehran",
    "iso:country":"IR",
    "name:fas_x_preferred":[
        "B\u0101gh-e \u1e28oseyn Beyg"
    ],
    "name:und_x_variant":[
        "B\u0101gh-i-Husain Beg"
    ],
    "wof:name":"Bagh-e Hoseyn Beyg",
    "wof:placetype":"locality"
},
  "geometry": {"coordinates":[57.31667,30.48333],"type":"Point"}
}