{
  "type": "Feature",
  "properties": {
    "gn:admin1_code":"29.0",
    "gn:asciiname":"Zanaghi",
    "gn:country_code":"IR",
    "gn:dem":1668,
    "gn:feature_class":"P",
    "gn:feature_code":"PPLL",
    "gn:name":"Zan\u0101gh\u012b",
    "gn:population":0,
    "gn:timezone":"Asia/Tehran",
    "iso:country":"IR",
    "name:fas_x_preferred":[
        "\u0632\u0646\u0627\u063a\u06cc"
    ],
    "name:und_x_variant":[
        "Zan\u0101gh\u012b"
    ],
    "wof:name":"Zanaghi",
    "wof:placetype":"locality"
},
  "geometry": {"coordinates":[58.54748000000001,28.39294000000001],"type":"Point"}
}