{
  "type": "Feature",
  "properties": {
    "gn:admin1_code":"11",
    "gn:asciiname":"Chah-e Mohammad `Ali",
    "gn:country_code":"IR",
    "gn:dem":15,
    "gn:feature_class":"P",
    "gn:feature_code":"PPL",
    "gn:name":"Ch\u0101h-e Mo\u1e29ammad \u2018Al\u012b",
    "gn:population":0,
    "gn:timezone":"Asia/Tehran",
    "iso:country":"IR",
    "name:fas_x_preferred":[
        "\u0686\u0627\u0647\u0650 \u0645\u064f\u062d\u064e\u0645\u064e\u0651\u062f \u0639\u064e\u0644\u06cc"
    ],
    "name:fas_x_variant":[
        "Ch\u0101h-e Mo\u1e29ammad \u2018Al\u012b"
    ],
    "wof:name":"Chah-e Mohammad `Ali",
    "wof:placetype":"locality"
},
  "geometry": {"coordinates":[56.37889000000001,27.25],"type":"Point"}
}