{
  "type": "Feature",
  "properties": {
    "gn:admin1_code":"33",
    "gn:asciiname":"Chichakli",
    "gn:country_code":"IR",
    "gn:dem":2431,
    "gn:feature_class":"P",
    "gn:feature_code":"PPL",
    "gn:name":"Ch\u012bchakl\u012b",
    "gn:population":0,
    "gn:timezone":"Asia/Tehran",
    "iso:country":"IR",
    "name:fas_x_preferred":[
        "\u0686\u06cc\u0686\u06a9\u0644\u0648"
    ],
    "name:fas_x_variant":[
        "Ch\u012bchakl\u016b",
        "\u0686\u06cc\u0686\u06a9\u0644\u06cc"
    ],
    "name:und_x_variant":[
        "Ch\u012bchakl\u012b"
    ],
    "wof:name":"Chichakli",
    "wof:placetype":"locality"
},
  "geometry": {"coordinates":[46.5428,37.6669],"type":"Point"}
}