{
  "type": "Feature",
  "properties": {
    "gn:admin1_code":"1",
    "gn:asciiname":"Panah Kandi",
    "gn:country_code":"IR",
    "gn:dem":812,
    "gn:feature_class":"P",
    "gn:feature_code":"PPL",
    "gn:name":"Pan\u0101h Kand\u012b",
    "gn:population":0,
    "gn:timezone":"Asia/Tehran",
    "iso:country":"IR",
    "name:fas_x_preferred":[
        "\u067e\u064e\u0646\u0627\u0647 \u0643\u064e\u0646\u062f\u06cc"
    ],
    "name:fas_x_variant":[
        "\u067e\u0646\u0627\u0647 \u06a9\u0646\u062f\u06cc",
        "Pan\u0101h Kand\u012b"
    ],
    "wof:name":"Panah Kandi",
    "wof:placetype":"locality"
},
  "geometry": {"coordinates":[45.0308,39.2716],"type":"Point"}
}