{
  "type": "Feature",
  "properties": {
    "gn:admin1_code":"11",
    "gn:asciiname":"Keltu'iyeh",
    "gn:country_code":"IR",
    "gn:dem":1157,
    "gn:feature_class":"P",
    "gn:feature_code":"PPL",
    "gn:name":"Kelt\u016b\u2019\u012byeh",
    "gn:population":0,
    "gn:timezone":"Asia/Tehran",
    "iso:country":"IR",
    "name:fas_x_preferred":[
        "\u0643\u0650\u0644\u0627\u062a\u0648"
    ],
    "name:fas_x_variant":[
        "\u0686\u0650\u0647\u0686\u064f\u0651",
        "\u0643\u064e\u0644\u0627\u062a\u0648",
        "\u0643\u064e\u0644\u064e\u062a\u064f",
        "\u0643\u064e\u0644\u064a\u062a\u0648\u064a\u0650\u0647",
        "\u06a9\u0644\u06cc \u062a\u0648",
        "Kel\u012bt\u016b\u2019\u012byeh",
        "Kel\u012b T\u016b",
        "\u0643\u0644\u062a\u0648\u0626\u064a\u0650\u0647",
        "\u06a9\u0644\u06cc\u062a\u0648 \u0626\u06cc\u0647"
    ],
    "name:msa_x_preferred":[
        "Kelituiyeh"
    ],
    "name:und_x_variant":[
        "Kalato",
        "Kel\u0101t\u016b",
        "Kal\u0101t\u016b",
        "Chehchoo",
        "Kal\u012bt\u016byeh",
        "Kelt\u016b\u2019\u012byeh"
    ],
    "wof:name":"Keltu'iyeh",
    "wof:placetype":"locality"
},
  "geometry": {"coordinates":[56.75156,28.03574],"type":"Point"}
}