{
  "type": "Feature",
  "properties": {
    "gn:admin1_code":"7.0",
    "gn:asciiname":"Tammaru",
    "gn:country_code":"IR",
    "gn:dem":459,
    "gn:feature_class":"P",
    "gn:feature_code":"PPL",
    "gn:name":"Tammar\u016b",
    "gn:population":0,
    "gn:timezone":"Asia/Tehran",
    "iso:country":"IR",
    "name:fas_x_preferred":[
        "\u062a\u0645\u0651\u0631\u0648"
    ],
    "name:fas_x_variant":[
        "Tamr\u016b",
        "Tammar\u016b",
        "\u062a\u0645\u0631\u0648\u06cc\u0647"
    ],
    "name:msa_x_preferred":[
        "Tammaru"
    ],
    "wof:name":"Tammaru",
    "wof:placetype":"locality"
},
  "geometry": {"coordinates":[53.2176,27.5313],"type":"Point"}
}