{
  "type": "Feature",
  "properties": {
    "gn:admin1_code":"15.0",
    "gn:asciiname":"Ab Zard",
    "gn:country_code":"IR",
    "gn:dem":814,
    "gn:feature_class":"P",
    "gn:feature_code":"PPL",
    "gn:name":"\u0100b Zard",
    "gn:population":0,
    "gn:timezone":"Asia/Tehran",
    "iso:country":"IR",
    "name:fas_x_preferred":[
        "\u0100b Zard"
    ],
    "wof:name":"Ab Zard",
    "wof:placetype":"locality"
},
  "geometry": {"coordinates":[50.01583,31.43139],"type":"Point"}
}