{
  "type": "Feature",
  "properties": {
    "gn:admin1_code":"8",
    "gn:asciiname":"Parneh Gah",
    "gn:country_code":"IR",
    "gn:dem":118,
    "gn:feature_class":"P",
    "gn:feature_code":"PPLL",
    "gn:name":"Parneh G\u0101h",
    "gn:population":0,
    "gn:timezone":"Asia/Tehran",
    "iso:country":"IR",
    "name:fas_x_preferred":[
        "\u067e\u0631\u0646\u0647 \u06af\u0627\u0647"
    ],
    "name:fas_x_variant":[
        "Parneh G\u0101h"
    ],
    "wof:name":"Parneh Gah",
    "wof:placetype":"locality"
},
  "geometry": {"coordinates":[48.8808,37.7612],"type":"Point"}
}