{
  "type": "Feature",
  "properties": {
    "gn:admin1_code":"26.0",
    "gn:asciiname":"Alard",
    "gn:country_code":"IR",
    "gn:dem":1062,
    "gn:feature_class":"P",
    "gn:feature_code":"PPL",
    "gn:name":"\u0100l\u0101rd",
    "gn:population":0,
    "gn:timezone":"Asia/Tehran",
    "iso:country":"IR",
    "name:fas_x_preferred":[
        "\u0627\u064e\u0644\u0627\u0631\u062f"
    ],
    "name:fas_x_variant":[
        "\u0622\u0644\u0627\u0631\u062f",
        "\u0627\u0644\u0627\u0631\u062f \u0686\u0647\u0627\u0631 \u062f\u0627\u0646\u06af",
        "Al\u0101rd",
        "Al\u0101rd-e Chah\u0101r D\u0101ng",
        "\u0627\u0644\u0627\u0631\u062f"
    ],
    "name:und_x_variant":[
        "\u0100l\u0101rd"
    ],
    "wof:name":"Alard",
    "wof:placetype":"locality"
},
  "geometry": {"coordinates":[51.05959,35.51296],"type":"Point"}
}