{
  "type": "Feature",
  "properties": {
    "gn:admin1_code":"34",
    "gn:asciiname":"Darestan",
    "gn:country_code":"IR",
    "gn:dem":1953,
    "gn:feature_class":"P",
    "gn:feature_code":"PPL",
    "gn:name":"D\u0101rest\u0101n",
    "gn:population":0,
    "gn:timezone":"Asia/Tehran",
    "iso:country":"IR",
    "name:fas_x_preferred":[
        "D\u0101rest\u0101n"
    ],
    "name:fas_x_variant":[
        "\u062f\u0627\u0631\u0633\u062a\u0627\u0646"
    ],
    "name:und_x_variant":[
        "Darist\u0101n",
        "\u062f\u0627\u0631\u0633\u062a\u0627\u0646"
    ],
    "wof:name":"Darestan",
    "wof:placetype":"locality"
},
  "geometry": {"coordinates":[49.80736,34.55947],"type":"Point"}
}