{
  "type": "Feature",
  "properties": {
    "gn:admin1_code":"16",
    "gn:asciiname":"Sheykhaleh",
    "gn:country_code":"IR",
    "gn:dem":1528,
    "gn:feature_class":"P",
    "gn:feature_code":"PPL",
    "gn:name":"Sheykhaleh",
    "gn:population":0,
    "gn:timezone":"Asia/Tehran",
    "iso:country":"IR",
    "name:ara_x_preferred":[
        "\u0634\u064a\u062e\u0644\u0647"
    ],
    "name:ckb_x_preferred":[
        "\u0634\u06ce\u062e\u06d5\u06b5\u06d5"
    ],
    "name:fas_x_preferred":[
        "\u0634\u064a\u062e \u0639\u0644\u06cc"
    ],
    "name:fas_x_variant":[
        "Sheykh \u2018Al\u012b",
        "\u0634\u06cc\u062e\u0644\u0647"
    ],
    "name:kur_x_preferred":[
        "\u015e\u00eaxelle"
    ],
    "wof:name":"Sheykhaleh",
    "wof:placetype":"locality"
},
  "geometry": {"coordinates":[46.52591,36.12211],"type":"Point"}
}