{
  "type": "Feature",
  "properties": {
    "gn:admin1_code":"34",
    "gn:asciiname":"Ghiasabad-e Bala",
    "gn:country_code":"IR",
    "gn:dem":1826,
    "gn:feature_class":"P",
    "gn:feature_code":"PPL",
    "gn:name":"Gh\u012b\u0101s\u0304\u0101b\u0101d-e B\u0101l\u0101",
    "gn:population":0,
    "gn:timezone":"Asia/Tehran",
    "iso:country":"IR",
    "name:fas_x_preferred":[
        "\u063a\u06cc\u0627\u062b \u0622\u0628\u0627\u062f \u0628\u0627\u0644\u0627"
    ],
    "name:fas_x_variant":[
        "Gh\u012b\u0101s\u0304\u0101b\u0101d",
        "Gh\u012b\u0101s\u0304\u0101b\u0101d-e B\u0101l\u0101",
        "\u063a\u06cc\u0627\u062b \u0622\u0628\u0627\u062f"
    ],
    "wof:name":"Ghiasabad-e Bala",
    "wof:placetype":"locality"
},
  "geometry": {"coordinates":[51.03791,34.04348],"type":"Point"}
}