{
  "type": "Feature",
  "properties": {
    "gn:admin1_code":"23.0",
    "gn:asciiname":"Hatami",
    "gn:country_code":"IR",
    "gn:dem":1214,
    "gn:feature_class":"P",
    "gn:feature_code":"PPL",
    "gn:name":"\u1e28\u0101tam\u012b",
    "gn:population":0,
    "gn:timezone":"Asia/Tehran",
    "iso:country":"IR",
    "name:deu_x_preferred":[
        "Hatami"
    ],
    "name:fas_x_preferred":[
        "\u062d\u0627\u062a\u0645\u06cc"
    ],
    "name:fas_x_variant":[
        "\u1e28\u0101tam\u012b"
    ],
    "wof:name":"Hatami",
    "wof:placetype":"locality"
},
  "geometry": {"coordinates":[48.145,33.5383],"type":"Point"}
}