{
  "type": "Feature",
  "properties": {
    "gn:admin1_code":"29.0",
    "gn:asciiname":"Darreh Now",
    "gn:country_code":"IR",
    "gn:dem":2760,
    "gn:feature_class":"P",
    "gn:feature_code":"PPL",
    "gn:name":"Darreh Now",
    "gn:population":0,
    "gn:timezone":"Asia/Tehran",
    "iso:country":"IR",
    "wof:name":"Darreh Now",
    "wof:placetype":"locality"
},
  "geometry": {"coordinates":[57.3225,29.21444],"type":"Point"}
}