{
  "type": "Feature",
  "properties": {
    "gn:admin1_code":"4.0",
    "gn:asciiname":"Haftadong",
    "gn:country_code":"IR",
    "gn:dem":43,
    "gn:feature_class":"P",
    "gn:feature_code":"PPL",
    "gn:name":"Haft\u0101dong",
    "gn:population":0,
    "gn:timezone":"Asia/Tehran",
    "iso:country":"IR",
    "name:fas_x_preferred":[
        "Haft\u0101dong"
    ],
    "name:fas_x_variant":[
        "\u0647\u0641\u062a\u0627\u062f\u0646\u06af"
    ],
    "name:und_x_variant":[
        "\u0647\u0641\u062a\u0627\u062f\u0646\u06af"
    ],
    "wof:name":"Haftadong",
    "wof:placetype":"locality"
},
  "geometry": {"coordinates":[61.0196,25.77154],"type":"Point"}
}