{
  "type": "Feature",
  "properties": {
    "gn:admin1_code":"35.0",
    "gn:asciiname":"Kur Kola",
    "gn:country_code":"IR",
    "gn:dem":-9,
    "gn:feature_class":"P",
    "gn:feature_code":"PPL",
    "gn:name":"K\u016br Kol\u0101",
    "gn:population":0,
    "gn:timezone":"Asia/Tehran",
    "iso:country":"IR",
    "name:fas_x_preferred":[
        "\u0643\u0648\u0631\u0650\u0647 \u0643\u0644\u0627"
    ],
    "name:fas_x_variant":[
        "K\u016br Kol\u0101",
        "\u06a9\u0648\u0631 \u06a9\u0644\u0627",
        "K\u016breh Kol\u0101"
    ],
    "name:und_x_variant":[
        "K\u016br Kal\u0101"
    ],
    "wof:name":"Kur Kola",
    "wof:placetype":"locality"
},
  "geometry": {"coordinates":[51.09907000000001,36.71294],"type":"Point"}
}