{
  "type": "Feature",
  "properties": {
    "gn:admin1_code":"1",
    "gn:asciiname":"Kar kosh",
    "gn:country_code":"IR",
    "gn:dem":2392,
    "gn:feature_class":"P",
    "gn:feature_code":"PPL",
    "gn:name":"Kar kosh",
    "gn:population":0,
    "gn:timezone":"Asia/Tehran",
    "iso:country":"IR",
    "name:fas_x_preferred":[
        "\u06a9\u0631\u06a9\u0648\u0634"
    ],
    "name:und_x_variant":[
        "Garkosh",
        "Kar kosh",
        "\u06a9\u0631\u06a9\u0648\u0634"
    ],
    "wof:name":"Kar kosh",
    "wof:placetype":"locality"
},
  "geometry": {"coordinates":[44.2866,38.726],"type":"Point"}
}