{
  "type": "Feature",
  "properties": {
    "gn:admin1_code":"16",
    "gn:asciiname":"Nazemabad",
    "gn:country_code":"IR",
    "gn:dem":1813,
    "gn:feature_class":"P",
    "gn:feature_code":"PPL",
    "gn:name":"N\u0101z\u0327em\u0101b\u0101d",
    "gn:population":0,
    "gn:timezone":"Asia/Tehran",
    "iso:country":"IR",
    "name:fas_x_preferred":[
        "\u062a\u0627\u0632\u0650\u0647 \u0622\u0628\u0627\u062f"
    ],
    "name:fas_x_variant":[
        "\u062a\u0627\u0632\u0650\u0647\u0627\u0628\u0627\u062f\u0650 \u062f\u064a\u0632\u064e\u062c",
        "\u0646\u0627\u0638\u0645 \u0622\u0628\u0627\u062f",
        "T\u0101zeh\u0101b\u0101d",
        "N\u0101z\u0327em\u0101b\u0101d"
    ],
    "name:und_x_variant":[
        "T\u0101zeh\u0101b\u0101d-e D\u012bzaj"
    ],
    "wof:name":"Nazemabad",
    "wof:placetype":"locality"
},
  "geometry": {"coordinates":[47.97234,35.10683],"type":"Point"}
}