{
  "type": "Feature",
  "properties": {
    "gn:admin1_code":"4.0",
    "gn:asciiname":"Mir Benze'i",
    "gn:country_code":"IR",
    "gn:dem":45,
    "gn:feature_class":"P",
    "gn:feature_code":"PPL",
    "gn:name":"M\u012br Benze\u2019\u012b",
    "gn:population":0,
    "gn:timezone":"Asia/Tehran",
    "iso:country":"IR",
    "name:fas_x_preferred":[
        "M\u012br Benze\u2019\u012b"
    ],
    "name:und_x_variant":[
        "M\u012br Banze\u2019t",
        "M\u012br Banze\u2019\u012b"
    ],
    "wof:name":"Mir Benze'i",
    "wof:placetype":"locality"
},
  "geometry": {"coordinates":[60.91639,25.70306],"type":"Point"}
}