{
  "type": "Feature",
  "properties": {
    "gn:admin1_code":"42",
    "gn:asciiname":"Murdestan",
    "gn:country_code":"IR",
    "gn:dem":1122,
    "gn:feature_class":"P",
    "gn:feature_code":"PPL",
    "gn:name":"M\u016brdest\u0101n",
    "gn:population":0,
    "gn:timezone":"Asia/Tehran",
    "iso:country":"IR",
    "name:fas_x_preferred":[
        "Z\u012brak"
    ],
    "name:fas_x_variant":[
        "\u0632\u06cc\u0631\u06a9",
        "\u0645\u0648\u0631\u062f\u0633\u062a\u0627\u0646"
    ],
    "name:und_x_variant":[
        "\u0632\u06cc\u0631\u06a9",
        "M\u016brdest\u0101n",
        "Murdest\u0101n"
    ],
    "wof:name":"Murdestan",
    "wof:placetype":"locality"
},
  "geometry": {"coordinates":[57.30749,33.80922],"type":"Point"}
}