{
  "type": "Feature",
  "properties": {
    "gn:admin1_code":"16",
    "gn:asciiname":"Marenj",
    "gn:country_code":"IR",
    "gn:dem":1730,
    "gn:feature_class":"P",
    "gn:feature_code":"PPL",
    "gn:name":"M\u0101renj",
    "gn:population":0,
    "gn:timezone":"Asia/Tehran",
    "iso:country":"IR",
    "name:fas_x_preferred":[
        "\u0645\u0627\u0631\u0646\u062c"
    ],
    "name:fas_x_variant":[
        "M\u0101renj"
    ],
    "name:und_x_variant":[
        "Malrenj",
        "M\u0101r\u012bnj",
        "M\u0101rj"
    ],
    "wof:name":"Marenj",
    "wof:placetype":"locality"
},
  "geometry": {"coordinates":[47.13637,35.07171],"type":"Point"}
}