{
  "type": "Feature",
  "properties": {
    "gn:admin1_code":"11",
    "gn:asciiname":"Kamuni",
    "gn:country_code":"IR",
    "gn:dem":1138,
    "gn:feature_class":"P",
    "gn:feature_code":"PPL",
    "gn:name":"Kam\u016bn\u012b",
    "gn:population":0,
    "gn:timezone":"Asia/Tehran",
    "iso:country":"IR",
    "name:fas_x_preferred":[
        "\u06a9\u0645\u0648\u0646\u06cc"
    ],
    "name:fas_x_variant":[
        "Kam\u016bn\u012b"
    ],
    "wof:name":"Kamuni",
    "wof:placetype":"locality"
},
  "geometry": {"coordinates":[56.1097,27.8859],"type":"Point"}
}