{
  "type": "Feature",
  "properties": {
    "gn:admin1_code":"13.0",
    "gn:asciiname":"Pir Hayati-ye Pa'in",
    "gn:country_code":"IR",
    "gn:dem":1357,
    "gn:feature_class":"P",
    "gn:feature_code":"PPL",
    "gn:name":"P\u012br \u1e28ay\u0101t\u012b-ye P\u0101\u2019\u012bn",
    "gn:population":0,
    "gn:timezone":"Asia/Tehran",
    "iso:country":"IR",
    "name:fas_x_preferred":[
        "P\u012br \u1e28ay\u0101t\u012b-ye P\u0101\u2019\u012bn"
    ],
    "wof:name":"Pir Hayati-ye Pa'in",
    "wof:placetype":"locality"
},
  "geometry": {"coordinates":[46.78333,34.28333],"type":"Point"}
}