{
  "type": "Feature",
  "properties": {
    "gn:admin1_code":"35.0",
    "gn:asciiname":"Zardeh Kand",
    "gn:country_code":"IR",
    "gn:dem":428,
    "gn:feature_class":"P",
    "gn:feature_code":"PPL",
    "gn:name":"Zardeh Kand",
    "gn:population":0,
    "gn:timezone":"Asia/Tehran",
    "iso:country":"IR",
    "name:fas_x_preferred":[
        "\u0632\u0631\u062f \u06a9\u0646\u062f"
    ],
    "name:fas_x_variant":[
        "\u0632\u0631\u062f\u0647 \u06a9\u0646\u062f"
    ],
    "name:und_x_variant":[
        "Zard Kand",
        "\u0632\u0631\u062f \u06a9\u0646\u062f",
        "Zardeh Kand"
    ],
    "wof:name":"Zardeh Kand",
    "wof:placetype":"locality"
},
  "geometry": {"coordinates":[50.83691,36.67632],"type":"Point"}
}