{
  "type": "Feature",
  "properties": {
    "gn:admin1_code":"7",
    "gn:asciiname":"Kereft",
    "gn:country_code":"IR",
    "gn:dem":1629,
    "gn:feature_class":"P",
    "gn:feature_code":"PPL",
    "gn:name":"Kereft",
    "gn:population":0,
    "gn:timezone":"Asia/Tehran",
    "iso:country":"IR",
    "name:fas_x_preferred":[
        "\u06a9\u0631\u0641\u062a"
    ],
    "name:msa_x_preferred":[
        "Kereft"
    ],
    "wof:name":"Kereft",
    "wof:placetype":"locality"
},
  "geometry": {"coordinates":[52.8738,29.0098],"type":"Point"}
}