{
  "type": "Feature",
  "properties": {
    "gn:admin1_code":"28.0",
    "gn:asciiname":"Shahrak-e Faz-e Do",
    "gn:country_code":"IR",
    "gn:dem":1841,
    "gn:feature_class":"P",
    "gn:feature_code":"PPL",
    "gn:name":"Shahrak-e F\u0101z-e Do",
    "gn:population":0,
    "gn:timezone":"Asia/Tehran",
    "iso:country":"IR",
    "name:fas_x_preferred":[
        "\u0634\u0647\u0631\u06a9 \u0641\u0627\u0632 \u0662"
    ],
    "name:und_x_variant":[
        "Shahrak-e F\u0101z-e Do"
    ],
    "wof:name":"Shahrak-e Faz-e Do",
    "wof:placetype":"locality"
},
  "geometry": {"coordinates":[51.832,31.995],"type":"Point"}
}