{
  "type": "Feature",
  "properties": {
    "gn:admin1_code":"29",
    "gn:asciiname":"Kahn Sameh",
    "gn:cc2":"IR",
    "gn:country_code":"IR",
    "gn:dem":2717,
    "gn:feature_class":"P",
    "gn:feature_code":"PPL",
    "gn:name":"Kahn Sameh",
    "gn:population":0,
    "gn:timezone":"Asia/Tehran",
    "iso:country":"IR",
    "name:fas_x_preferred":[
        "\u0643\u064e\u0647\u0646 \u0633\u064e\u0645\u0650\u0647"
    ],
    "name:fas_x_variant":[
        "\u0643\u064e\u0646 \u0633\u064e\u0645\u0648"
    ],
    "name:und_x_variant":[
        "Khanamandi",
        "Kan Sam\u016b",
        "Kahn Sameh"
    ],
    "wof:name":"Kahn Sameh",
    "wof:placetype":"locality"
},
  "geometry": {"coordinates":[57.32417,29.22222],"type":"Point"}
}