{
  "type": "Feature",
  "properties": {
    "gn:admin1_code":"34",
    "gn:asciiname":"Saman",
    "gn:country_code":"IR",
    "gn:dem":1924,
    "gn:feature_class":"P",
    "gn:feature_code":"PPL",
    "gn:name":"S\u0101m\u0101n",
    "gn:population":0,
    "gn:timezone":"Asia/Tehran",
    "iso:country":"IR",
    "name:ceb_x_preferred":[
        "Saman"
    ],
    "name:fas_x_preferred":[
        "\u0633\u0627\u0645\u0627\u0646"
    ],
    "name:fas_x_variant":[
        "S\u0101m\u0101n Qal\u2018eh-ye P\u0101\u2019\u012bn",
        "S\u0101m\u0101n"
    ],
    "name:fra_x_preferred":[
        "Saman"
    ],
    "name:ind_x_preferred":[
        "Saman"
    ],
    "name:kat_x_preferred":[
        "\u10e1\u10d0\u10db\u10d0\u10dc\u10d8"
    ],
    "name:nld_x_preferred":[
        "Saman"
    ],
    "name:pol_x_preferred":[
        "Saman"
    ],
    "name:rus_x_preferred":[
        "\u0421\u0430\u043c\u0430\u043d"
    ],
    "name:swe_x_preferred":[
        "Saman"
    ],
    "name:ukr_x_preferred":[
        "\u0421\u0430\u043c\u0430\u043d"
    ],
    "wof:name":"Saman",
    "wof:placetype":"locality"
},
  "geometry": {"coordinates":[49.57681,35.25852000000001],"type":"Point"}
}