{
  "type": "Feature",
  "properties": {
    "gn:admin1_code":"13",
    "gn:asciiname":"Bidkholah",
    "gn:country_code":"IR",
    "gn:dem":1434,
    "gn:feature_class":"P",
    "gn:feature_code":"PPL",
    "gn:name":"B\u012bdkholah",
    "gn:population":0,
    "gn:timezone":"Asia/Tehran",
    "iso:country":"IR",
    "name:fas_x_preferred":[
        "\u0628\u06cc\u062f\u062e\u0644\u0647"
    ],
    "name:fas_x_variant":[
        "B\u012bdkholah"
    ],
    "wof:name":"Bidkholah",
    "wof:placetype":"locality"
},
  "geometry": {"coordinates":[47.7971,34.3607],"type":"Point"}
}