{
  "type": "Feature",
  "properties": {
    "gn:admin1_code":"15",
    "gn:asciiname":"Dowbalutan",
    "gn:country_code":"IR",
    "gn:dem":1026,
    "gn:feature_class":"P",
    "gn:feature_code":"PPL",
    "gn:name":"Dowbal\u016bt\u0101n",
    "gn:population":0,
    "gn:timezone":"Asia/Tehran",
    "iso:country":"IR",
    "name:fas_x_preferred":[
        "Do Bal\u016b\u0163\u0101n"
    ],
    "name:fas_x_variant":[
        "\u062f\u0648 \u0628\u0644\u0648\u062a\u0627\u0646",
        "Dowbal\u016bt\u0101n",
        "\u067e\u0633 \u062a\u062e\u062a \u0633\u0631\u0644\u0627"
    ],
    "name:und_x_variant":[
        "Pas Takht-e Sarl\u0101"
    ],
    "wof:name":"Dowbalutan",
    "wof:placetype":"locality"
},
  "geometry": {"coordinates":[49.56559,31.87872],"type":"Point"}
}