{
  "type": "Feature",
  "properties": {
    "gn:admin1_code":"11",
    "gn:asciiname":"Chah Bashir",
    "gn:country_code":"IR",
    "gn:dem":1677,
    "gn:feature_class":"P",
    "gn:feature_code":"PPL",
    "gn:name":"Ch\u0101h Bash\u012br",
    "gn:population":0,
    "gn:timezone":"Asia/Tehran",
    "iso:country":"IR",
    "name:fas_x_preferred":[
        "\u0686\u0627\u0647 \u0628\u0634\u06cc\u0631"
    ],
    "name:fas_x_variant":[
        "Ch\u0101h Bash\u012br"
    ],
    "wof:name":"Chah Bashir",
    "wof:placetype":"locality"
},
  "geometry": {"coordinates":[55.9572,28.7286],"type":"Point"}
}