{
  "type": "Feature",
  "properties": {
    "gn:admin1_code":"29",
    "gn:asciiname":"Mohammadabad Seyyed Nezami",
    "gn:cc2":"IR",
    "gn:country_code":"IR",
    "gn:dem":903,
    "gn:feature_class":"P",
    "gn:feature_code":"PPL",
    "gn:name":"Mo\u1e29ammad\u0101b\u0101d Seyyed Nez\u0101m\u012b",
    "gn:population":0,
    "gn:timezone":"Asia/Tehran",
    "iso:country":"IR",
    "name:fas_x_preferred":[
        "Mo\u1e29ammad\u0101b\u0101d Seyyed Nez\u0101m\u012b"
    ],
    "name:und_x_variant":[
        "Mo\u1e29amm\u0101dab\u0101d",
        "Mohammad Abad Seyyed"
    ],
    "wof:name":"Mohammadabad Seyyed Nezami",
    "wof:placetype":"locality"
},
  "geometry": {"coordinates":[58.49806,29.15028],"type":"Point"}
}