{
  "type": "Feature",
  "properties": {
    "gn:admin1_code":"13",
    "gn:asciiname":"Mian Rud",
    "gn:country_code":"IR",
    "gn:dem":672,
    "gn:feature_class":"P",
    "gn:feature_code":"PPL",
    "gn:name":"M\u012b\u0101n R\u016bd",
    "gn:population":0,
    "gn:timezone":"Asia/Tehran",
    "iso:country":"IR",
    "name:fas_x_preferred":[
        "\u0645\u06cc\u0627\u0646 \u0631\u0648\u062f"
    ],
    "name:fas_x_variant":[
        "M\u012b\u0101n R\u016bd-e \u2018Oly\u0101",
        "M\u012b\u0101n R\u016bd"
    ],
    "name:und_x_variant":[
        "Varmazy\u0101r"
    ],
    "wof:name":"Mian Rud",
    "wof:placetype":"locality"
},
  "geometry": {"coordinates":[45.89162,34.3156],"type":"Point"}
}