{
  "type": "Feature",
  "properties": {
    "gn:admin1_code":"7",
    "gn:asciiname":"Ejoo",
    "gn:country_code":"IR",
    "gn:dem":1410,
    "gn:feature_class":"P",
    "gn:feature_code":"PPL",
    "gn:name":"Ejoo",
    "gn:population":0,
    "gn:timezone":"Asia/Tehran",
    "iso:country":"IR",
    "name:fas_x_preferred":[
        "\u0627\u06cc\u062c\u0648\u0628"
    ],
    "name:fas_x_variant":[
        "\u012aj\u016bb",
        "\u0627\u06cc\u062c \u0622\u0628"
    ],
    "name:und_x_variant":[
        "Eyj\u016bb",
        "\u012aj\u016b",
        "Ejoo",
        "Eyj\u016b",
        "\u2019\u012aj \u0100b"
    ],
    "wof:name":"Ejoo",
    "wof:placetype":"locality"
},
  "geometry": {"coordinates":[54.45981,28.83541],"type":"Point"}
}