{
  "type": "Feature",
  "properties": {
    "gn:admin1_code":"11",
    "gn:asciiname":"Yekboni",
    "gn:country_code":"IR",
    "gn:dem":3,
    "gn:feature_class":"P",
    "gn:feature_code":"PPL",
    "gn:name":"Yekbon\u012b",
    "gn:population":0,
    "gn:timezone":"Asia/Tehran",
    "iso:country":"IR",
    "name:fas_x_preferred":[
        "\u064a\u0650\u0643\u0628\u064f\u0646\u06cc"
    ],
    "name:fas_x_variant":[
        "Yekbon\u012b"
    ],
    "wof:name":"Yekboni",
    "wof:placetype":"locality"
},
  "geometry": {"coordinates":[57.81611,25.66528],"type":"Point"}
}