{
  "type": "Feature",
  "properties": {
    "gn:admin1_code":"15.0",
    "gn:asciiname":"Karganag",
    "gn:country_code":"IR",
    "gn:dem":1173,
    "gn:feature_class":"P",
    "gn:feature_code":"PPL",
    "gn:name":"Karganag",
    "gn:population":0,
    "gn:timezone":"Asia/Tehran",
    "iso:country":"IR",
    "name:fas_x_preferred":[
        "\u06a9\u0631\u06a9\u0646\u06af"
    ],
    "name:fas_x_variant":[
        "\u06a9\u0631\u06af\u0646\u06af",
        "\u06a9\u0631\u0647 \u06a9\u0646\u06af"
    ],
    "name:und_x_variant":[
        "Karkanag",
        "Karganag",
        "Kareh Kanag"
    ],
    "wof:name":"Karganag",
    "wof:placetype":"locality"
},
  "geometry": {"coordinates":[49.60709,32.29671],"type":"Point"}
}