{
  "type": "Feature",
  "properties": {
    "gn:admin1_code":"28.0",
    "gn:asciiname":"Arsur",
    "gn:country_code":"IR",
    "gn:dem":2177,
    "gn:feature_class":"P",
    "gn:feature_code":"PPL",
    "gn:name":"Ars\u016br",
    "gn:population":0,
    "gn:timezone":"Asia/Tehran",
    "iso:country":"IR",
    "name:fas_x_preferred":[
        "Ars\u016br"
    ],
    "name:fas_x_variant":[
        "\u0627\u0631\u0633\u0648\u0631"
    ],
    "name:und_x_variant":[
        "Arsoor",
        "Ans\u016br",
        "Aras\u016br",
        "\u0627\u0631\u0633\u0648\u0631"
    ],
    "wof:name":"Arsur",
    "wof:placetype":"locality"
},
  "geometry": {"coordinates":[50.3171,33.2431],"type":"Point"}
}