{
  "type": "Feature",
  "properties": {
    "gn:admin1_code":"3",
    "gn:asciiname":"Mian Ab",
    "gn:country_code":"IR",
    "gn:dem":1901,
    "gn:feature_class":"P",
    "gn:feature_code":"PPL",
    "gn:name":"M\u012b\u0101n \u0100b",
    "gn:population":0,
    "gn:timezone":"Asia/Tehran",
    "iso:country":"IR",
    "name:fas_x_preferred":[
        "\u0645\u064a\u0646\u0627\u0628"
    ],
    "name:fas_x_variant":[
        "M\u012bn\u0101b",
        "M\u012b\u0101n \u0100b",
        "\u0645\u06cc\u0627\u0646 \u0622\u0628",
        "\u0645\u06cc\u0627\u0646\u200c\u0622\u0628"
    ],
    "wof:name":"Mian Ab",
    "wof:placetype":"locality"
},
  "geometry": {"coordinates":[51.20474,31.29493],"type":"Point"}
}