{
  "type": "Feature",
  "properties": {
    "gn:admin1_code":"32.0",
    "gn:asciiname":"Gholamhoseyn Qeshlaqi",
    "gn:country_code":"IR",
    "gn:dem":724,
    "gn:feature_class":"P",
    "gn:feature_code":"PPL",
    "gn:name":"Ghol\u0101m\u1e29oseyn Qeshl\u0101q\u012b",
    "gn:population":0,
    "gn:timezone":"Asia/Tehran",
    "iso:country":"IR",
    "name:fas_x_preferred":[
        "\u063a\u0644\u0627\u0645\u062d\u0633\u06cc\u0646 \u0642\u0634\u0644\u0627\u0642\u06cc"
    ],
    "name:und_x_variant":[
        "Ghol\u0101m\u1e29oseyn Qeshl\u0101q\u012b"
    ],
    "wof:name":"Gholamhoseyn Qeshlaqi",
    "wof:placetype":"locality"
},
  "geometry": {"coordinates":[47.53595,38.70757],"type":"Point"}
}