{
  "type": "Feature",
  "properties": {
    "gn:admin1_code":"40.0",
    "gn:asciiname":"Mazra`eh-ye Darb Ashkaft",
    "gn:country_code":"IR",
    "gn:dem":2122,
    "gn:feature_class":"P",
    "gn:feature_code":"PPLF",
    "gn:name":"Mazra\u2018eh-ye Darb Ashkaft",
    "gn:population":0,
    "gn:timezone":"Asia/Tehran",
    "iso:country":"IR",
    "name:fas_x_preferred":[
        "\u0645\u0632\u0631\u0639\u0647 \u062f\u0631\u0628 \u0627\u0634\u06a9\u0641\u062a"
    ],
    "name:und_x_variant":[
        "Mazra\u2018eh-ye Darb Ashkaft"
    ],
    "wof:name":"Mazra`eh-ye Darb Ashkaft",
    "wof:placetype":"locality"
},
  "geometry": {"coordinates":[54.20808,31.57183],"type":"Point"}
}