{
  "type": "Feature",
  "properties": {
    "gn:admin1_code":"7",
    "gn:asciiname":"Darreh Ahaki",
    "gn:country_code":"IR",
    "gn:dem":1601,
    "gn:feature_class":"P",
    "gn:feature_code":"PPL",
    "gn:name":"Darreh \u0100hak\u012b",
    "gn:population":0,
    "gn:timezone":"Asia/Tehran",
    "iso:country":"IR",
    "name:fas_x_preferred":[
        "\u062f\u0631\u0647 \u0622\u0647\u06a9\u06cc"
    ],
    "name:fas_x_variant":[
        "Darreh \u0100hak\u012b"
    ],
    "wof:name":"Darreh Ahaki",
    "wof:placetype":"locality"
},
  "geometry": {"coordinates":[53.24276999999999,29.81112000000001],"type":"Point"}
}