{
  "type": "Feature",
  "properties": {
    "gn:admin1_code":"42",
    "gn:asciiname":"Chahar Gushli",
    "gn:country_code":"IR",
    "gn:dem":1639,
    "gn:feature_class":"P",
    "gn:feature_code":"PPL",
    "gn:name":"Chah\u0101r G\u016bshl\u012b",
    "gn:population":0,
    "gn:timezone":"Asia/Tehran",
    "iso:country":"IR",
    "name:fas_x_preferred":[
        "Chah\u0101r G\u016bshl\u012b"
    ],
    "name:fas_x_variant":[
        "\u0686\u0647\u0627\u0631 \u06af\u0648\u0634\u0644\u06cc",
        "Cheh\u0101r G\u016bsheh",
        "Chah\u0101r G\u016bsheh"
    ],
    "name:und_x_variant":[
        "Chah\u0101r G\u016bsheh",
        "Cheh\u0101r G\u016bsheh",
        "\u0686\u0647\u0627\u0631 \u06af\u0648\u0634\u0644\u06cc"
    ],
    "wof:name":"Chahar Gushli",
    "wof:placetype":"locality"
},
  "geometry": {"coordinates":[58.46167,36.63156],"type":"Point"}
}