{
  "type": "Feature",
  "properties": {
    "gn:admin1_code":"10",
    "gn:asciiname":"Buzhan",
    "gn:country_code":"IR",
    "gn:dem":926,
    "gn:feature_class":"P",
    "gn:feature_code":"PPL",
    "gn:name":"B\u016bzh\u0101n",
    "gn:population":0,
    "gn:timezone":"Asia/Tehran",
    "iso:country":"IR",
    "name:fas_x_preferred":[
        "\u0628\u0648\u0698\u0627\u0646"
    ],
    "name:fas_x_variant":[
        "B\u016bzh\u0101n"
    ],
    "name:msa_x_preferred":[
        "Buzhan"
    ],
    "wof:name":"Buzhan",
    "wof:placetype":"locality"
},
  "geometry": {"coordinates":[46.77868,33.53958],"type":"Point"}
}