{
  "type": "Feature",
  "properties": {
    "gn:admin1_code":"15",
    "gn:asciiname":"Nowbegan",
    "gn:country_code":"IR",
    "gn:dem":74,
    "gn:feature_class":"P",
    "gn:feature_code":"PPL",
    "gn:name":"Nowbeg\u0101n",
    "gn:population":0,
    "gn:timezone":"Asia/Tehran",
    "iso:country":"IR",
    "name:aze_x_preferred":[
        "N\u0259bgan"
    ],
    "name:fas_x_preferred":[
        "\u0646\u0648\u0628\u06a9\u0627\u0646"
    ],
    "name:fas_x_variant":[
        "Nobg\u0101n",
        "Nobak\u0101n",
        "\u0646\u0648\u0628\u06af\u0627\u0646",
        "\u0646\u0628\u06af\u0627\u0646"
    ],
    "name:und_x_variant":[
        "Nabgan",
        "Now Bag\u0101n",
        "Nowbeg\u0101n",
        "Nowbek\u0101n",
        "Nobeg\u0101n"
    ],
    "wof:name":"Nowbegan",
    "wof:placetype":"locality"
},
  "geometry": {"coordinates":[49.30909000000001,31.42775],"type":"Point"}
}