{
  "type": "Feature",
  "properties": {
    "gn:admin1_code":"26",
    "gn:asciiname":"Mardabad",
    "gn:country_code":"IR",
    "gn:dem":911,
    "gn:feature_class":"P",
    "gn:feature_code":"PPL",
    "gn:name":"Mard\u0101b\u0101d",
    "gn:population":0,
    "gn:timezone":"Asia/Tehran",
    "iso:country":"IR",
    "name:fas_x_preferred":[
        "\u0645\u064e\u0631\u062f \u0622\u0628\u0627\u062f"
    ],
    "name:fas_x_variant":[
        "Mard\u0101b\u0101d"
    ],
    "wof:name":"Mardabad",
    "wof:placetype":"locality"
},
  "geometry": {"coordinates":[51.62944,35.31583],"type":"Point"}
}