{
  "type": "Feature",
  "properties": {
    "gn:admin1_code":"4",
    "gn:asciiname":"Karimabad-e Pa'in",
    "gn:country_code":"IR",
    "gn:dem":873,
    "gn:feature_class":"P",
    "gn:feature_code":"PPL",
    "gn:name":"Kar\u012bm\u0101b\u0101d-e P\u0101\u2019\u012bn",
    "gn:population":0,
    "gn:timezone":"Asia/Tehran",
    "iso:country":"IR",
    "name:fas_x_preferred":[
        "\u06a9\u0631\u06cc\u0645 \u0622\u0628\u0627\u062f \u067e\u0627\u0626\u06cc\u0646"
    ],
    "name:fas_x_variant":[
        "Kar\u012bm\u0101b\u0101d-e P\u0101\u2019\u012bn"
    ],
    "wof:name":"Karimabad-e Pa'in",
    "wof:placetype":"locality"
},
  "geometry": {"coordinates":[60.00859000000001,28.48459],"type":"Point"}
}