{
  "type": "Feature",
  "properties": {
    "gn:admin1_code":"29.0",
    "gn:asciiname":"Ab Sardu'iyeh",
    "gn:country_code":"IR",
    "gn:dem":492,
    "gn:feature_class":"P",
    "gn:feature_code":"PPL",
    "gn:name":"\u0100b Sard\u016b\u2019\u012byeh",
    "gn:population":0,
    "gn:timezone":"Asia/Tehran",
    "iso:country":"IR",
    "name:fas_x_preferred":[
        "\u0622\u0628 \u0633\u0631\u062f\u0648\u0626\u06cc\u0647"
    ],
    "name:fas_x_variant":[
        "\u0100b Sard\u016b\u2019\u012byeh"
    ],
    "name:und_x_variant":[
        "Tump-i-\u0100bsardi",
        "\u0100bsard\u012byeh"
    ],
    "wof:name":"Ab Sardu'iyeh",
    "wof:placetype":"locality"
},
  "geometry": {"coordinates":[57.8746,28.0904],"type":"Point"}
}