{
  "type": "Feature",
  "properties": {
    "gn:admin1_code":"1.0",
    "gn:asciiname":"Ata Bolaghi",
    "gn:country_code":"IR",
    "gn:dem":1351,
    "gn:feature_class":"P",
    "gn:feature_code":"PPL",
    "gn:name":"\u0100t\u0101 Bol\u0101gh\u012b",
    "gn:population":0,
    "gn:timezone":"Asia/Tehran",
    "iso:country":"IR",
    "name:aze_x_preferred":[
        "Atabula\u011f\u0131"
    ],
    "name:ceb_x_preferred":[
        "\u0100t\u0101 Bol\u0101gh\u012b"
    ],
    "name:fas_x_preferred":[
        "\u0622\u062a\u0627 \u0628\u064f\u0644\u0627\u063a\u06cc"
    ],
    "name:fas_x_variant":[
        "\u0622\u062a\u0627 \u0628\u0644\u0627\u063a\u06cc",
        "\u0100t\u0101 Bol\u0101gh\u012b",
        "\u0627\u062a\u0627\u0628\u0644\u0627\u063a\u06cc"
    ],
    "name:msa_x_preferred":[
        "Ata Bolaghi"
    ],
    "name:swe_x_preferred":[
        "\u0100t\u0101 Bol\u0101gh\u012b"
    ],
    "wof:name":"Ata Bolaghi",
    "wof:placetype":"locality"
},
  "geometry": {"coordinates":[46.06100000000001,36.8079],"type":"Point"}
}