{
  "type": "Feature",
  "properties": {
    "gn:admin1_code":"44",
    "gn:asciiname":"Bagh-e Pir",
    "gn:country_code":"IR",
    "gn:dem":1437,
    "gn:feature_class":"P",
    "gn:feature_code":"PPL",
    "gn:name":"B\u0101gh-e P\u012br",
    "gn:population":0,
    "gn:timezone":"Asia/Tehran",
    "iso:country":"IR",
    "name:fas_x_preferred":[
        "\u0628\u0627\u063a\u0650 \u067e\u064a\u0631"
    ],
    "name:fas_x_variant":[
        "B\u0101gh-e P\u012br"
    ],
    "wof:name":"Bagh-e Pir",
    "wof:placetype":"locality"
},
  "geometry": {"coordinates":[51.05,35.83333],"type":"Point"}
}