{
  "type": "Feature",
  "properties": {
    "gn:admin1_code":"29.0",
    "gn:asciiname":"Ab Shur",
    "gn:country_code":"IR",
    "gn:dem":912,
    "gn:feature_class":"P",
    "gn:feature_code":"PPL",
    "gn:name":"\u0100b Sh\u016br",
    "gn:population":0,
    "gn:timezone":"Asia/Tehran",
    "iso:country":"IR",
    "name:fas_x_preferred":[
        "\u0622\u0628 \u0634\u0648\u0631"
    ],
    "name:und_x_variant":[
        "\u0100b Sh\u016br"
    ],
    "wof:name":"Ab Shur",
    "wof:placetype":"locality"
},
  "geometry": {"coordinates":[58.93954,28.02409],"type":"Point"}
}