{
  "type": "Feature",
  "properties": {
    "gn:admin1_code":"42",
    "gn:asciiname":"Shurbeyg",
    "gn:country_code":"IR",
    "gn:dem":1670,
    "gn:feature_class":"P",
    "gn:feature_code":"PPL",
    "gn:name":"Sh\u016brbeyg",
    "gn:population":0,
    "gn:timezone":"Asia/Tehran",
    "iso:country":"IR",
    "name:fas_x_preferred":[
        "\u0634\u0648\u0631\u0628\u06cc\u06af"
    ],
    "name:fas_x_variant":[
        "Sh\u016brbek",
        "Sh\u016brbeyg"
    ],
    "name:und_x_variant":[
        "Jal\u0101l\u0101b\u0101d"
    ],
    "wof:name":"Shurbeyg",
    "wof:placetype":"locality"
},
  "geometry": {"coordinates":[59.17901,35.55312],"type":"Point"}
}