{
  "type": "Feature",
  "properties": {
    "gn:admin1_code":"7.0",
    "gn:asciiname":"Shahrak-e Vali-ye `Asr-e Firuzi",
    "gn:country_code":"IR",
    "gn:dem":1619,
    "gn:feature_class":"P",
    "gn:feature_code":"PPL",
    "gn:name":"Shahrak-e Val\u012b-ye \u2018A\u015fr-e F\u012br\u016bz\u012b",
    "gn:population":0,
    "gn:timezone":"Asia/Tehran",
    "iso:country":"IR",
    "name:fas_x_preferred":[
        "\u0634\u0647\u0631\u06a9 \u0648\u0644\u06cc\u0639\u0635\u0631 \u0641\u06cc\u0631\u0648\u0632\u06cc"
    ],
    "name:fas_x_variant":[
        "Shahrak-e Val\u012b-ye \u2018A\u015fr-e F\u012br\u016bz\u012b"
    ],
    "wof:name":"Shahrak-e Vali-ye `Asr-e Firuzi",
    "wof:placetype":"locality"
},
  "geometry": {"coordinates":[52.847,29.9214],"type":"Point"}
}