{
  "type": "Feature",
  "properties": {
    "gn:admin1_code":"4.0",
    "gn:asciiname":"Chutabad",
    "gn:country_code":"IR",
    "gn:dem":485,
    "gn:feature_class":"P",
    "gn:feature_code":"PPL",
    "gn:name":"Ch\u016bt\u0101b\u0101d",
    "gn:population":0,
    "gn:timezone":"Asia/Tehran",
    "iso:country":"IR",
    "name:fas_x_preferred":[
        "\u0686\u0648\u062a \u0622\u0628\u0627\u062f"
    ],
    "name:fas_x_variant":[
        "Ch\u016bt\u0101b\u0101d",
        "\u0686\u0648\u062a\u200c\u0622\u0628\u0627\u062f"
    ],
    "wof:name":"Chutabad",
    "wof:placetype":"locality"
},
  "geometry": {"coordinates":[60.7209,26.2286],"type":"Point"}
}