{
  "type": "Feature",
  "properties": {
    "gn:admin1_code":"7",
    "gn:asciiname":"Qeshlaq va Darnian",
    "gn:country_code":"IR",
    "gn:dem":1567,
    "gn:feature_class":"P",
    "gn:feature_code":"PPL",
    "gn:name":"Qeshl\u0101q va Darn\u012b\u0101n",
    "gn:population":0,
    "gn:timezone":"Asia/Tehran",
    "iso:country":"IR",
    "name:fas_x_preferred":[
        "\u0642\u0634\u0644\u0627\u0642 \u0648 \u062f\u0631\u0646\u06cc\u0627\u0646"
    ],
    "name:fas_x_variant":[
        "Qeshl\u0101q va Darn\u012b\u0101n"
    ],
    "wof:name":"Qeshlaq va Darnian",
    "wof:placetype":"locality"
},
  "geometry": {"coordinates":[53.2557,29.6087],"type":"Point"}
}