{
  "type": "Feature",
  "properties": {
    "gn:admin1_code":"15",
    "gn:asciiname":"Albu `Obeyd",
    "gn:country_code":"IR",
    "gn:dem":7,
    "gn:feature_class":"P",
    "gn:feature_code":"PPL",
    "gn:name":"\u0100lb\u016b \u2018Obeyd",
    "gn:population":0,
    "gn:timezone":"Asia/Tehran",
    "iso:country":"IR",
    "name:fas_x_preferred":[
        "\u0100lb\u016b \u2018Obeyd"
    ],
    "name:fas_x_variant":[
        "Alb\u016b \u2018Obeyd",
        "\u0622\u0644\u0628\u0648 \u0639\u0628\u06cc\u062f"
    ],
    "name:und_x_variant":[
        "\u0622\u0644\u0628\u0648 \u0639\u0628\u06cc\u062f"
    ],
    "wof:name":"Albu `Obeyd",
    "wof:placetype":"locality"
},
  "geometry": {"coordinates":[48.6888,30.68929],"type":"Point"}
}