{
  "type": "Feature",
  "properties": {
    "gn:admin1_code":"37",
    "gn:asciiname":"Safiabad",
    "gn:country_code":"IR",
    "gn:dem":957,
    "gn:feature_class":"P",
    "gn:feature_code":"PPL",
    "gn:name":"\u015eaf\u012b\u0101b\u0101d",
    "gn:population":0,
    "gn:timezone":"Asia/Tehran",
    "iso:country":"IR",
    "name:fas_x_preferred":[
        "\u015eaf\u012b\u0101b\u0101d"
    ],
    "name:fas_x_variant":[
        "\u0635\u0641\u06cc \u0622\u0628\u0627\u062f"
    ],
    "name:und_x_variant":[
        "\u0635\u0641\u06cc \u0622\u0628\u0627\u062f"
    ],
    "wof:name":"Safiabad",
    "wof:placetype":"locality"
},
  "geometry": {"coordinates":[55.55206,37.17768],"type":"Point"}
}