{
  "type": "Feature",
  "properties": {
    "gn:admin1_code":"44",
    "gn:asciiname":"Mohammadabad",
    "gn:country_code":"IR",
    "gn:dem":1196,
    "gn:feature_class":"P",
    "gn:feature_code":"PPL",
    "gn:name":"Mo\u1e29ammad\u0101b\u0101d",
    "gn:population":0,
    "gn:timezone":"Asia/Tehran",
    "iso:country":"IR",
    "name:fas_x_preferred":[
        "\u0645\u062d\u0645\u0651\u062f \u0622\u0628\u0627\u062f"
    ],
    "name:fas_x_variant":[
        "\u0645\u064f\u062d\u064e\u0645\u064e\u0651\u062f\u0627\u0628\u0627\u062f\u0650 \u0627\u064e\u0631\u0628\u064e\u0639\u0650\u0647",
        "Mo\u1e29ammad\u0101b\u0101d",
        "\u0645\u062d\u0645\u062f\u0622\u0628\u0627\u062f"
    ],
    "name:msa_x_preferred":[
        "Mohammadabad"
    ],
    "name:rus_x_preferred":[
        "\u041c\u043e\u0445\u0430\u043c\u043c\u0435\u0434\u0430\u0431\u0430\u0434"
    ],
    "name:und_x_variant":[
        "Muhammad\u0101b\u0101d",
        "Mo\u1e29ammad\u0101b\u0101d-e Arba\u2018eh"
    ],
    "wof:name":"Mohammadabad",
    "wof:placetype":"locality"
},
  "geometry": {"coordinates":[50.6164,35.8343],"type":"Point"}
}