{
  "type": "Feature",
  "properties": {
    "gn:admin1_code":"29",
    "gn:asciiname":"Chah-e Hoseyn`ali",
    "gn:country_code":"IR",
    "gn:dem":401,
    "gn:feature_class":"P",
    "gn:feature_code":"PPL",
    "gn:name":"Ch\u0101h-e \u1e28oseyn\u2018al\u012b",
    "gn:population":0,
    "gn:timezone":"Asia/Tehran",
    "iso:country":"IR",
    "name:fas_x_preferred":[
        "\u0686\u0627\u0647 \u062d\u0633\u06cc\u0646\u0639\u0644\u06cc"
    ],
    "name:fas_x_variant":[
        "Ch\u0101h-e \u1e28oseyn\u2018al\u012b"
    ],
    "wof:name":"Chah-e Hoseyn`ali",
    "wof:placetype":"locality"
},
  "geometry": {"coordinates":[58.16696,27.35121],"type":"Point"}
}