{
  "type": "Feature",
  "properties": {
    "gn:admin1_code":"7",
    "gn:asciiname":"Kandar-e `Abd or Reza",
    "gn:country_code":"IR",
    "gn:dem":407,
    "gn:feature_class":"P",
    "gn:feature_code":"PPL",
    "gn:name":"Kandar-e \u2018Abd or Re\u1e95\u0101",
    "gn:population":0,
    "gn:timezone":"Asia/Tehran",
    "iso:country":"IR",
    "name:fas_x_preferred":[
        "\u06a9\u0646\u062f\u0631 \u0639\u0628\u062f \u0627\u0644\u0651\u0631\u0636\u0627"
    ],
    "name:fas_x_variant":[
        "Kandar-e \u2018Abd or Re\u1e95\u0101"
    ],
    "wof:name":"Kandar-e `Abd or Reza",
    "wof:placetype":"locality"
},
  "geometry": {"coordinates":[53.3539,27.2752],"type":"Point"}
}