{
  "type": "Feature",
  "properties": {
    "gn:admin1_code":"15",
    "gn:asciiname":"Finkhi-ye Bozorg",
    "gn:country_code":"IR",
    "gn:dem":10,
    "gn:feature_class":"P",
    "gn:feature_code":"PPL",
    "gn:name":"F\u012bnkh\u012b-ye Bozorg",
    "gn:population":0,
    "gn:timezone":"Asia/Tehran",
    "iso:country":"IR",
    "name:fas_x_preferred":[
        "F\u012br\u016bz\u0101b\u0101d-e Fen\u012bkh\u012b"
    ],
    "name:fas_x_variant":[
        "\u0641\u06cc\u0646\u062e\u06cc \u0628\u0632\u0631\u06af",
        "\u0641\u0646\u06cc\u062e\u06cc"
    ],
    "name:und_x_variant":[
        "F\u012bnkh\u012b-ye Bozorg",
        "Fan\u012bkh\u012b"
    ],
    "wof:name":"Finkhi-ye Bozorg",
    "wof:placetype":"locality"
},
  "geometry": {"coordinates":[48.0329,31.695],"type":"Point"}
}