{
  "type": "Feature",
  "properties": {
    "gn:admin1_code":"7",
    "gn:asciiname":"Behrestan",
    "gn:country_code":"IR",
    "gn:dem":459,
    "gn:feature_class":"P",
    "gn:feature_code":"PPL",
    "gn:name":"Behrest\u0101n",
    "gn:population":0,
    "gn:timezone":"Asia/Tehran",
    "iso:country":"IR",
    "name:fas_x_preferred":[
        "\u0628\u0647\u0631\u0633\u062a\u0627\u0646"
    ],
    "name:fas_x_variant":[
        "Behrest\u0101n"
    ],
    "name:msa_x_preferred":[
        "Behrestan"
    ],
    "name:und_x_variant":[
        "Bahrist\u0101n",
        "Behrist\u0101n",
        "Baharestan"
    ],
    "wof:name":"Behrestan",
    "wof:placetype":"locality"
},
  "geometry": {"coordinates":[52.7283,27.7016],"type":"Point"}
}