{
  "type": "Feature",
  "properties": {
    "gn:admin1_code":"35.0",
    "gn:asciiname":"Rafi`abad",
    "gn:country_code":"IR",
    "gn:dem":12,
    "gn:feature_class":"P",
    "gn:feature_code":"PPL",
    "gn:name":"Raf\u012b\u2018\u0101b\u0101d",
    "gn:population":0,
    "gn:timezone":"Asia/Tehran",
    "iso:country":"IR",
    "name:fas_x_preferred":[
        "\u0631\u0641\u064a\u0639 \u0622\u0628\u0627\u062f"
    ],
    "name:fas_x_variant":[
        "Raf\u012b\u2018\u0101b\u0101d"
    ],
    "wof:name":"Rafi`abad",
    "wof:placetype":"locality"
},
  "geometry": {"coordinates":[52.39103,36.54735],"type":"Point"}
}