{
  "type": "Feature",
  "properties": {
    "gn:admin1_code":"13",
    "gn:asciiname":"Kashkamir-e `Olya",
    "gn:country_code":"IR",
    "gn:dem":2044,
    "gn:feature_class":"P",
    "gn:feature_code":"PPL",
    "gn:name":"Kashkam\u012br-e \u2018Oly\u0101",
    "gn:population":0,
    "gn:timezone":"Asia/Tehran",
    "iso:country":"IR",
    "name:ceb_x_preferred":[
        "Kashkam\u012br-e \u2018Oly\u0101"
    ],
    "name:fas_x_preferred":[
        "\u06a9\u0634\u06a9\u0645\u06cc\u0631 \u0639\u0644\u06cc\u0627"
    ],
    "name:fas_x_variant":[
        "Kashkam\u012br-e \u2018Oly\u0101",
        "\u0633\u0631\u06a9\u0634\u06a9\u0645\u06cc\u0631"
    ],
    "name:swe_x_preferred":[
        "Kashkam\u012br-e \u2018Oly\u0101"
    ],
    "name:und_x_variant":[
        "Sar Kashkam\u012br",
        "Kashkeh M\u012br-e B\u0101l\u0101",
        "Kashkam\u012br-e B\u0101l\u0101",
        "Kashkam\u012br \u2018Uliya"
    ],
    "wof:name":"Kashkamir-e `Olya",
    "wof:placetype":"locality"
},
  "geometry": {"coordinates":[47.0892,34.8718],"type":"Point"}
}