{
  "type": "Feature",
  "properties": {
    "gn:admin1_code":"15.0",
    "gn:asciiname":"Taleqani-ye Seh",
    "gn:country_code":"IR",
    "gn:dem":169,
    "gn:feature_class":"P",
    "gn:feature_code":"PPL",
    "gn:name":"\u0162\u0101leq\u0101n\u012b-ye Seh",
    "gn:population":0,
    "gn:timezone":"Asia/Tehran",
    "iso:country":"IR",
    "name:fas_x_preferred":[
        "\u0162\u0101leq\u0101n\u012b-ye Seh"
    ],
    "name:fas_x_variant":[
        "\u0637\u0627\u0644\u0642\u0627\u0646\u06cc \u0633\u0647"
    ],
    "wof:name":"Taleqani-ye Seh",
    "wof:placetype":"locality"
},
  "geometry": {"coordinates":[49.62499,31.29719],"type":"Point"}
}