{
  "type": "Feature",
  "properties": {
    "gn:admin1_code":"35",
    "gn:asciiname":"Qarah Tappeh",
    "gn:country_code":"IR",
    "gn:dem":-15,
    "gn:feature_class":"P",
    "gn:feature_code":"PPL",
    "gn:name":"Qarah Tappeh",
    "gn:population":0,
    "gn:timezone":"Asia/Tehran",
    "iso:country":"IR",
    "name:fas_x_preferred":[
        "\u0642\u064e\u0631\u064e\u062a\u0650\u067e\u0650"
    ],
    "name:fas_x_variant":[
        "\u0642\u0631\u0647 \u062a\u067e\u0647"
    ],
    "name:und_x_variant":[
        "Qaratepe",
        "\u0642\u0631\u0647 \u062a\u067e\u0647",
        "Qarah Tappeh",
        "Qareh Tappeh"
    ],
    "wof:name":"Qarah Tappeh",
    "wof:placetype":"locality"
},
  "geometry": {"coordinates":[53.43549,36.73797],"type":"Point"}
}