{
  "type": "Feature",
  "properties": {
    "gn:admin1_code":"3",
    "gn:asciiname":"Golabad",
    "gn:country_code":"IR",
    "gn:dem":2397,
    "gn:feature_class":"P",
    "gn:feature_code":"PPL",
    "gn:name":"Gol\u0101b\u0101d",
    "gn:population":0,
    "gn:timezone":"Asia/Tehran",
    "iso:country":"IR",
    "name:fas_x_preferred":[
        "\u06af\u064f\u0644\u064e\u0643"
    ],
    "name:fas_x_variant":[
        "Gol\u0101b\u0101d",
        "\u06af\u0644 \u0622\u0628\u0627\u062f"
    ],
    "name:und_x_variant":[
        "Golak",
        "\u06af\u0644 \u0622\u0628\u0627\u062f"
    ],
    "wof:name":"Golabad",
    "wof:placetype":"locality"
},
  "geometry": {"coordinates":[50.31325,32.27146],"type":"Point"}
}