{
  "type": "Feature",
  "properties": {
    "gn:admin1_code":"4",
    "gn:asciiname":"Malkira",
    "gn:country_code":"IR",
    "gn:dem":1549,
    "gn:feature_class":"P",
    "gn:feature_code":"PPL",
    "gn:name":"Malk\u012br\u0101",
    "gn:population":0,
    "gn:timezone":"Asia/Tehran",
    "iso:country":"IR",
    "name:fas_x_preferred":[
        "\u0645\u0644\u06a9\u064a\u0631\u0627"
    ],
    "name:fas_x_variant":[
        "Malk\u012br\u0101"
    ],
    "wof:name":"Malkira",
    "wof:placetype":"locality"
},
  "geometry": {"coordinates":[61.00574,26.64371],"type":"Point"}
}