{
  "type": "Feature",
  "properties": {
    "gn:admin1_code":"35.0",
    "gn:asciiname":"Bala Qadi Kola",
    "gn:country_code":"IR",
    "gn:dem":-8,
    "gn:feature_class":"P",
    "gn:feature_code":"PPL",
    "gn:name":"B\u0101l\u0101 Q\u0101d\u012b Kol\u0101",
    "gn:population":0,
    "gn:timezone":"Asia/Tehran",
    "iso:country":"IR",
    "name:fas_x_preferred":[
        "B\u0101l\u0101 Q\u0101d\u012b Kol\u0101"
    ],
    "name:fas_x_variant":[
        "\u0628\u0627\u0644\u0627 \u0642\u0627\u062f\u06cc \u0643\u0644\u0627"
    ],
    "wof:name":"Bala Qadi Kola",
    "wof:placetype":"locality"
},
  "geometry": {"coordinates":[52.58501,36.58219],"type":"Point"}
}