{
  "type": "Feature",
  "properties": {
    "gn:admin1_code":"32",
    "gn:asciiname":"Sha`banlu",
    "gn:country_code":"IR",
    "gn:dem":851,
    "gn:feature_class":"P",
    "gn:feature_code":"PPL",
    "gn:name":"Sha\u2018b\u0101nl\u016b",
    "gn:population":0,
    "gn:timezone":"Asia/Tehran",
    "iso:country":"IR",
    "name:fas_x_preferred":[
        "\u0634\u0639\u0628\u0627\u0646\u0644\u0648"
    ],
    "name:fas_x_variant":[
        "Sha\u2018b\u0101nl\u016b"
    ],
    "wof:name":"Sha`banlu",
    "wof:placetype":"locality"
},
  "geometry": {"coordinates":[47.8555,39.025],"type":"Point"}
}