{
  "type": "Feature",
  "properties": {
    "gn:admin1_code":"5.0",
    "gn:asciiname":"Garr-e Kalagh Neshin",
    "gn:country_code":"IR",
    "gn:dem":2090,
    "gn:feature_class":"P",
    "gn:feature_code":"PPL",
    "gn:name":"Garr-e Kal\u0101gh Nesh\u012bn",
    "gn:population":0,
    "gn:timezone":"Asia/Tehran",
    "iso:country":"IR",
    "name:fas_x_preferred":[
        "Garr-e Kal\u0101gh Nesh\u012bn"
    ],
    "name:fas_x_variant":[
        "\u06af\u0631\u0651 \u06a9\u0644\u0627\u063a \u0646\u0634\u06cc\u0646"
    ],
    "wof:name":"Garr-e Kalagh Neshin",
    "wof:placetype":"locality"
},
  "geometry": {"coordinates":[51.51085,30.55976],"type":"Point"}
}