{
  "type": "Feature",
  "properties": {
    "gn:admin1_code":"4.0",
    "gn:asciiname":"Deh-e Hajji Hoseyn",
    "gn:country_code":"IR",
    "gn:dem":489,
    "gn:feature_class":"P",
    "gn:feature_code":"PPL",
    "gn:name":"Deh-e \u1e28\u0101jj\u012b \u1e28oseyn",
    "gn:population":0,
    "gn:timezone":"Asia/Tehran",
    "iso:country":"IR",
    "name:fas_x_preferred":[
        "\u062f\u0647 \u062d\u0627\u062c\u06cc \u062d\u0633\u06cc\u0646"
    ],
    "name:fas_x_variant":[
        "Deh-e \u1e28\u0101jj\u012b \u1e28oseyn"
    ],
    "wof:name":"Deh-e Hajji Hoseyn",
    "wof:placetype":"locality"
},
  "geometry": {"coordinates":[61.78717,30.99115],"type":"Point"}
}