{
  "type": "Feature",
  "properties": {
    "gn:admin1_code":"1",
    "gn:asciiname":"Qinar-e Sofla",
    "gn:country_code":"IR",
    "gn:dem":1712,
    "gn:feature_class":"P",
    "gn:feature_code":"PPL",
    "gn:name":"Q\u012bnar-e Sofl\u00e1",
    "gn:population":0,
    "gn:timezone":"Asia/Tehran",
    "iso:country":"IR",
    "name:fas_x_preferred":[
        "\u0642\u06cc\u0646\u0631 \u0633\u0641\u0644\u06cc"
    ],
    "name:fas_x_variant":[
        "Q\u012bnar-e Sofl\u00e1"
    ],
    "name:und_x_variant":[
        "Q\u012bz-e P\u0101\u2019\u012bn"
    ],
    "wof:name":"Qinar-e Sofla",
    "wof:placetype":"locality"
},
  "geometry": {"coordinates":[44.6288,38.7845],"type":"Point"}
}