{
  "type": "Feature",
  "properties": {
    "gn:admin1_code":"26",
    "gn:asciiname":"Hesar-e Amir",
    "gn:country_code":"IR",
    "gn:dem":1089,
    "gn:feature_class":"P",
    "gn:feature_code":"PPL",
    "gn:name":"\u1e28e\u015f\u0101r-e Am\u012br",
    "gn:population":0,
    "gn:timezone":"Asia/Tehran",
    "iso:country":"IR",
    "name:fas_x_preferred":[
        "\u062d\u0635\u0627\u0631 \u0627\u0645\u064a\u0631"
    ],
    "name:fas_x_variant":[
        "\u1e28e\u015f\u0101r-e Am\u012br",
        "\u062d\u0635\u0627\u0631\u0627\u0645\u06cc\u0631"
    ],
    "name:pol_x_preferred":[
        "Hesaramir"
    ],
    "name:und_x_variant":[
        "\u1e28e\u015f\u0101r Am\u012br"
    ],
    "wof:name":"Hesar-e Amir",
    "wof:placetype":"locality"
},
  "geometry": {"coordinates":[51.7012,35.5149],"type":"Point"}
}