{
  "type": "Feature",
  "properties": {
    "gn:admin1_code":"4.0",
    "gn:asciiname":"Deh-e Namaki",
    "gn:country_code":"IR",
    "gn:dem":480,
    "gn:feature_class":"P",
    "gn:feature_code":"PPL",
    "gn:name":"Deh-e Namak\u012b",
    "gn:population":0,
    "gn:timezone":"Asia/Tehran",
    "iso:country":"IR",
    "name:fas_x_preferred":[
        "\u062f\u0647 \u0646\u0645\u06a9\u06cc"
    ],
    "name:fas_x_variant":[
        "Deh-e Namak\u012b",
        "\u0646\u0645\u06a9\u06cc"
    ],
    "name:und_x_variant":[
        "Namak\u012b"
    ],
    "wof:name":"Deh-e Namaki",
    "wof:placetype":"locality"
},
  "geometry": {"coordinates":[61.6278,31.193],"type":"Point"}
}