{
  "type": "Feature",
  "properties": {
    "gn:admin1_code":"3.0",
    "gn:asciiname":"Cham Qal`eh",
    "gn:country_code":"IR",
    "gn:dem":1503,
    "gn:feature_class":"P",
    "gn:feature_code":"PPL",
    "gn:name":"Cham Qal\u2018eh",
    "gn:population":0,
    "gn:timezone":"Asia/Tehran",
    "iso:country":"IR",
    "name:fas_x_preferred":[
        "\u0686\u064e\u0645 \u0642\u064e\u0644\u0639\u0650\u06c0 \u067e\u0627\u0626\u064a\u0646"
    ],
    "name:fas_x_variant":[
        "Cham Qal\u2018eh-ye P\u0101\u2019\u012bn",
        "Cham Qal\u2018eh",
        "\u0686\u0645 \u0642\u0644\u0639\u0647"
    ],
    "name:und_x_variant":[
        "\u0686\u0645 \u0642\u0644\u0639\u0647"
    ],
    "wof:name":"Cham Qal`eh",
    "wof:placetype":"locality"
},
  "geometry": {"coordinates":[50.03064000000001,32.21075],"type":"Point"}
}