{
  "type": "Feature",
  "properties": {
    "gn:admin1_code":"41",
    "gn:asciiname":"Qala`",
    "gn:country_code":"IR",
    "gn:dem":1635,
    "gn:feature_class":"P",
    "gn:feature_code":"PPL",
    "gn:name":"Qal\u0101\u2018",
    "gn:population":0,
    "gn:timezone":"Asia/Tehran",
    "iso:country":"IR",
    "name:fas_x_preferred":[
        "Qal\u0101\u2018"
    ],
    "name:fas_x_variant":[
        "Qal\u0101gh",
        "\u0642\u0644\u0627\u0639"
    ],
    "name:und_x_variant":[
        "Kalai"
    ],
    "wof:name":"Qala`",
    "wof:placetype":"locality"
},
  "geometry": {"coordinates":[59.03341,32.36281],"type":"Point"}
}