{
  "type": "Feature",
  "properties": {
    "gn:admin1_code":"4.0",
    "gn:asciiname":"Deh-e Bashi",
    "gn:country_code":"IR",
    "gn:dem":482,
    "gn:feature_class":"P",
    "gn:feature_code":"PPL",
    "gn:name":"Deh-e B\u0101sh\u012b",
    "gn:population":0,
    "gn:timezone":"Asia/Tehran",
    "iso:country":"IR",
    "name:fas_x_preferred":[
        "\u062f\u0647 \u0628\u0627\u0634\u06cc"
    ],
    "name:und_x_variant":[
        "Deh-e B\u0101sh\u012b"
    ],
    "wof:name":"Deh-e Bashi",
    "wof:placetype":"locality"
},
  "geometry": {"coordinates":[61.4826,31.199],"type":"Point"}
}