{
  "type": "Feature",
  "properties": {
    "gn:admin1_code":"8",
    "gn:asciiname":"Kazkarak",
    "gn:country_code":"IR",
    "gn:dem":235,
    "gn:feature_class":"P",
    "gn:feature_code":"PPL",
    "gn:name":"Kazkarak",
    "gn:population":0,
    "gn:timezone":"Asia/Tehran",
    "iso:country":"IR",
    "name:fas_x_preferred":[
        "\u06a9\u0632\u06a9\u0631\u06a9"
    ],
    "name:fas_x_variant":[
        "\u06af\u0632\u06a9\u0631\u06a9"
    ],
    "name:und_x_variant":[
        "Gazkarak",
        "Kazkarak"
    ],
    "wof:name":"Kazkarak",
    "wof:placetype":"locality"
},
  "geometry": {"coordinates":[49.52406,37.00913],"type":"Point"}
}