{
  "type": "Feature",
  "properties": {
    "gn:admin1_code":"33.0",
    "gn:asciiname":"Ojaq Kandi",
    "gn:country_code":"IR",
    "gn:dem":422,
    "gn:feature_class":"P",
    "gn:feature_code":"PPL",
    "gn:name":"Oj\u0101q Kand\u012b",
    "gn:population":0,
    "gn:timezone":"Asia/Tehran",
    "iso:country":"IR",
    "name:fas_x_preferred":[
        "\u0627\u062c\u0627\u0642 \u06a9\u0646\u062f\u06cc"
    ],
    "name:fas_x_variant":[
        "Oj\u0101q Kand\u012b"
    ],
    "wof:name":"Ojaq Kandi",
    "wof:placetype":"locality"
},
  "geometry": {"coordinates":[47.2153,39.1764],"type":"Point"}
}