{
  "type": "Feature",
  "properties": {
    "gn:admin1_code":"33",
    "gn:asciiname":"Yengejeh-ye Sadat",
    "gn:country_code":"IR",
    "gn:dem":1650,
    "gn:feature_class":"P",
    "gn:feature_code":"PPL",
    "gn:name":"Yengejeh-ye S\u0101d\u0101t",
    "gn:population":0,
    "gn:timezone":"Asia/Tehran",
    "iso:country":"IR",
    "name:fas_x_preferred":[
        "\u064a\u0650\u0646\u06af\u0650\u062c\u0650\u06c0 \u0635\u0627\u062f\u0627\u062a"
    ],
    "name:fas_x_variant":[
        "\u06cc\u0646\u06af\u062c\u0647 \u0633\u0627\u062f\u0627\u062a",
        "Yengejeh-ye \u015e\u0101d\u0101t",
        "Yengejeh-ye S\u0101d\u0101t"
    ],
    "name:msa_x_preferred":[
        "Yengejeh-ye Sadat"
    ],
    "name:und_x_variant":[
        "Yengjeh S\u0101d\u0101t"
    ],
    "name:urd_x_preferred":[
        "\u06cc\u0646\u06af\u062c\u06cc\u06c1-\u0633\u0627\u062f\u0627\u062a"
    ],
    "wof:name":"Yengejeh-ye Sadat",
    "wof:placetype":"locality"
},
  "geometry": {"coordinates":[45.5219,38.6991],"type":"Point"}
}