{
  "type": "Feature",
  "properties": {
    "gn:admin1_code":"16.0",
    "gn:asciiname":"Avihang",
    "gn:country_code":"IR",
    "gn:dem":1688,
    "gn:feature_class":"P",
    "gn:feature_code":"PPL",
    "gn:name":"\u0100v\u012bhang",
    "gn:population":0,
    "gn:timezone":"Asia/Tehran",
    "iso:country":"IR",
    "name:fas_x_preferred":[
        "\u0100v\u012bhang"
    ],
    "name:fas_x_variant":[
        "\u0622\u0648\u06cc\u0647\u0646\u06af",
        "\u0627\u0648\u06cc\u0647\u0646\u06af"
    ],
    "name:und_x_variant":[
        "\u0100b-i-Hang",
        "\u0622\u0648\u06cc\u0647\u0646\u06af",
        "Av\u012bhang"
    ],
    "wof:name":"Avihang",
    "wof:placetype":"locality"
},
  "geometry": {"coordinates":[46.68,35.2571],"type":"Point"}
}