{
  "type": "Feature",
  "properties": {
    "gn:admin1_code":"8",
    "gn:asciiname":"Meyan Gaskar",
    "gn:country_code":"IR",
    "gn:dem":1,
    "gn:feature_class":"P",
    "gn:feature_code":"PPL",
    "gn:name":"Mey\u0101n Gaskar",
    "gn:population":0,
    "gn:timezone":"Asia/Tehran",
    "iso:country":"IR",
    "name:ceb_x_preferred":[
        "M\u012b\u0101ngaskar"
    ],
    "name:fas_x_preferred":[
        "\u0645\u06cc\u0627\u0646\u06af\u0633\u06a9\u0631"
    ],
    "name:fas_x_variant":[
        "M\u012b\u0101ngaskar",
        "\u0645\u06cc\u0627\u0646 \u06af\u0633\u06a9\u0631"
    ],
    "name:msa_x_preferred":[
        "Miangaskar"
    ],
    "name:swe_x_preferred":[
        "M\u012b\u0101ngaskar"
    ],
    "name:ukr_x_preferred":[
        "\u041c\u0456\u044f\u043d-\u0490\u0430\u0441\u043a\u0430\u0440"
    ],
    "name:und_x_variant":[
        "Mey\u0101n Gaskar"
    ],
    "wof:name":"Meyan Gaskar",
    "wof:placetype":"locality"
},
  "geometry": {"coordinates":[49.19796,37.41825],"type":"Point"}
}