{
  "type": "Feature",
  "properties": {
    "gn:admin1_code":"4.0",
    "gn:asciiname":"Jam",
    "gn:country_code":"IR",
    "gn:dem":659,
    "gn:feature_class":"P",
    "gn:feature_code":"PPL",
    "gn:name":"Jam",
    "gn:population":0,
    "gn:timezone":"Asia/Tehran",
    "iso:country":"IR",
    "name:tur_x_preferred":[
        "Re\u00e7el"
    ],
    "wof:name":"Jam",
    "wof:placetype":"locality"
},
  "geometry": {"coordinates":[60.30139000000001,26.195],"type":"Point"}
}