{
  "type": "Feature",
  "properties": {
    "gn:admin1_code":"8",
    "gn:asciiname":"Hasan Darmani",
    "gn:country_code":"IR",
    "gn:dem":1192,
    "gn:feature_class":"P",
    "gn:feature_code":"PPL",
    "gn:name":"\u1e28asan Darm\u0101n\u012b",
    "gn:population":0,
    "gn:timezone":"Asia/Tehran",
    "iso:country":"IR",
    "name:ceb_x_preferred":[
        "\u1e28asan Darm\u0101n\u012b"
    ],
    "name:fas_x_preferred":[
        "\u062d\u0633\u0646 \u062f\u0631\u0645\u0627\u0646\u06cc"
    ],
    "name:fas_x_variant":[
        "\u1e28asan D\u0101yer M\u0101n\u012b",
        "\u1e28asan Darm\u0101n\u012b",
        "\u062d\u0633\u0646 \u062f\u0627\u06cc\u0631\u0645\u0627\u0646"
    ],
    "name:msa_x_preferred":[
        "Hasan Dayerman"
    ],
    "name:swe_x_preferred":[
        "\u1e28asan Darm\u0101n\u012b"
    ],
    "name:ukr_x_preferred":[
        "\u0425\u0430\u0441\u0430\u043d-\u0414\u0430\u0454\u0440\u043c\u0430\u043d"
    ],
    "name:und_x_variant":[
        "\u1e28asan D\u0101yerm\u0101n"
    ],
    "wof:name":"Hasan Darmani",
    "wof:placetype":"locality"
},
  "geometry": {"coordinates":[48.62096,37.84912],"type":"Point"}
}