{
  "type": "Feature",
  "properties": {
    "gn:admin1_code":"13",
    "gn:asciiname":"Manuchehrabad",
    "gn:country_code":"IR",
    "gn:dem":1296,
    "gn:feature_class":"P",
    "gn:feature_code":"PPL",
    "gn:name":"Man\u016bchehr\u0101b\u0101d",
    "gn:population":0,
    "gn:timezone":"Asia/Tehran",
    "iso:country":"IR",
    "name:fas_x_preferred":[
        "\u0645\u0646\u0648\u0686\u0647\u0631 \u0622\u0628\u0627\u062f"
    ],
    "name:fas_x_variant":[
        "Man\u016bchehr\u0101b\u0101d",
        "\u0645\u0646\u0648\u0686\u0647\u0631\u0622\u0628\u0627\u062f"
    ],
    "wof:name":"Manuchehrabad",
    "wof:placetype":"locality"
},
  "geometry": {"coordinates":[47.15564000000001,34.30931],"type":"Point"}
}