{
  "type": "Feature",
  "properties": {
    "gn:admin1_code":"33.0",
    "gn:asciiname":"Amand",
    "gn:cc2":"IR",
    "gn:country_code":"IR",
    "gn:dem":1532,
    "gn:feature_class":"P",
    "gn:feature_code":"PPL",
    "gn:name":"Amand",
    "gn:population":0,
    "gn:timezone":"Asia/Tehran",
    "iso:country":"IR",
    "name:und_x_variant":[
        "Ammand\u012b",
        "Amandy",
        "Amand\u012b",
        "Amand"
    ],
    "wof:name":"Amand",
    "wof:placetype":"locality"
},
  "geometry": {"coordinates":[46.57694,38.11639],"type":"Point"}
}