{
  "type": "Feature",
  "properties": {
    "gn:admin1_code":"42",
    "gn:asciiname":"Cheshmeh-ye Sorkh",
    "gn:country_code":"IR",
    "gn:dem":889,
    "gn:feature_class":"P",
    "gn:feature_code":"PPL",
    "gn:name":"Cheshmeh-ye Sorkh",
    "gn:population":0,
    "gn:timezone":"Asia/Tehran",
    "iso:country":"IR",
    "wof:name":"Cheshmeh-ye Sorkh",
    "wof:placetype":"locality"
},
  "geometry": {"coordinates":[58.19194,34.70833],"type":"Point"}
}