{
  "type": "Feature",
  "properties": {
    "gn:admin1_code":"23",
    "gn:asciiname":"Kakareza-ye `Olya",
    "gn:country_code":"IR",
    "gn:dem":1780,
    "gn:feature_class":"P",
    "gn:feature_code":"PPL",
    "gn:name":"K\u0101k\u0101re\u1e95\u0101-ye \u2018Oly\u0101",
    "gn:population":0,
    "gn:timezone":"Asia/Tehran",
    "iso:country":"IR",
    "name:ceb_x_preferred":[
        "K\u0101k\u0101re\u1e95\u0101-ye \u2018Oly\u0101"
    ],
    "name:fas_x_preferred":[
        "\u06a9\u0627\u06a9\u0627\u0631\u0636\u0627 \u0633\u0641\u0644\u06cc"
    ],
    "name:fas_x_variant":[
        "K\u0101k\u0101re\u1e95\u0101-ye Sofl\u00e1",
        "\u06a9\u0627\u06a9\u0627\u0631\u0636\u0627 \u0639\u0644\u06cc\u0627"
    ],
    "name:swe_x_preferred":[
        "K\u0101k\u0101re\u1e95\u0101-ye \u2018Oly\u0101"
    ],
    "name:und_x_variant":[
        "K\u0101k\u0101re\u1e95\u0101-ye \u2018Oly\u0101"
    ],
    "wof:name":"Kakareza-ye `Olya",
    "wof:placetype":"locality"
},
  "geometry": {"coordinates":[48.2697,33.7292],"type":"Point"}
}