{
  "type": "Feature",
  "properties": {
    "gn:admin1_code":"10",
    "gn:asciiname":"Qalandar-e `Olya",
    "gn:country_code":"IR",
    "gn:dem":1085,
    "gn:feature_class":"P",
    "gn:feature_code":"PPL",
    "gn:name":"Qalandar-e \u2018Oly\u0101",
    "gn:population":0,
    "gn:timezone":"Asia/Tehran",
    "iso:country":"IR",
    "name:fas_x_preferred":[
        "\u0642\u0644\u0646\u062f\u0631 \u0639\u0644\u06cc\u0627"
    ],
    "name:fas_x_variant":[
        "Qalandar-e \u2018Oly\u0101"
    ],
    "name:msa_x_preferred":[
        "Qalandar-e Olya"
    ],
    "name:und_x_variant":[
        "Sh\u0101h Qalandar"
    ],
    "wof:name":"Qalandar-e `Olya",
    "wof:placetype":"locality"
},
  "geometry": {"coordinates":[46.6284,33.6441],"type":"Point"}
}