{
  "type": "Feature",
  "properties": {
    "gn:admin1_code":"7.0",
    "gn:asciiname":"Qardashabad",
    "gn:country_code":"IR",
    "gn:dem":795,
    "gn:feature_class":"P",
    "gn:feature_code":"PPL",
    "gn:name":"Qardash\u0101b\u0101d",
    "gn:population":0,
    "gn:timezone":"Asia/Tehran",
    "iso:country":"IR",
    "name:ara_x_preferred":[
        "\u0642\u0631\u062f\u0627\u0634\u200c\u0622\u0628\u0627\u062f"
    ],
    "name:fas_x_preferred":[
        "\u0642\u0631\u062f\u0634 \u0622\u0628\u0627\u062f"
    ],
    "name:fas_x_variant":[
        "Qardash\u0101b\u0101d",
        "\u0642\u0631\u062f\u0627\u0634\u200c\u0622\u0628\u0627\u062f"
    ],
    "name:msa_x_preferred":[
        "Qardashabad"
    ],
    "wof:name":"Qardashabad",
    "wof:placetype":"locality"
},
  "geometry": {"coordinates":[52.0657,29.0893],"type":"Point"}
}