{
  "type": "Feature",
  "properties": {
    "gn:admin1_code":"15",
    "gn:asciiname":"Yerisiyeh",
    "gn:country_code":"IR",
    "gn:dem":31,
    "gn:feature_class":"P",
    "gn:feature_code":"PPL",
    "gn:name":"Yer\u012bs\u012byeh",
    "gn:population":0,
    "gn:timezone":"Asia/Tehran",
    "iso:country":"IR",
    "name:ceb_x_preferred":[
        "Yer\u012bs\u012byeh"
    ],
    "name:fas_x_preferred":[
        "Yer\u012bs\u012byeh"
    ],
    "name:fas_x_variant":[
        "\u06cc\u0631\u06cc\u0633\u06cc\u0647"
    ],
    "name:swe_x_preferred":[
        "Yer\u012bs\u012byeh"
    ],
    "name:und_x_variant":[
        "Yereys\u012byeh"
    ],
    "name:urd_x_preferred":[
        "\u06cc\u0631\u06cc\u0633\u06cc\u06c1"
    ],
    "wof:name":"Yerisiyeh",
    "wof:placetype":"locality"
},
  "geometry": {"coordinates":[49.66851,30.8206],"type":"Point"}
}