{
  "type": "Feature",
  "properties": {
    "gn:admin1_code":"11",
    "gn:asciiname":"Dar Dast-e Eqdam",
    "gn:country_code":"IR",
    "gn:dem":98,
    "gn:feature_class":"P",
    "gn:feature_code":"PPL",
    "gn:name":"Dar Dast-e Eqd\u0101m",
    "gn:population":0,
    "gn:timezone":"Asia/Tehran",
    "iso:country":"IR",
    "name:fas_x_preferred":[
        "\u062f\u064e\u0631 \u062f\u064e\u0633\u062a\u0650 \u0627\u0650\u0642\u062f\u0627\u0645"
    ],
    "name:fas_x_variant":[
        "Dar Dast-e Eqd\u0101m"
    ],
    "wof:name":"Dar Dast-e Eqdam",
    "wof:placetype":"locality"
},
  "geometry": {"coordinates":[56.12222,27.32139],"type":"Point"}
}