{
  "type": "Feature",
  "properties": {
    "gn:admin1_code":"23",
    "gn:asciiname":"Nosratabad",
    "gn:country_code":"IR",
    "gn:dem":1653,
    "gn:feature_class":"P",
    "gn:feature_code":"PPL",
    "gn:name":"No\u015frat\u0101b\u0101d",
    "gn:population":0,
    "gn:timezone":"Asia/Tehran",
    "iso:country":"IR",
    "name:fas_x_preferred":[
        "\u0646\u0635\u0631\u062a \u0622\u0628\u0627\u062f \u0633\u0641\u0644\u06cc"
    ],
    "name:fas_x_variant":[
        "No\u015frat\u0101b\u0101d",
        "No\u015frat\u0101b\u0101d-e Sofl\u00e1",
        "\u0646\u0635\u0631\u062a \u0622\u0628\u0627\u062f",
        "\u0646\u0635\u0631\u062a \u0622\u0628\u0627\u062f \u0639\u0644\u06cc\u0627"
    ],
    "name:und_x_variant":[
        "No\u015frat\u0101b\u0101d-e Sofl\u00e1",
        "No\u015frat\u0101b\u0101d-e \u2018Oly\u0101"
    ],
    "wof:name":"Nosratabad",
    "wof:placetype":"locality"
},
  "geometry": {"coordinates":[48.01323,33.96967],"type":"Point"}
}