{
  "type": "Feature",
  "properties": {
    "gn:admin1_code":"10",
    "gn:asciiname":"Kani Keh",
    "gn:country_code":"IR",
    "gn:dem":1265,
    "gn:feature_class":"P",
    "gn:feature_code":"PPL",
    "gn:name":"K\u0101n\u012b Keh",
    "gn:population":0,
    "gn:timezone":"Asia/Tehran",
    "iso:country":"IR",
    "name:fas_x_preferred":[
        "\u0645\u06cc\u0627\u0646 \u062a\u0646\u06af"
    ],
    "name:fas_x_variant":[
        "M\u012b\u0101n Tang",
        "\u06a9\u0627\u0646\u06cc \u06a9\u0647"
    ],
    "name:und_x_variant":[
        "K\u0101n\u012b Keh"
    ],
    "wof:name":"Kani Keh",
    "wof:placetype":"locality"
},
  "geometry": {"coordinates":[46.5932,33.36213],"type":"Point"}
}