{
  "type": "Feature",
  "properties": {
    "gn:admin1_code":"0",
    "gn:asciiname":"Azbaram",
    "gn:cc2":"IR",
    "gn:country_code":"IR",
    "gn:dem":2209,
    "gn:feature_class":"P",
    "gn:feature_code":"PPL",
    "gn:name":"Azbaram",
    "gn:population":0,
    "gn:timezone":"Asia/Tehran",
    "iso:country":"IR",
    "name:fas_x_preferred":[
        "\u0627\u064e\u0632\u0628\u064e\u0631\u064e\u0645"
    ],
    "name:und_x_variant":[
        "Izberam",
        "Azbaram"
    ],
    "wof:name":"Azbaram",
    "wof:placetype":"locality"
},
  "geometry": {"coordinates":[48.91667,37.13333],"type":"Point"}
}