{
  "type": "Feature",
  "properties": {
    "gn:admin1_code":"29",
    "gn:asciiname":"Khvajeh Soheyl Bid Khun",
    "gn:country_code":"IR",
    "gn:dem":2716,
    "gn:feature_class":"P",
    "gn:feature_code":"PPL",
    "gn:name":"Khv\u0101jeh Soheyl B\u012bd Kh\u016bn",
    "gn:population":0,
    "gn:timezone":"Asia/Tehran",
    "iso:country":"IR",
    "name:ara_x_preferred":[
        "\u062e\u0648\u0627\u062c\u0629 \u0633\u0647\u064a\u0644"
    ],
    "name:ceb_x_preferred":[
        "Khv\u0101jeh Soheyl B\u012bd Kh\u016bn"
    ],
    "name:fas_x_preferred":[
        "\u0628\u06cc\u062f \u062e\u0648\u0646"
    ],
    "name:fas_x_variant":[
        "B\u012bd Kh\u0101n",
        "B\u012bd Kh\u016bn",
        "Khv\u0101jeh Soheyl B\u012bd Kh\u016bn",
        "\u062e\u0648\u0627\u062e\u0647 \u0633\u0647\u064a\u0644 \u0628\u064a\u062f \u062e\u0648\u0646",
        "Khv\u0101jeh Soheyl",
        "\u062e\u0648\u0627\u062c\u0647 \u0633\u0647\u06cc\u0644"
    ],
    "name:swe_x_preferred":[
        "Khv\u0101jeh Soheyl B\u012bd Kh\u016bn"
    ],
    "name:und_x_variant":[
        "B\u012bd-e Kh\u0101n",
        "B\u012bd-e Khv\u0101n",
        "B\u012bd Khv\u0101n"
    ],
    "wof:name":"Khvajeh Soheyl Bid Khun",
    "wof:placetype":"locality"
},
  "geometry": {"coordinates":[56.50866,29.60898],"type":"Point"}
}