{
  "type": "Feature",
  "properties": {
    "gn:admin1_code":"0",
    "gn:asciiname":"Molla Borhan",
    "gn:country_code":"IR",
    "gn:dem":368,
    "gn:feature_class":"P",
    "gn:feature_code":"PPL",
    "gn:name":"Moll\u0101 Borh\u0101n",
    "gn:population":0,
    "gn:timezone":"Asia/Tehran",
    "iso:country":"IR",
    "name:fas_x_preferred":[
        "\u0645\u0644\u0627 \u0628\u0631\u0647\u0627\u0646"
    ],
    "name:fas_x_variant":[
        "Moll\u0101 Borh\u0101n"
    ],
    "wof:name":"Molla Borhan",
    "wof:placetype":"locality"
},
  "geometry": {"coordinates":[57.5189,27.4954],"type":"Point"}
}