{
  "type": "Feature",
  "properties": {
    "gn:admin1_code":"36",
    "gn:asciiname":"Harunabad-e `Olya",
    "gn:country_code":"IR",
    "gn:dem":393,
    "gn:feature_class":"P",
    "gn:feature_code":"PPL",
    "gn:name":"H\u0101r\u016bn\u0101b\u0101d-e \u2018Oly\u0101",
    "gn:population":0,
    "gn:timezone":"Asia/Tehran",
    "iso:country":"IR",
    "name:fas_x_preferred":[
        "H\u0101r\u016bn\u0101b\u0101d-e B\u0101l\u0101"
    ],
    "name:fas_x_variant":[
        "\u0647\u0627\u0631\u0648\u0646 \u0622\u0628\u0627\u062f \u0639\u0644\u06cc\u0627"
    ],
    "name:und_x_variant":[
        "H\u0101r\u016bn\u0101b\u0101d-e \u2018Oly\u0101"
    ],
    "wof:name":"Harunabad-e `Olya",
    "wof:placetype":"locality"
},
  "geometry": {"coordinates":[48.90438,36.91515],"type":"Point"}
}