{
  "type": "Feature",
  "properties": {
    "gn:admin1_code":"23",
    "gn:asciiname":"Sadat-e Gandabeh",
    "gn:country_code":"IR",
    "gn:dem":1015,
    "gn:feature_class":"P",
    "gn:feature_code":"PPL",
    "gn:name":"S\u0101d\u0101t-e Gand\u0101beh",
    "gn:population":0,
    "gn:timezone":"Asia/Tehran",
    "iso:country":"IR",
    "name:fas_x_preferred":[
        "\u0633\u0627\u062f\u0627\u062a\u0650 \u06af\u064e\u0646\u062f\u0627\u0628\u0650\u0647"
    ],
    "wof:name":"Sadat-e Gandabeh",
    "wof:placetype":"locality"
},
  "geometry": {"coordinates":[47.95,33.55],"type":"Point"}
}