{
  "type": "Feature",
  "properties": {
    "gn:admin1_code":"23",
    "gn:asciiname":"Deh Now Moqaddasi",
    "gn:country_code":"IR",
    "gn:dem":1568,
    "gn:feature_class":"P",
    "gn:feature_code":"PPL",
    "gn:name":"Deh Now Moqaddas\u012b",
    "gn:population":0,
    "gn:timezone":"Asia/Tehran",
    "iso:country":"IR",
    "name:ara_x_preferred":[
        "\u062f\u0647\u0646\u0648 \u0645\u0642\u062f\u0633\u064a"
    ],
    "name:ceb_x_preferred":[
        "Deh Now Moqaddas\u012b"
    ],
    "name:fas_x_preferred":[
        "\u062f\u0647 \u0646\u0648 \u0645\u0642\u062f\u0633\u06cc"
    ],
    "name:fas_x_variant":[
        "\u062f\u0647 \u0646\u0648\u06cc \u0645\u0642\u062f\u0633",
        "Dehnow-ye Moqaddas\u012b",
        "\u062f\u0647\u200c\u0646\u0648 \u0645\u0642\u062f\u0633\u06cc"
    ],
    "name:swe_x_preferred":[
        "Deh Now Moqaddas\u012b"
    ],
    "name:und_x_variant":[
        "Deh Nau",
        "Deh Now",
        "Deh Now-e Maqaddas",
        "Deh-\u012b-Nau",
        "Deh Now-ye Moqaddas"
    ],
    "wof:name":"Deh Now Moqaddasi",
    "wof:placetype":"locality"
},
  "geometry": {"coordinates":[48.8026,33.8716],"type":"Point"}
}