{
  "type": "Feature",
  "properties": {
    "gn:admin1_code":"38.0",
    "gn:asciiname":"Nesa",
    "gn:country_code":"IR",
    "gn:dem":1629,
    "gn:feature_class":"P",
    "gn:feature_code":"PPL",
    "gn:name":"Nes\u0101",
    "gn:population":0,
    "gn:timezone":"Asia/Tehran",
    "iso:country":"IR",
    "name:fas_x_preferred":[
        "Nes\u0101\u2018"
    ],
    "name:fas_x_variant":[
        "\u0646\u0633\u0627\u0621",
        "\u0646\u0633\u0627"
    ],
    "name:und_x_variant":[
        "Nes\u0101"
    ],
    "wof:name":"Nesa",
    "wof:placetype":"locality"
},
  "geometry": {"coordinates":[50.67543,36.39356],"type":"Point"}
}