{
  "type": "Feature",
  "properties": {
    "gn:admin1_code":"42.0",
    "gn:asciiname":"Bokhayedeh",
    "gn:country_code":"IR",
    "gn:dem":1478,
    "gn:feature_class":"P",
    "gn:feature_code":"PPL",
    "gn:name":"Bokh\u0101yedeh",
    "gn:population":0,
    "gn:timezone":"Asia/Tehran",
    "iso:country":"IR",
    "name:ceb_x_preferred":[
        "Qaz"
    ],
    "name:fas_x_preferred":[
        "\u0642\u0632"
    ],
    "name:fas_x_variant":[
        "\u0628\u062e\u0627\u06cc\u062f\u0647"
    ],
    "name:swe_x_preferred":[
        "Qaz"
    ],
    "name:und_x_variant":[
        "Bokh\u0101yedeh"
    ],
    "wof:name":"Bokhayedeh",
    "wof:placetype":"locality"
},
  "geometry": {"coordinates":[57.6262,36.3571],"type":"Point"}
}