{
  "type": "Feature",
  "properties": {
    "gn:admin1_code":"5.0",
    "gn:asciiname":"Deh-e Bar",
    "gn:country_code":"IR",
    "gn:dem":1233,
    "gn:feature_class":"P",
    "gn:feature_code":"PPL",
    "gn:name":"Deh-e Bar",
    "gn:population":0,
    "gn:timezone":"Asia/Tehran",
    "iso:country":"IR",
    "name:fas_x_preferred":[
        "\u062f\u0647 \u0628\u0631"
    ],
    "wof:name":"Deh-e Bar",
    "wof:placetype":"locality"
},
  "geometry": {"coordinates":[50.14806,31.11302],"type":"Point"}
}