{
  "type": "Feature",
  "properties": {
    "gn:admin1_code":"26",
    "gn:asciiname":"Qeshlaq-e Karimabad",
    "gn:country_code":"IR",
    "gn:dem":990,
    "gn:feature_class":"P",
    "gn:feature_code":"PPL",
    "gn:name":"Qeshl\u0101q-e Kar\u012bm\u0101b\u0101d",
    "gn:population":0,
    "gn:timezone":"Asia/Tehran",
    "iso:country":"IR",
    "name:fas_x_preferred":[
        "\u0642\u0650\u0634\u0644\u0627\u0642\u0650 \u0643\u064e\u0631\u064a\u0645 \u0622\u0628\u0627\u062f"
    ],
    "name:fas_x_variant":[
        "Qeshl\u0101q-e Kar\u012bm\u0101b\u0101d",
        "\u0642\u0634\u0644\u0627\u0642 \u06a9\u0631\u064a\u0645 \u0622\u0628\u0627\u062f"
    ],
    "wof:name":"Qeshlaq-e Karimabad",
    "wof:placetype":"locality"
},
  "geometry": {"coordinates":[51.8099,35.3798],"type":"Point"}
}