{
  "type": "Feature",
  "properties": {
    "gn:admin1_code":"29",
    "gn:asciiname":"Gavaru'iyeh-ye Bala",
    "gn:country_code":"IR",
    "gn:dem":2655,
    "gn:feature_class":"P",
    "gn:feature_code":"PPL",
    "gn:name":"Gavar\u016b\u2019\u012byeh-ye B\u0101l\u0101",
    "gn:population":0,
    "gn:timezone":"Asia/Tehran",
    "iso:country":"IR",
    "name:fas_x_preferred":[
        "Gavar\u016b\u2019\u012byeh-ye B\u0101l\u0101"
    ],
    "wof:name":"Gavaru'iyeh-ye Bala",
    "wof:placetype":"locality"
},
  "geometry": {"coordinates":[57.98333,28.93333],"type":"Point"}
}