{
  "type": "Feature",
  "properties": {
    "gn:admin1_code":"1",
    "gn:asciiname":"Safar `Alikhan Kandi",
    "gn:country_code":"IR",
    "gn:dem":1285,
    "gn:feature_class":"P",
    "gn:feature_code":"PPL",
    "gn:name":"\u015eafar \u2018Al\u012bkh\u0101n Kand\u012b",
    "gn:population":0,
    "gn:timezone":"Asia/Tehran",
    "iso:country":"IR",
    "name:fas_x_preferred":[
        "\u0635\u0641\u0631 \u0639\u0644\u06cc\u062e\u0627\u0646 \u06a9\u0646\u062f\u06cc"
    ],
    "name:fas_x_variant":[
        "\u0635\u064e\u0641\u064e\u0631\u0642\u064f\u0644\u06cc \u0643\u064e\u0646\u062f\u06cc",
        "\u015eafarqol\u012b Kand\u012b",
        "\u015eafar \u2018Al\u012bkh\u0101n Kand\u012b"
    ],
    "wof:name":"Safar `Alikhan Kandi",
    "wof:placetype":"locality"
},
  "geometry": {"coordinates":[45.1275,37.6691],"type":"Point"}
}