{
  "type": "Feature",
  "properties": {
    "gn:admin1_code":"8.0",
    "gn:asciiname":"Shiyeh",
    "gn:country_code":"IR",
    "gn:dem":1555,
    "gn:feature_class":"P",
    "gn:feature_code":"PPL",
    "gn:name":"Sh\u012byeh",
    "gn:population":0,
    "gn:timezone":"Asia/Tehran",
    "iso:country":"IR",
    "name:ara_x_preferred":[
        "\u0634\u064a\u0629"
    ],
    "name:fas_x_preferred":[
        "Sh\u012byeh"
    ],
    "name:fas_x_variant":[
        "\u0634\u06cc\u0647"
    ],
    "name:msa_x_preferred":[
        "Shiyeh"
    ],
    "name:ukr_x_preferred":[
        "\u0428\u0456\u0454"
    ],
    "name:und_x_variant":[
        "\u0634\u06cc\u0647"
    ],
    "wof:name":"Shiyeh",
    "wof:placetype":"locality"
},
  "geometry": {"coordinates":[50.02886,36.88441],"type":"Point"}
}