{
  "type": "Feature",
  "properties": {
    "gn:admin1_code":"11.0",
    "gn:asciiname":"Bon Zeh",
    "gn:country_code":"IR",
    "gn:dem":234,
    "gn:feature_class":"P",
    "gn:feature_code":"PPL",
    "gn:name":"Bon Zeh",
    "gn:population":0,
    "gn:timezone":"Asia/Tehran",
    "iso:country":"IR",
    "name:fas_x_preferred":[
        "\u0628\u0646 \u0632\u0647"
    ],
    "wof:name":"Bon Zeh",
    "wof:placetype":"locality"
},
  "geometry": {"coordinates":[57.3536,27.0822],"type":"Point"}
}