{
  "type": "Feature",
  "properties": {
    "gn:admin1_code":"35.0",
    "gn:asciiname":"Mal`eh",
    "gn:country_code":"IR",
    "gn:dem":290,
    "gn:feature_class":"P",
    "gn:feature_code":"PPL",
    "gn:name":"Mal\u2018eh",
    "gn:population":0,
    "gn:timezone":"Asia/Tehran",
    "iso:country":"IR",
    "name:fas_x_preferred":[
        "\u0645\u064e\u0644\u0639\u0650\u0647"
    ],
    "name:fas_x_variant":[
        "Mal\u2018eh"
    ],
    "wof:name":"Mal`eh",
    "wof:placetype":"locality"
},
  "geometry": {"coordinates":[52.86666999999999,36.33333],"type":"Point"}
}