{
  "type": "Feature",
  "properties": {
    "gn:country":"IR",
    "gn:fcode":"PPL",
    "gn:population":29392,
    "iso:country":"IR",
    "name:ara_x_preferred":[
        "\u0642\u0647\u062f\u0631\u064a\u062c\u0627\u0646"
    ],
    "name:azb_x_preferred":[
        "\u0642\u0647\u062f\u0631\u06cc\u062c\u0627\u0646"
    ],
    "name:aze_x_preferred":[
        "Q\u0259hd\u0259rican"
    ],
    "name:ceb_x_preferred":[
        "Qahder\u012bj\u0101n"
    ],
    "name:eng_x_preferred":[
        "Qahderijan"
    ],
    "name:fas_x_preferred":[
        "Qahder\u012bj\u0101n"
    ],
    "name:fas_x_variant":[
        "\u0642\u0647\u062f\u0631\u06cc\u062c\u0627\u0646"
    ],
    "name:fra_x_preferred":[
        "Qahderijan"
    ],
    "name:gle_x_preferred":[
        "Qahderijan"
    ],
    "name:glg_x_preferred":[
        "Qahderijan"
    ],
    "name:ita_x_preferred":[
        "Qahderijan"
    ],
    "name:mlg_x_preferred":[
        "Qahderijan"
    ],
    "name:mzn_x_preferred":[
        "\u0642\u0647\u062f\u0631\u06cc\u062c\u0627\u0646"
    ],
    "name:nan_x_preferred":[
        "Qahderijan"
    ],
    "name:nld_x_preferred":[
        "Qahderijan"
    ],
    "name:pol_x_preferred":[
        "Ghahdarid\u017can"
    ],
    "name:rus_x_preferred":[
        "\u041a\u0435\u0445\u0434\u0435\u0440\u0438\u0434\u0436\u0430\u043d"
    ],
    "name:swe_x_preferred":[
        "Qahder\u012bj\u0101n"
    ],
    "name:tur_x_preferred":[
        "Kehderican"
    ],
    "name:und_x_variant":[
        "Kedarg\u016bn"
    ],
    "qs:name":"Qahder\u012bj\u0101n",
    "qs:photos_9r":0,
    "qs:photos_sr":0,
    "qs:pop_sr":"7",
    "wd:wordcount":110,
    "wof:name":"Qahder\u012bj\u0101n",
    "wof:placetype":"locality",
    "wof:population":29392
},
  "geometry": {"coordinates":[51.455,32.5767],"type":"Point"}
}