{
  "type": "Feature",
  "properties": {
    "gn:admin1_code":"23",
    "gn:asciiname":"Avareh",
    "gn:country_code":"IR",
    "gn:dem":1266,
    "gn:feature_class":"P",
    "gn:feature_code":"PPL",
    "gn:name":"\u0100v\u0101reh",
    "gn:population":0,
    "gn:timezone":"Asia/Tehran",
    "iso:country":"IR",
    "name:fas_x_preferred":[
        "\u0622\u0648\u0627\u0631\u0647"
    ],
    "name:fas_x_variant":[
        "\u0100v\u0101reh",
        "\u0627\u0648\u0627\u0631\u0647"
    ],
    "wof:name":"Avareh",
    "wof:placetype":"locality"
},
  "geometry": {"coordinates":[47.5117,33.4518],"type":"Point"}
}