{
  "type": "Feature",
  "properties": {
    "gn:admin1_code":"41",
    "gn:asciiname":"Joft Rud",
    "gn:country_code":"IR",
    "gn:dem":1241,
    "gn:feature_class":"P",
    "gn:feature_code":"PPL",
    "gn:name":"Joft R\u016bd",
    "gn:population":0,
    "gn:timezone":"Asia/Tehran",
    "iso:country":"IR",
    "name:fas_x_preferred":[
        "Joft R\u016bd"
    ],
    "name:fas_x_variant":[
        "\u062c\u0641\u062a \u0631\u0648\u062f",
        "Jufr\u016bd",
        "Jofr\u016bd"
    ],
    "name:und_x_variant":[
        "Jufr\u016bd",
        "Jofr\u016bd",
        "Joft Rood",
        "\u062c\u0641\u062a \u0631\u0648\u062f"
    ],
    "wof:name":"Joft Rud",
    "wof:placetype":"locality"
},
  "geometry": {"coordinates":[58.59812,32.86505],"type":"Point"}
}