{
  "type": "Feature",
  "properties": {
    "gn:admin1_code":"1.0",
    "gn:asciiname":"Shah Gildi",
    "gn:country_code":"IR",
    "gn:dem":1462,
    "gn:feature_class":"P",
    "gn:feature_code":"PPL",
    "gn:name":"Sh\u0101h G\u012bld\u012b",
    "gn:population":0,
    "gn:timezone":"Asia/Tehran",
    "iso:country":"IR",
    "name:fas_x_preferred":[
        "\u0634\u0627\u0647 \u06af\u06cc\u0644\u062f\u06cc"
    ],
    "name:fas_x_variant":[
        "Sh\u0101h G\u012bld\u012b"
    ],
    "wof:name":"Shah Gildi",
    "wof:placetype":"locality"
},
  "geometry": {"coordinates":[45.9083,36.4712],"type":"Point"}
}