{
  "type": "Feature",
  "properties": {
    "gn:admin1_code":"37",
    "gn:asciiname":"Yolmeh Khandan",
    "gn:country_code":"IR",
    "gn:dem":-11,
    "gn:feature_class":"P",
    "gn:feature_code":"PPL",
    "gn:name":"Yolmeh Khand\u0101n",
    "gn:population":0,
    "gn:timezone":"Asia/Tehran",
    "iso:country":"IR",
    "name:ara_x_preferred":[
        "\u064a\u0644\u0645\u0629 \u062e\u0646\u062f\u0627\u0646"
    ],
    "name:fas_x_preferred":[
        "Yolmeh Khand\u0101n"
    ],
    "name:fas_x_variant":[
        "Y\u016blmeh Khand\u0101n",
        "\u064a\u0644\u0645\u0647 \u062e\u0646\u062f\u0627\u0646",
        "\u064a\u0648\u0644\u0645\u0647 \u062e\u0646\u062f\u0627\u0646",
        "\u06cc\u0644\u0645\u0647\u200c\u062e\u0646\u062f\u0627\u0646"
    ],
    "name:msa_x_preferred":[
        "Yolmeh Khandan"
    ],
    "name:und_x_variant":[
        "Yolmeh Khand\u0101n-e P\u0101\u2019\u012bn"
    ],
    "name:urd_x_preferred":[
        "\u06cc\u0648\u0644\u0645\u06cc\u06c1 \u062e\u0627\u0646\u062f\u0627\u0646"
    ],
    "wof:name":"Yolmeh Khandan",
    "wof:placetype":"locality"
},
  "geometry": {"coordinates":[54.4991,37.02042],"type":"Point"}
}