{
  "type": "Feature",
  "properties": {
    "gn:admin1_code":"32",
    "gn:asciiname":"Qeshlaq-e Soleyman Akbar",
    "gn:country_code":"IR",
    "gn:dem":152,
    "gn:feature_class":"P",
    "gn:feature_code":"PPL",
    "gn:name":"Qeshl\u0101q-e Soleym\u0101n Akbar",
    "gn:population":0,
    "gn:timezone":"Asia/Tehran",
    "iso:country":"IR",
    "name:fas_x_preferred":[
        "Qeshl\u0101q-e Soleym\u0101n Akbar"
    ],
    "name:fas_x_variant":[
        "\u0642\u0650\u0634\u0644\u0627\u0642\u0650 \u0633\u064f\u0644\u0650\u064a\u0645\u0627\u0646 \u0627\u064e\u0643\u0628\u064e\u0631"
    ],
    "wof:name":"Qeshlaq-e Soleyman Akbar",
    "wof:placetype":"locality"
},
  "geometry": {"coordinates":[48.05,39.45],"type":"Point"}
}