{
  "type": "Feature",
  "properties": {
    "gn:admin1_code":"35",
    "gn:asciiname":"Reykandeh",
    "gn:country_code":"IR",
    "gn:dem":110,
    "gn:feature_class":"P",
    "gn:feature_code":"PPL",
    "gn:name":"Reykandeh",
    "gn:population":0,
    "gn:timezone":"Asia/Tehran",
    "iso:country":"IR",
    "name:ceb_x_preferred":[
        "Reykandeh"
    ],
    "name:fas_x_preferred":[
        "\u0631\u064a\u0643\u0646\u062f\u0647"
    ],
    "name:fas_x_variant":[
        "\u0631\u064a\u0643\u064e\u0646\u062f\u0650\u0647",
        "\u0631\u06cc\u06a9\u0646\u062f\u0647"
    ],
    "name:swe_x_preferred":[
        "Reykandeh"
    ],
    "name:und_x_variant":[
        "R\u012bkandeh",
        "Reykandeh"
    ],
    "wof:name":"Reykandeh",
    "wof:placetype":"locality"
},
  "geometry": {"coordinates":[52.97393,36.45009],"type":"Point"}
}