{
  "type": "Feature",
  "properties": {
    "gn:admin1_code":"16.0",
    "gn:asciiname":"sara",
    "gn:country_code":"IR",
    "gn:dem":1544,
    "gn:feature_class":"P",
    "gn:feature_code":"PPL",
    "gn:name":"\u0633\u064e\u0631\u0627",
    "gn:population":0,
    "gn:timezone":"Asia/Tehran",
    "iso:country":"IR",
    "name:fas_x_preferred":[
        "Sar\u0101"
    ],
    "name:fas_x_variant":[
        "\u0633\u0631\u0627",
        "\u0633\u064e\u0631\u0627"
    ],
    "wof:name":"sara",
    "wof:placetype":"locality"
},
  "geometry": {"coordinates":[46.2147,36.3756],"type":"Point"}
}