{
  "type": "Feature",
  "properties": {
    "gn:admin1_code":"33",
    "gn:asciiname":"Tanur Aghaj",
    "gn:country_code":"IR",
    "gn:dem":1978,
    "gn:feature_class":"P",
    "gn:feature_code":"PPL",
    "gn:name":"Tan\u016br \u0100gh\u0101j",
    "gn:population":0,
    "gn:timezone":"Asia/Tehran",
    "iso:country":"IR",
    "name:ara_x_preferred":[
        "\u062a\u0646\u062f\u0631 \u0623\u063a\u0627\u062c"
    ],
    "name:azb_x_preferred":[
        "\u062a\u0646\u062f\u06cc\u0631\u0622\u063a\u0627\u062c"
    ],
    "name:fas_x_preferred":[
        "\u062a\u0646\u0648\u0631 \u0622\u063a\u0627\u062c"
    ],
    "name:fas_x_variant":[
        "Tan\u016br \u0100gh\u0101j",
        "\u062a\u0646\u062f\u0631 \u0622\u063a\u0627\u062c",
        "\u062a\u0646\u062f\u0631\u0622\u063a\u0627\u062c"
    ],
    "name:msa_x_preferred":[
        "Tandar Aghaj"
    ],
    "name:und_x_variant":[
        "Tandar \u0100gh\u0101j"
    ],
    "wof:name":"Tanur Aghaj",
    "wof:placetype":"locality"
},
  "geometry": {"coordinates":[46.7216,37.76106],"type":"Point"}
}