{
  "type": "Feature",
  "properties": {
    "gn:admin1_code":"11",
    "gn:asciiname":"Dar Gir",
    "gn:country_code":"IR",
    "gn:dem":83,
    "gn:feature_class":"P",
    "gn:feature_code":"PPL",
    "gn:name":"Dar G\u012br",
    "gn:population":0,
    "gn:timezone":"Asia/Tehran",
    "iso:country":"IR",
    "name:fas_x_preferred":[
        "\u062f\u0631 \u06af\u064a\u0631"
    ],
    "name:fas_x_variant":[
        "Dar G\u012br"
    ],
    "wof:name":"Dar Gir",
    "wof:placetype":"locality"
},
  "geometry": {"coordinates":[56.2231,27.3307],"type":"Point"}
}