{
  "type": "Feature",
  "properties": {
    "gn:admin1_code":"23.0",
    "gn:asciiname":"Sorab Pardeh-ye Seh",
    "gn:country_code":"IR",
    "gn:dem":1390,
    "gn:feature_class":"P",
    "gn:feature_code":"PPL",
    "gn:name":"Sor\u0101b Pardeh-ye Seh",
    "gn:population":0,
    "gn:timezone":"Asia/Tehran",
    "iso:country":"IR",
    "name:fas_x_preferred":[
        "\u0633\u0631\u0627\u0628 \u067e\u0631\u062f\u0647 \u06f3"
    ],
    "name:und_x_variant":[
        "Sor\u0101b Pardeh-ye Seh"
    ],
    "wof:name":"Sorab Pardeh-ye Seh",
    "wof:placetype":"locality"
},
  "geometry": {"coordinates":[48.49423,33.45192],"type":"Point"}
}