{
  "type": "Feature",
  "properties": {
    "gn:admin1_code":"7",
    "gn:asciiname":"Kalhor-e Bala",
    "gn:country_code":"IR",
    "gn:dem":2074,
    "gn:feature_class":"P",
    "gn:feature_code":"PPL",
    "gn:name":"Kalhor-e B\u0101l\u0101",
    "gn:population":0,
    "gn:timezone":"Asia/Tehran",
    "iso:country":"IR",
    "name:fas_x_preferred":[
        "\u06a9\u0644\u0647\u0648\u0631"
    ],
    "name:fas_x_variant":[
        "Kalh\u016br",
        "\u06a9\u0644\u0647\u0631 \u0628\u0627\u0644\u0627",
        "\u06a9\u0644\u0647\u0631"
    ],
    "name:und_x_variant":[
        "Kalhor",
        "Kalhor-e B\u0101l\u0101"
    ],
    "wof:name":"Kalhor-e Bala",
    "wof:placetype":"locality"
},
  "geometry": {"coordinates":[53.3965,30.2897],"type":"Point"}
}