{
  "type": "Feature",
  "properties": {
    "gn:admin1_code":"15.0",
    "gn:asciiname":"`Abbas Yales-e Yek",
    "gn:country_code":"IR",
    "gn:dem":18,
    "gn:feature_class":"P",
    "gn:feature_code":"PPL",
    "gn:name":"\u2018Abb\u0101s Y\u0101les-e Yek",
    "gn:population":0,
    "gn:timezone":"Asia/Tehran",
    "iso:country":"IR",
    "name:fas_x_preferred":[
        "\u0639\u0628\u0627\u0633 \u06cc\u0627\u0644\u0633 \u06cc\u06a9"
    ],
    "name:fas_x_variant":[
        "\u2018Abb\u0101s-e Y\u0101l\u012bs",
        "\u2018Abb\u0101s Y\u0101les-e Yek"
    ],
    "name:und_x_variant":[
        "\u2018Abb\u0101s\u012b"
    ],
    "wof:name":"`Abbas Yales-e Yek",
    "wof:placetype":"locality"
},
  "geometry": {"coordinates":[48.43002,31.34946],"type":"Point"}
}