{
  "type": "Feature",
  "properties": {
    "gn:admin1_code":"15",
    "gn:asciiname":"Taq Hoseyn",
    "gn:country_code":"IR",
    "gn:dem":285,
    "gn:feature_class":"P",
    "gn:feature_code":"PPL",
    "gn:name":"\u0162\u0101q \u1e28oseyn",
    "gn:population":0,
    "gn:timezone":"Asia/Tehran",
    "iso:country":"IR",
    "name:fas_x_preferred":[
        "\u0637\u0627\u0642 \u062d\u0633\u06cc\u0646"
    ],
    "name:fas_x_variant":[
        "\u0162\u0101q \u1e28oseyn-e Kol\u0101dal\u012bl\u012b",
        "\u0162\u0101q \u1e28oseyn",
        "\u0637\u0627\u0642 \u062d\u0633\u06cc\u0646 \u06a9\u0644\u0627\u0647 \u062f\u0644\u06cc\u0644\u06cc"
    ],
    "name:und_x_variant":[
        "\u0162\u0101q \u1e28oseyn-e \u015eeyd H\u0101d\u012b",
        "\u0162\u0101q \u1e28oseyn-e Kol\u0101h Dal\u012bl\u012b"
    ],
    "wof:name":"Taq Hoseyn",
    "wof:placetype":"locality"
},
  "geometry": {"coordinates":[48.18656,32.61873],"type":"Point"}
}