{
  "type": "Feature",
  "properties": {
    "gn:admin1_code":"38",
    "gn:asciiname":"Bademjin",
    "gn:country_code":"IR",
    "gn:dem":1774,
    "gn:feature_class":"P",
    "gn:feature_code":"PPL",
    "gn:name":"B\u0101demj\u012bn",
    "gn:population":0,
    "gn:timezone":"Asia/Tehran",
    "iso:country":"IR",
    "name:ceb_x_preferred":[
        "B\u0101demj\u012bn"
    ],
    "name:fas_x_preferred":[
        "\u0628\u0627\u062f\u0645\u062c\u06cc\u0646"
    ],
    "name:fas_x_variant":[
        "B\u0101tmaj\u012bn",
        "B\u0101demj\u012bn"
    ],
    "name:swe_x_preferred":[
        "B\u0101demj\u012bn"
    ],
    "name:und_x_variant":[
        "Bademjin Ghaghzan Sharghi",
        "Batmadzhin"
    ],
    "wof:name":"Bademjin",
    "wof:placetype":"locality"
},
  "geometry": {"coordinates":[49.89665,36.41763],"type":"Point"}
}