{
  "type": "Feature",
  "properties": {
    "gn:admin1_code":"28.0",
    "gn:admin2_code":"449483",
    "gn:asciiname":"`Aliabad",
    "gn:country_code":"IR",
    "gn:dem":1773,
    "gn:feature_class":"P",
    "gn:feature_code":"PPL",
    "gn:name":"\u2018Al\u012b\u0101b\u0101d",
    "gn:population":0,
    "gn:timezone":"Asia/Tehran",
    "iso:country":"IR",
    "name:fas_x_historical":[
        "\u0639\u0644\u06cc \u0622\u0628\u0627\u062f \u062c\u0645\u0628\u0632\u0647"
    ],
    "name:fas_x_preferred":[
        "AliAbad"
    ],
    "name:fas_x_variant":[
        "\u2018Al\u012b\u0101b\u0101d",
        "\u0639\u0644\u06cc \u0622\u0628\u0627\u062f",
        "\u0639\u0644\u06cc \u0622\u0628\u0627\u062f \u062c\u0645\u0628\u0632\u0647"
    ],
    "wof:name":"`Aliabad",
    "wof:placetype":"locality"
},
  "geometry": {"coordinates":[51.62778,32.18233],"type":"Point"}
}