{
  "type": "Feature",
  "properties": {
    "gn:admin1_code":"3",
    "gn:asciiname":"Gorazabad",
    "gn:country_code":"IR",
    "gn:dem":1544,
    "gn:feature_class":"P",
    "gn:feature_code":"PPL",
    "gn:name":"Gor\u0101z\u0101b\u0101d",
    "gn:population":0,
    "gn:timezone":"Asia/Tehran",
    "iso:country":"IR",
    "name:fas_x_preferred":[
        "\u06af\u0631\u0627\u0632 \u0622\u0628\u0627\u062f"
    ],
    "name:fas_x_variant":[
        "Gor\u0101z\u0101b\u0101d",
        "\u0639\u0644\u06cc \u0622\u0628\u0627\u062f",
        "\u06af\u0631\u0627\u0632\u0622\u0628\u0627\u062f"
    ],
    "name:und_x_variant":[
        "\u2018Al\u012b\u0101b\u0101d"
    ],
    "wof:name":"Gorazabad",
    "wof:placetype":"locality"
},
  "geometry": {"coordinates":[50.75451,31.5129],"type":"Point"}
}