{
  "type": "Feature",
  "properties": {
    "gn:admin1_code":"25.0",
    "gn:asciiname":"Rezvan",
    "gn:country_code":"IR",
    "gn:dem":1342,
    "gn:feature_class":"P",
    "gn:feature_code":"PPL",
    "gn:name":"Re\u1e95v\u0101n",
    "gn:population":0,
    "gn:timezone":"Asia/Tehran",
    "iso:country":"IR",
    "name:fas_x_preferred":[
        "\u0633\u0648\u062f\u064f\u0642\u0644\u0627\u0646"
    ],
    "name:fas_x_variant":[
        "\u0631\u0636\u0648\u0627\u0646",
        "\u0633\u0648\u062f\u0627\u063a\u0644\u0627\u0646",
        "S\u016bdoql\u0101n",
        "S\u016b D\u0101ghel\u0101n",
        "\u0633\u0648 \u062f\u0627\u063a\u0650\u0644\u0627\u0646",
        "S\u016bd\u0101ghl\u0101n",
        "\u0633\u0648\u062f\u0627\u063a\u0644\u0646"
    ],
    "name:rus_x_preferred":[
        "\u0420\u0435\u0437\u0432\u0430\u043d"
    ],
    "name:und_x_variant":[
        "Re\u1e95v\u0101n",
        "S\u016bd\u0101ghlan"
    ],
    "wof:name":"Rezvan",
    "wof:placetype":"locality"
},
  "geometry": {"coordinates":[55.79825,37.18488],"type":"Point"}
}