{
  "type": "Feature",
  "properties": {
    "gn:admin1_code":"33",
    "gn:asciiname":"Nadilu",
    "gn:country_code":"IR",
    "gn:dem":1432,
    "gn:feature_class":"P",
    "gn:feature_code":"PPL",
    "gn:name":"N\u0101d\u012bl\u016b",
    "gn:population":0,
    "gn:timezone":"Asia/Tehran",
    "iso:country":"IR",
    "name:fas_x_preferred":[
        "\u0646\u0627\u062f\u06cc\u0644\u0648"
    ],
    "name:fas_x_variant":[
        "\u0646\u0627\u062f\u064a\u0644\u0651\u0648",
        "N\u0101d\u012bl\u016b"
    ],
    "name:msa_x_preferred":[
        "Nadilu"
    ],
    "name:und_x_variant":[
        "N\u0101d\u012bll\u016b"
    ],
    "wof:name":"Nadilu",
    "wof:placetype":"locality"
},
  "geometry": {"coordinates":[45.9649,37.7241],"type":"Point"}
}