{
  "type": "Feature",
  "properties": {
    "gn:admin1_code":"35.0",
    "gn:asciiname":"Vash Sara Dasht",
    "gn:country_code":"IR",
    "gn:dem":2442,
    "gn:feature_class":"P",
    "gn:feature_code":"PPL",
    "gn:name":"V\u0101sh Sar\u0101 Dasht",
    "gn:population":0,
    "gn:timezone":"Asia/Tehran",
    "iso:country":"IR",
    "name:fas_x_preferred":[
        "V\u0101sh Sar\u0101 Dasht"
    ],
    "name:fas_x_variant":[
        "\u0648\u0627\u0634 \u0633\u0631\u0627 \u062f\u0634\u062a"
    ],
    "name:und_x_variant":[
        "\u0648\u0627\u0634 \u0633\u0631\u0627 \u062f\u0634\u062a"
    ],
    "wof:name":"Vash Sara Dasht",
    "wof:placetype":"locality"
},
  "geometry": {"coordinates":[50.4659,36.83055],"type":"Point"}
}