{
  "type": "Feature",
  "properties": {
    "gn:admin1_code":"7",
    "gn:asciiname":"Tang-e Ru'in",
    "gn:country_code":"IR",
    "gn:dem":716,
    "gn:feature_class":"P",
    "gn:feature_code":"PPL",
    "gn:name":"Tang-e R\u016b\u2019\u012bn",
    "gn:population":0,
    "gn:timezone":"Asia/Tehran",
    "iso:country":"IR",
    "name:fas_x_preferred":[
        "\u062a\u0646\u06af \u0631\u0648\u0626\u06cc\u0646"
    ],
    "name:fas_x_variant":[
        "Tang-e R\u016bdeh",
        "Tang-e R\u016b\u2019\u012bn",
        "\u062a\u0646\u06af\u0631\u0648\u06cc\u06cc\u0646"
    ],
    "name:und_x_variant":[
        "Tangr\u016b\u012b\u012bn"
    ],
    "wof:name":"Tang-e Ru'in",
    "wof:placetype":"locality"
},
  "geometry": {"coordinates":[53.24800000000001,28.3387],"type":"Point"}
}