{
  "type": "Feature",
  "properties": {
    "gn:admin1_code":"8",
    "gn:asciiname":"Malek Mian-e `Olya",
    "gn:country_code":"IR",
    "gn:dem":14,
    "gn:feature_class":"P",
    "gn:feature_code":"PPL",
    "gn:name":"Malek M\u012b\u0101n-e \u2018Oly\u0101",
    "gn:population":0,
    "gn:timezone":"Asia/Tehran",
    "iso:country":"IR",
    "name:ceb_x_preferred":[
        "Malek M\u012b\u0101n"
    ],
    "name:fas_x_preferred":[
        "Malek M\u012b\u0101n"
    ],
    "name:fas_x_variant":[
        "\u0645\u0644\u06a9 \u0645\u06cc\u0627\u0646",
        "\u0645\u0644\u06a9 \u0645\u06cc\u0627\u0646 \u0639\u0644\u06cc\u0627"
    ],
    "name:msa_x_preferred":[
        "Molk-e Mian"
    ],
    "name:swe_x_preferred":[
        "Malek M\u012b\u0101n"
    ],
    "name:ukr_x_preferred":[
        "\u041c\u043e\u043b\u044c\u043a-\u0435-\u041c\u0456\u044f\u043d"
    ],
    "name:und_x_variant":[
        "Molk-e M\u012b\u0101n",
        "Molk Meyan",
        "Malek M\u012b\u0101n-e \u2018Oly\u0101"
    ],
    "wof:name":"Malek Mian-e `Olya",
    "wof:placetype":"locality"
},
  "geometry": {"coordinates":[50.46962,37.00185],"type":"Point"}
}