{
  "type": "Feature",
  "properties": {
    "gn:admin1_code":"9",
    "gn:asciiname":"Gholam Veys",
    "gn:country_code":"IR",
    "gn:dem":1903,
    "gn:feature_class":"P",
    "gn:feature_code":"PPL",
    "gn:name":"Ghol\u0101m Veys",
    "gn:population":0,
    "gn:timezone":"Asia/Tehran",
    "iso:country":"IR",
    "name:azb_x_preferred":[
        "\u063a\u0644\u0627\u0645 \u0648\u06cc\u0633"
    ],
    "name:fas_x_preferred":[
        "\u063a\u0644\u0627\u0645 \u0648\u064a\u0633"
    ],
    "name:fas_x_variant":[
        "Ghol\u0101m Veys",
        "\u063a\u0644\u0627\u0645 \u0648\u06cc\u0633"
    ],
    "name:und_x_variant":[
        "Ghul\u0101m Ra\u012bs",
        "Gholam veis"
    ],
    "wof:name":"Gholam Veys",
    "wof:placetype":"locality"
},
  "geometry": {"coordinates":[48.52583,35.62979],"type":"Point"}
}