{
  "type": "Feature",
  "properties": {
    "gn:admin1_code":"29.0",
    "gn:asciiname":"Zahedan",
    "gn:country_code":"IR",
    "gn:dem":1883,
    "gn:feature_class":"P",
    "gn:feature_code":"PPL",
    "gn:name":"Z\u0101hed\u0101n",
    "gn:population":0,
    "gn:timezone":"Asia/Tehran",
    "iso:country":"IR",
    "name:fas_x_preferred":[
        "Z\u0101hed\u0101n"
    ],
    "wof:name":"Zahedan",
    "wof:placetype":"locality"
},
  "geometry": {"coordinates":[57.87778,28.90167000000001],"type":"Point"}
}