{
  "type": "Feature",
  "properties": {
    "gn:admin1_code":"5.0",
    "gn:asciiname":"Bid Tak",
    "gn:country_code":"IR",
    "gn:dem":2194,
    "gn:feature_class":"P",
    "gn:feature_code":"PPL",
    "gn:name":"B\u012bd T\u0101k",
    "gn:population":0,
    "gn:timezone":"Asia/Tehran",
    "iso:country":"IR",
    "name:fas_x_preferred":[
        "B\u012bd T\u0101k"
    ],
    "name:fas_x_variant":[
        "\u0628\u06cc\u062f \u062a\u0627\u0643"
    ],
    "wof:name":"Bid Tak",
    "wof:placetype":"locality"
},
  "geometry": {"coordinates":[51.40945,30.56915],"type":"Point"}
}