{
  "type": "Feature",
  "properties": {
    "gn:admin1_code":"5",
    "gn:asciiname":"Sadat",
    "gn:cc2":"IR",
    "gn:country_code":"IR",
    "gn:dem":1402,
    "gn:feature_class":"P",
    "gn:feature_code":"PPL",
    "gn:name":"S\u0101d\u0101t",
    "gn:population":0,
    "gn:timezone":"Asia/Tehran",
    "iso:country":"IR",
    "name:fas_x_preferred":[
        "\u0633\u0627\u062f\u0627\u062a"
    ],
    "name:fas_x_variant":[
        "\u0633\u064e\u0639\u064e\u062f\u064e\u062a",
        "S\u0101d\u0101t"
    ],
    "name:fra_x_preferred":[
        "Sadat"
    ],
    "name:und_x_variant":[
        "Sa\u2018adat"
    ],
    "wof:name":"Sadat",
    "wof:placetype":"locality"
},
  "geometry": {"coordinates":[50.68472,31.38056],"type":"Point"}
}