{
  "type": "Feature",
  "properties": {
    "gn:admin1_code":"4",
    "gn:asciiname":"Chah-e Qanbar",
    "gn:country_code":"IR",
    "gn:dem":715,
    "gn:feature_class":"P",
    "gn:feature_code":"PPLF",
    "gn:name":"Ch\u0101h-e Qanbar",
    "gn:population":0,
    "gn:timezone":"Asia/Tehran",
    "iso:country":"IR",
    "name:fas_x_preferred":[
        "Cher\u0101p"
    ],
    "name:fas_x_variant":[
        "\u0686\u0627\u0647 \u0642\u0646\u0628\u0631",
        "\u0686\u0627\u0647 \u06a9\u0645\u0628\u0631",
        "\u0686\u0631\u0627\u0628"
    ],
    "name:und_x_variant":[
        "Ch\u0101h-e Qanbar",
        "Ch\u0101h K\u0101mbar",
        "Ch\u0101h-e K\u0101mbar",
        "Ch\u0101h-e Kambar",
        "Cher\u0101b"
    ],
    "wof:name":"Chah-e Qanbar",
    "wof:placetype":"locality"
},
  "geometry": {"coordinates":[59.57011,26.85747000000001],"type":"Point"}
}