{
  "type": "Feature",
  "properties": {
    "gn:admin1_code":"4.0",
    "gn:asciiname":"Polgan",
    "gn:country_code":"IR",
    "gn:dem":33,
    "gn:feature_class":"P",
    "gn:feature_code":"PPL",
    "gn:name":"Polg\u0101n",
    "gn:population":0,
    "gn:timezone":"Asia/Tehran",
    "iso:country":"IR",
    "name:fas_x_preferred":[
        "Polg\u0101n"
    ],
    "name:fas_x_variant":[
        "\u067e\u0644\u06af\u0627\u0646"
    ],
    "name:und_x_variant":[
        "\u067e\u0644\u06af\u0627\u0646",
        "Pol"
    ],
    "wof:name":"Polgan",
    "wof:placetype":"locality"
},
  "geometry": {"coordinates":[61.08331,25.58061],"type":"Point"}
}