{
  "type": "Feature",
  "properties": {
    "gn:admin1_code":"15",
    "gn:asciiname":"Gesvan-e Yek",
    "gn:country_code":"IR",
    "gn:dem":29,
    "gn:feature_class":"P",
    "gn:feature_code":"PPL",
    "gn:name":"Gesv\u0101n-e Yek",
    "gn:population":0,
    "gn:timezone":"Asia/Tehran",
    "iso:country":"IR",
    "name:ara_x_preferred":[
        "\u063a\u0635\u0648\u0627\u0646 \u0627\u0644\u0623\u0648\u0644\u0649"
    ],
    "name:ceb_x_preferred":[
        "Ge\u015fv\u0101n-e Yek"
    ],
    "name:fas_x_preferred":[
        "\u06af\u0635\u0648\u0627\u0646 \u06cc\u06a9"
    ],
    "name:fas_x_variant":[
        "G\u012bsov\u0101n-e Yek",
        "Ge\u015fv\u0101n-e Yek",
        "\u06af\u0633\u0648\u0627\u0646 \u06cc\u06a9"
    ],
    "name:swe_x_preferred":[
        "Ge\u015fv\u0101n-e Yek"
    ],
    "name:und_x_variant":[
        "Gaswan\u00e9 Yek",
        "G\u012bsv\u0101n-e Yek",
        "Gesv\u0101n Yak",
        "Gesv\u0101n-e Yek"
    ],
    "wof:name":"Gesvan-e Yek",
    "wof:placetype":"locality"
},
  "geometry": {"coordinates":[49.08356,31.44759],"type":"Point"}
}