{
  "type": "Feature",
  "properties": {
    "gn:admin1_code":"4.0",
    "gn:asciiname":"Mojtame`-e `Ali Akbar",
    "gn:country_code":"IR",
    "gn:dem":480,
    "gn:feature_class":"P",
    "gn:feature_code":"PPL",
    "gn:name":"Mojtame\u2018-e \u2018Al\u012b Akbar",
    "gn:population":0,
    "gn:timezone":"Asia/Tehran",
    "iso:country":"IR",
    "name:fas_x_preferred":[
        "\u0645\u062c\u062a\u0645\u0639 \u0639\u0644\u06cc \u0627\u06a9\u0628\u0631"
    ],
    "name:fas_x_variant":[
        "Deh-e \u2018Al\u012b Akbar",
        "Mojtame\u2018-e \u2018Al\u012b Akbar",
        "\u062f\u0647 \u0639\u0644\u06cc \u0627\u06a9\u0628\u0631",
        "\u0634\u0647\u0631\u06a9 \u0639\u0644\u06cc \u0627\u06a9\u0628\u0631"
    ],
    "name:und_x_variant":[
        "Shahrak-e \u2018Al\u012b Akbar"
    ],
    "wof:name":"Mojtame`-e `Ali Akbar",
    "wof:placetype":"locality"
},
  "geometry": {"coordinates":[61.32836,30.93912000000001],"type":"Point"}
}