{
  "type": "Feature",
  "properties": {
    "gn:admin1_code":"1",
    "gn:asciiname":"Heydarlu-ye Sir",
    "gn:country_code":"IR",
    "gn:dem":1572,
    "gn:feature_class":"P",
    "gn:feature_code":"PPL",
    "gn:name":"\u1e28eydarl\u016b-ye S\u012br",
    "gn:population":0,
    "gn:timezone":"Asia/Tehran",
    "iso:country":"IR",
    "name:fas_x_preferred":[
        "\u062d\u06cc\u062f\u0631\u0644\u0648\u06cc \u0633\u06cc\u0631"
    ],
    "name:fas_x_variant":[
        "\u1e28eydarl\u016b-ye S\u012br"
    ],
    "name:und_x_variant":[
        "\u1e28eydarl\u016b"
    ],
    "wof:name":"Heydarlu-ye Sir",
    "wof:placetype":"locality"
},
  "geometry": {"coordinates":[45.0462,37.4746],"type":"Point"}
}