{
  "type": "Feature",
  "properties": {
    "gn:admin1_code":"1",
    "gn:asciiname":"Zonbalan",
    "gn:country_code":"IR",
    "gn:dem":1318,
    "gn:feature_class":"P",
    "gn:feature_code":"PPL",
    "gn:name":"Zonbal\u0101n",
    "gn:population":0,
    "gn:timezone":"Asia/Tehran",
    "iso:country":"IR",
    "name:fas_x_preferred":[
        "\u0632\u064f\u0646\u0628\u064e\u0644\u0627\u0646"
    ],
    "name:fas_x_variant":[
        "\u0632\u064f\u0645\u0628\u0650\u0644\u0627\u0646",
        "\u0632\u0645\u0628\u0644\u0627\u0646",
        "Zonbal\u0101n",
        "Zombel\u0101n"
    ],
    "name:und_x_variant":[
        "Zombel\u0101n"
    ],
    "wof:name":"Zonbalan",
    "wof:placetype":"locality"
},
  "geometry": {"coordinates":[45.0344,37.6997],"type":"Point"}
}