{
  "type": "Feature",
  "properties": {
    "gn:admin1_code":"11",
    "gn:asciiname":"Tigh Siah",
    "gn:country_code":"IR",
    "gn:dem":511,
    "gn:feature_class":"P",
    "gn:feature_code":"PPL",
    "gn:name":"T\u012bgh S\u012b\u0101h",
    "gn:population":0,
    "gn:timezone":"Asia/Tehran",
    "iso:country":"IR",
    "name:fas_x_preferred":[
        "\u062a\u06cc\u063a \u0633\u06cc\u0627\u0647"
    ],
    "name:fas_x_variant":[
        "T\u012bk S\u012b\u0101h",
        "T\u012bgh S\u012b\u0101h"
    ],
    "name:msa_x_preferred":[
        "Tigh Siah"
    ],
    "name:und_x_variant":[
        "T\u012bk Sey\u0101h",
        "T\u012bk-e S\u012b\u0101h"
    ],
    "wof:name":"Tigh Siah",
    "wof:placetype":"locality"
},
  "geometry": {"coordinates":[57.5416,27.0113],"type":"Point"}
}