{
  "type": "Feature",
  "properties": {
    "gn:admin1_code":"23.0",
    "gn:asciiname":"Cheshmeh-ye Mahmud",
    "gn:country_code":"IR",
    "gn:dem":2442,
    "gn:feature_class":"P",
    "gn:feature_code":"PPL",
    "gn:name":"Cheshmeh-ye Ma\u1e29m\u016bd",
    "gn:population":0,
    "gn:timezone":"Asia/Tehran",
    "iso:country":"IR",
    "name:fas_x_preferred":[
        "\u0686\u0650\u0634\u0645\u0650\u06c0 \u0645\u064e\u062d\u0645\u0648\u062f"
    ],
    "name:fas_x_variant":[
        "Cheshmeh-ye Ma\u1e29m\u016bd"
    ],
    "wof:name":"Cheshmeh-ye Mahmud",
    "wof:placetype":"locality"
},
  "geometry": {"coordinates":[48.38333,33.75],"type":"Point"}
}