{
  "type": "Feature",
  "properties": {
    "gn:admin1_code":"35",
    "gn:asciiname":"Kava",
    "gn:country_code":"IR",
    "gn:dem":1605,
    "gn:feature_class":"P",
    "gn:feature_code":"PPL",
    "gn:name":"Kav\u0101",
    "gn:population":0,
    "gn:timezone":"Asia/Tehran",
    "iso:country":"IR",
    "name:fas_x_preferred":[
        "\u0643\u0650\u0648\u0627"
    ],
    "name:fas_x_variant":[
        "\u0643\u064e\u0648\u064e\u0632",
        "Kav\u0101",
        "Kov\u0101",
        "\u0643\u0648\u0627"
    ],
    "name:und_x_variant":[
        "Kavaz",
        "Kev\u0101",
        "\u0643\u0648\u0627"
    ],
    "wof:name":"Kava",
    "wof:placetype":"locality"
},
  "geometry": {"coordinates":[53.87851,36.52248],"type":"Point"}
}