{
  "type": "Feature",
  "properties": {
    "gn:admin1_code":"35",
    "gn:asciiname":"Kava",
    "gn:country_code":"IR",
    "gn:dem":1605,
    "gn:feature_class":"P",
    "gn:feature_code":"PPL",
    "gn:name":"Kav\u0101",
    "gn:population":0,
    "gn:timezone":"Asia/Tehran",
    "iso:country":"IR",
    "name:ara_x_preferred":[
        "\u0643\u0627\u0641\u0627"
    ],
    "name:ast_x_preferred":[
        "Piper methysticum"
    ],
    "name:bel_x_preferred":[
        "Piper methysticum"
    ],
    "name:bis_x_preferred":[
        "Kava"
    ],
    "name:cat_x_preferred":[
        "Piper methysticum"
    ],
    "name:ces_x_preferred":[
        "Pep\u0159ovn\u00edk opojn\u00fd"
    ],
    "name:dan_x_preferred":[
        "Kava"
    ],
    "name:deu_x_preferred":[
        "Kava"
    ],
    "name:epo_x_preferred":[
        "Kavao"
    ],
    "name:fas_x_preferred":[
        "\u0643\u0650\u0648\u0627"
    ],
    "name:fas_x_variant":[
        "\u0643\u064e\u0648\u064e\u0632",
        "Kav\u0101",
        "Kov\u0101",
        "\u0643\u0648\u0627",
        "\u06a9\u0627\u0648\u0627"
    ],
    "name:fij_x_preferred":[
        "Yaqona"
    ],
    "name:fin_x_preferred":[
        "Kava"
    ],
    "name:fra_x_preferred":[
        "Kava"
    ],
    "name:glg_x_preferred":[
        "Piper methysticum"
    ],
    "name:hsb_x_preferred":[
        "Kawowy popjerjowc"
    ],
    "name:hun_x_preferred":[
        "Kava"
    ],
    "name:ita_x_preferred":[
        "Piper methysticum"
    ],
    "name:jpn_x_preferred":[
        "\u30ab\u30f4\u30a1"
    ],
    "name:lat_x_preferred":[
        "Piper methysticum"
    ],
    "name:lav_x_preferred":[
        "Kava"
    ],
    "name:lit_x_preferred":[
        "Svaigusis pipiras"
    ],
    "name:mal_x_preferred":[
        "\u0d15\u0d3e\u0d35"
    ],
    "name:mkd_x_preferred":[
        "\u041a\u0430\u0432\u0430"
    ],
    "name:nld_x_preferred":[
        "Kava"
    ],
    "name:nor_x_preferred":[
        "Kava"
    ],
    "name:pol_x_preferred":[
        "Pieprz metystynowy"
    ],
    "name:por_x_preferred":[
        "Piper methysticum"
    ],
    "name:rus_x_preferred":[
        "\u041f\u0435\u0440\u0435\u0446 \u043e\u043f\u044c\u044f\u043d\u044f\u044e\u0449\u0438\u0439"
    ],
    "name:slv_x_preferred":[
        "Kava kava"
    ],
    "name:spa_x_preferred":[
        "Piper methysticum"
    ],
    "name:srp_x_preferred":[
        "Piper methysticum"
    ],
    "name:swe_x_preferred":[
        "Kava"
    ],
    "name:szl_x_preferred":[
        "Kava kava"
    ],
    "name:tah_x_preferred":[
        "Kava"
    ],
    "name:tam_x_preferred":[
        "\u0b95\u0bb5\u0bbe"
    ],
    "name:tha_x_preferred":[
        "\u0e04\u0e32\u0e27\u0e32"
    ],
    "name:ton_x_preferred":[
        "Kava"
    ],
    "name:ukr_x_preferred":[
        "\u041f\u0435\u0440\u0435\u0446\u044c \u043f'\u044f\u043d\u043a\u0438\u0439"
    ],
    "name:und_x_variant":[
        "Kavaz",
        "Kev\u0101",
        "\u0643\u0648\u0627"
    ],
    "name:zho_x_preferred":[
        "\u5361\u74e6\u9189\u6912"
    ],
    "wof:name":"Kava",
    "wof:placetype":"locality"
},
  "geometry": {"coordinates":[53.87851,36.52248],"type":"Point"}
}