{
  "type": "Feature",
  "properties": {
    "gn:admin1_code":"29",
    "gn:asciiname":"Kush Tarki",
    "gn:country_code":"IR",
    "gn:dem":2449,
    "gn:feature_class":"P",
    "gn:feature_code":"PPL",
    "gn:name":"K\u016bsh Tark\u012b",
    "gn:population":0,
    "gn:timezone":"Asia/Tehran",
    "iso:country":"IR",
    "name:fas_x_preferred":[
        "\u06a9\u0648\u0634 \u062a\u0631\u06a9\u06cc"
    ],
    "name:fas_x_variant":[
        "K\u016bsh Tark\u012b"
    ],
    "wof:name":"Kush Tarki",
    "wof:placetype":"locality"
},
  "geometry": {"coordinates":[56.0112,29.8139],"type":"Point"}
}