{
  "type": "Feature",
  "properties": {
    "gn:admin1_code":"26.0",
    "gn:asciiname":"`Abdollahabad-e Reza'iyeh",
    "gn:country_code":"IR",
    "gn:dem":977,
    "gn:feature_class":"P",
    "gn:feature_code":"PPL",
    "gn:name":"\u2018Abdoll\u0101h\u0101b\u0101d-e Re\u1e95\u0101\u2019\u012byeh",
    "gn:population":0,
    "gn:timezone":"Asia/Tehran",
    "iso:country":"IR",
    "name:fas_x_preferred":[
        "\u2018Abdoll\u0101h\u0101b\u0101d-e Re\u1e95\u0101\u2019\u012byeh"
    ],
    "name:fas_x_variant":[
        "\u0639\u0628\u062f\u0627\u0644\u0644\u0651\u0647 \u0622\u0628\u0627\u062f \u0631\u0650\u0636\u0627\u0626\u064a\u0647",
        "\u0639\u0628\u062f\u0627\u0644\u0644\u0651\u0647 \u0622\u0628\u0627\u062f \u0627\u062c\u0627\u0642",
        "\u0639\u0628\u062f\u0627\u0644\u0644\u0647\u200c\u0622\u0628\u0627\u062f \u0627\u062c\u0627\u0642"
    ],
    "name:und_x_variant":[
        "\u2018Abdoll\u0101h\u0101b\u0101d-e Oj\u0101q"
    ],
    "wof:name":"`Abdollahabad-e Reza'iyeh",
    "wof:placetype":"locality"
},
  "geometry": {"coordinates":[51.3821,35.4731],"type":"Point"}
}