{
  "type": "Feature",
  "properties": {
    "gn:admin1_code":"29.0",
    "gn:asciiname":"Tang Darreh",
    "gn:country_code":"IR",
    "gn:dem":1878,
    "gn:feature_class":"P",
    "gn:feature_code":"PPL",
    "gn:name":"Tang Darreh",
    "gn:population":0,
    "gn:timezone":"Asia/Tehran",
    "iso:country":"IR",
    "name:fas_x_preferred":[
        "\u062a\u0646\u06af \u062f\u0631\u0651\u0647"
    ],
    "name:und_x_variant":[
        "Tan Darreh",
        "Tang-e Darreh",
        "Tang Darreh"
    ],
    "wof:name":"Tang Darreh",
    "wof:placetype":"locality"
},
  "geometry": {"coordinates":[57.8731,28.9314],"type":"Point"}
}