{
  "type": "Feature",
  "properties": {
    "gn:admin1_code":"13.0",
    "gn:asciiname":"Cheshmeh Gineh",
    "gn:country_code":"IR",
    "gn:dem":1322,
    "gn:feature_class":"P",
    "gn:feature_code":"PPL",
    "gn:name":"Cheshmeh G\u012bneh",
    "gn:population":0,
    "gn:timezone":"Asia/Tehran",
    "iso:country":"IR",
    "name:ara_x_preferred":[
        "\u062a\u0634\u0634\u0645\u0647\u063a\u0644\u064a\u0646\u0647"
    ],
    "name:fas_x_preferred":[
        "\u0686\u0634\u0645\u0647 \u06af\u06cc\u0646\u0647"
    ],
    "name:fas_x_variant":[
        "Cheshmeh Gel\u012bneh",
        "Cheshmeh G\u012bneh",
        "\u0686\u0634\u0645\u0647\u200c\u06af\u0644\u06cc\u0646\u0647"
    ],
    "wof:name":"Cheshmeh Gineh",
    "wof:placetype":"locality"
},
  "geometry": {"coordinates":[46.2503,33.9736],"type":"Point"}
}