{
  "type": "Feature",
  "properties": {
    "gn:admin1_code":"8",
    "gn:asciiname":"Shirkuh",
    "gn:country_code":"IR",
    "gn:dem":6,
    "gn:feature_class":"P",
    "gn:feature_code":"PPL",
    "gn:name":"Sh\u012brk\u016bh",
    "gn:population":0,
    "gn:timezone":"Asia/Tehran",
    "iso:country":"IR",
    "name:fas_x_preferred":[
        "Sh\u012brk\u016bh"
    ],
    "name:fas_x_variant":[
        "\u0634\u06cc\u0631\u06a9\u0648\u0647",
        "Sh\u012br K\u016bh",
        "\u0634\u06cc\u0631\u06a9\u0648\u0647 \u0686\u0647\u0627\u0631 \u062f\u0647"
    ],
    "name:und_x_variant":[
        "ShirKooh",
        "Shirkukh",
        "Sh\u012brk\u016bh Chah\u0101r Deh"
    ],
    "wof:name":"Shirkuh",
    "wof:placetype":"locality"
},
  "geometry": {"coordinates":[49.81791,37.23126],"type":"Point"}
}