{
  "type": "Feature",
  "properties": {
    "gn:admin1_code":"8",
    "gn:asciiname":"Shirkuh",
    "gn:country_code":"IR",
    "gn:dem":6,
    "gn:feature_class":"P",
    "gn:feature_code":"PPL",
    "gn:name":"Sh\u012brk\u016bh",
    "gn:population":0,
    "gn:timezone":"Asia/Tehran",
    "iso:country":"IR",
    "name:ben_x_preferred":[
        "\u09b6\u09bf\u09b0\u0995\u09c1\u09b9"
    ],
    "name:cat_x_preferred":[
        "Xirkuh"
    ],
    "name:ces_x_preferred":[
        "\u0160\u00edrk\u00fah"
    ],
    "name:ckb_x_preferred":[
        "\u0626\u06d5\u0633\u06d5\u062f\u06d5\u062f\u062f\u06cc\u0646 \u0634\u06ce\u0631\u06a9\u06c6"
    ],
    "name:deu_x_preferred":[
        "Schirkuh"
    ],
    "name:fas_x_preferred":[
        "Sh\u012brk\u016bh"
    ],
    "name:fas_x_variant":[
        "\u0634\u06cc\u0631\u06a9\u0648\u0647",
        "Sh\u012br K\u016bh",
        "\u0634\u06cc\u0631\u06a9\u0648\u0647 \u0686\u0647\u0627\u0631 \u062f\u0647",
        "\u0627\u0633\u062f\u0627\u0644\u062f\u06cc\u0646 \u0634\u06cc\u0631\u06a9\u0648\u0647"
    ],
    "name:fin_x_preferred":[
        "Shirkuh"
    ],
    "name:fra_x_preferred":[
        "Shirkuh"
    ],
    "name:heb_x_preferred":[
        "\u05e9\u05d9\u05e8\u05db\u05d5\u05d4"
    ],
    "name:ita_x_preferred":[
        "Shirkuh"
    ],
    "name:jpn_x_preferred":[
        "\u30b7\u30fc\u30eb\u30fb\u30af\u30fc\u30d5"
    ],
    "name:kor_x_preferred":[
        "\uc2dc\ub974\ucfe0"
    ],
    "name:kur_x_preferred":[
        "\u015e\u00earko"
    ],
    "name:pnb_x_preferred":[
        "\u0634\u06cc\u0631 \u06a9\u0648\u06c1"
    ],
    "name:spa_x_preferred":[
        "Shirku"
    ],
    "name:srp_x_preferred":[
        "\u0428\u0438\u0440\u043a\u0443"
    ],
    "name:und_x_variant":[
        "ShirKooh",
        "Shirkukh",
        "Sh\u012brk\u016bh Chah\u0101r Deh"
    ],
    "name:urd_x_preferred":[
        "\u0634\u06cc\u0631 \u06a9\u0648\u06c1"
    ],
    "name:zho_x_preferred":[
        "\u8c22\u5c14\u5e93\u8d6b"
    ],
    "wof:name":"Shirkuh",
    "wof:placetype":"locality"
},
  "geometry": {"coordinates":[49.81791,37.23126],"type":"Point"}
}