{
  "type": "Feature",
  "properties": {
    "gn:admin1_code":"11",
    "gn:asciiname":"Behel",
    "gn:country_code":"IR",
    "gn:dem":4,
    "gn:feature_class":"P",
    "gn:feature_code":"PPL",
    "gn:name":"Be\u1e29el",
    "gn:population":0,
    "gn:timezone":"Asia/Tehran",
    "iso:country":"IR",
    "name:fas_x_preferred":[
        "\u0628\u062d\u0644"
    ],
    "name:und_x_variant":[
        "Be\u1e29al",
        "\u0628\u062d\u0644",
        "Be\u1e29el"
    ],
    "wof:name":"Behel",
    "wof:placetype":"locality"
},
  "geometry": {"coordinates":[57.85751,25.69068],"type":"Point"}
}