{
  "type": "Feature",
  "properties": {
    "gn:admin1_code":"8",
    "gn:asciiname":"Hafteh Khuni",
    "gn:country_code":"IR",
    "gn:dem":1550,
    "gn:feature_class":"P",
    "gn:feature_code":"PPL",
    "gn:name":"Hafteh Kh\u016bn\u012b",
    "gn:population":0,
    "gn:timezone":"Asia/Tehran",
    "iso:country":"IR",
    "name:fas_x_preferred":[
        "\u0647\u0641\u062a\u0647 \u062e\u0648\u0646\u06cc"
    ],
    "name:fas_x_variant":[
        "Hafteh Kh\u016bn\u012b"
    ],
    "wof:name":"Hafteh Khuni",
    "wof:placetype":"locality"
},
  "geometry": {"coordinates":[48.80996,37.45728],"type":"Point"}
}