{
  "type": "Feature",
  "properties": {
    "gn:admin1_code":"28.0",
    "gn:asciiname":"Anushirvan",
    "gn:cc2":"IR",
    "gn:country_code":"IR",
    "gn:dem":1595,
    "gn:feature_class":"P",
    "gn:feature_code":"PPL",
    "gn:name":"An\u016bsh\u012brv\u0101n",
    "gn:population":0,
    "gn:timezone":"Asia/Tehran",
    "iso:country":"IR",
    "name:fas_x_preferred":[
        "An\u016bsh\u012brv\u0101n"
    ],
    "name:fas_x_variant":[
        "\u0627\u0646\u0648\u0634\u06cc\u0631\u0648\u0627\u0646"
    ],
    "name:und_x_variant":[
        "K\u0101feh-ye Nowsh\u012brv\u0101n"
    ],
    "wof:name":"Anushirvan",
    "wof:placetype":"locality"
},
  "geometry": {"coordinates":[51.56,32.74528],"type":"Point"}
}