{
  "type": "Feature",
  "properties": {
    "gn:admin1_code":"39",
    "gn:asciiname":"Mohammad Beyk",
    "gn:country_code":"IR",
    "gn:dem":1350,
    "gn:feature_class":"P",
    "gn:feature_code":"PPL",
    "gn:name":"Mo\u1e29ammad Beyk",
    "gn:population":0,
    "gn:timezone":"Asia/Tehran",
    "iso:country":"IR",
    "name:fas_x_preferred":[
        "\u0645\u062d\u0645\u0651\u062f \u0628\u064a\u06af"
    ],
    "name:fas_x_variant":[
        "Mo\u1e29ammad Beyg",
        "\u0645\u062d\u0645\u062f \u0628\u06cc\u06a9",
        "\u0645\u062d\u0645\u062f\u0628\u06cc\u06a9"
    ],
    "name:und_x_variant":[
        "Mo\u1e29ammad Beyk"
    ],
    "wof:name":"Mohammad Beyk",
    "wof:placetype":"locality"
},
  "geometry": {"coordinates":[50.48365,34.54825],"type":"Point"}
}