{
  "type": "Feature",
  "properties": {
    "gn:admin1_code":"4.0",
    "gn:asciiname":"Yadegar",
    "gn:country_code":"IR",
    "gn:dem":491,
    "gn:feature_class":"P",
    "gn:feature_code":"PPL",
    "gn:name":"Y\u0101deg\u0101r",
    "gn:population":0,
    "gn:timezone":"Asia/Tehran",
    "iso:country":"IR",
    "name:fas_x_preferred":[
        "\u06cc\u0627\u062f\u06af\u0627\u0631"
    ],
    "name:fas_x_variant":[
        "Y\u0101deg\u0101r",
        "\u062f\u0647 \u06cc\u0627\u062f\u06af\u0627\u0631"
    ],
    "name:und_x_variant":[
        "\u2018Al\u012bj\u0101n",
        "Deh-e Y\u0101degar"
    ],
    "wof:name":"Yadegar",
    "wof:placetype":"locality"
},
  "geometry": {"coordinates":[61.723,30.8976],"type":"Point"}
}