{
  "type": "Feature",
  "properties": {
    "gn:admin1_code":"42",
    "gn:asciiname":"Poshteh Siah",
    "gn:country_code":"IR",
    "gn:dem":902,
    "gn:feature_class":"P",
    "gn:feature_code":"PPL",
    "gn:name":"Poshteh S\u012b\u0101h",
    "gn:population":0,
    "gn:timezone":"Asia/Tehran",
    "iso:country":"IR",
    "name:fas_x_preferred":[
        "Poshteh S\u012b\u0101h"
    ],
    "wof:name":"Poshteh Siah",
    "wof:placetype":"locality"
},
  "geometry": {"coordinates":[57.32167,34.35417],"type":"Point"}
}