{
  "type": "Feature",
  "properties": {
    "gn:admin1_code":"8.0",
    "gn:asciiname":"Mehdi Mahalleh",
    "gn:country_code":"IR",
    "gn:dem":80,
    "gn:feature_class":"P",
    "gn:feature_code":"PPL",
    "gn:name":"Mehd\u012b Ma\u1e29alleh",
    "gn:population":0,
    "gn:timezone":"Asia/Tehran",
    "iso:country":"IR",
    "name:fas_x_preferred":[
        "\u0645\u0647\u062f\u06cc \u0645\u062d\u0644\u0647"
    ],
    "name:und_x_variant":[
        "Mehd\u012b Ma\u1e29alleh"
    ],
    "wof:name":"Mehdi Mahalleh",
    "wof:placetype":"locality"
},
  "geometry": {"coordinates":[49.28386,37.17357],"type":"Point"}
}