{
  "type": "Feature",
  "properties": {
    "gn:admin1_code":"28.0",
    "gn:asciiname":"Golestaneh",
    "gn:country_code":"IR",
    "gn:dem":1541,
    "gn:feature_class":"P",
    "gn:feature_code":"PPL",
    "gn:name":"Golest\u0101neh",
    "gn:population":0,
    "gn:timezone":"Asia/Tehran",
    "iso:country":"IR",
    "name:fas_x_preferred":[
        "Golest\u0101neh"
    ],
    "name:fas_x_variant":[
        "\u06af\u0644\u0633\u062a\u0627\u0646\u0647"
    ],
    "name:und_x_variant":[
        "Golast\u0101n",
        "\u06af\u0644\u0633\u062a\u0627\u0646\u0647"
    ],
    "wof:name":"Golestaneh",
    "wof:placetype":"locality"
},
  "geometry": {"coordinates":[51.82548,32.52391],"type":"Point"}
}