{
  "type": "Feature",
  "properties": {
    "gn:admin1_code":"5.0",
    "gn:asciiname":"Kalvar",
    "gn:country_code":"IR",
    "gn:dem":1127,
    "gn:feature_class":"P",
    "gn:feature_code":"PPL",
    "gn:name":"Kalv\u0101r",
    "gn:population":0,
    "gn:timezone":"Asia/Tehran",
    "iso:country":"IR",
    "name:fas_x_preferred":[
        "Kal\u016bv\u0101r"
    ],
    "name:fas_x_variant":[
        "\u06a9\u0644\u0648\u0648\u0627\u0631",
        "\u06a9\u0644\u0648\u0627\u0631"
    ],
    "name:und_x_variant":[
        "Kalv\u0101r"
    ],
    "wof:name":"Kalvar",
    "wof:placetype":"locality"
},
  "geometry": {"coordinates":[50.53502,31.41413],"type":"Point"}
}