{
  "type": "Feature",
  "properties": {
    "gn:admin1_code":"15",
    "gn:asciiname":"Marzeh",
    "gn:country_code":"IR",
    "gn:dem":22,
    "gn:feature_class":"P",
    "gn:feature_code":"PPL",
    "gn:name":"Marzeh",
    "gn:population":0,
    "gn:timezone":"Asia/Tehran",
    "iso:country":"IR",
    "name:ceb_x_preferred":[
        "Marzeh"
    ],
    "name:fas_x_preferred":[
        "\u0645\u0631\u0632\u0647"
    ],
    "name:swe_x_preferred":[
        "Marzeh"
    ],
    "wof:name":"Marzeh",
    "wof:placetype":"locality"
},
  "geometry": {"coordinates":[49.39938,30.78694],"type":"Point"}
}