{
  "type": "Feature",
  "properties": {
    "gn:admin1_code":"1",
    "gn:asciiname":"Silvana",
    "gn:country_code":"IR",
    "gn:dem":1606,
    "gn:feature_class":"P",
    "gn:feature_code":"PPL",
    "gn:name":"Silvana",
    "gn:population":0,
    "gn:timezone":"Asia/Tehran",
    "iso:country":"IR",
    "name:ara_x_preferred":[
        "\u0633\u064a\u0644\u0648\u0627\u0646\u0647"
    ],
    "name:azb_x_preferred":[
        "\u0633\u06cc\u0644\u0648\u0627\u0646\u0627"
    ],
    "name:aze_x_preferred":[
        "Silvan\u0259"
    ],
    "name:ceb_x_preferred":[
        "Silvana"
    ],
    "name:ckb_x_preferred":[
        "\u0633\u0644\u06cc\u06a4\u0627\u0646\u0627"
    ],
    "name:fas_x_preferred":[
        "\u0633\u064a\u0644\u0648\u0627\u0646\u0650\u0647"
    ],
    "name:fas_x_variant":[
        "\u0633\u06cc\u0644\u0648\u0627\u0646\u0627",
        "S\u012blv\u0101neh",
        "\u0633\u0650\u0644\u0648\u0627\u0646\u064e\u0642",
        "\u0633\u0650\u0644\u0648\u0627\u0646\u0627",
        "S\u012blv\u0101n\u0101",
        "\u0633\u064e\u0644\u0648\u064e\u0646\u064e\u063a",
        "\u0633\u06cc\u0644\u0648\u0627\u0646\u0647"
    ],
    "name:kur_x_preferred":[
        "Sil\u00eevana"
    ],
    "name:mlg_x_preferred":[
        "Silvaneh"
    ],
    "name:msa_x_preferred":[
        "Silvaneh"
    ],
    "name:nld_x_preferred":[
        "Silvaneh"
    ],
    "name:swe_x_preferred":[
        "Silvana"
    ],
    "name:tur_x_preferred":[
        "Silvana"
    ],
    "name:und_x_variant":[
        "Selv\u0101n\u0101",
        "Selv\u0101naq",
        "Salvanagh"
    ],
    "name:urd_x_preferred":[
        "\u0633\u06cc\u0644\u0648\u0627\u0646\u06c1"
    ],
    "wof:name":"Silvana",
    "wof:placetype":"locality"
},
  "geometry": {"coordinates":[44.8532,37.4222],"type":"Point"}
}