{
  "type": "Feature",
  "properties": {
    "gn:admin1_code":"1",
    "gn:asciiname":"Silvana",
    "gn:country_code":"IR",
    "gn:dem":1606,
    "gn:feature_class":"P",
    "gn:feature_code":"PPL",
    "gn:name":"Silvana",
    "gn:population":0,
    "gn:timezone":"Asia/Tehran",
    "iso:country":"IR",
    "name:fas_x_preferred":[
        "\u0633\u064a\u0644\u0648\u0627\u0646\u0650\u0647"
    ],
    "name:fas_x_variant":[
        "\u0633\u06cc\u0644\u0648\u0627\u0646\u0627",
        "S\u012blv\u0101neh",
        "\u0633\u0650\u0644\u0648\u0627\u0646\u064e\u0642",
        "\u0633\u0650\u0644\u0648\u0627\u0646\u0627",
        "S\u012blv\u0101n\u0101",
        "\u0633\u064e\u0644\u0648\u064e\u0646\u064e\u063a"
    ],
    "name:und_x_variant":[
        "Selv\u0101n\u0101",
        "Silvana",
        "Selv\u0101naq",
        "Salvanagh"
    ],
    "wof:name":"Silvana",
    "wof:placetype":"locality"
},
  "geometry": {"coordinates":[44.8532,37.4222],"type":"Point"}
}