{
  "type": "Feature",
  "properties": {
    "gn:admin1_code":"0",
    "gn:asciiname":"Sasani",
    "gn:country_code":"IR",
    "gn:dem":1619,
    "gn:feature_class":"P",
    "gn:feature_code":"PPL",
    "gn:name":"S\u0101s\u0101n\u012b",
    "gn:population":0,
    "gn:timezone":"Asia/Tehran",
    "iso:country":"IR",
    "name:fas_x_preferred":[
        "\u0633\u0627\u0633\u0627\u0646\u06cc"
    ],
    "name:fas_x_variant":[
        "S\u0101s\u0101n\u012b"
    ],
    "wof:name":"Sasani",
    "wof:placetype":"locality"
},
  "geometry": {"coordinates":[57.7421,27.011],"type":"Point"}
}