{
  "type": "Feature",
  "properties": {
    "gn:admin1_code":"32",
    "gn:asciiname":"Beg Bagh",
    "gn:country_code":"IR",
    "gn:dem":676,
    "gn:feature_class":"P",
    "gn:feature_code":"PPL",
    "gn:name":"Beg B\u0101gh",
    "gn:population":0,
    "gn:timezone":"Asia/Tehran",
    "iso:country":"IR",
    "name:fas_x_preferred":[
        "\u0628\u06af \u0628\u0627\u063a"
    ],
    "name:fas_x_variant":[
        "Beyg B\u0101gh\u012b",
        "Beg B\u0101gh"
    ],
    "name:und_x_variant":[
        "B\u0101i Bagh",
        "B\u0101y B\u0101gh",
        "Beik Baghi"
    ],
    "wof:name":"Beg Bagh",
    "wof:placetype":"locality"
},
  "geometry": {"coordinates":[48.1088,39.0701],"type":"Point"}
}