{
  "type": "Feature",
  "properties": {
    "gn:admin1_code":"36.0",
    "gn:asciiname":"Bagh",
    "gn:country_code":"IR",
    "gn:dem":1819,
    "gn:feature_class":"P",
    "gn:feature_code":"PPL",
    "gn:name":"B\u0101gh",
    "gn:population":0,
    "gn:timezone":"Asia/Tehran",
    "iso:country":"IR",
    "name:fas_x_preferred":[
        "\u0628\u0627\u063a"
    ],
    "name:fas_x_variant":[
        "\u0628\u064e\u06af",
        "B\u0101gh"
    ],
    "name:und_x_variant":[
        "Bag"
    ],
    "wof:name":"Bagh",
    "wof:placetype":"locality"
},
  "geometry": {"coordinates":[48.31218,36.9779],"type":"Point"}
}