{
  "type": "Feature",
  "properties": {
    "gn:admin1_code":"42",
    "gn:asciiname":"Ferizi",
    "gn:country_code":"IR",
    "gn:dem":1639,
    "gn:feature_class":"P",
    "gn:feature_code":"PPL",
    "gn:name":"Fer\u012bz\u012b",
    "gn:population":0,
    "gn:timezone":"Asia/Tehran",
    "iso:country":"IR",
    "name:fas_x_preferred":[
        "\u0641\u0631\u06cc\u0632\u06cc"
    ],
    "name:fas_x_variant":[
        "Fer\u012bz\u012b"
    ],
    "name:und_x_variant":[
        "Farezi",
        "Far\u012bz\u012b",
        "Ferez\u012b"
    ],
    "wof:name":"Ferizi",
    "wof:placetype":"locality"
},
  "geometry": {"coordinates":[58.97597,36.48798],"type":"Point"}
}