{
  "type": "Feature",
  "properties": {
    "gn:admin1_code":"43",
    "gn:asciiname":"Kaltamanlu",
    "gn:country_code":"IR",
    "gn:dem":1643,
    "gn:feature_class":"P",
    "gn:feature_code":"PPL",
    "gn:name":"K\u0101lt\u0101m\u0101nl\u016b",
    "gn:population":0,
    "gn:timezone":"Asia/Tehran",
    "iso:country":"IR",
    "name:ceb_x_preferred":[
        "K\u0101lt\u0101m\u0101nl\u016b"
    ],
    "name:fas_x_preferred":[
        "Q\u0101ltam\u0101nl\u016b"
    ],
    "name:fas_x_variant":[
        "K\u0101lt\u0101m\u0101nl\u016b",
        "\u06a9\u0627\u0644\u062a\u0627\u0645\u0627\u0646\u0644\u0648",
        "\u06a9\u0627\u0644\u062a\u0645\u0627\u0646\u0644\u0648"
    ],
    "name:swe_x_preferred":[
        "K\u0101lt\u0101m\u0101nl\u016b"
    ],
    "name:und_x_variant":[
        "Kalt\u0101manl\u016b"
    ],
    "wof:name":"Kaltamanlu",
    "wof:placetype":"locality"
},
  "geometry": {"coordinates":[58.04161,37.68612],"type":"Point"}
}