{
  "type": "Feature",
  "properties": {
    "gn:admin1_code":"8.0",
    "gn:asciiname":"Now Deh-e Bala",
    "gn:country_code":"IR",
    "gn:dem":1362,
    "gn:feature_class":"P",
    "gn:feature_code":"PPL",
    "gn:name":"Now Deh-e B\u0101l\u0101",
    "gn:population":0,
    "gn:timezone":"Asia/Tehran",
    "iso:country":"IR",
    "name:fas_x_preferred":[
        "Now Deh-e B\u0101l\u0101"
    ],
    "name:fas_x_variant":[
        "\u0646\u0648 \u062f\u0647 \u0628\u0627\u0644\u0627",
        "\u0628\u0627\u0644\u0627\u0646\u0648\u062f\u0647"
    ],
    "name:msa_x_preferred":[
        "Bala Now Deh"
    ],
    "name:ukr_x_preferred":[
        "\u0411\u0430\u043b\u0430-\u041d\u043e\u0432\u0434\u0435\u0433"
    ],
    "name:und_x_variant":[
        "\u0646\u0648 \u062f\u0647 \u0628\u0627\u0644\u0627"
    ],
    "wof:name":"Now Deh-e Bala",
    "wof:placetype":"locality"
},
  "geometry": {"coordinates":[49.7285,36.67669],"type":"Point"}
}