{
  "type": "Feature",
  "properties": {
    "gn:admin1_code":"11.0",
    "gn:asciiname":"Mahalleh-ye Sa`adatabad",
    "gn:country_code":"IR",
    "gn:dem":63,
    "gn:feature_class":"P",
    "gn:feature_code":"PPL",
    "gn:name":"Ma\u1e29alleh-ye Sa\u2018\u0101dat\u0101b\u0101d",
    "gn:population":0,
    "gn:timezone":"Asia/Tehran",
    "iso:country":"IR",
    "name:fas_x_preferred":[
        "\u0645\u062d\u0644\u0647 \u0633\u0639\u0627\u062f\u062a \u0622\u0628\u0627\u062f"
    ],
    "name:und_x_variant":[
        "Ma\u1e29alleh-ye Sa\u2018\u0101dat\u0101b\u0101d"
    ],
    "wof:name":"Mahalleh-ye Sa`adatabad",
    "wof:placetype":"locality"
},
  "geometry": {"coordinates":[56.5503,27.4558],"type":"Point"}
}