{
  "type": "Feature",
  "properties": {
    "gn:admin1_code":"34",
    "gn:asciiname":"Khoshdun",
    "gn:country_code":"IR",
    "gn:dem":1696,
    "gn:feature_class":"P",
    "gn:feature_code":"PPL",
    "gn:name":"Khoshd\u016bn",
    "gn:population":0,
    "gn:timezone":"Asia/Tehran",
    "iso:country":"IR",
    "name:fas_x_preferred":[
        "\u062e\u0648\u0634\u062a\u0648\u0646"
    ],
    "name:fas_x_variant":[
        "\u062e\u064f\u0634\u062f\u0648\u062f",
        "Khvoshd\u016bn",
        "\u062e\u0648\u0634\u062f\u0648\u0646",
        "\u062e\u0634\u062f\u0648\u0646"
    ],
    "name:und_x_variant":[
        "Khoshd\u016bd",
        "Kh\u016bsht\u016bn",
        "Khoshd\u016bn",
        "\u062e\u0648\u0634\u062f\u0648\u0646",
        "Khowshd\u016bn"
    ],
    "wof:name":"Khoshdun",
    "wof:placetype":"locality"
},
  "geometry": {"coordinates":[49.75715,34.35294],"type":"Point"}
}