{
  "type": "Feature",
  "properties": {
    "gn:admin1_code":"28.0",
    "gn:asciiname":"Aminabad",
    "gn:country_code":"IR",
    "gn:dem":2077,
    "gn:feature_class":"P",
    "gn:feature_code":"PPL",
    "gn:name":"Am\u012bn\u0101b\u0101d",
    "gn:population":0,
    "gn:timezone":"Asia/Tehran",
    "iso:country":"IR",
    "name:fas_x_preferred":[
        "\u0627\u0645\u06cc\u0646 \u0622\u0628\u0627\u062f"
    ],
    "name:fas_x_variant":[
        "Am\u012bn\u0101b\u0101d",
        "\u0627\u0645\u06cc\u0646\u200c\u0622\u0628\u0627\u062f"
    ],
    "wof:name":"Aminabad",
    "wof:placetype":"locality"
},
  "geometry": {"coordinates":[52.0653,31.6736],"type":"Point"}
}