{
  "type": "Feature",
  "properties": {
    "gn:admin1_code":"29",
    "gn:asciiname":"Musa Hinu",
    "gn:country_code":"IR",
    "gn:dem":693,
    "gn:feature_class":"P",
    "gn:feature_code":"PPL",
    "gn:name":"M\u016bs\u00e1 H\u012bn\u016b",
    "gn:population":0,
    "gn:timezone":"Asia/Tehran",
    "iso:country":"IR",
    "name:fas_x_preferred":[
        "\u0645\u0648\u0633\u06cc \u0647\u06cc\u0646\u0648"
    ],
    "name:fas_x_variant":[
        "M\u016bs\u012bh\u012bn\u016b",
        "M\u016bs\u00e1 H\u012bn\u016b"
    ],
    "wof:name":"Musa Hinu",
    "wof:placetype":"locality"
},
  "geometry": {"coordinates":[57.5244,27.7317],"type":"Point"}
}