{
  "type": "Feature",
  "properties": {
    "gn:admin1_code":"23.0",
    "gn:asciiname":"Farrokhabad-e Sofla",
    "gn:country_code":"IR",
    "gn:dem":1298,
    "gn:feature_class":"P",
    "gn:feature_code":"PPL",
    "gn:name":"Farrokh\u0101b\u0101d-e Sofl\u00e1",
    "gn:population":0,
    "gn:timezone":"Asia/Tehran",
    "iso:country":"IR",
    "name:fas_x_preferred":[
        "\u0641\u0631\u062e \u0622\u0628\u0627\u062f \u0633\u0642\u0644\u06cc"
    ],
    "name:und_x_variant":[
        "Farrokh\u0101b\u0101d-e Sofl\u00e1"
    ],
    "wof:name":"Farrokhabad-e Sofla",
    "wof:placetype":"locality"
},
  "geometry": {"coordinates":[47.52891,33.41309],"type":"Point"}
}