{
  "type": "Feature",
  "properties": {
    "gn:admin1_code":"7",
    "gn:asciiname":"Mowzar",
    "gn:country_code":"IR",
    "gn:dem":1012,
    "gn:feature_class":"P",
    "gn:feature_code":"PPL",
    "gn:name":"Mowzar",
    "gn:population":0,
    "gn:timezone":"Asia/Tehran",
    "iso:country":"IR",
    "name:ara_x_preferred":[
        "\u0645\u0648\u0632\u0627\u0631\u0627\u062a"
    ],
    "name:fas_x_preferred":[
        "\u0645\u0648\u0632\u0631"
    ],
    "name:fas_x_variant":[
        "Mowz\u0101r",
        "\u0645\u0648\u0632\u0627\u0631"
    ],
    "name:msa_x_preferred":[
        "Mowzar"
    ],
    "wof:name":"Mowzar",
    "wof:placetype":"locality"
},
  "geometry": {"coordinates":[53.82339,28.25932],"type":"Point"}
}