{
  "type": "Feature",
  "properties": {
    "gn:admin1_code":"23",
    "gn:asciiname":"Horrabad-e Pa'in",
    "gn:country_code":"IR",
    "gn:dem":1863,
    "gn:feature_class":"P",
    "gn:feature_code":"PPL",
    "gn:name":"\u1e28orr\u0101b\u0101d-e P\u0101\u2019\u012bn",
    "gn:population":0,
    "gn:timezone":"Asia/Tehran",
    "iso:country":"IR",
    "name:ara_x_preferred":[
        "\u0647\u0648\u0631 \u0623\u0628\u0627\u062f \u0627\u0644\u0633\u0641\u0644\u064a"
    ],
    "name:ceb_x_preferred":[
        "\u1e28orr\u0101b\u0101d-e Sofl\u00e1"
    ],
    "name:fas_x_preferred":[
        "\u1e28orr\u0101b\u0101d-e Sofl\u00e1"
    ],
    "name:fas_x_variant":[
        "\u062d\u0631 \u0622\u0628\u0627\u062f \u0633\u0641\u0644\u0649",
        "\u062d\u0631 \u0622\u0628\u0627\u062f \u067e\u0627\u06cc\u06cc\u0646",
        "\u062d\u0631\u0622\u0628\u0627\u062f \u0633\u0641\u0644\u06cc"
    ],
    "name:swe_x_preferred":[
        "\u1e28orr\u0101b\u0101d-e Sofl\u00e1"
    ],
    "name:und_x_variant":[
        "\u1e28orr\u0101b\u0101d-e P\u0101\u2019\u012bn"
    ],
    "wof:name":"Horrabad-e Pa'in",
    "wof:placetype":"locality"
},
  "geometry": {"coordinates":[49.62947,33.03536],"type":"Point"}
}