{
  "type": "Feature",
  "properties": {
    "gn:admin1_code":"41",
    "gn:asciiname":"Ziarat",
    "gn:country_code":"IR",
    "gn:dem":2513,
    "gn:feature_class":"P",
    "gn:feature_code":"PPL",
    "gn:name":"Z\u012b\u0101rat",
    "gn:population":0,
    "gn:timezone":"Asia/Tehran",
    "iso:country":"IR",
    "name:fas_x_preferred":[
        "\u0632\u064a\u0627\u0631\u064e\u062a"
    ],
    "name:fas_x_variant":[
        "Z\u012b\u0101rat"
    ],
    "name:und_x_variant":[
        "Ziy\u0101rat"
    ],
    "wof:name":"Ziarat",
    "wof:placetype":"locality"
},
  "geometry": {"coordinates":[59.85,33.75],"type":"Point"}
}