{
  "type": "Feature",
  "properties": {
    "gn:admin1_code":"1",
    "gn:asciiname":"Tavreh",
    "gn:country_code":"IR",
    "gn:dem":1066,
    "gn:feature_class":"P",
    "gn:feature_code":"PPL",
    "gn:name":"\u0162avreh",
    "gn:population":0,
    "gn:timezone":"Asia/Tehran",
    "iso:country":"IR",
    "name:fas_x_preferred":[
        "\u0637\u064e\u0631\u0648\u0650\u0647"
    ],
    "name:fas_x_variant":[
        "\u0637\u0648\u0631\u0647",
        "\u0162arveh",
        "\u0162avreh"
    ],
    "wof:name":"Tavreh",
    "wof:placetype":"locality"
},
  "geometry": {"coordinates":[44.871,39.1623],"type":"Point"}
}