{
  "type": "Feature",
  "properties": {
    "gn:admin1_code":"33",
    "gn:asciiname":"Sarab",
    "gn:country_code":"IR",
    "gn:dem":1682,
    "gn:feature_class":"P",
    "gn:feature_code":"PPLA2",
    "gn:name":"Sar\u0101b",
    "gn:population":0,
    "gn:timezone":"Asia/Tehran",
    "iso:country":"IR",
    "name:ara_x_preferred":[
        "\u0633\u0631\u0627\u0628"
    ],
    "name:azb_x_preferred":[
        "\u0633\u0631\u0627\u0628"
    ],
    "name:aze_x_preferred":[
        "S\u0259rab"
    ],
    "name:cat_x_preferred":[
        "Sarab"
    ],
    "name:ceb_x_preferred":[
        "Sar\u0101b"
    ],
    "name:deu_x_preferred":[
        "Sar\u0101b"
    ],
    "name:fas_x_preferred":[
        "\u0633\u0631\u0627\u0628"
    ],
    "name:fas_x_variant":[
        "Sar\u0101b"
    ],
    "name:ita_x_preferred":[
        "Sarab"
    ],
    "name:mlg_x_preferred":[
        "Sarab"
    ],
    "name:nld_x_preferred":[
        "Sarab"
    ],
    "name:pnb_x_preferred":[
        "\u0633\u0631\u0627\u0628"
    ],
    "name:pol_x_preferred":[
        "Sarab"
    ],
    "name:ron_x_preferred":[
        "Sarab"
    ],
    "name:rus_x_preferred":[
        "\u0421\u0435\u0440\u0430\u0431"
    ],
    "name:swe_x_preferred":[
        "Sar\u0101b"
    ],
    "name:tgk_x_preferred":[
        "\u0421\u0430\u0440\u043e\u0431"
    ],
    "name:tur_x_preferred":[
        "Serab"
    ],
    "name:urd_x_preferred":[
        "\u0633\u0631\u0627\u0628"
    ],
    "name:zho_x_preferred":[
        "\u85a9\u62c9\u535c"
    ],
    "wof:name":"Sarab",
    "wof:placetype":"locality"
},
  "geometry": {"coordinates":[47.5367,37.9408],"type":"Point"}
}