{
  "type": "Feature",
  "properties": {
    "gn:admin1_code":"33",
    "gn:asciiname":"Sarab",
    "gn:country_code":"IR",
    "gn:dem":1682,
    "gn:feature_class":"P",
    "gn:feature_code":"PPLA2",
    "gn:name":"Sar\u0101b",
    "gn:population":0,
    "gn:timezone":"Asia/Tehran",
    "iso:country":"IR",
    "name:fas_x_preferred":[
        "\u0633\u0631\u0627\u0628"
    ],
    "name:fas_x_variant":[
        "Sar\u0101b"
    ],
    "wof:name":"Sarab",
    "wof:placetype":"locality"
},
  "geometry": {"coordinates":[47.5367,37.9408],"type":"Point"}
}