{
  "type": "Feature",
  "properties": {
    "gn:admin1_code":"16.0",
    "gn:asciiname":"Somaqan",
    "gn:country_code":"IR",
    "gn:dem":1518,
    "gn:feature_class":"P",
    "gn:feature_code":"PPL",
    "gn:name":"Som\u0101q\u0101n",
    "gn:population":0,
    "gn:timezone":"Asia/Tehran",
    "iso:country":"IR",
    "name:fas_x_preferred":[
        "\u0633\u0645\u0627\u0642\u0627\u0646"
    ],
    "name:fas_x_variant":[
        "Som\u0101q\u0101n"
    ],
    "wof:name":"Somaqan",
    "wof:placetype":"locality"
},
  "geometry": {"coordinates":[45.7284,36.1448],"type":"Point"}
}