{
  "type": "Feature",
  "properties": {
    "gn:admin1_code":"8",
    "gn:asciiname":"Lalandiz",
    "gn:country_code":"IR",
    "gn:dem":1367,
    "gn:feature_class":"P",
    "gn:feature_code":"PPL",
    "gn:name":"L\u0101land\u012bz",
    "gn:population":0,
    "gn:timezone":"Asia/Tehran",
    "iso:country":"IR",
    "name:fas_x_preferred":[
        "\u0644\u0627\u0644\u0646\u062f\u06cc\u0632"
    ],
    "name:fas_x_variant":[
        "Lanand\u012bz",
        "L\u0101land\u012bz",
        "\u0644\u0646\u0646\u062f\u06cc\u0632"
    ],
    "wof:name":"Lalandiz",
    "wof:placetype":"locality"
},
  "geometry": {"coordinates":[49.0131,37.1472],"type":"Point"}
}