{
  "type": "Feature",
  "properties": {
    "gn:admin1_code":"33",
    "gn:asciiname":"Darin Su",
    "gn:country_code":"IR",
    "gn:dem":1836,
    "gn:feature_class":"P",
    "gn:feature_code":"PPL",
    "gn:name":"Dar\u012bn S\u016b",
    "gn:population":0,
    "gn:timezone":"Asia/Tehran",
    "iso:country":"IR",
    "name:fas_x_preferred":[
        "\u062f\u0631\u06cc\u0646 \u0633\u0648"
    ],
    "name:fas_x_variant":[
        "Dar\u012bn S\u016b"
    ],
    "wof:name":"Darin Su",
    "wof:placetype":"locality"
},
  "geometry": {"coordinates":[46.6729,37.2478],"type":"Point"}
}