{
  "type": "Feature",
  "properties": {
    "gn:admin1_code":"29",
    "gn:asciiname":"Gitari",
    "gn:country_code":"IR",
    "gn:dem":2091,
    "gn:feature_class":"P",
    "gn:feature_code":"PPL",
    "gn:name":"G\u012btar\u012b",
    "gn:population":0,
    "gn:timezone":"Asia/Tehran",
    "iso:country":"IR",
    "name:ceb_x_preferred":[
        "G\u012btar\u012b"
    ],
    "name:fas_x_preferred":[
        "\u06af\u06cc\u062a\u0631\u06cc"
    ],
    "name:fas_x_variant":[
        "G\u012btar\u012b",
        "G\u012btr\u012b"
    ],
    "name:swe_x_preferred":[
        "G\u012btar\u012b"
    ],
    "wof:name":"Gitari",
    "wof:placetype":"locality"
},
  "geometry": {"coordinates":[56.3152,31.5216],"type":"Point"}
}