{
  "type": "Feature",
  "properties": {
    "gn:admin1_code":"16.0",
    "gn:asciiname":"Anjineh-ye Ebrahim",
    "gn:country_code":"IR",
    "gn:dem":1519,
    "gn:elevation":"0.0",
    "gn:feature_class":"P",
    "gn:feature_code":"PPL",
    "gn:name":"\u0100nj\u012bneh-ye Ebr\u0101h\u012bm",
    "gn:population":0,
    "gn:timezone":"Asia/Tehran",
    "iso:country":"IR",
    "name:ara_x_preferred":[
        "\u0623\u0646\u062c\u064a\u0646\u0629 \u0627\u0644\u0633\u0641\u0644\u064a"
    ],
    "name:ceb_x_preferred":[
        "\u0100nj\u012bneh-ye Ebr\u0101h\u012bm"
    ],
    "name:ckb_x_preferred":[
        "\u0626\u06d5\u0646\u062c\u06ce\u0646\u06d5 \u0642\u0648\u0648\u06b5"
    ],
    "name:fas_x_preferred":[
        "\u0627\u064e\u0646\u062c\u064a\u0646\u0650\u06c0 \u0633\u064f\u0641\u0644\u064e\u0649"
    ],
    "name:fas_x_variant":[
        "\u0622\u0646\u062c\u06cc\u0646\u0647 \u0627\u0628\u0631\u0627\u0647\u06cc\u0645",
        "Anj\u012bneh-ye Sofl\u00e1",
        "\u0100nj\u012bneh-ye Ebr\u0101h\u012bm",
        "\u0627\u0646\u062c\u06cc\u0646\u0647 \u0633\u0641\u0644\u06cc"
    ],
    "name:swe_x_preferred":[
        "\u0100nj\u012bneh-ye Ebr\u0101h\u012bm"
    ],
    "wof:name":"Anjineh-ye Ebrahim",
    "wof:placetype":"locality"
},
  "geometry": {"coordinates":[45.6334,35.9807],"type":"Point"}
}