{
  "type": "Feature",
  "properties": {
    "gn:admin1_code":"3",
    "gn:asciiname":"Rusta-ye Shahid Beheshti",
    "gn:country_code":"IR",
    "gn:dem":2293,
    "gn:feature_class":"P",
    "gn:feature_code":"PPL",
    "gn:name":"R\u016bst\u0101-ye Shah\u012bd Behesht\u012b",
    "gn:population":0,
    "gn:timezone":"Asia/Tehran",
    "iso:country":"IR",
    "name:fas_x_preferred":[
        "\u0643\u0648\u064a\u0650 \u0634\u064e\u0647\u064a\u062f \u0628\u0650\u0647\u0650\u0634\u062a\u06cc"
    ],
    "name:fas_x_variant":[
        "K\u016by-e Shah\u012bd Behesht\u012b",
        "R\u016bst\u0101-ye Shah\u012bd Behesht\u012b",
        "\u0631\u0648\u0633\u062a\u0627\u06cc \u0634\u0647\u06cc\u062f \u0628\u0647\u0634\u062a\u06cc"
    ],
    "name:und_x_variant":[
        "\u0631\u0648\u0633\u062a\u0627\u06cc \u0634\u0647\u06cc\u062f \u0628\u0647\u0634\u062a\u06cc"
    ],
    "wof:name":"Rusta-ye Shahid Beheshti",
    "wof:placetype":"locality"
},
  "geometry": {"coordinates":[50.14121,32.45294000000001],"type":"Point"}
}