{
  "type": "Feature",
  "properties": {
    "gn:admin1_code":"7",
    "gn:asciiname":"Eshkaftestan",
    "gn:country_code":"IR",
    "gn:dem":1177,
    "gn:feature_class":"P",
    "gn:feature_code":"PPL",
    "gn:name":"Eshkaftest\u0101n",
    "gn:population":0,
    "gn:timezone":"Asia/Tehran",
    "iso:country":"IR",
    "name:fas_x_preferred":[
        "Eshkoftest\u0101n"
    ],
    "name:fas_x_variant":[
        "Eshkaftest\u0101n",
        "\u0627\u0634\u06a9\u0641\u062a\u0633\u062a\u0627\u0646"
    ],
    "name:und_x_variant":[
        "Eshkaftest\u0101n",
        "Eshkaft",
        "\u0627\u0634\u06a9\u0641\u062a\u0633\u062a\u0627\u0646"
    ],
    "wof:name":"Eshkaftestan",
    "wof:placetype":"locality"
},
  "geometry": {"coordinates":[51.50462,30.35817],"type":"Point"}
}