{
  "type": "Feature",
  "properties": {
    "gn:admin1_code":"23",
    "gn:asciiname":"Talkastan",
    "gn:country_code":"IR",
    "gn:dem":1760,
    "gn:feature_class":"P",
    "gn:feature_code":"PPL",
    "gn:name":"Talkast\u0101n",
    "gn:population":0,
    "gn:timezone":"Asia/Tehran",
    "iso:country":"IR",
    "name:fas_x_preferred":[
        "\u062a\u0644 \u06a9\u0633\u0648"
    ],
    "name:fas_x_variant":[
        "Tall Kas\u016b",
        "\u062a\u0644\u06a9\u0633\u062a\u0627\u0646"
    ],
    "name:und_x_variant":[
        "Talkast\u0101n"
    ],
    "wof:name":"Talkastan",
    "wof:placetype":"locality"
},
  "geometry": {"coordinates":[48.9445,33.3367],"type":"Point"}
}