{
  "type": "Feature",
  "properties": {
    "gn:admin1_code":"26.0",
    "gn:asciiname":"Arjomand",
    "gn:country_code":"IR",
    "gn:dem":2150,
    "gn:feature_class":"P",
    "gn:feature_code":"PPL",
    "gn:name":"Arjomand",
    "gn:population":0,
    "gn:timezone":"Asia/Tehran",
    "iso:country":"IR",
    "name:fas_x_preferred":[
        "\u0627\u0631\u062c\u0645\u0646\u062f"
    ],
    "name:und_x_variant":[
        "Arjmand",
        "Arzam\u0101n",
        "Arjomad",
        "Arjomand"
    ],
    "wof:name":"Arjomand",
    "wof:placetype":"locality"
},
  "geometry": {"coordinates":[52.51177,35.81499],"type":"Point"}
}