{
  "type": "Feature",
  "properties": {
    "gn:admin1_code":"22",
    "gn:asciiname":"Hapulu",
    "gn:country_code":"IR",
    "gn:dem":10,
    "gn:feature_class":"P",
    "gn:feature_code":"PPL",
    "gn:name":"Hap\u016bl\u016b",
    "gn:population":0,
    "gn:timezone":"Asia/Tehran",
    "iso:country":"IR",
    "name:fas_x_preferred":[
        "\u0647\u064e\u067e\u0648\u0644\u0648"
    ],
    "name:und_x_variant":[
        "Hap\u016bl\u016b"
    ],
    "wof:name":"Hapulu",
    "wof:placetype":"locality"
},
  "geometry": {"coordinates":[51.01667,29.23333],"type":"Point"}
}