{
  "type": "Feature",
  "properties": {
    "gn:admin1_code":"35",
    "gn:asciiname":"Chetan",
    "gn:cc2":"IR",
    "gn:country_code":"IR",
    "gn:dem":1314,
    "gn:feature_class":"P",
    "gn:feature_code":"PPL",
    "gn:name":"Chetan",
    "gn:population":0,
    "gn:timezone":"Asia/Tehran",
    "iso:country":"IR",
    "name:fas_x_preferred":[
        "\u0686\u0650\u062a\u064e\u0646"
    ],
    "name:fas_x_variant":[
        "\u0686\u0650\u062a\u064a\u0646"
    ],
    "name:ita_x_preferred":[
        "Chetan"
    ],
    "name:und_x_variant":[
        "Chet\u012bn",
        "Chiten",
        "Chitin",
        "Chittin"
    ],
    "name:uzb_x_preferred":[
        "Chetan"
    ],
    "wof:name":"Chetan",
    "wof:placetype":"locality"
},
  "geometry": {"coordinates":[51.41083,36.39611],"type":"Point"}
}