{
  "type": "Feature",
  "properties": {
    "gn:admin1_code":"28.0",
    "gn:asciiname":"Shahrak-e Mobarezan",
    "gn:country_code":"IR",
    "gn:dem":1557,
    "gn:feature_class":"P",
    "gn:feature_code":"PPL",
    "gn:name":"Shahrak-e Mob\u0101rez\u0101n",
    "gn:population":0,
    "gn:timezone":"Asia/Tehran",
    "iso:country":"IR",
    "name:fas_x_preferred":[
        "\u0634\u0647\u0631\u06a9 \u0645\u0628\u0627\u0631\u0632\u0627\u0646"
    ],
    "name:und_x_variant":[
        "Shahrak-e Mob\u0101rez\u0101n"
    ],
    "wof:name":"Shahrak-e Mobarezan",
    "wof:placetype":"locality"
},
  "geometry": {"coordinates":[51.74693,32.69138],"type":"Point"}
}