{
  "type": "Feature",
  "properties": {
    "gn:admin1_code":"33",
    "gn:asciiname":"`Eyshabad",
    "gn:country_code":"IR",
    "gn:dem":1663,
    "gn:feature_class":"P",
    "gn:feature_code":"PPL",
    "gn:name":"\u2018Eysh\u0101b\u0101d",
    "gn:population":0,
    "gn:timezone":"Asia/Tehran",
    "iso:country":"IR",
    "name:fas_x_preferred":[
        "\u0639\u06cc\u0634 \u0622\u0628\u0627\u062f"
    ],
    "name:fas_x_variant":[
        "\u2018Eysh\u0101b\u0101d"
    ],
    "name:und_x_variant":[
        "Eshavand",
        "Eshavat"
    ],
    "wof:name":"`Eyshabad",
    "wof:placetype":"locality"
},
  "geometry": {"coordinates":[45.6126,38.3727],"type":"Point"}
}