{
  "type": "Feature",
  "properties": {
    "gn:admin1_code":"9",
    "gn:asciiname":"Owraqin",
    "gn:country_code":"IR",
    "gn:dem":1691,
    "gn:feature_class":"P",
    "gn:feature_code":"PPL",
    "gn:name":"Owraq\u012bn",
    "gn:population":0,
    "gn:timezone":"Asia/Tehran",
    "iso:country":"IR",
    "name:fas_x_preferred":[
        "\u0627\u0648\u0631\u0642\u06cc\u0646"
    ],
    "name:fas_x_variant":[
        "Ovraq\u012bn"
    ],
    "name:und_x_variant":[
        "Auwarghon",
        "Oorgh\u012bn",
        "\u016arq\u012bn",
        "Orq\u012bn",
        "Owraq\u012bn"
    ],
    "wof:name":"Owraqin",
    "wof:placetype":"locality"
},
  "geometry": {"coordinates":[48.69082,35.28259],"type":"Point"}
}