{
  "type": "Feature",
  "properties": {
    "gn:admin1_code":"28.0",
    "gn:asciiname":"Nesf Rah-e Qamsar",
    "gn:country_code":"IR",
    "gn:dem":1215,
    "gn:feature_class":"P",
    "gn:feature_code":"PPL",
    "gn:name":"Ne\u015ff R\u0101h-e Qam\u015far",
    "gn:population":0,
    "gn:timezone":"Asia/Tehran",
    "iso:country":"IR",
    "name:fas_x_preferred":[
        "\u0646\u0635\u0641 \u0631\u0627\u0647 \u0642\u0645\u0635\u0631"
    ],
    "name:fas_x_variant":[
        "Ne\u015ff-e R\u0101h",
        "Ne\u015ff R\u0101h-e Qam\u015far"
    ],
    "name:und_x_variant":[
        "B\u0101gh-e Ne\u015ff-e R\u0101h"
    ],
    "wof:name":"Nesf Rah-e Qamsar",
    "wof:placetype":"locality"
},
  "geometry": {"coordinates":[51.4601,33.8606],"type":"Point"}
}