{
  "type": "Feature",
  "properties": {
    "gn:admin1_code":"5",
    "gn:asciiname":"Gusheh",
    "gn:country_code":"IR",
    "gn:dem":1448,
    "gn:feature_class":"P",
    "gn:feature_code":"PPL",
    "gn:name":"G\u016bsheh",
    "gn:population":0,
    "gn:timezone":"Asia/Tehran",
    "iso:country":"IR",
    "name:fas_x_preferred":[
        "\u06af\u0648\u0634\u0650\u06c0 \u0633\u064f\u0641\u0644\u064e\u0649"
    ],
    "name:fas_x_variant":[
        "\u06af\u0648\u0634\u0650\u0647\u0650 \u0633\u064f\u0641\u0644\u064e\u0649",
        "G\u016bsheh-ye Sofl\u00e1",
        "G\u016bsheh",
        "\u06af\u0648\u0634\u0647"
    ],
    "name:und_x_variant":[
        "G\u016bsheh-e Sofl\u00e1",
        "G\u016bsheh",
        "\u06af\u0648\u0634\u0647"
    ],
    "wof:name":"Gusheh",
    "wof:placetype":"locality"
},
  "geometry": {"coordinates":[50.74741,30.93251],"type":"Point"}
}