{
  "type": "Feature",
  "properties": {
    "gn:admin1_code":"13",
    "gn:asciiname":"Qarah Qach",
    "gn:country_code":"IR",
    "gn:dem":1527,
    "gn:feature_class":"P",
    "gn:feature_code":"PPL",
    "gn:name":"Qarah Q\u0101ch",
    "gn:population":0,
    "gn:timezone":"Asia/Tehran",
    "iso:country":"IR",
    "name:fas_x_preferred":[
        "\u0642\u0631\u0647 \u0642\u0627\u0686"
    ],
    "name:fas_x_variant":[
        "Qarah Q\u0101ch",
        "Qareh Q\u0101ch"
    ],
    "name:und_x_variant":[
        "Qara Q\u0101j",
        "Qareh Q\u0101j",
        "Qareh Q\u0101ch",
        "Qareh Q\u0101reh"
    ],
    "wof:name":"Qarah Qach",
    "wof:placetype":"locality"
},
  "geometry": {"coordinates":[47.3711,34.678],"type":"Point"}
}