{
  "type": "Feature",
  "properties": {
    "gn:admin1_code":"35.0",
    "gn:asciiname":"Bandaforuz",
    "gn:country_code":"IR",
    "gn:dem":118,
    "gn:feature_class":"P",
    "gn:feature_code":"PPL",
    "gn:name":"Bandafor\u016bz",
    "gn:population":0,
    "gn:timezone":"Asia/Tehran",
    "iso:country":"IR",
    "name:fas_x_preferred":[
        "Bandafr\u016bz"
    ],
    "name:fas_x_variant":[
        "\u0628\u0646\u062f\u0627\u0641\u0631\u0648\u0632",
        "Bandafor\u016bz"
    ],
    "name:und_x_variant":[
        "\u0628\u0646\u062f\u0627\u0641\u0631\u0648\u0632"
    ],
    "wof:name":"Bandaforuz",
    "wof:placetype":"locality"
},
  "geometry": {"coordinates":[53.15642,36.53042],"type":"Point"}
}