{
  "type": "Feature",
  "properties": {
    "gn:admin1_code":"41",
    "gn:asciiname":"Razaviyeh",
    "gn:country_code":"IR",
    "gn:dem":1472,
    "gn:feature_class":"P",
    "gn:feature_code":"PPL",
    "gn:name":"Ra\u1e95av\u012byeh",
    "gn:population":0,
    "gn:timezone":"Asia/Tehran",
    "iso:country":"IR",
    "name:fas_x_preferred":[
        "Morte\u1e95av\u012byeh"
    ],
    "name:fas_x_variant":[
        "\u0645\u0631\u062a\u0636\u0648\u064a\u0647",
        "Murtazav\u012byeh",
        "\u0631\u0636\u0648\u064a\u0647"
    ],
    "name:und_x_variant":[
        "Murtazav\u012byeh",
        "\u0645\u0631\u062a\u0636\u0648\u064a\u0647",
        "Ra\u1e95av\u012byeh"
    ],
    "wof:name":"Razaviyeh",
    "wof:placetype":"locality"
},
  "geometry": {"coordinates":[59.12303000000001,32.55002],"type":"Point"}
}