{
  "type": "Feature",
  "properties": {
    "gn:admin1_code":"4.0",
    "gn:asciiname":"Shabuni",
    "gn:country_code":"IR",
    "gn:dem":381,
    "gn:feature_class":"P",
    "gn:feature_code":"PPLL",
    "gn:name":"Shab\u016bn\u012b",
    "gn:population":0,
    "gn:timezone":"Asia/Tehran",
    "iso:country":"IR",
    "name:fas_x_preferred":[
        "\u0634\u0628\u0648\u0646\u06cc"
    ],
    "name:und_x_variant":[
        "Shab\u016bn\u012b"
    ],
    "wof:name":"Shabuni",
    "wof:placetype":"locality"
},
  "geometry": {"coordinates":[59.09796,27.11927],"type":"Point"}
}