{
  "type": "Feature",
  "properties": {
    "gn:admin1_code":"15",
    "gn:asciiname":"Konjed Kar",
    "gn:country_code":"IR",
    "gn:dem":427,
    "gn:feature_class":"P",
    "gn:feature_code":"PPL",
    "gn:name":"Konjed K\u0101r",
    "gn:population":0,
    "gn:timezone":"Asia/Tehran",
    "iso:country":"IR",
    "name:fas_x_preferred":[
        "\u06a9\u0646\u062c\u062f \u06a9\u0627\u0631"
    ],
    "name:fas_x_variant":[
        "Konjed K\u0101r"
    ],
    "wof:name":"Konjed Kar",
    "wof:placetype":"locality"
},
  "geometry": {"coordinates":[49.05984,32.1804],"type":"Point"}
}