{
  "type": "Feature",
  "properties": {
    "gn:admin1_code":"13",
    "gn:asciiname":"`Abd ol Mohammad",
    "gn:country_code":"IR",
    "gn:dem":1661,
    "gn:feature_class":"P",
    "gn:feature_code":"PPL",
    "gn:name":"\u2018Abd ol Mo\u1e29ammad",
    "gn:population":0,
    "gn:timezone":"Asia/Tehran",
    "iso:country":"IR",
    "name:fas_x_preferred":[
        "\u0639\u0628\u062f\u0627\u0644\u0645\u062d\u0645\u0651\u062f"
    ],
    "name:fas_x_variant":[
        "\u2018Abd ol Mo\u1e29ammad"
    ],
    "wof:name":"`Abd ol Mohammad",
    "wof:placetype":"locality"
},
  "geometry": {"coordinates":[47.3357,34.6699],"type":"Point"}
}