{
  "type": "Feature",
  "properties": {
    "gn:admin1_code":"29.0",
    "gn:asciiname":"Amjeziyeh",
    "gn:country_code":"IR",
    "gn:dem":1452,
    "gn:feature_class":"P",
    "gn:feature_code":"PPL",
    "gn:name":"Amjez\u012byeh",
    "gn:population":0,
    "gn:timezone":"Asia/Tehran",
    "iso:country":"IR",
    "name:fas_x_preferred":[
        "Amjez\u012byeh"
    ],
    "wof:name":"Amjeziyeh",
    "wof:placetype":"locality"
},
  "geometry": {"coordinates":[58.04111,28.60528],"type":"Point"}
}