{
  "type": "Feature",
  "properties": {
    "gn:admin1_code":"8",
    "gn:asciiname":"Angula Deh",
    "gn:country_code":"IR",
    "gn:dem":55,
    "gn:feature_class":"P",
    "gn:feature_code":"PPL",
    "gn:name":"\u0100ng\u016bl\u0101 Deh",
    "gn:population":0,
    "gn:timezone":"Asia/Tehran",
    "iso:country":"IR",
    "name:fas_x_preferred":[
        "\u0622\u0646\u06af\u0648\u0644\u0627 \u062f\u0647"
    ],
    "name:fas_x_variant":[
        "\u0100ng\u016bl\u0101 Deh"
    ],
    "wof:name":"Angula Deh",
    "wof:placetype":"locality"
},
  "geometry": {"coordinates":[48.822,38.3017],"type":"Point"}
}