{
  "type": "Feature",
  "properties": {
    "gn:admin1_code":"7",
    "gn:asciiname":"Padarb Lavar",
    "gn:country_code":"IR",
    "gn:dem":468,
    "gn:feature_class":"P",
    "gn:feature_code":"PPL",
    "gn:name":"P\u0101darb L\u0101var",
    "gn:population":0,
    "gn:timezone":"Asia/Tehran",
    "iso:country":"IR",
    "name:fas_x_preferred":[
        "\u0628\u0627\u06cc\u062f\u0631"
    ],
    "name:fas_x_variant":[
        "B\u0101ydar",
        "\u067e\u0627\u062f\u0631\u0628 \u0644\u0627\u0648\u0631"
    ],
    "name:und_x_variant":[
        "P\u0101darb L\u0101var"
    ],
    "wof:name":"Padarb Lavar",
    "wof:placetype":"locality"
},
  "geometry": {"coordinates":[53.8923,27.2372],"type":"Point"}
}