{
  "type": "Feature",
  "properties": {
    "gn:admin1_code":"16",
    "gn:asciiname":"Shah Jub",
    "gn:country_code":"IR",
    "gn:dem":1881,
    "gn:feature_class":"P",
    "gn:feature_code":"PPL",
    "gn:name":"Sh\u0101h J\u016bb",
    "gn:population":0,
    "gn:timezone":"Asia/Tehran",
    "iso:country":"IR",
    "name:ara_x_preferred":[
        "\u0634\u0627\u0629 \u062c\u0648\u0628"
    ],
    "name:ceb_x_preferred":[
        "Sh\u0101h J\u016bb"
    ],
    "name:fas_x_preferred":[
        "\u0634\u0627\u0647 \u062c\u0648\u0628"
    ],
    "name:fas_x_variant":[
        "Sh\u0101h Ch\u016bb",
        "Sh\u0101h J\u016bb"
    ],
    "name:swe_x_preferred":[
        "Sh\u0101h J\u016bb"
    ],
    "name:und_x_variant":[
        "Shah Ju"
    ],
    "wof:name":"Shah Jub",
    "wof:placetype":"locality"
},
  "geometry": {"coordinates":[47.38662,35.12393],"type":"Point"}
}