{
  "type": "Feature",
  "properties": {
    "gn:admin1_code":"29",
    "gn:asciiname":"Dowdanag-e Bidaran",
    "gn:country_code":"IR",
    "gn:dem":1175,
    "gn:feature_class":"P",
    "gn:feature_code":"PPL",
    "gn:name":"Dowd\u0101nag-e B\u012bdar\u0101n",
    "gn:population":0,
    "gn:timezone":"Asia/Tehran",
    "iso:country":"IR",
    "name:fas_x_preferred":[
        "B\u012bdar\u0101n-e B\u0101l\u0101"
    ],
    "name:fas_x_variant":[
        "\u062f\u0648\u062f\u0627\u0646\u06af \u0628\u064a\u062f\u0631\u0627\u0646",
        "\u062f\u0647 \u062f\u0648\u0646\u06af"
    ],
    "name:und_x_variant":[
        "Dowd\u0101nag-e B\u012bdar\u0101n",
        "Deh Davang"
    ],
    "wof:name":"Dowdanag-e Bidaran",
    "wof:placetype":"locality"
},
  "geometry": {"coordinates":[58.25442,29.13379],"type":"Point"}
}