{
  "type": "Feature",
  "properties": {
    "gn:admin1_code":"4",
    "gn:asciiname":"Sar Kang",
    "gn:country_code":"IR",
    "gn:dem":2135,
    "gn:feature_class":"P",
    "gn:feature_code":"PPL",
    "gn:name":"Sar Kang",
    "gn:population":0,
    "gn:timezone":"Asia/Tehran",
    "iso:country":"IR",
    "name:fas_x_preferred":[
        "\u0633\u0631 \u06a9\u0646\u06af"
    ],
    "wof:name":"Sar Kang",
    "wof:placetype":"locality"
},
  "geometry": {"coordinates":[60.8196,28.7624],"type":"Point"}
}