{
  "type": "Feature",
  "properties": {
    "gn:admin1_code":"4",
    "gn:asciiname":"Chah-e Amir",
    "gn:country_code":"IR",
    "gn:dem":386,
    "gn:feature_class":"P",
    "gn:feature_code":"PPLF",
    "gn:name":"Ch\u0101h-e Am\u012br",
    "gn:population":0,
    "gn:timezone":"Asia/Tehran",
    "iso:country":"IR",
    "name:fas_x_preferred":[
        "\u062a\u0648\u06a9\u0651\u0644 \u0622\u0628\u0627\u062f"
    ],
    "name:fas_x_variant":[
        "Tavakkol\u0101b\u0101d",
        "\u0686\u0627\u0647 \u0627\u0645\u064a\u0631",
        "\u0686\u0627\u0647 \u062f\u0645\u064a\u0631"
    ],
    "name:und_x_variant":[
        "Ch\u0101h-e Am\u012br",
        "Ch\u0101h-e Dam\u012br"
    ],
    "wof:name":"Chah-e Amir",
    "wof:placetype":"locality"
},
  "geometry": {"coordinates":[59.29876,27.06211],"type":"Point"}
}