{
  "type": "Feature",
  "properties": {
    "gn:admin1_code":"11",
    "gn:asciiname":"Goleshvar",
    "gn:country_code":"IR",
    "gn:dem":577,
    "gn:feature_class":"P",
    "gn:feature_code":"PPL",
    "gn:name":"Goleshv\u0101r",
    "gn:population":0,
    "gn:timezone":"Asia/Tehran",
    "iso:country":"IR",
    "name:fas_x_preferred":[
        "\u06af\u0644\u0634\u0648\u0627\u0631"
    ],
    "name:fas_x_variant":[
        "\u06af\u064f\u0644\u064e\u0634\u0648\u0627\u0631",
        "Goleshv\u0101r"
    ],
    "name:msa_x_preferred":[
        "Goleshvar"
    ],
    "name:und_x_variant":[
        "Golashv\u0101r"
    ],
    "wof:name":"Goleshvar",
    "wof:placetype":"locality"
},
  "geometry": {"coordinates":[57.0972,27.6303],"type":"Point"}
}