{
  "type": "Feature",
  "properties": {
    "gn:admin1_code":"35.0",
    "gn:asciiname":"Tubon",
    "gn:country_code":"IR",
    "gn:dem":13,
    "gn:feature_class":"P",
    "gn:feature_code":"PPL",
    "gn:name":"T\u016bbon",
    "gn:population":0,
    "gn:timezone":"Asia/Tehran",
    "iso:country":"IR",
    "name:fas_x_preferred":[
        "T\u016bbon"
    ],
    "name:fas_x_variant":[
        "\u062a\u0648\u0628\u0646"
    ],
    "wof:name":"Tubon",
    "wof:placetype":"locality"
},
  "geometry": {"coordinates":[50.62244000000001,36.93307],"type":"Point"}
}