{
  "type": "Feature",
  "properties": {
    "gn:admin1_code":"32",
    "gn:asciiname":"Qarah Hasanlu",
    "gn:country_code":"IR",
    "gn:dem":1332,
    "gn:feature_class":"P",
    "gn:feature_code":"PPL",
    "gn:name":"Qarah \u1e28asanl\u016b",
    "gn:population":0,
    "gn:timezone":"Asia/Tehran",
    "iso:country":"IR",
    "name:azb_x_preferred":[
        "\u0642\u0627\u0631\u0627 \u062d\u0633\u0646\u0644\u06cc(\u0646\u0645\u06cc\u0646)"
    ],
    "name:fas_x_preferred":[
        "\u0642\u064e\u0631\u064e\u0647 \u062d\u064e\u0633\u064e\u0646\u0644\u0648"
    ],
    "name:fas_x_variant":[
        "\u0642\u0631\u0647 \u062d\u0633\u0646 \u0644\u0648",
        "Qarah \u1e28asanl\u016b",
        "\u0642\u0631\u0647\u200c\u062d\u0633\u0646\u0644\u0648"
    ],
    "name:msa_x_preferred":[
        "Qarah Hasanlu"
    ],
    "name:mzn_x_preferred":[
        "\u0642\u0631\u0647\u200c\u062d\u0633\u0646\u0644\u0648"
    ],
    "wof:name":"Qarah Hasanlu",
    "wof:placetype":"locality"
},
  "geometry": {"coordinates":[48.457,38.2534],"type":"Point"}
}