{
  "type": "Feature",
  "properties": {
    "gn:admin1_code":"8.0",
    "gn:asciiname":"Bagh Mahalleh",
    "gn:country_code":"IR",
    "gn:dem":-20,
    "gn:feature_class":"P",
    "gn:feature_code":"PPL",
    "gn:name":"B\u0101gh Ma\u1e29alleh",
    "gn:population":0,
    "gn:timezone":"Asia/Tehran",
    "iso:country":"IR",
    "name:ara_x_preferred":[
        "\u0628\u0627\u063a \u0645\u0644\u0627\u0644\u0629"
    ],
    "name:ceb_x_preferred":[
        "B\u0101gh Ma\u1e29alleh"
    ],
    "name:fas_x_preferred":[
        "B\u0101gh"
    ],
    "name:fas_x_variant":[
        "\u0628\u0627\u063a \u0645\u062d\u0644\u0647"
    ],
    "name:swe_x_preferred":[
        "B\u0101gh Ma\u1e29alleh"
    ],
    "name:und_x_variant":[
        "B\u0101gh Ma\u1e29alleh"
    ],
    "wof:name":"Bagh Mahalleh",
    "wof:placetype":"locality"
},
  "geometry": {"coordinates":[49.76736,37.4455],"type":"Point"}
}