{
  "type": "Feature",
  "properties": {
    "gn:admin1_code":"37.0",
    "gn:asciiname":"Mohammadabad",
    "gn:country_code":"IR",
    "gn:dem":157,
    "gn:feature_class":"P",
    "gn:feature_code":"PPL",
    "gn:name":"Mo\u1e29ammad\u0101b\u0101d",
    "gn:population":0,
    "gn:timezone":"Asia/Tehran",
    "iso:country":"IR",
    "name:fas_x_preferred":[
        "Sh\u0101h Mo\u1e29ammad"
    ],
    "name:fas_x_variant":[
        "\u0634\u0627\u0647 \u0645\u062d\u0645\u062f",
        "\u0645\u062d\u0645\u062f \u0622\u0628\u0627\u062f"
    ],
    "name:und_x_variant":[
        "\u0634\u0627\u0647 \u0645\u062d\u0645\u062f",
        "Mo\u1e29ammad\u0101b\u0101d"
    ],
    "wof:name":"Mohammadabad",
    "wof:placetype":"locality"
},
  "geometry": {"coordinates":[55.37623000000001,37.21168],"type":"Point"}
}