{
  "type": "Feature",
  "properties": {
    "gn:admin1_code":"33",
    "gn:asciiname":"Zaviyeh",
    "gn:country_code":"IR",
    "gn:dem":1893,
    "gn:feature_class":"P",
    "gn:feature_code":"PPL",
    "gn:name":"Z\u0101v\u012byeh",
    "gn:population":0,
    "gn:timezone":"Asia/Tehran",
    "iso:country":"IR",
    "name:fas_x_preferred":[
        "\u0632\u0627\u0648\u06cc\u0647"
    ],
    "name:fas_x_variant":[
        "Z\u0101v\u012byeh"
    ],
    "name:und_x_variant":[
        "Z\u0101veyeh"
    ],
    "wof:name":"Zaviyeh",
    "wof:placetype":"locality"
},
  "geometry": {"coordinates":[47.1708,37.3201],"type":"Point"}
}