{
  "type": "Feature",
  "properties": {
    "gn:admin1_code":"7",
    "gn:asciiname":"Tireh Bagh",
    "gn:country_code":"IR",
    "gn:dem":1684,
    "gn:feature_class":"P",
    "gn:feature_code":"PPL",
    "gn:name":"T\u012breh B\u0101gh",
    "gn:population":0,
    "gn:timezone":"Asia/Tehran",
    "iso:country":"IR",
    "name:fas_x_preferred":[
        "\u062a\u06cc\u0631 \u0628\u0627\u063a"
    ],
    "name:fas_x_variant":[
        "T\u012breh B\u0101gh",
        "T\u012br-e B\u0101gh",
        "\u062a\u06cc\u0631\u0647 \u0628\u0627\u063a"
    ],
    "name:msa_x_preferred":[
        "Tireh Bagh"
    ],
    "wof:name":"Tireh Bagh",
    "wof:placetype":"locality"
},
  "geometry": {"coordinates":[52.6757,30.2339],"type":"Point"}
}