{
  "type": "Feature",
  "properties": {
    "gn:admin1_code":"22",
    "gn:asciiname":"Bagh-e Payeh",
    "gn:cc2":"IR",
    "gn:country_code":"IR",
    "gn:dem":417,
    "gn:feature_class":"P",
    "gn:feature_code":"PPL",
    "gn:name":"B\u0101gh-e P\u0101yeh",
    "gn:population":0,
    "gn:timezone":"Asia/Tehran",
    "iso:country":"IR",
    "name:fas_x_preferred":[
        "\u0628\u0627\u063a\u0650 \u067e\u0627\u064a\u0650\u0647"
    ],
    "name:fas_x_variant":[
        "\u0628\u0627\u063a\u0650 \u067e\u064a\u0650\u0651\u0647",
        "B\u0101gh-e P\u0101yeh"
    ],
    "name:und_x_variant":[
        "B\u0101gh-i-P\u0101yeh",
        "B\u0101gh-e P\u012byeh"
    ],
    "wof:name":"Bagh-e Payeh",
    "wof:placetype":"locality"
},
  "geometry": {"coordinates":[52.43333000000001,27.88333],"type":"Point"}
}