{
  "type": "Feature",
  "properties": {
    "gn:admin1_code":"44",
    "gn:asciiname":"Kureh-ye Moqaddam",
    "gn:country_code":"IR",
    "gn:dem":1180,
    "gn:feature_class":"P",
    "gn:feature_code":"PPL",
    "gn:name":"K\u016breh-ye Moqaddam",
    "gn:population":0,
    "gn:timezone":"Asia/Tehran",
    "iso:country":"IR",
    "name:fas_x_preferred":[
        "\u0643\u0648\u0631\u0650\u06c0 \u0645\u064f\u0642\u064e\u062f\u064e\u0651\u0645"
    ],
    "name:fas_x_variant":[
        "K\u016breh-ye Moqaddam"
    ],
    "wof:name":"Kureh-ye Moqaddam",
    "wof:placetype":"locality"
},
  "geometry": {"coordinates":[50.58889,35.93889],"type":"Point"}
}