{
  "type": "Feature",
  "properties": {
    "gn:admin1_code":"43",
    "gn:asciiname":"Kalateh-ye Esma`il Khan",
    "gn:country_code":"IR",
    "gn:dem":830,
    "gn:feature_class":"P",
    "gn:feature_code":"PPL",
    "gn:name":"Kal\u0101teh-ye Esm\u0101\u2018\u012bl Kh\u0101n",
    "gn:population":0,
    "gn:timezone":"Asia/Tehran",
    "iso:country":"IR",
    "name:fas_x_preferred":[
        "Kal\u0101teh-ye Esm\u0101\u2018\u012bl Kh\u0101n"
    ],
    "name:fas_x_variant":[
        "\u06a9\u0644\u0627\u062a\u0647 \u0627\u0633\u0645\u0627\u0639\u06cc\u0644 \u062e\u0627\u0646"
    ],
    "wof:name":"Kalateh-ye Esma`il Khan",
    "wof:placetype":"locality"
},
  "geometry": {"coordinates":[56.76716,37.51084],"type":"Point"}
}