{
  "type": "Feature",
  "properties": {
    "gn:admin1_code":"35.0",
    "gn:asciiname":"Kia Pey",
    "gn:country_code":"IR",
    "gn:dem":145,
    "gn:feature_class":"P",
    "gn:feature_code":"PPL",
    "gn:name":"K\u012b\u0101 Pey",
    "gn:population":0,
    "gn:timezone":"Asia/Tehran",
    "iso:country":"IR",
    "name:ceb_x_preferred":[
        "K\u012b\u0101 Pey"
    ],
    "name:fas_x_preferred":[
        "\u0643\u0650\u064a\u0627 \u067e\u0650\u06cc"
    ],
    "name:fas_x_variant":[
        "K\u012b\u0101 Pey",
        "\u0643\u064a\u0627 \u067e\u06cc",
        "\u06a9\u06cc\u0627\u067e\u06cc"
    ],
    "name:swe_x_preferred":[
        "K\u012b\u0101 Pey"
    ],
    "name:und_x_variant":[
        "Key\u0101 Pey"
    ],
    "wof:name":"Kia Pey",
    "wof:placetype":"locality"
},
  "geometry": {"coordinates":[53.20352,36.55876],"type":"Point"}
}