{
  "type": "Feature",
  "properties": {
    "gn:admin1_code":"29",
    "gn:asciiname":"Chenalbarin",
    "gn:country_code":"IR",
    "gn:dem":2231,
    "gn:feature_class":"P",
    "gn:feature_code":"PPL",
    "gn:name":"Chen\u0101lbar\u012bn",
    "gn:population":0,
    "gn:timezone":"Asia/Tehran",
    "iso:country":"IR",
    "name:fas_x_preferred":[
        "\u0686\u0646\u0627\u0631\u0628\u0631\u06cc\u0646"
    ],
    "name:fas_x_variant":[
        "Chen\u0101rbar\u012bn",
        "\u0686\u0646\u0627\u0644\u0628\u0631\u06cc\u0646"
    ],
    "name:und_x_variant":[
        "Chenal Bari",
        "Chenal Parin",
        "Chen\u0101lbar\u012bn"
    ],
    "wof:name":"Chenalbarin",
    "wof:placetype":"locality"
},
  "geometry": {"coordinates":[55.8932,29.7909],"type":"Point"}
}