{
  "type": "Feature",
  "properties": {
    "gn:admin1_code":"13",
    "gn:asciiname":"Posht Gelah",
    "gn:cc2":"IR",
    "gn:country_code":"IR",
    "gn:dem":1426,
    "gn:feature_class":"P",
    "gn:feature_code":"PPL",
    "gn:name":"Posht Gelah",
    "gn:population":0,
    "gn:timezone":"Asia/Tehran",
    "iso:country":"IR",
    "name:und_x_variant":[
        "M\u0101veh Z\u0101r\u0101n",
        "Khosrow B\u0101sheh",
        "Posht Gelah"
    ],
    "wof:name":"Posht Gelah",
    "wof:placetype":"locality"
},
  "geometry": {"coordinates":[46.23333,34.76667],"type":"Point"}
}