{
  "type": "Feature",
  "properties": {
    "gn:admin1_code":"42",
    "gn:asciiname":"Mazra`eh-ye Sheykhha",
    "gn:country_code":"IR",
    "gn:dem":1165,
    "gn:feature_class":"P",
    "gn:feature_code":"PPL",
    "gn:name":"Mazra\u2018eh-ye Sheykhh\u0101",
    "gn:population":0,
    "gn:timezone":"Asia/Tehran",
    "iso:country":"IR",
    "name:ara_x_preferred":[
        "\u0643\u0644\u0627\u062a\u0647 \u0634\u064a\u062e\u200c\u0647\u0627"
    ],
    "name:ceb_x_preferred":[
        "Kal\u0101teh-ye Sheykhh\u0101"
    ],
    "name:fas_x_preferred":[
        "\u06a9\u0644\u0627\u062a\u0647 \u0634\u06cc\u062e \u0647\u0627"
    ],
    "name:fas_x_variant":[
        "Kal\u0101teh-ye Sheykhh\u0101",
        "\u0645\u0632\u0631\u0639\u0647 \u0634\u06cc\u062e \u0647\u0627",
        "\u06a9\u0644\u0627\u062a\u0647 \u0634\u06cc\u062e\u200c\u0647\u0627"
    ],
    "name:swe_x_preferred":[
        "Kal\u0101teh-ye Sheykhh\u0101"
    ],
    "name:und_x_variant":[
        "Mazra\u2018eh-ye Sheykhh\u0101"
    ],
    "wof:name":"Mazra`eh-ye Sheykhha",
    "wof:placetype":"locality"
},
  "geometry": {"coordinates":[59.19801,36.60307],"type":"Point"}
}