{
  "type": "Feature",
  "properties": {
    "gn:admin1_code":"4",
    "gn:asciiname":"Gati",
    "gn:country_code":"IR",
    "gn:dem":636,
    "gn:feature_class":"P",
    "gn:feature_code":"PPL",
    "gn:name":"Gat\u012b",
    "gn:population":0,
    "gn:timezone":"Asia/Tehran",
    "iso:country":"IR",
    "name:ceb_x_preferred":[
        "Gati"
    ],
    "name:fas_x_preferred":[
        "\u06af\u062a\u06cc"
    ],
    "name:fas_x_variant":[
        "Gat\u012b"
    ],
    "name:msa_x_preferred":[
        "Gati"
    ],
    "name:nep_x_preferred":[
        "\u0917\u093e\u0924\u0940"
    ],
    "name:pol_x_preferred":[
        "Gati"
    ],
    "wof:name":"Gati",
    "wof:placetype":"locality"
},
  "geometry": {"coordinates":[59.44675,26.4436],"type":"Point"}
}