{
  "type": "Feature",
  "properties": {
    "gn:admin1_code":"35",
    "gn:asciiname":"`Aliabad",
    "gn:country_code":"IR",
    "gn:dem":-20,
    "gn:feature_class":"P",
    "gn:feature_code":"PPL",
    "gn:name":"\u2018Al\u012b\u0101b\u0101d",
    "gn:population":0,
    "gn:timezone":"Asia/Tehran",
    "iso:country":"IR",
    "name:fas_x_preferred":[
        "\u0639\u064e\u0644\u064a\u0627\u0628\u0627\u062f\u0650 \u0628\u0627\u0644\u0627"
    ],
    "name:fas_x_variant":[
        "\u2018Al\u012b\u0101b\u0101d-e B\u0101l\u0101",
        "\u2018Al\u012b\u0101b\u0101d",
        "\u0639\u0644\u06cc \u0622\u0628\u0627\u062f"
    ],
    "wof:name":"`Aliabad",
    "wof:placetype":"locality"
},
  "geometry": {"coordinates":[52.644,36.6727],"type":"Point"}
}