{
  "type": "Feature",
  "properties": {
    "gn:admin1_code":"42.0",
    "gn:asciiname":"Kalateh-ye `Abd os Samad",
    "gn:country_code":"IR",
    "gn:dem":778,
    "gn:feature_class":"P",
    "gn:feature_code":"PPL",
    "gn:name":"Kal\u0101teh-ye \u2018Abd o\u015f \u015eamad",
    "gn:population":0,
    "gn:timezone":"Asia/Tehran",
    "iso:country":"IR",
    "name:fas_x_preferred":[
        "\u06a9\u0644\u0627\u062a\u0647 \u0639\u0628\u062f \u0627\u0644\u0635\u0645\u062f"
    ],
    "name:fas_x_variant":[
        "Kal\u0101teh-ye \u2018Abd o\u015f \u015eamad"
    ],
    "name:und_x_variant":[
        "\u1e28\u0101jj\u012b\u0101b\u0101d Moll\u0101 Q\u0101sem"
    ],
    "wof:name":"Kalateh-ye `Abd os Samad",
    "wof:placetype":"locality"
},
  "geometry": {"coordinates":[60.92947,35.0593],"type":"Point"}
}