{
  "type": "Feature",
  "properties": {
    "gn:admin1_code":"13",
    "gn:asciiname":"`Aliabad-e Dovvom",
    "gn:country_code":"IR",
    "gn:dem":1455,
    "gn:feature_class":"P",
    "gn:feature_code":"PPL",
    "gn:name":"\u2018Al\u012b\u0101b\u0101d-e Dovvom",
    "gn:population":0,
    "gn:timezone":"Asia/Tehran",
    "iso:country":"IR",
    "name:fas_x_preferred":[
        "\u2018Al\u012b\u0101b\u0101d-e Dovvom"
    ],
    "name:fas_x_variant":[
        "\u0639\u0644\u06cc \u0622\u0628\u0627\u062f \u062f\u0648\u0645",
        "\u2018Al\u012b\u0101b\u0101d-e Sofl\u00e1"
    ],
    "wof:name":"`Aliabad-e Dovvom",
    "wof:placetype":"locality"
},
  "geometry": {"coordinates":[48.01397,34.48045],"type":"Point"}
}