{
  "type": "Feature",
  "properties": {
    "gn:admin1_code":"35",
    "gn:asciiname":"Gornam",
    "gn:country_code":"IR",
    "gn:dem":1373,
    "gn:feature_class":"P",
    "gn:feature_code":"PPL",
    "gn:name":"Gorn\u0101m",
    "gn:population":0,
    "gn:timezone":"Asia/Tehran",
    "iso:country":"IR",
    "name:ara_x_preferred":[
        "\u063a\u0631\u0646\u0627\u0645"
    ],
    "name:ceb_x_preferred":[
        "Gorn\u0101m"
    ],
    "name:fas_x_preferred":[
        "Gorn\u0101m"
    ],
    "name:fas_x_variant":[
        "\u06af\u0631\u0646\u0627\u0645"
    ],
    "name:swe_x_preferred":[
        "Gorn\u0101m"
    ],
    "name:und_x_variant":[
        "\u06af\u0631\u0646\u0627\u0645"
    ],
    "wof:name":"Gornam",
    "wof:placetype":"locality"
},
  "geometry": {"coordinates":[53.79341,36.57518],"type":"Point"}
}