{
  "type": "Feature",
  "properties": {
    "gn:admin1_code":"34",
    "gn:asciiname":"Kasr-e Asef",
    "gn:country_code":"IR",
    "gn:dem":1630,
    "gn:feature_class":"P",
    "gn:feature_code":"PPL",
    "gn:name":"Kasr-e \u0100\u015fef",
    "gn:population":0,
    "gn:timezone":"Asia/Tehran",
    "iso:country":"IR",
    "name:ceb_x_preferred":[
        "Kasr-e \u0100\u015fef"
    ],
    "name:fas_x_preferred":[
        "Kasr-e \u0100\u015fef"
    ],
    "name:fas_x_variant":[
        "Ka\u015fr-e \u0100\u015fef",
        "\u06a9\u0633\u0631 \u0622\u0635\u0641"
    ],
    "name:swe_x_preferred":[
        "Kasr-e \u0100\u015fef"
    ],
    "name:ukr_x_preferred":[
        "\u041a\u0430\u0441\u0440-\u0435 \u0410\u0441\u0435\u0444"
    ],
    "name:und_x_variant":[
        "Ka\u015fr \u0100\u015fef",
        "Kh\u0101sr\u0101s",
        "Kasr\u0101set",
        "\u06a9\u0633\u0631 \u0622\u0635\u0641"
    ],
    "wof:name":"Kasr-e Asef",
    "wof:placetype":"locality"
},
  "geometry": {"coordinates":[49.55434,34.84097],"type":"Point"}
}