{
  "type": "Feature",
  "properties": {
    "gn:admin1_code":"15",
    "gn:asciiname":"Sho`eybeh",
    "gn:country_code":"IR",
    "gn:dem":31,
    "gn:feature_class":"P",
    "gn:feature_code":"PPL",
    "gn:name":"Sho\u2018eybeh",
    "gn:population":0,
    "gn:timezone":"Asia/Tehran",
    "iso:country":"IR",
    "name:fas_x_preferred":[
        "Sho\u2018eybeh"
    ],
    "wof:name":"Sho`eybeh",
    "wof:placetype":"locality"
},
  "geometry": {"coordinates":[48.79306,31.82333],"type":"Point"}
}