{
  "type": "Feature",
  "properties": {
    "gn:admin1_code":"1.0",
    "gn:asciiname":"Sadr od Din",
    "gn:country_code":"IR",
    "gn:dem":1770,
    "gn:feature_class":"P",
    "gn:feature_code":"PPL",
    "gn:name":"\u015eadr od D\u012bn",
    "gn:population":0,
    "gn:timezone":"Asia/Tehran",
    "iso:country":"IR",
    "name:fas_x_preferred":[
        "\u0635\u062f\u0631\u0627\u0644\u062f\u06cc\u0646"
    ],
    "name:fas_x_variant":[
        "\u015eadr od D\u012bn"
    ],
    "wof:name":"Sadr od Din",
    "wof:placetype":"locality"
},
  "geometry": {"coordinates":[44.3775,39.1196],"type":"Point"}
}