{
  "type": "Feature",
  "properties": {
    "gn:admin1_code":"7.0",
    "gn:asciiname":"Nowbonyad",
    "gn:country_code":"IR",
    "gn:dem":1482,
    "gn:feature_class":"P",
    "gn:feature_code":"PPL",
    "gn:name":"Nowbony\u0101d",
    "gn:population":0,
    "gn:timezone":"Asia/Tehran",
    "iso:country":"IR",
    "name:fas_x_preferred":[
        "Nowbony\u0101d"
    ],
    "wof:name":"Nowbonyad",
    "wof:placetype":"locality"
},
  "geometry": {"coordinates":[52.56778000000001,29.01278],"type":"Point"}
}