{
  "type": "Feature",
  "properties": {
    "gn:admin1_code":"8",
    "gn:asciiname":"Chehel Mardan",
    "gn:country_code":"IR",
    "gn:dem":-16,
    "gn:feature_class":"P",
    "gn:feature_code":"PPL",
    "gn:name":"Chehel Mard\u0101n",
    "gn:population":0,
    "gn:timezone":"Asia/Tehran",
    "iso:country":"IR",
    "name:fas_x_preferred":[
        "Chehel Mard\u0101n"
    ],
    "name:fas_x_variant":[
        "\u0686\u0647\u0644 \u0645\u0631\u062f\u0627\u0646"
    ],
    "name:und_x_variant":[
        "\u0686\u0647\u0644 \u0645\u0631\u062f\u0627\u0646"
    ],
    "wof:name":"Chehel Mardan",
    "wof:placetype":"locality"
},
  "geometry": {"coordinates":[49.52045,37.31743],"type":"Point"}
}