{
  "type": "Feature",
  "properties": {
    "gn:admin1_code":"42",
    "gn:asciiname":"Khvajehabad",
    "gn:country_code":"IR",
    "gn:dem":1572,
    "gn:feature_class":"P",
    "gn:feature_code":"PPL",
    "gn:name":"Khv\u0101jeh\u0101b\u0101d",
    "gn:population":0,
    "gn:timezone":"Asia/Tehran",
    "iso:country":"IR",
    "name:fas_x_preferred":[
        "Khv\u0101jeh\u0101b\u0101d"
    ],
    "name:fas_x_variant":[
        "Khajeh \u0100b\u0101d",
        "\u062e\u0648\u0627\u062c\u0647 \u0622\u0628\u0627\u062f"
    ],
    "wof:name":"Khvajehabad",
    "wof:placetype":"locality"
},
  "geometry": {"coordinates":[58.36064,36.79307],"type":"Point"}
}