{
  "type": "Feature",
  "properties": {
    "gn:admin1_code":"29",
    "gn:asciiname":"Esfena`",
    "gn:country_code":"IR",
    "gn:dem":2550,
    "gn:feature_class":"P",
    "gn:feature_code":"PPL",
    "gn:name":"Esfen\u0101\u2018",
    "gn:population":0,
    "gn:timezone":"Asia/Tehran",
    "iso:country":"IR",
    "name:fas_x_preferred":[
        "Esfen\u0101\u2018"
    ],
    "name:fas_x_variant":[
        "Esfen\u0101",
        "\u0627\u0633\u0641\u0646\u0627\u0621",
        "\u0627\u0633\u0641\u0646\u0627 \u0633\u0641\u0644\u06cc"
    ],
    "name:und_x_variant":[
        "Esfen\u0101-ye Sofl\u00e1"
    ],
    "wof:name":"Esfena`",
    "wof:placetype":"locality"
},
  "geometry": {"coordinates":[57.10121,29.3621],"type":"Point"}
}