{
  "type": "Feature",
  "properties": {
    "gn:admin1_code":"29",
    "gn:asciiname":"Dimchu",
    "gn:country_code":"IR",
    "gn:dem":2181,
    "gn:feature_class":"P",
    "gn:feature_code":"PPL",
    "gn:name":"D\u012bmch\u016b",
    "gn:population":0,
    "gn:timezone":"Asia/Tehran",
    "iso:country":"IR",
    "name:fas_x_preferred":[
        "\u062f\u06cc\u0645\u0686\u0648"
    ],
    "name:fas_x_variant":[
        "D\u012bmch\u016b"
    ],
    "wof:name":"Dimchu",
    "wof:placetype":"locality"
},
  "geometry": {"coordinates":[57.9077,29.0306],"type":"Point"}
}