{
  "type": "Feature",
  "properties": {
    "gn:admin1_code":"8",
    "gn:asciiname":"Khalu Bagh",
    "gn:country_code":"IR",
    "gn:dem":-1,
    "gn:feature_class":"P",
    "gn:feature_code":"PPL",
    "gn:name":"Kh\u0101l\u016b B\u0101gh",
    "gn:population":0,
    "gn:timezone":"Asia/Tehran",
    "iso:country":"IR",
    "name:fas_x_preferred":[
        "Kh\u0101l\u016b B\u0101gh"
    ],
    "name:fas_x_variant":[
        "\u062c\u0627\u0644\u0648 \u0628\u0627\u063a",
        "\u062e\u0627\u0644\u0648\u0628\u0627\u063a"
    ],
    "name:glk_x_preferred":[
        "\u062e\u0627\u0644\u06ca\u0628\u0627\u063a"
    ],
    "name:msa_x_preferred":[
        "Khalu Bagh"
    ],
    "name:ukr_x_preferred":[
        "\u0425\u0430\u043b\u0443-\u0411\u0430\u0491"
    ],
    "wof:name":"Khalu Bagh",
    "wof:placetype":"locality"
},
  "geometry": {"coordinates":[49.98363,37.20651],"type":"Point"}
}