{
  "type": "Feature",
  "properties": {
    "gn:admin1_code":"42",
    "gn:asciiname":"Kalateh",
    "gn:country_code":"IR",
    "gn:dem":1131,
    "gn:feature_class":"P",
    "gn:feature_code":"PPL",
    "gn:name":"Kal\u0101teh",
    "gn:population":0,
    "gn:timezone":"Asia/Tehran",
    "iso:country":"IR",
    "name:fas_x_preferred":[
        "\u06a9\u0644\u0627\u062a\u0647"
    ],
    "name:fas_x_variant":[
        "Kal\u0101teh"
    ],
    "wof:name":"Kalateh",
    "wof:placetype":"locality"
},
  "geometry": {"coordinates":[58.16447,35.94773],"type":"Point"}
}