{
  "type": "Feature",
  "properties": {
    "gn:admin1_code":"9",
    "gn:asciiname":"Jera",
    "gn:country_code":"IR",
    "gn:dem":1810,
    "gn:feature_class":"P",
    "gn:feature_code":"PPL",
    "gn:name":"Jer\u0101",
    "gn:population":0,
    "gn:timezone":"Asia/Tehran",
    "iso:country":"IR",
    "name:fas_x_preferred":[
        "\u062c\u0631\u0627"
    ],
    "name:fas_x_variant":[
        "Jer\u0101"
    ],
    "wof:name":"Jera",
    "wof:placetype":"locality"
},
  "geometry": {"coordinates":[48.29492,34.4126],"type":"Point"}
}