{
  "type": "Feature",
  "properties": {
    "gn:admin1_code":"42.0",
    "gn:asciiname":"Tut-e Lashgaran",
    "gn:country_code":"IR",
    "gn:dem":1021,
    "gn:feature_class":"P",
    "gn:feature_code":"PPL",
    "gn:name":"T\u016bt-e Lashgar\u0101n",
    "gn:population":0,
    "gn:timezone":"Asia/Tehran",
    "iso:country":"IR",
    "name:fas_x_preferred":[
        "T\u016bt-e Lashgar\u0101n"
    ],
    "wof:name":"Tut-e Lashgaran",
    "wof:placetype":"locality"
},
  "geometry": {"coordinates":[61.11917,35.47806],"type":"Point"}
}