{
  "type": "Feature",
  "properties": {
    "gn:admin1_code":"10.0",
    "gn:asciiname":"Gol Gol-e `Olya",
    "gn:country_code":"IR",
    "gn:dem":793,
    "gn:feature_class":"P",
    "gn:feature_code":"PPL",
    "gn:name":"Gol Gol-e \u2018Oly\u0101",
    "gn:population":0,
    "gn:timezone":"Asia/Tehran",
    "iso:country":"IR",
    "name:fas_x_preferred":[
        "\u06af\u0644 \u06af\u0644 \u0639\u0644\u064a\u0627"
    ],
    "name:fas_x_variant":[
        "\u06af\u0644 \u06af\u0644 \u0628\u0627\u0644\u0627",
        "Gol Gol-e \u2018Oly\u0101",
        "Gol Gol-e B\u0101l\u0101",
        "\u0643\u064f\u0644 \u0643\u064f\u0644",
        "\u06af\u0644 \u06af\u0644"
    ],
    "name:und_x_variant":[
        "Gol Gol",
        "Kol Kol",
        "Gol Gol-e Sofl\u00e1"
    ],
    "wof:name":"Gol Gol-e `Olya",
    "wof:placetype":"locality"
},
  "geometry": {"coordinates":[47.63325,32.86893],"type":"Point"}
}