{
  "type": "Feature",
  "properties": {
    "gn:admin1_code":"16",
    "gn:asciiname":"Gerger-e Pa'in",
    "gn:country_code":"IR",
    "gn:dem":1933,
    "gn:feature_class":"P",
    "gn:feature_code":"PPL",
    "gn:name":"Gerger-e P\u0101\u2019\u012bn",
    "gn:population":0,
    "gn:timezone":"Asia/Tehran",
    "iso:country":"IR",
    "name:fas_x_preferred":[
        "Gerger-e P\u0101\u2019\u012bn"
    ],
    "name:und_x_variant":[
        "Gerger-e Sofl\u00e1",
        "Gerger Sofl\u00e1",
        "Gerger",
        "Girgir"
    ],
    "wof:name":"Gerger-e Pa'in",
    "wof:placetype":"locality"
},
  "geometry": {"coordinates":[47.28333,35.01667],"type":"Point"}
}