{
  "type": "Feature",
  "properties": {
    "gn:admin1_code":"15",
    "gn:asciiname":"Bahmanabad",
    "gn:country_code":"IR",
    "gn:dem":396,
    "gn:feature_class":"P",
    "gn:feature_code":"PPL",
    "gn:name":"Bahman\u0101b\u0101d",
    "gn:population":0,
    "gn:timezone":"Asia/Tehran",
    "iso:country":"IR",
    "name:aze_x_preferred":[
        "B\u0259hm\u0259nabad"
    ],
    "name:fas_x_preferred":[
        "\u0628\u0647\u0645\u0646 \u0622\u0628\u0627\u062f"
    ],
    "name:fas_x_variant":[
        "Bahman\u0101b\u0101d",
        "\u0628\u0647\u0645\u0646\u200c\u0622\u0628\u0627\u062f"
    ],
    "name:sco_x_preferred":[
        "Bahmanabad"
    ],
    "name:und_x_variant":[
        "Haj\u012b Bahman"
    ],
    "wof:name":"Bahmanabad",
    "wof:placetype":"locality"
},
  "geometry": {"coordinates":[50.2356,30.4971],"type":"Point"}
}