{
  "type": "Feature",
  "properties": {
    "gn:admin1_code":"7",
    "gn:asciiname":"Emamzadeh Bazm",
    "gn:country_code":"IR",
    "gn:dem":1991,
    "gn:feature_class":"P",
    "gn:feature_code":"PPL",
    "gn:name":"Em\u0101mz\u0101deh Bazm",
    "gn:population":0,
    "gn:timezone":"Asia/Tehran",
    "iso:country":"IR",
    "name:ara_x_preferred":[
        "\u0623\u0645\u0627\u0645\u0632\u0627\u062f\u0629 \u0628\u0632\u0645"
    ],
    "name:fas_x_preferred":[
        "\u0628\u0632\u0645"
    ],
    "name:fas_x_variant":[
        "\u0627\u0645\u0627\u0645\u0632\u0627\u062f\u0647 \u0628\u0632\u0645"
    ],
    "name:msa_x_preferred":[
        "Emamzadeh Bazm"
    ],
    "name:und_x_variant":[
        "B\u0101z",
        "Bazm",
        "Em\u0101mz\u0101deh Bazm"
    ],
    "wof:name":"Emamzadeh Bazm",
    "wof:placetype":"locality"
},
  "geometry": {"coordinates":[53.79867,30.37514],"type":"Point"}
}