{
  "type": "Feature",
  "properties": {
    "gn:admin1_code":"42",
    "gn:asciiname":"Soltan `Abdollah",
    "gn:country_code":"IR",
    "gn:dem":1207,
    "gn:feature_class":"P",
    "gn:feature_code":"PPL",
    "gn:name":"Sol\u0163\u0101n \u2018Abdoll\u0101h",
    "gn:population":0,
    "gn:timezone":"Asia/Tehran",
    "iso:country":"IR",
    "name:fas_x_preferred":[
        "\u0633\u0644\u0637\u0627\u0646 \u0639\u0628\u062f \ufdf2"
    ],
    "name:fas_x_variant":[
        "Sol\u0163\u0101n \u2018Abdoll\u0101h"
    ],
    "wof:name":"Soltan `Abdollah",
    "wof:placetype":"locality"
},
  "geometry": {"coordinates":[59.07604,35.99602],"type":"Point"}
}