{
  "type": "Feature",
  "properties": {
    "gn:admin1_code":"34",
    "gn:asciiname":"Dineh Kabud-e Bala",
    "gn:country_code":"IR",
    "gn:dem":2208,
    "gn:feature_class":"P",
    "gn:feature_code":"PPL",
    "gn:name":"D\u012bneh Kab\u016bd-e B\u0101l\u0101",
    "gn:population":0,
    "gn:timezone":"Asia/Tehran",
    "iso:country":"IR",
    "name:fas_x_preferred":[
        "\u062f\u064a\u0646\u0647 \u0643\u0628\u0648\u062f"
    ],
    "name:fas_x_variant":[
        "D\u012bneh Kab\u016bd",
        "D\u012bneh Kab\u016bd-e \u2018Oly\u0101",
        "\u062f\u064a\u0646\u0647 \u0643\u0628\u0648\u062f \u0639\u0644\u06cc\u0627",
        "\u062f\u06cc\u0646\u0647 \u06a9\u0628\u0648\u062f \u0628\u0627\u0644\u0627"
    ],
    "name:und_x_variant":[
        "\u062f\u064a\u0646\u0647 \u0643\u0628\u0648\u062f \u0639\u0644\u06cc\u0627",
        "D\u012bneh Kab\u016bd-e B\u0101l\u0101"
    ],
    "wof:name":"Dineh Kabud-e Bala",
    "wof:placetype":"locality"
},
  "geometry": {"coordinates":[49.74221,33.8709],"type":"Point"}
}