{
  "type": "Feature",
  "properties": {
    "gn:admin1_code":"4.0",
    "gn:asciiname":"Fahreh",
    "gn:country_code":"IR",
    "gn:dem":1096,
    "gn:feature_class":"P",
    "gn:feature_code":"PPL",
    "gn:name":"Fahreh",
    "gn:population":0,
    "gn:timezone":"Asia/Tehran",
    "iso:country":"IR",
    "name:fas_x_preferred":[
        "\u0641\u0647\u0631\u0647"
    ],
    "name:und_x_variant":[
        "P\u0101h\u016br\u0101",
        "Fah\u016br\u0101",
        "Fahreh"
    ],
    "wof:name":"Fahreh",
    "wof:placetype":"locality"
},
  "geometry": {"coordinates":[62.7749,27.3623],"type":"Point"}
}