{
  "type": "Feature",
  "properties": {
    "gn:admin1_code":"33",
    "gn:asciiname":"Khenavand",
    "gn:country_code":"IR",
    "gn:dem":1520,
    "gn:feature_class":"P",
    "gn:feature_code":"PPL",
    "gn:name":"Khen\u0101vand",
    "gn:population":0,
    "gn:timezone":"Asia/Tehran",
    "iso:country":"IR",
    "name:azb_x_preferred":[
        "\u062e\u0646\u0627\u0648\u0646\u062f"
    ],
    "name:fas_x_preferred":[
        "Khen\u0101vand"
    ],
    "name:fas_x_variant":[
        "\u062e\u0646\u0627\u0648\u0646\u062f"
    ],
    "name:msa_x_preferred":[
        "Khenavand"
    ],
    "wof:name":"Khenavand",
    "wof:placetype":"locality"
},
  "geometry": {"coordinates":[47.91667,37.75],"type":"Point"}
}