{
  "type": "Feature",
  "properties": {
    "gn:admin1_code":"44.0",
    "gn:asciiname":"Kuy-e Mehr",
    "gn:country_code":"IR",
    "gn:dem":1232,
    "gn:feature_class":"P",
    "gn:feature_code":"PPL",
    "gn:name":"K\u016by-e Mehr",
    "gn:population":0,
    "gn:timezone":"Asia/Tehran",
    "iso:country":"IR",
    "name:fas_x_preferred":[
        "\u06a9\u0648\u06cc \u0645\u0647\u0631"
    ],
    "name:fas_x_variant":[
        "K\u016by-e Mehr"
    ],
    "wof:name":"Kuy-e Mehr",
    "wof:placetype":"locality"
},
  "geometry": {"coordinates":[50.8773,35.7896],"type":"Point"}
}