{
  "type": "Feature",
  "properties": {
    "gn:admin1_code":"1.0",
    "gn:asciiname":"Serin Chaveh",
    "gn:country_code":"IR",
    "gn:dem":1434,
    "gn:elevation":"0.0",
    "gn:feature_class":"P",
    "gn:feature_code":"PPL",
    "gn:name":"Ser\u012bn Ch\u0101veh",
    "gn:population":0,
    "gn:timezone":"Asia/Tehran",
    "iso:country":"IR",
    "name:azb_x_preferred":[
        "\u0633\u0631\u06cc\u0646 \u0686\u0627\u0648\u0647"
    ],
    "name:aze_x_preferred":[
        "S\u0259rin\u00e7av\u0259"
    ],
    "name:ceb_x_preferred":[
        "Ser\u012bn Ch\u0101veh"
    ],
    "name:fas_x_preferred":[
        "\u0633\u0631\u06cc\u0646 \u0686\u0627\u0648\u0647"
    ],
    "name:fas_x_variant":[
        "Ser\u012bn Ch\u0101veh",
        "\u0633\u0631\u06cc\u0646\u200c\u0686\u0627\u0648\u0647"
    ],
    "name:msa_x_preferred":[
        "Serin Chaveh"
    ],
    "name:swe_x_preferred":[
        "Ser\u012bn Ch\u0101veh"
    ],
    "wof:name":"Serin Chaveh",
    "wof:placetype":"locality"
},
  "geometry": {"coordinates":[45.3044,36.7598],"type":"Point"}
}