{
  "type": "Feature",
  "properties": {
    "gn:admin1_code":"25",
    "gn:asciiname":"Alu'ak",
    "gn:country_code":"IR",
    "gn:dem":865,
    "gn:feature_class":"P",
    "gn:feature_code":"PPL",
    "gn:name":"\u0100l\u016b\u2019ak",
    "gn:population":0,
    "gn:timezone":"Asia/Tehran",
    "iso:country":"IR",
    "name:fas_x_preferred":[
        "\u0622\u0644\u0648\u0626\u06a9"
    ],
    "name:fas_x_variant":[
        "\u0100l\u016b\u2019ak"
    ],
    "wof:name":"Alu'ak",
    "wof:placetype":"locality"
},
  "geometry": {"coordinates":[52.46807,35.21395],"type":"Point"}
}