{
  "type": "Feature",
  "properties": {
    "gn:admin1_code":"36",
    "gn:asciiname":"Dash Altu",
    "gn:country_code":"IR",
    "gn:dem":1577,
    "gn:feature_class":"P",
    "gn:feature_code":"PPL",
    "gn:name":"D\u0101sh \u0100lt\u016b",
    "gn:population":0,
    "gn:timezone":"Asia/Tehran",
    "iso:country":"IR",
    "name:azb_x_preferred":[
        "\u062f\u0627\u0634\u0627\u0644\u062a\u0648"
    ],
    "name:fas_x_preferred":[
        "\u062f\u0627\u0634 \u0622\u0644\u062a\u06cc"
    ],
    "name:fas_x_variant":[
        "\u06af\u0648\u062c\u0647 \u0644\u0648\u062c\u0647",
        "D\u0101sh \u0100lt\u012b",
        "G\u016bjeh L\u016bgeh",
        "D\u0101sh\u0101lt\u016b",
        "D\u0101sh \u0100lt\u016b",
        "\u062f\u0627\u0634 \u0622\u0644\u062a\u0648",
        "\u06af\u0648\u062c\u0650\u0647 \u0644\u0648\u06af\u0650\u0647",
        "\u062f\u0627\u0634\u0627\u0644\u062a\u0648",
        "G\u016bjeh L\u016bjeh",
        "\u06af\u0648\u062c\u0647 \u0644\u0648"
    ],
    "name:und_x_variant":[
        "Gowjehl\u016b"
    ],
    "wof:name":"Dash Altu",
    "wof:placetype":"locality"
},
  "geometry": {"coordinates":[48.33255,35.98885999999999],"type":"Point"}
}