{
  "type": "Feature",
  "properties": {
    "gn:admin1_code":"35",
    "gn:asciiname":"Bargeh",
    "gn:country_code":"IR",
    "gn:dem":-18,
    "gn:feature_class":"P",
    "gn:feature_code":"PPL",
    "gn:name":"Bargeh",
    "gn:population":0,
    "gn:timezone":"Asia/Tehran",
    "iso:country":"IR",
    "name:fas_x_preferred":[
        "\u0628\u0631\u06af\u0647"
    ],
    "wof:name":"Bargeh",
    "wof:placetype":"locality"
},
  "geometry": {"coordinates":[53.21264,36.79984],"type":"Point"}
}