{
  "type": "Feature",
  "properties": {
    "gn:admin1_code":"3",
    "gn:asciiname":"Seyyed `Ali-ye Taheri",
    "gn:country_code":"IR",
    "gn:dem":2304,
    "gn:feature_class":"P",
    "gn:feature_code":"PPL",
    "gn:name":"Seyyed \u2018\u0100l\u012b-ye \u0162\u0101her\u012b",
    "gn:population":0,
    "gn:timezone":"Asia/Tehran",
    "iso:country":"IR",
    "name:fas_x_preferred":[
        "Seyyed \u2018\u0100l\u012b-ye \u0162\u0101her\u012b"
    ],
    "name:fas_x_variant":[
        "\u0633\u0650\u064a\u0650\u0651\u062f \u0639\u0627\u0644\u0626 \u0637\u0627\u0647\u0650\u0631\u06cc"
    ],
    "wof:name":"Seyyed `Ali-ye Taheri",
    "wof:placetype":"locality"
},
  "geometry": {"coordinates":[50.86444,31.91889],"type":"Point"}
}