{
  "type": "Feature",
  "properties": {
    "gn:admin1_code":"34",
    "gn:asciiname":"Kohneh Hesar",
    "gn:country_code":"IR",
    "gn:dem":2077,
    "gn:feature_class":"P",
    "gn:feature_code":"PPL",
    "gn:name":"Kohneh \u1e28e\u015f\u0101r",
    "gn:population":0,
    "gn:timezone":"Asia/Tehran",
    "iso:country":"IR",
    "name:fas_x_preferred":[
        "\u0643\u0647\u0646\u0647 \u062d\u0635\u0627\u0631"
    ],
    "name:fas_x_variant":[
        "Kohneh \u1e28e\u015f\u0101r"
    ],
    "wof:name":"Kohneh Hesar",
    "wof:placetype":"locality"
},
  "geometry": {"coordinates":[49.25568,33.67354],"type":"Point"}
}