{
  "type": "Feature",
  "properties": {
    "gn:admin1_code":"16.0",
    "gn:asciiname":"Kani Bard",
    "gn:country_code":"IR",
    "gn:dem":1407,
    "gn:feature_class":"P",
    "gn:feature_code":"PPL",
    "gn:name":"K\u0101n\u012b Bard",
    "gn:population":0,
    "gn:timezone":"Asia/Tehran",
    "iso:country":"IR",
    "name:ara_x_preferred":[
        "\u06a9\u0627\u0646\u064a \u0628\u0631\u062f"
    ],
    "name:ceb_x_preferred":[
        "K\u0101n\u012b Bard"
    ],
    "name:ckb_x_preferred":[
        "\u06a9\u0627\u0646\u06cc \u0628\u06d5\u0631\u062f"
    ],
    "name:fas_x_preferred":[
        "\u06a9\u0627\u0646\u06cc \u0628\u0631\u062f"
    ],
    "name:fas_x_variant":[
        "K\u0101n\u012b Bard"
    ],
    "name:swe_x_preferred":[
        "K\u0101n\u012b Bard"
    ],
    "wof:name":"Kani Bard",
    "wof:placetype":"locality"
},
  "geometry": {"coordinates":[45.6428,36.0614],"type":"Point"}
}