{
  "type": "Feature",
  "properties": {
    "gn:admin1_code":"1",
    "gn:asciiname":"Mazanabad",
    "gn:country_code":"IR",
    "gn:dem":1078,
    "gn:feature_class":"P",
    "gn:feature_code":"PPL",
    "gn:name":"Mazan\u0101b\u0101d",
    "gn:population":0,
    "gn:timezone":"Asia/Tehran",
    "iso:country":"IR",
    "name:fas_x_preferred":[
        "\u0645\u0632\u0646 \u0622\u0628\u0627\u062f"
    ],
    "name:fas_x_variant":[
        "Mazan\u0101b\u0101d"
    ],
    "wof:name":"Mazanabad",
    "wof:placetype":"locality"
},
  "geometry": {"coordinates":[45.3902,36.0141],"type":"Point"}
}