{
  "type": "Feature",
  "properties": {
    "gn:admin1_code":"5",
    "gn:asciiname":"Lir-e Bozorg",
    "gn:country_code":"IR",
    "gn:dem":873,
    "gn:feature_class":"P",
    "gn:feature_code":"PPL",
    "gn:name":"L\u012br-e Bozorg",
    "gn:population":0,
    "gn:timezone":"Asia/Tehran",
    "iso:country":"IR",
    "name:ceb_x_preferred":[
        "L\u012br-e Bozorg"
    ],
    "name:fas_x_preferred":[
        "\u0644\u064a\u0631 \u0628\u0632\u0631\u06af"
    ],
    "name:fas_x_variant":[
        "L\u012br-e Bozorg",
        "\u0644\u06cc\u0631\u0628\u0632\u0631\u06af"
    ],
    "name:swe_x_preferred":[
        "L\u012br-e Bozorg"
    ],
    "wof:name":"Lir-e Bozorg",
    "wof:placetype":"locality"
},
  "geometry": {"coordinates":[50.4437,30.8956],"type":"Point"}
}