{
  "type": "Feature",
  "properties": {
    "gn:admin1_code":"29.0",
    "gn:asciiname":"`Anbarabad",
    "gn:country_code":"IR",
    "gn:dem":603,
    "gn:feature_class":"P",
    "gn:feature_code":"PPLA2",
    "gn:name":"\u2018Anbar\u0101b\u0101d",
    "gn:population":0,
    "gn:timezone":"Asia/Tehran",
    "iso:country":"IR",
    "name:fas_x_preferred":[
        "\u0639\u0646\u0628\u0631 \u0622\u0628\u0627\u062f"
    ],
    "name:fas_x_variant":[
        "\u2018Anbar\u0101b\u0101d"
    ],
    "name:und_x_variant":[
        "Amb\u0101r\u0101b\u0101d"
    ],
    "wof:name":"`Anbarabad",
    "wof:placetype":"locality"
},
  "geometry": {"coordinates":[57.848,28.4759],"type":"Point"}
}