{
  "type": "Feature",
  "properties": {
    "gn:admin1_code":"25",
    "gn:asciiname":"Barmadabad",
    "gn:country_code":"IR",
    "gn:dem":872,
    "gn:feature_class":"P",
    "gn:feature_code":"PPL",
    "gn:name":"Barm\u0101d\u0101b\u0101d",
    "gn:population":0,
    "gn:timezone":"Asia/Tehran",
    "iso:country":"IR",
    "name:fas_x_preferred":[
        "\u0628\u064e\u0631\u0645\u0627\u062f \u0622\u0628\u0627\u062f"
    ],
    "name:fas_x_variant":[
        "Barm\u0101d\u0101b\u0101d"
    ],
    "wof:name":"Barmadabad",
    "wof:placetype":"locality"
},
  "geometry": {"coordinates":[52.45,35.21667],"type":"Point"}
}