{
  "type": "Feature",
  "properties": {
    "gn:admin1_code":"40.0",
    "gn:asciiname":"Margh-e Mian",
    "gn:country_code":"IR",
    "gn:dem":1792,
    "gn:feature_class":"P",
    "gn:feature_code":"PPL",
    "gn:name":"Margh-e M\u012b\u0101n",
    "gn:population":0,
    "gn:timezone":"Asia/Tehran",
    "iso:country":"IR",
    "name:fas_x_preferred":[
        "\u0645\u0631\u063a \u0645\u064a\u0627\u0646"
    ],
    "name:fas_x_variant":[
        "\u0645\u064e\u0631\u06af\u0650\u0647 \u0645\u0650\u064a\u0627\u0646",
        "Margh-e M\u012b\u0101n"
    ],
    "name:und_x_variant":[
        "Margeh Mey\u0101n"
    ],
    "wof:name":"Margh-e Mian",
    "wof:placetype":"locality"
},
  "geometry": {"coordinates":[53.6274,32.3024],"type":"Point"}
}