{
  "type": "Feature",
  "properties": {
    "gn:admin1_code":"15",
    "gn:asciiname":"Darreh Gazu",
    "gn:cc2":"IR",
    "gn:country_code":"IR",
    "gn:dem":924,
    "gn:feature_class":"P",
    "gn:feature_code":"PPL",
    "gn:name":"Darreh Gaz\u016b",
    "gn:population":0,
    "gn:timezone":"Asia/Tehran",
    "iso:country":"IR",
    "name:fas_x_preferred":[
        "Darreh Gaz\u016b"
    ],
    "name:und_x_variant":[
        "Darreh-ye Gaz\u016b"
    ],
    "wof:name":"Darreh Gazu",
    "wof:placetype":"locality"
},
  "geometry": {"coordinates":[50.21194000000001,31.6525],"type":"Point"}
}