{
  "type": "Feature",
  "properties": {
    "gn:admin1_code":"35.0",
    "gn:asciiname":"Dehkalan",
    "gn:country_code":"IR",
    "gn:dem":383,
    "gn:feature_class":"P",
    "gn:feature_code":"PPL",
    "gn:name":"Dehkalan",
    "gn:population":0,
    "gn:timezone":"Asia/Tehran",
    "iso:country":"IR",
    "name:und_x_variant":[
        "Div Kalan"
    ],
    "wof:name":"Dehkalan",
    "wof:placetype":"locality"
},
  "geometry": {"coordinates":[52.80222,36.24778],"type":"Point"}
}