{
  "type": "Feature",
  "properties": {
    "gn:admin1_code":"1",
    "gn:asciiname":"Minas",
    "gn:country_code":"IR",
    "gn:dem":1314,
    "gn:feature_class":"P",
    "gn:feature_code":"PPL",
    "gn:name":"M\u012bn\u0101s",
    "gn:population":0,
    "gn:timezone":"Asia/Tehran",
    "iso:country":"IR",
    "name:ceb_x_preferred":[
        "Minas"
    ],
    "name:deu_x_preferred":[
        "Minas"
    ],
    "name:fas_x_preferred":[
        "\u0645\u06cc\u0646\u0627\u0633"
    ],
    "name:fas_x_variant":[
        "M\u012bn\u0101s"
    ],
    "name:fra_x_preferred":[
        "Minas"
    ],
    "name:hye_x_preferred":[
        "\u0544\u056b\u0576\u0561\u057d"
    ],
    "name:nld_x_preferred":[
        "Minas"
    ],
    "name:por_x_preferred":[
        "Minas"
    ],
    "name:rus_x_preferred":[
        "\u041c\u0438\u043d\u0430\u0441"
    ],
    "name:sco_x_preferred":[
        "Minas"
    ],
    "name:srp_x_preferred":[
        "\u041c\u0438\u043d\u0430\u0441"
    ],
    "name:swe_x_preferred":[
        "Minas"
    ],
    "name:ukr_x_preferred":[
        "\u041c\u0456\u043d\u0430\u0441"
    ],
    "wof:name":"Minas",
    "wof:placetype":"locality"
},
  "geometry": {"coordinates":[44.9047,38.1593],"type":"Point"}
}