{
  "type": "Feature",
  "properties": {
    "gn:admin1_code":"1",
    "gn:asciiname":"Minas",
    "gn:country_code":"IR",
    "gn:dem":1314,
    "gn:feature_class":"P",
    "gn:feature_code":"PPL",
    "gn:name":"M\u012bn\u0101s",
    "gn:population":0,
    "gn:timezone":"Asia/Tehran",
    "iso:country":"IR",
    "name:fas_x_preferred":[
        "\u0645\u06cc\u0646\u0627\u0633"
    ],
    "name:fas_x_variant":[
        "M\u012bn\u0101s"
    ],
    "wof:name":"Minas",
    "wof:placetype":"locality"
},
  "geometry": {"coordinates":[44.9047,38.1593],"type":"Point"}
}