{
  "type": "Feature",
  "properties": {
    "gn:admin1_code":"29.0",
    "gn:asciiname":"Asadabad-e Bala",
    "gn:country_code":"IR",
    "gn:dem":1535,
    "gn:feature_class":"P",
    "gn:feature_code":"PPL",
    "gn:name":"Asad\u0101b\u0101d-e B\u0101l\u0101",
    "gn:population":0,
    "gn:timezone":"Asia/Tehran",
    "iso:country":"IR",
    "name:fas_x_preferred":[
        "\u0627\u0633\u062f\u0622\u0628\u0627\u062f \u0628\u0627\u0644\u0627"
    ],
    "name:und_x_variant":[
        "Asad\u0101b\u0101d-e B\u0101l\u0101"
    ],
    "wof:name":"Asadabad-e Bala",
    "wof:placetype":"locality"
},
  "geometry": {"coordinates":[55.98899,30.37479],"type":"Point"}
}