{
  "type": "Feature",
  "properties": {
    "gn:admin1_code":"42",
    "gn:asciiname":"Khalilabad",
    "gn:country_code":"IR",
    "gn:dem":1015,
    "gn:feature_class":"P",
    "gn:feature_code":"PPL",
    "gn:name":"Khal\u012bl\u0101b\u0101d",
    "gn:population":0,
    "gn:timezone":"Asia/Tehran",
    "iso:country":"IR",
    "name:fas_x_preferred":[
        "\u062e\u0644\u06cc\u0644 \u0622\u0628\u0627\u062f"
    ],
    "name:fas_x_variant":[
        "Khal\u012bl\u0101b\u0101d"
    ],
    "wof:name":"Khalilabad",
    "wof:placetype":"locality"
},
  "geometry": {"coordinates":[59.85052,34.79075],"type":"Point"}
}