{
  "type": "Feature",
  "properties": {
    "gn:admin1_code":"25",
    "gn:asciiname":"Kolamu",
    "gn:country_code":"IR",
    "gn:dem":1419,
    "gn:feature_class":"P",
    "gn:feature_code":"PPL",
    "gn:name":"Kol\u0101m\u016b",
    "gn:population":0,
    "gn:timezone":"Asia/Tehran",
    "iso:country":"IR",
    "name:ceb_x_preferred":[
        "Kol\u0101m\u016b"
    ],
    "name:fas_x_preferred":[
        "Kol\u0101m\u016b"
    ],
    "name:fas_x_variant":[
        "\u0643\u0644\u0627\u0645\u0648",
        "\u06a9\u0644\u0627\u0645\u0648"
    ],
    "name:swe_x_preferred":[
        "Kol\u0101m\u016b"
    ],
    "name:und_x_variant":[
        "\u0643\u0644\u0627\u0645\u0648"
    ],
    "wof:name":"Kolamu",
    "wof:placetype":"locality"
},
  "geometry": {"coordinates":[55.06274000000001,36.60368],"type":"Point"}
}