{
  "type": "Feature",
  "properties": {
    "gn:admin1_code":"26",
    "gn:asciiname":"Shahrak-e Enqelab",
    "gn:country_code":"IR",
    "gn:dem":1053,
    "gn:feature_class":"P",
    "gn:feature_code":"PPL",
    "gn:name":"Shahrak-e Enqel\u0101b",
    "gn:population":0,
    "gn:timezone":"Asia/Tehran",
    "iso:country":"IR",
    "name:fas_x_preferred":[
        "\u0634\u0647\u0631\u06a9 \u0627\u0646\u0642\u0644\u0627\u0628"
    ],
    "name:fas_x_variant":[
        "Shahrak-e Enqel\u0101b"
    ],
    "wof:name":"Shahrak-e Enqelab",
    "wof:placetype":"locality"
},
  "geometry": {"coordinates":[51.6867,35.5156],"type":"Point"}
}