{
  "type": "Feature",
  "properties": {
    "gn:admin1_code":"11",
    "gn:asciiname":"Pi Bashk",
    "gn:country_code":"IR",
    "gn:dem":20,
    "gn:feature_class":"P",
    "gn:feature_code":"PPL",
    "gn:name":"P\u012b Bashk",
    "gn:population":0,
    "gn:timezone":"Asia/Tehran",
    "iso:country":"IR",
    "name:fas_x_preferred":[
        "\u067e\u064a \u0648\u0634\u0643"
    ],
    "name:fas_x_variant":[
        "P\u012b Bashk",
        "\u067e\u06cc \u0628\u0634\u0643",
        "\u067e\u06cc \u0648\u0634\u06a9"
    ],
    "name:msa_x_preferred":[
        "Piveshk"
    ],
    "name:und_x_variant":[
        "Bey\u0101sak",
        "Pey Beshk",
        "B\u012b\u0101sk",
        "P\u012b Vashk",
        "Bey Beshk",
        "Pvishk",
        "B\u012b\u0101sak"
    ],
    "wof:name":"Pi Bashk",
    "wof:placetype":"locality"
},
  "geometry": {"coordinates":[58.91639,25.555],"type":"Point"}
}