{
  "type": "Feature",
  "properties": {
    "gn:admin1_code":"13",
    "gn:asciiname":"Sarab-e Nilufar",
    "gn:country_code":"IR",
    "gn:dem":1323,
    "gn:feature_class":"P",
    "gn:feature_code":"PPL",
    "gn:name":"Sar\u0101b-e N\u012bl\u016bfar",
    "gn:population":0,
    "gn:timezone":"Asia/Tehran",
    "iso:country":"IR",
    "name:ceb_x_preferred":[
        "Sar\u0101b-e N\u012bl\u016bfar"
    ],
    "name:fas_x_preferred":[
        "\u0633\u0631\u0627\u0628 \u0646\u06cc\u0644\u0648\u0641\u0631"
    ],
    "name:fas_x_variant":[
        "Sar\u0101b-e N\u012bl\u016bfar",
        "\u0633\u0631\u0622\u0628 \u0646\u06cc\u0644\u0648\u0641\u0631"
    ],
    "name:swe_x_preferred":[
        "Sar\u0101b-e N\u012bl\u016bfar"
    ],
    "name:und_x_variant":[
        "Sar\u0101b N\u012bl\u016bfar"
    ],
    "wof:name":"Sarab-e Nilufar",
    "wof:placetype":"locality"
},
  "geometry": {"coordinates":[46.8574,34.4048],"type":"Point"}
}