{
  "type": "Feature",
  "properties": {
    "gn:admin1_code":"23",
    "gn:asciiname":"`Ayvali",
    "gn:country_code":"IR",
    "gn:dem":1964,
    "gn:feature_class":"P",
    "gn:feature_code":"PPL",
    "gn:name":"\u2018Ayval\u012b",
    "gn:population":0,
    "gn:timezone":"Asia/Tehran",
    "iso:country":"IR",
    "name:fas_x_preferred":[
        "\u2018Ayval\u012b"
    ],
    "name:und_x_variant":[
        "\u2018Eyvall\u012b",
        "Eyv\u2018al\u012b"
    ],
    "wof:name":"`Ayvali",
    "wof:placetype":"locality"
},
  "geometry": {"coordinates":[48.19972,34.02778],"type":"Point"}
}