{
  "type": "Feature",
  "properties": {
    "gn:admin1_code":"41.0",
    "gn:asciiname":"Rud Band",
    "gn:country_code":"IR",
    "gn:dem":740,
    "gn:feature_class":"P",
    "gn:feature_code":"PPL",
    "gn:name":"R\u016bd Band",
    "gn:population":0,
    "gn:timezone":"Asia/Tehran",
    "iso:country":"IR",
    "name:fas_x_preferred":[
        "R\u016bd Band"
    ],
    "wof:name":"Rud Band",
    "wof:placetype":"locality"
},
  "geometry": {"coordinates":[60.71833,31.39806],"type":"Point"}
}