{
  "type": "Feature",
  "properties": {
    "gn:admin1_code":"11",
    "gn:asciiname":"Kashduz",
    "gn:country_code":"IR",
    "gn:dem":433,
    "gn:feature_class":"P",
    "gn:feature_code":"PPL",
    "gn:name":"Kashd\u016bz",
    "gn:population":0,
    "gn:timezone":"Asia/Tehran",
    "iso:country":"IR",
    "name:fas_x_preferred":[
        "\u0643\u064e\u0634\u062f\u0648\u0632"
    ],
    "name:fas_x_variant":[
        "Kashd\u016bz"
    ],
    "wof:name":"Kashduz",
    "wof:placetype":"locality"
},
  "geometry": {"coordinates":[58.55,26.26667],"type":"Point"}
}