{
  "type": "Feature",
  "properties": {
    "gn:admin1_code":"7",
    "gn:asciiname":"Sheykh",
    "gn:country_code":"IR",
    "gn:dem":893,
    "gn:feature_class":"P",
    "gn:feature_code":"PPL",
    "gn:name":"Sheykh",
    "gn:population":0,
    "gn:timezone":"Asia/Tehran",
    "iso:country":"IR",
    "wof:name":"Sheykh",
    "wof:placetype":"locality"
},
  "geometry": {"coordinates":[52.03333,29.26667],"type":"Point"}
}