{
  "type": "Feature",
  "properties": {
    "gn:admin1_code":"1",
    "gn:asciiname":"Darah Zam",
    "gn:country_code":"IR",
    "gn:dem":1394,
    "gn:feature_class":"P",
    "gn:feature_code":"PPL",
    "gn:name":"Darah Zam",
    "gn:population":0,
    "gn:timezone":"Asia/Tehran",
    "iso:country":"IR",
    "name:fas_x_preferred":[
        "\u062f\u064e\u0631\u064e\u0632\u064e\u0645"
    ],
    "name:fas_x_variant":[
        "\u062f\u0631\u0647 \u0632\u0645"
    ],
    "name:und_x_variant":[
        "Darazam",
        "Darah Zam"
    ],
    "wof:name":"Darah Zam",
    "wof:placetype":"locality"
},
  "geometry": {"coordinates":[44.9839,37.6192],"type":"Point"}
}