{
  "type": "Feature",
  "properties": {
    "gn:admin1_code":"7",
    "gn:asciiname":"Yanderanlu",
    "gn:country_code":"IR",
    "gn:dem":652,
    "gn:feature_class":"P",
    "gn:feature_code":"PPL",
    "gn:name":"Y\u0101nder\u0101nl\u016b",
    "gn:population":0,
    "gn:timezone":"Asia/Tehran",
    "iso:country":"IR",
    "name:fas_x_preferred":[
        "Y\u0101nder\u0101nl\u016b"
    ],
    "name:fas_x_variant":[
        "\u06cc\u0627\u0646\u062f\u0631\u0627\u0646\u0644\u0648"
    ],
    "name:msa_x_preferred":[
        "Yanderanlu"
    ],
    "name:urd_x_preferred":[
        "\u06cc\u0646\u062f\u0631\u0627\u0646\u0644\u0648"
    ],
    "wof:name":"Yanderanlu",
    "wof:placetype":"locality"
},
  "geometry": {"coordinates":[51.795,29.40083],"type":"Point"}
}