{
  "type": "Feature",
  "properties": {
    "gn:admin1_code":"4.0",
    "gn:asciiname":"Abgurandan",
    "gn:country_code":"IR",
    "gn:dem":1459,
    "gn:feature_class":"P",
    "gn:feature_code":"PPL",
    "gn:name":"\u0100bg\u016br\u0101nd\u0101n",
    "gn:population":0,
    "gn:timezone":"Asia/Tehran",
    "iso:country":"IR",
    "name:fas_x_preferred":[
        "\u0622\u0628\u06af\u0648\u0631\u0627\u0646 \u062f\u0627\u0646"
    ],
    "name:fas_x_variant":[
        "\u0100b Char\u012b\u0101n",
        "\u0100bg\u016br\u0101nd\u0101n",
        "L\u0101g\u016b-ye Char\u012b\u0101n",
        "\u0622\u0628 \u06af\u0648\u0631\u0627\u0646\u062f\u0627\u0646"
    ],
    "name:und_x_variant":[
        "L\u0101g\u016b-ye Char\u012b\u0101n"
    ],
    "wof:name":"Abgurandan",
    "wof:placetype":"locality"
},
  "geometry": {"coordinates":[61.18297,26.96179],"type":"Point"}
}