{
  "type": "Feature",
  "properties": {
    "gn:admin1_code":"13",
    "gn:asciiname":"Dastjerd-e Sofla",
    "gn:country_code":"IR",
    "gn:dem":1430,
    "gn:feature_class":"P",
    "gn:feature_code":"PPL",
    "gn:name":"Dastjerd-e Sofl\u00e1",
    "gn:population":0,
    "gn:timezone":"Asia/Tehran",
    "iso:country":"IR",
    "name:ceb_x_preferred":[
        "Dastjerd-e Sofl\u00e1"
    ],
    "name:fas_x_preferred":[
        "\u062f\u0633\u062a\u062c\u0631\u062f \u0633\u0641\u0644\u06cc"
    ],
    "name:fas_x_variant":[
        "Dastjordeh-ye Sofl\u00e1",
        "Dastjerd-e Sofl\u00e1",
        "\u062f\u0633\u062a\u062c\u0631\u062f\u0647 \u0633\u0641\u0644\u06cc"
    ],
    "name:swe_x_preferred":[
        "Dastjerd-e Sofl\u00e1"
    ],
    "wof:name":"Dastjerd-e Sofla",
    "wof:placetype":"locality"
},
  "geometry": {"coordinates":[47.55102,34.57835],"type":"Point"}
}