{
  "type": "Feature",
  "properties": {
    "gn:admin1_code":"4",
    "gn:asciiname":"Kohneh Ab",
    "gn:cc2":"IR",
    "gn:country_code":"IR",
    "gn:dem":832,
    "gn:feature_class":"P",
    "gn:feature_code":"PPL",
    "gn:name":"Kohneh \u0100b",
    "gn:population":0,
    "gn:timezone":"Asia/Tehran",
    "iso:country":"IR",
    "name:ceb_x_preferred":[
        "Kohneh \u0100b"
    ],
    "name:fas_x_preferred":[
        "Kohneh \u0100b"
    ],
    "name:fas_x_variant":[
        "\u06a9\u0647\u0646\u0647\u200c\u0622\u0628"
    ],
    "name:swe_x_preferred":[
        "Kohneh \u0100b"
    ],
    "name:und_x_variant":[
        "Kh\u0101n \u0100bl",
        "Kohan \u0100b",
        "Kh\u0101n \u0100bi"
    ],
    "wof:name":"Kohneh Ab",
    "wof:placetype":"locality"
},
  "geometry": {"coordinates":[59.28333000000001,26.68333],"type":"Point"}
}