{
  "type": "Feature",
  "properties": {
    "gn:admin1_code":"35.0",
    "gn:asciiname":"March",
    "gn:country_code":"IR",
    "gn:dem":2171,
    "gn:feature_class":"P",
    "gn:feature_code":"PPL",
    "gn:name":"March",
    "gn:population":0,
    "gn:timezone":"Asia/Tehran",
    "iso:country":"IR",
    "name:fas_x_preferred":[
        "\u0645\u0631\u0686"
    ],
    "wof:name":"March",
    "wof:placetype":"locality"
},
  "geometry": {"coordinates":[51.81556,36.15184],"type":"Point"}
}