{
  "type": "Feature",
  "properties": {
    "gn:admin1_code":"26.0",
    "gn:asciiname":"Rostamabad",
    "gn:country_code":"IR",
    "gn:dem":1970,
    "gn:feature_class":"P",
    "gn:feature_code":"PPLF",
    "gn:name":"Rostam\u0101b\u0101d",
    "gn:population":0,
    "gn:timezone":"Asia/Tehran",
    "iso:country":"IR",
    "name:fas_x_preferred":[
        "\u0622\u0628\u0627 \u0628\u0627\u0631\u064a\u0643"
    ],
    "name:fas_x_variant":[
        "\u0622\u0628 \u0628\u0627\u0631\u064a\u06a9",
        "\u0100b-e B\u0101r\u012bk",
        "\u0631\u0633\u062a\u0645 \u0622\u0628\u0627\u062f"
    ],
    "name:und_x_variant":[
        "\u0100b\u0101 B\u0101r\u012bk",
        "\u0100b B\u0101r\u012bk",
        "Rostam\u0101b\u0101d"
    ],
    "wof:name":"Rostamabad",
    "wof:placetype":"locality"
},
  "geometry": {"coordinates":[52.09508,35.61566],"type":"Point"}
}