{
  "type": "Feature",
  "properties": {
    "gn:admin1_code":"7",
    "gn:asciiname":"Haft Dasht-e Bala",
    "gn:country_code":"IR",
    "gn:dem":808,
    "gn:feature_class":"P",
    "gn:feature_code":"PPL",
    "gn:name":"Haft Dasht-e B\u0101l\u0101",
    "gn:population":0,
    "gn:timezone":"Asia/Tehran",
    "iso:country":"IR",
    "name:fas_x_preferred":[
        "Haft Dasht-e B\u0101l\u0101"
    ],
    "name:fas_x_variant":[
        "\u0647\u0641\u062a \u062f\u0634\u062a \u0628\u0627\u0644\u0627"
    ],
    "name:und_x_variant":[
        "Haft Dasht-e P\u0101\u2019\u012bn",
        "\u0647\u0641\u062a \u062f\u0634\u062a \u0628\u0627\u0644\u0627"
    ],
    "wof:name":"Haft Dasht-e Bala",
    "wof:placetype":"locality"
},
  "geometry": {"coordinates":[51.0919,30.05838],"type":"Point"}
}