{
  "type": "Feature",
  "properties": {
    "gn:admin1_code":"33",
    "gn:asciiname":"Qermez Gol",
    "gn:country_code":"IR",
    "gn:dem":1725,
    "gn:feature_class":"P",
    "gn:feature_code":"PPL",
    "gn:name":"Qermez Gol",
    "gn:population":0,
    "gn:timezone":"Asia/Tehran",
    "iso:country":"IR",
    "name:fas_x_preferred":[
        "\u0642\u0631\u0645\u0632 \u06af\u0644"
    ],
    "name:fas_x_variant":[
        "\u0642\u0631\u0645\u0632\u06cc \u06af\u0644"
    ],
    "name:und_x_variant":[
        "Qermezgol",
        "Qermez Gol",
        "Qermez\u012b Gol"
    ],
    "wof:name":"Qermez Gol",
    "wof:placetype":"locality"
},
  "geometry": {"coordinates":[46.0843,37.7217],"type":"Point"}
}