{
  "type": "Feature",
  "properties": {
    "gn:admin1_code":"38.0",
    "gn:asciiname":"Takht-e Milaq",
    "gn:country_code":"IR",
    "gn:dem":2278,
    "gn:feature_class":"P",
    "gn:feature_code":"PPL",
    "gn:name":"Takht-e M\u012bl\u0101q",
    "gn:population":0,
    "gn:timezone":"Asia/Tehran",
    "iso:country":"IR",
    "name:fas_x_preferred":[
        "\u062a\u064e\u062e\u062a\u0650 \u064a\u0650\u064a\u0644\u0627\u0642"
    ],
    "name:fas_x_variant":[
        "\u062a\u062e\u062a \u0645\u06cc\u0644\u0627\u0642",
        "Takht-e Yeyl\u0101q",
        "Takht-e M\u012bl\u0101q"
    ],
    "wof:name":"Takht-e Milaq",
    "wof:placetype":"locality"
},
  "geometry": {"coordinates":[49.34808,35.57975],"type":"Point"}
}