{
  "type": "Feature",
  "properties": {
    "gn:admin1_code":"15.0",
    "gn:asciiname":"Tall-e Gorosneh",
    "gn:country_code":"IR",
    "gn:dem":156,
    "gn:feature_class":"P",
    "gn:feature_code":"PPL",
    "gn:name":"Tall-e Gorosneh",
    "gn:population":0,
    "gn:timezone":"Asia/Tehran",
    "iso:country":"IR",
    "name:fas_x_preferred":[
        "\u062a\u0644 \u06af\u0631\u0633\u0646\u0647"
    ],
    "wof:name":"Tall-e Gorosneh",
    "wof:placetype":"locality"
},
  "geometry": {"coordinates":[50.1659,30.3213],"type":"Point"}
}