{
  "type": "Feature",
  "properties": {
    "gn:admin1_code":"5",
    "gn:asciiname":"Papari",
    "gn:country_code":"IR",
    "gn:dem":1456,
    "gn:feature_class":"P",
    "gn:feature_code":"PPL",
    "gn:name":"P\u0101par\u012b",
    "gn:population":0,
    "gn:timezone":"Asia/Tehran",
    "iso:country":"IR",
    "name:ara_x_preferred":[
        "\u0628\u0627\u0628\u0627\u0631\u064a"
    ],
    "name:bos_x_preferred":[
        "Papari"
    ],
    "name:ceb_x_preferred":[
        "Papari"
    ],
    "name:ell_x_preferred":[
        "\u03a0\u03ac\u03c0\u03b1\u03c1\u03b9"
    ],
    "name:fas_x_preferred":[
        "\u067e\u064e\u0633\u067e\u064e\u0631\u06cc"
    ],
    "name:fas_x_variant":[
        "P\u0101par\u012b",
        "Paspar\u012b",
        "\u067e\u0627\u067e\u0631\u06cc"
    ],
    "name:fra_x_preferred":[
        "Papari"
    ],
    "name:hrv_x_preferred":[
        "Papari"
    ],
    "name:slv_x_preferred":[
        "Papari"
    ],
    "name:srp_x_preferred":[
        "\u041f\u0430\u043f\u0430\u0440\u0438"
    ],
    "name:und_x_variant":[
        "\u067e\u0627\u067e\u0631\u06cc"
    ],
    "wof:name":"Papari",
    "wof:placetype":"locality"
},
  "geometry": {"coordinates":[50.89531,30.79505],"type":"Point"}
}