{
  "type": "Feature",
  "properties": {
    "gn:admin1_code":"4.0",
    "gn:asciiname":"Molla Shir",
    "gn:country_code":"IR",
    "gn:dem":479,
    "gn:feature_class":"P",
    "gn:feature_code":"PPL",
    "gn:name":"Moll\u0101 Sh\u012br",
    "gn:population":0,
    "gn:timezone":"Asia/Tehran",
    "iso:country":"IR",
    "name:fas_x_preferred":[
        "\u0645\u0644\u0627 \u0634\u06cc\u0631"
    ],
    "name:fas_x_variant":[
        "Moll\u0101 Sh\u012br"
    ],
    "wof:name":"Molla Shir",
    "wof:placetype":"locality"
},
  "geometry": {"coordinates":[61.39703000000001,31.00666],"type":"Point"}
}