{
  "type": "Feature",
  "properties": {
    "gn:admin1_code":"8",
    "gn:asciiname":"Torshayeh",
    "gn:country_code":"IR",
    "gn:dem":1,
    "gn:feature_class":"P",
    "gn:feature_code":"PPL",
    "gn:name":"Torsh\u0101yeh",
    "gn:population":0,
    "gn:timezone":"Asia/Tehran",
    "iso:country":"IR",
    "name:fas_x_preferred":[
        "Torsh\u0101yeh"
    ],
    "name:fas_x_variant":[
        "\u062a\u0631\u0634\u0627\u06cc\u0647"
    ],
    "wof:name":"Torshayeh",
    "wof:placetype":"locality"
},
  "geometry": {"coordinates":[50.30745,37.09523],"type":"Point"}
}