{
  "type": "Feature",
  "properties": {
    "gn:admin1_code":"7.0",
    "gn:asciiname":"Shahrak-e Qods Chahar",
    "gn:country_code":"IR",
    "gn:dem":2209,
    "gn:feature_class":"P",
    "gn:feature_code":"PPL",
    "gn:name":"Shahrak-e Qods Chah\u0101r",
    "gn:population":0,
    "gn:timezone":"Asia/Tehran",
    "iso:country":"IR",
    "name:fas_x_preferred":[
        "\u0634\u0647\u0631\u06a9 \u0642\u062f\u0633 \u0686\u0647\u0627\u0631"
    ],
    "name:und_x_variant":[
        "Shahrak-e Qods Chah\u0101r"
    ],
    "wof:name":"Shahrak-e Qods Chahar",
    "wof:placetype":"locality"
},
  "geometry": {"coordinates":[52.72193000000001,30.90272],"type":"Point"}
}