{
  "type": "Feature",
  "properties": {
    "gn:admin1_code":"28",
    "gn:asciiname":"Nik Bey",
    "gn:country_code":"IR",
    "gn:dem":2155,
    "gn:feature_class":"P",
    "gn:feature_code":"PPL",
    "gn:name":"N\u012bk Bey",
    "gn:population":0,
    "gn:timezone":"Asia/Tehran",
    "iso:country":"IR",
    "name:fas_x_preferred":[
        "\u0646\u06cc\u06a9 \u0628\u06cc"
    ],
    "name:fas_x_variant":[
        "N\u012bkpey",
        "N\u012bk Bey"
    ],
    "wof:name":"Nik Bey",
    "wof:placetype":"locality"
},
  "geometry": {"coordinates":[50.6024,33.3672],"type":"Point"}
}