{
  "type": "Feature",
  "properties": {
    "gn:admin1_code":"29",
    "gn:asciiname":"Koniun",
    "gn:country_code":"IR",
    "gn:dem":528,
    "gn:feature_class":"P",
    "gn:feature_code":"PPL",
    "gn:name":"Kon\u012b\u016bn",
    "gn:population":0,
    "gn:timezone":"Asia/Tehran",
    "iso:country":"IR",
    "name:fas_x_preferred":[
        "Kon\u012b\u016bn"
    ],
    "wof:name":"Koniun",
    "wof:placetype":"locality"
},
  "geometry": {"coordinates":[57.41667,27.65],"type":"Point"}
}