{
  "type": "Feature",
  "properties": {
    "gn:admin1_code":"7",
    "gn:asciiname":"Jowkan",
    "gn:country_code":"IR",
    "gn:dem":1520,
    "gn:feature_class":"P",
    "gn:feature_code":"PPL",
    "gn:name":"Jowk\u0101n",
    "gn:population":0,
    "gn:timezone":"Asia/Tehran",
    "iso:country":"IR",
    "name:fas_x_preferred":[
        "\u062c\u0648\u06a9\u0627\u0646"
    ],
    "name:fas_x_variant":[
        "Jovak\u0101n",
        "Jowk\u0101n"
    ],
    "name:und_x_variant":[
        "Jowvak\u0101n",
        "Jookan"
    ],
    "wof:name":"Jowkan",
    "wof:placetype":"locality"
},
  "geometry": {"coordinates":[52.5714,29.0397],"type":"Point"}
}