{
  "type": "Feature",
  "properties": {
    "gn:admin1_code":"10",
    "gn:asciiname":"Choqa Baleh Chalab Zard",
    "gn:country_code":"IR",
    "gn:dem":976,
    "gn:feature_class":"P",
    "gn:feature_code":"PPL",
    "gn:name":"Choq\u0101 Baleh Ch\u0101l\u0101b Zard",
    "gn:population":0,
    "gn:timezone":"Asia/Tehran",
    "iso:country":"IR",
    "name:ara_x_preferred":[
        "\u062a\u0634\u0642\u0627\u0628\u0644\u0643 \u062a\u0634\u0627\u0644\u0627\u0628 \u0632\u0631\u062f"
    ],
    "name:ceb_x_preferred":[
        "Choq\u0101 Baleh Ch\u0101l\u0101b Zard"
    ],
    "name:fas_x_preferred":[
        "\u0686\u063a\u0627 \u0628\u0644\u06a9"
    ],
    "name:fas_x_variant":[
        "Choq\u0101 Balak-e Ch\u0101l\u0101b Zard",
        "Chaq\u0101 Balak",
        "\u0686\u0642\u0627 \u0628\u0644\u0647 \u0686\u0627\u0644\u0627\u0628 \u0632\u0631\u062f",
        "\u0686\u0642\u0627\u0628\u0644\u06a9 \u0686\u0627\u0644\u0627\u0628 \u0632\u0631\u062f"
    ],
    "name:msa_x_preferred":[
        "Choqa Balak-e Chalab Zard"
    ],
    "name:swe_x_preferred":[
        "Choq\u0101 Baleh Ch\u0101l\u0101b Zard"
    ],
    "name:und_x_variant":[
        "Choq\u0101 Balak",
        "Choq\u0101 Baleh Ch\u0101l\u0101b Zard",
        "Ch\u012b\u0101balak"
    ],
    "wof:name":"Choqa Baleh Chalab Zard",
    "wof:placetype":"locality"
},
  "geometry": {"coordinates":[46.8753,33.6538],"type":"Point"}
}