{
  "type": "Feature",
  "properties": {
    "gn:admin1_code":"42.0",
    "gn:asciiname":"Langar",
    "gn:country_code":"IR",
    "gn:dem":1018,
    "gn:feature_class":"P",
    "gn:feature_code":"PPL",
    "gn:name":"Langar",
    "gn:population":0,
    "gn:timezone":"Asia/Tehran",
    "iso:country":"IR",
    "name:fas_x_preferred":[
        "\u0644\u0646\u06af\u0631"
    ],
    "name:und_x_variant":[
        "Kharjerd",
        "Lengar",
        "Langar"
    ],
    "name:urd_x_preferred":[
        "\u0644\u0646\u06af\u0631"
    ],
    "wof:name":"Langar",
    "wof:placetype":"locality"
},
  "geometry": {"coordinates":[60.43575,35.38415999999999],"type":"Point"}
}