{
  "type": "Feature",
  "properties": {
    "gn:admin1_code":"41",
    "gn:asciiname":"Pesteh",
    "gn:country_code":"IR",
    "gn:dem":1683,
    "gn:feature_class":"P",
    "gn:feature_code":"PPL",
    "gn:name":"Pesteh",
    "gn:population":0,
    "gn:timezone":"Asia/Tehran",
    "iso:country":"IR",
    "name:fas_x_preferred":[
        "\u067e\u0633\u062a\u0647"
    ],
    "name:und_x_variant":[
        "Pisteh",
        "Pesteh",
        "\u067e\u0633\u062a\u0647"
    ],
    "wof:name":"Pesteh",
    "wof:placetype":"locality"
},
  "geometry": {"coordinates":[59.16541,32.30778],"type":"Point"}
}