{
  "type": "Feature",
  "properties": {
    "gn:admin1_code":"28",
    "gn:asciiname":"Mandegan",
    "gn:cc2":"IR",
    "gn:country_code":"IR",
    "gn:dem":2089,
    "gn:feature_class":"P",
    "gn:feature_code":"PPL",
    "gn:name":"M\u0101ndeg\u0101n",
    "gn:population":0,
    "gn:timezone":"Asia/Tehran",
    "iso:country":"IR",
    "name:fas_x_preferred":[
        "M\u0101ndeg\u0101n"
    ],
    "name:fas_x_variant":[
        "\u0645\u0627\u0646\u062f\u06af\u0627\u0646"
    ],
    "name:und_x_variant":[
        "M\u0101nd\u012bjan"
    ],
    "wof:name":"Mandegan",
    "wof:placetype":"locality"
},
  "geometry": {"coordinates":[51.44722,31.10167],"type":"Point"}
}