{
  "type": "Feature",
  "properties": {
    "gn:admin1_code":"41",
    "gn:asciiname":"Nowgidar",
    "gn:country_code":"IR",
    "gn:dem":2086,
    "gn:feature_class":"P",
    "gn:feature_code":"PPL",
    "gn:name":"Nowg\u012bdar",
    "gn:population":0,
    "gn:timezone":"Asia/Tehran",
    "iso:country":"IR",
    "name:fas_x_preferred":[
        "\u0646\u0648\u06af\u06cc\u062f\u0631"
    ],
    "name:fas_x_variant":[
        "N\u016bgd\u0101r"
    ],
    "name:und_x_variant":[
        "Naugidar",
        "N\u016bgd\u0101r",
        "Nowg\u012bdar"
    ],
    "wof:name":"Nowgidar",
    "wof:placetype":"locality"
},
  "geometry": {"coordinates":[59.40702,33.12571],"type":"Point"}
}