{
  "type": "Feature",
  "properties": {
    "gn:admin1_code":"5",
    "gn:asciiname":"Ganjeh Sariz",
    "gn:country_code":"IR",
    "gn:dem":1995,
    "gn:feature_class":"P",
    "gn:feature_code":"PPL",
    "gn:name":"Ganjeh Sar\u012bz",
    "gn:population":0,
    "gn:timezone":"Asia/Tehran",
    "iso:country":"IR",
    "name:fas_x_preferred":[
        "\u06af\u064e\u0646\u062c\u0650\u0647 \u0633\u064e\u0631 \u0631\u064a\u0632"
    ],
    "name:fas_x_variant":[
        "Ganjeh\u2019\u012b",
        "\u06af\u0646\u062c\u0647 \u0627\u06cc",
        "\u06af\u0646\u062c\u0647 \u0633\u0631\u064a\u0632",
        "\u06af\u064e\u0646\u062c\u0650\u0647\u0621\u0626 \u0633\u0650\u0647 \u0631\u064a\u0632"
    ],
    "name:und_x_variant":[
        "Ganjeh Sar R\u012bz",
        "\u06af\u0646\u062c\u0647 \u0627\u06cc",
        "Ganjeh Sar\u012bz",
        "Ganjeh\u2019\u012b-ye Seh R\u012bz"
    ],
    "wof:name":"Ganjeh Sariz",
    "wof:placetype":"locality"
},
  "geometry": {"coordinates":[51.5334,30.76017],"type":"Point"}
}