{
  "type": "Feature",
  "properties": {
    "gn:admin1_code":"33",
    "gn:asciiname":"Zaniq",
    "gn:country_code":"IR",
    "gn:dem":1357,
    "gn:feature_class":"P",
    "gn:feature_code":"PPL",
    "gn:name":"Zan\u012bq",
    "gn:population":0,
    "gn:timezone":"Asia/Tehran",
    "iso:country":"IR",
    "name:azb_x_preferred":[
        "\u0632\u0646\u0642"
    ],
    "name:fas_x_preferred":[
        "\u0632\u0646\u06cc\u0642"
    ],
    "name:fas_x_variant":[
        "Zan\u012bq",
        "\u0632\u0646\u0642"
    ],
    "name:msa_x_preferred":[
        "Zaneq"
    ],
    "name:und_x_variant":[
        "Zaneq"
    ],
    "wof:name":"Zaniq",
    "wof:placetype":"locality"
},
  "geometry": {"coordinates":[46.202,37.3304],"type":"Point"}
}