{
  "type": "Feature",
  "properties": {
    "gn:admin1_code":"8",
    "gn:asciiname":"Jur Gavabar",
    "gn:country_code":"IR",
    "gn:dem":117,
    "gn:feature_class":"P",
    "gn:feature_code":"PPL",
    "gn:name":"J\u016br Gav\u0101bar",
    "gn:population":0,
    "gn:timezone":"Asia/Tehran",
    "iso:country":"IR",
    "name:fas_x_preferred":[
        "J\u012br Gav\u0101bar"
    ],
    "name:fas_x_variant":[
        "\u062c\u06cc\u0631 \u06af\u0648\u0627\u0628\u0631",
        "\u062c\u0648\u0631 \u06af\u0648\u0627\u0628\u0631",
        "\u062c\u06cc\u0631\u06af\u0648\u0627\u0628\u0631"
    ],
    "name:msa_x_preferred":[
        "Jir Gavabar"
    ],
    "name:ukr_x_preferred":[
        "\u0414\u0436\u0456\u0440-\u0490\u0430\u0432\u0430\u0431\u0435\u0440"
    ],
    "name:und_x_variant":[
        "J\u016br Gav\u0101bar"
    ],
    "wof:name":"Jur Gavabar",
    "wof:placetype":"locality"
},
  "geometry": {"coordinates":[50.20241,37.03909],"type":"Point"}
}