{
  "type": "Feature",
  "properties": {
    "gn:admin1_code":"44",
    "gn:asciiname":"Vineh",
    "gn:country_code":"IR",
    "gn:dem":1534,
    "gn:feature_class":"P",
    "gn:feature_code":"PPL",
    "gn:name":"V\u012bneh",
    "gn:population":0,
    "gn:timezone":"Asia/Tehran",
    "iso:country":"IR",
    "name:fas_x_preferred":[
        "\u0648\u064a\u0646\u0647"
    ],
    "name:fas_x_variant":[
        "V\u012bneh",
        "\u0648\u06cc\u0646\u0647"
    ],
    "name:msa_x_preferred":[
        "Vineh"
    ],
    "name:und_x_variant":[
        "W\u012bneh"
    ],
    "wof:name":"Vineh",
    "wof:placetype":"locality"
},
  "geometry": {"coordinates":[51.0425,35.9012],"type":"Point"}
}