{
  "type": "Feature",
  "properties": {
    "gn:admin1_code":"42",
    "gn:asciiname":"Chehel Morghian",
    "gn:country_code":"IR",
    "gn:dem":1156,
    "gn:feature_class":"P",
    "gn:feature_code":"PPL",
    "gn:name":"Chehel Morgh\u012b\u0101n",
    "gn:population":0,
    "gn:timezone":"Asia/Tehran",
    "iso:country":"IR",
    "name:fas_x_preferred":[
        "\u0645\u0648\u063a\u06cc\u0627\u0646"
    ],
    "name:fas_x_variant":[
        "Chehel Morgh\u0101n",
        "Mowgh\u012b\u0101n",
        "\u0686\u0647\u0644 \u0645\u0631\u063a\u06cc\u0627\u0646"
    ],
    "name:und_x_variant":[
        "Chehel Morgh\u012b\u0101n"
    ],
    "wof:name":"Chehel Morghian",
    "wof:placetype":"locality"
},
  "geometry": {"coordinates":[58.72478,36.01094000000001],"type":"Point"}
}