{
  "type": "Feature",
  "properties": {
    "gn:admin1_code":"4.0",
    "gn:asciiname":"Shahrak-e Chah-e Eshaq",
    "gn:country_code":"IR",
    "gn:dem":402,
    "gn:feature_class":"P",
    "gn:feature_code":"PPL",
    "gn:name":"Shahrak-e Ch\u0101h-e Es\u1e29\u0101q",
    "gn:population":0,
    "gn:timezone":"Asia/Tehran",
    "iso:country":"IR",
    "name:fas_x_preferred":[
        "\u0634\u0647\u0631\u06a9 \u0686\u0627\u0647 \u0627\u0633\u062d\u0627\u0642"
    ],
    "name:und_x_variant":[
        "Shahrak-e Ch\u0101h-e Es\u1e29\u0101q"
    ],
    "wof:name":"Shahrak-e Chah-e Eshaq",
    "wof:placetype":"locality"
},
  "geometry": {"coordinates":[58.91113000000001,27.08108],"type":"Point"}
}