{
  "type": "Feature",
  "properties": {
    "gn:admin1_code":"26.0",
    "gn:asciiname":"Kuy-e Lavizan",
    "gn:country_code":"IR",
    "gn:dem":1532,
    "gn:feature_class":"P",
    "gn:feature_code":"PPL",
    "gn:name":"K\u016by-e Lav\u012bz\u0101n",
    "gn:population":0,
    "gn:timezone":"Asia/Tehran",
    "iso:country":"IR",
    "name:fas_x_preferred":[
        "\u06a9\u0648\u06cc \u0644\u0648\u06cc\u0632\u0627\u0646"
    ],
    "name:fas_x_variant":[
        "K\u016by-e Lav\u012bz\u0101n"
    ],
    "wof:name":"Kuy-e Lavizan",
    "wof:placetype":"locality"
},
  "geometry": {"coordinates":[51.4999,35.78],"type":"Point"}
}