{
  "type": "Feature",
  "properties": {
    "gn:admin1_code":"35",
    "gn:asciiname":"Taheri Mahalleh",
    "gn:country_code":"IR",
    "gn:dem":16,
    "gn:feature_class":"P",
    "gn:feature_code":"PPL",
    "gn:name":"\u0162\u0101her\u012b Ma\u1e29alleh",
    "gn:population":0,
    "gn:timezone":"Asia/Tehran",
    "iso:country":"IR",
    "name:fas_x_preferred":[
        "\u062a\u0627\u0631\u06cc \u0645\u064e\u062d\u064e\u0644\u0650\u0651\u0647"
    ],
    "name:fas_x_variant":[
        "T\u0101r\u012b Ma\u1e29alleh",
        "\u0162\u0101her\u012b Ma\u1e29alleh",
        "\u0637\u0627\u0647\u0631\u06cc \u0645\u062d\u0644\u0647"
    ],
    "wof:name":"Taheri Mahalleh",
    "wof:placetype":"locality"
},
  "geometry": {"coordinates":[52.51156999999999,36.47705],"type":"Point"}
}