{
  "type": "Feature",
  "properties": {
    "gn:admin1_code":"42",
    "gn:asciiname":"Jannatabad",
    "gn:country_code":"IR",
    "gn:dem":863,
    "gn:feature_class":"P",
    "gn:feature_code":"PPL",
    "gn:name":"Jannat\u0101b\u0101d",
    "gn:population":0,
    "gn:timezone":"Asia/Tehran",
    "iso:country":"IR",
    "name:fas_x_preferred":[
        "Jannat\u0101b\u0101d"
    ],
    "name:fas_x_variant":[
        "\u062c\u0646\u062a \u0622\u0628\u0627\u062f",
        "\u062c\u0646\u062a\u200c\u0622\u0628\u0627\u062f"
    ],
    "name:urd_x_preferred":[
        "\u062c\u0646\u062a \u0622\u0628\u0627\u062f"
    ],
    "wof:name":"Jannatabad",
    "wof:placetype":"locality"
},
  "geometry": {"coordinates":[58.65495,34.94345999999999],"type":"Point"}
}