{
  "type": "Feature",
  "properties": {
    "gn:admin1_code":"13",
    "gn:asciiname":"Tamal",
    "gn:country_code":"IR",
    "gn:dem":1594,
    "gn:feature_class":"P",
    "gn:feature_code":"PPL",
    "gn:name":"Tamal",
    "gn:population":0,
    "gn:timezone":"Asia/Tehran",
    "iso:country":"IR",
    "name:fas_x_preferred":[
        "\u062a\u0645\u0644"
    ],
    "name:und_x_variant":[
        "Tambaleh",
        "Tamal"
    ],
    "wof:name":"Tamal",
    "wof:placetype":"locality"
},
  "geometry": {"coordinates":[47.0847,34.7106],"type":"Point"}
}