{
  "type": "Feature",
  "properties": {
    "gn:admin1_code":"8.0",
    "gn:asciiname":"`Aziz Yurdi",
    "gn:country_code":"IR",
    "gn:dem":2284,
    "gn:feature_class":"P",
    "gn:feature_code":"PPL",
    "gn:name":"\u2018Az\u012bz Y\u016brd\u012b",
    "gn:population":0,
    "gn:timezone":"Asia/Tehran",
    "iso:country":"IR",
    "name:fas_x_preferred":[
        "\u0639\u0632\u06cc\u0632 \u06cc\u0648\u0631\u062f\u06cc"
    ],
    "name:und_x_variant":[
        "\u2018Az\u012bz Y\u016brd\u012b"
    ],
    "wof:name":"`Aziz Yurdi",
    "wof:placetype":"locality"
},
  "geometry": {"coordinates":[48.68476,37.93835],"type":"Point"}
}