{
  "type": "Feature",
  "properties": {
    "gn:admin1_code":"4.0",
    "gn:asciiname":"Patkub",
    "gn:country_code":"IR",
    "gn:dem":740,
    "gn:feature_class":"P",
    "gn:feature_code":"PPL",
    "gn:name":"P\u0101tk\u016bb",
    "gn:population":0,
    "gn:timezone":"Asia/Tehran",
    "iso:country":"IR",
    "name:fas_x_preferred":[
        "P\u0101tk\u016bb"
    ],
    "name:fas_x_variant":[
        "P\u0101dk\u016bb",
        "\u067e\u0627\u062a\u06a9\u0648\u0628",
        "\u067e\u0627\u062f\u06a9\u0648\u0628"
    ],
    "wof:name":"Patkub",
    "wof:placetype":"locality"
},
  "geometry": {"coordinates":[60.75374,26.42655],"type":"Point"}
}