{
  "type": "Feature",
  "properties": {
    "gn:admin1_code":"32",
    "gn:asciiname":"Kalanpa",
    "gn:country_code":"IR",
    "gn:dem":1315,
    "gn:elevation":"0.0",
    "gn:feature_class":"P",
    "gn:feature_code":"PPL",
    "gn:name":"Kalanp\u0101",
    "gn:population":0,
    "gn:timezone":"Asia/Tehran",
    "iso:country":"IR",
    "name:fas_x_preferred":[
        "\u0643\u0644\u0627\u0646\u067e\u0627"
    ],
    "name:fas_x_variant":[
        "\u06a9\u0644\u0645\u067e\u0627",
        "Kal\u0101np\u0101",
        "Kalamp\u0101",
        "\u0643\u0644\u0646\u067e\u0627",
        "\u0641\u064e\u0644\u0627\u0646\u067e\u0627"
    ],
    "name:und_x_variant":[
        "Kalanp\u0101",
        "Fal\u0101np\u0101"
    ],
    "wof:name":"Kalanpa",
    "wof:placetype":"locality"
},
  "geometry": {"coordinates":[47.4759,38.3457],"type":"Point"}
}