{
  "type": "Feature",
  "properties": {
    "gn:admin1_code":"35",
    "gn:asciiname":"Shub Mahalleh",
    "gn:country_code":"IR",
    "gn:dem":32,
    "gn:feature_class":"P",
    "gn:feature_code":"PPL",
    "gn:name":"Sh\u016bb Ma\u1e29alleh",
    "gn:population":0,
    "gn:timezone":"Asia/Tehran",
    "iso:country":"IR",
    "name:fas_x_preferred":[
        "\u0634\u0648\u0628 \u0645\u062d\u0644\u0647"
    ],
    "name:fas_x_variant":[
        "Showb Ma\u1e29alleh",
        "Sh\u016bb Ma\u1e29alleh"
    ],
    "name:und_x_variant":[
        "\u0634\u064f\u0648\u0628 \u0645\u064e\u062d\u064e\u0644\u0650\u0651\u0647"
    ],
    "wof:name":"Shub Mahalleh",
    "wof:placetype":"locality"
},
  "geometry": {"coordinates":[52.69366,36.4323],"type":"Point"}
}