{
  "type": "Feature",
  "properties": {
    "gn:admin1_code":"37",
    "gn:asciiname":"Qulaq Burteh",
    "gn:country_code":"IR",
    "gn:dem":74,
    "gn:feature_class":"P",
    "gn:feature_code":"PPL",
    "gn:name":"Q\u016bl\u0101q B\u016brteh",
    "gn:population":0,
    "gn:timezone":"Asia/Tehran",
    "iso:country":"IR",
    "name:ara_x_preferred":[
        "\u0642\u0644\u0627\u0642 \u0628\u0648\u0631\u062a\u0647"
    ],
    "name:ceb_x_preferred":[
        "Q\u016bl\u0101q B\u016brteh"
    ],
    "name:fas_x_preferred":[
        "\u0642\u0644\u0627\u0642\u0628\u0648\u0631\u062a\u0627"
    ],
    "name:fas_x_variant":[
        "\u0642\u0648\u0644\u0627\u0642 \u0628\u0648\u0631\u062a\u0647",
        "\u0642\u0644\u0627\u0642 \u0628\u0648\u0631\u062a\u0647"
    ],
    "name:msa_x_preferred":[
        "Qelaq Burteh"
    ],
    "name:swe_x_preferred":[
        "Q\u016bl\u0101q B\u016brteh"
    ],
    "name:und_x_variant":[
        "Qol\u0101qb\u016brt\u0101",
        "Qol\u0101q Q\u016brt\u0101",
        "Qal\u0101q Q\u016brt\u0101",
        "Qol\u0101q B\u016brteh"
    ],
    "wof:name":"Qulaq Burteh",
    "wof:placetype":"locality"
},
  "geometry": {"coordinates":[55.17961999999999,37.93998],"type":"Point"}
}