{
  "type": "Feature",
  "properties": {
    "gn:admin1_code":"7.0",
    "gn:asciiname":"Tall Koreh",
    "gn:country_code":"IR",
    "gn:dem":2201,
    "gn:feature_class":"P",
    "gn:feature_code":"PPL",
    "gn:name":"Tall Koreh",
    "gn:population":0,
    "gn:timezone":"Asia/Tehran",
    "iso:country":"IR",
    "name:fas_x_preferred":[
        "\u062a\u0644 \u06a9\u0631\u0647"
    ],
    "name:und_x_variant":[
        "\u062a\u0644 \u06a9\u0631\u0647"
    ],
    "wof:name":"Tall Koreh",
    "wof:placetype":"locality"
},
  "geometry": {"coordinates":[51.87241,29.77903],"type":"Point"}
}