{
  "type": "Feature",
  "properties": {
    "gn:admin1_code":"43.0",
    "gn:asciiname":"Obeh Mohammad Jan",
    "gn:country_code":"IR",
    "gn:dem":424,
    "gn:feature_class":"P",
    "gn:feature_code":"PPL",
    "gn:name":"Obeh Mo\u1e29ammad J\u0101n",
    "gn:population":0,
    "gn:timezone":"Asia/Tehran",
    "iso:country":"IR",
    "name:fas_x_preferred":[
        "\u0627\u0628\u0647 \u0645\u062d\u0645\u0651\u062f \u062c\u0627\u0646"
    ],
    "name:fas_x_variant":[
        "Oveh Mo\u1e29ammad J\u0101n",
        "Obeh Mo\u1e29ammad J\u0101n"
    ],
    "wof:name":"Obeh Mohammad Jan",
    "wof:placetype":"locality"
},
  "geometry": {"coordinates":[56.3595,37.8193],"type":"Point"}
}