{
  "type": "Feature",
  "properties": {
    "gn:admin1_code":"37.0",
    "gn:asciiname":"Qarah Aqashli",
    "gn:country_code":"IR",
    "gn:dem":898,
    "gn:feature_class":"P",
    "gn:feature_code":"PPL",
    "gn:name":"Qarah \u0100q\u0101shl\u012b",
    "gn:population":0,
    "gn:timezone":"Asia/Tehran",
    "iso:country":"IR",
    "name:fas_x_preferred":[
        "Qarah \u0100q\u0101shl\u012b"
    ],
    "name:fas_x_variant":[
        "Qareh \u0100q\u0101shl\u012b",
        "\u0642\u0631\u0647 \u0622\u0642\u0627\u0634\u0644\u06cc"
    ],
    "name:und_x_variant":[
        "\u0642\u0631\u0647 \u0622\u0642\u0627\u0634\u0644\u06cc"
    ],
    "wof:name":"Qarah Aqashli",
    "wof:placetype":"locality"
},
  "geometry": {"coordinates":[55.92324,37.61098],"type":"Point"}
}