{
  "type": "Feature",
  "properties": {
    "gn:admin1_code":"5",
    "gn:asciiname":"Zur Azema-ye Sofla",
    "gn:country_code":"IR",
    "gn:dem":594,
    "gn:feature_class":"P",
    "gn:feature_code":"PPL",
    "gn:name":"Z\u016br \u0100zem\u0101-ye Sofl\u00e1",
    "gn:population":0,
    "gn:timezone":"Asia/Tehran",
    "iso:country":"IR",
    "name:fas_x_preferred":[
        "\u0632\u0648\u0631 \u0622\u0632\u0650\u0645\u0627 \u0633\u0641\u0644\u06cc"
    ],
    "name:fas_x_variant":[
        "Z\u016br \u0100zem\u0101-ye Sofl\u00e1"
    ],
    "wof:name":"Zur Azema-ye Sofla",
    "wof:placetype":"locality"
},
  "geometry": {"coordinates":[50.0276,30.984],"type":"Point"}
}