{
  "type": "Feature",
  "properties": {
    "gn:admin1_code":"28",
    "gn:asciiname":"Asiab-e Khan",
    "gn:country_code":"IR",
    "gn:dem":1839,
    "gn:feature_class":"P",
    "gn:feature_code":"PPL",
    "gn:name":"\u0100s\u012b\u0101b-e Kh\u0101n",
    "gn:population":0,
    "gn:timezone":"Asia/Tehran",
    "iso:country":"IR",
    "name:fas_x_preferred":[
        "\u0100s\u012b\u0101b-e Kh\u0101n"
    ],
    "wof:name":"Asiab-e Khan",
    "wof:placetype":"locality"
},
  "geometry": {"coordinates":[51.83444,31.99694],"type":"Point"}
}