{
  "type": "Feature",
  "properties": {
    "gn:admin1_code":"23",
    "gn:asciiname":"Rika",
    "gn:country_code":"IR",
    "gn:dem":1193,
    "gn:feature_class":"P",
    "gn:feature_code":"PPL",
    "gn:name":"R\u012bk\u0101",
    "gn:population":0,
    "gn:timezone":"Asia/Tehran",
    "iso:country":"IR",
    "name:fas_x_preferred":[
        "\u0631\u064a\u0643\u0627"
    ],
    "wof:name":"Rika",
    "wof:placetype":"locality"
},
  "geometry": {"coordinates":[47.69917,33.40194],"type":"Point"}
}