{
  "type": "Feature",
  "properties": {
    "gn:admin1_code":"28",
    "gn:asciiname":"Samandegan",
    "gn:country_code":"IR",
    "gn:dem":2160,
    "gn:feature_class":"P",
    "gn:feature_code":"PPL",
    "gn:name":"Samandeg\u0101n",
    "gn:population":0,
    "gn:timezone":"Asia/Tehran",
    "iso:country":"IR",
    "name:fas_x_preferred":[
        "Samandeg\u0101n"
    ],
    "name:fas_x_variant":[
        "\u0633\u0645\u0646\u062f\u06af\u0627\u0646"
    ],
    "name:und_x_variant":[
        "Samandag\u0101n",
        "\u0633\u0645\u0646\u062f\u06af\u0627\u0646"
    ],
    "wof:name":"Samandegan",
    "wof:placetype":"locality"
},
  "geometry": {"coordinates":[50.61309,32.7928],"type":"Point"}
}