{
  "type": "Feature",
  "properties": {
    "gn:admin1_code":"33.0",
    "gn:asciiname":"Yuzband",
    "gn:country_code":"IR",
    "gn:dem":1688,
    "gn:feature_class":"P",
    "gn:feature_code":"PPL",
    "gn:name":"Y\u016bzband",
    "gn:population":0,
    "gn:timezone":"Asia/Tehran",
    "iso:country":"IR",
    "name:aze_x_preferred":[
        "Y\u00fczb\u0259nd"
    ],
    "name:fas_x_preferred":[
        "\u06cc\u0648\u0632\u0628\u0646\u062f"
    ],
    "name:fas_x_variant":[
        "Y\u016bzband",
        "\u06cc\u0648\u0632\u0628\u0646\u062f\u0647"
    ],
    "name:und_x_variant":[
        "Y\u016bzbandeh"
    ],
    "wof:name":"Yuzband",
    "wof:placetype":"locality"
},
  "geometry": {"coordinates":[47.18,38.3946],"type":"Point"}
}