{
  "type": "Feature",
  "properties": {
    "gn:admin1_code":"42.0",
    "gn:asciiname":"Damrud",
    "gn:country_code":"IR",
    "gn:dem":858,
    "gn:feature_class":"P",
    "gn:feature_code":"PPL",
    "gn:name":"D\u0101mr\u016bd",
    "gn:population":0,
    "gn:timezone":"Asia/Tehran",
    "iso:country":"IR",
    "name:ceb_x_preferred":[
        "D\u0101m R\u016bd"
    ],
    "name:fas_x_preferred":[
        "\u062f\u0627\u0645\u0631\u0648\u062f"
    ],
    "name:swe_x_preferred":[
        "D\u0101m R\u016bd"
    ],
    "name:und_x_variant":[
        "D\u0101mr\u016bd"
    ],
    "wof:name":"Damrud",
    "wof:placetype":"locality"
},
  "geometry": {"coordinates":[57.23692,36.03225],"type":"Point"}
}