{
  "type": "Feature",
  "properties": {
    "gn:admin1_code":"38.0",
    "gn:asciiname":"Abyek",
    "gn:country_code":"IR",
    "gn:dem":1258,
    "gn:feature_class":"P",
    "gn:feature_code":"PPLA2",
    "gn:name":"\u0100byek",
    "gn:population":0,
    "gn:timezone":"Asia/Tehran",
    "iso:country":"IR",
    "name:ara_x_preferred":[
        "\u0622\u0628\u064a\u0643"
    ],
    "name:azb_x_preferred":[
        "\u0622\u0628\u06cc\u06a9"
    ],
    "name:aze_x_preferred":[
        "Abyek"
    ],
    "name:ceb_x_preferred":[
        "\u0100byek"
    ],
    "name:fas_x_preferred":[
        "\u0622\u0628\u064a\u0650\u0643\u0650 \u067e\u0627\u0626\u064a\u0646"
    ],
    "name:fas_x_variant":[
        "\u0627\u064e\u0628\u064a\u0650\u0643 \u0633\u064f\u0641\u0644\u064e",
        "\u0100byek",
        "\u0622\u0628\u064a\u06a9",
        "\u0622\u0628\u06cc\u06a9"
    ],
    "name:fra_x_preferred":[
        "Abyek"
    ],
    "name:hin_x_preferred":[
        "\u0905\u092c\u092f\u0947\u0915"
    ],
    "name:hye_x_preferred":[
        "\u0531\u0562\u056b\u0565\u0584"
    ],
    "name:ita_x_preferred":[
        "Abyek"
    ],
    "name:mlg_x_preferred":[
        "Abyek"
    ],
    "name:pnb_x_preferred":[
        "\u0622\u0628\u06cc\u06a9"
    ],
    "name:pol_x_preferred":[
        "Abjek"
    ],
    "name:ron_x_preferred":[
        "Abeyek"
    ],
    "name:rus_x_preferred":[
        "\u0410\u0431\u044a\u0435\u043a"
    ],
    "name:swe_x_preferred":[
        "Abyek"
    ],
    "name:tgk_x_preferred":[
        "\u041e\u0431\u044f\u043a"
    ],
    "name:tur_x_preferred":[
        "Abyek"
    ],
    "name:ukr_x_preferred":[
        "\u0410\u0431\u0456\u0454\u043a"
    ],
    "name:und_x_variant":[
        "Abyek Sofla",
        "\u0100byek-e P\u0101\u2019\u012bn",
        "Abiak Sar\u0101i",
        "Abiak"
    ],
    "name:urd_x_preferred":[
        "\u0627\u0628\u06cc\u06a9"
    ],
    "name:zho_x_preferred":[
        "\u963f\u535c\u8036\u514b"
    ],
    "wof:name":"Abyek",
    "wof:placetype":"locality"
},
  "geometry": {"coordinates":[50.53101,36.03993],"type":"Point"}
}