{
  "type": "Feature",
  "properties": {
    "gn:admin1_code":"38.0",
    "gn:asciiname":"Abyek",
    "gn:country_code":"IR",
    "gn:dem":1258,
    "gn:feature_class":"P",
    "gn:feature_code":"PPLA2",
    "gn:name":"\u0100byek",
    "gn:population":0,
    "gn:timezone":"Asia/Tehran",
    "iso:country":"IR",
    "name:fas_x_preferred":[
        "\u0622\u0628\u064a\u0650\u0643\u0650 \u067e\u0627\u0626\u064a\u0646"
    ],
    "name:fas_x_variant":[
        "\u0627\u064e\u0628\u064a\u0650\u0643 \u0633\u064f\u0641\u0644\u064e",
        "\u0100byek",
        "\u0622\u0628\u064a\u06a9"
    ],
    "name:und_x_variant":[
        "Abyek Sofla",
        "\u0100byek-e P\u0101\u2019\u012bn",
        "Abiak Sar\u0101i",
        "\u0622\u0628\u064a\u06a9",
        "Abiak"
    ],
    "wof:name":"Abyek",
    "wof:placetype":"locality"
},
  "geometry": {"coordinates":[50.53101,36.03993],"type":"Point"}
}