{
  "type": "Feature",
  "properties": {
    "gn:admin1_code":"11",
    "gn:asciiname":"Kontaki",
    "gn:country_code":"IR",
    "gn:dem":13,
    "gn:feature_class":"P",
    "gn:feature_code":"PPL",
    "gn:name":"Kontak\u012b",
    "gn:population":0,
    "gn:timezone":"Asia/Tehran",
    "iso:country":"IR",
    "name:ceb_x_preferred":[
        "Kontak\u012b"
    ],
    "name:fas_x_preferred":[
        "\u0643\u064f\u0646\u062a\u0627\u06af\u06cc"
    ],
    "name:fas_x_variant":[
        "Kont\u0101g\u012b",
        "Kontak\u012b",
        "\u06a9\u0646\u062a\u06a9\u06cc",
        "\u06a9\u0646\u062a\u0627\u06a9\u06cc"
    ],
    "name:msa_x_preferred":[
        "Kontaki"
    ],
    "name:swe_x_preferred":[
        "Kontak\u012b"
    ],
    "name:und_x_variant":[
        "\u06a9\u0646\u062a\u06a9\u06cc"
    ],
    "wof:name":"Kontaki",
    "wof:placetype":"locality"
},
  "geometry": {"coordinates":[58.46112,25.72272],"type":"Point"}
}