{
  "type": "Feature",
  "properties": {
    "gn:admin1_code":"16.0",
    "gn:asciiname":"Anjineh-ye Reza",
    "gn:country_code":"IR",
    "gn:dem":1436,
    "gn:elevation":"0.0",
    "gn:feature_class":"P",
    "gn:feature_code":"PPL",
    "gn:name":"\u0100nj\u012bneh-ye Re\u1e95\u0101",
    "gn:population":0,
    "gn:timezone":"Asia/Tehran",
    "iso:country":"IR",
    "name:fas_x_preferred":[
        "\u0627\u064e\u0646\u062c\u064a\u0646\u0650\u06c0 \u0639\u064f\u0644\u064a\u0627"
    ],
    "name:fas_x_variant":[
        "\u0622\u0646\u062c\u06cc\u0646\u0647 \u0631\u0636\u0627",
        "Anj\u012bneh-ye B\u0101l\u0101",
        "Anj\u012bneh-ye \u2018Oly\u0101",
        "\u0100nj\u012bneh-ye Re\u1e95\u0101"
    ],
    "wof:name":"Anjineh-ye Reza",
    "wof:placetype":"locality"
},
  "geometry": {"coordinates":[45.6472,35.9721],"type":"Point"}
}