{
  "type": "Feature",
  "properties": {
    "gn:admin1_code":"33",
    "gn:asciiname":"Khachik",
    "gn:country_code":"IR",
    "gn:dem":2022,
    "gn:feature_class":"P",
    "gn:feature_code":"PPL",
    "gn:name":"Kh\u0101ch\u012bk",
    "gn:population":0,
    "gn:timezone":"Asia/Tehran",
    "iso:country":"IR",
    "name:fas_x_preferred":[
        "\u062e\u0627\u0686\u06cc\u06a9"
    ],
    "name:und_x_variant":[
        "Kh\u0101ch\u012bk"
    ],
    "wof:name":"Khachik",
    "wof:placetype":"locality"
},
  "geometry": {"coordinates":[46.6677,37.6216],"type":"Point"}
}