{
  "type": "Feature",
  "properties": {
    "gn:admin1_code":"29",
    "gn:asciiname":"Torang",
    "gn:country_code":"IR",
    "gn:dem":2085,
    "gn:feature_class":"P",
    "gn:feature_code":"PPL",
    "gn:name":"\u0162orang",
    "gn:population":0,
    "gn:timezone":"Asia/Tehran",
    "iso:country":"IR",
    "name:ara_x_preferred":[
        "\u0637\u0631\u0646\u063a"
    ],
    "name:ceb_x_preferred":[
        "\u0162orang"
    ],
    "name:fas_x_preferred":[
        "\u0637\u0631\u0646\u06af"
    ],
    "name:fas_x_variant":[
        "\u0162orang"
    ],
    "name:swe_x_preferred":[
        "\u0162orang"
    ],
    "name:und_x_variant":[
        "Tarank"
    ],
    "wof:name":"Torang",
    "wof:placetype":"locality"
},
  "geometry": {"coordinates":[56.8012,28.75800000000001],"type":"Point"}
}