{
  "type": "Feature",
  "properties": {
    "gn:admin1_code":"33",
    "gn:asciiname":"Idahlu",
    "gn:country_code":"IR",
    "gn:dem":1938,
    "gn:feature_class":"P",
    "gn:feature_code":"PPL",
    "gn:name":"\u012adahl\u016b",
    "gn:population":0,
    "gn:timezone":"Asia/Tehran",
    "iso:country":"IR",
    "name:fas_x_preferred":[
        "\u012adahl\u016b"
    ],
    "name:fas_x_variant":[
        "\u0627\u06cc\u062f\u0647\u0644\u0648",
        "\u0627\u06cc\u062f\u0647\u200c\u0644\u0648"
    ],
    "wof:name":"Idahlu",
    "wof:placetype":"locality"
},
  "geometry": {"coordinates":[46.8608,37.1654],"type":"Point"}
}