{
  "type": "Feature",
  "properties": {
    "gn:admin1_code":"29",
    "gn:asciiname":"Salmanabad",
    "gn:country_code":"IR",
    "gn:dem":717,
    "gn:feature_class":"P",
    "gn:feature_code":"PPL",
    "gn:name":"Salm\u0101n\u0101b\u0101d",
    "gn:population":0,
    "gn:timezone":"Asia/Tehran",
    "iso:country":"IR",
    "name:fas_x_preferred":[
        "\u0633\u0644\u0645\u0627\u0646 \u0622\u0628\u0627\u062f \u06af\u0646\u0628\u06af\u06cc"
    ],
    "name:fas_x_variant":[
        "Salm\u0101n\u0101b\u0101d",
        "Salm\u0101n\u0101b\u0101d-e Gonbag\u012b",
        "\u0633\u0644\u0645\u0627\u0646 \u0622\u0628\u0627\u062f"
    ],
    "wof:name":"Salmanabad",
    "wof:placetype":"locality"
},
  "geometry": {"coordinates":[58.85128,28.74694],"type":"Point"}
}