{
  "type": "Feature",
  "properties": {
    "gn:admin1_code":"15.0",
    "gn:asciiname":"Ab Anjirak-e `Olya",
    "gn:country_code":"IR",
    "gn:dem":296,
    "gn:feature_class":"P",
    "gn:feature_code":"PPL",
    "gn:name":"\u0100b Anj\u012brak-e `Oly\u0101",
    "gn:population":0,
    "gn:timezone":"Asia/Tehran",
    "iso:country":"IR",
    "wof:name":"Ab Anjirak-e `Olya",
    "wof:placetype":"locality"
},
  "geometry": {"coordinates":[49.23333,32.03333],"type":"Point"}
}