{
  "type": "Feature",
  "properties": {
    "gn:admin1_code":"33",
    "gn:asciiname":"Piranlu",
    "gn:country_code":"IR",
    "gn:dem":413,
    "gn:feature_class":"P",
    "gn:feature_code":"PPL",
    "gn:name":"P\u012br\u0101nl\u016b",
    "gn:population":0,
    "gn:timezone":"Asia/Tehran",
    "iso:country":"IR",
    "name:fas_x_preferred":[
        "\u067e\u064a\u0631\u0627\u0646\u0644\u0648"
    ],
    "name:fas_x_variant":[
        "P\u012br\u0101nl\u016b"
    ],
    "wof:name":"Piranlu",
    "wof:placetype":"locality"
},
  "geometry": {"coordinates":[47.03583,39.14556],"type":"Point"}
}