{
  "type": "Feature",
  "properties": {
    "gn:admin1_code":"42.0",
    "gn:asciiname":"Mikhak-e Seyyedabad",
    "gn:country_code":"IR",
    "gn:dem":821,
    "gn:feature_class":"P",
    "gn:feature_code":"PPL",
    "gn:name":"M\u012bkhak-e Seyyed\u0101b\u0101d",
    "gn:population":0,
    "gn:timezone":"Asia/Tehran",
    "iso:country":"IR",
    "name:fas_x_preferred":[
        "\u0645\u06cc\u062e\u06a9 \u0633\u06cc\u0651\u062f \u0622\u0628\u0627\u062f"
    ],
    "name:fas_x_variant":[
        "M\u012bkhak",
        "M\u012bkhak-e Seyyed\u0101b\u0101d"
    ],
    "wof:name":"Mikhak-e Seyyedabad",
    "wof:placetype":"locality"
},
  "geometry": {"coordinates":[60.84461,35.18926],"type":"Point"}
}