{
  "type": "Feature",
  "properties": {
    "gn:admin1_code":"4.0",
    "gn:asciiname":"Madeh Kariz",
    "gn:country_code":"IR",
    "gn:dem":834,
    "gn:feature_class":"P",
    "gn:feature_code":"PPL",
    "gn:name":"Madeh K\u0101r\u012bz",
    "gn:population":0,
    "gn:timezone":"Asia/Tehran",
    "iso:country":"IR",
    "name:fas_x_preferred":[
        "Madeh K\u0101r\u012bz"
    ],
    "name:fas_x_variant":[
        "M\u0101deh K\u0101r\u012bz",
        "\u0645\u062f\u0647 \u06a9\u0627\u0631\u064a\u0632",
        "Madgh Kar\u012bz",
        "Madeh K\u0101rez"
    ],
    "name:und_x_variant":[
        "Madeh",
        "Madeh K\u0101rez",
        "Madgh Kar\u012bz",
        "\u0645\u062f\u0647 \u06a9\u0627\u0631\u064a\u0632"
    ],
    "wof:name":"Madeh Kariz",
    "wof:placetype":"locality"
},
  "geometry": {"coordinates":[60.38949,31.14805],"type":"Point"}
}