{
  "type": "Feature",
  "properties": {
    "gn:admin1_code":"13",
    "gn:asciiname":"Gav Khari-ye Pa'in",
    "gn:country_code":"IR",
    "gn:dem":511,
    "gn:feature_class":"P",
    "gn:feature_code":"PPL",
    "gn:name":"G\u0101v Khar\u012b-ye P\u0101\u2019\u012bn",
    "gn:population":0,
    "gn:timezone":"Asia/Tehran",
    "iso:country":"IR",
    "name:fas_x_preferred":[
        "\u06af\u0627\u0648 \u062e\u0631\u06cc \u067e\u0627\u0626\u064a\u0646"
    ],
    "name:fas_x_variant":[
        "G\u0101v Khar\u012b-ye P\u0101\u2019\u012bn"
    ],
    "name:und_x_variant":[
        "G\u0101vkhor\u012b-ye P\u0101\u2019\u012bn"
    ],
    "wof:name":"Gav Khari-ye Pa'in",
    "wof:placetype":"locality"
},
  "geometry": {"coordinates":[45.79124,34.7409],"type":"Point"}
}