{
  "type": "Feature",
  "properties": {
    "gn:admin1_code":"23",
    "gn:asciiname":"Darreh-ye Bizhan-e Vosta",
    "gn:country_code":"IR",
    "gn:dem":1779,
    "gn:feature_class":"P",
    "gn:feature_code":"PPL",
    "gn:name":"Darreh-ye B\u012bzhan-e Vos\u0163\u00e1",
    "gn:population":0,
    "gn:timezone":"Asia/Tehran",
    "iso:country":"IR",
    "name:fas_x_preferred":[
        "\u062f\u0631\u0647 \u0628\u064a\u0698\u0646 \u0648\u0633\u0637\u0649"
    ],
    "name:fas_x_variant":[
        "Darreh-ye B\u012bzhan-e Vos\u0163\u00e1"
    ],
    "name:und_x_variant":[
        "Darreh B\u012bzan",
        "Darreh-ye B\u012bzhan",
        "Darreh B\u012bzhan"
    ],
    "wof:name":"Darreh-ye Bizhan-e Vosta",
    "wof:placetype":"locality"
},
  "geometry": {"coordinates":[48.6284,33.6874],"type":"Point"}
}