{
  "type": "Feature",
  "properties": {
    "gn:admin1_code":"35.0",
    "gn:asciiname":"Dehak",
    "gn:country_code":"IR",
    "gn:dem":5,
    "gn:feature_class":"P",
    "gn:feature_code":"PPL",
    "gn:name":"Dehak",
    "gn:population":0,
    "gn:timezone":"Asia/Tehran",
    "iso:country":"IR",
    "name:ceb_x_preferred":[
        "Dehak"
    ],
    "name:fas_x_preferred":[
        "\u062f\u0647\u0643"
    ],
    "name:swe_x_preferred":[
        "Dehak"
    ],
    "wof:name":"Dehak",
    "wof:placetype":"locality"
},
  "geometry": {"coordinates":[52.62084,36.52506],"type":"Point"}
}