{
  "type": "Feature",
  "properties": {
    "gn:admin1_code":"8.0",
    "gn:asciiname":"Joda Nowkar",
    "gn:country_code":"IR",
    "gn:dem":-3,
    "gn:feature_class":"P",
    "gn:feature_code":"PPL",
    "gn:name":"Jod\u0101 Nowkar",
    "gn:population":0,
    "gn:timezone":"Asia/Tehran",
    "iso:country":"IR",
    "name:fas_x_preferred":[
        "\u062c\u062f\u0627 \u0646\u0648\u06a9\u0631"
    ],
    "name:und_x_variant":[
        "Jod\u0101 Nowkar"
    ],
    "wof:name":"Joda Nowkar",
    "wof:placetype":"locality"
},
  "geometry": {"coordinates":[50.11901,37.19738],"type":"Point"}
}