{
  "type": "Feature",
  "properties": {
    "gn:admin1_code":"28.0",
    "gn:asciiname":"Chehel Dastgah",
    "gn:country_code":"IR",
    "gn:dem":1866,
    "gn:feature_class":"P",
    "gn:feature_code":"PPL",
    "gn:name":"Chehel Dastg\u0101h",
    "gn:population":0,
    "gn:timezone":"Asia/Tehran",
    "iso:country":"IR",
    "name:fas_x_preferred":[
        "Chehel Dastg\u0101h"
    ],
    "name:fas_x_variant":[
        "\u0686\u0647\u0644 \u062f\u0633\u062a\u06af\u0627\u0647",
        "\u0634\u0647\u0631\u06a9 \u0686\u0647\u0627\u0631 \u0635\u062f \u062f\u0633\u062a\u06af\u0627\u0647"
    ],
    "name:und_x_variant":[
        "\u0686\u0647\u0644 \u062f\u0633\u062a\u06af\u0627\u0647",
        "Shahrak-e Chah\u0101r \u015ead Dastg\u0101h"
    ],
    "wof:name":"Chehel Dastgah",
    "wof:placetype":"locality"
},
  "geometry": {"coordinates":[50.25741,33.47535],"type":"Point"}
}