{
  "type": "Feature",
  "properties": {
    "gn:admin1_code":"42",
    "gn:asciiname":"Khvajeh Gerdab",
    "gn:country_code":"IR",
    "gn:dem":1289,
    "gn:feature_class":"P",
    "gn:feature_code":"PPL",
    "gn:name":"Khv\u0101jeh Gerd\u0101b",
    "gn:population":0,
    "gn:timezone":"Asia/Tehran",
    "iso:country":"IR",
    "name:fas_x_preferred":[
        "\u062e\u0648\u0627\u062c\u0647 \u06af\u0631\u062f\u0627\u0628"
    ],
    "name:fas_x_variant":[
        "Khav\u0101jeh Gerd\u0101b",
        "Khv\u0101jeh Gerd\u0101b"
    ],
    "name:und_x_variant":[
        "Khv\u0101jehgerel\u0101b"
    ],
    "wof:name":"Khvajeh Gerdab",
    "wof:placetype":"locality"
},
  "geometry": {"coordinates":[59.06141,36.82176],"type":"Point"}
}