{
  "type": "Feature",
  "properties": {
    "gn:admin1_code":"42",
    "gn:asciiname":"Kalateh-ye Mian",
    "gn:country_code":"IR",
    "gn:dem":1497,
    "gn:feature_class":"P",
    "gn:feature_code":"PPL",
    "gn:name":"Kal\u0101teh-ye M\u012b\u0101n",
    "gn:population":0,
    "gn:timezone":"Asia/Tehran",
    "iso:country":"IR",
    "name:ara_x_preferred":[
        "\u0643\u0644\u0627\u062a\u0647 \u0645\u064a\u0627\u0646"
    ],
    "name:fas_x_preferred":[
        "Kal\u0101teh-ye M\u012b\u0101n"
    ],
    "name:fas_x_variant":[
        "\u06a9\u0644\u0627\u062a\u0647 \u0645\u064a\u0627\u0646",
        "\u06a9\u0644\u0627\u062a\u0647 \u0645\u06cc\u0627\u0646"
    ],
    "wof:name":"Kalateh-ye Mian",
    "wof:placetype":"locality"
},
  "geometry": {"coordinates":[58.96916,34.17542],"type":"Point"}
}