{
  "type": "Feature",
  "properties": {
    "gn:admin1_code":"32",
    "gn:asciiname":"Qeshlaq-e Ebrahim",
    "gn:country_code":"IR",
    "gn:dem":170,
    "gn:feature_class":"P",
    "gn:feature_code":"PPL",
    "gn:name":"Qeshl\u0101q-e Ebr\u0101h\u012bm",
    "gn:population":0,
    "gn:timezone":"Asia/Tehran",
    "iso:country":"IR",
    "name:fas_x_preferred":[
        "\u0627\u0650\u0628\u0631\u0627\u0647\u064a\u0645 \u0643\u064e\u0646\u062f\u0626 \u0639\u064f\u0644\u064a\u0627"
    ],
    "name:fas_x_variant":[
        "\u0642\u0634\u0644\u0627\u0642 \u0627\u0628\u0631\u0627\u0647\u064a\u0645",
        "Ebr\u0101h\u012bm Kand\u012b-ye \u2018Oly\u0101",
        "Qeshl\u0101q-e Ebr\u0101h\u012bm"
    ],
    "wof:name":"Qeshlaq-e Ebrahim",
    "wof:placetype":"locality"
},
  "geometry": {"coordinates":[47.7963,39.5286],"type":"Point"}
}