{
  "type": "Feature",
  "properties": {
    "gn:admin1_code":"23",
    "gn:asciiname":"Pasil",
    "gn:country_code":"IR",
    "gn:dem":1389,
    "gn:feature_class":"P",
    "gn:feature_code":"PPL",
    "gn:name":"Pas\u012bl",
    "gn:population":0,
    "gn:timezone":"Asia/Tehran",
    "iso:country":"IR",
    "name:fas_x_preferred":[
        "\u067e\u0633\u064a\u0644"
    ],
    "name:fas_x_variant":[
        "\u067e\u0633\u064a\u0631",
        "Pas\u012bl"
    ],
    "name:und_x_variant":[
        "Pas\u012br"
    ],
    "wof:name":"Pasil",
    "wof:placetype":"locality"
},
  "geometry": {"coordinates":[48.8748,33.3474],"type":"Point"}
}