{
  "type": "Feature",
  "properties": {
    "gn:admin1_code":"16",
    "gn:asciiname":"Hajji `Abdol",
    "gn:country_code":"IR",
    "gn:dem":1761,
    "gn:feature_class":"P",
    "gn:feature_code":"PPL",
    "gn:name":"\u1e28\u0101jj\u012b \u2018Abdol",
    "gn:population":0,
    "gn:timezone":"Asia/Tehran",
    "iso:country":"IR",
    "name:fas_x_preferred":[
        "\u062d\u0627\u062c\u06cc \u0639\u064e\u0628\u062f\u064f\u0644"
    ],
    "name:fas_x_variant":[
        "\u062d\u0627\u062c\u0651\u06cc \u0639\u0628\u062f\u0644",
        "\u1e28\u0101jj\u012b \u2018Abdol"
    ],
    "name:und_x_variant":[
        "H\u0101ji \u2018Abdul",
        "\u1e28\u0101j\u012b \u2018Abdol"
    ],
    "wof:name":"Hajji `Abdol",
    "wof:placetype":"locality"
},
  "geometry": {"coordinates":[46.2394,35.89],"type":"Point"}
}