{
  "type": "Feature",
  "properties": {
    "gn:admin1_code":"7",
    "gn:asciiname":"Zeynabad",
    "gn:country_code":"IR",
    "gn:dem":1120,
    "gn:feature_class":"P",
    "gn:feature_code":"PPL",
    "gn:name":"Zeyn\u0101b\u0101d",
    "gn:population":0,
    "gn:timezone":"Asia/Tehran",
    "iso:country":"IR",
    "name:fas_x_preferred":[
        "\u0632\u06cc\u0646 \u0622\u0628\u0627\u062f"
    ],
    "name:fas_x_variant":[
        "Zeyn\u0101b\u0101d-e Sang\u012b",
        "Zeyn\u0101b\u0101d",
        "\u0632\u06cc\u0646\u200c\u0622\u0628\u0627\u062f \u0633\u0646\u06af\u06cc"
    ],
    "name:msa_x_preferred":[
        "Zeynabad-e Sangi"
    ],
    "name:und_x_variant":[
        "Zin Abad"
    ],
    "wof:name":"Zeynabad",
    "wof:placetype":"locality"
},
  "geometry": {"coordinates":[54.6123,28.6874],"type":"Point"}
}