{
  "type": "Feature",
  "properties": {
    "gn:admin1_code":"1",
    "gn:asciiname":"Hajji Panirlu",
    "gn:country_code":"IR",
    "gn:dem":1287,
    "gn:feature_class":"P",
    "gn:feature_code":"PPL",
    "gn:name":"\u1e28\u0101jj\u012b Pan\u012brl\u016b",
    "gn:population":0,
    "gn:timezone":"Asia/Tehran",
    "iso:country":"IR",
    "name:azb_x_preferred":[
        "\u062d\u0627\u062c\u06cc \u067e\u06cc\u0631\u0644\u06cc"
    ],
    "name:aze_x_preferred":[
        "Hac\u0131pirli"
    ],
    "name:ceb_x_preferred":[
        "\u1e28\u0101jj\u012b Pan\u012brl\u016b"
    ],
    "name:fas_x_preferred":[
        "\u062d\u0627\u062c\u0651\u06cc \u067e\u064a\u0631\u0644\u0648"
    ],
    "name:fas_x_variant":[
        "\u062d\u0627\u062c\u0651\u06cc \u067e\u0646\u06cc\u0631\u0644\u0648",
        "\u1e28\u0101jj\u012b P\u012brl\u016b",
        "\u1e28\u0101jj\u012b Pan\u012brl\u016b",
        "\u062d\u0627\u062c\u06cc \u067e\u06cc\u0631\u0644\u0648"
    ],
    "name:msa_x_preferred":[
        "Hajji Pirlu"
    ],
    "name:pol_x_preferred":[
        "Had\u017ci Pirlu"
    ],
    "name:swe_x_preferred":[
        "\u1e28\u0101jj\u012b Pan\u012brl\u016b"
    ],
    "name:ukr_x_preferred":[
        "\u0425\u0430\u0434\u0436\u0456-\u041f\u0456\u0440\u043b\u0443"
    ],
    "wof:name":"Hajji Panirlu",
    "wof:placetype":"locality"
},
  "geometry": {"coordinates":[45.2073,37.5348],"type":"Point"}
}