{
  "type": "Feature",
  "properties": {
    "gn:admin1_code":"1",
    "gn:asciiname":"Torshab",
    "gn:country_code":"IR",
    "gn:dem":1016,
    "gn:feature_class":"P",
    "gn:feature_code":"PPL",
    "gn:name":"Torsh\u0101b",
    "gn:population":0,
    "gn:timezone":"Asia/Tehran",
    "iso:country":"IR",
    "name:fas_x_preferred":[
        "\u062a\u064f\u0631\u0634\u0627\u0628"
    ],
    "name:fas_x_variant":[
        "\u062a\u0631\u0634\u0627\u0628",
        "Torsh\u0101b"
    ],
    "wof:name":"Torshab",
    "wof:placetype":"locality"
},
  "geometry": {"coordinates":[45.1659,39.028],"type":"Point"}
}