{
  "type": "Feature",
  "properties": {
    "gn:admin1_code":"8",
    "gn:asciiname":"Sij",
    "gn:country_code":"IR",
    "gn:dem":594,
    "gn:feature_class":"P",
    "gn:feature_code":"PPL",
    "gn:name":"S\u012bj",
    "gn:population":0,
    "gn:timezone":"Asia/Tehran",
    "iso:country":"IR",
    "name:fas_x_preferred":[
        "\u0633\u06cc\u062c"
    ],
    "name:fas_x_variant":[
        "S\u012bj"
    ],
    "name:glk_x_preferred":[
        "\u0633\u064a\u062c"
    ],
    "name:msa_x_preferred":[
        "Sij"
    ],
    "name:ukr_x_preferred":[
        "\u0421\u0456\u0434\u0436"
    ],
    "wof:name":"Sij",
    "wof:placetype":"locality"
},
  "geometry": {"coordinates":[48.6329,38.3918],"type":"Point"}
}