{
  "type": "Feature",
  "properties": {
    "gn:admin1_code":"41.0",
    "gn:asciiname":"`Aladar-e Pa'in",
    "gn:country_code":"IR",
    "gn:dem":1632,
    "gn:feature_class":"P",
    "gn:feature_code":"PPLF",
    "gn:name":"\u2018Al\u0101dar-e P\u0101\u2019\u012bn",
    "gn:population":0,
    "gn:timezone":"Asia/Tehran",
    "iso:country":"IR",
    "name:fas_x_preferred":[
        "\u2018Al\u0101dar-e P\u0101\u2019\u012bn"
    ],
    "name:fas_x_variant":[
        "\u0639\u0644\u0627\u062f\u0631 \u067e\u0627\u0626\u064a\u0646",
        "\u0627\u0644\u0627\u062f\u0631 \u067e\u0627\u0626\u064a\u0646"
    ],
    "name:und_x_variant":[
        "Al\u0101dar-e P\u0101\u2019\u012bn"
    ],
    "wof:name":"`Aladar-e Pa'in",
    "wof:placetype":"locality"
},
  "geometry": {"coordinates":[59.25196999999999,32.82204],"type":"Point"}
}