{
  "type": "Feature",
  "properties": {
    "gn:admin1_code":"4.0",
    "gn:asciiname":"Tangak",
    "gn:country_code":"IR",
    "gn:dem":2206,
    "gn:feature_class":"P",
    "gn:feature_code":"PPL",
    "gn:name":"Tangak",
    "gn:population":0,
    "gn:timezone":"Asia/Tehran",
    "iso:country":"IR",
    "name:fas_x_preferred":[
        "\u062a\u0646\u06af\u06a9"
    ],
    "name:fas_x_variant":[
        "Tank\u016bk"
    ],
    "wof:name":"Tangak",
    "wof:placetype":"locality"
},
  "geometry": {"coordinates":[60.8886,28.6568],"type":"Point"}
}