{
  "type": "Feature",
  "properties": {
    "gn:admin1_code":"7.0",
    "gn:asciiname":"Argu",
    "gn:country_code":"IR",
    "gn:dem":1339,
    "gn:feature_class":"P",
    "gn:feature_code":"PPL",
    "gn:name":"\u0100rg\u016b",
    "gn:population":0,
    "gn:timezone":"Asia/Tehran",
    "iso:country":"IR",
    "name:fas_x_preferred":[
        "\u0622\u0631\u06af\u0648"
    ],
    "name:fas_x_variant":[
        "\u0100rj\u016byeh",
        "\u0100rg\u016b",
        "\u0627\u0631\u062c\u0648\u06cc\u0647"
    ],
    "name:msa_x_preferred":[
        "Arjuyeh"
    ],
    "name:und_x_variant":[
        "Arg\u016b"
    ],
    "wof:name":"Argu",
    "wof:placetype":"locality"
},
  "geometry": {"coordinates":[52.8713,28.7318],"type":"Point"}
}