{
  "type": "Feature",
  "properties": {
    "gn:admin1_code":"29",
    "gn:asciiname":"Divan Morad-e `Olya",
    "gn:country_code":"IR",
    "gn:dem":1080,
    "gn:feature_class":"P",
    "gn:feature_code":"PPL",
    "gn:name":"D\u012bv\u0101n Mor\u0101d-e \u2018Oly\u0101",
    "gn:population":0,
    "gn:timezone":"Asia/Tehran",
    "iso:country":"IR",
    "name:fas_x_preferred":[
        "\u062f\u06cc\u0648\u0627\u0646 \u0645\u0631\u0627\u062f \u0639\u0644\u06cc\u0627"
    ],
    "name:fas_x_variant":[
        "Z\u012b\u0101rat-e D\u012bv\u0101n Mor\u0101d-e B\u0101l\u0101",
        "D\u012bv\u0101n Mor\u0101d-e \u2018Oly\u0101"
    ],
    "name:und_x_variant":[
        "Z\u012b\u0101rat-e D\u012bv\u0101n Mor\u0101d \u2018Oly\u0101"
    ],
    "wof:name":"Divan Morad-e `Olya",
    "wof:placetype":"locality"
},
  "geometry": {"coordinates":[57.4898,27.9783],"type":"Point"}
}