{
  "type": "Feature",
  "properties": {
    "gn:admin1_code":"42",
    "gn:asciiname":"Abad Meshk",
    "gn:country_code":"IR",
    "gn:dem":1439,
    "gn:feature_class":"P",
    "gn:feature_code":"PPL",
    "gn:name":"\u0100b\u0101d Meshk",
    "gn:population":0,
    "gn:timezone":"Asia/Tehran",
    "iso:country":"IR",
    "name:fas_x_preferred":[
        "\u0622\u0628\u0627\u062f \u0645\u0634\u06a9"
    ],
    "name:fas_x_variant":[
        "\u0100b\u0101d Meshk"
    ],
    "wof:name":"Abad Meshk",
    "wof:placetype":"locality"
},
  "geometry": {"coordinates":[59.31634,36.77984],"type":"Point"}
}