{
  "type": "Feature",
  "properties": {
    "gn:admin1_code":"15.0",
    "gn:asciiname":"Abu Shenan-e `Olya",
    "gn:country_code":"IR",
    "gn:dem":29,
    "gn:feature_class":"P",
    "gn:feature_code":"PPL",
    "gn:name":"Ab\u016b Shen\u0101n-e \u2018Oly\u0101",
    "gn:population":0,
    "gn:timezone":"Asia/Tehran",
    "iso:country":"IR",
    "name:fas_x_preferred":[
        "\u0627\u0628\u0648 \u0634\u0646\u0627\u0646 \u0639\u0644\u06cc\u0627"
    ],
    "name:fas_x_variant":[
        "Ab\u016b Shen\u0101n-e \u2018Oly\u0101",
        "Ab\u016b Shen\u0101n-e B\u0101l\u0101"
    ],
    "wof:name":"Abu Shenan-e `Olya",
    "wof:placetype":"locality"
},
  "geometry": {"coordinates":[49.45422,30.92007000000001],"type":"Point"}
}