{
  "type": "Feature",
  "properties": {
    "gn:admin1_code":"7",
    "gn:asciiname":"Chah-e Sakhteman",
    "gn:country_code":"IR",
    "gn:dem":1603,
    "gn:feature_class":"P",
    "gn:feature_code":"PPL",
    "gn:name":"Ch\u0101h-e S\u0101khtem\u0101n",
    "gn:population":0,
    "gn:timezone":"Asia/Tehran",
    "iso:country":"IR",
    "name:fas_x_preferred":[
        "\u0686\u0627\u0647 \u0633\u0627\u062e\u062a\u0645\u0627\u0646"
    ],
    "name:fas_x_variant":[
        "Ch\u0101h-e S\u0101khtem\u0101n"
    ],
    "wof:name":"Chah-e Sakhteman",
    "wof:placetype":"locality"
},
  "geometry": {"coordinates":[55.0515,28.8126],"type":"Point"}
}