{
  "type": "Feature",
  "properties": {
    "gn:admin1_code":"37",
    "gn:asciiname":"Lamalang-e Gharbi",
    "gn:country_code":"IR",
    "gn:dem":34,
    "gn:feature_class":"P",
    "gn:feature_code":"PPL",
    "gn:name":"L\u0101malang-e Gharb\u012b",
    "gn:population":0,
    "gn:timezone":"Asia/Tehran",
    "iso:country":"IR",
    "name:fas_x_preferred":[
        "\u0644\u0627\u0644\u064e\u0646\u06af"
    ],
    "name:fas_x_variant":[
        "L\u0101mlang",
        "\u0644\u0627\u0645\u0644\u0646\u06af",
        "\u0644\u0627\u0645\u0644\u0646\u06af \u063a\u0631\u0628\u06cc"
    ],
    "name:und_x_variant":[
        "L\u0101lang",
        "\u0644\u0627\u0645\u0644\u0646\u06af",
        "L\u0101malang-e Gharb\u012b"
    ],
    "wof:name":"Lamalang-e Gharbi",
    "wof:placetype":"locality"
},
  "geometry": {"coordinates":[54.36919,36.86138],"type":"Point"}
}