{
  "type": "Feature",
  "properties": {
    "gn:admin1_code":"4.0",
    "gn:asciiname":"Siani",
    "gn:country_code":"IR",
    "gn:dem":44,
    "gn:feature_class":"P",
    "gn:feature_code":"PPL",
    "gn:name":"S\u012b\u0101n\u012b",
    "gn:population":0,
    "gn:timezone":"Asia/Tehran",
    "iso:country":"IR",
    "name:ara_x_preferred":[
        "\u0633\u0627\u064a\u0627\u0646\u064a"
    ],
    "name:fas_x_preferred":[
        "S\u0101y\u0101n\u012b"
    ],
    "name:fas_x_variant":[
        "S\u012b\u0101n\u012b",
        "\u0633\u06cc\u0627\u0646\u06cc",
        "\u0633\u0627\u06cc\u0627\u0646\u06cc"
    ],
    "wof:name":"Siani",
    "wof:placetype":"locality"
},
  "geometry": {"coordinates":[60.97329000000001,25.65879],"type":"Point"}
}