{
  "type": "Feature",
  "properties": {
    "gn:admin1_code":"7",
    "gn:asciiname":"Qasr-e Ahmad",
    "gn:country_code":"IR",
    "gn:dem":1512,
    "gn:feature_class":"P",
    "gn:feature_code":"PPL",
    "gn:name":"Qa\u015fr-e A\u1e29mad",
    "gn:population":0,
    "gn:timezone":"Asia/Tehran",
    "iso:country":"IR",
    "name:fas_x_preferred":[
        "\u0642\u0635\u0631 \u0627\u062d\u0645\u062f"
    ],
    "name:fas_x_variant":[
        "Qa\u015fr-e A\u1e29mad"
    ],
    "name:und_x_variant":[
        "Kasr A\u1e29mad",
        "Qasr Ahmad"
    ],
    "wof:name":"Qasr-e Ahmad",
    "wof:placetype":"locality"
},
  "geometry": {"coordinates":[52.7663,29.1742],"type":"Point"}
}