{
  "type": "Feature",
  "properties": {
    "gn:admin1_code":"7.0",
    "gn:asciiname":"Abu `Asgar",
    "gn:country_code":"IR",
    "gn:dem":672,
    "gn:feature_class":"P",
    "gn:feature_code":"PPL",
    "gn:name":"Ab\u016b \u2018Asgar",
    "gn:population":0,
    "gn:timezone":"Asia/Tehran",
    "iso:country":"IR",
    "name:fas_x_preferred":[
        "\u0627\u0628\u0648 \u0639\u0633\u06af\u0631"
    ],
    "name:fas_x_variant":[
        "Ab\u016b \u2018Asgar"
    ],
    "name:und_x_variant":[
        "Ab\u016b \u2018Askar"
    ],
    "wof:name":"Abu `Asgar",
    "wof:placetype":"locality"
},
  "geometry": {"coordinates":[52.6365,28.4177],"type":"Point"}
}