{
  "type": "Feature",
  "properties": {
    "gn:admin1_code":"28.0",
    "gn:asciiname":"Sefidu",
    "gn:country_code":"IR",
    "gn:dem":1224,
    "gn:feature_class":"P",
    "gn:feature_code":"PPLF",
    "gn:name":"Sef\u012bd\u016b",
    "gn:population":0,
    "gn:timezone":"Asia/Tehran",
    "iso:country":"IR",
    "name:fas_x_preferred":[
        "Sef\u012bd\u016b"
    ],
    "name:fas_x_variant":[
        "\u0633\u0641\u064a\u062f\u0648"
    ],
    "wof:name":"Sefidu",
    "wof:placetype":"locality"
},
  "geometry": {"coordinates":[54.72625,33.9287],"type":"Point"}
}