{
  "type": "Feature",
  "properties": {
    "gn:admin1_code":"10",
    "gn:asciiname":"Kalegah",
    "gn:country_code":"IR",
    "gn:dem":1001,
    "gn:feature_class":"P",
    "gn:feature_code":"PPL",
    "gn:name":"Kalegah",
    "gn:population":0,
    "gn:timezone":"Asia/Tehran",
    "iso:country":"IR",
    "name:fas_x_preferred":[
        "\u0643\u064e\u0644\u0650\u06af\u064e\u0647"
    ],
    "name:fas_x_variant":[
        "\u06a9\u0644\u06af\u0647"
    ],
    "wof:name":"Kalegah",
    "wof:placetype":"locality"
},
  "geometry": {"coordinates":[47.4157,33.7581],"type":"Point"}
}