{
  "type": "Feature",
  "properties": {
    "gn:admin1_code":"33",
    "gn:asciiname":"Qazanchay",
    "gn:country_code":"IR",
    "gn:dem":2174,
    "gn:feature_class":"P",
    "gn:feature_code":"PPL",
    "gn:name":"Q\u0101z\u0101nch\u0101y",
    "gn:population":0,
    "gn:timezone":"Asia/Tehran",
    "iso:country":"IR",
    "name:ara_x_preferred":[
        "\u0642\u0627\u0632\u0627\u0646\u062a\u0634\u0627\u064a"
    ],
    "name:ceb_x_preferred":[
        "Q\u0101z\u0101nch\u0101y"
    ],
    "name:fas_x_preferred":[
        "\u0642\u0627\u0632\u0627\u0646\u0686\u0627\u06cc"
    ],
    "name:msa_x_preferred":[
        "Qazan Chay"
    ],
    "name:swe_x_preferred":[
        "Q\u0101z\u0101nch\u0101y"
    ],
    "wof:name":"Qazanchay",
    "wof:placetype":"locality"
},
  "geometry": {"coordinates":[46.6451,37.7183],"type":"Point"}
}