{
  "type": "Feature",
  "properties": {
    "gn:admin1_code":"25",
    "gn:asciiname":"Judaneh",
    "gn:country_code":"IR",
    "gn:dem":1238,
    "gn:feature_class":"P",
    "gn:feature_code":"PPL",
    "gn:name":"J\u016bd\u0101neh",
    "gn:population":0,
    "gn:timezone":"Asia/Tehran",
    "iso:country":"IR",
    "name:fas_x_preferred":[
        "\u062c\u064f\u0648\u062f\u0627\u0646\u0650\u0647"
    ],
    "name:fas_x_variant":[
        "Jowd\u0101neh",
        "\u062c\u0648\u062f\u0627\u0646\u0647"
    ],
    "name:und_x_variant":[
        "J\u016bd\u0101neh"
    ],
    "wof:name":"Judaneh",
    "wof:placetype":"locality"
},
  "geometry": {"coordinates":[55.50846,36.38173],"type":"Point"}
}