{
  "type": "Feature",
  "properties": {
    "gn:admin1_code":"33",
    "gn:asciiname":"Siran",
    "gn:country_code":"IR",
    "gn:dem":1371,
    "gn:feature_class":"P",
    "gn:feature_code":"PPL",
    "gn:name":"S\u012br\u0101n",
    "gn:population":0,
    "gn:timezone":"Asia/Tehran",
    "iso:country":"IR",
    "name:fas_x_preferred":[
        "\u0633\u064a\u0631\u0627\u0646"
    ],
    "name:fas_x_variant":[
        "S\u012br\u0101n",
        "\u0633\u06cc\u0631\u0627\u0646"
    ],
    "name:msa_x_preferred":[
        "Siran"
    ],
    "wof:name":"Siran",
    "wof:placetype":"locality"
},
  "geometry": {"coordinates":[47.08729,38.96305],"type":"Point"}
}