{
  "type": "Feature",
  "properties": {
    "gn:admin1_code":"33",
    "gn:asciiname":"Huliq",
    "gn:country_code":"IR",
    "gn:dem":1678,
    "gn:feature_class":"P",
    "gn:feature_code":"PPL",
    "gn:name":"H\u016bl\u012bq",
    "gn:population":0,
    "gn:timezone":"Asia/Tehran",
    "iso:country":"IR",
    "name:ceb_x_preferred":[
        "H\u016bl\u012bq"
    ],
    "name:fas_x_preferred":[
        "\u0647\u0648\u0644\u06cc\u0642"
    ],
    "name:fas_x_variant":[
        "H\u016bl\u012bq"
    ],
    "name:msa_x_preferred":[
        "Huliq"
    ],
    "name:swe_x_preferred":[
        "H\u016bl\u012bq"
    ],
    "wof:name":"Huliq",
    "wof:placetype":"locality"
},
  "geometry": {"coordinates":[47.5571,37.8507],"type":"Point"}
}