{
  "type": "Feature",
  "properties": {
    "gn:admin1_code":"13",
    "gn:asciiname":"Darreh Khalil",
    "gn:country_code":"IR",
    "gn:dem":1712,
    "gn:feature_class":"P",
    "gn:feature_code":"PPL",
    "gn:name":"Darreh Khal\u012bl",
    "gn:population":0,
    "gn:timezone":"Asia/Tehran",
    "iso:country":"IR",
    "name:fas_x_preferred":[
        "\u062f\u0631\u0651\u0647 \u062e\u0644\u06cc\u0644"
    ],
    "name:fas_x_variant":[
        "Darreh Khal\u012bl"
    ],
    "wof:name":"Darreh Khalil",
    "wof:placetype":"locality"
},
  "geometry": {"coordinates":[47.3616,34.7213],"type":"Point"}
}