{
  "type": "Feature",
  "properties": {
    "gn:admin1_code":"28",
    "gn:asciiname":"Jowsheqan-e Qali",
    "gn:country_code":"IR",
    "gn:dem":2258,
    "gn:feature_class":"P",
    "gn:feature_code":"PPL",
    "gn:name":"Jowsheq\u0101n-e Q\u0101l\u012b",
    "gn:population":0,
    "gn:timezone":"Asia/Tehran",
    "iso:country":"IR",
    "name:fas_x_preferred":[
        "\u062c\u0648\u0634\u0642\u0627\u0646 \u0642\u0627\u0644\u06cc"
    ],
    "name:fas_x_variant":[
        "Jowsheq\u0101n-e Q\u0101l\u012b"
    ],
    "name:und_x_variant":[
        "J\u016bshq\u0101n Q\u0101li",
        "Jowshaq\u0101n-e-Q\u0101l\u012b",
        "Jowsheq\u0101n"
    ],
    "wof:name":"Jowsheqan-e Qali",
    "wof:placetype":"locality"
},
  "geometry": {"coordinates":[51.212,33.5888],"type":"Point"}
}