{
  "type": "Feature",
  "properties": {
    "gn:admin1_code":"29",
    "gn:asciiname":"Taherabad",
    "gn:country_code":"IR",
    "gn:dem":1750,
    "gn:feature_class":"P",
    "gn:feature_code":"PPL",
    "gn:name":"\u0162\u0101her\u0101b\u0101d",
    "gn:population":0,
    "gn:timezone":"Asia/Tehran",
    "iso:country":"IR",
    "name:aze_x_preferred":[
        "Tahirabad"
    ],
    "name:fas_x_preferred":[
        "\u0162\u0101her\u0101b\u0101d"
    ],
    "wof:name":"Taherabad",
    "wof:placetype":"locality"
},
  "geometry": {"coordinates":[56.99528000000001,30.30222],"type":"Point"}
}