{
  "type": "Feature",
  "properties": {
    "gn:admin1_code":"4.0",
    "gn:asciiname":"Esma`ilabad",
    "gn:country_code":"IR",
    "gn:dem":1371,
    "gn:feature_class":"P",
    "gn:feature_code":"PPL",
    "gn:name":"Esm\u0101\u2018\u012bl\u0101b\u0101d",
    "gn:population":0,
    "gn:timezone":"Asia/Tehran",
    "iso:country":"IR",
    "name:fas_x_preferred":[
        "Taqazz\u016bk"
    ],
    "name:fas_x_variant":[
        "\u0627\u0633\u0645\u0627\u0639\u064a\u0644 \u0622\u0628\u0627\u062f",
        "\u062a\u0627\u063a\u0632\u0648\u0627\u0631"
    ],
    "name:und_x_variant":[
        "Esm\u0101\u2018\u012bl\u0101b\u0101d",
        "T\u0101ghazv\u0101r"
    ],
    "wof:name":"Esma`ilabad",
    "wof:placetype":"locality"
},
  "geometry": {"coordinates":[61.51102,28.04378],"type":"Point"}
}