{
  "type": "Feature",
  "properties": {
    "gn:admin1_code":"3",
    "gn:asciiname":"Tereki",
    "gn:country_code":"IR",
    "gn:dem":1712,
    "gn:feature_class":"P",
    "gn:feature_code":"PPL",
    "gn:name":"Terek\u012b",
    "gn:population":0,
    "gn:timezone":"Asia/Tehran",
    "iso:country":"IR",
    "name:ceb_x_preferred":[
        "Terek\u012b"
    ],
    "name:fas_x_preferred":[
        "\u062a\u0650\u0631\u0643\u06cc"
    ],
    "name:fas_x_variant":[
        "Terek\u012b",
        "\u0628\u064e\u0632\u064e\u0631\u06af\u0627\u0646",
        "\u062a\u0631\u06a9\u06cc"
    ],
    "name:msa_x_preferred":[
        "Tereki"
    ],
    "name:swe_x_preferred":[
        "Terek\u012b"
    ],
    "name:und_x_variant":[
        "Bazarg\u0101n",
        "Terk\u012b"
    ],
    "wof:name":"Tereki",
    "wof:placetype":"locality"
},
  "geometry": {"coordinates":[49.93368,32.36651],"type":"Point"}
}