{
  "type": "Feature",
  "properties": {
    "gn:admin1_code":"13",
    "gn:asciiname":"Darreh Ti",
    "gn:country_code":"IR",
    "gn:dem":1386,
    "gn:feature_class":"P",
    "gn:feature_code":"PPL",
    "gn:name":"Darreh T\u012b",
    "gn:population":0,
    "gn:timezone":"Asia/Tehran",
    "iso:country":"IR",
    "name:fas_x_preferred":[
        "Darreh T\u012b"
    ],
    "wof:name":"Darreh Ti",
    "wof:placetype":"locality"
},
  "geometry": {"coordinates":[46.56667,34.11667],"type":"Point"}
}