{
  "type": "Feature",
  "properties": {
    "gn:admin1_code":"15",
    "gn:asciiname":"Kheyt-e Zowbeyd",
    "gn:country_code":"IR",
    "gn:dem":26,
    "gn:feature_class":"P",
    "gn:feature_code":"PPL",
    "gn:name":"Khey\u0163-e Zowbeyd",
    "gn:population":0,
    "gn:timezone":"Asia/Tehran",
    "iso:country":"IR",
    "name:fas_x_preferred":[
        "\u062e\u06cc\u0637 \u0632\u0628\u06cc\u062f"
    ],
    "name:fas_x_variant":[
        "Khey\u0163-e Zobeyd",
        "\u062e\u06cc\u0637 \u0632\u0648\u0628\u06cc\u062f",
        "\u062e\u06cc\u0637 \u0632\u0648\u06cc\u062f"
    ],
    "name:und_x_variant":[
        "Boneh-ye \u0162\u0101her",
        "Khey\u0163-e Zowbeyd",
        "Khey\u0163-e Zav\u012bd"
    ],
    "wof:name":"Kheyt-e Zowbeyd",
    "wof:placetype":"locality"
},
  "geometry": {"coordinates":[49.76385,30.69334000000001],"type":"Point"}
}