{
  "type": "Feature",
  "properties": {
    "gn:admin1_code":"4.0",
    "gn:asciiname":"Sheybani",
    "gn:country_code":"IR",
    "gn:dem":474,
    "gn:feature_class":"P",
    "gn:feature_code":"PPL",
    "gn:name":"Sheyb\u0101n\u012b",
    "gn:population":0,
    "gn:timezone":"Asia/Tehran",
    "iso:country":"IR",
    "name:fas_x_preferred":[
        "\u0634\u06cc\u0628\u0627\u0646\u06cc"
    ],
    "name:fas_x_variant":[
        "Sheyb\u0101n\u012b"
    ],
    "wof:name":"Sheybani",
    "wof:placetype":"locality"
},
  "geometry": {"coordinates":[61.3014,30.9077],"type":"Point"}
}