{
  "type": "Feature",
  "properties": {
    "gn:admin1_code":"5.0",
    "gn:asciiname":"Sar Darreh",
    "gn:country_code":"IR",
    "gn:dem":1586,
    "gn:feature_class":"P",
    "gn:feature_code":"PPL",
    "gn:name":"Sar Darreh",
    "gn:population":0,
    "gn:timezone":"Asia/Tehran",
    "iso:country":"IR",
    "name:ceb_x_preferred":[
        "Sar Darreh"
    ],
    "name:fas_x_preferred":[
        "\u0633\u0631 \u062f\u0631\u0647"
    ],
    "name:swe_x_preferred":[
        "Sar Darreh"
    ],
    "wof:name":"Sar Darreh",
    "wof:placetype":"locality"
},
  "geometry": {"coordinates":[50.4796,31.23543],"type":"Point"}
}