{
  "type": "Feature",
  "properties": {
    "gn:admin1_code":"33",
    "gn:asciiname":"Aqcheh Kand",
    "gn:country_code":"IR",
    "gn:dem":2000,
    "gn:feature_class":"P",
    "gn:feature_code":"PPL",
    "gn:name":"\u0100qcheh Kand",
    "gn:population":0,
    "gn:timezone":"Asia/Tehran",
    "iso:country":"IR",
    "name:ceb_x_preferred":[
        "\u0100qcheh Kand"
    ],
    "name:fas_x_preferred":[
        "\u0622\u0642\u0686\u0647 \u06a9\u0646\u062f"
    ],
    "name:fas_x_variant":[
        "\u0100ghcheh Kand",
        "\u0100qcheh Kand",
        "\u0622\u063a\u0686\u0647\u200c\u06a9\u0646\u062f"
    ],
    "name:msa_x_preferred":[
        "Aghcheh Kand"
    ],
    "name:pnb_x_preferred":[
        "\u062f\u06c1\u0633\u062a\u0627\u0646 \u0622\u0642\u0686\u0647 \u06a9\u0646\u062f"
    ],
    "wof:name":"Aqcheh Kand",
    "wof:placetype":"locality"
},
  "geometry": {"coordinates":[47.25,37.8066],"type":"Point"}
}