{
  "type": "Feature",
  "properties": {
    "gn:admin1_code":"16.0",
    "gn:asciiname":"Havar Karim",
    "gn:country_code":"IR",
    "gn:dem":2309,
    "gn:feature_class":"P",
    "gn:feature_code":"PPL",
    "gn:name":"Hav\u0101r Kar\u012bm",
    "gn:population":0,
    "gn:timezone":"Asia/Tehran",
    "iso:country":"IR",
    "name:fas_x_preferred":[
        "\u0647\u064e\u0648\u0627\u0631 \u0643\u064e\u0631\u064a\u0645"
    ],
    "name:fas_x_variant":[
        "Hav\u0101r Kar\u012bm"
    ],
    "wof:name":"Havar Karim",
    "wof:placetype":"locality"
},
  "geometry": {"coordinates":[46.91667,35.65],"type":"Point"}
}