{
  "type": "Feature",
  "properties": {
    "gn:admin1_code":"26.0",
    "gn:asciiname":"Murud",
    "gn:country_code":"IR",
    "gn:dem":2119,
    "gn:feature_class":"P",
    "gn:feature_code":"PPL",
    "gn:name":"M\u016br\u016bd",
    "gn:population":0,
    "gn:timezone":"Asia/Tehran",
    "iso:country":"IR",
    "name:fas_x_preferred":[
        "\u0645\u0648\u0631\u0648\u062f"
    ],
    "wof:name":"Murud",
    "wof:placetype":"locality"
},
  "geometry": {"coordinates":[51.17139,36.00417],"type":"Point"}
}