{
  "type": "Feature",
  "properties": {
    "gn:admin1_code":"26.0",
    "gn:asciiname":"Murud",
    "gn:country_code":"IR",
    "gn:dem":2119,
    "gn:feature_class":"P",
    "gn:feature_code":"PPL",
    "gn:name":"M\u016br\u016bd",
    "gn:population":0,
    "gn:timezone":"Asia/Tehran",
    "iso:country":"IR",
    "name:ben_x_preferred":[
        "\u09ae\u09c1\u09b0\u09c1\u09a6"
    ],
    "name:bpy_x_preferred":[
        "\u09ae\u09c1\u09b0\u09c1\u09a6"
    ],
    "name:ceb_x_preferred":[
        "Murud"
    ],
    "name:fas_x_preferred":[
        "\u0645\u0648\u0631\u0648\u062f"
    ],
    "name:fas_x_variant":[
        "M\u016br\u016bd"
    ],
    "name:mar_x_preferred":[
        "\u092e\u0941\u0930\u0942\u0921 \u0924\u093e\u0932\u0941\u0915\u093e"
    ],
    "name:msa_x_preferred":[
        "Murud"
    ],
    "name:new_x_preferred":[
        "\u092e\u0941\u0930\u0941\u0926"
    ],
    "name:rus_x_preferred":[
        "\u041c\u0443\u0440\u0443\u0434"
    ],
    "name:swe_x_preferred":[
        "Murud"
    ],
    "wof:name":"Murud",
    "wof:placetype":"locality"
},
  "geometry": {"coordinates":[51.17139,36.00417],"type":"Point"}
}