{
  "type": "Feature",
  "properties": {
    "gn:admin1_code":"44",
    "gn:asciiname":"Sar Ziarat",
    "gn:country_code":"IR",
    "gn:dem":1984,
    "gn:feature_class":"P",
    "gn:feature_code":"PPL",
    "gn:name":"Sar Z\u012b\u0101rat",
    "gn:population":0,
    "gn:timezone":"Asia/Tehran",
    "iso:country":"IR",
    "name:fas_x_preferred":[
        "\u0633\u0631 \u0632\u064a\u0627\u0631\u062a"
    ],
    "name:fas_x_variant":[
        "Sar Z\u012b\u0101rat",
        "\u0633\u0631\u0632\u06cc\u0627\u0631\u062a"
    ],
    "name:msa_x_preferred":[
        "Sar Ziarat"
    ],
    "wof:name":"Sar Ziarat",
    "wof:placetype":"locality"
},
  "geometry": {"coordinates":[51.1082,35.9211],"type":"Point"}
}