{
  "type": "Feature",
  "properties": {
    "gn:admin1_code":"29",
    "gn:asciiname":"Ahereh",
    "gn:country_code":"IR",
    "gn:dem":2604,
    "gn:feature_class":"P",
    "gn:feature_code":"PPLF",
    "gn:name":"A\u1e29ereh",
    "gn:population":0,
    "gn:timezone":"Asia/Tehran",
    "iso:country":"IR",
    "name:fas_x_preferred":[
        "A\u2018ereh"
    ],
    "name:fas_x_variant":[
        "\u0627\u062d\u0631\u0647"
    ],
    "name:und_x_variant":[
        "A\u1e29ereh"
    ],
    "wof:name":"Ahereh",
    "wof:placetype":"locality"
},
  "geometry": {"coordinates":[56.28641,29.64981],"type":"Point"}
}