{
  "type": "Feature",
  "properties": {
    "gn:admin1_code":"16.0",
    "gn:asciiname":"Gandoman",
    "gn:country_code":"IR",
    "gn:dem":1578,
    "gn:elevation":"0.0",
    "gn:feature_class":"P",
    "gn:feature_code":"PPL",
    "gn:name":"Gandom\u0101n",
    "gn:population":0,
    "gn:timezone":"Asia/Tehran",
    "iso:country":"IR",
    "name:fas_x_preferred":[
        "\u06af\u064e\u0646\u062f\u064f\u0645\u0627\u0646"
    ],
    "name:fas_x_variant":[
        "\u06af\u0646\u062f\u0645\u0627\u0646",
        "Gandom\u0101n"
    ],
    "wof:name":"Gandoman",
    "wof:placetype":"locality"
},
  "geometry": {"coordinates":[45.8187,35.9166],"type":"Point"}
}