{
  "type": "Feature",
  "properties": {
    "gn:admin1_code":"16.0",
    "gn:asciiname":"Gandoman",
    "gn:country_code":"IR",
    "gn:dem":1578,
    "gn:elevation":"0.0",
    "gn:feature_class":"P",
    "gn:feature_code":"PPL",
    "gn:name":"Gandom\u0101n",
    "gn:population":0,
    "gn:timezone":"Asia/Tehran",
    "iso:country":"IR",
    "name:ara_x_preferred":[
        "\u063a\u0646\u062f\u0645\u0627\u0646"
    ],
    "name:aze_x_preferred":[
        "G\u0259nd\u00fcman"
    ],
    "name:ceb_x_preferred":[
        "Gandom\u0101n"
    ],
    "name:fas_x_preferred":[
        "\u06af\u064e\u0646\u062f\u064f\u0645\u0627\u0646"
    ],
    "name:fas_x_variant":[
        "\u06af\u0646\u062f\u0645\u0627\u0646",
        "Gandom\u0101n"
    ],
    "name:ita_x_preferred":[
        "Gandoman"
    ],
    "name:mlg_x_preferred":[
        "Gandoman"
    ],
    "name:msa_x_preferred":[
        "Gandoman"
    ],
    "name:rus_x_preferred":[
        "\u0413\u0435\u043d\u0434\u043e\u043c\u0430\u043d"
    ],
    "name:swe_x_preferred":[
        "Gandom\u0101n"
    ],
    "name:tur_x_preferred":[
        "Gendoman"
    ],
    "name:urd_x_preferred":[
        "\u06af\u0646\u062f\u0645\u0627\u0646"
    ],
    "name:zho_x_preferred":[
        "\u7518\u591a\u66fc"
    ],
    "wof:name":"Gandoman",
    "wof:placetype":"locality"
},
  "geometry": {"coordinates":[45.8187,35.9166],"type":"Point"}
}