{
  "type": "Feature",
  "properties": {
    "gn:admin1_code":"7",
    "gn:asciiname":"Tang-e Tizab",
    "gn:country_code":"IR",
    "gn:dem":2117,
    "gn:feature_class":"P",
    "gn:feature_code":"PPL",
    "gn:name":"Tang-e T\u012bz\u0101b",
    "gn:population":0,
    "gn:timezone":"Asia/Tehran",
    "iso:country":"IR",
    "name:fas_x_preferred":[
        "Tang-e T\u012bz\u0101b"
    ],
    "name:fas_x_variant":[
        "Mazra\u2018eh-ye T\u012bz\u0101b",
        "\u062a\u0646\u06af \u062a\u06cc\u0632 \u0622\u0628"
    ],
    "wof:name":"Tang-e Tizab",
    "wof:placetype":"locality"
},
  "geometry": {"coordinates":[51.79071,30.3793],"type":"Point"}
}