{
  "type": "Feature",
  "properties": {
    "gn:admin1_code":"28",
    "gn:asciiname":"Gudarzan",
    "gn:country_code":"IR",
    "gn:dem":2002,
    "gn:feature_class":"P",
    "gn:feature_code":"PPL",
    "gn:name":"G\u016bdarzan",
    "gn:population":0,
    "gn:timezone":"Asia/Tehran",
    "iso:country":"IR",
    "name:fas_x_preferred":[
        "Mazra\u2018eh-ye G\u016bdarzan"
    ],
    "name:fas_x_variant":[
        "G\u016bdarzan",
        "\u06af\u0648\u062f\u0631\u0632\u0646"
    ],
    "name:und_x_variant":[
        "Gowd Razan"
    ],
    "wof:name":"Gudarzan",
    "wof:placetype":"locality"
},
  "geometry": {"coordinates":[51.94198,33.29528],"type":"Point"}
}