{
  "type": "Feature",
  "properties": {
    "gn:admin1_code":"42",
    "gn:asciiname":"Derakht-e Senjed",
    "gn:country_code":"IR",
    "gn:dem":1499,
    "gn:feature_class":"P",
    "gn:feature_code":"PPL",
    "gn:name":"Derakht-e Senjed",
    "gn:population":0,
    "gn:timezone":"Asia/Tehran",
    "iso:country":"IR",
    "name:fas_x_preferred":[
        "\u062f\u0631\u062e\u062a \u0633\u0646\u062c\u062f"
    ],
    "wof:name":"Derakht-e Senjed",
    "wof:placetype":"locality"
},
  "geometry": {"coordinates":[59.11148000000001,35.73813],"type":"Point"}
}