{
  "type": "Feature",
  "properties": {
    "gn:admin1_code":"5",
    "gn:asciiname":"Kabuteh",
    "gn:country_code":"IR",
    "gn:dem":1500,
    "gn:feature_class":"P",
    "gn:feature_code":"PPL",
    "gn:name":"Kab\u016bteh",
    "gn:population":0,
    "gn:timezone":"Asia/Tehran",
    "iso:country":"IR",
    "name:ara_x_preferred":[
        "\u06a9\u0628\u0648\u0646\u0629"
    ],
    "name:ceb_x_preferred":[
        "Kab\u016bteh"
    ],
    "name:fas_x_preferred":[
        "\u0643\u064e\u0628\u0648\u0646\u0650\u0647"
    ],
    "name:fas_x_variant":[
        "Kab\u016bteh",
        "\u0643\u0628\u0648\u062a\u0647",
        "\u06a9\u0628\u0648\u0646\u0647"
    ],
    "name:swe_x_preferred":[
        "Kab\u016bteh"
    ],
    "name:und_x_variant":[
        "Kab\u016bneh",
        "\u0643\u0628\u0648\u062a\u0647"
    ],
    "wof:name":"Kabuteh",
    "wof:placetype":"locality"
},
  "geometry": {"coordinates":[50.90715,30.96833],"type":"Point"}
}