{
  "type": "Feature",
  "properties": {
    "gn:admin1_code":"4.0",
    "gn:asciiname":"Ladkhukan",
    "gn:country_code":"IR",
    "gn:dem":1424,
    "gn:feature_class":"P",
    "gn:feature_code":"PPL",
    "gn:name":"Ladkh\u016bk\u0101n",
    "gn:population":0,
    "gn:timezone":"Asia/Tehran",
    "iso:country":"IR",
    "name:fas_x_preferred":[
        "\u0644\u062f\u062e\u0648\u06a9\u0627\u0646"
    ],
    "name:fas_x_variant":[
        "Ladh\u016bk\u0101n",
        "Ladkh\u016bk\u0101n"
    ],
    "wof:name":"Ladkhukan",
    "wof:placetype":"locality"
},
  "geometry": {"coordinates":[61.33753000000001,27.37942],"type":"Point"}
}