{
  "type": "Feature",
  "properties": {
    "gn:admin1_code":"33.0",
    "gn:asciiname":"Shah Yurdi",
    "gn:country_code":"IR",
    "gn:dem":1301,
    "gn:feature_class":"P",
    "gn:feature_code":"PPL",
    "gn:name":"Sh\u0101h Y\u016brd\u012b",
    "gn:population":0,
    "gn:timezone":"Asia/Tehran",
    "iso:country":"IR",
    "name:fas_x_preferred":[
        "\u0634\u0627\u0647 \u06cc\u0648\u0631\u062f\u06cc"
    ],
    "name:fas_x_variant":[
        "Sh\u0101h Y\u016brd\u012b"
    ],
    "wof:name":"Shah Yurdi",
    "wof:placetype":"locality"
},
  "geometry": {"coordinates":[47.1626,39.0108],"type":"Point"}
}