{
  "type": "Feature",
  "properties": {
    "gn:admin1_code":"13",
    "gn:asciiname":"Azreh-ye Mohammad Khan",
    "gn:country_code":"IR",
    "gn:dem":1344,
    "gn:feature_class":"P",
    "gn:feature_code":"PPL",
    "gn:name":"Azreh-ye Mo\u1e29ammad Kh\u0101n",
    "gn:population":0,
    "gn:timezone":"Asia/Tehran",
    "iso:country":"IR",
    "name:fas_x_preferred":[
        "\u0627\u0632\u0631\u0647 \u0645\u062d\u0645\u0651\u062f \u062e\u0627\u0646"
    ],
    "name:fas_x_variant":[
        "Azreh-ye Mokarram\u012b",
        "Azreh-ye Mo\u1e29ammad Kh\u0101n"
    ],
    "name:und_x_variant":[
        "Azreh-ye Mo\u1e29ammad Kh\u0101n"
    ],
    "wof:name":"Azreh-ye Mohammad Khan",
    "wof:placetype":"locality"
},
  "geometry": {"coordinates":[46.6525,34.4355],"type":"Point"}
}