{
  "type": "Feature",
  "properties": {
    "gn:admin1_code":"29.0",
    "gn:asciiname":"Seghenak",
    "gn:country_code":"IR",
    "gn:dem":1949,
    "gn:feature_class":"P",
    "gn:feature_code":"PPL",
    "gn:name":"Seghenak",
    "gn:population":0,
    "gn:timezone":"Asia/Tehran",
    "iso:country":"IR",
    "name:fas_x_preferred":[
        "Segh\u012bng"
    ],
    "name:fas_x_variant":[
        "\u0633\u063a\u0646\u06a9",
        "\u0633\u0641\u06cc\u0646\u06a9"
    ],
    "name:und_x_variant":[
        "Sagh\u012bnak",
        "Seghenak",
        "Sef\u012bnak"
    ],
    "wof:name":"Seghenak",
    "wof:placetype":"locality"
},
  "geometry": {"coordinates":[56.8768,28.48502],"type":"Point"}
}