{
  "type": "Feature",
  "properties": {
    "gn:admin1_code":"8",
    "gn:asciiname":"Sepestanak",
    "gn:country_code":"IR",
    "gn:dem":1519,
    "gn:feature_class":"P",
    "gn:feature_code":"PPL",
    "gn:name":"Sepest\u0101nak",
    "gn:population":0,
    "gn:timezone":"Asia/Tehran",
    "iso:country":"IR",
    "name:ceb_x_preferred":[
        "Sepest\u0101nak"
    ],
    "name:fas_x_preferred":[
        "S\u012bbest\u0101nak"
    ],
    "name:fas_x_variant":[
        "Seh Pest\u0101nak",
        "\u0633\u06cc\u0628\u0633\u062a\u0627\u0646\u06a9",
        "\u0633\u067e\u0633\u062a\u0627\u0646\u06a9",
        "\u0633\u0647 \u067e\u0633\u062a\u0627\u0646\u06a9"
    ],
    "name:msa_x_preferred":[
        "Seh Pestanak"
    ],
    "name:swe_x_preferred":[
        "Sepest\u0101nak"
    ],
    "name:ukr_x_preferred":[
        "\u0421\u0435-\u041f\u0430\u0441\u0442\u0430\u043d\u0430\u043a"
    ],
    "name:und_x_variant":[
        "Sivistanak"
    ],
    "wof:name":"Sepestanak",
    "wof:placetype":"locality"
},
  "geometry": {"coordinates":[49.81104000000001,36.78815],"type":"Point"}
}