{
  "type": "Feature",
  "properties": {
    "gn:admin1_code":"0",
    "gn:asciiname":"Barmian",
    "gn:country_code":"IR",
    "gn:dem":351,
    "gn:feature_class":"P",
    "gn:feature_code":"PPL",
    "gn:name":"Barm\u012b\u0101n",
    "gn:population":0,
    "gn:timezone":"Asia/Tehran",
    "iso:country":"IR",
    "name:fas_x_preferred":[
        "\u0628\u0631\u0645\u06cc\u0627\u0646"
    ],
    "name:fas_x_variant":[
        "Barm\u012b\u0101n"
    ],
    "wof:name":"Barmian",
    "wof:placetype":"locality"
},
  "geometry": {"coordinates":[57.5081,27.4468],"type":"Point"}
}