{
  "type": "Feature",
  "properties": {
    "gn:admin1_code":"8",
    "gn:asciiname":"Sir`alivar",
    "gn:country_code":"IR",
    "gn:dem":9,
    "gn:feature_class":"P",
    "gn:feature_code":"PPL",
    "gn:name":"S\u012br\u2018\u0101l\u012bvar",
    "gn:population":0,
    "gn:timezone":"Asia/Tehran",
    "iso:country":"IR",
    "name:fas_x_preferred":[
        "\u0633\u06cc\u0631 \u0639\u0644\u06cc \u0648\u0631"
    ],
    "name:fas_x_variant":[
        "S\u012br\u0101l\u012bveh",
        "S\u012br\u2018\u0101l\u012bvar"
    ],
    "wof:name":"Sir`alivar",
    "wof:placetype":"locality"
},
  "geometry": {"coordinates":[48.838,38.3176],"type":"Point"}
}