{
  "type": "Feature",
  "properties": {
    "gn:admin1_code":"1",
    "gn:asciiname":"Kani Sharak",
    "gn:country_code":"IR",
    "gn:dem":1696,
    "gn:feature_class":"P",
    "gn:feature_code":"PPL",
    "gn:name":"K\u0101n\u012b Sharak",
    "gn:population":0,
    "gn:timezone":"Asia/Tehran",
    "iso:country":"IR",
    "name:fas_x_preferred":[
        "\u0643\u0627\u0646\u06cc \u0634\u0648\u0631\u064a\u0643"
    ],
    "name:fas_x_variant":[
        "\u0643\u0627\u0646\u06cc \u0634\u064e\u0631\u064a\u0643",
        "\u06a9\u0627\u0646\u06cc \u0634\u0631\u06a9",
        "K\u0101n\u012b Sh\u016br\u012bk",
        "K\u0101n\u012b Sharak"
    ],
    "name:und_x_variant":[
        "K\u0101n\u012b Shar\u012bk"
    ],
    "wof:name":"Kani Sharak",
    "wof:placetype":"locality"
},
  "geometry": {"coordinates":[44.7467,37.6659],"type":"Point"}
}