{
  "type": "Feature",
  "properties": {
    "gn:admin1_code":"8",
    "gn:asciiname":"Pa'izan",
    "gn:country_code":"IR",
    "gn:dem":828,
    "gn:feature_class":"P",
    "gn:feature_code":"PPL",
    "gn:name":"P\u0101\u2019\u012bz\u0101n",
    "gn:population":0,
    "gn:timezone":"Asia/Tehran",
    "iso:country":"IR",
    "name:fas_x_preferred":[
        "P\u0101\u2019\u012bz\u0101n"
    ],
    "name:fas_x_variant":[
        "\u067e\u0627\u0626\u06cc\u0632\u0627\u0646"
    ],
    "wof:name":"Pa'izan",
    "wof:placetype":"locality"
},
  "geometry": {"coordinates":[49.17111,37.135],"type":"Point"}
}