{
  "type": "Feature",
  "properties": {
    "gn:admin1_code":"13",
    "gn:asciiname":"Kamar Surakh",
    "gn:country_code":"IR",
    "gn:dem":1228,
    "gn:feature_class":"P",
    "gn:feature_code":"PPL",
    "gn:name":"Kamar S\u016br\u0101kh",
    "gn:population":0,
    "gn:timezone":"Asia/Tehran",
    "iso:country":"IR",
    "name:ara_x_preferred":[
        "\u0643\u0645\u0631\u0633\u0648\u0631\u0627\u062e"
    ],
    "name:ceb_x_preferred":[
        "Kamar S\u016br\u0101kh"
    ],
    "name:fas_x_preferred":[
        "\u06a9\u0645\u0631\u0633\u0648\u0631\u0627\u062e"
    ],
    "name:fas_x_variant":[
        "Kamar S\u016br\u0101kh"
    ],
    "name:swe_x_preferred":[
        "Kamar S\u016br\u0101kh"
    ],
    "wof:name":"Kamar Surakh",
    "wof:placetype":"locality"
},
  "geometry": {"coordinates":[46.7349,33.8308],"type":"Point"}
}