{
  "type": "Feature",
  "properties": {
    "gn:admin1_code":"42",
    "gn:asciiname":"Khowr-e Bala",
    "gn:country_code":"IR",
    "gn:dem":1511,
    "gn:feature_class":"P",
    "gn:feature_code":"PPL",
    "gn:name":"Khowr-e B\u0101l\u0101",
    "gn:population":0,
    "gn:timezone":"Asia/Tehran",
    "iso:country":"IR",
    "name:fas_x_preferred":[
        "\u062e\u0648\u0631 \u0628\u0627\u0644\u0627"
    ],
    "name:und_x_variant":[
        "Khowr-e B\u0101l\u0101"
    ],
    "wof:name":"Khowr-e Bala",
    "wof:placetype":"locality"
},
  "geometry": {"coordinates":[59.85372,36.6898],"type":"Point"}
}