{
  "type": "Feature",
  "properties": {
    "gn:admin1_code":"7",
    "gn:asciiname":"Mahmudabad-e Do Dangeh",
    "gn:cc2":"IR",
    "gn:country_code":"IR",
    "gn:dem":1521,
    "gn:feature_class":"P",
    "gn:feature_code":"PPL",
    "gn:name":"Ma\u1e29m\u016bd\u0101b\u0101d-e Do D\u0101ngeh",
    "gn:population":0,
    "gn:timezone":"Asia/Tehran",
    "iso:country":"IR",
    "name:fas_x_preferred":[
        "Ma\u1e29m\u016bd\u0101b\u0101d-e Do D\u0101ngeh"
    ],
    "name:und_x_variant":[
        "Mahmood Abad\u00e9 Dow Dangeh"
    ],
    "wof:name":"Mahmudabad-e Do Dangeh",
    "wof:placetype":"locality"
},
  "geometry": {"coordinates":[52.69306,29.24444],"type":"Point"}
}