{
  "type": "Feature",
  "properties": {
    "gn:admin1_code":"4.0",
    "gn:asciiname":"Deh-e Nader-e `Alam",
    "gn:country_code":"IR",
    "gn:dem":491,
    "gn:feature_class":"P",
    "gn:feature_code":"PPL",
    "gn:name":"Deh-e N\u0101der-e \u2018Alam",
    "gn:population":0,
    "gn:timezone":"Asia/Tehran",
    "iso:country":"IR",
    "name:fas_x_preferred":[
        "\u062f\u0647 \u0646\u0627\u062f\u0631 \u0639\u0644\u0645"
    ],
    "name:fas_x_variant":[
        "Deh-e N\u0101der-e \u2018Alam",
        "\u062f\u0647 \u0646\u0627\u062f\u0631"
    ],
    "name:und_x_variant":[
        "Deh-e N\u0101der"
    ],
    "wof:name":"Deh-e Nader-e `Alam",
    "wof:placetype":"locality"
},
  "geometry": {"coordinates":[61.77692,30.89368],"type":"Point"}
}