{
  "type": "Feature",
  "properties": {
    "gn:admin1_code":"33.0",
    "gn:asciiname":"Zaviyeh",
    "gn:country_code":"IR",
    "gn:dem":1449,
    "gn:feature_class":"P",
    "gn:feature_code":"PPL",
    "gn:name":"Z\u0101v\u012byeh",
    "gn:population":0,
    "gn:timezone":"Asia/Tehran",
    "iso:country":"IR",
    "name:ara_x_preferred":[
        "\u0632\u0627\u0648\u064a\u0629"
    ],
    "name:azb_x_preferred":[
        "\u0632\u0627\u0648\u06cc\u0647"
    ],
    "name:aze_x_preferred":[
        "Zaviy\u0259"
    ],
    "name:ceb_x_preferred":[
        "Z\u0101v\u012byeh"
    ],
    "name:fas_x_preferred":[
        "\u0632\u0627\u0648\u06cc\u0647"
    ],
    "name:fas_x_variant":[
        "Z\u0101v\u012byeh"
    ],
    "name:fra_x_preferred":[
        "Zaviyeh"
    ],
    "name:ita_x_preferred":[
        "Zaviyeh"
    ],
    "name:mlg_x_preferred":[
        "Zaviyeh"
    ],
    "name:rus_x_preferred":[
        "\u0417\u0430\u0432\u0438\u0439\u0435"
    ],
    "name:spa_x_preferred":[
        "Zaviyeh"
    ],
    "name:tur_x_preferred":[
        "Zaviye"
    ],
    "wof:name":"Zaviyeh",
    "wof:placetype":"locality"
},
  "geometry": {"coordinates":[46.0461,37.503],"type":"Point"}
}