{
  "type": "Feature",
  "properties": {
    "gn:admin1_code":"7",
    "gn:asciiname":"Dasht-e Chenar",
    "gn:cc2":"IR",
    "gn:country_code":"IR",
    "gn:dem":1501,
    "gn:feature_class":"P",
    "gn:feature_code":"PPL",
    "gn:name":"Dasht-e Chen\u0101r",
    "gn:population":0,
    "gn:timezone":"Asia/Tehran",
    "iso:country":"IR",
    "name:fas_x_preferred":[
        "Dasht-e Chen\u0101r"
    ],
    "name:und_x_variant":[
        "Dast Chen\u0101r",
        "Dasht Chen\u0101r"
    ],
    "wof:name":"Dasht-e Chenar",
    "wof:placetype":"locality"
},
  "geometry": {"coordinates":[52.58221999999999,29.56],"type":"Point"}
}