{
  "type": "Feature",
  "properties": {
    "gn:admin1_code":"13",
    "gn:asciiname":"Mojahedeh",
    "gn:country_code":"IR",
    "gn:dem":1211,
    "gn:feature_class":"P",
    "gn:feature_code":"PPL",
    "gn:name":"Moj\u0101hedeh",
    "gn:population":0,
    "gn:timezone":"Asia/Tehran",
    "iso:country":"IR",
    "name:fas_x_preferred":[
        "Moj\u0101hedeh"
    ],
    "wof:name":"Mojahedeh",
    "wof:placetype":"locality"
},
  "geometry": {"coordinates":[46.40389,34.76917],"type":"Point"}
}