{
  "type": "Feature",
  "properties": {
    "gn:admin1_code":"43",
    "gn:asciiname":"Qeshlaq-e Langar",
    "gn:country_code":"IR",
    "gn:dem":1289,
    "gn:feature_class":"P",
    "gn:feature_code":"PPL",
    "gn:name":"Qeshl\u0101q-e Langar",
    "gn:population":0,
    "gn:timezone":"Asia/Tehran",
    "iso:country":"IR",
    "name:fas_x_preferred":[
        "Qeshl\u0101q-e Langar"
    ],
    "wof:name":"Qeshlaq-e Langar",
    "wof:placetype":"locality"
},
  "geometry": {"coordinates":[57.23333,37.53333],"type":"Point"}
}