{
  "type": "Feature",
  "properties": {
    "gn:admin1_code":"23",
    "gn:asciiname":"Eslamabad",
    "gn:country_code":"IR",
    "gn:dem":1807,
    "gn:feature_class":"P",
    "gn:feature_code":"PPL",
    "gn:name":"Esl\u0101m\u0101b\u0101d",
    "gn:population":0,
    "gn:timezone":"Asia/Tehran",
    "iso:country":"IR",
    "name:ara_x_preferred":[
        "\u0625\u0633\u0644\u0627\u0645 \u0622\u0628\u0627\u062f"
    ],
    "name:fas_x_preferred":[
        "\u0642\u0644\u0639\u0647 \u062e\u0627\u0646\u062c\u0627\u0646"
    ],
    "name:fas_x_variant":[
        "\u062e\u0627\u0646\u062c\u0627\u0646 \u062e\u0627\u0646",
        "\u0642\u064e\u0644\u0639\u0650\u06c0 \u062e\u0627\u0646\u062c\u0627\u0646 \u062e\u0627\u0646",
        "\u0633\u064e\u0631 \u062a\u064e\u0646\u06af\u0650 \u0627\u0650\u0633\u0644\u0627\u0645 \u0622\u0628\u0627\u062f",
        "Qal\u2018eh-ye Kh\u0101nj\u0101n",
        "\u0627\u0633\u0644\u0627\u0645 \u0622\u0628\u0627\u062f",
        "\u0627\u0633\u0644\u0627\u0645\u200c\u0622\u0628\u0627\u062f"
    ],
    "name:und_x_variant":[
        "Sar Tang-e Esl\u0101m\u0101b\u0101d",
        "Qal\u2018eh-ye Kh\u0101nj\u0101n Kh\u0101n",
        "Kh\u0101nj\u0101n Kh\u0101n",
        "Esl\u0101m\u0101b\u0101d"
    ],
    "wof:name":"Eslamabad",
    "wof:placetype":"locality"
},
  "geometry": {"coordinates":[48.7151,33.3093],"type":"Point"}
}