{
  "type": "Feature",
  "properties": {
    "gn:admin1_code":"26.0",
    "gn:asciiname":"Shahrak-e Darkia",
    "gn:country_code":"IR",
    "gn:dem":2254,
    "gn:feature_class":"P",
    "gn:feature_code":"PPLF",
    "gn:name":"Shahrak-e D\u0101rk\u012b\u0101",
    "gn:population":0,
    "gn:timezone":"Asia/Tehran",
    "iso:country":"IR",
    "name:fas_x_preferred":[
        "\u062f\u0627\u0631\u06a9\u06cc\u0627"
    ],
    "name:fas_x_variant":[
        "D\u0101rk\u012b\u0101",
        "\u0634\u0647\u0631\u06a9 \u062f\u0627\u0631\u06a9\u064a\u0627"
    ],
    "name:und_x_variant":[
        "Shahrak-e D\u0101rk\u012b\u0101"
    ],
    "wof:name":"Shahrak-e Darkia",
    "wof:placetype":"locality"
},
  "geometry": {"coordinates":[51.56241,35.91565],"type":"Point"}
}