{
  "type": "Feature",
  "properties": {
    "gn:admin1_code":"1",
    "gn:asciiname":"Aydinlu",
    "gn:country_code":"IR",
    "gn:dem":1285,
    "gn:feature_class":"P",
    "gn:feature_code":"PPL",
    "gn:name":"\u0100yd\u012bnl\u016b",
    "gn:population":0,
    "gn:timezone":"Asia/Tehran",
    "iso:country":"IR",
    "name:fas_x_preferred":[
        "\u0622\u064a\u062f\u0650\u0646\u0644\u0648"
    ],
    "name:fas_x_variant":[
        "\u0622\u06cc\u062f\u06cc\u0646\u0644\u0648",
        "\u0100ydenl\u016b",
        "\u0100yd\u012bnl\u016b"
    ],
    "wof:name":"Aydinlu",
    "wof:placetype":"locality"
},
  "geometry": {"coordinates":[45.2063,37.5369],"type":"Point"}
}