{
  "type": "Feature",
  "properties": {
    "gn:admin1_code":"23",
    "gn:asciiname":"Budineh",
    "gn:country_code":"IR",
    "gn:dem":1522,
    "gn:feature_class":"P",
    "gn:feature_code":"PPL",
    "gn:name":"B\u016bd\u012bneh",
    "gn:population":0,
    "gn:timezone":"Asia/Tehran",
    "iso:country":"IR",
    "name:fas_x_preferred":[
        "\u0628\u0648\u062f\u06cc\u0646\u0647"
    ],
    "name:fas_x_variant":[
        "B\u016bd\u012bneh"
    ],
    "wof:name":"Budineh",
    "wof:placetype":"locality"
},
  "geometry": {"coordinates":[49.14362,33.50108],"type":"Point"}
}