{
  "type": "Feature",
  "properties": {
    "gn:admin1_code":"8",
    "gn:asciiname":"Shabkhusalat-e Pa'in",
    "gn:country_code":"IR",
    "gn:dem":58,
    "gn:feature_class":"P",
    "gn:feature_code":"PPL",
    "gn:name":"Shabkh\u016bsal\u0101t-e P\u0101\u2019\u012bn",
    "gn:population":0,
    "gn:timezone":"Asia/Tehran",
    "iso:country":"IR",
    "name:fas_x_preferred":[
        "Shabkh\u016bsal\u0101t"
    ],
    "name:fas_x_variant":[
        "\u0634\u0628\u062e\u0648\u0633\u0644\u0627\u062a",
        "\u0634\u0628\u062e\u0648\u0633\u0644\u0627\u062a \u067e\u0627\u06cc\u06cc\u0646"
    ],
    "name:und_x_variant":[
        "Shabkh\u016bsal\u0101t-e P\u0101\u2019\u012bn"
    ],
    "wof:name":"Shabkhusalat-e Pa'in",
    "wof:placetype":"locality"
},
  "geometry": {"coordinates":[50.23753,37.04577000000001],"type":"Point"}
}