{
  "type": "Feature",
  "properties": {
    "gn:admin1_code":"29",
    "gn:asciiname":"Razinu'iyeh",
    "gn:country_code":"IR",
    "gn:dem":2045,
    "gn:feature_class":"P",
    "gn:feature_code":"PPLL",
    "gn:name":"Raz\u012bn\u016b\u2019\u012byeh",
    "gn:population":0,
    "gn:timezone":"Asia/Tehran",
    "iso:country":"IR",
    "name:fas_x_preferred":[
        "Razen\u016b\u2019\u012byeh"
    ],
    "name:fas_x_variant":[
        "Raz\u012bn\u016b\u2019\u012byeh",
        "\u0631\u0632\u06cc\u0646\u0648\u0626\u06cc\u0647",
        "\u0631\u0636\u0646\u0648\u064a\u06cc\u0647"
    ],
    "name:und_x_variant":[
        "\u0631\u0632\u06cc\u0646\u0648\u0626\u06cc\u0647",
        "Ra\u1e95en\u016b\u2019\u012byeh"
    ],
    "wof:name":"Razinu'iyeh",
    "wof:placetype":"locality"
},
  "geometry": {"coordinates":[57.04146,29.22088],"type":"Point"}
}