{
  "type": "Feature",
  "properties": {
    "gn:admin1_code":"23",
    "gn:asciiname":"Tarkaleh",
    "gn:country_code":"IR",
    "gn:dem":1620,
    "gn:feature_class":"P",
    "gn:feature_code":"PPL",
    "gn:name":"Tarkaleh",
    "gn:population":0,
    "gn:timezone":"Asia/Tehran",
    "iso:country":"IR",
    "name:fas_x_preferred":[
        "\u062f\u0650\u0647 \u064a\u0648\u0633\u0650\u0641\u0627\u0646\u0650 \u0628\u0627\u0644\u0627"
    ],
    "name:fas_x_variant":[
        "\u062f\u06cc\u0648\u0633\u0641\u0651\u0627\u0646 \u0639\u0644\u06cc\u0627",
        "Deh Y\u016bsef\u0101n-e B\u0101l\u0101",
        "D\u012bv Saff\u0101n-e \u2018Oly\u0101",
        "\u062a\u0631\u06a9\u0644\u0647"
    ],
    "wof:name":"Tarkaleh",
    "wof:placetype":"locality"
},
  "geometry": {"coordinates":[47.96495,33.86315],"type":"Point"}
}