{
  "type": "Feature",
  "properties": {
    "gn:admin1_code":"11",
    "gn:asciiname":"Vadasht",
    "gn:country_code":"IR",
    "gn:dem":10,
    "gn:feature_class":"P",
    "gn:feature_code":"PPL",
    "gn:name":"V\u0101d\u0101sht",
    "gn:population":0,
    "gn:timezone":"Asia/Tehran",
    "iso:country":"IR",
    "name:ceb_x_preferred":[
        "V\u0101d\u0101sht"
    ],
    "name:fas_x_preferred":[
        "\u0648\u0627\u062f\u0627\u0634\u062a"
    ],
    "name:fas_x_variant":[
        "V\u0101d\u0101sht"
    ],
    "name:msa_x_preferred":[
        "Vadasht"
    ],
    "name:swe_x_preferred":[
        "V\u0101d\u0101sht"
    ],
    "wof:name":"Vadasht",
    "wof:placetype":"locality"
},
  "geometry": {"coordinates":[57.04528000000001,26.84222],"type":"Point"}
}