{
  "type": "Feature",
  "properties": {
    "gn:admin1_code":"1",
    "gn:asciiname":"Qal`eh Hasan",
    "gn:country_code":"IR",
    "gn:dem":1280,
    "gn:feature_class":"P",
    "gn:feature_code":"PPL",
    "gn:name":"Qal\u2018eh \u1e28asan",
    "gn:population":0,
    "gn:timezone":"Asia/Tehran",
    "iso:country":"IR",
    "name:fas_x_preferred":[
        "\u0642\u064e\u0644\u0639\u0650\u0647 \u062d\u064e\u0633\u064e\u0646"
    ],
    "name:fas_x_variant":[
        "\u0642\u0644\u0639\u0647 \u062d\u0633\u0646",
        "\u0642\u064f\u0644 \u062d\u064e\u0633\u064e\u0646",
        "Qol \u1e28asan",
        "\u063a\u064e\u0644\u0639\u0650\u0647 \u0647\u064e\u0633\u064e\u0646",
        "\u0643\u0648\u0644\u0648\u0633\u0627\u0646",
        "\u0643\u064f\u0644\u064f\u0633\u064e\u0646",
        "Qal\u2018eh \u1e28asan"
    ],
    "name:und_x_variant":[
        "Kolosan",
        "K\u016bl\u016bs\u0101n",
        "Qal\u2018eh \u1e28asan"
    ],
    "wof:name":"Qal`eh Hasan",
    "wof:placetype":"locality"
},
  "geometry": {"coordinates":[45.8306,37.0003],"type":"Point"}
}