{
  "type": "Feature",
  "properties": {
    "gn:admin1_code":"32",
    "gn:asciiname":"Mashkul",
    "gn:country_code":"IR",
    "gn:dem":1549,
    "gn:feature_class":"P",
    "gn:feature_code":"PPL",
    "gn:name":"Mashk\u016bl",
    "gn:population":0,
    "gn:timezone":"Asia/Tehran",
    "iso:country":"IR",
    "name:ceb_x_preferred":[
        "Mashk\u016bl"
    ],
    "name:fas_x_preferred":[
        "\u0645\u0634\u06a9\u0648\u0644"
    ],
    "name:fas_x_variant":[
        "Mashkyul\u2019",
        "Mashk\u016bl"
    ],
    "name:msa_x_preferred":[
        "Mashkul"
    ],
    "name:swe_x_preferred":[
        "Mashk\u016bl"
    ],
    "name:und_x_variant":[
        "Abvar",
        "Mashkyu",
        "Mashg\u016bl"
    ],
    "wof:name":"Mashkul",
    "wof:placetype":"locality"
},
  "geometry": {"coordinates":[48.19832,37.49293],"type":"Point"}
}