{
  "type": "Feature",
  "properties": {
    "gn:admin1_code":"15.0",
    "gn:asciiname":"Tang Do",
    "gn:country_code":"IR",
    "gn:dem":432,
    "gn:feature_class":"P",
    "gn:feature_code":"PPLL",
    "gn:name":"Tang Do",
    "gn:population":0,
    "gn:timezone":"Asia/Tehran",
    "iso:country":"IR",
    "name:ara_x_preferred":[
        "\u062a\u0646\u063a \u062f\u0648"
    ],
    "name:azb_x_preferred":[
        "\u062a\u0646\u06af \u062f\u0648(\u0627\u0646\u062f\u06cc\u0645\u0634\u06a9)"
    ],
    "name:fas_x_preferred":[
        "\u062a\u0646\u06af \u062f\u0648"
    ],
    "wof:name":"Tang Do",
    "wof:placetype":"locality"
},
  "geometry": {"coordinates":[48.68,32.7756],"type":"Point"}
}