{
  "type": "Feature",
  "properties": {
    "gn:admin1_code":"43",
    "gn:asciiname":"Zafarabad",
    "gn:country_code":"IR",
    "gn:dem":1326,
    "gn:feature_class":"P",
    "gn:feature_code":"PPL",
    "gn:name":"Z\u0327afar\u0101b\u0101d",
    "gn:population":0,
    "gn:timezone":"Asia/Tehran",
    "iso:country":"IR",
    "name:fas_x_preferred":[
        "Z\u0327afar\u0101b\u0101d"
    ],
    "name:fas_x_variant":[
        "\u0638\u0641\u0631 \u0622\u0628\u0627\u062f"
    ],
    "wof:name":"Zafarabad",
    "wof:placetype":"locality"
},
  "geometry": {"coordinates":[57.56748,37.67406],"type":"Point"}
}