{
  "type": "Feature",
  "properties": {
    "gn:admin1_code":"29",
    "gn:asciiname":"Bid Kheyri",
    "gn:cc2":"IR",
    "gn:country_code":"IR",
    "gn:dem":659,
    "gn:feature_class":"P",
    "gn:feature_code":"PPL",
    "gn:name":"B\u012bd Kheyr\u012b",
    "gn:population":0,
    "gn:timezone":"Asia/Tehran",
    "iso:country":"IR",
    "name:fas_x_preferred":[
        "B\u012bd Kheyr\u012b"
    ],
    "name:fas_x_variant":[
        "\u0628\u06cc\u062f\u062e\u06cc\u0631\u06cc"
    ],
    "name:und_x_variant":[
        "B\u012bd Kheyr",
        "B\u012bd Kheri"
    ],
    "wof:name":"Bid Kheyri",
    "wof:placetype":"locality"
},
  "geometry": {"coordinates":[57.81667,28.61667000000001],"type":"Point"}
}