{
  "type": "Feature",
  "properties": {
    "gn:admin1_code":"22",
    "gn:asciiname":"Mozaffari-ye Shomali",
    "gn:country_code":"IR",
    "gn:dem":32,
    "gn:feature_class":"P",
    "gn:feature_code":"PPL",
    "gn:name":"Moz\u0327affar\u012b-ye Shom\u0101l\u012b",
    "gn:population":0,
    "gn:timezone":"Asia/Tehran",
    "iso:country":"IR",
    "name:ara_x_preferred":[
        "\u0645\u0638\u0641\u0631\u064a \u0634\u0645\u0627\u0644\u064a"
    ],
    "name:ceb_x_preferred":[
        "Moz\u0327affar\u012b-ye Shom\u0101l\u012b"
    ],
    "name:fas_x_preferred":[
        "\u0645\u0638\u0641\u0631\u06cc \u0634\u0645\u0627\u0644\u06cc"
    ],
    "name:fas_x_variant":[
        "Moz\u0327affar\u012b-ye Shom\u0101l\u012b"
    ],
    "name:msa_x_preferred":[
        "Mozaffari-ye Shomali"
    ],
    "name:swe_x_preferred":[
        "Moz\u0327affar\u012b-ye Shom\u0101l\u012b"
    ],
    "name:und_x_variant":[
        "Moz\u0327affar\u012b"
    ],
    "wof:name":"Mozaffari-ye Shomali",
    "wof:placetype":"locality"
},
  "geometry": {"coordinates":[50.36426,30.01269000000001],"type":"Point"}
}