{
  "type": "Feature",
  "properties": {
    "gn:admin1_code":"16",
    "gn:asciiname":"Kikan",
    "gn:country_code":"IR",
    "gn:dem":1348,
    "gn:feature_class":"P",
    "gn:feature_code":"PPL",
    "gn:name":"K\u012bkan",
    "gn:population":0,
    "gn:timezone":"Asia/Tehran",
    "iso:country":"IR",
    "name:fas_x_preferred":[
        "\u0643\u064a\u0643\u0650\u0646"
    ],
    "name:fas_x_variant":[
        "\u06a9\u06cc\u06a9\u0646",
        "K\u012bkan"
    ],
    "name:und_x_variant":[
        "K\u012bkin",
        "K\u012bken"
    ],
    "wof:name":"Kikan",
    "wof:placetype":"locality"
},
  "geometry": {"coordinates":[46.1042,35.6496],"type":"Point"}
}