{
  "type": "Feature",
  "properties": {
    "gn:admin1_code":"1",
    "gn:asciiname":"Oghul Beyg",
    "gn:country_code":"IR",
    "gn:dem":1842,
    "gn:feature_class":"P",
    "gn:feature_code":"PPL",
    "gn:name":"Ogh\u016bl Beyg",
    "gn:population":0,
    "gn:timezone":"Asia/Tehran",
    "iso:country":"IR",
    "name:azb_x_preferred":[
        "\u0627\u0648\u063a\u0648\u0644 \u0628\u0647\u200c\u06cc"
    ],
    "name:aze_x_preferred":[
        "O\u011fulb\u0259y"
    ],
    "name:ckb_x_preferred":[
        "\u0626\u06c6\u063a\u0644 \u0628\u06d5\u06af"
    ],
    "name:fas_x_preferred":[
        "\u0627\u063a\u0648\u0644 \u0628\u06cc\u06a9"
    ],
    "name:fas_x_variant":[
        "\u016agh\u016bl Beyg",
        "Ogh\u016bl Beyk",
        "\u0627\u063a\u0648\u0644\u0628\u0650\u064a\u06af",
        "\u0627\u0648\u063a\u0648\u0644 \u0628\u0650\u064a\u06af",
        "\u0627\u0648\u063a\u0648\u0644\u200c\u0628\u06cc\u06af"
    ],
    "name:msa_x_preferred":[
        "Ughul Beyg"
    ],
    "name:und_x_variant":[
        "Ogh\u016bl Beyg"
    ],
    "wof:name":"Oghul Beyg",
    "wof:placetype":"locality"
},
  "geometry": {"coordinates":[47.13427,36.44873],"type":"Point"}
}