{
  "type": "Feature",
  "properties": {
    "gn:admin1_code":"36",
    "gn:asciiname":"Khan Kandi",
    "gn:country_code":"IR",
    "gn:dem":1338,
    "gn:feature_class":"P",
    "gn:feature_code":"PPL",
    "gn:name":"Kh\u0101n Kand\u012b",
    "gn:population":0,
    "gn:timezone":"Asia/Tehran",
    "iso:country":"IR",
    "name:fas_x_preferred":[
        "\u062e\u0627\u0646\u0643\u0646\u062f\u06cc"
    ],
    "name:fas_x_variant":[
        "Kh\u0101n Kand\u012b",
        "Kh\u0101nkand\u012b",
        "\u062e\u0627\u0646 \u06a9\u0646\u062f\u06cc",
        "\u0627\u0645\u0627\u0645 \u06a9\u0646\u062f\u06cc"
    ],
    "name:und_x_variant":[
        "Em\u0101m Kand\u012b"
    ],
    "wof:name":"Khan Kandi",
    "wof:placetype":"locality"
},
  "geometry": {"coordinates":[47.78293,36.58547],"type":"Point"}
}