{
  "type": "Feature",
  "properties": {
    "gn:admin1_code":"36.0",
    "gn:asciiname":"Aliabad",
    "gn:country_code":"IR",
    "gn:dem":1740,
    "gn:feature_class":"P",
    "gn:feature_code":"PPL",
    "gn:name":"Aliabad",
    "gn:population":0,
    "gn:timezone":"Asia/Tehran",
    "iso:country":"IR",
    "name:azb_x_preferred":[
        "\u0639\u0644\u06cc\u200c\u0622\u0628\u0627\u062f"
    ],
    "name:aze_x_preferred":[
        "\u018fliabad"
    ],
    "name:fas_x_preferred":[
        "\u0639\u0644\u06cc \u0622\u0628\u0627\u062f \u0628\u0627\u0644\u0627"
    ],
    "name:fas_x_variant":[
        "\u2018Al\u012b\u0101b\u0101d-e B\u0101l\u0101",
        "\u0639\u0644\u06cc \u0622\u0628\u0627\u062f \u0645\u0639\u06cc\u0646\u06cc",
        "\u0639\u0644\u06cc\u200c\u0622\u0628\u0627\u062f"
    ],
    "name:hin_x_preferred":[
        "\u0906\u0932\u093f\u092f\u093e\u092c\u093e\u0926"
    ],
    "name:ita_x_preferred":[
        "Aliabad"
    ],
    "name:kat_x_preferred":[
        "\u10d0\u10da\u10d8\u10d0\u10d1\u10d0\u10d3\u10d8"
    ],
    "name:mzn_x_preferred":[
        "\u0639\u0644\u06cc\u200c\u0622\u0628\u0627\u062f"
    ],
    "name:nld_x_preferred":[
        "Aliabad"
    ],
    "name:pol_x_preferred":[
        "Aliabad"
    ],
    "name:tur_x_preferred":[
        "Aliabad"
    ],
    "name:und_x_variant":[
        "\u2018Al\u012b\u0101b\u0101d B\u0101l\u0101",
        "\u2018Al\u012b\u0101b\u0101d \u2018Oly\u0101",
        "\u2018Al\u012b\u0101b\u0101d-e Mo\u2018\u012bn\u012b"
    ],
    "wof:name":"Aliabad",
    "wof:placetype":"locality"
},
  "geometry": {"coordinates":[48.6728,36.8136],"type":"Point"}
}