{
  "type": "Feature",
  "properties": {
    "gn:admin1_code":"9",
    "gn:asciiname":"Ganjvaran-e Vosta",
    "gn:country_code":"IR",
    "gn:dem":1743,
    "gn:feature_class":"P",
    "gn:feature_code":"PPL",
    "gn:name":"Ganjvar\u0101n-e Vos\u0163\u00e1",
    "gn:population":0,
    "gn:timezone":"Asia/Tehran",
    "iso:country":"IR",
    "name:fas_x_preferred":[
        "\u06af\u064e\u0646\u062c\u0648\u064e\u0631\u0627\u0646\u0650 \u0648\u064f\u0633\u0637\u064e\u0649"
    ],
    "wof:name":"Ganjvaran-e Vosta",
    "wof:placetype":"locality"
},
  "geometry": {"coordinates":[48.18333,34.55],"type":"Point"}
}