{
  "type": "Feature",
  "properties": {
    "gn:admin1_code":"34",
    "gn:asciiname":"Deh-e Shir Khan",
    "gn:country_code":"IR",
    "gn:dem":1795,
    "gn:feature_class":"P",
    "gn:feature_code":"PPL",
    "gn:name":"Deh-e Sh\u012br Kh\u0101n",
    "gn:population":0,
    "gn:timezone":"Asia/Tehran",
    "iso:country":"IR",
    "name:fas_x_preferred":[
        "\u062f\u0647 \u0634\u06cc\u0631 \u062e\u0627\u0646"
    ],
    "name:fas_x_variant":[
        "Deh-e Sh\u012br Kh\u0101n",
        "\u062f\u0647 \u0634\u06cc\u0631\u062e\u0627\u0646"
    ],
    "name:ukr_x_preferred":[
        "\u0414\u0435\u0433-\u0435 \u0428\u0456\u0440-\u0425\u0430\u043d"
    ],
    "name:und_x_variant":[
        "Deh Sh\u012br Kh\u0101n"
    ],
    "wof:name":"Deh-e Shir Khan",
    "wof:placetype":"locality"
},
  "geometry": {"coordinates":[49.35974,34.1635],"type":"Point"}
}