{
  "type": "Feature",
  "properties": {
    "gn:admin1_code":"15",
    "gn:asciiname":"Ab Khigan",
    "gn:country_code":"IR",
    "gn:dem":1090,
    "gn:feature_class":"P",
    "gn:feature_code":"PPL",
    "gn:name":"\u0100b Kh\u012bg\u0101n",
    "gn:population":0,
    "gn:timezone":"Asia/Tehran",
    "iso:country":"IR",
    "name:fas_x_preferred":[
        "\u0100b Kh\u012bg\u0101n"
    ],
    "wof:name":"Ab Khigan",
    "wof:placetype":"locality"
},
  "geometry": {"coordinates":[49.98333,31.76667],"type":"Point"}
}