{
  "type": "Feature",
  "properties": {
    "gn:admin1_code":"35",
    "gn:asciiname":"Kashkah",
    "gn:country_code":"IR",
    "gn:dem":91,
    "gn:feature_class":"P",
    "gn:feature_code":"PPL",
    "gn:name":"Kashk\u0101h",
    "gn:population":0,
    "gn:timezone":"Asia/Tehran",
    "iso:country":"IR",
    "name:fas_x_preferred":[
        "\u0643\u064e\u0634\u0643\u0627"
    ],
    "name:fas_x_variant":[
        "Kashk\u0101",
        "Kashk\u0101h",
        "\u0643\u0634\u0643\u0627\u0647"
    ],
    "wof:name":"Kashkah",
    "wof:placetype":"locality"
},
  "geometry": {"coordinates":[52.82761,36.4153],"type":"Point"}
}