{
  "type": "Feature",
  "properties": {
    "gn:admin1_code":"32",
    "gn:asciiname":"Own Bir Beyglu",
    "gn:country_code":"IR",
    "gn:dem":686,
    "gn:feature_class":"P",
    "gn:feature_code":"PPL",
    "gn:name":"Own B\u012br Beygl\u016b",
    "gn:population":0,
    "gn:timezone":"Asia/Tehran",
    "iso:country":"IR",
    "name:ara_x_preferred":[
        "\u0627\u0648\u0646\u200c\u0628\u064a\u0631\u0628\u064a\u063a\u0644\u0648"
    ],
    "name:azb_x_preferred":[
        "\u0627\u0648\u0646\u200c\u0628\u06cc\u0631\u0628\u064e\u06cc\u200c\u0644\u06cc"
    ],
    "name:ceb_x_preferred":[
        "Own B\u012br Beygl\u016b"
    ],
    "name:fas_x_preferred":[
        "\u0648\u0646\u0628\u064a\u0631 \u0628\u0650\u064a\u06af\u0644\u0648"
    ],
    "name:fas_x_variant":[
        "\u0627\u0648\u0646 \u0628\u064a\u0631 \u0628\u064a\u06af\u0644\u0648",
        "\u016anb\u012br Beygl\u016b",
        "Own B\u012br Beygl\u016b",
        "\u0627\u0648\u0646\u200c\u0628\u06cc\u0631\u0628\u06cc\u06af\u200c\u0644\u0648"
    ],
    "name:msa_x_preferred":[
        "Own Bir Beyglu"
    ],
    "name:mzn_x_preferred":[
        "\u0627\u0648\u0646\u200c\u0628\u06cc\u0631\u0628\u06cc\u06af\u200c\u0644\u0648"
    ],
    "name:swe_x_preferred":[
        "Own B\u012br Beygl\u016b"
    ],
    "wof:name":"Own Bir Beyglu",
    "wof:placetype":"locality"
},
  "geometry": {"coordinates":[47.9989,39.0821],"type":"Point"}
}