{
  "type": "Feature",
  "properties": {
    "gn:admin1_code":"15",
    "gn:asciiname":"Longir-e Sofla",
    "gn:country_code":"IR",
    "gn:dem":83,
    "gn:feature_class":"P",
    "gn:feature_code":"PPL",
    "gn:name":"Long\u012br-e Sofl\u00e1",
    "gn:population":0,
    "gn:timezone":"Asia/Tehran",
    "iso:country":"IR",
    "name:fas_x_preferred":[
        "\u0644\u0646\u06af\u06cc\u0631 \u0633\u0641\u0644\u06cc"
    ],
    "name:fas_x_variant":[
        "Long\u012br-e P\u0101\u2019\u012bn",
        "Long\u012br-e Sofl\u00e1"
    ],
    "name:und_x_variant":[
        "Long\u012br Sofl\u00e1",
        "Long\u012br",
        "L\u012bngor"
    ],
    "wof:name":"Longir-e Sofla",
    "wof:placetype":"locality"
},
  "geometry": {"coordinates":[49.98938,30.46549000000001],"type":"Point"}
}