{
  "type": "Feature",
  "properties": {
    "gn:admin1_code":"13",
    "gn:asciiname":"Cheshmeh-ye Baha` od Din",
    "gn:country_code":"IR",
    "gn:dem":1744,
    "gn:feature_class":"P",
    "gn:feature_code":"PPL",
    "gn:name":"Cheshmeh-ye Bah\u0101\u2018 od D\u012bn",
    "gn:population":0,
    "gn:timezone":"Asia/Tehran",
    "iso:country":"IR",
    "name:fas_x_preferred":[
        "\u0686\u0634\u0645\u0647 \u0628\u0647\u0627\u0621 \u0627\u0644\u062f\u06cc\u0646"
    ],
    "name:fas_x_variant":[
        "Cheshmeh-ye Bah\u0101\u2018 od D\u012bn"
    ],
    "name:und_x_variant":[
        "Cheshmeh-ye Bah\u0101\u2019 ed D\u012bn",
        "Cheshmeh B\u0101h\u0101\u2019ed D\u012bn",
        "Chashmeh Baha ud D\u012bn",
        "Cheshmeh-ye Bah\u0101\u2018 od D\u012bn"
    ],
    "wof:name":"Cheshmeh-ye Baha` od Din",
    "wof:placetype":"locality"
},
  "geometry": {"coordinates":[47.4328,34.8559],"type":"Point"}
}