{
  "type": "Feature",
  "properties": {
    "gn:admin1_code":"23",
    "gn:asciiname":"Hanam",
    "gn:country_code":"IR",
    "gn:dem":1872,
    "gn:feature_class":"P",
    "gn:feature_code":"PPL",
    "gn:name":"Han\u0101m",
    "gn:population":0,
    "gn:timezone":"Asia/Tehran",
    "iso:country":"IR",
    "name:fas_x_preferred":[
        "\u0647\u0646\u0627\u0645"
    ],
    "name:fas_x_variant":[
        "\u062d\u0646\u0627\u0645",
        "\u062d\u064e\u0646\u0627\u0645\u0650 \u0628\u0627\u0644\u0627",
        "Han\u0101m",
        "\u1e28an\u0101m"
    ],
    "name:und_x_variant":[
        "\u1e28an\u0101m-e B\u0101l\u0101"
    ],
    "wof:name":"Hanam",
    "wof:placetype":"locality"
},
  "geometry": {"coordinates":[48.6755,33.3329],"type":"Point"}
}