{
  "type": "Feature",
  "properties": {
    "gn:admin1_code":"4",
    "gn:asciiname":"Chahan",
    "gn:country_code":"IR",
    "gn:dem":1293,
    "gn:feature_class":"P",
    "gn:feature_code":"PPL",
    "gn:name":"Ch\u0101h\u0101n",
    "gn:population":0,
    "gn:timezone":"Asia/Tehran",
    "iso:country":"IR",
    "name:fas_x_preferred":[
        "\u0686\u0627\u0647\u0627\u0646"
    ],
    "name:fas_x_variant":[
        "Ch\u0101h\u0101n"
    ],
    "wof:name":"Chahan",
    "wof:placetype":"locality"
},
  "geometry": {"coordinates":[62.76204,26.83301],"type":"Point"}
}