{
  "type": "Feature",
  "properties": {
    "gn:admin1_code":"35.0",
    "gn:asciiname":"Bagh-e Movahed",
    "gn:country_code":"IR",
    "gn:dem":1131,
    "gn:feature_class":"P",
    "gn:feature_code":"PPL",
    "gn:name":"B\u0101gh-e Mova\u1e29ed",
    "gn:population":0,
    "gn:timezone":"Asia/Tehran",
    "iso:country":"IR",
    "name:fas_x_preferred":[
        "\u0628\u0627\u063a \u0645\u0648\u062d\u062f"
    ],
    "name:fas_x_variant":[
        "B\u0101gh-e Mova\u1e29ed"
    ],
    "name:und_x_variant":[
        "B\u0101gh-e Mova\u1e29ed",
        "\u0628\u0627\u063a \u0645\u0648\u062d\u062f"
    ],
    "wof:name":"Bagh-e Movahed",
    "wof:placetype":"locality"
},
  "geometry": {"coordinates":[51.17992,36.50806],"type":"Point"}
}