{
  "type": "Feature",
  "properties": {
    "gn:admin1_code":"8",
    "gn:asciiname":"Khanevaneh",
    "gn:country_code":"IR",
    "gn:dem":132,
    "gn:feature_class":"P",
    "gn:feature_code":"PPL",
    "gn:name":"Kh\u0101nev\u0101neh",
    "gn:population":0,
    "gn:timezone":"Asia/Tehran",
    "iso:country":"IR",
    "name:ara_x_preferred":[
        "\u062e\u0627\u0646\u0648\u0627\u0646\u0647"
    ],
    "name:ceb_x_preferred":[
        "Kh\u0101nev\u0101neh"
    ],
    "name:fas_x_preferred":[
        "\u062e\u0627\u0646\u0648\u0627\u0646\u0647"
    ],
    "name:fas_x_variant":[
        "Kh\u0101neh V\u0101neh",
        "Kh\u0101nev\u0101neh"
    ],
    "name:glk_x_preferred":[
        "\u062e\u0627\u0646\u0647 \u0648\u0627\u0646\u0647"
    ],
    "name:msa_x_preferred":[
        "Khaneh Vaneh"
    ],
    "name:swe_x_preferred":[
        "Kh\u0101nev\u0101neh"
    ],
    "name:ukr_x_preferred":[
        "\u0425\u0430\u043d\u0435-\u0412\u0430\u043d\u0435"
    ],
    "name:und_x_variant":[
        "Khana-Vona"
    ],
    "wof:name":"Khanevaneh",
    "wof:placetype":"locality"
},
  "geometry": {"coordinates":[49.20054,37.20584],"type":"Point"}
}