{
  "type": "Feature",
  "properties": {
    "gn:admin1_code":"5",
    "gn:asciiname":"Ghazanfarkhani",
    "gn:country_code":"IR",
    "gn:dem":2344,
    "gn:feature_class":"P",
    "gn:feature_code":"PPL",
    "gn:name":"Gha\u1e95anfarkh\u0101n\u012b",
    "gn:population":0,
    "gn:timezone":"Asia/Tehran",
    "iso:country":"IR",
    "name:ara_x_preferred":[
        "\u063a\u0636\u0646\u0641\u0631 \u062e\u0627\u0646\u064a"
    ],
    "name:ceb_x_preferred":[
        "Gha\u1e95anfarkh\u0101n\u012b"
    ],
    "name:fas_x_preferred":[
        "Gha\u1e95anfarkh\u0101n\u012b"
    ],
    "name:fas_x_variant":[
        "\u063a\u0636\u0646\u0641\u0631\u062e\u0627\u0646\u06cc",
        "\u0627\u0633\u0644\u0627\u0645 \u0622\u0628\u0627\u062f",
        "\u063a\u0636\u0646\u0641\u0631 \u062e\u0627\u0646\u06cc"
    ],
    "name:swe_x_preferred":[
        "Gha\u1e95anfarkh\u0101n\u012b"
    ],
    "name:und_x_variant":[
        "Qal\u2018eh-ye Gha\u1e95anfarkh\u0101n\u012b",
        "Esl\u0101m\u0101b\u0101d"
    ],
    "wof:name":"Ghazanfarkhani",
    "wof:placetype":"locality"
},
  "geometry": {"coordinates":[51.80323,30.65184],"type":"Point"}
}