{
  "type": "Feature",
  "properties": {
    "gn:admin1_code":"4.0",
    "gn:asciiname":"Nali",
    "gn:country_code":"IR",
    "gn:dem":1241,
    "gn:feature_class":"P",
    "gn:feature_code":"PPL",
    "gn:name":"N\u0101l\u012b",
    "gn:population":0,
    "gn:timezone":"Asia/Tehran",
    "iso:country":"IR",
    "name:ceb_x_preferred":[
        "Nali"
    ],
    "name:fas_x_preferred":[
        "\u0646\u0627\u0644\u06cc"
    ],
    "name:fas_x_variant":[
        "N\u0101l\u012b"
    ],
    "name:swe_x_preferred":[
        "Nali"
    ],
    "wof:name":"Nali",
    "wof:placetype":"locality"
},
  "geometry": {"coordinates":[61.09924,27.56542],"type":"Point"}
}