{
  "type": "Feature",
  "properties": {
    "gn:admin1_code":"41",
    "gn:asciiname":"Hami",
    "gn:country_code":"IR",
    "gn:dem":1541,
    "gn:feature_class":"P",
    "gn:feature_code":"PPL",
    "gn:name":"\u1e28\u0101m\u012b",
    "gn:population":0,
    "gn:timezone":"Asia/Tehran",
    "iso:country":"IR",
    "name:cdo_x_preferred":[
        "Kumul"
    ],
    "name:ceb_x_preferred":[
        "Hami Shi"
    ],
    "name:deu_x_preferred":[
        "Kumul"
    ],
    "name:est_x_preferred":[
        "Hami ringkond"
    ],
    "name:eus_x_preferred":[
        "Kumul prefektura"
    ],
    "name:fas_x_preferred":[
        "K\u0101mi"
    ],
    "name:fas_x_variant":[
        "\u1e28\u0101m\u012b",
        "\u062d\u0627\u0645\u06cc",
        "\u0647\u0627\u0645\u06cc"
    ],
    "name:fin_x_preferred":[
        "Hami"
    ],
    "name:hun_x_preferred":[
        "H\u00e1mi"
    ],
    "name:ind_x_preferred":[
        "Hami"
    ],
    "name:jpn_x_preferred":[
        "\u30af\u30e0\u30eb\u5e02"
    ],
    "name:kor_x_preferred":[
        "\ud558\ubbf8\uc2dc"
    ],
    "name:lit_x_preferred":[
        "Kumulo prefekt\u016bra"
    ],
    "name:mlg_x_preferred":[
        "Hami"
    ],
    "name:mon_x_preferred":[
        "\u0425\u0430\u043c\u0438\u043b \u0442\u043e\u0439\u0440\u043e\u0433"
    ],
    "name:nor_x_preferred":[
        "Kumul"
    ],
    "name:pol_x_preferred":[
        "Hami"
    ],
    "name:rus_x_preferred":[
        "\u0425\u0430\u043c\u0438"
    ],
    "name:spa_x_preferred":[
        "Kumul"
    ],
    "name:swe_x_preferred":[
        "Hami"
    ],
    "name:tat_x_preferred":[
        "\u041a\u043e\u043c\u044b\u043b"
    ],
    "name:tur_x_preferred":[
        "Kumul \u0130li"
    ],
    "name:uig_x_preferred":[
        "\u0642\u06c7\u0645\u06c7\u0644 \u0634\u06d5\u06be\u0649\u0631\u0649"
    ],
    "name:ukr_x_preferred":[
        "\u0425\u0430\u043c\u0456"
    ],
    "name:urd_x_preferred":[
        "\u06c1\u0627\u0645\u06cc \u0634\u06c1\u0631"
    ],
    "name:vie_x_preferred":[
        "Kumul"
    ],
    "name:zho_x_preferred":[
        "\u54c8\u5bc6\u5e02"
    ],
    "wof:name":"Hami",
    "wof:placetype":"locality"
},
  "geometry": {"coordinates":[58.66146,33.01919],"type":"Point"}
}