{
  "type": "Feature",
  "properties": {
    "gn:admin1_code":"41",
    "gn:asciiname":"Hami",
    "gn:country_code":"IR",
    "gn:dem":1541,
    "gn:feature_class":"P",
    "gn:feature_code":"PPL",
    "gn:name":"\u1e28\u0101m\u012b",
    "gn:population":0,
    "gn:timezone":"Asia/Tehran",
    "iso:country":"IR",
    "name:fas_x_preferred":[
        "K\u0101mi"
    ],
    "name:fas_x_variant":[
        "\u1e28\u0101m\u012b",
        "\u062d\u0627\u0645\u06cc"
    ],
    "name:und_x_variant":[
        "\u1e28\u0101m\u012b",
        "\u062d\u0627\u0645\u06cc"
    ],
    "wof:name":"Hami",
    "wof:placetype":"locality"
},
  "geometry": {"coordinates":[58.66146,33.01919],"type":"Point"}
}