{
  "type": "Feature",
  "properties": {
    "gn:admin1_code":"28",
    "gn:asciiname":"Noqol",
    "gn:country_code":"IR",
    "gn:dem":2287,
    "gn:feature_class":"P",
    "gn:feature_code":"PPL",
    "gn:name":"Noqol",
    "gn:population":0,
    "gn:timezone":"Asia/Tehran",
    "iso:country":"IR",
    "name:fas_x_preferred":[
        "\u0646\u0642\u0644"
    ],
    "name:tur_x_preferred":[
        "Nukul"
    ],
    "name:und_x_variant":[
        "\u0646\u0642\u0644"
    ],
    "wof:name":"Noqol",
    "wof:placetype":"locality"
},
  "geometry": {"coordinates":[51.65306,30.86754],"type":"Point"}
}