{
  "type": "Feature",
  "properties": {
    "gn:admin1_code":"23",
    "gn:asciiname":"Kamandun",
    "gn:country_code":"IR",
    "gn:dem":2030,
    "gn:feature_class":"P",
    "gn:feature_code":"PPL",
    "gn:name":"Kamand\u016bn",
    "gn:population":0,
    "gn:timezone":"Asia/Tehran",
    "iso:country":"IR",
    "name:ceb_x_preferred":[
        "Kamand\u0101n"
    ],
    "name:fas_x_preferred":[
        "\u0643\u0645\u0646\u062f\u0627\u0646"
    ],
    "name:fas_x_variant":[
        "Kamand\u0101n",
        "\u06a9\u0645\u0646\u062f\u0648\u0646",
        "\u06a9\u0645\u0646\u062f\u0627\u0646"
    ],
    "name:swe_x_preferred":[
        "Kamand\u0101n"
    ],
    "name:und_x_variant":[
        "Kamand\u016bn"
    ],
    "wof:name":"Kamandun",
    "wof:placetype":"locality"
},
  "geometry": {"coordinates":[49.44382,33.30817],"type":"Point"}
}