{
  "type": "Feature",
  "properties": {
    "gn:admin1_code":"15.0",
    "gn:asciiname":"`Arab Hasan",
    "gn:country_code":"IR",
    "gn:dem":31,
    "gn:feature_class":"P",
    "gn:feature_code":"PPL",
    "gn:name":"\u2018Arab \u1e28asan",
    "gn:population":0,
    "gn:timezone":"Asia/Tehran",
    "iso:country":"IR",
    "name:fas_x_preferred":[
        "\u0639\u0631\u0628 \u062d\u0633\u0646"
    ],
    "name:fas_x_variant":[
        "\u2018Arab \u1e28asan"
    ],
    "wof:name":"`Arab Hasan",
    "wof:placetype":"locality"
},
  "geometry": {"coordinates":[48.89707,31.83265],"type":"Point"}
}