{
  "type": "Feature",
  "properties": {
    "gn:admin1_code":"22",
    "gn:asciiname":"Neynizak",
    "gn:country_code":"IR",
    "gn:dem":174,
    "gn:feature_class":"P",
    "gn:feature_code":"PPL",
    "gn:name":"Neyn\u012bzak",
    "gn:population":0,
    "gn:timezone":"Asia/Tehran",
    "iso:country":"IR",
    "name:fas_x_preferred":[
        "\u0646\u0646\u064a\u0632\u0643"
    ],
    "name:fas_x_variant":[
        "\u0646\u0627\u0646\u0632\u064e\u0643",
        "\u0646\u064a\u0646\u064a\u0632\u06a9",
        "Nan\u012bzak"
    ],
    "name:und_x_variant":[
        "N\u0101nzak",
        "Neyn\u012bzak"
    ],
    "wof:name":"Neynizak",
    "wof:placetype":"locality"
},
  "geometry": {"coordinates":[51.30729,29.1768],"type":"Point"}
}