{
  "type": "Feature",
  "properties": {
    "gn:admin1_code":"1.0",
    "gn:asciiname":"Kulseh-ye `Olya",
    "gn:country_code":"IR",
    "gn:dem":1393,
    "gn:elevation":"0.0",
    "gn:feature_class":"P",
    "gn:feature_code":"PPL",
    "gn:name":"K\u016blseh-ye \u2018Oly\u0101",
    "gn:population":0,
    "gn:timezone":"Asia/Tehran",
    "iso:country":"IR",
    "name:fas_x_preferred":[
        "\u0643\u0648\u0644\u0633\u0650\u06c0 \u0628\u0627\u0644\u0627"
    ],
    "name:fas_x_variant":[
        "\u06a9\u0648\u0644\u0633\u0647 \u0639\u0644\u06cc\u0627",
        "K\u016blseh-ye B\u0101l\u0101",
        "K\u016blseh-ye \u2018Oly\u0101"
    ],
    "wof:name":"Kulseh-ye `Olya",
    "wof:placetype":"locality"
},
  "geometry": {"coordinates":[45.5513,36.0957],"type":"Point"}
}