{
  "type": "Feature",
  "properties": {
    "gn:admin1_code":"43.0",
    "gn:asciiname":"Amand",
    "gn:country_code":"IR",
    "gn:dem":468,
    "gn:feature_class":"P",
    "gn:feature_code":"PPL",
    "gn:name":"Amand",
    "gn:population":0,
    "gn:timezone":"Asia/Tehran",
    "iso:country":"IR",
    "name:fas_x_preferred":[
        "\u0627\u0645\u0646\u062f"
    ],
    "name:und_x_variant":[
        "\u0100mand",
        "Amand"
    ],
    "wof:name":"Amand",
    "wof:placetype":"locality"
},
  "geometry": {"coordinates":[56.3519,37.7731],"type":"Point"}
}