{
  "type": "Feature",
  "properties": {
    "gn:admin1_code":"22",
    "gn:asciiname":"Moghdan",
    "gn:country_code":"IR",
    "gn:dem":22,
    "gn:feature_class":"P",
    "gn:feature_code":"PPL",
    "gn:name":"Moghd\u0101n",
    "gn:population":0,
    "gn:timezone":"Asia/Tehran",
    "iso:country":"IR",
    "name:fas_x_preferred":[
        "\u0645\u063a\u062f\u0627\u0646"
    ],
    "name:fas_x_variant":[
        "\u0645\u062e\u062f\u0627\u0646",
        "Moghd\u0101n"
    ],
    "name:und_x_variant":[
        "Mukhd\u0101n",
        "Mokhd\u0101n"
    ],
    "wof:name":"Moghdan",
    "wof:placetype":"locality"
},
  "geometry": {"coordinates":[51.51122,28.14267000000001],"type":"Point"}
}