{
  "type": "Feature",
  "properties": {
    "gn:admin1_code":"4.0",
    "gn:asciiname":"Vashnam-e Gholam Rosul",
    "gn:country_code":"IR",
    "gn:dem":15,
    "gn:feature_class":"P",
    "gn:feature_code":"PPL",
    "gn:name":"Vashn\u0101m-e Ghol\u0101m Ros\u016bl",
    "gn:population":0,
    "gn:timezone":"Asia/Tehran",
    "iso:country":"IR",
    "name:fas_x_preferred":[
        "Vashn\u0101m-e \u1e28\u0101jj\u012b Rama\u1e95\u0101n"
    ],
    "name:fas_x_variant":[
        "\u0648\u0634\u0646\u0627\u0645 \u063a\u0644\u0627\u0645 \u0631\u0633\u0648\u0644",
        "\u0648\u0634\u0646\u0627\u0645"
    ],
    "name:und_x_variant":[
        "Vashn\u0101m-e Ghol\u0101m Ros\u016bl",
        "Wajn\u0101n",
        "Veshn\u0101m-e D\u016bst Mo\u1e29ammad",
        "V\u0101zhn\u0101n",
        "V\u0101jn\u0101n",
        "Vashn\u0101m"
    ],
    "wof:name":"Vashnam-e Gholam Rosul",
    "wof:placetype":"locality"
},
  "geometry": {"coordinates":[60.8125,25.38611],"type":"Point"}
}