{
  "type": "Feature",
  "properties": {
    "gn:admin1_code":"33.0",
    "gn:asciiname":"Dehkadeh-ye Fasli-ye Jaliq",
    "gn:country_code":"IR",
    "gn:dem":1439,
    "gn:feature_class":"P",
    "gn:feature_code":"PPL",
    "gn:name":"Dehkadeh-ye Fa\u015fl\u012b-ye J\u0101l\u012bq",
    "gn:population":0,
    "gn:timezone":"Asia/Tehran",
    "iso:country":"IR",
    "name:fas_x_preferred":[
        "\u062f\u0647\u06a9\u062f\u0647 \u0641\u0635\u0644\u06cc \u062c\u0627\u0644\u06cc\u0642"
    ],
    "name:und_x_variant":[
        "Dehkadeh-ye Fa\u015fl\u012b-ye J\u0101l\u012bq"
    ],
    "wof:name":"Dehkadeh-ye Fasli-ye Jaliq",
    "wof:placetype":"locality"
},
  "geometry": {"coordinates":[47.389,38.5307],"type":"Point"}
}