{
  "type": "Feature",
  "properties": {
    "gn:admin1_code":"8",
    "gn:asciiname":"Zu ol Piran",
    "gn:country_code":"IR",
    "gn:dem":40,
    "gn:feature_class":"P",
    "gn:feature_code":"PPL",
    "gn:name":"Z\u0304\u016b ol P\u012br\u0101n",
    "gn:population":0,
    "gn:timezone":"Asia/Tehran",
    "iso:country":"IR",
    "name:fas_x_preferred":[
        "\u0630\u0648\u0644 \u067e\u06cc\u0631\u0627\u0646"
    ],
    "name:fas_x_variant":[
        "Z\u0304owl P\u012br\u0101n",
        "\u0630\u0648 \u0627\u0644\u067e\u06cc\u0631\u0627\u0646"
    ],
    "name:und_x_variant":[
        "Z\u0304owl P\u012br\u0101n",
        "Z\u0304\u016b ol P\u012br\u0101n"
    ],
    "wof:name":"Zu ol Piran",
    "wof:placetype":"locality"
},
  "geometry": {"coordinates":[49.42193,37.16096],"type":"Point"}
}