{
  "type": "Feature",
  "properties": {
    "gn:admin1_code":"23",
    "gn:asciiname":"Mamu-ye Pa'in",
    "gn:country_code":"IR",
    "gn:dem":1869,
    "gn:feature_class":"P",
    "gn:feature_code":"PPL",
    "gn:name":"M\u0101m\u016b-ye P\u0101\u2019\u012bn",
    "gn:population":0,
    "gn:timezone":"Asia/Tehran",
    "iso:country":"IR",
    "name:fas_x_preferred":[
        "\u0645\u0627\u0645\u0648\u06cc \u0633\u064f\u0641\u0644\u064e\u0649"
    ],
    "name:fas_x_variant":[
        "\u0645\u0627\u0645\u0648 \u067e\u0627\u0626\u06cc\u0646",
        "M\u0101m\u016b-ye Sofl\u00e1",
        "M\u0101m\u016b-ye P\u0101\u2019\u012bn"
    ],
    "wof:name":"Mamu-ye Pa'in",
    "wof:placetype":"locality"
},
  "geometry": {"coordinates":[47.6096,34.1907],"type":"Point"}
}