{
  "type": "Feature",
  "properties": {
    "gn:admin1_code":"38",
    "gn:asciiname":"Shizar",
    "gn:country_code":"IR",
    "gn:dem":1554,
    "gn:feature_class":"P",
    "gn:feature_code":"PPL",
    "gn:name":"Sh\u012bzar",
    "gn:population":0,
    "gn:timezone":"Asia/Tehran",
    "iso:country":"IR",
    "name:fas_x_preferred":[
        "\u0634\u06cc\u0632\u0631"
    ],
    "name:fas_x_variant":[
        "\u0634\u064e\u0632\u064e\u0631",
        "Sh\u012bzar"
    ],
    "name:und_x_variant":[
        "Shazar",
        "Shizar Afshariyeh"
    ],
    "wof:name":"Shizar",
    "wof:placetype":"locality"
},
  "geometry": {"coordinates":[49.42862,35.78595],"type":"Point"}
}