{
  "type": "Feature",
  "properties": {
    "gn:admin1_code":"35.0",
    "gn:asciiname":"Hezar Khuni",
    "gn:country_code":"IR",
    "gn:dem":1761,
    "gn:feature_class":"P",
    "gn:feature_code":"PPL",
    "gn:name":"Hez\u0101r Kh\u016bn\u012b",
    "gn:population":0,
    "gn:timezone":"Asia/Tehran",
    "iso:country":"IR",
    "name:fas_x_preferred":[
        "\u0647\u0632\u0627\u0631 \u062e\u0648\u0646\u06cc"
    ],
    "name:und_x_variant":[
        "Hez\u0101r Kh\u016bn\u012b"
    ],
    "wof:name":"Hezar Khuni",
    "wof:placetype":"locality"
},
  "geometry": {"coordinates":[51.29944,36.24582],"type":"Point"}
}