{
  "type": "Feature",
  "properties": {
    "gn:admin1_code":"1",
    "gn:asciiname":"Dizaj-e Rahim Pur",
    "gn:country_code":"IR",
    "gn:dem":1319,
    "gn:feature_class":"P",
    "gn:feature_code":"PPL",
    "gn:name":"D\u012bzaj-e Ra\u1e29\u012bm P\u016br",
    "gn:population":0,
    "gn:timezone":"Asia/Tehran",
    "iso:country":"IR",
    "name:fas_x_preferred":[
        "\u062f\u064a\u0632\u064e\u062c\u0650 \u0631\u064e\u062d\u064a\u0645\u067e\u0648\u0631"
    ],
    "name:fas_x_variant":[
        "\u062f\u06cc\u0632\u062c \u0631\u062d\u06cc\u0645 \u067e\u0648\u0631",
        "D\u012bzaj-e Ra\u1e29\u012bmp\u016br",
        "D\u012bzaj-e Ra\u1e29\u012bm P\u016br"
    ],
    "wof:name":"Dizaj-e Rahim Pur",
    "wof:placetype":"locality"
},
  "geometry": {"coordinates":[45.1041,37.4094],"type":"Point"}
}