{
  "type": "Feature",
  "properties": {
    "gn:admin1_code":"1",
    "gn:asciiname":"Dizaj-e Rahim Pur",
    "gn:country_code":"IR",
    "gn:dem":1319,
    "gn:feature_class":"P",
    "gn:feature_code":"PPL",
    "gn:name":"D\u012bzaj-e Ra\u1e29\u012bm P\u016br",
    "gn:population":0,
    "gn:timezone":"Asia/Tehran",
    "iso:country":"IR",
    "name:azb_x_preferred":[
        "\u062f\u06cc\u0632\u062c \u0631\u062d\u06cc\u0645 \u067e\u0648\u0631"
    ],
    "name:aze_x_preferred":[
        "Dizac-i R\u0259himpur"
    ],
    "name:ceb_x_preferred":[
        "D\u012bzaj-e Ra\u1e29\u012bm P\u016br"
    ],
    "name:fas_x_preferred":[
        "\u062f\u064a\u0632\u064e\u062c\u0650 \u0631\u064e\u062d\u064a\u0645\u067e\u0648\u0631"
    ],
    "name:fas_x_variant":[
        "\u062f\u06cc\u0632\u062c \u0631\u062d\u06cc\u0645 \u067e\u0648\u0631",
        "D\u012bzaj-e Ra\u1e29\u012bmp\u016br",
        "D\u012bzaj-e Ra\u1e29\u012bm P\u016br",
        "\u062f\u06cc\u0632\u062c \u0631\u062d\u06cc\u0645\u200c\u067e\u0648\u0631"
    ],
    "name:msa_x_preferred":[
        "Dizaj-e Rahim Pur"
    ],
    "name:pol_x_preferred":[
        "Dizad\u017c-e Rahim Pur"
    ],
    "name:swe_x_preferred":[
        "D\u012bzaj-e Ra\u1e29\u012bm P\u016br"
    ],
    "name:ukr_x_preferred":[
        "\u0414\u0456\u0437\u0430\u0434\u0436-\u0435-\u0420\u0430\u0445\u0456\u043c-\u041f\u0443\u0440"
    ],
    "wof:name":"Dizaj-e Rahim Pur",
    "wof:placetype":"locality"
},
  "geometry": {"coordinates":[45.1041,37.4094],"type":"Point"}
}