{
  "type": "Feature",
  "properties": {
    "gn:admin1_code":"29",
    "gn:asciiname":"Nuq",
    "gn:country_code":"IR",
    "gn:dem":1374,
    "gn:feature_class":"P",
    "gn:feature_code":"PPL",
    "gn:name":"N\u016bq",
    "gn:population":0,
    "gn:timezone":"Asia/Tehran",
    "iso:country":"IR",
    "name:fas_x_preferred":[
        "N\u016bq"
    ],
    "wof:name":"Nuq",
    "wof:placetype":"locality"
},
  "geometry": {"coordinates":[55.81222,30.83722],"type":"Point"}
}