{
  "type": "Feature",
  "properties": {
    "gn:admin1_code":"1",
    "gn:asciiname":"Hasulazgu",
    "gn:country_code":"IR",
    "gn:dem":1569,
    "gn:feature_class":"P",
    "gn:feature_code":"PPL",
    "gn:name":"\u1e28as\u016blazg\u016b",
    "gn:population":0,
    "gn:timezone":"Asia/Tehran",
    "iso:country":"IR",
    "name:azb_x_preferred":[
        "\u062d\u0633\u0648\u0644\u0632\u06af\u06cc"
    ],
    "name:aze_x_preferred":[
        "Hasul\u0259zgi"
    ],
    "name:fas_x_preferred":[
        "\u062d\u064e\u0633\u0648\u0644\u064e\u0632\u06af\u06cc"
    ],
    "name:fas_x_variant":[
        "\u062d\u0633\u0648\u0644\u0632\u06af\u0648",
        "\u1e28as\u016blazg\u012b",
        "\u1e28as\u016blazg\u016b",
        "\u062d\u0633\u0648\u0644\u0632\u06af\u06cc"
    ],
    "name:msa_x_preferred":[
        "Hasulazgi"
    ],
    "wof:name":"Hasulazgu",
    "wof:placetype":"locality"
},
  "geometry": {"coordinates":[44.6521,39.4662],"type":"Point"}
}