{
  "type": "Feature",
  "properties": {
    "gn:admin1_code":"8",
    "gn:asciiname":"Pa'in Mahalleh-ye Eghlam",
    "gn:country_code":"IR",
    "gn:dem":-20,
    "gn:feature_class":"P",
    "gn:feature_code":"PPL",
    "gn:name":"P\u0101\u2019\u012bn Ma\u1e29alleh-ye Eghl\u0101m",
    "gn:population":0,
    "gn:timezone":"Asia/Tehran",
    "iso:country":"IR",
    "name:fas_x_preferred":[
        "Jers\u016b Sheshkal"
    ],
    "name:fas_x_variant":[
        "\u0634\u0634\u06a9\u0644",
        "\u067e\u0627\u0626\u06cc\u0646 \u0645\u062d\u0644\u0647 \u0627\u063a\u0644\u0627\u0645"
    ],
    "name:und_x_variant":[
        "Sheshkal",
        "P\u0101\u2019\u012bn Ma\u1e29alleh-ye Eghl\u0101m"
    ],
    "wof:name":"Pa'in Mahalleh-ye Eghlam",
    "wof:placetype":"locality"
},
  "geometry": {"coordinates":[50.04319,37.36329],"type":"Point"}
}