{
  "type": "Feature",
  "properties": {
    "gn:admin1_code":"32",
    "gn:asciiname":"Guney Kand",
    "gn:country_code":"IR",
    "gn:dem":1106,
    "gn:feature_class":"P",
    "gn:feature_code":"PPL",
    "gn:name":"G\u016bney Kand",
    "gn:population":0,
    "gn:timezone":"Asia/Tehran",
    "iso:country":"IR",
    "name:fas_x_preferred":[
        "\u06af\u0648\u0646\u06cc \u0643\u0646\u062f\u06cc"
    ],
    "name:fas_x_variant":[
        "G\u016bney Kand\u012b",
        "\u06af\u0648\u0646\u06cc \u06a9\u0646\u062f",
        "\u06af\u0646\u06cc \u0642\u0634\u0644\u0627\u0642",
        "\u06af\u0648\u0646\u06cc \u06a9\u0646\u062f\u06cc"
    ],
    "name:msa_x_preferred":[
        "Guni Kandi"
    ],
    "name:und_x_variant":[
        "G\u016bn\u012b Kand\u012b",
        "G\u016bney Kand",
        "Gon\u012b Qeshl\u0101q"
    ],
    "wof:name":"Guney Kand",
    "wof:placetype":"locality"
},
  "geometry": {"coordinates":[47.63244,38.7174],"type":"Point"}
}