{
  "type": "Feature",
  "properties": {
    "gn:admin1_code":"26.0",
    "gn:asciiname":"Miandasht",
    "gn:country_code":"IR",
    "gn:dem":1307,
    "gn:feature_class":"P",
    "gn:feature_code":"PPL",
    "gn:name":"M\u012b\u0101ndasht",
    "gn:population":0,
    "gn:timezone":"Asia/Tehran",
    "iso:country":"IR",
    "name:fas_x_preferred":[
        "\u0645\u06cc\u0627\u0646\u062f\u0634\u062a"
    ],
    "name:fas_x_variant":[
        "M\u012b\u0101ndasht"
    ],
    "wof:name":"Miandasht",
    "wof:placetype":"locality"
},
  "geometry": {"coordinates":[51.75367,35.63555],"type":"Point"}
}