{
  "type": "Feature",
  "properties": {
    "gn:admin1_code":"8",
    "gn:asciiname":"Davan",
    "gn:country_code":"IR",
    "gn:dem":32,
    "gn:feature_class":"P",
    "gn:feature_code":"PPL",
    "gn:name":"D\u0101v\u0101n",
    "gn:population":0,
    "gn:timezone":"Asia/Tehran",
    "iso:country":"IR",
    "name:fas_x_preferred":[
        "\u062f\u0627\u0648\u0627\u0646"
    ],
    "name:fas_x_variant":[
        "D\u0101v\u0101n"
    ],
    "name:msa_x_preferred":[
        "Davan"
    ],
    "name:ukr_x_preferred":[
        "\u0414\u0430\u0432\u0430\u043d"
    ],
    "wof:name":"Davan",
    "wof:placetype":"locality"
},
  "geometry": {"coordinates":[48.89296,37.93699],"type":"Point"}
}