{
  "type": "Feature",
  "properties": {
    "gn:admin1_code":"42",
    "gn:asciiname":"Gol Qandasht",
    "gn:country_code":"IR",
    "gn:dem":1118,
    "gn:feature_class":"P",
    "gn:feature_code":"PPL",
    "gn:name":"Gol Qandasht",
    "gn:population":0,
    "gn:timezone":"Asia/Tehran",
    "iso:country":"IR",
    "name:ceb_x_preferred":[
        "Gol Qandasht"
    ],
    "name:fas_x_preferred":[
        "\u06af\u0644 \u0642\u0646\u062f\u0634\u062a"
    ],
    "name:fas_x_variant":[
        "\u06af\u0644\u200c\u0642\u0646\u062f\u0634\u062a"
    ],
    "name:swe_x_preferred":[
        "Gol Qandasht"
    ],
    "wof:name":"Gol Qandasht",
    "wof:placetype":"locality"
},
  "geometry": {"coordinates":[58.52314000000001,36.01522999999999],"type":"Point"}
}