{
  "type": "Feature",
  "properties": {
    "gn:admin1_code":"23",
    "gn:asciiname":"Posht Ku",
    "gn:country_code":"IR",
    "gn:dem":1336,
    "gn:feature_class":"P",
    "gn:feature_code":"PPL",
    "gn:name":"Posht K\u016b",
    "gn:population":0,
    "gn:timezone":"Asia/Tehran",
    "iso:country":"IR",
    "name:fas_x_preferred":[
        "\u0628\u06af\u0647"
    ],
    "name:fas_x_variant":[
        "\u067e\u0634\u062a \u06a9\u0648"
    ],
    "name:und_x_variant":[
        "Bageh",
        "Posht K\u016b"
    ],
    "wof:name":"Posht Ku",
    "wof:placetype":"locality"
},
  "geometry": {"coordinates":[47.5067,33.7718],"type":"Point"}
}