{
  "type": "Feature",
  "properties": {
    "gn:admin1_code":"42.0",
    "gn:asciiname":"Ahmadabad-e Sowlat",
    "gn:country_code":"IR",
    "gn:dem":900,
    "gn:feature_class":"P",
    "gn:feature_code":"PPL",
    "gn:name":"A\u1e29mad\u0101b\u0101d-e \u015eowlat",
    "gn:population":0,
    "gn:timezone":"Asia/Tehran",
    "iso:country":"IR",
    "name:fas_x_preferred":[
        "\u0627\u062d\u0645\u062f \u0622\u0628\u0627\u062f \u0635\u0648\u0644\u062a"
    ],
    "name:fas_x_variant":[
        "A\u1e29mad\u0101b\u0101d-e \u015eowlat",
        "\u0627\u062d\u0645\u062f\u0622\u0628\u0627\u062f \u0635\u0648\u0644\u062a"
    ],
    "name:und_x_variant":[
        "Ahmad Abad Pa\u2019in",
        "A\u1e29mad\u0101b\u0101d",
        "A\u1e29mad\u0101b\u0101d-e P\u0101\u2019\u012bn"
    ],
    "wof:name":"Ahmadabad-e Sowlat",
    "wof:placetype":"locality"
},
  "geometry": {"coordinates":[60.6899,35.1158],"type":"Point"}
}