{
  "type": "Feature",
  "properties": {
    "gn:admin1_code":"41",
    "gn:asciiname":"Mazra`eh-ye Kalateh-ye Mostafa",
    "gn:country_code":"IR",
    "gn:dem":1931,
    "gn:feature_class":"P",
    "gn:feature_code":"PPL",
    "gn:name":"Mazra\u2018eh-ye Kal\u0101teh-ye Mo\u015f\u0163af\u00e1",
    "gn:population":0,
    "gn:timezone":"Asia/Tehran",
    "iso:country":"IR",
    "name:fas_x_preferred":[
        "\u06a9\u0644\u0627\u062a\u0647 \u0645\u0635\u0637\u0641\u06cc"
    ],
    "name:fas_x_variant":[
        "Kal\u0101teh-ye Mo\u015f\u0163af\u00e1",
        "\u0645\u0632\u0631\u0639\u0647 \u06a9\u0644\u0627\u062a\u0647 \u0645\u0635\u0637\u0641\u06cc",
        "\u0645\u0635\u0637\u0641\u06cc \u0631\u062d\u0645\u0627\u0646\u06cc"
    ],
    "name:und_x_variant":[
        "Kal\u0101teh Mo\u015f\u0163af\u00e1",
        "Mazra\u2018eh-ye Kal\u0101teh-ye Mo\u015f\u0163af\u00e1",
        "Mo\u015f\u0163af\u00e1 Ra\u1e29m\u0101n\u012b"
    ],
    "wof:name":"Mazra`eh-ye Kalateh-ye Mostafa",
    "wof:placetype":"locality"
},
  "geometry": {"coordinates":[59.28882,33.39256],"type":"Point"}
}