{
  "type": "Feature",
  "properties": {
    "gn:admin1_code":"11.0",
    "gn:asciiname":"Sukhu",
    "gn:cc2":"IR",
    "gn:country_code":"IR",
    "gn:dem":958,
    "gn:feature_class":"P",
    "gn:feature_code":"PPL",
    "gn:name":"S\u016bkh\u016b",
    "gn:population":0,
    "gn:timezone":"Asia/Tehran",
    "iso:country":"IR",
    "name:fas_x_preferred":[
        "\u0633\u0648\u062e\u0648"
    ],
    "name:fas_x_variant":[
        "\u0633\u064f\u0648\u0643\u0650\u0647\u0648",
        "S\u016bkh\u016b"
    ],
    "name:und_x_variant":[
        "Sowkeh\u016b"
    ],
    "wof:name":"Sukhu",
    "wof:placetype":"locality"
},
  "geometry": {"coordinates":[57.68278000000001,26.99361],"type":"Point"}
}