{
  "type": "Feature",
  "properties": {
    "gn:admin1_code":"41",
    "gn:asciiname":"Mehdiabad",
    "gn:country_code":"IR",
    "gn:dem":1052,
    "gn:feature_class":"P",
    "gn:feature_code":"PPL",
    "gn:name":"Mehd\u012b\u0101b\u0101d",
    "gn:population":0,
    "gn:timezone":"Asia/Tehran",
    "iso:country":"IR",
    "name:aze_x_preferred":[
        "Mehdiabad"
    ],
    "name:che_x_preferred":[
        "\u041c\u0435\u0445\u0434\u0438\u0430\u0431\u0430\u0434"
    ],
    "name:fas_x_preferred":[
        "Ebr\u0101h\u012bm\u0101b\u0101d"
    ],
    "name:fas_x_variant":[
        "\u0627\u0628\u0631\u0627\u0647\u06cc\u0645 \u0622\u0628\u0627\u062f",
        "\u0645\u0647\u062f\u06cc \u0622\u0628\u0627\u062f",
        "\u0645\u0647\u062f\u06cc\u200c\u0622\u0628\u0627\u062f"
    ],
    "name:kat_x_preferred":[
        "\u10db\u10d4\u10f0\u10d3\u10d8\u10d0\u10d1\u10d0\u10d3\u10d8"
    ],
    "name:und_x_variant":[
        "Qal\u2018eh-i-\u0100gha H\u0101ji",
        "Qal\u2018eh \u0100q\u0101 \u1e28\u0101j\u012b",
        "Qal\u2018eh-ye \u0100q\u0101 \u1e28\u0101jj\u012b",
        "Mehd\u012b\u0101b\u0101d"
    ],
    "wof:name":"Mehdiabad",
    "wof:placetype":"locality"
},
  "geometry": {"coordinates":[59.58875,33.92822],"type":"Point"}
}