{
  "type": "Feature",
  "properties": {
    "gn:admin1_code":"25.0",
    "gn:asciiname":"Farinu",
    "gn:country_code":"IR",
    "gn:dem":1425,
    "gn:feature_class":"P",
    "gn:feature_code":"PPL",
    "gn:name":"Far\u012bn\u016b",
    "gn:population":0,
    "gn:timezone":"Asia/Tehran",
    "iso:country":"IR",
    "name:fas_x_preferred":[
        "\u0641\u064e\u0631\u064a\u0646\u0648"
    ],
    "name:fas_x_variant":[
        "Far\u012bn\u016b"
    ],
    "wof:name":"Farinu",
    "wof:placetype":"locality"
},
  "geometry": {"coordinates":[56.83333,35.43333],"type":"Point"}
}