{
  "type": "Feature",
  "properties": {
    "gn:admin1_code":"8.0",
    "gn:asciiname":"Sura Sar",
    "gn:country_code":"IR",
    "gn:dem":2019,
    "gn:feature_class":"P",
    "gn:feature_code":"PPL",
    "gn:name":"S\u016br\u0101 Sar",
    "gn:population":0,
    "gn:timezone":"Asia/Tehran",
    "iso:country":"IR",
    "name:fas_x_preferred":[
        "\u0633\u0648\u0631\u0627 \u0633\u0631"
    ],
    "name:und_x_variant":[
        "S\u016br\u0101 Sar"
    ],
    "wof:name":"Sura Sar",
    "wof:placetype":"locality"
},
  "geometry": {"coordinates":[50.13435,36.9185],"type":"Point"}
}