{
  "type": "Feature",
  "properties": {
    "gn:admin1_code":"35",
    "gn:asciiname":"Abelu",
    "gn:country_code":"IR",
    "gn:dem":57,
    "gn:feature_class":"P",
    "gn:feature_code":"PPL",
    "gn:name":"\u0100bel\u016b",
    "gn:population":0,
    "gn:timezone":"Asia/Tehran",
    "iso:country":"IR",
    "name:fas_x_preferred":[
        "\u0100bel\u016b"
    ],
    "name:fas_x_variant":[
        "\u0622\u0628\u0644\u0648"
    ],
    "wof:name":"Abelu",
    "wof:placetype":"locality"
},
  "geometry": {"coordinates":[53.3191,36.64248],"type":"Point"}
}