{
  "type": "Feature",
  "properties": {
    "gn:admin1_code":"42",
    "gn:asciiname":"Chahar Bast",
    "gn:country_code":"IR",
    "gn:dem":1947,
    "gn:feature_class":"P",
    "gn:feature_code":"PPL",
    "gn:name":"Chah\u0101r Bast",
    "gn:population":0,
    "gn:timezone":"Asia/Tehran",
    "iso:country":"IR",
    "name:fas_x_preferred":[
        "\u0686\u0647\u0627\u0631 \u0628\u0633\u062a"
    ],
    "name:fas_x_variant":[
        "Chah\u0101r Bast"
    ],
    "wof:name":"Chahar Bast",
    "wof:placetype":"locality"
},
  "geometry": {"coordinates":[59.63488,35.63336],"type":"Point"}
}