{
  "type": "Feature",
  "properties": {
    "gn:admin1_code":"8",
    "gn:asciiname":"Aghuz Keleh",
    "gn:country_code":"IR",
    "gn:dem":641,
    "gn:feature_class":"P",
    "gn:feature_code":"PPL",
    "gn:name":"\u0100gh\u016bz Keleh",
    "gn:population":0,
    "gn:timezone":"Asia/Tehran",
    "iso:country":"IR",
    "name:fas_x_preferred":[
        "\u0100gh\u016bz Keleh"
    ],
    "name:fas_x_variant":[
        "\u0622\u063a\u0648\u0632 \u06a9\u0644\u0647"
    ],
    "wof:name":"Aghuz Keleh",
    "wof:placetype":"locality"
},
  "geometry": {"coordinates":[49.03086,37.16029],"type":"Point"}
}