{
  "type": "Feature",
  "properties": {
    "gn:admin1_code":"26.0",
    "gn:asciiname":"Dar-e Bala",
    "gn:country_code":"IR",
    "gn:dem":910,
    "gn:feature_class":"P",
    "gn:feature_code":"PPL",
    "gn:name":"Dar-e B\u0101l\u0101",
    "gn:population":0,
    "gn:timezone":"Asia/Tehran",
    "iso:country":"IR",
    "name:fas_x_preferred":[
        "Darb\u0101l\u0101"
    ],
    "name:fas_x_variant":[
        "Dar-e B\u0101l\u0101",
        "\u062f\u0631 \u0628\u0627\u0644\u0627"
    ],
    "name:und_x_variant":[
        "Dar-e B\u0101l\u0101",
        "\u062f\u0631 \u0628\u0627\u0644\u0627"
    ],
    "wof:name":"Dar-e Bala",
    "wof:placetype":"locality"
},
  "geometry": {"coordinates":[51.6957,35.3047],"type":"Point"}
}