{
  "type": "Feature",
  "properties": {
    "gn:admin1_code":"23.0",
    "gn:asciiname":"Sarab Sangi",
    "gn:country_code":"IR",
    "gn:dem":1895,
    "gn:feature_class":"P",
    "gn:feature_code":"PPL",
    "gn:name":"Sar\u0101b Sang\u012b",
    "gn:population":0,
    "gn:timezone":"Asia/Tehran",
    "iso:country":"IR",
    "name:fas_x_preferred":[
        "\u0633\u064e\u0631\u0627\u0628 \u0633\u064e\u0646\u06af\u06cc"
    ],
    "name:fas_x_variant":[
        "Sar\u0101b Sang\u012b"
    ],
    "wof:name":"Sarab Sangi",
    "wof:placetype":"locality"
},
  "geometry": {"coordinates":[48.66667,33.33333],"type":"Point"}
}