{
  "type": "Feature",
  "properties": {
    "gn:admin1_code":"7",
    "gn:asciiname":"Dehnow",
    "gn:country_code":"IR",
    "gn:dem":1584,
    "gn:feature_class":"P",
    "gn:feature_code":"PPL",
    "gn:name":"Dehnow",
    "gn:population":0,
    "gn:timezone":"Asia/Tehran",
    "iso:country":"IR",
    "name:ara_x_preferred":[
        "\u062f\u0647 \u0646\u0648"
    ],
    "name:fas_x_preferred":[
        "\u062f\u0647\u0646\u0648"
    ],
    "name:fas_x_variant":[
        "\u062f\u0647\u200c\u0646\u0648"
    ],
    "name:msa_x_preferred":[
        "Deh Now"
    ],
    "name:und_x_variant":[
        "Deh-e Now",
        "Deh Now Na\u015f\u012br\u0101b\u0101d",
        "Dehnow"
    ],
    "wof:name":"Dehnow",
    "wof:placetype":"locality"
},
  "geometry": {"coordinates":[53.20338,29.76723],"type":"Point"}
}