{
  "type": "Feature",
  "properties": {
    "gn:admin1_code":"4.0",
    "gn:asciiname":"Shandan",
    "gn:country_code":"IR",
    "gn:dem":1166,
    "gn:feature_class":"P",
    "gn:feature_code":"PPL",
    "gn:name":"Shand\u0101n",
    "gn:population":0,
    "gn:timezone":"Asia/Tehran",
    "iso:country":"IR",
    "name:fas_x_preferred":[
        "\u0634\u0646\u062f\u0627\u0646"
    ],
    "name:fas_x_variant":[
        "Shand\u0101n"
    ],
    "wof:name":"Shandan",
    "wof:placetype":"locality"
},
  "geometry": {"coordinates":[61.8978,27.3793],"type":"Point"}
}