{
  "type": "Feature",
  "properties": {
    "gn:admin1_code":"15",
    "gn:asciiname":"Temmad-e Bazar Gah",
    "gn:country_code":"IR",
    "gn:dem":578,
    "gn:feature_class":"P",
    "gn:feature_code":"PPLL",
    "gn:name":"Temmad-e B\u0101z\u0101r Gah",
    "gn:population":0,
    "gn:timezone":"Asia/Tehran",
    "iso:country":"IR",
    "name:fas_x_preferred":[
        "Temmad-e B\u0101z\u0101r Gah"
    ],
    "name:fas_x_variant":[
        "\u062a\u0645\u062f \u0628\u0627\u0632\u0627\u0631\u06af\u0647"
    ],
    "name:und_x_variant":[
        "Tamad"
    ],
    "wof:name":"Temmad-e Bazar Gah",
    "wof:placetype":"locality"
},
  "geometry": {"coordinates":[48.95332,32.59043],"type":"Point"}
}