{
  "type": "Feature",
  "properties": {
    "gn:admin1_code":"29",
    "gn:asciiname":"Khaleseh",
    "gn:country_code":"IR",
    "gn:dem":953,
    "gn:feature_class":"P",
    "gn:feature_code":"PPL",
    "gn:name":"Kh\u0101le\u015feh",
    "gn:population":0,
    "gn:timezone":"Asia/Tehran",
    "iso:country":"IR",
    "name:fas_x_preferred":[
        "Kh\u0101le\u015feh"
    ],
    "wof:name":"Khaleseh",
    "wof:placetype":"locality"
},
  "geometry": {"coordinates":[57.54306,30.37444],"type":"Point"}
}