{
  "type": "Feature",
  "properties": {
    "gn:admin1_code":"42.0",
    "gn:asciiname":"Kalateh-ye Hasan Khan",
    "gn:country_code":"IR",
    "gn:dem":954,
    "gn:feature_class":"P",
    "gn:feature_code":"PPL",
    "gn:name":"Kal\u0101teh-ye \u1e28asan Kh\u0101n",
    "gn:population":0,
    "gn:timezone":"Asia/Tehran",
    "iso:country":"IR",
    "name:fas_x_preferred":[
        "Kal\u0101teh-ye \u1e28asan Kh\u0101n"
    ],
    "wof:name":"Kalateh-ye Hasan Khan",
    "wof:placetype":"locality"
},
  "geometry": {"coordinates":[57.66806,36.20111],"type":"Point"}
}