{
  "type": "Feature",
  "properties": {
    "gn:admin1_code":"3",
    "gn:asciiname":"Garmdarreh",
    "gn:country_code":"IR",
    "gn:dem":1988,
    "gn:feature_class":"P",
    "gn:feature_code":"PPL",
    "gn:name":"Garmdarreh",
    "gn:population":0,
    "gn:timezone":"Asia/Tehran",
    "iso:country":"IR",
    "name:ara_x_preferred":[
        "\u063a\u0631\u0645\u062f\u0631\u0647"
    ],
    "name:aze_x_preferred":[
        "G\u0259rmd\u0259r\u0259"
    ],
    "name:ceb_x_preferred":[
        "Garmdarreh"
    ],
    "name:fas_x_preferred":[
        "\u06af\u0631\u0645\u062f\u0631\u0651\u0647"
    ],
    "name:fas_x_variant":[
        "\u06af\u0631\u0645\u062f\u0631\u0647"
    ],
    "name:ita_x_preferred":[
        "Garmdarreh"
    ],
    "name:mlg_x_preferred":[
        "Garmdarreh"
    ],
    "name:msa_x_preferred":[
        "Garmdarreh"
    ],
    "name:rus_x_preferred":[
        "\u0413\u0435\u0440\u043c\u0434\u0435\u0440\u0440\u0435"
    ],
    "name:swe_x_preferred":[
        "Garmdarreh"
    ],
    "name:tur_x_preferred":[
        "Germdere"
    ],
    "name:urd_x_preferred":[
        "\u06af\u0631\u0645\u062f\u0631\u06c1"
    ],
    "wof:name":"Garmdarreh",
    "wof:placetype":"locality"
},
  "geometry": {"coordinates":[50.81653,32.68857],"type":"Point"}
}