{
  "type": "Feature",
  "properties": {
    "gn:admin1_code":"7",
    "gn:asciiname":"Ranjeh Kuh",
    "gn:country_code":"IR",
    "gn:dem":1238,
    "gn:feature_class":"P",
    "gn:feature_code":"PPL",
    "gn:name":"Ranjeh K\u016bh",
    "gn:population":0,
    "gn:timezone":"Asia/Tehran",
    "iso:country":"IR",
    "name:fas_x_preferred":[
        "\u0631\u0646\u062c \u06a9\u0648\u0647"
    ],
    "name:fas_x_variant":[
        "Ronjek\u016b va Seh Darreh",
        "Ronj K\u016bh",
        "\u0631\u0646\u062c\u0647 \u06a9\u0648\u0647",
        "\u0631\u0646\u062c\u06a9\u0648"
    ],
    "name:und_x_variant":[
        "Ronjek\u016b",
        "Ranjeh K\u016bh"
    ],
    "wof:name":"Ranjeh Kuh",
    "wof:placetype":"locality"
},
  "geometry": {"coordinates":[53.69577,28.48582],"type":"Point"}
}