{
  "type": "Feature",
  "properties": {
    "gn:admin1_code":"28",
    "gn:asciiname":"Rahmatabad",
    "gn:country_code":"IR",
    "gn:dem":1164,
    "gn:feature_class":"P",
    "gn:feature_code":"PPL",
    "gn:name":"Ra\u1e29mat\u0101b\u0101d",
    "gn:population":0,
    "gn:timezone":"Asia/Tehran",
    "iso:country":"IR",
    "name:ara_x_preferred":[
        "\u0631\u062d\u0645\u062a \u0623\u0628\u0627\u062f"
    ],
    "name:fas_x_preferred":[
        "Ra\u1e29mat\u0101b\u0101d"
    ],
    "name:fas_x_variant":[
        "\u0631\u062d\u0645\u062a\u200c\u0622\u0628\u0627\u062f"
    ],
    "wof:name":"Rahmatabad",
    "wof:placetype":"locality"
},
  "geometry": {"coordinates":[52.77472,33.3575],"type":"Point"}
}