{
  "type": "Feature",
  "properties": {
    "gn:admin1_code":"7",
    "gn:asciiname":"Gumehr",
    "gn:country_code":"IR",
    "gn:dem":2154,
    "gn:feature_class":"P",
    "gn:feature_code":"PPL",
    "gn:name":"G\u016bmehr",
    "gn:population":0,
    "gn:timezone":"Asia/Tehran",
    "iso:country":"IR",
    "name:fas_x_preferred":[
        "G\u016bmehr"
    ],
    "wof:name":"Gumehr",
    "wof:placetype":"locality"
},
  "geometry": {"coordinates":[51.96,30.18639000000001],"type":"Point"}
}