{
  "type": "Feature",
  "properties": {
    "gn:admin1_code":"23",
    "gn:asciiname":"Shahrak-e Sur",
    "gn:country_code":"IR",
    "gn:dem":1909,
    "gn:feature_class":"P",
    "gn:feature_code":"PPL",
    "gn:name":"Shahrak-e S\u016br",
    "gn:population":0,
    "gn:timezone":"Asia/Tehran",
    "iso:country":"IR",
    "name:fas_x_preferred":[
        "\u0634\u0647\u0631\u06a9 \u0633\u0648\u0631"
    ],
    "name:fas_x_variant":[
        "Shahrak-e S\u016br",
        "\u0634\u0647\u0631\u06a9 \u0627\u0634\u062a\u0631\u0627\u0646 \u06a9\u0648\u0647"
    ],
    "name:und_x_variant":[
        "Shahrak-e Oshtor\u0101n K\u016bh"
    ],
    "wof:name":"Shahrak-e Sur",
    "wof:placetype":"locality"
},
  "geometry": {"coordinates":[49.56679000000001,33.3963],"type":"Point"}
}