{
  "type": "Feature",
  "properties": {
    "gn:admin1_code":"5",
    "gn:asciiname":"Darreh Talkh",
    "gn:country_code":"IR",
    "gn:dem":1203,
    "gn:feature_class":"P",
    "gn:feature_code":"PPL",
    "gn:name":"Darreh Talkh",
    "gn:population":0,
    "gn:timezone":"Asia/Tehran",
    "iso:country":"IR",
    "name:fas_x_preferred":[
        "\u062f\u0631\u0647 \u062a\u0644\u062e"
    ],
    "wof:name":"Darreh Talkh",
    "wof:placetype":"locality"
},
  "geometry": {"coordinates":[50.51635,31.14127],"type":"Point"}
}