{
  "type": "Feature",
  "properties": {
    "gn:admin1_code":"11",
    "gn:asciiname":"Saruk",
    "gn:country_code":"IR",
    "gn:dem":462,
    "gn:feature_class":"P",
    "gn:feature_code":"PPL",
    "gn:name":"Sar\u016bk",
    "gn:population":0,
    "gn:timezone":"Asia/Tehran",
    "iso:country":"IR",
    "name:fas_x_preferred":[
        "S\u016brak"
    ],
    "name:fas_x_variant":[
        "Sh\u016brak",
        "\u0634\u0648\u0631\u0643",
        "\u0633\u0631\u0648\u06a9"
    ],
    "name:und_x_variant":[
        "Sar\u016bk"
    ],
    "wof:name":"Saruk",
    "wof:placetype":"locality"
},
  "geometry": {"coordinates":[55.16925,27.14042],"type":"Point"}
}