{
  "type": "Feature",
  "properties": {
    "gn:admin1_code":"13",
    "gn:asciiname":"Davazdah Emam",
    "gn:country_code":"IR",
    "gn:dem":733,
    "gn:feature_class":"P",
    "gn:feature_code":"PPL",
    "gn:name":"Dav\u0101zdah Em\u0101m",
    "gn:population":0,
    "gn:timezone":"Asia/Tehran",
    "iso:country":"IR",
    "name:fas_x_preferred":[
        "Dav\u0101zdah Em\u0101m"
    ],
    "wof:name":"Davazdah Emam",
    "wof:placetype":"locality"
},
  "geometry": {"coordinates":[45.96333,34.37528],"type":"Point"}
}