{
  "type": "Feature",
  "properties": {
    "gn:admin1_code":"9",
    "gn:asciiname":"Dastjerd",
    "gn:country_code":"IR",
    "gn:dem":1682,
    "gn:feature_class":"P",
    "gn:feature_code":"PPL",
    "gn:name":"Dastjerd",
    "gn:population":0,
    "gn:timezone":"Asia/Tehran",
    "iso:country":"IR",
    "name:fas_x_preferred":[
        "\u062f\u0633\u062a\u062c\u0631\u062f"
    ],
    "name:msa_x_preferred":[
        "Dastjerd"
    ],
    "name:und_x_variant":[
        "Dast-\u012b-J\u012brd",
        "Dasteh Jerd",
        "Dastjerd"
    ],
    "wof:name":"Dastjerd",
    "wof:placetype":"locality"
},
  "geometry": {"coordinates":[48.71954,35.2492],"type":"Point"}
}