{
  "type": "Feature",
  "properties": {
    "gn:admin1_code":"3",
    "gn:asciiname":"Durak",
    "gn:country_code":"IR",
    "gn:dem":1744,
    "gn:feature_class":"P",
    "gn:feature_code":"PPL",
    "gn:name":"D\u016brak",
    "gn:population":0,
    "gn:timezone":"Asia/Tehran",
    "iso:country":"IR",
    "name:bel_x_preferred":[
        "\u0414\u0443\u0440\u0430\u043d\u044c"
    ],
    "name:ces_x_preferred":[
        "Dud\u00e1k"
    ],
    "name:deu_x_preferred":[
        "Durak"
    ],
    "name:est_x_preferred":[
        "Turakas"
    ],
    "name:fas_x_preferred":[
        "D\u016brak-e B\u0101l\u0101"
    ],
    "name:fas_x_variant":[
        "D\u016brak-e P\u0101\u2019\u012bn",
        "D\u016brak",
        "\u062f\u0648\u0631\u0643"
    ],
    "name:fin_x_preferred":[
        "Durak"
    ],
    "name:fra_x_preferred":[
        "Durak"
    ],
    "name:heb_x_preferred":[
        "\u05d3\u05d5\u05e8\u05d0\u05e7"
    ],
    "name:hye_x_preferred":[
        "\u0534\u0578\u0582\u057c\u0561\u056f"
    ],
    "name:jpn_x_preferred":[
        "\u30c9\u30a5\u30e9\u30fc\u30af"
    ],
    "name:kor_x_preferred":[
        "\ub450\ub77c\ud06c"
    ],
    "name:lav_x_preferred":[
        "C\u016bkas"
    ],
    "name:lit_x_preferred":[
        "Durnius"
    ],
    "name:nld_x_preferred":[
        "Doerak"
    ],
    "name:pol_x_preferred":[
        "Dure\u0144"
    ],
    "name:rus_x_preferred":[
        "\u0414\u0443\u0440\u0430\u043a"
    ],
    "name:spa_x_preferred":[
        "Durak"
    ],
    "name:swe_x_preferred":[
        "Durak"
    ],
    "name:ukr_x_preferred":[
        "\u0414\u0443\u0440\u0435\u043d\u044c"
    ],
    "name:und_x_variant":[
        "D\u016brak",
        "Doorak Bazaft",
        "\u062f\u0648\u0631\u0643"
    ],
    "name:vie_x_preferred":[
        "B\u00e0i t\u1ea5n"
    ],
    "name:zho_x_preferred":[
        "\u50bb\u74dc"
    ],
    "wof:name":"Durak",
    "wof:placetype":"locality"
},
  "geometry": {"coordinates":[49.99407,32.22835],"type":"Point"}
}