{
  "type": "Feature",
  "properties": {
    "gn:admin1_code":"3",
    "gn:asciiname":"Durak",
    "gn:country_code":"IR",
    "gn:dem":1744,
    "gn:feature_class":"P",
    "gn:feature_code":"PPL",
    "gn:name":"D\u016brak",
    "gn:population":0,
    "gn:timezone":"Asia/Tehran",
    "iso:country":"IR",
    "name:fas_x_preferred":[
        "D\u016brak-e B\u0101l\u0101"
    ],
    "name:fas_x_variant":[
        "D\u016brak-e P\u0101\u2019\u012bn",
        "D\u016brak",
        "\u062f\u0648\u0631\u0643"
    ],
    "name:und_x_variant":[
        "D\u016brak",
        "Doorak Bazaft",
        "\u062f\u0648\u0631\u0643"
    ],
    "wof:name":"Durak",
    "wof:placetype":"locality"
},
  "geometry": {"coordinates":[49.99407,32.22835],"type":"Point"}
}