{
  "type": "Feature",
  "properties": {
    "gn:admin1_code":"8",
    "gn:asciiname":"Divshal",
    "gn:country_code":"IR",
    "gn:dem":8,
    "gn:feature_class":"P",
    "gn:feature_code":"PPL",
    "gn:name":"D\u012bvshal",
    "gn:population":0,
    "gn:timezone":"Asia/Tehran",
    "iso:country":"IR",
    "name:fas_x_preferred":[
        "D\u012bvshal"
    ],
    "name:fas_x_variant":[
        "\u062f\u06cc\u0648\u0634\u0644"
    ],
    "name:msa_x_preferred":[
        "Divshal"
    ],
    "name:ukr_x_preferred":[
        "\u0414\u0456\u0432\u0448\u0430\u043b\u044c"
    ],
    "name:und_x_variant":[
        "B\u012bj\u0101r B\u0101gh D\u012bvshal",
        "B\u012bj\u0101r B\u0101gh-e D\u012bvshal",
        "\u062f\u06cc\u0648\u0634\u0644"
    ],
    "wof:name":"Divshal",
    "wof:placetype":"locality"
},
  "geometry": {"coordinates":[50.11058,37.18037],"type":"Point"}
}