{
  "type": "Feature",
  "properties": {
    "gn:admin1_code":"13",
    "gn:asciiname":"Bardarmian",
    "gn:country_code":"IR",
    "gn:dem":1449,
    "gn:feature_class":"P",
    "gn:feature_code":"PPL",
    "gn:name":"Bardarm\u012b\u0101n",
    "gn:population":0,
    "gn:timezone":"Asia/Tehran",
    "iso:country":"IR",
    "name:fas_x_preferred":[
        "Bardarm\u012b\u0101n"
    ],
    "name:fas_x_variant":[
        "\u0628\u0631\u062f\u0631\u0645\u064a\u0627\u0646",
        "\u0628\u0631\u0647 \u06af\u06cc\u0646\u0647 \u0642\u0627\u0633\u0645 \u062e\u0627\u0646\u06cc"
    ],
    "name:und_x_variant":[
        "Bareh G\u012bneh-ye Q\u0101sem Kh\u0101n\u012b"
    ],
    "wof:name":"Bardarmian",
    "wof:placetype":"locality"
},
  "geometry": {"coordinates":[46.5215,33.9095],"type":"Point"}
}