{
  "type": "Feature",
  "properties": {
    "gn:admin1_code":"28.0",
    "gn:asciiname":"Agarjeh",
    "gn:country_code":"IR",
    "gn:dem":2222,
    "gn:feature_class":"P",
    "gn:feature_code":"PPL",
    "gn:name":"Agarjeh",
    "gn:population":0,
    "gn:timezone":"Asia/Tehran",
    "iso:country":"IR",
    "name:fas_x_preferred":[
        "Akr\u012bcheh"
    ],
    "name:fas_x_variant":[
        "\u0627\u06af\u0631\u062c\u0647"
    ],
    "name:und_x_variant":[
        "Agar\u012bjeh",
        "Akarcheh",
        "Agarjeh",
        "\u0627\u06af\u0631\u062c\u0647"
    ],
    "wof:name":"Agarjeh",
    "wof:placetype":"locality"
},
  "geometry": {"coordinates":[50.4028,32.59855],"type":"Point"}
}