{
  "type": "Feature",
  "properties": {
    "gn:admin1_code":"26.0",
    "gn:asciiname":"Pey Gonbad",
    "gn:country_code":"IR",
    "gn:dem":2194,
    "gn:feature_class":"P",
    "gn:feature_code":"PPLF",
    "gn:name":"Pey Gonbad",
    "gn:population":0,
    "gn:timezone":"Asia/Tehran",
    "iso:country":"IR",
    "name:fas_x_preferred":[
        "\u067e\u06cc \u06af\u0646\u0628\u062f"
    ],
    "name:fas_x_variant":[
        "B\u012b Gaband",
        "\u0628\u06cc \u06af\u0628\u0646\u062f"
    ],
    "name:und_x_variant":[
        "\u0628\u06cc \u06af\u0628\u0646\u062f"
    ],
    "wof:name":"Pey Gonbad",
    "wof:placetype":"locality"
},
  "geometry": {"coordinates":[51.3599,35.9669],"type":"Point"}
}