{
  "type": "Feature",
  "properties": {
    "gn:admin1_code":"23",
    "gn:asciiname":"Irveh",
    "gn:country_code":"IR",
    "gn:dem":1263,
    "gn:feature_class":"P",
    "gn:feature_code":"PPL",
    "gn:name":"\u012arveh",
    "gn:population":0,
    "gn:timezone":"Asia/Tehran",
    "iso:country":"IR",
    "name:ceb_x_preferred":[
        "\u012arveh"
    ],
    "name:fas_x_preferred":[
        "\u0627\u06cc\u0631\u0648\u0647"
    ],
    "name:fas_x_variant":[
        "\u064a\u0631\u0648\u064e\u0646\u062f",
        "\u012arveh"
    ],
    "name:swe_x_preferred":[
        "\u012arveh"
    ],
    "name:und_x_variant":[
        "\u012arvand"
    ],
    "wof:name":"Irveh",
    "wof:placetype":"locality"
},
  "geometry": {"coordinates":[48.8483,33.2207],"type":"Point"}
}