{
  "type": "Feature",
  "properties": {
    "gn:admin1_code":"8",
    "gn:asciiname":"Padegam",
    "gn:country_code":"IR",
    "gn:dem":822,
    "gn:feature_class":"P",
    "gn:feature_code":"PPL",
    "gn:name":"P\u0101deg\u0101m",
    "gn:population":0,
    "gn:timezone":"Asia/Tehran",
    "iso:country":"IR",
    "name:fas_x_preferred":[
        "\u067e\u0627\u0631\u06af\u0627\u0645"
    ],
    "name:fas_x_variant":[
        "P\u0101rg\u0101m",
        "\u067e\u0627\u062f\u06af\u0627\u0645"
    ],
    "name:und_x_variant":[
        "P\u0101deg\u0101m"
    ],
    "wof:name":"Padegam",
    "wof:placetype":"locality"
},
  "geometry": {"coordinates":[48.8289,37.5061],"type":"Point"}
}