{
  "type": "Feature",
  "properties": {
    "gn:admin1_code":"5.0",
    "gn:asciiname":"Mansurabad-e Vasat",
    "gn:country_code":"IR",
    "gn:dem":861,
    "gn:feature_class":"P",
    "gn:feature_code":"PPL",
    "gn:name":"Man\u015f\u016br\u0101b\u0101d-e Vasa\u0163",
    "gn:population":0,
    "gn:timezone":"Asia/Tehran",
    "iso:country":"IR",
    "name:fas_x_preferred":[
        "Man\u015f\u016br\u0101b\u0101d-e Vasa\u0163"
    ],
    "name:fas_x_variant":[
        "\u0645\u0646\u0635\u0648\u0631 \u0622\u0628\u0627\u062f \u0648\u0633\u0637"
    ],
    "name:und_x_variant":[
        "\u0645\u0646\u0635\u0648\u0631 \u0622\u0628\u0627\u062f \u0648\u0633\u0637"
    ],
    "wof:name":"Mansurabad-e Vasat",
    "wof:placetype":"locality"
},
  "geometry": {"coordinates":[51.15163,30.34015],"type":"Point"}
}