{
  "type": "Feature",
  "properties": {
    "gn:admin1_code":"23",
    "gn:asciiname":"Chah Shirin",
    "gn:country_code":"IR",
    "gn:dem":901,
    "gn:feature_class":"P",
    "gn:feature_code":"PPL",
    "gn:name":"Ch\u0101h Sh\u012br\u012bn",
    "gn:population":0,
    "gn:timezone":"Asia/Tehran",
    "iso:country":"IR",
    "name:fas_x_preferred":[
        "\u0686\u0627\u0647 \u0634\u064a\u0631\u064a\u0646\u0650 \u0648\u0627\u0634\u064a\u0627\u0646"
    ],
    "name:fas_x_variant":[
        "\u0648\u0627\u0634\u064a\u0627\u0646\u0650 \u0686\u0627\u0647\u0650 \u0634\u064a\u0631\u064a\u0646",
        "\u0648\u0627\u0634\u064a\u0627\u0646",
        "\u0686\u0627\u0647 \u0634\u06cc\u0631 \u0648\u0627\u0634\u06cc\u0627\u0646",
        "Ch\u0101h Sh\u012br\u012bn-e V\u0101sh\u012b\u0101n",
        "Ch\u0101h Sh\u012br-e V\u0101sh\u012by\u0101n",
        "\u0686\u0627\u0647 \u0634\u06cc\u0631\u06cc\u0646"
    ],
    "name:und_x_variant":[
        "V\u0101sh\u012by\u0101n",
        "V\u0101sh\u012b\u0101n",
        "V\u0101shey\u0101n",
        "V\u0101sh\u012b\u0101n-e Ch\u0101h-e Sh\u012br\u012bn",
        "Ch\u0101h Sh\u012br\u012bn"
    ],
    "wof:name":"Chah Shirin",
    "wof:placetype":"locality"
},
  "geometry": {"coordinates":[47.7901,33.1928],"type":"Point"}
}