{
  "type": "Feature",
  "properties": {
    "gn:admin1_code":"13",
    "gn:asciiname":"Farrokh Khani",
    "gn:country_code":"IR",
    "gn:dem":1445,
    "gn:feature_class":"P",
    "gn:feature_code":"PPL",
    "gn:name":"Farrokh Kh\u0101n\u012b",
    "gn:population":0,
    "gn:timezone":"Asia/Tehran",
    "iso:country":"IR",
    "name:ara_x_preferred":[
        "\u0641\u0631\u062d\u200c\u062e\u0627\u0646\u064a"
    ],
    "name:ceb_x_preferred":[
        "Farrokh Kh\u0101n\u012b"
    ],
    "name:fas_x_preferred":[
        "\u0641\u0631\u0651\u062e \u062e\u0627\u0646\u06cc"
    ],
    "name:fas_x_variant":[
        "Farrokh Kh\u0101n\u012b",
        "\u0641\u0631\u062d\u200c\u062e\u0627\u0646\u06cc"
    ],
    "name:swe_x_preferred":[
        "Farrokh Kh\u0101n\u012b"
    ],
    "name:und_x_variant":[
        "Deh Farokh Kh\u0101n"
    ],
    "wof:name":"Farrokh Khani",
    "wof:placetype":"locality"
},
  "geometry": {"coordinates":[46.6988,34.1273],"type":"Point"}
}