{
  "type": "Feature",
  "properties": {
    "gn:admin1_code":"15",
    "gn:asciiname":"Beyt-e Bavi",
    "gn:country_code":"IR",
    "gn:dem":64,
    "gn:feature_class":"P",
    "gn:feature_code":"PPL",
    "gn:name":"Beyt-e B\u0101v\u012b",
    "gn:population":0,
    "gn:timezone":"Asia/Tehran",
    "iso:country":"IR",
    "name:ceb_x_preferred":[
        "Beyt-e B\u0101v\u012b"
    ],
    "name:fas_x_preferred":[
        "\u0628\u06cc\u062a \u0628\u0627\u0648\u06cc"
    ],
    "name:fas_x_variant":[
        "Beyt-e B\u0101v\u012b",
        "\u0634\u0627\u0648\u0647 \u0648\u062d\u062f\u062a"
    ],
    "name:swe_x_preferred":[
        "Beyt-e B\u0101v\u012b"
    ],
    "name:und_x_variant":[
        "Shamakl\u012b",
        "Shem\u0101l\u012b",
        "Shomakel\u012b",
        "B\u0101wi",
        "Sh\u0101veh-ye Va\u1e29dat"
    ],
    "wof:name":"Beyt-e Bavi",
    "wof:placetype":"locality"
},
  "geometry": {"coordinates":[49.35198,31.09802],"type":"Point"}
}