{
  "type": "Feature",
  "properties": {
    "gn:admin1_code":"7",
    "gn:asciiname":"Mahalleh-ye Dadenjan",
    "gn:country_code":"IR",
    "gn:dem":2330,
    "gn:feature_class":"P",
    "gn:feature_code":"PPL",
    "gn:name":"Ma\u1e29alleh-ye D\u0101denj\u0101n",
    "gn:population":0,
    "gn:timezone":"Asia/Tehran",
    "iso:country":"IR",
    "name:fas_x_preferred":[
        "\u062f\u0627\u062f\u0646 \u062c\u0627\u0646"
    ],
    "name:fas_x_variant":[
        "D\u0101den J\u0101n",
        "\u0645\u062d\u0644\u0647 \u062f\u0627\u062f\u0646\u062c\u0627\u0646"
    ],
    "name:und_x_variant":[
        "Ma\u1e29alleh-ye D\u0101denj\u0101n"
    ],
    "wof:name":"Mahalleh-ye Dadenjan",
    "wof:placetype":"locality"
},
  "geometry": {"coordinates":[53.2186,30.6222],"type":"Point"}
}