{
  "type": "Feature",
  "properties": {
    "gn:admin1_code":"41.0",
    "gn:asciiname":"Chah Shahid Bahonar",
    "gn:country_code":"IR",
    "gn:dem":1889,
    "gn:feature_class":"P",
    "gn:feature_code":"PPLF",
    "gn:name":"Ch\u0101h Shah\u012bd B\u0101honar",
    "gn:population":0,
    "gn:timezone":"Asia/Tehran",
    "iso:country":"IR",
    "name:fas_x_preferred":[
        "\u0686\u0627\u0647 \u0634\u0647\u06cc\u062f \u0628\u0627\u0647\u0646\u0631"
    ],
    "name:fas_x_variant":[
        "\u0686\u0627\u0647 \u0634\u0645\u0627\u0631\u0647 \u0686\u0647\u0627\u0631",
        "\u0686\u0627\u0647 \u0633\u0645 \u067e\u0648\u0631"
    ],
    "name:und_x_variant":[
        "Ch\u0101h Shah\u012bd B\u0101honar",
        "Ch\u0101h Shom\u0101reh-ye Chah\u0101r",
        "Ch\u0101h Sam P\u016br"
    ],
    "wof:name":"Chah Shahid Bahonar",
    "wof:placetype":"locality"
},
  "geometry": {"coordinates":[59.77733000000001,32.6657],"type":"Point"}
}