{
  "type": "Feature",
  "properties": {
    "gn:admin1_code":"15",
    "gn:asciiname":"Harnub",
    "gn:country_code":"IR",
    "gn:dem":3,
    "gn:feature_class":"P",
    "gn:feature_code":"PPL",
    "gn:name":"\u1e28arn\u016bb",
    "gn:population":0,
    "gn:timezone":"Asia/Tehran",
    "iso:country":"IR",
    "name:fas_x_preferred":[
        "\u1e28arn\u016bb"
    ],
    "wof:name":"Harnub",
    "wof:placetype":"locality"
},
  "geometry": {"coordinates":[48.22417,30.35],"type":"Point"}
}