{
  "type": "Feature",
  "properties": {
    "gn:admin1_code":"15",
    "gn:asciiname":"Omm ol Helianeh",
    "gn:country_code":"IR",
    "gn:dem":24,
    "gn:feature_class":"P",
    "gn:feature_code":"PPL",
    "gn:name":"Omm ol \u1e28el\u012b\u0101neh",
    "gn:population":0,
    "gn:timezone":"Asia/Tehran",
    "iso:country":"IR",
    "name:ara_x_preferred":[
        "\u0623\u0645 \u0625\u062d\u0644\u064a\u0627\u0646\u0629"
    ],
    "name:azb_x_preferred":[
        "\u0627\u0645 \u0627\u0644\u062d\u0644\u06cc\u0627\u0646\u0647(\u0627\u0647\u0648\u0627\u0632)"
    ],
    "name:fas_x_preferred":[
        "\u0627\u0645\u0651 \u0627\u0644\u0647\u0644\u06cc\u0627\u0646\u0647"
    ],
    "name:fas_x_variant":[
        "Om Hely\u0101neh",
        "Omm ol Hel\u012b\u0101neh",
        "\u0627\u0645 \u0627\u0644\u062d\u0644\u06cc\u0627\u0646\u0647",
        "\u0627\u0645\u200c\u0627\u0644\u062d\u0644\u06cc\u0627\u0646\u0647"
    ],
    "name:und_x_variant":[
        "Ommo\u1e29ley\u0101neh",
        "Omm-e Haly\u0101neh",
        "Om Hely\u0101neh-ye Now",
        "Omm ol \u1e28el\u012b\u0101neh"
    ],
    "wof:name":"Omm ol Helianeh",
    "wof:placetype":"locality"
},
  "geometry": {"coordinates":[49.06688,31.38761],"type":"Point"}
}