{
  "type": "Feature",
  "properties": {
    "gn:admin1_code":"37",
    "gn:asciiname":"Baluchabad-e Siah Khal",
    "gn:country_code":"IR",
    "gn:dem":101,
    "gn:feature_class":"P",
    "gn:feature_code":"PPL",
    "gn:name":"Bal\u016bch\u0101b\u0101d-e S\u012b\u0101h Kh\u0101l",
    "gn:population":0,
    "gn:timezone":"Asia/Tehran",
    "iso:country":"IR",
    "name:fas_x_preferred":[
        "Bal\u016bch\u0101b\u0101d-e S\u012b\u0101h Kh\u0101n"
    ],
    "name:fas_x_variant":[
        "\u0628\u0644\u0648\u0686 \u0622\u0628\u0627\u062f \u0633\u06cc\u0627\u0647 \u062e\u0627\u0646",
        "\u0628\u0644\u0648\u0686 \u0622\u0628\u0627\u062f \u0633\u06cc\u0627\u0647 \u062e\u0627\u0644",
        "\u0628\u0644\u0648\u0686 \u0622\u0628\u0627\u062f"
    ],
    "name:und_x_variant":[
        "\u0628\u0644\u0648\u0686 \u0622\u0628\u0627\u062f \u0633\u06cc\u0627\u0647 \u062e\u0627\u0646",
        "Bal\u016bch\u0101b\u0101d-e S\u012b\u0101h Kh\u0101l",
        "Bal\u016bch\u0101b\u0101d"
    ],
    "wof:name":"Baluchabad-e Siah Khal",
    "wof:placetype":"locality"
},
  "geometry": {"coordinates":[54.93842,36.95435],"type":"Point"}
}