{
  "type": "Feature",
  "properties": {
    "gn:admin1_code":"16",
    "gn:asciiname":"Naneh",
    "gn:country_code":"IR",
    "gn:dem":1324,
    "gn:feature_class":"P",
    "gn:feature_code":"PPL",
    "gn:name":"Naneh",
    "gn:population":0,
    "gn:timezone":"Asia/Tehran",
    "iso:country":"IR",
    "name:ceb_x_preferred":[
        "Naneh"
    ],
    "name:ckb_x_preferred":[
        "\u0646\u06d5\u0646\u06d5"
    ],
    "name:fas_x_preferred":[
        "\u0646\u0646\u0647"
    ],
    "name:swe_x_preferred":[
        "Naneh"
    ],
    "name:und_x_variant":[
        "Nehneh"
    ],
    "wof:name":"Naneh",
    "wof:placetype":"locality"
},
  "geometry": {"coordinates":[46.3025,35.4199],"type":"Point"}
}