{
  "type": "Feature",
  "properties": {
    "gn:admin1_code":"15",
    "gn:asciiname":"Shahid Bahonar",
    "gn:country_code":"IR",
    "gn:dem":82,
    "gn:feature_class":"P",
    "gn:feature_code":"PPL",
    "gn:name":"Shah\u012bd B\u0101honar",
    "gn:population":0,
    "gn:timezone":"Asia/Tehran",
    "iso:country":"IR",
    "name:fas_x_preferred":[
        "Shah\u012bd B\u0101honar"
    ],
    "name:fas_x_variant":[
        "\u0637\u0627\u0644\u0628 \u0622\u0628\u0627\u062f",
        "\u0162\u0101leb\u0101b\u0101d",
        "\u0634\u0647\u06cc\u062f \u0628\u0627\u0647\u0646\u0631",
        "\u0637\u0627\u0644\u0628"
    ],
    "name:und_x_variant":[
        "\u0162\u0101leb"
    ],
    "wof:name":"Shahid Bahonar",
    "wof:placetype":"locality"
},
  "geometry": {"coordinates":[48.30166,32.15018],"type":"Point"}
}