{
  "type": "Feature",
  "properties": {
    "gn:admin1_code":"4.0",
    "gn:asciiname":"Ziar",
    "gn:country_code":"IR",
    "gn:dem":1853,
    "gn:feature_class":"P",
    "gn:feature_code":"PPLF",
    "gn:name":"Z\u012b\u0101r",
    "gn:population":0,
    "gn:timezone":"Asia/Tehran",
    "iso:country":"IR",
    "name:ceb_x_preferred":[
        "Ziar"
    ],
    "name:fas_x_preferred":[
        "\u0632\u06cc\u0627\u0631"
    ],
    "name:fas_x_variant":[
        "Z\u012b\u0101r"
    ],
    "name:swe_x_preferred":[
        "Ziar"
    ],
    "wof:name":"Ziar",
    "wof:placetype":"locality"
},
  "geometry": {"coordinates":[61.1711,28.7189],"type":"Point"}
}