{
  "type": "Feature",
  "properties": {
    "gn:admin1_code":"8.0",
    "gn:asciiname":"Kuh Kari",
    "gn:country_code":"IR",
    "gn:dem":3,
    "gn:feature_class":"P",
    "gn:feature_code":"PPL",
    "gn:name":"K\u016bh Kar\u012b",
    "gn:population":0,
    "gn:timezone":"Asia/Tehran",
    "iso:country":"IR",
    "name:fas_x_preferred":[
        "K\u016bhakar\u012b"
    ],
    "name:fas_x_variant":[
        "\u06a9\u0648\u0647 \u06a9\u0631\u06cc",
        "\u06a9\u0648\u0627 \u06a9\u0631\u06cc"
    ],
    "name:und_x_variant":[
        "K\u016bh Kar\u012b",
        "Kav\u0101 Kar\u012b"
    ],
    "wof:name":"Kuh Kari",
    "wof:placetype":"locality"
},
  "geometry": {"coordinates":[48.9249,37.83049000000001],"type":"Point"}
}