{
  "type": "Feature",
  "properties": {
    "gn:admin1_code":"15.0",
    "gn:asciiname":"Boneh-ye Gah",
    "gn:country_code":"IR",
    "gn:dem":376,
    "gn:feature_class":"P",
    "gn:feature_code":"PPL",
    "gn:name":"Boneh-ye Gah",
    "gn:population":0,
    "gn:timezone":"Asia/Tehran",
    "iso:country":"IR",
    "name:fas_x_preferred":[
        "\u0628\u0646\u0647 \u06af\u0647"
    ],
    "name:fas_x_variant":[
        "\u0642\u0644\u0639\u0647 \u0628\u0646\u0647"
    ],
    "name:und_x_variant":[
        "Qal\u2018eh-ye Boneh"
    ],
    "wof:name":"Boneh-ye Gah",
    "wof:placetype":"locality"
},
  "geometry": {"coordinates":[49.0623,32.3505],"type":"Point"}
}