{
  "type": "Feature",
  "properties": {
    "gn:admin1_code":"37",
    "gn:asciiname":"Palcheqli Aqlar",
    "gn:country_code":"IR",
    "gn:dem":427,
    "gn:feature_class":"P",
    "gn:feature_code":"PPL",
    "gn:name":"P\u0101lcheql\u012b \u0100qlar",
    "gn:population":0,
    "gn:timezone":"Asia/Tehran",
    "iso:country":"IR",
    "name:fas_x_preferred":[
        "P\u0101lcheql\u012b \u0100qlar"
    ],
    "name:fas_x_variant":[
        "\u067e\u0627\u0644\u0686\u0642\u0644\u06cc \u0622\u0642 \u0644\u0631"
    ],
    "wof:name":"Palcheqli Aqlar",
    "wof:placetype":"locality"
},
  "geometry": {"coordinates":[56.2094,37.96713],"type":"Point"}
}