{
  "type": "Feature",
  "properties": {
    "gn:admin1_code":"35",
    "gn:asciiname":"Pa'in Davod Kola",
    "gn:country_code":"IR",
    "gn:dem":14,
    "gn:feature_class":"P",
    "gn:feature_code":"PPL",
    "gn:name":"P\u0101\u2019\u012bn D\u0101vod Kol\u0101",
    "gn:population":0,
    "gn:timezone":"Asia/Tehran",
    "iso:country":"IR",
    "name:fas_x_preferred":[
        "\u062f\u0627\u0648\u0648\u062f \u0643\u064f\u0644\u0627"
    ],
    "name:fas_x_variant":[
        "D\u0101v\u016bd Kol\u0101",
        "P\u0101\u2019\u012bn D\u0101vod Kol\u0101",
        "\u067e\u0627\u0626\u06cc\u0646 \u062f\u0627\u0648\u062f \u0643\u0644\u0627",
        "\u062f\u0627\u0648\u0648\u062f \u0643\u064f\u0644\u0627\u06cc \u067e\u0627\u0626\u064a\u0646"
    ],
    "wof:name":"Pa'in Davod Kola",
    "wof:placetype":"locality"
},
  "geometry": {"coordinates":[52.55067,36.48125],"type":"Point"}
}