{
  "type": "Feature",
  "properties": {
    "gn:admin1_code":"13",
    "gn:asciiname":"Darreh Maran",
    "gn:country_code":"IR",
    "gn:dem":1636,
    "gn:feature_class":"P",
    "gn:feature_code":"PPL",
    "gn:name":"Darreh Mar\u0101n",
    "gn:population":0,
    "gn:timezone":"Asia/Tehran",
    "iso:country":"IR",
    "name:fas_x_preferred":[
        "\u062f\u0631\u0651\u0647 \u0645\u0631\u0627\u0646"
    ],
    "name:fas_x_variant":[
        "Darreh-ye Marr\u0101n",
        "Darreh Mar\u0101n"
    ],
    "wof:name":"Darreh Maran",
    "wof:placetype":"locality"
},
  "geometry": {"coordinates":[47.7929,34.4568],"type":"Point"}
}