{
  "type": "Feature",
  "properties": {
    "gn:admin1_code":"43",
    "gn:asciiname":"Nezamabad",
    "gn:country_code":"IR",
    "gn:dem":956,
    "gn:feature_class":"P",
    "gn:feature_code":"PPL",
    "gn:name":"Nez\u0327\u0101m\u0101b\u0101d",
    "gn:population":0,
    "gn:timezone":"Asia/Tehran",
    "iso:country":"IR",
    "name:fas_x_preferred":[
        "Nez\u0327\u0101m\u0101b\u0101d"
    ],
    "wof:name":"Nezamabad",
    "wof:placetype":"locality"
},
  "geometry": {"coordinates":[56.95,37.05],"type":"Point"}
}