{
  "type": "Feature",
  "properties": {
    "gn:admin1_code":"16.0",
    "gn:asciiname":"Rudkhaneh-ye Vazman",
    "gn:country_code":"IR",
    "gn:dem":1866,
    "gn:feature_class":"P",
    "gn:feature_code":"PPL",
    "gn:name":"R\u016bdkh\u0101neh-ye Vazm\u0101n",
    "gn:population":0,
    "gn:timezone":"Asia/Tehran",
    "iso:country":"IR",
    "name:fas_x_preferred":[
        "R\u016bdkh\u0101neh-ye Vazm\u0101n"
    ],
    "wof:name":"Rudkhaneh-ye Vazman",
    "wof:placetype":"locality"
},
  "geometry": {"coordinates":[47.13333,36.03333],"type":"Point"}
}