{
  "type": "Feature",
  "properties": {
    "gn:admin1_code":"32",
    "gn:asciiname":"Qeshlaq-e Asghar",
    "gn:country_code":"IR",
    "gn:dem":120,
    "gn:feature_class":"P",
    "gn:feature_code":"PPL",
    "gn:name":"Qeshl\u0101q-e A\u015fghar",
    "gn:population":0,
    "gn:timezone":"Asia/Tehran",
    "iso:country":"IR",
    "name:ara_x_preferred":[
        "\u0642\u0634\u0644\u0627\u0642 \u0623\u0635\u063a\u0631"
    ],
    "name:fas_x_preferred":[
        "\u0642\u0634\u0644\u0627\u0642 \u0627\u0635\u063a\u0631"
    ],
    "name:fas_x_variant":[
        "Qeshl\u0101q-e A\u015fghar"
    ],
    "name:msa_x_preferred":[
        "Qeshlaq-e Asghar"
    ],
    "wof:name":"Qeshlaq-e Asghar",
    "wof:placetype":"locality"
},
  "geometry": {"coordinates":[48.1585,39.4486],"type":"Point"}
}