{
  "type": "Feature",
  "properties": {
    "gn:admin1_code":"8",
    "gn:asciiname":"Rud Pish-e Bala",
    "gn:country_code":"IR",
    "gn:dem":8,
    "gn:feature_class":"P",
    "gn:feature_code":"PPL",
    "gn:name":"R\u016bd P\u012bsh-e B\u0101l\u0101",
    "gn:population":0,
    "gn:timezone":"Asia/Tehran",
    "iso:country":"IR",
    "name:fas_x_preferred":[
        "\u0631\u0648\u062f \u067e\u06cc\u0634"
    ],
    "name:fas_x_variant":[
        "R\u016bd P\u012bsh",
        "\u0631\u0648\u062f \u067e\u06cc\u0634 \u0628\u0627\u0644\u0627",
        "\u062e\u0631\u0645 \u0628\u06cc\u0634\u0647",
        "\u06af\u06cc\u06af\u0627\u0633\u0631"
    ],
    "name:und_x_variant":[
        "R\u016bd P\u012bsh",
        "R\u016bd P\u012bsh-e B\u0101l\u0101",
        "Khorram B\u012bsheh",
        "G\u012bg\u0101sar"
    ],
    "wof:name":"Rud Pish-e Bala",
    "wof:placetype":"locality"
},
  "geometry": {"coordinates":[49.39278,37.24609],"type":"Point"}
}