{
  "type": "Feature",
  "properties": {
    "gn:admin1_code":"10",
    "gn:asciiname":"Eyvan",
    "gn:country_code":"IR",
    "gn:dem":1184,
    "gn:feature_class":"P",
    "gn:feature_code":"PPLA2",
    "gn:name":"Eyv\u0101n",
    "gn:population":0,
    "gn:timezone":"Asia/Tehran",
    "iso:country":"IR",
    "name:ara_x_preferred":[
        "\u0625\u064a\u0648\u0627\u0646"
    ],
    "name:aze_x_preferred":[
        "Eyvan"
    ],
    "name:ceb_x_preferred":[
        "Eyv\u0101n"
    ],
    "name:ckb_x_preferred":[
        "\u0626\u06d5\u06cc\u0648\u0627\u0646"
    ],
    "name:fas_x_preferred":[
        "\u0628\u0627\u063a\u0650 \u0634\u0627\u0647"
    ],
    "name:fas_x_variant":[
        "\u0627\u06cc\u0648\u0627\u0646 \u063a\u0631\u0628",
        "Eyv\u0101n",
        "\u062c\u0648\u06cc \u0632\u064e\u0631",
        "Eyv\u0101n-e Gharb",
        "\u0627\u064a\u0648\u0627\u0646",
        "\u0627\u06cc\u0648\u0627\u0646"
    ],
    "name:ita_x_preferred":[
        "Eyvan"
    ],
    "name:mlg_x_preferred":[
        "Eyvan"
    ],
    "name:msa_x_preferred":[
        "Eyvan"
    ],
    "name:nld_x_preferred":[
        "Aivan"
    ],
    "name:pnb_x_preferred":[
        "\u0627\u06cc\u0648\u0627\u0646"
    ],
    "name:pol_x_preferred":[
        "Ejwan"
    ],
    "name:rus_x_preferred":[
        "\u042d\u0439\u0432\u0430\u043d"
    ],
    "name:tgk_x_preferred":[
        "\u0410\u0439\u0432\u043e\u043d"
    ],
    "name:tur_x_preferred":[
        "Eyvan"
    ],
    "name:und_x_variant":[
        "J\u016by Zar",
        "A\u012bw\u0101n",
        "B\u0101gh-e Sh\u0101h",
        "B\u0101gh-\u012b-Sh\u0101h"
    ],
    "name:urd_x_preferred":[
        "\u0627\u06cc\u0648\u0627\u0646"
    ],
    "name:zho_x_preferred":[
        "\u5df4\u683c\u6c99"
    ],
    "wof:name":"Eyvan",
    "wof:placetype":"locality"
},
  "geometry": {"coordinates":[46.3097,33.8272],"type":"Point"}
}