{
  "type": "Feature",
  "properties": {
    "gn:admin1_code":"5",
    "gn:asciiname":"Do Band-e Zilu",
    "gn:country_code":"IR",
    "gn:dem":1349,
    "gn:feature_class":"P",
    "gn:feature_code":"PPL",
    "gn:name":"Do Band-e Z\u012bl\u016b",
    "gn:population":0,
    "gn:timezone":"Asia/Tehran",
    "iso:country":"IR",
    "name:fas_x_preferred":[
        "Do Band-e Z\u012bl\u016b\u2019\u012b"
    ],
    "name:fas_x_variant":[
        "\u062f\u0648 \u0628\u0646\u062f \u0632\u06cc\u0644\u0648"
    ],
    "name:und_x_variant":[
        "Do Band-e Z\u012bl\u016b"
    ],
    "wof:name":"Do Band-e Zilu",
    "wof:placetype":"locality"
},
  "geometry": {"coordinates":[50.57883,31.17294],"type":"Point"}
}