{
  "type": "Feature",
  "properties": {
    "gn:admin1_code":"29.0",
    "gn:asciiname":"Baba Jan",
    "gn:country_code":"IR",
    "gn:dem":2733,
    "gn:feature_class":"P",
    "gn:feature_code":"PPLF",
    "gn:name":"B\u0101b\u0101 J\u0101n",
    "gn:population":0,
    "gn:timezone":"Asia/Tehran",
    "iso:country":"IR",
    "name:fas_x_preferred":[
        "B\u0101b\u0101 J\u0101n"
    ],
    "name:fas_x_variant":[
        "B\u0101b\u016b J\u0101n",
        "\u0628\u0627\u0628\u0648 \u062c\u0627\u0646",
        "\u0628\u0627\u0628\u0627 \u062c\u0627\u0646"
    ],
    "name:und_x_variant":[
        "B\u0101b\u016b J\u0101n",
        "\u0628\u0627\u0628\u0648 \u062c\u0627\u0646"
    ],
    "wof:name":"Baba Jan",
    "wof:placetype":"locality"
},
  "geometry": {"coordinates":[57.32021999999999,29.2233],"type":"Point"}
}