{
  "type": "Feature",
  "properties": {
    "gn:admin1_code":"8",
    "gn:asciiname":"Poshtestan",
    "gn:country_code":"IR",
    "gn:dem":-22,
    "gn:feature_class":"P",
    "gn:feature_code":"PPL",
    "gn:name":"Poshtest\u0101n",
    "gn:population":0,
    "gn:timezone":"Asia/Tehran",
    "iso:country":"IR",
    "name:fas_x_preferred":[
        "Poshts\u0101n"
    ],
    "name:fas_x_variant":[
        "\u067e\u0634\u062a\u0633\u0627\u0646",
        "\u067e\u0634\u062a\u0633\u062a\u0627\u0646",
        "\u067e\u0634\u062a\u0633\u062a\u0627\u0646 \u06af\u0648\u0631 \u0627\u0628\u062c\u0648\u0631"
    ],
    "name:und_x_variant":[
        "Poshtest\u0101n",
        "Poshtest\u0101n G\u016br Abj\u016br"
    ],
    "wof:name":"Poshtestan",
    "wof:placetype":"locality"
},
  "geometry": {"coordinates":[49.6437,37.41455],"type":"Point"}
}