{
  "type": "Feature",
  "properties": {
    "gn:admin1_code":"33",
    "gn:asciiname":"Seyah Dowlan",
    "gn:country_code":"IR",
    "gn:dem":2023,
    "gn:elevation":"0.0",
    "gn:feature_class":"P",
    "gn:feature_code":"PPL",
    "gn:name":"Seyah Dowl\u0101n",
    "gn:population":0,
    "gn:timezone":"Asia/Tehran",
    "iso:country":"IR",
    "name:fas_x_preferred":[
        "\u0633\u064a\u0627\u0647 \u062f\u0648\u0644\u0627\u0646"
    ],
    "name:fas_x_variant":[
        "S\u012b\u0101h Dowl\u0101n",
        "\u0633\u064a\u0647 \u062f\u0648\u0644\u0627\u0646"
    ],
    "name:und_x_variant":[
        "Seyah Dowl\u0101n",
        "Tappeh D\u016bl\u0101"
    ],
    "wof:name":"Seyah Dowlan",
    "wof:placetype":"locality"
},
  "geometry": {"coordinates":[47.3725,38.0983],"type":"Point"}
}