{
  "type": "Feature",
  "properties": {
    "gn:admin1_code":"7",
    "gn:asciiname":"Laleh Buneh",
    "gn:country_code":"IR",
    "gn:dem":2224,
    "gn:feature_class":"P",
    "gn:feature_code":"PPL",
    "gn:name":"L\u0101leh B\u016bneh",
    "gn:population":0,
    "gn:timezone":"Asia/Tehran",
    "iso:country":"IR",
    "name:fas_x_preferred":[
        "L\u0101leh B\u016bneh"
    ],
    "name:und_x_variant":[
        "L\u0101l\u0101b\u016bna"
    ],
    "wof:name":"Laleh Buneh",
    "wof:placetype":"locality"
},
  "geometry": {"coordinates":[55.15,28.58333],"type":"Point"}
}