{
  "type": "Feature",
  "properties": {
    "gn:admin1_code":"28",
    "gn:asciiname":"Hanjan",
    "gn:country_code":"IR",
    "gn:dem":1551,
    "gn:feature_class":"P",
    "gn:feature_code":"PPL",
    "gn:name":"Hanjan",
    "gn:population":0,
    "gn:timezone":"Asia/Tehran",
    "iso:country":"IR",
    "name:fas_x_preferred":[
        "\u0647\u0646\u062c\u0646"
    ],
    "wof:name":"Hanjan",
    "wof:placetype":"locality"
},
  "geometry": {"coordinates":[51.7473,33.6108],"type":"Point"}
}