{
  "type": "Feature",
  "properties": {
    "gn:admin1_code":"9",
    "gn:asciiname":"Tappeh Dibi",
    "gn:country_code":"IR",
    "gn:dem":1814,
    "gn:feature_class":"P",
    "gn:feature_code":"PPL",
    "gn:name":"Tappeh D\u012bb\u012b",
    "gn:population":0,
    "gn:timezone":"Asia/Tehran",
    "iso:country":"IR",
    "name:fas_x_preferred":[
        "\u062a\u067e\u0647\u062f\u064a\u0628\u06cc"
    ],
    "name:fas_x_variant":[
        "Tappeh-ye D\u012bb\u012b",
        "Tappehd\u012bb\u012b",
        "\u062a\u067e\u0647 \u062f\u06cc\u0628\u06cc"
    ],
    "name:msa_x_preferred":[
        "Tappeh-ye Dibi"
    ],
    "name:und_x_variant":[
        "Tepe Dapi",
        "Tappeh D\u012bb\u012b",
        "Tapeh Dibi",
        "Tappah D\u012bb\u012b"
    ],
    "wof:name":"Tappeh Dibi",
    "wof:placetype":"locality"
},
  "geometry": {"coordinates":[48.69453,35.42946],"type":"Point"}
}