{
  "type": "Feature",
  "properties": {
    "gn:admin1_code":"11",
    "gn:asciiname":"Band-e Kalakshu",
    "gn:cc2":"IR",
    "gn:country_code":"IR",
    "gn:dem":740,
    "gn:feature_class":"P",
    "gn:feature_code":"PPL",
    "gn:name":"Band-e Kal\u0101ksh\u016b",
    "gn:population":0,
    "gn:timezone":"Asia/Tehran",
    "iso:country":"IR",
    "name:fas_x_preferred":[
        "\u0628\u064e\u0646\u062f\u0650 \u0643\u064e\u0644\u0627\u0643\u0634\u0648"
    ],
    "name:fas_x_variant":[
        "\u0628\u064e\u0646\u062f\u0650 \u0643\u064e\u0644\u0627\u0686\u0648",
        "Band-e Kal\u0101ksh\u016b"
    ],
    "name:und_x_variant":[
        "Band-e Kal\u0101ch\u016b",
        "Band-i-Kal\u0101chu"
    ],
    "wof:name":"Band-e Kalakshu",
    "wof:placetype":"locality"
},
  "geometry": {"coordinates":[57.65,26.43333],"type":"Point"}
}