{
  "type": "Feature",
  "properties": {
    "gn:admin1_code":"29",
    "gn:asciiname":"Shahzadeh Mohammad",
    "gn:country_code":"IR",
    "gn:dem":2349,
    "gn:feature_class":"P",
    "gn:feature_code":"PPL",
    "gn:name":"Sh\u0101hz\u0101deh Mo\u1e29ammad",
    "gn:population":0,
    "gn:timezone":"Asia/Tehran",
    "iso:country":"IR",
    "name:fas_x_preferred":[
        "Sh\u0101hz\u0101deh Mo\u1e29ammad"
    ],
    "name:fas_x_variant":[
        "\u0634\u0627\u0647\u0632\u0627\u062f\u0647 \u0645\u062d\u0645\u0651\u062f"
    ],
    "wof:name":"Shahzadeh Mohammad",
    "wof:placetype":"locality"
},
  "geometry": {"coordinates":[56.92613000000001,30.80579],"type":"Point"}
}