{
  "type": "Feature",
  "properties": {
    "gn:admin1_code":"29",
    "gn:asciiname":"Dehu'iyeh",
    "gn:country_code":"IR",
    "gn:dem":2505,
    "gn:feature_class":"P",
    "gn:feature_code":"PPL",
    "gn:name":"Deh\u016b\u2019\u012byeh",
    "gn:population":0,
    "gn:timezone":"Asia/Tehran",
    "iso:country":"IR",
    "name:fas_x_preferred":[
        "\u062f\u0647\u0648\u0626\u06cc\u0647"
    ],
    "name:fas_x_variant":[
        "Deh\u016b",
        "Deh\u016b\u2019\u012byeh"
    ],
    "wof:name":"Dehu'iyeh",
    "wof:placetype":"locality"
},
  "geometry": {"coordinates":[57.11816999999999,30.65642],"type":"Point"}
}