{
  "type": "Feature",
  "properties": {
    "gn:admin1_code":"41.0",
    "gn:asciiname":"Buteh Zirk",
    "gn:country_code":"IR",
    "gn:dem":1827,
    "gn:feature_class":"P",
    "gn:feature_code":"PPL",
    "gn:name":"B\u016bteh Z\u012brk",
    "gn:population":0,
    "gn:timezone":"Asia/Tehran",
    "iso:country":"IR",
    "name:fas_x_preferred":[
        "\u0628\u0648\u062a\u0647 \u0632\u064a\u0631\u06a9"
    ],
    "name:fas_x_variant":[
        "B\u016bteh Z\u012brk",
        "B\u016bteh Z\u012brak",
        "B\u016bteh Z\u012br"
    ],
    "wof:name":"Buteh Zirk",
    "wof:placetype":"locality"
},
  "geometry": {"coordinates":[60.02566,33.15146],"type":"Point"}
}