{
  "type": "Feature",
  "properties": {
    "gn:admin1_code":"40.0",
    "gn:asciiname":"Aluri",
    "gn:country_code":"IR",
    "gn:dem":1726,
    "gn:feature_class":"P",
    "gn:feature_code":"PPL",
    "gn:name":"Aluri",
    "gn:population":0,
    "gn:timezone":"Asia/Tehran",
    "iso:country":"IR",
    "name:fas_x_preferred":[
        "\u0639\u064e\u0644\u0627\u0626\u06cc"
    ],
    "name:fas_x_variant":[
        "\u0639\u064e\u0644\u064e\u0648",
        "\u0627\u064e\u0644\u0648\u0648",
        "\u0639\u064e\u0644\u0627\u0621",
        "\u2018Al\u0101\u2019\u012b"
    ],
    "name:und_x_variant":[
        "Al\u016bv",
        "\u2018Alav",
        "\u2018Al\u0101\u2019",
        "Aluri"
    ],
    "wof:name":"Aluri",
    "wof:placetype":"locality"
},
  "geometry": {"coordinates":[53.65971999999999,32.05444],"type":"Point"}
}