{
  "type": "Feature",
  "properties": {
    "gn:admin1_code":"15",
    "gn:asciiname":"Taraz",
    "gn:country_code":"IR",
    "gn:dem":1116,
    "gn:feature_class":"P",
    "gn:feature_code":"PPL",
    "gn:name":"T\u0101r\u0101z",
    "gn:population":0,
    "gn:timezone":"Asia/Tehran",
    "iso:country":"IR",
    "name:fas_x_preferred":[
        "T\u0101r\u0101z-e Ken\u0101r\u012b"
    ],
    "name:fas_x_variant":[
        "T\u0101r\u0101z",
        "\u062a\u0627\u0631\u0627\u0632",
        "\u062c\u0645\u0639\u0647",
        "\u0645\u062d\u0645\u062f \u062a\u0642\u06cc"
    ],
    "name:und_x_variant":[
        "\u062a\u0627\u0631\u0627\u0632",
        "Jom\u2018eh",
        "T\u0101r\u0101z-e Jom\u2018eh",
        "T\u0101r\u0101z-e Mo\u1e29ammad Taq\u012b",
        "Mo\u1e29ammad Taq\u012b"
    ],
    "wof:name":"Taraz",
    "wof:placetype":"locality"
},
  "geometry": {"coordinates":[49.71093,32.13164],"type":"Point"}
}