{
  "type": "Feature",
  "properties": {
    "gn:admin1_code":"42.0",
    "gn:asciiname":"Qarah Qun Darreh",
    "gn:country_code":"IR",
    "gn:dem":823,
    "gn:feature_class":"P",
    "gn:feature_code":"PPL",
    "gn:name":"Qarah Q\u016bn Darreh",
    "gn:population":0,
    "gn:timezone":"Asia/Tehran",
    "iso:country":"IR",
    "name:fas_x_preferred":[
        "\u0642\u0631\u0647 \u0642\u0648\u0646 \u062f\u0631\u0647"
    ],
    "name:fas_x_variant":[
        "Qarah Q\u016bn Darreh"
    ],
    "wof:name":"Qarah Qun Darreh",
    "wof:placetype":"locality"
},
  "geometry": {"coordinates":[60.0765,36.7464],"type":"Point"}
}