{
  "type": "Feature",
  "properties": {
    "gn:admin1_code":"15",
    "gn:asciiname":"Farahani",
    "gn:country_code":"IR",
    "gn:dem":15,
    "gn:feature_class":"P",
    "gn:feature_code":"PPL",
    "gn:name":"Farah\u0101n\u012b",
    "gn:population":0,
    "gn:timezone":"Asia/Tehran",
    "iso:country":"IR",
    "name:fas_x_preferred":[
        "Farah\u0101n\u012b"
    ],
    "name:fas_x_variant":[
        "\u0641\u0631\u0647\u0627\u0646\u06cc \u0635\u0627\u062d\u0628",
        "Fara\u1e29\u0101n\u012b-ye \u015e\u0101\u1e29eb",
        "\u0641\u0631\u0647\u0627\u0646\u06cc"
    ],
    "name:und_x_variant":[
        "Fara\u1e29\u0101n\u012b-ye \u015e\u0101\u1e29eb",
        "\u0641\u0631\u0647\u0627\u0646\u06cc \u0635\u0627\u062d\u0628"
    ],
    "wof:name":"Farahani",
    "wof:placetype":"locality"
},
  "geometry": {"coordinates":[48.86916,30.76081],"type":"Point"}
}