{
  "type": "Feature",
  "properties": {
    "gn:admin1_code":"41",
    "gn:asciiname":"Barayeman",
    "gn:country_code":"IR",
    "gn:dem":1733,
    "gn:feature_class":"P",
    "gn:feature_code":"PPL",
    "gn:name":"Bar\u0101yem\u0101n",
    "gn:population":0,
    "gn:timezone":"Asia/Tehran",
    "iso:country":"IR",
    "name:fas_x_preferred":[
        "Bar\u0101yem\u0101n"
    ],
    "name:fas_x_variant":[
        "\u0628\u0631\u0627\u06cc\u0645\u0627\u0646"
    ],
    "name:und_x_variant":[
        "\u0628\u0631\u0627\u06cc\u0645\u0627\u0646"
    ],
    "wof:name":"Barayeman",
    "wof:placetype":"locality"
},
  "geometry": {"coordinates":[58.7967,32.99745],"type":"Point"}
}