{
  "type": "Feature",
  "properties": {
    "gn:admin1_code":"5",
    "gn:asciiname":"Darreh Chah",
    "gn:country_code":"IR",
    "gn:dem":1335,
    "gn:feature_class":"P",
    "gn:feature_code":"PPL",
    "gn:name":"Darreh Ch\u0101h",
    "gn:population":0,
    "gn:timezone":"Asia/Tehran",
    "iso:country":"IR",
    "name:fas_x_preferred":[
        "\u062f\u064e\u0631\u0650\u0651\u0647 \u0686\u0627\u0647"
    ],
    "name:fas_x_variant":[
        "Darreh Ch\u0101h"
    ],
    "wof:name":"Darreh Chah",
    "wof:placetype":"locality"
},
  "geometry": {"coordinates":[51.12694000000001,30.46306],"type":"Point"}
}