{
  "type": "Feature",
  "properties": {
    "gn:admin1_code":"9",
    "gn:asciiname":"Kusaj Khalil",
    "gn:country_code":"IR",
    "gn:dem":1666,
    "gn:feature_class":"P",
    "gn:feature_code":"PPL",
    "gn:name":"K\u016bsaj Khal\u012bl",
    "gn:population":0,
    "gn:timezone":"Asia/Tehran",
    "iso:country":"IR",
    "name:fas_x_preferred":[
        "\u0643\u0648\u0633\u064e\u062c \u062e\u064e\u0644\u064a\u0644"
    ],
    "wof:name":"Kusaj Khalil",
    "wof:placetype":"locality"
},
  "geometry": {"coordinates":[48.60667,34.39139],"type":"Point"}
}