{
  "type": "Feature",
  "properties": {
    "gn:admin1_code":"35.0",
    "gn:asciiname":"Mi Kola",
    "gn:country_code":"IR",
    "gn:dem":70,
    "gn:feature_class":"P",
    "gn:feature_code":"PPL",
    "gn:name":"M\u012b Kol\u0101",
    "gn:population":0,
    "gn:timezone":"Asia/Tehran",
    "iso:country":"IR",
    "name:ceb_x_preferred":[
        "M\u012b Kol\u0101"
    ],
    "name:fas_x_preferred":[
        "M\u012b Kol\u0101"
    ],
    "name:fas_x_variant":[
        "\u0645\u06cc \u06a9\u0644\u0627",
        "\u0645\u06cc\u200c\u06a9\u0644\u0627"
    ],
    "name:swe_x_preferred":[
        "M\u012b Kol\u0101"
    ],
    "wof:name":"Mi Kola",
    "wof:placetype":"locality"
},
  "geometry": {"coordinates":[52.75821,36.40846],"type":"Point"}
}