{
  "type": "Feature",
  "properties": {
    "gn:admin1_code":"33",
    "gn:asciiname":"Javanan-e Goruh",
    "gn:country_code":"IR",
    "gn:dem":1593,
    "gn:feature_class":"P",
    "gn:feature_code":"PPL",
    "gn:name":"Jav\u0101n\u0101n-e Gor\u016bh",
    "gn:population":0,
    "gn:timezone":"Asia/Tehran",
    "iso:country":"IR",
    "name:azb_x_preferred":[
        "\u062c\u0648\u0627\u0646\u0627\u0646\u200c\u06af\u0631\u0648\u0647"
    ],
    "name:fas_x_preferred":[
        "\u062c\u0648\u0627\u0646\u0627\u0646 \u06af\u0631\u0648\u0647"
    ],
    "name:fas_x_variant":[
        "Jav\u0101n\u0101n-e Gor\u016bh",
        "\u062c\u0648\u0627\u0646\u0627\u0646\u200c\u06af\u0631\u0648\u0647"
    ],
    "name:msa_x_preferred":[
        "Javanan-e Goruh"
    ],
    "name:und_x_variant":[
        "Geviana Girvia",
        "Jav\u0101n\u0101n Gor\u016bh",
        "Gavaneh G\u012brvey\u0101",
        "Javanan Gorooh",
        "Gevyana-Gireya"
    ],
    "name:urd_x_preferred":[
        "\u062c\u0648\u0627\u0646\u0627\u0646 \u06af\u0631\u0648\u06c1"
    ],
    "wof:name":"Javanan-e Goruh",
    "wof:placetype":"locality"
},
  "geometry": {"coordinates":[46.23568,38.56569],"type":"Point"}
}