{
  "type": "Feature",
  "properties": {
    "gn:admin1_code":"34",
    "gn:asciiname":"Shanbeh Dezh",
    "gn:country_code":"IR",
    "gn:dem":1290,
    "gn:feature_class":"P",
    "gn:feature_code":"PPL",
    "gn:name":"Shanbeh Dezh",
    "gn:population":0,
    "gn:timezone":"Asia/Tehran",
    "iso:country":"IR",
    "name:fas_x_preferred":[
        "\u0634\u064e\u0646\u0628\u0650\u0647 \u062f\u0650\u0698"
    ],
    "wof:name":"Shanbeh Dezh",
    "wof:placetype":"locality"
},
  "geometry": {"coordinates":[50.94833,35.82167000000001],"type":"Point"}
}