{
  "type": "Feature",
  "properties": {
    "gn:admin1_code":"35.0",
    "gn:asciiname":"Qal`eh Gardan",
    "gn:country_code":"IR",
    "gn:dem":1025,
    "gn:feature_class":"P",
    "gn:feature_code":"PPL",
    "gn:name":"Qal\u2018eh Gardan",
    "gn:population":0,
    "gn:timezone":"Asia/Tehran",
    "iso:country":"IR",
    "name:fas_x_preferred":[
        "\u0642\u064e\u0644\u0639\u0650\u0647 \u06af\u064e\u0631\u062f\u064e\u0646"
    ],
    "name:fas_x_variant":[
        "Qal\u2018eh Gardan"
    ],
    "wof:name":"Qal`eh Gardan",
    "wof:placetype":"locality"
},
  "geometry": {"coordinates":[51.25,36.31667],"type":"Point"}
}