{
  "type": "Feature",
  "properties": {
    "gn:admin1_code":"7",
    "gn:asciiname":"Hasanabad-e Marmeh",
    "gn:country_code":"IR",
    "gn:dem":849,
    "gn:feature_class":"P",
    "gn:feature_code":"PPL",
    "gn:name":"\u1e28asan\u0101b\u0101d-e M\u0101rmeh",
    "gn:population":0,
    "gn:timezone":"Asia/Tehran",
    "iso:country":"IR",
    "name:fas_x_preferred":[
        "\u062d\u0633\u0646 \u0622\u0628\u0627\u062f"
    ],
    "name:fas_x_variant":[
        "\u1e28asan\u0101b\u0101d-e Margem\u0101r\u012b",
        "\u1e28asan\u0101b\u0101d",
        "\u062d\u0633\u0646 \u0622\u0628\u0627\u062f \u0645\u0627\u0631\u0645\u0647",
        "\u062d\u0633\u0646 \u0622\u0628\u0627\u062f \u0645\u0631\u06af \u0645\u0627\u0631\u06cc"
    ],
    "name:und_x_variant":[
        "\u1e28asan\u0101b\u0101d-e M\u0101rmeh",
        "\u1e28asan\u0101b\u0101d-e Marg M\u0101r\u012b"
    ],
    "wof:name":"Hasanabad-e Marmeh",
    "wof:placetype":"locality"
},
  "geometry": {"coordinates":[53.9126,28.07226],"type":"Point"}
}