{
  "type": "Feature",
  "properties": {
    "gn:admin1_code":"16.0",
    "gn:asciiname":"Bahram",
    "gn:country_code":"IR",
    "gn:dem":1632,
    "gn:feature_class":"P",
    "gn:feature_code":"PPL",
    "gn:name":"Bahr\u0101m",
    "gn:population":0,
    "gn:timezone":"Asia/Tehran",
    "iso:country":"IR",
    "name:fas_x_preferred":[
        "\u0628\u0647\u0631\u0627\u0645"
    ],
    "name:fas_x_variant":[
        "Bahr\u0101m"
    ],
    "wof:name":"Bahram",
    "wof:placetype":"locality"
},
  "geometry": {"coordinates":[46.3649,36.083],"type":"Point"}
}