{
  "type": "Feature",
  "properties": {
    "gn:admin1_code":"32",
    "gn:asciiname":"Tazeh Kand",
    "gn:country_code":"IR",
    "gn:dem":1189,
    "gn:feature_class":"P",
    "gn:feature_code":"PPL",
    "gn:name":"T\u0101zeh Kand",
    "gn:population":0,
    "gn:timezone":"Asia/Tehran",
    "iso:country":"IR",
    "name:fas_x_preferred":[
        "\u062a\u0627\u0632\u0647 \u0643\u0646\u062f \u062d\u0627\u062c\u06cc \u062e\u0627\u0646"
    ],
    "name:fas_x_variant":[
        "T\u0101zeh Kand-e \u1e28\u0101jj\u012bkh\u0101n",
        "\u062a\u0627\u0632\u0647 \u06a9\u0646\u062f"
    ],
    "name:und_x_variant":[
        "T\u0101zeh Kand"
    ],
    "wof:name":"Tazeh Kand",
    "wof:placetype":"locality"
},
  "geometry": {"coordinates":[47.43623,38.3744],"type":"Point"}
}