{
  "type": "Feature",
  "properties": {
    "gn:admin1_code":"37",
    "gn:asciiname":"`Abbasabad",
    "gn:country_code":"IR",
    "gn:dem":240,
    "gn:feature_class":"P",
    "gn:feature_code":"PPL",
    "gn:name":"\u2018Abb\u0101s\u0101b\u0101d",
    "gn:population":0,
    "gn:timezone":"Asia/Tehran",
    "iso:country":"IR",
    "name:ara_x_preferred":[
        "\u0639\u0628\u0627\u0633\u200c\u0622\u0628\u0627\u062f"
    ],
    "name:fas_x_preferred":[
        "\u2018Abb\u0101s\u0101b\u0101d-e Kat\u016bl"
    ],
    "name:fas_x_variant":[
        "\u2018Abb\u0101s\u0101b\u0101d",
        "\u0639\u0628\u0627\u0633 \u0622\u0628\u0627\u062f \u06a9\u062a\u0648\u0644",
        "\u0639\u0628\u0627\u0633 \u0622\u0628\u0627\u062f",
        "\u0639\u0628\u0627\u0633\u200c\u0622\u0628\u0627\u062f"
    ],
    "name:msa_x_preferred":[
        "Abbasabad"
    ],
    "wof:name":"`Abbasabad",
    "wof:placetype":"locality"
},
  "geometry": {"coordinates":[54.7897,36.88471],"type":"Point"}
}