{
  "type": "Feature",
  "properties": {
    "gn:admin1_code":"15",
    "gn:asciiname":"Naseri",
    "gn:country_code":"IR",
    "gn:dem":5,
    "gn:feature_class":"P",
    "gn:feature_code":"PPL",
    "gn:name":"N\u0101\u015fer\u012b",
    "gn:population":0,
    "gn:timezone":"Asia/Tehran",
    "iso:country":"IR",
    "name:fas_x_preferred":[
        "N\u0101\u015fer\u012b"
    ],
    "name:fas_x_variant":[
        "\u0646\u0627\u0635\u0631\u06cc"
    ],
    "wof:name":"Naseri",
    "wof:placetype":"locality"
},
  "geometry": {"coordinates":[48.62071,30.65018],"type":"Point"}
}