{
  "type": "Feature",
  "properties": {
    "gn:admin1_code":"16",
    "gn:asciiname":"Daram Rud",
    "gn:country_code":"IR",
    "gn:dem":1577,
    "gn:feature_class":"P",
    "gn:feature_code":"PPL",
    "gn:name":"D\u0101ram R\u016bd",
    "gn:population":0,
    "gn:timezone":"Asia/Tehran",
    "iso:country":"IR",
    "name:fas_x_preferred":[
        "\u062f\u0627\u0631\u064e\u0645\u0631\u0648\u062f"
    ],
    "name:fas_x_variant":[
        "\u062f\u0627\u0631\u0645 \u0631\u0648\u062f",
        "D\u0101ramr\u016bd",
        "D\u0101ram R\u016bd"
    ],
    "wof:name":"Daram Rud",
    "wof:placetype":"locality"
},
  "geometry": {"coordinates":[47.1349,34.9486],"type":"Point"}
}