{
  "type": "Feature",
  "properties": {
    "gn:admin1_code":"28",
    "gn:asciiname":"Varbad-e Pa'in",
    "gn:country_code":"IR",
    "gn:dem":2164,
    "gn:feature_class":"P",
    "gn:feature_code":"PPL",
    "gn:name":"Varb\u0101d-e P\u0101\u2019\u012bn",
    "gn:population":0,
    "gn:timezone":"Asia/Tehran",
    "iso:country":"IR",
    "name:fas_x_preferred":[
        "Varb\u0101d-e Sofl\u00e1"
    ],
    "name:fas_x_variant":[
        "Varb\u0101d-e P\u0101\u2019\u012bn",
        "\u0648\u0631\u0628\u0627\u062f \u067e\u0627\u0626\u06cc\u0646"
    ],
    "name:und_x_variant":[
        "Varb\u0101d",
        "\u0648\u0631\u0628\u0627\u062f \u067e\u0627\u0626\u06cc\u0646"
    ],
    "wof:name":"Varbad-e Pa'in",
    "wof:placetype":"locality"
},
  "geometry": {"coordinates":[50.41286,32.63323],"type":"Point"}
}