{
  "type": "Feature",
  "properties": {
    "gn:admin1_code":"15",
    "gn:asciiname":"Jahalgard",
    "gn:country_code":"IR",
    "gn:dem":763,
    "gn:feature_class":"P",
    "gn:feature_code":"PPL",
    "gn:name":"Jah\u0101lgard",
    "gn:population":0,
    "gn:timezone":"Asia/Tehran",
    "iso:country":"IR",
    "name:fas_x_preferred":[
        "Jah\u0101lgard"
    ],
    "wof:name":"Jahalgard",
    "wof:placetype":"locality"
},
  "geometry": {"coordinates":[50.06472,31.86472],"type":"Point"}
}