{
  "type": "Feature",
  "properties": {
    "gn:admin1_code":"16",
    "gn:asciiname":"Gol Tappeh",
    "gn:country_code":"IR",
    "gn:dem":1797,
    "gn:feature_class":"P",
    "gn:feature_code":"PPL",
    "gn:name":"Gol Tappeh",
    "gn:population":0,
    "gn:timezone":"Asia/Tehran",
    "iso:country":"IR",
    "name:ara_x_preferred":[
        "\u063a\u0644 \u062a\u0628\u0629 \u0633\u0641\u0644\u064a"
    ],
    "name:ceb_x_preferred":[
        "Gol Tappeh"
    ],
    "name:ckb_x_preferred":[
        "\u06a9\u0648\u06b5\u062a\u06d5\u067e\u06d5\u06cc \u062e\u0648\u0627\u0631\u06c6"
    ],
    "name:fas_x_preferred":[
        "\u06af\u064f\u0644 \u062a\u064e\u067e\u0650\u0651\u06c0 \u0633\u064f\u0641\u0644\u064e\u0649"
    ],
    "name:fas_x_variant":[
        "\u06af\u0644 \u062a\u067e\u0647",
        "Gol Tappeh-ye Sofl\u00e1",
        "\u06af\u0644 \u062a\u067e\u0647 \u0633\u0641\u0644\u06cc"
    ],
    "wof:name":"Gol Tappeh",
    "wof:placetype":"locality"
},
  "geometry": {"coordinates":[47.1231,36.0301],"type":"Point"}
}