{
  "type": "Feature",
  "properties": {
    "gn:admin1_code":"35",
    "gn:asciiname":"Now Sar",
    "gn:country_code":"IR",
    "gn:dem":2259,
    "gn:feature_class":"P",
    "gn:feature_code":"PPL",
    "gn:name":"Now Sar",
    "gn:population":0,
    "gn:timezone":"Asia/Tehran",
    "iso:country":"IR",
    "name:fas_x_preferred":[
        "\u0646\u0648 \u0633\u0631"
    ],
    "wof:name":"Now Sar",
    "wof:placetype":"locality"
},
  "geometry": {"coordinates":[52.97863,35.87039],"type":"Point"}
}