{
  "type": "Feature",
  "properties": {
    "gn:admin1_code":"35",
    "gn:asciiname":"Qabadileh",
    "gn:country_code":"IR",
    "gn:dem":62,
    "gn:feature_class":"P",
    "gn:feature_code":"PPL",
    "gn:name":"Qab\u0101d\u012bleh",
    "gn:population":0,
    "gn:timezone":"Asia/Tehran",
    "iso:country":"IR",
    "name:fas_x_preferred":[
        "\u0642\u064e\u0628\u0627\u062f\u064a\u0644\u0650\u0647"
    ],
    "name:und_x_variant":[
        "Qab\u0101d\u012bleh"
    ],
    "wof:name":"Qabadileh",
    "wof:placetype":"locality"
},
  "geometry": {"coordinates":[52.86666999999999,36.45],"type":"Point"}
}