{
  "type": "Feature",
  "properties": {
    "gn:admin1_code":"28",
    "gn:asciiname":"Sahamiyeh",
    "gn:country_code":"IR",
    "gn:dem":982,
    "gn:feature_class":"P",
    "gn:feature_code":"PPL",
    "gn:name":"Sah\u0101m\u012byeh",
    "gn:population":0,
    "gn:timezone":"Asia/Tehran",
    "iso:country":"IR",
    "name:fas_x_preferred":[
        "\u0633\u0647\u0627\u0645\u06cc\u0647"
    ],
    "name:fas_x_variant":[
        "Sah\u0101m\u012byeh"
    ],
    "name:und_x_variant":[
        "Nahum\u012byeh",
        "Sar\u0101y",
        "Sarai"
    ],
    "wof:name":"Sahamiyeh",
    "wof:placetype":"locality"
},
  "geometry": {"coordinates":[52.2814,33.4922],"type":"Point"}
}