{
  "type": "Feature",
  "properties": {
    "gn:admin1_code":"26.0",
    "gn:asciiname":"Hakimeh",
    "gn:country_code":"IR",
    "gn:dem":1465,
    "gn:feature_class":"P",
    "gn:feature_code":"PPL",
    "gn:name":"\u1e28ak\u012bmeh",
    "gn:population":0,
    "gn:timezone":"Asia/Tehran",
    "iso:country":"IR",
    "name:fas_x_preferred":[
        "\u062d\u064e\u0643\u064a\u0645\u0650\u0647"
    ],
    "name:fas_x_variant":[
        "\u1e28ak\u012bmeh"
    ],
    "wof:name":"Hakimeh",
    "wof:placetype":"locality"
},
  "geometry": {"coordinates":[51.57694,35.73694000000001],"type":"Point"}
}