{
  "type": "Feature",
  "properties": {
    "gn:admin1_code":"8.0",
    "gn:asciiname":"Gusfand Gacheh",
    "gn:country_code":"IR",
    "gn:dem":123,
    "gn:feature_class":"P",
    "gn:feature_code":"PPL",
    "gn:name":"G\u016bsfand G\u0101cheh",
    "gn:population":0,
    "gn:timezone":"Asia/Tehran",
    "iso:country":"IR",
    "name:fas_x_preferred":[
        "\u06af\u0648\u0633\u0641\u0646\u062f \u06af\u0627\u0686\u0647"
    ],
    "name:und_x_variant":[
        "G\u016bsfand G\u0101cheh"
    ],
    "wof:name":"Gusfand Gacheh",
    "wof:placetype":"locality"
},
  "geometry": {"coordinates":[49.79261,37.09761],"type":"Point"}
}