{
  "type": "Feature",
  "properties": {
    "gn:admin1_code":"28.0",
    "gn:asciiname":"Sirvah",
    "gn:country_code":"IR",
    "gn:dem":2345,
    "gn:feature_class":"P",
    "gn:feature_code":"PPL",
    "gn:name":"S\u012brvah",
    "gn:population":0,
    "gn:timezone":"Asia/Tehran",
    "iso:country":"IR",
    "name:fas_x_preferred":[
        "\u0633\u06cc\u0631\u0648\u0647"
    ],
    "name:und_x_variant":[
        "S\u012brvah"
    ],
    "wof:name":"Sirvah",
    "wof:placetype":"locality"
},
  "geometry": {"coordinates":[51.33647,31.41071],"type":"Point"}
}