{
  "type": "Feature",
  "properties": {
    "gn:admin1_code":"13",
    "gn:asciiname":"Shahr-e Fashah",
    "gn:cc2":"IR",
    "gn:country_code":"IR",
    "gn:dem":640,
    "gn:feature_class":"P",
    "gn:feature_code":"PPL",
    "gn:name":"Shahr-e Fash\u0101h",
    "gn:population":0,
    "gn:timezone":"Asia/Tehran",
    "iso:country":"IR",
    "name:fas_x_preferred":[
        "Shahr-e Fash\u0101h"
    ],
    "name:fas_x_variant":[
        "\u0634\u0631\u0641\u200c\u0634\u0627\u0647"
    ],
    "name:und_x_variant":[
        "Sharafsh\u0101h"
    ],
    "wof:name":"Shahr-e Fashah",
    "wof:placetype":"locality"
},
  "geometry": {"coordinates":[45.83194,33.90555999999999],"type":"Point"}
}