{
  "type": "Feature",
  "properties": {
    "gn:admin1_code":"1.0",
    "gn:asciiname":"Kuzehrash",
    "gn:country_code":"IR",
    "gn:dem":2343,
    "gn:feature_class":"P",
    "gn:feature_code":"PPL",
    "gn:name":"K\u016bzehrash",
    "gn:population":0,
    "gn:timezone":"Asia/Tehran",
    "iso:country":"IR",
    "name:fas_x_preferred":[
        "K\u016bzehrash"
    ],
    "name:fas_x_variant":[
        "\u06a9\u0648\u0632\u0647 \u0631\u0634",
        "K\u016bzeh Rash"
    ],
    "wof:name":"Kuzehrash",
    "wof:placetype":"locality"
},
  "geometry": {"coordinates":[44.4665,38.1609],"type":"Point"}
}