{
  "type": "Feature",
  "properties": {
    "gn:admin1_code":"0.0",
    "gn:asciiname":"Kahnak",
    "gn:cc2":"IR",
    "gn:country_code":"IR",
    "gn:dem":158,
    "gn:feature_class":"P",
    "gn:feature_code":"PPL",
    "gn:name":"Kahnak",
    "gn:population":0,
    "gn:timezone":"Asia/Tehran",
    "iso:country":"IR",
    "name:fas_x_preferred":[
        "\u0643\u064e\u0647\u0646\u064e\u0643"
    ],
    "name:fas_x_variant":[
        "\u062e\u0627\u0646"
    ],
    "name:und_x_variant":[
        "Kh\u0101n",
        "Kahnak"
    ],
    "wof:name":"Kahnak",
    "wof:placetype":"locality"
},
  "geometry": {"coordinates":[60.91667,25.95],"type":"Point"}
}