{
  "type": "Feature",
  "properties": {
    "gn:admin1_code":"4.0",
    "gn:asciiname":"Dapkor",
    "gn:country_code":"IR",
    "gn:dem":750,
    "gn:feature_class":"P",
    "gn:feature_code":"PPL",
    "gn:name":"Dapkor",
    "gn:population":0,
    "gn:timezone":"Asia/Tehran",
    "iso:country":"IR",
    "name:fas_x_preferred":[
        "\u062f\u067e\u06a9\u0631"
    ],
    "name:und_x_variant":[
        "Dapas K\u016br",
        "Dap Kaur",
        "Dabk\u016br",
        "D\u0101s K\u016brt",
        "Dapkor"
    ],
    "wof:name":"Dapkor",
    "wof:placetype":"locality"
},
  "geometry": {"coordinates":[61.18876,26.49573],"type":"Point"}
}