{
  "type": "Feature",
  "properties": {
    "gn:admin1_code":"43",
    "gn:asciiname":"Kalateh-ye Ma`sumi",
    "gn:country_code":"IR",
    "gn:dem":1056,
    "gn:feature_class":"P",
    "gn:feature_code":"PPL",
    "gn:name":"Kal\u0101teh-ye Ma\u2018\u015f\u016bm\u012b",
    "gn:population":0,
    "gn:timezone":"Asia/Tehran",
    "iso:country":"IR",
    "name:fas_x_preferred":[
        "Kal\u0101teh-ye Ma\u2018\u015f\u016bm\u012b"
    ],
    "name:fas_x_variant":[
        "Kal\u0101teh-ye B\u0101qer Kh\u0101n Shom\u0101reh Seh",
        "\u06a9\u0644\u0627\u062a\u0647 \u0645\u0639\u0635\u0648\u0645\u06cc"
    ],
    "name:und_x_variant":[
        "\u06a9\u0644\u0627\u062a\u0647 \u0645\u0639\u0635\u0648\u0645\u06cc"
    ],
    "wof:name":"Kalateh-ye Ma`sumi",
    "wof:placetype":"locality"
},
  "geometry": {"coordinates":[57.36107,37.48747],"type":"Point"}
}