{
  "type": "Feature",
  "properties": {
    "gn:admin1_code":"7",
    "gn:asciiname":"Darvish-e Sa`adat",
    "gn:country_code":"IR",
    "gn:dem":1600,
    "gn:feature_class":"P",
    "gn:feature_code":"PPL",
    "gn:name":"Darv\u012bsh-e Sa\u2018\u0101dat",
    "gn:population":0,
    "gn:timezone":"Asia/Tehran",
    "iso:country":"IR",
    "name:fas_x_preferred":[
        "\u0686\u0627\u0647 \u062f\u0631\u0648\u06cc\u0634 \u0633\u0639\u0627\u062f\u062a"
    ],
    "name:fas_x_variant":[
        "Ch\u0101h-e Darv\u012bsh-e Se\u2018\u0101dat",
        "\u062f\u0631\u0648\u06cc\u0634 \u0633\u0639\u0627\u062f\u062a"
    ],
    "name:und_x_variant":[
        "Darv\u012bsh-e Sa\u2018\u0101dat"
    ],
    "wof:name":"Darvish-e Sa`adat",
    "wof:placetype":"locality"
},
  "geometry": {"coordinates":[55.0612,28.811],"type":"Point"}
}