{
  "type": "Feature",
  "properties": {
    "gn:admin1_code":"41",
    "gn:asciiname":"Keydasht",
    "gn:country_code":"IR",
    "gn:dem":1666,
    "gn:feature_class":"P",
    "gn:feature_code":"PPL",
    "gn:name":"Keydasht",
    "gn:population":0,
    "gn:timezone":"Asia/Tehran",
    "iso:country":"IR",
    "name:fas_x_preferred":[
        "\u06a9\u062f\u0627\u0634"
    ],
    "name:fas_x_variant":[
        "Kad\u0101sh",
        "\u06a9\u06cc\u062f\u0627\u0634\u062a"
    ],
    "name:und_x_variant":[
        "K\u012bdosht",
        "Kaidasht",
        "Keydasht"
    ],
    "wof:name":"Keydasht",
    "wof:placetype":"locality"
},
  "geometry": {"coordinates":[59.7111,32.3039],"type":"Point"}
}