{
  "type": "Feature",
  "properties": {
    "gn:admin1_code":"28",
    "gn:asciiname":"Eskandari",
    "gn:country_code":"IR",
    "gn:dem":2151,
    "gn:feature_class":"P",
    "gn:feature_code":"PPL",
    "gn:name":"Eskandar\u012b",
    "gn:population":0,
    "gn:timezone":"Asia/Tehran",
    "iso:country":"IR",
    "name:fas_x_preferred":[
        "Eskandar\u012b"
    ],
    "name:fas_x_variant":[
        "\u0627\u0633\u06a9\u0646\u062f\u0631\u06cc"
    ],
    "name:und_x_variant":[
        "\u012askandar\u012b",
        "\u0627\u0633\u06a9\u0646\u062f\u0631\u06cc"
    ],
    "wof:name":"Eskandari",
    "wof:placetype":"locality"
},
  "geometry": {"coordinates":[50.43732,32.82745],"type":"Point"}
}