{
  "type": "Feature",
  "properties": {
    "gn:admin1_code":"4.0",
    "gn:asciiname":"Deh-e Jalali",
    "gn:country_code":"IR",
    "gn:dem":490,
    "gn:feature_class":"P",
    "gn:feature_code":"PPL",
    "gn:name":"Deh-e Jal\u0101l\u012b",
    "gn:population":0,
    "gn:timezone":"Asia/Tehran",
    "iso:country":"IR",
    "name:fas_x_preferred":[
        "\u062f\u0647 \u062c\u0644\u0627\u0644\u06cc"
    ],
    "name:fas_x_variant":[
        "Jal\u0101l\u012b",
        "Deh-e Jal\u0101l\u012b",
        "\u062c\u0644\u0627\u0644\u06cc"
    ],
    "wof:name":"Deh-e Jalali",
    "wof:placetype":"locality"
},
  "geometry": {"coordinates":[61.6797,30.9159],"type":"Point"}
}