{
  "type": "Feature",
  "properties": {
    "gn:admin1_code":"29",
    "gn:asciiname":"Jowkar-e `Olya",
    "gn:country_code":"IR",
    "gn:dem":2543,
    "gn:feature_class":"P",
    "gn:feature_code":"PPL",
    "gn:name":"Jowk\u0101r-e \u2018Oly\u0101",
    "gn:population":0,
    "gn:timezone":"Asia/Tehran",
    "iso:country":"IR",
    "name:fas_x_preferred":[
        "Jowk\u0101r-e \u2018Oly\u0101"
    ],
    "name:fas_x_variant":[
        "Jowk\u0101r-e B\u0101l\u0101",
        "\u062c\u0648\u06a9\u0627\u0631 \u0639\u0644\u06cc\u0627"
    ],
    "name:und_x_variant":[
        "Jowk\u0101r",
        "B\u0101gh-e B\u0101qer\u0101b\u0101d"
    ],
    "wof:name":"Jowkar-e `Olya",
    "wof:placetype":"locality"
},
  "geometry": {"coordinates":[56.4016,29.4313],"type":"Point"}
}