{
  "type": "Feature",
  "properties": {
    "gn:admin1_code":"41",
    "gn:asciiname":"Bozquch-e `Olya",
    "gn:country_code":"IR",
    "gn:dem":1944,
    "gn:feature_class":"P",
    "gn:feature_code":"PPL",
    "gn:name":"Bozq\u016bch-e \u2018Oly\u0101",
    "gn:population":0,
    "gn:timezone":"Asia/Tehran",
    "iso:country":"IR",
    "name:fas_x_preferred":[
        "Bozq\u016bch-e \u2018Oly\u0101"
    ],
    "name:fas_x_variant":[
        "\u0628\u0632\u0642\u0648\u0686 \u0628\u0627\u0644\u0627",
        "Buzq\u016bch",
        "Bozq\u016bch B\u0101l\u0101",
        "Boz Q\u016bch",
        "\u0628\u0632\u0642\u0648\u0686 \u0639\u0644\u06cc\u0627"
    ],
    "name:und_x_variant":[
        "Bozq\u016bch B\u0101l\u0101",
        "Boz Q\u016bch",
        "Buzq\u016bch",
        "Bozq\u016bch-e B\u0101l\u0101"
    ],
    "wof:name":"Bozquch-e `Olya",
    "wof:placetype":"locality"
},
  "geometry": {"coordinates":[59.4419,33.01152],"type":"Point"}
}