{
  "type": "Feature",
  "properties": {
    "gn:admin1_code":"10",
    "gn:asciiname":"Turabeh Marate`",
    "gn:country_code":"IR",
    "gn:dem":884,
    "gn:feature_class":"P",
    "gn:feature_code":"PPL",
    "gn:name":"T\u016br\u0101beh Mar\u0101te\u2018",
    "gn:population":0,
    "gn:timezone":"Asia/Tehran",
    "iso:country":"IR",
    "name:fas_x_preferred":[
        "\u0634\u0648\u0631\u0627\u0628\u0647"
    ],
    "name:fas_x_variant":[
        "Sh\u016br\u0101beh",
        "\u062a\u0648\u0631\u0627\u0628\u0647 \u0645\u0631\u0627\u062a\u0639"
    ],
    "name:und_x_variant":[
        "T\u016br\u0101beh Mar\u0101te\u2018"
    ],
    "wof:name":"Turabeh Marate`",
    "wof:placetype":"locality"
},
  "geometry": {"coordinates":[46.76819,33.68286],"type":"Point"}
}