{
  "type": "Feature",
  "properties": {
    "gn:admin1_code":"28.0",
    "gn:asciiname":"Ashnan",
    "gn:country_code":"IR",
    "gn:dem":2159,
    "gn:feature_class":"P",
    "gn:feature_code":"PPL",
    "gn:name":"\u0100shn\u0101n",
    "gn:population":0,
    "gn:timezone":"Asia/Tehran",
    "iso:country":"IR",
    "name:fas_x_preferred":[
        "\u0622\u0634\u0646\u0627\u0646"
    ],
    "name:fas_x_variant":[
        "\u0100shn\u0101n"
    ],
    "name:und_x_variant":[
        "Ashn\u0101n"
    ],
    "wof:name":"Ashnan",
    "wof:placetype":"locality"
},
  "geometry": {"coordinates":[52.6585,32.9149],"type":"Point"}
}