{
  "type": "Feature",
  "properties": {
    "gn:admin1_code":"7",
    "gn:asciiname":"Jolgeh-e Namdan",
    "gn:country_code":"IR",
    "gn:dem":2318,
    "gn:feature_class":"P",
    "gn:feature_code":"PPL",
    "gn:name":"Jolgeh-e Namd\u0101n",
    "gn:population":0,
    "gn:timezone":"Asia/Tehran",
    "iso:country":"IR",
    "name:fas_x_preferred":[
        "Jolgeh-e Namd\u0101n"
    ],
    "wof:name":"Jolgeh-e Namdan",
    "wof:placetype":"locality"
},
  "geometry": {"coordinates":[52.49611,30.71417000000001],"type":"Point"}
}