{
  "type": "Feature",
  "properties": {
    "gn:admin1_code":"0",
    "gn:asciiname":"Vashnaveh",
    "gn:country_code":"IR",
    "gn:dem":2000,
    "gn:feature_class":"P",
    "gn:feature_code":"PPL",
    "gn:name":"Vashnaveh",
    "gn:population":0,
    "gn:timezone":"Asia/Tehran",
    "iso:country":"IR",
    "name:fas_x_preferred":[
        "\u0648\u0634\u0646\u0648\u0647"
    ],
    "wof:name":"Vashnaveh",
    "wof:placetype":"locality"
},
  "geometry": {"coordinates":[50.9961,34.2505],"type":"Point"}
}