{
  "type": "Feature",
  "properties": {
    "gn:admin1_code":"35.0",
    "gn:asciiname":"Pol-e Kalantari",
    "gn:country_code":"IR",
    "gn:dem":1331,
    "gn:feature_class":"P",
    "gn:feature_code":"PPL",
    "gn:name":"Pol-e Kal\u0101ntar\u012b",
    "gn:population":0,
    "gn:timezone":"Asia/Tehran",
    "iso:country":"IR",
    "name:fas_x_preferred":[
        "\u067e\u064f\u0644\u0650 \u0643\u064e\u0644\u0627\u0646\u062a\u064e\u0631\u06cc"
    ],
    "name:fas_x_variant":[
        "Pol-e Kal\u0101ntar\u012b"
    ],
    "wof:name":"Pol-e Kalantari",
    "wof:placetype":"locality"
},
  "geometry": {"coordinates":[53.03333000000001,36.01667],"type":"Point"}
}