{
  "type": "Feature",
  "properties": {
    "gn:admin1_code":"34",
    "gn:asciiname":"Pandar Jan",
    "gn:country_code":"IR",
    "gn:dem":1896,
    "gn:feature_class":"P",
    "gn:feature_code":"PPL",
    "gn:name":"Pandar J\u0101n",
    "gn:population":0,
    "gn:timezone":"Asia/Tehran",
    "iso:country":"IR",
    "name:fas_x_preferred":[
        "\u067e\u0650\u0646\u062f\u0650\u0631\u062c\u0627\u0646"
    ],
    "name:fas_x_variant":[
        "Pandar J\u0101n",
        "\u067e\u0646\u062f\u0631 \u062c\u0627\u0646",
        "\u067e\u0646\u062f\u0631\u062c\u0627\u0646"
    ],
    "name:ukr_x_preferred":[
        "\u041f\u0430\u043d\u0434\u0430\u0440-\u0414\u0436\u0430\u043d"
    ],
    "name:und_x_variant":[
        "Penderj\u0101n",
        "\u067e\u0646\u062f\u0631 \u062c\u0627\u0646"
    ],
    "wof:name":"Pandar Jan",
    "wof:placetype":"locality"
},
  "geometry": {"coordinates":[50.07557,33.82555],"type":"Point"}
}