{
  "type": "Feature",
  "properties": {
    "gn:admin1_code":"23.0",
    "gn:asciiname":"Razli",
    "gn:country_code":"IR",
    "gn:dem":1593,
    "gn:feature_class":"P",
    "gn:feature_code":"PPL",
    "gn:name":"Razl\u012b",
    "gn:population":0,
    "gn:timezone":"Asia/Tehran",
    "iso:country":"IR",
    "name:fas_x_preferred":[
        "\u0631\u0632\u0644\u06cc"
    ],
    "name:und_x_variant":[
        "Razl\u012b"
    ],
    "wof:name":"Razli",
    "wof:placetype":"locality"
},
  "geometry": {"coordinates":[47.65712,33.91749],"type":"Point"}
}