{
  "type": "Feature",
  "properties": {
    "gn:admin1_code":"5",
    "gn:asciiname":"Tagargi",
    "gn:country_code":"IR",
    "gn:dem":759,
    "gn:feature_class":"P",
    "gn:feature_code":"PPL",
    "gn:name":"Tagarg\u012b",
    "gn:population":0,
    "gn:timezone":"Asia/Tehran",
    "iso:country":"IR",
    "name:fas_x_preferred":[
        "Tagarg\u012b"
    ],
    "wof:name":"Tagargi",
    "wof:placetype":"locality"
},
  "geometry": {"coordinates":[50.45,30.93333],"type":"Point"}
}