{
  "type": "Feature",
  "properties": {
    "gn:admin1_code":"41",
    "gn:asciiname":"Sar-e Qabrestan",
    "gn:country_code":"IR",
    "gn:dem":2110,
    "gn:feature_class":"P",
    "gn:feature_code":"PPL",
    "gn:name":"Sar-e Qabrest\u0101n",
    "gn:population":0,
    "gn:timezone":"Asia/Tehran",
    "iso:country":"IR",
    "name:fas_x_preferred":[
        "Sar-e Qabrest\u0101n"
    ],
    "name:und_x_variant":[
        "Sar-i-Qabrist\u0101n"
    ],
    "wof:name":"Sar-e Qabrestan",
    "wof:placetype":"locality"
},
  "geometry": {"coordinates":[59.28333000000001,32.71667],"type":"Point"}
}