{
  "type": "Feature",
  "properties": {
    "gn:admin1_code":"4.0",
    "gn:asciiname":"`Alikhan",
    "gn:country_code":"IR",
    "gn:dem":481,
    "gn:feature_class":"P",
    "gn:feature_code":"PPL",
    "gn:name":"\u2018Al\u012bkh\u0101n",
    "gn:population":0,
    "gn:timezone":"Asia/Tehran",
    "iso:country":"IR",
    "name:fas_x_preferred":[
        "\u0639\u0644\u06cc\u062e\u0627\u0646"
    ],
    "name:fas_x_variant":[
        "\u2018Al\u012bkh\u0101n"
    ],
    "wof:name":"`Alikhan",
    "wof:placetype":"locality"
},
  "geometry": {"coordinates":[61.74483000000001,31.17521],"type":"Point"}
}