{
  "type": "Feature",
  "properties": {
    "gn:admin1_code":"7",
    "gn:asciiname":"Shaldan",
    "gn:country_code":"IR",
    "gn:dem":461,
    "gn:feature_class":"P",
    "gn:feature_code":"PPL",
    "gn:name":"Shald\u0101n",
    "gn:population":0,
    "gn:timezone":"Asia/Tehran",
    "iso:country":"IR",
    "name:fas_x_preferred":[
        "\u0634\u0646\u062f\u0627\u0646"
    ],
    "name:fas_x_variant":[
        "Shald\u0101n",
        "Shand\u0101n",
        "\u0634\u0644\u062f\u0627\u0646"
    ],
    "wof:name":"Shaldan",
    "wof:placetype":"locality"
},
  "geometry": {"coordinates":[52.6474,27.7387],"type":"Point"}
}