{
  "type": "Feature",
  "properties": {
    "gn:admin1_code":"4",
    "gn:asciiname":"Kaphak",
    "gn:country_code":"IR",
    "gn:dem":883,
    "gn:feature_class":"P",
    "gn:feature_code":"PPL",
    "gn:name":"Kaphak",
    "gn:population":0,
    "gn:timezone":"Asia/Tehran",
    "iso:country":"IR",
    "name:fas_x_preferred":[
        "\u06a9\u067e\u0648\u06a9"
    ],
    "name:fas_x_variant":[
        "Kap\u016bk",
        "\u06a9\u067e\u0647\u06a9",
        "\u0641\u064a\u0631\u0648\u0632 \u0622\u0628\u0627\u062f"
    ],
    "name:und_x_variant":[
        "F\u012br\u016bz\u0101b\u0101d"
    ],
    "wof:name":"Kaphak",
    "wof:placetype":"locality"
},
  "geometry": {"coordinates":[59.90355,26.70918],"type":"Point"}
}