{
  "type": "Feature",
  "properties": {
    "gn:admin1_code":"16",
    "gn:asciiname":"hasan salaran",
    "gn:country_code":"IR",
    "gn:dem":1592,
    "gn:feature_class":"P",
    "gn:feature_code":"PPL",
    "gn:name":"\u062d\u064e\u0633\u064e\u0646 \u0633\u0627\u0644\u0627\u0631\u0627\u0646",
    "gn:population":0,
    "gn:timezone":"Asia/Tehran",
    "iso:country":"IR",
    "name:ara_x_preferred":[
        "\u062d\u0633\u0646 \u0633\u0644\u0627\u0631\u0627\u0646"
    ],
    "name:ceb_x_preferred":[
        "Hasan salaran"
    ],
    "name:ckb_x_preferred":[
        "\u062d\u06d5\u0633\u06d5\u0646 \u0633\u06d5\u0644\u0627\u0631\u0627\u0646"
    ],
    "name:fas_x_preferred":[
        "\u1e28asan S\u0101l\u0101r\u0101n"
    ],
    "name:fas_x_variant":[
        "\u062d\u0633\u0646 \u0633\u0627\u0644\u0627\u0631\u0627\u0646",
        "\u062d\u064e\u0633\u064e\u0646 \u0633\u0627\u0644\u0627\u0631\u0627\u0646",
        "\u062d\u0633\u0646\u200c\u0633\u0627\u0644\u0627\u0631\u0627\u0646"
    ],
    "name:kur_x_preferred":[
        "Hesenselaran"
    ],
    "name:swe_x_preferred":[
        "Hasan salaran"
    ],
    "wof:name":"hasan salaran",
    "wof:placetype":"locality"
},
  "geometry": {"coordinates":[46.2821,36.05],"type":"Point"}
}