{
  "type": "Feature",
  "properties": {
    "gn:admin1_code":"1.0",
    "gn:asciiname":"Qalandar",
    "gn:country_code":"IR",
    "gn:dem":1495,
    "gn:feature_class":"P",
    "gn:feature_code":"PPL",
    "gn:name":"Qalandar",
    "gn:population":0,
    "gn:timezone":"Asia/Tehran",
    "iso:country":"IR",
    "name:fas_x_preferred":[
        "\u0642\u064e\u0644\u064e\u0646\u062f\u064e\u0631"
    ],
    "name:fas_x_variant":[
        "\u0642\u0644\u0646\u062f\u0631"
    ],
    "wof:name":"Qalandar",
    "wof:placetype":"locality"
},
  "geometry": {"coordinates":[46.4811,36.3923],"type":"Point"}
}