{
  "type": "Feature",
  "properties": {
    "gn:admin1_code":"44",
    "gn:asciiname":"Banu Sahra",
    "gn:country_code":"IR",
    "gn:dem":1435,
    "gn:feature_class":"P",
    "gn:feature_code":"PPL",
    "gn:name":"B\u0101n\u016b \u015ea\u1e29r\u0101",
    "gn:population":0,
    "gn:timezone":"Asia/Tehran",
    "iso:country":"IR",
    "name:ceb_x_preferred":[
        "B\u0101n\u016b \u015ea\u1e29r\u0101"
    ],
    "name:fas_x_preferred":[
        "\u0628\u0627\u0646\u0648 \u0635\u062d\u0631\u0627"
    ],
    "name:fas_x_variant":[
        "\u0628\u0627\u0644\u0633\u064e\u0647\u0631\u064e",
        "B\u0101n\u016b \u015ea\u1e29r\u0101",
        "\u0628\u0627\u0646\u0648\u0635\u062d\u0631\u0627"
    ],
    "name:msa_x_preferred":[
        "Banu Sahra"
    ],
    "name:rus_x_preferred":[
        "\u0411\u0430\u043d\u0443-\u0421\u0435\u0445\u0440\u0430"
    ],
    "name:swe_x_preferred":[
        "B\u0101n\u016b \u015ea\u1e29r\u0101"
    ],
    "name:und_x_variant":[
        "B\u0101lsahra"
    ],
    "wof:name":"Banu Sahra",
    "wof:placetype":"locality"
},
  "geometry": {"coordinates":[50.81961,35.9486],"type":"Point"}
}