{
  "type": "Feature",
  "properties": {
    "gn:admin1_code":"33",
    "gn:asciiname":"Valin Jeq",
    "gn:country_code":"IR",
    "gn:dem":1327,
    "gn:feature_class":"P",
    "gn:feature_code":"PPL",
    "gn:name":"Val\u012bn Jeq",
    "gn:population":0,
    "gn:timezone":"Asia/Tehran",
    "iso:country":"IR",
    "name:ara_x_preferred":[
        "\u0648\u0644\u064a\u0646 \u062c\u0642"
    ],
    "name:ceb_x_preferred":[
        "Val\u012bn Jeq"
    ],
    "name:fas_x_preferred":[
        "\u0648\u0644\u06cc\u0646 \u062c\u0642"
    ],
    "name:fas_x_variant":[
        "Var\u012bnjeq",
        "Val\u012bn Jeq",
        "\u0648\u0644\u06cc\u0646\u062c\u0642"
    ],
    "name:msa_x_preferred":[
        "Valin Jeq"
    ],
    "name:swe_x_preferred":[
        "Val\u012bn Jeq"
    ],
    "wof:name":"Valin Jeq",
    "wof:placetype":"locality"
},
  "geometry": {"coordinates":[45.95,37.481],"type":"Point"}
}