{
  "type": "Feature",
  "properties": {
    "gn:admin1_code":"42",
    "gn:asciiname":"Layen-e Now",
    "gn:country_code":"IR",
    "gn:dem":850,
    "gn:feature_class":"P",
    "gn:feature_code":"PPL",
    "gn:name":"L\u0101yen-e Now",
    "gn:population":0,
    "gn:timezone":"Asia/Tehran",
    "iso:country":"IR",
    "name:fas_x_preferred":[
        "\u0644\u0627\u06cc\u0646 \u0646\u0648"
    ],
    "name:fas_x_variant":[
        "L\u0101yen-e Now",
        "\u062d\u0633\u0646 \u0622\u0628\u0627\u062f \u0644\u0627\u06cc\u0646 \u0646\u0648",
        "\u062d\u0633\u0646\u200c\u0622\u0628\u0627\u062f \u0644\u0627\u0626\u06cc\u0646 \u0646\u0648"
    ],
    "name:und_x_variant":[
        "\u1e28asan\u0101b\u0101d-e L\u0101yen-e Now"
    ],
    "wof:name":"Layen-e Now",
    "wof:placetype":"locality"
},
  "geometry": {"coordinates":[59.49936,37.13076],"type":"Point"}
}