{
  "type": "Feature",
  "properties": {
    "gn:admin1_code":"42.0",
    "gn:asciiname":"Pirshahbaz",
    "gn:country_code":"IR",
    "gn:dem":1742,
    "gn:feature_class":"P",
    "gn:feature_code":"PPL",
    "gn:name":"P\u012brshahb\u0101z",
    "gn:population":0,
    "gn:timezone":"Asia/Tehran",
    "iso:country":"IR",
    "name:fas_x_preferred":[
        "P\u012brshahb\u0101z"
    ],
    "name:fas_x_variant":[
        "\u067e\u06cc\u0631\u0634\u0647\u0628\u0627\u0632"
    ],
    "name:und_x_variant":[
        "\u067e\u06cc\u0631\u0634\u0647\u0628\u0627\u0632"
    ],
    "wof:name":"Pirshahbaz",
    "wof:placetype":"locality"
},
  "geometry": {"coordinates":[58.23793000000001,36.88212],"type":"Point"}
}