{
  "type": "Feature",
  "properties": {
    "gn:admin1_code":"40",
    "gn:asciiname":"Nasrabad",
    "gn:country_code":"IR",
    "gn:dem":2257,
    "gn:feature_class":"P",
    "gn:feature_code":"PPL",
    "gn:name":"Na\u015fr\u0101b\u0101d",
    "gn:population":0,
    "gn:timezone":"Asia/Tehran",
    "iso:country":"IR",
    "name:fas_x_preferred":[
        "\u0646\u064e\u0635\u0631\u0627\u0628\u0627\u062f\u0650 \u067e\u064a\u0634\u0643\u0648\u0647"
    ],
    "name:fas_x_variant":[
        "\u0646\u064e\u0633\u0631\u0627\u0628\u0627\u062f\u0650 \u067e\u064a\u0634\u0643\u0648\u0647",
        "\u0646\u0635\u0631 \u0622\u0628\u0627\u062f",
        "Na\u015fr\u0101b\u0101d-e P\u012bshk\u016bh",
        "Na\u015fr\u0101b\u0101d"
    ],
    "name:und_x_variant":[
        "Nasr Abad Pishkooh",
        "Nasr\u0101b\u0101d-e P\u012bshk\u016bh"
    ],
    "wof:name":"Nasrabad",
    "wof:placetype":"locality"
},
  "geometry": {"coordinates":[53.8636,31.7613],"type":"Point"}
}