{
  "type": "Feature",
  "properties": {
    "gn:admin1_code":"35",
    "gn:asciiname":"Sang Kali",
    "gn:country_code":"IR",
    "gn:dem":1330,
    "gn:feature_class":"P",
    "gn:feature_code":"PPL",
    "gn:name":"Sang Kal\u012b",
    "gn:population":0,
    "gn:timezone":"Asia/Tehran",
    "iso:country":"IR",
    "name:fas_x_preferred":[
        "\u0633\u0646\u06af \u06a9\u0644\u06cc"
    ],
    "name:fas_x_variant":[
        "Sang Kal\u012b"
    ],
    "wof:name":"Sang Kali",
    "wof:placetype":"locality"
},
  "geometry": {"coordinates":[53.27242,36.04651],"type":"Point"}
}