{
  "type": "Feature",
  "properties": {
    "gn:admin1_code":"4",
    "gn:asciiname":"Gazan",
    "gn:country_code":"IR",
    "gn:dem":1084,
    "gn:feature_class":"P",
    "gn:feature_code":"PPL",
    "gn:name":"Gazan",
    "gn:population":0,
    "gn:timezone":"Asia/Tehran",
    "iso:country":"IR",
    "name:ceb_x_preferred":[
        "Gazan"
    ],
    "name:fas_x_preferred":[
        "\u06af\u0632\u0646"
    ],
    "name:fra_x_preferred":[
        "Gazan"
    ],
    "name:swe_x_preferred":[
        "Gazan"
    ],
    "wof:name":"Gazan",
    "wof:placetype":"locality"
},
  "geometry": {"coordinates":[62.6213,26.7305],"type":"Point"}
}