{
  "type": "Feature",
  "properties": {
    "gn:admin1_code":"15.0",
    "gn:asciiname":"Khoms",
    "gn:country_code":"IR",
    "gn:dem":15,
    "gn:feature_class":"P",
    "gn:feature_code":"PPL",
    "gn:name":"Khoms",
    "gn:population":0,
    "gn:timezone":"Asia/Tehran",
    "iso:country":"IR",
    "name:fas_x_preferred":[
        "\u062e\u0645\u0633"
    ],
    "wof:name":"Khoms",
    "wof:placetype":"locality"
},
  "geometry": {"coordinates":[48.84908,30.76433],"type":"Point"}
}