{
  "type": "Feature",
  "properties": {
    "gn:admin1_code":"22",
    "gn:asciiname":"Gowdeh",
    "gn:country_code":"IR",
    "gn:dem":22,
    "gn:feature_class":"P",
    "gn:feature_code":"PPL",
    "gn:name":"Gowdeh",
    "gn:population":0,
    "gn:timezone":"Asia/Tehran",
    "iso:country":"IR",
    "name:fas_x_preferred":[
        "\u06af\u0648\u062f\u0646"
    ],
    "name:fas_x_variant":[
        "\u06af\u0648\u062f\u0647",
        "\u06af\u064f\u0648\u062f"
    ],
    "name:und_x_variant":[
        "Gowd",
        "Gowden"
    ],
    "wof:name":"Gowdeh",
    "wof:placetype":"locality"
},
  "geometry": {"coordinates":[52.04397,27.85477],"type":"Point"}
}