{
  "type": "Feature",
  "properties": {
    "gn:admin1_code":"15",
    "gn:asciiname":"Mo`ag",
    "gn:country_code":"IR",
    "gn:dem":12,
    "gn:feature_class":"P",
    "gn:feature_code":"PPL",
    "gn:name":"Mo\u2018\u0101g",
    "gn:population":0,
    "gn:timezone":"Asia/Tehran",
    "iso:country":"IR",
    "name:fas_x_preferred":[
        "Mo\u2018\u0101g"
    ],
    "wof:name":"Mo`ag",
    "wof:placetype":"locality"
},
  "geometry": {"coordinates":[48.02694,31.53861],"type":"Point"}
}