{
  "type": "Feature",
  "properties": {
    "gn:admin1_code":"4",
    "gn:asciiname":"Keshari-ye Azadi",
    "gn:country_code":"IR",
    "gn:dem":126,
    "gn:feature_class":"P",
    "gn:feature_code":"PPL",
    "gn:name":"Kesh\u0101r\u012b-ye \u0100z\u0101d\u012b",
    "gn:population":0,
    "gn:timezone":"Asia/Tehran",
    "iso:country":"IR",
    "name:fas_x_preferred":[
        "\u06a9\u0634\u0627\u0631\u06cc \u0622\u0632\u0627\u062f\u06cc"
    ],
    "name:fas_x_variant":[
        "Kesh\u0101r\u012b-ye \u0100z\u0101d\u012b"
    ],
    "wof:name":"Keshari-ye Azadi",
    "wof:placetype":"locality"
},
  "geometry": {"coordinates":[61.5805,25.9674],"type":"Point"}
}