{
  "type": "Feature",
  "properties": {
    "gn:admin1_code":"11.0",
    "gn:asciiname":"Hash Gazu",
    "gn:country_code":"IR",
    "gn:dem":1198,
    "gn:feature_class":"P",
    "gn:feature_code":"PPL",
    "gn:name":"H\u0101sh Gaz\u016b",
    "gn:population":0,
    "gn:timezone":"Asia/Tehran",
    "iso:country":"IR",
    "name:fas_x_preferred":[
        "\u0647\u0627\u0634 \u06af\u0632\u0648"
    ],
    "name:und_x_variant":[
        "H\u0101sh Gaz\u016b"
    ],
    "wof:name":"Hash Gazu",
    "wof:placetype":"locality"
},
  "geometry": {"coordinates":[56.80606,28.03655],"type":"Point"}
}