{
  "type": "Feature",
  "properties": {
    "gn:admin1_code":"5",
    "gn:asciiname":"Gendizar",
    "gn:cc2":"IR",
    "gn:country_code":"IR",
    "gn:dem":1572,
    "gn:feature_class":"P",
    "gn:feature_code":"PPL",
    "gn:name":"Gend\u012bz\u0101r",
    "gn:population":0,
    "gn:timezone":"Asia/Tehran",
    "iso:country":"IR",
    "name:fas_x_preferred":[
        "\u06af\u0650\u0646\u062f\u064a\u0632\u0627\u0631"
    ],
    "name:fas_x_variant":[
        "\u06af\u064e\u0646\u062f\u064a\u0632\u064e\u0631",
        "Gend\u012bz\u0101r"
    ],
    "name:und_x_variant":[
        "Gandi Zad",
        "Gand\u012bzar"
    ],
    "wof:name":"Gendizar",
    "wof:placetype":"locality"
},
  "geometry": {"coordinates":[51.27361,30.95083],"type":"Point"}
}