{
  "type": "Feature",
  "properties": {
    "gn:admin1_code":"32",
    "gn:asciiname":"Dushanlu",
    "gn:country_code":"IR",
    "gn:dem":1177,
    "gn:feature_class":"P",
    "gn:feature_code":"PPL",
    "gn:name":"D\u016bsh\u0101nl\u016b",
    "gn:population":0,
    "gn:timezone":"Asia/Tehran",
    "iso:country":"IR",
    "name:fas_x_preferred":[
        "\u062f\u0648\u0634\u0627\u0646\u0644\u0648"
    ],
    "name:fas_x_variant":[
        "D\u016bsh\u0101nl\u016b",
        "\u0633\u0644\u0645\u0627\u0646 \u06a9\u0646\u062f\u06cc"
    ],
    "name:und_x_variant":[
        "Salm\u0101n Kand\u012b"
    ],
    "wof:name":"Dushanlu",
    "wof:placetype":"locality"
},
  "geometry": {"coordinates":[47.4597,38.3672],"type":"Point"}
}