{
  "type": "Feature",
  "properties": {
    "gn:admin1_code":"5",
    "gn:asciiname":"Shahrokhi",
    "gn:country_code":"IR",
    "gn:dem":1024,
    "gn:feature_class":"P",
    "gn:feature_code":"PPL",
    "gn:name":"Sh\u0101hrokh\u012b",
    "gn:population":0,
    "gn:timezone":"Asia/Tehran",
    "iso:country":"IR",
    "name:fas_x_preferred":[
        "\u0634\u0627\u0647\u0631\u064f\u062e\u06cc"
    ],
    "name:fas_x_variant":[
        "Sh\u0101hrokh\u012b"
    ],
    "wof:name":"Shahrokhi",
    "wof:placetype":"locality"
},
  "geometry": {"coordinates":[50.47917,31.02361],"type":"Point"}
}