{
  "type": "Feature",
  "properties": {
    "gn:admin1_code":"8",
    "gn:asciiname":"Nalus",
    "gn:country_code":"IR",
    "gn:dem":777,
    "gn:feature_class":"P",
    "gn:feature_code":"PPLL",
    "gn:name":"N\u0101l\u016bs",
    "gn:population":0,
    "gn:timezone":"Asia/Tehran",
    "iso:country":"IR",
    "name:ara_x_preferred":[
        "\u0646\u0627\u0644\u0648\u0633"
    ],
    "name:aze_x_preferred":[
        "Nalus"
    ],
    "name:ceb_x_preferred":[
        "N\u0101l\u016bs"
    ],
    "name:ckb_x_preferred":[
        "\u0646\u06d5\u06b5\u06c6\u0633"
    ],
    "name:fas_x_preferred":[
        "\u0646\u0627\u0644\u0648\u0633"
    ],
    "name:fas_x_variant":[
        "N\u0101l\u016bs"
    ],
    "name:kur_x_preferred":[
        "Nellos"
    ],
    "name:mlg_x_preferred":[
        "Nalus"
    ],
    "name:msa_x_preferred":[
        "Nalus"
    ],
    "name:swe_x_preferred":[
        "N\u0101l\u016bs"
    ],
    "name:tur_x_preferred":[
        "Nalus"
    ],
    "name:urd_x_preferred":[
        "\u0646\u0627\u0644\u0648\u0633"
    ],
    "wof:name":"Nalus",
    "wof:placetype":"locality"
},
  "geometry": {"coordinates":[49.4319,36.8797],"type":"Point"}
}