{
  "type": "Feature",
  "properties": {
    "gn:admin1_code":"42",
    "gn:asciiname":"Kenar Gusheh",
    "gn:country_code":"IR",
    "gn:dem":941,
    "gn:feature_class":"P",
    "gn:feature_code":"PPL",
    "gn:name":"Ken\u0101r G\u016bsheh",
    "gn:population":0,
    "gn:timezone":"Asia/Tehran",
    "iso:country":"IR",
    "name:fas_x_preferred":[
        "\u06a9\u0646\u0627\u0631 \u06af\u0648\u0634\u0647"
    ],
    "name:fas_x_variant":[
        "Ken\u0101r G\u016bsheh"
    ],
    "name:und_x_variant":[
        "Kaneh G\u016bsheh"
    ],
    "wof:name":"Kenar Gusheh",
    "wof:placetype":"locality"
},
  "geometry": {"coordinates":[59.7679,36.3512],"type":"Point"}
}