{
  "type": "Feature",
  "properties": {
    "gn:admin1_code":"15",
    "gn:asciiname":"Karim Khalaf",
    "gn:country_code":"IR",
    "gn:dem":39,
    "gn:feature_class":"P",
    "gn:feature_code":"PPL",
    "gn:name":"Kar\u012bm Khalaf",
    "gn:population":0,
    "gn:timezone":"Asia/Tehran",
    "iso:country":"IR",
    "name:fas_x_preferred":[
        "\u06a9\u0631\u06cc\u0645 \u062e\u0644\u0641"
    ],
    "name:fas_x_variant":[
        "Kar\u012bm Khalaf"
    ],
    "name:und_x_variant":[
        "Khalaf",
        "Kar\u012bm Khal\u012bf"
    ],
    "wof:name":"Karim Khalaf",
    "wof:placetype":"locality"
},
  "geometry": {"coordinates":[48.42374,31.78055],"type":"Point"}
}