{
  "type": "Feature",
  "properties": {
    "gn:admin1_code":"38.0",
    "gn:asciiname":"Alkeh Dasht",
    "gn:country_code":"IR",
    "gn:dem":1537,
    "gn:feature_class":"P",
    "gn:feature_code":"PPL",
    "gn:name":"Alkeh Dasht",
    "gn:population":0,
    "gn:timezone":"Asia/Tehran",
    "iso:country":"IR",
    "name:fas_x_preferred":[
        "\u0627\u0644\u06a9\u0647 \u062f\u0634\u062a"
    ],
    "wof:name":"Alkeh Dasht",
    "wof:placetype":"locality"
},
  "geometry": {"coordinates":[49.55821,36.46582],"type":"Point"}
}