{
  "type": "Feature",
  "properties": {
    "gn:admin1_code":"7",
    "gn:asciiname":"Chah-e Anjir",
    "gn:country_code":"IR",
    "gn:dem":1517,
    "gn:feature_class":"P",
    "gn:feature_code":"PPL",
    "gn:name":"Ch\u0101h-e Anj\u012br",
    "gn:population":0,
    "gn:timezone":"Asia/Tehran",
    "iso:country":"IR",
    "name:fas_x_preferred":[
        "\u0686\u0627\u0647 \u0627\u0646\u062c\u06cc\u0631"
    ],
    "name:fas_x_variant":[
        "Ch\u0101h-e Anj\u012br"
    ],
    "wof:name":"Chah-e Anjir",
    "wof:placetype":"locality"
},
  "geometry": {"coordinates":[53.78041999999999,28.42758],"type":"Point"}
}