{
  "type": "Feature",
  "properties": {
    "gn:admin1_code":"35.0",
    "gn:asciiname":"Hajji Qushandaz",
    "gn:country_code":"IR",
    "gn:dem":109,
    "gn:feature_class":"P",
    "gn:feature_code":"PPL",
    "gn:name":"\u1e28\u0101jj\u012b Q\u016bsh\u0101nd\u0101z",
    "gn:population":0,
    "gn:timezone":"Asia/Tehran",
    "iso:country":"IR",
    "name:fas_x_preferred":[
        "\u062d\u0627\u062c\u0651\u06cc \u0642\u0648\u0634\u0627\u0646\u062f\u0627\u0632"
    ],
    "wof:name":"Hajji Qushandaz",
    "wof:placetype":"locality"
},
  "geometry": {"coordinates":[55.36666999999999,37.43333],"type":"Point"}
}