{
  "type": "Feature",
  "properties": {
    "gn:admin1_code":"38.0",
    "gn:asciiname":"Kheyrabad",
    "gn:country_code":"IR",
    "gn:dem":1269,
    "gn:feature_class":"P",
    "gn:feature_code":"PPL",
    "gn:name":"Kheyr\u0101b\u0101d",
    "gn:population":0,
    "gn:timezone":"Asia/Tehran",
    "iso:country":"IR",
    "name:fas_x_preferred":[
        "\u062e\u06cc\u0631 \u0622\u0628\u0627\u062f"
    ],
    "name:fas_x_variant":[
        "Kheyr\u0101b\u0101d",
        "\u0686\u0648\u0628\u06cc\u0646 \u062f\u0631"
    ],
    "name:und_x_variant":[
        "Ch\u016bb\u012bn Dar"
    ],
    "wof:name":"Kheyrabad",
    "wof:placetype":"locality"
},
  "geometry": {"coordinates":[49.95459,36.23755],"type":"Point"}
}