{
  "type": "Feature",
  "properties": {
    "gn:admin1_code":"29",
    "gn:asciiname":"Murang Ebrahim Mahmudia",
    "gn:country_code":"IR",
    "gn:dem":2196,
    "gn:feature_class":"P",
    "gn:feature_code":"PPL",
    "gn:name":"M\u016brang Ebr\u0101h\u012bm Ma\u1e29m\u016bd\u012b\u0101",
    "gn:population":0,
    "gn:timezone":"Asia/Tehran",
    "iso:country":"IR",
    "name:fas_x_preferred":[
        "\u0645\u0648\u0631\u0646\u06af \u0627\u0628\u0631\u0627\u0647\u06cc\u0645 \u0645\u062d\u0645\u0648\u062f\u06cc\u0627"
    ],
    "name:fas_x_variant":[
        "\u0645\u0648\u0631\u0646\u06af"
    ],
    "name:und_x_variant":[
        "Moreng",
        "M\u016brang Ebr\u0101h\u012bm Ma\u1e29m\u016bd\u012b\u0101",
        "M\u016brang"
    ],
    "wof:name":"Murang Ebrahim Mahmudia",
    "wof:placetype":"locality"
},
  "geometry": {"coordinates":[55.38931,30.22417],"type":"Point"}
}