{
  "type": "Feature",
  "properties": {
    "gn:admin1_code":"7",
    "gn:asciiname":"Shahrak-e Montazeri",
    "gn:country_code":"IR",
    "gn:dem":739,
    "gn:feature_class":"P",
    "gn:feature_code":"PPL",
    "gn:name":"Shahrak-e Montaz\u0327er\u012b",
    "gn:population":0,
    "gn:timezone":"Asia/Tehran",
    "iso:country":"IR",
    "name:ara_x_preferred":[
        "\u0634\u0647\u0631\u0643 \u0627\u0644\u0645\u0646\u062a\u0638\u0631\u064a"
    ],
    "name:fas_x_preferred":[
        "Shahrak-e Montaz\u0327er\u012b"
    ],
    "name:fas_x_variant":[
        "\u0634\u0647\u0631\u06a9 \u0645\u0646\u062a\u0638\u0631\u06cc"
    ],
    "wof:name":"Shahrak-e Montazeri",
    "wof:placetype":"locality"
},
  "geometry": {"coordinates":[53.06222,28.47194],"type":"Point"}
}