{
  "type": "Feature",
  "properties": {
    "gn:admin1_code":"7",
    "gn:asciiname":"Shahrak-e Montazeri",
    "gn:country_code":"IR",
    "gn:dem":739,
    "gn:feature_class":"P",
    "gn:feature_code":"PPL",
    "gn:name":"Shahrak-e Montaz\u0327er\u012b",
    "gn:population":0,
    "gn:timezone":"Asia/Tehran",
    "iso:country":"IR",
    "name:fas_x_preferred":[
        "Shahrak-e Montaz\u0327er\u012b"
    ],
    "wof:name":"Shahrak-e Montazeri",
    "wof:placetype":"locality"
},
  "geometry": {"coordinates":[53.06222,28.47194],"type":"Point"}
}