{
  "type": "Feature",
  "properties": {
    "gn:admin1_code":"40",
    "gn:asciiname":"Banadkuk-e Dizeh",
    "gn:country_code":"IR",
    "gn:dem":2301,
    "gn:feature_class":"P",
    "gn:feature_code":"PPL",
    "gn:name":"Ban\u0101dk\u016bk-e D\u012bzeh",
    "gn:population":0,
    "gn:timezone":"Asia/Tehran",
    "iso:country":"IR",
    "name:fas_x_preferred":[
        "\u0628\u0646\u0627\u062f\u0643\u0648\u06a9 \u062f\u064a\u0632\u0647"
    ],
    "name:fas_x_variant":[
        "\u0628\u064e\u0646\u0627\u062f\u0643\u0650 \u062f\u064a\u0632\u0650\u0647",
        "\u0628\u064e\u0646\u064e\u062f \u0643\u064f\u0651\u0643",
        "\u0628\u064e\u0646\u0627\u062f\u0643\u0648\u0643",
        "Ban\u0101dk\u016bk-e D\u012bzeh"
    ],
    "name:und_x_variant":[
        "Ban\u0101dk-e D\u012bzeh",
        "Ban\u0101dk\u016bk",
        "Banad Kook"
    ],
    "wof:name":"Banadkuk-e Dizeh",
    "wof:placetype":"locality"
},
  "geometry": {"coordinates":[53.9684,31.4702],"type":"Point"}
}