{
  "type": "Feature",
  "properties": {
    "gn:admin1_code":"11",
    "gn:asciiname":"Bu'ikan",
    "gn:country_code":"IR",
    "gn:dem":901,
    "gn:feature_class":"P",
    "gn:feature_code":"PPLL",
    "gn:name":"B\u016b\u2019\u012bk\u0101n",
    "gn:population":0,
    "gn:timezone":"Asia/Tehran",
    "iso:country":"IR",
    "name:ara_x_preferred":[
        "\u0628\u0648\u0626\u064a\u06a9\u0627\u0646"
    ],
    "name:fas_x_preferred":[
        "B\u016b\u2019\u012bg\u0101n"
    ],
    "name:fas_x_variant":[
        "\u0628\u0648\u0626\u06cc\u06a9\u0627\u0646",
        "B\u016b\u2019\u012bk\u0101n"
    ],
    "name:msa_x_preferred":[
        "Buikan"
    ],
    "wof:name":"Bu'ikan",
    "wof:placetype":"locality"
},
  "geometry": {"coordinates":[58.27524,26.51513],"type":"Point"}
}