{
  "type": "Feature",
  "properties": {
    "gn:admin1_code":"4.0",
    "gn:asciiname":"Piridan",
    "gn:country_code":"IR",
    "gn:dem":580,
    "gn:feature_class":"P",
    "gn:feature_code":"PPL",
    "gn:name":"P\u012br\u012bdan",
    "gn:population":0,
    "gn:timezone":"Asia/Tehran",
    "iso:country":"IR",
    "name:fas_x_preferred":[
        "\u067e\u06cc\u0631\u06cc \u062f\u0646"
    ],
    "name:fas_x_variant":[
        "P\u012br\u012bdan"
    ],
    "name:und_x_variant":[
        "B\u012br\u012bdan"
    ],
    "wof:name":"Piridan",
    "wof:placetype":"locality"
},
  "geometry": {"coordinates":[61.2995,26.3472],"type":"Point"}
}