{
  "type": "Feature",
  "properties": {
    "gn:admin1_code":"43",
    "gn:asciiname":"Sankhvast",
    "gn:country_code":"IR",
    "gn:dem":967,
    "gn:feature_class":"P",
    "gn:feature_code":"PPL",
    "gn:name":"Sankhv\u0101st",
    "gn:population":0,
    "gn:timezone":"Asia/Tehran",
    "iso:country":"IR",
    "name:ara_x_preferred":[
        "\u0633\u0646\u062e\u0648\u0627\u0633\u062a"
    ],
    "name:aze_x_preferred":[
        "S\u0259nxast"
    ],
    "name:ceb_x_preferred":[
        "Sankh\u0101st"
    ],
    "name:fas_x_preferred":[
        "Sankhv\u0101st"
    ],
    "name:fas_x_variant":[
        "\u0633\u0646\u062e\u0648\u0627\u0633\u062a"
    ],
    "name:mlg_x_preferred":[
        "Sankhast"
    ],
    "name:swe_x_preferred":[
        "Sankh\u0101st"
    ],
    "name:tur_x_preferred":[
        "Senhvast"
    ],
    "name:und_x_variant":[
        "Sanghas",
        "Sangkhuast",
        "Sankh\u0101\u015f"
    ],
    "wof:name":"Sankhvast",
    "wof:placetype":"locality"
},
  "geometry": {"coordinates":[56.85183000000001,37.09916],"type":"Point"}
}