{
  "type": "Feature",
  "properties": {
    "gn:admin1_code":"43",
    "gn:asciiname":"Sankhvast",
    "gn:country_code":"IR",
    "gn:dem":967,
    "gn:feature_class":"P",
    "gn:feature_code":"PPL",
    "gn:name":"Sankhv\u0101st",
    "gn:population":0,
    "gn:timezone":"Asia/Tehran",
    "iso:country":"IR",
    "name:fas_x_preferred":[
        "Sankhv\u0101st"
    ],
    "name:fas_x_variant":[
        "\u0633\u0646\u062e\u0648\u0627\u0633\u062a"
    ],
    "name:und_x_variant":[
        "Sankh\u0101st",
        "Sanghas",
        "Sangkhuast",
        "Sankh\u0101\u015f",
        "\u0633\u0646\u062e\u0648\u0627\u0633\u062a"
    ],
    "wof:name":"Sankhvast",
    "wof:placetype":"locality"
},
  "geometry": {"coordinates":[56.85183000000001,37.09916],"type":"Point"}
}