{
  "type": "Feature",
  "properties": {
    "gn:admin1_code":"5",
    "gn:asciiname":"Cheshmeh Darreh",
    "gn:country_code":"IR",
    "gn:dem":1773,
    "gn:feature_class":"P",
    "gn:feature_code":"PPL",
    "gn:name":"Cheshmeh Darreh",
    "gn:population":0,
    "gn:timezone":"Asia/Tehran",
    "iso:country":"IR",
    "name:fas_x_preferred":[
        "\u0686\u0650\u0634\u0645\u0650\u0647 \u062f\u064e\u0631\u0650\u0651\u0647"
    ],
    "name:fas_x_variant":[
        "\u0686\u0634\u0645\u0647 \u062f\u0631\u0647"
    ],
    "wof:name":"Cheshmeh Darreh",
    "wof:placetype":"locality"
},
  "geometry": {"coordinates":[51.33583,30.89444],"type":"Point"}
}