{
  "type": "Feature",
  "properties": {
    "gn:admin1_code":"38",
    "gn:asciiname":"Yam Cheshmeh",
    "gn:country_code":"IR",
    "gn:dem":1677,
    "gn:feature_class":"P",
    "gn:feature_code":"PPL",
    "gn:name":"Y\u0101m Cheshmeh",
    "gn:population":0,
    "gn:timezone":"Asia/Tehran",
    "iso:country":"IR",
    "name:fas_x_preferred":[
        "\u06cc\u0627\u0645 \u0686\u0634\u0645\u0647"
    ],
    "name:fas_x_variant":[
        "\u064a\u0627\u0646 \u0686\u064e\u0634\u0645\u0650\u0647",
        "\u064a\u0627\u0645 \u0686\u064e\u0634\u0645\u0650\u0647",
        "Y\u0101m Cheshmeh"
    ],
    "name:und_x_variant":[
        "Y\u0101m Chashmeh",
        "Y\u0101n Chashmeh"
    ],
    "name:urd_x_preferred":[
        "\u06cc\u0645 \u0686\u0634\u0645\u06c1"
    ],
    "wof:name":"Yam Cheshmeh",
    "wof:placetype":"locality"
},
  "geometry": {"coordinates":[49.38009,35.94972999999999],"type":"Point"}
}