{
  "type": "Feature",
  "properties": {
    "gn:admin1_code":"26.0",
    "gn:asciiname":"Sefid Kamar",
    "gn:country_code":"IR",
    "gn:dem":2137,
    "gn:feature_class":"P",
    "gn:feature_code":"PPL",
    "gn:name":"Sef\u012bd Kamar",
    "gn:population":0,
    "gn:timezone":"Asia/Tehran",
    "iso:country":"IR",
    "name:fas_x_preferred":[
        "\u0633\u0650\u0641\u064a\u062f \u0643\u064e\u0645\u064e\u0631\u0650 \u067e\u0627\u0626\u064a\u0646"
    ],
    "name:fas_x_variant":[
        "Sef\u012bd Kamar-e P\u0101\u2019\u012bn",
        "\u0633\u0641\u064a\u062f \u06a9\u0645\u0631"
    ],
    "name:und_x_variant":[
        "Sef\u012bd Kamar"
    ],
    "wof:name":"Sefid Kamar",
    "wof:placetype":"locality"
},
  "geometry": {"coordinates":[52.05461,35.59933],"type":"Point"}
}