{
  "type": "Feature",
  "properties": {
    "gn:admin1_code":"7",
    "gn:asciiname":"Bahme'i",
    "gn:country_code":"IR",
    "gn:dem":1612,
    "gn:feature_class":"P",
    "gn:feature_code":"PPL",
    "gn:name":"Bahme\u2019\u012b",
    "gn:population":0,
    "gn:timezone":"Asia/Tehran",
    "iso:country":"IR",
    "name:fas_x_preferred":[
        "Bahme\u2019\u012b"
    ],
    "name:fas_x_variant":[
        "Bahmeh\u2019\u012b",
        "\u0628\u0647\u0645\u0647 \u0627\u06cc",
        "\u0628\u0647\u0645\u0626\u06cc",
        "\u0628\u0647\u0645\u0646\u06cc"
    ],
    "name:und_x_variant":[
        "Bahm\u00e9",
        "Bahman\u012b",
        "\u0628\u0647\u0645\u0647 \u0627\u06cc"
    ],
    "wof:name":"Bahme'i",
    "wof:placetype":"locality"
},
  "geometry": {"coordinates":[52.4536,30.0642],"type":"Point"}
}