{
  "type": "Feature",
  "properties": {
    "gn:admin1_code":"1",
    "gn:asciiname":"Kusehabad",
    "gn:country_code":"IR",
    "gn:dem":1287,
    "gn:feature_class":"P",
    "gn:feature_code":"PPL",
    "gn:name":"K\u016bseh\u0101b\u0101d",
    "gn:population":0,
    "gn:timezone":"Asia/Tehran",
    "iso:country":"IR",
    "name:azb_x_preferred":[
        "\u06a9\u0648\u0633\u0627 \u0622\u0628\u0627\u062f"
    ],
    "name:aze_x_preferred":[
        "Kus\u0259abad"
    ],
    "name:ceb_x_preferred":[
        "K\u016bseh\u0101b\u0101d"
    ],
    "name:fas_x_preferred":[
        "\u0643\u0648\u0633\u0650\u0647 \u0622\u0628\u0627\u062f"
    ],
    "name:fas_x_variant":[
        "\u06a9\u0648\u0633\u0647 \u0622\u0628\u0627\u062f",
        "K\u016bseh\u0101b\u0101d",
        "\u06a9\u0648\u0633\u0647\u200c\u0622\u0628\u0627\u062f"
    ],
    "name:msa_x_preferred":[
        "Kusehabad"
    ],
    "name:swe_x_preferred":[
        "K\u016bseh\u0101b\u0101d"
    ],
    "wof:name":"Kusehabad",
    "wof:placetype":"locality"
},
  "geometry": {"coordinates":[45.1877,37.4488],"type":"Point"}
}