{
  "type": "Feature",
  "properties": {
    "gn:admin1_code":"23",
    "gn:asciiname":"Sakvand-e Chavari",
    "gn:country_code":"IR",
    "gn:dem":1831,
    "gn:feature_class":"P",
    "gn:feature_code":"PPL",
    "gn:name":"Sakvand-e Chav\u0101r\u012b",
    "gn:population":0,
    "gn:timezone":"Asia/Tehran",
    "iso:country":"IR",
    "name:ara_x_preferred":[
        "\u0633\u064a\u0643\u0648\u0646\u062f\u062a\u0634\u0648\u0627\u0631\u064a"
    ],
    "name:ceb_x_preferred":[
        "Seykvand"
    ],
    "name:fas_x_preferred":[
        "\u0633\u064a\u0643\u0648\u0646\u062f \u0686\u0648\u0627\u0631\u06cc"
    ],
    "name:fas_x_variant":[
        "Seykavand-e Chav\u0101r\u012b",
        "\u0633\u06cc\u06a9\u0648\u0646\u062f",
        "\u0633\u06a9\u0648\u0646\u062f \u0686\u0648\u0627\u0631\u06cc",
        "\u0633\u06cc\u06a9\u0648\u0646\u062f\u0686\u0648\u0627\u0631\u06cc"
    ],
    "name:swe_x_preferred":[
        "Seykvand"
    ],
    "name:und_x_variant":[
        "S\u012bkvand",
        "Sagvand",
        "Seykvand",
        "\u0633\u06cc\u06a9\u0648\u0646\u062f",
        "Seykavand",
        "Sakvand-e Chav\u0101r\u012b"
    ],
    "wof:name":"Sakvand-e Chavari",
    "wof:placetype":"locality"
},
  "geometry": {"coordinates":[48.0062,34.16651],"type":"Point"}
}