{
  "type": "Feature",
  "properties": {
    "gn:admin1_code":"8.0",
    "gn:asciiname":"Sufun Sar",
    "gn:country_code":"IR",
    "gn:dem":1808,
    "gn:feature_class":"P",
    "gn:feature_code":"PPL",
    "gn:name":"S\u016bf\u016bn Sar",
    "gn:population":0,
    "gn:timezone":"Asia/Tehran",
    "iso:country":"IR",
    "name:fas_x_preferred":[
        "S\u016bf\u016bn Sar"
    ],
    "name:fas_x_variant":[
        "\u015e\u016bf\u012b\u0101n Sar",
        "\u0633\u0648\u0641\u0648\u0646 \u0633\u0631",
        "\u0635\u0648\u0641\u06cc\u0627\u0646 \u0633\u0631"
    ],
    "name:msa_x_preferred":[
        "Sufian Sar"
    ],
    "name:ukr_x_preferred":[
        "\u0421\u0443\u0444\u0456\u044f\u043d-\u0421\u0430\u0440"
    ],
    "wof:name":"Sufun Sar",
    "wof:placetype":"locality"
},
  "geometry": {"coordinates":[49.89274,36.91542000000001],"type":"Point"}
}