{
  "type": "Feature",
  "properties": {
    "gn:admin1_code":"3",
    "gn:asciiname":"Qaraqush",
    "gn:country_code":"IR",
    "gn:dem":1961,
    "gn:feature_class":"P",
    "gn:feature_code":"PPL",
    "gn:name":"Qar\u0101q\u016bsh",
    "gn:population":0,
    "gn:timezone":"Asia/Tehran",
    "iso:country":"IR",
    "name:ceb_x_preferred":[
        "Qar\u0101q\u016bsh"
    ],
    "name:fas_x_preferred":[
        "\u0642\u064e\u0631\u0650\u0647 \u0642\u0627\u0686"
    ],
    "name:fas_x_variant":[
        "Qar\u0101q\u016bsh",
        "\u063a\u064e\u0631\u064e\u063a\u064f\u0651\u0634",
        "\u0642\u064e\u0631\u0627\u06af\u0627\u0686",
        "\u0642\u0631\u0627\u0642\u0648\u0634"
    ],
    "name:msa_x_preferred":[
        "Qaraqush"
    ],
    "name:swe_x_preferred":[
        "Qar\u0101q\u016bsh"
    ],
    "name:und_x_variant":[
        "Qareh Q\u0101ch",
        "Qar\u0101g\u0101ch",
        "Gharaghoosh",
        "\u0642\u0631\u0627\u0642\u0648\u0634"
    ],
    "wof:name":"Qaraqush",
    "wof:placetype":"locality"
},
  "geometry": {"coordinates":[50.80246,32.6978],"type":"Point"}
}