{
  "type": "Feature",
  "properties": {
    "gn:admin1_code":"36",
    "gn:asciiname":"Qafasabad",
    "gn:country_code":"IR",
    "gn:dem":2104,
    "gn:feature_class":"P",
    "gn:feature_code":"PPL",
    "gn:name":"Qafas\u0101b\u0101d",
    "gn:population":0,
    "gn:timezone":"Asia/Tehran",
    "iso:country":"IR",
    "name:fas_x_preferred":[
        "\u0642\u0641\u0633 \u0622\u0628\u0627\u062f"
    ],
    "name:fas_x_variant":[
        "Qafas\u0101b\u0101d"
    ],
    "name:und_x_variant":[
        "Feyz\u0101b\u0101d",
        "Qabas\u0101b\u0101d",
        "K\u0101bas\u0101b\u0101d",
        "Kabsabad"
    ],
    "wof:name":"Qafasabad",
    "wof:placetype":"locality"
},
  "geometry": {"coordinates":[48.94309000000001,36.14513],"type":"Point"}
}