{
  "type": "Feature",
  "properties": {
    "gn:admin1_code":"16",
    "gn:asciiname":"Jebre'il",
    "gn:country_code":"IR",
    "gn:dem":1778,
    "gn:feature_class":"P",
    "gn:feature_code":"PPL",
    "gn:name":"Jebre\u2019\u012bl",
    "gn:population":0,
    "gn:timezone":"Asia/Tehran",
    "iso:country":"IR",
    "name:fas_x_preferred":[
        "\u062c\u0628\u0631\u0626\u06cc\u0644"
    ],
    "name:fas_x_variant":[
        "\u062c\u064e\u0628\u0631\u0627\u0626\u064a\u0644",
        "\u062c\u0650\u0628\u0631\u0627\u0626\u064a\u0644",
        "Jebre\u2019\u012bl"
    ],
    "name:und_x_variant":[
        "Jebr\u0101\u2019\u012bl",
        "J\u012bbr\u0101\u2018il",
        "Jabr\u0101\u2019\u012bl"
    ],
    "wof:name":"Jebre'il",
    "wof:placetype":"locality"
},
  "geometry": {"coordinates":[47.9546,35.6631],"type":"Point"}
}