{
  "type": "Feature",
  "properties": {
    "gn:admin1_code":"26",
    "gn:asciiname":"`Aliabad-e Mohit",
    "gn:country_code":"IR",
    "gn:dem":851,
    "gn:feature_class":"P",
    "gn:feature_code":"PPL",
    "gn:name":"\u2018Al\u012b\u0101b\u0101d-e Mo\u1e29\u012b\u0163",
    "gn:population":0,
    "gn:timezone":"Asia/Tehran",
    "iso:country":"IR",
    "name:fas_x_preferred":[
        "\u0639\u064e\u0644\u064a\u0627\u0628\u0627\u062f\u0650 \u0645\u064f\u062d\u064a\u0637"
    ],
    "name:fas_x_variant":[
        "\u0639\u0644\u06cc \u0622\u0628\u0627\u062f \u0645\u062d\u064a\u0637",
        "\u2018Al\u012b\u0101b\u0101d-e Mo\u1e29\u012b\u0163"
    ],
    "wof:name":"`Aliabad-e Mohit",
    "wof:placetype":"locality"
},
  "geometry": {"coordinates":[51.7452,35.2275],"type":"Point"}
}