{
  "type": "Feature",
  "properties": {
    "gn:admin1_code":"22",
    "gn:asciiname":"Molla Salemi",
    "gn:country_code":"IR",
    "gn:dem":37,
    "gn:feature_class":"P",
    "gn:feature_code":"PPL",
    "gn:name":"Moll\u0101 S\u0101lem\u012b",
    "gn:population":0,
    "gn:timezone":"Asia/Tehran",
    "iso:country":"IR",
    "name:ara_x_preferred":[
        "\u0645\u0644\u0627\u0633\u0627\u0644\u0645\u064a"
    ],
    "name:ceb_x_preferred":[
        "Moll\u0101 S\u0101lem\u012b"
    ],
    "name:fas_x_preferred":[
        "\u0645\u0644\u0627 \u0633\u0627\u0644\u0645\u06cc"
    ],
    "name:fas_x_variant":[
        "Moll\u0101 S\u0101lem\u012b",
        "\u0645\u0644\u0627\u0633\u0627\u0644\u0645\u06cc"
    ],
    "name:msa_x_preferred":[
        "Molla Salemi"
    ],
    "name:swe_x_preferred":[
        "Moll\u0101 S\u0101lem\u012b"
    ],
    "wof:name":"Molla Salemi",
    "wof:placetype":"locality"
},
  "geometry": {"coordinates":[51.786,27.9613],"type":"Point"}
}