{
  "type": "Feature",
  "properties": {
    "gn:admin1_code":"35.0",
    "gn:asciiname":"Khar Chang",
    "gn:country_code":"IR",
    "gn:dem":229,
    "gn:feature_class":"P",
    "gn:feature_code":"PPL",
    "gn:name":"Khar Chang",
    "gn:population":0,
    "gn:timezone":"Asia/Tehran",
    "iso:country":"IR",
    "name:fas_x_preferred":[
        "\u062e\u0631 \u0686\u0646\u06af"
    ],
    "wof:name":"Khar Chang",
    "wof:placetype":"locality"
},
  "geometry": {"coordinates":[53.17378000000001,36.38261],"type":"Point"}
}