{
  "type": "Feature",
  "properties": {
    "gn:admin1_code":"13",
    "gn:asciiname":"Chalav-e Bekr",
    "gn:country_code":"IR",
    "gn:dem":1455,
    "gn:feature_class":"P",
    "gn:feature_code":"PPL",
    "gn:name":"Ch\u0101l\u0101v-e Bekr",
    "gn:population":0,
    "gn:timezone":"Asia/Tehran",
    "iso:country":"IR",
    "name:fas_x_preferred":[
        "\u0686\u0627\u0644\u0627\u0648 \u0628\u06a9\u0631"
    ],
    "name:fas_x_variant":[
        "Ch\u0101l\u0101b-e Bekreh",
        "Ch\u0101l\u0101v-e Bekr"
    ],
    "name:und_x_variant":[
        "Ch\u0101leh Bekar"
    ],
    "wof:name":"Chalav-e Bekr",
    "wof:placetype":"locality"
},
  "geometry": {"coordinates":[46.3384,34.1267],"type":"Point"}
}