{
  "type": "Feature",
  "properties": {
    "gn:admin1_code":"42.0",
    "gn:asciiname":"Barenjegan",
    "gn:country_code":"IR",
    "gn:dem":704,
    "gn:feature_class":"P",
    "gn:feature_code":"PPL",
    "gn:name":"B\u0101renjeg\u0101n",
    "gn:population":0,
    "gn:timezone":"Asia/Tehran",
    "iso:country":"IR",
    "name:fas_x_preferred":[
        "\u0628\u0627\u0631\u0646\u062c\u06af\u0627\u0646"
    ],
    "name:fas_x_variant":[
        "B\u0101renjeg\u0101n"
    ],
    "name:und_x_variant":[
        "B\u0101renjk\u0101n",
        "B\u0101renjek\u0101n"
    ],
    "wof:name":"Barenjegan",
    "wof:placetype":"locality"
},
  "geometry": {"coordinates":[60.4272,33.60879],"type":"Point"}
}