{
  "type": "Feature",
  "properties": {
    "gn:admin1_code":"37",
    "gn:asciiname":"Qoli Tappeh",
    "gn:country_code":"IR",
    "gn:dem":226,
    "gn:feature_class":"P",
    "gn:feature_code":"PPL",
    "gn:name":"Qol\u012b Tappeh",
    "gn:population":0,
    "gn:timezone":"Asia/Tehran",
    "iso:country":"IR",
    "name:fas_x_preferred":[
        "Qol\u012b Tappeh"
    ],
    "name:fas_x_variant":[
        "\u0642\u0644\u06cc \u062a\u067e\u0647"
    ],
    "name:und_x_variant":[
        "K\u0101l\u012b Tappeh",
        "K\u0101litepe",
        "\u0642\u0644\u06cc \u062a\u067e\u0647"
    ],
    "wof:name":"Qoli Tappeh",
    "wof:placetype":"locality"
},
  "geometry": {"coordinates":[55.42009,37.24801],"type":"Point"}
}