{
  "type": "Feature",
  "properties": {
    "gn:admin1_code":"38",
    "gn:asciiname":"Zarrin Khani",
    "gn:country_code":"IR",
    "gn:dem":497,
    "gn:feature_class":"P",
    "gn:feature_code":"PPL",
    "gn:name":"Zarr\u012bn Kh\u0101n\u012b",
    "gn:population":0,
    "gn:timezone":"Asia/Tehran",
    "iso:country":"IR",
    "name:ara_x_preferred":[
        "\u0632\u0631\u064a\u0646 \u062e\u0627\u0646\u064a"
    ],
    "name:fas_x_preferred":[
        "\u0632\u0631\u06cc\u0646 \u062e\u0627\u0646\u06cc"
    ],
    "name:fas_x_variant":[
        "Zarr\u012bn Kh\u0101n\u012b"
    ],
    "name:und_x_variant":[
        "Zarin-Khani"
    ],
    "wof:name":"Zarrin Khani",
    "wof:placetype":"locality"
},
  "geometry": {"coordinates":[49.57756,36.58909],"type":"Point"}
}