{
  "type": "Feature",
  "properties": {
    "gn:admin1_code":"29.0",
    "gn:asciiname":"Moradabad",
    "gn:country_code":"IR",
    "gn:dem":599,
    "gn:feature_class":"P",
    "gn:feature_code":"PPL",
    "gn:name":"Mor\u0101d\u0101b\u0101d",
    "gn:population":0,
    "gn:timezone":"Asia/Tehran",
    "iso:country":"IR",
    "name:fas_x_preferred":[
        "\u0645\u0631\u0627\u062f \u0622\u0628\u0627\u062f"
    ],
    "name:fas_x_variant":[
        "Kah\u016br\u0101b\u0101d",
        "\u06a9\u0647\u0648\u0631 \u0622\u0628\u0627\u062f",
        "Mor\u0101d\u0101b\u0101d"
    ],
    "wof:name":"Moradabad",
    "wof:placetype":"locality"
},
  "geometry": {"coordinates":[57.7777,28.5352],"type":"Point"}
}