{
  "type": "Feature",
  "properties": {
    "gn:admin1_code":"7",
    "gn:asciiname":"Ahl",
    "gn:country_code":"IR",
    "gn:dem":397,
    "gn:feature_class":"P",
    "gn:feature_code":"PPL",
    "gn:name":"Ahl",
    "gn:population":0,
    "gn:timezone":"Asia/Tehran",
    "iso:country":"IR",
    "name:fas_x_preferred":[
        "K\u016bd\u012ban"
    ],
    "name:fas_x_variant":[
        "\u0627\u0647\u0644"
    ],
    "name:und_x_variant":[
        "De\u2019ow",
        "K\u016bh-e De\u2019ow",
        "K\u016bh-i-Deo",
        "Kowd\u012ban",
        "K\u016bh-e-De\u2019\u016b",
        "K\u016bdey\u0101n",
        "Kody\u0101n",
        "Ahl"
    ],
    "wof:name":"Ahl",
    "wof:placetype":"locality"
},
  "geometry": {"coordinates":[53.6594,27.21063],"type":"Point"}
}