{
  "type": "Feature",
  "properties": {
    "gn:admin1_code":"40",
    "gn:asciiname":"Salimabad-e Vosta",
    "gn:country_code":"IR",
    "gn:dem":1574,
    "gn:feature_class":"P",
    "gn:feature_code":"PPL",
    "gn:name":"Sal\u012bm\u0101b\u0101d-e Vos\u0163\u00e1",
    "gn:population":0,
    "gn:timezone":"Asia/Tehran",
    "iso:country":"IR",
    "name:fas_x_preferred":[
        "\u0633\u0644\u064a\u0645 \u0622\u0628\u0627\u062f \u0645\u064a\u0627\u0646\u06cc"
    ],
    "name:fas_x_variant":[
        "Sal\u012bm\u0101b\u0101d-e M\u012b\u0101n\u012b",
        "\u0633\u0644\u064a\u0645 \u0622\u0628\u0627\u062f \u0648\u0633\u0637\u06cc"
    ],
    "name:und_x_variant":[
        "Sal\u012bm\u0101b\u0101d-e Vos\u0163\u00e1"
    ],
    "wof:name":"Salimabad-e Vosta",
    "wof:placetype":"locality"
},
  "geometry": {"coordinates":[54.36601,30.08674],"type":"Point"}
}