{
  "type": "Feature",
  "properties": {
    "gn:admin1_code":"4.0",
    "gn:asciiname":"Barak",
    "gn:country_code":"IR",
    "gn:dem":627,
    "gn:feature_class":"P",
    "gn:feature_code":"PPL",
    "gn:name":"B\u0101rak",
    "gn:population":0,
    "gn:timezone":"Asia/Tehran",
    "iso:country":"IR",
    "name:ara_x_preferred":[
        "\u0628\u0627\u0631\u0627\u0642"
    ],
    "name:bre_x_preferred":[
        "Barak"
    ],
    "name:ces_x_preferred":[
        "B\u00e1rak"
    ],
    "name:deu_x_preferred":[
        "Barak"
    ],
    "name:ell_x_preferred":[
        "\u0392\u03b1\u03c1\u03ac\u03ba"
    ],
    "name:epo_x_preferred":[
        "Barak"
    ],
    "name:fas_x_preferred":[
        "B\u0101rak"
    ],
    "name:fas_x_variant":[
        "\u0628\u0627\u0631\u0627\u06a9"
    ],
    "name:fin_x_preferred":[
        "Barak"
    ],
    "name:fra_x_preferred":[
        "Barac"
    ],
    "name:ind_x_preferred":[
        "Barak"
    ],
    "name:ita_x_preferred":[
        "Barac"
    ],
    "name:jpn_x_preferred":[
        "\u30d0\u30e9\u30af"
    ],
    "name:nld_x_preferred":[
        "Barak"
    ],
    "name:nor_x_preferred":[
        "Barak"
    ],
    "name:pnb_x_preferred":[
        "\u0628\u0627\u0631\u0627\u06a9"
    ],
    "name:pol_x_preferred":[
        "Barak"
    ],
    "name:por_x_preferred":[
        "Baraque"
    ],
    "name:rus_x_preferred":[
        "\u0412\u0430\u0440\u0430\u043a"
    ],
    "name:spa_x_preferred":[
        "Barac"
    ],
    "name:swa_x_preferred":[
        "Barak"
    ],
    "name:swe_x_preferred":[
        "Barak"
    ],
    "name:ukr_x_preferred":[
        "\u0411\u0430\u0440\u0430\u043a"
    ],
    "name:urd_x_preferred":[
        "\u0628\u0631\u0642"
    ],
    "name:wol_x_preferred":[
        "Barag"
    ],
    "wof:name":"Barak",
    "wof:placetype":"locality"
},
  "geometry": {"coordinates":[60.84083,26.09083],"type":"Point"}
}