{
  "type": "Feature",
  "properties": {
    "gn:admin1_code":"4.0",
    "gn:asciiname":"Barak",
    "gn:country_code":"IR",
    "gn:dem":627,
    "gn:feature_class":"P",
    "gn:feature_code":"PPL",
    "gn:name":"B\u0101rak",
    "gn:population":0,
    "gn:timezone":"Asia/Tehran",
    "iso:country":"IR",
    "name:fas_x_preferred":[
        "B\u0101rak"
    ],
    "wof:name":"Barak",
    "wof:placetype":"locality"
},
  "geometry": {"coordinates":[60.84083,26.09083],"type":"Point"}
}