{
  "type": "Feature",
  "properties": {
    "gn:admin1_code":"15",
    "gn:asciiname":"Sar Ab",
    "gn:country_code":"IR",
    "gn:dem":630,
    "gn:feature_class":"P",
    "gn:feature_code":"PPL",
    "gn:name":"Sar \u0100b",
    "gn:population":0,
    "gn:timezone":"Asia/Tehran",
    "iso:country":"IR",
    "name:fas_x_preferred":[
        "Sar \u0100b"
    ],
    "name:fas_x_variant":[
        "\u0633\u0631\u0627\u0628"
    ],
    "wof:name":"Sar Ab",
    "wof:placetype":"locality"
},
  "geometry": {"coordinates":[49.81811,32.00801],"type":"Point"}
}