{
  "type": "Feature",
  "properties": {
    "gn:admin1_code":"16",
    "gn:asciiname":"Ebrahimabad-e Bala",
    "gn:country_code":"IR",
    "gn:dem":2226,
    "gn:feature_class":"P",
    "gn:feature_code":"PPL",
    "gn:name":"Ebr\u0101h\u012bm\u0101b\u0101d-e B\u0101l\u0101",
    "gn:population":0,
    "gn:timezone":"Asia/Tehran",
    "iso:country":"IR",
    "name:fas_x_preferred":[
        "\u0627\u0628\u0631\u0627\u0647\u064a\u0645 \u0622\u0628\u0627\u062f \u0628\u0627\u0644\u0627"
    ],
    "name:fas_x_variant":[
        "Ebr\u0101h\u012bm\u0101b\u0101d-e B\u0101l\u0101"
    ],
    "name:und_x_variant":[
        "Ebr\u0101h\u012bm\u0101b\u0101d B\u0101l\u0101"
    ],
    "wof:name":"Ebrahimabad-e Bala",
    "wof:placetype":"locality"
},
  "geometry": {"coordinates":[47.1818,35.716],"type":"Point"}
}