{
  "type": "Feature",
  "properties": {
    "gn:admin1_code":"13",
    "gn:asciiname":"Javanmiri",
    "gn:country_code":"IR",
    "gn:dem":871,
    "gn:feature_class":"P",
    "gn:feature_code":"PPL",
    "gn:name":"Jav\u0101nm\u012br\u012b",
    "gn:population":0,
    "gn:timezone":"Asia/Tehran",
    "iso:country":"IR",
    "name:ceb_x_preferred":[
        "Jav\u0101nm\u012br\u012b"
    ],
    "name:fas_x_preferred":[
        "\u062c\u0648\u0627\u0646 \u0645\u064a\u0631\u06cc"
    ],
    "name:fas_x_variant":[
        "Jav\u0101nm\u012br\u012b",
        "\u062c\u0648\u0627\u0646\u0645\u06cc\u0631\u06cc"
    ],
    "name:swe_x_preferred":[
        "Jav\u0101nm\u012br\u012b"
    ],
    "name:urd_x_preferred":[
        "\u062c\u0648\u0627\u0646\u0645\u06cc\u0631\u06cc"
    ],
    "wof:name":"Javanmiri",
    "wof:placetype":"locality"
},
  "geometry": {"coordinates":[45.96444,34.59856],"type":"Point"}
}