{
  "type": "Feature",
  "properties": {
    "gn:admin1_code":"33",
    "gn:asciiname":"Hajji Kord",
    "gn:country_code":"IR",
    "gn:dem":1475,
    "gn:feature_class":"P",
    "gn:feature_code":"PPL",
    "gn:name":"\u1e28\u0101jj\u012b Kord",
    "gn:population":0,
    "gn:timezone":"Asia/Tehran",
    "iso:country":"IR",
    "name:azb_x_preferred":[
        "\u062d\u0627\u062c\u06cc\u200c\u06a9\u0631\u062f"
    ],
    "name:fas_x_preferred":[
        "\u062d\u0627\u062c\u06cc \u06a9\u0631\u062f"
    ],
    "name:fas_x_variant":[
        "\u1e28\u0101jj\u012b Kord",
        "\u062d\u0627\u062c\u06cc\u200c\u06a9\u0631\u062f"
    ],
    "name:msa_x_preferred":[
        "Hajji Kord"
    ],
    "wof:name":"Hajji Kord",
    "wof:placetype":"locality"
},
  "geometry": {"coordinates":[46.18908,37.39093],"type":"Point"}
}