{
  "type": "Feature",
  "properties": {
    "gn:admin1_code":"8",
    "gn:asciiname":"Gurabjir-e Sahra",
    "gn:country_code":"IR",
    "gn:dem":-24,
    "gn:feature_class":"P",
    "gn:feature_code":"PPL",
    "gn:name":"G\u016br\u0101bj\u012br-e \u015ea\u1e29r\u0101",
    "gn:population":0,
    "gn:timezone":"Asia/Tehran",
    "iso:country":"IR",
    "name:fas_x_preferred":[
        "G\u016br \u0100bj\u012br"
    ],
    "name:fas_x_variant":[
        "G\u016br\u0101bj\u012br-e \u015ea\u1e29r\u0101",
        "\u06af\u0648\u0631 \u0622\u0628\u062c\u06cc\u0631",
        "\u06af\u0648\u0631 \u0627\u0628\u062c\u06cc\u0631 \u0635\u062d\u0631\u0627",
        "\u06af\u0648\u0631\u0627\u0628\u200c\u062c\u06cc\u0631"
    ],
    "name:msa_x_preferred":[
        "Gur Abjir"
    ],
    "name:ukr_x_preferred":[
        "\u0490\u0443\u0440-\u0410\u0431\u0434\u0436\u0456\u0440"
    ],
    "name:und_x_variant":[
        "Gurabir",
        "Goorab Jir"
    ],
    "wof:name":"Gurabjir-e Sahra",
    "wof:placetype":"locality"
},
  "geometry": {"coordinates":[49.63109,37.44555],"type":"Point"}
}