{
  "type": "Feature",
  "properties": {
    "gn:admin1_code":"5.0",
    "gn:asciiname":"Jujaq",
    "gn:country_code":"IR",
    "gn:dem":2162,
    "gn:feature_class":"P",
    "gn:feature_code":"PPL",
    "gn:name":"J\u016bjaq",
    "gn:population":0,
    "gn:timezone":"Asia/Tehran",
    "iso:country":"IR",
    "name:fas_x_preferred":[
        "\u062c\u0648\u062c\u0642"
    ],
    "name:und_x_variant":[
        "J\u016bjaq"
    ],
    "wof:name":"Jujaq",
    "wof:placetype":"locality"
},
  "geometry": {"coordinates":[50.78916,31.20637],"type":"Point"}
}