{
  "type": "Feature",
  "properties": {
    "gn:admin1_code":"29",
    "gn:asciiname":"Mogh Ahmadi",
    "gn:country_code":"IR",
    "gn:dem":717,
    "gn:feature_class":"P",
    "gn:feature_code":"PPL",
    "gn:name":"Mogh A\u1e29mad\u012b",
    "gn:population":0,
    "gn:timezone":"Asia/Tehran",
    "iso:country":"IR",
    "name:fas_x_preferred":[
        "\u0645\u063a \u0627\u062d\u0645\u062f\u06cc"
    ],
    "name:fas_x_variant":[
        "Mogh-e A\u1e29mad\u012b",
        "Mogh A\u1e29mad\u012b"
    ],
    "wof:name":"Mogh Ahmadi",
    "wof:placetype":"locality"
},
  "geometry": {"coordinates":[57.7134,27.6088],"type":"Point"}
}