{
  "type": "Feature",
  "properties": {
    "gn:admin1_code":"4.0",
    "gn:asciiname":"Dizuk",
    "gn:country_code":"IR",
    "gn:dem":1332,
    "gn:feature_class":"P",
    "gn:feature_code":"PPL",
    "gn:name":"D\u012bz\u016bk",
    "gn:population":0,
    "gn:timezone":"Asia/Tehran",
    "iso:country":"IR",
    "name:fas_x_preferred":[
        "D\u012bz\u016bk"
    ],
    "name:fas_x_variant":[
        "\u062f\u06cc\u0632\u0648\u06a9"
    ],
    "name:und_x_variant":[
        "Dezuk",
        "D\u012bzak",
        "Dazuk",
        "D\u012bzok"
    ],
    "wof:name":"Dizuk",
    "wof:placetype":"locality"
},
  "geometry": {"coordinates":[61.21239,28.92195],"type":"Point"}
}