{
  "type": "Feature",
  "properties": {
    "gn:admin1_code":"35.0",
    "gn:asciiname":"Shahrak-e Asadi",
    "gn:country_code":"IR",
    "gn:dem":-24,
    "gn:feature_class":"P",
    "gn:feature_code":"PPL",
    "gn:name":"Shahrak-e Asad\u012b",
    "gn:population":0,
    "gn:timezone":"Asia/Tehran",
    "iso:country":"IR",
    "name:fas_x_preferred":[
        "Shahrak-e Asad\u012b"
    ],
    "name:fas_x_variant":[
        "\u0634\u0647\u0631\u06a9 \u0627\u0633\u062f\u06cc"
    ],
    "wof:name":"Shahrak-e Asadi",
    "wof:placetype":"locality"
},
  "geometry": {"coordinates":[52.52495,36.67904],"type":"Point"}
}