{
  "type": "Feature",
  "properties": {
    "gn:admin1_code":"15",
    "gn:asciiname":"Tall-e Siasat",
    "gn:country_code":"IR",
    "gn:dem":83,
    "gn:feature_class":"P",
    "gn:feature_code":"PPL",
    "gn:name":"Tall-e S\u012b\u0101sat",
    "gn:population":0,
    "gn:timezone":"Asia/Tehran",
    "iso:country":"IR",
    "name:azb_x_preferred":[
        "\u062a\u0644 \u0633\u06cc\u0627\u0633\u062a(\u0628\u0647\u0628\u0647\u0627\u0646)"
    ],
    "name:ceb_x_preferred":[
        "Tol S\u012b\u0101sat"
    ],
    "name:fas_x_preferred":[
        "\u062a\u0644 \u0633\u06cc\u0627\u0633\u062a"
    ],
    "name:fas_x_variant":[
        "Tol S\u012b\u0101sat",
        "\u062a\u0644\u200c\u0633\u06cc\u0627\u0633\u062a"
    ],
    "name:swe_x_preferred":[
        "Tol S\u012b\u0101sat"
    ],
    "name:und_x_variant":[
        "Tall-e S\u012b\u0101sat"
    ],
    "wof:name":"Tall-e Siasat",
    "wof:placetype":"locality"
},
  "geometry": {"coordinates":[49.95046,30.44087],"type":"Point"}
}