{
  "type": "Feature",
  "properties": {
    "gn:admin1_code":"8",
    "gn:asciiname":"Salak Mo`allem",
    "gn:country_code":"IR",
    "gn:dem":132,
    "gn:feature_class":"P",
    "gn:feature_code":"PPL",
    "gn:name":"S\u0101lak Mo\u2018allem",
    "gn:population":0,
    "gn:timezone":"Asia/Tehran",
    "iso:country":"IR",
    "name:fas_x_preferred":[
        "S\u0101lek Mo\u2018allem"
    ],
    "name:fas_x_variant":[
        "\u0633\u0627\u0644\u06a9 \u0645\u0639\u0644\u0645"
    ],
    "name:und_x_variant":[
        "S\u0101lak Mo\u2018allem"
    ],
    "wof:name":"Salak Mo`allem",
    "wof:placetype":"locality"
},
  "geometry": {"coordinates":[49.31529000000001,37.10901],"type":"Point"}
}