{
  "type": "Feature",
  "properties": {
    "gn:admin1_code":"35.0",
    "gn:asciiname":"Beramsar",
    "gn:country_code":"IR",
    "gn:dem":-5,
    "gn:feature_class":"P",
    "gn:feature_code":"PPL",
    "gn:name":"Ber\u0101msar",
    "gn:population":0,
    "gn:timezone":"Asia/Tehran",
    "iso:country":"IR",
    "name:ceb_x_preferred":[
        "Ber\u0101msar"
    ],
    "name:fas_x_preferred":[
        "Ber\u0101msar"
    ],
    "name:fas_x_variant":[
        "\u0628\u0631\u0627\u0645\u0633\u0631"
    ],
    "name:swe_x_preferred":[
        "Ber\u0101msar"
    ],
    "wof:name":"Beramsar",
    "wof:placetype":"locality"
},
  "geometry": {"coordinates":[50.80956,36.8327],"type":"Point"}
}