{
  "type": "Feature",
  "properties": {
    "gn:admin1_code":"43.0",
    "gn:asciiname":"Qahremanabad",
    "gn:country_code":"IR",
    "gn:dem":1272,
    "gn:feature_class":"P",
    "gn:feature_code":"PPL",
    "gn:name":"Qahrem\u0101n\u0101b\u0101d",
    "gn:population":0,
    "gn:timezone":"Asia/Tehran",
    "iso:country":"IR",
    "name:ara_x_preferred":[
        "\u0642\u0647\u0631\u0645\u0627\u0646\u200c\u0622\u0628\u0627\u062f"
    ],
    "name:ceb_x_preferred":[
        "Qahrem\u0101n\u0101b\u0101d"
    ],
    "name:fas_x_preferred":[
        "Qahrem\u0101n\u0101b\u0101d"
    ],
    "name:fas_x_variant":[
        "\u0642\u0647\u0631\u0645\u0627\u0646 \u0622\u0628\u0627\u062f",
        "\u0642\u0647\u0631\u0645\u0627\u0646\u200c\u0622\u0628\u0627\u062f"
    ],
    "name:swe_x_preferred":[
        "Qahrem\u0101n\u0101b\u0101d"
    ],
    "wof:name":"Qahremanabad",
    "wof:placetype":"locality"
},
  "geometry": {"coordinates":[57.60756,36.94204000000001],"type":"Point"}
}