{
  "type": "Feature",
  "properties": {
    "gn:admin1_code":"15.0",
    "gn:asciiname":"Sar Kandeh-ye Pa'in",
    "gn:country_code":"IR",
    "gn:dem":946,
    "gn:feature_class":"P",
    "gn:feature_code":"PPL",
    "gn:name":"Sar Kandeh-ye P\u0101\u2019\u012bn",
    "gn:population":0,
    "gn:timezone":"Asia/Tehran",
    "iso:country":"IR",
    "name:fas_x_preferred":[
        "\u0633\u0631 \u06a9\u0646\u062f\u0647"
    ],
    "name:fas_x_variant":[
        "\u0633\u0631 \u06a9\u0646\u062f\u0647 \u067e\u0627\u0626\u06cc\u0646"
    ],
    "name:und_x_variant":[
        "Sar Kandeh",
        "Sar Kandeh-ye P\u0101\u2019\u012bn"
    ],
    "wof:name":"Sar Kandeh-ye Pa'in",
    "wof:placetype":"locality"
},
  "geometry": {"coordinates":[49.58759000000001,32.28677],"type":"Point"}
}