{
  "type": "Feature",
  "properties": {
    "gn:admin1_code":"15",
    "gn:asciiname":"Kamp-e Baghbuya",
    "gn:cc2":"IR",
    "gn:country_code":"IR",
    "gn:dem":169,
    "gn:feature_class":"P",
    "gn:feature_code":"PPL",
    "gn:name":"Kamp-e B\u0101ghb\u016by\u0101",
    "gn:population":0,
    "gn:timezone":"Asia/Tehran",
    "iso:country":"IR",
    "name:fas_x_preferred":[
        "Kamp-e B\u0101ghb\u016by\u0101"
    ],
    "name:und_x_variant":[
        "Kamp B\u0101ghb\u016bn\u0101"
    ],
    "wof:name":"Kamp-e Baghbuya",
    "wof:placetype":"locality"
},
  "geometry": {"coordinates":[49.69722,30.81167],"type":"Point"}
}