{
  "type": "Feature",
  "properties": {
    "gn:admin1_code":"7",
    "gn:asciiname":"`Aliabad",
    "gn:country_code":"IR",
    "gn:dem":1589,
    "gn:feature_class":"P",
    "gn:feature_code":"PPL",
    "gn:name":"\u2018Al\u012b\u0101b\u0101d",
    "gn:population":0,
    "gn:timezone":"Asia/Tehran",
    "iso:country":"IR",
    "name:fas_x_preferred":[
        "Kh\u0101nb\u0101z"
    ],
    "name:fas_x_variant":[
        "\u0639\u0644\u06cc \u0622\u0628\u0627\u062f",
        "\u062a\u0644\u0645\u0628\u0647 \u062e\u0627\u0646 \u0628\u0627\u0632 \u06a9\u0631\u0648\u0646\u06cc",
        "\u0686\u0627\u0647 \u0636\u06cc\u063a\u0645\u06cc"
    ],
    "name:und_x_variant":[
        "Tolombeh-ye Kh\u0101nb\u0101z",
        "\u2018Al\u012b\u0101b\u0101d",
        "Tolombeh-ye Kh\u0101nb\u0101z Kor\u016bn\u012b",
        "Ch\u0101h \u1e94eygham\u012b"
    ],
    "wof:name":"`Aliabad",
    "wof:placetype":"locality"
},
  "geometry": {"coordinates":[54.12654000000001,29.5172],"type":"Point"}
}