{
  "type": "Feature",
  "properties": {
    "gn:admin1_code":"33",
    "gn:asciiname":"Khameneh",
    "gn:country_code":"IR",
    "gn:dem":1522,
    "gn:feature_class":"P",
    "gn:feature_code":"PPL",
    "gn:name":"Kh\u0101meneh",
    "gn:population":0,
    "gn:timezone":"Asia/Tehran",
    "iso:country":"IR",
    "name:ara_x_preferred":[
        "\u062e\u0627\u0645\u0646\u0647"
    ],
    "name:azb_x_preferred":[
        "\u062e\u0627\u0645\u0646\u0647"
    ],
    "name:aze_x_preferred":[
        "Xamn\u0259"
    ],
    "name:deu_x_preferred":[
        "Chameneh"
    ],
    "name:fas_x_preferred":[
        "\u062e\u0627\u0645\u0646\u0650\u0647"
    ],
    "name:fas_x_variant":[
        "\u062e\u0627\u0645\u0646\u0647",
        "\u062e\u064e\u0645\u064e\u0646\u0650\u0647",
        "Kh\u0101meneh",
        "\u062e\u0627\u0645\u0650\u0646\u0650\u0647"
    ],
    "name:mlg_x_preferred":[
        "Khamaneh"
    ],
    "name:msa_x_preferred":[
        "Khamaneh"
    ],
    "name:pol_x_preferred":[
        "Chamene"
    ],
    "name:rus_x_preferred":[
        "\u0425\u0430\u043c\u0435\u043d\u0435"
    ],
    "name:tur_x_preferred":[
        "Hamene"
    ],
    "name:ukr_x_preferred":[
        "\u0425\u0430\u043c\u0435\u043d\u0435"
    ],
    "name:und_x_variant":[
        "Khumla",
        "Khumna",
        "Kh\u0101mneh"
    ],
    "name:urd_x_preferred":[
        "\u062e\u0627\u0645\u0646\u06c1"
    ],
    "wof:name":"Khameneh",
    "wof:placetype":"locality"
},
  "geometry": {"coordinates":[45.6309,38.1934],"type":"Point"}
}