{
  "type": "Feature",
  "properties": {
    "gn:admin1_code":"16",
    "gn:asciiname":"Qablantu",
    "gn:country_code":"IR",
    "gn:dem":1746,
    "gn:feature_class":"P",
    "gn:feature_code":"PPL",
    "gn:name":"Qabl\u0101nt\u016b",
    "gn:population":0,
    "gn:timezone":"Asia/Tehran",
    "iso:country":"IR",
    "name:ara_x_preferred":[
        "\u0642\u0628\u0644\u0627\u0646\u062a\u0648"
    ],
    "name:ceb_x_preferred":[
        "Qapl\u0101n T\u016b"
    ],
    "name:ckb_x_preferred":[
        "\u0642\u06d5\u067e\u06b5\u0627\u0646\u062a\u0648\u0648"
    ],
    "name:fas_x_preferred":[
        "\u0642\u067e\u0644\u0627\u0646 \u062a\u0648"
    ],
    "name:fas_x_variant":[
        "Qapl\u0101nt\u016b",
        "\u0642\u067e\u0644\u0627\u0646\u062a\u0648",
        "Qapl\u0101n T\u016b",
        "\u0642\u0628\u0644\u0627\u0646\u062a\u0648"
    ],
    "name:kur_x_preferred":[
        "Qeplant\u00fb"
    ],
    "name:swe_x_preferred":[
        "Qapl\u0101n T\u016b"
    ],
    "name:und_x_variant":[
        "Qabl\u0101nt\u016b"
    ],
    "wof:name":"Qablantu",
    "wof:placetype":"locality"
},
  "geometry": {"coordinates":[46.72501,36.24003],"type":"Point"}
}