{
  "type": "Feature",
  "properties": {
    "gn:admin1_code":"28",
    "gn:asciiname":"Qal`eh-ye `Ajam",
    "gn:country_code":"IR",
    "gn:dem":2201,
    "gn:feature_class":"P",
    "gn:feature_code":"PPL",
    "gn:name":"Qal\u2018eh-ye \u2018Ajam",
    "gn:population":0,
    "gn:timezone":"Asia/Tehran",
    "iso:country":"IR",
    "name:fas_x_preferred":[
        "Qal\u2018eh-ye \u2018Ajam"
    ],
    "name:fas_x_variant":[
        "\u0642\u0644\u0639\u0647 \u0639\u062c\u0645"
    ],
    "wof:name":"Qal`eh-ye `Ajam",
    "wof:placetype":"locality"
},
  "geometry": {"coordinates":[50.39062,32.54969000000001],"type":"Point"}
}