{
  "type": "Feature",
  "properties": {
    "gn:admin1_code":"40",
    "gn:asciiname":"Kalateh-ye Lushu",
    "gn:country_code":"IR",
    "gn:dem":1330,
    "gn:feature_class":"P",
    "gn:feature_code":"PPL",
    "gn:name":"Kal\u0101teh-ye L\u016bsh\u016b",
    "gn:population":0,
    "gn:timezone":"Asia/Tehran",
    "iso:country":"IR",
    "name:fas_x_preferred":[
        "Senjed\u016b"
    ],
    "name:fas_x_variant":[
        "\u0633\u0646\u062c\u062f\u0648",
        "\u06a9\u0644\u0627\u062a\u0647 \u0644\u0648\u0634\u0648",
        "\u0644\u0648\u0634\u0627\u0628"
    ],
    "name:und_x_variant":[
        "\u0633\u0646\u062c\u062f\u0648",
        "Kal\u0101teh-ye L\u016bsh\u016b",
        "L\u016bsh\u0101b"
    ],
    "wof:name":"Kalateh-ye Lushu",
    "wof:placetype":"locality"
},
  "geometry": {"coordinates":[57.26769,34.87611],"type":"Point"}
}