{
  "type": "Feature",
  "properties": {
    "gn:admin1_code":"4.0",
    "gn:asciiname":"Feyzabad",
    "gn:country_code":"IR",
    "gn:dem":1608,
    "gn:feature_class":"P",
    "gn:feature_code":"PPL",
    "gn:name":"Fey\u1e95\u0101b\u0101d",
    "gn:population":0,
    "gn:timezone":"Asia/Tehran",
    "iso:country":"IR",
    "name:fas_x_preferred":[
        "\u0641\u06cc\u0636 \u0622\u0628\u0627\u062f"
    ],
    "name:fas_x_variant":[
        "\u0631\u062d\u06cc\u0645 \u0622\u0628\u0627\u062f \u0644\u0648\u0686\u0627\u0646",
        "Fey\u1e95\u0101b\u0101d",
        "Ra\u1e29\u012bm\u0101b\u0101d-e L\u016bch\u0101n"
    ],
    "wof:name":"Feyzabad",
    "wof:placetype":"locality"
},
  "geometry": {"coordinates":[60.754,29.3121],"type":"Point"}
}