{
  "type": "Feature",
  "properties": {
    "gn:admin1_code":"4",
    "gn:asciiname":"Pak",
    "gn:country_code":"IR",
    "gn:dem":1113,
    "gn:feature_class":"P",
    "gn:feature_code":"PPL",
    "gn:name":"P\u0101k",
    "gn:population":0,
    "gn:timezone":"Asia/Tehran",
    "iso:country":"IR",
    "name:fas_x_preferred":[
        "\u067e\u0627\u06a9"
    ],
    "name:fas_x_variant":[
        "P\u0101k"
    ],
    "wof:name":"Pak",
    "wof:placetype":"locality"
},
  "geometry": {"coordinates":[59.55636,28.02034],"type":"Point"}
}