{
  "type": "Feature",
  "properties": {
    "gn:admin1_code":"5",
    "gn:asciiname":"Kalgah",
    "gn:country_code":"IR",
    "gn:dem":2078,
    "gn:feature_class":"P",
    "gn:feature_code":"PPL",
    "gn:name":"Kalg\u0101h",
    "gn:population":0,
    "gn:timezone":"Asia/Tehran",
    "iso:country":"IR",
    "name:fas_x_preferred":[
        "\u0643\u064e\u0644\u06af\u0627\u0647"
    ],
    "name:fas_x_variant":[
        "Kalg\u0101h"
    ],
    "wof:name":"Kalgah",
    "wof:placetype":"locality"
},
  "geometry": {"coordinates":[51.64111,30.61722],"type":"Point"}
}