{
  "type": "Feature",
  "properties": {
    "gn:admin1_code":"4",
    "gn:asciiname":"Gonbad-e Qasemabad",
    "gn:country_code":"IR",
    "gn:dem":380,
    "gn:feature_class":"P",
    "gn:feature_code":"PPL",
    "gn:name":"Gonbad-e Q\u0101sem\u0101b\u0101d",
    "gn:population":0,
    "gn:timezone":"Asia/Tehran",
    "iso:country":"IR",
    "name:ara_x_preferred":[
        "\u0642\u0627\u0633\u0645\u200c\u0622\u0628\u0627\u062f \u063a\u0646\u0628\u062f"
    ],
    "name:fas_x_preferred":[
        "\u06af\u0646\u0628\u062f \u0642\u0627\u0633\u0645 \u0622\u0628\u0627\u062f"
    ],
    "name:fas_x_variant":[
        "Gonbad-e Q\u0101sem\u0101b\u0101d",
        "\u0642\u0627\u0633\u0645\u200c\u0622\u0628\u0627\u062f \u06af\u0646\u0628\u062f"
    ],
    "wof:name":"Gonbad-e Qasemabad",
    "wof:placetype":"locality"
},
  "geometry": {"coordinates":[59.15541999999999,27.67658],"type":"Point"}
}