{
  "type": "Feature",
  "properties": {
    "gn:admin1_code":"4.0",
    "gn:asciiname":"Shusheha'i",
    "gn:country_code":"IR",
    "gn:dem":1705,
    "gn:feature_class":"P",
    "gn:feature_code":"PPL",
    "gn:name":"Sh\u016bsheh\u0101\u2019\u012b",
    "gn:population":0,
    "gn:timezone":"Asia/Tehran",
    "iso:country":"IR",
    "name:fas_x_preferred":[
        "\u0634\u0648\u0634\u0647 \u0627\u06cc\u06cc"
    ],
    "name:und_x_variant":[
        "Sh\u016bsheh\u0101\u2019\u012b"
    ],
    "wof:name":"Shusheha'i",
    "wof:placetype":"locality"
},
  "geometry": {"coordinates":[61.87722,27.91454],"type":"Point"}
}