{
  "type": "Feature",
  "properties": {
    "gn:admin1_code":"22",
    "gn:asciiname":"Damigaz-e Jonubi",
    "gn:country_code":"IR",
    "gn:dem":8,
    "gn:feature_class":"P",
    "gn:feature_code":"PPL",
    "gn:name":"Dam\u012bgaz-e Jon\u016bb\u012b",
    "gn:population":0,
    "gn:timezone":"Asia/Tehran",
    "iso:country":"IR",
    "name:fas_x_preferred":[
        "\u062f\u0645\u064a\u06af\u064e\u0632 \u062c\u0646\u0648\u0628\u06cc"
    ],
    "name:fas_x_variant":[
        "Dam\u012bgaz-e Jon\u016bb\u012b"
    ],
    "wof:name":"Damigaz-e Jonubi",
    "wof:placetype":"locality"
},
  "geometry": {"coordinates":[51.69457,27.84069],"type":"Point"}
}