{
  "type": "Feature",
  "properties": {
    "gn:admin1_code":"29.0",
    "gn:asciiname":"Mazra`eh-ye Shahid Nazari",
    "gn:country_code":"IR",
    "gn:dem":2823,
    "gn:feature_class":"P",
    "gn:feature_code":"PPL",
    "gn:name":"Mazra\u2018eh-ye Shah\u012bd Naz\u0327ar\u012b",
    "gn:population":0,
    "gn:timezone":"Asia/Tehran",
    "iso:country":"IR",
    "name:fas_x_preferred":[
        "Sh\u0101h N\u0101z\u0327ar\u012b"
    ],
    "name:fas_x_variant":[
        "\u0645\u0632\u0631\u0639\u0647 \u0634\u0647\u064a\u062f \u0646\u0638\u0631\u06cc",
        "\u0628\u0627\u063a \u0646\u0638\u0631\u06cc",
        "\u0634\u0627\u0647 \u0646\u0638\u0631\u06cc"
    ],
    "name:und_x_variant":[
        "Mazra\u2018eh-ye Shah\u012bd Naz\u0327ar\u012b",
        "B\u0101gh-e Naz\u0327ar\u012b",
        "Sh\u0101h Naz\u0327ar\u012b"
    ],
    "wof:name":"Mazra`eh-ye Shahid Nazari",
    "wof:placetype":"locality"
},
  "geometry": {"coordinates":[57.37711,29.14603],"type":"Point"}
}