{
  "type": "Feature",
  "properties": {
    "gn:admin1_code":"5",
    "gn:asciiname":"Hajji `Abbas`ali Khani",
    "gn:country_code":"IR",
    "gn:dem":2259,
    "gn:feature_class":"P",
    "gn:feature_code":"PPL",
    "gn:name":"\u1e28\u0101jj\u012b \u2018Abb\u0101s\u2018al\u012b Kh\u0101n\u012b",
    "gn:population":0,
    "gn:timezone":"Asia/Tehran",
    "iso:country":"IR",
    "name:fas_x_preferred":[
        "\u1e28\u0101jj\u012bkh\u0101n\u012b"
    ],
    "name:fas_x_variant":[
        "\u062d\u0627\u062c\u06cc \u0639\u0628\u0627\u0633\u0639\u0644\u06cc \u062e\u0627\u0646\u06cc",
        "\u0639\u0644\u06cc \u0622\u0628\u0627\u062f"
    ],
    "name:und_x_variant":[
        "\u1e28\u0101jj\u012b \u2018Abb\u0101s\u2018al\u012b Kh\u0101n\u012b",
        "\u2018Al\u012b\u0101b\u0101d"
    ],
    "wof:name":"Hajji `Abbas`ali Khani",
    "wof:placetype":"locality"
},
  "geometry": {"coordinates":[51.79345,30.62586],"type":"Point"}
}