{
  "type": "Feature",
  "properties": {
    "gn:admin1_code":"33",
    "gn:asciiname":"Palchoqlu",
    "gn:country_code":"IR",
    "gn:dem":1914,
    "gn:feature_class":"P",
    "gn:feature_code":"PPL",
    "gn:name":"P\u0101lchoql\u016b",
    "gn:population":0,
    "gn:timezone":"Asia/Tehran",
    "iso:country":"IR",
    "name:fas_x_preferred":[
        "\u067e\u0627\u0644\u0686\u0642\u0644\u0648"
    ],
    "name:fas_x_variant":[
        "P\u0101lchoql\u016b"
    ],
    "wof:name":"Palchoqlu",
    "wof:placetype":"locality"
},
  "geometry": {"coordinates":[47.0742,37.1326],"type":"Point"}
}