{
  "type": "Feature",
  "properties": {
    "gn:admin1_code":"23",
    "gn:asciiname":"Hajji Besat Bak",
    "gn:country_code":"IR",
    "gn:dem":1019,
    "gn:feature_class":"P",
    "gn:feature_code":"PPL",
    "gn:name":"\u1e28\u0101jj\u012b Besa\u0163 Bak",
    "gn:population":0,
    "gn:timezone":"Asia/Tehran",
    "iso:country":"IR",
    "name:fas_x_preferred":[
        "\u1e28\u0101jj\u012b Besa\u0163 Bak"
    ],
    "wof:name":"Hajji Besat Bak",
    "wof:placetype":"locality"
},
  "geometry": {"coordinates":[47.13333,33.48333],"type":"Point"}
}