{
  "type": "Feature",
  "properties": {
    "gn:admin1_code":"16.0",
    "gn:asciiname":"Ya`qubabad",
    "gn:country_code":"IR",
    "gn:dem":1491,
    "gn:feature_class":"P",
    "gn:feature_code":"PPL",
    "gn:name":"Ya\u2018q\u016bb\u0101b\u0101d",
    "gn:population":0,
    "gn:timezone":"Asia/Tehran",
    "iso:country":"IR",
    "name:fas_x_preferred":[
        "\u06cc\u0639\u0642\u0648\u0628 \u0622\u0628\u0627\u062f"
    ],
    "name:fas_x_variant":[
        "Ya\u2018q\u016bb\u0101b\u0101d"
    ],
    "wof:name":"Ya`qubabad",
    "wof:placetype":"locality"
},
  "geometry": {"coordinates":[45.7318,36.0337],"type":"Point"}
}