{
  "type": "Feature",
  "properties": {
    "gn:admin1_code":"11",
    "gn:asciiname":"Dowfuri",
    "gn:country_code":"IR",
    "gn:dem":16,
    "gn:feature_class":"P",
    "gn:feature_code":"PPL",
    "gn:name":"Dowf\u016br\u012b",
    "gn:population":0,
    "gn:timezone":"Asia/Tehran",
    "iso:country":"IR",
    "name:fas_x_preferred":[
        "\u0643\u0627\u0628\u0644\u06cc"
    ],
    "name:fas_x_variant":[
        "K\u0101bol\u012b",
        "\u062f\u0648\u0641\u0648\u0631\u06cc",
        "\u062f\u0641\u0627\u0631\u06cc"
    ],
    "name:und_x_variant":[
        "Dowf\u016br\u012b",
        "K\u0101bel\u012b",
        "Daf\u0101r\u012b"
    ],
    "wof:name":"Dowfuri",
    "wof:placetype":"locality"
},
  "geometry": {"coordinates":[56.2077,26.9429],"type":"Point"}
}