{
  "type": "Feature",
  "properties": {
    "gn:admin1_code":"16",
    "gn:asciiname":"Yapeshkhan",
    "gn:country_code":"IR",
    "gn:dem":1461,
    "gn:feature_class":"P",
    "gn:feature_code":"PPL",
    "gn:name":"Y\u0101peshkh\u0101n",
    "gn:population":0,
    "gn:timezone":"Asia/Tehran",
    "iso:country":"IR",
    "name:fas_x_preferred":[
        "\u067e\u0627\u06cc\u0634 \u062e\u0627\u0646"
    ],
    "name:fas_x_variant":[
        "Y\u0101pesh Kh\u0101n",
        "P\u0101yesh Kh\u0101n",
        "\u06cc\u0627\u067e\u0634\u062e\u0627\u0646"
    ],
    "name:und_x_variant":[
        "Y\u0101peshkh\u0101n"
    ],
    "wof:name":"Yapeshkhan",
    "wof:placetype":"locality"
},
  "geometry": {"coordinates":[46.58562,36.29155],"type":"Point"}
}