{
  "type": "Feature",
  "properties": {
    "gn:admin1_code":"1",
    "gn:asciiname":"Gubeh",
    "gn:country_code":"IR",
    "gn:dem":2357,
    "gn:feature_class":"P",
    "gn:feature_code":"PPL",
    "gn:name":"G\u016bbeh",
    "gn:population":0,
    "gn:timezone":"Asia/Tehran",
    "iso:country":"IR",
    "name:aze_x_preferred":[
        "G\u00fcb\u0259"
    ],
    "name:ceb_x_preferred":[
        "G\u016bbeh"
    ],
    "name:fas_x_preferred":[
        "G\u016bbeh"
    ],
    "name:fas_x_variant":[
        "\u06af\u0648\u0628\u0647"
    ],
    "name:msa_x_preferred":[
        "Gubeh"
    ],
    "name:swe_x_preferred":[
        "G\u016bbeh"
    ],
    "wof:name":"Gubeh",
    "wof:placetype":"locality"
},
  "geometry": {"coordinates":[44.61667,38.31667],"type":"Point"}
}