{
  "type": "Feature",
  "properties": {
    "gn:admin1_code":"29",
    "gn:asciiname":"Sar Meydan",
    "gn:country_code":"IR",
    "gn:dem":703,
    "gn:feature_class":"P",
    "gn:feature_code":"PPL",
    "gn:name":"Sar Meyd\u0101n",
    "gn:population":0,
    "gn:timezone":"Asia/Tehran",
    "iso:country":"IR",
    "name:fas_x_preferred":[
        "\u0633\u0631 \u0645\u06cc\u062f\u0627\u0646"
    ],
    "name:fas_x_variant":[
        "Sar Meyd\u0101n",
        "\u0627\u0633\u0644\u0627\u0645 \u0622\u0628\u0627\u062f \u0633\u0631 \u0645\u06cc\u062f\u0627\u0646"
    ],
    "name:und_x_variant":[
        "Esl\u0101m\u0101b\u0101d Sar Meyd\u0101n"
    ],
    "wof:name":"Sar Meydan",
    "wof:placetype":"locality"
},
  "geometry": {"coordinates":[58.70736,26.90408],"type":"Point"}
}