{
  "type": "Feature",
  "properties": {
    "gn:admin1_code":"23.0",
    "gn:asciiname":"Mantaqeh-ye Dar Hava",
    "gn:country_code":"IR",
    "gn:dem":1734,
    "gn:feature_class":"P",
    "gn:feature_code":"PPL",
    "gn:name":"Man\u0163aqeh-ye D\u0101r Hav\u0101",
    "gn:population":0,
    "gn:timezone":"Asia/Tehran",
    "iso:country":"IR",
    "name:fas_x_preferred":[
        "\u0645\u0646\u0637\u0642\u0647 \u062f\u0627\u0631 \u0647\u0648\u0627"
    ],
    "name:und_x_variant":[
        "Man\u0163aqeh-ye D\u0101r Hav\u0101"
    ],
    "wof:name":"Mantaqeh-ye Dar Hava",
    "wof:placetype":"locality"
},
  "geometry": {"coordinates":[48.70127,33.27146],"type":"Point"}
}