{
  "type": "Feature",
  "properties": {
    "gn:admin1_code":"28.0",
    "gn:asciiname":"Kand-e Qabrestan",
    "gn:country_code":"IR",
    "gn:dem":2455,
    "gn:feature_class":"P",
    "gn:feature_code":"PPL",
    "gn:name":"Kand-e Qabrest\u0101n",
    "gn:population":0,
    "gn:timezone":"Asia/Tehran",
    "iso:country":"IR",
    "name:fas_x_preferred":[
        "\u06a9\u0646\u062f \u0642\u0628\u0631\u0633\u062a\u0627\u0646"
    ],
    "name:fas_x_variant":[
        "\u06a9\u0646\u062f\u0647 \u0642\u0628\u0631\u0633\u062a\u0627\u0646"
    ],
    "name:und_x_variant":[
        "Kand-e Qabrest\u0101n"
    ],
    "wof:name":"Kand-e Qabrestan",
    "wof:placetype":"locality"
},
  "geometry": {"coordinates":[51.65762,31.61606],"type":"Point"}
}