{
  "type": "Feature",
  "properties": {
    "gn:admin1_code":"4.0",
    "gn:asciiname":"Chah-e Abd ol Qader",
    "gn:country_code":"IR",
    "gn:dem":1165,
    "gn:feature_class":"P",
    "gn:feature_code":"PPL",
    "gn:name":"Ch\u0101h-e Abd ol Q\u0101der",
    "gn:population":0,
    "gn:timezone":"Asia/Tehran",
    "iso:country":"IR",
    "name:fas_x_preferred":[
        "\u0686\u0627\u0647 \u0645\u0644\u0651\u0627\u06a9"
    ],
    "name:fas_x_variant":[
        "Ch\u0101h-e Malek",
        "Ch\u0101h-e Mall\u0101k",
        "\u0686\u0627\u0647 \u0639\u0628\u062f \u0627\u0644\u0642\u0627\u062f\u0631"
    ],
    "name:und_x_variant":[
        "Ch\u0101h-e Abd ol Q\u0101der"
    ],
    "wof:name":"Chah-e Abd ol Qader",
    "wof:placetype":"locality"
},
  "geometry": {"coordinates":[61.8845,27.3237],"type":"Point"}
}