{
  "type": "Feature",
  "properties": {
    "gn:admin1_code":"1.0",
    "gn:asciiname":"Sa`idabad",
    "gn:country_code":"IR",
    "gn:dem":1445,
    "gn:feature_class":"P",
    "gn:feature_code":"PPL",
    "gn:name":"Sa\u2018\u012bd\u0101b\u0101d",
    "gn:population":0,
    "gn:timezone":"Asia/Tehran",
    "iso:country":"IR",
    "name:fas_x_preferred":[
        "\u0633\u0639\u06cc\u062f \u0622\u0628\u0627\u062f"
    ],
    "name:fas_x_variant":[
        "Sa\u2018\u012bd\u0101b\u0101d"
    ],
    "wof:name":"Sa`idabad",
    "wof:placetype":"locality"
},
  "geometry": {"coordinates":[45.4658,36.3445],"type":"Point"}
}