{
  "type": "Feature",
  "properties": {
    "gn:admin1_code":"13",
    "gn:asciiname":"Qal`eh Zanjir",
    "gn:country_code":"IR",
    "gn:dem":1512,
    "gn:feature_class":"P",
    "gn:feature_code":"PPL",
    "gn:name":"Qal\u2018eh Zanj\u012br",
    "gn:population":0,
    "gn:timezone":"Asia/Tehran",
    "iso:country":"IR",
    "name:fas_x_preferred":[
        "\u0642\u0644\u0639\u0647 \u0632\u0646\u062c\u06cc\u0631"
    ],
    "name:fas_x_variant":[
        "Qal\u2018eh Zanj\u012br-e Sofl\u00e1",
        "Qal\u2018eh Zanj\u012br"
    ],
    "wof:name":"Qal`eh Zanjir",
    "wof:placetype":"locality"
},
  "geometry": {"coordinates":[46.2143,34.598],"type":"Point"}
}