{
  "type": "Feature",
  "properties": {
    "iso:country":"IR",
    "name:fas_x_preferred":[
        "\u0635\u064e\u062f\u0631 \u0622\u0628\u0627\u062f"
    ],
    "name:fas_x_variant":[
        "\u0633\u064e\u062f\u0631\u0650 \u0627\u064e\u0628\u064e\u062f \u0627\u064e\u0631\u062f\u064e\u0643\u064e\u0646",
        "\u0635\u064e\u062f\u0631\u0627\u0628\u0627\u062f\u0650 \u0627\u064e\u0631\u062f\u064e\u0643\u0627\u0646",
        "\u015eadr\u0101b\u0101d",
        "\u0635\u062f\u0631\u0622\u0628\u0627\u062f",
        "\u015eadr\u0101b\u0101d-e Ardak\u0101n"
    ],
    "qs:gn_country":"IR",
    "qs:gn_fcode":"PPLX",
    "qs:gn_pop":0,
    "qs:name":"Sadre Abad Ardakan",
    "qs:name_adm0":"Iran",
    "qs:name_adm1":"Yazd",
    "qs:photos":3,
    "qs:photos_1k":1,
    "qs:photos_9k":1,
    "qs:photos_9r":1,
    "qs:photos_all":3,
    "qs:photos_sr":1,
    "qs:placetype":"Town",
    "qs:pop_sr":"0",
    "qs:woe_adm0":23424851,
    "wof:name":"Sadre Abad Ardakan",
    "wof:placetype":"locality"
},
  "geometry": {"coordinates":[54.00559,32.31512],"type":"Point"}
}