{
  "type": "Feature",
  "properties": {
    "gn:admin1_code":"32",
    "gn:asciiname":"Nigejeh",
    "gn:country_code":"IR",
    "gn:dem":1324,
    "gn:feature_class":"P",
    "gn:feature_code":"PPL",
    "gn:name":"N\u012bgejeh",
    "gn:population":0,
    "gn:timezone":"Asia/Tehran",
    "iso:country":"IR",
    "name:fas_x_preferred":[
        "\u064a\u0650\u0646\u06af\u0650\u062c\u0650\u0647"
    ],
    "name:fas_x_variant":[
        "\u0646\u06cc\u06af\u062c\u0647",
        "N\u012bgejeh"
    ],
    "name:und_x_variant":[
        "Yengejeh"
    ],
    "wof:name":"Nigejeh",
    "wof:placetype":"locality"
},
  "geometry": {"coordinates":[48.4764,38.3659],"type":"Point"}
}