{
  "type": "Feature",
  "properties": {
    "gn:admin1_code":"29",
    "gn:asciiname":"Gowd-e Sorkh",
    "gn:country_code":"IR",
    "gn:dem":2403,
    "gn:feature_class":"P",
    "gn:feature_code":"PPL",
    "gn:name":"Gowd-e Sorkh",
    "gn:population":0,
    "gn:timezone":"Asia/Tehran",
    "iso:country":"IR",
    "name:ara_x_preferred":[
        "\u063a\u0648\u062f \u0633\u0631\u062e"
    ],
    "name:fas_x_preferred":[
        "\u06af\u0648\u062f \u0633\u0631\u062e"
    ],
    "name:fas_x_variant":[
        "\u06af\u0648\u062f\u0633\u0631\u062e"
    ],
    "wof:name":"Gowd-e Sorkh",
    "wof:placetype":"locality"
},
  "geometry": {"coordinates":[55.2173,30.4604],"type":"Point"}
}