{
  "type": "Feature",
  "properties": {
    "gn:admin1_code":"34",
    "gn:asciiname":"Band-e Amir",
    "gn:country_code":"IR",
    "gn:dem":1915,
    "gn:feature_class":"P",
    "gn:feature_code":"PPL",
    "gn:name":"Band-e Am\u012br",
    "gn:population":0,
    "gn:timezone":"Asia/Tehran",
    "iso:country":"IR",
    "name:fas_x_preferred":[
        "\u0628\u0646\u062f \u0627\u0645\u064a\u0631"
    ],
    "name:fas_x_variant":[
        "Band Am\u012br",
        "Band-e Am\u012br"
    ],
    "wof:name":"Band-e Amir",
    "wof:placetype":"locality"
},
  "geometry": {"coordinates":[50.0499,35.2697],"type":"Point"}
}