{
  "type": "Feature",
  "properties": {
    "gn:admin1_code":"26.0",
    "gn:asciiname":"Mavin",
    "gn:country_code":"IR",
    "gn:dem":1492,
    "gn:feature_class":"P",
    "gn:feature_code":"PPL",
    "gn:name":"Mav\u012bn",
    "gn:population":0,
    "gn:timezone":"Asia/Tehran",
    "iso:country":"IR",
    "name:fas_x_preferred":[
        "\u0645\u064e\u0648\u064a\u0646"
    ],
    "name:fas_x_variant":[
        "Mav\u012bn"
    ],
    "wof:name":"Mavin",
    "wof:placetype":"locality"
},
  "geometry": {"coordinates":[52.4975,35.52889000000001],"type":"Point"}
}