{
  "type": "Feature",
  "properties": {
    "gn:admin1_code":"5",
    "gn:asciiname":"Cheshmeh Chenar",
    "gn:country_code":"IR",
    "gn:dem":2207,
    "gn:feature_class":"P",
    "gn:feature_code":"PPL",
    "gn:name":"Cheshmeh Chen\u0101r",
    "gn:population":0,
    "gn:timezone":"Asia/Tehran",
    "iso:country":"IR",
    "name:fas_x_preferred":[
        "Cheshmeh Chen\u0101r"
    ],
    "name:fas_x_variant":[
        "\u0686\u0634\u0645\u0647 \u0686\u0646\u0627\u0631"
    ],
    "name:und_x_variant":[
        "\u0686\u0634\u0645\u0647 \u0686\u0646\u0627\u0631"
    ],
    "wof:name":"Cheshmeh Chenar",
    "wof:placetype":"locality"
},
  "geometry": {"coordinates":[51.63845,30.70598],"type":"Point"}
}