{
  "type": "Feature",
  "properties": {
    "gn:admin1_code":"1",
    "gn:asciiname":"Gol Sa`id",
    "gn:country_code":"IR",
    "gn:dem":2242,
    "gn:feature_class":"P",
    "gn:feature_code":"PPL",
    "gn:name":"Gol Sa\u2018\u012bd",
    "gn:population":0,
    "gn:timezone":"Asia/Tehran",
    "iso:country":"IR",
    "name:fas_x_preferred":[
        "\u06af\u0644 \u0633\u0639\u06cc\u062f"
    ],
    "name:fas_x_variant":[
        "\u06af\u064f\u0644 \u0633\u064e\u0639\u064a\u062f",
        "Gol Sa\u2018\u012bd"
    ],
    "wof:name":"Gol Sa`id",
    "wof:placetype":"locality"
},
  "geometry": {"coordinates":[44.333,39.2158],"type":"Point"}
}