{
  "type": "Feature",
  "properties": {
    "gn:admin1_code":"32",
    "gn:asciiname":"Tarazuj",
    "gn:country_code":"IR",
    "gn:dem":1914,
    "gn:feature_class":"P",
    "gn:feature_code":"PPL",
    "gn:name":"Tar\u0101z\u016bj",
    "gn:population":0,
    "gn:timezone":"Asia/Tehran",
    "iso:country":"IR",
    "name:fas_x_preferred":[
        "Tar\u0101z\u016bj"
    ],
    "name:fas_x_variant":[
        "\u062a\u0631\u0627\u0632\u0648\u062c"
    ],
    "name:und_x_variant":[
        "Tarazi"
    ],
    "wof:name":"Tarazuj",
    "wof:placetype":"locality"
},
  "geometry": {"coordinates":[48.46808,37.46838],"type":"Point"}
}