{
  "type": "Feature",
  "properties": {
    "gn:admin1_code":"28.0",
    "gn:asciiname":"Karevanchi",
    "gn:country_code":"IR",
    "gn:dem":1532,
    "gn:feature_class":"P",
    "gn:feature_code":"PPL",
    "gn:name":"K\u0101rev\u0101nch\u012b",
    "gn:population":0,
    "gn:timezone":"Asia/Tehran",
    "iso:country":"IR",
    "name:fas_x_preferred":[
        "K\u0101rev\u0101nch\u012b"
    ],
    "name:fas_x_variant":[
        "\u06a9\u0627\u0631\u0648\u0627\u0646\u0686\u06cc"
    ],
    "name:und_x_variant":[
        "\u06a9\u0627\u0631\u0648\u0627\u0646\u0686\u06cc"
    ],
    "wof:name":"Karevanchi",
    "wof:placetype":"locality"
},
  "geometry": {"coordinates":[51.92157,32.53502],"type":"Point"}
}