{
  "type": "Feature",
  "properties": {
    "gn:admin1_code":"7",
    "gn:asciiname":"Kushk-e Qazi",
    "gn:country_code":"IR",
    "gn:dem":1346,
    "gn:feature_class":"P",
    "gn:feature_code":"PPL",
    "gn:name":"K\u016bshk-e Q\u0101\u1e95\u012b",
    "gn:population":0,
    "gn:timezone":"Asia/Tehran",
    "iso:country":"IR",
    "name:ara_x_preferred":[
        "\u0643\u0648\u0634\u0643 \u0642\u0627\u0636\u064a"
    ],
    "name:fas_x_preferred":[
        "\u06a9\u0648\u0634\u06a9 \u0642\u0627\u0636\u06cc"
    ],
    "name:fas_x_variant":[
        "K\u016bshk-e Q\u0101z\u012b",
        "K\u016bshk-e Q\u0101\u1e95\u012b"
    ],
    "name:msa_x_preferred":[
        "Kushk-e Qazi"
    ],
    "name:und_x_variant":[
        "Khoshk Q\u0101z\u012b",
        "K\u016bshk-i-Q\u0101zi",
        "K\u016bsk-e Q\u0101z\u012b"
    ],
    "wof:name":"Kushk-e Qazi",
    "wof:placetype":"locality"
},
  "geometry": {"coordinates":[53.68564,28.92919],"type":"Point"}
}