{
  "type": "Feature",
  "properties": {
    "gn:admin1_code":"35.0",
    "gn:asciiname":"Kolik",
    "gn:country_code":"IR",
    "gn:dem":2076,
    "gn:feature_class":"P",
    "gn:feature_code":"PPL",
    "gn:name":"Kol\u012bk",
    "gn:population":0,
    "gn:timezone":"Asia/Tehran",
    "iso:country":"IR",
    "name:fas_x_preferred":[
        "\u06a9\u0644\u06cc\u06a9"
    ],
    "name:fas_x_variant":[
        "Kol\u012bk"
    ],
    "wof:name":"Kolik",
    "wof:placetype":"locality"
},
  "geometry": {"coordinates":[51.78963,36.17616],"type":"Point"}
}