{
  "type": "Feature",
  "properties": {
    "gn:admin1_code":"38",
    "gn:asciiname":"Mehin",
    "gn:country_code":"IR",
    "gn:dem":1602,
    "gn:feature_class":"P",
    "gn:feature_code":"PPL",
    "gn:name":"Meh\u012bn",
    "gn:population":0,
    "gn:timezone":"Asia/Tehran",
    "iso:country":"IR",
    "name:fas_x_preferred":[
        "\u0645\u0647\u064a\u0646"
    ],
    "name:fas_x_variant":[
        "Meh\u012bn",
        "\u0645\u0647\u06cc\u0646"
    ],
    "name:und_x_variant":[
        "Mah\u012bn",
        "Mikhin",
        "Mih\u012bn",
        "M\u012bhan"
    ],
    "wof:name":"Mehin",
    "wof:placetype":"locality"
},
  "geometry": {"coordinates":[49.4728,36.1429],"type":"Point"}
}