{
  "type": "Feature",
  "properties": {
    "gn:admin1_code":"25.0",
    "gn:asciiname":"Faridar",
    "gn:country_code":"IR",
    "gn:dem":1209,
    "gn:feature_class":"P",
    "gn:feature_code":"PPL",
    "gn:name":"Far\u012bdar",
    "gn:population":0,
    "gn:timezone":"Asia/Tehran",
    "iso:country":"IR",
    "name:fas_x_preferred":[
        "\u0641\u0631\u06cc\u062f\u0631"
    ],
    "name:fas_x_variant":[
        "Far\u012bdar"
    ],
    "wof:name":"Faridar",
    "wof:placetype":"locality"
},
  "geometry": {"coordinates":[56.7608,35.57768],"type":"Point"}
}