{
  "type": "Feature",
  "properties": {
    "gn:admin1_code":"7",
    "gn:asciiname":"Pasalari",
    "gn:country_code":"IR",
    "gn:dem":1085,
    "gn:feature_class":"P",
    "gn:feature_code":"PPL",
    "gn:name":"P\u0101s\u0101l\u0101r\u012b",
    "gn:population":0,
    "gn:timezone":"Asia/Tehran",
    "iso:country":"IR",
    "name:ara_x_preferred":[
        "\u0628\u0627\u0633\u0627\u0644\u0627\u0631\u064a"
    ],
    "name:fas_x_preferred":[
        "\u067e\u0627\u0633\u0627\u0644\u0627\u0631\u06cc"
    ],
    "name:fas_x_variant":[
        "P\u0101s\u0101l\u0101r\u012b"
    ],
    "name:msa_x_preferred":[
        "Pasalari"
    ],
    "wof:name":"Pasalari",
    "wof:placetype":"locality"
},
  "geometry": {"coordinates":[54.31931,28.65523],"type":"Point"}
}