{
  "type": "Feature",
  "properties": {
    "gn:admin1_code":"8",
    "gn:asciiname":"Khalifabad",
    "gn:country_code":"IR",
    "gn:dem":45,
    "gn:feature_class":"P",
    "gn:feature_code":"PPL",
    "gn:name":"Khal\u012bf\u0101b\u0101d",
    "gn:population":0,
    "gn:timezone":"Asia/Tehran",
    "iso:country":"IR",
    "name:fas_x_preferred":[
        "Khal\u012bf\u0101b\u0101d"
    ],
    "name:und_x_variant":[
        "Khamp\u0101r\u016b",
        "Khal\u012bfeh\u0101b\u0101d"
    ],
    "wof:name":"Khalifabad",
    "wof:placetype":"locality"
},
  "geometry": {"coordinates":[48.95889,37.68972],"type":"Point"}
}