{
  "type": "Feature",
  "properties": {
    "gn:admin1_code":"34",
    "gn:asciiname":"Kahak",
    "gn:country_code":"IR",
    "gn:dem":2112,
    "gn:feature_class":"P",
    "gn:feature_code":"PPL",
    "gn:name":"Kahak",
    "gn:population":0,
    "gn:timezone":"Asia/Tehran",
    "iso:country":"IR",
    "name:ceb_x_preferred":[
        "Kahak"
    ],
    "name:fas_x_preferred":[
        "\u0643\u0650\u0631\u0650\u0643"
    ],
    "name:fas_x_variant":[
        "\u0643\u0647\u0643",
        "\u06a9\u0647\u06a9"
    ],
    "name:sco_x_preferred":[
        "Kahak"
    ],
    "name:swe_x_preferred":[
        "Kahak"
    ],
    "name:und_x_variant":[
        "Kerek",
        "\u0643\u0647\u0643",
        "Kahak"
    ],
    "wof:name":"Kahak",
    "wof:placetype":"locality"
},
  "geometry": {"coordinates":[50.06791,34.69475],"type":"Point"}
}