{
  "type": "Feature",
  "properties": {
    "gn:admin1_code":"15",
    "gn:asciiname":"`Amerabad-e Do",
    "gn:country_code":"IR",
    "gn:dem":21,
    "gn:feature_class":"P",
    "gn:feature_code":"PPL",
    "gn:name":"\u2018\u0100mer\u0101b\u0101d-e Do",
    "gn:population":0,
    "gn:timezone":"Asia/Tehran",
    "iso:country":"IR",
    "name:fas_x_preferred":[
        "\u2018\u0100mer\u0101b\u0101d-e Do"
    ],
    "wof:name":"`Amerabad-e Do",
    "wof:placetype":"locality"
},
  "geometry": {"coordinates":[48.7425,31.32333],"type":"Point"}
}