{
  "type": "Feature",
  "properties": {
    "gn:admin1_code":"29",
    "gn:asciiname":"Gazabad",
    "gn:country_code":"IR",
    "gn:dem":407,
    "gn:feature_class":"P",
    "gn:feature_code":"PPLF",
    "gn:name":"Gaz\u0101b\u0101d",
    "gn:population":0,
    "gn:timezone":"Asia/Tehran",
    "iso:country":"IR",
    "name:fas_x_preferred":[
        "\u06af\u0632 \u0622\u0628\u0627\u062f"
    ],
    "name:fas_x_variant":[
        "Gaz\u0101b\u0101d"
    ],
    "wof:name":"Gazabad",
    "wof:placetype":"locality"
},
  "geometry": {"coordinates":[58.29178,27.80614000000001],"type":"Point"}
}