{
  "type": "Feature",
  "properties": {
    "gn:admin1_code":"29",
    "gn:asciiname":"Bonzeh",
    "gn:country_code":"IR",
    "gn:dem":611,
    "gn:feature_class":"P",
    "gn:feature_code":"PPL",
    "gn:name":"Bonzeh",
    "gn:population":0,
    "gn:timezone":"Asia/Tehran",
    "iso:country":"IR",
    "wof:name":"Bonzeh",
    "wof:placetype":"locality"
},
  "geometry": {"coordinates":[57.47667,27.74778],"type":"Point"}
}