{
  "type": "Feature",
  "properties": {
    "gn:admin1_code":"33",
    "gn:asciiname":"Makhdum Kandi",
    "gn:country_code":"IR",
    "gn:dem":2188,
    "gn:feature_class":"P",
    "gn:feature_code":"PPL",
    "gn:name":"Makhd\u016bm Kand\u012b",
    "gn:population":0,
    "gn:timezone":"Asia/Tehran",
    "iso:country":"IR",
    "name:ara_x_preferred":[
        "\u0645\u062e\u062f\u0648\u0645\u0643\u0646\u062f\u064a"
    ],
    "name:ceb_x_preferred":[
        "Makhd\u016bm Kand\u012b"
    ],
    "name:fas_x_preferred":[
        "\u0645\u062e\u062f\u0648\u0645 \u06a9\u0646\u062f\u06cc"
    ],
    "name:fas_x_variant":[
        "Makhd\u016bm Kand\u012b",
        "\u0645\u062e\u062f\u0648\u0645\u200c\u06a9\u0646\u062f\u06cc"
    ],
    "name:msa_x_preferred":[
        "Makhdum Kandi"
    ],
    "name:swe_x_preferred":[
        "Makhd\u016bm Kand\u012b"
    ],
    "wof:name":"Makhdum Kandi",
    "wof:placetype":"locality"
},
  "geometry": {"coordinates":[46.8634,37.0548],"type":"Point"}
}