{
  "type": "Feature",
  "properties": {
    "gn:admin1_code":"23",
    "gn:asciiname":"Garmurt Nosrati",
    "gn:country_code":"IR",
    "gn:dem":1182,
    "gn:feature_class":"P",
    "gn:feature_code":"PPL",
    "gn:name":"Garm\u016brt No\u015frat\u012b",
    "gn:population":0,
    "gn:timezone":"Asia/Tehran",
    "iso:country":"IR",
    "name:ara_x_preferred":[
        "\u063a\u0631\u0645\u0648\u0631\u062a \u0646\u0635\u0631\u062a\u064a"
    ],
    "name:ceb_x_preferred":[
        "Garm\u016brt No\u015frat\u012b"
    ],
    "name:fas_x_preferred":[
        "\u06af\u0631\u0645\u0648\u0631\u062a"
    ],
    "name:fas_x_variant":[
        "Garm\u016brt",
        "\u06af\u0631\u0645\u0648\u0631\u062a \u0646\u0635\u0631\u062a\u06cc"
    ],
    "name:swe_x_preferred":[
        "Garm\u016brt No\u015frat\u012b"
    ],
    "name:und_x_variant":[
        "Garm\u016brt-e No\u015frat\u012b",
        "Garm\u016brt No\u015frat\u012b"
    ],
    "wof:name":"Garmurt Nosrati",
    "wof:placetype":"locality"
},
  "geometry": {"coordinates":[47.8141,33.7057],"type":"Point"}
}