{
  "type": "Feature",
  "properties": {
    "gn:admin1_code":"28",
    "gn:asciiname":"Helaghareh",
    "gn:country_code":"IR",
    "gn:dem":2405,
    "gn:feature_class":"P",
    "gn:feature_code":"PPL",
    "gn:name":"Hel\u0101ghareh",
    "gn:population":0,
    "gn:timezone":"Asia/Tehran",
    "iso:country":"IR",
    "name:ara_x_preferred":[
        "\u0647\u0644\u0627 \u063a\u0631\u0629"
    ],
    "name:fas_x_preferred":[
        "Hal\u0101gharreh"
    ],
    "name:fas_x_variant":[
        "Hel\u0101ghareh",
        "\u0647\u0644\u0627\u063a\u0631\u0647"
    ],
    "name:und_x_variant":[
        "Hilla Ghurreh",
        "Hal\u0101 Ghorreh"
    ],
    "wof:name":"Helaghareh",
    "wof:placetype":"locality"
},
  "geometry": {"coordinates":[50.16932,33.22569],"type":"Point"}
}