{
  "type": "Feature",
  "properties": {
    "gn:admin1_code":"36",
    "gn:asciiname":"Sheykh Jaber",
    "gn:country_code":"IR",
    "gn:dem":1994,
    "gn:feature_class":"P",
    "gn:feature_code":"PPL",
    "gn:name":"Sheykh J\u0101ber",
    "gn:population":0,
    "gn:timezone":"Asia/Tehran",
    "iso:country":"IR",
    "name:azb_x_preferred":[
        "\u0634\u06cc\u062e \u062c\u0627\u0628\u0631"
    ],
    "name:ceb_x_preferred":[
        "Sheykh J\u0101ber"
    ],
    "name:fas_x_preferred":[
        "\u0634\u06cc\u062e \u062c\u0627\u0628\u0631"
    ],
    "name:fas_x_variant":[
        "Sheykh J\u0101ber"
    ],
    "name:swe_x_preferred":[
        "Sheykh J\u0101ber"
    ],
    "wof:name":"Sheykh Jaber",
    "wof:placetype":"locality"
},
  "geometry": {"coordinates":[47.99086,36.53998],"type":"Point"}
}