{
  "type": "Feature",
  "properties": {
    "gn:admin1_code":"29",
    "gn:asciiname":"Mowtowr-e Shahsavari",
    "gn:country_code":"IR",
    "gn:dem":1743,
    "gn:feature_class":"P",
    "gn:feature_code":"PPL",
    "gn:name":"Mowtowr-e Shahsav\u0101r\u012b",
    "gn:population":0,
    "gn:timezone":"Asia/Tehran",
    "iso:country":"IR",
    "name:fas_x_preferred":[
        "\u0645\u0648\u062a\u0648\u0631 \u0634\u0647\u0633\u0648\u0627\u0631\u06cc"
    ],
    "name:fas_x_variant":[
        "\u062a\u0644\u0645\u0628\u0647 \u0633\u0631\u0647\u0646\u06af \u0634\u0647\u0633\u0648\u0627\u0631\u06cc"
    ],
    "name:und_x_variant":[
        "Mowtowr-e Shahsav\u0101r\u012b",
        "Tolombeh-ye Sarhang Shahsav\u0101r\u012b"
    ],
    "wof:name":"Mowtowr-e Shahsavari",
    "wof:placetype":"locality"
},
  "geometry": {"coordinates":[55.8648,28.891],"type":"Point"}
}