{
  "type": "Feature",
  "properties": {
    "gn:admin1_code":"11",
    "gn:asciiname":"Gel Kan",
    "gn:country_code":"IR",
    "gn:dem":526,
    "gn:feature_class":"P",
    "gn:feature_code":"PPL",
    "gn:name":"Gel Kan",
    "gn:population":0,
    "gn:timezone":"Asia/Tehran",
    "iso:country":"IR",
    "name:fas_x_preferred":[
        "\u06af\u0644 \u06a9\u0646"
    ],
    "name:und_x_variant":[
        "Gol Kan",
        "Gol Kand",
        "Gel Kan"
    ],
    "wof:name":"Gel Kan",
    "wof:placetype":"locality"
},
  "geometry": {"coordinates":[57.3461,27.7842],"type":"Point"}
}