{
  "type": "Feature",
  "properties": {
    "gn:admin1_code":"35.0",
    "gn:asciiname":"Sheykh Deh",
    "gn:country_code":"IR",
    "gn:dem":2017,
    "gn:feature_class":"P",
    "gn:feature_code":"PPL",
    "gn:name":"Sheykh Deh",
    "gn:population":0,
    "gn:timezone":"Asia/Tehran",
    "iso:country":"IR",
    "name:fas_x_preferred":[
        "\u0634\u06cc\u062e \u062f\u0647"
    ],
    "wof:name":"Sheykh Deh",
    "wof:placetype":"locality"
},
  "geometry": {"coordinates":[51.69875,36.40138],"type":"Point"}
}