{
  "type": "Feature",
  "properties": {
    "gn:admin1_code":"29",
    "gn:asciiname":"Omrudu'iyeh",
    "gn:country_code":"IR",
    "gn:dem":2221,
    "gn:feature_class":"P",
    "gn:feature_code":"PPL",
    "gn:name":"Omr\u016bd\u016b\u2019\u012byeh",
    "gn:population":0,
    "gn:timezone":"Asia/Tehran",
    "iso:country":"IR",
    "name:ara_x_preferred":[
        "\u0639\u0645\u0631\u0648\u062f\u0648\u0626\u064a\u0629"
    ],
    "name:fas_x_preferred":[
        "\u0627\u0645\u0631\u0648\u062f\u0648\u0626\u06cc\u0647"
    ],
    "name:fas_x_variant":[
        "\u2018Omr\u016bd\u016b\u2019\u012byeh",
        "Omr\u016bd\u016b\u2019\u012byeh",
        "\u0639\u0645\u0631\u0648\u062f\u0648\u0626\u06cc\u0647"
    ],
    "wof:name":"Omrudu'iyeh",
    "wof:placetype":"locality"
},
  "geometry": {"coordinates":[56.85833,28.59067000000001],"type":"Point"}
}