{
  "type": "Feature",
  "properties": {
    "gn:admin1_code":"8.0",
    "gn:asciiname":"Lu Sara",
    "gn:country_code":"IR",
    "gn:dem":296,
    "gn:feature_class":"P",
    "gn:feature_code":"PPL",
    "gn:name":"L\u016b Sar\u0101",
    "gn:population":0,
    "gn:timezone":"Asia/Tehran",
    "iso:country":"IR",
    "name:fas_x_preferred":[
        "L\u016b Sar\u0101"
    ],
    "name:fas_x_variant":[
        "\u0644\u0648 \u0633\u0631\u0627"
    ],
    "name:und_x_variant":[
        "\u0644\u0648 \u0633\u0631\u0627"
    ],
    "wof:name":"Lu Sara",
    "wof:placetype":"locality"
},
  "geometry": {"coordinates":[50.25,36.9746],"type":"Point"}
}