{
  "type": "Feature",
  "properties": {
    "gn:admin1_code":"29",
    "gn:asciiname":"Goraghan-e Tangan",
    "gn:country_code":"IR",
    "gn:dem":1471,
    "gn:feature_class":"P",
    "gn:feature_code":"PPL",
    "gn:name":"Gor\u0101gh\u0101n-e Tang\u0101n",
    "gn:population":0,
    "gn:timezone":"Asia/Tehran",
    "iso:country":"IR",
    "name:fas_x_preferred":[
        "Gor\u0101gh\u0101n-e Tang\u0101n"
    ],
    "name:fas_x_variant":[
        "\u06af\u0631\u0627\u063a\u0627\u0646 \u062a\u0646\u06af\u0627\u0646"
    ],
    "wof:name":"Goraghan-e Tangan",
    "wof:placetype":"locality"
},
  "geometry": {"coordinates":[57.76667,28.95],"type":"Point"}
}