{
  "type": "Feature",
  "properties": {
    "gn:admin1_code":"4.0",
    "gn:asciiname":"Shahrak-e Behdari",
    "gn:country_code":"IR",
    "gn:dem":21,
    "gn:feature_class":"P",
    "gn:feature_code":"PPL",
    "gn:name":"Shahrak-e Behd\u0101r\u012b",
    "gn:population":0,
    "gn:timezone":"Asia/Tehran",
    "iso:country":"IR",
    "name:fas_x_preferred":[
        "Shahrak-e Behd\u0101r\u012b"
    ],
    "name:fas_x_variant":[
        "\u0634\u0647\u0631\u06a9 \u0628\u0647\u062f\u0627\u0631\u06cc"
    ],
    "wof:name":"Shahrak-e Behdari",
    "wof:placetype":"locality"
},
  "geometry": {"coordinates":[59.38066,25.57592],"type":"Point"}
}