{
  "type": "Feature",
  "properties": {
    "gn:admin1_code":"32",
    "gn:asciiname":"Qeshlaq-e Para Hajj Barish",
    "gn:country_code":"IR",
    "gn:dem":134,
    "gn:feature_class":"P",
    "gn:feature_code":"PPL",
    "gn:name":"Qeshl\u0101q-e P\u0101r\u0101 \u1e28\u0101jj B\u0101r\u012bsh",
    "gn:population":0,
    "gn:timezone":"Asia/Tehran",
    "iso:country":"IR",
    "name:fas_x_preferred":[
        "\u0642\u0650\u0634\u0644\u0627\u0642\u0650 \u067e\u0627\u0631\u0627 \u062d\u0627\u062c\u0651 \u0628\u0627\u0631\u064a\u0634"
    ],
    "name:fas_x_variant":[
        "Qeshl\u0101q-e P\u0101r\u0101 \u1e28\u0101jj B\u0101r\u012bsh"
    ],
    "wof:name":"Qeshlaq-e Para Hajj Barish",
    "wof:placetype":"locality"
},
  "geometry": {"coordinates":[47.85,39.51667],"type":"Point"}
}