{
  "type": "Feature",
  "properties": {
    "gn:admin1_code":"32",
    "gn:asciiname":"Yeznabad",
    "gn:country_code":"IR",
    "gn:dem":1332,
    "gn:feature_class":"P",
    "gn:feature_code":"PPL",
    "gn:name":"Yezn\u0101b\u0101d",
    "gn:population":0,
    "gn:timezone":"Asia/Tehran",
    "iso:country":"IR",
    "name:azb_x_preferred":[
        "\u06cc\u0632\u0646 \u0622\u0628\u0627\u062f(\u0646\u0645\u06cc\u0646)"
    ],
    "name:fas_x_preferred":[
        "\u064a\u0632\u0646 \u0622\u0628\u0627\u062f"
    ],
    "name:fas_x_variant":[
        "Yezn\u0101b\u0101d",
        "\u06cc\u0632\u0646\u200c\u0622\u0628\u0627\u062f"
    ],
    "name:msa_x_preferred":[
        "Yeznabad"
    ],
    "name:mzn_x_preferred":[
        "\u06cc\u0632\u0646\u200c\u0622\u0628\u0627\u062f"
    ],
    "name:urd_x_preferred":[
        "\u06cc\u0632\u0646 \u0622\u0628\u0627\u062f"
    ],
    "wof:name":"Yeznabad",
    "wof:placetype":"locality"
},
  "geometry": {"coordinates":[48.3406,38.3989],"type":"Point"}
}