{
  "type": "Feature",
  "properties": {
    "gn:admin1_code":"7",
    "gn:asciiname":"Cheshmeh-ye Takht",
    "gn:country_code":"IR",
    "gn:dem":1625,
    "gn:feature_class":"P",
    "gn:feature_code":"PPL",
    "gn:name":"Cheshmeh-ye Takht",
    "gn:population":0,
    "gn:timezone":"Asia/Tehran",
    "iso:country":"IR",
    "name:fas_x_preferred":[
        "\u0686\u0634\u0645\u0647 \u062a\u062e\u062a"
    ],
    "wof:name":"Cheshmeh-ye Takht",
    "wof:placetype":"locality"
},
  "geometry": {"coordinates":[52.5852,30.2042],"type":"Point"}
}