{
  "type": "Feature",
  "properties": {
    "gn:admin1_code":"4",
    "gn:asciiname":"Dak Jamal",
    "gn:country_code":"IR",
    "gn:dem":1235,
    "gn:feature_class":"P",
    "gn:feature_code":"PPL",
    "gn:name":"Dak Jam\u0101l",
    "gn:population":0,
    "gn:timezone":"Asia/Tehran",
    "iso:country":"IR",
    "name:fas_x_preferred":[
        "\u062f\u06a9 \u062c\u0645\u0627\u0644"
    ],
    "name:fas_x_variant":[
        "Dak Jam\u0101l"
    ],
    "wof:name":"Dak Jamal",
    "wof:placetype":"locality"
},
  "geometry": {"coordinates":[60.95641,27.69683],"type":"Point"}
}