{
  "type": "Feature",
  "properties": {
    "gn:admin1_code":"41",
    "gn:asciiname":"Rubokht",
    "gn:country_code":"IR",
    "gn:dem":1859,
    "gn:feature_class":"P",
    "gn:feature_code":"PPL",
    "gn:name":"R\u016bbokht",
    "gn:population":0,
    "gn:timezone":"Asia/Tehran",
    "iso:country":"IR",
    "name:ara_x_preferred":[
        "\u0631\u0648\u0628\u062e\u062a"
    ],
    "name:ceb_x_preferred":[
        "R\u016bbokht"
    ],
    "name:fas_x_preferred":[
        "R\u016bbokht"
    ],
    "name:fas_x_variant":[
        "\u0631\u0648\u0628\u062e\u062a",
        "\u0631\u06cc\u062e\u062a",
        "\u0631\u0628\u062e\u062a"
    ],
    "name:swe_x_preferred":[
        "R\u016bbokht"
    ],
    "name:und_x_variant":[
        "Robakht",
        "Rovokht",
        "Rowvokht",
        "R\u012bkht"
    ],
    "wof:name":"Rubokht",
    "wof:placetype":"locality"
},
  "geometry": {"coordinates":[59.33614,33.22752],"type":"Point"}
}