{
  "type": "Feature",
  "properties": {
    "gn:admin1_code":"1",
    "gn:asciiname":"Ow`ali",
    "gn:country_code":"IR",
    "gn:dem":1734,
    "gn:feature_class":"P",
    "gn:feature_code":"PPL",
    "gn:name":"Ow\u2018al\u012b",
    "gn:population":0,
    "gn:timezone":"Asia/Tehran",
    "iso:country":"IR",
    "name:fas_x_preferred":[
        "\u0627\u064f\u0648\u0639\u064e\u0644\u06cc"
    ],
    "name:fas_x_variant":[
        "Ow\u2018al\u012b",
        "\u0627\u0648\u0639\u0644\u06cc"
    ],
    "wof:name":"Ow`ali",
    "wof:placetype":"locality"
},
  "geometry": {"coordinates":[44.9348,37.4958],"type":"Point"}
}