{
  "type": "Feature",
  "properties": {
    "gn:admin1_code":"7",
    "gn:asciiname":"Murd Abi",
    "gn:country_code":"IR",
    "gn:dem":965,
    "gn:feature_class":"P",
    "gn:feature_code":"PPL",
    "gn:name":"M\u016brd \u0100b\u012b",
    "gn:population":0,
    "gn:timezone":"Asia/Tehran",
    "iso:country":"IR",
    "name:fas_x_preferred":[
        "M\u016brd \u0100b\u012b"
    ],
    "name:fas_x_variant":[
        "M\u016brd\u0101b\u012b-ye P\u0101\u2019\u012bn",
        "\u0645\u0648\u0631\u062f \u0622\u0628\u06cc"
    ],
    "wof:name":"Murd Abi",
    "wof:placetype":"locality"
},
  "geometry": {"coordinates":[51.53863,30.12048],"type":"Point"}
}