{
  "type": "Feature",
  "properties": {
    "gn:admin1_code":"15.0",
    "gn:asciiname":"Zaras",
    "gn:country_code":"IR",
    "gn:dem":1142,
    "gn:feature_class":"P",
    "gn:feature_code":"PPL",
    "gn:name":"Zar\u0101s",
    "gn:population":0,
    "gn:timezone":"Asia/Tehran",
    "iso:country":"IR",
    "name:fas_x_preferred":[
        "\u0632\u0631\u0627\u0633"
    ],
    "name:und_x_variant":[
        "Zar\u0101s"
    ],
    "wof:name":"Zaras",
    "wof:placetype":"locality"
},
  "geometry": {"coordinates":[50.27847,31.60807],"type":"Point"}
}