{
  "type": "Feature",
  "properties": {
    "gn:admin1_code":"41",
    "gn:asciiname":"Kuh-e Mohammad Hoseyn-e `Abedi",
    "gn:country_code":"IR",
    "gn:dem":2295,
    "gn:feature_class":"P",
    "gn:feature_code":"PPL",
    "gn:name":"K\u016bh-e Mo\u1e29ammad \u1e28oseyn-e \u2018Abed\u012b",
    "gn:population":0,
    "gn:timezone":"Asia/Tehran",
    "iso:country":"IR",
    "name:fas_x_preferred":[
        "K\u016bh-e Mo\u1e29ammad \u1e28oseyn-e \u2018Abed\u012b"
    ],
    "wof:name":"Kuh-e Mohammad Hoseyn-e `Abedi",
    "wof:placetype":"locality"
},
  "geometry": {"coordinates":[59.65306,33.2625],"type":"Point"}
}