{
  "type": "Feature",
  "properties": {
    "gn:admin1_code":"4",
    "gn:asciiname":"Sid Daran",
    "gn:country_code":"IR",
    "gn:dem":30,
    "gn:feature_class":"P",
    "gn:feature_code":"PPL",
    "gn:name":"S\u012bd Dar\u0101n",
    "gn:population":0,
    "gn:timezone":"Asia/Tehran",
    "iso:country":"IR",
    "name:fas_x_preferred":[
        "S\u012bd Dar\u0101n"
    ],
    "wof:name":"Sid Daran",
    "wof:placetype":"locality"
},
  "geometry": {"coordinates":[59.5925,25.50139],"type":"Point"}
}