{
  "type": "Feature",
  "properties": {
    "gn:admin1_code":"38",
    "gn:asciiname":"Ajor-e Haqiqat",
    "gn:country_code":"IR",
    "gn:dem":1182,
    "gn:feature_class":"P",
    "gn:feature_code":"PPL",
    "gn:name":"\u0100jor-e \u1e28aq\u012bqat",
    "gn:population":0,
    "gn:timezone":"Asia/Tehran",
    "iso:country":"IR",
    "name:fas_x_preferred":[
        "\u0100jor-e \u1e28aq\u012bqat"
    ],
    "wof:name":"Ajor-e Haqiqat",
    "wof:placetype":"locality"
},
  "geometry": {"coordinates":[50.23333,35.75],"type":"Point"}
}