{
  "type": "Feature",
  "properties": {
    "gn:admin1_code":"29",
    "gn:asciiname":"Montazeriyeh",
    "gn:country_code":"IR",
    "gn:dem":472,
    "gn:feature_class":"P",
    "gn:feature_code":"PPL",
    "gn:name":"Montaz\u0327er\u012byeh",
    "gn:population":0,
    "gn:timezone":"Asia/Tehran",
    "iso:country":"IR",
    "name:fas_x_preferred":[
        "\u0645\u0646\u062a\u0638\u0631\u06cc\u0647"
    ],
    "name:fas_x_variant":[
        "Montaz\u0327er\u012byeh"
    ],
    "wof:name":"Montazeriyeh",
    "wof:placetype":"locality"
},
  "geometry": {"coordinates":[57.8186,27.9767],"type":"Point"}
}