{
  "type": "Feature",
  "properties": {
    "gn:admin1_code":"7",
    "gn:asciiname":"Deh-e Pas Qalat",
    "gn:country_code":"IR",
    "gn:dem":1146,
    "gn:feature_class":"P",
    "gn:feature_code":"PPL",
    "gn:name":"Deh-e Pas Qal\u0101t",
    "gn:population":0,
    "gn:timezone":"Asia/Tehran",
    "iso:country":"IR",
    "name:fas_x_preferred":[
        "Deh-e Pas Qal\u0101t"
    ],
    "name:fas_x_variant":[
        "\u062f\u0647 \u067e\u0633 \u0642\u0644\u0627\u062a"
    ],
    "name:msa_x_preferred":[
        "Deh-e Pas Qalat"
    ],
    "name:und_x_variant":[
        "Pas Qal\u0101t",
        "Deh-e Pas-e Qal\u0101t"
    ],
    "wof:name":"Deh-e Pas Qalat",
    "wof:placetype":"locality"
},
  "geometry": {"coordinates":[51.57594,29.97429],"type":"Point"}
}