{
  "type": "Feature",
  "properties": {
    "gn:admin1_code":"8",
    "gn:asciiname":"Gurab Zarmikh",
    "gn:country_code":"IR",
    "gn:dem":23,
    "gn:feature_class":"P",
    "gn:feature_code":"PPL",
    "gn:name":"G\u016br\u0101b Zarm\u012bkh",
    "gn:population":0,
    "gn:timezone":"Asia/Tehran",
    "iso:country":"IR",
    "name:ara_x_preferred":[
        "\u063a\u0648\u0631\u0627\u0628 \u0632\u0631\u0645\u064a\u062e"
    ],
    "name:aze_x_preferred":[
        "Gurab Z\u0259rmix"
    ],
    "name:ceb_x_preferred":[
        "G\u016br\u0101b Zarm\u012bkh"
    ],
    "name:fas_x_preferred":[
        "\u06af\u0648\u0631\u0627\u0628 \u0632\u0631\u0645\u06cc\u062e"
    ],
    "name:fas_x_variant":[
        "G\u016br\u0101b Zarmakh",
        "G\u016br\u0101b Zarm\u012bkh"
    ],
    "name:ita_x_preferred":[
        "Gurab Zarmikh"
    ],
    "name:mlg_x_preferred":[
        "Gurab Zarmikh"
    ],
    "name:msa_x_preferred":[
        "Gurab Zarmikh"
    ],
    "name:pol_x_preferred":[
        "Gurab Zarmich"
    ],
    "name:swe_x_preferred":[
        "G\u016br\u0101b Zarm\u012bkh"
    ],
    "name:tur_x_preferred":[
        "Gurab Zermih"
    ],
    "name:und_x_variant":[
        "Kurab-Zermakh",
        "G\u016br\u0101b Zarmanj"
    ],
    "wof:name":"Gurab Zarmikh",
    "wof:placetype":"locality"
},
  "geometry": {"coordinates":[49.23756,37.29325],"type":"Point"}
}