{
  "type": "Feature",
  "properties": {
    "gn:admin1_code":"41",
    "gn:asciiname":"Ray",
    "gn:country_code":"IR",
    "gn:dem":1660,
    "gn:feature_class":"P",
    "gn:feature_code":"PPL",
    "gn:name":"R\u0101y",
    "gn:population":0,
    "gn:timezone":"Asia/Tehran",
    "iso:country":"IR",
    "name:fas_x_preferred":[
        "\u0631\u0627\u06cc"
    ],
    "name:fas_x_variant":[
        "R\u0101i",
        "R\u0101y"
    ],
    "wof:name":"Ray",
    "wof:placetype":"locality"
},
  "geometry": {"coordinates":[59.97232,31.83759],"type":"Point"}
}