{
  "type": "Feature",
  "properties": {
    "gn:admin1_code":"41",
    "gn:asciiname":"Ray",
    "gn:country_code":"IR",
    "gn:dem":1660,
    "gn:feature_class":"P",
    "gn:feature_code":"PPL",
    "gn:name":"R\u0101y",
    "gn:population":0,
    "gn:timezone":"Asia/Tehran",
    "iso:country":"IR",
    "name:ara_x_preferred":[
        "\u0634\u0639\u0627\u0639"
    ],
    "name:bel_x_preferred":[
        "\u0420\u044d\u0439"
    ],
    "name:ben_x_preferred":[
        "\u09b6\u0999\u09cd\u0995\u09b0 \u09ae\u09be\u099b"
    ],
    "name:bul_x_preferred":[
        "\u0420\u0435\u0439"
    ],
    "name:cat_x_preferred":[
        "Ray"
    ],
    "name:ceb_x_preferred":[
        "Ray"
    ],
    "name:ces_x_preferred":[
        "Ray"
    ],
    "name:deu_x_preferred":[
        "Ray"
    ],
    "name:fas_x_preferred":[
        "\u0631\u0627\u06cc"
    ],
    "name:fas_x_variant":[
        "R\u0101i",
        "R\u0101y",
        "\u0631\u06cc"
    ],
    "name:fin_x_preferred":[
        "Ray"
    ],
    "name:fra_x_preferred":[
        "Ray"
    ],
    "name:heb_x_preferred":[
        "\u05e8\u05d9\u05d9"
    ],
    "name:kaz_x_preferred":[
        "\u0420\u0435\u0439"
    ],
    "name:lav_x_preferred":[
        "Rejs"
    ],
    "name:nld_x_preferred":[
        "Ray"
    ],
    "name:nor_x_preferred":[
        "Ray"
    ],
    "name:pol_x_preferred":[
        "Ray"
    ],
    "name:por_x_preferred":[
        "Ray"
    ],
    "name:pus_x_preferred":[
        "\u0648\u0693\u0627\u0646\u06af\u0647"
    ],
    "name:rus_x_preferred":[
        "\u0420\u0435\u0439"
    ],
    "name:slv_x_preferred":[
        "Ray"
    ],
    "name:spa_x_preferred":[
        "Ray"
    ],
    "name:srp_x_preferred":[
        "\u0420\u0435\u0458"
    ],
    "name:swe_x_preferred":[
        "Ray"
    ],
    "name:tur_x_preferred":[
        "Ray"
    ],
    "name:ukr_x_preferred":[
        "\u0420\u0435\u0439"
    ],
    "name:vol_x_preferred":[
        "Ray"
    ],
    "name:zho_x_preferred":[
        "Ray"
    ],
    "wof:name":"Ray",
    "wof:placetype":"locality"
},
  "geometry": {"coordinates":[59.97232,31.83759],"type":"Point"}
}