{
  "type": "Feature",
  "properties": {
    "gn:admin1_code":"43.0",
    "gn:asciiname":"Mahalleh-ye Qal`eh Pirakha",
    "gn:country_code":"IR",
    "gn:dem":1268,
    "gn:feature_class":"P",
    "gn:feature_code":"PPL",
    "gn:name":"Ma\u1e29alleh-ye Qal\u2018eh P\u012brakh\u0101",
    "gn:population":0,
    "gn:timezone":"Asia/Tehran",
    "iso:country":"IR",
    "name:fas_x_preferred":[
        "\u0645\u062d\u0644\u0647 \u0642\u0644\u0639\u0647 \u067e\u06cc\u0631\u06a9 \u0647\u0627"
    ],
    "name:und_x_variant":[
        "Ma\u1e29alleh-ye Qal\u2018eh P\u012brakh\u0101"
    ],
    "wof:name":"Mahalleh-ye Qal`eh Pirakha",
    "wof:placetype":"locality"
},
  "geometry": {"coordinates":[57.59235,36.99496],"type":"Point"}
}