{
  "type": "Feature",
  "properties": {
    "gn:admin1_code":"4",
    "gn:asciiname":"Chah-e Alvand",
    "gn:country_code":"IR",
    "gn:dem":376,
    "gn:feature_class":"P",
    "gn:feature_code":"PPL",
    "gn:name":"Ch\u0101h-e Alvand",
    "gn:population":0,
    "gn:timezone":"Asia/Tehran",
    "iso:country":"IR",
    "name:ara_x_preferred":[
        "\u062a\u0634\u0627\u0629 \u0627\u0644\u0648\u0646\u062f"
    ],
    "name:fas_x_preferred":[
        "\u0686\u0627\u0647 \u0627\u0644\u0648\u0646\u062f"
    ],
    "name:fas_x_variant":[
        "Ch\u0101h-e Alvand"
    ],
    "wof:name":"Chah-e Alvand",
    "wof:placetype":"locality"
},
  "geometry": {"coordinates":[59.27837,27.53861],"type":"Point"}
}