{
  "type": "Feature",
  "properties": {
    "gn:admin1_code":"37",
    "gn:asciiname":"Urkat Hajji",
    "gn:country_code":"IR",
    "gn:dem":-25,
    "gn:feature_class":"P",
    "gn:feature_code":"PPL",
    "gn:name":"\u016arkat \u1e28\u0101jj\u012b",
    "gn:population":0,
    "gn:timezone":"Asia/Tehran",
    "iso:country":"IR",
    "name:fas_x_preferred":[
        "\u0648\u0631\u0643\u064e\u062a \u062d\u0627\u062c\u0651\u06cc"
    ],
    "name:fas_x_variant":[
        "\u016arkat \u1e28\u0101jj\u012b"
    ],
    "wof:name":"Urkat Hajji",
    "wof:placetype":"locality"
},
  "geometry": {"coordinates":[54.11944,36.90889],"type":"Point"}
}