{
  "type": "Feature",
  "properties": {
    "gn:admin1_code":"29",
    "gn:asciiname":"Shahidabad",
    "gn:country_code":"IR",
    "gn:dem":381,
    "gn:feature_class":"P",
    "gn:feature_code":"PPLL",
    "gn:name":"Shah\u012bd\u0101b\u0101d",
    "gn:population":0,
    "gn:timezone":"Asia/Tehran",
    "iso:country":"IR",
    "name:fas_x_preferred":[
        "\u0634\u0647\u06cc\u062f \u0622\u0628\u0627\u062f"
    ],
    "name:fas_x_variant":[
        "Shah\u012bd\u0101b\u0101d"
    ],
    "wof:name":"Shahidabad",
    "wof:placetype":"locality"
},
  "geometry": {"coordinates":[58.71758000000001,27.77073],"type":"Point"}
}