{
  "type": "Feature",
  "properties": {
    "gn:admin1_code":"29",
    "gn:asciiname":"Zarkuh",
    "gn:country_code":"IR",
    "gn:dem":2253,
    "gn:feature_class":"P",
    "gn:feature_code":"PPLF",
    "gn:name":"Z\u0101rk\u016bh",
    "gn:population":0,
    "gn:timezone":"Asia/Tehran",
    "iso:country":"IR",
    "name:fas_x_preferred":[
        "Z\u0101rk\u016bh"
    ],
    "name:fas_x_variant":[
        "\u0632\u0627\u0631\u06a9\u0648\u0647"
    ],
    "wof:name":"Zarkuh",
    "wof:placetype":"locality"
},
  "geometry": {"coordinates":[56.43912,30.53309],"type":"Point"}
}