{
  "type": "Feature",
  "properties": {
    "gn:admin1_code":"33",
    "gn:asciiname":"Darreh Masjedlu",
    "gn:country_code":"IR",
    "gn:dem":1882,
    "gn:feature_class":"P",
    "gn:feature_code":"PPL",
    "gn:name":"Darreh Masjedl\u016b",
    "gn:population":0,
    "gn:timezone":"Asia/Tehran",
    "iso:country":"IR",
    "name:fas_x_preferred":[
        "Darreh Masjedl\u016b"
    ],
    "wof:name":"Darreh Masjedlu",
    "wof:placetype":"locality"
},
  "geometry": {"coordinates":[47.23333,37.46667],"type":"Point"}
}