{
  "type": "Feature",
  "properties": {
    "gn:admin1_code":"16",
    "gn:asciiname":"Mantesh",
    "gn:country_code":"IR",
    "gn:dem":1716,
    "gn:feature_class":"P",
    "gn:feature_code":"PPL",
    "gn:name":"Mantesh",
    "gn:population":0,
    "gn:timezone":"Asia/Tehran",
    "iso:country":"IR",
    "name:fas_x_preferred":[
        "\u0645\u0646\u062a\u0634"
    ],
    "name:und_x_variant":[
        "Mantash",
        "Mantesh"
    ],
    "wof:name":"Mantesh",
    "wof:placetype":"locality"
},
  "geometry": {"coordinates":[47.65785,35.41289000000001],"type":"Point"}
}