{
  "type": "Feature",
  "properties": {
    "gn:admin1_code":"35.0",
    "gn:asciiname":"Chenar Bon",
    "gn:country_code":"IR",
    "gn:dem":-2,
    "gn:feature_class":"P",
    "gn:feature_code":"PPL",
    "gn:name":"Chen\u0101r Bon",
    "gn:population":0,
    "gn:timezone":"Asia/Tehran",
    "iso:country":"IR",
    "name:fas_x_preferred":[
        "Chen\u0101r Bon"
    ],
    "name:fas_x_variant":[
        "\u0686\u0646\u0627\u0631 \u0628\u0646",
        "\u0686\u0646\u0627\u0631\u0628\u0646"
    ],
    "name:mzn_x_preferred":[
        "\u0686\u0646\u0627\u0631\u0628\u0646"
    ],
    "wof:name":"Chenar Bon",
    "wof:placetype":"locality"
},
  "geometry": {"coordinates":[52.98383000000001,36.58727],"type":"Point"}
}