{
  "type": "Feature",
  "properties": {
    "gn:admin1_code":"33",
    "gn:asciiname":"Zardughan",
    "gn:country_code":"IR",
    "gn:dem":1707,
    "gn:feature_class":"P",
    "gn:feature_code":"PPL",
    "gn:name":"Zard\u016bgh\u0101n",
    "gn:population":0,
    "gn:timezone":"Asia/Tehran",
    "iso:country":"IR",
    "name:fas_x_preferred":[
        "Zard\u016bgh\u0101n"
    ],
    "name:fas_x_variant":[
        "\u0632\u0631\u062f\u0648\u063a\u0627\u0646",
        "\u0632\u0631\u062f\u0642\u0627\u0646"
    ],
    "name:und_x_variant":[
        "Zardeq\u0101n"
    ],
    "wof:name":"Zardughan",
    "wof:placetype":"locality"
},
  "geometry": {"coordinates":[47.09684,38.8246],"type":"Point"}
}