{
  "type": "Feature",
  "properties": {
    "gn:admin1_code":"32",
    "gn:asciiname":"Kalleh Sar-e Pa'in",
    "gn:country_code":"IR",
    "gn:dem":394,
    "gn:feature_class":"P",
    "gn:feature_code":"PPL",
    "gn:name":"Kalleh Sar-e P\u0101\u2019\u012bn",
    "gn:population":0,
    "gn:timezone":"Asia/Tehran",
    "iso:country":"IR",
    "name:ara_x_preferred":[
        "\u0643\u0644\u0647 \u0633\u0631 \u0633\u0641\u0644\u0633"
    ],
    "name:azb_x_preferred":[
        "\u0622\u0634\u0627\u063a\u0627 \u06a9\u0627\u0644\u0627\u0633\u0627\u0631"
    ],
    "name:fas_x_preferred":[
        "\u0643\u064e\u0644\u0650\u0651\u0647 \u0633\u064e\u0631\u0650 \u0633\u064f\u0641\u0644\u064e\u0649"
    ],
    "name:fas_x_variant":[
        "\u0643\u0644\u0647 \u0633\u0631 \u067e\u0627\u0626\u06cc\u0646",
        "Kalleh Sar-e Sofl\u00e1",
        "Kalleh Sar-e P\u0101\u2019\u012bn",
        "\u06a9\u0644\u0647 \u0633\u0631\u0633\u0641\u0644\u06cc"
    ],
    "name:msa_x_preferred":[
        "Kalleh Sar-e Sofla"
    ],
    "wof:name":"Kalleh Sar-e Pa'in",
    "wof:placetype":"locality"
},
  "geometry": {"coordinates":[48.1225,39.1603],"type":"Point"}
}