{
  "type": "Feature",
  "properties": {
    "gn:admin1_code":"9",
    "gn:asciiname":"Qerekhlar",
    "gn:country_code":"IR",
    "gn:dem":1655,
    "gn:feature_class":"P",
    "gn:feature_code":"PPL",
    "gn:name":"Qerekhlar",
    "gn:population":0,
    "gn:timezone":"Asia/Tehran",
    "iso:country":"IR",
    "name:fas_x_preferred":[
        "\u0642\u0631\u062e\u0644\u0631"
    ],
    "name:und_x_variant":[
        "Gherkhlar",
        "Qerekhlar",
        "Qarkhl\u0101r",
        "Qerkhlar"
    ],
    "wof:name":"Qerekhlar",
    "wof:placetype":"locality"
},
  "geometry": {"coordinates":[48.74808,35.05121],"type":"Point"}
}