{
  "type": "Feature",
  "properties": {
    "gn:admin1_code":"11",
    "gn:asciiname":"Berkeh-ye Soflin",
    "gn:country_code":"IR",
    "gn:dem":14,
    "gn:feature_class":"P",
    "gn:feature_code":"PPL",
    "gn:name":"Berkeh-ye Sofl\u012bn",
    "gn:population":0,
    "gn:timezone":"Asia/Tehran",
    "iso:country":"IR",
    "name:fas_x_preferred":[
        "\u0628\u0631\u06a9\u0647 \u0633\u0641\u0644\u064a\u0646"
    ],
    "name:fas_x_variant":[
        "Berkeh-ye Sofl\u012bn"
    ],
    "name:und_x_variant":[
        "B\u012brkeh-ye Sofl\u012bn",
        "Bandar Suflin",
        "Berkeh-e-Sefl\u012bn",
        "Berkeh-ye Sofleyn"
    ],
    "wof:name":"Berkeh-ye Soflin",
    "wof:placetype":"locality"
},
  "geometry": {"coordinates":[55.2173,26.7589],"type":"Point"}
}