{
  "type": "Feature",
  "properties": {
    "gn:admin1_code":"29.0",
    "gn:asciiname":"Darreh Bid",
    "gn:country_code":"IR",
    "gn:dem":2625,
    "gn:feature_class":"P",
    "gn:feature_code":"PPL",
    "gn:name":"Darreh B\u012bd",
    "gn:population":0,
    "gn:timezone":"Asia/Tehran",
    "iso:country":"IR",
    "name:ceb_x_preferred":[
        "Darreh Bid"
    ],
    "name:fas_x_preferred":[
        "Darreh B\u012bd"
    ],
    "name:fas_x_variant":[
        "\u062f\u0631\u0647 \u0628\u064a\u062f"
    ],
    "name:swe_x_preferred":[
        "Darreh Bid"
    ],
    "wof:name":"Darreh Bid",
    "wof:placetype":"locality"
},
  "geometry": {"coordinates":[57.14771,29.31153],"type":"Point"}
}