{
  "type": "Feature",
  "properties": {
    "gn:admin1_code":"23",
    "gn:asciiname":"Dorud",
    "gn:country_code":"IR",
    "gn:dem":1454,
    "gn:feature_class":"P",
    "gn:feature_code":"PPLA2",
    "gn:name":"Dor\u016bd",
    "gn:population":0,
    "gn:timezone":"Asia/Tehran",
    "iso:country":"IR",
    "name:ara_x_preferred":[
        "\u062f\u0648\u0631\u0648\u062f"
    ],
    "name:azb_x_preferred":[
        "\u062f\u0648\u0631\u0648\u062f"
    ],
    "name:aze_x_preferred":[
        "D\u00fcrud"
    ],
    "name:ceb_x_preferred":[
        "Dor\u016bd"
    ],
    "name:epo_x_preferred":[
        "Dorud"
    ],
    "name:fas_x_preferred":[
        "\u062f\u0648\u0631\u0648\u062f"
    ],
    "name:fas_x_variant":[
        "Dor\u016bd"
    ],
    "name:fra_x_preferred":[
        "Doroud"
    ],
    "name:hin_x_preferred":[
        "\u0926\u094b\u0930\u0942\u0926"
    ],
    "name:hun_x_preferred":[
        "Dou-Rud"
    ],
    "name:ita_x_preferred":[
        "Dorud"
    ],
    "name:jpn_x_preferred":[
        "\u30c9\u30eb\u30fc\u30c9"
    ],
    "name:kor_x_preferred":[
        "\ub3c4\ub8e8\ub4dc"
    ],
    "name:lrc_x_preferred":[
        "\u062f\u0648\u0631\u06ca\u062f"
    ],
    "name:mlg_x_preferred":[
        "Dorud"
    ],
    "name:pnb_x_preferred":[
        "\u062f\u0648\u0631\u0648\u062f"
    ],
    "name:pol_x_preferred":[
        "Dorud"
    ],
    "name:ron_x_preferred":[
        "Do Rud"
    ],
    "name:rus_x_preferred":[
        "\u0414\u043e\u0440\u0443\u0434"
    ],
    "name:swe_x_preferred":[
        "Dorud"
    ],
    "name:tgk_x_preferred":[
        "\u0414\u0443\u0440\u04ef\u0434"
    ],
    "name:tur_x_preferred":[
        "Dorud"
    ],
    "name:ukr_x_preferred":[
        "\u0414\u043e\u0440\u0443\u0434"
    ],
    "name:und_x_variant":[
        "Dow R\u016bd",
        "D\u016br\u016bd",
        "Dorood Garan"
    ],
    "name:urd_x_preferred":[
        "\u062f\u0648\u0631\u0648\u062f"
    ],
    "name:zho_x_preferred":[
        "\u9053\u9b6f\u5fb7"
    ],
    "wof:name":"Dorud",
    "wof:placetype":"locality"
},
  "geometry": {"coordinates":[49.0616,33.49218],"type":"Point"}
}