{
  "type": "Feature",
  "properties": {
    "gn:admin1_code":"23",
    "gn:asciiname":"Dorud",
    "gn:country_code":"IR",
    "gn:dem":1454,
    "gn:feature_class":"P",
    "gn:feature_code":"PPLA2",
    "gn:name":"Dor\u016bd",
    "gn:population":0,
    "gn:timezone":"Asia/Tehran",
    "iso:country":"IR",
    "name:fas_x_preferred":[
        "\u062f\u0648\u0631\u0648\u062f"
    ],
    "name:fas_x_variant":[
        "Dor\u016bd"
    ],
    "name:und_x_variant":[
        "Dow R\u016bd",
        "D\u016br\u016bd",
        "Dorood Garan"
    ],
    "wof:name":"Dorud",
    "wof:placetype":"locality"
},
  "geometry": {"coordinates":[49.0616,33.49218],"type":"Point"}
}