{
  "type": "Feature",
  "properties": {
    "gn:admin1_code":"7",
    "gn:asciiname":"Deh-e Kohneh",
    "gn:country_code":"IR",
    "gn:dem":1708,
    "gn:feature_class":"P",
    "gn:feature_code":"PPL",
    "gn:name":"Deh-e Kohneh",
    "gn:population":0,
    "gn:timezone":"Asia/Tehran",
    "iso:country":"IR",
    "name:fas_x_preferred":[
        "\u067e\u0627\u0644\u0646\u06af\u0631\u06cc \u06a9\u0647\u0646\u0647"
    ],
    "name:fas_x_variant":[
        "P\u0101langar\u012b-ye Kohneh",
        "\u062f\u0647 \u06a9\u0647\u0646\u0647"
    ],
    "wof:name":"Deh-e Kohneh",
    "wof:placetype":"locality"
},
  "geometry": {"coordinates":[52.2837,30.3155],"type":"Point"}
}