{
  "type": "Feature",
  "properties": {
    "gn:admin1_code":"11.0",
    "gn:asciiname":"Bagh-e Bala",
    "gn:country_code":"IR",
    "gn:dem":41,
    "gn:feature_class":"P",
    "gn:feature_code":"PPL",
    "gn:name":"B\u0101gh-e B\u0101l\u0101",
    "gn:population":0,
    "gn:timezone":"Asia/Tehran",
    "iso:country":"IR",
    "name:fas_x_preferred":[
        "\u0628\u0627\u063a \u0628\u0627\u0644\u0627"
    ],
    "name:fas_x_variant":[
        "B\u0101gh-e B\u0101l\u0101"
    ],
    "name:msa_x_preferred":[
        "Bagh-e Bala"
    ],
    "name:und_x_variant":[
        "B\u0101gh B\u0101l\u0101"
    ],
    "wof:name":"Bagh-e Bala",
    "wof:placetype":"locality"
},
  "geometry": {"coordinates":[56.0325,26.8826],"type":"Point"}
}