{
  "type": "Feature",
  "properties": {
    "gn:admin1_code":"15",
    "gn:asciiname":"Toveyhat",
    "gn:country_code":"IR",
    "gn:dem":5,
    "gn:feature_class":"P",
    "gn:feature_code":"PPL",
    "gn:name":"\u0162ovey\u1e29\u0101t",
    "gn:population":0,
    "gn:timezone":"Asia/Tehran",
    "iso:country":"IR",
    "name:fas_x_preferred":[
        "\u0637\u0648\u06cc\u062d\u0627\u062a"
    ],
    "name:fas_x_variant":[
        "\u0162oveyj\u0101t",
        "\u0162ovey\u1e29\u0101t"
    ],
    "name:und_x_variant":[
        "Tavijat"
    ],
    "wof:name":"Toveyhat",
    "wof:placetype":"locality"
},
  "geometry": {"coordinates":[48.18901,30.40991],"type":"Point"}
}