{
  "type": "Feature",
  "properties": {
    "gn:admin1_code":"5",
    "gn:asciiname":"Cham Gharbi",
    "gn:country_code":"IR",
    "gn:dem":1501,
    "gn:feature_class":"P",
    "gn:feature_code":"PPL",
    "gn:name":"Cham Gharb\u012b",
    "gn:population":0,
    "gn:timezone":"Asia/Tehran",
    "iso:country":"IR",
    "name:fas_x_preferred":[
        "Cham Gharb\u012b"
    ],
    "name:fas_x_variant":[
        "Cham \u2018Arab\u012b",
        "\u0686\u0645 \u063a\u0631\u0628\u06cc"
    ],
    "wof:name":"Cham Gharbi",
    "wof:placetype":"locality"
},
  "geometry": {"coordinates":[51.2638,30.93967],"type":"Point"}
}