{
  "type": "Feature",
  "properties": {
    "gn:admin1_code":"8",
    "gn:asciiname":"Gol Sarak-e Saravan",
    "gn:country_code":"IR",
    "gn:dem":117,
    "gn:feature_class":"P",
    "gn:feature_code":"PPL",
    "gn:name":"Gol Sarak-e Sar\u0101v\u0101n",
    "gn:population":0,
    "gn:timezone":"Asia/Tehran",
    "iso:country":"IR",
    "name:fas_x_preferred":[
        "Gol Sarak-e Sar\u0101v\u0101n"
    ],
    "wof:name":"Gol Sarak-e Saravan",
    "wof:placetype":"locality"
},
  "geometry": {"coordinates":[49.63389,37.02889],"type":"Point"}
}