{
  "type": "Feature",
  "properties": {
    "gn:admin1_code":"29",
    "gn:asciiname":"Tolombeh-ye Manshurabad",
    "gn:country_code":"IR",
    "gn:dem":1707,
    "gn:feature_class":"P",
    "gn:feature_code":"PPL",
    "gn:name":"Tolombeh-ye Mansh\u016br\u0101b\u0101d",
    "gn:population":0,
    "gn:timezone":"Asia/Tehran",
    "iso:country":"IR",
    "name:fas_x_preferred":[
        "Tolombeh-ye Mansh\u016br\u0101b\u0101d"
    ],
    "wof:name":"Tolombeh-ye Manshurabad",
    "wof:placetype":"locality"
},
  "geometry": {"coordinates":[55.52972,29.49028],"type":"Point"}
}