{
  "type": "Feature",
  "properties": {
    "gn:admin1_code":"15.0",
    "gn:asciiname":"`Ammeh",
    "gn:country_code":"IR",
    "gn:dem":8,
    "gn:feature_class":"P",
    "gn:feature_code":"PPL",
    "gn:name":"\u2018Ammeh",
    "gn:population":0,
    "gn:timezone":"Asia/Tehran",
    "iso:country":"IR",
    "name:fas_x_preferred":[
        "\u2018Ameh"
    ],
    "name:fas_x_variant":[
        "\u2018Ammeh",
        "\u0639\u0645\u0647"
    ],
    "wof:name":"`Ammeh",
    "wof:placetype":"locality"
},
  "geometry": {"coordinates":[48.78181,30.76509],"type":"Point"}
}