{
  "type": "Feature",
  "properties": {
    "gn:admin1_code":"7",
    "gn:asciiname":"Qanat Bagh",
    "gn:country_code":"IR",
    "gn:dem":753,
    "gn:feature_class":"P",
    "gn:feature_code":"PPL",
    "gn:name":"Qan\u0101t B\u0101gh",
    "gn:population":0,
    "gn:timezone":"Asia/Tehran",
    "iso:country":"IR",
    "name:ara_x_preferred":[
        "\u0642\u0646\u0627\u062a\u0628\u0627\u063a"
    ],
    "name:fas_x_preferred":[
        "Qan\u0101t B\u0101gh"
    ],
    "name:fas_x_variant":[
        "\u0642\u0646\u0627\u062a \u0628\u0627\u063a",
        "\u0642\u0646\u0627\u062a\u0628\u0627\u063a"
    ],
    "name:msa_x_preferred":[
        "Qanat Bagh"
    ],
    "name:und_x_variant":[
        "Qan\u0101t-i-B\u0101gh"
    ],
    "wof:name":"Qanat Bagh",
    "wof:placetype":"locality"
},
  "geometry": {"coordinates":[51.87683,29.0676],"type":"Point"}
}