{
  "type": "Feature",
  "properties": {
    "gn:admin1_code":"26.0",
    "gn:asciiname":"Shamsabad",
    "gn:country_code":"IR",
    "gn:dem":1106,
    "gn:feature_class":"P",
    "gn:feature_code":"PPL",
    "gn:name":"Shams\u0101b\u0101d",
    "gn:population":0,
    "gn:timezone":"Asia/Tehran",
    "iso:country":"IR",
    "name:fas_x_preferred":[
        "\u0634\u0645\u0633 \u0622\u0628\u0627\u062f"
    ],
    "name:fas_x_variant":[
        "Shams\u0101b\u0101d",
        "\u0634\u0645\u0633\u200c\u0622\u0628\u0627\u062f"
    ],
    "wof:name":"Shamsabad",
    "wof:placetype":"locality"
},
  "geometry": {"coordinates":[51.2719,35.6233],"type":"Point"}
}