{
  "type": "Feature",
  "properties": {
    "gn:admin1_code":"4",
    "gn:asciiname":"Garm Bit-e Pain",
    "gn:country_code":"IR",
    "gn:dem":84,
    "gn:feature_class":"P",
    "gn:feature_code":"PPL",
    "gn:name":"Garm B\u012bt-e P\u0101\u012bn",
    "gn:population":0,
    "gn:timezone":"Asia/Tehran",
    "iso:country":"IR",
    "name:ara_x_preferred":[
        "\u063a\u0631\u0645\u200c\u0628\u064a\u062a \u0628\u0627\u064a\u064a\u0646"
    ],
    "name:fas_x_preferred":[
        "\u06af\u0631\u0645 \u0628\u06cc\u062a \u067e\u0627\u0626\u06cc\u0646"
    ],
    "name:fas_x_variant":[
        "Garm B\u012bt-e P\u0101\u012bn",
        "\u06af\u0631\u0645\u200c\u0628\u06cc\u062a \u067e\u0627\u06cc\u06cc\u0646"
    ],
    "wof:name":"Garm Bit-e Pain",
    "wof:placetype":"locality"
},
  "geometry": {"coordinates":[61.5187,25.8643],"type":"Point"}
}