{
  "type": "Feature",
  "properties": {
    "gn:admin1_code":"11.0",
    "gn:asciiname":"Nareh",
    "gn:country_code":"IR",
    "gn:dem":69,
    "gn:feature_class":"P",
    "gn:feature_code":"PPL",
    "gn:name":"Nareh",
    "gn:population":0,
    "gn:timezone":"Asia/Tehran",
    "iso:country":"IR",
    "name:ceb_x_preferred":[
        "Nareh"
    ],
    "name:fas_x_preferred":[
        "\u0646\u0631\u0647"
    ],
    "name:msa_x_preferred":[
        "Nareh"
    ],
    "name:swe_x_preferred":[
        "Nareh"
    ],
    "wof:name":"Nareh",
    "wof:placetype":"locality"
},
  "geometry": {"coordinates":[55.56325,27.26376],"type":"Point"}
}