{
  "type": "Feature",
  "properties": {
    "gn:admin1_code":"15",
    "gn:asciiname":"Hasasaneh-ye Yek",
    "gn:country_code":"IR",
    "gn:dem":13,
    "gn:feature_class":"P",
    "gn:feature_code":"PPL",
    "gn:name":"\u1e28as\u0101saneh-ye Yek",
    "gn:population":0,
    "gn:timezone":"Asia/Tehran",
    "iso:country":"IR",
    "name:fas_x_preferred":[
        "\u062d\u0633\u0627\u0633\u0646\u0647 \u06cc\u06a9"
    ],
    "name:fas_x_variant":[
        "\u1e28as\u0101saneh-ye B\u0101l\u0101",
        "\u1e28as\u0101saneh-ye Yek",
        "\u062d\u0633\u0627\u0633\u0646\u0647 \u0628\u0627\u0644\u0627"
    ],
    "wof:name":"Hasasaneh-ye Yek",
    "wof:placetype":"locality"
},
  "geometry": {"coordinates":[48.0359,31.5073],"type":"Point"}
}