{
  "type": "Feature",
  "properties": {
    "gn:admin1_code":"4",
    "gn:asciiname":"Shir Sar",
    "gn:country_code":"IR",
    "gn:dem":983,
    "gn:feature_class":"P",
    "gn:feature_code":"PPL",
    "gn:name":"Sh\u012br Sar",
    "gn:population":0,
    "gn:timezone":"Asia/Tehran",
    "iso:country":"IR",
    "name:fas_x_preferred":[
        "Sh\u012br Sar"
    ],
    "name:fas_x_variant":[
        "\u0634\u06cc\u0631 \u0633\u0631"
    ],
    "name:und_x_variant":[
        "\u0634\u06cc\u0631 \u0633\u0631"
    ],
    "wof:name":"Shir Sar",
    "wof:placetype":"locality"
},
  "geometry": {"coordinates":[60.94406,26.44495],"type":"Point"}
}