{
  "type": "Feature",
  "properties": {
    "gn:admin1_code":"29",
    "gn:asciiname":"Puraz",
    "gn:country_code":"IR",
    "gn:dem":2370,
    "gn:feature_class":"P",
    "gn:feature_code":"PPL",
    "gn:name":"P\u016br\u0101z",
    "gn:population":0,
    "gn:timezone":"Asia/Tehran",
    "iso:country":"IR",
    "name:fas_x_preferred":[
        "Y\u016br\u0101s"
    ],
    "name:fas_x_variant":[
        "\u067e\u0648\u0631\u0627\u0632"
    ],
    "name:und_x_variant":[
        "P\u016br\u0101z"
    ],
    "wof:name":"Puraz",
    "wof:placetype":"locality"
},
  "geometry": {"coordinates":[55.38968000000001,30.25295],"type":"Point"}
}