{
  "type": "Feature",
  "properties": {
    "gn:admin1_code":"8.0",
    "gn:asciiname":"Sajiran",
    "gn:country_code":"IR",
    "gn:dem":762,
    "gn:feature_class":"P",
    "gn:feature_code":"PPL",
    "gn:name":"Saj\u012br\u0101n",
    "gn:population":0,
    "gn:timezone":"Asia/Tehran",
    "iso:country":"IR",
    "name:ceb_x_preferred":[
        "Saj\u012br\u0101n"
    ],
    "name:fas_x_preferred":[
        "Saj\u012br\u0101n"
    ],
    "name:fas_x_variant":[
        "S\u012b Jeyr\u0101n",
        "\u0633\u06cc \u062c\u06cc\u0631\u0627\u0646",
        "\u0633\u062c\u06cc\u0631\u0627\u0646"
    ],
    "name:msa_x_preferred":[
        "Sajiran"
    ],
    "name:swe_x_preferred":[
        "Saj\u012br\u0101n"
    ],
    "name:ukr_x_preferred":[
        "\u0421\u0430\u0434\u0436\u0456\u0440\u0430\u043d"
    ],
    "wof:name":"Sajiran",
    "wof:placetype":"locality"
},
  "geometry": {"coordinates":[50.23775,36.88192],"type":"Point"}
}