{
  "type": "Feature",
  "properties": {
    "gn:admin1_code":"8",
    "gn:asciiname":"Gijav",
    "gn:country_code":"IR",
    "gn:dem":257,
    "gn:feature_class":"P",
    "gn:feature_code":"PPL",
    "gn:name":"G\u012bj\u0101v",
    "gn:population":0,
    "gn:timezone":"Asia/Tehran",
    "iso:country":"IR",
    "name:ceb_x_preferred":[
        "G\u012bjow"
    ],
    "name:fas_x_preferred":[
        "\u06af\u06cc\u062c\u0648"
    ],
    "name:fas_x_variant":[
        "G\u012bjow",
        "\u06af\u06cc\u062c\u0627\u0648"
    ],
    "name:msa_x_preferred":[
        "Gijow"
    ],
    "name:swe_x_preferred":[
        "G\u012bjow"
    ],
    "name:ukr_x_preferred":[
        "\u0490\u0456\u0434\u0436\u0443"
    ],
    "name:und_x_variant":[
        "G\u012bj\u016b",
        "G\u012bj\u0101v"
    ],
    "wof:name":"Gijav",
    "wof:placetype":"locality"
},
  "geometry": {"coordinates":[48.8568,37.6905],"type":"Point"}
}