{
  "type": "Feature",
  "properties": {
    "gn:admin1_code":"29.0",
    "gn:asciiname":"Salman Shahr",
    "gn:country_code":"IR",
    "gn:dem":2087,
    "gn:feature_class":"P",
    "gn:feature_code":"PPL",
    "gn:name":"Salm\u0101n Shahr",
    "gn:population":0,
    "gn:timezone":"Asia/Tehran",
    "iso:country":"IR",
    "name:ara_x_preferred":[
        "\u0633\u0644\u0645\u0627\u0646 \u0634\u0647\u0631"
    ],
    "name:aze_x_preferred":[
        "S\u0259lman\u015f\u0259hr"
    ],
    "name:ceb_x_preferred":[
        "Motel Q\u016b"
    ],
    "name:fas_x_preferred":[
        "\u0633\u0644\u0645\u0627\u0646 \u0634\u0647\u0631"
    ],
    "name:fas_x_variant":[
        "\u0633\u0644\u0645\u0627\u0646\u200c\u0634\u0647\u0631"
    ],
    "name:ita_x_preferred":[
        "Salman Shahr"
    ],
    "name:mlg_x_preferred":[
        "Salman Shahr"
    ],
    "name:mzn_x_preferred":[
        "\u0633\u0644\u0645\u0627\u0646\u200c\u0634\u0647\u0631"
    ],
    "name:por_x_preferred":[
        "Salman Shahr"
    ],
    "name:swe_x_preferred":[
        "Motel Q\u016b"
    ],
    "name:tur_x_preferred":[
        "Selman\u015fehr"
    ],
    "name:und_x_variant":[
        "Salm\u0101n Shahr"
    ],
    "wof:name":"Salman Shahr",
    "wof:placetype":"locality"
},
  "geometry": {"coordinates":[56.37944,31.14503],"type":"Point"}
}