{
  "type": "Feature",
  "properties": {
    "gn:admin1_code":"0",
    "gn:asciiname":"Chah Morid",
    "gn:country_code":"IR",
    "gn:dem":532,
    "gn:feature_class":"P",
    "gn:feature_code":"PPL",
    "gn:name":"Ch\u0101h Mor\u012bd",
    "gn:population":0,
    "gn:timezone":"Asia/Tehran",
    "iso:country":"IR",
    "name:fas_x_preferred":[
        "\u0686\u0627\u0647 \u0645\u0631\u06cc\u062f"
    ],
    "name:fas_x_variant":[
        "Ch\u0101h Mor\u012bd"
    ],
    "wof:name":"Chah Morid",
    "wof:placetype":"locality"
},
  "geometry": {"coordinates":[57.5544,27.9408],"type":"Point"}
}