{
  "type": "Feature",
  "properties": {
    "gn:admin1_code":"16.0",
    "gn:asciiname":"Allah Darreh-ye `Olya",
    "gn:country_code":"IR",
    "gn:dem":2114,
    "gn:feature_class":"P",
    "gn:feature_code":"PPL",
    "gn:name":"All\u0101h Darreh-ye \u2018Oly\u0101",
    "gn:population":0,
    "gn:timezone":"Asia/Tehran",
    "iso:country":"IR",
    "name:fas_x_preferred":[
        "\u0627\u064e\u0644\u0651\u0627\u0647 \u062f\u064e\u0631\u0650\u0651\u06c0 \u0639\u064f\u0644\u064a\u0627"
    ],
    "name:fas_x_variant":[
        "\u0647\u0627\u0644\u0650\u0647 \u062f\u064e\u0631\u0650\u0651\u06c0 \u0627\u064f\u0644\u064a\u0627",
        "\u0622\u0644\u0650\u0647 \u062f\u064e\u0631\u0650\u0651\u0647 \u0628\u0627\u0644\u0627",
        "\u062d\u064e\u0644\u0650\u0647 \u062f\u064e\u0631\u0650\u0651\u0647",
        "\u0647\u064e\u0644\u064e \u062f\u064e\u0631\u0650\u0651\u0647",
        "\u0622\u0644\u064e\u0647 \u062f\u064e\u0631\u0650\u0651\u06c0 \u0628\u064e\u0644\u0627",
        "\u0627\u064e\u0644\u0651\u0627\u0647 \u062f\u064e\u0631\u0650\u0651\u06c0 \u0628\u0627\u0644\u0627",
        "All\u0101h Darreh-ye \u2018Oly\u0101"
    ],
    "name:und_x_variant":[
        "H\u0101leh Darreh-ye Oly\u0101",
        "\u0100lah Darreh-ye Bal\u0101",
        "\u1e28aleh Darreh",
        "All\u0101h Darreh-ye B\u0101l\u0101",
        "Hala Darreh",
        "\u0100leh Darreh B\u0101l\u0101"
    ],
    "wof:name":"Allah Darreh-ye `Olya",
    "wof:placetype":"locality"
},
  "geometry": {"coordinates":[46.96667,35.76667],"type":"Point"}
}