{
  "type": "Feature",
  "properties": {
    "gn:admin1_code":"41",
    "gn:asciiname":"Haft Gowd",
    "gn:country_code":"IR",
    "gn:dem":656,
    "gn:feature_class":"P",
    "gn:feature_code":"PPL",
    "gn:name":"Haft Gowd",
    "gn:population":0,
    "gn:timezone":"Asia/Tehran",
    "iso:country":"IR",
    "name:und_x_variant":[
        "Haft G\u016bd",
        "Haft Gowd"
    ],
    "wof:name":"Haft Gowd",
    "wof:placetype":"locality"
},
  "geometry": {"coordinates":[57.88528,31.72806],"type":"Point"}
}