{
  "type": "Feature",
  "properties": {
    "gn:admin1_code":"1.0",
    "gn:asciiname":"Qareh Bolagh-e `Olya",
    "gn:country_code":"IR",
    "gn:dem":1557,
    "gn:feature_class":"P",
    "gn:feature_code":"PPL",
    "gn:name":"Qareh Bol\u0101gh-e \u2018Oly\u0101",
    "gn:population":0,
    "gn:timezone":"Asia/Tehran",
    "iso:country":"IR",
    "name:fas_x_preferred":[
        "\u0642\u064e\u0631\u0650\u0647 \u0628\u064f\u0644\u0627\u063a\u0650 \u0639\u064f\u0644\u064a\u0627"
    ],
    "name:fas_x_variant":[
        "\u0642\u0631\u0647 \u0628\u0644\u0627\u063a \u0639\u0644\u064a\u0627",
        "Qareh Bol\u0101gh-e \u2018Oly\u0101"
    ],
    "wof:name":"Qareh Bolagh-e `Olya",
    "wof:placetype":"locality"
},
  "geometry": {"coordinates":[46.4848,36.85],"type":"Point"}
}