{
  "type": "Feature",
  "properties": {
    "gn:admin1_code":"26.0",
    "gn:asciiname":"Beryanchal",
    "gn:country_code":"IR",
    "gn:dem":1797,
    "gn:feature_class":"P",
    "gn:feature_code":"PPL",
    "gn:name":"Bery\u0101nch\u0101l",
    "gn:population":0,
    "gn:timezone":"Asia/Tehran",
    "iso:country":"IR",
    "name:fas_x_preferred":[
        "\u0628\u0650\u0631\u064a\u0627\u0646\u0686\u0627\u0644"
    ],
    "wof:name":"Beryanchal",
    "wof:placetype":"locality"
},
  "geometry": {"coordinates":[50.98333,35.96667],"type":"Point"}
}