{
  "type": "Feature",
  "properties": {
    "gn:admin1_code":"7.0",
    "gn:asciiname":"Amirabad",
    "gn:country_code":"IR",
    "gn:dem":1610,
    "gn:feature_class":"P",
    "gn:feature_code":"PPL",
    "gn:name":"Am\u012br\u0101b\u0101d",
    "gn:population":0,
    "gn:timezone":"Asia/Tehran",
    "iso:country":"IR",
    "name:ara_x_preferred":[
        "\u0623\u0645\u064a\u0631 \u0623\u0628\u0627\u062f"
    ],
    "name:aze_x_preferred":[
        "\u018fmirabad"
    ],
    "name:ceb_x_preferred":[
        "Amirabad"
    ],
    "name:fas_x_preferred":[
        "Am\u012br\u0101b\u0101d"
    ],
    "name:fas_x_variant":[
        "\u0627\u0645\u06cc\u0631 \u0622\u0628\u0627\u062f",
        "\u0627\u0645\u06cc\u0631\u0622\u0628\u0627\u062f"
    ],
    "name:mzn_x_preferred":[
        "\u0627\u0645\u06cc\u0631\u0622\u0628\u0627\u062f"
    ],
    "name:swe_x_preferred":[
        "Amirabad"
    ],
    "name:und_x_variant":[
        "\u0627\u0645\u06cc\u0631 \u0622\u0628\u0627\u062f"
    ],
    "wof:name":"Amirabad",
    "wof:placetype":"locality"
},
  "geometry": {"coordinates":[52.4516,30.0911],"type":"Point"}
}