{
  "type": "Feature",
  "properties": {
    "gn:admin1_code":"29",
    "gn:asciiname":"Javaran",
    "gn:cc2":"IR",
    "gn:country_code":"IR",
    "gn:dem":2538,
    "gn:feature_class":"P",
    "gn:feature_code":"PPL",
    "gn:name":"Jav\u0101r\u0101n",
    "gn:population":0,
    "gn:timezone":"Asia/Tehran",
    "iso:country":"IR",
    "name:ceb_x_preferred":[
        "Jav\u0101r\u0101n"
    ],
    "name:fas_x_preferred":[
        "Jav\u0101r\u0101n"
    ],
    "name:fas_x_variant":[
        "\u062c\u0648\u0627\u0631\u0627\u0646"
    ],
    "name:swe_x_preferred":[
        "Jav\u0101r\u0101n"
    ],
    "name:und_x_variant":[
        "Jaw\u0101r\u016bn"
    ],
    "name:urd_x_preferred":[
        "\u062c\u0648\u0627\u0631\u0627\u0646"
    ],
    "wof:name":"Javaran",
    "wof:placetype":"locality"
},
  "geometry": {"coordinates":[56.98444,29.32528],"type":"Point"}
}