{
  "type": "Feature",
  "properties": {
    "gn:admin1_code":"25",
    "gn:asciiname":"Qal`eh-ye Seddiq",
    "gn:country_code":"IR",
    "gn:dem":1241,
    "gn:feature_class":"P",
    "gn:feature_code":"PPL",
    "gn:name":"Qal\u2018eh-ye \u015eedd\u012bq",
    "gn:population":0,
    "gn:timezone":"Asia/Tehran",
    "iso:country":"IR",
    "name:fas_x_preferred":[
        "Qal\u2018eh-ye \u015eedd\u012bq"
    ],
    "name:fas_x_variant":[
        "\u0642\u0644\u0639\u0647 \u0635\u062f\u06cc\u0642"
    ],
    "wof:name":"Qal`eh-ye Seddiq",
    "wof:placetype":"locality"
},
  "geometry": {"coordinates":[54.96916,36.34309],"type":"Point"}
}