{
  "type": "Feature",
  "properties": {
    "gn:admin1_code":"5.0",
    "gn:asciiname":"Deh-e Bonar-e Sofla",
    "gn:country_code":"IR",
    "gn:dem":1087,
    "gn:feature_class":"P",
    "gn:feature_code":"PPL",
    "gn:name":"Deh-e Bon\u0101r-e Sofl\u00e1",
    "gn:population":0,
    "gn:timezone":"Asia/Tehran",
    "iso:country":"IR",
    "name:fas_x_preferred":[
        "\u062f\u0647 \u0628\u0646\u0627\u0631 \u0633\u0641\u0644\u06cc"
    ],
    "name:und_x_variant":[
        "Deh-e Bon\u0101r-e Sofl\u00e1"
    ],
    "wof:name":"Deh-e Bonar-e Sofla",
    "wof:placetype":"locality"
},
  "geometry": {"coordinates":[50.23152,31.03593],"type":"Point"}
}