{
  "type": "Feature",
  "properties": {
    "gn:admin1_code":"35",
    "gn:asciiname":"Ganeh",
    "gn:country_code":"IR",
    "gn:dem":-21,
    "gn:feature_class":"P",
    "gn:feature_code":"PPL",
    "gn:name":"G\u0101neh",
    "gn:population":0,
    "gn:timezone":"Asia/Tehran",
    "iso:country":"IR",
    "name:fas_x_preferred":[
        "\u0643\u0627\u0644\u0650\u0647"
    ],
    "name:fas_x_variant":[
        "K\u0101leh",
        "G\u0101neh",
        "\u06af\u0627\u0646\u0647"
    ],
    "wof:name":"Ganeh",
    "wof:placetype":"locality"
},
  "geometry": {"coordinates":[52.74800000000001,36.694],"type":"Point"}
}