{
  "type": "Feature",
  "properties": {
    "gn:admin1_code":"29",
    "gn:asciiname":"Get Maran",
    "gn:country_code":"IR",
    "gn:dem":980,
    "gn:feature_class":"P",
    "gn:feature_code":"PPL",
    "gn:name":"Get Mar\u0101n",
    "gn:population":0,
    "gn:timezone":"Asia/Tehran",
    "iso:country":"IR",
    "name:fas_x_preferred":[
        "Get Mar\u0101n"
    ],
    "wof:name":"Get Maran",
    "wof:placetype":"locality"
},
  "geometry": {"coordinates":[58.4925,26.66333],"type":"Point"}
}