{
  "type": "Feature",
  "properties": {
    "gn:admin1_code":"5.0",
    "gn:asciiname":"Meleh Chaharrah",
    "gn:country_code":"IR",
    "gn:dem":2073,
    "gn:feature_class":"P",
    "gn:feature_code":"PPL",
    "gn:name":"Meleh Chah\u0101rrah",
    "gn:population":0,
    "gn:timezone":"Asia/Tehran",
    "iso:country":"IR",
    "name:fas_x_preferred":[
        "\u0645\u0644\u0647 \u0686\u0647\u0627\u0631\u0631\u0647"
    ],
    "name:und_x_variant":[
        "Meleh Chah\u0101rrah"
    ],
    "wof:name":"Meleh Chaharrah",
    "wof:placetype":"locality"
},
  "geometry": {"coordinates":[50.68604000000001,31.17321],"type":"Point"}
}