{
  "type": "Feature",
  "properties": {
    "gn:admin1_code":"33.0",
    "gn:asciiname":"Sardar Rashid Mehdi-ye Bakeri",
    "gn:country_code":"IR",
    "gn:dem":1316,
    "gn:feature_class":"P",
    "gn:feature_code":"PPL",
    "gn:name":"Sard\u0101r R\u0101sh\u012bd Mehd\u012b-ye B\u0101ker\u012b",
    "gn:population":0,
    "gn:timezone":"Asia/Tehran",
    "iso:country":"IR",
    "name:fas_x_preferred":[
        "Sard\u0101r R\u0101sh\u012bd Mehd\u012b-ye B\u0101ker\u012b"
    ],
    "wof:name":"Sardar Rashid Mehdi-ye Bakeri",
    "wof:placetype":"locality"
},
  "geometry": {"coordinates":[48.26528,37.28139],"type":"Point"}
}