{
  "type": "Feature",
  "properties": {
    "gn:admin1_code":"5",
    "gn:asciiname":"Dar Boland",
    "gn:country_code":"IR",
    "gn:dem":826,
    "gn:feature_class":"P",
    "gn:feature_code":"PPL",
    "gn:name":"D\u0101r Boland",
    "gn:population":0,
    "gn:timezone":"Asia/Tehran",
    "iso:country":"IR",
    "name:fas_x_preferred":[
        "D\u0101r Boland"
    ],
    "name:fas_x_variant":[
        "\u062f\u0627\u0631 \u0628\u0644\u0646\u062f"
    ],
    "wof:name":"Dar Boland",
    "wof:placetype":"locality"
},
  "geometry": {"coordinates":[50.31745,30.80176],"type":"Point"}
}