{
  "type": "Feature",
  "properties": {
    "gn:admin1_code":"3",
    "gn:asciiname":"Bard-e Karkhaneh",
    "gn:country_code":"IR",
    "gn:dem":1927,
    "gn:feature_class":"P",
    "gn:feature_code":"PPL",
    "gn:name":"Bard-e K\u0101rkh\u0101neh",
    "gn:population":0,
    "gn:timezone":"Asia/Tehran",
    "iso:country":"IR",
    "name:fas_x_preferred":[
        "Bard-e K\u0101rkh\u0101neh"
    ],
    "name:fas_x_variant":[
        "\u0628\u064e\u0631\u062f\u0650 \u0643\u0627\u0631\u062e\u0627\u0646\u0650\u0647",
        "Bar-e K\u0101rkh\u0101neh",
        "\u0628\u0631 \u0643\u0627\u0631\u062e\u0627\u0646\u0647",
        "\u0628\u0631\u062f \u06a9\u0627\u0631\u062e\u0627\u0646\u0647"
    ],
    "name:und_x_variant":[
        "\u0628\u0631 \u0643\u0627\u0631\u062e\u0627\u0646\u0647"
    ],
    "wof:name":"Bard-e Karkhaneh",
    "wof:placetype":"locality"
},
  "geometry": {"coordinates":[50.70722,31.4774],"type":"Point"}
}