{
  "type": "Feature",
  "properties": {
    "gn:admin1_code":"7",
    "gn:asciiname":"Baleh Kareh",
    "gn:country_code":"IR",
    "gn:dem":330,
    "gn:feature_class":"P",
    "gn:feature_code":"PPL",
    "gn:name":"Baleh Kareh",
    "gn:population":0,
    "gn:timezone":"Asia/Tehran",
    "iso:country":"IR",
    "name:fas_x_preferred":[
        "\u0628\u0644\u0647 \u06a9\u0631\u0647"
    ],
    "wof:name":"Baleh Kareh",
    "wof:placetype":"locality"
},
  "geometry": {"coordinates":[52.5372,27.8943],"type":"Point"}
}