{
  "type": "Feature",
  "properties": {
    "gn:admin1_code":"23",
    "gn:asciiname":"Mirzavand",
    "gn:country_code":"IR",
    "gn:dem":1264,
    "gn:feature_class":"P",
    "gn:feature_code":"PPL",
    "gn:name":"M\u012brz\u0101vand",
    "gn:population":0,
    "gn:timezone":"Asia/Tehran",
    "iso:country":"IR",
    "name:fas_x_preferred":[
        "\u0645\u064a\u0631\u0632\u0627\u0648\u064e\u0646\u062f\u0650 \u064a\u0650\u0643"
    ],
    "name:fas_x_variant":[
        "\u0686\u06af\u0647 \u0645\u064a\u0631\u0632\u0627\u0648\u0646\u062f",
        "\u0645\u06cc\u0631\u0632\u0627\u0648\u0646\u062f",
        "\u0633\u0631\u0627\u0628\u0686\u06af\u0647",
        "\u0633\u064e\u0631\u0627\u0628\u0650 \u0686\u0650\u0643\u0650\u0651\u06c0 \u0628\u0627\u0644\u0627",
        "\u0686\u064e\u063a\u064e",
        "\u0633\u064e\u0631\u0627\u0628\u0650 \u0686\u0650\u0643\u0650\u0651\u06c0 \u0639\u064f\u0644\u064a\u0627",
        "\u0633\u064e\u0631\u064e\u0628 \u0686\u064e\u0643\u0650\u0647",
        "\u0633\u064e\u0631\u0627\u0628\u0650 \u0686\u0650\u0643\u0650\u0651\u0647"
    ],
    "name:und_x_variant":[
        "M\u012brz\u0101vand",
        "M\u012brz\u0101vand-e Yek",
        "Chegeh M\u012brz\u0101vand",
        "\u0686\u06af\u0647 \u0645\u064a\u0631\u0632\u0627\u0648\u0646\u062f",
        "Sar\u0101bchegeh",
        "Sar\u0101b-e Chekkeh-ye B\u0101l\u0101",
        "Chagha",
        "Sar\u0101b-e Chekkeh-ye \u2018Oly\u0101",
        "Sarab Chakeh",
        "Sar\u0101b-e Chekkeh"
    ],
    "wof:name":"Mirzavand",
    "wof:placetype":"locality"
},
  "geometry": {"coordinates":[48.0576,33.5962],"type":"Point"}
}