{
  "type": "Feature",
  "properties": {
    "gn:admin1_code":"36",
    "gn:asciiname":"Amabad",
    "gn:country_code":"IR",
    "gn:dem":1637,
    "gn:feature_class":"P",
    "gn:feature_code":"PPL",
    "gn:name":"Am\u0101b\u0101d",
    "gn:population":0,
    "gn:timezone":"Asia/Tehran",
    "iso:country":"IR",
    "name:azb_x_preferred":[
        "\u0627\u0645 \u0622\u0628\u0627\u062f"
    ],
    "name:fas_x_preferred":[
        "\u0627\u0645 \u0622\u0628\u0627\u062f"
    ],
    "name:fas_x_variant":[
        "Am\u0101b\u0101d",
        "Omm\u0101b\u0101d",
        "\u0627\u0645\u200c\u0622\u0628\u0627\u062f"
    ],
    "wof:name":"Amabad",
    "wof:placetype":"locality"
},
  "geometry": {"coordinates":[48.22967,37.22344],"type":"Point"}
}