{
  "type": "Feature",
  "properties": {
    "gn:admin1_code":"8.0",
    "gn:asciiname":"Nur ol `Arash",
    "gn:country_code":"IR",
    "gn:dem":1288,
    "gn:feature_class":"P",
    "gn:feature_code":"PPL",
    "gn:name":"N\u016br ol \u2018Arash",
    "gn:population":0,
    "gn:timezone":"Asia/Tehran",
    "iso:country":"IR",
    "name:fas_x_preferred":[
        "N\u016br ol \u2018Arash"
    ],
    "name:fas_x_variant":[
        "\u0646\u0648\u0631 \u0627\u0644\u0639\u0631\u0634"
    ],
    "name:und_x_variant":[
        "\u0646\u0648\u0631 \u0627\u0644\u0639\u0631\u0634"
    ],
    "wof:name":"Nur ol `Arash",
    "wof:placetype":"locality"
},
  "geometry": {"coordinates":[49.72156,36.84614000000001],"type":"Point"}
}