{
  "type": "Feature",
  "properties": {
    "gn:admin1_code":"42",
    "gn:asciiname":"`Aliabad-e Shahid",
    "gn:country_code":"IR",
    "gn:dem":1172,
    "gn:feature_class":"P",
    "gn:feature_code":"PPL",
    "gn:name":"\u2018Al\u012b\u0101b\u0101d-e Shah\u012bd",
    "gn:population":0,
    "gn:timezone":"Asia/Tehran",
    "iso:country":"IR",
    "name:fas_x_preferred":[
        "\u0639\u0644\u06cc \u0622\u0628\u0627\u062f \u0634\u0647\u06cc\u062f"
    ],
    "name:fas_x_variant":[
        "\u2018Al\u012b\u0101b\u0101d-e Shah\u012bd"
    ],
    "wof:name":"`Aliabad-e Shahid",
    "wof:placetype":"locality"
},
  "geometry": {"coordinates":[58.8759,36.10609],"type":"Point"}
}