{
  "type": "Feature",
  "properties": {
    "gn:admin1_code":"29",
    "gn:asciiname":"Deh NowY-ye Khvajeh",
    "gn:country_code":"IR",
    "gn:dem":2007,
    "gn:feature_class":"P",
    "gn:feature_code":"PPL",
    "gn:name":"Deh NowY-ye Khv\u0101jeh",
    "gn:population":0,
    "gn:timezone":"Asia/Tehran",
    "iso:country":"IR",
    "name:fas_x_preferred":[
        "Deh NowY-ye Khv\u0101jeh"
    ],
    "wof:name":"Deh NowY-ye Khvajeh",
    "wof:placetype":"locality"
},
  "geometry": {"coordinates":[56.26667,31.41667],"type":"Point"}
}