{
  "type": "Feature",
  "properties": {
    "gn:admin1_code":"42",
    "gn:asciiname":"Mureshk",
    "gn:country_code":"IR",
    "gn:dem":1326,
    "gn:feature_class":"P",
    "gn:feature_code":"PPL",
    "gn:name":"M\u016breshk",
    "gn:population":0,
    "gn:timezone":"Asia/Tehran",
    "iso:country":"IR",
    "name:fas_x_preferred":[
        "M\u016breshk"
    ],
    "wof:name":"Mureshk",
    "wof:placetype":"locality"
},
  "geometry": {"coordinates":[59.21889,35.25722000000001],"type":"Point"}
}