{
  "type": "Feature",
  "properties": {
    "gn:admin1_code":"8",
    "gn:asciiname":"Urma",
    "gn:country_code":"IR",
    "gn:dem":794,
    "gn:feature_class":"P",
    "gn:feature_code":"PPL",
    "gn:name":"\u016arm\u0101",
    "gn:population":0,
    "gn:timezone":"Asia/Tehran",
    "iso:country":"IR",
    "name:ceb_x_preferred":[
        "Urma"
    ],
    "name:fas_x_preferred":[
        "\u016arm\u0101"
    ],
    "name:msa_x_preferred":[
        "Urma"
    ],
    "name:nep_x_preferred":[
        "\u0909\u0930\u094d\u092e\u093e"
    ],
    "name:new_x_preferred":[
        "\u0909\u0930\u094d\u092e\u093e"
    ],
    "name:pol_x_preferred":[
        "Urma"
    ],
    "wof:name":"Urma",
    "wof:placetype":"locality"
},
  "geometry": {"coordinates":[48.94056,37.42972],"type":"Point"}
}