{
  "type": "Feature",
  "properties": {
    "gn:admin1_code":"7",
    "gn:asciiname":"Gonbad",
    "gn:country_code":"IR",
    "gn:dem":794,
    "gn:feature_class":"P",
    "gn:feature_code":"PPL",
    "gn:name":"Gonbad",
    "gn:population":0,
    "gn:timezone":"Asia/Tehran",
    "iso:country":"IR",
    "name:ara_x_preferred":[
        "\u063a\u0646\u0628\u062f"
    ],
    "name:fas_x_preferred":[
        "\u06af\u0646\u0628\u062f"
    ],
    "name:msa_x_preferred":[
        "Gonbad"
    ],
    "name:und_x_variant":[
        "Gombaz",
        "Gunbad"
    ],
    "wof:name":"Gonbad",
    "wof:placetype":"locality"
},
  "geometry": {"coordinates":[52.0368,28.9692],"type":"Point"}
}