{
  "type": "Feature",
  "properties": {
    "gn:admin1_code":"15.0",
    "gn:asciiname":"Talavar-e Vosta",
    "gn:country_code":"IR",
    "gn:dem":828,
    "gn:feature_class":"P",
    "gn:feature_code":"PPL",
    "gn:name":"\u0162al\u0101var-e Vos\u0163\u00e1",
    "gn:population":0,
    "gn:timezone":"Asia/Tehran",
    "iso:country":"IR",
    "name:fas_x_preferred":[
        "\u0637\u0644\u0627\u0648\u0631 \u0648\u0633\u0637\u06cc"
    ],
    "name:und_x_variant":[
        "\u0162al\u0101var-e Vos\u0163\u00e1"
    ],
    "wof:name":"Talavar-e Vosta",
    "wof:placetype":"locality"
},
  "geometry": {"coordinates":[50.05097,31.35451],"type":"Point"}
}