{
  "type": "Feature",
  "properties": {
    "gn:admin1_code":"43.0",
    "gn:asciiname":"Kalateh-ye Shur",
    "gn:country_code":"IR",
    "gn:dem":1017,
    "gn:feature_class":"P",
    "gn:feature_code":"PPL",
    "gn:name":"Kal\u0101teh-ye Sh\u016br",
    "gn:population":0,
    "gn:timezone":"Asia/Tehran",
    "iso:country":"IR",
    "name:fas_x_preferred":[
        "Kal\u0101teh-ye Sh\u016br"
    ],
    "name:fas_x_variant":[
        "\u06a9\u0644\u0627\u062a\u0647 \u0634\u0648\u0631"
    ],
    "wof:name":"Kalateh-ye Shur",
    "wof:placetype":"locality"
},
  "geometry": {"coordinates":[57.19979,37.04343],"type":"Point"}
}