{
  "type": "Feature",
  "properties": {
    "gn:admin1_code":"8",
    "gn:asciiname":"Eskataneh",
    "gn:country_code":"IR",
    "gn:dem":2102,
    "gn:feature_class":"P",
    "gn:feature_code":"PPL",
    "gn:name":"Eskat\u0101neh",
    "gn:population":0,
    "gn:timezone":"Asia/Tehran",
    "iso:country":"IR",
    "name:fas_x_preferred":[
        "\u0627\u0633\u06a9\u062a\u0627\u0646\u0647"
    ],
    "name:fas_x_variant":[
        "Eskat\u0101neh"
    ],
    "wof:name":"Eskataneh",
    "wof:placetype":"locality"
},
  "geometry": {"coordinates":[48.8333,37.4319],"type":"Point"}
}