{
  "type": "Feature",
  "properties": {
    "gn:admin1_code":"13",
    "gn:asciiname":"Tomianeh",
    "gn:country_code":"IR",
    "gn:dem":1342,
    "gn:feature_class":"P",
    "gn:feature_code":"PPL",
    "gn:name":"Tom\u012b\u0101neh",
    "gn:population":0,
    "gn:timezone":"Asia/Tehran",
    "iso:country":"IR",
    "name:fas_x_preferred":[
        "\u062a\u0645\u06cc\u0627\u0646\u0647"
    ],
    "name:fas_x_variant":[
        "T\u016bm\u012b\u0101neh",
        "Tom\u012b\u0101neh"
    ],
    "wof:name":"Tomianeh",
    "wof:placetype":"locality"
},
  "geometry": {"coordinates":[46.7797,33.9846],"type":"Point"}
}