{
  "type": "Feature",
  "properties": {
    "gn:admin1_code":"26",
    "gn:asciiname":"Mahalleh-ye Neyshaburiha",
    "gn:country_code":"IR",
    "gn:dem":1189,
    "gn:feature_class":"P",
    "gn:feature_code":"PPL",
    "gn:name":"Ma\u1e29alleh-ye Neysh\u0101b\u016br\u012bh\u0101",
    "gn:population":0,
    "gn:timezone":"Asia/Tehran",
    "iso:country":"IR",
    "name:fas_x_preferred":[
        "\u0645\u064e\u062d\u064e\u0644\u0650\u0651\u06c0 \u0646\u0650\u064a\u0634\u0627\u0628\u0648\u0631\u06cc\u200c\u0647\u064e\u0627"
    ],
    "name:fas_x_variant":[
        "\u0645\u064e\u062d\u0644\u0650\u0651\u06c0 \u0646\u0650\u064a\u0634\u0627\u0628\u0648\u0631\u06cc\u200c\u0647\u064e\u0627",
        "\u0634\u0627\u0647 \u0622\u0628\u0627\u062f",
        "Ma\u1e29alleh-ye Neysh\u0101b\u016br\u012bh\u0101"
    ],
    "name:und_x_variant":[
        "Sh\u0101h\u0101b\u0101d",
        "Ma\u1e29lleh-ye Neysh\u0101b\u016br\u012bh\u0101"
    ],
    "wof:name":"Mahalleh-ye Neyshaburiha",
    "wof:placetype":"locality"
},
  "geometry": {"coordinates":[50.91333,35.71556],"type":"Point"}
}