{
  "type": "Feature",
  "properties": {
    "gn:admin1_code":"25",
    "gn:asciiname":"Zardavan",
    "gn:country_code":"IR",
    "gn:dem":1869,
    "gn:feature_class":"P",
    "gn:feature_code":"PPL",
    "gn:name":"Zardav\u0101n",
    "gn:population":0,
    "gn:timezone":"Asia/Tehran",
    "iso:country":"IR",
    "name:fas_x_preferred":[
        "Zardav\u0101n"
    ],
    "name:fas_x_variant":[
        "\u0632\u0631\u062f\u0648\u0627\u0646"
    ],
    "wof:name":"Zardavan",
    "wof:placetype":"locality"
},
  "geometry": {"coordinates":[54.23522,36.42833],"type":"Point"}
}