{
  "type": "Feature",
  "properties": {
    "gn:admin1_code":"15",
    "gn:asciiname":"Neyzar-e `Olya",
    "gn:country_code":"IR",
    "gn:dem":11,
    "gn:feature_class":"P",
    "gn:feature_code":"PPL",
    "gn:name":"Neyz\u0101r-e \u2018Oly\u0101",
    "gn:population":0,
    "gn:timezone":"Asia/Tehran",
    "iso:country":"IR",
    "name:fas_x_preferred":[
        "\u0646\u06cc\u0632\u0627\u0631 \u0639\u0644\u06cc\u0627"
    ],
    "name:fas_x_variant":[
        "Yanz\u0101r-e \u2018Oly\u0101",
        "Neyz\u0101r-e \u2018Oly\u0101"
    ],
    "name:und_x_variant":[
        "Nozz\u0101r-e \u2018Oly\u0101",
        "Naz\u0327\u0101r-e B\u0101l\u0101",
        "Nozz\u0101r-e B\u0101l\u0101"
    ],
    "wof:name":"Neyzar-e `Olya",
    "wof:placetype":"locality"
},
  "geometry": {"coordinates":[49.31256,30.68364],"type":"Point"}
}