{
  "type": "Feature",
  "properties": {
    "gn:admin1_code":"11",
    "gn:asciiname":"Mazra`eh-ye Sheykh `Ali",
    "gn:country_code":"IR",
    "gn:dem":338,
    "gn:feature_class":"P",
    "gn:feature_code":"PPLF",
    "gn:name":"Mazra\u2018eh-ye Sheykh \u2018\u0100l\u012b",
    "gn:population":0,
    "gn:timezone":"Asia/Tehran",
    "iso:country":"IR",
    "name:fas_x_preferred":[
        "\u0634\u064a\u062e \u0639\u0627\u0644\u06cc"
    ],
    "name:fas_x_variant":[
        "\u0634\u06cc\u062e\u0627\u0626\u06cc",
        "Sheykh \u2018\u0100l\u012b",
        "Sheykh\u0101\u2019\u012b",
        "\u0645\u0632\u0631\u0639\u0647 \u0634\u064a\u062e \u0639\u0627\u0644\u06cc"
    ],
    "name:und_x_variant":[
        "Mazra\u2018eh-ye Sheykh \u2018\u0100l\u012b"
    ],
    "wof:name":"Mazra`eh-ye Sheykh `Ali",
    "wof:placetype":"locality"
},
  "geometry": {"coordinates":[55.98263000000001,27.62298],"type":"Point"}
}