{
  "type": "Feature",
  "properties": {
    "gn:admin1_code":"4.0",
    "gn:asciiname":"Mogh",
    "gn:country_code":"IR",
    "gn:dem":880,
    "gn:feature_class":"P",
    "gn:feature_code":"PPL",
    "gn:name":"Mogh",
    "gn:population":0,
    "gn:timezone":"Asia/Tehran",
    "iso:country":"IR",
    "name:fas_x_preferred":[
        "\u0645\u063a"
    ],
    "name:und_x_variant":[
        "Magh",
        "Moq",
        "Mogh"
    ],
    "wof:name":"Mogh",
    "wof:placetype":"locality"
},
  "geometry": {"coordinates":[61.25156,26.61109],"type":"Point"}
}