{
  "type": "Feature",
  "properties": {
    "gn:admin1_code":"34",
    "gn:asciiname":"Qalavar-e Pa'in",
    "gn:country_code":"IR",
    "gn:dem":1479,
    "gn:feature_class":"P",
    "gn:feature_code":"PPL",
    "gn:name":"Qal\u0101var-e P\u0101\u2019\u012bn",
    "gn:population":0,
    "gn:timezone":"Asia/Tehran",
    "iso:country":"IR",
    "name:fas_x_preferred":[
        "\u0642\u0644\u0627\u0648\u0631 \u067e\u0627\u0626\u06cc\u0646"
    ],
    "name:fas_x_variant":[
        "Qal\u0101var-e P\u0101\u2019\u012bn"
    ],
    "wof:name":"Qalavar-e Pa'in",
    "wof:placetype":"locality"
},
  "geometry": {"coordinates":[50.5934,33.9183],"type":"Point"}
}