{
  "type": "Feature",
  "properties": {
    "gn:admin1_code":"11",
    "gn:asciiname":"Patal",
    "gn:country_code":"IR",
    "gn:dem":7,
    "gn:feature_class":"P",
    "gn:feature_code":"PPL",
    "gn:name":"P\u0101tal",
    "gn:population":0,
    "gn:timezone":"Asia/Tehran",
    "iso:country":"IR",
    "name:fas_x_preferred":[
        "\u067e\u0627\u062a\u064e\u0644"
    ],
    "name:fas_x_variant":[
        "P\u0101tal",
        "\u067e\u0627\u062a\u0644"
    ],
    "name:msa_x_preferred":[
        "Patal"
    ],
    "wof:name":"Patal",
    "wof:placetype":"locality"
},
  "geometry": {"coordinates":[57.06306,26.85556],"type":"Point"}
}