{
  "type": "Feature",
  "properties": {
    "gn:admin1_code":"40",
    "gn:asciiname":"Bozorgabad",
    "gn:country_code":"IR",
    "gn:dem":2001,
    "gn:feature_class":"P",
    "gn:feature_code":"PPL",
    "gn:name":"Bozorg\u0101b\u0101d",
    "gn:population":0,
    "gn:timezone":"Asia/Tehran",
    "iso:country":"IR",
    "name:fas_x_preferred":[
        "Bozg\u0101b\u0101d"
    ],
    "name:fas_x_variant":[
        "\u0628\u0632\u06af \u0622\u0628\u0627\u062f",
        "\u0628\u0632\u0631\u06af \u0622\u0628\u0627\u062f"
    ],
    "name:und_x_variant":[
        "Bezg\u0101b\u0101d",
        "Bozorg\u0101b\u0101d"
    ],
    "wof:name":"Bozorgabad",
    "wof:placetype":"locality"
},
  "geometry": {"coordinates":[54.07323,31.31255],"type":"Point"}
}