{
  "type": "Feature",
  "properties": {
    "gn:admin1_code":"29",
    "gn:asciiname":"Pa'in",
    "gn:country_code":"IR",
    "gn:dem":2302,
    "gn:feature_class":"P",
    "gn:feature_code":"PPL",
    "gn:name":"P\u0101\u2019\u012bn",
    "gn:population":0,
    "gn:timezone":"Asia/Tehran",
    "iso:country":"IR",
    "name:fas_x_preferred":[
        "\u067e\u0627\u0626\u06cc\u0646"
    ],
    "name:fas_x_variant":[
        "P\u0101\u2019\u012bn"
    ],
    "wof:name":"Pa'in",
    "wof:placetype":"locality"
},
  "geometry": {"coordinates":[57.7099,29.0342],"type":"Point"}
}