{
  "type": "Feature",
  "properties": {
    "gn:admin1_code":"8.0",
    "gn:asciiname":"Dowkal",
    "gn:country_code":"IR",
    "gn:dem":1527,
    "gn:feature_class":"P",
    "gn:feature_code":"PPL",
    "gn:name":"Dowkal",
    "gn:population":0,
    "gn:timezone":"Asia/Tehran",
    "iso:country":"IR",
    "name:fas_x_preferred":[
        "\u062f\u0648\u06a9\u0644"
    ],
    "wof:name":"Dowkal",
    "wof:placetype":"locality"
},
  "geometry": {"coordinates":[50.35021,36.69056],"type":"Point"}
}