{
  "type": "Feature",
  "properties": {
    "gn:admin1_code":"35.0",
    "gn:asciiname":"Sarbura",
    "gn:country_code":"IR",
    "gn:dem":110,
    "gn:feature_class":"P",
    "gn:feature_code":"PPL",
    "gn:name":"Sarb\u016br\u0101",
    "gn:population":0,
    "gn:timezone":"Asia/Tehran",
    "iso:country":"IR",
    "name:ceb_x_preferred":[
        "Sarb\u016br\u0101"
    ],
    "name:fas_x_preferred":[
        "\u0628\u0627\u0644\u0627 \u0628\u064f\u0648\u0631\u0627"
    ],
    "name:fas_x_variant":[
        "\u0633\u0631\u0628\u0648\u0631\u0627",
        "\u0633\u064e\u0631 \u0628\u0648\u0631\u0627",
        "B\u0101l\u0101 Bowr\u0101",
        "Sarb\u016br\u0101",
        "\u0628\u0627\u0644\u0627\u0628\u0648\u0631\u0627"
    ],
    "name:mzn_x_preferred":[
        "\u0628\u0627\u0644\u0627\u0628\u0648\u0631\u0627"
    ],
    "name:swe_x_preferred":[
        "Sarb\u016br\u0101"
    ],
    "name:und_x_variant":[
        "Sar B\u016br\u0101",
        "Sarb\u016br\u0101"
    ],
    "wof:name":"Sarbura",
    "wof:placetype":"locality"
},
  "geometry": {"coordinates":[52.56516,36.3514],"type":"Point"}
}