{
  "type": "Feature",
  "properties": {
    "gn:admin1_code":"8",
    "gn:asciiname":"Kahlestan",
    "gn:country_code":"IR",
    "gn:dem":35,
    "gn:feature_class":"P",
    "gn:feature_code":"PPL",
    "gn:name":"Kahlest\u0101n",
    "gn:population":0,
    "gn:timezone":"Asia/Tehran",
    "iso:country":"IR",
    "name:ceb_x_preferred":[
        "K\u016blest\u0101n"
    ],
    "name:fas_x_preferred":[
        "K\u016blest\u0101n"
    ],
    "name:fas_x_variant":[
        "\u06a9\u0647\u0644\u0633\u062a\u0627\u0646"
    ],
    "name:msa_x_preferred":[
        "Kahlestan"
    ],
    "name:swe_x_preferred":[
        "K\u016blest\u0101n"
    ],
    "name:ukr_x_preferred":[
        "\u041a\u0430\u0433\u043b\u0435\u0441\u0442\u0430\u043d"
    ],
    "name:und_x_variant":[
        "Kahlest\u0101n"
    ],
    "wof:name":"Kahlestan",
    "wof:placetype":"locality"
},
  "geometry": {"coordinates":[50.16126,37.09179],"type":"Point"}
}