{
  "type": "Feature",
  "properties": {
    "gn:admin1_code":"10",
    "gn:asciiname":"`Eyn-e Khowsh",
    "gn:country_code":"IR",
    "gn:dem":146,
    "gn:feature_class":"P",
    "gn:feature_code":"PPL",
    "gn:name":"\u2018Eyn-e Khowsh",
    "gn:population":0,
    "gn:timezone":"Asia/Tehran",
    "iso:country":"IR",
    "name:ara_x_preferred":[
        "\u0639\u064a\u0646 \u062e\u0648\u0634"
    ],
    "name:fas_x_preferred":[
        "\u0627\u0650\u064a\u0646 \u062e\u0648\u0634"
    ],
    "name:fas_x_variant":[
        "\u0639\u06cc\u0646 \u062e\u0648\u0634",
        "\u2018Eyn Khvosh"
    ],
    "name:msa_x_preferred":[
        "Eyn Khvosh"
    ],
    "name:und_x_variant":[
        "Chashmeh Khush",
        "\u2018Eyn-e Khowsh",
        "Eyn Kh\u016bsh",
        "\u2018Eyn-e Khvosh"
    ],
    "wof:name":"`Eyn-e Khowsh",
    "wof:placetype":"locality"
},
  "geometry": {"coordinates":[47.6373,32.4124],"type":"Point"}
}