{
  "type": "Feature",
  "properties": {
    "gn:admin1_code":"4",
    "gn:asciiname":"Kahnug",
    "gn:country_code":"IR",
    "gn:dem":1172,
    "gn:feature_class":"P",
    "gn:feature_code":"PPL",
    "gn:name":"Kahn\u016bg",
    "gn:population":0,
    "gn:timezone":"Asia/Tehran",
    "iso:country":"IR",
    "name:fas_x_preferred":[
        "\u06a9\u0647\u0646\u0648\u06af"
    ],
    "name:fas_x_variant":[
        "Kahn\u016bg",
        "\u06a9\u0647\u0646\u06a9"
    ],
    "name:und_x_variant":[
        "Kahnak"
    ],
    "wof:name":"Kahnug",
    "wof:placetype":"locality"
},
  "geometry": {"coordinates":[61.3261,28.9184],"type":"Point"}
}