{
  "type": "Feature",
  "properties": {
    "gn:admin1_code":"8",
    "gn:asciiname":"Salim Jaf",
    "gn:country_code":"IR",
    "gn:dem":-12,
    "gn:feature_class":"P",
    "gn:feature_code":"PPL",
    "gn:name":"Sal\u012bm J\u0101f",
    "gn:population":0,
    "gn:timezone":"Asia/Tehran",
    "iso:country":"IR",
    "name:ara_x_preferred":[
        "\u0633\u0644\u064a\u0645 \u062a\u0634\u0627\u0641"
    ],
    "name:fas_x_preferred":[
        "Sal\u012bm Ch\u0101f"
    ],
    "name:fas_x_variant":[
        "Sal\u012bm Ch\u0101k",
        "\u0633\u0644\u06cc\u0645 \u0686\u0627\u06a9",
        "\u0633\u0644\u06cc\u0645 \u062c\u0627\u0641",
        "\u0633\u0644\u06cc\u0645 \u0686\u0627\u0641"
    ],
    "name:msa_x_preferred":[
        "Salim Chaf"
    ],
    "name:por_x_preferred":[
        "Salim Chaf"
    ],
    "name:ukr_x_preferred":[
        "\u0421\u0430\u043b\u0456\u043c-\u0427\u0430\u0444"
    ],
    "name:und_x_variant":[
        "\u0633\u0644\u06cc\u0645 \u0686\u0627\u06a9",
        "Sal\u012bm J\u0101f",
        "\u0633\u0644\u06cc\u0645 \u0686\u0627\u0641"
    ],
    "wof:name":"Salim Jaf",
    "wof:placetype":"locality"
},
  "geometry": {"coordinates":[50.10362,37.38465],"type":"Point"}
}