{
  "type": "Feature",
  "properties": {
    "gn:admin1_code":"13",
    "gn:asciiname":"Mir`ali-ye Mirkhan",
    "gn:country_code":"IR",
    "gn:dem":790,
    "gn:feature_class":"P",
    "gn:feature_code":"PPL",
    "gn:name":"M\u012br\u2018al\u012b-ye M\u012brkh\u0101n",
    "gn:population":0,
    "gn:timezone":"Asia/Tehran",
    "iso:country":"IR",
    "name:ceb_x_preferred":[
        "M\u012br\u2018al\u012b-ye M\u012brkh\u0101n"
    ],
    "name:fas_x_preferred":[
        "\u0645\u064a\u0631\u0639\u0644\u06cc \u0645\u064a\u0631\u062e\u0627\u0646"
    ],
    "name:fas_x_variant":[
        "M\u012bval\u012b-ye Sofl\u00e1",
        "M\u012br\u2018al\u012b-ye M\u012brkh\u0101n",
        "\u0645\u06cc\u0648\u0644\u06cc \u0633\u0641\u0644\u06cc"
    ],
    "name:swe_x_preferred":[
        "M\u012br\u2018al\u012b-ye M\u012brkh\u0101n"
    ],
    "name:und_x_variant":[
        "Meyvol\u012b",
        "M\u012bval\u012b"
    ],
    "wof:name":"Mir`ali-ye Mirkhan",
    "wof:placetype":"locality"
},
  "geometry": {"coordinates":[45.94437,34.60798],"type":"Point"}
}