{
  "type": "Feature",
  "properties": {
    "gn:admin1_code":"23",
    "gn:asciiname":"Gandabeh",
    "gn:country_code":"IR",
    "gn:dem":1534,
    "gn:feature_class":"P",
    "gn:feature_code":"PPL",
    "gn:name":"Gand\u0101beh",
    "gn:population":0,
    "gn:timezone":"Asia/Tehran",
    "iso:country":"IR",
    "name:fas_x_preferred":[
        "\u06af\u064e\u0646\u062f\u0627\u0648\u0650\u0647"
    ],
    "name:fas_x_variant":[
        "\u06af\u0646\u062f\u0627\u0628\u0647",
        "Hoseyn\u0101b\u0101d",
        "Gand\u0101veh",
        "Gand\u0101beh \u1e28oseyn\u0101b\u0101d",
        "\u0647\u064f\u0633\u0650\u064a\u0646 \u0622\u0628\u0627\u062f",
        "\u06af\u064e\u0646\u062f\u0627\u0628\u0650\u0647 \u062d\u064f\u0633\u0650\u064a\u0646 \u0622\u0628\u0627\u062f",
        "Gand\u0101beh"
    ],
    "wof:name":"Gandabeh",
    "wof:placetype":"locality"
},
  "geometry": {"coordinates":[48.5542,33.4197],"type":"Point"}
}