{
  "type": "Feature",
  "properties": {
    "gn:admin1_code":"28",
    "gn:asciiname":"Torzeh",
    "gn:country_code":"IR",
    "gn:dem":2371,
    "gn:feature_class":"P",
    "gn:feature_code":"PPL",
    "gn:name":"Torzeh",
    "gn:population":0,
    "gn:timezone":"Asia/Tehran",
    "iso:country":"IR",
    "name:ara_x_preferred":[
        "\u062a\u0631\u0632\u0647"
    ],
    "name:fas_x_preferred":[
        "\u0162orzeh"
    ],
    "name:fas_x_variant":[
        "\u062a\u0631\u0632\u0647"
    ],
    "name:und_x_variant":[
        "Tarzeh",
        "T\u016brzah",
        "Towrzeh",
        "Torzeh",
        "\u062a\u0631\u0632\u0647",
        "\u0637\u0631\u0632\u0647"
    ],
    "wof:name":"Torzeh",
    "wof:placetype":"locality"
},
  "geometry": {"coordinates":[49.80246,32.90211],"type":"Point"}
}