{
  "type": "Feature",
  "properties": {
    "gn:admin1_code":"11",
    "gn:asciiname":"Patal-e Isin",
    "gn:country_code":"IR",
    "gn:dem":67,
    "gn:feature_class":"P",
    "gn:feature_code":"PPL",
    "gn:name":"P\u0101tal-e \u012as\u012bn",
    "gn:population":0,
    "gn:timezone":"Asia/Tehran",
    "iso:country":"IR",
    "name:ara_x_preferred":[
        "\u0628\u0627\u062a\u0644 \u0623\u064a\u0633\u064a\u0646"
    ],
    "name:fas_x_preferred":[
        "\u067e\u0627\u062a\u064e\u0644\u0650 \u064a\u0633\u064a\u0646"
    ],
    "name:fas_x_variant":[
        "\u067e\u0627 \u062a\u064e\u0644\u0650\u0651 \u064a\u0633\u064a\u0646",
        "\u067e\u0627\u06cc \u062a\u064e\u0644\u0650\u0651 \u064a\u0633\u064a\u0646",
        "\u067e\u0627\u062a\u0644 \u0627\u06cc\u0633\u06cc\u0646",
        "P\u0101tal-e \u012as\u012bn"
    ],
    "name:msa_x_preferred":[
        "Patal-e Isin"
    ],
    "name:und_x_variant":[
        "P\u0101-ye Tall-e \u012as\u012bn",
        "P\u0101 Tall-e \u012as\u012bn"
    ],
    "wof:name":"Patal-e Isin",
    "wof:placetype":"locality"
},
  "geometry": {"coordinates":[56.2404,27.3007],"type":"Point"}
}