{
  "type": "Feature",
  "properties": {
    "gn:admin1_code":"11.0",
    "gn:asciiname":"Gaz-e Taheri",
    "gn:country_code":"IR",
    "gn:dem":16,
    "gn:feature_class":"P",
    "gn:feature_code":"PPL",
    "gn:name":"Gaz-e \u0162\u0101her\u012b",
    "gn:population":0,
    "gn:timezone":"Asia/Tehran",
    "iso:country":"IR",
    "name:fas_x_preferred":[
        "\u06af\u0632 \u0637\u0627\u0647\u0631\u06cc"
    ],
    "name:fas_x_variant":[
        "Gaz-e \u0162\u0101her\u012b"
    ],
    "wof:name":"Gaz-e Taheri",
    "wof:placetype":"locality"
},
  "geometry": {"coordinates":[57.185,26.4114],"type":"Point"}
}