{
  "type": "Feature",
  "properties": {
    "gn:admin1_code":"29",
    "gn:asciiname":"Sar Asiab",
    "gn:country_code":"IR",
    "gn:dem":1880,
    "gn:feature_class":"P",
    "gn:feature_code":"PPL",
    "gn:name":"Sar \u0100s\u012b\u0101b",
    "gn:population":0,
    "gn:timezone":"Asia/Tehran",
    "iso:country":"IR",
    "name:fas_x_preferred":[
        "\u0633\u0631 \u0622\u0633\u06cc\u0627\u0628"
    ],
    "name:fas_x_variant":[
        "Sar As\u012b\u0101b",
        "Sar \u0100s\u012b\u0101b",
        "Sar \u0100syab",
        "As\u012b\u0101b-e M\u012b\u0101n Dasht",
        "\u0633\u0631\u0622\u0633\u06cc\u0627\u0628"
    ],
    "wof:name":"Sar Asiab",
    "wof:placetype":"locality"
},
  "geometry": {"coordinates":[57.29781,30.48155],"type":"Point"}
}