{
  "type": "Feature",
  "properties": {
    "gn:admin1_code":"41",
    "gn:asciiname":"Karizan",
    "gn:country_code":"IR",
    "gn:dem":1023,
    "gn:feature_class":"P",
    "gn:feature_code":"PPL",
    "gn:name":"Kar\u012bz\u0101n",
    "gn:population":0,
    "gn:timezone":"Asia/Tehran",
    "iso:country":"IR",
    "name:fas_x_preferred":[
        "Kal\u0101teh-ye Gar\u012bz\u0101n-e B\u0101l\u0101"
    ],
    "name:fas_x_variant":[
        "\u06a9\u0631\u06cc\u0632\u0627\u0646",
        "\u06a9\u0631\u064a\u0632\u0627\u0646 \u0639\u0644\u064a\u0627",
        "\u06a9\u0644\u0627\u062a\u0647 \u06af\u0631\u06cc\u0632\u0627\u0646",
        "\u06a9\u0631\u06cc\u0632\u0627\u0646 \u0633\u0641\u0644\u06cc"
    ],
    "name:und_x_variant":[
        "Kar\u012bz\u0101n",
        "Kar\u012bz\u0101n-e \u2018Oly\u0101",
        "Kar\u012bz\u0101n-e Sofl\u00e1",
        "K\u0101r\u012bz\u0101n",
        "Kal\u0101teh-ye Ker\u012bz\u0101n",
        "Kal\u0101teh K\u0101r\u012bz\u0101n",
        "Kal\u0101teh-ye K\u0101r\u012bz\u0101n",
        "Kal\u0101teh-ye Gar\u012bz\u0101n",
        "Kal\u0101teh-ye Gar\u012bz\u0101n-e P\u0101\u2019\u012bn"
    ],
    "wof:name":"Karizan",
    "wof:placetype":"locality"
},
  "geometry": {"coordinates":[59.81335,33.88988],"type":"Point"}
}