{
  "type": "Feature",
  "properties": {
    "gn:admin1_code":"9",
    "gn:asciiname":"Darsibeh",
    "gn:country_code":"IR",
    "gn:dem":1906,
    "gn:feature_class":"P",
    "gn:feature_code":"PPL",
    "gn:name":"D\u0101rs\u012bbeh",
    "gn:population":0,
    "gn:timezone":"Asia/Tehran",
    "iso:country":"IR",
    "name:ceb_x_preferred":[
        "D\u0101rs\u012bb"
    ],
    "name:ckb_x_preferred":[
        "\u06af\u0648\u0648\u0631\u0646\u06d5\u0633\u06d5\u0648"
    ],
    "name:fas_x_preferred":[
        "D\u0101rs\u012bb"
    ],
    "name:fas_x_variant":[
        "D\u0101rs\u012bbeh",
        "\u062f\u0627\u0631\u0633\u06cc\u0628",
        "\u062f\u0627\u0631\u0633\u06cc\u0628\u0647"
    ],
    "name:msa_x_preferred":[
        "Darsibeh"
    ],
    "name:swe_x_preferred":[
        "D\u0101rs\u012bb"
    ],
    "name:und_x_variant":[
        "\u062f\u0627\u0631\u0633\u06cc\u0628"
    ],
    "wof:name":"Darsibeh",
    "wof:placetype":"locality"
},
  "geometry": {"coordinates":[48.00686,34.26993],"type":"Point"}
}