{
  "type": "Feature",
  "properties": {
    "gn:admin1_code":"29",
    "gn:asciiname":"Dowjangan",
    "gn:country_code":"IR",
    "gn:dem":2319,
    "gn:feature_class":"P",
    "gn:feature_code":"PPL",
    "gn:name":"Dowjang\u0101n",
    "gn:population":0,
    "gn:timezone":"Asia/Tehran",
    "iso:country":"IR",
    "name:fas_x_preferred":[
        "\u062f\u0648\u062c\u0646\u06af\u0627\u0646"
    ],
    "name:fas_x_variant":[
        "Dowjang\u0101n"
    ],
    "name:und_x_variant":[
        "Jang\u0101n",
        "Do Jang\u0101n",
        "Jeng\u0101n",
        "Do Jeng\u0101n"
    ],
    "wof:name":"Dowjangan",
    "wof:placetype":"locality"
},
  "geometry": {"coordinates":[57.8821,29.0825],"type":"Point"}
}