{
  "type": "Feature",
  "properties": {
    "gn:admin1_code":"40.0",
    "gn:asciiname":"Mazra`eh-ye Kabirabad",
    "gn:country_code":"IR",
    "gn:dem":2216,
    "gn:feature_class":"P",
    "gn:feature_code":"PPL",
    "gn:name":"Mazra\u2018eh-ye K\u0101b\u012br\u0101b\u0101d",
    "gn:population":0,
    "gn:timezone":"Asia/Tehran",
    "iso:country":"IR",
    "name:fas_x_preferred":[
        "\u0645\u064e\u0632\u0631\u064e\u0639\u0650\u06c0 \u0643\u0627\u0628\u064a\u0631 \u0622\u0628\u0627\u062f"
    ],
    "name:fas_x_variant":[
        "Mazra\u2018eh-ye K\u0101b\u012br\u0101b\u0101d"
    ],
    "wof:name":"Mazra`eh-ye Kabirabad",
    "wof:placetype":"locality"
},
  "geometry": {"coordinates":[53.89222,31.48889],"type":"Point"}
}