{
  "type": "Feature",
  "properties": {
    "gn:admin1_code":"36",
    "gn:asciiname":"Esfejin",
    "gn:country_code":"IR",
    "gn:dem":1514,
    "gn:feature_class":"P",
    "gn:feature_code":"PPL",
    "gn:name":"Esfej\u012bn",
    "gn:population":0,
    "gn:timezone":"Asia/Tehran",
    "iso:country":"IR",
    "name:azb_x_preferred":[
        "\u0627\u0633\u0641\u062c\u06cc\u0646"
    ],
    "name:ceb_x_preferred":[
        "Esfaj\u012bn"
    ],
    "name:fas_x_preferred":[
        "\u0627\u0633\u0641\u062c\u06cc\u0646"
    ],
    "name:fas_x_variant":[
        "\u0627\u0650\u0633\u0641\u0650\u062c\u064a\u0646",
        "Esfaj\u012bn"
    ],
    "name:swe_x_preferred":[
        "Esfaj\u012bn"
    ],
    "name:und_x_variant":[
        "Isb\u0101jin",
        "Esfej\u012bn",
        "Isbadzhin"
    ],
    "wof:name":"Esfejin",
    "wof:placetype":"locality"
},
  "geometry": {"coordinates":[48.2481,36.74494],"type":"Point"}
}