{
  "type": "Feature",
  "properties": {
    "gn:admin1_code":"1",
    "gn:asciiname":"`Ali Mardan",
    "gn:country_code":"IR",
    "gn:dem":1949,
    "gn:feature_class":"P",
    "gn:feature_code":"PPL",
    "gn:name":"\u2018Al\u012b Mard\u0101n",
    "gn:population":0,
    "gn:timezone":"Asia/Tehran",
    "iso:country":"IR",
    "name:fas_x_preferred":[
        "\u0639\u064e\u0644\u06cc \u0645\u064e\u0631\u062f\u0627\u0646"
    ],
    "name:fas_x_variant":[
        "\u0639\u0644\u06cc \u0645\u0631\u062f\u0627\u0646",
        "\u2018Al\u012b Mard\u0101n"
    ],
    "wof:name":"`Ali Mardan",
    "wof:placetype":"locality"
},
  "geometry": {"coordinates":[44.6656,39.0476],"type":"Point"}
}