{
  "type": "Feature",
  "properties": {
    "gn:admin1_code":"38",
    "gn:asciiname":"Kallaj",
    "gn:country_code":"IR",
    "gn:dem":427,
    "gn:feature_class":"P",
    "gn:feature_code":"PPL",
    "gn:name":"Kallaj",
    "gn:population":0,
    "gn:timezone":"Asia/Tehran",
    "iso:country":"IR",
    "name:fas_x_preferred":[
        "\u0643\u0644\u062c"
    ],
    "name:und_x_variant":[
        "Kalaj",
        "Kalladzh",
        "Kallaj"
    ],
    "wof:name":"Kallaj",
    "wof:placetype":"locality"
},
  "geometry": {"coordinates":[49.2606,36.70527],"type":"Point"}
}