{
  "type": "Feature",
  "properties": {
    "gn:admin1_code":"5.0",
    "gn:asciiname":"Rezaabad",
    "gn:country_code":"IR",
    "gn:dem":1984,
    "gn:feature_class":"P",
    "gn:feature_code":"PPL",
    "gn:name":"Re\u1e95\u0101\u0101b\u0101d",
    "gn:population":0,
    "gn:timezone":"Asia/Tehran",
    "iso:country":"IR",
    "name:fas_x_preferred":[
        "Re\u1e95\u0101\u0101b\u0101d"
    ],
    "name:fas_x_variant":[
        "\u0631\u0636\u0627 \u0622\u0628\u0627\u062f"
    ],
    "name:und_x_variant":[
        "\u0631\u0636\u0627 \u0622\u0628\u0627\u062f"
    ],
    "wof:name":"Rezaabad",
    "wof:placetype":"locality"
},
  "geometry": {"coordinates":[51.70091,30.56222],"type":"Point"}
}