{
  "type": "Feature",
  "properties": {
    "gn:admin1_code":"35.0",
    "gn:asciiname":"Vashkan",
    "gn:country_code":"IR",
    "gn:dem":1669,
    "gn:feature_class":"P",
    "gn:feature_code":"PPL",
    "gn:name":"V\u0101shkan",
    "gn:population":0,
    "gn:timezone":"Asia/Tehran",
    "iso:country":"IR",
    "name:fas_x_preferred":[
        "\u0648\u0627\u0634\u06a9\u0646"
    ],
    "name:fas_x_variant":[
        "V\u0101shkan"
    ],
    "wof:name":"Vashkan",
    "wof:placetype":"locality"
},
  "geometry": {"coordinates":[51.71878,36.31298],"type":"Point"}
}