{
  "type": "Feature",
  "properties": {
    "gn:admin1_code":"36",
    "gn:asciiname":"Ramin",
    "gn:country_code":"IR",
    "gn:dem":1810,
    "gn:feature_class":"P",
    "gn:feature_code":"PPL",
    "gn:name":"R\u0101m\u012bn",
    "gn:population":0,
    "gn:timezone":"Asia/Tehran",
    "iso:country":"IR",
    "name:azb_x_preferred":[
        "\u0631\u0627\u0645\u06cc\u0646"
    ],
    "name:fas_x_preferred":[
        "\u0631\u0627\u0645\u06cc\u0646"
    ],
    "name:fas_x_variant":[
        "\u062f\u0627\u0645\u06cc\u0646",
        "R\u0101m\u012bn",
        "D\u0101m\u012bn"
    ],
    "name:und_x_variant":[
        "Iraman",
        "Rahm\u012bn"
    ],
    "wof:name":"Ramin",
    "wof:placetype":"locality"
},
  "geometry": {"coordinates":[48.55685,36.55717],"type":"Point"}
}