{
  "type": "Feature",
  "properties": {
    "gn:admin1_code":"40",
    "gn:asciiname":"Anjireh-ye Paiin",
    "gn:country_code":"IR",
    "gn:dem":828,
    "gn:feature_class":"P",
    "gn:feature_code":"PPL",
    "gn:name":"Anj\u012breh-ye P\u0101\u012b\u012bn",
    "gn:population":0,
    "gn:timezone":"Asia/Tehran",
    "iso:country":"IR",
    "name:fas_x_preferred":[
        "Ch\u0101h Anj\u012br-e P\u0101\u2019\u012bn"
    ],
    "name:fas_x_variant":[
        "Ch\u0101h Anj\u012br",
        "\u0686\u0627\u0647 \u0627\u0646\u062c\u06cc\u0631 \u067e\u0627\u0626\u064a\u0646",
        "\u0627\u0646\u062c\u06cc\u0631\u0647 \u067e\u0627\u06cc\u06cc\u0646"
    ],
    "name:und_x_variant":[
        "Anj\u012breh-ye P\u0101\u012b\u012bn"
    ],
    "wof:name":"Anjireh-ye Paiin",
    "wof:placetype":"locality"
},
  "geometry": {"coordinates":[57.57252,34.80862],"type":"Point"}
}