{
  "type": "Feature",
  "properties": {
    "gn:admin1_code":"13",
    "gn:asciiname":"Sheykh Jabr'il",
    "gn:country_code":"IR",
    "gn:dem":1353,
    "gn:feature_class":"P",
    "gn:feature_code":"PPL",
    "gn:name":"Sheykh Jabr\u2019\u012bl",
    "gn:population":0,
    "gn:timezone":"Asia/Tehran",
    "iso:country":"IR",
    "name:fas_x_preferred":[
        "\u0634\u06cc\u062e \u062c\u0628\u0631\u0626\u06cc\u0644"
    ],
    "name:und_x_variant":[
        "Chek\u0101n-e Mans\u016br\u012b",
        "Sheykh Jarv\u0101\u2019\u012bl",
        "Shaikh Jarw\u0101il",
        "Sheykh Jabr\u2019\u012bl"
    ],
    "wof:name":"Sheykh Jabr'il",
    "wof:placetype":"locality"
},
  "geometry": {"coordinates":[46.5995,33.8801],"type":"Point"}
}