{
  "type": "Feature",
  "properties": {
    "gn:admin1_code":"7",
    "gn:asciiname":"Tarun-e Pa'in",
    "gn:country_code":"IR",
    "gn:dem":2035,
    "gn:feature_class":"P",
    "gn:feature_code":"PPL",
    "gn:name":"T\u0101r\u016bn-e P\u0101\u2019\u012bn",
    "gn:population":0,
    "gn:timezone":"Asia/Tehran",
    "iso:country":"IR",
    "name:fas_x_preferred":[
        "\u0633\u0627\u0631\u0627\u0646 \u0633\u0641\u0644\u06cc"
    ],
    "name:fas_x_variant":[
        "S\u0101r\u0101n-e P\u0101\u2019\u012bn",
        "S\u0101r\u0101n-e Sofl\u00e1",
        "\u062a\u0627\u0631\u0648\u0646 \u067e\u0627\u0626\u06cc\u0646",
        "\u0633\u0627\u0631\u0627\u0646 \u067e\u0627\u0626\u06cc\u0646",
        "\u0633\u0627\u0631\u0648\u0646 \u067e\u0627\u0626\u06cc\u0646"
    ],
    "name:und_x_variant":[
        "Deh-e Dameshgaft\u012b",
        "S\u0101r\u0101n-e Seyyed Mo\u1e29ammad",
        "S\u0101r\u0101n Sofl\u00e1",
        "S\u0101r\u0101n",
        "T\u0101r\u016bn-e P\u0101\u2019\u012bn",
        "Sar\u016bn-e P\u0101\u2019\u012bn"
    ],
    "wof:name":"Tarun-e Pa'in",
    "wof:placetype":"locality"
},
  "geometry": {"coordinates":[52.09799,30.39595],"type":"Point"}
}