{
  "type": "Feature",
  "properties": {
    "gn:admin1_code":"15",
    "gn:asciiname":"Shifeh",
    "gn:country_code":"IR",
    "gn:dem":103,
    "gn:feature_class":"P",
    "gn:feature_code":"PPL",
    "gn:name":"Sh\u012bfeh",
    "gn:population":0,
    "gn:timezone":"Asia/Tehran",
    "iso:country":"IR",
    "name:ara_x_preferred":[
        "\u0634\u064a\u0641\u0629"
    ],
    "name:fas_x_preferred":[
        "Sh\u012bfeh"
    ],
    "name:fas_x_variant":[
        "\u0634\u06cc\u0641\u0647"
    ],
    "wof:name":"Shifeh",
    "wof:placetype":"locality"
},
  "geometry": {"coordinates":[49.51081,31.36857],"type":"Point"}
}