{
  "type": "Feature",
  "properties": {
    "gn:admin1_code":"35.0",
    "gn:asciiname":"Powtak",
    "gn:country_code":"IR",
    "gn:dem":262,
    "gn:feature_class":"P",
    "gn:feature_code":"PPL",
    "gn:name":"Powtak",
    "gn:population":0,
    "gn:timezone":"Asia/Tehran",
    "iso:country":"IR",
    "name:fas_x_preferred":[
        "\u06a9\u0647\u0646\u0647 \u067e\u062a\u06a9"
    ],
    "name:fas_x_variant":[
        "\u067e\u0648\u062a\u06a9",
        "\u06a9\u0647\u0646\u0647\u200c\u067e\u062a\u06a9"
    ],
    "name:und_x_variant":[
        "Kohneh Patak",
        "\u06a9\u0647\u0646\u0647 \u067e\u062a\u06a9",
        "Powtak"
    ],
    "wof:name":"Powtak",
    "wof:placetype":"locality"
},
  "geometry": {"coordinates":[50.61164,36.93433],"type":"Point"}
}