{
  "type": "Feature",
  "properties": {
    "gn:admin1_code":"7",
    "gn:asciiname":"Tang-e Hana",
    "gn:country_code":"IR",
    "gn:dem":1585,
    "gn:feature_class":"P",
    "gn:feature_code":"PPL",
    "gn:name":"Tang-e \u1e28an\u0101",
    "gn:population":0,
    "gn:timezone":"Asia/Tehran",
    "iso:country":"IR",
    "name:fas_x_preferred":[
        "\u062a\u0646\u06af \u062d\u0646\u0627"
    ],
    "name:fas_x_variant":[
        "Tang-e \u1e28an\u0101",
        "\u0634\u0647\u0631\u06a9 \u062a\u0646\u06af \u062d\u0646\u0627"
    ],
    "name:msa_x_preferred":[
        "Shahrak-e Tang-e Hana"
    ],
    "name:und_x_variant":[
        "Tang \u1e28an\u0101",
        "Shahrak-e Tang-e \u1e28an\u0101"
    ],
    "wof:name":"Tang-e Hana",
    "wof:placetype":"locality"
},
  "geometry": {"coordinates":[54.12018000000001,29.45334],"type":"Point"}
}