{
  "type": "Feature",
  "properties": {
    "gn:admin1_code":"13",
    "gn:asciiname":"Darkeh-ye Mofidi",
    "gn:country_code":"IR",
    "gn:dem":1600,
    "gn:feature_class":"P",
    "gn:feature_code":"PPL",
    "gn:name":"Darkeh-ye Mof\u012bd\u012b",
    "gn:population":0,
    "gn:timezone":"Asia/Tehran",
    "iso:country":"IR",
    "name:fas_x_preferred":[
        "Darkeh-ye Mof\u012bd\u012b"
    ],
    "wof:name":"Darkeh-ye Mofidi",
    "wof:placetype":"locality"
},
  "geometry": {"coordinates":[46.9425,34.33028],"type":"Point"}
}