{
  "type": "Feature",
  "properties": {
    "gn:admin1_code":"35.0",
    "gn:asciiname":"Chi Tan",
    "gn:country_code":"IR",
    "gn:dem":1630,
    "gn:feature_class":"P",
    "gn:feature_code":"PPL",
    "gn:name":"Ch\u012b Tan",
    "gn:population":0,
    "gn:timezone":"Asia/Tehran",
    "iso:country":"IR",
    "name:fas_x_preferred":[
        "Ch\u012btan"
    ],
    "name:fas_x_variant":[
        "Chet\u012bn",
        "\u0686\u062a\u0646",
        "\u0686\u064a\u062a\u0646",
        "\u0686\u06cc \u062a\u0646"
    ],
    "name:und_x_variant":[
        "Chasan",
        "Ch\u012bten",
        "Chetan",
        "Chitin",
        "Chittin",
        "Ch\u012b Tan"
    ],
    "wof:name":"Chi Tan",
    "wof:placetype":"locality"
},
  "geometry": {"coordinates":[51.4702,36.34412],"type":"Point"}
}