{
  "type": "Feature",
  "properties": {
    "gn:admin1_code":"44",
    "gn:asciiname":"Zakiabad",
    "gn:country_code":"IR",
    "gn:dem":1217,
    "gn:feature_class":"P",
    "gn:feature_code":"PPL",
    "gn:name":"Zak\u012b\u0101b\u0101d",
    "gn:population":0,
    "gn:timezone":"Asia/Tehran",
    "iso:country":"IR",
    "name:fas_x_preferred":[
        "\u0632\u0643\u06cc \u0622\u0628\u0627\u062f"
    ],
    "name:fas_x_variant":[
        "Zak\u012b\u0101b\u0101d",
        "\u0632\u06a9\u06cc\u200c\u0622\u0628\u0627\u062f"
    ],
    "name:msa_x_preferred":[
        "Zakiabad"
    ],
    "name:rus_x_preferred":[
        "\u0417\u0435\u043a\u0438\u0430\u0431\u0430\u0434"
    ],
    "name:und_x_variant":[
        "Zek\u012b\u0101b\u0101d",
        "Zakki\u0101b\u0101d"
    ],
    "wof:name":"Zakiabad",
    "wof:placetype":"locality"
},
  "geometry": {"coordinates":[50.67486,35.83179000000001],"type":"Point"}
}