{
  "type": "Feature",
  "properties": {
    "gn:admin1_code":"8.0",
    "gn:asciiname":"Sangeh Sar",
    "gn:country_code":"IR",
    "gn:dem":716,
    "gn:feature_class":"P",
    "gn:feature_code":"PPL",
    "gn:name":"Sangeh Sar",
    "gn:population":0,
    "gn:timezone":"Asia/Tehran",
    "iso:country":"IR",
    "name:fas_x_preferred":[
        "\u0633\u0646\u06af\u0647 \u0633\u0631"
    ],
    "name:und_x_variant":[
        "\u0633\u0646\u06af\u0647 \u0633\u0631"
    ],
    "wof:name":"Sangeh Sar",
    "wof:placetype":"locality"
},
  "geometry": {"coordinates":[49.78895,36.96556],"type":"Point"}
}