{
  "type": "Feature",
  "properties": {
    "gn:admin1_code":"35.0",
    "gn:asciiname":"Qala Koti",
    "gn:country_code":"IR",
    "gn:dem":11,
    "gn:feature_class":"P",
    "gn:feature_code":"PPL",
    "gn:name":"Qal\u0101 Kot\u012b",
    "gn:population":0,
    "gn:timezone":"Asia/Tehran",
    "iso:country":"IR",
    "name:ara_x_preferred":[
        "\u0642\u0644\u0627\u06a9\u062a\u064a"
    ],
    "name:fas_x_preferred":[
        "Qal\u0101 Kot\u012b"
    ],
    "name:fas_x_variant":[
        "\u0642\u0644\u0627 \u06a9\u062a\u06cc",
        "\u0642\u0644\u0627\u06a9\u062a\u06cc"
    ],
    "name:mzn_x_preferred":[
        "\u0642\u0644\u0627\u06a9\u062a\u06cc"
    ],
    "name:ukr_x_preferred":[
        "\u041a\u0430\u043b\u0430-\u041a\u043e\u0442\u0456"
    ],
    "wof:name":"Qala Koti",
    "wof:placetype":"locality"
},
  "geometry": {"coordinates":[52.47238,36.52128],"type":"Point"}
}