{
  "type": "Feature",
  "properties": {
    "gn:admin1_code":"28.0",
    "gn:asciiname":"Dastgerd-e Mehr Avaran",
    "gn:country_code":"IR",
    "gn:dem":1643,
    "gn:feature_class":"P",
    "gn:feature_code":"PPL",
    "gn:name":"Dastgerd-e Mehr \u0100var\u0101n",
    "gn:population":0,
    "gn:timezone":"Asia/Tehran",
    "iso:country":"IR",
    "name:fas_x_preferred":[
        "Dastjerd-e Mehr \u0100var\u0101n"
    ],
    "name:fas_x_variant":[
        "Dastgerd-e Mehr \u0100var\u0101n",
        "\u062f\u0633\u062a\u06af\u0631\u062f \u0645\u0647\u0631 \u0622\u0648\u0631\u0627\u0646"
    ],
    "name:und_x_variant":[
        "Dastgerd",
        "Dastgerd-e Mehr \u0100var\u0101n",
        "\u062f\u0633\u062a\u06af\u0631\u062f \u0645\u0647\u0631 \u0622\u0648\u0631\u0627\u0646"
    ],
    "wof:name":"Dastgerd-e Mehr Avaran",
    "wof:placetype":"locality"
},
  "geometry": {"coordinates":[51.58433,32.40832],"type":"Point"}
}