{
  "type": "Feature",
  "properties": {
    "gn:admin1_code":"7",
    "gn:asciiname":"Seyyedabad-e Bala",
    "gn:country_code":"IR",
    "gn:dem":1582,
    "gn:feature_class":"P",
    "gn:feature_code":"PPL",
    "gn:name":"Seyyed\u0101b\u0101d-e B\u0101l\u0101",
    "gn:population":0,
    "gn:timezone":"Asia/Tehran",
    "iso:country":"IR",
    "name:fas_x_preferred":[
        "Seyyed\u0101b\u0101d-e B\u0101l\u0101"
    ],
    "wof:name":"Seyyedabad-e Bala",
    "wof:placetype":"locality"
},
  "geometry": {"coordinates":[53.22583,29.77889],"type":"Point"}
}