{
  "type": "Feature",
  "properties": {
    "gn:admin1_code":"28",
    "gn:asciiname":"Bakhsh-e Kommeh",
    "gn:country_code":"IR",
    "gn:dem":2033,
    "gn:feature_class":"P",
    "gn:feature_code":"PPL",
    "gn:name":"Bakhsh-e Kommeh",
    "gn:population":0,
    "gn:timezone":"Asia/Tehran",
    "iso:country":"IR",
    "name:ara_x_preferred":[
        "\u0643\u0645\u0647"
    ],
    "name:aze_x_preferred":[
        "K\u00fcm\u0259"
    ],
    "name:ceb_x_preferred":[
        "Bakhsh-e Kommeh"
    ],
    "name:fas_x_preferred":[
        "\u0628\u062e\u0634 \u06a9\u0645\u0651\u0647"
    ],
    "name:fas_x_variant":[
        "\u06a9\u0645\u0647"
    ],
    "name:mlg_x_preferred":[
        "Komeh"
    ],
    "name:mzn_x_preferred":[
        "\u06a9\u0645\u0647"
    ],
    "name:pol_x_preferred":[
        "Kome"
    ],
    "name:swe_x_preferred":[
        "Bakhsh-e Kommeh"
    ],
    "name:tur_x_preferred":[
        "Kome"
    ],
    "name:und_x_variant":[
        "Komeh",
        "Bakhsh-e Kommeh",
        "Kommeh"
    ],
    "wof:name":"Bakhsh-e Kommeh",
    "wof:placetype":"locality"
},
  "geometry": {"coordinates":[51.59272,31.06828],"type":"Point"}
}