{
  "type": "Feature",
  "properties": {
    "gn:admin1_code":"4.0",
    "gn:asciiname":"Zardari",
    "gn:country_code":"IR",
    "gn:dem":263,
    "gn:feature_class":"P",
    "gn:feature_code":"PPL",
    "gn:name":"Zard\u0101r\u012b",
    "gn:population":0,
    "gn:timezone":"Asia/Tehran",
    "iso:country":"IR",
    "name:fas_x_preferred":[
        "\u0632\u0631\u062f\u0627\u0631\u06cc"
    ],
    "name:und_x_variant":[
        "Zard\u0101r\u012b"
    ],
    "wof:name":"Zardari",
    "wof:placetype":"locality"
},
  "geometry": {"coordinates":[59.25006,26.19372000000001],"type":"Point"}
}