{
  "type": "Feature",
  "properties": {
    "gn:admin1_code":"42",
    "gn:asciiname":"Janabad",
    "gn:country_code":"IR",
    "gn:dem":1250,
    "gn:feature_class":"P",
    "gn:feature_code":"PPL",
    "gn:name":"J\u0101n\u0101b\u0101d",
    "gn:population":0,
    "gn:timezone":"Asia/Tehran",
    "iso:country":"IR",
    "name:fas_x_preferred":[
        "\u062c\u0627\u0646 \u0622\u0628\u0627\u062f"
    ],
    "name:fas_x_variant":[
        "J\u0101n\u0101b\u0101d"
    ],
    "wof:name":"Janabad",
    "wof:placetype":"locality"
},
  "geometry": {"coordinates":[59.60197,35.96098],"type":"Point"}
}