{
  "type": "Feature",
  "properties": {
    "gn:admin1_code":"8",
    "gn:asciiname":"Bishehgah",
    "gn:country_code":"IR",
    "gn:dem":12,
    "gn:feature_class":"P",
    "gn:feature_code":"PPL",
    "gn:name":"B\u012bshehg\u0101h",
    "gn:population":0,
    "gn:timezone":"Asia/Tehran",
    "iso:country":"IR",
    "name:ceb_x_preferred":[
        "B\u012bshehg\u0101h"
    ],
    "name:fas_x_preferred":[
        "\u0628\u06cc\u0634\u0647 \u06af\u0627\u0647"
    ],
    "name:fas_x_variant":[
        "B\u012bshehg\u0101h",
        "\u0628\u06cc\u0634\u0647\u200c\u06af\u0627\u0647"
    ],
    "name:msa_x_preferred":[
        "Bishehgah"
    ],
    "name:swe_x_preferred":[
        "B\u012bshehg\u0101h"
    ],
    "name:ukr_x_preferred":[
        "\u0411\u0456\u0448\u0435-\u0490\u0430\u0445"
    ],
    "name:und_x_variant":[
        "V\u012bshk\u0101"
    ],
    "wof:name":"Bishehgah",
    "wof:placetype":"locality"
},
  "geometry": {"coordinates":[49.17729,37.42382],"type":"Point"}
}