{
  "type": "Feature",
  "properties": {
    "gn:admin1_code":"32.0",
    "gn:asciiname":"Qeshlaq-e Sheykh Mehdi",
    "gn:country_code":"IR",
    "gn:dem":648,
    "gn:feature_class":"P",
    "gn:feature_code":"PPLL",
    "gn:name":"Qeshl\u0101q-e Sheykh Mehd\u012b",
    "gn:population":0,
    "gn:timezone":"Asia/Tehran",
    "iso:country":"IR",
    "name:fas_x_preferred":[
        "\u0642\u0634\u0644\u0627\u0642 \u0634\u06cc\u062e \u0645\u0647\u062f\u06cc"
    ],
    "name:und_x_variant":[
        "Qeshl\u0101q-e Sheykh Mehd\u012b"
    ],
    "wof:name":"Qeshlaq-e Sheykh Mehdi",
    "wof:placetype":"locality"
},
  "geometry": {"coordinates":[47.51600000000001,38.73946],"type":"Point"}
}