{
  "type": "Feature",
  "properties": {
    "gn:admin1_code":"28.0",
    "gn:asciiname":"Rahatabad",
    "gn:country_code":"IR",
    "gn:dem":2088,
    "gn:feature_class":"P",
    "gn:feature_code":"PPL",
    "gn:name":"R\u0101\u1e29at\u0101b\u0101d",
    "gn:population":0,
    "gn:timezone":"Asia/Tehran",
    "iso:country":"IR",
    "name:fas_x_preferred":[
        "\u0631\u0627\u062d\u062a \u0622\u0628\u0627\u062f"
    ],
    "name:fas_x_variant":[
        "R\u0101\u1e29at\u0101b\u0101d",
        "\u0631\u0627\u062d\u062a\u200c\u0622\u0628\u0627\u062f"
    ],
    "wof:name":"Rahatabad",
    "wof:placetype":"locality"
},
  "geometry": {"coordinates":[52.9131,32.7362],"type":"Point"}
}