{
  "type": "Feature",
  "properties": {
    "gn:admin1_code":"15.0",
    "gn:asciiname":"Sho`eyb Nabi-ye Jadid",
    "gn:country_code":"IR",
    "gn:dem":37,
    "gn:feature_class":"P",
    "gn:feature_code":"PPL",
    "gn:name":"Sho\u2018eyb Nab\u012b-ye Jad\u012bd",
    "gn:population":0,
    "gn:timezone":"Asia/Tehran",
    "iso:country":"IR",
    "name:fas_x_preferred":[
        "\u0634\u0639\u06cc\u0628\u0647 \u0646\u0628\u06cc \u062c\u062f\u06cc\u062f"
    ],
    "name:fas_x_variant":[
        "Sho\u2018eybeh Nab\u012b-ye Jad\u012bd",
        "\u0634\u0639\u06cc\u0628 \u0646\u0628\u06cc \u062c\u062f\u06cc\u062f"
    ],
    "name:und_x_variant":[
        "Sho\u2018eyb Nab\u012b-ye Jad\u012bd"
    ],
    "wof:name":"Sho`eyb Nabi-ye Jadid",
    "wof:placetype":"locality"
},
  "geometry": {"coordinates":[48.72402,31.88568],"type":"Point"}
}