{
  "type": "Feature",
  "properties": {
    "gn:admin1_code":"3.0",
    "gn:asciiname":"Dezak",
    "gn:country_code":"IR",
    "gn:dem":2037,
    "gn:feature_class":"P",
    "gn:feature_code":"PPL",
    "gn:name":"Dezak",
    "gn:population":0,
    "gn:timezone":"Asia/Tehran",
    "iso:country":"IR",
    "name:fas_x_preferred":[
        "\u062f\u0650\u0647\u0650 \u0632\u064e\u0643"
    ],
    "name:fas_x_variant":[
        "\u062f\u0632\u0643"
    ],
    "name:und_x_variant":[
        "Deh-e Zak",
        "Dezak",
        "\u062f\u0632\u0643"
    ],
    "wof:name":"Dezak",
    "wof:placetype":"locality"
},
  "geometry": {"coordinates":[50.9636,32.08056],"type":"Point"}
}