{
  "type": "Feature",
  "properties": {
    "gn:admin1_code":"25",
    "gn:asciiname":"Kalateh",
    "gn:country_code":"IR",
    "gn:dem":1665,
    "gn:feature_class":"P",
    "gn:feature_code":"PPL",
    "gn:name":"Kal\u0101teh",
    "gn:population":0,
    "gn:timezone":"Asia/Tehran",
    "iso:country":"IR",
    "name:fas_x_preferred":[
        "Kal\u0101teh"
    ],
    "name:fas_x_variant":[
        "\u0643\u0644\u0627\u062a\u0647"
    ],
    "name:und_x_variant":[
        "\u0643\u0644\u0627\u062a\u0647"
    ],
    "wof:name":"Kalateh",
    "wof:placetype":"locality"
},
  "geometry": {"coordinates":[54.14487,36.35654],"type":"Point"}
}