{
  "type": "Feature",
  "properties": {
    "gn:admin1_code":"44",
    "gn:asciiname":"Mohammadabad-e Nazarabad",
    "gn:country_code":"IR",
    "gn:dem":1176,
    "gn:feature_class":"P",
    "gn:feature_code":"PPL",
    "gn:name":"Mo\u1e29ammad\u0101b\u0101d-e Naz\u0327ar\u0101b\u0101d",
    "gn:population":0,
    "gn:timezone":"Asia/Tehran",
    "iso:country":"IR",
    "name:fas_x_preferred":[
        "\u0645\u064f\u062d\u064e\u0645\u064e\u0651\u062f\u0627\u0628\u0627\u062f\u0650 \u0646\u064e\u0638\u064e\u0631 \u0622\u0628\u0627\u062f"
    ],
    "name:fas_x_variant":[
        "Mo\u1e29ammad\u0101b\u0101d-e Naz\u0327ar\u0101b\u0101d"
    ],
    "wof:name":"Mohammadabad-e Nazarabad",
    "wof:placetype":"locality"
},
  "geometry": {"coordinates":[50.56167,35.96111],"type":"Point"}
}