{
  "type": "Feature",
  "properties": {
    "gn:admin1_code":"4.0",
    "gn:asciiname":"Chileh Sar",
    "gn:country_code":"IR",
    "gn:dem":14,
    "gn:feature_class":"P",
    "gn:feature_code":"PPL",
    "gn:name":"Ch\u012bleh Sar",
    "gn:population":0,
    "gn:timezone":"Asia/Tehran",
    "iso:country":"IR",
    "name:fas_x_preferred":[
        "Ch\u012bleh Sar"
    ],
    "name:fas_x_variant":[
        "\u0686\u06cc\u0644\u0647 \u0633\u0631"
    ],
    "name:und_x_variant":[
        "Temb\u016b\u2019\u012b",
        "N\u012blag",
        "\u0686\u06cc\u0644\u0647 \u0633\u0631"
    ],
    "wof:name":"Chileh Sar",
    "wof:placetype":"locality"
},
  "geometry": {"coordinates":[61.31171,25.42471],"type":"Point"}
}