{
  "type": "Feature",
  "properties": {
    "gn:admin1_code":"34",
    "gn:asciiname":"Qeshlaq-e Aghbagh",
    "gn:country_code":"IR",
    "gn:dem":920,
    "gn:feature_class":"P",
    "gn:feature_code":"PPL",
    "gn:name":"Qeshl\u0101q-e \u0100ghb\u0101gh",
    "gn:population":0,
    "gn:timezone":"Asia/Tehran",
    "iso:country":"IR",
    "name:fas_x_preferred":[
        "\u0642\u0650\u0634\u0644\u0627\u0642\u0650 \u0622\u063a\u0628\u0627\u063a"
    ],
    "name:fas_x_variant":[
        "Qeshl\u0101q-e \u0100ghb\u0101gh"
    ],
    "wof:name":"Qeshlaq-e Aghbagh",
    "wof:placetype":"locality"
},
  "geometry": {"coordinates":[50.61667,34.95],"type":"Point"}
}