{
  "type": "Feature",
  "properties": {
    "gn:admin1_code":"13",
    "gn:asciiname":"Bani `Abdi",
    "gn:country_code":"IR",
    "gn:dem":1279,
    "gn:feature_class":"P",
    "gn:feature_code":"PPL",
    "gn:name":"Ban\u012b \u2018Abd\u012b",
    "gn:population":0,
    "gn:timezone":"Asia/Tehran",
    "iso:country":"IR",
    "name:fas_x_preferred":[
        "Ban\u012b \u2018Abd\u012b"
    ],
    "wof:name":"Bani `Abdi",
    "wof:placetype":"locality"
},
  "geometry": {"coordinates":[47.45306,34.38],"type":"Point"}
}