{
  "type": "Feature",
  "properties": {
    "gn:admin1_code":"42",
    "gn:asciiname":"Maghilan",
    "gn:country_code":"IR",
    "gn:dem":2217,
    "gn:feature_class":"P",
    "gn:feature_code":"PPL",
    "gn:name":"Magh\u012bl\u0101n",
    "gn:population":0,
    "gn:timezone":"Asia/Tehran",
    "iso:country":"IR",
    "name:fas_x_preferred":[
        "\u0645\u0642\u06cc\u0644\u0627\u0646"
    ],
    "name:fas_x_variant":[
        "Magh\u012bl\u0101n",
        "Moq\u012bl\u0101n",
        "\u0645\u063a\u06cc\u0644\u0627\u0646"
    ],
    "name:und_x_variant":[
        "Mag\u012bl\u0101n"
    ],
    "wof:name":"Maghilan",
    "wof:placetype":"locality"
},
  "geometry": {"coordinates":[59.91189,33.30445],"type":"Point"}
}