{
  "type": "Feature",
  "properties": {
    "gn:admin1_code":"38",
    "gn:asciiname":"Kareh Rud",
    "gn:country_code":"IR",
    "gn:dem":852,
    "gn:feature_class":"P",
    "gn:feature_code":"PPL",
    "gn:name":"Kareh R\u016bd",
    "gn:population":0,
    "gn:timezone":"Asia/Tehran",
    "iso:country":"IR",
    "name:fas_x_preferred":[
        "Kareh R\u016bd"
    ],
    "name:fas_x_variant":[
        "Qareh R\u016bd",
        "\u06a9\u0631\u0647 \u0631\u0648\u062f"
    ],
    "name:und_x_variant":[
        "Karehr\u016bd",
        "Kera Rood",
        "Korakhrud",
        "Korahr\u016bd",
        "Koreh R\u016bd",
        "\u06a9\u0631\u0647 \u0631\u0648\u062f"
    ],
    "wof:name":"Kareh Rud",
    "wof:placetype":"locality"
},
  "geometry": {"coordinates":[49.73073,36.57604],"type":"Point"}
}