{
  "type": "Feature",
  "properties": {
    "gn:admin1_code":"4.0",
    "gn:asciiname":"Kaputi",
    "gn:country_code":"IR",
    "gn:dem":1292,
    "gn:feature_class":"P",
    "gn:feature_code":"PPL",
    "gn:name":"Kap\u016bt\u012b",
    "gn:population":0,
    "gn:timezone":"Asia/Tehran",
    "iso:country":"IR",
    "name:fas_x_preferred":[
        "Kap\u016bt\u012b"
    ],
    "wof:name":"Kaputi",
    "wof:placetype":"locality"
},
  "geometry": {"coordinates":[62.50806,26.73861],"type":"Point"}
}