{
  "type": "Feature",
  "properties": {
    "gn:admin1_code":"41",
    "gn:asciiname":"Kalateh-ye Sa`id",
    "gn:country_code":"IR",
    "gn:dem":1957,
    "gn:feature_class":"P",
    "gn:feature_code":"PPL",
    "gn:name":"Kal\u0101teh-ye Sa\u2018\u012bd",
    "gn:population":0,
    "gn:timezone":"Asia/Tehran",
    "iso:country":"IR",
    "name:fas_x_preferred":[
        "Kal\u0101teh-ye Sa\u2018\u012bd"
    ],
    "name:fas_x_variant":[
        "\u06a9\u0644\u0627\u062a\u0647 \u0633\u0639\u06cc\u062f"
    ],
    "wof:name":"Kalateh-ye Sa`id",
    "wof:placetype":"locality"
},
  "geometry": {"coordinates":[58.94904,33.68295],"type":"Point"}
}