{
  "type": "Feature",
  "properties": {
    "gn:admin1_code":"5",
    "gn:asciiname":"Bufah Zari",
    "gn:country_code":"IR",
    "gn:dem":1187,
    "gn:feature_class":"P",
    "gn:feature_code":"PPL",
    "gn:name":"B\u016bfah Z\u0101r\u012b",
    "gn:population":0,
    "gn:timezone":"Asia/Tehran",
    "iso:country":"IR",
    "name:fas_x_preferred":[
        "B\u016bfah Z\u0101r\u012b"
    ],
    "name:fas_x_variant":[
        "\u0628\u0648\u0641\u0647 \u0632\u0627\u0631\u06cc",
        "\u0628\u06cc\u0641\u0647 \u0632\u0627\u0631\u06cc"
    ],
    "name:und_x_variant":[
        "\u0628\u0648\u0641\u0647 \u0632\u0627\u0631\u06cc",
        "B\u012bfah Z\u0101r\u012b"
    ],
    "wof:name":"Bufah Zari",
    "wof:placetype":"locality"
},
  "geometry": {"coordinates":[50.52889,31.12831],"type":"Point"}
}