{
  "type": "Feature",
  "properties": {
    "gn:admin1_code":"15.0",
    "gn:asciiname":"Leh Bid",
    "gn:country_code":"IR",
    "gn:dem":2022,
    "gn:feature_class":"P",
    "gn:feature_code":"PPL",
    "gn:name":"Leh B\u012bd",
    "gn:population":0,
    "gn:timezone":"Asia/Tehran",
    "iso:country":"IR",
    "name:fas_x_preferred":[
        "Leh B\u012bd"
    ],
    "name:fas_x_variant":[
        "\u0644\u0647 \u0628\u06cc\u062f"
    ],
    "name:und_x_variant":[
        "\u0644\u0647 \u0628\u06cc\u062f"
    ],
    "wof:name":"Leh Bid",
    "wof:placetype":"locality"
},
  "geometry": {"coordinates":[50.31068,31.73831],"type":"Point"}
}