{
  "type": "Feature",
  "properties": {
    "gn:admin1_code":"13",
    "gn:asciiname":"Mianrud",
    "gn:country_code":"IR",
    "gn:dem":1365,
    "gn:feature_class":"P",
    "gn:feature_code":"PPL",
    "gn:name":"M\u012b\u0101nr\u016bd",
    "gn:population":0,
    "gn:timezone":"Asia/Tehran",
    "iso:country":"IR",
    "name:ara_x_preferred":[
        "\u0645\u064a\u0627\u0646\u0631\u0648\u062f"
    ],
    "name:aze_x_preferred":[
        "Miyanrud"
    ],
    "name:ceb_x_preferred":[
        "M\u012b\u0101nr\u016bd\u0101n"
    ],
    "name:fas_x_preferred":[
        "\u0645\u06cc\u0627\u0646\u0631\u0648\u062f"
    ],
    "name:fas_x_variant":[
        "M\u012b\u0101nr\u016bd"
    ],
    "name:ita_x_preferred":[
        "Mianrud"
    ],
    "name:mlg_x_preferred":[
        "Mianrud"
    ],
    "name:mzn_x_preferred":[
        "\u0645\u06cc\u0627\u0646\u0631\u0648\u062f"
    ],
    "name:rus_x_preferred":[
        "\u041c\u0438\u0430\u043d\u0440\u0443\u0434"
    ],
    "name:swe_x_preferred":[
        "M\u012b\u0101nr\u016bd\u0101n"
    ],
    "name:zho_x_preferred":[
        "\u7c73\u63da\u9b6f\u5fb7"
    ],
    "wof:name":"Mianrud",
    "wof:placetype":"locality"
},
  "geometry": {"coordinates":[47.0571,33.8887],"type":"Point"}
}