{
  "type": "Feature",
  "properties": {
    "gn:admin1_code":"13",
    "gn:asciiname":"Mianrud",
    "gn:country_code":"IR",
    "gn:dem":1365,
    "gn:feature_class":"P",
    "gn:feature_code":"PPL",
    "gn:name":"M\u012b\u0101nr\u016bd",
    "gn:population":0,
    "gn:timezone":"Asia/Tehran",
    "iso:country":"IR",
    "name:fas_x_preferred":[
        "\u0645\u06cc\u0627\u0646\u0631\u0648\u062f"
    ],
    "name:fas_x_variant":[
        "M\u012b\u0101nr\u016bd"
    ],
    "wof:name":"Mianrud",
    "wof:placetype":"locality"
},
  "geometry": {"coordinates":[47.0571,33.8887],"type":"Point"}
}