{
  "type": "Feature",
  "properties": {
    "gn:admin1_code":"35.0",
    "gn:asciiname":"Paski Mahalleh",
    "gn:country_code":"IR",
    "gn:dem":119,
    "gn:feature_class":"P",
    "gn:feature_code":"PPL",
    "gn:name":"P\u0101sk\u012b Ma\u1e29alleh",
    "gn:population":0,
    "gn:timezone":"Asia/Tehran",
    "iso:country":"IR",
    "name:fas_x_preferred":[
        "\u0643\u064e\u062a\u0650\u0647 \u067e\u064f\u0634\u062a\u0650 \u0633\u064f\u0641\u0644\u064e\u0649"
    ],
    "name:fas_x_variant":[
        "\u0643\u064f\u062a\u0650\u0647 \u067e\u064f\u0634\u062a\u0650 \u067e\u0627\u0633\u064e\u06af\u06cc \u0645\u064e\u062d\u064e\u0644\u0650\u0651\u0647",
        "Kateh Posht-e Sofl\u00e1",
        "P\u0101sk\u012b Ma\u1e29alleh",
        "\u067e\u0627\u0633\u06a9\u06cc \u0645\u062d\u0644\u0647"
    ],
    "name:und_x_variant":[
        "Koteh Posht-e P\u0101sag\u012b Ma\u1e29alleh"
    ],
    "wof:name":"Paski Mahalleh",
    "wof:placetype":"locality"
},
  "geometry": {"coordinates":[52.38565,36.44183],"type":"Point"}
}