{
  "type": "Feature",
  "properties": {
    "gn:admin1_code":"4.0",
    "gn:asciiname":"Rahimabad-e Luchak",
    "gn:country_code":"IR",
    "gn:dem":1712,
    "gn:feature_class":"P",
    "gn:feature_code":"PPL",
    "gn:name":"Ra\u1e29\u012bm\u0101b\u0101d-e L\u016bchak",
    "gn:population":0,
    "gn:timezone":"Asia/Tehran",
    "iso:country":"IR",
    "name:fas_x_preferred":[
        "Ra\u1e29\u012bm\u0101b\u0101d-e L\u016bchak"
    ],
    "wof:name":"Rahimabad-e Luchak",
    "wof:placetype":"locality"
},
  "geometry": {"coordinates":[60.73333,29.33333],"type":"Point"}
}