{
  "type": "Feature",
  "properties": {
    "gn:admin1_code":"16",
    "gn:asciiname":"Bayanlu",
    "gn:country_code":"IR",
    "gn:dem":1539,
    "gn:feature_class":"P",
    "gn:feature_code":"PPL",
    "gn:name":"Bay\u0101nl\u016b",
    "gn:population":0,
    "gn:timezone":"Asia/Tehran",
    "iso:country":"IR",
    "name:fas_x_preferred":[
        "\u0628\u06cc\u0627\u0646\u0644\u0648"
    ],
    "name:fas_x_variant":[
        "Bay\u0101nl\u016b"
    ],
    "name:und_x_variant":[
        "B\u012banu",
        "Bey\u0101nl\u016b",
        "Bayanloo",
        "Biy\u0101nlu"
    ],
    "wof:name":"Bayanlu",
    "wof:placetype":"locality"
},
  "geometry": {"coordinates":[47.85688,36.00439],"type":"Point"}
}