{
  "type": "Feature",
  "properties": {
    "gn:admin1_code":"4",
    "gn:asciiname":"Gholamak",
    "gn:country_code":"IR",
    "gn:dem":144,
    "gn:feature_class":"P",
    "gn:feature_code":"PPL",
    "gn:name":"Ghol\u0101mak",
    "gn:population":0,
    "gn:timezone":"Asia/Tehran",
    "iso:country":"IR",
    "name:fas_x_preferred":[
        "Gol\u0101mak"
    ],
    "name:fas_x_variant":[
        "\u063a\u0644\u0627\u0645\u06a9"
    ],
    "name:und_x_variant":[
        "Ghol\u0101mak"
    ],
    "wof:name":"Gholamak",
    "wof:placetype":"locality"
},
  "geometry": {"coordinates":[59.70907,25.86538],"type":"Point"}
}