{
  "type": "Feature",
  "properties": {
    "gn:admin1_code":"15",
    "gn:asciiname":"Boneh-ye Mashhadi `Al",
    "gn:country_code":"IR",
    "gn:dem":709,
    "gn:feature_class":"P",
    "gn:feature_code":"PPL",
    "gn:name":"Boneh-ye Mashhad\u012b \u2018Al",
    "gn:population":0,
    "gn:timezone":"Asia/Tehran",
    "iso:country":"IR",
    "name:fas_x_preferred":[
        "\u0628\u064f\u0646\u0650\u06c0 \u0645\u064e\u0634\u0647\u064e\u062f\u06cc \u0639\u064e\u0644"
    ],
    "name:fas_x_variant":[
        "Boneh-ye Mashhad\u012b \u2018Al"
    ],
    "name:und_x_variant":[
        "Bunneh Mashidi \u2018Ali"
    ],
    "wof:name":"Boneh-ye Mashhadi `Al",
    "wof:placetype":"locality"
},
  "geometry": {"coordinates":[49.85,31.56667],"type":"Point"}
}