{
  "type": "Feature",
  "properties": {
    "gn:admin1_code":"13.0",
    "gn:asciiname":"Qalkhani",
    "gn:country_code":"IR",
    "gn:dem":1992,
    "gn:feature_class":"P",
    "gn:feature_code":"PPL",
    "gn:name":"Qalkh\u0101n\u012b",
    "gn:population":0,
    "gn:timezone":"Asia/Tehran",
    "iso:country":"IR",
    "name:fas_x_preferred":[
        "\u0642\u0644\u062e\u0627\u0646\u06cc"
    ],
    "name:fas_x_variant":[
        "Qalkh\u0101n\u012b"
    ],
    "wof:name":"Qalkhani",
    "wof:placetype":"locality"
},
  "geometry": {"coordinates":[46.1523,34.5761],"type":"Point"}
}