{
  "type": "Feature",
  "properties": {
    "gn:admin1_code":"5",
    "gn:asciiname":"Cheshmeh Chenar",
    "gn:country_code":"IR",
    "gn:dem":1749,
    "gn:feature_class":"P",
    "gn:feature_code":"PPL",
    "gn:name":"Cheshmeh Chen\u0101r",
    "gn:population":0,
    "gn:timezone":"Asia/Tehran",
    "iso:country":"IR",
    "name:fas_x_preferred":[
        "\u062f\u0648\u0644\u0686\u064e\u0646\u062f\u064e\u0631"
    ],
    "name:fas_x_variant":[
        "Cheshmeh Chen\u0101r",
        "\u0686\u0634\u0645\u0647 \u0686\u0646\u0627\u0631",
        "D\u016blchend\u0101r",
        "\u062f\u0648\u0644\u0686\u0646\u062f\u0627\u0631"
    ],
    "name:und_x_variant":[
        "D\u016blchandar"
    ],
    "wof:name":"Cheshmeh Chenar",
    "wof:placetype":"locality"
},
  "geometry": {"coordinates":[51.34415,30.73521],"type":"Point"}
}