{
  "type": "Feature",
  "properties": {
    "gn:admin1_code":"11.0",
    "gn:asciiname":"Berkeh-ye Now",
    "gn:country_code":"IR",
    "gn:dem":284,
    "gn:feature_class":"P",
    "gn:feature_code":"PPL",
    "gn:name":"Berkeh-ye Now",
    "gn:population":0,
    "gn:timezone":"Asia/Tehran",
    "iso:country":"IR",
    "name:fas_x_preferred":[
        "\u062f\u0648\u06a9\u0644 \u067e\u0647\u0646"
    ],
    "name:fas_x_variant":[
        "\u0628\u0631\u06a9\u0647 \u0646\u0648"
    ],
    "name:und_x_variant":[
        "Dowkal Pahn",
        "Berkeh-ye Now"
    ],
    "wof:name":"Berkeh-ye Now",
    "wof:placetype":"locality"
},
  "geometry": {"coordinates":[55.31203000000001,27.29858],"type":"Point"}
}