{
  "type": "Feature",
  "properties": {
    "gn:admin1_code":"41",
    "gn:asciiname":"Karimu",
    "gn:country_code":"IR",
    "gn:dem":1988,
    "gn:feature_class":"P",
    "gn:feature_code":"PPL",
    "gn:name":"Kar\u012bm\u016b",
    "gn:population":0,
    "gn:timezone":"Asia/Tehran",
    "iso:country":"IR",
    "name:ceb_x_preferred":[
        "Kar\u012bm\u016b"
    ],
    "name:fas_x_preferred":[
        "Kar\u012bm\u016b"
    ],
    "name:fas_x_variant":[
        "\u06a9\u0631\u064a\u0645\u0648",
        "\u06a9\u0631\u06cc\u0645\u0648"
    ],
    "name:swe_x_preferred":[
        "Kar\u012bm\u016b"
    ],
    "wof:name":"Karimu",
    "wof:placetype":"locality"
},
  "geometry": {"coordinates":[58.50384,34.03169],"type":"Point"}
}