{
  "type": "Feature",
  "properties": {
    "gn:admin1_code":"11",
    "gn:asciiname":"Dam Tang Bagh",
    "gn:country_code":"IR",
    "gn:dem":433,
    "gn:feature_class":"P",
    "gn:feature_code":"PPL",
    "gn:name":"Dam Tang B\u0101gh",
    "gn:population":0,
    "gn:timezone":"Asia/Tehran",
    "iso:country":"IR",
    "name:ara_x_preferred":[
        "\u062a\u0646\u063a \u0628\u0627\u063a"
    ],
    "name:fas_x_preferred":[
        "\u062f\u064e\u0645 \u062a\u064e\u0646\u06af \u0628\u0627\u063a"
    ],
    "name:fas_x_variant":[
        "\u062f\u064e\u0645\u0650 \u062a\u064e\u0646\u06af \u0628\u0627\u063a",
        "Dam Tang B\u0101gh",
        "\u062a\u0646\u06af \u0628\u0627\u063a"
    ],
    "name:msa_x_preferred":[
        "Tang-e Bagh"
    ],
    "name:und_x_variant":[
        "Dam-e Tang B\u0101gh"
    ],
    "wof:name":"Dam Tang Bagh",
    "wof:placetype":"locality"
},
  "geometry": {"coordinates":[56.23222,27.46913],"type":"Point"}
}