{
  "type": "Feature",
  "properties": {
    "gn:admin1_code":"29",
    "gn:asciiname":"Hamidabad",
    "gn:country_code":"IR",
    "gn:dem":2568,
    "gn:feature_class":"P",
    "gn:feature_code":"PPL",
    "gn:name":"\u1e28am\u012bd\u0101b\u0101d",
    "gn:population":0,
    "gn:timezone":"Asia/Tehran",
    "iso:country":"IR",
    "name:fas_x_preferred":[
        "\u062d\u0645\u06cc\u062f \u0622\u0628\u0627\u062f"
    ],
    "name:fas_x_variant":[
        "\u1e28am\u012bd\u0101b\u0101d"
    ],
    "wof:name":"Hamidabad",
    "wof:placetype":"locality"
},
  "geometry": {"coordinates":[56.8862,29.3402],"type":"Point"}
}