{
  "type": "Feature",
  "properties": {
    "gn:admin1_code":"7",
    "gn:asciiname":"Rahmatabad",
    "gn:country_code":"IR",
    "gn:dem":1268,
    "gn:feature_class":"P",
    "gn:feature_code":"PPL",
    "gn:name":"Ra\u1e29mat\u0101b\u0101d",
    "gn:population":0,
    "gn:timezone":"Asia/Tehran",
    "iso:country":"IR",
    "name:fas_x_preferred":[
        "K\u0101z\u0327em\u0101b\u0101d"
    ],
    "name:fas_x_variant":[
        "\u06a9\u0627\u0638\u0645 \u0622\u0628\u0627\u062f",
        "\u0631\u062d\u0645\u062a \u0622\u0628\u0627\u062f"
    ],
    "name:und_x_variant":[
        "\u06a9\u0627\u0638\u0645 \u0622\u0628\u0627\u062f",
        "Ra\u1e29mat\u0101b\u0101d"
    ],
    "wof:name":"Rahmatabad",
    "wof:placetype":"locality"
},
  "geometry": {"coordinates":[53.8992,28.3514],"type":"Point"}
}