{
  "type": "Feature",
  "properties": {
    "gn:admin1_code":"35",
    "gn:asciiname":"Tappeh Sar",
    "gn:country_code":"IR",
    "gn:dem":238,
    "gn:feature_class":"P",
    "gn:feature_code":"PPL",
    "gn:name":"Tappeh Sar",
    "gn:population":0,
    "gn:timezone":"Asia/Tehran",
    "iso:country":"IR",
    "name:fas_x_preferred":[
        "\u062a\u067e\u0647 \u0633\u0631"
    ],
    "name:fas_x_variant":[
        "\u062a\u067e\u0647\u200c\u0633\u0631"
    ],
    "name:mzn_x_preferred":[
        "\u062a\u067e\u0647\u200c\u0633\u0631"
    ],
    "wof:name":"Tappeh Sar",
    "wof:placetype":"locality"
},
  "geometry": {"coordinates":[52.86645,36.33134],"type":"Point"}
}