{
  "type": "Feature",
  "properties": {
    "gn:admin1_code":"9.0",
    "gn:asciiname":"Aq Tappeh",
    "gn:country_code":"IR",
    "gn:dem":1913,
    "gn:feature_class":"P",
    "gn:feature_code":"PPL",
    "gn:name":"\u0100q Tappeh",
    "gn:population":0,
    "gn:timezone":"Asia/Tehran",
    "iso:country":"IR",
    "name:fas_x_preferred":[
        "\u0100q Tappeh"
    ],
    "name:fas_x_variant":[
        "\u0622\u0642 \u062a\u067e\u0647",
        "\u0622\u0642\u200c\u062a\u067e\u0647"
    ],
    "name:msa_x_preferred":[
        "Aq Tappeh"
    ],
    "name:und_x_variant":[
        "\u0100q Tappeh-ye Nashr",
        "\u0100q Tepe"
    ],
    "wof:name":"Aq Tappeh",
    "wof:placetype":"locality"
},
  "geometry": {"coordinates":[48.83843,34.68421],"type":"Point"}
}