{
  "type": "Feature",
  "properties": {
    "gn:admin1_code":"29",
    "gn:asciiname":"Maleshkahu",
    "gn:country_code":"IR",
    "gn:dem":1055,
    "gn:feature_class":"P",
    "gn:feature_code":"PPL",
    "gn:name":"Maleshkah\u016b",
    "gn:population":0,
    "gn:timezone":"Asia/Tehran",
    "iso:country":"IR",
    "name:fas_x_preferred":[
        "\u0645\u0644\u0634\u06a9\u0647\u0648"
    ],
    "name:fas_x_variant":[
        "Maleshkah\u016b"
    ],
    "name:und_x_variant":[
        "Molshakah\u016b"
    ],
    "wof:name":"Maleshkahu",
    "wof:placetype":"locality"
},
  "geometry": {"coordinates":[57.9572,26.9732],"type":"Point"}
}