{
  "type": "Feature",
  "properties": {
    "gn:admin1_code":"15",
    "gn:asciiname":"Nowtaragi-ye Mokhtari",
    "gn:country_code":"IR",
    "gn:dem":779,
    "gn:feature_class":"P",
    "gn:feature_code":"PPL",
    "gn:name":"Nowtarag\u012b-ye Mokht\u0101r\u012b",
    "gn:population":0,
    "gn:timezone":"Asia/Tehran",
    "iso:country":"IR",
    "name:fas_x_preferred":[
        "Nowtarg\u012b-ye Mokht\u0101r\u012b"
    ],
    "name:fas_x_variant":[
        "Nartark\u012b-ye Mokht\u0101r\u012b",
        "\u0646\u0631\u062a\u0631\u06a9\u06cc \u0645\u062e\u062a\u0627\u0631\u06cc",
        "\u0646\u0648\u062a\u0631\u06af\u06cc \u0645\u062e\u062a\u0627\u0631\u06cc"
    ],
    "name:und_x_variant":[
        "\u0646\u0631\u062a\u0631\u06a9\u06cc \u0645\u062e\u062a\u0627\u0631\u06cc",
        "Nowtarag\u012b-ye Mokht\u0101r\u012b"
    ],
    "wof:name":"Nowtaragi-ye Mokhtari",
    "wof:placetype":"locality"
},
  "geometry": {"coordinates":[49.74538,31.84052],"type":"Point"}
}