{
  "type": "Feature",
  "properties": {
    "gn:admin1_code":"13",
    "gn:asciiname":"Habibvand-e `Olya",
    "gn:country_code":"IR",
    "gn:dem":765,
    "gn:feature_class":"P",
    "gn:feature_code":"PPL",
    "gn:name":"\u1e28ab\u012bbvand-e \u2018Oly\u0101",
    "gn:population":0,
    "gn:timezone":"Asia/Tehran",
    "iso:country":"IR",
    "name:fas_x_preferred":[
        "\u1e28ab\u012bbvand-e \u2018Oly\u0101"
    ],
    "name:und_x_variant":[
        "Mahak\u012b \u2018\u0100bed",
        "\u1e28ab\u012bbvand"
    ],
    "wof:name":"Habibvand-e `Olya",
    "wof:placetype":"locality"
},
  "geometry": {"coordinates":[45.95,34.45],"type":"Point"}
}