{
  "type": "Feature",
  "properties": {
    "gn:admin1_code":"13",
    "gn:asciiname":"Dowkushkan-e Hoseynkhani",
    "gn:country_code":"IR",
    "gn:dem":1408,
    "gn:feature_class":"P",
    "gn:feature_code":"PPL",
    "gn:name":"Dowk\u016bshk\u0101n-e \u1e28oseynkh\u0101n\u012b",
    "gn:population":0,
    "gn:timezone":"Asia/Tehran",
    "iso:country":"IR",
    "name:fas_x_preferred":[
        "\u062f\u0648\u06a9\u0648\u0634\u06a9\u0627\u0646 \u062d\u0633\u06cc\u0646 \u062e\u0627\u0646\u06cc"
    ],
    "name:fas_x_variant":[
        "Dok\u016bshk\u0101n-e \u1e28oseynkh\u0101n\u012b",
        "Dowk\u016bshk\u0101n-e \u1e28oseynkh\u0101n\u012b",
        "\u062f\u0648\u06a9\u0648\u0634\u06a9\u0627\u0646\u200c\u062d\u0633\u06cc\u0646\u062e\u0627\u0646\u06cc"
    ],
    "wof:name":"Dowkushkan-e Hoseynkhani",
    "wof:placetype":"locality"
},
  "geometry": {"coordinates":[46.9438,34.1895],"type":"Point"}
}