{
  "type": "Feature",
  "properties": {
    "gn:admin1_code":"16.0",
    "gn:asciiname":"Kukh-e Darbar",
    "gn:country_code":"IR",
    "gn:dem":1432,
    "gn:feature_class":"P",
    "gn:feature_code":"PPL",
    "gn:name":"K\u016bkh-e D\u0101rbar",
    "gn:population":0,
    "gn:timezone":"Asia/Tehran",
    "iso:country":"IR",
    "name:fas_x_preferred":[
        "\u06a9\u0648\u062e \u062f\u0627\u0631\u0628\u0631"
    ],
    "name:fas_x_variant":[
        "K\u016bkh-e D\u0101rbar"
    ],
    "wof:name":"Kukh-e Darbar",
    "wof:placetype":"locality"
},
  "geometry": {"coordinates":[45.7783,35.9653],"type":"Point"}
}