{
  "type": "Feature",
  "properties": {
    "gn:admin1_code":"16",
    "gn:asciiname":"Chul Bolagh",
    "gn:country_code":"IR",
    "gn:dem":1961,
    "gn:feature_class":"P",
    "gn:feature_code":"PPL",
    "gn:name":"Ch\u016bl Bol\u0101gh",
    "gn:population":0,
    "gn:timezone":"Asia/Tehran",
    "iso:country":"IR",
    "name:ara_x_preferred":[
        "\u062a\u0634\u0648\u0644 \u0628\u0644\u0627\u063a"
    ],
    "name:ceb_x_preferred":[
        "Ch\u016bl Bol\u0101gh"
    ],
    "name:ckb_x_preferred":[
        "\u0686\u06c6\u06b5\u0628\u06b5\u0627\u062e"
    ],
    "name:fas_x_preferred":[
        "\u0686\u0648\u0644 \u0628\u064f\u0644\u0627\u063a"
    ],
    "name:fas_x_variant":[
        "\u0686\u064f\u0644 \u0628\u064f\u0644\u0627\u063a",
        "\u0686\u0648\u0644 \u0628\u064f\u0644\u0627\u062e",
        "Ch\u016bl Bol\u0101gh",
        "Chel Bol\u0101gh",
        "\u0686\u0644 \u0628\u0644\u0627\u063a",
        "\u0686\u0648\u0644 \u0628\u0644\u0627\u063a"
    ],
    "name:swe_x_preferred":[
        "Ch\u016bl Bol\u0101gh"
    ],
    "name:und_x_variant":[
        "Chul\u0101gh",
        "Chul Bul\u0101q",
        "Chol Bol\u0101gh",
        "Ch\u016bl Bol\u0101kh"
    ],
    "wof:name":"Chul Bolagh",
    "wof:placetype":"locality"
},
  "geometry": {"coordinates":[46.95702,35.97325],"type":"Point"}
}