{
  "type": "Feature",
  "properties": {
    "gn:admin1_code":"3.0",
    "gn:asciiname":"Yan Bolaghi",
    "gn:country_code":"IR",
    "gn:dem":2382,
    "gn:feature_class":"P",
    "gn:feature_code":"PPL",
    "gn:name":"Y\u0101n Bol\u0101gh\u012b",
    "gn:population":0,
    "gn:timezone":"Asia/Tehran",
    "iso:country":"IR",
    "name:fas_x_preferred":[
        "Y\u0101n Bol\u0101gh\u012b"
    ],
    "name:fas_x_variant":[
        "\u06cc\u0627\u0646 \u0628\u0644\u0627\u063a\u06cc"
    ],
    "name:und_x_variant":[
        "\u06cc\u0627\u0646 \u0628\u0644\u0627\u063a\u06cc"
    ],
    "wof:name":"Yan Bolaghi",
    "wof:placetype":"locality"
},
  "geometry": {"coordinates":[50.45311,32.55658],"type":"Point"}
}