{
  "type": "Feature",
  "properties": {
    "gn:admin1_code":"42",
    "gn:asciiname":"Kaj Derakht",
    "gn:country_code":"IR",
    "gn:dem":1261,
    "gn:feature_class":"P",
    "gn:feature_code":"PPL",
    "gn:name":"K\u0101j Derakht",
    "gn:population":0,
    "gn:timezone":"Asia/Tehran",
    "iso:country":"IR",
    "name:fas_x_preferred":[
        "\u06a9\u0627\u062c \u062f\u0631\u062e\u062a"
    ],
    "name:fas_x_variant":[
        "K\u0101j Derakht"
    ],
    "wof:name":"Kaj Derakht",
    "wof:placetype":"locality"
},
  "geometry": {"coordinates":[59.11525,35.21632],"type":"Point"}
}