{
  "type": "Feature",
  "properties": {
    "gn:admin1_code":"9",
    "gn:asciiname":"Pir Bak",
    "gn:country_code":"IR",
    "gn:dem":1771,
    "gn:feature_class":"P",
    "gn:feature_code":"PPL",
    "gn:name":"P\u012br Bak",
    "gn:population":0,
    "gn:timezone":"Asia/Tehran",
    "iso:country":"IR",
    "name:fas_x_preferred":[
        "\u067e\u064a\u0631 \u0628\u064e\u0643"
    ],
    "name:fas_x_variant":[
        "\u067e\u064a\u0631 \u062f\u064e\u0643",
        "\u067e\u064a\u0631\u06cc \u0628\u06cc\u06a9",
        "P\u012br Bak",
        "P\u012br\u012b Beyk",
        "\u067e\u06cc\u0631 \u0628\u06a9",
        "\u067e\u06cc\u0631 \u0628\u06af"
    ],
    "name:und_x_variant":[
        "P\u012br Dak",
        "P\u012br Bag"
    ],
    "wof:name":"Pir Bak",
    "wof:placetype":"locality"
},
  "geometry": {"coordinates":[49.12347000000001,35.28494],"type":"Point"}
}