{
  "type": "Feature",
  "properties": {
    "gn:admin1_code":"10",
    "gn:asciiname":"Remavand-e `Olya",
    "gn:country_code":"IR",
    "gn:dem":629,
    "gn:feature_class":"P",
    "gn:feature_code":"PPL",
    "gn:name":"Rem\u0101vand-e \u2018Oly\u0101",
    "gn:population":0,
    "gn:timezone":"Asia/Tehran",
    "iso:country":"IR",
    "name:fas_x_preferred":[
        "Rem\u0101vand-e \u2018Oly\u0101"
    ],
    "wof:name":"Remavand-e `Olya",
    "wof:placetype":"locality"
},
  "geometry": {"coordinates":[47.15,33.33333],"type":"Point"}
}