{
  "type": "Feature",
  "properties": {
    "gn:admin1_code":"26.0",
    "gn:asciiname":"Towchal Hotel",
    "gn:country_code":"IR",
    "gn:dem":3581,
    "gn:feature_class":"P",
    "gn:feature_code":"PPL",
    "gn:name":"Towch\u0101l Hotel",
    "gn:population":0,
    "gn:timezone":"Asia/Tehran",
    "iso:country":"IR",
    "name:fas_x_preferred":[
        "\u062a\u064f\u0648\u0686\u0627\u0644 \u064a\u0633\u062a\u06af\u0627\u0647\u0650"
    ],
    "name:fas_x_variant":[
        "Towch\u0101l \u012astg\u0101h-e"
    ],
    "wof:name":"Towchal Hotel",
    "wof:placetype":"locality"
},
  "geometry": {"coordinates":[51.40103,35.88763],"type":"Point"}
}