{
  "type": "Feature",
  "properties": {
    "gn:admin1_code":"43",
    "gn:asciiname":"Dartum",
    "gn:country_code":"IR",
    "gn:dem":1552,
    "gn:feature_class":"P",
    "gn:feature_code":"PPL",
    "gn:name":"Dart\u016bm",
    "gn:population":0,
    "gn:timezone":"Asia/Tehran",
    "iso:country":"IR",
    "name:fas_x_preferred":[
        "Dart\u016bm"
    ],
    "name:fas_x_variant":[
        "\u062f\u0631\u062a\u0648\u0645"
    ],
    "name:und_x_variant":[
        "Dartowm",
        "Dartum",
        "\u062f\u0631\u062a\u0648\u0645"
    ],
    "wof:name":"Dartum",
    "wof:placetype":"locality"
},
  "geometry": {"coordinates":[57.30501,37.29162],"type":"Point"}
}