{
  "type": "Feature",
  "properties": {
    "gn:admin1_code":"7",
    "gn:asciiname":"Berkow",
    "gn:country_code":"IR",
    "gn:dem":292,
    "gn:feature_class":"P",
    "gn:feature_code":"PPL",
    "gn:name":"Berkow",
    "gn:population":0,
    "gn:timezone":"Asia/Tehran",
    "iso:country":"IR",
    "name:fas_x_preferred":[
        "\u0628\u0631\u0643\u0648"
    ],
    "name:fas_x_variant":[
        "\u0628\u0650\u0631\u0643\u0650\u0647",
        "\u0628\u064e\u0631\u0643\u0648",
        "\u0628\u0631\u06a9\u0647 \u0627\u0628\u06cc"
    ],
    "name:und_x_variant":[
        "Berkeh",
        "Bark\u016b",
        "Berkow",
        "Berkeh Ab\u012b"
    ],
    "wof:name":"Berkow",
    "wof:placetype":"locality"
},
  "geometry": {"coordinates":[52.39206,27.96911],"type":"Point"}
}