{
  "type": "Feature",
  "properties": {
    "gn:admin1_code":"29",
    "gn:asciiname":"Hoseynabad-e Hejri",
    "gn:country_code":"IR",
    "gn:dem":2074,
    "gn:feature_class":"P",
    "gn:feature_code":"PPL",
    "gn:name":"\u1e28oseyn\u0101b\u0101d-e Hejr\u012b",
    "gn:population":0,
    "gn:timezone":"Asia/Tehran",
    "iso:country":"IR",
    "name:fas_x_preferred":[
        "\u1e28oseyn\u0101b\u0101d-e Hejr\u012b"
    ],
    "wof:name":"Hoseynabad-e Hejri",
    "wof:placetype":"locality"
},
  "geometry": {"coordinates":[56.18306,30.62083],"type":"Point"}
}