{
  "type": "Feature",
  "properties": {
    "gn:admin1_code":"9",
    "gn:asciiname":"Paridar",
    "gn:country_code":"IR",
    "gn:dem":2017,
    "gn:feature_class":"P",
    "gn:feature_code":"PPL",
    "gn:name":"Par\u012bdar",
    "gn:population":0,
    "gn:timezone":"Asia/Tehran",
    "iso:country":"IR",
    "name:fas_x_preferred":[
        "\u067e\u0631\u06cc\u062f\u0631"
    ],
    "name:fas_x_variant":[
        "Par\u012by\u0101n",
        "Par\u012bdar"
    ],
    "name:und_x_variant":[
        "F\u0101r\u012bd\u0101r",
        "Par\u012bdar Par\u012b",
        "Paridar Pari",
        "Par\u012bdar-e Par\u012b"
    ],
    "wof:name":"Paridar",
    "wof:placetype":"locality"
},
  "geometry": {"coordinates":[49.02965,34.11868],"type":"Point"}
}