{
  "type": "Feature",
  "properties": {
    "gn:admin1_code":"32",
    "gn:asciiname":"Hoshneh",
    "gn:country_code":"IR",
    "gn:dem":1765,
    "gn:feature_class":"P",
    "gn:feature_code":"PPL",
    "gn:name":"Hoshneh",
    "gn:population":0,
    "gn:timezone":"Asia/Tehran",
    "iso:country":"IR",
    "name:fas_x_preferred":[
        "\u0647\u0634\u0646\u0647"
    ],
    "wof:name":"Hoshneh",
    "wof:placetype":"locality"
},
  "geometry": {"coordinates":[48.3751,38.571],"type":"Point"}
}