{
  "type": "Feature",
  "properties": {
    "gn:admin1_code":"41.0",
    "gn:asciiname":"Dalun",
    "gn:country_code":"IR",
    "gn:dem":1538,
    "gn:feature_class":"P",
    "gn:feature_code":"PPL",
    "gn:name":"D\u0101l\u016bn",
    "gn:population":0,
    "gn:timezone":"Asia/Tehran",
    "iso:country":"IR",
    "name:fas_x_preferred":[
        "D\u0101l\u016bn"
    ],
    "name:und_x_variant":[
        "D\u0101l\u0101n"
    ],
    "wof:name":"Dalun",
    "wof:placetype":"locality"
},
  "geometry": {"coordinates":[60.54694,32.46194000000001],"type":"Point"}
}