{
  "type": "Feature",
  "properties": {
    "gn:admin1_code":"23",
    "gn:asciiname":"Zir Tang",
    "gn:country_code":"IR",
    "gn:dem":1456,
    "gn:feature_class":"P",
    "gn:feature_code":"PPL",
    "gn:name":"Z\u012br Tang",
    "gn:population":0,
    "gn:timezone":"Asia/Tehran",
    "iso:country":"IR",
    "name:fas_x_preferred":[
        "\u0632\u064a\u0631 \u062a\u0646\u06af"
    ],
    "name:fas_x_variant":[
        "Z\u012br Tang"
    ],
    "wof:name":"Zir Tang",
    "wof:placetype":"locality"
},
  "geometry": {"coordinates":[48.9418,33.3821],"type":"Point"}
}