{
  "type": "Feature",
  "properties": {
    "gn:admin1_code":"16",
    "gn:asciiname":"Qarah Nav",
    "gn:country_code":"IR",
    "gn:dem":1557,
    "gn:feature_class":"P",
    "gn:feature_code":"PPL",
    "gn:name":"Qarah N\u0101v",
    "gn:population":0,
    "gn:timezone":"Asia/Tehran",
    "iso:country":"IR",
    "name:ara_x_preferred":[
        "\u0642\u0631\u0647 \u0646\u0627\u0648"
    ],
    "name:ceb_x_preferred":[
        "Qarah N\u0101v"
    ],
    "name:ckb_x_preferred":[
        "\u0642\u06d5\u0631\u06d5\u0646\u0627\u0648"
    ],
    "name:fas_x_preferred":[
        "\u0642\u0631\u0647 \u0646\u0627\u0648"
    ],
    "name:fas_x_variant":[
        "Qareh N\u0101v",
        "Qarah N\u0101v",
        "\u0642\u0631\u0647\u200c\u0646\u0627\u0648"
    ],
    "name:kur_x_preferred":[
        "Qerenaw"
    ],
    "name:swe_x_preferred":[
        "Qarah N\u0101v"
    ],
    "wof:name":"Qarah Nav",
    "wof:placetype":"locality"
},
  "geometry": {"coordinates":[46.65678,36.28976],"type":"Point"}
}