{
  "type": "Feature",
  "properties": {
    "gn:admin1_code":"4.0",
    "gn:asciiname":"Rimdan Kamal",
    "gn:country_code":"IR",
    "gn:dem":18,
    "gn:feature_class":"P",
    "gn:feature_code":"PPL",
    "gn:name":"R\u012bmd\u0101n Kam\u0101l",
    "gn:population":0,
    "gn:timezone":"Asia/Tehran",
    "iso:country":"IR",
    "name:fas_x_preferred":[
        "Mo\u1e29ammad Kam\u0101l"
    ],
    "name:fas_x_variant":[
        "R\u012bmd\u0101n Kam\u0101l",
        "\u0631\u06cc\u0645\u062f\u0627\u0646 \u06a9\u0645\u0627\u0644"
    ],
    "wof:name":"Rimdan Kamal",
    "wof:placetype":"locality"
},
  "geometry": {"coordinates":[61.44043000000001,25.42722],"type":"Point"}
}