{
  "type": "Feature",
  "properties": {
    "gn:admin1_code":"4.0",
    "gn:asciiname":"Rujegan",
    "gn:country_code":"IR",
    "gn:dem":720,
    "gn:feature_class":"P",
    "gn:feature_code":"PPL",
    "gn:name":"R\u016bjeg\u0101n",
    "gn:population":0,
    "gn:timezone":"Asia/Tehran",
    "iso:country":"IR",
    "name:fas_x_preferred":[
        "R\u016bjeg\u0101n"
    ],
    "wof:name":"Rujegan",
    "wof:placetype":"locality"
},
  "geometry": {"coordinates":[60.17306,26.38167],"type":"Point"}
}