{
  "type": "Feature",
  "properties": {
    "gn:admin1_code":"28.0",
    "gn:asciiname":"Artijan",
    "gn:country_code":"IR",
    "gn:dem":2635,
    "gn:feature_class":"P",
    "gn:feature_code":"PPL",
    "gn:name":"Art\u012bj\u0101n",
    "gn:population":0,
    "gn:timezone":"Asia/Tehran",
    "iso:country":"IR",
    "name:ara_x_preferred":[
        "\u0623\u0631\u062a\u064a \u062c\u0627\u0646"
    ],
    "name:fas_x_preferred":[
        "\u0100rt\u012bj\u0101n"
    ],
    "name:fas_x_variant":[
        "Art\u012bj\u0101n",
        "\u0627\u0631\u062a\u06cc\u062c\u0627\u0646",
        "\u0622\u0631\u062a\u06cc \u062c\u0627\u0646",
        "\u0627\u0631\u062a\u06af\u0648\u0646",
        "\u0627\u0631\u062a\u06cc\u200c\u062c\u0627\u0646"
    ],
    "name:und_x_variant":[
        "Artej\u0101n",
        "\u0627\u0631\u062a\u06cc\u062c\u0627\u0646",
        "\u0100rt\u012b J\u0101n",
        "Artag\u016bn"
    ],
    "wof:name":"Artijan",
    "wof:placetype":"locality"
},
  "geometry": {"coordinates":[50.30447,33.12811],"type":"Point"}
}