{
  "type": "Feature",
  "properties": {
    "gn:admin1_code":"23.0",
    "gn:asciiname":"Serenji",
    "gn:country_code":"IR",
    "gn:dem":1719,
    "gn:feature_class":"P",
    "gn:feature_code":"PPL",
    "gn:name":"Serenj\u012b",
    "gn:population":0,
    "gn:timezone":"Asia/Tehran",
    "iso:country":"IR",
    "name:fas_x_preferred":[
        "\u0633\u0631\u0646\u062c\u06cc"
    ],
    "name:und_x_variant":[
        "Serenj\u012b"
    ],
    "wof:name":"Serenji",
    "wof:placetype":"locality"
},
  "geometry": {"coordinates":[47.99795,33.88402],"type":"Point"}
}