{
  "type": "Feature",
  "properties": {
    "gn:admin1_code":"41",
    "gn:asciiname":"Mazra`eh-ye Amirabad",
    "gn:country_code":"IR",
    "gn:dem":1560,
    "gn:feature_class":"P",
    "gn:feature_code":"PPLF",
    "gn:name":"Mazra\u2018eh-ye Am\u012br\u0101b\u0101d",
    "gn:population":0,
    "gn:timezone":"Asia/Tehran",
    "iso:country":"IR",
    "name:fas_x_preferred":[
        "\u0627\u0645\u06cc\u0631 \u0622\u0628\u0627\u062f"
    ],
    "name:fas_x_variant":[
        "\u0645\u0632\u0631\u0639\u0647 \u0627\u0645\u06cc\u0631 \u0622\u0628\u0627\u062f"
    ],
    "name:und_x_variant":[
        "Am\u012br\u0101b\u0101d",
        "Mazra\u2018eh-ye Am\u012br\u0101b\u0101d"
    ],
    "wof:name":"Mazra`eh-ye Amirabad",
    "wof:placetype":"locality"
},
  "geometry": {"coordinates":[59.65272,33.52500999999999],"type":"Point"}
}