{
  "type": "Feature",
  "properties": {
    "gn:admin1_code":"33",
    "gn:asciiname":"Chorur",
    "gn:country_code":"IR",
    "gn:dem":1665,
    "gn:feature_class":"P",
    "gn:feature_code":"PPL",
    "gn:name":"Chor\u016br",
    "gn:population":0,
    "gn:timezone":"Asia/Tehran",
    "iso:country":"IR",
    "name:fas_x_preferred":[
        "\u0686\u0631\u0648\u0631"
    ],
    "name:fas_x_variant":[
        "Chor\u016br"
    ],
    "wof:name":"Chorur",
    "wof:placetype":"locality"
},
  "geometry": {"coordinates":[47.7459,37.6495],"type":"Point"}
}