{
  "type": "Feature",
  "properties": {
    "gn:admin1_code":"35",
    "gn:asciiname":"Kenet",
    "gn:country_code":"IR",
    "gn:dem":609,
    "gn:feature_class":"P",
    "gn:feature_code":"PPL",
    "gn:name":"Kenet",
    "gn:population":0,
    "gn:timezone":"Asia/Tehran",
    "iso:country":"IR",
    "name:fas_x_preferred":[
        "\u0643\u0646\u062a"
    ],
    "name:und_x_variant":[
        "\u0643\u0646\u062a",
        "Kenet"
    ],
    "wof:name":"Kenet",
    "wof:placetype":"locality"
},
  "geometry": {"coordinates":[53.5401,36.58839],"type":"Point"}
}