{
  "type": "Feature",
  "properties": {
    "gn:admin1_code":"26",
    "gn:asciiname":"Meshkin Dasht",
    "gn:country_code":"IR",
    "gn:dem":1241,
    "gn:feature_class":"P",
    "gn:feature_code":"PPL",
    "gn:name":"Meshk\u012bn Dasht",
    "gn:population":0,
    "gn:timezone":"Asia/Tehran",
    "iso:country":"IR",
    "name:ara_x_preferred":[
        "\u0645\u0634\u0643\u064a\u0646 \u062f\u0634\u062a"
    ],
    "name:aze_x_preferred":[
        "Me\u015fkind\u0259\u015ft"
    ],
    "name:fas_x_preferred":[
        "\u0645\u0650\u0634\u06af\u064a\u0646 \u0622\u0628\u0627\u062f"
    ],
    "name:fas_x_variant":[
        "\u0645\u064f\u0634\u0643\u064a\u0646 \u0622\u0628\u0627\u062f",
        "\u0645\u0634\u06a9\u06cc\u0646 \u0622\u0628\u0627\u062f",
        "Meshg\u012bn\u0101b\u0101d",
        "Meshk\u012bn\u0101b\u0101d",
        "\u0645\u0634\u06a9\u06cc\u0646 \u062f\u0634\u062a",
        "\u0645\u0634\u06a9\u06cc\u0646\u200c\u062f\u0634\u062a"
    ],
    "name:ita_x_preferred":[
        "Meshkin Dasht"
    ],
    "name:mlg_x_preferred":[
        "Meshkin Dasht"
    ],
    "name:msa_x_preferred":[
        "Meshkin Dasht"
    ],
    "name:rus_x_preferred":[
        "\u041c\u0435\u0448\u043a\u0438\u043d\u0434\u0435\u0448\u0442"
    ],
    "name:tur_x_preferred":[
        "Me\u015fkinde\u015ft"
    ],
    "name:und_x_variant":[
        "Mushk\u012bn\u0101b\u0101d",
        "Miskin\u0101b\u0101d",
        "Moshk\u012bn\u0101b\u0101d",
        "Meshk\u012bn Dasht"
    ],
    "name:urd_x_preferred":[
        "\u0645\u0634\u06a9\u06cc\u0646\u200c\u062f\u0634\u062a"
    ],
    "wof:name":"Meshkin Dasht",
    "wof:placetype":"locality"
},
  "geometry": {"coordinates":[50.94376,35.74988],"type":"Point"}
}