{
  "type": "Feature",
  "properties": {
    "gn:admin1_code":"32",
    "gn:asciiname":"Esma`il Kandi",
    "gn:country_code":"IR",
    "gn:dem":1055,
    "gn:feature_class":"P",
    "gn:feature_code":"PPL",
    "gn:name":"Esm\u0101\u2018\u012bl Kand\u012b",
    "gn:population":0,
    "gn:timezone":"Asia/Tehran",
    "iso:country":"IR",
    "name:fas_x_preferred":[
        "\u0627\u0633\u0645\u0627\u0639\u064a\u0644 \u0643\u0646\u062f\u06cc"
    ],
    "name:fas_x_variant":[
        "\u0627\u0650\u0633\u0645\u0627\u0639\u064a\u0644\u06cc \u0643\u064e\u0646\u062f\u06cc",
        "Esm\u0101\u2018\u012bl Kand\u012b"
    ],
    "name:und_x_variant":[
        "Esm\u0101\u2018\u012bl\u012b Kand\u012b"
    ],
    "wof:name":"Esma`il Kandi",
    "wof:placetype":"locality"
},
  "geometry": {"coordinates":[47.8937,38.9629],"type":"Point"}
}