{
  "type": "Feature",
  "properties": {
    "gn:admin1_code":"15.0",
    "gn:asciiname":"Ordofeh",
    "gn:country_code":"IR",
    "gn:dem":666,
    "gn:feature_class":"P",
    "gn:feature_code":"PPL",
    "gn:name":"Ordofeh",
    "gn:population":0,
    "gn:timezone":"Asia/Tehran",
    "iso:country":"IR",
    "name:fas_x_preferred":[
        "\u0647\u0631\u062f\u0641\u0647"
    ],
    "name:fas_x_variant":[
        "\u0627\u0631\u062f\u0641\u0647"
    ],
    "name:und_x_variant":[
        "Hardafeh",
        "Ordofeh"
    ],
    "wof:name":"Ordofeh",
    "wof:placetype":"locality"
},
  "geometry": {"coordinates":[49.87873,31.99144],"type":"Point"}
}