{
  "type": "Feature",
  "properties": {
    "gn:admin1_code":"35",
    "gn:asciiname":"Shoomiya",
    "gn:country_code":"IR",
    "gn:dem":-3,
    "gn:feature_class":"P",
    "gn:feature_code":"PPL",
    "gn:name":"Shoomiya",
    "gn:population":0,
    "gn:timezone":"Asia/Tehran",
    "iso:country":"IR",
    "name:fas_x_preferred":[
        "\u0634\u0648\u0645\u064a\u0627"
    ],
    "name:fas_x_variant":[
        "\u0634\u0648\u0645\u0627",
        "\u0634\u0648\u0645\u064a\u0651\u0627",
        "Sh\u016bm\u012b\u0101",
        "\u0634\u0648\u0645\u06cc\u0627"
    ],
    "name:und_x_variant":[
        "Sh\u016bm\u0101",
        "Sh\u016bm\u012by\u0101"
    ],
    "wof:name":"Shoomiya",
    "wof:placetype":"locality"
},
  "geometry": {"coordinates":[52.25598,36.55865],"type":"Point"}
}