{
  "type": "Feature",
  "properties": {
    "gn:admin1_code":"29",
    "gn:asciiname":"Kamar Koti",
    "gn:country_code":"IR",
    "gn:dem":618,
    "gn:feature_class":"P",
    "gn:feature_code":"PPL",
    "gn:name":"Kamar Kot\u012b",
    "gn:population":0,
    "gn:timezone":"Asia/Tehran",
    "iso:country":"IR",
    "name:fas_x_preferred":[
        "Kamar Kot\u012b"
    ],
    "wof:name":"Kamar Koti",
    "wof:placetype":"locality"
},
  "geometry": {"coordinates":[57.21666999999999,28.01667],"type":"Point"}
}