{
  "type": "Feature",
  "properties": {
    "gn:admin1_code":"4",
    "gn:asciiname":"Gahrigan",
    "gn:country_code":"IR",
    "gn:dem":1689,
    "gn:feature_class":"P",
    "gn:feature_code":"PPL",
    "gn:name":"Gahr\u012bg\u0101n",
    "gn:population":0,
    "gn:timezone":"Asia/Tehran",
    "iso:country":"IR",
    "name:fas_x_preferred":[
        "\u06af\u0647\u0631\u06cc\u06af\u0627\u0646"
    ],
    "name:fas_x_variant":[
        "Gahr\u012bg\u0101n"
    ],
    "wof:name":"Gahrigan",
    "wof:placetype":"locality"
},
  "geometry": {"coordinates":[60.6735,28.6264],"type":"Point"}
}