{
  "type": "Feature",
  "properties": {
    "gn:admin1_code":"4",
    "gn:asciiname":"Bangoli-ye-Sorkh",
    "gn:cc2":"IR",
    "gn:country_code":"IR",
    "gn:dem":308,
    "gn:feature_class":"P",
    "gn:feature_code":"PPL",
    "gn:name":"Bangol\u012b-ye-Sorkh",
    "gn:population":0,
    "gn:timezone":"Asia/Tehran",
    "iso:country":"IR",
    "name:fas_x_preferred":[
        "Bangol\u012b-ye-Sorkh"
    ],
    "name:und_x_variant":[
        "Bangol\u012b-Ye-Sorkh",
        "Bangol\u012b Sorkh"
    ],
    "wof:name":"Bangoli-ye-Sorkh",
    "wof:placetype":"locality"
},
  "geometry": {"coordinates":[59.52139,26.14083],"type":"Point"}
}