{
  "type": "Feature",
  "properties": {
    "gn:admin1_code":"4.0",
    "gn:asciiname":"Qaderabad",
    "gn:country_code":"IR",
    "gn:dem":1302,
    "gn:feature_class":"P",
    "gn:feature_code":"PPLF",
    "gn:name":"Q\u0101der\u0101b\u0101d",
    "gn:population":0,
    "gn:timezone":"Asia/Tehran",
    "iso:country":"IR",
    "name:fas_x_preferred":[
        "\u0642\u0627\u062f\u0631 \u0622\u0628\u0627\u062f"
    ],
    "name:fas_x_variant":[
        "Q\u0101der\u0101b\u0101d"
    ],
    "name:und_x_variant":[
        "Ghader Abad"
    ],
    "wof:name":"Qaderabad",
    "wof:placetype":"locality"
},
  "geometry": {"coordinates":[61.58251,27.14839000000001],"type":"Point"}
}