{
  "type": "Feature",
  "properties": {
    "gn:admin1_code":"15",
    "gn:asciiname":"Mo'asseseh-ye Sheykh Jaber Ka`b",
    "gn:country_code":"IR",
    "gn:dem":32,
    "gn:feature_class":"P",
    "gn:feature_code":"PPL",
    "gn:name":"Mo\u2019asseseh-ye Sheykh J\u0101ber Ka\u2018b",
    "gn:population":0,
    "gn:timezone":"Asia/Tehran",
    "iso:country":"IR",
    "name:fas_x_preferred":[
        "Mo\u2019asseseh-ye Sheykh J\u0101ber Ka\u2018b"
    ],
    "wof:name":"Mo'asseseh-ye Sheykh Jaber Ka`b",
    "wof:placetype":"locality"
},
  "geometry": {"coordinates":[48.54417,31.71417000000001],"type":"Point"}
}