{
  "type": "Feature",
  "properties": {
    "gn:admin1_code":"9",
    "gn:asciiname":"Qeshlaq-e Mohammadi",
    "gn:cc2":"IR",
    "gn:country_code":"IR",
    "gn:dem":2009,
    "gn:feature_class":"P",
    "gn:feature_code":"PPL",
    "gn:name":"Qeshl\u0101q-e Mo\u1e29ammad\u012b",
    "gn:population":0,
    "gn:timezone":"Asia/Tehran",
    "iso:country":"IR",
    "name:fas_x_preferred":[
        "\u0642\u0650\u0634\u0644\u0627\u0642\u0650 \u0645\u064f\u062d\u064e\u0645\u064e\u0651\u062f\u06cc"
    ],
    "name:fas_x_variant":[
        "\u063a\u0650\u0634\u0644\u064e\u063a",
        "Qeshl\u0101q-e Mo\u1e29ammad\u012b",
        "\u0642\u0634\u0644\u0627\u0642 \u0645\u062d\u0645\u062f\u06cc"
    ],
    "name:msa_x_preferred":[
        "Qeshlaq-e Mohammadi"
    ],
    "name:und_x_variant":[
        "Gheshlagh"
    ],
    "wof:name":"Qeshlaq-e Mohammadi",
    "wof:placetype":"locality"
},
  "geometry": {"coordinates":[48.91667,34.06667],"type":"Point"}
}