{
  "type": "Feature",
  "properties": {
    "gn:admin1_code":"29",
    "gn:asciiname":"Geru",
    "gn:cc2":"IR",
    "gn:country_code":"IR",
    "gn:dem":2016,
    "gn:feature_class":"P",
    "gn:feature_code":"PPL",
    "gn:name":"Ger\u016b",
    "gn:population":0,
    "gn:timezone":"Asia/Tehran",
    "iso:country":"IR",
    "name:fas_x_preferred":[
        "Ger\u016b"
    ],
    "name:und_x_variant":[
        "Gor\u016b"
    ],
    "wof:name":"Geru",
    "wof:placetype":"locality"
},
  "geometry": {"coordinates":[56.32361,28.82111],"type":"Point"}
}