{
  "type": "Feature",
  "properties": {
    "gn:admin1_code":"36",
    "gn:asciiname":"Chehrabad",
    "gn:country_code":"IR",
    "gn:dem":1450,
    "gn:feature_class":"P",
    "gn:feature_code":"PPL",
    "gn:name":"Chehr\u0101b\u0101d",
    "gn:population":0,
    "gn:timezone":"Asia/Tehran",
    "iso:country":"IR",
    "name:azb_x_preferred":[
        "\u0686\u0647\u0631\u0647 \u0622\u0628\u0627\u062f"
    ],
    "name:ceb_x_preferred":[
        "Chehr\u0101b\u0101d"
    ],
    "name:fas_x_preferred":[
        "\u0686\u0647\u0631 \u0622\u0628\u0627\u062f"
    ],
    "name:fas_x_variant":[
        "\u0686\u0650\u0647\u0631\u0650\u0647 \u0622\u0628\u0627\u062f",
        "Chehr\u0101b\u0101d",
        "\u0686\u0647\u0631\u0647\u200c\u0622\u0628\u0627\u062f"
    ],
    "name:swe_x_preferred":[
        "Chehr\u0101b\u0101d"
    ],
    "name:und_x_variant":[
        "Chehreh\u0101b\u0101d"
    ],
    "wof:name":"Chehrabad",
    "wof:placetype":"locality"
},
  "geometry": {"coordinates":[47.8717,36.8774],"type":"Point"}
}