{
  "type": "Feature",
  "properties": {
    "gn:admin1_code":"15.0",
    "gn:asciiname":"Seyyed Behzad",
    "gn:country_code":"IR",
    "gn:dem":966,
    "gn:feature_class":"P",
    "gn:feature_code":"PPL",
    "gn:name":"Seyyed Behz\u0101d",
    "gn:population":0,
    "gn:timezone":"Asia/Tehran",
    "iso:country":"IR",
    "name:fas_x_preferred":[
        "Seyyed Behz\u0101d"
    ],
    "name:fas_x_variant":[
        "\u0633\u06cc\u062f \u0628\u0647\u0632\u0627\u062f"
    ],
    "wof:name":"Seyyed Behzad",
    "wof:placetype":"locality"
},
  "geometry": {"coordinates":[50.09685,31.36771],"type":"Point"}
}