{
  "type": "Feature",
  "properties": {
    "gn:admin1_code":"23",
    "gn:asciiname":"Kahriz Bazvand",
    "gn:country_code":"IR",
    "gn:dem":1153,
    "gn:feature_class":"P",
    "gn:feature_code":"PPL",
    "gn:name":"Kahr\u012bz B\u0101zvand",
    "gn:population":0,
    "gn:timezone":"Asia/Tehran",
    "iso:country":"IR",
    "name:fas_x_preferred":[
        "\u0627\u0650\u0645\u0627\u0645\u0632\u0627\u062f\u0650\u0647 \u06af\u064a\u0698\u0627\u0646"
    ],
    "name:fas_x_variant":[
        "\u06af\u06cc\u0698\u0627\u0646",
        "G\u012bzh\u0101n",
        "\u06a9\u0647\u0631\u06cc\u0632 \u0628\u0627\u0632\u0648\u0646\u062f",
        "\u06a9\u0647\u0631\u06cc\u0632"
    ],
    "name:und_x_variant":[
        "Kahr\u012bz B\u0101zvand",
        "Kahr\u012bz"
    ],
    "wof:name":"Kahriz Bazvand",
    "wof:placetype":"locality"
},
  "geometry": {"coordinates":[47.61107,33.25391],"type":"Point"}
}