{
  "type": "Feature",
  "properties": {
    "gn:admin1_code":"16",
    "gn:asciiname":"Rasheh Deh",
    "gn:country_code":"IR",
    "gn:dem":1403,
    "gn:feature_class":"P",
    "gn:feature_code":"PPL",
    "gn:name":"Rasheh Deh",
    "gn:population":0,
    "gn:timezone":"Asia/Tehran",
    "iso:country":"IR",
    "name:fas_x_preferred":[
        "\u0631\u064e\u0634\u0650\u0647 \u062f\u0650\u0647"
    ],
    "name:fas_x_variant":[
        "\u0631\u064e\u0634\u064e\u0647 \u062f\u0650\u0647",
        "\u0631\u0634\u0647 \u062f\u0647"
    ],
    "name:und_x_variant":[
        "Rashah Deh",
        "Rasheh Deh"
    ],
    "wof:name":"Rasheh Deh",
    "wof:placetype":"locality"
},
  "geometry": {"coordinates":[46.2455,35.5685],"type":"Point"}
}