{
  "type": "Feature",
  "properties": {
    "gn:admin1_code":"15",
    "gn:asciiname":"`Avazabad",
    "gn:country_code":"IR",
    "gn:dem":590,
    "gn:feature_class":"P",
    "gn:feature_code":"PPL",
    "gn:name":"\u2018Ava\u1e95\u0101b\u0101d",
    "gn:population":0,
    "gn:timezone":"Asia/Tehran",
    "iso:country":"IR",
    "name:fas_x_preferred":[
        "\u0639\u0648\u0636 \u0622\u0628\u0627\u062f"
    ],
    "name:fas_x_variant":[
        "\u2018Ava\u1e95\u0101b\u0101d"
    ],
    "wof:name":"`Avazabad",
    "wof:placetype":"locality"
},
  "geometry": {"coordinates":[49.36229,31.95944],"type":"Point"}
}