{
  "type": "Feature",
  "properties": {
    "gn:admin1_code":"43.0",
    "gn:asciiname":"Davidokh-e `Olya",
    "gn:country_code":"IR",
    "gn:dem":1041,
    "gn:feature_class":"P",
    "gn:feature_code":"PPL",
    "gn:name":"Dav\u012bdokh-e \u2018Oly\u0101",
    "gn:population":0,
    "gn:timezone":"Asia/Tehran",
    "iso:country":"IR",
    "name:fas_x_preferred":[
        "Yekkeh T\u016bt D\u016bydokh-e B\u0101l\u0101"
    ],
    "name:fas_x_variant":[
        "\u062f\u0648\u06cc\u062f\u062e \u0639\u0644\u064a\u0627",
        "\u062f\u0648\u06cc\u062f\u062e \u0628\u0627\u0644\u0627",
        "\u062f\u0648\u06cc\u062f\u0648\u062e \u0639\u0644\u064a\u0627"
    ],
    "name:und_x_variant":[
        "Dav\u012bdokh-e \u2018Oly\u0101",
        "Duydokh",
        "Dav\u012bdokh-e B\u0101l\u0101",
        "Dav\u012bd\u016bkh-e \u2018Oly\u0101"
    ],
    "wof:name":"Davidokh-e `Olya",
    "wof:placetype":"locality"
},
  "geometry": {"coordinates":[56.68856,38.12408],"type":"Point"}
}