{
  "type": "Feature",
  "properties": {
    "gn:admin1_code":"5",
    "gn:asciiname":"Kal",
    "gn:country_code":"IR",
    "gn:dem":910,
    "gn:feature_class":"P",
    "gn:feature_code":"PPL",
    "gn:name":"Kal",
    "gn:population":0,
    "gn:timezone":"Asia/Tehran",
    "iso:country":"IR",
    "name:bos_x_preferred":[
        "Kal"
    ],
    "name:ceb_x_preferred":[
        "Kal"
    ],
    "name:ces_x_preferred":[
        "Kal"
    ],
    "name:fas_x_preferred":[
        "\u0643\u064e\u0644"
    ],
    "name:nld_x_preferred":[
        "Kal"
    ],
    "name:pol_x_preferred":[
        "Kal"
    ],
    "name:por_x_preferred":[
        "Kal"
    ],
    "name:slv_x_preferred":[
        "Kal"
    ],
    "name:swe_x_preferred":[
        "Kal"
    ],
    "name:tur_x_preferred":[
        "Kal"
    ],
    "name:uzb_x_preferred":[
        "Kal"
    ],
    "wof:name":"Kal",
    "wof:placetype":"locality"
},
  "geometry": {"coordinates":[50.28389,31.00167],"type":"Point"}
}