{
  "type": "Feature",
  "properties": {
    "gn:admin1_code":"33",
    "gn:asciiname":"Bayram Kandi",
    "gn:country_code":"IR",
    "gn:dem":1413,
    "gn:feature_class":"P",
    "gn:feature_code":"PPL",
    "gn:name":"B\u0101yr\u0101m Kand\u012b",
    "gn:population":0,
    "gn:timezone":"Asia/Tehran",
    "iso:country":"IR",
    "name:fas_x_preferred":[
        "\u0628\u0627\u06cc\u0631\u0627\u0645 \u06a9\u0646\u062f\u06cc"
    ],
    "name:fas_x_variant":[
        "B\u0101yr\u0101m Kand\u012b",
        "\u0628\u0627\u06cc\u0631\u0627\u0645\u200c\u06a9\u0646\u062f\u06cc"
    ],
    "name:msa_x_preferred":[
        "Bayram Kandi"
    ],
    "wof:name":"Bayram Kandi",
    "wof:placetype":"locality"
},
  "geometry": {"coordinates":[46.2236,37.0837],"type":"Point"}
}