{
  "type": "Feature",
  "properties": {
    "gn:admin1_code":"4",
    "gn:asciiname":"Kondeh Gordak",
    "gn:country_code":"IR",
    "gn:dem":2038,
    "gn:feature_class":"P",
    "gn:feature_code":"PPL",
    "gn:name":"Kondeh Gord\u0101k",
    "gn:population":0,
    "gn:timezone":"Asia/Tehran",
    "iso:country":"IR",
    "name:fas_x_preferred":[
        "\u06a9\u0646\u062f\u0647 \u06af\u0631\u062f\u0627\u06a9"
    ],
    "name:fas_x_variant":[
        "Kondeh Gord\u0101k"
    ],
    "wof:name":"Kondeh Gordak",
    "wof:placetype":"locality"
},
  "geometry": {"coordinates":[60.9952,28.5476],"type":"Point"}
}