{
  "type": "Feature",
  "properties": {
    "gn:admin1_code":"16",
    "gn:asciiname":"Su Tappeh",
    "gn:country_code":"IR",
    "gn:dem":1819,
    "gn:feature_class":"P",
    "gn:feature_code":"PPL",
    "gn:name":"S\u016b Tappeh",
    "gn:population":0,
    "gn:timezone":"Asia/Tehran",
    "iso:country":"IR",
    "name:fas_x_preferred":[
        "\u0633\u0648 \u062a\u067e\u0647"
    ],
    "name:fas_x_variant":[
        "S\u016b Tappeh"
    ],
    "name:und_x_variant":[
        "Sutapeh"
    ],
    "wof:name":"Su Tappeh",
    "wof:placetype":"locality"
},
  "geometry": {"coordinates":[47.99075,34.97166],"type":"Point"}
}