{
  "type": "Feature",
  "properties": {
    "gn:admin1_code":"9.0",
    "gn:asciiname":"Morvar-e Pa'in",
    "gn:country_code":"IR",
    "gn:dem":2259,
    "gn:feature_class":"P",
    "gn:feature_code":"PPL",
    "gn:name":"Morv\u0101r-e P\u0101\u2019\u012bn",
    "gn:population":0,
    "gn:timezone":"Asia/Tehran",
    "iso:country":"IR",
    "name:fas_x_preferred":[
        "\u0645\u0631\u0648\u0627\u0631 \u067e\u0627\u06cc\u06cc\u0646"
    ],
    "name:und_x_variant":[
        "Morv\u0101r-e P\u0101\u2019\u012bn"
    ],
    "wof:name":"Morvar-e Pa'in",
    "wof:placetype":"locality"
},
  "geometry": {"coordinates":[49.08373,34.16379000000001],"type":"Point"}
}