{
  "type": "Feature",
  "properties": {
    "gn:admin1_code":"11",
    "gn:asciiname":"Khabunamaki",
    "gn:country_code":"IR",
    "gn:dem":497,
    "gn:feature_class":"P",
    "gn:feature_code":"PPL",
    "gn:name":"Kh\u0101b\u016bnamak\u012b",
    "gn:population":0,
    "gn:timezone":"Asia/Tehran",
    "iso:country":"IR",
    "name:fas_x_preferred":[
        "\u062e\u0627\u0628\u0648\u0646\u064e\u0645\u064e\u0643\u06cc"
    ],
    "name:fas_x_variant":[
        "Kh\u0101b\u016bnamak\u012b"
    ],
    "wof:name":"Khabunamaki",
    "wof:placetype":"locality"
},
  "geometry": {"coordinates":[57.29083000000001,27.75667],"type":"Point"}
}