{
  "type": "Feature",
  "properties": {
    "gn:admin1_code":"1",
    "gn:asciiname":"Khvoshaku",
    "gn:country_code":"IR",
    "gn:dem":1946,
    "gn:feature_class":"P",
    "gn:feature_code":"PPL",
    "gn:name":"Khvosh\u0101k\u016b",
    "gn:population":0,
    "gn:timezone":"Asia/Tehran",
    "iso:country":"IR",
    "name:fas_x_preferred":[
        "\u062e\u0648\u064f\u0634\u0627\u0644\u0648"
    ],
    "name:fas_x_variant":[
        "Khvosh\u0101l\u016b",
        "Khvosh\u0101k\u016b",
        "\u062e\u0648\u0634\u0627\u06a9\u0648"
    ],
    "name:und_x_variant":[
        "\u062e\u0648\u0634\u0627\u06a9\u0648"
    ],
    "wof:name":"Khvoshaku",
    "wof:placetype":"locality"
},
  "geometry": {"coordinates":[44.7835,37.4655],"type":"Point"}
}