{
  "type": "Feature",
  "properties": {
    "gn:admin1_code":"9.0",
    "gn:asciiname":"Artiman",
    "gn:country_code":"IR",
    "gn:dem":1889,
    "gn:feature_class":"P",
    "gn:feature_code":"PPL",
    "gn:name":"\u0100rt\u012bm\u0101n",
    "gn:population":0,
    "gn:timezone":"Asia/Tehran",
    "iso:country":"IR",
    "name:fas_x_preferred":[
        "\u0622\u0631\u062a\u0645\u0627\u0646"
    ],
    "name:fas_x_variant":[
        "\u0100rt\u012bm\u0101n",
        "\u0622\u0631\u062a\u06cc\u0645\u0627\u0646"
    ],
    "name:msa_x_preferred":[
        "Artiman"
    ],
    "name:und_x_variant":[
        "\u0100rtm\u0101n"
    ],
    "wof:name":"Artiman",
    "wof:placetype":"locality"
},
  "geometry": {"coordinates":[48.44741,34.57938],"type":"Point"}
}