{
  "type": "Feature",
  "properties": {
    "gn:admin1_code":"42",
    "gn:asciiname":"Darvishabad",
    "gn:country_code":"IR",
    "gn:dem":1053,
    "gn:feature_class":"P",
    "gn:feature_code":"PPL",
    "gn:name":"Darv\u012bsh\u0101b\u0101d",
    "gn:population":0,
    "gn:timezone":"Asia/Tehran",
    "iso:country":"IR",
    "name:fas_x_preferred":[
        "Darv\u012bsh\u0101b\u0101d"
    ],
    "wof:name":"Darvishabad",
    "wof:placetype":"locality"
},
  "geometry": {"coordinates":[59.88,34.82861],"type":"Point"}
}