{
  "type": "Feature",
  "properties": {
    "gn:admin1_code":"7.0",
    "gn:asciiname":"Abgozar",
    "gn:country_code":"IR",
    "gn:dem":1318,
    "gn:feature_class":"P",
    "gn:feature_code":"PPL",
    "gn:name":"\u0100bgoz\u0304ar",
    "gn:population":0,
    "gn:timezone":"Asia/Tehran",
    "iso:country":"IR",
    "name:fas_x_preferred":[
        "\u0622\u0628\u06af\u0630\u0631"
    ],
    "name:fas_x_variant":[
        "\u0100bgoz\u0304ar"
    ],
    "wof:name":"Abgozar",
    "wof:placetype":"locality"
},
  "geometry": {"coordinates":[52.1644,29.3942],"type":"Point"}
}