{
  "type": "Feature",
  "properties": {
    "gn:admin1_code":"42.0",
    "gn:asciiname":"`Eshqabad",
    "gn:country_code":"IR",
    "gn:dem":1750,
    "gn:feature_class":"P",
    "gn:feature_code":"PPL",
    "gn:name":"\u2018Eshq\u0101b\u0101d",
    "gn:population":0,
    "gn:timezone":"Asia/Tehran",
    "iso:country":"IR",
    "name:fas_x_preferred":[
        "\u2018\u0100sheq\u0101b\u0101d"
    ],
    "name:fas_x_variant":[
        "\u2018Eshq\u0101b\u0101d",
        "\u0639\u0627\u0634\u0642 \u0622\u0628\u0627\u062f",
        "\u0639\u0634\u0642 \u0622\u0628\u0627\u062f",
        "\u0639\u0634\u0642\u200c\u0622\u0628\u0627\u062f"
    ],
    "name:und_x_variant":[
        "\u0639\u0627\u0634\u0642 \u0622\u0628\u0627\u062f"
    ],
    "wof:name":"`Eshqabad",
    "wof:placetype":"locality"
},
  "geometry": {"coordinates":[58.40308,36.87584],"type":"Point"}
}