{
  "type": "Feature",
  "properties": {
    "gn:admin1_code":"29",
    "gn:asciiname":"Garku'iyeh",
    "gn:country_code":"IR",
    "gn:dem":565,
    "gn:feature_class":"P",
    "gn:feature_code":"PPL",
    "gn:name":"Gark\u016b\u2019\u012byeh",
    "gn:population":0,
    "gn:timezone":"Asia/Tehran",
    "iso:country":"IR",
    "name:ara_x_preferred":[
        "\u063a\u0631\u06a9\u0648\u064a\u064a\u0629"
    ],
    "name:fas_x_preferred":[
        "Gark\u016b\u2019\u012byeh"
    ],
    "name:fas_x_variant":[
        "\u06af\u0631\u06a9\u0648\u06cc\u06cc\u0647"
    ],
    "name:und_x_variant":[
        "Gar Gooh"
    ],
    "wof:name":"Garku'iyeh",
    "wof:placetype":"locality"
},
  "geometry": {"coordinates":[57.70916999999999,28.345],"type":"Point"}
}