{
  "type": "Feature",
  "properties": {
    "gn:admin1_code":"5",
    "gn:asciiname":"Murderaz-e Rahbar",
    "gn:country_code":"IR",
    "gn:dem":1787,
    "gn:feature_class":"P",
    "gn:feature_code":"PPL",
    "gn:name":"M\u016brder\u0101z-e Rahbar",
    "gn:population":0,
    "gn:timezone":"Asia/Tehran",
    "iso:country":"IR",
    "name:ara_x_preferred":[
        "\u0645\u0648\u0631\u062f\u0631\u0627\u0632 \u0631\u0647\u0628\u0631"
    ],
    "name:ceb_x_preferred":[
        "M\u016brder\u0101z-e Rahbar"
    ],
    "name:fas_x_preferred":[
        "M\u016brder\u0101z-e Rahbar"
    ],
    "name:fas_x_variant":[
        "\u0645\u0648\u0631\u062f\u0631\u0627\u0632 \u0631\u0647\u0628\u0631"
    ],
    "name:swe_x_preferred":[
        "M\u016brder\u0101z-e Rahbar"
    ],
    "wof:name":"Murderaz-e Rahbar",
    "wof:placetype":"locality"
},
  "geometry": {"coordinates":[51.5609,30.61536],"type":"Point"}
}