{
  "type": "Feature",
  "properties": {
    "gn:admin1_code":"7.0",
    "gn:asciiname":"Chah-e Qabri",
    "gn:country_code":"IR",
    "gn:dem":1594,
    "gn:feature_class":"P",
    "gn:feature_code":"PPL",
    "gn:name":"Ch\u0101h-e Qabr\u012b",
    "gn:population":0,
    "gn:timezone":"Asia/Tehran",
    "iso:country":"IR",
    "name:fas_x_preferred":[
        "\u0686\u0627\u0647 \u0642\u0628\u0631\u06cc"
    ],
    "name:fas_x_variant":[
        "\u0627\u0645\u064a\u0631\u064a\u0647"
    ],
    "name:und_x_variant":[
        "Ch\u0101h-e Qabr\u012b",
        "Am\u012br\u012byeh"
    ],
    "wof:name":"Chah-e Qabri",
    "wof:placetype":"locality"
},
  "geometry": {"coordinates":[55.10558,28.9952],"type":"Point"}
}