{
  "type": "Feature",
  "properties": {
    "gn:admin1_code":"36",
    "gn:asciiname":"Khak Riz",
    "gn:country_code":"IR",
    "gn:dem":2000,
    "gn:feature_class":"P",
    "gn:feature_code":"PPL",
    "gn:name":"Kh\u0101k R\u012bz",
    "gn:population":0,
    "gn:timezone":"Asia/Tehran",
    "iso:country":"IR",
    "name:fas_x_preferred":[
        "\u062e\u0627\u0643 \u0631\u064a\u0632"
    ],
    "name:fas_x_variant":[
        "\u062e\u0627\u0643\u0631\u064e\u0632",
        "\u062e\u0627\u06a9\u0631\u06cc\u0632",
        "Kh\u0101k R\u012bz",
        "Kh\u0101kr\u012bz"
    ],
    "name:und_x_variant":[
        "Khakir",
        "Kh\u0101kraz"
    ],
    "wof:name":"Khak Riz",
    "wof:placetype":"locality"
},
  "geometry": {"coordinates":[48.44878,36.45129],"type":"Point"}
}