{
  "type": "Feature",
  "properties": {
    "gn:admin1_code":"33",
    "gn:asciiname":"Nosratabad",
    "gn:country_code":"IR",
    "gn:dem":2046,
    "gn:feature_class":"P",
    "gn:feature_code":"PPL",
    "gn:name":"No\u015frat\u0101b\u0101d",
    "gn:population":0,
    "gn:timezone":"Asia/Tehran",
    "iso:country":"IR",
    "name:fas_x_preferred":[
        "\u0646\u064f\u0635\u0631\u064e\u062a \u0622\u0628\u0627\u062f"
    ],
    "name:fas_x_variant":[
        "\u0646\u0635\u0631\u062a \u0622\u0628\u0627\u062f",
        "No\u015frat\u0101b\u0101d"
    ],
    "wof:name":"Nosratabad",
    "wof:placetype":"locality"
},
  "geometry": {"coordinates":[46.38132,38.43765],"type":"Point"}
}