{
  "type": "Feature",
  "properties": {
    "gn:admin1_code":"7",
    "gn:asciiname":"`Ataabad",
    "gn:country_code":"IR",
    "gn:dem":818,
    "gn:feature_class":"P",
    "gn:feature_code":"PPL",
    "gn:name":"\u2018A\u0163\u0101\u0101b\u0101d",
    "gn:population":0,
    "gn:timezone":"Asia/Tehran",
    "iso:country":"IR",
    "name:fas_x_preferred":[
        "\u0639\u0637\u0627 \u0622\u0628\u0627\u062f"
    ],
    "name:fas_x_variant":[
        "\u2018A\u0163\u0101\u0101b\u0101d"
    ],
    "wof:name":"`Ataabad",
    "wof:placetype":"locality"
},
  "geometry": {"coordinates":[53.83263,28.19582],"type":"Point"}
}