{
  "type": "Feature",
  "properties": {
    "gn:admin1_code":"36",
    "gn:asciiname":"Qareh Kahriz",
    "gn:country_code":"IR",
    "gn:dem":1707,
    "gn:feature_class":"P",
    "gn:feature_code":"PPL",
    "gn:name":"Qareh Kahr\u012bz",
    "gn:population":0,
    "gn:timezone":"Asia/Tehran",
    "iso:country":"IR",
    "name:azb_x_preferred":[
        "\u0642\u0631\u0647 \u06a9\u0647\u0631\u06cc\u0632"
    ],
    "name:fas_x_preferred":[
        "\u0642\u064e\u0631\u0647 \u0643\u0647\u0631\u064a\u0632"
    ],
    "name:fas_x_variant":[
        "\u0642\u0631\u0647 \u06a9\u0647\u0631\u06cc\u0632",
        "\u0642\u064e\u0631\u064e \u0643\u0627\u0631\u064a\u0632",
        "Qareh Kahr\u012bz",
        "Qarah Kahr\u012bz"
    ],
    "name:und_x_variant":[
        "Qara K\u0101r\u012bz",
        "Ghareh Kahriz"
    ],
    "wof:name":"Qareh Kahriz",
    "wof:placetype":"locality"
},
  "geometry": {"coordinates":[48.40562,35.73927],"type":"Point"}
}