{
  "type": "Feature",
  "properties": {
    "gn:admin1_code":"7.0",
    "gn:asciiname":"`Abd Shah-e Khvosh Ravesh",
    "gn:country_code":"IR",
    "gn:dem":772,
    "gn:feature_class":"P",
    "gn:feature_code":"PPL",
    "gn:name":"\u2018Abd Sh\u0101h-e Khvosh Ravesh",
    "gn:population":0,
    "gn:timezone":"Asia/Tehran",
    "iso:country":"IR",
    "name:fas_x_preferred":[
        "\u2018Abd Sh\u0101h-e Khvosh Ravesh"
    ],
    "name:fas_x_variant":[
        "\u0639\u0628\u062f \u0634\u0627\u0647 \u062e\u0648\u0634 \u0631\u0648\u0634"
    ],
    "name:und_x_variant":[
        "\u0639\u0628\u062f \u0634\u0627\u0647 \u062e\u0648\u0634 \u0631\u0648\u0634"
    ],
    "wof:name":"`Abd Shah-e Khvosh Ravesh",
    "wof:placetype":"locality"
},
  "geometry": {"coordinates":[51.93111,29.20343],"type":"Point"}
}