{
  "type": "Feature",
  "properties": {
    "gn:admin1_code":"38",
    "gn:asciiname":"Dakhrajin",
    "gn:country_code":"IR",
    "gn:dem":1600,
    "gn:feature_class":"P",
    "gn:feature_code":"PPL",
    "gn:name":"D\u0101khraj\u012bn",
    "gn:population":0,
    "gn:timezone":"Asia/Tehran",
    "iso:country":"IR",
    "name:ceb_x_preferred":[
        "D\u0101khraj\u012bn"
    ],
    "name:fas_x_preferred":[
        "\u062f\u064e\u062e\u064e\u0631\u062c\u064a\u0646"
    ],
    "name:fas_x_variant":[
        "\u062f\u0627\u062e\u0631\u062c\u064a\u0646",
        "Dakharj\u012bn",
        "D\u0101khraj\u012bn",
        "\u062f\u0627\u062e\u0631\u062c\u06cc\u0646"
    ],
    "name:swe_x_preferred":[
        "D\u0101khraj\u012bn"
    ],
    "wof:name":"Dakhrajin",
    "wof:placetype":"locality"
},
  "geometry": {"coordinates":[49.22465,35.75279000000001],"type":"Point"}
}