{
  "type": "Feature",
  "properties": {
    "gn:admin1_code":"15.0",
    "gn:asciiname":"Taheriyeh-ye Do",
    "gn:country_code":"IR",
    "gn:dem":14,
    "gn:feature_class":"P",
    "gn:feature_code":"PPL",
    "gn:name":"\u0162\u0101her\u012byeh-ye Do",
    "gn:population":0,
    "gn:timezone":"Asia/Tehran",
    "iso:country":"IR",
    "name:fas_x_preferred":[
        "\u0645\u062d\u0644\u0651 \u0627\u062d\u062f\u0627\u062b \u0631\u0648\u0633\u062a\u0627\u06cc \u0637\u0627\u0647\u0631\u06cc\u0651\u0647 \u0633\u0647"
    ],
    "name:fas_x_variant":[
        "Ma\u1e29all-e E\u1e29d\u0101s\u0304-e R\u016bst\u0101y-e \u0162\u0101her\u012byeh-ye She",
        "\u0637\u0627\u0647\u0631\u06cc\u0647 \u062f\u0648"
    ],
    "name:und_x_variant":[
        "\u0162\u0101her\u012byeh-ye Do"
    ],
    "wof:name":"Taheriyeh-ye Do",
    "wof:placetype":"locality"
},
  "geometry": {"coordinates":[48.2632,31.2737],"type":"Point"}
}