{
  "type": "Feature",
  "properties": {
    "gn:admin1_code":"4",
    "gn:asciiname":"Murtak-e Pa'in",
    "gn:country_code":"IR",
    "gn:dem":1977,
    "gn:feature_class":"P",
    "gn:feature_code":"PPL",
    "gn:name":"M\u016brtak-e P\u0101\u2019\u012bn",
    "gn:population":0,
    "gn:timezone":"Asia/Tehran",
    "iso:country":"IR",
    "name:fas_x_preferred":[
        "\u0645\u0648\u0631\u062a\u06a9 \u067e\u0627\u0626\u06cc\u0646"
    ],
    "name:fas_x_variant":[
        "M\u016brtak-e P\u0101\u2019\u012bn"
    ],
    "wof:name":"Murtak-e Pa'in",
    "wof:placetype":"locality"
},
  "geometry": {"coordinates":[60.7941,28.6984],"type":"Point"}
}