{
  "type": "Feature",
  "properties": {
    "gn:admin1_code":"38",
    "gn:asciiname":"Tablashkin",
    "gn:country_code":"IR",
    "gn:dem":1651,
    "gn:feature_class":"P",
    "gn:feature_code":"PPL",
    "gn:name":"\u0162ablashk\u012bn",
    "gn:population":0,
    "gn:timezone":"Asia/Tehran",
    "iso:country":"IR",
    "name:fas_x_preferred":[
        "\u0637\u0628\u0644\u0634\u06a9\u0646"
    ],
    "name:fas_x_variant":[
        "\u0162ablashg\u012bn",
        "\u0162ablshekan",
        "\u0637\u0628\u0644\u0634\u06a9\u06cc\u0646"
    ],
    "name:und_x_variant":[
        "\u0162ablashk\u012bn"
    ],
    "wof:name":"Tablashkin",
    "wof:placetype":"locality"
},
  "geometry": {"coordinates":[49.07666,35.81330999999999],"type":"Point"}
}