{
  "type": "Feature",
  "properties": {
    "gn:admin1_code":"28",
    "gn:asciiname":"Qazi Darreh",
    "gn:country_code":"IR",
    "gn:dem":2474,
    "gn:feature_class":"P",
    "gn:feature_code":"PPL",
    "gn:name":"Q\u0101\u1e95\u012b Darreh",
    "gn:population":0,
    "gn:timezone":"Asia/Tehran",
    "iso:country":"IR",
    "name:fas_x_preferred":[
        "\u0642\u0627\u0636\u06cc \u062f\u0631\u0651\u0647"
    ],
    "name:fas_x_variant":[
        "Q\u0101\u1e95\u012b Darreh"
    ],
    "name:und_x_variant":[
        "Joghd\u016b",
        "\u062c\u063a\u062f\u0648"
    ],
    "wof:name":"Qazi Darreh",
    "wof:placetype":"locality"
},
  "geometry": {"coordinates":[50.666,33.4264],"type":"Point"}
}