{
  "type": "Feature",
  "properties": {
    "gn:admin1_code":"9",
    "gn:asciiname":"Vashur",
    "gn:country_code":"IR",
    "gn:dem":1991,
    "gn:feature_class":"P",
    "gn:feature_code":"PPL",
    "gn:name":"V\u0101sh\u016br",
    "gn:population":0,
    "gn:timezone":"Asia/Tehran",
    "iso:country":"IR",
    "name:ceb_x_preferred":[
        "V\u0101sh\u016br"
    ],
    "name:fas_x_preferred":[
        "\u0648\u0627\u0634\u0648\u0631"
    ],
    "name:fas_x_variant":[
        "V\u0101sh\u016br"
    ],
    "name:msa_x_preferred":[
        "Vashur"
    ],
    "name:swe_x_preferred":[
        "V\u0101sh\u016br"
    ],
    "name:und_x_variant":[
        "B\u0101ch\u016br",
        "Vashoor",
        "B\u0101sh\u016br"
    ],
    "wof:name":"Vashur",
    "wof:placetype":"locality"
},
  "geometry": {"coordinates":[48.35153,35.2317],"type":"Point"}
}