{
  "type": "Feature",
  "properties": {
    "gn:admin1_code":"10",
    "gn:asciiname":"Naderabad",
    "gn:country_code":"IR",
    "gn:dem":1339,
    "gn:feature_class":"P",
    "gn:feature_code":"PPL",
    "gn:name":"N\u0101der\u0101b\u0101d",
    "gn:population":0,
    "gn:timezone":"Asia/Tehran",
    "iso:country":"IR",
    "name:fas_x_preferred":[
        "\u0646\u0627\u062f\u0631 \u0622\u0628\u0627\u062f \u0634\u0648\u0647\u0627\u0646"
    ],
    "name:fas_x_variant":[
        "N\u0101der\u0101b\u0101d",
        "N\u0101der\u0101b\u0101d-e Showh\u0101n",
        "\u0646\u0627\u062f\u0631 \u0622\u0628\u0627\u062f",
        "\u0646\u0627\u062f\u0631\u0622\u0628\u0627\u062f"
    ],
    "name:msa_x_preferred":[
        "Naderabad"
    ],
    "wof:name":"Naderabad",
    "wof:placetype":"locality"
},
  "geometry": {"coordinates":[46.8224,33.2639],"type":"Point"}
}