{
  "type": "Feature",
  "properties": {
    "gn:admin1_code":"36",
    "gn:asciiname":"Daydar-e `Olya",
    "gn:country_code":"IR",
    "gn:dem":1465,
    "gn:feature_class":"P",
    "gn:feature_code":"PPL",
    "gn:name":"D\u0101yd\u0101r-e \u2018Oly\u0101",
    "gn:population":0,
    "gn:timezone":"Asia/Tehran",
    "iso:country":"IR",
    "name:azb_x_preferred":[
        "\u062f\u0627\u06cc\u062f\u0627\u0631\u0639\u0644\u06cc\u0627"
    ],
    "name:fas_x_preferred":[
        "\u062f\u0627\u06cc\u062f\u0627\u0631 \u0639\u0644\u06cc\u0627"
    ],
    "name:fas_x_variant":[
        "\u062f\u064e\u064a\u062f\u064e\u0631 \u0627\u064f\u0644\u064a\u064e",
        "\u062f\u0627\u064a\u0650\u062f\u0627\u0631\u0650 \u0628\u0627\u0644\u0627",
        "\u062f\u0627\u064a\u0650\u062f\u0627\u0631",
        "\u062f\u064e\u064a\u062f\u064e\u0631",
        "D\u0101yd\u0101r-e \u2018Oly\u0101"
    ],
    "name:und_x_variant":[
        "D\u0101id\u0101r \u2018Uliya",
        "Daydar",
        "Daydar Olya",
        "D\u0101yed\u0101r-e B\u0101l\u0101",
        "D\u0101yed\u0101r"
    ],
    "wof:name":"Daydar-e `Olya",
    "wof:placetype":"locality"
},
  "geometry": {"coordinates":[48.10051,36.15162],"type":"Point"}
}