{
  "type": "Feature",
  "properties": {
    "gn:admin1_code":"4.0",
    "gn:asciiname":"Sahran",
    "gn:country_code":"IR",
    "gn:dem":855,
    "gn:feature_class":"P",
    "gn:feature_code":"PPL",
    "gn:name":"Sahr\u0101n",
    "gn:population":0,
    "gn:timezone":"Asia/Tehran",
    "iso:country":"IR",
    "name:fas_x_preferred":[
        "Sar\u0101v\u0101n"
    ],
    "name:fas_x_variant":[
        "\u0633\u0647\u0631\u0627\u0646"
    ],
    "name:und_x_variant":[
        "Sar\u0101wan",
        "S\u016br\u0101n",
        "Sahr\u0101n"
    ],
    "wof:name":"Sahran",
    "wof:placetype":"locality"
},
  "geometry": {"coordinates":[61.01693,27.24708],"type":"Point"}
}