{
  "type": "Feature",
  "properties": {
    "gn:admin1_code":"33",
    "gn:asciiname":"Aqjeh Darband",
    "gn:country_code":"IR",
    "gn:dem":1517,
    "gn:feature_class":"P",
    "gn:feature_code":"PPL",
    "gn:name":"\u0100qjeh Darband",
    "gn:population":0,
    "gn:timezone":"Asia/Tehran",
    "iso:country":"IR",
    "name:azb_x_preferred":[
        "\u0622\u063a\u0686\u0647\u200c\u062f\u0631\u0628\u0646\u062f"
    ],
    "name:fas_x_preferred":[
        "\u0622\u0642\u062c\u0647 \u062f\u0631\u0628\u0646\u062f"
    ],
    "name:fas_x_variant":[
        "\u0100ghcheh Darband",
        "\u0100qjeh Darband",
        "\u0622\u063a\u0686\u0647\u200c\u062f\u0631\u0628\u0646\u062f"
    ],
    "name:msa_x_preferred":[
        "Aghcheh Darband"
    ],
    "wof:name":"Aqjeh Darband",
    "wof:placetype":"locality"
},
  "geometry": {"coordinates":[47.5043,37.4499],"type":"Point"}
}