{
  "type": "Feature",
  "properties": {
    "gn:admin1_code":"29",
    "gn:asciiname":"Kushk Mur",
    "gn:country_code":"IR",
    "gn:dem":1080,
    "gn:feature_class":"P",
    "gn:feature_code":"PPL",
    "gn:name":"K\u016bshk M\u016br",
    "gn:population":0,
    "gn:timezone":"Asia/Tehran",
    "iso:country":"IR",
    "name:ara_x_preferred":[
        "\u0643\u0648\u0634\u0643 \u0645\u0648\u0631"
    ],
    "name:fas_x_preferred":[
        "\u06a9\u0648\u0634 \u06a9\u0648\u0645\u0648\u0631"
    ],
    "name:fas_x_variant":[
        "K\u016bshk-e M\u016br",
        "K\u016bsh K\u016bm\u016br",
        "\u06a9\u0648\u0634\u06a9 \u0645\u0648\u0631"
    ],
    "name:und_x_variant":[
        "K\u016bshk M\u016br"
    ],
    "wof:name":"Kushk Mur",
    "wof:placetype":"locality"
},
  "geometry": {"coordinates":[58.27219,28.33329],"type":"Point"}
}