{
  "type": "Feature",
  "properties": {
    "gn:admin1_code":"29.0",
    "gn:asciiname":"Boridu'iyeh",
    "gn:country_code":"IR",
    "gn:dem":2005,
    "gn:feature_class":"P",
    "gn:feature_code":"PPL",
    "gn:name":"Bor\u012bd\u016b\u2019\u012byeh",
    "gn:population":0,
    "gn:timezone":"Asia/Tehran",
    "iso:country":"IR",
    "name:fas_x_preferred":[
        "\u0628\u0631\u06cc\u062f\u0648\u0626\u06cc\u0647"
    ],
    "name:fas_x_variant":[
        "Bar\u012bd\u016b\u2019\u012byeh",
        "Bar\u012bd\u016b",
        "Beridoo\u2019eyeh",
        "Bor\u012bd\u016b\u2019\u012byeh"
    ],
    "name:und_x_variant":[
        "Bor\u012bd\u016b\u2019 Yeh"
    ],
    "wof:name":"Boridu'iyeh",
    "wof:placetype":"locality"
},
  "geometry": {"coordinates":[56.6161,28.9922],"type":"Point"}
}