{
  "type": "Feature",
  "properties": {
    "gn:admin1_code":"35",
    "gn:asciiname":"Afra Koti",
    "gn:country_code":"IR",
    "gn:dem":37,
    "gn:feature_class":"P",
    "gn:feature_code":"PPL",
    "gn:name":"Afr\u0101 Kot\u012b",
    "gn:population":0,
    "gn:timezone":"Asia/Tehran",
    "iso:country":"IR",
    "name:fas_x_preferred":[
        "\u067e\u0627\u0626\u064a\u0646 \u0627\u064e\u0641\u0631\u0627 \u0643\u064f\u062a\u06cc"
    ],
    "name:fas_x_variant":[
        "P\u0101\u2019\u012bn Afr\u0101 Kot\u012b",
        "Afr\u0101 Kot\u012b",
        "\u0627\u0641\u0631\u0627 \u0643\u062a\u06cc"
    ],
    "wof:name":"Afra Koti",
    "wof:placetype":"locality"
},
  "geometry": {"coordinates":[52.91834,36.47849],"type":"Point"}
}