{
  "type": "Feature",
  "properties": {
    "gn:admin1_code":"22.0",
    "gn:asciiname":"Ahmadi",
    "gn:country_code":"IR",
    "gn:dem":12,
    "gn:feature_class":"P",
    "gn:feature_code":"PPL",
    "gn:name":"A\u1e29mad\u012b",
    "gn:population":0,
    "gn:timezone":"Asia/Tehran",
    "iso:country":"IR",
    "name:ara_x_preferred":[
        "\u0627\u062d\u0645\u062f\u064a"
    ],
    "name:fas_x_preferred":[
        "\u0627\u062d\u0645\u062f\u06cc"
    ],
    "name:fas_x_variant":[
        "A\u1e29mad\u012b"
    ],
    "name:msa_x_preferred":[
        "Ahmadi"
    ],
    "wof:name":"Ahmadi",
    "wof:placetype":"locality"
},
  "geometry": {"coordinates":[51.0607,29.0769],"type":"Point"}
}