{
  "type": "Feature",
  "properties": {
    "gn:admin1_code":"26.0",
    "gn:asciiname":"Shahrak-e Chitgar-e Shomali",
    "gn:country_code":"IR",
    "gn:dem":1221,
    "gn:feature_class":"P",
    "gn:feature_code":"PPL",
    "gn:name":"Shahrak-e Ch\u012btgar-e Shom\u0101l\u012b",
    "gn:population":0,
    "gn:timezone":"Asia/Tehran",
    "iso:country":"IR",
    "name:fas_x_preferred":[
        "\u0686\u064a\u062a\u06af\u064e\u0631\u0650 \u062c\u064f\u0646\u0648\u0628\u06cc"
    ],
    "name:fas_x_variant":[
        "\u0686\u064a\u062a\u06af\u064e\u0631",
        "\u0634\u0647\u0631\u06a9 \u0686\u064a\u062a\u06af\u0631\u0650",
        "Ch\u012btgar-e Jon\u016bb\u012b",
        "Shahrak-e Ch\u012btgar",
        "\u0634\u0647\u0631\u06a9 \u0686\u06cc\u062a\u06af\u0631 \u0634\u0645\u0627\u0644\u06cc",
        "\u0686\u064a\u062a\u06af\u0631 \u0634\u0645\u0627\u0644\u06cc"
    ],
    "name:und_x_variant":[
        "Ch\u012btgar",
        "Shahrak-e Ch\u012btgar-e Shom\u0101l\u012b",
        "Ch\u012btgar-e Shom\u0101l\u012b"
    ],
    "wof:name":"Shahrak-e Chitgar-e Shomali",
    "wof:placetype":"locality"
},
  "geometry": {"coordinates":[51.1859,35.7242],"type":"Point"}
}