{
  "type": "Feature",
  "properties": {
    "gn:admin1_code":"22.0",
    "gn:asciiname":"Jahad",
    "gn:country_code":"IR",
    "gn:dem":58,
    "gn:feature_class":"P",
    "gn:feature_code":"PPL",
    "gn:name":"Jah\u0101d",
    "gn:population":0,
    "gn:timezone":"Asia/Tehran",
    "iso:country":"IR",
    "name:fas_x_preferred":[
        "\u0686\u0647\u0627\u062f"
    ],
    "name:und_x_variant":[
        "Jah\u0101d"
    ],
    "wof:name":"Jahad",
    "wof:placetype":"locality"
},
  "geometry": {"coordinates":[51.12798,29.39378],"type":"Point"}
}