{
  "type": "Feature",
  "properties": {
    "gn:admin1_code":"34",
    "gn:asciiname":"Qeshlaq-e Sabz `Ali",
    "gn:country_code":"IR",
    "gn:dem":1405,
    "gn:feature_class":"P",
    "gn:feature_code":"PPL",
    "gn:name":"Qeshl\u0101q-e Sabz \u2018Al\u012b",
    "gn:population":0,
    "gn:timezone":"Asia/Tehran",
    "iso:country":"IR",
    "name:fas_x_preferred":[
        "\u0642\u0634\u0644\u0627\u0642 \u0633\u0628\u0632 \u0639\u0644\u06cc"
    ],
    "name:fas_x_variant":[
        "Qeshl\u0101q-e Sabz \u2018Al\u012b"
    ],
    "wof:name":"Qeshlaq-e Sabz `Ali",
    "wof:placetype":"locality"
},
  "geometry": {"coordinates":[50.2859,35.4891],"type":"Point"}
}