{
  "type": "Feature",
  "properties": {
    "gn:admin1_code":"36",
    "gn:asciiname":"Tavileh-ye Darrahsi",
    "gn:cc2":"IR",
    "gn:country_code":"IR",
    "gn:dem":2191,
    "gn:feature_class":"P",
    "gn:feature_code":"PPL",
    "gn:name":"\u0162av\u012bleh-ye Darrahs\u012b",
    "gn:population":0,
    "gn:timezone":"Asia/Tehran",
    "iso:country":"IR",
    "name:fas_x_preferred":[
        "\u0637\u064e\u0648\u064a\u0644\u0650\u06c0 \u062f\u064e\u0631\u064e\u0651\u0647\u0633\u06cc"
    ],
    "name:fas_x_variant":[
        "\u0637\u064e\u0648\u064a\u0644\u0650\u0647 \u062f\u064e\u0631\u0650\u0651\u0647\u0633\u06cc",
        "\u0637\u064e\u0648\u064a\u0644\u0650\u0647 \u062f\u064e\u0631\u064e\u0642",
        "\u0162av\u012bleh-ye Darrahs\u012b"
    ],
    "name:und_x_variant":[
        "Tula Darreh",
        "\u0162av\u012bleh Darrehs\u012b",
        "Tula-Darrekh",
        "\u0162av\u012bleh Daraq"
    ],
    "wof:name":"Tavileh-ye Darrahsi",
    "wof:placetype":"locality"
},
  "geometry": {"coordinates":[48.56667,36.46667],"type":"Point"}
}