{
  "type": "Feature",
  "properties": {
    "gn:admin1_code":"32",
    "gn:asciiname":"Sari Bolagh",
    "gn:country_code":"IR",
    "gn:dem":568,
    "gn:feature_class":"P",
    "gn:feature_code":"PPL",
    "gn:name":"S\u0101r\u012b Bol\u0101gh",
    "gn:population":0,
    "gn:timezone":"Asia/Tehran",
    "iso:country":"IR",
    "name:aze_x_preferred":[
        "Sar\u0131bulaq"
    ],
    "name:fas_x_preferred":[
        "\u0633\u0627\u0631\u06cc \u0628\u0644\u0627\u063a"
    ],
    "name:fas_x_variant":[
        "S\u0101r\u012b Bol\u0101gh"
    ],
    "wof:name":"Sari Bolagh",
    "wof:placetype":"locality"
},
  "geometry": {"coordinates":[48.012,39.2374],"type":"Point"}
}