{
  "type": "Feature",
  "properties": {
    "gn:admin1_code":"42.0",
    "gn:asciiname":"Nashib-e `Olya",
    "gn:country_code":"IR",
    "gn:dem":1709,
    "gn:feature_class":"P",
    "gn:feature_code":"PPL",
    "gn:name":"Nash\u012bb-e \u2018Oly\u0101",
    "gn:population":0,
    "gn:timezone":"Asia/Tehran",
    "iso:country":"IR",
    "name:fas_x_preferred":[
        "Nash\u012bb"
    ],
    "name:fas_x_variant":[
        "Nash\u012bb-e \u2018Oly\u0101",
        "\u0646\u0634\u06cc\u0628",
        "\u0646\u0634\u06cc\u0628 \u0639\u0644\u06cc\u0627"
    ],
    "name:und_x_variant":[
        "\u0646\u0634\u06cc\u0628"
    ],
    "wof:name":"Nashib-e `Olya",
    "wof:placetype":"locality"
},
  "geometry": {"coordinates":[58.16261,36.85352],"type":"Point"}
}