{
  "type": "Feature",
  "properties": {
    "gn:admin1_code":"4.0",
    "gn:asciiname":"Nokuch",
    "gn:country_code":"IR",
    "gn:dem":989,
    "gn:feature_class":"P",
    "gn:feature_code":"PPL",
    "gn:name":"Nok\u016bch",
    "gn:population":0,
    "gn:timezone":"Asia/Tehran",
    "iso:country":"IR",
    "name:fas_x_preferred":[
        "\u0646\u06a9\u0648\u0686"
    ],
    "name:fas_x_variant":[
        "Now K\u0101y Kal",
        "N\u016bk\u0101ykal",
        "\u0646\u0648 \u06a9\u0627\u06cc \u06a9\u0644",
        "Nok\u016bch"
    ],
    "name:und_x_variant":[
        "Nok\u0101ikal",
        "Now K\u0101kol",
        "Now K\u0101\u2019\u012b Kol",
        "Nok\u0101ykal"
    ],
    "wof:name":"Nokuch",
    "wof:placetype":"locality"
},
  "geometry": {"coordinates":[60.5528,26.4309],"type":"Point"}
}