{
  "type": "Feature",
  "properties": {
    "gn:admin1_code":"11",
    "gn:asciiname":"Salakh",
    "gn:country_code":"IR",
    "gn:dem":8,
    "gn:feature_class":"P",
    "gn:feature_code":"PPL",
    "gn:name":"\u015ealakh",
    "gn:population":0,
    "gn:timezone":"Asia/Tehran",
    "iso:country":"IR",
    "name:fas_x_preferred":[
        "\u0635\u0644\u062e"
    ],
    "name:fas_x_variant":[
        "\u0635\u064e\u0644\u064e\u063a",
        "\u0633\u0650\u0644\u064e\u0642",
        "\u015ealakh"
    ],
    "name:msa_x_preferred":[
        "Salakh"
    ],
    "name:und_x_variant":[
        "Selaq",
        "\u015ealagh",
        "\u015eelagh"
    ],
    "wof:name":"Salakh",
    "wof:placetype":"locality"
},
  "geometry": {"coordinates":[55.7069,26.6899],"type":"Point"}
}