{
  "type": "Feature",
  "properties": {
    "gn:admin1_code":"23",
    "gn:asciiname":"Sarab-e Nurkar",
    "gn:country_code":"IR",
    "gn:dem":1764,
    "gn:feature_class":"P",
    "gn:feature_code":"PPL",
    "gn:name":"Sar\u0101b-e N\u016brkar",
    "gn:population":0,
    "gn:timezone":"Asia/Tehran",
    "iso:country":"IR",
    "name:fas_x_preferred":[
        "\u0633\u064e\u0631\u0627\u0628\u0650 \u0646\u0648\u0631\u0643\u064e\u0631"
    ],
    "name:fas_x_variant":[
        "Sar\u0101b-e N\u016brkar"
    ],
    "wof:name":"Sarab-e Nurkar",
    "wof:placetype":"locality"
},
  "geometry": {"coordinates":[48.45,33.76667],"type":"Point"}
}