{
  "type": "Feature",
  "properties": {
    "gn:admin1_code":"23",
    "gn:asciiname":"Raken-e Sofla",
    "gn:country_code":"IR",
    "gn:dem":1383,
    "gn:feature_class":"P",
    "gn:feature_code":"PPL",
    "gn:name":"R\u0101ken-e Sofl\u00e1",
    "gn:population":0,
    "gn:timezone":"Asia/Tehran",
    "iso:country":"IR",
    "name:fas_x_preferred":[
        "\u0631\u0627\u0643\u0646 \u067e\u0627\u0626\u064a\u0646"
    ],
    "name:fas_x_variant":[
        "R\u0101ken-e P\u0101\u2019\u012bn",
        "\u0631\u0627\u06a9\u0646 \u0633\u0641\u0644\u06cc"
    ],
    "name:und_x_variant":[
        "R\u0101ken-e Sofl\u00e1"
    ],
    "wof:name":"Raken-e Sofla",
    "wof:placetype":"locality"
},
  "geometry": {"coordinates":[49.00862,33.42533],"type":"Point"}
}