{
  "type": "Feature",
  "properties": {
    "gn:admin1_code":"42",
    "gn:asciiname":"Javadiyeh",
    "gn:country_code":"IR",
    "gn:dem":1649,
    "gn:feature_class":"P",
    "gn:feature_code":"PPL",
    "gn:name":"Jav\u0101d\u012byeh",
    "gn:population":0,
    "gn:timezone":"Asia/Tehran",
    "iso:country":"IR",
    "name:fas_x_preferred":[
        "\u062c\u0648\u0627\u062f\u06cc\u0647"
    ],
    "name:fas_x_variant":[
        "Jav\u0101d\u012byeh"
    ],
    "name:und_x_variant":[
        "Jav\u0101d\u012byyeh"
    ],
    "wof:name":"Javadiyeh",
    "wof:placetype":"locality"
},
  "geometry": {"coordinates":[59.12364,35.59015],"type":"Point"}
}