{
  "type": "Feature",
  "properties": {
    "gn:admin1_code":"15.0",
    "gn:asciiname":"Shahid Danesh",
    "gn:country_code":"IR",
    "gn:dem":84,
    "gn:feature_class":"P",
    "gn:feature_code":"PPL",
    "gn:name":"Shah\u012bd D\u0101nesh",
    "gn:population":0,
    "gn:timezone":"Asia/Tehran",
    "iso:country":"IR",
    "name:fas_x_preferred":[
        "\u2018Amaleh"
    ],
    "name:fas_x_variant":[
        "\u0634\u0647\u06cc\u062f \u062f\u0627\u0646\u0634",
        "\u0639\u0645\u0644\u0647",
        "Shah\u012bd D\u0101nesh",
        "\u0645\u062d\u0644\u0647 \u0635\u06cc\u0641",
        "\u0639\u0645\u0644\u0647 \u0633\u064a\u0641"
    ],
    "name:und_x_variant":[
        "\u2018Amaleh Seyf",
        "Ma\u1e29alleh-ye \u015eeyf"
    ],
    "wof:name":"Shahid Danesh",
    "wof:placetype":"locality"
},
  "geometry": {"coordinates":[48.24665,32.22007],"type":"Point"}
}