{
  "type": "Feature",
  "properties": {
    "gn:admin1_code":"13",
    "gn:asciiname":"Surni-ye Pa'in",
    "gn:country_code":"IR",
    "gn:dem":1430,
    "gn:feature_class":"P",
    "gn:feature_code":"PPL",
    "gn:name":"S\u016brn\u012b-ye P\u0101\u2019\u012bn",
    "gn:population":0,
    "gn:timezone":"Asia/Tehran",
    "iso:country":"IR",
    "name:fas_x_preferred":[
        "\u0633\u0648\u0631\u0646\u06cc \u067e\u0627\u0626\u06cc\u0646"
    ],
    "name:fas_x_variant":[
        "S\u016brn\u012b-ye Sofl\u00e1"
    ],
    "name:und_x_variant":[
        "Sooreni\u00e9- Sofla",
        "S\u016br\u012bni",
        "S\u016bren\u012b-ye Sofl\u00e1",
        "S\u016br\u012bn\u012b-ye Sofl\u00e1",
        "S\u016brn\u012b-ye P\u0101\u2019\u012bn"
    ],
    "wof:name":"Surni-ye Pa'in",
    "wof:placetype":"locality"
},
  "geometry": {"coordinates":[47.0145,34.6943],"type":"Point"}
}