{
  "type": "Feature",
  "properties": {
    "gn:admin1_code":"5.0",
    "gn:asciiname":"Darreh Bid",
    "gn:country_code":"IR",
    "gn:dem":2294,
    "gn:feature_class":"P",
    "gn:feature_code":"PPL",
    "gn:name":"Darreh B\u012bd",
    "gn:population":0,
    "gn:timezone":"Asia/Tehran",
    "iso:country":"IR",
    "name:fas_x_preferred":[
        "Darreh B\u012bd"
    ],
    "name:fas_x_variant":[
        "\u062f\u0631\u0651\u0647 \u0628\u06cc\u062f"
    ],
    "wof:name":"Darreh Bid",
    "wof:placetype":"locality"
},
  "geometry": {"coordinates":[50.8085,31.218],"type":"Point"}
}