{
  "type": "Feature",
  "properties": {
    "gn:admin1_code":"16",
    "gn:asciiname":"Karju",
    "gn:country_code":"IR",
    "gn:dem":1798,
    "gn:feature_class":"P",
    "gn:feature_code":"PPL",
    "gn:name":"Karj\u016b",
    "gn:population":0,
    "gn:timezone":"Asia/Tehran",
    "iso:country":"IR",
    "name:fas_x_preferred":[
        "\u06a9\u0631\u062c\u0648"
    ],
    "name:fas_x_variant":[
        "Karj\u016b"
    ],
    "name:und_x_variant":[
        "Qaraju"
    ],
    "wof:name":"Karju",
    "wof:placetype":"locality"
},
  "geometry": {"coordinates":[46.83600000000001,35.2897],"type":"Point"}
}