{
  "type": "Feature",
  "properties": {
    "gn:admin1_code":"3",
    "gn:asciiname":"Cheshmeh Soleyman",
    "gn:country_code":"IR",
    "gn:dem":2070,
    "gn:feature_class":"P",
    "gn:feature_code":"PPL",
    "gn:name":"Cheshmeh Soleym\u0101n",
    "gn:population":0,
    "gn:timezone":"Asia/Tehran",
    "iso:country":"IR",
    "name:ara_x_preferred":[
        "\u062c\u0634\u0645\u0629 \u0633\u0644\u064a\u0645\u0627\u0646"
    ],
    "name:fas_x_preferred":[
        "Cheshmeh Soleym\u0101n"
    ],
    "name:fas_x_variant":[
        "\u0686\u0634\u0645\u0647 \u0633\u0644\u064a\u0645\u0627\u0646",
        "\u0686\u0634\u0645\u0647 \u0633\u0644\u06cc\u0645\u0627\u0646"
    ],
    "name:msa_x_preferred":[
        "Cheshmeh Soleyman"
    ],
    "wof:name":"Cheshmeh Soleyman",
    "wof:placetype":"locality"
},
  "geometry": {"coordinates":[50.37764,32.04595],"type":"Point"}
}