{
  "type": "Feature",
  "properties": {
    "gn:admin1_code":"41.0",
    "gn:asciiname":"`Ali Hedyeh-ye `Olya",
    "gn:country_code":"IR",
    "gn:dem":1357,
    "gn:feature_class":"P",
    "gn:feature_code":"PPL",
    "gn:name":"\u2018Al\u012b Hedyeh-ye \u2018Oly\u0101",
    "gn:population":0,
    "gn:timezone":"Asia/Tehran",
    "iso:country":"IR",
    "name:fas_x_preferred":[
        "\u0639\u0644\u06cc \u0647\u062f\u06cc\u0647 \u0639\u0644\u06cc\u0627"
    ],
    "name:fas_x_variant":[
        "\u2018Al\u012b Hedyeh",
        "\u2018Al\u012b Hedyeh-ye B\u0101l\u0101",
        "\u2018Al\u012b Hedyeh-ye \u2018Oly\u0101"
    ],
    "name:und_x_variant":[
        "Al\u012b Hedye Bala"
    ],
    "wof:name":"`Ali Hedyeh-ye `Olya",
    "wof:placetype":"locality"
},
  "geometry": {"coordinates":[60.6208,32.3643],"type":"Point"}
}