{
  "type": "Feature",
  "properties": {
    "gn:admin1_code":"29",
    "gn:asciiname":"Bard-e Yalan",
    "gn:country_code":"IR",
    "gn:dem":523,
    "gn:feature_class":"P",
    "gn:feature_code":"PPL",
    "gn:name":"Bard-e Y\u0101l\u0101n",
    "gn:population":0,
    "gn:timezone":"Asia/Tehran",
    "iso:country":"IR",
    "name:fas_x_preferred":[
        "\u0628\u064e\u0631\u062f\u0650 \u064a\u0627\u0644\u0627\u0646"
    ],
    "name:fas_x_variant":[
        "Bard-e Y\u0101l\u0101n"
    ],
    "wof:name":"Bard-e Yalan",
    "wof:placetype":"locality"
},
  "geometry": {"coordinates":[57.31028000000001,27.595],"type":"Point"}
}