{
  "type": "Feature",
  "properties": {
    "gn:admin1_code":"28",
    "gn:asciiname":"Hajj Bolagh",
    "gn:country_code":"IR",
    "gn:dem":2158,
    "gn:feature_class":"P",
    "gn:feature_code":"PPL",
    "gn:name":"\u1e28\u0101jj Bol\u0101gh",
    "gn:population":0,
    "gn:timezone":"Asia/Tehran",
    "iso:country":"IR",
    "name:fas_x_preferred":[
        "\u062d\u0627\u062c \u0628\u0644\u0627\u063a"
    ],
    "name:fas_x_variant":[
        "\u1e28\u0101jj Bol\u0101gh"
    ],
    "name:und_x_variant":[
        "\u1e28\u0101jj\u012b Bol\u0101gh",
        "\u1e28\u0101j\u012b Bol\u0101gh",
        "H\u0101j\u012bbul\u0101gh",
        "Haj Bolagh"
    ],
    "wof:name":"Hajj Bolagh",
    "wof:placetype":"locality"
},
  "geometry": {"coordinates":[50.6155,33.2429],"type":"Point"}
}