{
  "type": "Feature",
  "properties": {
    "gn:admin1_code":"5.0",
    "gn:asciiname":"Ruchak",
    "gn:country_code":"IR",
    "gn:dem":1415,
    "gn:feature_class":"P",
    "gn:feature_code":"PPL",
    "gn:name":"R\u016bchak",
    "gn:population":0,
    "gn:timezone":"Asia/Tehran",
    "iso:country":"IR",
    "name:fas_x_preferred":[
        "Bardar\u0101st"
    ],
    "name:fas_x_variant":[
        "\u0628\u0631\u062f\u0631\u0627\u0633\u062a",
        "\u0631\u0648\u0686\u06a9"
    ],
    "name:und_x_variant":[
        "R\u016bchak"
    ],
    "wof:name":"Ruchak",
    "wof:placetype":"locality"
},
  "geometry": {"coordinates":[50.46501,31.24133],"type":"Point"}
}