{
  "type": "Feature",
  "properties": {
    "gn:admin1_code":"35.0",
    "gn:asciiname":"Muzi `Isa",
    "gn:country_code":"IR",
    "gn:dem":1516,
    "gn:feature_class":"P",
    "gn:feature_code":"PPL",
    "gn:name":"M\u016bz\u012b \u2018\u012as\u00e1",
    "gn:population":0,
    "gn:timezone":"Asia/Tehran",
    "iso:country":"IR",
    "name:fas_x_preferred":[
        "\u0645\u0648\u0632\u06cc \u0639\u064a\u0633\u0649"
    ],
    "name:fas_x_variant":[
        "M\u016bz\u012b \u2018\u012as\u00e1"
    ],
    "wof:name":"Muzi `Isa",
    "wof:placetype":"locality"
},
  "geometry": {"coordinates":[53.55525,36.35469000000001],"type":"Point"}
}