{
  "type": "Feature",
  "properties": {
    "gn:admin1_code":"36",
    "gn:asciiname":"Sonbolabad",
    "gn:country_code":"IR",
    "gn:dem":1795,
    "gn:feature_class":"P",
    "gn:feature_code":"PPL",
    "gn:name":"Sonbol\u0101b\u0101d",
    "gn:population":0,
    "gn:timezone":"Asia/Tehran",
    "iso:country":"IR",
    "name:fas_x_preferred":[
        "\u0633\u0646\u0628\u0644 \u0622\u0628\u0627\u062f"
    ],
    "name:fas_x_variant":[
        "Sonbol\u0101b\u0101d"
    ],
    "name:und_x_variant":[
        "Sanbalabad"
    ],
    "wof:name":"Sonbolabad",
    "wof:placetype":"locality"
},
  "geometry": {"coordinates":[48.8777,36.43622],"type":"Point"}
}