{
  "type": "Feature",
  "properties": {
    "gn:admin1_code":"4.0",
    "gn:asciiname":"Jahlu",
    "gn:country_code":"IR",
    "gn:dem":1127,
    "gn:feature_class":"P",
    "gn:feature_code":"PPL",
    "gn:name":"Jahl\u016b",
    "gn:population":0,
    "gn:timezone":"Asia/Tehran",
    "iso:country":"IR",
    "name:fas_x_preferred":[
        "\u062c\u0647\u0644\u0648"
    ],
    "name:und_x_variant":[
        "Jahl\u016b"
    ],
    "wof:name":"Jahlu",
    "wof:placetype":"locality"
},
  "geometry": {"coordinates":[62.14259000000001,27.22586],"type":"Point"}
}