{
  "type": "Feature",
  "properties": {
    "gn:admin1_code":"23",
    "gn:asciiname":"Daluzohreh",
    "gn:country_code":"IR",
    "gn:dem":1838,
    "gn:feature_class":"P",
    "gn:feature_code":"PPL",
    "gn:name":"D\u0101l\u016bzohreh",
    "gn:population":0,
    "gn:timezone":"Asia/Tehran",
    "iso:country":"IR",
    "name:fas_x_preferred":[
        "\u062f\u0627\u0644\u0648\u0632\u064f\u0647\u0631\u0650\u0647"
    ],
    "name:fas_x_variant":[
        "D\u0101l\u016bzohreh"
    ],
    "wof:name":"Daluzohreh",
    "wof:placetype":"locality"
},
  "geometry": {"coordinates":[49.63333,33.03333],"type":"Point"}
}