{
  "type": "Feature",
  "properties": {
    "gn:admin1_code":"42",
    "gn:asciiname":"Neqab",
    "gn:country_code":"IR",
    "gn:dem":1073,
    "gn:feature_class":"P",
    "gn:feature_code":"PPLA2",
    "gn:name":"Neq\u0101b",
    "gn:population":0,
    "gn:timezone":"Asia/Tehran",
    "iso:country":"IR",
    "name:fas_x_preferred":[
        "Neq\u0101b"
    ],
    "name:fas_x_variant":[
        "\u0646\u0642\u0627\u0628"
    ],
    "name:und_x_variant":[
        "\u0646\u0642\u0627\u0628"
    ],
    "wof:name":"Neqab",
    "wof:placetype":"locality"
},
  "geometry": {"coordinates":[57.42146,36.70792],"type":"Point"}
}