{
  "type": "Feature",
  "properties": {
    "gn:admin1_code":"5",
    "gn:asciiname":"Heridun",
    "gn:country_code":"IR",
    "gn:dem":1172,
    "gn:feature_class":"P",
    "gn:feature_code":"PPL",
    "gn:name":"Her\u012bd\u016bn",
    "gn:population":0,
    "gn:timezone":"Asia/Tehran",
    "iso:country":"IR",
    "name:fas_x_preferred":[
        "Her\u012bd\u016bn"
    ],
    "name:fas_x_variant":[
        "\u0647\u0631\u064a\u062f\u0648\u0646"
    ],
    "wof:name":"Heridun",
    "wof:placetype":"locality"
},
  "geometry": {"coordinates":[50.53514000000001,31.075],"type":"Point"}
}