{
  "type": "Feature",
  "properties": {
    "gn:admin1_code":"23",
    "gn:asciiname":"Burbur-e Sofla",
    "gn:country_code":"IR",
    "gn:dem":1619,
    "gn:feature_class":"P",
    "gn:feature_code":"PPL",
    "gn:name":"B\u016brb\u016br-e Sofl\u00e1",
    "gn:population":0,
    "gn:timezone":"Asia/Tehran",
    "iso:country":"IR",
    "name:ara_x_preferred":[
        "\u0628\u0648\u0631\u0628\u0648\u0631 \u0633\u0641\u0644\u064a"
    ],
    "name:fas_x_preferred":[
        "\u0628\u0648\u0631\u0628\u0648\u0631\u0650 \u0633\u064f\u0641\u0644\u064e\u0649"
    ],
    "name:fas_x_variant":[
        "B\u016brb\u016br-e Sofl\u00e1",
        "\u0628\u0648\u0631\u0628\u0648\u0631 \u0633\u0641\u0644\u06cc"
    ],
    "wof:name":"Burbur-e Sofla",
    "wof:placetype":"locality"
},
  "geometry": {"coordinates":[47.56667,34.11667],"type":"Point"}
}