{
  "type": "Feature",
  "properties": {
    "gn:admin1_code":"28.0",
    "gn:asciiname":"Mazra`eh Emam",
    "gn:country_code":"IR",
    "gn:dem":1513,
    "gn:feature_class":"P",
    "gn:feature_code":"PPL",
    "gn:name":"Mazra\u2018eh Emam",
    "gn:population":0,
    "gn:timezone":"Asia/Tehran",
    "iso:country":"IR",
    "name:fas_x_preferred":[
        "Mazra\u2018eh Emam"
    ],
    "name:fas_x_variant":[
        "\u0645\u0632\u0631\u0639\u0647 \u0627\u0645\u0627\u0645"
    ],
    "wof:name":"Mazra`eh Emam",
    "wof:placetype":"locality"
},
  "geometry": {"coordinates":[53.12431,32.85221],"type":"Point"}
}