{
  "type": "Feature",
  "properties": {
    "gn:admin1_code":"42.0",
    "gn:asciiname":"Baghan",
    "gn:country_code":"IR",
    "gn:dem":945,
    "gn:feature_class":"P",
    "gn:feature_code":"PPL",
    "gn:name":"B\u0101gh\u0101n",
    "gn:population":0,
    "gn:timezone":"Asia/Tehran",
    "iso:country":"IR",
    "name:fas_x_preferred":[
        "\u0628\u0627\u063a\u0627\u0646"
    ],
    "name:fas_x_variant":[
        "B\u0101gh\u0101n"
    ],
    "wof:name":"Baghan",
    "wof:placetype":"locality"
},
  "geometry": {"coordinates":[57.76422,36.19053],"type":"Point"}
}