{
  "type": "Feature",
  "properties": {
    "gn:admin1_code":"35",
    "gn:asciiname":"Bon Tangeh",
    "gn:country_code":"IR",
    "gn:dem":1231,
    "gn:feature_class":"P",
    "gn:feature_code":"PPL",
    "gn:name":"Bon Tangeh",
    "gn:population":0,
    "gn:timezone":"Asia/Tehran",
    "iso:country":"IR",
    "name:fas_x_preferred":[
        "\u0628\u0646 \u062a\u0646\u06af\u0647"
    ],
    "name:fas_x_variant":[
        "\u0633\u0631 \u062a\u0646\u06af\u0647"
    ],
    "name:und_x_variant":[
        "Sar Tangeh"
    ],
    "wof:name":"Bon Tangeh",
    "wof:placetype":"locality"
},
  "geometry": {"coordinates":[53.11663000000001,35.94679],"type":"Point"}
}