{
  "type": "Feature",
  "properties": {
    "gn:admin1_code":"11",
    "gn:asciiname":"Mogh Gap",
    "gn:country_code":"IR",
    "gn:dem":647,
    "gn:feature_class":"P",
    "gn:feature_code":"PPL",
    "gn:name":"Mogh Gap",
    "gn:population":0,
    "gn:timezone":"Asia/Tehran",
    "iso:country":"IR",
    "name:fas_x_preferred":[
        "\u0645\u063a \u06af\u067e"
    ],
    "wof:name":"Mogh Gap",
    "wof:placetype":"locality"
},
  "geometry": {"coordinates":[56.4159,27.7017],"type":"Point"}
}