{
  "type": "Feature",
  "properties": {
    "gn:admin1_code":"8.0",
    "gn:asciiname":"Dastgah Sara",
    "gn:country_code":"IR",
    "gn:dem":160,
    "gn:feature_class":"P",
    "gn:feature_code":"PPL",
    "gn:name":"Dastg\u0101h Sar\u0101",
    "gn:population":0,
    "gn:timezone":"Asia/Tehran",
    "iso:country":"IR",
    "name:fas_x_preferred":[
        "\u062f\u0633\u062a\u06af\u0627\u0647 \u0633\u0631\u0627"
    ],
    "name:und_x_variant":[
        "Dastg\u0101h Sar\u0101"
    ],
    "wof:name":"Dastgah Sara",
    "wof:placetype":"locality"
},
  "geometry": {"coordinates":[49.72425,37.0585],"type":"Point"}
}