{
  "type": "Feature",
  "properties": {
    "gn:admin1_code":"42",
    "gn:asciiname":"Esma`ilabad",
    "gn:country_code":"IR",
    "gn:dem":1366,
    "gn:feature_class":"P",
    "gn:feature_code":"PPL",
    "gn:name":"Esm\u0101\u2018\u012bl\u0101b\u0101d",
    "gn:population":0,
    "gn:timezone":"Asia/Tehran",
    "iso:country":"IR",
    "name:fas_x_preferred":[
        "Esm\u0101\u2018\u012bl\u0101b\u0101d"
    ],
    "wof:name":"Esma`ilabad",
    "wof:placetype":"locality"
},
  "geometry": {"coordinates":[59.34083,35.28944],"type":"Point"}
}