{
  "type": "Feature",
  "properties": {
    "gn:admin1_code":"28.0",
    "gn:asciiname":"Khormenan",
    "gn:country_code":"IR",
    "gn:dem":2622,
    "gn:feature_class":"P",
    "gn:feature_code":"PPL",
    "gn:name":"Khormen\u0101n",
    "gn:population":0,
    "gn:timezone":"Asia/Tehran",
    "iso:country":"IR",
    "name:fas_x_preferred":[
        "Khormen\u0101n"
    ],
    "name:fas_x_variant":[
        "\u062e\u064f\u0631\u0645\u0650\u0646\u0627\u0646"
    ],
    "wof:name":"Khormenan",
    "wof:placetype":"locality"
},
  "geometry": {"coordinates":[50.19389,32.77333],"type":"Point"}
}