{
  "type": "Feature",
  "properties": {
    "gn:admin1_code":"3",
    "gn:asciiname":"Salah Chin",
    "gn:cc2":"IR",
    "gn:country_code":"IR",
    "gn:dem":1866,
    "gn:feature_class":"P",
    "gn:feature_code":"PPL",
    "gn:name":"Sala\u1e29 Ch\u012bn",
    "gn:population":0,
    "gn:timezone":"Asia/Tehran",
    "iso:country":"IR",
    "name:ceb_x_preferred":[
        "Sala\u1e29 Ch\u012bn"
    ],
    "name:fas_x_preferred":[
        "\u0633\u064e\u0646\u0643\u0628\u064f\u0631"
    ],
    "name:fas_x_variant":[
        "Sala\u1e29 Ch\u012bn",
        "\u0633\u064e\u0644\u064e\u062d \u0686\u064a\u0646",
        "\u0633\u064e\u0646\u06af \u0628\u0648\u0631",
        "\u0633\u0644\u062d \u0686\u06cc\u0646"
    ],
    "name:msa_x_preferred":[
        "Salah Chin"
    ],
    "name:swe_x_preferred":[
        "Sala\u1e29 Ch\u012bn"
    ],
    "name:und_x_variant":[
        "Sankbor",
        "Sang B\u016br"
    ],
    "wof:name":"Salah Chin",
    "wof:placetype":"locality"
},
  "geometry": {"coordinates":[50.99806,31.50139],"type":"Point"}
}