{
  "type": "Feature",
  "properties": {
    "gn:admin1_code":"13",
    "gn:asciiname":"Siah Darreh",
    "gn:country_code":"IR",
    "gn:dem":1886,
    "gn:feature_class":"P",
    "gn:feature_code":"PPL",
    "gn:name":"S\u012b\u0101h Darreh",
    "gn:population":0,
    "gn:timezone":"Asia/Tehran",
    "iso:country":"IR",
    "name:ceb_x_preferred":[
        "Siah Darreh"
    ],
    "name:fas_x_preferred":[
        "\u0633\u06cc\u0627\u0647 \u062f\u0631\u0651\u0647"
    ],
    "name:fas_x_variant":[
        "S\u012b\u0101h Darreh"
    ],
    "name:swe_x_preferred":[
        "Siah Darreh"
    ],
    "name:und_x_variant":[
        "Sey\u0101h Darreh",
        "Siah Darra"
    ],
    "wof:name":"Siah Darreh",
    "wof:placetype":"locality"
},
  "geometry": {"coordinates":[47.2385,34.769],"type":"Point"}
}