{
  "type": "Feature",
  "properties": {
    "gn:admin1_code":"4.0",
    "gn:asciiname":"Naskand",
    "gn:country_code":"IR",
    "gn:dem":1089,
    "gn:feature_class":"P",
    "gn:feature_code":"PPL",
    "gn:name":"Naskand",
    "gn:population":0,
    "gn:timezone":"Asia/Tehran",
    "iso:country":"IR",
    "name:fas_x_preferred":[
        "Nashkand P\u0101\u2019\u012bn"
    ],
    "name:fas_x_variant":[
        "Qal\u2018 eh-ye Nashkand",
        "Nashkand-e P\u0101\u2019\u012bn",
        "\u0646\u0633\u06a9\u0646\u062f",
        "N\u0101zkand",
        "Nask\u0101n"
    ],
    "name:und_x_variant":[
        "Nashkand",
        "Nask\u0101n",
        "N\u0101zkand",
        "Naskand"
    ],
    "wof:name":"Naskand",
    "wof:placetype":"locality"
},
  "geometry": {"coordinates":[61.4625,26.70423],"type":"Point"}
}