{
  "type": "Feature",
  "properties": {
    "gn:admin1_code":"25",
    "gn:asciiname":"Qal`eh-ye Bala",
    "gn:country_code":"IR",
    "gn:dem":1249,
    "gn:feature_class":"P",
    "gn:feature_code":"PPL",
    "gn:name":"Qal\u2018eh-ye B\u0101l\u0101",
    "gn:population":0,
    "gn:timezone":"Asia/Tehran",
    "iso:country":"IR",
    "name:fas_x_preferred":[
        "\u0642\u0644\u0639\u0647 \u0628\u0627\u0644\u0627"
    ],
    "name:fas_x_variant":[
        "Qal\u2018eh-ye B\u0101l\u0101"
    ],
    "name:und_x_variant":[
        "Qal\u2018eh B\u0101l\u0101"
    ],
    "wof:name":"Qal`eh-ye Bala",
    "wof:placetype":"locality"
},
  "geometry": {"coordinates":[56.00176999999999,36.00214000000001],"type":"Point"}
}