{
  "type": "Feature",
  "properties": {
    "gn:admin1_code":"38",
    "gn:asciiname":"Kikhanan",
    "gn:country_code":"IR",
    "gn:dem":1546,
    "gn:elevation":"0.0",
    "gn:feature_class":"P",
    "gn:feature_code":"PPL",
    "gn:name":"K\u012bkhan\u0101n",
    "gn:population":0,
    "gn:timezone":"Asia/Tehran",
    "iso:country":"IR",
    "name:ceb_x_preferred":[
        "K\u012bkhan\u0101n"
    ],
    "name:fas_x_preferred":[
        "\u06a9\u06cc\u062e\u0646\u0627\u0646"
    ],
    "name:fas_x_variant":[
        "K\u012bkhan\u0101n"
    ],
    "name:swe_x_preferred":[
        "K\u012bkhan\u0101n"
    ],
    "wof:name":"Kikhanan",
    "wof:placetype":"locality"
},
  "geometry": {"coordinates":[49.79656,36.39299000000001],"type":"Point"}
}