{
  "type": "Feature",
  "properties": {
    "gn:admin1_code":"35.0",
    "gn:asciiname":"Khas Kola",
    "gn:country_code":"IR",
    "gn:dem":136,
    "gn:feature_class":"P",
    "gn:feature_code":"PPL",
    "gn:name":"Kh\u0101\u015f Kol\u0101",
    "gn:population":0,
    "gn:timezone":"Asia/Tehran",
    "iso:country":"IR",
    "name:ara_x_preferred":[
        "\u062e\u0627\u0635 \u06a9\u0644\u0627"
    ],
    "name:ceb_x_preferred":[
        "Kh\u0101\u015f Kol\u0101"
    ],
    "name:fas_x_preferred":[
        "\u062e\u0627\u0635\u0650\u0643\u064f\u0644\u0627"
    ],
    "name:fas_x_variant":[
        "Kh\u0101\u015fekol\u0101",
        "Kh\u0101\u015f Kol\u0101",
        "\u062e\u0627\u0635 \u0643\u0644\u0627",
        "\u062e\u0627\u0635\u200c\u06a9\u0644\u0627"
    ],
    "name:mzn_x_preferred":[
        "\u062e\u0627\u0635\u200c\u06a9\u0644\u0627"
    ],
    "name:swe_x_preferred":[
        "Kh\u0101\u015f Kol\u0101"
    ],
    "name:ukr_x_preferred":[
        "\u0425\u0430\u0441-\u041a\u043e\u043b\u0430"
    ],
    "wof:name":"Khas Kola",
    "wof:placetype":"locality"
},
  "geometry": {"coordinates":[52.33547,36.43402],"type":"Point"}
}