{
  "type": "Feature",
  "properties": {
    "gn:admin1_code":"28",
    "gn:asciiname":"Davaran",
    "gn:country_code":"IR",
    "gn:dem":1963,
    "gn:feature_class":"P",
    "gn:feature_code":"PPL",
    "gn:name":"D\u0101var\u0101n",
    "gn:population":0,
    "gn:timezone":"Asia/Tehran",
    "iso:country":"IR",
    "name:ara_x_preferred":[
        "\u062f\u0627\u0648\u0631\u0627\u0646"
    ],
    "name:fas_x_preferred":[
        "\u062f\u0627\u0648\u0631\u0627\u0646"
    ],
    "name:fas_x_variant":[
        "D\u0101var\u0101n"
    ],
    "wof:name":"Davaran",
    "wof:placetype":"locality"
},
  "geometry": {"coordinates":[52.2683,33.2347],"type":"Point"}
}