{
  "type": "Feature",
  "properties": {
    "gn:admin1_code":"7",
    "gn:asciiname":"Sigar",
    "gn:country_code":"IR",
    "gn:dem":408,
    "gn:feature_class":"P",
    "gn:feature_code":"PPL",
    "gn:name":"S\u012bg\u0101r",
    "gn:population":0,
    "gn:timezone":"Asia/Tehran",
    "iso:country":"IR",
    "name:fas_x_preferred":[
        "\u0633\u06cc\u06af\u0627\u0631"
    ],
    "name:fas_x_variant":[
        "S\u012bg\u0101r-e B\u0101l\u0101",
        "S\u012bg\u0101r-e \u2018Oly\u0101",
        "S\u012bg\u0101r-e Sofl\u00e1",
        "S\u012bg\u0101r",
        "\u0633\u06cc\u06af\u0627\u0631 \u067e\u0627\u06cc\u06cc\u0646"
    ],
    "name:und_x_variant":[
        "Sigar Bala",
        "S\u012bg\u0101r-e P\u0101\u2019\u012bn"
    ],
    "wof:name":"Sigar",
    "wof:placetype":"locality"
},
  "geometry": {"coordinates":[53.3184,27.2901],"type":"Point"}
}