{
  "type": "Feature",
  "properties": {
    "gn:admin1_code":"41",
    "gn:asciiname":"Mazra`eh-ye Ijand",
    "gn:country_code":"IR",
    "gn:dem":1960,
    "gn:feature_class":"P",
    "gn:feature_code":"PPL",
    "gn:name":"Mazra\u2018eh-ye \u012ajand",
    "gn:population":0,
    "gn:timezone":"Asia/Tehran",
    "iso:country":"IR",
    "name:fas_x_preferred":[
        "\u0627\u06cc\u062c\u0646\u062f"
    ],
    "name:fas_x_variant":[
        "\u012ajand-e B\u0101l\u0101",
        "\u012ajand",
        "\u0645\u0632\u0631\u0639\u0647 \u0627\u06cc\u062c\u0646\u062f"
    ],
    "name:und_x_variant":[
        "Mazra\u2018eh-ye \u012ajand"
    ],
    "wof:name":"Mazra`eh-ye Ijand",
    "wof:placetype":"locality"
},
  "geometry": {"coordinates":[59.41625,33.35325],"type":"Point"}
}