{
  "type": "Feature",
  "properties": {
    "gn:admin1_code":"33",
    "gn:asciiname":"Idir-e Bala",
    "gn:country_code":"IR",
    "gn:dem":239,
    "gn:feature_class":"P",
    "gn:feature_code":"PPL",
    "gn:name":"\u012ad\u012br-e B\u0101l\u0101",
    "gn:population":0,
    "gn:timezone":"Asia/Tehran",
    "iso:country":"IR",
    "name:fas_x_preferred":[
        "\u064a\u062f\u064a\u0631\u0650 \u0639\u064f\u0644\u064a\u0627"
    ],
    "name:fas_x_variant":[
        "\u0627\u06cc\u062f\u06cc\u0631 \u0628\u0627\u0644\u0627",
        "\u012ad\u012br-e \u2018Oly\u0101",
        "\u012ad\u012br-e B\u0101l\u0101"
    ],
    "wof:name":"Idir-e Bala",
    "wof:placetype":"locality"
},
  "geometry": {"coordinates":[47.4701,39.3377],"type":"Point"}
}