{
  "type": "Feature",
  "properties": {
    "gn:admin1_code":"44",
    "gn:asciiname":"Vayeh Bek",
    "gn:country_code":"IR",
    "gn:dem":1171,
    "gn:feature_class":"P",
    "gn:feature_code":"PPL",
    "gn:name":"V\u0101yeh Bek",
    "gn:population":0,
    "gn:timezone":"Asia/Tehran",
    "iso:country":"IR",
    "name:fas_x_preferred":[
        "\u0648\u0627\u064a\u0650\u0647 \u0628\u0650\u064a\u06af"
    ],
    "name:fas_x_variant":[
        "\u0648\u0627\u06cc\u0628\u06a9",
        "V\u0101yeh Beyg",
        "V\u0101ybek",
        "\u0648\u0627\u06cc\u0647 \u0628\u06a9"
    ],
    "name:und_x_variant":[
        "V\u0101yeh Bek"
    ],
    "wof:name":"Vayeh Bek",
    "wof:placetype":"locality"
},
  "geometry": {"coordinates":[50.5614,35.9126],"type":"Point"}
}