{
  "type": "Feature",
  "properties": {
    "gn:admin1_code":"10",
    "gn:asciiname":"Gol Gol-e `Olya",
    "gn:country_code":"IR",
    "gn:dem":1118,
    "gn:feature_class":"P",
    "gn:feature_code":"PPL",
    "gn:name":"Gol Gol-e \u2018Oly\u0101",
    "gn:population":0,
    "gn:timezone":"Asia/Tehran",
    "iso:country":"IR",
    "name:fas_x_preferred":[
        "\u06af\u064f\u0644\u06af\u064f\u0644\u0650 \u0639\u064f\u0644\u064a\u0627"
    ],
    "name:fas_x_variant":[
        "\u06af\u0644 \u06af\u0644 \u0639\u0644\u06cc\u0627",
        "Golgol-e \u2018Oly\u0101",
        "Gol Gol-e \u2018Oly\u0101",
        "\u06af\u064f\u0644 \u06af\u064f\u0644",
        "\u06af\u0644\u200c\u06af\u0644 \u0639\u0644\u06cc\u0627"
    ],
    "name:msa_x_preferred":[
        "Gol Gol-e Olya"
    ],
    "name:und_x_variant":[
        "Gol Gol"
    ],
    "wof:name":"Gol Gol-e `Olya",
    "wof:placetype":"locality"
},
  "geometry": {"coordinates":[46.4904,33.4809],"type":"Point"}
}