{
  "type": "Feature",
  "properties": {
    "gn:admin1_code":"33",
    "gn:asciiname":"Yasavol",
    "gn:country_code":"IR",
    "gn:dem":2027,
    "gn:feature_class":"P",
    "gn:feature_code":"PPL",
    "gn:name":"Yas\u0101vol",
    "gn:population":0,
    "gn:timezone":"Asia/Tehran",
    "iso:country":"IR",
    "name:ara_x_preferred":[
        "\u064a\u0633\u0627\u0648\u0644"
    ],
    "name:fas_x_preferred":[
        "\u06cc\u0633\u0627\u0648\u0644"
    ],
    "name:fas_x_variant":[
        "Yas\u0101vol"
    ],
    "name:msa_x_preferred":[
        "Yasavol"
    ],
    "name:urd_x_preferred":[
        "\u06cc\u0633\u0648\u0648\u0644"
    ],
    "wof:name":"Yasavol",
    "wof:placetype":"locality"
},
  "geometry": {"coordinates":[46.9535,37.0725],"type":"Point"}
}