{
  "type": "Feature",
  "properties": {
    "gn:admin1_code":"34",
    "gn:asciiname":"Valazjerd",
    "gn:country_code":"IR",
    "gn:dem":1936,
    "gn:feature_class":"P",
    "gn:feature_code":"PPL",
    "gn:name":"Val\u0101zjerd",
    "gn:population":0,
    "gn:timezone":"Asia/Tehran",
    "iso:country":"IR",
    "name:fas_x_preferred":[
        "\u0648\u0644\u0627\u0632\u062c\u0631\u062f"
    ],
    "name:fas_x_variant":[
        "V\u0101l\u0101zjerd",
        "Val\u0101zjerd"
    ],
    "name:und_x_variant":[
        "Zejerd",
        "Vel\u0101zjerd",
        "Waliajig\u0101r"
    ],
    "wof:name":"Valazjerd",
    "wof:placetype":"locality"
},
  "geometry": {"coordinates":[49.27967,34.78547],"type":"Point"}
}