{
  "type": "Feature",
  "properties": {
    "gn:admin1_code":"15.0",
    "gn:asciiname":"Bani Tamim",
    "gn:country_code":"IR",
    "gn:dem":13,
    "gn:feature_class":"P",
    "gn:feature_code":"PPLF",
    "gn:name":"Ban\u012b Tam\u012bm",
    "gn:population":0,
    "gn:timezone":"Asia/Tehran",
    "iso:country":"IR",
    "name:fas_x_preferred":[
        "\u062a\u062e\u062a\u06cc\u0647 \u06a9\u0648\u0686\u06a9"
    ],
    "name:fas_x_variant":[
        "Takht\u012byeh-ye K\u016bchek",
        "\u0628\u0646\u06cc \u062a\u0645\u06cc\u0645"
    ],
    "name:und_x_variant":[
        "Ban\u012b Tam\u012bm"
    ],
    "wof:name":"Bani Tamim",
    "wof:placetype":"locality"
},
  "geometry": {"coordinates":[48.42193,31.22509],"type":"Point"}
}