{
  "type": "Feature",
  "properties": {
    "gn:admin1_code":"29",
    "gn:asciiname":"Chenar",
    "gn:country_code":"IR",
    "gn:dem":2139,
    "gn:feature_class":"P",
    "gn:feature_code":"PPL",
    "gn:name":"Chen\u0101r",
    "gn:population":0,
    "gn:timezone":"Asia/Tehran",
    "iso:country":"IR",
    "name:fas_x_preferred":[
        "\u0686\u0646\u0627\u0631"
    ],
    "name:fas_x_variant":[
        "Chen\u0101r"
    ],
    "name:und_x_variant":[
        "Chenaroo\u2019eyeh",
        "Chin\u0101r"
    ],
    "wof:name":"Chenar",
    "wof:placetype":"locality"
},
  "geometry": {"coordinates":[55.449,30.1974],"type":"Point"}
}