{
  "type": "Feature",
  "properties": {
    "gn:admin1_code":"11",
    "gn:asciiname":"Lardeh Bastu",
    "gn:cc2":"IR",
    "gn:country_code":"IR",
    "gn:dem":397,
    "gn:feature_class":"P",
    "gn:feature_code":"PPL",
    "gn:name":"Lardeh Bast\u016b",
    "gn:population":0,
    "gn:timezone":"Asia/Tehran",
    "iso:country":"IR",
    "name:fas_x_preferred":[
        "\u0644\u064e\u0631\u062f\u0650\u0647 \u0628\u064e\u0633\u062a\u0648"
    ],
    "name:fas_x_variant":[
        "\u0644\u0627\u0631 \u062f\u0650\u0647\u0650\u0644\u0633\u062a\u0648",
        "Lardeh Bast\u016b"
    ],
    "name:und_x_variant":[
        "L\u0101r Dehelst\u016b"
    ],
    "wof:name":"Lardeh Bastu",
    "wof:placetype":"locality"
},
  "geometry": {"coordinates":[54.73333,27.31667],"type":"Point"}
}