{
  "type": "Feature",
  "properties": {
    "gn:admin1_code":"11",
    "gn:asciiname":"Mazi Kara",
    "gn:country_code":"IR",
    "gn:dem":980,
    "gn:feature_class":"P",
    "gn:feature_code":"PPL",
    "gn:name":"M\u0101z\u012b Kar\u0101",
    "gn:population":0,
    "gn:timezone":"Asia/Tehran",
    "iso:country":"IR",
    "name:fas_x_preferred":[
        "\u0645\u0627\u0632\u06cc \u06a9\u0631\u0627"
    ],
    "name:fas_x_variant":[
        "M\u0101z\u012b Kar\u0101"
    ],
    "wof:name":"Mazi Kara",
    "wof:placetype":"locality"
},
  "geometry": {"coordinates":[56.6646,27.9277],"type":"Point"}
}