{
  "type": "Feature",
  "properties": {
    "gn:admin1_code":"32",
    "gn:asciiname":"Changan",
    "gn:country_code":"IR",
    "gn:dem":974,
    "gn:feature_class":"P",
    "gn:feature_code":"PPL",
    "gn:name":"Chang\u0101n",
    "gn:population":0,
    "gn:timezone":"Asia/Tehran",
    "iso:country":"IR",
    "name:ara_x_preferred":[
        "\u062a\u0634\u0646\u063a\u0627\u0646"
    ],
    "name:azb_x_preferred":[
        "\u062c\u0646\u06af\u0627\u0646"
    ],
    "name:fas_x_preferred":[
        "\u0686\u0646\u06af\u0627\u0646"
    ],
    "name:fas_x_variant":[
        "Jang\u0101n",
        "\u062c\u064e\u0646\u06af\u0627\u0646",
        "Chang\u0101n"
    ],
    "name:msa_x_preferred":[
        "Jangan"
    ],
    "name:urd_x_preferred":[
        "\u062c\u0646\u06af\u0627\u0646"
    ],
    "wof:name":"Changan",
    "wof:placetype":"locality"
},
  "geometry": {"coordinates":[48.2642,39.0018],"type":"Point"}
}