{
  "type": "Feature",
  "properties": {
    "gn:admin1_code":"3.0",
    "gn:asciiname":"Sangnamak",
    "gn:country_code":"IR",
    "gn:dem":1921,
    "gn:feature_class":"P",
    "gn:feature_code":"PPL",
    "gn:name":"Sangnamak",
    "gn:population":0,
    "gn:timezone":"Asia/Tehran",
    "iso:country":"IR",
    "name:fas_x_preferred":[
        "\u0633\u064e\u0646\u06af\u0646\u064e\u0645\u064e\u0643"
    ],
    "wof:name":"Sangnamak",
    "wof:placetype":"locality"
},
  "geometry": {"coordinates":[50.11139,32.21],"type":"Point"}
}