{
  "type": "Feature",
  "properties": {
    "gn:admin1_code":"33",
    "gn:asciiname":"Qalandar",
    "gn:country_code":"IR",
    "gn:dem":1354,
    "gn:feature_class":"P",
    "gn:feature_code":"PPL",
    "gn:name":"Qalandar",
    "gn:population":0,
    "gn:timezone":"Asia/Tehran",
    "iso:country":"IR",
    "name:ara_x_preferred":[
        "\u0642\u0644\u0646\u062f\u0627\u0631"
    ],
    "name:fas_x_preferred":[
        "\u0642\u064e\u0644\u064e\u0646\u062f\u064e\u0631"
    ],
    "name:fas_x_variant":[
        "\u0642\u0644\u0646\u062f\u0631"
    ],
    "name:msa_x_preferred":[
        "Qalandar"
    ],
    "wof:name":"Qalandar",
    "wof:placetype":"locality"
},
  "geometry": {"coordinates":[45.538,38.5978],"type":"Point"}
}