{
  "type": "Feature",
  "properties": {
    "gn:admin1_code":"15.0",
    "gn:asciiname":"Bid Zar",
    "gn:country_code":"IR",
    "gn:dem":905,
    "gn:feature_class":"P",
    "gn:feature_code":"PPL",
    "gn:name":"B\u012bd Zar",
    "gn:population":0,
    "gn:timezone":"Asia/Tehran",
    "iso:country":"IR",
    "name:fas_x_preferred":[
        "B\u012bd Zard"
    ],
    "name:fas_x_variant":[
        "\u0628\u06cc\u062f \u0632\u0631\u062f",
        "\u0628\u06cc\u062f \u0632\u0631"
    ],
    "name:und_x_variant":[
        "B\u012bd Zar"
    ],
    "wof:name":"Bid Zar",
    "wof:placetype":"locality"
},
  "geometry": {"coordinates":[49.83366,31.79644],"type":"Point"}
}