{
  "type": "Feature",
  "properties": {
    "gn:admin1_code":"35",
    "gn:asciiname":"Mo`allem Kolayeh",
    "gn:country_code":"IR",
    "gn:dem":7,
    "gn:feature_class":"P",
    "gn:feature_code":"PPL",
    "gn:name":"Mo\u2018allem Kol\u0101yeh",
    "gn:population":0,
    "gn:timezone":"Asia/Tehran",
    "iso:country":"IR",
    "name:fas_x_preferred":[
        "\u067e\u0627\u0626\u064a\u0646 \u0645\u064f\u0639\u064e\u0644\u0650\u0651\u0645 \u0643\u064f\u0644\u0627"
    ],
    "name:fas_x_variant":[
        "Mo\u2018allem Kol\u0101yeh",
        "P\u0101\u2019\u012bn Mo\u2018allem Kol\u0101",
        "\u0645\u0639\u0644\u0645 \u0643\u0644\u0627\u064a\u0647"
    ],
    "name:und_x_variant":[
        "\u0645\u0639\u0644\u0645 \u0643\u0644\u0627\u064a\u0647"
    ],
    "wof:name":"Mo`allem Kolayeh",
    "wof:placetype":"locality"
},
  "geometry": {"coordinates":[53.09814,36.62147],"type":"Point"}
}