{
  "type": "Feature",
  "properties": {
    "gn:admin1_code":"33.0",
    "gn:asciiname":"Mantaqeh-ye Golzar Yari",
    "gn:country_code":"IR",
    "gn:dem":1225,
    "gn:feature_class":"P",
    "gn:feature_code":"PPLL",
    "gn:name":"Man\u0163aqeh-ye Golz\u0101r Yar\u012b",
    "gn:population":0,
    "gn:timezone":"Asia/Tehran",
    "iso:country":"IR",
    "name:fas_x_preferred":[
        "\u0645\u0646\u0637\u0642\u0647 \u06af\u0644\u0632\u0627\u0631 \u06cc\u0631\u06cc"
    ],
    "name:und_x_variant":[
        "Man\u0163aqeh-ye Golz\u0101r Yar\u012b"
    ],
    "wof:name":"Mantaqeh-ye Golzar Yari",
    "wof:placetype":"locality"
},
  "geometry": {"coordinates":[45.71318,38.52015],"type":"Point"}
}