{
  "type": "Feature",
  "properties": {
    "gn:admin1_code":"29.0",
    "gn:asciiname":"Chah Daqq-e `Olya",
    "gn:country_code":"IR",
    "gn:dem":1723,
    "gn:feature_class":"P",
    "gn:feature_code":"PPL",
    "gn:name":"Ch\u0101h Daqq-e \u2018Olya",
    "gn:population":0,
    "gn:timezone":"Asia/Tehran",
    "iso:country":"IR",
    "name:fas_x_preferred":[
        "\u0686\u0627\u0647 \u062f\u0642 \u0639\u0644\u064a\u0627"
    ],
    "name:und_x_variant":[
        "Ch\u0101h Daqq-e \u2018Olya"
    ],
    "wof:name":"Chah Daqq-e `Olya",
    "wof:placetype":"locality"
},
  "geometry": {"coordinates":[55.92745,29.11732],"type":"Point"}
}