{
  "type": "Feature",
  "properties": {
    "gn:admin1_code":"33",
    "gn:asciiname":"Zangbar",
    "gn:country_code":"IR",
    "gn:dem":1949,
    "gn:feature_class":"P",
    "gn:feature_code":"PPL",
    "gn:name":"Zangb\u0101r",
    "gn:population":0,
    "gn:timezone":"Asia/Tehran",
    "iso:country":"IR",
    "name:ara_x_preferred":[
        "\u0632\u0646\u063a\u0628\u0627\u0631"
    ],
    "name:fas_x_preferred":[
        "\u0632\u0646\u06af\u0628\u0627\u0631"
    ],
    "name:fas_x_variant":[
        "Zangb\u0101r"
    ],
    "name:msa_x_preferred":[
        "Zangbar"
    ],
    "name:tur_x_preferred":[
        "Zangibar"
    ],
    "wof:name":"Zangbar",
    "wof:placetype":"locality"
},
  "geometry": {"coordinates":[46.7448,37.7572],"type":"Point"}
}