{
  "type": "Feature",
  "properties": {
    "gn:admin1_code":"40",
    "gn:asciiname":"Mazra`eh",
    "gn:country_code":"IR",
    "gn:dem":1872,
    "gn:feature_class":"P",
    "gn:feature_code":"PPL",
    "gn:name":"Mazra\u2018eh",
    "gn:population":0,
    "gn:timezone":"Asia/Tehran",
    "iso:country":"IR",
    "name:fas_x_preferred":[
        "\u0645\u064e\u0632\u0631\u064e\u0639\u0650\u0647"
    ],
    "name:fas_x_variant":[
        "Mazra\u2018eh"
    ],
    "wof:name":"Mazra`eh",
    "wof:placetype":"locality"
},
  "geometry": {"coordinates":[53.28722,32.1725],"type":"Point"}
}