{
  "type": "Feature",
  "properties": {
    "gn:admin1_code":"7",
    "gn:asciiname":"Zameni",
    "gn:country_code":"IR",
    "gn:dem":896,
    "gn:feature_class":"P",
    "gn:feature_code":"PPL",
    "gn:name":"\u1e94\u0101men\u012b",
    "gn:population":0,
    "gn:timezone":"Asia/Tehran",
    "iso:country":"IR",
    "name:fas_x_preferred":[
        "\u1e94\u0101men\u012b"
    ],
    "name:fas_x_variant":[
        "\u1e94\u0101men\u012b-ye B\u0101l\u0101",
        "\u0636\u0627\u0645\u0646\u06cc"
    ],
    "name:msa_x_preferred":[
        "Zameni"
    ],
    "name:und_x_variant":[
        "Zamen\u012b",
        "Z\u0101men\u012b-ye \u2018Oly\u0101",
        "\u0636\u0627\u0645\u0646\u06cc"
    ],
    "wof:name":"Zameni",
    "wof:placetype":"locality"
},
  "geometry": {"coordinates":[51.538,30.231],"type":"Point"}
}