{
  "type": "Feature",
  "properties": {
    "gn:admin1_code":"7",
    "gn:asciiname":"Baghuyeh",
    "gn:country_code":"IR",
    "gn:dem":2013,
    "gn:feature_class":"P",
    "gn:feature_code":"PPLF",
    "gn:name":"B\u0101gh\u016byeh",
    "gn:population":0,
    "gn:timezone":"Asia/Tehran",
    "iso:country":"IR",
    "name:fas_x_preferred":[
        "\u0628\u0627\u063a\u0648\u06cc\u0647"
    ],
    "name:fas_x_variant":[
        "B\u0101gh\u016byeh"
    ],
    "name:und_x_variant":[
        "Baghoo"
    ],
    "wof:name":"Baghuyeh",
    "wof:placetype":"locality"
},
  "geometry": {"coordinates":[54.44089,29.47424],"type":"Point"}
}