{
  "type": "Feature",
  "properties": {
    "gn:admin1_code":"23",
    "gn:asciiname":"Khorusan",
    "gn:country_code":"IR",
    "gn:dem":1991,
    "gn:feature_class":"P",
    "gn:feature_code":"PPL",
    "gn:name":"Khor\u016bs\u0101n",
    "gn:population":0,
    "gn:timezone":"Asia/Tehran",
    "iso:country":"IR",
    "name:fas_x_preferred":[
        "\u062e\u064f\u0648\u0631\u064a\u0634\u0627\u0646"
    ],
    "name:fas_x_variant":[
        "Khor\u016bs\u0101n",
        "\u062e\u0631\u0648\u0633\u0627\u0646"
    ],
    "name:und_x_variant":[
        "Khur\u012bsh\u0101n",
        "Khowr\u012bsh\u0101n",
        "Khoroosan",
        "\u062e\u0631\u0648\u0633\u0627\u0646"
    ],
    "wof:name":"Khorusan",
    "wof:placetype":"locality"
},
  "geometry": {"coordinates":[49.55852,33.67079],"type":"Point"}
}