{
  "type": "Feature",
  "properties": {
    "gn:admin1_code":"28",
    "gn:asciiname":"Zendevan",
    "gn:country_code":"IR",
    "gn:dem":1539,
    "gn:feature_class":"P",
    "gn:feature_code":"PPL",
    "gn:name":"Zendev\u0101n",
    "gn:population":0,
    "gn:timezone":"Asia/Tehran",
    "iso:country":"IR",
    "name:fas_x_preferred":[
        "Zendev\u0101n"
    ],
    "name:fas_x_variant":[
        "\u0632\u0646\u062f\u0648\u0627\u0646"
    ],
    "name:und_x_variant":[
        "Zindw\u0101n",
        "Zandav\u0101n",
        "Zandov\u0101n",
        "Z\u012bndav\u0101n"
    ],
    "wof:name":"Zendevan",
    "wof:placetype":"locality"
},
  "geometry": {"coordinates":[53.10596,32.84714],"type":"Point"}
}