{
  "type": "Feature",
  "properties": {
    "gn:admin1_code":"9",
    "gn:asciiname":"Kollijah",
    "gn:country_code":"IR",
    "gn:dem":1695,
    "gn:feature_class":"P",
    "gn:feature_code":"PPL",
    "gn:name":"Koll\u012bjah",
    "gn:population":0,
    "gn:timezone":"Asia/Tehran",
    "iso:country":"IR",
    "name:fas_x_preferred":[
        "\u06a9\u0644\u06cc\u062c\u0647"
    ],
    "name:fas_x_variant":[
        "Koll\u012bjah"
    ],
    "wof:name":"Kollijah",
    "wof:placetype":"locality"
},
  "geometry": {"coordinates":[48.98503,35.23885],"type":"Point"}
}