{
  "type": "Feature",
  "properties": {
    "gn:admin1_code":"1",
    "gn:asciiname":"Qezel Aghol",
    "gn:country_code":"IR",
    "gn:dem":2143,
    "gn:feature_class":"P",
    "gn:feature_code":"PPL",
    "gn:name":"Qezel \u0100ghol",
    "gn:population":0,
    "gn:timezone":"Asia/Tehran",
    "iso:country":"IR",
    "name:aze_x_preferred":[
        "Q\u0131z\u0131la\u011f\u0131l"
    ],
    "name:ceb_x_preferred":[
        "Qezel \u0100ghol"
    ],
    "name:fas_x_preferred":[
        "Qezel \u0100ghol"
    ],
    "name:fas_x_variant":[
        "\u0642\u0632\u0644 \u0622\u063a\u0644",
        "\u0642\u0632\u0644\u200c\u0622\u063a\u0644"
    ],
    "name:msa_x_preferred":[
        "Qezel Aghol"
    ],
    "name:swe_x_preferred":[
        "Qezel \u0100ghol"
    ],
    "wof:name":"Qezel Aghol",
    "wof:placetype":"locality"
},
  "geometry": {"coordinates":[44.4914,38.6997],"type":"Point"}
}