{
  "type": "Feature",
  "properties": {
    "gn:admin1_code":"8.0",
    "gn:asciiname":"Dizin",
    "gn:country_code":"IR",
    "gn:dem":23,
    "gn:feature_class":"P",
    "gn:feature_code":"PPL",
    "gn:name":"D\u012bz\u012bn",
    "gn:population":0,
    "gn:timezone":"Asia/Tehran",
    "iso:country":"IR",
    "name:fas_x_preferred":[
        "D\u012bz\u012bn"
    ],
    "name:fas_x_variant":[
        "\u062f\u06cc\u0632\u06cc\u0646"
    ],
    "name:und_x_variant":[
        "\u062f\u06cc\u0632\u06cc\u0646"
    ],
    "wof:name":"Dizin",
    "wof:placetype":"locality"
},
  "geometry": {"coordinates":[50.09198,37.19115],"type":"Point"}
}