{
  "type": "Feature",
  "properties": {
    "gn:admin1_code":"35.0",
    "gn:asciiname":"Kenar",
    "gn:country_code":"IR",
    "gn:dem":-22,
    "gn:feature_class":"P",
    "gn:feature_code":"PPL",
    "gn:name":"Ken\u0101r",
    "gn:population":0,
    "gn:timezone":"Asia/Tehran",
    "iso:country":"IR",
    "name:fas_x_preferred":[
        "\u0643\u0650\u0646\u0627\u0631"
    ],
    "name:fas_x_variant":[
        "Ken\u0101r"
    ],
    "wof:name":"Kenar",
    "wof:placetype":"locality"
},
  "geometry": {"coordinates":[52.48333,36.68333],"type":"Point"}
}