{
  "type": "Feature",
  "properties": {
    "gn:admin1_code":"23",
    "gn:asciiname":"Cham Bagh",
    "gn:country_code":"IR",
    "gn:dem":956,
    "gn:feature_class":"P",
    "gn:feature_code":"PPL",
    "gn:name":"Cham B\u0101gh",
    "gn:population":0,
    "gn:timezone":"Asia/Tehran",
    "iso:country":"IR",
    "name:fas_x_preferred":[
        "\u0686\u0650\u0634\u0645\u0650\u0647 \u0628\u0627\u063a"
    ],
    "name:fas_x_variant":[
        "\u0686\u0645 \u0628\u0627\u063a",
        "Cheshmeh B\u0101gh",
        "Cham B\u0101gh",
        "\u0686\u0645\u0628\u0627\u063a"
    ],
    "wof:name":"Cham Bagh",
    "wof:placetype":"locality"
},
  "geometry": {"coordinates":[47.9627,33.4901],"type":"Point"}
}