{
  "type": "Feature",
  "properties": {
    "gn:admin1_code":"9",
    "gn:asciiname":"Sanjuran",
    "gn:country_code":"IR",
    "gn:dem":2151,
    "gn:feature_class":"P",
    "gn:feature_code":"PPL",
    "gn:name":"Sanj\u016br\u0101n",
    "gn:population":0,
    "gn:timezone":"Asia/Tehran",
    "iso:country":"IR",
    "name:fas_x_preferred":[
        "\u0633\u0646\u062c\u0648\u0632\u0627\u0646"
    ],
    "name:fas_x_variant":[
        "\u0633\u064e\u0646\u062c\u064f\u0648\u0632\u0627\u0646",
        "Sach\u016bz\u0101n",
        "Sanj\u016bz\u0101n",
        "\u0633\u0686\u0648\u0632\u0627\u0646",
        "\u0633\u0646\u062c\u0648\u0631\u0627\u0646"
    ],
    "name:und_x_variant":[
        "Sanjowz\u0101n",
        "\u0633\u0686\u0648\u0632\u0627\u0646",
        "Sanj\u016br\u0101n"
    ],
    "wof:name":"Sanjuran",
    "wof:placetype":"locality"
},
  "geometry": {"coordinates":[48.3934,34.65603],"type":"Point"}
}