{
  "type": "Feature",
  "properties": {
    "gn:admin1_code":"15.0",
    "gn:asciiname":"Mel Boland",
    "gn:country_code":"IR",
    "gn:dem":982,
    "gn:feature_class":"P",
    "gn:feature_code":"PPL",
    "gn:name":"Mel Boland",
    "gn:population":0,
    "gn:timezone":"Asia/Tehran",
    "iso:country":"IR",
    "name:fas_x_preferred":[
        "\u0645\u0644 \u0628\u0644\u0646\u062f"
    ],
    "name:und_x_variant":[
        "\u0645\u0644 \u0628\u0644\u0646\u062f"
    ],
    "wof:name":"Mel Boland",
    "wof:placetype":"locality"
},
  "geometry": {"coordinates":[49.68786,32.04103],"type":"Point"}
}