{
  "type": "Feature",
  "properties": {
    "gn:admin1_code":"29.0",
    "gn:asciiname":"Chekeri",
    "gn:cc2":"IR",
    "gn:country_code":"IR",
    "gn:dem":599,
    "gn:feature_class":"P",
    "gn:feature_code":"PPL",
    "gn:name":"Cheker\u012b",
    "gn:population":0,
    "gn:timezone":"Asia/Tehran",
    "iso:country":"IR",
    "name:fas_x_preferred":[
        "Cheker\u012b"
    ],
    "name:und_x_variant":[
        "Chaker\u012b"
    ],
    "wof:name":"Chekeri",
    "wof:placetype":"locality"
},
  "geometry": {"coordinates":[57.77778000000001,28.53472],"type":"Point"}
}