{
  "type": "Feature",
  "properties": {
    "gn:admin1_code":"15.0",
    "gn:asciiname":"Garmeh Khorusi",
    "gn:country_code":"IR",
    "gn:dem":5,
    "gn:feature_class":"P",
    "gn:feature_code":"PPL",
    "gn:name":"Garmeh Khor\u016bs\u012b",
    "gn:population":0,
    "gn:timezone":"Asia/Tehran",
    "iso:country":"IR",
    "name:fas_x_preferred":[
        "Garm\u0101b"
    ],
    "name:fas_x_variant":[
        "\u06af\u0631\u0645\u0627\u0628",
        "\u06af\u0631\u0645\u0647 \u062e\u0631\u0648\u0633\u06cc"
    ],
    "name:und_x_variant":[
        "\u06af\u0631\u0645\u0627\u0628",
        "Garmeh Khor\u016bs\u012b"
    ],
    "wof:name":"Garmeh Khorusi",
    "wof:placetype":"locality"
},
  "geometry": {"coordinates":[48.58166,30.62168],"type":"Point"}
}