{
  "type": "Feature",
  "properties": {
    "gn:admin1_code":"35.0",
    "gn:asciiname":"Namavar Kola",
    "gn:country_code":"IR",
    "gn:dem":56,
    "gn:feature_class":"P",
    "gn:feature_code":"PPL",
    "gn:name":"Nam\u0101var Kol\u0101",
    "gn:population":0,
    "gn:timezone":"Asia/Tehran",
    "iso:country":"IR",
    "name:fas_x_preferred":[
        "\u0646\u0645\u0627\u0648\u0631 \u0643\u0644\u0627"
    ],
    "name:fas_x_variant":[
        "Nam\u0101var Kol\u0101"
    ],
    "wof:name":"Namavar Kola",
    "wof:placetype":"locality"
},
  "geometry": {"coordinates":[52.79702,36.44727],"type":"Point"}
}