{
  "type": "Feature",
  "properties": {
    "gn:admin1_code":"15",
    "gn:asciiname":"Hajji `Aziz-e Ma`lumi",
    "gn:country_code":"IR",
    "gn:dem":7,
    "gn:feature_class":"P",
    "gn:feature_code":"PPL",
    "gn:name":"\u1e28\u0101jj\u012b \u2018Az\u012bz-e Ma\u2018l\u016bm\u012b",
    "gn:population":0,
    "gn:timezone":"Asia/Tehran",
    "iso:country":"IR",
    "name:fas_x_preferred":[
        "\u0639\u064e\u0632\u064a\u0632"
    ],
    "name:fas_x_variant":[
        "\u1e28\u0101jj\u012b \u2018Az\u012bz-e Ma\u2018l\u016bm\u012b",
        "\u2018Az\u012bz",
        "\u062d\u0627\u062c\u06cc \u0639\u0632\u06cc\u0632 \u0645\u0639\u0644\u0648\u0645\u06cc"
    ],
    "name:und_x_variant":[
        "\u2018Aliz",
        "\u062d\u0627\u062c\u06cc \u0639\u0632\u06cc\u0632 \u0645\u0639\u0644\u0648\u0645\u06cc"
    ],
    "wof:name":"Hajji `Aziz-e Ma`lumi",
    "wof:placetype":"locality"
},
  "geometry": {"coordinates":[48.65736,30.63658],"type":"Point"}
}