{
  "type": "Feature",
  "properties": {
    "gn:admin1_code":"15",
    "gn:asciiname":"Boneh-ye Sukhteh",
    "gn:country_code":"IR",
    "gn:dem":150,
    "gn:feature_class":"P",
    "gn:feature_code":"PPL",
    "gn:name":"Boneh-ye S\u016bkhteh",
    "gn:population":0,
    "gn:timezone":"Asia/Tehran",
    "iso:country":"IR",
    "name:fas_x_preferred":[
        "Boneh-ye S\u016bkhteh"
    ],
    "name:fas_x_variant":[
        "\u0628\u0646\u0647 \u0633\u0648\u062e\u062a\u0647"
    ],
    "name:und_x_variant":[
        "Sookhteh"
    ],
    "wof:name":"Boneh-ye Sukhteh",
    "wof:placetype":"locality"
},
  "geometry": {"coordinates":[49.58371,31.23789],"type":"Point"}
}