{
  "type": "Feature",
  "properties": {
    "gn:admin1_code":"37.0",
    "gn:asciiname":"Mazra`eh-ye Katul",
    "gn:country_code":"IR",
    "gn:dem":90,
    "gn:feature_class":"P",
    "gn:feature_code":"PPL",
    "gn:name":"Mazra\u2018eh-ye Kat\u016bl",
    "gn:population":0,
    "gn:timezone":"Asia/Tehran",
    "iso:country":"IR",
    "name:fas_x_preferred":[
        "Mazra\u2018eh Kat\u016bl"
    ],
    "name:fas_x_variant":[
        "\u0645\u0632\u0631\u0639\u0647",
        "Mazra\u2018eh-ye Kat\u016bl",
        "Mazra\u2018eh",
        "\u0645\u0632\u0631\u0639\u0647 \u06a9\u062a\u0648\u0644"
    ],
    "wof:name":"Mazra`eh-ye Katul",
    "wof:placetype":"locality"
},
  "geometry": {"coordinates":[54.85626,36.95426],"type":"Point"}
}