{
  "type": "Feature",
  "properties": {
    "gn:admin1_code":"9",
    "gn:asciiname":"Darani-ye `Olya",
    "gn:country_code":"IR",
    "gn:dem":1871,
    "gn:feature_class":"P",
    "gn:feature_code":"PPL",
    "gn:name":"D\u0101r\u0101n\u012b-ye \u2018Oly\u0101",
    "gn:population":0,
    "gn:timezone":"Asia/Tehran",
    "iso:country":"IR",
    "name:fas_x_preferred":[
        "\u062f\u0627\u0631\u0627\u0646\u0626 \u0639\u064f\u0644\u064a\u0627"
    ],
    "name:fas_x_variant":[
        "\u062f\u0627\u0631\u0627\u0646\u06cc",
        "\u062f\u0627\u0631\u0627\u0646\u0626 \u0628\u0627\u0644\u0627",
        "D\u0101r\u0101n\u012b-ye \u2018Oly\u0101",
        "\u062f\u0627\u0631\u0627\u0646\u06cc \u0639\u0644\u06cc\u0627"
    ],
    "name:und_x_variant":[
        "D\u0101r\u0101n\u012b",
        "D\u0101r\u0101n\u012b-ye B\u0101l\u0101",
        "\u062f\u0627\u0631\u0627\u0646\u06cc \u0639\u0644\u06cc\u0627"
    ],
    "wof:name":"Darani-ye `Olya",
    "wof:placetype":"locality"
},
  "geometry": {"coordinates":[48.43091,34.50238],"type":"Point"}
}