{
  "type": "Feature",
  "properties": {
    "gn:admin1_code":"11",
    "gn:asciiname":"Qal`eh-ye Gushki",
    "gn:country_code":"IR",
    "gn:dem":41,
    "gn:feature_class":"P",
    "gn:feature_code":"PPL",
    "gn:name":"Qal\u2018eh-ye G\u016bshk\u012b",
    "gn:population":0,
    "gn:timezone":"Asia/Tehran",
    "iso:country":"IR",
    "name:fas_x_preferred":[
        "\u06af\u0648\u0634\u0643\u06cc"
    ],
    "name:fas_x_variant":[
        "\u0642\u0644\u0639\u0647 \u06af\u0648\u0634\u0643\u06cc",
        "G\u016bshk\u012b",
        "Qal\u2018eh-ye G\u016bshk\u012b"
    ],
    "name:und_x_variant":[
        "Karg\u016bshk\u012b",
        "Qal\u2018eh-ye G\u016bsh\u012b",
        "Goshki",
        "Qal\u2018eh-ye K\u016bshk\u012b"
    ],
    "wof:name":"Qal`eh-ye Gushki",
    "wof:placetype":"locality"
},
  "geometry": {"coordinates":[57.30298000000001,26.35769],"type":"Point"}
}