{
  "type": "Feature",
  "properties": {
    "gn:admin1_code":"8",
    "gn:asciiname":"Shaneh Deh",
    "gn:country_code":"IR",
    "gn:dem":197,
    "gn:feature_class":"P",
    "gn:feature_code":"PPL",
    "gn:name":"Sh\u0101neh Deh",
    "gn:population":0,
    "gn:timezone":"Asia/Tehran",
    "iso:country":"IR",
    "name:fas_x_preferred":[
        "\u0634\u0627\u0646\u0647 \u062f\u0647"
    ],
    "name:fas_x_variant":[
        "Sh\u0101neh Deh"
    ],
    "wof:name":"Shaneh Deh",
    "wof:placetype":"locality"
},
  "geometry": {"coordinates":[49.10838,37.29622],"type":"Point"}
}