{
  "type": "Feature",
  "properties": {
    "gn:admin1_code":"37",
    "gn:asciiname":"Zangian",
    "gn:country_code":"IR",
    "gn:dem":54,
    "gn:feature_class":"P",
    "gn:feature_code":"PPL",
    "gn:name":"Zang\u012b\u0101n",
    "gn:population":0,
    "gn:timezone":"Asia/Tehran",
    "iso:country":"IR",
    "name:fas_x_preferred":[
        "\u0632\u064e\u0646\u06af\u0650\u0646\u0650\u0647 \u0645\u064e\u062d\u064e\u0644\u0650\u0651\u0647"
    ],
    "name:fas_x_variant":[
        "Zang\u012b\u0101n",
        "\u0632\u0646\u06af\u064a\u0627\u0646"
    ],
    "name:und_x_variant":[
        "Zangiyan",
        "Zangeneh Ma\u1e29alleh",
        "Zang\u012b Ma\u1e29all\u0113h",
        "\u0632\u0646\u06af\u064a\u0627\u0646"
    ],
    "wof:name":"Zangian",
    "wof:placetype":"locality"
},
  "geometry": {"coordinates":[54.40068,36.8561],"type":"Point"}
}