{
  "type": "Feature",
  "properties": {
    "gn:admin1_code":"13",
    "gn:asciiname":"Darakhshandeh",
    "gn:country_code":"IR",
    "gn:dem":686,
    "gn:feature_class":"P",
    "gn:feature_code":"PPL",
    "gn:name":"Darakhshandeh",
    "gn:population":0,
    "gn:timezone":"Asia/Tehran",
    "iso:country":"IR",
    "name:fas_x_preferred":[
        "\u062f\u0631\u062e\u0634\u0646\u062f\u0647"
    ],
    "name:fas_x_variant":[
        "Derakhshandeh Gal\u016bz\u012b",
        "Gal\u016bzy\u0101",
        "Gal\u016bz\u012b P\u0101sh\u0101",
        "Gal\u016bzey\u0101",
        "Gol\u016bz\u012b\u0101"
    ],
    "name:und_x_variant":[
        "Darakhshandeh"
    ],
    "wof:name":"Darakhshandeh",
    "wof:placetype":"locality"
},
  "geometry": {"coordinates":[45.89909,34.33381],"type":"Point"}
}