{
  "type": "Feature",
  "properties": {
    "gn:admin1_code":"32",
    "gn:asciiname":"Kalkhvoran-e Viyand",
    "gn:country_code":"IR",
    "gn:dem":1584,
    "gn:feature_class":"P",
    "gn:feature_code":"PPL",
    "gn:name":"Kalkhvor\u0101n-e V\u012byand",
    "gn:population":0,
    "gn:timezone":"Asia/Tehran",
    "iso:country":"IR",
    "name:ceb_x_preferred":[
        "Kalkhvor\u0101n-e V\u012byand"
    ],
    "name:fas_x_preferred":[
        "\u0643\u064e\u0644\u062e\u0648\u0631\u0627\u0646\u0650 \u0648\u064a\u0627\u0646\u062f"
    ],
    "name:fas_x_variant":[
        "\u0643\u0644\u062e\u0648\u0631\u0627\u0646 \u0648\u064a\u0646\u062f",
        "Kalkh\u016br\u0101n-e V\u012b\u0101nd",
        "Kalkhvor\u0101n-e V\u012byand",
        "\u06a9\u0644\u062e\u0648\u0631\u0627\u0646 \u0648\u06cc\u0646\u062f"
    ],
    "name:msa_x_preferred":[
        "Kalkhvoran-e Viyand"
    ],
    "name:mzn_x_preferred":[
        "\u06a9\u0644\u062e\u0648\u0631\u0627\u0646\u200c\u0648\u06cc\u0646\u062f"
    ],
    "name:swe_x_preferred":[
        "Kalkhvor\u0101n-e V\u012byand"
    ],
    "name:und_x_variant":[
        "Kalkh\u016br\u0101n-e V\u012byand"
    ],
    "wof:name":"Kalkhvoran-e Viyand",
    "wof:placetype":"locality"
},
  "geometry": {"coordinates":[48.0851,38.1194],"type":"Point"}
}