{
  "type": "Feature",
  "properties": {
    "gn:admin1_code":"8",
    "gn:asciiname":"Ahangar Mahalleh",
    "gn:country_code":"IR",
    "gn:dem":-8,
    "gn:feature_class":"P",
    "gn:feature_code":"PPL",
    "gn:name":"\u0100hangar Ma\u1e29alleh",
    "gn:population":0,
    "gn:timezone":"Asia/Tehran",
    "iso:country":"IR",
    "name:fas_x_preferred":[
        "\u0622\u0647\u0646\u06af\u0631 \u0645\u062d\u0644\u0647"
    ],
    "name:fas_x_variant":[
        "\u0100hangar Ma\u1e29alleh",
        "\u0622\u0647\u0646\u06af\u0631\u0645\u062d\u0644\u0647"
    ],
    "name:msa_x_preferred":[
        "Ahangar Mahalleh"
    ],
    "name:ukr_x_preferred":[
        "\u0410\u0433\u0430\u043d\u0491\u0430\u0440-\u041c\u0430\u0445\u0430\u043b\u0435"
    ],
    "wof:name":"Ahangar Mahalleh",
    "wof:placetype":"locality"
},
  "geometry": {"coordinates":[49.05638,37.63736],"type":"Point"}
}