{
  "type": "Feature",
  "properties": {
    "gn:admin1_code":"36",
    "gn:asciiname":"Mir Akhowr",
    "gn:country_code":"IR",
    "gn:dem":1292,
    "gn:feature_class":"P",
    "gn:feature_code":"PPL",
    "gn:name":"M\u012br \u0100khowr",
    "gn:population":0,
    "gn:timezone":"Asia/Tehran",
    "iso:country":"IR",
    "name:fas_x_preferred":[
        "\u0645\u06cc\u0631 \u0622\u062e\u0648\u0631"
    ],
    "name:fas_x_variant":[
        "M\u012br\u0101khor",
        "M\u012br \u0100khvor"
    ],
    "name:und_x_variant":[
        "M\u012br \u0100khowr"
    ],
    "wof:name":"Mir Akhowr",
    "wof:placetype":"locality"
},
  "geometry": {"coordinates":[47.71813,36.71768],"type":"Point"}
}