{
  "type": "Feature",
  "properties": {
    "gn:admin1_code":"5",
    "gn:asciiname":"Mazeh Kharideh",
    "gn:country_code":"IR",
    "gn:dem":1760,
    "gn:feature_class":"P",
    "gn:feature_code":"PPL",
    "gn:name":"M\u0101zeh Khar\u012bdeh",
    "gn:population":0,
    "gn:timezone":"Asia/Tehran",
    "iso:country":"IR",
    "name:ara_x_preferred":[
        "\u0645\u0627\u0632\u0629 \u062e\u0631\u064a\u062f\u0629"
    ],
    "name:ceb_x_preferred":[
        "M\u0101zeh Khar\u012bdeh"
    ],
    "name:fas_x_preferred":[
        "M\u0101zeh Khar\u012bdeh"
    ],
    "name:fas_x_variant":[
        "\u0645\u0627\u0632\u0647 \u062e\u0631\u064a\u062f\u0647",
        "\u0645\u0627\u0632\u0647 \u062e\u0631\u06cc\u062f\u0647"
    ],
    "name:swe_x_preferred":[
        "M\u0101zeh Khar\u012bdeh"
    ],
    "name:und_x_variant":[
        "\u0645\u0627\u0632\u0647 \u062e\u0631\u064a\u062f\u0647"
    ],
    "wof:name":"Mazeh Kharideh",
    "wof:placetype":"locality"
},
  "geometry": {"coordinates":[51.55528,30.6384],"type":"Point"}
}