{
  "type": "Feature",
  "properties": {
    "gn:admin1_code":"3.0",
    "gn:asciiname":"Li Li Gar",
    "gn:country_code":"IR",
    "gn:dem":1132,
    "gn:feature_class":"P",
    "gn:feature_code":"PPLL",
    "gn:name":"L\u012b L\u012b Gar",
    "gn:population":0,
    "gn:timezone":"Asia/Tehran",
    "iso:country":"IR",
    "name:fas_x_preferred":[
        "\u0644\u06cc \u0644\u06cc \u06af\u0631"
    ],
    "name:und_x_variant":[
        "L\u012b L\u012b Gar"
    ],
    "wof:name":"Li Li Gar",
    "wof:placetype":"locality"
},
  "geometry": {"coordinates":[50.64086,31.62675],"type":"Point"}
}