{
  "type": "Feature",
  "properties": {
    "gn:admin1_code":"7.0",
    "gn:asciiname":"Cherr Ab Qalandari-ye Sofla",
    "gn:country_code":"IR",
    "gn:dem":2124,
    "gn:feature_class":"P",
    "gn:feature_code":"PPL",
    "gn:name":"Cherr \u0100b Qalandar\u012b-ye Sofl\u00e1",
    "gn:population":0,
    "gn:timezone":"Asia/Tehran",
    "iso:country":"IR",
    "name:fas_x_preferred":[
        "\u0686\u0631\u0651 \u0622\u0628 \u0642\u0644\u0646\u062f\u0631\u06cc \u0633\u0641\u0644\u06cc"
    ],
    "name:fas_x_variant":[
        "Cherr \u0100b Qalandar\u012b-ye Sofl\u00e1"
    ],
    "wof:name":"Cherr Ab Qalandari-ye Sofla",
    "wof:placetype":"locality"
},
  "geometry": {"coordinates":[52.212,29.7118],"type":"Point"}
}