{
  "type": "Feature",
  "properties": {
    "gn:admin1_code":"4.0",
    "gn:asciiname":"Kambel-e Buheyr",
    "gn:country_code":"IR",
    "gn:dem":19,
    "gn:feature_class":"P",
    "gn:feature_code":"PPL",
    "gn:name":"Kambel-e B\u016bheyr",
    "gn:population":0,
    "gn:timezone":"Asia/Tehran",
    "iso:country":"IR",
    "name:fas_x_preferred":[
        "Kambel-e B\u016bheyr"
    ],
    "wof:name":"Kambel-e Buheyr",
    "wof:placetype":"locality"
},
  "geometry": {"coordinates":[60.90083000000001,25.41444],"type":"Point"}
}