{
  "type": "Feature",
  "properties": {
    "gn:admin1_code":"35.0",
    "gn:asciiname":"Bur Kheyl",
    "gn:country_code":"IR",
    "gn:dem":72,
    "gn:feature_class":"P",
    "gn:feature_code":"PPL",
    "gn:name":"B\u016br Kheyl",
    "gn:population":0,
    "gn:timezone":"Asia/Tehran",
    "iso:country":"IR",
    "name:fas_x_preferred":[
        "\u0628\u0648\u0631 \u062e\u0650\u064a\u0644"
    ],
    "name:fas_x_variant":[
        "B\u016br Kheyl"
    ],
    "wof:name":"Bur Kheyl",
    "wof:placetype":"locality"
},
  "geometry": {"coordinates":[52.95,36.48333],"type":"Point"}
}