{
  "type": "Feature",
  "properties": {
    "gn:admin1_code":"10",
    "gn:asciiname":"Cheghabol",
    "gn:country_code":"IR",
    "gn:dem":458,
    "gn:feature_class":"P",
    "gn:feature_code":"PPL",
    "gn:name":"Chegh\u0101bol",
    "gn:population":0,
    "gn:timezone":"Asia/Tehran",
    "iso:country":"IR",
    "name:fas_x_preferred":[
        "\u0686\u063a\u0627\u0628\u0644"
    ],
    "name:fas_x_variant":[
        "Chegh\u0101bol"
    ],
    "wof:name":"Cheghabol",
    "wof:placetype":"locality"
},
  "geometry": {"coordinates":[47.6996,32.6589],"type":"Point"}
}