{
  "type": "Feature",
  "properties": {
    "gn:admin1_code":"36.0",
    "gn:asciiname":"Khalifeh",
    "gn:country_code":"IR",
    "gn:dem":1514,
    "gn:feature_class":"P",
    "gn:feature_code":"PPL",
    "gn:name":"Khal\u012bfeh",
    "gn:population":0,
    "gn:timezone":"Asia/Tehran",
    "iso:country":"IR",
    "name:deu_x_preferred":[
        "Khalifeh"
    ],
    "name:fas_x_preferred":[
        "\u062e\u0644\u06cc\u0641\u0647"
    ],
    "name:fas_x_variant":[
        "Khal\u012bfeh",
        "\u062e\u0644\u06cc\u0641\u0647 \u0644\u0648"
    ],
    "name:und_x_variant":[
        "Khal\u012bfehl\u016b"
    ],
    "wof:name":"Khalifeh",
    "wof:placetype":"locality"
},
  "geometry": {"coordinates":[47.9929,35.99499],"type":"Point"}
}