{
  "type": "Feature",
  "properties": {
    "gn:admin1_code":"13",
    "gn:asciiname":"Sar Fizul",
    "gn:country_code":"IR",
    "gn:dem":1480,
    "gn:feature_class":"P",
    "gn:feature_code":"PPL",
    "gn:name":"Sar F\u012bz\u016bl",
    "gn:population":0,
    "gn:timezone":"Asia/Tehran",
    "iso:country":"IR",
    "name:fas_x_preferred":[
        "Sar F\u012bz\u016bl"
    ],
    "wof:name":"Sar Fizul",
    "wof:placetype":"locality"
},
  "geometry": {"coordinates":[47.08389,34.135],"type":"Point"}
}