{
  "type": "Feature",
  "properties": {
    "gn:admin1_code":"41",
    "gn:asciiname":"Soltanabad",
    "gn:country_code":"IR",
    "gn:dem":1859,
    "gn:feature_class":"P",
    "gn:feature_code":"PPLF",
    "gn:name":"Sol\u0163\u0101n\u0101b\u0101d",
    "gn:population":0,
    "gn:timezone":"Asia/Tehran",
    "iso:country":"IR",
    "name:ara_x_preferred":[
        "\u0633\u0644\u0637\u0627\u0646 \u0623\u0628\u0627\u062f"
    ],
    "name:aze_x_preferred":[
        "Soltanabad"
    ],
    "name:cat_x_preferred":[
        "Soltanabad"
    ],
    "name:ceb_x_preferred":[
        "Soltanabad"
    ],
    "name:fas_x_preferred":[
        "\u0633\u0644\u0637\u0627\u0646 \u0622\u0628\u0627\u062f"
    ],
    "name:fas_x_variant":[
        "Sol\u0163\u0101n\u0101b\u0101d",
        "\u0633\u0644\u0637\u0627\u0646\u200c\u0622\u0628\u0627\u062f"
    ],
    "name:mzn_x_preferred":[
        "\u0633\u0644\u0637\u0627\u0646\u200c\u0622\u0628\u0627\u062f"
    ],
    "name:swe_x_preferred":[
        "Soltanabad"
    ],
    "name:und_x_variant":[
        "Sol\u0163\u0101n\u0101b\u0101d-e Behand\u0101n",
        "Soltan Abad Behandan"
    ],
    "wof:name":"Soltanabad",
    "wof:placetype":"locality"
},
  "geometry": {"coordinates":[59.77168,31.79032],"type":"Point"}
}