{
  "type": "Feature",
  "properties": {
    "gn:admin1_code":"33",
    "gn:asciiname":"Chetab-e Aqa Karim",
    "gn:country_code":"IR",
    "gn:dem":1095,
    "gn:feature_class":"P",
    "gn:feature_code":"PPL",
    "gn:name":"Chet\u0101b-e \u0100q\u0101 Kar\u012bm",
    "gn:population":0,
    "gn:timezone":"Asia/Tehran",
    "iso:country":"IR",
    "name:fas_x_preferred":[
        "\u0686\u062a\u0627\u0628 \u0622\u0642\u0627 \u06a9\u0631\u06cc\u0645"
    ],
    "name:fas_x_variant":[
        "Chet\u0101b-e \u0100q\u0101kar\u012bm",
        "Chet\u0101b-e \u0100q\u0101 Kar\u012bm"
    ],
    "wof:name":"Chetab-e Aqa Karim",
    "wof:placetype":"locality"
},
  "geometry": {"coordinates":[47.8418,37.5109],"type":"Point"}
}