{
  "type": "Feature",
  "properties": {
    "gn:admin1_code":"15.0",
    "gn:asciiname":"`Add-e Sovadi",
    "gn:country_code":"IR",
    "gn:dem":25,
    "gn:feature_class":"P",
    "gn:feature_code":"PPL",
    "gn:name":"\u2018Add-e Sov\u0101d\u012b",
    "gn:population":0,
    "gn:timezone":"Asia/Tehran",
    "iso:country":"IR",
    "name:fas_x_preferred":[
        "\u0639\u062f \u0633\u0648\u0627\u062f\u06cc"
    ],
    "name:fas_x_variant":[
        "\u2018Edd-e Sov\u0101d\u012b",
        "\u2018Add-e Sov\u0101d\u012b"
    ],
    "name:und_x_variant":[
        "\u2018Ad-e Sav\u0101ri",
        "\u2018Add-e Sav\u0101d\u012b",
        "\u2018Ad-e Sav\u0101d\u012b"
    ],
    "wof:name":"`Add-e Sovadi",
    "wof:placetype":"locality"
},
  "geometry": {"coordinates":[49.43237,30.80685],"type":"Point"}
}