{
  "type": "Feature",
  "properties": {
    "gn:admin1_code":"15",
    "gn:asciiname":"Kushk Khalaf-e Sofla",
    "gn:country_code":"IR",
    "gn:dem":304,
    "gn:feature_class":"P",
    "gn:feature_code":"PPL",
    "gn:name":"K\u016bshk Khalaf-e Sofl\u00e1",
    "gn:population":0,
    "gn:timezone":"Asia/Tehran",
    "iso:country":"IR",
    "name:fas_x_preferred":[
        "\u06a9\u0648\u0634\u06a9 \u062e\u0644\u0641 \u0633\u0641\u0644\u06cc"
    ],
    "name:fas_x_variant":[
        "K\u016bshk Khalaf-e Sofl\u00e1"
    ],
    "name:und_x_variant":[
        "Kooshk Khalaf",
        "K\u016bshk Khalaf"
    ],
    "wof:name":"Kushk Khalaf-e Sofla",
    "wof:placetype":"locality"
},
  "geometry": {"coordinates":[49.00333,32.15866],"type":"Point"}
}