{
  "type": "Feature",
  "properties": {
    "gn:admin1_code":"11",
    "gn:asciiname":"Sarsomat",
    "gn:country_code":"IR",
    "gn:dem":49,
    "gn:feature_class":"P",
    "gn:feature_code":"PPL",
    "gn:name":"Sarsom\u0101t",
    "gn:population":0,
    "gn:timezone":"Asia/Tehran",
    "iso:country":"IR",
    "name:ara_x_preferred":[
        "\u0633\u0631\u0633\u0645\u0627\u062f"
    ],
    "name:ceb_x_preferred":[
        "Sarsom\u0101t"
    ],
    "name:fas_x_preferred":[
        "\u0633\u0631 \u0633\u0645\u0627\u062a"
    ],
    "name:fas_x_variant":[
        "Sarsom\u0101t",
        "\u0633\u0631 \u0635\u0645\u062f",
        "\u0633\u0631\u0633\u0645\u0627\u062f"
    ],
    "name:msa_x_preferred":[
        "Sar Samad"
    ],
    "name:swe_x_preferred":[
        "Sarsom\u0101t"
    ],
    "name:und_x_variant":[
        "Sar \u015eamad"
    ],
    "wof:name":"Sarsomat",
    "wof:placetype":"locality"
},
  "geometry": {"coordinates":[56.82084,27.47856],"type":"Point"}
}