{
  "type": "Feature",
  "properties": {
    "gn:admin1_code":"10",
    "gn:asciiname":"Mazhin-e `Olya",
    "gn:country_code":"IR",
    "gn:dem":1202,
    "gn:feature_class":"P",
    "gn:feature_code":"PPL",
    "gn:name":"M\u0101zh\u012bn-e \u2018Oly\u0101",
    "gn:population":0,
    "gn:timezone":"Asia/Tehran",
    "iso:country":"IR",
    "name:ara_x_preferred":[
        "\u0645\u0627\u062c\u064a\u0646"
    ],
    "name:fas_x_preferred":[
        "\u0645\u0627\u0698\u06cc\u0646 \u0639\u0644\u06cc\u0627"
    ],
    "name:fas_x_variant":[
        "M\u0101zh\u012bn-e Sofl\u00e1",
        "M\u0101zh\u012bn-e \u2018Oly\u0101",
        "\u0645\u0627\u0698\u06cc\u0646"
    ],
    "name:msa_x_preferred":[
        "Mazhin"
    ],
    "name:und_x_variant":[
        "M\u0101jin",
        "M\u0101zh\u012bn"
    ],
    "wof:name":"Mazhin-e `Olya",
    "wof:placetype":"locality"
},
  "geometry": {"coordinates":[46.26371,33.81504],"type":"Point"}
}