{
  "type": "Feature",
  "properties": {
    "gn:admin1_code":"15.0",
    "gn:asciiname":"Ab Garmak",
    "gn:country_code":"IR",
    "gn:dem":834,
    "gn:feature_class":"P",
    "gn:feature_code":"PPL",
    "gn:name":"\u0100b Garmak",
    "gn:population":0,
    "gn:timezone":"Asia/Tehran",
    "iso:country":"IR",
    "name:fas_x_preferred":[
        "\u0100bgarmak-e B\u0101l\u0101"
    ],
    "name:fas_x_variant":[
        "\u0622\u0628\u06af\u0631\u0645\u06a9 \u0628\u0627\u0644\u0627",
        "\u0622\u0628 \u06af\u0631\u0645\u06a9"
    ],
    "name:und_x_variant":[
        "\u0622\u0628\u06af\u0631\u0645\u06a9 \u0628\u0627\u0644\u0627",
        "\u0100b Garmak"
    ],
    "wof:name":"Ab Garmak",
    "wof:placetype":"locality"
},
  "geometry": {"coordinates":[49.96342,31.29216],"type":"Point"}
}