{
  "type": "Feature",
  "properties": {
    "gn:admin1_code":"11",
    "gn:asciiname":"Lavardin",
    "gn:country_code":"IR",
    "gn:dem":243,
    "gn:feature_class":"P",
    "gn:feature_code":"PPL",
    "gn:name":"L\u0101vard\u012bn",
    "gn:population":0,
    "gn:timezone":"Asia/Tehran",
    "iso:country":"IR",
    "name:ceb_x_preferred":[
        "Lavardin"
    ],
    "name:deu_x_preferred":[
        "Lavardin"
    ],
    "name:fas_x_preferred":[
        "\u062f\u064a\u0646"
    ],
    "name:fas_x_variant":[
        "D\u012bn",
        "L\u0101vard\u012bn",
        "\u0644\u0627\u0648\u0631\u062f\u06cc\u0646"
    ],
    "name:fra_x_preferred":[
        "Lavardin"
    ],
    "name:ita_x_preferred":[
        "Lavardin"
    ],
    "name:nds_x_preferred":[
        "Lavardin"
    ],
    "name:nld_x_preferred":[
        "Lavardin"
    ],
    "name:oci_x_preferred":[
        "Lavardin"
    ],
    "name:pol_x_preferred":[
        "Lavardin"
    ],
    "name:por_x_preferred":[
        "Lavardin"
    ],
    "name:slk_x_preferred":[
        "Lavardin"
    ],
    "name:spa_x_preferred":[
        "Lavardin"
    ],
    "name:swe_x_preferred":[
        "Lavardin"
    ],
    "name:ukr_x_preferred":[
        "\u041b\u0430\u0432\u0430\u0440\u0434\u0435\u043d"
    ],
    "wof:name":"Lavardin",
    "wof:placetype":"locality"
},
  "geometry": {"coordinates":[54.56884,26.95772],"type":"Point"}
}