{
  "type": "Feature",
  "properties": {
    "gn:admin1_code":"35",
    "gn:asciiname":"Mofti Kola",
    "gn:country_code":"IR",
    "gn:dem":16,
    "gn:feature_class":"P",
    "gn:feature_code":"PPL",
    "gn:name":"Moft\u012b Kol\u0101",
    "gn:population":0,
    "gn:timezone":"Asia/Tehran",
    "iso:country":"IR",
    "name:fas_x_preferred":[
        "\u0645\u064f\u0641\u062a\u06cc \u0643\u064f\u0644\u0627"
    ],
    "name:fas_x_variant":[
        "Moft\u012b Kol\u0101"
    ],
    "wof:name":"Mofti Kola",
    "wof:placetype":"locality"
},
  "geometry": {"coordinates":[53.01667,36.56667],"type":"Point"}
}