{
  "type": "Feature",
  "properties": {
    "gn:admin1_code":"29",
    "gn:asciiname":"Kuchendar",
    "gn:cc2":"IR",
    "gn:country_code":"IR",
    "gn:dem":309,
    "gn:feature_class":"P",
    "gn:feature_code":"PPL",
    "gn:name":"K\u016bchendar",
    "gn:population":0,
    "gn:timezone":"Asia/Tehran",
    "iso:country":"IR",
    "name:fas_x_preferred":[
        "K\u016bchendar"
    ],
    "name:und_x_variant":[
        "K\u016bshmandar",
        "K\u016bchandar"
    ],
    "wof:name":"Kuchendar",
    "wof:placetype":"locality"
},
  "geometry": {"coordinates":[57.33028,27.57778],"type":"Point"}
}