{
  "type": "Feature",
  "properties": {
    "gn:admin1_code":"16",
    "gn:asciiname":"Palangan",
    "gn:country_code":"IR",
    "gn:dem":992,
    "gn:feature_class":"P",
    "gn:feature_code":"PPL",
    "gn:name":"Palang\u0101n",
    "gn:population":0,
    "gn:timezone":"Asia/Tehran",
    "iso:country":"IR",
    "name:ceb_x_preferred":[
        "Palangan"
    ],
    "name:fas_x_preferred":[
        "\u067e\u064e\u062a\u064e\u0643\u0627\u0646"
    ],
    "name:fas_x_variant":[
        "\u062a\u064e\u0646\u06af\u0627\u0646",
        "\u067e\u064e\u062a\u064e\u06af\u0627\u0646",
        "\u067e\u0644\u0646\u06af\u0627\u0646",
        "Palang\u0101n"
    ],
    "name:nld_x_preferred":[
        "Palangan"
    ],
    "name:swe_x_preferred":[
        "Palangan"
    ],
    "name:und_x_variant":[
        "Tang\u0101n",
        "Patag\u0101n",
        "Patak\u0101n"
    ],
    "wof:name":"Palangan",
    "wof:placetype":"locality"
},
  "geometry": {"coordinates":[46.60336,35.06764],"type":"Point"}
}