{
  "type": "Feature",
  "properties": {
    "gn:admin1_code":"13",
    "gn:asciiname":"`Ali Yar",
    "gn:country_code":"IR",
    "gn:dem":592,
    "gn:feature_class":"P",
    "gn:feature_code":"PPL",
    "gn:name":"\u2018Al\u012b Y\u0101r",
    "gn:population":0,
    "gn:timezone":"Asia/Tehran",
    "iso:country":"IR",
    "name:fas_x_preferred":[
        "\u0639\u0644\u064a \u064a\u0627\u0631"
    ],
    "name:fas_x_variant":[
        "\u2018Al\u012b Y\u0101rk\u012b",
        "\u2018Al\u012b Y\u0101r"
    ],
    "wof:name":"`Ali Yar",
    "wof:placetype":"locality"
},
  "geometry": {"coordinates":[45.8274,34.6937],"type":"Point"}
}