{
  "type": "Feature",
  "properties": {
    "gn:admin1_code":"40.0",
    "gn:asciiname":"Asadabad-e `Olya",
    "gn:country_code":"IR",
    "gn:dem":1505,
    "gn:feature_class":"P",
    "gn:feature_code":"PPL",
    "gn:name":"Asad\u0101b\u0101d-e \u2018Oly\u0101",
    "gn:population":0,
    "gn:timezone":"Asia/Tehran",
    "iso:country":"IR",
    "name:fas_x_preferred":[
        "\u0627\u0633\u062f\u0627\u0628\u0627\u062f \u0628\u0627\u0644\u0627"
    ],
    "name:fas_x_variant":[
        "\u0627\u064e\u0633\u064e\u062f\u0627\u0628\u0627\u062f\u0650 \u0633\u064f\u0641\u0644\u064e",
        "\u0627\u0633\u062f \u0622\u0628\u0627\u062f \u0639\u0644\u06cc\u0627",
        "\u0627\u064e\u0633\u064e\u062f\u0627\u0628\u0627\u062f\u0650 \u067e\u0627\u0626\u064a\u0646",
        "\u0627\u064e\u0633\u064e\u062f \u0622\u0628\u0627\u062f",
        "Asad\u0101b\u0101d-e B\u0101l\u0101",
        "Asad\u0101b\u0101d-e \u2018Oly\u0101"
    ],
    "name:und_x_variant":[
        "Asad\u0101b\u0101d",
        "Asad\u0101b\u0101d-e Sofla",
        "Asad\u0101b\u0101d Kuchik",
        "Asad\u0101b\u0101d-e P\u0101\u2019\u012bn"
    ],
    "wof:name":"Asadabad-e `Olya",
    "wof:placetype":"locality"
},
  "geometry": {"coordinates":[53.3077,31.0602],"type":"Point"}
}