{
  "type": "Feature",
  "properties": {
    "gn:admin1_code":"1",
    "gn:asciiname":"Ali",
    "gn:country_code":"IR",
    "gn:dem":1908,
    "gn:feature_class":"P",
    "gn:feature_code":"PPL",
    "gn:name":"\u0100l\u012b",
    "gn:population":0,
    "gn:timezone":"Asia/Tehran",
    "iso:country":"IR",
    "name:fas_x_preferred":[
        "\u0627\u0644\u0651\u0648"
    ],
    "name:fas_x_variant":[
        "\u0100l\u012b",
        "All\u016b",
        "\u0622\u0644\u06cc"
    ],
    "wof:name":"Ali",
    "wof:placetype":"locality"
},
  "geometry": {"coordinates":[46.70052,36.93776],"type":"Point"}
}