{
  "type": "Feature",
  "properties": {
    "gn:admin1_code":"5",
    "gn:asciiname":"Nazarabad",
    "gn:country_code":"IR",
    "gn:dem":1460,
    "gn:feature_class":"P",
    "gn:feature_code":"PPL",
    "gn:name":"Naz\u0327ar\u0101b\u0101d",
    "gn:population":0,
    "gn:timezone":"Asia/Tehran",
    "iso:country":"IR",
    "name:fas_x_preferred":[
        "Naz\u0327ar\u0101b\u0101d"
    ],
    "name:fas_x_variant":[
        "\u0646\u0638\u0631 \u0622\u0628\u0627\u062f"
    ],
    "name:und_x_variant":[
        "\u0646\u0638\u0631 \u0622\u0628\u0627\u062f"
    ],
    "wof:name":"Nazarabad",
    "wof:placetype":"locality"
},
  "geometry": {"coordinates":[50.91184000000001,30.94282],"type":"Point"}
}