{
  "type": "Feature",
  "properties": {
    "gn:admin1_code":"23",
    "gn:asciiname":"Zurandul",
    "gn:country_code":"IR",
    "gn:dem":976,
    "gn:feature_class":"P",
    "gn:feature_code":"PPL",
    "gn:name":"Z\u016br\u0101nd\u016bl",
    "gn:population":0,
    "gn:timezone":"Asia/Tehran",
    "iso:country":"IR",
    "name:ara_x_preferred":[
        "\u0632\u0648\u0631\u0627\u0646\u062f\u0648\u0644"
    ],
    "name:ceb_x_preferred":[
        "Z\u016br\u0101nd\u016bl"
    ],
    "name:fas_x_preferred":[
        "\u0632\u0648\u0631\u0627\u0646\u062f\u0648\u0644"
    ],
    "name:fas_x_variant":[
        "Z\u016br\u0101nd\u016bl"
    ],
    "name:swe_x_preferred":[
        "Z\u016br\u0101nd\u016bl"
    ],
    "wof:name":"Zurandul",
    "wof:placetype":"locality"
},
  "geometry": {"coordinates":[47.99091,33.48968],"type":"Point"}
}