{
  "type": "Feature",
  "properties": {
    "gn:admin1_code":"23",
    "gn:asciiname":"Gandab",
    "gn:country_code":"IR",
    "gn:dem":1803,
    "gn:feature_class":"P",
    "gn:feature_code":"PPL",
    "gn:name":"Gand\u0101b",
    "gn:population":0,
    "gn:timezone":"Asia/Tehran",
    "iso:country":"IR",
    "name:ceb_x_preferred":[
        "Gandab"
    ],
    "name:fas_x_preferred":[
        "\u06af\u0646\u062c\u0627\u0628"
    ],
    "name:fas_x_variant":[
        "Gand \u0100b",
        "Ganj\u0101b",
        "\u06af\u0646\u062f\u0627\u0628"
    ],
    "name:mzn_x_preferred":[
        "\u06af\u0646\u062f\u0627\u0628"
    ],
    "name:swe_x_preferred":[
        "Gandab"
    ],
    "name:und_x_variant":[
        "Gan\u0101u",
        "Gan\u0101v",
        "Gand\u0101b"
    ],
    "wof:name":"Gandab",
    "wof:placetype":"locality"
},
  "geometry": {"coordinates":[48.7509,33.9776],"type":"Point"}
}