{
  "type": "Feature",
  "properties": {
    "gn:admin1_code":"5.0",
    "gn:asciiname":"Pachad-e Chirbiun",
    "gn:country_code":"IR",
    "gn:dem":2044,
    "gn:feature_class":"P",
    "gn:feature_code":"PPL",
    "gn:name":"P\u0101ch\u0101d-e Ch\u012brb\u012b\u016bn",
    "gn:population":0,
    "gn:timezone":"Asia/Tehran",
    "iso:country":"IR",
    "name:fas_x_preferred":[
        "P\u0101ch\u0101t"
    ],
    "name:fas_x_variant":[
        "\u067e\u0627\u0686\u0627\u062a",
        "\u067e\u0627\u0686\u0627\u062f \u0686\u06cc\u0631\u0628\u06cc\u0648\u0646"
    ],
    "name:und_x_variant":[
        "P\u0101ch\u0101d-e Ch\u012brb\u012b\u016bn"
    ],
    "wof:name":"Pachad-e Chirbiun",
    "wof:placetype":"locality"
},
  "geometry": {"coordinates":[50.71451,31.23345],"type":"Point"}
}