{
  "type": "Feature",
  "properties": {
    "gn:admin1_code":"29",
    "gn:asciiname":"Darzin",
    "gn:country_code":"IR",
    "gn:dem":1327,
    "gn:feature_class":"P",
    "gn:feature_code":"PPL",
    "gn:name":"D\u0101rz\u012bn",
    "gn:population":0,
    "gn:timezone":"Asia/Tehran",
    "iso:country":"IR",
    "name:fas_x_preferred":[
        "D\u0101rze\u012bn"
    ],
    "name:fas_x_variant":[
        "\u062f\u0627\u0631\u0632\u064a\u0646",
        "Draz\u012bn"
    ],
    "name:und_x_variant":[
        "D\u0101rz\u012bn",
        "Mehd\u012b\u0101b\u0101d-e D\u0101rz\u012bn"
    ],
    "wof:name":"Darzin",
    "wof:placetype":"locality"
},
  "geometry": {"coordinates":[58.12311999999999,29.18015],"type":"Point"}
}