{
  "type": "Feature",
  "properties": {
    "gn:admin1_code":"22",
    "gn:asciiname":"Tangag-e Mohammad Ja`fari",
    "gn:country_code":"IR",
    "gn:dem":19,
    "gn:feature_class":"P",
    "gn:feature_code":"PPL",
    "gn:name":"Tangag-e Mo\u1e29ammad Ja\u2018far\u012b",
    "gn:population":0,
    "gn:timezone":"Asia/Tehran",
    "iso:country":"IR",
    "name:fas_x_preferred":[
        "\u062a\u0646\u06af\u0643 \u0645\u062d\u0645\u0651\u062f \u062c\u0639\u0641\u0631\u06cc"
    ],
    "name:fas_x_variant":[
        "\u062a\u0646\u06af\u064e\u0643 \u0645\u062d\u0645\u062f \u062c\u0639\u0641\u0631",
        "Tangak-e Mo\u1e29ammad Ja\u2018far\u012b",
        "\u062a\u0646\u06af\u06af \u0645\u062d\u0645\u062f \u062c\u0639\u0641\u0631\u06cc",
        "\u062a\u0646\u06af \u062f\u0648\u0645"
    ],
    "name:und_x_variant":[
        "Tangak-e Mo\u1e29ammad Ja\u2018far",
        "Tang Mohammad Ja\u2018fari",
        "Tangak-e -afar\u012b",
        "Tangag-e Mo\u1e29ammad Ja\u2018far\u012b",
        "Tang-e Dovvom"
    ],
    "wof:name":"Tangag-e Mohammad Ja`fari",
    "wof:placetype":"locality"
},
  "geometry": {"coordinates":[50.8752,28.906],"type":"Point"}
}