{
  "type": "Feature",
  "properties": {
    "gn:admin1_code":"33",
    "gn:asciiname":"Khaneh-ye Barq-e Mojarlu",
    "gn:country_code":"IR",
    "gn:dem":1284,
    "gn:feature_class":"P",
    "gn:feature_code":"PPL",
    "gn:name":"Kh\u0101neh-ye Barq-e Mojarl\u016b",
    "gn:population":0,
    "gn:timezone":"Asia/Tehran",
    "iso:country":"IR",
    "name:fas_x_preferred":[
        "\u062e\u0627\u0646\u0647 \u0628\u0631\u0642 \u0645\u062c\u0631\u0644\u0648"
    ],
    "name:fas_x_variant":[
        "Kh\u0101neh-ye Barq-e Jad\u012bd",
        "Kh\u0101neh-ye Barq-e Mojarl\u016b",
        "\u0642\u0634\u0644\u0627\u0642 \u062e\u0627\u0646\u0647 \u0628\u0631\u0642",
        "\u062e\u0627\u0646\u0647 \u0628\u0631\u0642 \u062c\u062f\u064a\u062f"
    ],
    "name:und_x_variant":[
        "Qeshl\u0101q Kh\u0101neh-ye Barq"
    ],
    "wof:name":"Khaneh-ye Barq-e Mojarlu",
    "wof:placetype":"locality"
},
  "geometry": {"coordinates":[46.0208,37.30502],"type":"Point"}
}