{
  "type": "Feature",
  "properties": {
    "gn:admin1_code":"41",
    "gn:asciiname":"Esma`ilabad",
    "gn:country_code":"IR",
    "gn:dem":1392,
    "gn:feature_class":"P",
    "gn:feature_code":"PPL",
    "gn:name":"Esm\u0101\u2018\u012bl\u0101b\u0101d",
    "gn:population":0,
    "gn:timezone":"Asia/Tehran",
    "iso:country":"IR",
    "name:fas_x_preferred":[
        "\u0627\u0633\u0645\u0627\u0639\u06cc\u0644 \u0622\u0628\u0627\u062f"
    ],
    "name:fas_x_variant":[
        "Esm\u0101\u2018\u012bl\u0101b\u0101d"
    ],
    "name:und_x_variant":[
        "Ism\u0101\u2018\u012bl\u0101b\u0101d",
        "Esma\u2018il Abad Behandan"
    ],
    "wof:name":"Esma`ilabad",
    "wof:placetype":"locality"
},
  "geometry": {"coordinates":[59.81583000000001,32.05475999999999],"type":"Point"}
}