{
  "type": "Feature",
  "properties": {
    "gn:admin1_code":"42",
    "gn:asciiname":"Dehnow Filkhaneh",
    "gn:country_code":"IR",
    "gn:dem":1199,
    "gn:feature_class":"P",
    "gn:feature_code":"PPL",
    "gn:name":"Dehnow F\u012blkh\u0101neh",
    "gn:population":0,
    "gn:timezone":"Asia/Tehran",
    "iso:country":"IR",
    "name:fas_x_preferred":[
        "\u062f\u0647 \u0646\u0648"
    ],
    "name:fas_x_variant":[
        "\u062f\u0647\u0646\u0648 \u0641\u06cc\u0644\u062e\u0627\u0646\u0647"
    ],
    "name:und_x_variant":[
        "Deh Now",
        "Dehnow F\u012blkh\u0101neh"
    ],
    "wof:name":"Dehnow Filkhaneh",
    "wof:placetype":"locality"
},
  "geometry": {"coordinates":[58.86454000000001,36.1667],"type":"Point"}
}