{
  "type": "Feature",
  "properties": {
    "gn:admin1_code":"16",
    "gn:asciiname":"Poshteh",
    "gn:country_code":"IR",
    "gn:dem":1845,
    "gn:feature_class":"P",
    "gn:feature_code":"PPL",
    "gn:name":"Poshteh",
    "gn:population":0,
    "gn:timezone":"Asia/Tehran",
    "iso:country":"IR",
    "name:fas_x_preferred":[
        "\u067e\u064f\u0634\u062a\u0650\u0647"
    ],
    "name:fas_x_variant":[
        "\u067e\u0634\u062a\u0647"
    ],
    "wof:name":"Poshteh",
    "wof:placetype":"locality"
},
  "geometry": {"coordinates":[46.7461,34.8164],"type":"Point"}
}