{
  "type": "Feature",
  "properties": {
    "gn:admin1_code":"15.0",
    "gn:asciiname":"Pas Golam",
    "gn:country_code":"IR",
    "gn:dem":729,
    "gn:feature_class":"P",
    "gn:feature_code":"PPL",
    "gn:name":"Pas Gol\u0101m",
    "gn:population":0,
    "gn:timezone":"Asia/Tehran",
    "iso:country":"IR",
    "name:fas_x_preferred":[
        "\u067e\u0633\u06af\u0644\u0645"
    ],
    "name:fas_x_variant":[
        "\u067e\u0633 \u06af\u0644\u0627\u0645"
    ],
    "name:und_x_variant":[
        "Pasgolam",
        "Pas Gol\u0101m"
    ],
    "wof:name":"Pas Golam",
    "wof:placetype":"locality"
},
  "geometry": {"coordinates":[48.15975,32.97107],"type":"Point"}
}