{
  "type": "Feature",
  "properties": {
    "gn:admin1_code":"32.0",
    "gn:asciiname":"Aqchay-e `Olya",
    "gn:country_code":"IR",
    "gn:dem":1753,
    "gn:feature_class":"P",
    "gn:feature_code":"PPL",
    "gn:name":"\u0100qch\u0101y-e \u2018Oly\u0101",
    "gn:population":0,
    "gn:timezone":"Asia/Tehran",
    "iso:country":"IR",
    "name:fas_x_preferred":[
        "\u0622\u0642 \u0686\u0627\u06cc \u0639\u0644\u06cc\u0627"
    ],
    "name:fas_x_variant":[
        "\u0622\u0642\u0627 \u0686\u0627\u06cc \u0628\u0627\u0644\u0627",
        "\u0100qch\u0101y-e \u2018Oly\u0101",
        "\u0100q\u0101 Ch\u0101y-e B\u0101l\u0101",
        "\u0622\u0642\u0686\u0627\u06cc \u0639\u0644\u06cc\u0627"
    ],
    "name:msa_x_preferred":[
        "Aqchay-e Olya"
    ],
    "name:und_x_variant":[
        "\u0100gh Ch\u0101y B\u0101l\u0101",
        "Akchay-Ulia",
        "\u0100q Ch\u0101y-e B\u0101l\u0101",
        "Aqch\u0101i Ulia",
        "\u0100q Ch\u0101y",
        "\u0100q Ch\u0101y \u2018Oly\u0101"
    ],
    "wof:name":"Aqchay-e `Olya",
    "wof:placetype":"locality"
},
  "geometry": {"coordinates":[48.11951,37.92599000000001],"type":"Point"}
}