{
  "type": "Feature",
  "properties": {
    "gn:admin1_code":"26.0",
    "gn:asciiname":"Qal`eh Hajj Heydar",
    "gn:country_code":"IR",
    "gn:dem":1073,
    "gn:feature_class":"P",
    "gn:feature_code":"PPL",
    "gn:name":"Qal\u2018eh \u1e28\u0101jj \u1e28eydar",
    "gn:population":0,
    "gn:timezone":"Asia/Tehran",
    "iso:country":"IR",
    "name:fas_x_preferred":[
        "\u0642\u0644\u0639\u0647 \u062d\u0627\u062c\u0651 \u062d\u06cc\u062f\u0631"
    ],
    "name:und_x_variant":[
        "Qal\u2018eh \u1e28\u0101jj \u1e28eydar"
    ],
    "wof:name":"Qal`eh Hajj Heydar",
    "wof:placetype":"locality"
},
  "geometry": {"coordinates":[51.7381,35.4491],"type":"Point"}
}