{
  "type": "Feature",
  "properties": {
    "gn:admin1_code":"11",
    "gn:asciiname":"Abshur",
    "gn:country_code":"IR",
    "gn:dem":1210,
    "gn:feature_class":"P",
    "gn:feature_code":"PPL",
    "gn:name":"\u0100bsh\u016br",
    "gn:population":0,
    "gn:timezone":"Asia/Tehran",
    "iso:country":"IR",
    "name:fas_x_preferred":[
        "\u0622\u0628\u0634\u0648\u0631"
    ],
    "name:fas_x_variant":[
        "\u0100bsh\u016br"
    ],
    "wof:name":"Abshur",
    "wof:placetype":"locality"
},
  "geometry": {"coordinates":[56.5998,27.8155],"type":"Point"}
}