{
  "type": "Feature",
  "properties": {
    "gn:admin1_code":"33.0",
    "gn:asciiname":"Qarah Gaz",
    "gn:country_code":"IR",
    "gn:dem":1563,
    "gn:feature_class":"P",
    "gn:feature_code":"PPL",
    "gn:name":"Qarah Gaz",
    "gn:population":0,
    "gn:timezone":"Asia/Tehran",
    "iso:country":"IR",
    "name:fas_x_preferred":[
        "\u0642\u0631\u0647 \u06af\u0632"
    ],
    "wof:name":"Qarah Gaz",
    "wof:placetype":"locality"
},
  "geometry": {"coordinates":[47.2448,38.6127],"type":"Point"}
}