{
  "type": "Feature",
  "properties": {
    "gn:admin1_code":"1.0",
    "gn:asciiname":"Chumelan",
    "gn:country_code":"IR",
    "gn:dem":1559,
    "gn:feature_class":"P",
    "gn:feature_code":"PPL",
    "gn:name":"Ch\u016bmel\u0101n",
    "gn:population":0,
    "gn:timezone":"Asia/Tehran",
    "iso:country":"IR",
    "name:fas_x_preferred":[
        "\u0686\u0648\u0645\u0644\u0627\u0646"
    ],
    "name:fas_x_variant":[
        "Ch\u016bmel\u0101n"
    ],
    "wof:name":"Chumelan",
    "wof:placetype":"locality"
},
  "geometry": {"coordinates":[45.6232,36.8553],"type":"Point"}
}