{
  "type": "Feature",
  "properties": {
    "gn:admin1_code":"1.0",
    "gn:asciiname":"Chumelan",
    "gn:country_code":"IR",
    "gn:dem":1559,
    "gn:feature_class":"P",
    "gn:feature_code":"PPL",
    "gn:name":"Ch\u016bmel\u0101n",
    "gn:population":0,
    "gn:timezone":"Asia/Tehran",
    "iso:country":"IR",
    "name:azb_x_preferred":[
        "\u0686\u0648\u0645\u0644\u0627\u0646(\u0633\u0648\u06cc\u0648\u0642\u200c\u0628\u0648\u0644\u0627\u0642)"
    ],
    "name:aze_x_preferred":[
        "\u00c7\u00fcm\u0259lan"
    ],
    "name:ceb_x_preferred":[
        "Ch\u016bmel\u0101n"
    ],
    "name:ckb_x_preferred":[
        "\u0686\u06c6\u0645\u06d5\u06b5\u0627\u0646"
    ],
    "name:fas_x_preferred":[
        "\u0686\u0648\u0645\u0644\u0627\u0646"
    ],
    "name:fas_x_variant":[
        "Ch\u016bmel\u0101n"
    ],
    "name:msa_x_preferred":[
        "Chumelan"
    ],
    "name:swe_x_preferred":[
        "Ch\u016bmel\u0101n"
    ],
    "wof:name":"Chumelan",
    "wof:placetype":"locality"
},
  "geometry": {"coordinates":[45.6232,36.8553],"type":"Point"}
}