{
  "type": "Feature",
  "properties": {
    "gn:admin1_code":"41",
    "gn:asciiname":"`Asgarabad",
    "gn:country_code":"IR",
    "gn:dem":1482,
    "gn:feature_class":"P",
    "gn:feature_code":"PPL",
    "gn:name":"\u2018Asgar\u0101b\u0101d",
    "gn:population":0,
    "gn:timezone":"Asia/Tehran",
    "iso:country":"IR",
    "name:fas_x_preferred":[
        "\u2018Asgar\u0101b\u0101d"
    ],
    "name:fas_x_variant":[
        "A\u015fghar\u0101b\u0101d",
        "\u0639\u0633\u06af\u0631 \u0622\u0628\u0627\u062f",
        "\u0627\u0635\u063a\u0631 \u0622\u0628\u0627\u062f"
    ],
    "name:und_x_variant":[
        "\u0639\u0633\u06af\u0631 \u0622\u0628\u0627\u062f"
    ],
    "wof:name":"`Asgarabad",
    "wof:placetype":"locality"
},
  "geometry": {"coordinates":[59.17699,32.50918],"type":"Point"}
}