{
  "type": "Feature",
  "properties": {
    "gn:admin1_code":"8",
    "gn:asciiname":"`Ali Owsat Mahalleh",
    "gn:country_code":"IR",
    "gn:dem":17,
    "gn:feature_class":"P",
    "gn:feature_code":"PPL",
    "gn:name":"\u2018Al\u012b Owsa\u0163 Ma\u1e29alleh",
    "gn:population":0,
    "gn:timezone":"Asia/Tehran",
    "iso:country":"IR",
    "name:fas_x_preferred":[
        "\u2018Al\u012b Owsa\u0163 Ma\u1e29alleh"
    ],
    "name:fas_x_variant":[
        "\u0639\u0644\u06cc \u0627\u0648\u0633\u0637 \u0645\u062d\u0644\u0647"
    ],
    "name:und_x_variant":[
        "\u0639\u0644\u06cc \u0627\u0648\u0633\u0637 \u0645\u062d\u0644\u0647"
    ],
    "wof:name":"`Ali Owsat Mahalleh",
    "wof:placetype":"locality"
},
  "geometry": {"coordinates":[50.34503,37.05743],"type":"Point"}
}