{
  "type": "Feature",
  "properties": {
    "gn:admin1_code":"11",
    "gn:asciiname":"Arabi",
    "gn:country_code":"IR",
    "gn:dem":25,
    "gn:feature_class":"P",
    "gn:feature_code":"PPL",
    "gn:name":"\u0100r\u0101b\u012b",
    "gn:population":0,
    "gn:timezone":"Asia/Tehran",
    "iso:country":"IR",
    "name:fas_x_preferred":[
        "\u0622\u0631\u0627\u0628\u06cc"
    ],
    "name:fas_x_variant":[
        "\u0100r\u0101b\u012b",
        "\u0627\u0631\u0627\u0628\u06cc"
    ],
    "name:msa_x_preferred":[
        "Arabi"
    ],
    "wof:name":"Arabi",
    "wof:placetype":"locality"
},
  "geometry": {"coordinates":[55.6909,27.1943],"type":"Point"}
}