{
  "type": "Feature",
  "properties": {
    "gn:admin1_code":"29",
    "gn:asciiname":"Karpu'iyeh",
    "gn:country_code":"IR",
    "gn:dem":2806,
    "gn:feature_class":"P",
    "gn:feature_code":"PPLF",
    "gn:name":"Karp\u016b\u2019\u012byeh",
    "gn:population":0,
    "gn:timezone":"Asia/Tehran",
    "iso:country":"IR",
    "name:fas_x_preferred":[
        "\u06a9\u0631\u067e\u0648\u0626\u06cc\u0647"
    ],
    "name:fas_x_variant":[
        "Karp\u016b\u2019\u012byeh"
    ],
    "name:und_x_variant":[
        "Kerp\u016b\u2019\u012byeh"
    ],
    "wof:name":"Karpu'iyeh",
    "wof:placetype":"locality"
},
  "geometry": {"coordinates":[56.3396,29.57817],"type":"Point"}
}