{
  "type": "Feature",
  "properties": {
    "gn:admin1_code":"3",
    "gn:asciiname":"Kalgeh Milas",
    "gn:cc2":"IR",
    "gn:country_code":"IR",
    "gn:dem":1618,
    "gn:feature_class":"P",
    "gn:feature_code":"PPL",
    "gn:name":"Kalgeh M\u012bl\u0101s",
    "gn:population":0,
    "gn:timezone":"Asia/Tehran",
    "iso:country":"IR",
    "name:fas_x_preferred":[
        "Kalgeh M\u012bl\u0101s"
    ],
    "name:fas_x_variant":[
        "\u0643\u064e\u0644\u06af\u0650\u0647 \u0645\u064a\u0644\u0627\u0633",
        "\u0643\u064e\u0644\u06af\u064e\u0647 \u0645\u064a\u0644\u0627\u0633"
    ],
    "name:und_x_variant":[
        "Kalgah M\u012bl\u0101s"
    ],
    "wof:name":"Kalgeh Milas",
    "wof:placetype":"locality"
},
  "geometry": {"coordinates":[50.76667,31.48611],"type":"Point"}
}