{
  "type": "Feature",
  "properties": {
    "gn:admin1_code":"5",
    "gn:asciiname":"Chenarestan-e Vosta",
    "gn:country_code":"IR",
    "gn:dem":1770,
    "gn:feature_class":"P",
    "gn:feature_code":"PPL",
    "gn:name":"Chen\u0101rest\u0101n-e Vos\u0163\u00e1",
    "gn:population":0,
    "gn:timezone":"Asia/Tehran",
    "iso:country":"IR",
    "name:ara_x_preferred":[
        "\u062a\u0634\u0646\u0627\u0631\u0633\u062a\u0627\u0646 \u0627\u0644\u0648\u0633\u0637"
    ],
    "name:ceb_x_preferred":[
        "Chen\u0101rest\u0101n-e Vos\u0163\u00e1"
    ],
    "name:fas_x_preferred":[
        "Chen\u0101rest\u0101n-e Vos\u0163\u00e1"
    ],
    "name:fas_x_variant":[
        "Chen\u0101rest\u0101n-e Vasa\u0163",
        "\u0686\u0646\u0627\u0631\u0633\u062a\u0627\u0646 \u0648\u0633\u0637\u06cc"
    ],
    "name:swe_x_preferred":[
        "Chen\u0101rest\u0101n-e Vos\u0163\u00e1"
    ],
    "name:und_x_variant":[
        "\u0686\u0646\u0627\u0631\u0633\u062a\u0627\u0646 \u0648\u0633\u0637\u06cc"
    ],
    "wof:name":"Chenarestan-e Vosta",
    "wof:placetype":"locality"
},
  "geometry": {"coordinates":[51.55657,30.6291],"type":"Point"}
}