{
  "type": "Feature",
  "properties": {
    "gn:admin1_code":"7.0",
    "gn:asciiname":"Qarah Bas",
    "gn:country_code":"IR",
    "gn:dem":1054,
    "gn:feature_class":"P",
    "gn:feature_code":"PPL",
    "gn:name":"Qarah Bas",
    "gn:population":0,
    "gn:timezone":"Asia/Tehran",
    "iso:country":"IR",
    "name:fas_x_preferred":[
        "\u0642\u0631\u0647 \u0628\u0633"
    ],
    "wof:name":"Qarah Bas",
    "wof:placetype":"locality"
},
  "geometry": {"coordinates":[51.30534,30.07424],"type":"Point"}
}