{
  "type": "Feature",
  "properties": {
    "gn:admin1_code":"35.0",
    "gn:asciiname":"Zarrin Kola-ye Pa'in",
    "gn:country_code":"IR",
    "gn:dem":13,
    "gn:feature_class":"P",
    "gn:feature_code":"PPL",
    "gn:name":"Zarr\u012bn Kol\u0101-ye P\u0101\u2019\u012bn",
    "gn:population":0,
    "gn:timezone":"Asia/Tehran",
    "iso:country":"IR",
    "name:ceb_x_preferred":[
        "Zarr\u012bn Kol\u0101-ye P\u0101'\u012bn"
    ],
    "name:fas_x_preferred":[
        "Zarr\u012bn Kol\u0101-ye P\u0101\u2019\u012bn"
    ],
    "name:fas_x_variant":[
        "\u0632\u0631\u06cc\u0646 \u06a9\u0644\u0627 \u067e\u0627\u0626\u06cc\u0646",
        "Zarr\u012bn Kol\u0101",
        "\u0632\u0631\u06cc\u0646\u200c\u06a9\u0644\u0627"
    ],
    "name:swe_x_preferred":[
        "Zarr\u012bn Kol\u0101-ye P\u0101'\u012bn"
    ],
    "wof:name":"Zarrin Kola-ye Pa'in",
    "wof:placetype":"locality"
},
  "geometry": {"coordinates":[51.92672,36.55041],"type":"Point"}
}