{
  "type": "Feature",
  "properties": {
    "gn:admin1_code":"4.0",
    "gn:asciiname":"Hut Gat",
    "gn:country_code":"IR",
    "gn:dem":60,
    "gn:feature_class":"P",
    "gn:feature_code":"PPL",
    "gn:name":"H\u016bt Gat",
    "gn:population":0,
    "gn:timezone":"Asia/Tehran",
    "iso:country":"IR",
    "name:fas_x_preferred":[
        "H\u016btgat-e P\u0101\u2019\u012bn"
    ],
    "name:fas_x_variant":[
        "H\u016bt Gat",
        "\u0647\u0648\u062a \u06af\u062a"
    ],
    "name:und_x_variant":[
        "\u0647\u0648\u062a \u06af\u062a"
    ],
    "wof:name":"Hut Gat",
    "wof:placetype":"locality"
},
  "geometry": {"coordinates":[61.4907,25.78906],"type":"Point"}
}