{
  "type": "Feature",
  "properties": {
    "gn:admin1_code":"33",
    "gn:asciiname":"Oshnar",
    "gn:country_code":"IR",
    "gn:dem":1704,
    "gn:feature_class":"P",
    "gn:feature_code":"PPL",
    "gn:name":"Oshn\u0101r",
    "gn:population":0,
    "gn:timezone":"Asia/Tehran",
    "iso:country":"IR",
    "name:azb_x_preferred":[
        "\u0627\u0634\u06cc\u0646\u0627\u0631"
    ],
    "name:ceb_x_preferred":[
        "Oshn\u0101r"
    ],
    "name:fas_x_preferred":[
        "\u0627\u0634\u0646\u0627\u0631"
    ],
    "name:fas_x_variant":[
        "Oshn\u0101r"
    ],
    "name:msa_x_preferred":[
        "Oshnar"
    ],
    "name:swe_x_preferred":[
        "Oshn\u0101r"
    ],
    "wof:name":"Oshnar",
    "wof:placetype":"locality"
},
  "geometry": {"coordinates":[47.5086,37.6121],"type":"Point"}
}