{
  "type": "Feature",
  "properties": {
    "gn:admin1_code":"13",
    "gn:asciiname":"Shireh Choqa",
    "gn:country_code":"IR",
    "gn:dem":1372,
    "gn:feature_class":"P",
    "gn:feature_code":"PPL",
    "gn:name":"Sh\u012breh Choq\u0101",
    "gn:population":0,
    "gn:timezone":"Asia/Tehran",
    "iso:country":"IR",
    "name:ara_x_preferred":[
        "\u0634\u064a\u0631\u0647\u062a\u0634\u0642\u0627"
    ],
    "name:ceb_x_preferred":[
        "Sh\u012breh Choq\u0101"
    ],
    "name:fas_x_preferred":[
        "\u0634\u06cc\u0631\u0647 \u0686\u0642\u0627"
    ],
    "name:fas_x_variant":[
        "Sh\u012breh Cheq\u0101",
        "Sh\u012breh Choq\u0101",
        "\u0634\u06cc\u0631\u0647\u200c\u0686\u0642\u0627"
    ],
    "name:swe_x_preferred":[
        "Sh\u012breh Choq\u0101"
    ],
    "wof:name":"Shireh Choqa",
    "wof:placetype":"locality"
},
  "geometry": {"coordinates":[46.1001,34.3622],"type":"Point"}
}