{
  "type": "Feature",
  "properties": {
    "gn:admin1_code":"28",
    "gn:asciiname":"Varaq",
    "gn:country_code":"IR",
    "gn:dem":2321,
    "gn:feature_class":"P",
    "gn:feature_code":"PPL",
    "gn:name":"Varaq",
    "gn:population":0,
    "gn:timezone":"Asia/Tehran",
    "iso:country":"IR",
    "name:fas_x_preferred":[
        "\u0648\u0631\u0642"
    ],
    "name:und_x_variant":[
        "\u0648\u0631\u0642"
    ],
    "wof:name":"Varaq",
    "wof:placetype":"locality"
},
  "geometry": {"coordinates":[51.51609000000001,31.70231],"type":"Point"}
}