{
  "type": "Feature",
  "properties": {
    "gn:admin1_code":"35.0",
    "gn:asciiname":"Anar Jar",
    "gn:country_code":"IR",
    "gn:dem":50,
    "gn:feature_class":"P",
    "gn:feature_code":"PPL",
    "gn:name":"An\u0101r J\u0101r",
    "gn:population":0,
    "gn:timezone":"Asia/Tehran",
    "iso:country":"IR",
    "name:ceb_x_preferred":[
        "An\u0101r J\u0101r"
    ],
    "name:fas_x_preferred":[
        "\u0627\u0646\u0627\u0631\u062c\u0627\u0631"
    ],
    "name:fas_x_variant":[
        "An\u0101r J\u0101r"
    ],
    "name:swe_x_preferred":[
        "An\u0101r J\u0101r"
    ],
    "wof:name":"Anar Jar",
    "wof:placetype":"locality"
},
  "geometry": {"coordinates":[51.97745,36.51338],"type":"Point"}
}