{
  "type": "Feature",
  "properties": {
    "gn:admin1_code":"15.0",
    "gn:asciiname":"Shahid Baqer Manjezi",
    "gn:country_code":"IR",
    "gn:dem":357,
    "gn:feature_class":"P",
    "gn:feature_code":"PPL",
    "gn:name":"Shah\u012bd B\u0101qer Manjez\u012b",
    "gn:population":0,
    "gn:timezone":"Asia/Tehran",
    "iso:country":"IR",
    "name:fas_x_preferred":[
        "\u06cc\u062f\u0627\u0644\u0644\u0651\u0647"
    ],
    "name:fas_x_variant":[
        "Yadoll\u0101h",
        "\u0634\u0647\u06cc\u062f \u0628\u0627\u0642\u0631 \u0645\u0646\u062c\u0632\u06cc",
        "\u0633\u0627\u0644\u0648\u0646\u062f\u0648\u0646"
    ],
    "name:und_x_variant":[
        "Shah\u012bd B\u0101qer Manjez\u012b",
        "S\u0101lvand\u016bn"
    ],
    "wof:name":"Shahid Baqer Manjezi",
    "wof:placetype":"locality"
},
  "geometry": {"coordinates":[49.0213,32.1639],"type":"Point"}
}