{
  "type": "Feature",
  "properties": {
    "gn:admin1_code":"7",
    "gn:asciiname":"Barasteskun",
    "gn:country_code":"IR",
    "gn:dem":1828,
    "gn:feature_class":"P",
    "gn:feature_code":"PPL",
    "gn:name":"Bar\u0101stesk\u016bn",
    "gn:population":0,
    "gn:timezone":"Asia/Tehran",
    "iso:country":"IR",
    "name:fas_x_preferred":[
        "Bar\u0101stesk\u016bn"
    ],
    "wof:name":"Barasteskun",
    "wof:placetype":"locality"
},
  "geometry": {"coordinates":[54.85,28.93333],"type":"Point"}
}