{
  "type": "Feature",
  "properties": {
    "gn:admin1_code":"16",
    "gn:asciiname":"Balqolu",
    "gn:country_code":"IR",
    "gn:dem":1425,
    "gn:feature_class":"P",
    "gn:feature_code":"PPL",
    "gn:name":"B\u0101lqol\u016b",
    "gn:population":0,
    "gn:timezone":"Asia/Tehran",
    "iso:country":"IR",
    "name:ara_x_preferred":[
        "\u0628\u0627\u0644\u0642\u0644\u0648"
    ],
    "name:ckb_x_preferred":[
        "\u0628\u0627\u06b5\u06d5\u0642\u06b5\u0648\u0648"
    ],
    "name:fas_x_preferred":[
        "\u0628\u0627\u0644\u0627\u0642\u0644\u0648"
    ],
    "name:fas_x_variant":[
        "\u0628\u0627\u0644\u0642\u0644\u0648",
        "B\u0101l\u0101qol\u016b",
        "B\u0101lqol\u016b"
    ],
    "name:kur_x_preferred":[
        "Baleql\u00fb"
    ],
    "wof:name":"Balqolu",
    "wof:placetype":"locality"
},
  "geometry": {"coordinates":[46.62484,36.39745],"type":"Point"}
}