{
  "type": "Feature",
  "properties": {
    "gn:admin1_code":"7",
    "gn:asciiname":"Moshtakan",
    "gn:country_code":"IR",
    "gn:dem":936,
    "gn:feature_class":"P",
    "gn:feature_code":"PPL",
    "gn:name":"Moshtak\u0101n",
    "gn:population":0,
    "gn:timezone":"Asia/Tehran",
    "iso:country":"IR",
    "name:fas_x_preferred":[
        "Moshtak\u0101n"
    ],
    "name:fas_x_variant":[
        "Mashtak\u0101n",
        "\u0645\u0634\u062a\u06a9\u0627\u0646"
    ],
    "wof:name":"Moshtakan",
    "wof:placetype":"locality"
},
  "geometry": {"coordinates":[51.50073,30.09207],"type":"Point"}
}