{
  "type": "Feature",
  "properties": {
    "gn:admin1_code":"26.0",
    "gn:asciiname":"Mohammad Shahr",
    "gn:country_code":"IR",
    "gn:dem":1202,
    "gn:feature_class":"P",
    "gn:feature_code":"PPL",
    "gn:name":"Mo\u1e29ammad Shahr",
    "gn:population":0,
    "gn:timezone":"Asia/Tehran",
    "iso:country":"IR",
    "name:fas_x_preferred":[
        "\u062c\u0639\u0641\u0631 \u0622\u0628\u0627\u062f"
    ],
    "name:fas_x_variant":[
        "Ja\u2018far\u0101b\u0101d",
        "\u0645\u062d\u0645\u062f \u0634\u0647\u0631"
    ],
    "name:und_x_variant":[
        "Mo\u1e29ammad Shahr"
    ],
    "wof:name":"Mohammad Shahr",
    "wof:placetype":"locality"
},
  "geometry": {"coordinates":[50.88066,35.74016],"type":"Point"}
}