{
  "type": "Feature",
  "properties": {
    "gn:admin1_code":"4",
    "gn:asciiname":"Sar Poshteh",
    "gn:country_code":"IR",
    "gn:dem":2071,
    "gn:feature_class":"P",
    "gn:feature_code":"PPL",
    "gn:name":"Sar Poshteh",
    "gn:population":0,
    "gn:timezone":"Asia/Tehran",
    "iso:country":"IR",
    "name:fas_x_preferred":[
        "\u0633\u0631 \u067e\u0634\u062a\u0647"
    ],
    "wof:name":"Sar Poshteh",
    "wof:placetype":"locality"
},
  "geometry": {"coordinates":[61.00252,28.55493],"type":"Point"}
}