{
  "type": "Feature",
  "properties": {
    "gn:admin1_code":"9",
    "gn:asciiname":"Band Amun",
    "gn:country_code":"IR",
    "gn:dem":1517,
    "gn:feature_class":"P",
    "gn:feature_code":"PPL",
    "gn:name":"Band \u0100m\u016bn",
    "gn:population":0,
    "gn:timezone":"Asia/Tehran",
    "iso:country":"IR",
    "name:fas_x_preferred":[
        "\u0628\u0646\u062f \u0627\u0645\u0627\u0646"
    ],
    "name:fas_x_variant":[
        "Band \u0100m\u016bn",
        "Band Am\u0101n",
        "\u0628\u0646\u062f \u0622\u0645\u0648\u0646",
        "Band\u0101m\u016bn"
    ],
    "name:und_x_variant":[
        "Band\u0101m\u016bn",
        "\u0628\u0646\u062f \u0622\u0645\u0648\u0646"
    ],
    "wof:name":"Band Amun",
    "wof:placetype":"locality"
},
  "geometry": {"coordinates":[48.22874,34.22344],"type":"Point"}
}