{
  "type": "Feature",
  "properties": {
    "gn:admin1_code":"37",
    "gn:asciiname":"Qeremseh",
    "gn:country_code":"IR",
    "gn:dem":98,
    "gn:feature_class":"P",
    "gn:feature_code":"PPL",
    "gn:name":"Qeremseh",
    "gn:population":0,
    "gn:timezone":"Asia/Tehran",
    "iso:country":"IR",
    "name:fas_x_preferred":[
        "\u0642\u0650\u0631\u0650\u0645\u0633\u0650\u0647"
    ],
    "wof:name":"Qeremseh",
    "wof:placetype":"locality"
},
  "geometry": {"coordinates":[55.06639000000001,36.99833],"type":"Point"}
}