{
  "type": "Feature",
  "properties": {
    "gn:admin1_code":"35.0",
    "gn:asciiname":"Jir Sar Balan",
    "gn:country_code":"IR",
    "gn:dem":1360,
    "gn:feature_class":"P",
    "gn:feature_code":"PPL",
    "gn:name":"J\u012br Sar B\u0101l\u0101n",
    "gn:population":0,
    "gn:timezone":"Asia/Tehran",
    "iso:country":"IR",
    "name:fas_x_preferred":[
        "Sar B\u0101l\u0101n"
    ],
    "name:fas_x_variant":[
        "\u0633\u0631 \u0628\u0627\u0644\u0627\u0646",
        "\u062c\u064a\u0631 \u0633\u0631 \u0628\u0627\u0644\u0627\u0646",
        "\u062c\u064a\u0631 \u0628\u0627\u0644\u0627\u0646",
        "\u0633\u0631\u0628\u0627\u0644\u0627\u0646"
    ],
    "name:und_x_variant":[
        "J\u012br Sar B\u0101l\u0101n",
        "J\u012br B\u0101l\u0101n"
    ],
    "wof:name":"Jir Sar Balan",
    "wof:placetype":"locality"
},
  "geometry": {"coordinates":[50.83909,36.50653],"type":"Point"}
}