{
  "type": "Feature",
  "properties": {
    "gn:admin1_code":"1.0",
    "gn:asciiname":"Shahid Mohammad Ra'uf",
    "gn:country_code":"IR",
    "gn:dem":1383,
    "gn:feature_class":"P",
    "gn:feature_code":"PPL",
    "gn:name":"Shah\u012bd Mo\u1e29ammad Ra\u2019\u016bf",
    "gn:population":0,
    "gn:timezone":"Asia/Tehran",
    "iso:country":"IR",
    "name:fas_x_preferred":[
        "\u0634\u064e\u0647\u064a\u062f \u0645\u064f\u062d\u064e\u0645\u064e\u0651\u062f \u0631\u064e\u0621\u0648\u0641"
    ],
    "name:fas_x_variant":[
        "Shah\u012bd Mo\u1e29ammad Ra\u2019\u016bf"
    ],
    "wof:name":"Shahid Mohammad Ra'uf",
    "wof:placetype":"locality"
},
  "geometry": {"coordinates":[45.56667,36.86667],"type":"Point"}
}