{
  "type": "Feature",
  "properties": {
    "gn:admin1_code":"16",
    "gn:asciiname":"Lenjabad",
    "gn:country_code":"IR",
    "gn:dem":1393,
    "gn:feature_class":"P",
    "gn:feature_code":"PPL",
    "gn:name":"Lenj\u0101b\u0101d",
    "gn:population":0,
    "gn:timezone":"Asia/Tehran",
    "iso:country":"IR",
    "name:fas_x_preferred":[
        "\u0644\u0646\u062c \u0622\u0628\u0627\u062f"
    ],
    "name:fas_x_variant":[
        "Lenj\u0101b\u0101d",
        "Lanj\u0101b\u0101d"
    ],
    "wof:name":"Lenjabad",
    "wof:placetype":"locality"
},
  "geometry": {"coordinates":[46.2327,35.5095],"type":"Point"}
}