{
  "type": "Feature",
  "properties": {
    "gn:admin1_code":"28.0",
    "gn:asciiname":"Hajji Alvan",
    "gn:cc2":"IR",
    "gn:country_code":"IR",
    "gn:dem":1963,
    "gn:feature_class":"P",
    "gn:feature_code":"PPL",
    "gn:name":"\u1e28\u0101jj\u012b Alv\u0101n",
    "gn:population":0,
    "gn:timezone":"Asia/Tehran",
    "iso:country":"IR",
    "name:fas_x_preferred":[
        "\u1e28\u0101jj\u012b Alv\u0101n"
    ],
    "name:und_x_variant":[
        "\u1e28\u0101j\u012b Alv\u0101n"
    ],
    "wof:name":"Hajji Alvan",
    "wof:placetype":"locality"
},
  "geometry": {"coordinates":[51.14972,32.50972],"type":"Point"}
}