{
  "type": "Feature",
  "properties": {
    "gn:admin1_code":"40.0",
    "gn:asciiname":"Taqi",
    "gn:country_code":"IR",
    "gn:dem":969,
    "gn:feature_class":"P",
    "gn:feature_code":"PPL",
    "gn:name":"\u0162\u0101q\u012b",
    "gn:population":0,
    "gn:timezone":"Asia/Tehran",
    "iso:country":"IR",
    "name:fas_x_preferred":[
        "\u0637\u0627\u0642\u06cc"
    ],
    "name:und_x_variant":[
        "\u0162\u0101q\u012b"
    ],
    "wof:name":"Taqi",
    "wof:placetype":"locality"
},
  "geometry": {"coordinates":[57.56258,34.95587],"type":"Point"}
}