{
  "type": "Feature",
  "properties": {
    "gn:admin1_code":"16",
    "gn:asciiname":"Bidar",
    "gn:country_code":"IR",
    "gn:dem":1784,
    "gn:feature_class":"P",
    "gn:feature_code":"PPL",
    "gn:name":"B\u012bdar",
    "gn:population":0,
    "gn:timezone":"Asia/Tehran",
    "iso:country":"IR",
    "name:ara_x_preferred":[
        "\u0628\u064a\u062f\u0627\u0631"
    ],
    "name:ceb_x_preferred":[
        "B\u012bdar"
    ],
    "name:ckb_x_preferred":[
        "\u0628\u06ce\u06d5\u0631\u06d5"
    ],
    "name:ell_x_preferred":[
        "\u039c\u03c0\u03b9\u03bd\u03c4\u03ac\u03c1"
    ],
    "name:fas_x_preferred":[
        "\u0628\u064a\u062f \u062f\u0631\u0647"
    ],
    "name:fas_x_variant":[
        "\u0628\u06cc\u062f\u0631",
        "B\u012bdarreh",
        "B\u012bdar",
        "\u0628\u06cc\u062f\u062f\u0631\u0647"
    ],
    "name:heb_x_preferred":[
        "\u05d1\u05d9\u05d3\u05d0\u05e8"
    ],
    "name:hun_x_preferred":[
        "Bidar"
    ],
    "name:ind_x_preferred":[
        "Bidar"
    ],
    "name:swe_x_preferred":[
        "B\u012bdar"
    ],
    "name:tur_x_preferred":[
        "Bidar"
    ],
    "name:und_x_variant":[
        "Baidarreh",
        "B\u012bd\u0101reh",
        "B\u012bd Darreh"
    ],
    "wof:name":"Bidar",
    "wof:placetype":"locality"
},
  "geometry": {"coordinates":[46.4625,35.3784],"type":"Point"}
}