{
  "type": "Feature",
  "properties": {
    "gn:admin1_code":"7",
    "gn:asciiname":"Chah Tut",
    "gn:country_code":"IR",
    "gn:dem":2001,
    "gn:feature_class":"P",
    "gn:feature_code":"PPL",
    "gn:name":"Ch\u0101h T\u016bt",
    "gn:population":0,
    "gn:timezone":"Asia/Tehran",
    "iso:country":"IR",
    "name:fas_x_preferred":[
        "Ch\u0101h T\u016bt"
    ],
    "name:fas_x_variant":[
        "\u0686\u0627\u0647 \u062a\u0648\u062a"
    ],
    "name:und_x_variant":[
        "\u0686\u0627\u0647 \u062a\u0648\u062a"
    ],
    "wof:name":"Chah Tut",
    "wof:placetype":"locality"
},
  "geometry": {"coordinates":[51.68731,30.04583],"type":"Point"}
}