{
  "type": "Feature",
  "properties": {
    "gn:admin1_code":"32",
    "gn:asciiname":"Lanjabad",
    "gn:country_code":"IR",
    "gn:dem":2078,
    "gn:feature_class":"P",
    "gn:feature_code":"PPL",
    "gn:name":"Lanj\u0101b\u0101d",
    "gn:population":0,
    "gn:timezone":"Asia/Tehran",
    "iso:country":"IR",
    "name:fas_x_preferred":[
        "\u0644\u0646\u062c \u0622\u0628\u0627\u062f"
    ],
    "name:fas_x_variant":[
        "Lanj\u0101b\u0101d"
    ],
    "name:und_x_variant":[
        "Fat\u1e29\u0101b\u0101d"
    ],
    "wof:name":"Lanjabad",
    "wof:placetype":"locality"
},
  "geometry": {"coordinates":[47.9299,38.4053],"type":"Point"}
}