{
  "type": "Feature",
  "properties": {
    "gn:admin1_code":"4.0",
    "gn:asciiname":"Dirman",
    "gn:country_code":"IR",
    "gn:dem":40,
    "gn:feature_class":"P",
    "gn:feature_code":"PPL",
    "gn:name":"D\u012brm\u0101n",
    "gn:population":0,
    "gn:timezone":"Asia/Tehran",
    "iso:country":"IR",
    "name:fas_x_preferred":[
        "D\u012brm\u0101n"
    ],
    "name:fas_x_variant":[
        "\u062f\u06cc\u0631\u0645\u0627\u0646"
    ],
    "name:und_x_variant":[
        "Dayerm\u0101n",
        "\u062f\u06cc\u0631\u0645\u0627\u0646"
    ],
    "wof:name":"Dirman",
    "wof:placetype":"locality"
},
  "geometry": {"coordinates":[61.05274,25.79071],"type":"Point"}
}