{
  "type": "Feature",
  "properties": {
    "gn:admin1_code":"4",
    "gn:asciiname":"Bent",
    "gn:cc2":"IR",
    "gn:country_code":"IR",
    "gn:dem":419,
    "gn:feature_class":"P",
    "gn:feature_code":"PPL",
    "gn:name":"Bent",
    "gn:population":0,
    "gn:timezone":"Asia/Tehran",
    "iso:country":"IR",
    "name:und_x_variant":[
        "Bint",
        "Bent"
    ],
    "wof:name":"Bent",
    "wof:placetype":"locality"
},
  "geometry": {"coordinates":[59.46528000000001,26.31611],"type":"Point"}
}