{
  "type": "Feature",
  "properties": {
    "gn:admin1_code":"4",
    "gn:asciiname":"Konardar",
    "gn:country_code":"IR",
    "gn:dem":390,
    "gn:feature_class":"P",
    "gn:feature_code":"PPL",
    "gn:name":"Kon\u0101rdar",
    "gn:population":0,
    "gn:timezone":"Asia/Tehran",
    "iso:country":"IR",
    "name:fas_x_preferred":[
        "\u06a9\u0648\u0646\u0627\u062f\u0631"
    ],
    "name:fas_x_variant":[
        "K\u016bn\u0101dar",
        "\u06a9\u0646\u0627\u0631\u062f\u0631"
    ],
    "name:und_x_variant":[
        "Kon\u0101rdar"
    ],
    "wof:name":"Konardar",
    "wof:placetype":"locality"
},
  "geometry": {"coordinates":[58.88016999999999,26.34734000000001],"type":"Point"}
}