{
  "type": "Feature",
  "properties": {
    "gn:admin1_code":"39.0",
    "gn:asciiname":"Ilikh Bolakhi",
    "gn:country_code":"IR",
    "gn:dem":1031,
    "gn:feature_class":"P",
    "gn:feature_code":"PPL",
    "gn:name":"\u012al\u012bkh Bol\u0101kh\u012b",
    "gn:population":0,
    "gn:timezone":"Asia/Tehran",
    "iso:country":"IR",
    "name:fas_x_preferred":[
        "\u064a\u0644\u064a\u062e"
    ],
    "name:fas_x_variant":[
        "\u0627\u06cc\u0644\u062e \u0628\u0644\u0627\u063a\u06cc",
        "\u012alkh Bol\u0101gh\u012b",
        "\u0627\u06cc\u0644\u06cc\u062e \u0628\u0644\u0627\u062e\u06cc",
        "\u0627\u06cc\u0644\u06cc\u062e \u0628\u0644\u0627\u063a\u06cc",
        "\u0627\u06cc\u0644\u06cc\u062e\u06cc \u0628\u0644\u0627\u063a\u06cc"
    ],
    "name:und_x_variant":[
        "\u012al\u012bkh",
        "\u012al\u012bkh Bol\u0101kh\u012b",
        "\u012al\u012bkh Bol\u0101gh\u012b",
        "\u012al\u012bkh\u012b Bol\u0101gh\u012b",
        "Yel\u012bkh"
    ],
    "wof:name":"Ilikh Bolakhi",
    "wof:placetype":"locality"
},
  "geometry": {"coordinates":[50.82085,35.11304000000001],"type":"Point"}
}