{
  "type": "Feature",
  "properties": {
    "gn:admin1_code":"5",
    "gn:asciiname":"Qal`eh-ye Markazi",
    "gn:country_code":"IR",
    "gn:dem":2382,
    "gn:feature_class":"P",
    "gn:feature_code":"PPL",
    "gn:name":"Qal\u2018eh-ye Markaz\u012b",
    "gn:population":0,
    "gn:timezone":"Asia/Tehran",
    "iso:country":"IR",
    "name:fas_x_preferred":[
        "\u0642\u064e\u0644\u0639\u0650\u06c0 \u0645\u064e\u0631\u0643\u064e\u0632\u06cc"
    ],
    "name:fas_x_variant":[
        "Qal\u2018eh-ye Markaz\u012b"
    ],
    "wof:name":"Qal`eh-ye Markazi",
    "wof:placetype":"locality"
},
  "geometry": {"coordinates":[51.43417,30.85056],"type":"Point"}
}