{
  "type": "Feature",
  "properties": {
    "gn:admin1_code":"8.0",
    "gn:asciiname":"Bala Aquz Bunak",
    "gn:country_code":"IR",
    "gn:dem":471,
    "gn:feature_class":"P",
    "gn:feature_code":"PPL",
    "gn:name":"B\u0101l\u0101 \u0100q\u016bz B\u016bnak",
    "gn:population":0,
    "gn:timezone":"Asia/Tehran",
    "iso:country":"IR",
    "name:fas_x_preferred":[
        "\u0628\u0627\u0644\u0627 \u0622\u0642\u0648\u0632 \u0628\u0648\u0646\u06a9"
    ],
    "name:und_x_variant":[
        "B\u0101l\u0101 \u0100q\u016bz B\u016bnak"
    ],
    "wof:name":"Bala Aquz Bunak",
    "wof:placetype":"locality"
},
  "geometry": {"coordinates":[49.91009,37.05422],"type":"Point"}
}