{
  "type": "Feature",
  "properties": {
    "gn:admin1_code":"1.0",
    "gn:asciiname":"Sabadabad",
    "gn:country_code":"IR",
    "gn:dem":1979,
    "gn:feature_class":"P",
    "gn:feature_code":"PPL",
    "gn:name":"Sabad\u0101b\u0101d",
    "gn:population":0,
    "gn:timezone":"Asia/Tehran",
    "iso:country":"IR",
    "name:fas_x_preferred":[
        "\u0633\u0628\u062f \u0622\u0628\u0627\u062f"
    ],
    "name:fas_x_variant":[
        "Sabad\u0101b\u0101d"
    ],
    "wof:name":"Sabadabad",
    "wof:placetype":"locality"
},
  "geometry": {"coordinates":[45.5021,36.751],"type":"Point"}
}