{
  "type": "Feature",
  "properties": {
    "gn:admin1_code":"9",
    "gn:asciiname":"Bohraz",
    "gn:cc2":"IR",
    "gn:country_code":"IR",
    "gn:dem":1566,
    "gn:feature_class":"P",
    "gn:feature_code":"PPL",
    "gn:name":"Bohr\u0101z",
    "gn:population":0,
    "gn:timezone":"Asia/Tehran",
    "iso:country":"IR",
    "name:fas_x_preferred":[
        "\u0628\u064f\u0647\u0631\u0627\u0632"
    ],
    "name:fas_x_variant":[
        "\u0646\u064f\u0635\u0631\u064e\u062a\u0627\u0628\u0627\u062f\u0650 \u0628\u064f\u0647\u0631\u0627\u0632",
        "\u0646\u064f\u0635\u0631\u064e\u062a \u0622\u0628\u0627\u062f \u0628\u064e\u0647\u0631\u064e\u0632",
        "Bohr\u0101z"
    ],
    "name:und_x_variant":[
        "No\u015frat\u0101b\u0101d Bahraz",
        "No\u015frat\u0101b\u0101d-e Bohr\u0101z"
    ],
    "wof:name":"Bohraz",
    "wof:placetype":"locality"
},
  "geometry": {"coordinates":[48.10222,34.66667],"type":"Point"}
}