{
  "type": "Feature",
  "properties": {
    "gn:admin1_code":"22",
    "gn:asciiname":"Dasht-e Gur",
    "gn:country_code":"IR",
    "gn:dem":134,
    "gn:feature_class":"P",
    "gn:feature_code":"PPL",
    "gn:name":"Dasht-e G\u016br",
    "gn:population":0,
    "gn:timezone":"Asia/Tehran",
    "iso:country":"IR",
    "name:fas_x_preferred":[
        "\u062f\u0634\u062a \u06af\u0648\u0631"
    ],
    "name:fas_x_variant":[
        "\u062f\u064e\u0634\u062a\u0650 \u0643\u0648\u0631",
        "\u062f\u064e\u0634\u062a \u06af\u0648\u0631",
        "Dasht-e G\u016br"
    ],
    "name:und_x_variant":[
        "Dasht G\u016br",
        "Dasht-i-K\u016br",
        "Dasht-e K\u016br"
    ],
    "wof:name":"Dasht-e Gur",
    "wof:placetype":"locality"
},
  "geometry": {"coordinates":[51.0863,29.5526],"type":"Point"}
}