{
  "type": "Feature",
  "properties": {
    "gn:admin1_code":"1",
    "gn:asciiname":"E`tezadiyeh",
    "gn:country_code":"IR",
    "gn:dem":943,
    "gn:feature_class":"P",
    "gn:feature_code":"PPL",
    "gn:name":"E\u2018te\u1e95\u0101d\u012byeh",
    "gn:population":0,
    "gn:timezone":"Asia/Tehran",
    "iso:country":"IR",
    "name:fas_x_preferred":[
        "E\u2018te\u1e95\u0101d\u012byeh"
    ],
    "wof:name":"E`tezadiyeh",
    "wof:placetype":"locality"
},
  "geometry": {"coordinates":[45.23333,38.78333],"type":"Point"}
}