{
  "type": "Feature",
  "properties": {
    "gn:admin1_code":"38.0",
    "gn:asciiname":"`Alan Qiyeh",
    "gn:country_code":"IR",
    "gn:dem":1509,
    "gn:feature_class":"P",
    "gn:feature_code":"PPL",
    "gn:name":"\u2018Alan Q\u012byeh",
    "gn:population":0,
    "gn:timezone":"Asia/Tehran",
    "iso:country":"IR",
    "name:fas_x_preferred":[
        "\u0639\u0644\u0646\u0642\u06cc\u0647"
    ],
    "name:fas_x_variant":[
        "\u2018Al\u012bnqayeh",
        "\u2018Alnaq\u012byah",
        "\u0639\u0644\u0646 \u0642\u06cc\u0647"
    ],
    "name:und_x_variant":[
        "Alanghiyeh",
        "\u2018Al\u012bng\u012byeh",
        "\u2018Alanqayah",
        "\u2018Alanqayeh",
        "Alangir",
        "\u2018Alan Q\u012byeh",
        "\u2018Alanq\u012byeh"
    ],
    "wof:name":"`Alan Qiyeh",
    "wof:placetype":"locality"
},
  "geometry": {"coordinates":[49.6383,36.16557],"type":"Point"}
}