{
  "type": "Feature",
  "properties": {
    "gn:admin1_code":"41.0",
    "gn:asciiname":"Chah Buk",
    "gn:country_code":"IR",
    "gn:dem":1210,
    "gn:feature_class":"P",
    "gn:feature_code":"PPL",
    "gn:name":"Ch\u0101h B\u016bk",
    "gn:population":0,
    "gn:timezone":"Asia/Tehran",
    "iso:country":"IR",
    "name:fas_x_preferred":[
        "\u0686\u0627\u0647 \u0628\u0648\u06a9"
    ],
    "name:fas_x_variant":[
        "Ch\u0101h-e Bok",
        "Ch\u0101h Bok"
    ],
    "name:und_x_variant":[
        "Ch\u0101h Bok",
        "Ch\u0101h B\u016bk",
        "Chabok"
    ],
    "wof:name":"Chah Buk",
    "wof:placetype":"locality"
},
  "geometry": {"coordinates":[60.40184,31.7326],"type":"Point"}
}