{
  "type": "Feature",
  "properties": {
    "gn:admin1_code":"26",
    "gn:asciiname":"Zayegan",
    "gn:country_code":"IR",
    "gn:dem":2230,
    "gn:feature_class":"P",
    "gn:feature_code":"PPL",
    "gn:name":"Z\u0101yeg\u0101n",
    "gn:population":0,
    "gn:timezone":"Asia/Tehran",
    "iso:country":"IR",
    "name:ceb_x_preferred":[
        "Z\u0101yeg\u0101n"
    ],
    "name:fas_x_preferred":[
        "\u0632\u0627\u064a\u06af\u0627\u0646"
    ],
    "name:fas_x_variant":[
        "Z\u0101yeg\u0101n",
        "\u0632\u0627\u06cc\u06af\u0627\u0646"
    ],
    "name:mzn_x_preferred":[
        "\u0632\u0627\u06af\u0648\u0646"
    ],
    "name:swe_x_preferred":[
        "Z\u0101yeg\u0101n"
    ],
    "name:und_x_variant":[
        "Z\u0101yg\u0101n"
    ],
    "wof:name":"Zayegan",
    "wof:placetype":"locality"
},
  "geometry": {"coordinates":[51.587,35.972],"type":"Point"}
}