{
  "type": "Feature",
  "properties": {
    "gn:admin1_code":"16",
    "gn:asciiname":"Cheshmeh Khalil",
    "gn:country_code":"IR",
    "gn:dem":1803,
    "gn:feature_class":"P",
    "gn:feature_code":"PPL",
    "gn:name":"Cheshmeh Khal\u012bl",
    "gn:population":0,
    "gn:timezone":"Asia/Tehran",
    "iso:country":"IR",
    "name:fas_x_preferred":[
        "\u0686\u0634\u0645\u0647 \u062e\u0644\u06cc\u0644"
    ],
    "name:fas_x_variant":[
        "\u0686\u064e\u0634\u0645\u0650\u06c0 \u062e\u064e\u0644\u064a\u0644",
        "\u0686\u064e\u0634\u0645\u0650\u0647 \u062e\u064e\u0644\u064a\u0644",
        "\u0686\u0650\u0634\u0645\u0650\u06c0 \u062e\u064e\u0644\u064a\u0644",
        "Cheshmeh Khal\u012bl"
    ],
    "name:und_x_variant":[
        "Shashma Khalil",
        "Cheshmeh-ye Khal\u012bl",
        "Chashmeh-ye Khal\u012bl",
        "Chashmeh Khal\u012bl"
    ],
    "wof:name":"Cheshmeh Khalil",
    "wof:placetype":"locality"
},
  "geometry": {"coordinates":[47.61798,35.58811],"type":"Point"}
}