{
  "type": "Feature",
  "properties": {
    "gn:admin1_code":"42.0",
    "gn:asciiname":"`Annabestan",
    "gn:country_code":"IR",
    "gn:dem":1421,
    "gn:feature_class":"P",
    "gn:feature_code":"PPL",
    "gn:name":"\u2018Ann\u0101best\u0101n",
    "gn:population":0,
    "gn:timezone":"Asia/Tehran",
    "iso:country":"IR",
    "name:fas_x_preferred":[
        "\u2018Ann\u0101best\u0101n"
    ],
    "name:fas_x_variant":[
        "\u0639\u0646\u0627\u0628\u0633\u062a\u0627\u0646"
    ],
    "wof:name":"`Annabestan",
    "wof:placetype":"locality"
},
  "geometry": {"coordinates":[57.86016,36.37349],"type":"Point"}
}