{
  "type": "Feature",
  "properties": {
    "gn:admin1_code":"29",
    "gn:asciiname":"Rig-e Bahram",
    "gn:country_code":"IR",
    "gn:dem":455,
    "gn:feature_class":"P",
    "gn:feature_code":"PPL",
    "gn:name":"R\u012bg-e Bahr\u0101m",
    "gn:population":0,
    "gn:timezone":"Asia/Tehran",
    "iso:country":"IR",
    "name:fas_x_preferred":[
        "\u0631\u06cc\u06af \u0628\u0647\u0631\u0627\u0645"
    ],
    "name:fas_x_variant":[
        "R\u012bg-e Bahr\u0101m"
    ],
    "wof:name":"Rig-e Bahram",
    "wof:placetype":"locality"
},
  "geometry": {"coordinates":[57.9206,27.8944],"type":"Point"}
}