{
  "type": "Feature",
  "properties": {
    "gn:admin1_code":"7",
    "gn:asciiname":"Hajjiabad",
    "gn:cc2":"IR",
    "gn:country_code":"IR",
    "gn:dem":1955,
    "gn:feature_class":"P",
    "gn:feature_code":"PPL",
    "gn:name":"\u1e28\u0101jj\u012b\u0101b\u0101d",
    "gn:population":0,
    "gn:timezone":"Asia/Tehran",
    "iso:country":"IR",
    "name:fas_x_preferred":[
        "\u1e28\u0101jj\u012b\u0101b\u0101d"
    ],
    "name:und_x_variant":[
        "\u1e28\u0101j\u012b\u0101b\u0101d"
    ],
    "wof:name":"Hajjiabad",
    "wof:placetype":"locality"
},
  "geometry": {"coordinates":[52.21667,30.11667000000001],"type":"Point"}
}