{
  "type": "Feature",
  "properties": {
    "gn:admin1_code":"8",
    "gn:asciiname":"Golab Posht",
    "gn:country_code":"IR",
    "gn:dem":43,
    "gn:feature_class":"P",
    "gn:feature_code":"PPLF",
    "gn:name":"Gol\u0101b Posht",
    "gn:population":0,
    "gn:timezone":"Asia/Tehran",
    "iso:country":"IR",
    "name:fas_x_preferred":[
        "\u06af\u0644\u0627\u0628 \u067e\u0634\u062a"
    ],
    "name:fas_x_variant":[
        "Gol\u0101b Posht"
    ],
    "name:und_x_variant":[
        "Gol\u0101b Posht"
    ],
    "wof:name":"Golab Posht",
    "wof:placetype":"locality"
},
  "geometry": {"coordinates":[49.28207,37.24267],"type":"Point"}
}