{
  "type": "Feature",
  "properties": {
    "gn:admin1_code":"16",
    "gn:asciiname":"Harmedal",
    "gn:country_code":"IR",
    "gn:dem":1802,
    "gn:feature_class":"P",
    "gn:feature_code":"PPL",
    "gn:name":"Harmedal",
    "gn:population":0,
    "gn:timezone":"Asia/Tehran",
    "iso:country":"IR",
    "name:ara_x_preferred":[
        "\u0647\u0631\u0645\u064a \u062f\u0648\u0644"
    ],
    "name:ceb_x_preferred":[
        "Harmedal"
    ],
    "name:ckb_x_preferred":[
        "\u06be\u06d5\u0631\u0645\u06ce \u062f\u06c6\u06b5"
    ],
    "name:fas_x_preferred":[
        "\u0647\u064e\u0631\u0645\u0650\u0647 \u062f\u0648\u0644"
    ],
    "name:fas_x_variant":[
        "\u06af\u064e\u0631\u0645\u0650\u06c0 \u062f\u0648\u0644",
        "\u06af\u064e\u0631\u0645\u064e\u062f\u064f\u0644",
        "\u0647\u064e\u0631\u0645\u0650\u062f\u064f\u0644",
        "\u0647\u0631\u0645\u064a\u062f\u0648\u0644",
        "\u0647\u0631\u0645\u062f\u0644",
        "Harmeh D\u016bl",
        "\u0647\u0631\u0645\u06cc\u062f\u0648\u0644"
    ],
    "name:kur_x_preferred":[
        "Herm\u00eadol"
    ],
    "name:swe_x_preferred":[
        "Harmedal"
    ],
    "name:und_x_variant":[
        "Garmadol",
        "Harm\u012bd\u016bl",
        "Garmeh-ye D\u016bl",
        "Harmedol",
        "Harmedal"
    ],
    "wof:name":"Harmedal",
    "wof:placetype":"locality"
},
  "geometry": {"coordinates":[46.2008,35.88],"type":"Point"}
}