{
  "type": "Feature",
  "properties": {
    "gn:admin1_code":"4.0",
    "gn:asciiname":"Kondorak",
    "gn:country_code":"IR",
    "gn:dem":484,
    "gn:feature_class":"P",
    "gn:feature_code":"PPL",
    "gn:name":"Kondorak",
    "gn:population":0,
    "gn:timezone":"Asia/Tehran",
    "iso:country":"IR",
    "name:fas_x_preferred":[
        "\u06a9\u0646\u062f\u0631\u06a9"
    ],
    "name:fas_x_variant":[
        "\u06a9\u0631\u062a\u06a9\u0647"
    ],
    "name:und_x_variant":[
        "Kartakeh",
        "Kondorak"
    ],
    "wof:name":"Kondorak",
    "wof:placetype":"locality"
},
  "geometry": {"coordinates":[61.5569,30.9102],"type":"Point"}
}