{
  "type": "Feature",
  "properties": {
    "gn:admin1_code":"15",
    "gn:asciiname":"Mowluli",
    "gn:country_code":"IR",
    "gn:dem":733,
    "gn:feature_class":"P",
    "gn:feature_code":"PPL",
    "gn:name":"Mowl\u016bl\u012b",
    "gn:population":0,
    "gn:timezone":"Asia/Tehran",
    "iso:country":"IR",
    "name:azb_x_preferred":[
        "\u0645\u0648\u0644\u0644\u06cc(\u0627\u06cc\u0630\u0647)"
    ],
    "name:fas_x_preferred":[
        "M\u016blal\u012b"
    ],
    "name:fas_x_variant":[
        "Mowl\u016bl\u012b",
        "\u0645\u0648\u0644\u0648\u0644\u06cc",
        "\u0645\u0648\u0644\u0644\u06cc"
    ],
    "wof:name":"Mowluli",
    "wof:placetype":"locality"
},
  "geometry": {"coordinates":[50.03667,31.94621],"type":"Point"}
}