{
  "type": "Feature",
  "properties": {
    "gn:admin1_code":"15.0",
    "gn:asciiname":"Shahrak-e Meysam",
    "gn:country_code":"IR",
    "gn:dem":622,
    "gn:feature_class":"P",
    "gn:feature_code":"PPL",
    "gn:name":"Shahrak-e Meys\u0304am",
    "gn:population":0,
    "gn:timezone":"Asia/Tehran",
    "iso:country":"IR",
    "name:fas_x_preferred":[
        "\u0634\u0647\u0631\u06a9 \u0631\u0634\u0645"
    ],
    "name:fas_x_variant":[
        "\u0634\u0647\u0631\u06a9 \u0645\u06cc\u062b\u0645"
    ],
    "name:und_x_variant":[
        "Shahrak-e Rashm",
        "Shahrak-e Meys\u0304am"
    ],
    "wof:name":"Shahrak-e Meysam",
    "wof:placetype":"locality"
},
  "geometry": {"coordinates":[49.48685,32.05184000000001],"type":"Point"}
}