{
  "type": "Feature",
  "properties": {
    "gn:admin1_code":"28.0",
    "gn:asciiname":"Kaj",
    "gn:country_code":"IR",
    "gn:dem":1540,
    "gn:feature_class":"P",
    "gn:feature_code":"PPL",
    "gn:name":"K\u0101j",
    "gn:population":0,
    "gn:timezone":"Asia/Tehran",
    "iso:country":"IR",
    "name:fas_x_preferred":[
        "K\u0101j"
    ],
    "name:fas_x_variant":[
        "\u06a9\u0627\u062c"
    ],
    "name:und_x_variant":[
        "\u06a9\u0627\u062c"
    ],
    "wof:name":"Kaj",
    "wof:placetype":"locality"
},
  "geometry": {"coordinates":[51.83403,32.53905],"type":"Point"}
}