{
  "type": "Feature",
  "properties": {
    "gn:admin1_code":"16",
    "gn:asciiname":"Dar Tut",
    "gn:country_code":"IR",
    "gn:dem":1606,
    "gn:feature_class":"P",
    "gn:feature_code":"PPL",
    "gn:name":"D\u0101r T\u016bt",
    "gn:population":0,
    "gn:timezone":"Asia/Tehran",
    "iso:country":"IR",
    "name:fas_x_preferred":[
        "\u062f\u0627\u0631 \u062a\u0648\u062a"
    ],
    "name:fas_x_variant":[
        "\u062f\u0627\u0631\u062a\u0648\u062a",
        "D\u0101r T\u016bt"
    ],
    "wof:name":"Dar Tut",
    "wof:placetype":"locality"
},
  "geometry": {"coordinates":[47.0126,34.7781],"type":"Point"}
}