{
  "type": "Feature",
  "properties": {
    "gn:admin1_code":"34",
    "gn:asciiname":"Shahsavaran",
    "gn:country_code":"IR",
    "gn:dem":1679,
    "gn:feature_class":"P",
    "gn:feature_code":"PPL",
    "gn:name":"Sh\u0101hsav\u0101r\u0101n",
    "gn:population":0,
    "gn:timezone":"Asia/Tehran",
    "iso:country":"IR",
    "name:ara_x_preferred":[
        "\u0634\u0647\u0633\u0648\u0627\u0631\u0627\u0646"
    ],
    "name:ceb_x_preferred":[
        "Sh\u0101hsav\u0101r\u0101n"
    ],
    "name:fas_x_preferred":[
        "\u0634\u0627\u0647\u0633\u064e\u0648\u0627\u0631"
    ],
    "name:fas_x_variant":[
        "Sh\u0101hsav\u0101r\u0101n",
        "\u0634\u0627\u0647\u0633\u0648\u0627\u0631\u0627\u0646",
        "\u0634\u0647\u0633\u0648\u0627\u0631\u0627\u0646"
    ],
    "name:swe_x_preferred":[
        "Sh\u0101hsav\u0101r\u0101n"
    ],
    "name:ukr_x_preferred":[
        "\u0428\u0430\u0433\u0441\u0430\u0432\u0430\u0440\u0430\u043d"
    ],
    "name:und_x_variant":[
        "Sh\u0101hsav\u0101r"
    ],
    "wof:name":"Shahsavaran",
    "wof:placetype":"locality"
},
  "geometry": {"coordinates":[50.02181,34.17335],"type":"Point"}
}