{
  "type": "Feature",
  "properties": {
    "gn:admin1_code":"11",
    "gn:asciiname":"Guru Finu",
    "gn:country_code":"IR",
    "gn:dem":1376,
    "gn:feature_class":"P",
    "gn:feature_code":"PPL",
    "gn:name":"G\u016br\u016b F\u012bn\u016b",
    "gn:population":0,
    "gn:timezone":"Asia/Tehran",
    "iso:country":"IR",
    "name:fas_x_preferred":[
        "\u06af\u0648\u0631\u0648 \u0641\u064a\u0646\u0648"
    ],
    "name:fas_x_variant":[
        "G\u016br\u016b F\u012bn\u016b"
    ],
    "wof:name":"Guru Finu",
    "wof:placetype":"locality"
},
  "geometry": {"coordinates":[56.17972,27.89667],"type":"Point"}
}