{
  "type": "Feature",
  "properties": {
    "gn:admin1_code":"32",
    "gn:asciiname":"Nilaq",
    "gn:country_code":"IR",
    "gn:dem":1394,
    "gn:feature_class":"P",
    "gn:feature_code":"PPL",
    "gn:name":"N\u012blaq",
    "gn:population":0,
    "gn:timezone":"Asia/Tehran",
    "iso:country":"IR",
    "name:fas_x_preferred":[
        "\u0646\u06cc\u0644\u0642"
    ],
    "name:fas_x_variant":[
        "N\u012blaq"
    ],
    "name:und_x_variant":[
        "Lailia",
        "Neylaq",
        "Leyleyeh",
        "Ley-lya"
    ],
    "wof:name":"Nilaq",
    "wof:placetype":"locality"
},
  "geometry": {"coordinates":[48.20157,37.70228],"type":"Point"}
}