{
  "type": "Feature",
  "properties": {
    "gn:admin1_code":"23",
    "gn:asciiname":"Tang Namak",
    "gn:country_code":"IR",
    "gn:dem":1474,
    "gn:feature_class":"P",
    "gn:feature_code":"PPL",
    "gn:name":"Tang Namak",
    "gn:population":0,
    "gn:timezone":"Asia/Tehran",
    "iso:country":"IR",
    "name:fas_x_preferred":[
        "\u0631\u064f\u0643 \u0631\u064f\u0643"
    ],
    "name:fas_x_variant":[
        "\u0631\u064f\u0643 \u0631\u064f\u0643 \u062a\u064e\u0646\u06af\u0650 \u0646\u064e\u0645\u064e\u0643",
        "\u062a\u0646\u06af \u0646\u0645\u06a9"
    ],
    "name:und_x_variant":[
        "Rok Rok",
        "Tang-i-Namak",
        "Rok Rok Tang-e Namak",
        "Tang Namak"
    ],
    "wof:name":"Tang Namak",
    "wof:placetype":"locality"
},
  "geometry": {"coordinates":[48.4768,33.5471],"type":"Point"}
}