{
  "type": "Feature",
  "properties": {
    "gn:admin1_code":"32.0",
    "gn:asciiname":"Tirid",
    "gn:country_code":"IR",
    "gn:dem":151,
    "gn:feature_class":"P",
    "gn:feature_code":"PPL",
    "gn:name":"T\u012br\u012bd",
    "gn:population":0,
    "gn:timezone":"Asia/Tehran",
    "iso:country":"IR",
    "name:fas_x_preferred":[
        "\u062a\u06cc\u0631\u06cc\u062f"
    ],
    "name:fas_x_variant":[
        "T\u012br\u012bd"
    ],
    "wof:name":"Tirid",
    "wof:placetype":"locality"
},
  "geometry": {"coordinates":[47.4307,39.4583],"type":"Point"}
}