{
  "type": "Feature",
  "properties": {
    "gn:admin1_code":"23",
    "gn:asciiname":"Mamulah",
    "gn:country_code":"IR",
    "gn:dem":1866,
    "gn:feature_class":"P",
    "gn:feature_code":"PPL",
    "gn:name":"Mam\u016blah",
    "gn:population":0,
    "gn:timezone":"Asia/Tehran",
    "iso:country":"IR",
    "name:ara_x_preferred":[
        "\u0645\u0639\u0645\u0648\u0644\u0647"
    ],
    "name:fas_x_preferred":[
        "\u0645\u064e\u0645\u0648\u0644\u064e\u0647"
    ],
    "name:fas_x_variant":[
        "\u0645\u0645\u0648\u0644\u0647",
        "Mam\u016blah",
        "\u0645\u0639\u0645\u0648\u0644\u0647"
    ],
    "wof:name":"Mamulah",
    "wof:placetype":"locality"
},
  "geometry": {"coordinates":[47.7853,34.2758],"type":"Point"}
}