{
  "type": "Feature",
  "properties": {
    "gn:admin1_code":"41",
    "gn:asciiname":"Mazra`eh-ye Malekabad",
    "gn:country_code":"IR",
    "gn:dem":1892,
    "gn:feature_class":"P",
    "gn:feature_code":"PPLF",
    "gn:name":"Mazra\u2018eh-ye Malek\u0101b\u0101d",
    "gn:population":0,
    "gn:timezone":"Asia/Tehran",
    "iso:country":"IR",
    "name:fas_x_preferred":[
        "Malek\u0101b\u0101d"
    ],
    "name:fas_x_variant":[
        "\u0645\u0644\u06a9 \u0622\u0628\u0627\u062f",
        "\u0645\u0632\u0631\u0639\u0647 \u0645\u0644\u06a9 \u0622\u0628\u0627\u062f"
    ],
    "name:und_x_variant":[
        "\u0645\u0644\u06a9 \u0622\u0628\u0627\u062f",
        "Mazra\u2018eh-ye Malek\u0101b\u0101d"
    ],
    "wof:name":"Mazra`eh-ye Malekabad",
    "wof:placetype":"locality"
},
  "geometry": {"coordinates":[58.72448000000001,33.91982],"type":"Point"}
}