{
  "type": "Feature",
  "properties": {
    "gn:admin1_code":"38",
    "gn:asciiname":"Kaneshkin",
    "gn:country_code":"IR",
    "gn:dem":1574,
    "gn:feature_class":"P",
    "gn:feature_code":"PPL",
    "gn:name":"Kaneshk\u012bn",
    "gn:population":0,
    "gn:timezone":"Asia/Tehran",
    "iso:country":"IR",
    "name:fas_x_preferred":[
        "\u06a9\u0646\u0634\u06a9\u06cc\u0646"
    ],
    "name:fas_x_variant":[
        "\u06a9\u0634\u06af\u06cc\u0646",
        "Kaneshk\u012bn",
        "Kashg\u012bn"
    ],
    "name:und_x_variant":[
        "Kereshkin",
        "Kanishk\u012bn",
        "K\u012bshk\u012bn",
        "Kaneshg\u012bn"
    ],
    "wof:name":"Kaneshkin",
    "wof:placetype":"locality"
},
  "geometry": {"coordinates":[49.58267,36.24393],"type":"Point"}
}