{
  "type": "Feature",
  "properties": {
    "gn:admin1_code":"16",
    "gn:asciiname":"Shahrak",
    "gn:country_code":"IR",
    "gn:dem":2096,
    "gn:feature_class":"P",
    "gn:feature_code":"PPL",
    "gn:name":"Shahrak",
    "gn:population":0,
    "gn:timezone":"Asia/Tehran",
    "iso:country":"IR",
    "name:fas_x_preferred":[
        "\u0634\u0647\u0631\u0643"
    ],
    "wof:name":"Shahrak",
    "wof:placetype":"locality"
},
  "geometry": {"coordinates":[47.52646,36.4152],"type":"Point"}
}