{
  "type": "Feature",
  "properties": {
    "gn:admin1_code":"8.0",
    "gn:asciiname":"Naka Khani",
    "gn:country_code":"IR",
    "gn:dem":2317,
    "gn:feature_class":"P",
    "gn:feature_code":"PPL",
    "gn:name":"N\u0101k\u0101 Kh\u0101n\u012b",
    "gn:population":0,
    "gn:timezone":"Asia/Tehran",
    "iso:country":"IR",
    "name:fas_x_preferred":[
        "N\u0101k\u0101 Kh\u0101n\u012b"
    ],
    "name:fas_x_variant":[
        "\u0646\u0627\u06a9\u0627 \u062e\u0627\u0646\u06cc"
    ],
    "wof:name":"Naka Khani",
    "wof:placetype":"locality"
},
  "geometry": {"coordinates":[50.10724,36.72529],"type":"Point"}
}