{
  "type": "Feature",
  "properties": {
    "gn:admin1_code":"32",
    "gn:asciiname":"Dushan Bolaghi",
    "gn:country_code":"IR",
    "gn:dem":1420,
    "gn:feature_class":"P",
    "gn:feature_code":"PPL",
    "gn:name":"D\u016bsh\u0101n Bol\u0101gh\u012b",
    "gn:population":0,
    "gn:timezone":"Asia/Tehran",
    "iso:country":"IR",
    "name:azb_x_preferred":[
        "\u062f\u0648\u0634\u0627\u0646 \u0628\u0648\u0644\u0627\u063a\u06cc(\u0646\u0645\u06cc\u0646)"
    ],
    "name:ceb_x_preferred":[
        "D\u016bsh\u0101n Bol\u0101gh\u012b"
    ],
    "name:fas_x_preferred":[
        "\u062f\u0648\u0634\u0627\u0646 \u0628\u0644\u0627\u063a\u06cc"
    ],
    "name:fas_x_variant":[
        "D\u016bsh\u0101n Bol\u0101gh\u012b"
    ],
    "name:msa_x_preferred":[
        "Dushan Bolaghi"
    ],
    "name:swe_x_preferred":[
        "D\u016bsh\u0101n Bol\u0101gh\u012b"
    ],
    "wof:name":"Dushan Bolaghi",
    "wof:placetype":"locality"
},
  "geometry": {"coordinates":[48.322,38.4639],"type":"Point"}
}