{
  "type": "Feature",
  "properties": {
    "gn:admin1_code":"35",
    "gn:asciiname":"Kheyr Sar",
    "gn:country_code":"IR",
    "gn:dem":17,
    "gn:feature_class":"P",
    "gn:feature_code":"PPL",
    "gn:name":"Kheyr Sar",
    "gn:population":0,
    "gn:timezone":"Asia/Tehran",
    "iso:country":"IR",
    "name:fas_x_preferred":[
        "Kh\u012breh Sar"
    ],
    "name:fas_x_variant":[
        "\u062e\u064a\u0631\u0647 \u0633\u0631",
        "\u062e\u06cc\u0631 \u0633\u0631"
    ],
    "name:und_x_variant":[
        "Kareh Sar",
        "Kashk Sar\u0101",
        "Kheyr Sar"
    ],
    "wof:name":"Kheyr Sar",
    "wof:placetype":"locality"
},
  "geometry": {"coordinates":[51.48618,36.6256],"type":"Point"}
}