{
  "type": "Feature",
  "properties": {
    "gn:admin1_code":"28.0",
    "gn:asciiname":"Hormozabad",
    "gn:country_code":"IR",
    "gn:dem":1545,
    "gn:feature_class":"P",
    "gn:feature_code":"PPL",
    "gn:name":"Hormoz\u0101b\u0101d",
    "gn:population":0,
    "gn:timezone":"Asia/Tehran",
    "iso:country":"IR",
    "name:fas_x_preferred":[
        "Hormoz\u0101b\u0101d"
    ],
    "name:und_x_variant":[
        "\u0647\u0631\u0645\u0632 \u0622\u0628\u0627\u062f"
    ],
    "wof:name":"Hormozabad",
    "wof:placetype":"locality"
},
  "geometry": {"coordinates":[51.865,32.47833],"type":"Point"}
}