{
  "type": "Feature",
  "properties": {
    "gn:admin1_code":"29",
    "gn:asciiname":"Allahabad",
    "gn:country_code":"IR",
    "gn:dem":389,
    "gn:feature_class":"P",
    "gn:feature_code":"PPL",
    "gn:name":"All\u0101h\u0101b\u0101d",
    "gn:population":0,
    "gn:timezone":"Asia/Tehran",
    "iso:country":"IR",
    "name:fas_x_preferred":[
        "\u0633\u0627\u0646\u06a9 \u0622\u0628\u0627\u062f"
    ],
    "name:fas_x_variant":[
        "S\u0101nek\u0101b\u0101d",
        "\u0627\u0644\u0644\u0647 \u0622\u0628\u0627\u062f"
    ],
    "name:und_x_variant":[
        "All\u0101h\u0101b\u0101d"
    ],
    "wof:name":"Allahabad",
    "wof:placetype":"locality"
},
  "geometry": {"coordinates":[58.55725,27.77468],"type":"Point"}
}