{
  "type": "Feature",
  "properties": {
    "gn:admin1_code":"8",
    "gn:asciiname":"Kama",
    "gn:country_code":"IR",
    "gn:dem":21,
    "gn:feature_class":"P",
    "gn:feature_code":"PPL",
    "gn:name":"Kam\u0101",
    "gn:population":0,
    "gn:timezone":"Asia/Tehran",
    "iso:country":"IR",
    "name:fas_x_preferred":[
        "\u06a9\u0645\u0627"
    ],
    "name:fas_x_variant":[
        "Kam\u0101"
    ],
    "name:und_x_variant":[
        "Kam\u0101"
    ],
    "wof:name":"Kama",
    "wof:placetype":"locality"
},
  "geometry": {"coordinates":[49.27871,37.27674],"type":"Point"}
}