{
  "type": "Feature",
  "properties": {
    "gn:admin1_code":"23",
    "gn:asciiname":"Taj Amir",
    "gn:country_code":"IR",
    "gn:dem":1918,
    "gn:feature_class":"P",
    "gn:feature_code":"PPL",
    "gn:name":"T\u0101j Am\u012br",
    "gn:population":0,
    "gn:timezone":"Asia/Tehran",
    "iso:country":"IR",
    "name:ara_x_preferred":[
        "\u062a\u0627\u062c \u0627\u0645\u064a\u0631"
    ],
    "name:ceb_x_preferred":[
        "T\u0101j Am\u012br"
    ],
    "name:fas_x_preferred":[
        "T\u0101j Am\u012br"
    ],
    "name:fas_x_variant":[
        "\u062a\u0627\u062c \u0627\u0645\u06cc\u0631"
    ],
    "name:swe_x_preferred":[
        "T\u0101j Am\u012br"
    ],
    "wof:name":"Taj Amir",
    "wof:placetype":"locality"
},
  "geometry": {"coordinates":[48.16306,34.0213],"type":"Point"}
}