{
  "type": "Feature",
  "properties": {
    "gn:admin1_code":"7.0",
    "gn:asciiname":"Tolombeh-ye Karimi",
    "gn:country_code":"IR",
    "gn:dem":809,
    "gn:feature_class":"P",
    "gn:feature_code":"PPL",
    "gn:name":"Tolombeh-ye Kar\u012bm\u012b",
    "gn:population":0,
    "gn:timezone":"Asia/Tehran",
    "iso:country":"IR",
    "name:fas_x_preferred":[
        "Tolombeh-ye Kar\u012bm\u012b"
    ],
    "name:fas_x_variant":[
        "\u062a\u0644\u0645\u0628\u0647 \u06a9\u0631\u06cc\u0645\u06cc"
    ],
    "name:msa_x_preferred":[
        "Tolombeh-ye Karimi"
    ],
    "name:und_x_variant":[
        "\u062a\u0644\u0645\u0628\u0647 \u06a9\u0631\u06cc\u0645\u06cc"
    ],
    "wof:name":"Tolombeh-ye Karimi",
    "wof:placetype":"locality"
},
  "geometry": {"coordinates":[51.58794,29.61109],"type":"Point"}
}