{
  "type": "Feature",
  "properties": {
    "gn:admin1_code":"5",
    "gn:asciiname":"Taparqu",
    "gn:country_code":"IR",
    "gn:dem":2107,
    "gn:feature_class":"P",
    "gn:feature_code":"PPL",
    "gn:name":"Taparq\u016b",
    "gn:population":0,
    "gn:timezone":"Asia/Tehran",
    "iso:country":"IR",
    "name:fas_x_preferred":[
        "\u0633\u0650\u0647 \u06af\u0650\u0644\u06cc"
    ],
    "name:fas_x_variant":[
        "Seh Gel\u012b",
        "Taparq\u016b",
        "\u062a\u067e\u0631\u0642\u0648"
    ],
    "name:und_x_variant":[
        "Taparq\u016b",
        "\u062a\u067e\u0631\u0642\u0648"
    ],
    "wof:name":"Taparqu",
    "wof:placetype":"locality"
},
  "geometry": {"coordinates":[51.5056,30.61311],"type":"Point"}
}