{
  "type": "Feature",
  "properties": {
    "gn:admin1_code":"23.0",
    "gn:asciiname":"Rusta-ye Fasli-ye Pakabud",
    "gn:country_code":"IR",
    "gn:dem":974,
    "gn:feature_class":"P",
    "gn:feature_code":"PPL",
    "gn:name":"R\u016bst\u0101-ye Fa\u015fl\u012b-ye P\u0101kab\u016bd",
    "gn:population":0,
    "gn:timezone":"Asia/Tehran",
    "iso:country":"IR",
    "name:fas_x_preferred":[
        "\u0631\u0648\u0633\u062a\u0627\u06cc \u0641\u0635\u0644\u06cc \u067e\u0627\u06a9\u0628\u0648\u062f"
    ],
    "name:und_x_variant":[
        "R\u016bst\u0101-ye Fa\u015fl\u012b-ye P\u0101kab\u016bd"
    ],
    "wof:name":"Rusta-ye Fasli-ye Pakabud",
    "wof:placetype":"locality"
},
  "geometry": {"coordinates":[48.84485,33.17493],"type":"Point"}
}