{
  "type": "Feature",
  "properties": {
    "gn:admin1_code":"8",
    "gn:asciiname":"`Ayuz Sara",
    "gn:country_code":"IR",
    "gn:dem":-15,
    "gn:feature_class":"P",
    "gn:feature_code":"PPL",
    "gn:name":"\u2018Ay\u016b\u1e95 Sar\u0101",
    "gn:population":0,
    "gn:timezone":"Asia/Tehran",
    "iso:country":"IR",
    "name:fas_x_preferred":[
        "\u0639\u06cc\u0648\u0636 \u0633\u0631\u0627"
    ],
    "name:fas_x_variant":[
        "\u2018Ay\u016b\u1e95 Sar\u0101"
    ],
    "wof:name":"`Ayuz Sara",
    "wof:placetype":"locality"
},
  "geometry": {"coordinates":[49.05084,37.65263],"type":"Point"}
}