{
  "type": "Feature",
  "properties": {
    "gn:admin1_code":"28",
    "gn:asciiname":"Ramsheh",
    "gn:country_code":"IR",
    "gn:dem":1552,
    "gn:feature_class":"P",
    "gn:feature_code":"PPL",
    "gn:name":"R\u0101msheh",
    "gn:population":0,
    "gn:timezone":"Asia/Tehran",
    "iso:country":"IR",
    "name:fas_x_preferred":[
        "\u0631\u0627\u0645\u0634\u0647"
    ],
    "name:fas_x_variant":[
        "R\u0101msheh"
    ],
    "name:und_x_variant":[
        "R\u0101mshah",
        "R\u016bm Sh\u0101h"
    ],
    "wof:name":"Ramsheh",
    "wof:placetype":"locality"
},
  "geometry": {"coordinates":[52.5021,31.8257],"type":"Point"}
}