{
  "type": "Feature",
  "properties": {
    "gn:admin1_code":"22",
    "gn:asciiname":"Heydari",
    "gn:country_code":"IR",
    "gn:dem":13,
    "gn:feature_class":"P",
    "gn:feature_code":"PPL",
    "gn:name":"\u1e28eydar\u012b",
    "gn:population":0,
    "gn:timezone":"Asia/Tehran",
    "iso:country":"IR",
    "name:fas_x_preferred":[
        "\u062d\u064a\u062f\u0631\u06cc"
    ],
    "name:fas_x_variant":[
        "\u1e28eydar\u012b"
    ],
    "name:und_x_variant":[
        "Heidari Alkali"
    ],
    "wof:name":"Heydari",
    "wof:placetype":"locality"
},
  "geometry": {"coordinates":[50.978,29.2796],"type":"Point"}
}