{
  "type": "Feature",
  "properties": {
    "gn:admin1_code":"7.0",
    "gn:asciiname":"Ab Garm",
    "gn:cc2":"IR",
    "gn:country_code":"IR",
    "gn:dem":1502,
    "gn:feature_class":"P",
    "gn:feature_code":"PPL",
    "gn:name":"\u0100b Garm",
    "gn:population":0,
    "gn:timezone":"Asia/Tehran",
    "iso:country":"IR",
    "name:fas_x_preferred":[
        "\u0100b Garm"
    ],
    "name:und_x_variant":[
        "\u0100b-i-Garm"
    ],
    "wof:name":"Ab Garm",
    "wof:placetype":"locality"
},
  "geometry": {"coordinates":[52.88333000000001,29.13333],"type":"Point"}
}