{
  "type": "Feature",
  "properties": {
    "gn:admin1_code":"1",
    "gn:asciiname":"Hendovan",
    "gn:country_code":"IR",
    "gn:dem":1919,
    "gn:feature_class":"P",
    "gn:feature_code":"PPL",
    "gn:name":"Hendov\u0101n",
    "gn:population":0,
    "gn:timezone":"Asia/Tehran",
    "iso:country":"IR",
    "name:fas_x_preferred":[
        "\u0647\u0646\u062f\u0648\u0627\u0646"
    ],
    "name:fas_x_variant":[
        "Hendv\u0101n",
        "Hendov\u0101n"
    ],
    "wof:name":"Hendovan",
    "wof:placetype":"locality"
},
  "geometry": {"coordinates":[44.6587,38.5176],"type":"Point"}
}