{
  "type": "Feature",
  "properties": {
    "gn:admin1_code":"15",
    "gn:asciiname":"Murd-e Fal",
    "gn:country_code":"IR",
    "gn:dem":631,
    "gn:feature_class":"P",
    "gn:feature_code":"PPL",
    "gn:name":"M\u016brd-e Fal",
    "gn:population":0,
    "gn:timezone":"Asia/Tehran",
    "iso:country":"IR",
    "name:fas_x_preferred":[
        "M\u016brd-e Fal"
    ],
    "name:fas_x_variant":[
        "\u0645\u0648\u0631\u062f \u0641\u0644",
        "\u0628\u0646\u0647 \u0631\u062d\u0645\u0627\u0644\u06cc"
    ],
    "name:und_x_variant":[
        "M\u016brdfal",
        "Moordfel",
        "Boneh Ra\u1e29m\u0101l\u012b"
    ],
    "wof:name":"Murd-e Fal",
    "wof:placetype":"locality"
},
  "geometry": {"coordinates":[49.68359,31.81241],"type":"Point"}
}