{
  "type": "Feature",
  "properties": {
    "gn:admin1_code":"23",
    "gn:asciiname":"Khodavardi",
    "gn:country_code":"IR",
    "gn:dem":1432,
    "gn:feature_class":"P",
    "gn:feature_code":"PPL",
    "gn:name":"Khod\u0101vard\u012b",
    "gn:population":0,
    "gn:timezone":"Asia/Tehran",
    "iso:country":"IR",
    "name:fas_x_preferred":[
        "\u062e\u064f\u0631\u062f\u06cc"
    ],
    "name:fas_x_variant":[
        "Khord\u012b",
        "\u062e\u062f\u0627\u0648\u0631\u062f\u06cc"
    ],
    "name:und_x_variant":[
        "Khod\u0101vard\u012b"
    ],
    "wof:name":"Khodavardi",
    "wof:placetype":"locality"
},
  "geometry": {"coordinates":[47.79897,33.86799],"type":"Point"}
}