{
  "type": "Feature",
  "properties": {
    "gn:admin1_code":"32.0",
    "gn:asciiname":"Hajji Mirvardi Kandi",
    "gn:country_code":"IR",
    "gn:dem":529,
    "gn:feature_class":"P",
    "gn:feature_code":"PPL",
    "gn:name":"\u1e28\u0101jj\u012b M\u012brvard\u012b Kand\u012b",
    "gn:population":0,
    "gn:timezone":"Asia/Tehran",
    "iso:country":"IR",
    "wof:name":"Hajji Mirvardi Kandi",
    "wof:placetype":"locality"
},
  "geometry": {"coordinates":[47.78556,39.23556],"type":"Point"}
}