{
  "type": "Feature",
  "properties": {
    "gn:admin1_code":"15.0",
    "gn:asciiname":"Al-e Tayyeb",
    "gn:country_code":"IR",
    "gn:dem":336,
    "gn:feature_class":"P",
    "gn:feature_code":"PPL",
    "gn:name":"\u0100l-e \u0162ayyeb",
    "gn:population":0,
    "gn:timezone":"Asia/Tehran",
    "iso:country":"IR",
    "name:azb_x_preferred":[
        "\u0627\u0644 \u0637\u06cc\u0628(\u0628\u0647\u0628\u0647\u0627\u0646)"
    ],
    "name:ceb_x_preferred":[
        "\u0100l-e \u0162ayyeb"
    ],
    "name:fas_x_preferred":[
        "\u0622\u0644 \u0637\u06cc\u0628"
    ],
    "name:fas_x_variant":[
        "\u0100l-e \u0162ayyeb",
        "\u0622\u0644\u200c\u0637\u06cc\u0628"
    ],
    "name:swe_x_preferred":[
        "\u0100l-e \u0162ayyeb"
    ],
    "name:und_x_variant":[
        "\u2018Al\u012b Tay\u0101b",
        "\u2018Al\u012b \u0162ayeb\u012b",
        "\u2018Al\u012b T\u012b\u0101b"
    ],
    "wof:name":"Al-e Tayyeb",
    "wof:placetype":"locality"
},
  "geometry": {"coordinates":[50.194,30.7416],"type":"Point"}
}