{
  "type": "Feature",
  "properties": {
    "gn:admin1_code":"10.0",
    "gn:asciiname":"Gowhar",
    "gn:country_code":"IR",
    "gn:dem":1132,
    "gn:feature_class":"P",
    "gn:feature_code":"PPL",
    "gn:name":"Gowhar",
    "gn:population":0,
    "gn:timezone":"Asia/Tehran",
    "iso:country":"IR",
    "name:ceb_x_preferred":[
        "Gowhar"
    ],
    "name:fas_x_preferred":[
        "\u06af\u064f\u0648\u0647\u064e\u0631"
    ],
    "name:swe_x_preferred":[
        "Gowhar"
    ],
    "wof:name":"Gowhar",
    "wof:placetype":"locality"
},
  "geometry": {"coordinates":[46.23333,33.85],"type":"Point"}
}