{
  "type": "Feature",
  "properties": {
    "gn:admin1_code":"15",
    "gn:asciiname":"Saleh Hamid",
    "gn:country_code":"IR",
    "gn:dem":872,
    "gn:feature_class":"P",
    "gn:feature_code":"PPL",
    "gn:name":"\u015e\u0101le\u1e29 \u1e28am\u012bd",
    "gn:population":0,
    "gn:timezone":"Asia/Tehran",
    "iso:country":"IR",
    "wof:name":"Saleh Hamid",
    "wof:placetype":"locality"
},
  "geometry": {"coordinates":[48.66667,33.01667],"type":"Point"}
}