{
  "type": "Feature",
  "properties": {
    "gn:admin1_code":"33",
    "gn:asciiname":"Kordlar",
    "gn:country_code":"IR",
    "gn:dem":1692,
    "gn:feature_class":"P",
    "gn:feature_code":"PPL",
    "gn:name":"Kordlar",
    "gn:population":0,
    "gn:timezone":"Asia/Tehran",
    "iso:country":"IR",
    "name:ara_x_preferred":[
        "\u0643\u0631\u062f\u0644\u0631"
    ],
    "name:azb_x_preferred":[
        "\u06a9\u0631\u062f\u0644\u0631"
    ],
    "name:fas_x_preferred":[
        "\u06a9\u0631\u062f\u0644\u0631"
    ],
    "name:fas_x_variant":[
        "K\u016brtar",
        "\u0643\u0648\u0631\u062a\u064e\u0631"
    ],
    "name:msa_x_preferred":[
        "Kordlar"
    ],
    "wof:name":"Kordlar",
    "wof:placetype":"locality"
},
  "geometry": {"coordinates":[47.0795,38.6983],"type":"Point"}
}