{
  "type": "Feature",
  "properties": {
    "gn:admin1_code":"23",
    "gn:asciiname":"Darreh-ye Mohammad Qoli",
    "gn:country_code":"IR",
    "gn:dem":1089,
    "gn:feature_class":"P",
    "gn:feature_code":"PPL",
    "gn:name":"Darreh-ye Mo\u1e29ammad Qol\u012b",
    "gn:population":0,
    "gn:timezone":"Asia/Tehran",
    "iso:country":"IR",
    "name:ara_x_preferred":[
        "\u062f\u0631\u0629 \u0645\u062d\u0645\u062f\u0642\u0644\u064a"
    ],
    "name:fas_x_preferred":[
        "Darreh-ye Mo\u1e29ammad Qol\u012b"
    ],
    "name:fas_x_variant":[
        "\u062f\u0631\u0651\u0647 \u0645\u062d\u0645\u0651\u062f \u0642\u0644\u06cc",
        "\u062f\u0631\u0647 \u0645\u062d\u0645\u062f\u0642\u0644\u06cc"
    ],
    "wof:name":"Darreh-ye Mohammad Qoli",
    "wof:placetype":"locality"
},
  "geometry": {"coordinates":[48.183,33.4648],"type":"Point"}
}