{
  "type": "Feature",
  "properties": {
    "gn:admin1_code":"4.0",
    "gn:asciiname":"Kalihimeh",
    "gn:country_code":"IR",
    "gn:dem":849,
    "gn:feature_class":"P",
    "gn:feature_code":"PPL",
    "gn:name":"Kal\u012bh\u012bmeh",
    "gn:population":0,
    "gn:timezone":"Asia/Tehran",
    "iso:country":"IR",
    "name:fas_x_preferred":[
        "Kal\u012bh\u012bmeh"
    ],
    "wof:name":"Kalihimeh",
    "wof:placetype":"locality"
},
  "geometry": {"coordinates":[59.48721999999999,26.69028],"type":"Point"}
}