{
  "type": "Feature",
  "properties": {
    "gn:admin1_code":"7",
    "gn:asciiname":"Lay Zangan",
    "gn:country_code":"IR",
    "gn:dem":1967,
    "gn:feature_class":"P",
    "gn:feature_code":"PPL",
    "gn:name":"L\u0101y Zang\u0101n",
    "gn:population":0,
    "gn:timezone":"Asia/Tehran",
    "iso:country":"IR",
    "name:ara_x_preferred":[
        "\u0644\u0627\u064a\u0632\u0646\u063a\u0627\u0646"
    ],
    "name:fas_x_preferred":[
        "\u0644\u0627\u06cc \u0632\u0646\u06af\u0627\u0646"
    ],
    "name:fas_x_variant":[
        "L\u0101y Zang\u0101n",
        "\u0644\u0627\u06cc\u0632\u0646\u06af\u0627\u0646"
    ],
    "name:msa_x_preferred":[
        "Lay Zangan"
    ],
    "name:und_x_variant":[
        "L\u0101y-e Zang\u0101n"
    ],
    "wof:name":"Lay Zangan",
    "wof:placetype":"locality"
},
  "geometry": {"coordinates":[54.9844,28.6742],"type":"Point"}
}