{
  "type": "Feature",
  "properties": {
    "gn:admin1_code":"4",
    "gn:asciiname":"Gazrinek-e Pa'in",
    "gn:country_code":"IR",
    "gn:dem":1075,
    "gn:feature_class":"P",
    "gn:feature_code":"PPL",
    "gn:name":"Gazr\u012bnek-e P\u0101\u2019\u012bn",
    "gn:population":0,
    "gn:timezone":"Asia/Tehran",
    "iso:country":"IR",
    "name:fas_x_preferred":[
        "\u06af\u0632\u0631\u06cc\u0646\u06a9 \u067e\u0627\u0626\u06cc\u0646"
    ],
    "name:fas_x_variant":[
        "Gazr\u012bnek-e P\u0101\u2019\u012bn"
    ],
    "wof:name":"Gazrinek-e Pa'in",
    "wof:placetype":"locality"
},
  "geometry": {"coordinates":[61.5968,26.6205],"type":"Point"}
}