{
  "type": "Feature",
  "properties": {
    "gn:admin1_code":"33",
    "gn:asciiname":"Masqaran",
    "gn:country_code":"IR",
    "gn:dem":1887,
    "gn:feature_class":"P",
    "gn:feature_code":"PPL",
    "gn:name":"Masqar\u0101n",
    "gn:population":0,
    "gn:timezone":"Asia/Tehran",
    "iso:country":"IR",
    "name:ceb_x_preferred":[
        "Masqar\u0101n"
    ],
    "name:fas_x_preferred":[
        "\u0645\u0633\u0642\u0631\u0627\u0646"
    ],
    "name:fas_x_variant":[
        "Masqar\u0101n"
    ],
    "name:msa_x_preferred":[
        "Masqaran"
    ],
    "name:swe_x_preferred":[
        "Masqar\u0101n"
    ],
    "name:und_x_variant":[
        "Mackaran",
        "Maskar\u0101n"
    ],
    "wof:name":"Masqaran",
    "wof:placetype":"locality"
},
  "geometry": {"coordinates":[46.865,38.601],"type":"Point"}
}