{
  "type": "Feature",
  "properties": {
    "gn:admin1_code":"35.0",
    "gn:asciiname":"Sa`din Kola",
    "gn:country_code":"IR",
    "gn:dem":17,
    "gn:feature_class":"P",
    "gn:feature_code":"PPL",
    "gn:name":"Sa\u2018d\u012bn Kol\u0101",
    "gn:population":0,
    "gn:timezone":"Asia/Tehran",
    "iso:country":"IR",
    "name:fas_x_preferred":[
        "\u0633\u0639\u062f\u064a\u0646 \u0643\u0644\u0627"
    ],
    "name:fas_x_variant":[
        "Sa\u2018d\u012bn Kol\u0101"
    ],
    "wof:name":"Sa`din Kola",
    "wof:placetype":"locality"
},
  "geometry": {"coordinates":[52.35901,36.53809],"type":"Point"}
}