{
  "type": "Feature",
  "properties": {
    "gn:admin1_code":"29",
    "gn:asciiname":"Deh-e Morghi",
    "gn:country_code":"IR",
    "gn:dem":1978,
    "gn:feature_class":"P",
    "gn:feature_code":"PPL",
    "gn:name":"Deh-e Morgh\u012b",
    "gn:population":0,
    "gn:timezone":"Asia/Tehran",
    "iso:country":"IR",
    "name:fas_x_preferred":[
        "Deh Morgh\u012b"
    ],
    "name:fas_x_variant":[
        "Deh-e Morgh\u012b",
        "\u062f\u0647 \u0645\u0631\u063a\u06cc"
    ],
    "name:und_x_variant":[
        "Morghi Deh Morghi",
        "Deh-e Morgh\u012b",
        "\u062f\u0647 \u0645\u0631\u063a\u06cc"
    ],
    "wof:name":"Deh-e Morghi",
    "wof:placetype":"locality"
},
  "geometry": {"coordinates":[55.77228,29.70785],"type":"Point"}
}