{
  "type": "Feature",
  "properties": {
    "gn:admin1_code":"35.0",
    "gn:asciiname":"Velasht",
    "gn:country_code":"IR",
    "gn:dem":1132,
    "gn:feature_class":"P",
    "gn:feature_code":"PPL",
    "gn:name":"Velasht",
    "gn:population":0,
    "gn:timezone":"Asia/Tehran",
    "iso:country":"IR",
    "name:ara_x_preferred":[
        "\u0648\u0644\u0634\u062a"
    ],
    "name:fas_x_preferred":[
        "\u0648\u0644\u0634\u062a"
    ],
    "name:und_x_variant":[
        "Velasht",
        "Valasht"
    ],
    "wof:name":"Velasht",
    "wof:placetype":"locality"
},
  "geometry": {"coordinates":[51.30271,36.38689],"type":"Point"}
}