{
  "type": "Feature",
  "properties": {
    "gn:admin1_code":"37.0",
    "gn:asciiname":"Qolhaz",
    "gn:country_code":"IR",
    "gn:dem":105,
    "gn:feature_class":"P",
    "gn:feature_code":"PPL",
    "gn:name":"Qolhaz",
    "gn:population":0,
    "gn:timezone":"Asia/Tehran",
    "iso:country":"IR",
    "name:fas_x_preferred":[
        "\u0642\u0644\u0647\u0632"
    ],
    "wof:name":"Qolhaz",
    "wof:placetype":"locality"
},
  "geometry": {"coordinates":[55.45612,37.92109],"type":"Point"}
}