{
  "type": "Feature",
  "properties": {
    "gn:admin1_code":"28",
    "gn:asciiname":"Vahregan",
    "gn:country_code":"IR",
    "gn:dem":2073,
    "gn:feature_class":"P",
    "gn:feature_code":"PPL",
    "gn:name":"Vahreg\u0101n",
    "gn:population":0,
    "gn:timezone":"Asia/Tehran",
    "iso:country":"IR",
    "name:ara_x_preferred":[
        "\u0648\u0647\u0631\u063a\u0627\u0646"
    ],
    "name:fas_x_preferred":[
        "Vahreg\u0101n"
    ],
    "name:fas_x_variant":[
        "\u0648\u0647\u0631\u06af\u0627\u0646"
    ],
    "name:und_x_variant":[
        "Vahreh"
    ],
    "wof:name":"Vahregan",
    "wof:placetype":"locality"
},
  "geometry": {"coordinates":[49.83812,32.98694],"type":"Point"}
}