{
  "type": "Feature",
  "properties": {
    "gn:admin1_code":"29",
    "gn:asciiname":"Hoseynabad-e `Alam Khvah",
    "gn:country_code":"IR",
    "gn:dem":709,
    "gn:feature_class":"P",
    "gn:feature_code":"PPL",
    "gn:name":"\u1e28oseyn\u0101b\u0101d-e \u2018Alam Khv\u0101h",
    "gn:population":0,
    "gn:timezone":"Asia/Tehran",
    "iso:country":"IR",
    "name:fas_x_preferred":[
        "\u062d\u0633\u06cc\u0646 \u0622\u0628\u0627\u062f"
    ],
    "name:fas_x_variant":[
        "\u1e28oseyn\u0101b\u0101d-e \u2018Alam Kh\u0101n",
        "\u1e28oseyn\u0101b\u0101d",
        "\u062d\u0633\u06cc\u0646 \u0622\u0628\u0627\u062f \u0639\u0644\u0645 \u062e\u0648\u0627\u0647",
        "\u062d\u0633\u06cc\u0646 \u0622\u0628\u0627\u062f \u0639\u0644\u0645 \u062e\u0627\u0646"
    ],
    "name:und_x_variant":[
        "Hosein Abad",
        "\u1e28oseyn\u0101b\u0101d-e \u2018Alam Khv\u0101h"
    ],
    "wof:name":"Hoseynabad-e `Alam Khvah",
    "wof:placetype":"locality"
},
  "geometry": {"coordinates":[58.82869,28.91492],"type":"Point"}
}