{
  "type": "Feature",
  "properties": {
    "gn:admin1_code":"13",
    "gn:asciiname":"Qeysevand",
    "gn:country_code":"IR",
    "gn:dem":1335,
    "gn:feature_class":"P",
    "gn:feature_code":"PPL",
    "gn:name":"Qeysevand",
    "gn:population":0,
    "gn:timezone":"Asia/Tehran",
    "iso:country":"IR",
    "name:fas_x_preferred":[
        "\u0642\u06cc\u0633\u0648\u0646\u062f"
    ],
    "wof:name":"Qeysevand",
    "wof:placetype":"locality"
},
  "geometry": {"coordinates":[46.613,34.5384],"type":"Point"}
}