{
  "type": "Feature",
  "properties": {
    "gn:admin1_code":"13.0",
    "gn:asciiname":"Bahram Beg",
    "gn:country_code":"IR",
    "gn:dem":1499,
    "gn:feature_class":"P",
    "gn:feature_code":"PPL",
    "gn:name":"Bahr\u0101m Beg",
    "gn:population":0,
    "gn:timezone":"Asia/Tehran",
    "iso:country":"IR",
    "name:fas_x_preferred":[
        "\u0628\u0647\u0631\u0627\u0645 \u0628\u06af"
    ],
    "name:fas_x_variant":[
        "Bahr\u0101m Bayg",
        "Bahr\u0101m Beg"
    ],
    "wof:name":"Bahram Beg",
    "wof:placetype":"locality"
},
  "geometry": {"coordinates":[46.4075,33.9834],"type":"Point"}
}