{
  "type": "Feature",
  "properties": {
    "gn:admin1_code":"11",
    "gn:asciiname":"Poshteh Chahu",
    "gn:country_code":"IR",
    "gn:dem":762,
    "gn:feature_class":"P",
    "gn:feature_code":"PPL",
    "gn:name":"Poshteh Ch\u0101h\u016b",
    "gn:population":0,
    "gn:timezone":"Asia/Tehran",
    "iso:country":"IR",
    "name:ara_x_preferred":[
        "\u0628\u0634\u062a\u0629 \u062a\u0634\u0627\u0647\u0648"
    ],
    "name:fas_x_preferred":[
        "\u067e\u0634\u062a\u0647 \u0686\u0627\u0647\u0648"
    ],
    "name:fas_x_variant":[
        "Poshteh Ch\u0101h\u016b"
    ],
    "name:msa_x_preferred":[
        "Poshteh Chahu"
    ],
    "wof:name":"Poshteh Chahu",
    "wof:placetype":"locality"
},
  "geometry": {"coordinates":[56.5984,27.7686],"type":"Point"}
}