{
  "type": "Feature",
  "properties": {
    "gn:admin1_code":"8",
    "gn:asciiname":"Khaleh Sara-ye Panjah-o Haft",
    "gn:country_code":"IR",
    "gn:dem":3,
    "gn:feature_class":"P",
    "gn:feature_code":"PPL",
    "gn:name":"Kh\u0101leh Sar\u0101-ye Panj\u0101h-o Haft",
    "gn:population":0,
    "gn:timezone":"Asia/Tehran",
    "iso:country":"IR",
    "name:fas_x_preferred":[
        "Kh\u0101leh Sar\u0101"
    ],
    "name:fas_x_variant":[
        "Kh\u0101leh Sar\u0101-ye Panj\u0101h ow Haft",
        "\u062e\u0627\u0644\u0647 \u0633\u0631\u0627\u06cc \u067e\u0646\u062c\u0627\u0647 \u0648 \u0647\u0641\u062a"
    ],
    "name:und_x_variant":[
        "Qal\u2018eh Sar\u0101i",
        "Ma\u1e29alleh Kh\u0101leh Sar\u0101",
        "Qal\u2018eh Sar\u0101y",
        "Kh\u0101leh Sar\u0101-ye 59",
        "Kh\u0101leh Sar\u0101-ye Panj\u0101h va Haft",
        "Kh\u0101lehsar\u0101-ye Panj\u0101h-o-haft",
        "Kh\u0101leh Sar\u0101-ye Panj\u0101h va Noh",
        "Khalassera",
        "Kh\u0101lehsar\u0101-ye Panj\u0101h-o-noh",
        "Kh\u0101lehsar\u0101-ye 57",
        "Kh\u0101leh Sar\u0101-ye Panj\u0101h-o Haft"
    ],
    "wof:name":"Khaleh Sara-ye Panjah-o Haft",
    "wof:placetype":"locality"
},
  "geometry": {"coordinates":[49.00101,37.68754000000001],"type":"Point"}
}