{
  "type": "Feature",
  "properties": {
    "gn:admin1_code":"42",
    "gn:asciiname":"Shahrak",
    "gn:country_code":"IR",
    "gn:dem":1178,
    "gn:feature_class":"P",
    "gn:feature_code":"PPL",
    "gn:name":"Shahrak",
    "gn:population":0,
    "gn:timezone":"Asia/Tehran",
    "iso:country":"IR",
    "name:fas_x_preferred":[
        "\u0634\u0647\u0631\u0643"
    ],
    "name:fas_x_variant":[
        "\u0634\u0647\u0631\u06a9"
    ],
    "wof:name":"Shahrak",
    "wof:placetype":"locality"
},
  "geometry": {"coordinates":[58.75963,36.21341],"type":"Point"}
}