{
  "type": "Feature",
  "properties": {
    "gn:admin1_code":"42",
    "gn:asciiname":"Najmabad",
    "gn:country_code":"IR",
    "gn:dem":1127,
    "gn:feature_class":"P",
    "gn:feature_code":"PPL",
    "gn:name":"Najm\u0101b\u0101d",
    "gn:population":0,
    "gn:timezone":"Asia/Tehran",
    "iso:country":"IR",
    "name:fas_x_preferred":[
        "\u0646\u062c\u0645 \u0622\u0628\u0627\u062f"
    ],
    "name:fas_x_variant":[
        "Najm\u0101b\u0101d"
    ],
    "wof:name":"Najmabad",
    "wof:placetype":"locality"
},
  "geometry": {"coordinates":[59.17915,36.6664],"type":"Point"}
}