{
  "type": "Feature",
  "properties": {
    "gn:admin1_code":"4.0",
    "gn:asciiname":"Kheyrabad",
    "gn:cc2":"IR",
    "gn:country_code":"IR",
    "gn:dem":514,
    "gn:feature_class":"P",
    "gn:feature_code":"PPL",
    "gn:name":"Kheyr\u0101b\u0101d",
    "gn:population":0,
    "gn:timezone":"Asia/Tehran",
    "iso:country":"IR",
    "name:aze_x_preferred":[
        "Xeyrabad"
    ],
    "name:fas_x_preferred":[
        "Kheyr\u0101b\u0101d"
    ],
    "name:fas_x_variant":[
        "\u062e\u06cc\u0631 \u0622\u0628\u0627\u062f",
        "\u1e28eydar\u0101b\u0101d",
        "\u062e\u06cc\u0631\u0622\u0628\u0627\u062f"
    ],
    "wof:name":"Kheyrabad",
    "wof:placetype":"locality"
},
  "geometry": {"coordinates":[60.44944,27.17944],"type":"Point"}
}