{
  "type": "Feature",
  "properties": {
    "gn:admin1_code":"28.0",
    "gn:asciiname":"Shur Ab",
    "gn:country_code":"IR",
    "gn:dem":1155,
    "gn:feature_class":"P",
    "gn:feature_code":"PPLF",
    "gn:name":"Sh\u016br \u0100b",
    "gn:population":0,
    "gn:timezone":"Asia/Tehran",
    "iso:country":"IR",
    "name:fas_x_preferred":[
        "\u0634\u0648\u0631 \u0622\u0628"
    ],
    "name:fas_x_variant":[
        "Sh\u016br \u0100b"
    ],
    "wof:name":"Shur Ab",
    "wof:placetype":"locality"
},
  "geometry": {"coordinates":[51.7682,33.7472],"type":"Point"}
}