{
  "type": "Feature",
  "properties": {
    "gn:admin1_code":"35",
    "gn:asciiname":"Barik Absar",
    "gn:country_code":"IR",
    "gn:dem":33,
    "gn:feature_class":"P",
    "gn:feature_code":"PPL",
    "gn:name":"B\u0101r\u012bk \u0100bsar",
    "gn:population":0,
    "gn:timezone":"Asia/Tehran",
    "iso:country":"IR",
    "name:ceb_x_preferred":[
        "B\u0101r\u012bk \u0100bsar"
    ],
    "name:fas_x_preferred":[
        "\u0628\u0627\u0631\u064a\u06a9 \u0622\u0628\u0633\u0631"
    ],
    "name:fas_x_variant":[
        "B\u0101r\u012bk \u0100bsar",
        "\u0628\u0627\u0631\u06cc\u06a9 \u0622\u0628\u0633\u0631"
    ],
    "name:mzn_x_preferred":[
        "\u0628\u0627\u0631\u06cc\u06a9 \u0622\u0628\u0633\u0631"
    ],
    "name:swe_x_preferred":[
        "B\u0101r\u012bk \u0100bsar"
    ],
    "wof:name":"Barik Absar",
    "wof:placetype":"locality"
},
  "geometry": {"coordinates":[52.9871,36.50643],"type":"Point"}
}