{
  "type": "Feature",
  "properties": {
    "gn:admin1_code":"23",
    "gn:asciiname":"Qal`eh-ye Nav Kesh",
    "gn:country_code":"IR",
    "gn:dem":1036,
    "gn:feature_class":"P",
    "gn:feature_code":"PPL",
    "gn:name":"Qal\u2018eh-ye N\u0101v Kesh",
    "gn:population":0,
    "gn:timezone":"Asia/Tehran",
    "iso:country":"IR",
    "name:fas_x_preferred":[
        "\u0642\u064e\u0644\u0639\u0650\u06c0 \u0646\u0627\u0648\u0650\u0647 \u0643\u0650\u0634"
    ],
    "name:fas_x_variant":[
        "Qal\u2018eh-ye N\u0101veh Kesh",
        "\u0642\u0644\u0639\u0647 \u0646\u0627\u0648\u0647 \u06a9\u0634",
        "\u0642\u0644\u0639\u0647 \u0646\u0627\u0648 \u06a9\u0634"
    ],
    "name:und_x_variant":[
        "\u0642\u0644\u0639\u0647 \u0646\u0627\u0648\u0647 \u06a9\u0634",
        "Qal\u2018eh-ye N\u0101v Kesh"
    ],
    "wof:name":"Qal`eh-ye Nav Kesh",
    "wof:placetype":"locality"
},
  "geometry": {"coordinates":[48.11368,33.48474],"type":"Point"}
}