{
  "type": "Feature",
  "properties": {
    "gn:admin1_code":"7.0",
    "gn:asciiname":"Dehuyeh",
    "gn:country_code":"IR",
    "gn:dem":1572,
    "gn:feature_class":"P",
    "gn:feature_code":"PPL",
    "gn:name":"Deh\u016byeh",
    "gn:population":0,
    "gn:timezone":"Asia/Tehran",
    "iso:country":"IR",
    "name:fas_x_preferred":[
        "\u062f\u0647\u0648\u06cc\u0647 \u0631\u0648\u0646\u06cc\u0632"
    ],
    "name:fas_x_variant":[
        "Deh\u016byeh",
        "Deh\u016byeh-ye R\u016bn\u012bz",
        "\u062f\u0647\u0648\u06cc\u0647"
    ],
    "wof:name":"Dehuyeh",
    "wof:placetype":"locality"
},
  "geometry": {"coordinates":[53.7258,29.1893],"type":"Point"}
}