{
  "type": "Feature",
  "properties": {
    "gn:admin1_code":"1.0",
    "gn:asciiname":"Qaderabad",
    "gn:country_code":"IR",
    "gn:dem":1344,
    "gn:feature_class":"P",
    "gn:feature_code":"PPL",
    "gn:name":"Q\u0101der\u0101b\u0101d",
    "gn:population":0,
    "gn:timezone":"Asia/Tehran",
    "iso:country":"IR",
    "name:ara_x_preferred":[
        "\u0642\u0627\u062f\u0631 \u0623\u0628\u0627\u062f"
    ],
    "name:aze_x_preferred":[
        "Qadirabad"
    ],
    "name:ceb_x_preferred":[
        "Q\u0101der\u0101b\u0101d"
    ],
    "name:fas_x_preferred":[
        "\u0642\u0627\u062f\u0631 \u0622\u0628\u0627\u062f"
    ],
    "name:fas_x_variant":[
        "Q\u0101der\u0101b\u0101d",
        "\u0642\u0627\u062f\u0631\u0622\u0628\u0627\u062f"
    ],
    "name:ita_x_preferred":[
        "Qaderabad"
    ],
    "name:mlg_x_preferred":[
        "Qaderabad"
    ],
    "name:msa_x_preferred":[
        "Qaderabad"
    ],
    "name:mzn_x_preferred":[
        "\u0642\u0627\u062f\u0631\u0622\u0628\u0627\u062f"
    ],
    "name:rus_x_preferred":[
        "\u041a\u0430\u0434\u0435\u0440\u0430\u0431\u0430\u0434"
    ],
    "name:swe_x_preferred":[
        "Q\u0101der\u0101b\u0101d"
    ],
    "name:tur_x_preferred":[
        "Kadirabad"
    ],
    "name:urd_x_preferred":[
        "\u0642\u0627\u062f\u0631\u0622\u0628\u0627\u062f"
    ],
    "name:zho_x_preferred":[
        "\u52a0\u4ee3\u62c9\u5df4\u5fb7"
    ],
    "wof:name":"Qaderabad",
    "wof:placetype":"locality"
},
  "geometry": {"coordinates":[45.3141,36.5125],"type":"Point"}
}