{
  "type": "Feature",
  "properties": {
    "gn:admin1_code":"1",
    "gn:asciiname":"Yushanlu",
    "gn:country_code":"IR",
    "gn:dem":1287,
    "gn:feature_class":"P",
    "gn:feature_code":"PPL",
    "gn:name":"Y\u016bsh\u0101nl\u016b",
    "gn:population":0,
    "gn:timezone":"Asia/Tehran",
    "iso:country":"IR",
    "name:fas_x_preferred":[
        "\u06cc\u0648\u0634\u0627\u0646\u0644\u0648"
    ],
    "name:fas_x_variant":[
        "B\u016bsh\u0101nl\u016b",
        "\u064a\u064f\u0634\u064e\u0646\u0644\u064f\u0651",
        "Y\u016bsh\u0101nl\u016b",
        "\u064a\u064f\u0648\u0634\u0627\u0646\u0644\u0648"
    ],
    "name:und_x_variant":[
        "Yavshanlu",
        "Yoshanloo",
        "Yowsh\u0101nl\u016b"
    ],
    "wof:name":"Yushanlu",
    "wof:placetype":"locality"
},
  "geometry": {"coordinates":[44.9711,38.2221],"type":"Point"}
}