{
  "type": "Feature",
  "properties": {
    "gn:admin1_code":"10.0",
    "gn:asciiname":"Hesar-e Shaveh",
    "gn:country_code":"IR",
    "gn:dem":1115,
    "gn:feature_class":"P",
    "gn:feature_code":"PPL",
    "gn:name":"\u1e28e\u015f\u0101r-e Sh\u0101veh",
    "gn:population":0,
    "gn:timezone":"Asia/Tehran",
    "iso:country":"IR",
    "name:ara_x_preferred":[
        "\u062d\u0635\u0627\u0631\u0634\u0627\u0648\u0629"
    ],
    "name:ceb_x_preferred":[
        "\u1e28e\u015f\u0101r-e Sh\u0101veh"
    ],
    "name:fas_x_preferred":[
        "\u062d\u0635\u0627\u0631 \u0634\u0627\u0648\u0647"
    ],
    "name:fas_x_variant":[
        "\u1e28e\u015f\u0101r Sh\u0101veh",
        "\u1e28e\u015f\u0101r-e Sh\u0101veh",
        "\u062d\u0635\u0627\u0631\u0634\u0627\u0648\u0647"
    ],
    "name:msa_x_preferred":[
        "Hesar-e Shaveh"
    ],
    "name:swe_x_preferred":[
        "\u1e28e\u015f\u0101r-e Sh\u0101veh"
    ],
    "wof:name":"Hesar-e Shaveh",
    "wof:placetype":"locality"
},
  "geometry": {"coordinates":[46.2426,33.8562],"type":"Point"}
}