{
  "type": "Feature",
  "properties": {
    "gn:admin1_code":"8.0",
    "gn:asciiname":"Yeylaq-e Ilan Bulaghi",
    "gn:country_code":"IR",
    "gn:dem":2402,
    "gn:feature_class":"P",
    "gn:feature_code":"PPL",
    "gn:name":"Yeyl\u0101q-e \u012al\u0101n B\u016bl\u0101gh\u012b",
    "gn:population":0,
    "gn:timezone":"Asia/Tehran",
    "iso:country":"IR",
    "name:fas_x_preferred":[
        "\u06cc\u06cc\u0644\u0627\u0642 \u0627\u06cc\u0644\u0627\u0646 \u0628\u0648\u0644\u0627\u063a\u06cc"
    ],
    "name:fas_x_variant":[
        "\u0627\u0634\u06a9 \u06cc\u0648\u0631\u062f\u06cc"
    ],
    "name:und_x_variant":[
        "Yeyl\u0101q-e \u012al\u0101n B\u016bl\u0101gh\u012b",
        "Ashk Y\u016brd\u012b"
    ],
    "wof:name":"Yeylaq-e Ilan Bulaghi",
    "wof:placetype":"locality"
},
  "geometry": {"coordinates":[48.55731,37.81222],"type":"Point"}
}