{
  "type": "Feature",
  "properties": {
    "gn:admin1_code":"15",
    "gn:asciiname":"Hoseyniyeh-ye Khezayer",
    "gn:country_code":"IR",
    "gn:dem":21,
    "gn:feature_class":"P",
    "gn:feature_code":"PPL",
    "gn:name":"\u1e28oseyn\u012byeh-ye Khe\u1e95ayer",
    "gn:population":0,
    "gn:timezone":"Asia/Tehran",
    "iso:country":"IR",
    "name:fas_x_preferred":[
        "\u1e28oseyn\u012byeh-ye Khe\u1e95ayer"
    ],
    "wof:name":"Hoseyniyeh-ye Khezayer",
    "wof:placetype":"locality"
},
  "geometry": {"coordinates":[49.41667,30.93333],"type":"Point"}
}