{
  "type": "Feature",
  "properties": {
    "gn:admin1_code":"7",
    "gn:asciiname":"`Ezzabad",
    "gn:country_code":"IR",
    "gn:dem":1624,
    "gn:feature_class":"P",
    "gn:feature_code":"PPL",
    "gn:name":"\u2018Ezz\u0101b\u0101d",
    "gn:population":0,
    "gn:timezone":"Asia/Tehran",
    "iso:country":"IR",
    "name:fas_x_preferred":[
        "\u0639\u0632 \u0622\u0628\u0627\u062f"
    ],
    "name:fas_x_variant":[
        "\u2018Ezz\u0101b\u0101d",
        "\u0639\u0632\u0647 \u0622\u0628\u0627\u062f"
    ],
    "name:und_x_variant":[
        "\u2018Ezzeh\u0101b\u0101d"
    ],
    "wof:name":"`Ezzabad",
    "wof:placetype":"locality"
},
  "geometry": {"coordinates":[52.48672,30.10145],"type":"Point"}
}