{
  "type": "Feature",
  "properties": {
    "gn:admin1_code":"36",
    "gn:asciiname":"Goljik",
    "gn:country_code":"IR",
    "gn:dem":1990,
    "gn:feature_class":"P",
    "gn:feature_code":"PPL",
    "gn:name":"Golj\u012bk",
    "gn:population":0,
    "gn:timezone":"Asia/Tehran",
    "iso:country":"IR",
    "name:azb_x_preferred":[
        "\u06af\u0644\u062c\u06cc\u06a9"
    ],
    "name:ceb_x_preferred":[
        "Golj\u012bk"
    ],
    "name:fas_x_preferred":[
        "\u06af\u0644\u062c\u064a\u06a9"
    ],
    "name:fas_x_variant":[
        "Golj\u012bk",
        "\u06af\u0644\u062c\u06cc\u06a9"
    ],
    "name:swe_x_preferred":[
        "Golj\u012bk"
    ],
    "name:und_x_variant":[
        "Guljak"
    ],
    "wof:name":"Goljik",
    "wof:placetype":"locality"
},
  "geometry": {"coordinates":[48.09535,36.68283],"type":"Point"}
}