{
  "type": "Feature",
  "properties": {
    "gn:admin1_code":"8",
    "gn:asciiname":"Tasku",
    "gn:country_code":"IR",
    "gn:dem":154,
    "gn:feature_class":"P",
    "gn:feature_code":"PPL",
    "gn:name":"\u0162\u0101sk\u016b",
    "gn:population":0,
    "gn:timezone":"Asia/Tehran",
    "iso:country":"IR",
    "name:fas_x_preferred":[
        "\u0637\u0627\u0633\u06a9\u0648"
    ],
    "name:fas_x_variant":[
        "\u0162\u0101sk\u016b"
    ],
    "wof:name":"Tasku",
    "wof:placetype":"locality"
},
  "geometry": {"coordinates":[49.0707,37.335],"type":"Point"}
}