{
  "type": "Feature",
  "properties": {
    "gn:admin1_code":"32.0",
    "gn:asciiname":"Abr Bakuh",
    "gn:country_code":"IR",
    "gn:dem":1517,
    "gn:feature_class":"P",
    "gn:feature_code":"PPL",
    "gn:name":"Abr Bak\u016bh",
    "gn:population":0,
    "gn:timezone":"Asia/Tehran",
    "iso:country":"IR",
    "name:ara_x_preferred":[
        "\u0627\u0628\u0631\u0628\u06a9\u0648\u0629"
    ],
    "name:azb_x_preferred":[
        "\u0627\u0628\u0631\u06a9\u0648\u0647"
    ],
    "name:ceb_x_preferred":[
        "Abr Bak\u016bh"
    ],
    "name:fas_x_preferred":[
        "\u0627\u0628\u0631 \u0628\u0643\u0648\u0647"
    ],
    "name:fas_x_variant":[
        "\u012arebk\u016b",
        "Abr Bak\u016bh",
        "\u0627\u064e\u0628\u0631\u0628\u064e\u0643\u064f\u0651",
        "\u0627\u0628\u0631\u0628\u06a9\u0648\u0647"
    ],
    "name:msa_x_preferred":[
        "Abr Bakuh"
    ],
    "name:mzn_x_preferred":[
        "\u0627\u0628\u0631\u0628\u06a9\u0648\u0647"
    ],
    "name:swe_x_preferred":[
        "Abr Bak\u016bh"
    ],
    "name:und_x_variant":[
        "Abrbakoo"
    ],
    "wof:name":"Abr Bakuh",
    "wof:placetype":"locality"
},
  "geometry": {"coordinates":[48.1054,38.3668],"type":"Point"}
}