{
  "type": "Feature",
  "properties": {
    "gn:admin1_code":"23",
    "gn:asciiname":"Saravand",
    "gn:country_code":"IR",
    "gn:dem":2037,
    "gn:feature_class":"P",
    "gn:feature_code":"PPL",
    "gn:name":"Sar\u0101vand",
    "gn:population":0,
    "gn:timezone":"Asia/Tehran",
    "iso:country":"IR",
    "name:ara_x_preferred":[
        "\u0633\u0631\u0627\u0648\u0646\u062f"
    ],
    "name:ceb_x_preferred":[
        "Sar\u0101vand"
    ],
    "name:fas_x_preferred":[
        "\u0633\u0631\u0627\u0648\u0646\u062f"
    ],
    "name:fas_x_variant":[
        "Sar\u0101vand"
    ],
    "name:swe_x_preferred":[
        "Sar\u0101vand"
    ],
    "name:und_x_variant":[
        "Sar\u0101wand"
    ],
    "wof:name":"Saravand",
    "wof:placetype":"locality"
},
  "geometry": {"coordinates":[49.16718,33.37342],"type":"Point"}
}