{
  "type": "Feature",
  "properties": {
    "gn:admin1_code":"10",
    "gn:asciiname":"Meleh Shotorkhan",
    "gn:country_code":"IR",
    "gn:dem":1026,
    "gn:feature_class":"P",
    "gn:feature_code":"PPL",
    "gn:name":"Meleh Shotorkh\u0101n",
    "gn:population":0,
    "gn:timezone":"Asia/Tehran",
    "iso:country":"IR",
    "name:fas_x_preferred":[
        "\u062a\u0646\u06af \u0632\u0631\u062f \u0641\u0631\u062e\u064a\u0648\u0646\u062f"
    ],
    "name:fas_x_variant":[
        "\u062a\u0646\u06af \u0632\u0631\u062f",
        "\u0645\u0644\u0647 \u0634\u062a\u0631\u062e\u0627\u0646"
    ],
    "name:und_x_variant":[
        "Tang Zard-e Farkh\u012bvand",
        "Tang Zard",
        "Meleh Shotorkh\u0101n"
    ],
    "wof:name":"Meleh Shotorkhan",
    "wof:placetype":"locality"
},
  "geometry": {"coordinates":[46.98378,33.62726],"type":"Point"}
}