{
  "type": "Feature",
  "properties": {
    "gn:admin1_code":"11",
    "gn:asciiname":"Gabrik",
    "gn:cc2":"IR",
    "gn:country_code":"IR",
    "gn:dem":15,
    "gn:feature_class":"P",
    "gn:feature_code":"PPL",
    "gn:name":"G\u0101br\u012bk",
    "gn:population":0,
    "gn:timezone":"Asia/Tehran",
    "iso:country":"IR",
    "name:fas_x_preferred":[
        "\u06af\u0627\u0628\u0631\u064a\u0643"
    ],
    "name:fas_x_variant":[
        "\u06af\u064e\u0628\u0631\u064a\u06af",
        "G\u0101br\u012bk"
    ],
    "name:und_x_variant":[
        "Gabr\u012bg"
    ],
    "wof:name":"Gabrik",
    "wof:placetype":"locality"
},
  "geometry": {"coordinates":[58.46139,25.72111],"type":"Point"}
}