{
  "type": "Feature",
  "properties": {
    "gn:admin1_code":"4.0",
    "gn:asciiname":"Gazgun",
    "gn:country_code":"IR",
    "gn:dem":612,
    "gn:feature_class":"P",
    "gn:feature_code":"PPL",
    "gn:name":"Gazg\u016bn",
    "gn:population":0,
    "gn:timezone":"Asia/Tehran",
    "iso:country":"IR",
    "name:fas_x_preferred":[
        "\u06af\u0632\u06af\u0648\u0646"
    ],
    "name:und_x_variant":[
        "Gazg\u016bn"
    ],
    "wof:name":"Gazgun",
    "wof:placetype":"locality"
},
  "geometry": {"coordinates":[59.54734000000001,26.42188],"type":"Point"}
}