{
  "type": "Feature",
  "properties": {
    "gn:admin1_code":"28",
    "gn:asciiname":"Moqandar",
    "gn:country_code":"IR",
    "gn:dem":2678,
    "gn:feature_class":"P",
    "gn:feature_code":"PPL",
    "gn:name":"Moqandar",
    "gn:population":0,
    "gn:timezone":"Asia/Tehran",
    "iso:country":"IR",
    "name:ara_x_preferred":[
        "\u0645\u063a\u0627\u0646\u062f\u0631"
    ],
    "name:fas_x_preferred":[
        "Mogh\u0101mdarreh"
    ],
    "name:fas_x_variant":[
        "Mogh\u0101ndar",
        "\u0645\u063a\u0627\u0646\u062f\u0631",
        "\u0645\u0642\u0646\u062f\u0631"
    ],
    "name:und_x_variant":[
        "M\u016bgh\u0101ndar",
        "Moqandar"
    ],
    "wof:name":"Moqandar",
    "wof:placetype":"locality"
},
  "geometry": {"coordinates":[49.96355,33.07437],"type":"Point"}
}