{
  "type": "Feature",
  "properties": {
    "gn:admin1_code":"1",
    "gn:asciiname":"Taherabad",
    "gn:country_code":"IR",
    "gn:dem":1110,
    "gn:feature_class":"P",
    "gn:feature_code":"PPL",
    "gn:name":"\u0162\u0101her\u0101b\u0101d",
    "gn:population":0,
    "gn:timezone":"Asia/Tehran",
    "iso:country":"IR",
    "name:aze_x_preferred":[
        "Tahirabad"
    ],
    "name:fas_x_preferred":[
        "\u0637\u0627\u0647\u0631 \u0622\u0628\u0627\u062f"
    ],
    "name:fas_x_variant":[
        "\u0162\u0101her\u0101b\u0101d"
    ],
    "wof:name":"Taherabad",
    "wof:placetype":"locality"
},
  "geometry": {"coordinates":[45.1442,38.8313],"type":"Point"}
}