{
  "type": "Feature",
  "properties": {
    "gn:admin1_code":"32",
    "gn:asciiname":"Malihlu",
    "gn:country_code":"IR",
    "gn:dem":915,
    "gn:feature_class":"P",
    "gn:feature_code":"PPL",
    "gn:name":"Mal\u012bhl\u016b",
    "gn:population":0,
    "gn:timezone":"Asia/Tehran",
    "iso:country":"IR",
    "name:fas_x_preferred":[
        "\u0645\u0644\u06cc\u0647 \u0644\u0648"
    ],
    "name:fas_x_variant":[
        "Mal\u012bhl\u016b"
    ],
    "wof:name":"Malihlu",
    "wof:placetype":"locality"
},
  "geometry": {"coordinates":[47.7191,39.0252],"type":"Point"}
}