{
  "type": "Feature",
  "properties": {
    "gn:admin1_code":"4",
    "gn:asciiname":"Dob-e Kur",
    "gn:country_code":"IR",
    "gn:dem":1158,
    "gn:feature_class":"P",
    "gn:feature_code":"PPL",
    "gn:name":"Dob-e K\u016br",
    "gn:population":0,
    "gn:timezone":"Asia/Tehran",
    "iso:country":"IR",
    "name:fas_x_preferred":[
        "\u062f\u0628 \u06a9\u0648\u0631"
    ],
    "name:fas_x_variant":[
        "Dob-e K\u016br"
    ],
    "wof:name":"Dob-e Kur",
    "wof:placetype":"locality"
},
  "geometry": {"coordinates":[62.5337,26.9259],"type":"Point"}
}