{
  "type": "Feature",
  "properties": {
    "gn:admin1_code":"16",
    "gn:asciiname":"Cheshmeh Kuri",
    "gn:country_code":"IR",
    "gn:dem":1671,
    "gn:feature_class":"P",
    "gn:feature_code":"PPL",
    "gn:name":"Cheshmeh K\u016br\u012b",
    "gn:population":0,
    "gn:timezone":"Asia/Tehran",
    "iso:country":"IR",
    "name:ara_x_preferred":[
        "\u062c\u0634\u0645\u0629 \u06a9\u0648\u0631\u0629"
    ],
    "name:ceb_x_preferred":[
        "Cheshmeh K\u016breh"
    ],
    "name:fas_x_preferred":[
        "\u0686\u0634\u0645\u0647 \u0643\u0648\u0631\u0647"
    ],
    "name:fas_x_variant":[
        "\u0686\u064e\u0634\u0645\u0650\u0647 \u0643\u0648\u0631\u0650\u0647",
        "Cheshmeh K\u016breh",
        "\u0686\u0634\u0645\u0647 \u06a9\u0648\u0631\u06cc",
        "\u0686\u0634\u0645\u0647 \u06a9\u0648\u0631\u0647"
    ],
    "name:swe_x_preferred":[
        "Cheshmeh K\u016breh"
    ],
    "name:und_x_variant":[
        "Chashmeh K\u016bra",
        "Chashmeh K\u016breh",
        "Cheshmeh K\u016br\u012b"
    ],
    "wof:name":"Cheshmeh Kuri",
    "wof:placetype":"locality"
},
  "geometry": {"coordinates":[47.83771,35.87337],"type":"Point"}
}