{
  "type": "Feature",
  "properties": {
    "gn:admin1_code":"7",
    "gn:asciiname":"Hajjiabad-e Ghuri",
    "gn:country_code":"IR",
    "gn:dem":845,
    "gn:feature_class":"P",
    "gn:feature_code":"PPL",
    "gn:name":"\u1e28\u0101jj\u012b\u0101b\u0101d-e Gh\u016br\u012b",
    "gn:population":0,
    "gn:timezone":"Asia/Tehran",
    "iso:country":"IR",
    "name:fas_x_preferred":[
        "\u1e28\u0101jj\u012b\u0101b\u0101d-e Gh\u016br\u012b"
    ],
    "name:fas_x_variant":[
        "\u062d\u0627\u062c\u06cc \u0622\u0628\u0627\u062f \u063a\u0648\u0631\u06cc",
        "\u062d\u0627\u062c\u06cc\u200c\u0622\u0628\u0627\u062f \u063a\u0648\u0631\u06cc"
    ],
    "name:msa_x_preferred":[
        "Hajjiabad-e Ghuri"
    ],
    "name:und_x_variant":[
        "\u1e28\u0101j\u012b\u0101b\u0101d \u2018Oly\u0101",
        "\u1e28\u0101jj\u012b\u0101b\u0101d-e B\u0101l\u0101",
        "\u1e28\u0101jj\u012b\u0101b\u0101d"
    ],
    "wof:name":"Hajjiabad-e Ghuri",
    "wof:placetype":"locality"
},
  "geometry": {"coordinates":[51.56157,29.82615],"type":"Point"}
}