{
  "type": "Feature",
  "properties": {
    "gn:admin1_code":"1.0",
    "gn:asciiname":"Torgheh",
    "gn:country_code":"IR",
    "gn:dem":1667,
    "gn:feature_class":"P",
    "gn:feature_code":"PPL",
    "gn:name":"Torgheh",
    "gn:population":0,
    "gn:timezone":"Asia/Tehran",
    "iso:country":"IR",
    "name:fas_x_preferred":[
        "\u062a\u064e\u0631\u0627\u0642\u0650\u0647"
    ],
    "name:fas_x_variant":[
        "\u0637\u0631\u063a\u0647",
        "Tar\u0101qeh"
    ],
    "wof:name":"Torgheh",
    "wof:placetype":"locality"
},
  "geometry": {"coordinates":[45.9755,36.5271],"type":"Point"}
}