{
  "type": "Feature",
  "properties": {
    "gn:admin1_code":"33",
    "gn:asciiname":"Hoseyn Kandi",
    "gn:country_code":"IR",
    "gn:dem":832,
    "gn:elevation":"0.0",
    "gn:feature_class":"P",
    "gn:feature_code":"PPL",
    "gn:name":"\u1e28oseyn Kand\u012b",
    "gn:population":0,
    "gn:timezone":"Asia/Tehran",
    "iso:country":"IR",
    "name:ara_x_preferred":[
        "\u062d\u0633\u064a\u0646 \u06a9\u0646\u062f\u064a"
    ],
    "name:aze_x_preferred":[
        "H\u00fcseyn k\u0259ndi"
    ],
    "name:fas_x_preferred":[
        "\u062d\u0633\u06cc\u0646 \u06a9\u0646\u062f\u06cc"
    ],
    "name:fas_x_variant":[
        "\u1e28oseyn Kand\u012b",
        "\u062d\u0633\u06cc\u0646\u200c\u06a9\u0646\u062f\u06cc"
    ],
    "name:msa_x_preferred":[
        "Hoseyn Kandi"
    ],
    "wof:name":"Hoseyn Kandi",
    "wof:placetype":"locality"
},
  "geometry": {"coordinates":[47.46627,38.62662],"type":"Point"}
}