{
  "type": "Feature",
  "properties": {
    "gn:admin1_code":"1.0",
    "gn:asciiname":"`Ali Kand",
    "gn:country_code":"IR",
    "gn:dem":1340,
    "gn:feature_class":"P",
    "gn:feature_code":"PPL",
    "gn:name":"\u2018Al\u012b Kand",
    "gn:population":0,
    "gn:timezone":"Asia/Tehran",
    "iso:country":"IR",
    "name:fas_x_preferred":[
        "\u0639\u0644\u06cc \u06a9\u0646\u062f"
    ],
    "name:fas_x_variant":[
        "\u2018Al\u012b Kand"
    ],
    "wof:name":"`Ali Kand",
    "wof:placetype":"locality"
},
  "geometry": {"coordinates":[46.115,36.6457],"type":"Point"}
}