{
  "type": "Feature",
  "properties": {
    "gn:admin1_code":"15",
    "gn:asciiname":"Mohammad-e Chalibeh",
    "gn:cc2":"IR",
    "gn:country_code":"IR",
    "gn:dem":24,
    "gn:feature_class":"P",
    "gn:feature_code":"PPL",
    "gn:name":"Mo\u1e29ammad-e Chal\u012bbeh",
    "gn:population":0,
    "gn:timezone":"Asia/Tehran",
    "iso:country":"IR",
    "name:fas_x_preferred":[
        "Mo\u1e29ammad-e Chal\u012bbeh"
    ],
    "name:und_x_variant":[
        "Muhammad Shalaiba"
    ],
    "wof:name":"Mohammad-e Chalibeh",
    "wof:placetype":"locality"
},
  "geometry": {"coordinates":[48.65,31.55],"type":"Point"}
}