{
  "type": "Feature",
  "properties": {
    "gn:admin1_code":"35",
    "gn:asciiname":"Pa'in Masir Mahalleh",
    "gn:country_code":"IR",
    "gn:dem":20,
    "gn:feature_class":"P",
    "gn:feature_code":"PPL",
    "gn:name":"P\u0101\u2019\u012bn Mas\u012br Ma\u1e29alleh",
    "gn:population":0,
    "gn:timezone":"Asia/Tehran",
    "iso:country":"IR",
    "name:fas_x_preferred":[
        "Ma\u015f\u012br Ma\u1e29alleh-ye P\u0101\u2019in"
    ],
    "name:fas_x_variant":[
        "P\u0101\u2019\u012bn Mas\u012br Ma\u1e29alleh",
        "\u067e\u0627\u0626\u06cc\u0646 \u0645\u0633\u06cc\u0631 \u0645\u062d\u0644\u0647"
    ],
    "wof:name":"Pa'in Masir Mahalleh",
    "wof:placetype":"locality"
},
  "geometry": {"coordinates":[52.52229000000001,36.47084],"type":"Point"}
}