{
  "type": "Feature",
  "properties": {
    "gn:admin1_code":"42",
    "gn:asciiname":"Ghazanfari",
    "gn:country_code":"IR",
    "gn:dem":860,
    "gn:feature_class":"P",
    "gn:feature_code":"PPL",
    "gn:name":"Gha\u1e95anfar\u012b",
    "gn:population":0,
    "gn:timezone":"Asia/Tehran",
    "iso:country":"IR",
    "name:ceb_x_preferred":[
        "Gha\u1e95anfar\u012b"
    ],
    "name:fas_x_preferred":[
        "\u063a\u0636\u0646\u0641\u0631\u06cc"
    ],
    "name:fas_x_variant":[
        "Gha\u1e95anfar\u012b"
    ],
    "name:swe_x_preferred":[
        "Gha\u1e95anfar\u012b"
    ],
    "wof:name":"Ghazanfari",
    "wof:placetype":"locality"
},
  "geometry": {"coordinates":[59.84425,34.18233],"type":"Point"}
}