{
  "type": "Feature",
  "properties": {
    "gn:admin1_code":"15",
    "gn:asciiname":"Kuh-e Shur",
    "gn:country_code":"IR",
    "gn:dem":963,
    "gn:feature_class":"P",
    "gn:feature_code":"PPL",
    "gn:name":"K\u016bh-e Sh\u016br",
    "gn:population":0,
    "gn:timezone":"Asia/Tehran",
    "iso:country":"IR",
    "name:fas_x_preferred":[
        "K\u016bh Sh\u016br-e Sofl\u00e1"
    ],
    "name:fas_x_variant":[
        "Kahsh\u016br-e P\u0101\u2019\u012bn",
        "\u06a9\u0647\u0634\u0648\u0631 \u067e\u0627\u0626\u06cc\u0646",
        "\u06a9\u0648\u0647 \u0634\u0648\u0631",
        "\u0634\u0646\u0628\u0647",
        "\u06a9\u0647\u0634\u0648\u0631 \u0639\u0644\u06cc \u0646\u0638\u0631"
    ],
    "name:und_x_variant":[
        "Kooh Shor Sofla",
        "K\u016bh Sh\u016br-e P\u0101\u2019\u012bn",
        "K\u016bh Sh\u016br Sofl\u00e1",
        "K\u016bh-e Sh\u016br",
        "Shanbeh",
        "Kohsh\u016br-e \u2018Al\u012bnaz\u0327ar"
    ],
    "wof:name":"Kuh-e Shur",
    "wof:placetype":"locality"
},
  "geometry": {"coordinates":[49.91541,31.78166],"type":"Point"}
}