{
  "type": "Feature",
  "properties": {
    "gn:admin1_code":"4.0",
    "gn:asciiname":"Tijnan-e Bala",
    "gn:country_code":"IR",
    "gn:dem":1213,
    "gn:feature_class":"P",
    "gn:feature_code":"PPL",
    "gn:name":"T\u012bjn\u0101n-e B\u0101l\u0101",
    "gn:population":0,
    "gn:timezone":"Asia/Tehran",
    "iso:country":"IR",
    "name:fas_x_preferred":[
        "\u062a\u064a\u062c\u0646\u0627\u0646 \u0628\u0627\u0644\u0627"
    ],
    "name:fas_x_variant":[
        "T\u012bj N\u0101n",
        "T\u012bjn\u0101n-e B\u0101l\u0101",
        "Tezn\u0101n"
    ],
    "name:und_x_variant":[
        "Tezn\u0101n"
    ],
    "wof:name":"Tijnan-e Bala",
    "wof:placetype":"locality"
},
  "geometry": {"coordinates":[61.4457,26.78461],"type":"Point"}
}