{
  "type": "Feature",
  "properties": {
    "gn:admin1_code":"28",
    "gn:asciiname":"Lahneh-ye Bala",
    "gn:country_code":"IR",
    "gn:dem":1560,
    "gn:feature_class":"P",
    "gn:feature_code":"PPL",
    "gn:name":"Lahneh-ye B\u0101l\u0101",
    "gn:population":0,
    "gn:timezone":"Asia/Tehran",
    "iso:country":"IR",
    "name:fas_x_preferred":[
        "\u0644\u0647\u0646\u0647 \u0628\u0627\u0644\u0627"
    ],
    "name:fas_x_variant":[
        "Lahneh-ye B\u0101l\u0101"
    ],
    "wof:name":"Lahneh-ye Bala",
    "wof:placetype":"locality"
},
  "geometry": {"coordinates":[52.2703,33.3007],"type":"Point"}
}