{
  "type": "Feature",
  "properties": {
    "gn:admin1_code":"23.0",
    "gn:asciiname":"Darbeygi",
    "gn:country_code":"IR",
    "gn:dem":1966,
    "gn:feature_class":"P",
    "gn:feature_code":"PPL",
    "gn:name":"D\u0101rbeyg\u012b",
    "gn:population":0,
    "gn:timezone":"Asia/Tehran",
    "iso:country":"IR",
    "name:fas_x_preferred":[
        "D\u0101rbeyg\u012b"
    ],
    "wof:name":"Darbeygi",
    "wof:placetype":"locality"
},
  "geometry": {"coordinates":[48.28333,33.53333],"type":"Point"}
}