{
  "type": "Feature",
  "properties": {
    "gn:admin1_code":"7",
    "gn:asciiname":"Tarbor-e Ja`fari",
    "gn:country_code":"IR",
    "gn:dem":1602,
    "gn:feature_class":"P",
    "gn:feature_code":"PPL",
    "gn:name":"Tarbor-e Ja\u2018far\u012b",
    "gn:population":0,
    "gn:timezone":"Asia/Tehran",
    "iso:country":"IR",
    "name:fas_x_preferred":[
        "\u062a\u0631\u0628\u0631 \u062c\u0639\u0641\u0631\u06cc"
    ],
    "name:fas_x_variant":[
        "Tarbor-e B\u0101l\u0101",
        "Tarbor-e Ja\u2018far\u012b"
    ],
    "wof:name":"Tarbor-e Ja`fari",
    "wof:placetype":"locality"
},
  "geometry": {"coordinates":[52.8587,29.6172],"type":"Point"}
}