{
  "type": "Feature",
  "properties": {
    "gn:admin1_code":"39",
    "gn:asciiname":"Mazra`eh Ab Danak",
    "gn:country_code":"IR",
    "gn:dem":1731,
    "gn:feature_class":"P",
    "gn:feature_code":"PPL",
    "gn:name":"Mazra\u2018eh \u0100b D\u0101nak",
    "gn:population":0,
    "gn:timezone":"Asia/Tehran",
    "iso:country":"IR",
    "name:fas_x_preferred":[
        "\u0100b D\u0101nak"
    ],
    "name:fas_x_variant":[
        "\u0622\u0628 \u062f\u0627\u0646\u0643",
        "\u0645\u0632\u0631\u0639\u0647 \u0622\u0628 \u062f\u0627\u0646\u0643",
        "\u0622\u0628\u062f\u0627\u0646\u06a9"
    ],
    "name:und_x_variant":[
        "Mazra\u2018eh \u0100b D\u0101nak"
    ],
    "name:urd_x_preferred":[
        "\u0622\u0628\u062f\u0627\u0646\u06a9"
    ],
    "wof:name":"Mazra`eh Ab Danak",
    "wof:placetype":"locality"
},
  "geometry": {"coordinates":[50.25685,34.7888],"type":"Point"}
}