{
  "type": "Feature",
  "properties": {
    "gn:admin1_code":"5",
    "gn:asciiname":"Darreh Geru-ye Pa'in",
    "gn:country_code":"IR",
    "gn:dem":1518,
    "gn:feature_class":"P",
    "gn:feature_code":"PPL",
    "gn:name":"Darreh Ger\u016b-ye P\u0101\u2019\u012bn",
    "gn:population":0,
    "gn:timezone":"Asia/Tehran",
    "iso:country":"IR",
    "name:fas_x_preferred":[
        "\u062f\u064e\u0631\u0650\u0651\u0647 \u06af\u0650\u0631\u0648\u0647 \u067e\u0627\u0626\u064a\u0646"
    ],
    "name:fas_x_variant":[
        "\u062f\u064e\u0631\u0650\u0651\u0647 \u06af\u064f\u0631\u0648\u0647 \u0633\u064f\u0641\u0644\u064e\u0649",
        "\u062f\u064e\u0631\u0650\u0651\u0647 \u06af\u0650\u0631\u064f\u0648\u06cc \u067e\u0627\u0626\u064a\u0646",
        "Darreh Ger\u016bh P\u0101\u2019\u012bn",
        "Darreh Ger\u016b-ye P\u0101\u2019\u012bn",
        "\u062f\u0631\u0647 \u06af\u0631\u0648 \u067e\u0627\u0626\u06cc\u0646",
        "Darreh Gor\u016bh Sofl\u00e1",
        "Darreh Gerow-ye P\u0101\u2019\u012bn"
    ],
    "wof:name":"Darreh Geru-ye Pa'in",
    "wof:placetype":"locality"
},
  "geometry": {"coordinates":[50.3792,31.241],"type":"Point"}
}