{
  "type": "Feature",
  "properties": {
    "gn:admin1_code":"42",
    "gn:asciiname":"Juymand",
    "gn:country_code":"IR",
    "gn:dem":1095,
    "gn:feature_class":"P",
    "gn:feature_code":"PPL",
    "gn:name":"J\u016bymand",
    "gn:population":0,
    "gn:timezone":"Asia/Tehran",
    "iso:country":"IR",
    "name:fas_x_preferred":[
        "J\u016bymand"
    ],
    "name:und_x_variant":[
        "J\u016bm\u012bn",
        "Juimand"
    ],
    "wof:name":"Juymand",
    "wof:placetype":"locality"
},
  "geometry": {"coordinates":[58.67806,34.35694],"type":"Point"}
}