{
  "type": "Feature",
  "properties": {
    "gn:admin1_code":"9.0",
    "gn:asciiname":"Tamachi",
    "gn:country_code":"IR",
    "gn:dem":1713,
    "gn:feature_class":"P",
    "gn:feature_code":"PPL",
    "gn:name":"\u0162amach\u012b",
    "gn:population":0,
    "gn:timezone":"Asia/Tehran",
    "iso:country":"IR",
    "name:fas_x_preferred":[
        "\u0637\u0645\u0686\u06cc"
    ],
    "name:fas_x_variant":[
        "\u0162amach\u012b"
    ],
    "name:und_x_variant":[
        "\u0162ameh Ch\u012b",
        "Tamch\u012b"
    ],
    "wof:name":"Tamachi",
    "wof:placetype":"locality"
},
  "geometry": {"coordinates":[49.2055,34.98602],"type":"Point"}
}