{
  "type": "Feature",
  "properties": {
    "gn:admin1_code":"7",
    "gn:asciiname":"Murdak",
    "gn:country_code":"IR",
    "gn:dem":1510,
    "gn:feature_class":"P",
    "gn:feature_code":"PPL",
    "gn:name":"M\u016brdak",
    "gn:population":0,
    "gn:timezone":"Asia/Tehran",
    "iso:country":"IR",
    "name:fas_x_preferred":[
        "M\u016brdak"
    ],
    "name:fas_x_variant":[
        "\u0645\u0648\u0631\u062f\u0643"
    ],
    "name:und_x_variant":[
        "\u0645\u0648\u0631\u062f\u0643"
    ],
    "wof:name":"Murdak",
    "wof:placetype":"locality"
},
  "geometry": {"coordinates":[53.88012,28.44393],"type":"Point"}
}