{
  "type": "Feature",
  "properties": {
    "gn:admin1_code":"8.0",
    "gn:asciiname":"Rangarz Mahalleh",
    "gn:country_code":"IR",
    "gn:dem":13,
    "gn:feature_class":"P",
    "gn:feature_code":"PPL",
    "gn:name":"Rangarz Ma\u1e29alleh",
    "gn:population":0,
    "gn:timezone":"Asia/Tehran",
    "iso:country":"IR",
    "name:fas_x_preferred":[
        "Rangarj Ma\u1e29alleh"
    ],
    "name:fas_x_variant":[
        "\u0631\u0646\u06af\u0631\u0632 \u0645\u062d\u0644\u0647",
        "\u0644\u0646\u06af\u0631\u0627\u062c \u0645\u062d\u0644\u0647",
        "\u0631\u0646\u06af\u0631\u062c \u0645\u062d\u0644\u0647",
        "\u0631\u0646\u06af\u0631\u062c\u200c\u0645\u062d\u0644\u0647"
    ],
    "name:msa_x_preferred":[
        "Rangarj Mahalleh"
    ],
    "name:ukr_x_preferred":[
        "\u0420\u0430\u043d\u0491\u0430\u0440\u0434\u0436-\u041c\u0430\u0445\u0430\u043b\u0435"
    ],
    "name:und_x_variant":[
        "Rangarz Ma\u1e29alleh",
        "Langar\u0101j Ma\u1e29alleh",
        "Rangaraj Ma\u1e29alleh"
    ],
    "wof:name":"Rangarz Mahalleh",
    "wof:placetype":"locality"
},
  "geometry": {"coordinates":[48.97468,37.6953],"type":"Point"}
}