{
  "type": "Feature",
  "properties": {
    "gn:admin1_code":"10.0",
    "gn:asciiname":"Amlak",
    "gn:country_code":"IR",
    "gn:dem":1060,
    "gn:feature_class":"P",
    "gn:feature_code":"PPL",
    "gn:name":"Aml\u0101k",
    "gn:population":0,
    "gn:timezone":"Asia/Tehran",
    "iso:country":"IR",
    "name:fas_x_preferred":[
        "\u0632\u064e\u0631\u0646\u0650\u0647 \u0643\u0648\u0686\u0650\u0643"
    ],
    "name:fas_x_variant":[
        "\u0632\u064e\u0631\u0646\u0650\u0647 \u0643\u0648\u0686\u064e\u0643",
        "\u0627\u064e\u0645\u0644\u0627\u0643\u0650 \u0632\u064e\u0631\u0646\u0650\u0647",
        "Aml\u0101k",
        "\u0627\u0645\u0644\u0627\u06a9",
        "Zarneh K\u016bchek",
        "Zarneh K\u016bchak"
    ],
    "name:und_x_variant":[
        "Aml\u0101k-e Zarneh",
        "Zarneh K\u016bchak"
    ],
    "wof:name":"Amlak",
    "wof:placetype":"locality"
},
  "geometry": {"coordinates":[46.1934,33.9187],"type":"Point"}
}