{
  "type": "Feature",
  "properties": {
    "gn:admin1_code":"1",
    "gn:asciiname":"Vali Kandi",
    "gn:country_code":"IR",
    "gn:dem":808,
    "gn:feature_class":"P",
    "gn:feature_code":"PPL",
    "gn:name":"Val\u012b Kand\u012b",
    "gn:population":0,
    "gn:timezone":"Asia/Tehran",
    "iso:country":"IR",
    "name:fas_x_preferred":[
        "\u0648\u0644\u06cc \u06a9\u0646\u062f\u06cc"
    ],
    "name:fas_x_variant":[
        "\u0648\u0627\u0644\u06cc \u0642\u0650\u0634\u0644\u0627\u0642",
        "Val\u012b Kand\u012b",
        "\u0648\u064e\u0644\u06cc \u0643\u064e\u0646\u062f\u06cc"
    ],
    "name:und_x_variant":[
        "Qeshlaq-e-V\u0101l\u012b",
        "V\u0101l\u012b Qeshl\u0101q",
        "Vali Qishl\u0101q",
        "Vali Kans"
    ],
    "wof:name":"Vali Kandi",
    "wof:placetype":"locality"
},
  "geometry": {"coordinates":[44.6294,39.7368],"type":"Point"}
}