{
  "type": "Feature",
  "properties": {
    "gn:admin1_code":"42",
    "gn:asciiname":"Solhabad",
    "gn:country_code":"IR",
    "gn:dem":1374,
    "gn:feature_class":"P",
    "gn:feature_code":"PPL",
    "gn:name":"\u015eol\u1e29\u0101b\u0101d",
    "gn:population":0,
    "gn:timezone":"Asia/Tehran",
    "iso:country":"IR",
    "name:fas_x_preferred":[
        "\u015eol\u1e29\u0101b\u0101d"
    ],
    "name:fas_x_variant":[
        "\u0635\u0644\u062d \u0622\u0628\u0627\u062f"
    ],
    "name:und_x_variant":[
        "\u0635\u0644\u062d \u0622\u0628\u0627\u062f"
    ],
    "wof:name":"Solhabad",
    "wof:placetype":"locality"
},
  "geometry": {"coordinates":[58.03153,34.49563],"type":"Point"}
}