{
  "type": "Feature",
  "properties": {
    "gn:admin1_code":"11",
    "gn:asciiname":"Kashrudkhaneh",
    "gn:country_code":"IR",
    "gn:dem":884,
    "gn:feature_class":"P",
    "gn:feature_code":"PPL",
    "gn:name":"Kashr\u016bdkh\u0101neh",
    "gn:population":0,
    "gn:timezone":"Asia/Tehran",
    "iso:country":"IR",
    "name:fas_x_preferred":[
        "\u06a9\u0634\u0631\u0648\u062f\u062e\u0627\u0646\u0647"
    ],
    "name:fas_x_variant":[
        "Kashr\u016bdkh\u0101neh"
    ],
    "wof:name":"Kashrudkhaneh",
    "wof:placetype":"locality"
},
  "geometry": {"coordinates":[56.2122,28.1478],"type":"Point"}
}