{
  "type": "Feature",
  "properties": {
    "gn:admin1_code":"16",
    "gn:asciiname":"Chapan-e Sofla",
    "gn:country_code":"IR",
    "gn:dem":1546,
    "gn:feature_class":"P",
    "gn:feature_code":"PPL",
    "gn:name":"Ch\u0101p\u0101n-e Sofl\u00e1",
    "gn:population":0,
    "gn:timezone":"Asia/Tehran",
    "iso:country":"IR",
    "name:ara_x_preferred":[
        "\u062a\u0634\u0627\u0628\u0627\u0646 \u0627\u0644\u0633\u0641\u0644\u064a"
    ],
    "name:ceb_x_preferred":[
        "Ch\u0101p\u0101n-e P\u0101'\u012bn"
    ],
    "name:ckb_x_preferred":[
        "\u0686\u0627\u067e\u0627\u0646 \u062e\u0648\u0627\u0631\u0648\u0648"
    ],
    "name:fas_x_preferred":[
        "\u0686\u0627\u067e\u0627\u0646\u0650 \u0633\u064f\u0641\u0644\u064e\u0649"
    ],
    "name:fas_x_variant":[
        "\u0686\u0627\u067e\u0627\u0646",
        "\u0686\u0627\u067e\u0627\u0646 \u0633\u064f\u0641\u0644\u064e\u0649",
        "\u0686\u0627\u067e\u0627\u0646 \u067e\u0627\u0626\u064a\u0646",
        "Ch\u0101p\u0101n-e Sofl\u00e1",
        "Ch\u0101p\u0101n-e P\u0101\u2019\u012bn",
        "\u0686\u0627\u067e\u0627\u0646 \u0633\u0641\u0644\u06cc"
    ],
    "name:kur_x_preferred":[
        "\u00c7apan xwar\u00fb"
    ],
    "name:swe_x_preferred":[
        "Ch\u0101p\u0101n-e P\u0101'\u012bn"
    ],
    "name:und_x_variant":[
        "Ch\u0101p\u0101n Sofl\u00e1",
        "Ch\u0101p\u0101n"
    ],
    "wof:name":"Chapan-e Sofla",
    "wof:placetype":"locality"
},
  "geometry": {"coordinates":[46.59354,36.18733],"type":"Point"}
}