{
  "type": "Feature",
  "properties": {
    "gn:admin1_code":"15",
    "gn:asciiname":"Pahvand-e Pa'in",
    "gn:country_code":"IR",
    "gn:dem":74,
    "gn:feature_class":"P",
    "gn:feature_code":"PPL",
    "gn:name":"Pahvand-e P\u0101\u2019\u012bn",
    "gn:population":0,
    "gn:timezone":"Asia/Tehran",
    "iso:country":"IR",
    "name:fas_x_preferred":[
        "Pahvand-e P\u0101\u2019\u012bn"
    ],
    "name:und_x_variant":[
        "Pahvandeh-ye P\u0101\u2019\u012bn",
        "Pahvandeh-ye Sofl\u0101",
        "Pahvandeh-ye Khod\u0101 Ra\u1e29\u012bm"
    ],
    "wof:name":"Pahvand-e Pa'in",
    "wof:placetype":"locality"
},
  "geometry": {"coordinates":[48.68333,32.18333],"type":"Point"}
}