{
  "type": "Feature",
  "properties": {
    "gn:admin1_code":"8",
    "gn:asciiname":"Saravandan",
    "gn:country_code":"IR",
    "gn:dem":28,
    "gn:feature_class":"P",
    "gn:feature_code":"PPL",
    "gn:name":"Sar\u0101vand\u0101n",
    "gn:population":0,
    "gn:timezone":"Asia/Tehran",
    "iso:country":"IR",
    "name:fas_x_preferred":[
        "Sarvand\u0101n"
    ],
    "name:fas_x_variant":[
        "\u0633\u0631\u0648\u0646\u062f\u0627\u0646",
        "\u0633\u0631\u0627\u0648\u0646\u062f\u0627\u0646"
    ],
    "name:und_x_variant":[
        "Sorvand\u0101n",
        "Surbandan",
        "\u0633\u0631\u0648\u0646\u062f\u0627\u0646",
        "Sar\u0101vand\u0101n"
    ],
    "wof:name":"Saravandan",
    "wof:placetype":"locality"
},
  "geometry": {"coordinates":[49.71708,37.1817],"type":"Point"}
}