{
  "type": "Feature",
  "properties": {
    "gn:admin1_code":"35.0",
    "gn:asciiname":"Sefid Ab",
    "gn:country_code":"IR",
    "gn:dem":347,
    "gn:feature_class":"P",
    "gn:feature_code":"PPL",
    "gn:name":"Sef\u012bd \u0100b",
    "gn:population":0,
    "gn:timezone":"Asia/Tehran",
    "iso:country":"IR",
    "name:fas_x_preferred":[
        "\u0633\u0641\u06cc\u062f \u0622\u0628"
    ],
    "name:fas_x_variant":[
        "Sef\u012bd \u0100b",
        "\u0633\u0641\u06cc\u062f\u0622\u0628"
    ],
    "wof:name":"Sefid Ab",
    "wof:placetype":"locality"
},
  "geometry": {"coordinates":[51.01787,36.67468],"type":"Point"}
}