{
  "type": "Feature",
  "properties": {
    "gn:admin1_code":"34",
    "gn:asciiname":"Deh-e Sefid",
    "gn:country_code":"IR",
    "gn:dem":2107,
    "gn:feature_class":"P",
    "gn:feature_code":"PPL",
    "gn:name":"Deh-e Sef\u012bd",
    "gn:population":0,
    "gn:timezone":"Asia/Tehran",
    "iso:country":"IR",
    "name:fas_x_preferred":[
        "\u062f\u0650\u0647\u0650 \u0633\u0650\u0641\u064a\u062f"
    ],
    "name:fas_x_variant":[
        "Deh-e Sef\u012bd",
        "\u062f\u0647\u200c\u0633\u0641\u06cc\u062f"
    ],
    "wof:name":"Deh-e Sefid",
    "wof:placetype":"locality"
},
  "geometry": {"coordinates":[49.55806,33.91305999999999],"type":"Point"}
}