{
  "type": "Feature",
  "properties": {
    "gn:admin1_code":"23.0",
    "gn:asciiname":"Tanab Sar Koshti",
    "gn:country_code":"IR",
    "gn:dem":1878,
    "gn:feature_class":"P",
    "gn:feature_code":"PPL",
    "gn:name":"Tan\u0101b Sar Kosht\u012b",
    "gn:population":0,
    "gn:timezone":"Asia/Tehran",
    "iso:country":"IR",
    "name:fas_x_preferred":[
        "\u062a\u0646\u0627\u0628 \u0633\u0631 \u06a9\u0634\u062a\u06cc"
    ],
    "name:und_x_variant":[
        "Tan\u0101b Sar Kosht\u012b"
    ],
    "wof:name":"Tanab Sar Koshti",
    "wof:placetype":"locality"
},
  "geometry": {"coordinates":[47.78326,33.99219],"type":"Point"}
}