{
  "type": "Feature",
  "properties": {
    "gn:admin1_code":"26",
    "gn:asciiname":"Shahrak-e Taleqani",
    "gn:country_code":"IR",
    "gn:dem":1145,
    "gn:feature_class":"P",
    "gn:feature_code":"PPL",
    "gn:name":"Shahrak-e \u0162\u0101leq\u0101n\u012b",
    "gn:population":0,
    "gn:timezone":"Asia/Tehran",
    "iso:country":"IR",
    "name:fas_x_preferred":[
        "\u0634\u0647\u0631\u06a9 \u0637\u0627\u0644\u0642\u0627\u0646\u06cc"
    ],
    "name:fas_x_variant":[
        "\u0633\u064a\u0646\u0627",
        "Shahrak-e \u0162\u0101leq\u0101n\u012b",
        "\u062e\u0644\u06cc\u062c \u0641\u0627\u0631\u0633 \u062c\u0646\u0648\u0628\u06cc"
    ],
    "name:und_x_variant":[
        "S\u012bn\u0101",
        "Khal\u012bj-e F\u0101rs Jon\u016bb\u012b"
    ],
    "wof:name":"Shahrak-e Taleqani",
    "wof:placetype":"locality"
},
  "geometry": {"coordinates":[51.26703,35.65953],"type":"Point"}
}