{
  "type": "Feature",
  "properties": {
    "gn:admin1_code":"13.0",
    "gn:asciiname":"Dizgaran",
    "gn:country_code":"IR",
    "gn:dem":1349,
    "gn:feature_class":"P",
    "gn:feature_code":"PPL",
    "gn:name":"Dizgaran",
    "gn:population":0,
    "gn:timezone":"Asia/Tehran",
    "iso:country":"IR",
    "name:fas_x_preferred":[
        "\u0639\u0644\u06cc \u0622\u0628\u0627\u062f"
    ],
    "name:fas_x_variant":[
        "\u2018Al\u012b\u0101b\u0101d",
        "\u062f\u06cc\u0632\u06af\u0631\u0627\u0646"
    ],
    "name:und_x_variant":[
        "Qal\u2019a Aliabad",
        "Dizgaran",
        "Qal\u2018eh \u2018Ali\u0101b\u0101d",
        "D\u012bzger\u0101n"
    ],
    "wof:name":"Dizgaran",
    "wof:placetype":"locality"
},
  "geometry": {"coordinates":[46.909,33.814],"type":"Point"}
}