{
  "type": "Feature",
  "properties": {
    "gn:admin1_code":"33",
    "gn:asciiname":"Qarah Qayah",
    "gn:country_code":"IR",
    "gn:dem":476,
    "gn:feature_class":"P",
    "gn:feature_code":"PPL",
    "gn:name":"Qarah Qayah",
    "gn:population":0,
    "gn:timezone":"Asia/Tehran",
    "iso:country":"IR",
    "name:fas_x_preferred":[
        "\u0642\u0631\u0647 \u0642\u064a\u0647"
    ],
    "wof:name":"Qarah Qayah",
    "wof:placetype":"locality"
},
  "geometry": {"coordinates":[47.31100000000001,39.1816],"type":"Point"}
}