{
  "type": "Feature",
  "properties": {
    "gn:admin1_code":"42",
    "gn:asciiname":"Kuh-e Boz Gir",
    "gn:country_code":"IR",
    "gn:dem":1717,
    "gn:feature_class":"P",
    "gn:feature_code":"PPL",
    "gn:name":"K\u016bh-e Boz G\u012br",
    "gn:population":0,
    "gn:timezone":"Asia/Tehran",
    "iso:country":"IR",
    "name:fas_x_preferred":[
        "K\u016bh-e Boz G\u012br"
    ],
    "wof:name":"Kuh-e Boz Gir",
    "wof:placetype":"locality"
},
  "geometry": {"coordinates":[59.60056,35.78055999999999],"type":"Point"}
}