{
  "type": "Feature",
  "properties": {
    "gn:admin1_code":"8",
    "gn:asciiname":"Basakmal Chal",
    "gn:country_code":"IR",
    "gn:dem":1163,
    "gn:feature_class":"P",
    "gn:feature_code":"PPLL",
    "gn:name":"B\u0101sakmal Ch\u0101l",
    "gn:population":0,
    "gn:timezone":"Asia/Tehran",
    "iso:country":"IR",
    "name:fas_x_preferred":[
        "\u0628\u0627\u0633\u06a9\u0645\u0644 \u0686\u0627\u0644"
    ],
    "name:und_x_variant":[
        "B\u0101sakmal Ch\u0101l"
    ],
    "wof:name":"Basakmal Chal",
    "wof:placetype":"locality"
},
  "geometry": {"coordinates":[49.02806,37.10269],"type":"Point"}
}