{
  "type": "Feature",
  "properties": {
    "gn:admin1_code":"36.0",
    "gn:asciiname":"Alwari",
    "gn:country_code":"IR",
    "gn:dem":1150,
    "gn:feature_class":"P",
    "gn:feature_code":"PPL",
    "gn:name":"Alwari",
    "gn:population":0,
    "gn:timezone":"Asia/Tehran",
    "iso:country":"IR",
    "name:fas_x_preferred":[
        "\u0627\u064e\u0644\u0648\u0627\u0631\u0644\u0648"
    ],
    "name:fas_x_variant":[
        "\u06af\u0648\u0632\u06cc \u0631\u064e\u062c\u0639\u064a\u0646",
        "\u0622\u0644\u0648\u0627\u0631\u0644\u0648",
        "Alv\u0101rl\u016b",
        "\u0100lv\u0101rl\u016b"
    ],
    "name:und_x_variant":[
        "G\u016bz\u012b Raj\u2018\u012bn",
        "Alwari"
    ],
    "wof:name":"Alwari",
    "wof:placetype":"locality"
},
  "geometry": {"coordinates":[47.8442,37.1195],"type":"Point"}
}