{
  "type": "Feature",
  "properties": {
    "gn:admin1_code":"1",
    "gn:asciiname":"Yowrqanlu",
    "gn:country_code":"IR",
    "gn:dem":1359,
    "gn:feature_class":"P",
    "gn:feature_code":"PPL",
    "gn:name":"Yowrq\u0101nl\u016b",
    "gn:population":0,
    "gn:timezone":"Asia/Tehran",
    "iso:country":"IR",
    "name:fas_x_preferred":[
        "\u064a\u064f\u0648\u0631\u0642\u0627\u0646\u0644\u0648\u06cc \u062c\u064e\u0646\u064a\u0632\u0650\u0647"
    ],
    "name:fas_x_variant":[
        "\u06cc\u0648\u0631\u0642\u0627\u0646\u0644\u0648",
        "Yowrq\u0101nl\u016b-ye Jan\u012bzeh",
        "Yowrq\u0101nl\u016b"
    ],
    "wof:name":"Yowrqanlu",
    "wof:placetype":"locality"
},
  "geometry": {"coordinates":[44.9674,37.662],"type":"Point"}
}