{
  "type": "Feature",
  "properties": {
    "gn:admin1_code":"13",
    "gn:asciiname":"Baderban",
    "gn:country_code":"IR",
    "gn:dem":1321,
    "gn:feature_class":"P",
    "gn:feature_code":"PPL",
    "gn:name":"Baderb\u0101n",
    "gn:population":0,
    "gn:timezone":"Asia/Tehran",
    "iso:country":"IR",
    "name:ceb_x_preferred":[
        "Baderb\u0101n"
    ],
    "name:fas_x_preferred":[
        "\u0628\u062f\u0631\u0628\u0627\u0646"
    ],
    "name:fas_x_variant":[
        "Baderb\u0101n"
    ],
    "name:fra_x_preferred":[
        "Baderban"
    ],
    "name:swe_x_preferred":[
        "Baderb\u0101n"
    ],
    "wof:name":"Baderban",
    "wof:placetype":"locality"
},
  "geometry": {"coordinates":[47.4976,34.4897],"type":"Point"}
}