{
  "type": "Feature",
  "properties": {
    "gn:admin1_code":"23",
    "gn:asciiname":"`Abd ol Mohammad",
    "gn:country_code":"IR",
    "gn:dem":1132,
    "gn:feature_class":"P",
    "gn:feature_code":"PPL",
    "gn:name":"\u2018Abd ol Mo\u1e29ammad",
    "gn:population":0,
    "gn:timezone":"Asia/Tehran",
    "iso:country":"IR",
    "name:fas_x_preferred":[
        "\u062a\u0648\u0647 \u062e\u0634\u06a9\u0647 \u0648\u0633\u0637\u0649 \u06a9\u0627\u0638\u0645"
    ],
    "name:fas_x_variant":[
        "T\u016bh Khoshkeh-ye Vos\u0163\u00e1",
        "Tovah Khoshkeh Vos\u0163\u00e1 K\u0101z\u0327em",
        "\u0639\u0628\u062f \u0627\u0644\u0645\u062d\u0645\u062f"
    ],
    "name:und_x_variant":[
        "\u2018Abd ol Mo\u1e29ammad"
    ],
    "wof:name":"`Abd ol Mohammad",
    "wof:placetype":"locality"
},
  "geometry": {"coordinates":[47.4714,33.3369],"type":"Point"}
}