{
  "type": "Feature",
  "properties": {
    "gn:admin1_code":"33.0",
    "gn:asciiname":"Varnakesh",
    "gn:country_code":"IR",
    "gn:dem":1886,
    "gn:feature_class":"P",
    "gn:feature_code":"PPL",
    "gn:name":"Varnakesh",
    "gn:population":0,
    "gn:timezone":"Asia/Tehran",
    "iso:country":"IR",
    "name:azb_x_preferred":[
        "\u0648\u0631\u0646\u06a9\u0634"
    ],
    "name:fas_x_preferred":[
        "\u0648\u0631\u0646\u0643\u0634"
    ],
    "name:fas_x_variant":[
        "\u0648\u0631\u0646\u06a9\u0634"
    ],
    "name:msa_x_preferred":[
        "Varnakesh"
    ],
    "wof:name":"Varnakesh",
    "wof:placetype":"locality"
},
  "geometry": {"coordinates":[47.449,37.6559],"type":"Point"}
}