{
  "type": "Feature",
  "properties": {
    "gn:admin1_code":"33",
    "gn:asciiname":"Pir `Azizam",
    "gn:country_code":"IR",
    "gn:dem":1948,
    "gn:feature_class":"P",
    "gn:feature_code":"PPL",
    "gn:name":"P\u012br \u2018Az\u012bzam",
    "gn:population":0,
    "gn:timezone":"Asia/Tehran",
    "iso:country":"IR",
    "name:ara_x_preferred":[
        "\u0628\u064a\u0631\u0639\u0632\u064a\u0632"
    ],
    "name:fas_x_preferred":[
        "\u067e\u06cc\u0631 \u0639\u0632\u06cc\u0632"
    ],
    "name:fas_x_variant":[
        "P\u012br \u2018Az\u012bz",
        "\u067e\u06cc\u0631 \u0639\u0632\u06cc\u0632\u0645",
        "\u067e\u06cc\u0631\u0639\u0632\u06cc\u0632"
    ],
    "name:msa_x_preferred":[
        "Pir Aziz"
    ],
    "name:und_x_variant":[
        "P\u012br \u2018Az\u012bzam"
    ],
    "wof:name":"Pir `Azizam",
    "wof:placetype":"locality"
},
  "geometry": {"coordinates":[47.29751,36.99327],"type":"Point"}
}