{
  "type": "Feature",
  "properties": {
    "gn:admin1_code":"29",
    "gn:asciiname":"Gol Moridan",
    "gn:country_code":"IR",
    "gn:dem":2045,
    "gn:feature_class":"P",
    "gn:feature_code":"PPL",
    "gn:name":"Gol Mor\u012bd\u0101n",
    "gn:population":0,
    "gn:timezone":"Asia/Tehran",
    "iso:country":"IR",
    "name:fas_x_preferred":[
        "\u06af\u0644 \u0645\u0631\u06cc\u062f\u0627\u0646"
    ],
    "name:fas_x_variant":[
        "Gol Mor\u012bd\u0101n"
    ],
    "wof:name":"Gol Moridan",
    "wof:placetype":"locality"
},
  "geometry": {"coordinates":[57.8837,28.9503],"type":"Point"}
}