{
  "type": "Feature",
  "properties": {
    "gn:admin1_code":"28.0",
    "gn:asciiname":"Sadd-e-Zayandeh Rud",
    "gn:country_code":"IR",
    "gn:dem":2131,
    "gn:feature_class":"P",
    "gn:feature_code":"PPL",
    "gn:name":"Sadd-e-Z\u0101yandeh R\u016bd",
    "gn:population":0,
    "gn:timezone":"Asia/Tehran",
    "iso:country":"IR",
    "name:fas_x_preferred":[
        "Sadd-e-Z\u0101yandeh R\u016bd"
    ],
    "wof:name":"Sadd-e-Zayandeh Rud",
    "wof:placetype":"locality"
},
  "geometry": {"coordinates":[50.74028,32.73611],"type":"Point"}
}