{
  "type": "Feature",
  "properties": {
    "gn:admin1_code":"23",
    "gn:asciiname":"Darreh Chenar",
    "gn:country_code":"IR",
    "gn:dem":1460,
    "gn:feature_class":"P",
    "gn:feature_code":"PPL",
    "gn:name":"Darreh Chen\u0101r",
    "gn:population":0,
    "gn:timezone":"Asia/Tehran",
    "iso:country":"IR",
    "name:fas_x_preferred":[
        "\u0686\u0646\u0627\u0631"
    ],
    "name:fas_x_variant":[
        "Darreh Chen\u0101r",
        "Chen\u0101r",
        "\u062f\u0631\u0647 \u0686\u0646\u0627\u0631"
    ],
    "wof:name":"Darreh Chenar",
    "wof:placetype":"locality"
},
  "geometry": {"coordinates":[49.01805,33.38305],"type":"Point"}
}