{
  "type": "Feature",
  "properties": {
    "gn:admin1_code":"1.0",
    "gn:asciiname":"Neysakabad",
    "gn:country_code":"IR",
    "gn:dem":1173,
    "gn:feature_class":"P",
    "gn:feature_code":"PPL",
    "gn:name":"Neysak\u0101b\u0101d",
    "gn:population":0,
    "gn:timezone":"Asia/Tehran",
    "iso:country":"IR",
    "name:fas_x_preferred":[
        "\u0646\u06cc\u0633\u06a9 \u0622\u0628\u0627\u062f"
    ],
    "name:fas_x_variant":[
        "Neysak\u0101b\u0101d"
    ],
    "wof:name":"Neysakabad",
    "wof:placetype":"locality"
},
  "geometry": {"coordinates":[45.4326,36.3568],"type":"Point"}
}