{
  "type": "Feature",
  "properties": {
    "gn:admin1_code":"7",
    "gn:asciiname":"Evaz",
    "gn:country_code":"IR",
    "gn:dem":968,
    "gn:feature_class":"P",
    "gn:feature_code":"PPL",
    "gn:name":"Evaz",
    "gn:population":0,
    "gn:timezone":"Asia/Tehran",
    "iso:country":"IR",
    "name:fas_x_preferred":[
        "\u0627\u0648\u0632"
    ],
    "name:und_x_variant":[
        "Avaz",
        "\u2018Iwaz",
        "\u2018Avaz",
        "Evazeh",
        "Evaz"
    ],
    "wof:name":"Evaz",
    "wof:placetype":"locality"
},
  "geometry": {"coordinates":[54.00417,27.7622],"type":"Point"}
}