{
  "type": "Feature",
  "properties": {
    "gn:admin1_code":"7",
    "gn:asciiname":"Evaz",
    "gn:country_code":"IR",
    "gn:dem":968,
    "gn:feature_class":"P",
    "gn:feature_code":"PPL",
    "gn:name":"Evaz",
    "gn:population":0,
    "gn:timezone":"Asia/Tehran",
    "iso:country":"IR",
    "name:ara_x_preferred":[
        "\u0639\u0648\u0636"
    ],
    "name:aze_x_preferred":[
        "Evaz"
    ],
    "name:ceb_x_preferred":[
        "Evaz"
    ],
    "name:fas_x_preferred":[
        "\u0627\u0648\u0632"
    ],
    "name:ita_x_preferred":[
        "Evaz"
    ],
    "name:mlg_x_preferred":[
        "Evaz"
    ],
    "name:msa_x_preferred":[
        "Evaz"
    ],
    "name:ron_x_preferred":[
        "Evaz"
    ],
    "name:rus_x_preferred":[
        "\u042d\u0432\u0435\u0437"
    ],
    "name:swe_x_preferred":[
        "Evaz"
    ],
    "name:tur_x_preferred":[
        "Evaz"
    ],
    "name:und_x_variant":[
        "Avaz",
        "\u2018Iwaz",
        "\u2018Avaz",
        "Evazeh"
    ],
    "name:urd_x_preferred":[
        "\u0627\u0648\u0632"
    ],
    "name:zho_x_preferred":[
        "\u57c3\u74e6\u8332"
    ],
    "wof:name":"Evaz",
    "wof:placetype":"locality"
},
  "geometry": {"coordinates":[54.00417,27.7622],"type":"Point"}
}