{
  "type": "Feature",
  "properties": {
    "gn:admin1_code":"15",
    "gn:asciiname":"Rafi`",
    "gn:country_code":"IR",
    "gn:dem":8,
    "gn:feature_class":"P",
    "gn:feature_code":"PPL",
    "gn:name":"Raf\u012b\u2018",
    "gn:population":0,
    "gn:timezone":"Asia/Tehran",
    "iso:country":"IR",
    "name:fas_x_preferred":[
        "\u0631\u0641\u06cc\u0639"
    ],
    "name:fas_x_variant":[
        "Raf\u012b\u2018"
    ],
    "wof:name":"Rafi`",
    "wof:placetype":"locality"
},
  "geometry": {"coordinates":[47.8946,31.5957],"type":"Point"}
}