{
  "type": "Feature",
  "properties": {
    "gn:admin1_code":"28",
    "gn:asciiname":"La Sib",
    "gn:country_code":"IR",
    "gn:dem":2008,
    "gn:feature_class":"P",
    "gn:feature_code":"PPL",
    "gn:name":"L\u0101 S\u012bb",
    "gn:population":0,
    "gn:timezone":"Asia/Tehran",
    "iso:country":"IR",
    "name:ara_x_preferred":[
        "\u0644\u0627\u0633\u064a\u0628"
    ],
    "name:fas_x_preferred":[
        "\u0644\u0627 \u0633\u06cc\u0628"
    ],
    "name:fas_x_variant":[
        "L\u0101 S\u012bb",
        "\u0644\u0627\u0633\u06cc\u0628"
    ],
    "name:und_x_variant":[
        "L\u0101seb"
    ],
    "name:urd_x_preferred":[
        "\u0644\u0627 \u0633\u06cc\u0628"
    ],
    "wof:name":"La Sib",
    "wof:placetype":"locality"
},
  "geometry": {"coordinates":[52.2633,33.1919],"type":"Point"}
}