{
  "type": "Feature",
  "properties": {
    "gn:admin1_code":"7.0",
    "gn:asciiname":"Khushbajan",
    "gn:country_code":"IR",
    "gn:dem":691,
    "gn:feature_class":"P",
    "gn:feature_code":"PPL",
    "gn:name":"Kh\u016bshb\u0101j\u0101n",
    "gn:population":0,
    "gn:timezone":"Asia/Tehran",
    "iso:country":"IR",
    "name:fas_x_preferred":[
        "Kh\u016bshb\u0101j\u0101n"
    ],
    "name:fas_x_variant":[
        "\u062e\u0648\u0634\u0627\u0628\u062c\u0627\u0646"
    ],
    "name:msa_x_preferred":[
        "Khushbajan"
    ],
    "wof:name":"Khushbajan",
    "wof:placetype":"locality"
},
  "geometry": {"coordinates":[52.88833,28.41056],"type":"Point"}
}