{
  "type": "Feature",
  "properties": {
    "gn:admin1_code":"41",
    "gn:asciiname":"Mahallabad",
    "gn:country_code":"IR",
    "gn:dem":1730,
    "gn:feature_class":"P",
    "gn:feature_code":"PPL",
    "gn:name":"Ma\u1e29all\u0101b\u0101d",
    "gn:population":0,
    "gn:timezone":"Asia/Tehran",
    "iso:country":"IR",
    "name:fas_x_preferred":[
        "\u0645\u062d\u0644 \u0622\u0628\u0627\u062f"
    ],
    "name:und_x_variant":[
        "Ma\u1e29all\u0101b\u0101d"
    ],
    "wof:name":"Mahallabad",
    "wof:placetype":"locality"
},
  "geometry": {"coordinates":[59.57859000000001,32.00694],"type":"Point"}
}