{
  "type": "Feature",
  "properties": {
    "gn:admin1_code":"1",
    "gn:asciiname":"Qal`eh-ye Qurineh",
    "gn:country_code":"IR",
    "gn:dem":2016,
    "gn:feature_class":"P",
    "gn:feature_code":"PPL",
    "gn:name":"Qal\u2018eh-ye Q\u016br\u012bneh",
    "gn:population":0,
    "gn:timezone":"Asia/Tehran",
    "iso:country":"IR",
    "name:fas_x_preferred":[
        "\u0642\u0644\u0639\u0647 \u0642\u0648\u0631\u06cc\u0646\u0647"
    ],
    "name:fas_x_variant":[
        "Qal\u2018eh Q\u016br\u012bneh"
    ],
    "name:und_x_variant":[
        "Qal\u2018eh-ye Q\u016br\u012bneh"
    ],
    "wof:name":"Qal`eh-ye Qurineh",
    "wof:placetype":"locality"
},
  "geometry": {"coordinates":[46.84211,36.55392],"type":"Point"}
}