{
  "type": "Feature",
  "properties": {
    "gn:admin1_code":"4.0",
    "gn:asciiname":"Deh-e Heydari",
    "gn:country_code":"IR",
    "gn:dem":483,
    "gn:feature_class":"P",
    "gn:feature_code":"PPL",
    "gn:name":"Deh-e \u1e28eydar\u012b",
    "gn:population":0,
    "gn:timezone":"Asia/Tehran",
    "iso:country":"IR",
    "name:fas_x_preferred":[
        "\u062f\u0647 \u062d\u06cc\u062f\u0631\u06cc"
    ],
    "name:fas_x_variant":[
        "Deh-e \u1e28eydar\u012b"
    ],
    "name:und_x_variant":[
        "Deh-e \u1e28eydar\u012b"
    ],
    "wof:name":"Deh-e Heydari",
    "wof:placetype":"locality"
},
  "geometry": {"coordinates":[61.5414,30.9611],"type":"Point"}
}