{
  "type": "Feature",
  "properties": {
    "gn:admin1_code":"10",
    "gn:asciiname":"Ban-e Rushan",
    "gn:country_code":"IR",
    "gn:dem":858,
    "gn:feature_class":"P",
    "gn:feature_code":"PPL",
    "gn:name":"B\u0101n-e R\u016bsh\u0101n",
    "gn:population":0,
    "gn:timezone":"Asia/Tehran",
    "iso:country":"IR",
    "name:fas_x_preferred":[
        "\u0628\u0627\u0646 \u0631\u0648\u0634\u0627\u0646"
    ],
    "name:fas_x_variant":[
        "B\u0101n-e R\u016bsh\u0101n",
        "\u0628\u064e\u0646\u062f\u064e\u0631\u0650 \u0648\u0633\u0627\u0646",
        "\u0628\u0627\u0646\u062f\u064e\u0631\u064a\u0634\u0627\u0646",
        "\u0628\u064e\u0646\u062f\u064e\u0631\u0633\u0627\u0646",
        "\u0628\u064e\u0646\u062f\u0631\u064a\u0634\u064e\u0646",
        "\u0628\u0627\u0646 \u0631\u064a\u0634\u0627\u0646",
        "\u0628\u0627\u0646\u0631\u0648\u0634\u0627\u0646"
    ],
    "name:msa_x_preferred":[
        "Ban-e Rushan"
    ],
    "name:und_x_variant":[
        "Bandars\u0101n",
        "B\u0101ndar\u012bsh\u0101n",
        "B\u0101n R\u012bsh\u0101n",
        "Bandr\u012bshan",
        "Bandar-o-S\u0101n",
        "Bandar-e \u016as\u0101n"
    ],
    "wof:name":"Ban-e Rushan",
    "wof:placetype":"locality"
},
  "geometry": {"coordinates":[46.2192,33.5587],"type":"Point"}
}