{
  "type": "Feature",
  "properties": {
    "gn:admin1_code":"1",
    "gn:asciiname":"Qezeljah",
    "gn:country_code":"IR",
    "gn:dem":1310,
    "gn:feature_class":"P",
    "gn:feature_code":"PPL",
    "gn:name":"Qezeljah",
    "gn:population":0,
    "gn:timezone":"Asia/Tehran",
    "iso:country":"IR",
    "name:fas_x_preferred":[
        "\u0642\u0632\u0644\u062c\u0647"
    ],
    "wof:name":"Qezeljah",
    "wof:placetype":"locality"
},
  "geometry": {"coordinates":[44.8941,38.1995],"type":"Point"}
}