{
  "type": "Feature",
  "properties": {
    "gn:admin1_code":"32",
    "gn:asciiname":"Khalifeh Davud",
    "gn:country_code":"IR",
    "gn:dem":1233,
    "gn:feature_class":"P",
    "gn:feature_code":"PPL",
    "gn:name":"Khal\u012bfeh D\u0101v\u016bd",
    "gn:population":0,
    "gn:timezone":"Asia/Tehran",
    "iso:country":"IR",
    "name:azb_x_preferred":[
        "\u062e\u0644\u06cc\u0641\u0647 \u062f\u0627\u0648\u0648\u062f"
    ],
    "name:ceb_x_preferred":[
        "Khal\u012bfeh D\u0101v\u016bd"
    ],
    "name:fas_x_preferred":[
        "\u062e\u0644\u064a\u0641\u0647 \u062f\u0627\u0648\u062f"
    ],
    "name:fas_x_variant":[
        "Khal\u012bfeh D\u0101v\u016bd",
        "\u062e\u0644\u06cc\u0641\u0647\u200c\u062f\u0627\u0648\u062f"
    ],
    "name:msa_x_preferred":[
        "Khalifeh Davud"
    ],
    "name:mzn_x_preferred":[
        "\u062e\u0644\u06cc\u0641\u0647\u200c\u062f\u0627\u0648\u062f"
    ],
    "name:swe_x_preferred":[
        "Khal\u012bfeh D\u0101v\u016bd"
    ],
    "wof:name":"Khalifeh Davud",
    "wof:placetype":"locality"
},
  "geometry": {"coordinates":[47.8885,38.7444],"type":"Point"}
}