{
  "type": "Feature",
  "properties": {
    "gn:admin1_code":"35",
    "gn:asciiname":"Qal`eh-ye Palangan",
    "gn:country_code":"IR",
    "gn:dem":-23,
    "gn:feature_class":"P",
    "gn:feature_code":"PPL",
    "gn:name":"Qal\u2018eh-ye Palang\u0101n",
    "gn:population":0,
    "gn:timezone":"Asia/Tehran",
    "iso:country":"IR",
    "name:fas_x_preferred":[
        "\u0642\u064e\u0644\u0639\u0650\u0647"
    ],
    "name:fas_x_variant":[
        "\u0642\u0644\u0639\u0647 \u067e\u0644\u0646\u06af\u0627\u0646",
        "Qal\u2018eh",
        "Qal\u2018eh-ye Palang\u0101n"
    ],
    "name:und_x_variant":[
        "Qal sh-i-Palang\u0101n",
        "Qal\u2019eh-i-Palangan"
    ],
    "wof:name":"Qal`eh-ye Palangan",
    "wof:placetype":"locality"
},
  "geometry": {"coordinates":[53.41906,36.84907000000001],"type":"Point"}
}