{
  "type": "Feature",
  "properties": {
    "gn:admin1_code":"37",
    "gn:asciiname":"Sadd-e Anushirvan",
    "gn:country_code":"IR",
    "gn:dem":15,
    "gn:feature_class":"P",
    "gn:feature_code":"PPL",
    "gn:name":"Sadd-e An\u016bsh\u012brv\u0101n",
    "gn:population":0,
    "gn:timezone":"Asia/Tehran",
    "iso:country":"IR",
    "name:fas_x_preferred":[
        "Sadd-e An\u016bsh\u012brv\u0101n"
    ],
    "name:fas_x_variant":[
        "\u0633\u062f \u0627\u0646\u0648\u0634\u06cc\u0631\u0648\u0627\u0646"
    ],
    "name:und_x_variant":[
        "\u0633\u062f \u0627\u0646\u0648\u0634\u06cc\u0631\u0648\u0627\u0646"
    ],
    "wof:name":"Sadd-e Anushirvan",
    "wof:placetype":"locality"
},
  "geometry": {"coordinates":[54.80392,37.24417],"type":"Point"}
}