{
  "type": "Feature",
  "properties": {
    "gn:admin1_code":"38",
    "gn:asciiname":"Khosrowabad",
    "gn:country_code":"IR",
    "gn:dem":2114,
    "gn:feature_class":"P",
    "gn:feature_code":"PPL",
    "gn:name":"Khosrow\u0101b\u0101d",
    "gn:population":0,
    "gn:timezone":"Asia/Tehran",
    "iso:country":"IR",
    "name:fas_x_preferred":[
        "\u062e\u0633\u0631\u0648 \u0622\u0628\u0627\u062f"
    ],
    "name:fas_x_variant":[
        "\u0647\u064e\u0631\u0627\u0626\u064a\u0646",
        "Khosrow\u0101b\u0101d"
    ],
    "name:und_x_variant":[
        "Har\u0101\u2019\u012bn"
    ],
    "wof:name":"Khosrowabad",
    "wof:placetype":"locality"
},
  "geometry": {"coordinates":[49.31491,35.51117],"type":"Point"}
}