{
  "type": "Feature",
  "properties": {
    "gn:admin1_code":"8.0",
    "gn:asciiname":"Yari Mahalleh",
    "gn:country_code":"IR",
    "gn:dem":92,
    "gn:feature_class":"P",
    "gn:feature_code":"PPL",
    "gn:name":"Y\u0101r\u012b Ma\u1e29alleh",
    "gn:population":0,
    "gn:timezone":"Asia/Tehran",
    "iso:country":"IR",
    "name:ceb_x_preferred":[
        "Y\u0101r\u012b Ma\u1e29alleh"
    ],
    "name:fas_x_preferred":[
        "\u06cc\u0627\u0631\u06cc \u0645\u062d\u0644\u0647"
    ],
    "name:fas_x_variant":[
        "Y\u0101r\u012b Ma\u1e29alleh",
        "\u06cc\u0627\u0631\u06cc\u200c\u0645\u062d\u0644\u0647"
    ],
    "name:msa_x_preferred":[
        "Yari Mahalleh"
    ],
    "name:swe_x_preferred":[
        "Y\u0101r\u012b Ma\u1e29alleh"
    ],
    "name:ukr_x_preferred":[
        "\u042f\u0440\u0456-\u041c\u0430\u0445\u0430\u043b\u0435"
    ],
    "name:urd_x_preferred":[
        "\u06cc\u0627\u0631\u06cc \u0645\u06c1\u0627\u0644\u06c1"
    ],
    "wof:name":"Yari Mahalleh",
    "wof:placetype":"locality"
},
  "geometry": {"coordinates":[48.9317,37.7205],"type":"Point"}
}