{
  "type": "Feature",
  "properties": {
    "gn:admin1_code":"13",
    "gn:asciiname":"Bazan-e Kikan",
    "gn:country_code":"IR",
    "gn:dem":1787,
    "gn:feature_class":"P",
    "gn:feature_code":"PPL",
    "gn:name":"B\u0101z\u0101n-e K\u012bk\u0101n",
    "gn:population":0,
    "gn:timezone":"Asia/Tehran",
    "iso:country":"IR",
    "name:fas_x_preferred":[
        "\u0628\u0627\u0632\u0627\u0646 \u06a9\u064a\u06a9\u0627\u0646"
    ],
    "name:fas_x_variant":[
        "B\u0101z\u0101n-e K\u012bk\u0101n"
    ],
    "wof:name":"Bazan-e Kikan",
    "wof:placetype":"locality"
},
  "geometry": {"coordinates":[46.39100000000001,34.7316],"type":"Point"}
}