{
  "type": "Feature",
  "properties": {
    "gn:admin1_code":"1",
    "gn:asciiname":"Narziveh",
    "gn:country_code":"IR",
    "gn:dem":1403,
    "gn:feature_class":"P",
    "gn:feature_code":"PPL",
    "gn:name":"Narz\u012bveh",
    "gn:population":0,
    "gn:timezone":"Asia/Tehran",
    "iso:country":"IR",
    "name:fas_x_preferred":[
        "\u0646\u0631\u0632\u06cc\u0648\u0647"
    ],
    "name:fas_x_variant":[
        "Narz\u012bveh"
    ],
    "wof:name":"Narziveh",
    "wof:placetype":"locality"
},
  "geometry": {"coordinates":[45.1278,37.018],"type":"Point"}
}