{
  "type": "Feature",
  "properties": {
    "gn:admin1_code":"23.0",
    "gn:asciiname":"Japelaq",
    "gn:country_code":"IR",
    "gn:dem":1939,
    "gn:feature_class":"P",
    "gn:feature_code":"PPL",
    "gn:name":"J\u0101pelaq",
    "gn:population":0,
    "gn:timezone":"Asia/Tehran",
    "iso:country":"IR",
    "name:fas_x_preferred":[
        "\u062c\u0627\u067e\u0650\u0644\u064e\u0642"
    ],
    "name:und_x_variant":[
        "J\u0101pelaq"
    ],
    "wof:name":"Japelaq",
    "wof:placetype":"locality"
},
  "geometry": {"coordinates":[49.57694,33.62472],"type":"Point"}
}