{
  "type": "Feature",
  "properties": {
    "gn:admin1_code":"38.0",
    "gn:asciiname":"Shahrak-e Narjeh",
    "gn:country_code":"IR",
    "gn:dem":1298,
    "gn:feature_class":"P",
    "gn:feature_code":"PPL",
    "gn:name":"Shahrak-e Narjeh",
    "gn:population":0,
    "gn:timezone":"Asia/Tehran",
    "iso:country":"IR",
    "name:fas_x_preferred":[
        "\u0646\u0631\u062c\u0647"
    ],
    "name:fas_x_variant":[
        "\u0634\u0647\u0631\u06a9 \u0646\u0631\u062c\u0647"
    ],
    "name:und_x_variant":[
        "Narjeh",
        "Shahrak-e Narjeh"
    ],
    "wof:name":"Shahrak-e Narjeh",
    "wof:placetype":"locality"
},
  "geometry": {"coordinates":[49.61534,36.00082000000001],"type":"Point"}
}