{
  "type": "Feature",
  "properties": {
    "gn:admin1_code":"4",
    "gn:asciiname":"Malekabad-e Now Kabur",
    "gn:country_code":"IR",
    "gn:dem":1891,
    "gn:feature_class":"P",
    "gn:feature_code":"PPL",
    "gn:name":"Malek\u0101b\u0101d-e Now Kab\u016br",
    "gn:population":0,
    "gn:timezone":"Asia/Tehran",
    "iso:country":"IR",
    "name:fas_x_preferred":[
        "\u0645\u0644\u06a9 \u0622\u0628\u0627\u062f \u0646\u0648 \u06a9\u0628\u0648\u0631"
    ],
    "name:fas_x_variant":[
        "Malek\u0101b\u0101d-e Now Kab\u016br"
    ],
    "wof:name":"Malekabad-e Now Kabur",
    "wof:placetype":"locality"
},
  "geometry": {"coordinates":[60.9599,28.5312],"type":"Point"}
}