{
  "type": "Feature",
  "properties": {
    "gn:admin1_code":"11.0",
    "gn:asciiname":"Kontaki-ye `Ali Gerd `Ali",
    "gn:country_code":"IR",
    "gn:dem":16,
    "gn:feature_class":"P",
    "gn:feature_code":"PPL",
    "gn:name":"Kontak\u012b-ye \u2018Al\u012b Gerd \u2018Al\u012b",
    "gn:population":0,
    "gn:timezone":"Asia/Tehran",
    "iso:country":"IR",
    "name:fas_x_preferred":[
        "Kontak\u012b-ye \u2018Al\u012b Gerd \u2018Al\u012b"
    ],
    "name:fas_x_variant":[
        "\u06a9\u0646\u062a\u06a9\u06cc \u0639\u0644\u06cc \u06af\u0631\u062f \u0639\u0644\u06cc"
    ],
    "wof:name":"Kontaki-ye `Ali Gerd `Ali",
    "wof:placetype":"locality"
},
  "geometry": {"coordinates":[58.47059,25.71408],"type":"Point"}
}