{
  "type": "Feature",
  "properties": {
    "gn:admin1_code":"35.0",
    "gn:asciiname":"Vaposhteh",
    "gn:country_code":"IR",
    "gn:dem":1139,
    "gn:feature_class":"P",
    "gn:feature_code":"PPL",
    "gn:name":"V\u0101poshteh",
    "gn:population":0,
    "gn:timezone":"Asia/Tehran",
    "iso:country":"IR",
    "name:fas_x_preferred":[
        "V\u0101poshteh"
    ],
    "name:fas_x_variant":[
        "\u0648\u0627\u067e\u0634\u062a\u0647"
    ],
    "wof:name":"Vaposhteh",
    "wof:placetype":"locality"
},
  "geometry": {"coordinates":[50.61044,36.82932],"type":"Point"}
}