{
  "type": "Feature",
  "properties": {
    "gn:admin1_code":"29.0",
    "gn:asciiname":"Goraghan",
    "gn:country_code":"IR",
    "gn:dem":2001,
    "gn:feature_class":"P",
    "gn:feature_code":"PPL",
    "gn:name":"Gor\u0101gh\u0101n",
    "gn:population":0,
    "gn:timezone":"Asia/Tehran",
    "iso:country":"IR",
    "name:fas_x_preferred":[
        "\u06af\u0631\u0627\u063a\u0627\u0646"
    ],
    "name:fas_x_variant":[
        "Gor\u0101gh\u0101n"
    ],
    "wof:name":"Goraghan",
    "wof:placetype":"locality"
},
  "geometry": {"coordinates":[57.8993,28.8865],"type":"Point"}
}