{
  "type": "Feature",
  "properties": {
    "gn:admin1_code":"4",
    "gn:asciiname":"Kuh-e Vang",
    "gn:country_code":"IR",
    "gn:dem":186,
    "gn:feature_class":"P",
    "gn:feature_code":"PPL",
    "gn:name":"K\u016bh-e Vang",
    "gn:population":0,
    "gn:timezone":"Asia/Tehran",
    "iso:country":"IR",
    "name:fas_x_preferred":[
        "K\u016bh-e Vang"
    ],
    "wof:name":"Kuh-e Vang",
    "wof:placetype":"locality"
},
  "geometry": {"coordinates":[59.65667,26.02722],"type":"Point"}
}