{
  "type": "Feature",
  "properties": {
    "gn:admin1_code":"23",
    "gn:asciiname":"`Alimorad Khan",
    "gn:country_code":"IR",
    "gn:dem":1713,
    "gn:feature_class":"P",
    "gn:feature_code":"PPL",
    "gn:name":"\u2018Al\u012bmor\u0101d Kh\u0101n",
    "gn:population":0,
    "gn:timezone":"Asia/Tehran",
    "iso:country":"IR",
    "name:fas_x_preferred":[
        "\u0639\u064e\u0644\u064a\u0645\u064f\u0631\u0627\u062f \u062e\u0627\u0646"
    ],
    "name:fas_x_variant":[
        "\u2018Al\u012bmor\u0101d Kh\u0101n"
    ],
    "wof:name":"`Alimorad Khan",
    "wof:placetype":"locality"
},
  "geometry": {"coordinates":[47.58333,34.01667],"type":"Point"}
}