{
  "type": "Feature",
  "properties": {
    "gn:admin1_code":"25",
    "gn:asciiname":"Kan Qoli Khan",
    "gn:country_code":"IR",
    "gn:dem":864,
    "gn:feature_class":"P",
    "gn:feature_code":"PPL",
    "gn:name":"Kan Qol\u012b Kh\u0101n",
    "gn:population":0,
    "gn:timezone":"Asia/Tehran",
    "iso:country":"IR",
    "name:fas_x_preferred":[
        "\u0643\u0646\u062f"
    ],
    "name:fas_x_variant":[
        "\u06a9\u0646 \u0642\u0644\u06cc \u062e\u0627\u0646",
        "\u0643\u064e\u0646\u062f\u0650 \u0642\u064f\u0644\u06cc \u062e\u0627\u0646"
    ],
    "name:und_x_variant":[
        "Kond",
        "Kan Qol\u012b Kh\u0101n",
        "Kand-e Qol\u012b Kh\u0101n"
    ],
    "wof:name":"Kan Qoli Khan",
    "wof:placetype":"locality"
},
  "geometry": {"coordinates":[52.49358,35.22494000000001],"type":"Point"}
}