{
  "type": "Feature",
  "properties": {
    "gn:admin1_code":"42",
    "gn:asciiname":"Maqsudabad",
    "gn:country_code":"IR",
    "gn:dem":1184,
    "gn:feature_class":"P",
    "gn:feature_code":"PPL",
    "gn:name":"Maq\u015f\u016bd\u0101b\u0101d",
    "gn:population":0,
    "gn:timezone":"Asia/Tehran",
    "iso:country":"IR",
    "name:fas_x_preferred":[
        "\u0645\u0642\u0635\u0648\u062f \u0622\u0628\u0627\u062f \u067e\u0627\u0626\u06cc\u0646"
    ],
    "name:fas_x_variant":[
        "Maq\u015f\u016bd\u0101b\u0101d-e P\u0101\u2019\u012bn",
        "\u0645\u0642\u0635\u0648\u062f \u0622\u0628\u0627\u062f",
        "\u0645\u0642\u0635\u0648\u062f\u0622\u0628\u0627\u062f"
    ],
    "name:und_x_variant":[
        "Maq\u015f\u016bd\u0101b\u0101d"
    ],
    "wof:name":"Maqsudabad",
    "wof:placetype":"locality"
},
  "geometry": {"coordinates":[58.87984,36.80319],"type":"Point"}
}