{
  "type": "Feature",
  "properties": {
    "gn:admin1_code":"8",
    "gn:asciiname":"Gorbeh Kuchak",
    "gn:country_code":"IR",
    "gn:dem":16,
    "gn:feature_class":"P",
    "gn:feature_code":"PPL",
    "gn:name":"Gorbeh K\u016bchak",
    "gn:population":0,
    "gn:timezone":"Asia/Tehran",
    "iso:country":"IR",
    "name:fas_x_preferred":[
        "\u06af\u0631\u0628\u0647 \u06a9\u0648\u0686\u06a9"
    ],
    "name:fas_x_variant":[
        "Gorbeh K\u016bchak"
    ],
    "wof:name":"Gorbeh Kuchak",
    "wof:placetype":"locality"
},
  "geometry": {"coordinates":[49.3213,37.2453],"type":"Point"}
}