{
  "type": "Feature",
  "properties": {
    "gn:admin1_code":"37",
    "gn:asciiname":"Namazabad",
    "gn:country_code":"IR",
    "gn:dem":-26,
    "gn:feature_class":"P",
    "gn:feature_code":"PPL",
    "gn:name":"Nam\u0101z\u0101b\u0101d",
    "gn:population":0,
    "gn:timezone":"Asia/Tehran",
    "iso:country":"IR",
    "name:fas_x_preferred":[
        "\u0646\u064e\u0645\u0627\u0632 \u0622\u0628\u0627\u062f"
    ],
    "wof:name":"Namazabad",
    "wof:placetype":"locality"
},
  "geometry": {"coordinates":[54.08333,36.85],"type":"Point"}
}