{
  "type": "Feature",
  "properties": {
    "gn:admin1_code":"4.0",
    "gn:asciiname":"Dahan",
    "gn:country_code":"IR",
    "gn:dem":1128,
    "gn:feature_class":"P",
    "gn:feature_code":"PPL",
    "gn:name":"Dah\u0101n",
    "gn:population":0,
    "gn:timezone":"Asia/Tehran",
    "iso:country":"IR",
    "name:ceb_x_preferred":[
        "Dahan"
    ],
    "name:deu_x_preferred":[
        "Dahan"
    ],
    "name:fas_x_preferred":[
        "\u062f\u0647\u0646"
    ],
    "name:fas_x_variant":[
        "Dah\u0101n",
        "\u062f\u0647\u0627\u0646"
    ],
    "name:fra_x_preferred":[
        "Dahan"
    ],
    "name:heb_x_preferred":[
        "\u05d3\u05d4\u05d0\u05df"
    ],
    "name:swe_x_preferred":[
        "Dahan"
    ],
    "name:ukr_x_preferred":[
        "\u0414\u0430\u0430\u043d"
    ],
    "name:und_x_variant":[
        "Deh\u0101n"
    ],
    "wof:name":"Dahan",
    "wof:placetype":"locality"
},
  "geometry": {"coordinates":[62.14946,27.22437],"type":"Point"}
}