{
  "type": "Feature",
  "properties": {
    "gn:admin1_code":"38.0",
    "gn:asciiname":"Zargar",
    "gn:country_code":"IR",
    "gn:dem":1195,
    "gn:elevation":"0.0",
    "gn:feature_class":"P",
    "gn:feature_code":"PPL",
    "gn:name":"Zargar",
    "gn:population":0,
    "gn:timezone":"Asia/Tehran",
    "iso:country":"IR",
    "name:ara_x_preferred":[
        "\u0632\u0631\u063a\u0631"
    ],
    "name:fas_x_preferred":[
        "\u0632\u0631\u06af\u0631"
    ],
    "wof:name":"Zargar",
    "wof:placetype":"locality"
},
  "geometry": {"coordinates":[50.3826,36.0562],"type":"Point"}
}