{
  "type": "Feature",
  "properties": {
    "gn:admin1_code":"5.0",
    "gn:asciiname":"Bard Gayun",
    "gn:country_code":"IR",
    "gn:dem":1562,
    "gn:feature_class":"P",
    "gn:feature_code":"PPL",
    "gn:name":"Bard G\u0101y\u016bn",
    "gn:population":0,
    "gn:timezone":"Asia/Tehran",
    "iso:country":"IR",
    "name:fas_x_preferred":[
        "Bard G\u0101y\u016bn"
    ],
    "name:fas_x_variant":[
        "\u0628\u0631\u062f \u06af\u0627\u06cc\u0648\u0646"
    ],
    "wof:name":"Bard Gayun",
    "wof:placetype":"locality"
},
  "geometry": {"coordinates":[50.93979,30.6535],"type":"Point"}
}