{
  "type": "Feature",
  "properties": {
    "gn:admin1_code":"29",
    "gn:asciiname":"Tolombeh-ye Tala'i",
    "gn:country_code":"IR",
    "gn:dem":1651,
    "gn:feature_class":"P",
    "gn:feature_code":"PPL",
    "gn:name":"Tolombeh-ye \u0162al\u0101\u2019\u012b",
    "gn:population":0,
    "gn:timezone":"Asia/Tehran",
    "iso:country":"IR",
    "name:fas_x_preferred":[
        "\u062a\u0644\u0645\u0628\u0647 \u0637\u0644\u0627\u0626\u06cc"
    ],
    "name:fas_x_variant":[
        "\u0162al\u0101\u2019\u012b",
        "Tolombeh-ye \u0162al\u0101\u2019\u012b"
    ],
    "wof:name":"Tolombeh-ye Tala'i",
    "wof:placetype":"locality"
},
  "geometry": {"coordinates":[56.4114,30.3366],"type":"Point"}
}