{
  "type": "Feature",
  "properties": {
    "gn:admin1_code":"26.0",
    "gn:asciiname":"Lashgarabad",
    "gn:country_code":"IR",
    "gn:dem":1253,
    "gn:feature_class":"P",
    "gn:feature_code":"PPL",
    "gn:name":"Lashgar\u0101b\u0101d",
    "gn:population":0,
    "gn:timezone":"Asia/Tehran",
    "iso:country":"IR",
    "name:fas_x_preferred":[
        "\u0644\u0634\u06af\u0631 \u0622\u0628\u0627\u062f"
    ],
    "wof:name":"Lashgarabad",
    "wof:placetype":"locality"
},
  "geometry": {"coordinates":[50.7505,35.8578],"type":"Point"}
}