{
  "type": "Feature",
  "properties": {
    "gn:admin1_code":"35.0",
    "gn:asciiname":"Kumeh Kola",
    "gn:country_code":"IR",
    "gn:dem":118,
    "gn:feature_class":"P",
    "gn:feature_code":"PPL",
    "gn:name":"K\u016bmeh Kol\u0101",
    "gn:population":0,
    "gn:timezone":"Asia/Tehran",
    "iso:country":"IR",
    "name:fas_x_preferred":[
        "\u0643\u0627\u0645\u06cc \u0643\u064f\u0644\u0627"
    ],
    "name:fas_x_variant":[
        "\u0643\u0648\u0645\u0650\u0647 \u0643\u064e\u0644\u0627",
        "\u0643\u0648\u0645\u0647 \u0643\u0644\u0627",
        "K\u0101m\u012b Kol\u0101",
        "K\u016bmeh Kol\u0101"
    ],
    "name:und_x_variant":[
        "K\u016bmeh Kal\u0101"
    ],
    "wof:name":"Kumeh Kola",
    "wof:placetype":"locality"
},
  "geometry": {"coordinates":[52.54346,36.35972],"type":"Point"}
}