{
  "type": "Feature",
  "properties": {
    "gn:admin1_code":"3",
    "gn:asciiname":"Kondar",
    "gn:country_code":"IR",
    "gn:dem":1819,
    "gn:feature_class":"P",
    "gn:feature_code":"PPL",
    "gn:name":"Kondar",
    "gn:population":0,
    "gn:timezone":"Asia/Tehran",
    "iso:country":"IR",
    "name:fas_x_preferred":[
        "\u0643\u064f\u0646\u062f\u064f\u0631"
    ],
    "name:fas_x_variant":[
        "\u0641\u064e\u0644\u064e\u062a",
        "\u0643\u0646\u062f\u0631"
    ],
    "name:und_x_variant":[
        "Falat",
        "Kondor",
        "Kondar",
        "\u0643\u0646\u062f\u0631"
    ],
    "wof:name":"Kondar",
    "wof:placetype":"locality"
},
  "geometry": {"coordinates":[51.22796,31.32214],"type":"Point"}
}