{
  "type": "Feature",
  "properties": {
    "gn:admin1_code":"25.0",
    "gn:asciiname":"Hoseynabad-e Hajj `Alinaqi",
    "gn:country_code":"IR",
    "gn:dem":1099,
    "gn:feature_class":"P",
    "gn:feature_code":"PPL",
    "gn:name":"\u1e28oseyn\u0101b\u0101d-e \u1e28\u0101jj \u2018Al\u012bnaq\u012b",
    "gn:population":0,
    "gn:timezone":"Asia/Tehran",
    "iso:country":"IR",
    "name:fas_x_preferred":[
        "\u062d\u0633\u06cc\u0646 \u0622\u0628\u0627\u062f"
    ],
    "name:fas_x_variant":[
        "\u1e28oseyn\u0101b\u0101d-e \u1e28\u0101jj \u2018Al\u012b Naq\u012b",
        "\u1e28oseyn\u0101b\u0101d-e \u1e28\u0101j \u2018Al\u012b Naq\u012b",
        "Husain\u0101b\u0101d",
        "\u1e28oseyn\u0101b\u0101d",
        "\u062d\u0633\u06cc\u0646 \u0622\u0628\u0627\u062f \u062d\u0627\u062c \u0639\u0644\u06cc\u0646\u0642\u06cc",
        "\u062d\u0633\u06cc\u0646 \u0622\u0628\u0627\u062f \u062d\u0627\u062c\u06cc \u0639\u0644\u06cc \u0646\u0642\u06cc"
    ],
    "name:und_x_variant":[
        "\u1e28oseyn\u0101b\u0101d-e \u1e28\u0101jj \u2018Al\u012bnaq\u012b",
        "\u1e28oseyn\u0101b\u0101d-e \u1e28\u0101jj\u012b \u2018Al\u012b Naq\u012b"
    ],
    "wof:name":"Hoseynabad-e Hajj `Alinaqi",
    "wof:placetype":"locality"
},
  "geometry": {"coordinates":[54.4724,36.1945],"type":"Point"}
}