{
  "type": "Feature",
  "properties": {
    "gn:admin1_code":"4.0",
    "gn:asciiname":"Pol",
    "gn:country_code":"IR",
    "gn:dem":32,
    "gn:feature_class":"P",
    "gn:feature_code":"PPL",
    "gn:name":"Pol",
    "gn:population":0,
    "gn:timezone":"Asia/Tehran",
    "iso:country":"IR",
    "wof:name":"Pol",
    "wof:placetype":"locality"
},
  "geometry": {"coordinates":[61.07944000000001,25.58389],"type":"Point"}
}