{
  "type": "Feature",
  "properties": {
    "gn:admin1_code":"4.0",
    "gn:asciiname":"Pol",
    "gn:country_code":"IR",
    "gn:dem":32,
    "gn:feature_class":"P",
    "gn:feature_code":"PPL",
    "gn:name":"Pol",
    "gn:population":0,
    "gn:timezone":"Asia/Tehran",
    "iso:country":"IR",
    "name:bul_x_preferred":[
        "\u041f\u043e\u043b"
    ],
    "name:cat_x_preferred":[
        "Pol"
    ],
    "name:ceb_x_preferred":[
        "Pol"
    ],
    "name:ces_x_preferred":[
        "P\u00f3l"
    ],
    "name:dan_x_preferred":[
        "Pol"
    ],
    "name:deu_x_preferred":[
        "Pol"
    ],
    "name:fra_x_preferred":[
        "Pol"
    ],
    "name:glg_x_preferred":[
        "Pol"
    ],
    "name:hrv_x_preferred":[
        "Pol"
    ],
    "name:hun_x_preferred":[
        "Pol"
    ],
    "name:ltz_x_preferred":[
        "Pol"
    ],
    "name:nld_x_preferred":[
        "Pol"
    ],
    "name:nno_x_preferred":[
        "Pol"
    ],
    "name:nor_x_preferred":[
        "Pol"
    ],
    "name:pol_x_preferred":[
        "Pol"
    ],
    "name:ron_x_preferred":[
        "Pol"
    ],
    "name:rus_x_preferred":[
        "\u041f\u043e\u043b"
    ],
    "name:slk_x_preferred":[
        "P\u00f3l"
    ],
    "name:spa_x_preferred":[
        "Pol"
    ],
    "name:srp_x_preferred":[
        "\u041f\u043e\u043b"
    ],
    "name:swe_x_preferred":[
        "Pol"
    ],
    "name:tgk_x_preferred":[
        "\u04b6\u0438\u043d\u0441"
    ],
    "name:ukr_x_preferred":[
        "\u041f\u043e\u043b"
    ],
    "wof:name":"Pol",
    "wof:placetype":"locality"
},
  "geometry": {"coordinates":[61.07944000000001,25.58389],"type":"Point"}
}