{
  "type": "Feature",
  "properties": {
    "gn:admin1_code":"34.0",
    "gn:asciiname":"Anjirak",
    "gn:country_code":"IR",
    "gn:dem":1873,
    "gn:feature_class":"P",
    "gn:feature_code":"PPL",
    "gn:name":"Anj\u012brak",
    "gn:population":0,
    "gn:timezone":"Asia/Tehran",
    "iso:country":"IR",
    "name:fas_x_preferred":[
        "\u0627\u0646\u062c\u06cc\u0631\u06a9"
    ],
    "name:fas_x_variant":[
        "Anj\u012brak"
    ],
    "name:und_x_variant":[
        "Inj\u012blak"
    ],
    "wof:name":"Anjirak",
    "wof:placetype":"locality"
},
  "geometry": {"coordinates":[49.79957,34.01052],"type":"Point"}
}