{
  "type": "Feature",
  "properties": {
    "gn:admin1_code":"37",
    "gn:asciiname":"Arjanli",
    "gn:country_code":"IR",
    "gn:dem":526,
    "gn:feature_class":"P",
    "gn:feature_code":"PPL",
    "gn:name":"Arjanl\u012b",
    "gn:population":0,
    "gn:timezone":"Asia/Tehran",
    "iso:country":"IR",
    "name:ceb_x_preferred":[
        "Arjanl\u012b"
    ],
    "name:fas_x_preferred":[
        "Arjanl\u012b"
    ],
    "name:fas_x_variant":[
        "\u0627\u0631\u062c\u0646\u0644\u06cc"
    ],
    "name:msa_x_preferred":[
        "Arjanli"
    ],
    "name:swe_x_preferred":[
        "Arjanl\u012b"
    ],
    "wof:name":"Arjanli",
    "wof:placetype":"locality"
},
  "geometry": {"coordinates":[55.68912,37.4802],"type":"Point"}
}