{
  "type": "Feature",
  "properties": {
    "gn:admin1_code":"35.0",
    "gn:asciiname":"Aghuzki-ye Pa'in",
    "gn:country_code":"IR",
    "gn:dem":1731,
    "gn:feature_class":"P",
    "gn:feature_code":"PPL",
    "gn:name":"\u0100gh\u016bzk\u012b-ye P\u0101\u2019\u012bn",
    "gn:population":0,
    "gn:timezone":"Asia/Tehran",
    "iso:country":"IR",
    "name:fas_x_preferred":[
        "\u0100gh\u016bzk\u012b-ye P\u0101\u2019\u012bn"
    ],
    "name:fas_x_variant":[
        "\u0622\u063a\u0648\u0632\u0643\u06cc \u067e\u0627\u0626\u06cc\u0646"
    ],
    "wof:name":"Aghuzki-ye Pa'in",
    "wof:placetype":"locality"
},
  "geometry": {"coordinates":[50.58276,36.73738],"type":"Point"}
}