{
  "type": "Feature",
  "properties": {
    "gn:admin1_code":"32",
    "gn:asciiname":"In",
    "gn:country_code":"IR",
    "gn:dem":1537,
    "gn:feature_class":"P",
    "gn:feature_code":"PPL",
    "gn:name":"\u012an",
    "gn:population":0,
    "gn:timezone":"Asia/Tehran",
    "iso:country":"IR",
    "name:fas_x_preferred":[
        "\u064a\u0646"
    ],
    "name:fas_x_variant":[
        "\u012an"
    ],
    "wof:name":"In",
    "wof:placetype":"locality"
},
  "geometry": {"coordinates":[48.02694,38.82861],"type":"Point"}
}