{
  "type": "Feature",
  "properties": {
    "gn:admin1_code":"32.0",
    "gn:asciiname":"A`zamabad",
    "gn:country_code":"IR",
    "gn:dem":1361,
    "gn:feature_class":"P",
    "gn:feature_code":"PPL",
    "gn:name":"A\u2018z\u0327am\u0101b\u0101d",
    "gn:population":0,
    "gn:timezone":"Asia/Tehran",
    "iso:country":"IR",
    "name:fas_x_preferred":[
        "\u0627\u0639\u0638\u0645 \u0622\u0628\u0627\u062f"
    ],
    "name:fas_x_variant":[
        "A\u2018z\u0327am\u0101b\u0101d",
        "\u0639\u0638\u06cc\u0645 \u0622\u0628\u0627\u062f",
        "\u0639\u0638\u06cc\u0645\u200c\u0622\u0628\u0627\u062f"
    ],
    "name:msa_x_preferred":[
        "Azimabad"
    ],
    "name:und_x_variant":[
        "\u2018Az\u0327\u012bm\u0101b\u0101d"
    ],
    "wof:name":"A`zamabad",
    "wof:placetype":"locality"
},
  "geometry": {"coordinates":[48.17283,37.6149],"type":"Point"}
}