{
  "type": "Feature",
  "properties": {
    "gn:admin1_code":"33",
    "gn:asciiname":"Daghalian-e `Olya",
    "gn:country_code":"IR",
    "gn:dem":1817,
    "gn:feature_class":"P",
    "gn:feature_code":"PPL",
    "gn:name":"Daghal\u012b\u0101n-e \u2018Oly\u0101",
    "gn:population":0,
    "gn:timezone":"Asia/Tehran",
    "iso:country":"IR",
    "name:fas_x_preferred":[
        "\u062f\u063a\u0644\u06cc\u0627\u0646 \u0628\u0627\u0644\u0627"
    ],
    "name:fas_x_variant":[
        "Daghl\u012b\u0101n-e \u2018Oly\u0101",
        "Daghal\u012b\u0101n-e B\u0101l\u0101",
        "\u062f\u063a\u0644\u06cc\u0627\u0646 \u0639\u0644\u06cc\u0627"
    ],
    "name:und_x_variant":[
        "D\u0101ghl\u012b\u0101n-e \u2018Oly\u0101",
        "Daghliyan Olya",
        "Daghal\u012b\u0101n-e \u2018Oly\u0101"
    ],
    "wof:name":"Daghalian-e `Olya",
    "wof:placetype":"locality"
},
  "geometry": {"coordinates":[46.7878,38.4683],"type":"Point"}
}