{
  "type": "Feature",
  "properties": {
    "gn:admin1_code":"26",
    "gn:asciiname":"Kond-e `Olya",
    "gn:country_code":"IR",
    "gn:dem":2073,
    "gn:feature_class":"P",
    "gn:feature_code":"PPL",
    "gn:name":"Kond-e \u2018Oly\u0101",
    "gn:population":0,
    "gn:timezone":"Asia/Tehran",
    "iso:country":"IR",
    "name:fas_x_preferred":[
        "\u0643\u0646\u062f \u0628\u0627\u0644\u0627"
    ],
    "name:fas_x_variant":[
        "\u0643\u0646\u062f \u0639\u0644\u064a\u0627",
        "Kond-e B\u0101l\u0101",
        "\u06a9\u0646\u062f \u0628\u0627\u0644\u0627"
    ],
    "name:und_x_variant":[
        "Kand-e B\u0101l\u0101",
        "Kond \u2018Oly\u0101",
        "Kond-e \u2018Oly\u0101"
    ],
    "wof:name":"Kond-e `Olya",
    "wof:placetype":"locality"
},
  "geometry": {"coordinates":[51.6539,35.8731],"type":"Point"}
}