{
  "type": "Feature",
  "properties": {
    "gn:admin1_code":"11.0",
    "gn:asciiname":"Gurichi",
    "gn:country_code":"IR",
    "gn:dem":983,
    "gn:feature_class":"P",
    "gn:feature_code":"PPL",
    "gn:name":"G\u016br\u012bch\u012b",
    "gn:population":0,
    "gn:timezone":"Asia/Tehran",
    "iso:country":"IR",
    "name:ara_x_preferred":[
        "\u063a\u0648\u0631\u064a\u062a\u0634\u064a"
    ],
    "name:ceb_x_preferred":[
        "G\u016br\u012bch\u012b"
    ],
    "name:fas_x_preferred":[
        "\u06af\u0648\u0631\u064a\u0686\u06cc \u0628\u0627\u0644\u0627"
    ],
    "name:fas_x_variant":[
        "\u06af\u0648\u0631\u06cc\u0686\u06cc",
        "G\u016br\u012bch\u012b B\u0101l\u0101",
        "G\u016br\u012bch\u012b"
    ],
    "name:msa_x_preferred":[
        "Gurichi"
    ],
    "name:swe_x_preferred":[
        "G\u016br\u012bch\u012b"
    ],
    "wof:name":"Gurichi",
    "wof:placetype":"locality"
},
  "geometry": {"coordinates":[57.7514,26.4563],"type":"Point"}
}