{
  "type": "Feature",
  "properties": {
    "gn:admin1_code":"42",
    "gn:asciiname":"Elang",
    "gn:country_code":"IR",
    "gn:dem":1227,
    "gn:feature_class":"P",
    "gn:feature_code":"PPL",
    "gn:name":"Elang",
    "gn:population":0,
    "gn:timezone":"Asia/Tehran",
    "iso:country":"IR",
    "wof:name":"Elang",
    "wof:placetype":"locality"
},
  "geometry": {"coordinates":[59.63417,36.01556],"type":"Point"}
}