{
  "type": "Feature",
  "properties": {
    "gn:admin1_code":"23",
    "gn:asciiname":"Qamesh",
    "gn:cc2":"IR",
    "gn:country_code":"IR",
    "gn:dem":1797,
    "gn:feature_class":"P",
    "gn:feature_code":"PPL",
    "gn:name":"Qamesh",
    "gn:population":0,
    "gn:timezone":"Asia/Tehran",
    "iso:country":"IR",
    "name:fas_x_preferred":[
        "\u0642\u064e\u0645\u0650\u0634"
    ],
    "name:fas_x_variant":[
        "\u0642\u064e\u0645\u0634"
    ],
    "name:und_x_variant":[
        "Qamsh"
    ],
    "wof:name":"Qamesh",
    "wof:placetype":"locality"
},
  "geometry": {"coordinates":[47.79028,34.01056],"type":"Point"}
}