{
  "type": "Feature",
  "properties": {
    "gn:admin1_code":"16",
    "gn:asciiname":"Seyf-e Bala",
    "gn:country_code":"IR",
    "gn:dem":1517,
    "gn:feature_class":"P",
    "gn:feature_code":"PPL",
    "gn:name":"Seyf-e B\u0101l\u0101",
    "gn:population":0,
    "gn:timezone":"Asia/Tehran",
    "iso:country":"IR",
    "name:fas_x_preferred":[
        "\u0633\u064a\u0641 \u0639\u0644\u064a\u0627"
    ],
    "name:fas_x_variant":[
        "\u0633\u0650\u0641\u0650 \u0628\u0627\u0644\u0627",
        "\u0633\u06cc\u0641 \u0628\u0627\u0644\u0627",
        "Seyf-e \u2018Oly\u0101",
        "Seyf-e B\u0101l\u0101"
    ],
    "name:und_x_variant":[
        "Saif-i-Saru",
        "Sef-e B\u0101l\u0101"
    ],
    "wof:name":"Seyf-e Bala",
    "wof:placetype":"locality"
},
  "geometry": {"coordinates":[46.1781,35.5987],"type":"Point"}
}