{
  "type": "Feature",
  "properties": {
    "gn:admin1_code":"35.0",
    "gn:asciiname":"Dangasi",
    "gn:country_code":"IR",
    "gn:dem":1425,
    "gn:feature_class":"P",
    "gn:feature_code":"PPL",
    "gn:name":"Dang\u0101s\u012b",
    "gn:population":0,
    "gn:timezone":"Asia/Tehran",
    "iso:country":"IR",
    "name:fas_x_preferred":[
        "\u062f\u0646\u06af\u0627\u0633\u06cc"
    ],
    "name:und_x_variant":[
        "Dang\u0101s\u012b"
    ],
    "wof:name":"Dangasi",
    "wof:placetype":"locality"
},
  "geometry": {"coordinates":[51.5345,36.37186],"type":"Point"}
}