{
  "type": "Feature",
  "properties": {
    "gn:admin1_code":"29",
    "gn:asciiname":"Garang",
    "gn:cc2":"IR",
    "gn:country_code":"IR",
    "gn:dem":2272,
    "gn:feature_class":"P",
    "gn:feature_code":"PPL",
    "gn:name":"Garang",
    "gn:population":0,
    "gn:timezone":"Asia/Tehran",
    "iso:country":"IR",
    "name:fas_x_preferred":[
        "\u06af\u064e\u0631\u064e\u0646\u06af"
    ],
    "name:fas_x_variant":[
        "\u0686\u064e\u0631\u064e\u0646\u06af",
        "\u06af\u064e\u0631\u064e\u0646\u062c"
    ],
    "name:fra_x_preferred":[
        "Garang"
    ],
    "name:und_x_variant":[
        "Charang",
        "Garanj",
        "Oburang"
    ],
    "wof:name":"Garang",
    "wof:placetype":"locality"
},
  "geometry": {"coordinates":[56.81667,28.78333],"type":"Point"}
}