{
  "type": "Feature",
  "properties": {
    "gn:admin1_code":"37.0",
    "gn:asciiname":"Tumachlar",
    "gn:country_code":"IR",
    "gn:dem":-17,
    "gn:feature_class":"P",
    "gn:feature_code":"PPL",
    "gn:name":"T\u016bm\u0101chlar",
    "gn:population":0,
    "gn:timezone":"Asia/Tehran",
    "iso:country":"IR",
    "name:fas_x_preferred":[
        "T\u016bm\u0101chlar"
    ],
    "name:fas_x_variant":[
        "\u062a\u0648\u0645\u0627\u0686\u0644\u0631",
        "\u062a\u0648\u0645\u0627\u0686\u0644\u0631 \u0627\u0644\u062a\u064a\u0646",
        "\u062a\u0648\u0645\u0627\u0686\u0644\u0631\u0627\u0644\u062a\u06cc\u0646"
    ],
    "name:msa_x_preferred":[
        "Tumachlar-e Altin"
    ],
    "name:und_x_variant":[
        "T\u016bm\u0101ch\u0101r",
        "\u062a\u0648\u0645\u0627\u0686\u0644\u0631",
        "T\u016bm\u0101chlar ot T\u012bn"
    ],
    "wof:name":"Tumachlar",
    "wof:placetype":"locality"
},
  "geometry": {"coordinates":[54.30968000000001,37.09298],"type":"Point"}
}