{
  "type": "Feature",
  "properties": {
    "gn:admin1_code":"4.0",
    "gn:asciiname":"Deh-e Hoseyn Samani",
    "gn:cc2":"IR",
    "gn:country_code":"IR",
    "gn:dem":488,
    "gn:feature_class":"P",
    "gn:feature_code":"PPL",
    "gn:name":"Deh-e \u1e28oseyn S\u0101m\u0101n\u012b",
    "gn:population":0,
    "gn:timezone":"Asia/Tehran",
    "iso:country":"IR",
    "name:fas_x_preferred":[
        "Deh-e \u1e28oseyn S\u0101m\u0101n\u012b"
    ],
    "name:und_x_variant":[
        "Deh-e \u1e28oseyn"
    ],
    "wof:name":"Deh-e Hoseyn Samani",
    "wof:placetype":"locality"
},
  "geometry": {"coordinates":[61.63333000000001,30.88333],"type":"Point"}
}