{
  "type": "Feature",
  "properties": {
    "gn:admin1_code":"29.0",
    "gn:asciiname":"Bab Nedan",
    "gn:country_code":"IR",
    "gn:dem":2256,
    "gn:feature_class":"P",
    "gn:feature_code":"PPLF",
    "gn:name":"B\u0101b Ned\u0101n",
    "gn:population":0,
    "gn:timezone":"Asia/Tehran",
    "iso:country":"IR",
    "name:fas_x_preferred":[
        "B\u0101bend\u0101n"
    ],
    "name:fas_x_variant":[
        "B\u0101b Ned\u0101n",
        "\u0628\u0627\u0628 \u0646\u062f\u0627\u0646",
        "Darned\u016bn",
        "B\u0101band\u016bn"
    ],
    "wof:name":"Bab Nedan",
    "wof:placetype":"locality"
},
  "geometry": {"coordinates":[56.14664000000001,30.71161],"type":"Point"}
}