{
  "type": "Feature",
  "properties": {
    "gn:admin1_code":"43",
    "gn:asciiname":"Qalanlu",
    "gn:country_code":"IR",
    "gn:dem":1314,
    "gn:feature_class":"P",
    "gn:feature_code":"PPLF",
    "gn:name":"Qal\u0101nl\u016b",
    "gn:population":0,
    "gn:timezone":"Asia/Tehran",
    "iso:country":"IR",
    "name:fas_x_preferred":[
        "Qal\u0101nl\u016b"
    ],
    "name:fas_x_variant":[
        "\u0642\u0644\u0627\u0646\u0644\u0648",
        "\u0642\u0648\u0644\u0627\u0646\u0644\u0648"
    ],
    "name:und_x_variant":[
        "\u0642\u0644\u0627\u0646\u0644\u0648",
        "Q\u016bl\u0101nl\u016b"
    ],
    "wof:name":"Qalanlu",
    "wof:placetype":"locality"
},
  "geometry": {"coordinates":[56.30929,37.47384],"type":"Point"}
}