{
  "type": "Feature",
  "properties": {
    "gn:admin1_code":"4.0",
    "gn:asciiname":"Rahimabad",
    "gn:country_code":"IR",
    "gn:dem":1846,
    "gn:feature_class":"P",
    "gn:feature_code":"PPL",
    "gn:name":"Ra\u1e29\u012bm\u0101b\u0101d",
    "gn:population":0,
    "gn:timezone":"Asia/Tehran",
    "iso:country":"IR",
    "name:fas_x_preferred":[
        "Ra\u1e29\u012bm\u0101b\u0101d"
    ],
    "wof:name":"Rahimabad",
    "wof:placetype":"locality"
},
  "geometry": {"coordinates":[60.51667,29.43333],"type":"Point"}
}