{
  "type": "Feature",
  "properties": {
    "gn:admin1_code":"42.0",
    "gn:asciiname":"Arzancheh-ye `Olya",
    "gn:country_code":"IR",
    "gn:dem":797,
    "gn:feature_class":"P",
    "gn:feature_code":"PPL",
    "gn:name":"Arzancheh-ye \u2018Oly\u0101",
    "gn:population":0,
    "gn:timezone":"Asia/Tehran",
    "iso:country":"IR",
    "name:fas_x_preferred":[
        "\u0627\u0631\u0632\u0646\u0686\u0647 \u0639\u0644\u064a\u0627"
    ],
    "name:fas_x_variant":[
        "Arzanjeh-ye B\u0101l\u0101",
        "Arzancheh-ye \u2018Oly\u0101"
    ],
    "name:und_x_variant":[
        "Arzancheh-ye B\u0101l\u0101"
    ],
    "wof:name":"Arzancheh-ye `Olya",
    "wof:placetype":"locality"
},
  "geometry": {"coordinates":[60.8117,34.8444],"type":"Point"}
}