{
  "type": "Feature",
  "properties": {
    "gn:admin1_code":"7.0",
    "gn:asciiname":"Arudan",
    "gn:country_code":"IR",
    "gn:dem":444,
    "gn:feature_class":"P",
    "gn:feature_code":"PPL",
    "gn:name":"Ar\u016bd\u0101n",
    "gn:population":0,
    "gn:timezone":"Asia/Tehran",
    "iso:country":"IR",
    "name:fas_x_preferred":[
        "\u0627\u0631\u0648\u062f\u0627\u0646"
    ],
    "name:fas_x_variant":[
        "Ar\u016bd\u0101n-e B\u0101l\u0101",
        "Ar\u016bd\u0101n-e P\u0101\u2019\u012bn",
        "Ar\u016bd\u0101n P\u0101\u2019\u012bn",
        "Ar\u016bd\u0101n"
    ],
    "name:und_x_variant":[
        "Aroodan",
        "Arud\u016bn"
    ],
    "wof:name":"Arudan",
    "wof:placetype":"locality"
},
  "geometry": {"coordinates":[52.799,27.5859],"type":"Point"}
}