{
  "type": "Feature",
  "properties": {
    "gn:admin1_code":"28",
    "gn:asciiname":"Tok Lor",
    "gn:country_code":"IR",
    "gn:dem":2244,
    "gn:feature_class":"P",
    "gn:feature_code":"PPL",
    "gn:name":"Tok Lor",
    "gn:population":0,
    "gn:timezone":"Asia/Tehran",
    "iso:country":"IR",
    "name:fas_x_preferred":[
        "\u062a\u06a9\u0644\u0631 \u06a9\u0644\u0647\u0631\u0648\u062f"
    ],
    "name:fas_x_variant":[
        "Tok Lor Kolahr\u016bd",
        "Toklor Kalahr\u016bd",
        "\u062a\u06a9 \u0644\u0631"
    ],
    "wof:name":"Tok Lor",
    "wof:placetype":"locality"
},
  "geometry": {"coordinates":[51.5612,33.3599],"type":"Point"}
}