{
  "type": "Feature",
  "properties": {
    "gn:admin1_code":"8",
    "gn:asciiname":"Anush Mahalleh",
    "gn:country_code":"IR",
    "gn:dem":21,
    "gn:feature_class":"P",
    "gn:feature_code":"PPLL",
    "gn:name":"An\u016bsh Ma\u1e29alleh",
    "gn:population":0,
    "gn:timezone":"Asia/Tehran",
    "iso:country":"IR",
    "name:ceb_x_preferred":[
        "An\u016bsh Ma\u1e29alleh-ye Avval"
    ],
    "name:fas_x_preferred":[
        "\u0627\u0646\u0648\u0634 \u0645\u062d\u0644\u0647 \u062f\u0648\u0645"
    ],
    "name:fas_x_variant":[
        "An\u016bsh Ma\u1e29alleh-ye Dowvom",
        "\u0627\u0646\u0648\u0634 \u0645\u062d\u0644\u0647",
        "\u0627\u0646\u0648\u0634\u200c\u0645\u062d\u0644\u0647"
    ],
    "name:msa_x_preferred":[
        "Anush Mahalleh"
    ],
    "name:swe_x_preferred":[
        "An\u016bsh Ma\u1e29alleh-ye Avval"
    ],
    "name:ukr_x_preferred":[
        "\u0410\u043d\u0443\u0448-\u041c\u0430\u0445\u0430\u043b\u0435"
    ],
    "name:und_x_variant":[
        "An\u016bsh Ma\u1e29alleh"
    ],
    "wof:name":"Anush Mahalleh",
    "wof:placetype":"locality"
},
  "geometry": {"coordinates":[48.89543,37.88817],"type":"Point"}
}