{
  "type": "Feature",
  "properties": {
    "gn:admin1_code":"42.0",
    "gn:asciiname":"Asadabad",
    "gn:country_code":"IR",
    "gn:dem":1714,
    "gn:feature_class":"P",
    "gn:feature_code":"PPL",
    "gn:name":"Asad\u0101b\u0101d",
    "gn:population":0,
    "gn:timezone":"Asia/Tehran",
    "iso:country":"IR",
    "name:fas_x_preferred":[
        "\u0627\u0633\u062f \u0622\u0628\u0627\u062f"
    ],
    "name:fas_x_variant":[
        "Asad\u0101b\u0101d"
    ],
    "name:und_x_variant":[
        "Qal\u2019eh Sh\u0101hz\u0101deh"
    ],
    "wof:name":"Asadabad",
    "wof:placetype":"locality"
},
  "geometry": {"coordinates":[59.35893000000001,35.63158],"type":"Point"}
}