{
  "type": "Feature",
  "properties": {
    "gn:admin1_code":"13",
    "gn:asciiname":"Darneh",
    "gn:country_code":"IR",
    "gn:dem":1057,
    "gn:feature_class":"P",
    "gn:feature_code":"PPL",
    "gn:name":"Darneh",
    "gn:population":0,
    "gn:timezone":"Asia/Tehran",
    "iso:country":"IR",
    "name:fas_x_preferred":[
        "\u062f\u0631\u0646\u0647"
    ],
    "wof:name":"Darneh",
    "wof:placetype":"locality"
},
  "geometry": {"coordinates":[46.1694,34.7901],"type":"Point"}
}