{
  "type": "Feature",
  "properties": {
    "gn:admin1_code":"4.0",
    "gn:asciiname":"Mendar",
    "gn:country_code":"IR",
    "gn:dem":1253,
    "gn:feature_class":"P",
    "gn:feature_code":"PPL",
    "gn:name":"Mendar",
    "gn:population":0,
    "gn:timezone":"Asia/Tehran",
    "iso:country":"IR",
    "name:fas_x_preferred":[
        "\u0645\u0646\u062f\u0631"
    ],
    "name:und_x_variant":[
        "Mandar",
        "Maindar",
        "Mendar"
    ],
    "wof:name":"Mendar",
    "wof:placetype":"locality"
},
  "geometry": {"coordinates":[62.6268,26.8326],"type":"Point"}
}