{
  "type": "Feature",
  "properties": {
    "gn:admin1_code":"37",
    "gn:asciiname":"Malech Aram",
    "gn:country_code":"IR",
    "gn:dem":1427,
    "gn:feature_class":"P",
    "gn:feature_code":"PPL",
    "gn:name":"Malech \u0100r\u0101m",
    "gn:population":0,
    "gn:timezone":"Asia/Tehran",
    "iso:country":"IR",
    "name:fas_x_preferred":[
        "\u0645\u0644\u0686 \u0622\u0631\u0627\u0645"
    ],
    "name:fas_x_variant":[
        "\u0645\u064e\u0644\u0650\u0686 \u0627\u064e\u0631\u0627\u0646",
        "Malech \u0100r\u0101m"
    ],
    "name:und_x_variant":[
        "Malech Ar\u0101n"
    ],
    "wof:name":"Malech Aram",
    "wof:placetype":"locality"
},
  "geometry": {"coordinates":[55.2322,36.85938],"type":"Point"}
}