{
  "type": "Feature",
  "properties": {
    "gn:admin1_code":"42",
    "gn:asciiname":"Khowsh-e Bala",
    "gn:country_code":"IR",
    "gn:dem":1221,
    "gn:feature_class":"P",
    "gn:feature_code":"PPL",
    "gn:name":"Khowsh-e B\u0101l\u0101",
    "gn:population":0,
    "gn:timezone":"Asia/Tehran",
    "iso:country":"IR",
    "name:ceb_x_preferred":[
        "Khvosh-e B\u0101l\u0101"
    ],
    "name:fas_x_preferred":[
        "\u062e\u0648\u0634 \u0628\u0627\u0644\u0627"
    ],
    "name:fas_x_variant":[
        "Khowsh-e B\u0101l\u0101",
        "Khvosh-e B\u0101l\u0101"
    ],
    "name:swe_x_preferred":[
        "Khvosh-e B\u0101l\u0101"
    ],
    "wof:name":"Khowsh-e Bala",
    "wof:placetype":"locality"
},
  "geometry": {"coordinates":[58.85657,36.18982000000001],"type":"Point"}
}