{
  "type": "Feature",
  "properties": {
    "gn:admin1_code":"23",
    "gn:asciiname":"Abgarmak-e `Olya",
    "gn:country_code":"IR",
    "gn:dem":2027,
    "gn:feature_class":"P",
    "gn:feature_code":"PPL",
    "gn:name":"\u0100bgarmak-e \u2018Oly\u0101",
    "gn:population":0,
    "gn:timezone":"Asia/Tehran",
    "iso:country":"IR",
    "name:fas_x_preferred":[
        "\u0622\u0628 \u06af\u064e\u0631\u0645\u0650\u06c0 \u0628\u064e\u0631 \u0622\u0641\u062a\u0627\u0628"
    ],
    "name:fas_x_variant":[
        "\u0100b Garmeh-ye Bar \u0100ft\u0101b",
        "\u0100bgarmak-e B\u0101l\u0101",
        "\u0622\u0628\u06af\u0631\u0645\u06a9 \u0628\u0627\u0644\u0627",
        "\u0622\u0628\u06af\u0631\u0645\u06a9 \u0639\u0644\u06cc\u0627"
    ],
    "name:und_x_variant":[
        "\u0100bgarmak-e \u2018Oly\u0101"
    ],
    "wof:name":"Abgarmak-e `Olya",
    "wof:placetype":"locality"
},
  "geometry": {"coordinates":[49.69758,33.09831],"type":"Point"}
}