{
  "type": "Feature",
  "properties": {
    "gn:admin1_code":"13",
    "gn:asciiname":"Shahrak-e Banmazaran",
    "gn:country_code":"IR",
    "gn:dem":928,
    "gn:feature_class":"P",
    "gn:feature_code":"PPL",
    "gn:name":"Shahrak-e B\u0101nmaz\u0101r\u0101n",
    "gn:population":0,
    "gn:timezone":"Asia/Tehran",
    "iso:country":"IR",
    "name:fas_x_preferred":[
        "\u0634\u0647\u0631\u06a9 \u0628\u0627\u0646\u0645\u0632\u0627\u0631\u0627\u0646"
    ],
    "name:fas_x_variant":[
        "Shahrak-e B\u0101nmaz\u0101r\u0101n"
    ],
    "wof:name":"Shahrak-e Banmazaran",
    "wof:placetype":"locality"
},
  "geometry": {"coordinates":[45.98073,34.47019],"type":"Point"}
}