{
  "type": "Feature",
  "properties": {
    "gn:admin1_code":"34",
    "gn:asciiname":"Zanjiran",
    "gn:country_code":"IR",
    "gn:dem":1988,
    "gn:feature_class":"P",
    "gn:feature_code":"PPL",
    "gn:name":"Zanj\u012br\u0101n",
    "gn:population":0,
    "gn:timezone":"Asia/Tehran",
    "iso:country":"IR",
    "name:ceb_x_preferred":[
        "Zanj\u012br\u0101n"
    ],
    "name:fas_x_preferred":[
        "\u0632\u0646\u062c\u064a\u0631\u0627\u0646"
    ],
    "name:fas_x_variant":[
        "Zanj\u012br\u0101n",
        "\u0632\u0646\u062c\u06cc\u0631\u0627\u0646"
    ],
    "name:swe_x_preferred":[
        "Zanj\u012br\u0101n"
    ],
    "name:ukr_x_preferred":[
        "\u0417\u0430\u043d\u0434\u0436\u0456\u0440\u0430\u043d"
    ],
    "wof:name":"Zanjiran",
    "wof:placetype":"locality"
},
  "geometry": {"coordinates":[49.47832,34.66815],"type":"Point"}
}