{
  "type": "Feature",
  "properties": {
    "gn:admin1_code":"29",
    "gn:asciiname":"Zamanabad",
    "gn:country_code":"IR",
    "gn:dem":671,
    "gn:feature_class":"P",
    "gn:feature_code":"PPL",
    "gn:name":"Zam\u0101n\u0101b\u0101d",
    "gn:population":0,
    "gn:timezone":"Asia/Tehran",
    "iso:country":"IR",
    "name:fas_x_preferred":[
        "\u0632\u0645\u0627\u0646 \u0622\u0628\u0627\u062f"
    ],
    "name:fas_x_variant":[
        "Zam\u0101n\u0101b\u0101d",
        "\u0632\u0645\u0627\u0646\u200c\u0622\u0628\u0627\u062f"
    ],
    "wof:name":"Zamanabad",
    "wof:placetype":"locality"
},
  "geometry": {"coordinates":[58.8949,28.8591],"type":"Point"}
}