{
  "type": "Feature",
  "properties": {
    "gn:admin1_code":"3",
    "gn:asciiname":"Saman",
    "gn:country_code":"IR",
    "gn:dem":1967,
    "gn:feature_class":"P",
    "gn:feature_code":"PPL",
    "gn:name":"S\u0101m\u0101n",
    "gn:population":0,
    "gn:timezone":"Asia/Tehran",
    "iso:country":"IR",
    "name:fas_x_preferred":[
        "S\u0101m\u0101n"
    ],
    "name:fas_x_variant":[
        "\u0633\u0627\u0645\u0627\u0646"
    ],
    "name:und_x_variant":[
        "\u0633\u0627\u0645\u0627\u0646"
    ],
    "wof:name":"Saman",
    "wof:placetype":"locality"
},
  "geometry": {"coordinates":[50.91102,32.4515],"type":"Point"}
}