{
  "type": "Feature",
  "properties": {
    "gn:admin1_code":"35.0",
    "gn:asciiname":"Kones-e Marz",
    "gn:country_code":"IR",
    "gn:dem":-1,
    "gn:feature_class":"P",
    "gn:feature_code":"PPL",
    "gn:name":"Kones-e Marz",
    "gn:population":0,
    "gn:timezone":"Asia/Tehran",
    "iso:country":"IR",
    "name:ceb_x_preferred":[
        "Kones-e Marz"
    ],
    "name:fas_x_preferred":[
        "\u0643\u0646\u0633 \u0645\u0631\u0632"
    ],
    "name:fas_x_variant":[
        "\u06a9\u0646\u0633\u200c\u0645\u0631\u0632"
    ],
    "name:swe_x_preferred":[
        "Kones-e Marz"
    ],
    "wof:name":"Kones-e Marz",
    "wof:placetype":"locality"
},
  "geometry": {"coordinates":[52.40191,36.57809],"type":"Point"}
}