{
  "type": "Feature",
  "properties": {
    "gn:admin1_code":"32",
    "gn:asciiname":"Qeshlaq-e Seyyedlar-e Musa",
    "gn:country_code":"IR",
    "gn:dem":798,
    "gn:feature_class":"P",
    "gn:feature_code":"PPL",
    "gn:name":"Qeshl\u0101q-e Seyyedlar-e M\u016bs\u00e1",
    "gn:population":0,
    "gn:timezone":"Asia/Tehran",
    "iso:country":"IR",
    "name:ara_x_preferred":[
        "\u0642\u0634\u0644\u0627\u0642 \u0633\u064a\u062f\u0644\u0631 \u0645\u0648\u0633\u064a"
    ],
    "name:fas_x_preferred":[
        "\u0642\u0650\u0634\u0644\u0627\u0642\u0650 \u0633\u0650\u064a\u0650\u0651\u062f\u0644\u064e\u0631\u0650 \u0645\u0648\u0633\u064e\u0649"
    ],
    "name:fas_x_variant":[
        "Qeshl\u0101q-e Seyyedlar-e M\u016bs\u00e1",
        "\u0642\u0634\u0644\u0627\u0642 \u0633\u06cc\u062f\u0644\u0631 \u0645\u0648\u0633\u06cc"
    ],
    "name:msa_x_preferred":[
        "Qeshlaq-e Seyyedlar-e Musa"
    ],
    "wof:name":"Qeshlaq-e Seyyedlar-e Musa",
    "wof:placetype":"locality"
},
  "geometry": {"coordinates":[47.71667,39.21667],"type":"Point"}
}