{
  "type": "Feature",
  "properties": {
    "gn:admin1_code":"42",
    "gn:asciiname":"Daraabad",
    "gn:country_code":"IR",
    "gn:dem":1678,
    "gn:feature_class":"P",
    "gn:feature_code":"PPL",
    "gn:name":"D\u0101r\u0101\u0101b\u0101d",
    "gn:population":0,
    "gn:timezone":"Asia/Tehran",
    "iso:country":"IR",
    "name:fas_x_preferred":[
        "D\u0101r\u0101\u0101b\u0101d"
    ],
    "wof:name":"Daraabad",
    "wof:placetype":"locality"
},
  "geometry": {"coordinates":[59.34917,35.5925],"type":"Point"}
}