{
  "type": "Feature",
  "properties": {
    "gn:admin1_code":"35.0",
    "gn:asciiname":"Palbandan",
    "gn:country_code":"IR",
    "gn:dem":12,
    "gn:feature_class":"P",
    "gn:feature_code":"PPL",
    "gn:name":"P\u0101lband\u0101n",
    "gn:population":0,
    "gn:timezone":"Asia/Tehran",
    "iso:country":"IR",
    "name:fas_x_preferred":[
        "P\u0101lband\u0101n"
    ],
    "name:fas_x_variant":[
        "\u067e\u0627\u0644\u0628\u0646\u062f\u0627\u0646",
        "\u06cc\u0627\u0644\u0628\u0646\u062f\u0627\u0646"
    ],
    "name:und_x_variant":[
        "\u067e\u0627\u0644\u0628\u0646\u062f\u0627\u0646",
        "Y\u0101lband\u0101n"
    ],
    "wof:name":"Palbandan",
    "wof:placetype":"locality"
},
  "geometry": {"coordinates":[51.27472,36.66983],"type":"Point"}
}