{
  "type": "Feature",
  "properties": {
    "gn:admin1_code":"29",
    "gn:asciiname":"Sar Ra's",
    "gn:country_code":"IR",
    "gn:dem":355,
    "gn:feature_class":"P",
    "gn:feature_code":"PPL",
    "gn:name":"Sar R\u0101\u2019s",
    "gn:population":0,
    "gn:timezone":"Asia/Tehran",
    "iso:country":"IR",
    "name:fas_x_preferred":[
        "\u0633\u0631 \u0631\u0627\u0626\u0633"
    ],
    "name:fas_x_variant":[
        "Sar R\u0101\u2019s"
    ],
    "name:und_x_variant":[
        "S\u0101r\u0101s"
    ],
    "wof:name":"Sar Ra's",
    "wof:placetype":"locality"
},
  "geometry": {"coordinates":[57.5377,27.4877],"type":"Point"}
}