{
  "type": "Feature",
  "properties": {
    "gn:admin1_code":"9",
    "gn:asciiname":"Gonbaleh",
    "gn:country_code":"IR",
    "gn:dem":1564,
    "gn:feature_class":"P",
    "gn:feature_code":"PPL",
    "gn:name":"Gonbaleh",
    "gn:population":0,
    "gn:timezone":"Asia/Tehran",
    "iso:country":"IR",
    "name:ara_x_preferred":[
        "\u063a\u0646\u0628\u0644\u0629"
    ],
    "name:fas_x_preferred":[
        "\u06af\u0646\u0628\u0644\u0647"
    ],
    "name:msa_x_preferred":[
        "Gonbaleh"
    ],
    "name:und_x_variant":[
        "Gombaleh",
        "G\u016bn Baleh",
        "Gum\u0101la"
    ],
    "wof:name":"Gonbaleh",
    "wof:placetype":"locality"
},
  "geometry": {"coordinates":[47.9727,34.61510999999999],"type":"Point"}
}