{
  "type": "Feature",
  "properties": {
    "gn:admin1_code":"10",
    "gn:asciiname":"Haft Kadeh",
    "gn:country_code":"IR",
    "gn:dem":817,
    "gn:feature_class":"P",
    "gn:feature_code":"PPL",
    "gn:name":"Haft Kadeh",
    "gn:population":0,
    "gn:timezone":"Asia/Tehran",
    "iso:country":"IR",
    "name:fas_x_preferred":[
        "\u0647\u0641\u062a \u06a9\u062f\u0647"
    ],
    "wof:name":"Haft Kadeh",
    "wof:placetype":"locality"
},
  "geometry": {"coordinates":[46.9028,33.0635],"type":"Point"}
}