{
  "type": "Feature",
  "properties": {
    "gn:admin1_code":"5",
    "gn:asciiname":"Gav Daneh",
    "gn:country_code":"IR",
    "gn:dem":1457,
    "gn:feature_class":"P",
    "gn:feature_code":"PPL",
    "gn:name":"G\u0101v D\u0101neh",
    "gn:population":0,
    "gn:timezone":"Asia/Tehran",
    "iso:country":"IR",
    "name:fas_x_preferred":[
        "G\u0101v D\u0101neh"
    ],
    "wof:name":"Gav Daneh",
    "wof:placetype":"locality"
},
  "geometry": {"coordinates":[50.8325,31.00111],"type":"Point"}
}