{
  "type": "Feature",
  "properties": {
    "gn:admin1_code":"35.0",
    "gn:asciiname":"Fulad Kola",
    "gn:country_code":"IR",
    "gn:dem":144,
    "gn:feature_class":"P",
    "gn:feature_code":"PPL",
    "gn:name":"F\u016bl\u0101d Kol\u0101",
    "gn:population":0,
    "gn:timezone":"Asia/Tehran",
    "iso:country":"IR",
    "name:fas_x_preferred":[
        "\u0641\u0648\u0644\u0627\u062f \u06a9\u0644\u0627"
    ],
    "name:fas_x_variant":[
        "F\u016bl\u0101d Kol\u0101",
        "P\u016bl\u0101d Kol\u0101",
        "\u067e\u0648\u0644\u0627\u062f \u0643\u0644\u0627",
        "\u0641\u0648\u0644\u0627\u062f\u06a9\u0644\u0627"
    ],
    "wof:name":"Fulad Kola",
    "wof:placetype":"locality"
},
  "geometry": {"coordinates":[52.24983,36.41697],"type":"Point"}
}