{
  "type": "Feature",
  "properties": {
    "gn:admin1_code":"1",
    "gn:asciiname":"Kord Kandi",
    "gn:country_code":"IR",
    "gn:dem":1282,
    "gn:feature_class":"P",
    "gn:feature_code":"PPL",
    "gn:name":"Kord Kand\u012b",
    "gn:population":0,
    "gn:timezone":"Asia/Tehran",
    "iso:country":"IR",
    "name:fas_x_preferred":[
        "\u06a9\u0631\u062f\u06a9\u0646\u062f\u06cc"
    ],
    "name:fas_x_variant":[
        "\u0643\u064f\u0631\u062f \u0643\u064e\u0646\u062f\u06cc",
        "Kord Kand\u012b"
    ],
    "wof:name":"Kord Kandi",
    "wof:placetype":"locality"
},
  "geometry": {"coordinates":[45.9449,37.0802],"type":"Point"}
}