{
  "type": "Feature",
  "properties": {
    "gn:admin1_code":"13",
    "gn:asciiname":"Deh Sorkh",
    "gn:country_code":"IR",
    "gn:dem":1373,
    "gn:feature_class":"P",
    "gn:feature_code":"PPL",
    "gn:name":"Deh Sorkh",
    "gn:population":0,
    "gn:timezone":"Asia/Tehran",
    "iso:country":"IR",
    "name:fas_x_preferred":[
        "\u062f\u0647 \u0633\u0631\u062e"
    ],
    "wof:name":"Deh Sorkh",
    "wof:placetype":"locality"
},
  "geometry": {"coordinates":[46.4118,34.8386],"type":"Point"}
}