{
  "type": "Feature",
  "properties": {
    "gn:admin1_code":"7.0",
    "gn:asciiname":"Deh Pa'in",
    "gn:country_code":"IR",
    "gn:dem":1172,
    "gn:feature_class":"P",
    "gn:feature_code":"PPL",
    "gn:name":"Deh Pa\u2019in",
    "gn:population":0,
    "gn:timezone":"Asia/Tehran",
    "iso:country":"IR",
    "name:fas_x_preferred":[
        "Deh Pa\u2019in"
    ],
    "wof:name":"Deh Pa'in",
    "wof:placetype":"locality"
},
  "geometry": {"coordinates":[53.0675,28.74028],"type":"Point"}
}