{
  "type": "Feature",
  "properties": {
    "gn:admin1_code":"1",
    "gn:asciiname":"Razangeh",
    "gn:country_code":"IR",
    "gn:dem":1598,
    "gn:feature_class":"P",
    "gn:feature_code":"PPL",
    "gn:name":"Razangeh",
    "gn:population":0,
    "gn:timezone":"Asia/Tehran",
    "iso:country":"IR",
    "name:fas_x_preferred":[
        "\u0631\u064e\u0632\u06af\u0650\u0647"
    ],
    "name:fas_x_variant":[
        "\u0631\u0632\u0646\u06af\u0647"
    ],
    "name:und_x_variant":[
        "Razgeh",
        "Razangeh"
    ],
    "wof:name":"Razangeh",
    "wof:placetype":"locality"
},
  "geometry": {"coordinates":[44.8855,37.3322],"type":"Point"}
}