{
  "type": "Feature",
  "properties": {
    "gn:admin1_code":"42",
    "gn:asciiname":"Jalali",
    "gn:country_code":"IR",
    "gn:dem":1105,
    "gn:feature_class":"P",
    "gn:feature_code":"PPL",
    "gn:name":"Jal\u0101l\u012b",
    "gn:population":0,
    "gn:timezone":"Asia/Tehran",
    "iso:country":"IR",
    "name:fas_x_preferred":[
        "\u062c\u0644\u0627\u0644\u06cc"
    ],
    "name:fas_x_variant":[
        "Jal\u0101l\u012b"
    ],
    "name:urd_x_preferred":[
        "\u062c\u0644\u0627\u0644\u06cc"
    ],
    "wof:name":"Jalali",
    "wof:placetype":"locality"
},
  "geometry": {"coordinates":[59.32385,36.55058],"type":"Point"}
}