{
  "type": "Feature",
  "properties": {
    "gn:admin1_code":"40",
    "gn:asciiname":"Torkanabad",
    "gn:country_code":"IR",
    "gn:dem":2371,
    "gn:feature_class":"P",
    "gn:feature_code":"PPLF",
    "gn:name":"Tork\u0101n\u0101b\u0101d",
    "gn:population":0,
    "gn:timezone":"Asia/Tehran",
    "iso:country":"IR",
    "name:fas_x_preferred":[
        "Tark\u0101n\u0101b\u0101d"
    ],
    "name:fas_x_variant":[
        "Tork\u0101n\u0101b\u0101d",
        "\u062a\u0631\u06a9\u0627\u0646 \u0622\u0628\u0627\u062f"
    ],
    "wof:name":"Torkanabad",
    "wof:placetype":"locality"
},
  "geometry": {"coordinates":[54.11767,31.46135],"type":"Point"}
}