{
  "type": "Feature",
  "properties": {
    "gn:admin1_code":"15",
    "gn:asciiname":"Qanbari",
    "gn:country_code":"IR",
    "gn:dem":315,
    "gn:feature_class":"P",
    "gn:feature_code":"PPL",
    "gn:name":"Qanbar\u012b",
    "gn:population":0,
    "gn:timezone":"Asia/Tehran",
    "iso:country":"IR",
    "name:fas_x_preferred":[
        "\u0642\u0646\u0628\u0631\u06cc"
    ],
    "name:fas_x_variant":[
        "Qanbar\u012b"
    ],
    "wof:name":"Qanbari",
    "wof:placetype":"locality"
},
  "geometry": {"coordinates":[50.191,30.7188],"type":"Point"}
}