{
  "type": "Feature",
  "properties": {
    "gn:admin1_code":"29",
    "gn:asciiname":"Qal`eh Hajj Maleki",
    "gn:country_code":"IR",
    "gn:dem":1474,
    "gn:feature_class":"P",
    "gn:feature_code":"PPL",
    "gn:name":"Qal\u2018eh \u1e28\u0101jj Malek\u012b",
    "gn:population":0,
    "gn:timezone":"Asia/Tehran",
    "iso:country":"IR",
    "name:fas_x_preferred":[
        "\u0642\u0644\u0639\u0647 \u062d\u0627\u062c \u0645\u0644\u06a9\u06cc"
    ],
    "name:fas_x_variant":[
        "Qal\u2018eh \u1e28\u0101jj Malek\u012b"
    ],
    "wof:name":"Qal`eh Hajj Maleki",
    "wof:placetype":"locality"
},
  "geometry": {"coordinates":[55.858,30.4194],"type":"Point"}
}