{
  "type": "Feature",
  "properties": {
    "gn:admin1_code":"42.0",
    "gn:asciiname":"Bereyli",
    "gn:country_code":"IR",
    "gn:dem":1150,
    "gn:feature_class":"P",
    "gn:feature_code":"PPL",
    "gn:name":"Bereyl\u012b",
    "gn:population":0,
    "gn:timezone":"Asia/Tehran",
    "iso:country":"IR",
    "name:fas_x_preferred":[
        "Bereyl\u012b"
    ],
    "name:fas_x_variant":[
        "\u0628\u0631\u06cc\u0644\u06cc"
    ],
    "wof:name":"Bereyli",
    "wof:placetype":"locality"
},
  "geometry": {"coordinates":[60.5681,35.82058],"type":"Point"}
}