{
  "type": "Feature",
  "properties": {
    "gn:admin1_code":"43",
    "gn:asciiname":"Borzolabad",
    "gn:country_code":"IR",
    "gn:dem":1134,
    "gn:feature_class":"P",
    "gn:feature_code":"PPL",
    "gn:name":"Borzol\u0101b\u0101d",
    "gn:population":0,
    "gn:timezone":"Asia/Tehran",
    "iso:country":"IR",
    "name:fas_x_preferred":[
        "Borzol\u0101b\u0101d"
    ],
    "name:fas_x_variant":[
        "\u0628\u0631\u0632\u0644 \u0622\u0628\u0627\u062f"
    ],
    "name:und_x_variant":[
        "Borz\u012bl\u0101b\u0101d",
        "Burzil\u0101b\u0101d"
    ],
    "wof:name":"Borzolabad",
    "wof:placetype":"locality"
},
  "geometry": {"coordinates":[58.12419000000001,37.32294],"type":"Point"}
}