{
  "type": "Feature",
  "properties": {
    "gn:admin1_code":"8",
    "gn:asciiname":"Vaqfi",
    "gn:country_code":"IR",
    "gn:dem":552,
    "gn:feature_class":"P",
    "gn:feature_code":"PPL",
    "gn:name":"Vaqf\u012b",
    "gn:population":0,
    "gn:timezone":"Asia/Tehran",
    "iso:country":"IR",
    "name:fas_x_preferred":[
        "Vaqf\u012b"
    ],
    "name:fas_x_variant":[
        "\u0648\u0642\u0641\u06cc"
    ],
    "wof:name":"Vaqfi",
    "wof:placetype":"locality"
},
  "geometry": {"coordinates":[49.11287,37.16011],"type":"Point"}
}