{
  "type": "Feature",
  "properties": {
    "gn:admin1_code":"4.0",
    "gn:asciiname":"Sorkh Gazi",
    "gn:country_code":"IR",
    "gn:dem":648,
    "gn:feature_class":"P",
    "gn:feature_code":"PPLL",
    "gn:name":"Sorkh Gaz\u012b",
    "gn:population":0,
    "gn:timezone":"Asia/Tehran",
    "iso:country":"IR",
    "name:fas_x_preferred":[
        "\u0633\u0631\u062e \u06af\u0632\u06cc"
    ],
    "name:fas_x_variant":[
        "\u0633\u0631\u062e \u06af\u0632\u06cc \u0686\u0627\u0647 \u06af\u0632\u06cc"
    ],
    "name:und_x_variant":[
        "Sorkh Gaz\u012b",
        "Sorkh Gaz\u012b-ye Ch\u0101h-e Gaz\u012b"
    ],
    "wof:name":"Sorkh Gazi",
    "wof:placetype":"locality"
},
  "geometry": {"coordinates":[59.73051,26.86244000000001],"type":"Point"}
}