{
  "type": "Feature",
  "properties": {
    "gn:admin1_code":"16",
    "gn:asciiname":"Nimeh Kar",
    "gn:country_code":"IR",
    "gn:dem":1490,
    "gn:feature_class":"P",
    "gn:feature_code":"PPL",
    "gn:name":"N\u012bmeh K\u0101r",
    "gn:population":0,
    "gn:timezone":"Asia/Tehran",
    "iso:country":"IR",
    "name:fas_x_preferred":[
        "\u0646\u064a\u0645\u0647 \u0643\u0627\u0631\u0647"
    ],
    "name:fas_x_variant":[
        "N\u012bmeh K\u0101r",
        "N\u012bmeh K\u0101reh",
        "\u0646\u06cc\u0645\u0647 \u06a9\u0627\u0631"
    ],
    "name:und_x_variant":[
        "N\u012bmahk\u0101r"
    ],
    "wof:name":"Nimeh Kar",
    "wof:placetype":"locality"
},
  "geometry": {"coordinates":[47.92459,36.285],"type":"Point"}
}