{
  "type": "Feature",
  "properties": {
    "gn:admin1_code":"8",
    "gn:asciiname":"Liastan",
    "gn:country_code":"IR",
    "gn:dem":23,
    "gn:feature_class":"P",
    "gn:feature_code":"PPL",
    "gn:name":"L\u012b\u0101st\u0101n",
    "gn:population":0,
    "gn:timezone":"Asia/Tehran",
    "iso:country":"IR",
    "name:fas_x_preferred":[
        "L\u012b\u0101lest\u0101n"
    ],
    "name:fas_x_variant":[
        "L\u012b\u0101rest\u0101n",
        "\u0644\u06cc\u0627\u0631\u0633\u062a\u0627\u0646",
        "\u0644\u06cc\u0627\u0633\u062a\u0627\u0646",
        "\u0644\u06cc\u0627\u0644\u0633\u062a\u0627\u0646"
    ],
    "name:und_x_variant":[
        "Leyarest\u0101n",
        "L\u012barest\u0101n",
        "L\u012by\u0101lest\u0101n",
        "\u0644\u06cc\u0627\u0631\u0633\u062a\u0627\u0646",
        "L\u012b\u0101st\u0101n"
    ],
    "wof:name":"Liastan",
    "wof:placetype":"locality"
},
  "geometry": {"coordinates":[50.07174000000001,37.20188],"type":"Point"}
}