{
  "type": "Feature",
  "properties": {
    "gn:admin1_code":"11",
    "gn:asciiname":"Dahan-e Rah",
    "gn:country_code":"IR",
    "gn:dem":514,
    "gn:feature_class":"P",
    "gn:feature_code":"PPL",
    "gn:name":"Dahan-e R\u0101h",
    "gn:population":0,
    "gn:timezone":"Asia/Tehran",
    "iso:country":"IR",
    "name:fas_x_preferred":[
        "\u062f\u0647\u0646 \u0631\u0627\u0647"
    ],
    "name:fas_x_variant":[
        "Dahan-e R\u0101h"
    ],
    "wof:name":"Dahan-e Rah",
    "wof:placetype":"locality"
},
  "geometry": {"coordinates":[57.5679,26.629],"type":"Point"}
}