{
  "type": "Feature",
  "properties": {
    "gn:admin1_code":"7",
    "gn:asciiname":"Parishan",
    "gn:country_code":"IR",
    "gn:dem":850,
    "gn:feature_class":"P",
    "gn:feature_code":"PPL",
    "gn:name":"Par\u012bsh\u0101n",
    "gn:population":0,
    "gn:timezone":"Asia/Tehran",
    "iso:country":"IR",
    "name:fas_x_preferred":[
        "Par\u012bsh\u0101n"
    ],
    "name:fas_x_variant":[
        "\u067e\u0631\u06cc\u0634\u0627\u0646"
    ],
    "name:msa_x_preferred":[
        "Parishan"
    ],
    "name:und_x_variant":[
        "\u067e\u0631\u06cc\u0634\u0627\u0646"
    ],
    "wof:name":"Parishan",
    "wof:placetype":"locality"
},
  "geometry": {"coordinates":[51.82062,29.52986],"type":"Point"}
}