{
  "type": "Feature",
  "properties": {
    "gn:admin1_code":"7",
    "gn:asciiname":"Moqbelabad",
    "gn:country_code":"IR",
    "gn:dem":1574,
    "gn:feature_class":"P",
    "gn:feature_code":"PPL",
    "gn:name":"Moqbel\u0101b\u0101d",
    "gn:population":0,
    "gn:timezone":"Asia/Tehran",
    "iso:country":"IR",
    "name:ara_x_preferred":[
        "\u0645\u0642\u0628\u0644 \u0623\u0628\u0627\u062f"
    ],
    "name:fas_x_preferred":[
        "\u0645\u0642\u0628\u0644 \u0622\u0628\u0627\u062f"
    ],
    "name:fas_x_variant":[
        "Moqbel\u0101b\u0101d",
        "\u0645\u0642\u0628\u0644\u200c\u0622\u0628\u0627\u062f"
    ],
    "name:msa_x_preferred":[
        "Moqbelabad"
    ],
    "name:und_x_variant":[
        "Moghbel Abad"
    ],
    "wof:name":"Moqbelabad",
    "wof:placetype":"locality"
},
  "geometry": {"coordinates":[53.2575,29.7088],"type":"Point"}
}