{
  "type": "Feature",
  "properties": {
    "gn:admin1_code":"28",
    "gn:asciiname":"Gukan",
    "gn:country_code":"IR",
    "gn:dem":2051,
    "gn:feature_class":"P",
    "gn:feature_code":"PPL",
    "gn:name":"G\u016bk\u0101n",
    "gn:population":0,
    "gn:timezone":"Asia/Tehran",
    "iso:country":"IR",
    "name:ara_x_preferred":[
        "\u063a\u0648\u0643\u0627\u0646"
    ],
    "name:fas_x_preferred":[
        "G\u016bk\u0101n"
    ],
    "name:fas_x_variant":[
        "\u06af\u0648\u06a9\u0627\u0646"
    ],
    "name:und_x_variant":[
        "Ga\u016bk\u016bn",
        "G\u016bk\u0101n-e \u2018Oly\u0101",
        "Gowk\u0101n"
    ],
    "wof:name":"Gukan",
    "wof:placetype":"locality"
},
  "geometry": {"coordinates":[50.06086,32.68939],"type":"Point"}
}