{
  "type": "Feature",
  "properties": {
    "gn:admin1_code":"9",
    "gn:asciiname":"Sowlijeh",
    "gn:country_code":"IR",
    "gn:dem":1964,
    "gn:feature_class":"P",
    "gn:feature_code":"PPL",
    "gn:name":"Sowl\u012bjeh",
    "gn:population":0,
    "gn:timezone":"Asia/Tehran",
    "iso:country":"IR",
    "name:fas_x_preferred":[
        "\u0633\u0648\u0644\u064a\u062c\u0647"
    ],
    "name:fas_x_variant":[
        "S\u016bl\u012bjeh"
    ],
    "name:und_x_variant":[
        "Soolcheh",
        "Sulujeh",
        "Sowl\u012bjeh"
    ],
    "wof:name":"Sowlijeh",
    "wof:placetype":"locality"
},
  "geometry": {"coordinates":[48.33453,35.26895],"type":"Point"}
}