{
  "type": "Feature",
  "properties": {
    "gn:admin1_code":"16.0",
    "gn:asciiname":"Kukh-e Hasan Kordeh",
    "gn:country_code":"IR",
    "gn:dem":1592,
    "gn:feature_class":"P",
    "gn:feature_code":"PPL",
    "gn:name":"K\u016bkh-e \u1e28asan Kordeh",
    "gn:population":0,
    "gn:timezone":"Asia/Tehran",
    "iso:country":"IR",
    "name:fas_x_preferred":[
        "\u0643\u0648\u062e\u0650 \u062d\u064e\u0633\u064e\u0646 \u0643\u064f\u0631\u062f\u0650\u0647"
    ],
    "name:fas_x_variant":[
        "K\u016bkh-e \u1e28asan Kordeh"
    ],
    "wof:name":"Kukh-e Hasan Kordeh",
    "wof:placetype":"locality"
},
  "geometry": {"coordinates":[45.86667,35.95],"type":"Point"}
}