{
  "type": "Feature",
  "properties": {
    "gn:admin1_code":"7",
    "gn:asciiname":"Kherreh",
    "gn:country_code":"IR",
    "gn:dem":411,
    "gn:feature_class":"P",
    "gn:feature_code":"PPL",
    "gn:name":"Kherreh",
    "gn:population":0,
    "gn:timezone":"Asia/Tehran",
    "iso:country":"IR",
    "name:fas_x_preferred":[
        "\u062e\u0631\u0647"
    ],
    "name:msa_x_preferred":[
        "Kherreh"
    ],
    "wof:name":"Kherreh",
    "wof:placetype":"locality"
},
  "geometry": {"coordinates":[53.2464,27.3165],"type":"Point"}
}