{
  "type": "Feature",
  "properties": {
    "gn:admin1_code":"29",
    "gn:asciiname":"Deh-e `Ali Naqi",
    "gn:country_code":"IR",
    "gn:dem":1843,
    "gn:feature_class":"P",
    "gn:feature_code":"PPL",
    "gn:name":"Deh-e \u2018Al\u012b Naq\u012b",
    "gn:population":0,
    "gn:timezone":"Asia/Tehran",
    "iso:country":"IR",
    "name:fas_x_preferred":[
        "\u062f\u0647 \u0639\u0644\u06cc \u0646\u0642\u06cc"
    ],
    "name:fas_x_variant":[
        "\u2018Al\u012bnaq",
        "Deh-e \u2018Al\u012b Naq\u012b"
    ],
    "wof:name":"Deh-e `Ali Naqi",
    "wof:placetype":"locality"
},
  "geometry": {"coordinates":[55.2852,30.061],"type":"Point"}
}