{
  "type": "Feature",
  "properties": {
    "gn:admin1_code":"4.0",
    "gn:asciiname":"Gelingan",
    "gn:country_code":"IR",
    "gn:dem":956,
    "gn:feature_class":"P",
    "gn:feature_code":"PPL",
    "gn:name":"Gel\u012bng\u0101n",
    "gn:population":0,
    "gn:timezone":"Asia/Tehran",
    "iso:country":"IR",
    "name:fas_x_preferred":[
        "Gel\u012bng\u0101n"
    ],
    "name:fas_x_variant":[
        "Gel\u012bnk\u0101n",
        "\u06af\u0644\u06cc\u0646\u06af\u0627\u0646"
    ],
    "name:und_x_variant":[
        "\u06af\u0644\u06cc\u0646\u06af\u0627\u0646"
    ],
    "wof:name":"Gelingan",
    "wof:placetype":"locality"
},
  "geometry": {"coordinates":[61.06807,26.44987],"type":"Point"}
}