{
  "type": "Feature",
  "properties": {
    "gn:admin1_code":"35.0",
    "gn:asciiname":"Lar Sanur",
    "gn:country_code":"IR",
    "gn:dem":339,
    "gn:feature_class":"P",
    "gn:feature_code":"PPL",
    "gn:name":"Lar S\u0101n\u016br",
    "gn:population":0,
    "gn:timezone":"Asia/Tehran",
    "iso:country":"IR",
    "name:fas_x_preferred":[
        "\u0644\u062a\u0631 \u0633\u0627\u0645\u0631"
    ],
    "name:fas_x_variant":[
        "\u0644\u0631 \u0633\u0627\u0646\u0648\u0631",
        "\u0644\u0631 \u0633\u0627\u0646\u0648\u0631\u0647"
    ],
    "name:und_x_variant":[
        "Latr S\u0101mer",
        "Lar S\u0101n\u016br",
        "Lar S\u0101n\u016breh"
    ],
    "wof:name":"Lar Sanur",
    "wof:placetype":"locality"
},
  "geometry": {"coordinates":[50.69382,36.84736],"type":"Point"}
}