{
  "type": "Feature",
  "properties": {
    "gn:admin1_code":"5.0",
    "gn:asciiname":"Deh-e Now",
    "gn:country_code":"IR",
    "gn:dem":1223,
    "gn:feature_class":"P",
    "gn:feature_code":"PPL",
    "gn:name":"Deh-e Now",
    "gn:population":0,
    "gn:timezone":"Asia/Tehran",
    "iso:country":"IR",
    "name:fas_x_preferred":[
        "Tang-e Gol\u012b"
    ],
    "name:fas_x_variant":[
        "\u062a\u0646\u06af \u06af\u0644\u06cc",
        "\u062f\u0647 \u0646\u0648"
    ],
    "name:und_x_variant":[
        "Deh-e Now"
    ],
    "wof:name":"Deh-e Now",
    "wof:placetype":"locality"
},
  "geometry": {"coordinates":[50.54891,31.14107000000001],"type":"Point"}
}