{
  "type": "Feature",
  "properties": {
    "gn:admin1_code":"5",
    "gn:asciiname":"Sar Rud",
    "gn:country_code":"IR",
    "gn:dem":1691,
    "gn:feature_class":"P",
    "gn:feature_code":"PPL",
    "gn:name":"Sar R\u016bd",
    "gn:population":0,
    "gn:timezone":"Asia/Tehran",
    "iso:country":"IR",
    "name:fas_x_preferred":[
        "Sar B\u012bsheh-ye \u2018Oly\u0101"
    ],
    "name:fas_x_variant":[
        "\u0633\u0631 \u0628\u06cc\u0634\u0647 \u0639\u0644\u06cc\u0627",
        "\u0633\u0631 \u0631\u0648\u062f"
    ],
    "name:und_x_variant":[
        "\u0633\u0631 \u0628\u06cc\u0634\u0647 \u0639\u0644\u06cc\u0627",
        "Sar R\u016bd"
    ],
    "wof:name":"Sar Rud",
    "wof:placetype":"locality"
},
  "geometry": {"coordinates":[50.35262,31.26641],"type":"Point"}
}