{
  "type": "Feature",
  "properties": {
    "gn:admin1_code":"29",
    "gn:asciiname":"Sar Kik",
    "gn:country_code":"IR",
    "gn:dem":1101,
    "gn:feature_class":"P",
    "gn:feature_code":"PPLF",
    "gn:name":"Sar K\u012bk",
    "gn:population":0,
    "gn:timezone":"Asia/Tehran",
    "iso:country":"IR",
    "name:fas_x_preferred":[
        "\u0633\u0631\u06a9\u06cc\u06a9"
    ],
    "name:fas_x_variant":[
        "Sar K\u012bk",
        "\u0633\u0631\u0647 \u06a9\u06a9"
    ],
    "name:und_x_variant":[
        "Sareh Kek"
    ],
    "wof:name":"Sar Kik",
    "wof:placetype":"locality"
},
  "geometry": {"coordinates":[58.14908000000001,26.87508],"type":"Point"}
}