{
  "type": "Feature",
  "properties": {
    "gn:admin1_code":"16.0",
    "gn:asciiname":"Holucheh",
    "gn:country_code":"IR",
    "gn:dem":1458,
    "gn:feature_class":"P",
    "gn:feature_code":"PPL",
    "gn:name":"Hol\u016bcheh",
    "gn:population":0,
    "gn:timezone":"Asia/Tehran",
    "iso:country":"IR",
    "name:fas_x_preferred":[
        "\u0647\u0644\u0648\u0686\u0647"
    ],
    "name:fas_x_variant":[
        "Hol\u016bcheh"
    ],
    "wof:name":"Holucheh",
    "wof:placetype":"locality"
},
  "geometry": {"coordinates":[45.6707,36.0568],"type":"Point"}
}