{
  "type": "Feature",
  "properties": {
    "gn:admin1_code":"40.0",
    "gn:asciiname":"Mahalleh-ye Dar Kazhdar",
    "gn:country_code":"IR",
    "gn:dem":2183,
    "gn:feature_class":"P",
    "gn:feature_code":"PPL",
    "gn:name":"Ma\u1e29alleh-ye Dar Kazhdar",
    "gn:population":0,
    "gn:timezone":"Asia/Tehran",
    "iso:country":"IR",
    "name:fas_x_preferred":[
        "\u0645\u062d\u0644\u0647 \u062f\u0631 \u06a9\u0698\u062f\u0631"
    ],
    "name:und_x_variant":[
        "Ma\u1e29alleh-ye Dar Kazhdar"
    ],
    "wof:name":"Mahalleh-ye Dar Kazhdar",
    "wof:placetype":"locality"
},
  "geometry": {"coordinates":[54.19676,31.56683],"type":"Point"}
}