{
  "type": "Feature",
  "properties": {
    "gn:admin1_code":"40",
    "gn:asciiname":"Hakimabad",
    "gn:country_code":"IR",
    "gn:dem":1484,
    "gn:feature_class":"P",
    "gn:feature_code":"PPL",
    "gn:name":"\u1e28ak\u012bm\u0101b\u0101d",
    "gn:population":0,
    "gn:timezone":"Asia/Tehran",
    "iso:country":"IR",
    "name:fas_x_preferred":[
        "\u1e28ak\u012bm\u0101b\u0101d"
    ],
    "name:und_x_variant":[
        "\u1e28ak\u012bm"
    ],
    "wof:name":"Hakimabad",
    "wof:placetype":"locality"
},
  "geometry": {"coordinates":[53.37667,31.17111],"type":"Point"}
}