{
  "type": "Feature",
  "properties": {
    "gn:admin1_code":"11",
    "gn:asciiname":"Gav Miri",
    "gn:country_code":"IR",
    "gn:dem":29,
    "gn:feature_class":"P",
    "gn:feature_code":"PPL",
    "gn:name":"Gav M\u012br\u012b",
    "gn:population":0,
    "gn:timezone":"Asia/Tehran",
    "iso:country":"IR",
    "name:ara_x_preferred":[
        "\u063a\u0627\u0648 \u0645\u064a\u0631\u064a"
    ],
    "name:ceb_x_preferred":[
        "Gav M\u012br\u012b"
    ],
    "name:fas_x_preferred":[
        "\u06af\u0627\u0648\u0645\u064a\u0631\u06cc"
    ],
    "name:fas_x_variant":[
        "G\u0101vm\u012br\u012b",
        "\u06af\u0648 \u0645\u064a\u0631\u06cc",
        "\u0628\u0627\u063a \u06a9\u0646\u0627\u0631",
        "\u06af\u0627\u0648\u0645\u06cc\u0631\u06cc"
    ],
    "name:msa_x_preferred":[
        "Gavmiri"
    ],
    "name:swe_x_preferred":[
        "Gav M\u012br\u012b"
    ],
    "name:und_x_variant":[
        "Gowh",
        "Goveh",
        "Gav M\u012br\u012b",
        "B\u0101gh-e Kon\u0101r"
    ],
    "wof:name":"Gav Miri",
    "wof:placetype":"locality"
},
  "geometry": {"coordinates":[55.3281,26.8922],"type":"Point"}
}