{
  "type": "Feature",
  "properties": {
    "gn:admin1_code":"1",
    "gn:asciiname":"Zaspi",
    "gn:country_code":"IR",
    "gn:dem":1639,
    "gn:feature_class":"P",
    "gn:feature_code":"PPL",
    "gn:name":"Z\u0101sp\u012b",
    "gn:population":0,
    "gn:timezone":"Asia/Tehran",
    "iso:country":"IR",
    "name:fas_x_preferred":[
        "Z\u0101sp\u012b"
    ],
    "wof:name":"Zaspi",
    "wof:placetype":"locality"
},
  "geometry": {"coordinates":[44.83333,38.05],"type":"Point"}
}