{
  "type": "Feature",
  "properties": {
    "gn:admin1_code":"25",
    "gn:asciiname":"Khers",
    "gn:country_code":"IR",
    "gn:dem":1102,
    "gn:feature_class":"P",
    "gn:feature_code":"PPLF",
    "gn:name":"Khers",
    "gn:population":0,
    "gn:timezone":"Asia/Tehran",
    "iso:country":"IR",
    "name:fas_x_preferred":[
        "\u062e\u0648\u0631\u0633"
    ],
    "name:fas_x_variant":[
        "\u062e\u064f\u0648\u0633",
        "\u062e\u0631\u0633"
    ],
    "name:und_x_variant":[
        "Khows",
        "Khuras",
        "Khvors",
        "Khers",
        "Khowrs"
    ],
    "wof:name":"Khers",
    "wof:placetype":"locality"
},
  "geometry": {"coordinates":[54.61387,35.69481],"type":"Point"}
}