{
  "type": "Feature",
  "properties": {
    "gn:admin1_code":"8",
    "gn:asciiname":"Hajji Mahalleh",
    "gn:country_code":"IR",
    "gn:dem":-14,
    "gn:feature_class":"P",
    "gn:feature_code":"PPL",
    "gn:name":"\u1e28\u0101jj\u012b Ma\u1e29alleh",
    "gn:population":0,
    "gn:timezone":"Asia/Tehran",
    "iso:country":"IR",
    "name:ceb_x_preferred":[
        "\u1e28\u0101jj\u012b Ma\u1e29alleh"
    ],
    "name:fas_x_preferred":[
        "\u062d\u0627\u062c \u062a\u06cc\u0645\u0648\u0631 \u0645\u062d\u0644\u0647"
    ],
    "name:fas_x_variant":[
        "\u1e28\u0101jj Teym\u016br Ma\u1e29alleh",
        "\u062d\u0627\u062c\u06cc \u0645\u062d\u0644\u0647",
        "\u062d\u0627\u062c\u06cc\u200c\u0645\u062d\u0644\u0647"
    ],
    "name:swe_x_preferred":[
        "\u1e28\u0101jj\u012b Ma\u1e29alleh"
    ],
    "wof:name":"Hajji Mahalleh",
    "wof:placetype":"locality"
},
  "geometry": {"coordinates":[49.05295,37.65651],"type":"Point"}
}