{
  "type": "Feature",
  "properties": {
    "gn:admin1_code":"7",
    "gn:asciiname":"Hashemabad",
    "gn:country_code":"IR",
    "gn:dem":1568,
    "gn:feature_class":"P",
    "gn:feature_code":"PPL",
    "gn:name":"H\u0101shem\u0101b\u0101d",
    "gn:population":0,
    "gn:timezone":"Asia/Tehran",
    "iso:country":"IR",
    "name:fas_x_preferred":[
        "\u0647\u0627\u0634\u0645 \u0622\u0628\u0627\u062f"
    ],
    "name:fas_x_variant":[
        "Qal\u2018eh Now",
        "\u0642\u0644\u0639\u0647 \u0646\u0648",
        "H\u0101shem\u0101b\u0101d"
    ],
    "wof:name":"Hashemabad",
    "wof:placetype":"locality"
},
  "geometry": {"coordinates":[53.14118000000001,29.64195],"type":"Point"}
}