{
  "type": "Feature",
  "properties": {
    "gn:admin1_code":"7",
    "gn:asciiname":"Kupon-e `Olya",
    "gn:country_code":"IR",
    "gn:dem":786,
    "gn:feature_class":"P",
    "gn:feature_code":"PPL",
    "gn:name":"K\u016bpon-e \u2018Oly\u0101",
    "gn:population":0,
    "gn:timezone":"Asia/Tehran",
    "iso:country":"IR",
    "name:fas_x_preferred":[
        "K\u016bpon-e \u2018Oly\u0101"
    ],
    "name:fas_x_variant":[
        "K\u016bpon-e B\u0101l\u0101",
        "\u06a9\u0648\u067e\u0646 \u0639\u0644\u06cc\u0627",
        "\u0643\u0648\u067e\u064f\u0646 \u0633\u064f\u0631\u0646\u0627 \u0628\u0627\u0644\u0627"
    ],
    "name:und_x_variant":[
        "K\u016bp\u0101n-e \u2018Oly\u0101",
        "K\u016bp\u0101n",
        "\u06a9\u0648\u067e\u0646 \u0639\u0644\u06cc\u0627",
        "K\u016bpon Sorn\u0101 B\u0101l\u0101"
    ],
    "wof:name":"Kupon-e `Olya",
    "wof:placetype":"locality"
},
  "geometry": {"coordinates":[51.29161,30.33506],"type":"Point"}
}