{
  "type": "Feature",
  "properties": {
    "gn:admin1_code":"4",
    "gn:asciiname":"Kashhak",
    "gn:country_code":"IR",
    "gn:dem":575,
    "gn:feature_class":"P",
    "gn:feature_code":"PPL",
    "gn:name":"Kashhak",
    "gn:population":0,
    "gn:timezone":"Asia/Tehran",
    "iso:country":"IR",
    "name:fas_x_preferred":[
        "\u0632\u06cc\u0627\u0631\u062a"
    ],
    "name:fas_x_variant":[
        "Z\u012b\u0101rat",
        "Zey\u0101rat",
        "Z\u012by\u0101rat",
        "\u06a9\u0634\u0647\u06a9"
    ],
    "name:und_x_variant":[
        "Kashhak"
    ],
    "wof:name":"Kashhak",
    "wof:placetype":"locality"
},
  "geometry": {"coordinates":[59.47906999999999,26.91426],"type":"Point"}
}