{
  "type": "Feature",
  "properties": {
    "gn:admin1_code":"8",
    "gn:asciiname":"Buyeh",
    "gn:country_code":"IR",
    "gn:dem":1390,
    "gn:feature_class":"P",
    "gn:feature_code":"PPL",
    "gn:name":"B\u016byeh",
    "gn:population":0,
    "gn:timezone":"Asia/Tehran",
    "iso:country":"IR",
    "name:ara_x_preferred":[
        "\u0628\u0648\u064a\u0629"
    ],
    "name:fas_x_preferred":[
        "B\u016byeh"
    ],
    "name:fas_x_variant":[
        "\u0628\u0648\u06cc\u0647"
    ],
    "name:msa_x_preferred":[
        "Buyeh"
    ],
    "name:ukr_x_preferred":[
        "\u0411\u0443\u0454"
    ],
    "name:und_x_variant":[
        "\u0628\u0648\u06cc\u0647"
    ],
    "wof:name":"Buyeh",
    "wof:placetype":"locality"
},
  "geometry": {"coordinates":[50.10721,36.85323],"type":"Point"}
}