{
  "type": "Feature",
  "properties": {
    "gn:admin1_code":"28.0",
    "gn:asciiname":"Sho`beh Naft",
    "gn:country_code":"IR",
    "gn:dem":1557,
    "gn:feature_class":"P",
    "gn:feature_code":"PPLS",
    "gn:name":"Sho\u2018beh Naft",
    "gn:population":0,
    "gn:timezone":"Asia/Tehran",
    "iso:country":"IR",
    "name:fas_x_preferred":[
        "Sho\u2018beh Naft"
    ],
    "name:fas_x_variant":[
        "\u0634\u0639\u0628\u0647 \u0646\u0641\u062a"
    ],
    "wof:name":"Sho`beh Naft",
    "wof:placetype":"locality"
},
  "geometry": {"coordinates":[51.7464,32.69208],"type":"Point"}
}