{
  "type": "Feature",
  "properties": {
    "gn:admin1_code":"13",
    "gn:asciiname":"Sar Takhtgah",
    "gn:country_code":"IR",
    "gn:dem":1514,
    "gn:feature_class":"P",
    "gn:feature_code":"PPL",
    "gn:name":"Sar Takhtg\u0101h",
    "gn:population":0,
    "gn:timezone":"Asia/Tehran",
    "iso:country":"IR",
    "name:ara_x_preferred":[
        "\u0633\u0631\u062a\u062e\u062a\u063a\u0627\u0647"
    ],
    "name:ceb_x_preferred":[
        "Sar Takhtg\u0101h"
    ],
    "name:fas_x_preferred":[
        "\u0633\u0631 \u062a\u062e\u062a\u06af\u0627\u0647"
    ],
    "name:fas_x_variant":[
        "Sartakhtg\u0101h",
        "Sar Takhtg\u0101h",
        "\u0633\u0631\u062a\u062e\u062a\u06af\u0627\u0647"
    ],
    "name:swe_x_preferred":[
        "Sar Takhtg\u0101h"
    ],
    "wof:name":"Sar Takhtgah",
    "wof:placetype":"locality"
},
  "geometry": {"coordinates":[46.4894,34.4617],"type":"Point"}
}