{
  "type": "Feature",
  "properties": {
    "gn:admin1_code":"22",
    "gn:asciiname":"Kathak-e Sheykha",
    "gn:country_code":"IR",
    "gn:dem":23,
    "gn:feature_class":"P",
    "gn:feature_code":"PPL",
    "gn:name":"Kat\u1e29ak-e Sheykh\u0101",
    "gn:population":0,
    "gn:timezone":"Asia/Tehran",
    "iso:country":"IR",
    "name:ara_x_preferred":[
        "\u063a\u0646\u062e\u0643 \u0634\u064a\u062e\u064a"
    ],
    "name:ceb_x_preferred":[
        "Kat\u1e29ak-e Sheykh\u0101"
    ],
    "name:fas_x_preferred":[
        "\u06af\u064e\u0646\u062e\u064e\u0643\u0650 \u0686\u0627\u0647 \u0634\u0648\u0631"
    ],
    "name:fas_x_variant":[
        "\u0643\u0646\u062e\u06a9 \u0686\u0627\u0647 \u0634\u0648\u0631",
        "Gankhak-e Ch\u0101h Sh\u016br",
        "\u06a9\u062a\u062d\u06a9 \u0634\u06cc\u062e\u0627",
        "\u06a9\u062a\u062d\u06a9 \u0634\u0645\u0627\u0644\u06cc",
        "\u0643\u064e\u0646\u062e\u064e\u0643\u0650 \u0634\u0650\u0645\u0627\u0644",
        "\u06af\u0646\u062e\u06a9 \u0631\u0626\u06cc\u0633\u06cc",
        "\u06af\u0646\u062e\u06a9 \u0634\u06cc\u062e\u06cc"
    ],
    "name:msa_x_preferred":[
        "Gankhak-e Sheykhi"
    ],
    "name:swe_x_preferred":[
        "Kat\u1e29ak-e Sheykh\u0101"
    ],
    "name:und_x_variant":[
        "Kankhak-e Ch\u0101h Sh\u016br",
        "Kat\u1e29ak-e Sheykh\u0101",
        "Kat\u1e29ak-e Shom\u0101l\u012b",
        "Kankhak-e Shem\u0101l",
        "Gankhak-e Ra\u2019\u012bs\u012b",
        "Gankhak-e Sheykh\u012b"
    ],
    "wof:name":"Kathak-e Sheykha",
    "wof:placetype":"locality"
},
  "geometry": {"coordinates":[51.59379000000001,28.26601],"type":"Point"}
}