{
  "type": "Feature",
  "properties": {
    "gn:admin1_code":"13",
    "gn:asciiname":"Chahar Melan",
    "gn:country_code":"IR",
    "gn:dem":1772,
    "gn:feature_class":"P",
    "gn:feature_code":"PPL",
    "gn:name":"Chah\u0101r Mel\u0101n",
    "gn:population":0,
    "gn:timezone":"Asia/Tehran",
    "iso:country":"IR",
    "name:ceb_x_preferred":[
        "Chah\u0101r Mel\u0101n"
    ],
    "name:fas_x_preferred":[
        "\u0686\u0647\u0627\u0631 \u0645\u0644\u0627\u0646"
    ],
    "name:fas_x_variant":[
        "Chah\u0101r Mel\u0101n",
        "\u0686\u0647\u0627\u0631\u0645\u0644\u0627\u0646"
    ],
    "name:swe_x_preferred":[
        "Chah\u0101r Mel\u0101n"
    ],
    "wof:name":"Chahar Melan",
    "wof:placetype":"locality"
},
  "geometry": {"coordinates":[47.3245,34.832],"type":"Point"}
}