{
  "type": "Feature",
  "properties": {
    "gn:admin1_code":"35",
    "gn:asciiname":"Lalim",
    "gn:country_code":"IR",
    "gn:dem":97,
    "gn:feature_class":"P",
    "gn:feature_code":"PPL",
    "gn:name":"L\u0101l\u012bm",
    "gn:population":0,
    "gn:timezone":"Asia/Tehran",
    "iso:country":"IR",
    "name:fas_x_preferred":[
        "\u0644\u0627\u0644\u064a\u0645"
    ],
    "name:fas_x_variant":[
        "L\u0101l\u012bm"
    ],
    "wof:name":"Lalim",
    "wof:placetype":"locality"
},
  "geometry": {"coordinates":[53.21391,36.57523],"type":"Point"}
}