{
  "type": "Feature",
  "properties": {
    "gn:admin1_code":"42.0",
    "gn:asciiname":"Eshtivan",
    "gn:country_code":"IR",
    "gn:dem":1251,
    "gn:feature_class":"P",
    "gn:feature_code":"PPL",
    "gn:name":"Esht\u012bv\u0101n",
    "gn:population":0,
    "gn:timezone":"Asia/Tehran",
    "iso:country":"IR",
    "name:ara_x_preferred":[
        "\u0627\u0634\u062a\u064a\u0648\u0627\u0646"
    ],
    "name:ceb_x_preferred":[
        "Esht\u012bv\u0101n"
    ],
    "name:fas_x_preferred":[
        "\u0627\u0634\u062a\u064a\u0648\u0627\u0646"
    ],
    "name:fas_x_variant":[
        "Esht\u012bv\u0101n",
        "\u0627\u0634\u062a\u06cc\u0648\u0627\u0646"
    ],
    "name:swe_x_preferred":[
        "Esht\u012bv\u0101n"
    ],
    "wof:name":"Eshtivan",
    "wof:placetype":"locality"
},
  "geometry": {"coordinates":[60.39466,34.94594],"type":"Point"}
}