{
  "type": "Feature",
  "properties": {
    "gn:admin1_code":"4.0",
    "gn:asciiname":"Azaz",
    "gn:country_code":"IR",
    "gn:dem":22,
    "gn:feature_class":"P",
    "gn:feature_code":"PPL",
    "gn:name":"Az\u0101z",
    "gn:population":0,
    "gn:timezone":"Asia/Tehran",
    "iso:country":"IR",
    "name:fas_x_preferred":[
        "\u0627\u064e\u0632\u0627\u0632"
    ],
    "name:fas_x_variant":[
        "\u0627\u064e\u0632\u064a\u0632",
        "Az\u0101z"
    ],
    "name:und_x_variant":[
        "Az\u012bz"
    ],
    "wof:name":"Azaz",
    "wof:placetype":"locality"
},
  "geometry": {"coordinates":[61.18333000000001,25.53333],"type":"Point"}
}