{
  "type": "Feature",
  "properties": {
    "gn:admin1_code":"4.0",
    "gn:asciiname":"Azaz",
    "gn:country_code":"IR",
    "gn:dem":22,
    "gn:feature_class":"P",
    "gn:feature_code":"PPL",
    "gn:name":"Az\u0101z",
    "gn:population":0,
    "gn:timezone":"Asia/Tehran",
    "iso:country":"IR",
    "name:ara_x_preferred":[
        "\u0623\u0639\u0632\u0627\u0632"
    ],
    "name:aze_x_preferred":[
        "Az\u0259z"
    ],
    "name:cat_x_preferred":[
        "Azaz"
    ],
    "name:ceb_x_preferred":[
        "I\u2018z\u0101z"
    ],
    "name:ces_x_preferred":[
        "Azaz"
    ],
    "name:ckb_x_preferred":[
        "\u0626\u06d5\u0639\u0632\u0627\u0632"
    ],
    "name:deu_x_preferred":[
        "A\u02bfz\u0101z"
    ],
    "name:diq_x_preferred":[
        "Ezaz"
    ],
    "name:fas_x_preferred":[
        "\u0627\u064e\u0632\u0627\u0632"
    ],
    "name:fas_x_variant":[
        "\u0627\u064e\u0632\u064a\u0632",
        "Az\u0101z",
        "\u0627\u0639\u0632\u0627\u0632"
    ],
    "name:fin_x_preferred":[
        "Azaz"
    ],
    "name:fra_x_preferred":[
        "Azaz"
    ],
    "name:hye_x_preferred":[
        "\u0531\u0566\u0561\u0566"
    ],
    "name:ita_x_preferred":[
        "A'zaz"
    ],
    "name:kat_x_preferred":[
        "\u10d0\u10d6\u10d0\u10d6\u10d8"
    ],
    "name:kur_x_preferred":[
        "Ezaz"
    ],
    "name:lit_x_preferred":[
        "Azazas"
    ],
    "name:mzn_x_preferred":[
        "\u0627\u0639\u0632\u0627\u0632"
    ],
    "name:nld_x_preferred":[
        "Azaz"
    ],
    "name:nno_x_preferred":[
        "Azaz"
    ],
    "name:nor_x_preferred":[
        "Azaz"
    ],
    "name:pol_x_preferred":[
        "Azaz"
    ],
    "name:ron_x_preferred":[
        "Azaz"
    ],
    "name:rus_x_preferred":[
        "\u0410\u0430\u0437\u0430\u0437"
    ],
    "name:spa_x_preferred":[
        "Azaz"
    ],
    "name:sqi_x_preferred":[
        "Azez"
    ],
    "name:srp_x_preferred":[
        "\u0410\u0437\u0430\u0437"
    ],
    "name:swe_x_preferred":[
        "I\u2018z\u0101z"
    ],
    "name:tur_x_preferred":[
        "Azez"
    ],
    "name:ukr_x_preferred":[
        "\u0410\u0430\u0437\u0430\u0437"
    ],
    "name:und_x_variant":[
        "Az\u012bz"
    ],
    "name:urd_x_preferred":[
        "\u0627\u0639\u0632\u0627\u0632"
    ],
    "name:vie_x_preferred":[
        "Azaz"
    ],
    "name:zho_x_preferred":[
        "\u963f\u624e\u8332"
    ],
    "wof:name":"Azaz",
    "wof:placetype":"locality"
},
  "geometry": {"coordinates":[61.18333000000001,25.53333],"type":"Point"}
}