{
  "type": "Feature",
  "properties": {
    "gn:admin1_code":"4.0",
    "gn:asciiname":"Qasr-e Qand",
    "gn:country_code":"IR",
    "gn:dem":503,
    "gn:feature_class":"P",
    "gn:feature_code":"PPL",
    "gn:name":"Qa\u015fr-e Qand",
    "gn:population":0,
    "gn:timezone":"Asia/Tehran",
    "iso:country":"IR",
    "name:fas_x_preferred":[
        "\u0642\u0635\u0631 \u0642\u0646\u062f"
    ],
    "name:fas_x_variant":[
        "Q\u0101seg\u0101n",
        "Qa\u015fr-e Qand",
        "\u0642\u0646\u062f"
    ],
    "name:und_x_variant":[
        "Q\u0101sag\u0101n",
        "Qand"
    ],
    "wof:name":"Qasr-e Qand",
    "wof:placetype":"locality"
},
  "geometry": {"coordinates":[60.7408,26.2369],"type":"Point"}
}