{
  "type": "Feature",
  "properties": {
    "gn:admin1_code":"29",
    "gn:asciiname":"Gavin",
    "gn:country_code":"IR",
    "gn:dem":2667,
    "gn:feature_class":"P",
    "gn:feature_code":"PPL",
    "gn:name":"Gav\u012bn",
    "gn:population":0,
    "gn:timezone":"Asia/Tehran",
    "iso:country":"IR",
    "name:bre_x_preferred":[
        "Gavin"
    ],
    "name:cym_x_preferred":[
        "Gavin"
    ],
    "name:deu_x_preferred":[
        "Gavin"
    ],
    "name:fas_x_preferred":[
        "\u06af\u0648\u06cc\u0646"
    ],
    "name:fas_x_variant":[
        "Gav\u012bn"
    ],
    "name:fra_x_preferred":[
        "Gavin"
    ],
    "wof:name":"Gavin",
    "wof:placetype":"locality"
},
  "geometry": {"coordinates":[56.5239,29.4364],"type":"Point"}
}