{
  "type": "Feature",
  "properties": {
    "gn:admin1_code":"4.0",
    "gn:asciiname":"Giran",
    "gn:country_code":"IR",
    "gn:dem":750,
    "gn:feature_class":"P",
    "gn:feature_code":"PPL",
    "gn:name":"G\u012br\u0101n",
    "gn:population":0,
    "gn:timezone":"Asia/Tehran",
    "iso:country":"IR",
    "name:fas_x_preferred":[
        "\u06af\u06cc\u0632\u0627\u0646"
    ],
    "name:fas_x_variant":[
        "G\u012br\u0101n",
        "G\u012bz\u0101n",
        "\u06af\u06cc\u0631\u0627\u0646"
    ],
    "wof:name":"Giran",
    "wof:placetype":"locality"
},
  "geometry": {"coordinates":[59.0155,26.64412],"type":"Point"}
}