{
  "type": "Feature",
  "properties": {
    "gn:admin1_code":"0",
    "gn:asciiname":"Cheshmeh-ye Sefid",
    "gn:cc2":"IR",
    "gn:country_code":"IR",
    "gn:dem":2303,
    "gn:feature_class":"P",
    "gn:feature_code":"PPL",
    "gn:name":"Cheshmeh-ye Sef\u012bd",
    "gn:population":0,
    "gn:timezone":"Asia/Tehran",
    "iso:country":"IR",
    "name:fas_x_preferred":[
        "\u0686\u0650\u0634\u0645\u0650\u06c0 \u0633\u0650\u0641\u064a\u062f"
    ],
    "name:und_x_variant":[
        "Chashmeh Sefid"
    ],
    "wof:name":"Cheshmeh-ye Sefid",
    "wof:placetype":"locality"
},
  "geometry": {"coordinates":[51.95,30.25],"type":"Point"}
}