{
  "type": "Feature",
  "properties": {
    "gn:admin1_code":"13",
    "gn:asciiname":"Qobad-e Shian",
    "gn:country_code":"IR",
    "gn:dem":1370,
    "gn:feature_class":"P",
    "gn:feature_code":"PPL",
    "gn:name":"Qob\u0101d-e Sh\u012b\u0101n",
    "gn:population":0,
    "gn:timezone":"Asia/Tehran",
    "iso:country":"IR",
    "name:fas_x_preferred":[
        "\u0642\u0628\u0627\u062f\u0634\u06cc\u0627\u0646"
    ],
    "name:fas_x_variant":[
        "Qob\u0101d",
        "Qob\u0101d-e Sh\u012b\u0101n"
    ],
    "name:und_x_variant":[
        "Kab\u0101t",
        "Akbar Qob\u0101d",
        "Ko\u0101i"
    ],
    "wof:name":"Qobad-e Shian",
    "wof:placetype":"locality"
},
  "geometry": {"coordinates":[46.709,34.0376],"type":"Point"}
}