{
  "type": "Feature",
  "properties": {
    "gn:admin1_code":"36",
    "gn:asciiname":"Qandi Bolagh",
    "gn:country_code":"IR",
    "gn:dem":1559,
    "gn:feature_class":"P",
    "gn:feature_code":"PPL",
    "gn:name":"Qand\u012b Bol\u0101gh",
    "gn:population":0,
    "gn:timezone":"Asia/Tehran",
    "iso:country":"IR",
    "name:azb_x_preferred":[
        "\u0642\u0646\u062f\u06cc \u0628\u0644\u0627\u063a"
    ],
    "name:fas_x_preferred":[
        "\u0642\u0646\u062f \u0628\u0644\u0627\u063a"
    ],
    "name:fas_x_variant":[
        "Qand Bol\u0101gh",
        "\u0642\u0646\u062f\u06cc \u0628\u0644\u0627\u063a",
        "\u0642\u0646\u062f\u06cc\u200c\u0628\u0644\u0627\u063a"
    ],
    "name:und_x_variant":[
        "Kandbul\u0101q",
        "Kand Bulag",
        "Qand\u012b Bol\u0101gh"
    ],
    "wof:name":"Qandi Bolagh",
    "wof:placetype":"locality"
},
  "geometry": {"coordinates":[48.01801,36.29193],"type":"Point"}
}