{
  "type": "Feature",
  "properties": {
    "gn:admin1_code":"16",
    "gn:asciiname":"Qamishaleh",
    "gn:country_code":"IR",
    "gn:dem":1689,
    "gn:feature_class":"P",
    "gn:feature_code":"PPL",
    "gn:name":"Q\u0101m\u012bshaleh",
    "gn:population":0,
    "gn:timezone":"Asia/Tehran",
    "iso:country":"IR",
    "name:fas_x_preferred":[
        "\u0642\u0627\u0645\u064a\u0634\u064e\u0644\u0650\u0647"
    ],
    "name:fas_x_variant":[
        "\u0642\u0627\u0645\u064a\u0634\u0644\u0650\u0647",
        "\u0642\u0627\u0645\u06cc \u0634\u0650\u0644\u0650\u0647",
        "\u0642\u0627\u0645\u06cc\u0634\u0644\u0647",
        "Q\u0101m\u012bshaleh",
        "Q\u0101m\u012bshleh"
    ],
    "name:und_x_variant":[
        "Q\u0101m\u012b Sheleh",
        "Q\u0101m\u012bshleh"
    ],
    "wof:name":"Qamishaleh",
    "wof:placetype":"locality"
},
  "geometry": {"coordinates":[46.267,35.67800000000001],"type":"Point"}
}