{
  "type": "Feature",
  "properties": {
    "gn:admin1_code":"11",
    "gn:asciiname":"Posht-e Kenow",
    "gn:country_code":"IR",
    "gn:dem":1095,
    "gn:feature_class":"P",
    "gn:feature_code":"PPL",
    "gn:name":"Posht-e Kenow",
    "gn:population":0,
    "gn:timezone":"Asia/Tehran",
    "iso:country":"IR",
    "name:fas_x_preferred":[
        "\u067e\u0634\u062a \u0643\u0646\u0648\u0646"
    ],
    "name:fas_x_variant":[
        "\u067e\u0634\u062a \u0643\u0646\u0648",
        "\u062f\u064e\u0634\u062a\u0650 \u0643\u0650\u0646\u0648",
        "Posht-e Kon\u016bn"
    ],
    "name:und_x_variant":[
        "Dasht-e Ken\u016b",
        "Posht-e Kenow"
    ],
    "wof:name":"Posht-e Kenow",
    "wof:placetype":"locality"
},
  "geometry": {"coordinates":[56.4101,27.829],"type":"Point"}
}