{
  "type": "Feature",
  "properties": {
    "gn:admin1_code":"16.0",
    "gn:asciiname":"Handiman",
    "gn:country_code":"IR",
    "gn:dem":1410,
    "gn:elevation":"0.0",
    "gn:feature_class":"P",
    "gn:feature_code":"PPL",
    "gn:name":"Hand\u012bman",
    "gn:population":0,
    "gn:timezone":"Asia/Tehran",
    "iso:country":"IR",
    "name:fas_x_preferred":[
        "\u0647\u0646\u062f\u064a\u0645\u0646"
    ],
    "name:fas_x_variant":[
        "\u0627\u0646\u062f\u06cc\u0645\u0646",
        "Hand\u012bman",
        "And\u012bman"
    ],
    "name:und_x_variant":[
        "And\u012bmen",
        "H\u012bndam\u0101n",
        "Hend\u012bman",
        "Hendam\u0101n",
        "Handm\u0101n",
        "\u0647\u064e\u0646\u062f\u0645\u0627\u0646",
        "\u0647\u064a\u0646\u062f\u064e\u0645\u0627\u0646"
    ],
    "wof:name":"Handiman",
    "wof:placetype":"locality"
},
  "geometry": {"coordinates":[46.77165,35.00994],"type":"Point"}
}