{
  "type": "Feature",
  "properties": {
    "gn:admin1_code":"28",
    "gn:asciiname":"Hejrak",
    "gn:cc2":"IR",
    "gn:country_code":"IR",
    "gn:dem":1666,
    "gn:feature_class":"P",
    "gn:feature_code":"PPL",
    "gn:name":"Hejrak",
    "gn:population":0,
    "gn:timezone":"Asia/Tehran",
    "iso:country":"IR",
    "name:und_x_variant":[
        "Hajrak",
        "Hejrak"
    ],
    "wof:name":"Hejrak",
    "wof:placetype":"locality"
},
  "geometry": {"coordinates":[54.59194,33.42610999999999],"type":"Point"}
}