{
  "type": "Feature",
  "properties": {
    "gn:admin1_code":"28.0",
    "gn:asciiname":"Tangestan",
    "gn:country_code":"IR",
    "gn:dem":2186,
    "gn:feature_class":"P",
    "gn:feature_code":"PPL",
    "gn:name":"Tangest\u0101n",
    "gn:population":0,
    "gn:timezone":"Asia/Tehran",
    "iso:country":"IR",
    "name:ara_x_preferred":[
        "\u062a\u0646\u063a\u0633\u062a\u0627\u0646"
    ],
    "name:fas_x_preferred":[
        "\u062a\u0646\u06af\u0633\u062a\u0627\u0646"
    ],
    "name:fas_x_variant":[
        "Tangest\u0101n"
    ],
    "wof:name":"Tangestan",
    "wof:placetype":"locality"
},
  "geometry": {"coordinates":[52.8905,32.7543],"type":"Point"}
}