{
  "type": "Feature",
  "properties": {
    "gn:admin1_code":"44",
    "gn:asciiname":"Ajor Pazi-ye Bradaran-e Kadkhoda'i",
    "gn:country_code":"IR",
    "gn:dem":1189,
    "gn:feature_class":"P",
    "gn:feature_code":"PPL",
    "gn:name":"\u0100jor Paz\u012b-ye Br\u0101dar\u0101n-e Kadkhod\u0101\u2019\u012b",
    "gn:population":0,
    "gn:timezone":"Asia/Tehran",
    "iso:country":"IR",
    "name:fas_x_preferred":[
        "\u0622\u062c\u064f\u0631 \u067e\u064e\u0632\u0626 \u0628\u0631\u0627\u062f\u064e\u0631\u0627\u0646\u0650 \u0643\u064e\u062f\u062e\u064f\u062f\u0627\u0626\u06cc"
    ],
    "name:fas_x_variant":[
        "\u0100jor Paz\u012b-ye Br\u0101dar\u0101n-e Kadkhod\u0101\u2019\u012b"
    ],
    "wof:name":"Ajor Pazi-ye Bradaran-e Kadkhoda'i",
    "wof:placetype":"locality"
},
  "geometry": {"coordinates":[50.25,35.73333],"type":"Point"}
}