{
  "type": "Feature",
  "properties": {
    "gn:admin1_code":"23",
    "gn:asciiname":"Mesgari",
    "gn:country_code":"IR",
    "gn:dem":1987,
    "gn:feature_class":"P",
    "gn:feature_code":"PPL",
    "gn:name":"Mesgar\u012b",
    "gn:population":0,
    "gn:timezone":"Asia/Tehran",
    "iso:country":"IR",
    "name:ara_x_preferred":[
        "\u0645\u0633\u063a\u0631\u064a"
    ],
    "name:fas_x_preferred":[
        "\u0647\u064e\u0633\u06af\u064e\u0631\u06cc"
    ],
    "name:fas_x_variant":[
        "Mesgar\u012b",
        "\u0645\u0633\u06af\u0631\u06cc"
    ],
    "name:und_x_variant":[
        "Hasgar\u012b"
    ],
    "wof:name":"Mesgari",
    "wof:placetype":"locality"
},
  "geometry": {"coordinates":[49.6619,33.11943],"type":"Point"}
}