{
  "type": "Feature",
  "properties": {
    "gn:admin1_code":"1.0",
    "gn:asciiname":"Amir Beyg-e `Olya",
    "gn:country_code":"IR",
    "gn:dem":1184,
    "gn:feature_class":"P",
    "gn:feature_code":"PPL",
    "gn:name":"Am\u012br Beyg-e \u2018Oly\u0101",
    "gn:population":0,
    "gn:timezone":"Asia/Tehran",
    "iso:country":"IR",
    "name:fas_x_preferred":[
        "\u0627\u0645\u06cc\u0631 \u0628\u06cc\u06af \u0639\u0644\u06cc\u0627"
    ],
    "name:fas_x_variant":[
        "Am\u012br Beyg-e \u2018Oly\u0101"
    ],
    "wof:name":"Amir Beyg-e `Olya",
    "wof:placetype":"locality"
},
  "geometry": {"coordinates":[44.9232,38.5101],"type":"Point"}
}