{
  "type": "Feature",
  "properties": {
    "gn:admin1_code":"8",
    "gn:asciiname":"Mahalleh-ye Agri Bujaq",
    "gn:country_code":"IR",
    "gn:dem":-7,
    "gn:feature_class":"P",
    "gn:feature_code":"PPL",
    "gn:name":"Ma\u1e29alleh-ye Agr\u012b B\u016bj\u0101q",
    "gn:population":0,
    "gn:timezone":"Asia/Tehran",
    "iso:country":"IR",
    "name:fas_x_preferred":[
        "Agr\u012bb\u012bj\u0101r"
    ],
    "name:fas_x_variant":[
        "\u0645\u062d\u0644\u0647 \u0627\u06af\u0631\u06cc \u0628\u0648\u062c\u0627\u0642",
        "\u0627\u06af\u0631\u06cc \u0628\u0648\u062c\u0627\u0642",
        "\u06cc\u0648\u0645\u0627\u0631\u0647 \u0633\u0631\u0627"
    ],
    "name:und_x_variant":[
        "\u012ar\u016bboj\u0101gh",
        "Ma\u1e29alleh-ye Agr\u012b B\u016bj\u0101q",
        "Agar\u012b B\u016bj\u0101q",
        "Egr\u012b B\u016bj\u0101q",
        "Agr\u012b B\u012bj\u0101r",
        "Qanbar Ma\u1e29alleh",
        "Agr\u012b B\u016bj\u0101q",
        "Y\u016bm\u0101reh Sar\u0101"
    ],
    "wof:name":"Mahalleh-ye Agri Bujaq",
    "wof:placetype":"locality"
},
  "geometry": {"coordinates":[48.90413,37.98121],"type":"Point"}
}