{
  "type": "Feature",
  "properties": {
    "gn:admin1_code":"35",
    "gn:asciiname":"Pol-e Gardan",
    "gn:country_code":"IR",
    "gn:dem":57,
    "gn:feature_class":"P",
    "gn:feature_code":"PPL",
    "gn:name":"Pol-e Gardan",
    "gn:population":0,
    "gn:timezone":"Asia/Tehran",
    "iso:country":"IR",
    "name:fas_x_preferred":[
        "\u067e\u0644 \u06af\u0631\u062f\u0646"
    ],
    "name:und_x_variant":[
        "\u067e\u0644 \u06af\u0631\u062f\u0646",
        "Pol-e Gardan"
    ],
    "wof:name":"Pol-e Gardan",
    "wof:placetype":"locality"
},
  "geometry": {"coordinates":[53.07983,36.54397],"type":"Point"}
}