{
  "type": "Feature",
  "properties": {
    "gn:admin1_code":"16",
    "gn:asciiname":"Piranshah",
    "gn:cc2":"IR",
    "gn:country_code":"IR",
    "gn:dem":1459,
    "gn:feature_class":"P",
    "gn:feature_code":"PPL",
    "gn:name":"P\u012br\u0101nsh\u0101h",
    "gn:population":0,
    "gn:timezone":"Asia/Tehran",
    "iso:country":"IR",
    "name:fas_x_preferred":[
        "\u067e\u064a\u0631\u0627\u0646\u0634\u0627\u0647"
    ],
    "name:fas_x_variant":[
        "P\u012br\u0101nsh\u0101h"
    ],
    "name:und_x_variant":[
        "Piran"
    ],
    "wof:name":"Piranshah",
    "wof:placetype":"locality"
},
  "geometry": {"coordinates":[46.02306,35.50583],"type":"Point"}
}