{
  "type": "Feature",
  "properties": {
    "gn:admin1_code":"8",
    "gn:asciiname":"Now Deh-e Markhal",
    "gn:country_code":"IR",
    "gn:dem":6,
    "gn:feature_class":"P",
    "gn:feature_code":"PPL",
    "gn:name":"Now Deh-e Markh\u0101l",
    "gn:population":0,
    "gn:timezone":"Asia/Tehran",
    "iso:country":"IR",
    "name:fas_x_preferred":[
        "\u0646\u0648 \u062f\u0647 \u0645\u0631\u062e\u0627\u0644"
    ],
    "name:fas_x_variant":[
        "Now Deh-e Markh\u0101l"
    ],
    "wof:name":"Now Deh-e Markhal",
    "wof:placetype":"locality"
},
  "geometry": {"coordinates":[49.44023,37.23265],"type":"Point"}
}