{
  "type": "Feature",
  "properties": {
    "gn:admin1_code":"38",
    "gn:asciiname":"Raziabad",
    "gn:country_code":"IR",
    "gn:dem":1172,
    "gn:feature_class":"P",
    "gn:feature_code":"PPL",
    "gn:name":"Ra\u1e95\u012b\u0101b\u0101d",
    "gn:population":0,
    "gn:timezone":"Asia/Tehran",
    "iso:country":"IR",
    "name:ara_x_preferred":[
        "\u0631\u0627\u0636\u064a \u0623\u0628\u0627\u062f"
    ],
    "name:fas_x_preferred":[
        "\u0631\u064e\u0632\u06cc \u0622\u0628\u0627\u062f"
    ],
    "name:fas_x_variant":[
        "\u0631\u0636\u06cc \u0622\u0628\u0627\u062f",
        "Raz\u012b\u0101b\u0101d",
        "Ra\u1e95\u012b\u0101b\u0101d",
        "\u0631\u0636\u06cc\u200c\u0622\u0628\u0627\u062f"
    ],
    "name:und_x_variant":[
        "Riza\u0101b\u0101d"
    ],
    "wof:name":"Raziabad",
    "wof:placetype":"locality"
},
  "geometry": {"coordinates":[50.1853,36.0494],"type":"Point"}
}