{
  "type": "Feature",
  "properties": {
    "gn:admin1_code":"35.0",
    "gn:asciiname":"Berenjestanak-e Bala",
    "gn:country_code":"IR",
    "gn:dem":216,
    "gn:feature_class":"P",
    "gn:feature_code":"PPL",
    "gn:name":"Berenjest\u0101nak-e B\u0101l\u0101",
    "gn:population":0,
    "gn:timezone":"Asia/Tehran",
    "iso:country":"IR",
    "name:fas_x_preferred":[
        "\u0628\u0631\u0646\u062c\u0633\u062a\u0627\u0646\u06a9 \u0628\u0627\u0644\u0627"
    ],
    "name:fas_x_variant":[
        "Berenjest\u0101nak-e B\u0101l\u0101"
    ],
    "wof:name":"Berenjestanak-e Bala",
    "wof:placetype":"locality"
},
  "geometry": {"coordinates":[52.93397,36.37287],"type":"Point"}
}