{
  "type": "Feature",
  "properties": {
    "gn:admin1_code":"0",
    "gn:asciiname":"Arisman",
    "gn:country_code":"IR",
    "gn:dem":1006,
    "gn:feature_class":"P",
    "gn:feature_code":"PPL",
    "gn:name":"Ar\u012bsm\u0101n",
    "gn:population":0,
    "gn:timezone":"Asia/Tehran",
    "iso:country":"IR",
    "name:fas_x_preferred":[
        "\u0627\u0631\u06cc\u0633\u0645\u0627\u0646"
    ],
    "name:fas_x_variant":[
        "Ar\u012bsm\u0101n"
    ],
    "wof:name":"Arisman",
    "wof:placetype":"locality"
},
  "geometry": {"coordinates":[51.997,33.6627],"type":"Point"}
}