{
  "type": "Feature",
  "properties": {
    "gn:admin1_code":"29",
    "gn:asciiname":"Bagh-e Baba'i",
    "gn:country_code":"IR",
    "gn:dem":2005,
    "gn:feature_class":"P",
    "gn:feature_code":"PPL",
    "gn:name":"B\u0101gh-e B\u0101b\u0101\u2019\u012b",
    "gn:population":0,
    "gn:timezone":"Asia/Tehran",
    "iso:country":"IR",
    "name:fas_x_preferred":[
        "\u0628\u0627\u063a \u0628\u0627\u0628\u0627\u0626\u06cc"
    ],
    "name:fas_x_variant":[
        "B\u0101gh-e B\u0101b\u0101\u2019\u012b"
    ],
    "wof:name":"Bagh-e Baba'i",
    "wof:placetype":"locality"
},
  "geometry": {"coordinates":[56.79479,28.73987],"type":"Point"}
}