{
  "type": "Feature",
  "properties": {
    "gn:admin1_code":"16",
    "gn:asciiname":"Gazneh",
    "gn:country_code":"IR",
    "gn:dem":1394,
    "gn:feature_class":"P",
    "gn:feature_code":"PPL",
    "gn:name":"Gazneh",
    "gn:population":0,
    "gn:timezone":"Asia/Tehran",
    "iso:country":"IR",
    "name:fas_x_preferred":[
        "\u062c\u064e\u0632\u0646\u0650\u0647"
    ],
    "name:fas_x_variant":[
        "\u06af\u0632\u0646\u0647"
    ],
    "name:und_x_variant":[
        "Jazneh",
        "Gazaneh",
        "Gazneh"
    ],
    "wof:name":"Gazneh",
    "wof:placetype":"locality"
},
  "geometry": {"coordinates":[46.9417,35.1676],"type":"Point"}
}