{
  "type": "Feature",
  "properties": {
    "gn:admin1_code":"29.0",
    "gn:asciiname":"Golbaf",
    "gn:country_code":"IR",
    "gn:dem":1756,
    "gn:feature_class":"P",
    "gn:feature_code":"PPL",
    "gn:name":"Golb\u0101f",
    "gn:population":0,
    "gn:timezone":"Asia/Tehran",
    "iso:country":"IR",
    "name:ara_x_preferred":[
        "\u063a\u0644\u0628\u0627\u0641"
    ],
    "name:aze_x_preferred":[
        "G\u00fclbaf"
    ],
    "name:ceb_x_preferred":[
        "Golb\u0101f"
    ],
    "name:fas_x_preferred":[
        "\u06af\u0644\u0628\u0627\u0641"
    ],
    "name:fas_x_variant":[
        "Golb\u0101f"
    ],
    "name:ita_x_preferred":[
        "Golbaf"
    ],
    "name:mlg_x_preferred":[
        "Golbaf"
    ],
    "name:swe_x_preferred":[
        "Golb\u0101f"
    ],
    "name:tur_x_preferred":[
        "G\u00fclbaf"
    ],
    "name:und_x_variant":[
        "Gowg",
        "G\u016bk",
        "Gowk"
    ],
    "wof:name":"Golbaf",
    "wof:placetype":"locality"
},
  "geometry": {"coordinates":[57.7305,29.885],"type":"Point"}
}