{
  "type": "Feature",
  "properties": {
    "gn:admin1_code":"23",
    "gn:asciiname":"Rey Row",
    "gn:country_code":"IR",
    "gn:dem":886,
    "gn:feature_class":"P",
    "gn:feature_code":"PPL",
    "gn:name":"Rey Row",
    "gn:population":0,
    "gn:timezone":"Asia/Tehran",
    "iso:country":"IR",
    "name:fas_x_preferred":[
        "\u062e\u0631 \u067e\u0634\u062a"
    ],
    "name:fas_x_variant":[
        "\u0631\u06cc \u0631\u0648"
    ],
    "name:und_x_variant":[
        "Khar Posht",
        "Rey Row"
    ],
    "wof:name":"Rey Row",
    "wof:placetype":"locality"
},
  "geometry": {"coordinates":[48.7737,33.1318],"type":"Point"}
}