{
  "type": "Feature",
  "properties": {
    "gn:admin1_code":"42",
    "gn:asciiname":"Soltanabad",
    "gn:country_code":"IR",
    "gn:dem":1212,
    "gn:feature_class":"P",
    "gn:feature_code":"PPLA2",
    "gn:name":"Sol\u0163\u0101n\u0101b\u0101d",
    "gn:population":0,
    "gn:timezone":"Asia/Tehran",
    "iso:country":"IR",
    "name:fas_x_preferred":[
        "Sol\u0163\u0101n\u0101b\u0101d"
    ],
    "name:fas_x_variant":[
        "\u0633\u0644\u0637\u0627\u0646 \u0622\u0628\u0627\u062f",
        "Sult\u0101n\u0101b\u0101d"
    ],
    "name:und_x_variant":[
        "Kashmar",
        "Turshiz",
        "Sult\u0101n\u0101b\u0101d",
        "\u0633\u0644\u0637\u0627\u0646 \u0622\u0628\u0627\u062f"
    ],
    "wof:name":"Soltanabad",
    "wof:placetype":"locality"
},
  "geometry": {"coordinates":[58.03894,36.40352],"type":"Point"}
}