{
  "type": "Feature",
  "properties": {
    "gn:admin1_code":"1",
    "gn:asciiname":"Tappeh Bashi",
    "gn:country_code":"IR",
    "gn:dem":1336,
    "gn:feature_class":"P",
    "gn:feature_code":"PPL",
    "gn:name":"Tappeh B\u0101sh\u012b",
    "gn:population":0,
    "gn:timezone":"Asia/Tehran",
    "iso:country":"IR",
    "name:fas_x_preferred":[
        "Tappeh B\u0101sh\u012b"
    ],
    "name:fas_x_variant":[
        "\u062a\u067e\u0651\u0647 \u0628\u0627\u0634\u06cc"
    ],
    "wof:name":"Tappeh Bashi",
    "wof:placetype":"locality"
},
  "geometry": {"coordinates":[44.8352,38.5711],"type":"Point"}
}