{
  "type": "Feature",
  "properties": {
    "gn:admin1_code":"9",
    "gn:asciiname":"Salilak",
    "gn:country_code":"IR",
    "gn:dem":1738,
    "gn:feature_class":"P",
    "gn:feature_code":"PPL",
    "gn:name":"Sal\u012blak",
    "gn:population":0,
    "gn:timezone":"Asia/Tehran",
    "iso:country":"IR",
    "name:fas_x_preferred":[
        "\u0633\u0644\u06cc\u0644\u06a9"
    ],
    "name:fas_x_variant":[
        "Sal\u012blak",
        "\u0645\u064e\u0644\u064a\u0644\u064e\u0643"
    ],
    "name:und_x_variant":[
        "Mal\u012blak"
    ],
    "wof:name":"Salilak",
    "wof:placetype":"locality"
},
  "geometry": {"coordinates":[49.11888,35.25264],"type":"Point"}
}