{
  "type": "Feature",
  "properties": {
    "gn:admin1_code":"16",
    "gn:asciiname":"Chenareh",
    "gn:country_code":"IR",
    "gn:dem":1509,
    "gn:feature_class":"P",
    "gn:feature_code":"PPL",
    "gn:name":"Chen\u0101reh",
    "gn:population":0,
    "gn:timezone":"Asia/Tehran",
    "iso:country":"IR",
    "name:ara_x_preferred":[
        "\u062a\u0634\u0646\u0627\u0631\u0647"
    ],
    "name:aze_x_preferred":[
        "\u00c7inar\u0259"
    ],
    "name:ceb_x_preferred":[
        "Chen\u0101reh"
    ],
    "name:ckb_x_preferred":[
        "\u0686\u0646\u0627\u0631\u06d5"
    ],
    "name:fas_x_preferred":[
        "\u0686\u0646\u0627\u0631"
    ],
    "name:fas_x_variant":[
        "Chen\u0101reh",
        "\u0686\u0646\u0627\u0631\u0647",
        "Chen\u0101r"
    ],
    "name:mlg_x_preferred":[
        "Chenareh"
    ],
    "name:mzn_x_preferred":[
        "\u0686\u0646\u0627\u0631\u0647"
    ],
    "name:swe_x_preferred":[
        "Chen\u0101reh"
    ],
    "name:tur_x_preferred":[
        "\u00c7inare"
    ],
    "name:urd_x_preferred":[
        "\u0686\u0646\u0627\u0631\u0647"
    ],
    "wof:name":"Chenareh",
    "wof:placetype":"locality"
},
  "geometry": {"coordinates":[46.57198,36.14425],"type":"Point"}
}