{
  "type": "Feature",
  "properties": {
    "iso:country":"IR",
    "name:ara_x_preferred":[
        "\u0645\u064a\u0627\u0646\u062f\u0648\u0622\u0628"
    ],
    "name:azb_x_preferred":[
        "\u0645\u06cc\u0627\u0646\u062f\u0648\u0622\u0628"
    ],
    "name:aze_x_preferred":[
        "Miyand\u00fcab"
    ],
    "name:aze_x_variant":[
        "Qo\u015fa\u00e7ay"
    ],
    "name:ceb_x_preferred":[
        "M\u012b\u0101ndo\u0101b"
    ],
    "name:ckb_x_preferred":[
        "\u0645\u06cc\u0627\u0646\u062f\u0648\u0627\u0648"
    ],
    "name:deu_x_preferred":[
        "Miandoab"
    ],
    "name:eng_x_preferred":[
        "Miandoab"
    ],
    "name:epo_x_preferred":[
        "Miandoab"
    ],
    "name:fas_x_preferred":[
        "\u0645\u06cc\u0627\u0646\u062f\u0648\u0622\u0628"
    ],
    "name:fas_x_variant":[
        "M\u012b\u0101ndow\u0101b",
        "M\u012b\u0101ndo\u0101b"
    ],
    "name:fra_x_preferred":[
        "Miandoab"
    ],
    "name:hbs_x_preferred":[
        "Mijandoab"
    ],
    "name:heb_x_preferred":[
        "\u05de\u05d9\u05d0\u05e0\u05d3\u05d5\u05d0\u05d1"
    ],
    "name:hin_x_preferred":[
        "\u092e\u093f\u092f\u093e\u0902\u0926\u094b\u0906\u092c"
    ],
    "name:ita_x_preferred":[
        "Miandoab"
    ],
    "name:kaz_x_preferred":[
        "\u041c\u0438\u0430\u043d\u0434\u043e\u0430\u0431"
    ],
    "name:kur_x_preferred":[
        "Miyanduaw"
    ],
    "name:mlg_x_preferred":[
        "Miandoab"
    ],
    "name:msa_x_preferred":[
        "Miandoab"
    ],
    "name:nld_x_preferred":[
        "Miandoab"
    ],
    "name:pnb_x_preferred":[
        "\u0645\u06cc\u0627\u0646\u062f\u0648\u0622\u0628"
    ],
    "name:pol_x_preferred":[
        "Mijandoab"
    ],
    "name:por_x_preferred":[
        "Miandoab"
    ],
    "name:ron_x_preferred":[
        "Miandoab"
    ],
    "name:rus_x_preferred":[
        "\u041c\u0438\u0430\u043d\u0434\u043e\u0430\u0431"
    ],
    "name:swe_x_preferred":[
        "Miandoab"
    ],
    "name:tgk_x_preferred":[
        "\u041c\u0438\u0451\u043d\u0434\u0443\u043e\u0431"
    ],
    "name:tur_x_preferred":[
        "Miyanduab"
    ],
    "name:und_x_variant":[
        "Miy\u0101nd\u016b\u0101b"
    ],
    "name:urd_x_preferred":[
        "\u0645\u06cc\u0627\u0646\u062f\u0648\u0622\u0628"
    ],
    "name:zho_x_preferred":[
        "\u7c73\u63da\u9053\u963f\u535c"
    ],
    "qs:gn_country":"IR",
    "qs:gn_fcode":"PPL",
    "qs:gn_pop":132819,
    "qs:name":"Meyandoab",
    "qs:name_adm0":"Iran",
    "qs:name_adm1":"Azarbayjan-e Gharbi",
    "qs:photos":0,
    "qs:photos_1k":0,
    "qs:photos_9k":1,
    "qs:photos_9r":1,
    "qs:photos_all":1,
    "qs:photos_sr":0,
    "qs:placetype":"Town",
    "qs:pop_sr":"9",
    "qs:woe_adm0":23424851,
    "wd:wordcount":441,
    "wof:name":"Meyandoab",
    "wof:placetype":"locality",
    "wof:population":132819
},
  "geometry": {"coordinates":[46.1027,36.9694],"type":"Point"}
}