{
  "type": "Feature",
  "properties": {
    "gn:admin1_code":"15.0",
    "gn:asciiname":"Shenaneh",
    "gn:country_code":"IR",
    "gn:dem":10,
    "gn:feature_class":"P",
    "gn:feature_code":"PPL",
    "gn:name":"Shen\u0101neh",
    "gn:population":0,
    "gn:timezone":"Asia/Tehran",
    "iso:country":"IR",
    "name:fas_x_preferred":[
        "\u0634\u0646\u0627\u0646\u0647"
    ],
    "name:fas_x_variant":[
        "Shen\u0101neh"
    ],
    "wof:name":"Shenaneh",
    "wof:placetype":"locality"
},
  "geometry": {"coordinates":[48.0573,31.3058],"type":"Point"}
}