{
  "type": "Feature",
  "properties": {
    "gn:admin1_code":"38",
    "gn:asciiname":"Cheshmeh-ye Gholam`ali",
    "gn:country_code":"IR",
    "gn:dem":1664,
    "gn:elevation":"0.0",
    "gn:feature_class":"P",
    "gn:feature_code":"PPL",
    "gn:name":"Cheshmeh-ye Ghol\u0101m\u2018al\u012b",
    "gn:population":0,
    "gn:timezone":"Asia/Tehran",
    "iso:country":"IR",
    "name:fas_x_preferred":[
        "\u0686\u0634\u0645\u0647 \u063a\u0644\u0627\u0645\u0639\u0644\u06cc"
    ],
    "name:fas_x_variant":[
        "Cheshmeh-ye Ghol\u0101m\u2018al\u012b"
    ],
    "wof:name":"Cheshmeh-ye Gholam`ali",
    "wof:placetype":"locality"
},
  "geometry": {"coordinates":[49.824,36.40756],"type":"Point"}
}