{
  "type": "Feature",
  "properties": {
    "gn:admin1_code":"8.0",
    "gn:asciiname":"Kolzeh Khvar",
    "gn:country_code":"IR",
    "gn:dem":1512,
    "gn:feature_class":"P",
    "gn:feature_code":"PPL",
    "gn:name":"Kolzeh Khv\u0101r",
    "gn:population":0,
    "gn:timezone":"Asia/Tehran",
    "iso:country":"IR",
    "name:fas_x_preferred":[
        "\u06a9\u0644\u0632\u0647 \u062e\u0648\u0627\u0631"
    ],
    "name:fas_x_variant":[
        "\u06af\u0646\u0632\u0647 \u062e\u0648\u0627\u0631"
    ],
    "name:und_x_variant":[
        "Kolzeh Khv\u0101r",
        "Gonzeh Khv\u0101r"
    ],
    "wof:name":"Kolzeh Khvar",
    "wof:placetype":"locality"
},
  "geometry": {"coordinates":[48.79364,37.48244],"type":"Point"}
}