{
  "type": "Feature",
  "properties": {
    "gn:admin1_code":"35.0",
    "gn:asciiname":"Eshkardasht",
    "gn:country_code":"IR",
    "gn:dem":25,
    "gn:feature_class":"P",
    "gn:feature_code":"PPL",
    "gn:name":"Eshk\u0101rdasht",
    "gn:population":0,
    "gn:timezone":"Asia/Tehran",
    "iso:country":"IR",
    "name:fas_x_preferred":[
        "Eshk\u0101rdasht"
    ],
    "name:fas_x_variant":[
        "\u0627\u0634\u06a9\u0627\u0631 \u062f\u0634\u062a"
    ],
    "wof:name":"Eshkardasht",
    "wof:placetype":"locality"
},
  "geometry": {"coordinates":[51.44185,36.64032],"type":"Point"}
}