{
  "type": "Feature",
  "properties": {
    "gn:admin1_code":"1.0",
    "gn:asciiname":"Shahrak-e Rabt",
    "gn:country_code":"IR",
    "gn:dem":1156,
    "gn:feature_class":"P",
    "gn:feature_code":"PPL",
    "gn:name":"Shahrak-e Rab\u0163",
    "gn:population":0,
    "gn:timezone":"Asia/Tehran",
    "iso:country":"IR",
    "name:fas_x_preferred":[
        "\u0634\u0647\u0631\u06a9 \u0631\u0628\u0637"
    ],
    "name:fas_x_variant":[
        "Shahrak-e Rab\u0163"
    ],
    "wof:name":"Shahrak-e Rabt",
    "wof:placetype":"locality"
},
  "geometry": {"coordinates":[45.5493,36.2091],"type":"Point"}
}