{
  "type": "Feature",
  "properties": {
    "gn:admin1_code":"8.0",
    "gn:asciiname":"Safalak",
    "gn:country_code":"IR",
    "gn:dem":16,
    "gn:feature_class":"P",
    "gn:feature_code":"PPL",
    "gn:name":"Saf\u0101lak",
    "gn:population":0,
    "gn:timezone":"Asia/Tehran",
    "iso:country":"IR",
    "name:fas_x_preferred":[
        "\u0633\u0641\u0627\u0644\u06a9"
    ],
    "name:und_x_variant":[
        "Saf\u0101lak"
    ],
    "wof:name":"Safalak",
    "wof:placetype":"locality"
},
  "geometry": {"coordinates":[49.84377,37.17817],"type":"Point"}
}