{
  "type": "Feature",
  "properties": {
    "gn:admin1_code":"28",
    "gn:asciiname":"Koluchan",
    "gn:country_code":"IR",
    "gn:dem":1780,
    "gn:feature_class":"P",
    "gn:feature_code":"PPL",
    "gn:name":"Kol\u016bch\u0101n",
    "gn:population":0,
    "gn:timezone":"Asia/Tehran",
    "iso:country":"IR",
    "name:ara_x_preferred":[
        "\u0643\u0644\u0648\u062a\u0634\u0627\u0646"
    ],
    "name:fas_x_preferred":[
        "Kol\u016bch\u0101n"
    ],
    "name:fas_x_variant":[
        "\u06a9\u0644\u0648\u0686\u0627\u0646"
    ],
    "name:und_x_variant":[
        "Kal\u016bch\u0101n",
        "Kel\u016bch\u0101n",
        "Kaloochan"
    ],
    "wof:name":"Koluchan",
    "wof:placetype":"locality"
},
  "geometry": {"coordinates":[50.36378,33.50373],"type":"Point"}
}