{
  "type": "Feature",
  "properties": {
    "gn:admin1_code":"41.0",
    "gn:asciiname":"`Aliabad",
    "gn:country_code":"IR",
    "gn:dem":1282,
    "gn:feature_class":"P",
    "gn:feature_code":"PPL",
    "gn:name":"\u2018Al\u012b\u0101b\u0101d",
    "gn:population":0,
    "gn:timezone":"Asia/Tehran",
    "iso:country":"IR",
    "name:fas_x_preferred":[
        "\u0639\u0644\u06cc \u0622\u0628\u0627\u062f"
    ],
    "name:fas_x_variant":[
        "\u2018Al\u012b\u0101b\u0101d"
    ],
    "wof:name":"`Aliabad",
    "wof:placetype":"locality"
},
  "geometry": {"coordinates":[60.23111,32.77641],"type":"Point"}
}