{
  "type": "Feature",
  "properties": {
    "gn:admin1_code":"1",
    "gn:asciiname":"Tuli",
    "gn:country_code":"IR",
    "gn:dem":1774,
    "gn:feature_class":"P",
    "gn:feature_code":"PPL",
    "gn:name":"T\u016bl\u012b",
    "gn:population":0,
    "gn:timezone":"Asia/Tehran",
    "iso:country":"IR",
    "name:bar_x_preferred":[
        "Tuli"
    ],
    "name:ceb_x_preferred":[
        "Tuli"
    ],
    "name:fas_x_preferred":[
        "\u062a\u0648\u0644\u06cc"
    ],
    "name:fas_x_variant":[
        "T\u016bl\u012b",
        "\u062a\u064e\u0644\u0648"
    ],
    "name:fra_x_preferred":[
        "Tuli"
    ],
    "name:swe_x_preferred":[
        "Tuli"
    ],
    "name:und_x_variant":[
        "Tal\u016b"
    ],
    "wof:name":"Tuli",
    "wof:placetype":"locality"
},
  "geometry": {"coordinates":[44.7877,37.4992],"type":"Point"}
}