{
  "type": "Feature",
  "properties": {
    "gn:admin1_code":"33",
    "gn:asciiname":"Shabana",
    "gn:country_code":"IR",
    "gn:dem":1656,
    "gn:feature_class":"P",
    "gn:feature_code":"PPL",
    "gn:name":"Shab\u0101n\u0101",
    "gn:population":0,
    "gn:timezone":"Asia/Tehran",
    "iso:country":"IR",
    "name:fas_x_preferred":[
        "\u0634\u0628\u0627\u0646\u0627"
    ],
    "name:fas_x_variant":[
        "\u0686\u0628\u0627\u0646\u0644\u0648"
    ],
    "name:und_x_variant":[
        "Shab\u0101n\u0101",
        "Chab\u0101nal\u016b"
    ],
    "wof:name":"Shabana",
    "wof:placetype":"locality"
},
  "geometry": {"coordinates":[46.8385,37.2905],"type":"Point"}
}