{
  "type": "Feature",
  "properties": {
    "gn:admin1_code":"7",
    "gn:asciiname":"Emamzadeh Abu ol Hasan",
    "gn:country_code":"IR",
    "gn:dem":1123,
    "gn:feature_class":"P",
    "gn:feature_code":"PPL",
    "gn:name":"Em\u0101mz\u0101deh Ab\u016b ol \u1e28asan",
    "gn:population":0,
    "gn:timezone":"Asia/Tehran",
    "iso:country":"IR",
    "name:fas_x_preferred":[
        "Em\u0101mz\u0101deh Ab\u016b ol \u1e28asan"
    ],
    "name:fas_x_variant":[
        "P\u012br Ab\u016b ol \u1e28asan",
        "\u0627\u0645\u0627\u0645\u0632\u0627\u062f\u0647 \u0627\u0628\u0648 \u0627\u0644\u062d\u0633\u0646",
        "\u0627\u0645\u0627\u0645\u0632\u0627\u062f\u0647 \u067e\u06cc\u0631\u0627\u0628\u0648\u0627\u0644\u062d\u0633\u0646"
    ],
    "name:msa_x_preferred":[
        "Emamzadeh Pir Abu ol Hasan"
    ],
    "name:und_x_variant":[
        "Sh\u0101hz\u0101deh Ab\u016b ol \u1e28asan",
        "P\u012br Abul Hasan",
        "Sheykh Ab\u016b ol \u1e28asan"
    ],
    "wof:name":"Emamzadeh Abu ol Hasan",
    "wof:placetype":"locality"
},
  "geometry": {"coordinates":[51.78145,29.67244],"type":"Point"}
}