{
  "type": "Feature",
  "properties": {
    "gn:admin1_code":"32",
    "gn:asciiname":"Arallu-ye Bozorg",
    "gn:country_code":"IR",
    "gn:dem":1397,
    "gn:feature_class":"P",
    "gn:feature_code":"PPL",
    "gn:name":"\u0100r\u0101ll\u016b-ye Bozorg",
    "gn:population":0,
    "gn:timezone":"Asia/Tehran",
    "iso:country":"IR",
    "name:fas_x_preferred":[
        "\u0622\u0631\u0627\u0644\u0651\u0648\u06cc \u0628\u064f\u0632\u064f\u0631\u06af"
    ],
    "name:fas_x_variant":[
        "\u0622\u0631\u0627\u0644\u0644\u0648\u06cc \u0628\u0632\u0631\u06af",
        "B\u012blah Daraq-e F\u016bl\u0101dl\u016b",
        "B\u012blah Daraq",
        "\u0628\u064a\u0644\u064e\u0647 \u062f\u064e\u0631\u064e\u0642\u0650 \u0641\u0648\u0644\u0627\u062f\u0644\u0648",
        "\u0628\u064a\u0644\u064e\u0647 \u062f\u064e\u0631\u064e\u0642",
        "\u0100r\u0101ll\u016b-ye Bozorg"
    ],
    "wof:name":"Arallu-ye Bozorg",
    "wof:placetype":"locality"
},
  "geometry": {"coordinates":[48.424,38.1444],"type":"Point"}
}