{
  "type": "Feature",
  "properties": {
    "gn:admin1_code":"28.0",
    "gn:asciiname":"Raran",
    "gn:country_code":"IR",
    "gn:dem":1558,
    "gn:feature_class":"P",
    "gn:feature_code":"PPL",
    "gn:name":"R\u0101r\u0101n",
    "gn:population":0,
    "gn:timezone":"Asia/Tehran",
    "iso:country":"IR",
    "name:fas_x_preferred":[
        "\u0631\u0627\u0631\u0627\u0646 \u0642\u0647\u0627\u0628"
    ],
    "name:fas_x_variant":[
        "\u0631\u0627\u0631\u0627\u0646"
    ],
    "name:und_x_variant":[
        "R\u0101d\u0101n",
        "R\u0101r\u0101n Qah\u0101b",
        "R\u0101r\u0101n"
    ],
    "wof:name":"Raran",
    "wof:placetype":"locality"
},
  "geometry": {"coordinates":[51.75334,32.67634],"type":"Point"}
}