{
  "type": "Feature",
  "properties": {
    "gn:admin1_code":"8",
    "gn:asciiname":"Khesht-e Masjed",
    "gn:country_code":"IR",
    "gn:dem":-3,
    "gn:feature_class":"P",
    "gn:feature_code":"PPL",
    "gn:name":"Khesht-e Masjed",
    "gn:population":0,
    "gn:timezone":"Asia/Tehran",
    "iso:country":"IR",
    "name:fas_x_preferred":[
        "\u062e\u0634\u062a \u0645\u0633\u062c\u062f"
    ],
    "name:fas_x_variant":[
        "\u0628\u0627\u0644\u0627 \u0645\u062d\u0644\u0647 \u062e\u0634\u062a \u0645\u0633\u062c\u062f",
        "\u0628\u0627\u0644\u0627 \u0645\u062d\u0644\u0647"
    ],
    "name:und_x_variant":[
        "Khachta-Mechet",
        "Khesht Masjed",
        "Khesht Masjed Kooch Esfahan",
        "Khesht-e Masjed",
        "\u062e\u0634\u062a \u0645\u0633\u062c\u062f",
        "B\u0101l\u0101 Ma\u1e29alleh-ye Khesht-e Masjed",
        "B\u0101l\u0101 Ma\u1e29alleh"
    ],
    "wof:name":"Khesht-e Masjed",
    "wof:placetype":"locality"
},
  "geometry": {"coordinates":[49.74949,37.31564],"type":"Point"}
}