{
  "type": "Feature",
  "properties": {
    "gn:admin1_code":"26.0",
    "gn:asciiname":"Aru",
    "gn:country_code":"IR",
    "gn:dem":2341,
    "gn:feature_class":"P",
    "gn:feature_code":"PPL",
    "gn:name":"\u0100r\u016b",
    "gn:population":0,
    "gn:timezone":"Asia/Tehran",
    "iso:country":"IR",
    "name:ara_x_preferred":[
        "\u0623\u0631\u0648"
    ],
    "name:fas_x_preferred":[
        "\u0622\u0631\u0648"
    ],
    "name:fas_x_variant":[
        "\u0627\u064e\u0631\u0648\u062f",
        "\u0100r\u016b"
    ],
    "name:und_x_variant":[
        "Ar\u016bd"
    ],
    "wof:name":"Aru",
    "wof:placetype":"locality"
},
  "geometry": {"coordinates":[52.40357,35.66999000000001],"type":"Point"}
}