{
  "type": "Feature",
  "properties": {
    "gn:admin1_code":"35.0",
    "gn:asciiname":"Kharman Kola",
    "gn:country_code":"IR",
    "gn:dem":74,
    "gn:feature_class":"P",
    "gn:feature_code":"PPL",
    "gn:name":"Kharman Kol\u0101",
    "gn:population":0,
    "gn:timezone":"Asia/Tehran",
    "iso:country":"IR",
    "name:ara_x_preferred":[
        "\u062e\u0631\u0645\u0646 \u06a9\u0644\u0627"
    ],
    "name:ceb_x_preferred":[
        "Kharman Kol\u0101"
    ],
    "name:fas_x_preferred":[
        "\u062e\u0631\u0645\u0646 \u0643\u0644\u0627"
    ],
    "name:fas_x_variant":[
        "Kharman Kol\u0101",
        "\u062e\u0631\u0645\u0646\u200c\u06a9\u0644\u0627"
    ],
    "name:swe_x_preferred":[
        "Kharman Kol\u0101"
    ],
    "name:ukr_x_preferred":[
        "\u0425\u0430\u0440\u043c\u0430\u043d-\u041a\u043e\u043b\u0430"
    ],
    "wof:name":"Kharman Kola",
    "wof:placetype":"locality"
},
  "geometry": {"coordinates":[52.45339,36.41727],"type":"Point"}
}