{
  "type": "Feature",
  "properties": {
    "gn:admin1_code":"8",
    "gn:asciiname":"Gorbeh Kucheh",
    "gn:country_code":"IR",
    "gn:dem":20,
    "gn:feature_class":"P",
    "gn:feature_code":"PPL",
    "gn:name":"Gorbeh K\u016bcheh",
    "gn:population":0,
    "gn:timezone":"Asia/Tehran",
    "iso:country":"IR",
    "name:fas_x_preferred":[
        "\u06af\u0631\u0628\u0647 \u06a9\u0648\u0686\u0647"
    ],
    "name:fas_x_variant":[
        "Gorbeh K\u016bjeh",
        "Gorbeh K\u016bcheh"
    ],
    "wof:name":"Gorbeh Kucheh",
    "wof:placetype":"locality"
},
  "geometry": {"coordinates":[49.32932,37.24106],"type":"Point"}
}