{
  "type": "Feature",
  "properties": {
    "gn:admin1_code":"3",
    "gn:asciiname":"Konarak-e `Olya",
    "gn:country_code":"IR",
    "gn:dem":2218,
    "gn:feature_class":"P",
    "gn:feature_code":"PPL",
    "gn:name":"Konarak-e \u2018Oly\u0101",
    "gn:population":0,
    "gn:timezone":"Asia/Tehran",
    "iso:country":"IR",
    "name:ara_x_preferred":[
        "\u0643\u0646\u0627\u0631\u0643 \u0628\u0627\u0644\u0627"
    ],
    "name:ceb_x_preferred":[
        "Konarak-e \u2018Oly\u0101"
    ],
    "name:fas_x_preferred":[
        "Konarak-e B\u0101l\u0101"
    ],
    "name:fas_x_variant":[
        "\u0643\u064f\u0646\u0631\u064f\u0643 \u0628\u0627\u0644\u0627",
        "Konarak-e \u2018Oly\u0101",
        "\u0643\u064e\u0646\u0627\u0631\u064e\u0643\u0650 \u0628\u0627\u0644\u0627",
        "\u0643\u064f\u0646\u064e\u0631\u064e\u0643\u0650 \u0628\u0627\u0644\u0627",
        "\u06a9\u0646\u0631\u0643 \u0639\u0644\u06cc\u0627",
        "\u06a9\u0646\u0627\u0631\u06a9 \u0628\u0627\u0644\u0627"
    ],
    "name:msa_x_preferred":[
        "Konarak-e Bala"
    ],
    "name:swe_x_preferred":[
        "Konarak-e \u2018Oly\u0101"
    ],
    "name:und_x_variant":[
        "Kan\u0101rak-e B\u0101l\u0101",
        "Konrok B\u0101l\u0101"
    ],
    "wof:name":"Konarak-e `Olya",
    "wof:placetype":"locality"
},
  "geometry": {"coordinates":[51.14928,31.79901],"type":"Point"}
}