{
  "type": "Feature",
  "properties": {
    "gn:admin1_code":"9",
    "gn:asciiname":"Khanjarabad",
    "gn:country_code":"IR",
    "gn:dem":1898,
    "gn:feature_class":"P",
    "gn:feature_code":"PPL",
    "gn:name":"Khanjar\u0101b\u0101d",
    "gn:population":0,
    "gn:timezone":"Asia/Tehran",
    "iso:country":"IR",
    "name:fas_x_preferred":[
        "\u062e\u0646\u062c\u0631 \u0622\u0628\u0627\u062f"
    ],
    "name:fas_x_variant":[
        "Khanjar\u0101b\u0101d",
        "\u062e\u0646\u062c\u0631\u0622\u0628\u0627\u062f"
    ],
    "name:msa_x_preferred":[
        "Khanjarabad"
    ],
    "wof:name":"Khanjarabad",
    "wof:placetype":"locality"
},
  "geometry": {"coordinates":[48.88647,35.44517000000001],"type":"Point"}
}