{
  "type": "Feature",
  "properties": {
    "gn:admin1_code":"33",
    "gn:asciiname":"Kordan",
    "gn:country_code":"IR",
    "gn:dem":1363,
    "gn:feature_class":"P",
    "gn:feature_code":"PPL",
    "gn:name":"Kord\u0101n",
    "gn:population":0,
    "gn:timezone":"Asia/Tehran",
    "iso:country":"IR",
    "name:fas_x_preferred":[
        "Kord\u0101n"
    ],
    "name:fas_x_variant":[
        "\u06a9\u0648\u0631\u062f\u0627\u0646"
    ],
    "wof:name":"Kordan",
    "wof:placetype":"locality"
},
  "geometry": {"coordinates":[45.96667,37.75],"type":"Point"}
}