{
  "type": "Feature",
  "properties": {
    "gn:admin1_code":"42",
    "gn:asciiname":"Dasht Khaneh",
    "gn:country_code":"IR",
    "gn:dem":1251,
    "gn:feature_class":"P",
    "gn:feature_code":"PPL",
    "gn:name":"Dasht Kh\u0101neh",
    "gn:population":0,
    "gn:timezone":"Asia/Tehran",
    "iso:country":"IR",
    "name:fas_x_preferred":[
        "D\u0101shkh\u0101neh"
    ],
    "name:fas_x_variant":[
        "D\u0101sh Kh\u0101neh",
        "\u062f\u0627\u0634\u062e\u0627\u0646\u0647",
        "\u062f\u0634\u062a \u062e\u0627\u0646\u0647"
    ],
    "name:und_x_variant":[
        "\u062f\u0627\u0634\u062e\u0627\u0646\u0647",
        "Dasht Kh\u0101neh"
    ],
    "wof:name":"Dasht Khaneh",
    "wof:placetype":"locality"
},
  "geometry": {"coordinates":[57.87285,36.43418],"type":"Point"}
}