{
  "type": "Feature",
  "properties": {
    "gn:admin1_code":"33",
    "gn:asciiname":"Dizaj-e Leyli Khani",
    "gn:country_code":"IR",
    "gn:dem":1826,
    "gn:feature_class":"P",
    "gn:feature_code":"PPL",
    "gn:name":"D\u012bzaj-e Leyl\u012b Kh\u0101n\u012b",
    "gn:population":0,
    "gn:timezone":"Asia/Tehran",
    "iso:country":"IR",
    "name:fas_x_preferred":[
        "\u062f\u06cc\u0632\u062c \u0644\u06cc\u0644\u06cc \u062e\u0627\u0646\u06cc"
    ],
    "name:fas_x_variant":[
        "D\u012bzaj-eLeyl\u012bkh\u0101n",
        "D\u012bzaj-e Leyl\u012b Khv\u0101n\u012b",
        "D\u012bzaj-e Leyl\u012b Kh\u0101n\u012b",
        "\u062f\u064a\u0632\u062c \u0644\u064a\u0644\u06cc \u062e\u0648\u0627\u0646\u06cc"
    ],
    "wof:name":"Dizaj-e Leyli Khani",
    "wof:placetype":"locality"
},
  "geometry": {"coordinates":[46.49734,37.96988],"type":"Point"}
}