{
  "type": "Feature",
  "properties": {
    "gn:admin1_code":"15.0",
    "gn:asciiname":"Seyyed Hamadi-ye Yek",
    "gn:country_code":"IR",
    "gn:dem":36,
    "gn:feature_class":"P",
    "gn:feature_code":"PPL",
    "gn:name":"Seyyed \u1e28am\u0101d\u012b-ye Yek",
    "gn:population":0,
    "gn:timezone":"Asia/Tehran",
    "iso:country":"IR",
    "name:ceb_x_preferred":[
        "Seyyed \u1e28am\u0101d\u012b"
    ],
    "name:fas_x_preferred":[
        "\u0633\u06cc\u0651\u062f \u062d\u0645\u0627\u062f\u06cc"
    ],
    "name:fas_x_variant":[
        "Seyyed \u1e28am\u0101d\u012b",
        "\u0633\u06cc\u062f \u062d\u0645\u0627\u062f\u06cc \u06cc\u06a9",
        "\u0633\u06cc\u062f \u062d\u0645\u0627\u062f\u06cc"
    ],
    "name:swe_x_preferred":[
        "Seyyed \u1e28am\u0101d\u012b"
    ],
    "name:und_x_variant":[
        "Seyyed \u1e28am\u0101d\u012b-ye Yek"
    ],
    "wof:name":"Seyyed Hamadi-ye Yek",
    "wof:placetype":"locality"
},
  "geometry": {"coordinates":[48.43667,31.80499],"type":"Point"}
}