{
  "type": "Feature",
  "properties": {
    "gn:admin1_code":"23",
    "gn:asciiname":"Shaterabad",
    "gn:country_code":"IR",
    "gn:dem":1847,
    "gn:feature_class":"P",
    "gn:feature_code":"PPL",
    "gn:name":"Sh\u0101\u0163er\u0101b\u0101d",
    "gn:population":0,
    "gn:timezone":"Asia/Tehran",
    "iso:country":"IR",
    "name:fas_x_preferred":[
        "\u0634\u0627\u0637\u0631 \u0622\u0628\u0627\u062f"
    ],
    "name:fas_x_variant":[
        "Sh\u0101\u0163er\u0101b\u0101d"
    ],
    "wof:name":"Shaterabad",
    "wof:placetype":"locality"
},
  "geometry": {"coordinates":[47.9423,34.0447],"type":"Point"}
}