{
  "type": "Feature",
  "properties": {
    "gn:admin1_code":"9",
    "gn:asciiname":"Qelij Baghi",
    "gn:country_code":"IR",
    "gn:dem":1999,
    "gn:feature_class":"P",
    "gn:feature_code":"PPL",
    "gn:name":"Qel\u012bj B\u0101gh\u012b",
    "gn:population":0,
    "gn:timezone":"Asia/Tehran",
    "iso:country":"IR",
    "name:fas_x_preferred":[
        "\u0642\u0644\u064a\u0686 \u0628\u0627\u063a\u06cc"
    ],
    "name:fas_x_variant":[
        "Qel\u012bj B\u0101gh\u012b",
        "Qel\u012bch B\u0101gh\u012b",
        "\u0642\u0644\u06cc\u062c \u0628\u0627\u063a\u06cc",
        "\u0642\u0644\u0634 \u0628\u0627\u063a\u06cc"
    ],
    "name:und_x_variant":[
        "Kalashb\u0101gh",
        "Ghelich Baghi",
        "Qalash B\u0101gh\u012b"
    ],
    "wof:name":"Qelij Baghi",
    "wof:placetype":"locality"
},
  "geometry": {"coordinates":[48.26763,35.31292],"type":"Point"}
}