{
  "type": "Feature",
  "properties": {
    "gn:admin1_code":"42",
    "gn:asciiname":"Damkeh",
    "gn:country_code":"IR",
    "gn:dem":641,
    "gn:feature_class":"P",
    "gn:feature_code":"PPL",
    "gn:name":"Damkeh",
    "gn:population":0,
    "gn:timezone":"Asia/Tehran",
    "iso:country":"IR",
    "name:fas_x_preferred":[
        "\u062f\u0645\u06a9\u0647"
    ],
    "wof:name":"Damkeh",
    "wof:placetype":"locality"
},
  "geometry": {"coordinates":[59.08539,37.34749],"type":"Point"}
}