{
  "type": "Feature",
  "properties": {
    "gn:admin1_code":"29",
    "gn:asciiname":"Kharqan",
    "gn:country_code":"IR",
    "gn:dem":2504,
    "gn:feature_class":"P",
    "gn:feature_code":"PPL",
    "gn:name":"Kh\u0101rq\u0101n",
    "gn:population":0,
    "gn:timezone":"Asia/Tehran",
    "iso:country":"IR",
    "name:fas_x_preferred":[
        "\u062e\u0627\u0631\u0642\u0627\u0646"
    ],
    "name:fas_x_variant":[
        "Kh\u0101rq\u0101n"
    ],
    "wof:name":"Kharqan",
    "wof:placetype":"locality"
},
  "geometry": {"coordinates":[56.0985,29.7906],"type":"Point"}
}