{
  "type": "Feature",
  "properties": {
    "gn:admin1_code":"42.0",
    "gn:asciiname":"Vila Shahr",
    "gn:country_code":"IR",
    "gn:dem":1176,
    "gn:feature_class":"P",
    "gn:feature_code":"PPL",
    "gn:name":"V\u012bl\u0101 Shahr",
    "gn:population":0,
    "gn:timezone":"Asia/Tehran",
    "iso:country":"IR",
    "name:fas_x_preferred":[
        "\u0648\u064a\u0644\u0627 \u0634\u0647\u0631"
    ],
    "name:und_x_variant":[
        "V\u012bl\u0101 Shahr"
    ],
    "wof:name":"Vila Shahr",
    "wof:placetype":"locality"
},
  "geometry": {"coordinates":[59.43741,36.3381],"type":"Point"}
}