{
  "type": "Feature",
  "properties": {
    "gn:admin1_code":"11",
    "gn:asciiname":"Ab Damil",
    "gn:country_code":"IR",
    "gn:dem":1093,
    "gn:feature_class":"P",
    "gn:feature_code":"PPL",
    "gn:name":"\u0100b Dam\u012bl",
    "gn:population":0,
    "gn:timezone":"Asia/Tehran",
    "iso:country":"IR",
    "name:fas_x_preferred":[
        "\u0622\u0628 \u062f\u0645\u06cc\u0644"
    ],
    "name:fas_x_variant":[
        "\u0100b Dam\u012bl"
    ],
    "name:msa_x_preferred":[
        "Ab Damil"
    ],
    "name:urd_x_preferred":[
        "\u0622\u0628 \u062f\u0645\u06cc\u0644"
    ],
    "wof:name":"Ab Damil",
    "wof:placetype":"locality"
},
  "geometry": {"coordinates":[56.8969,27.9945],"type":"Point"}
}