{
  "type": "Feature",
  "properties": {
    "gn:admin1_code":"1.0",
    "gn:asciiname":"Keshtar",
    "gn:country_code":"IR",
    "gn:dem":1919,
    "gn:feature_class":"P",
    "gn:feature_code":"PPL",
    "gn:name":"Kesht\u0101r",
    "gn:population":0,
    "gn:timezone":"Asia/Tehran",
    "iso:country":"IR",
    "name:fas_x_preferred":[
        "\u06a9\u0634\u062a\u0627\u0631"
    ],
    "name:fas_x_variant":[
        "Kesht\u0101r"
    ],
    "wof:name":"Keshtar",
    "wof:placetype":"locality"
},
  "geometry": {"coordinates":[44.2716,39.3184],"type":"Point"}
}