{
  "type": "Feature",
  "properties": {
    "gn:admin1_code":"13",
    "gn:asciiname":"Shahmar-e Baba Morad",
    "gn:country_code":"IR",
    "gn:dem":1356,
    "gn:feature_class":"P",
    "gn:feature_code":"PPL",
    "gn:name":"Sh\u0101hm\u0101r-e B\u0101b\u0101 Mor\u0101d",
    "gn:population":0,
    "gn:timezone":"Asia/Tehran",
    "iso:country":"IR",
    "name:ara_x_preferred":[
        "\u0634\u0627\u0647\u200c\u0645\u0627\u0631 \u0628\u0627\u0628\u0627\u0645\u0631\u0627\u062f"
    ],
    "name:ceb_x_preferred":[
        "Sh\u0101hm\u0101r-e B\u0101b\u0101 Mor\u0101d"
    ],
    "name:fas_x_preferred":[
        "\u0634\u0627\u0647\u0645\u0627\u0631 \u0628\u0627\u0628\u0627 \u0645\u0631\u0627\u062f"
    ],
    "name:fas_x_variant":[
        "Sh\u0101hm\u0101r-e B\u0101b\u0101 Mor\u0101d",
        "\u0634\u0627\u0647\u200c\u0645\u0627\u0631 \u0628\u0627\u0628\u0627\u0645\u0631\u0627\u062f"
    ],
    "name:swe_x_preferred":[
        "Sh\u0101hm\u0101r-e B\u0101b\u0101 Mor\u0101d"
    ],
    "name:und_x_variant":[
        "Sheykh Morad-e Tofangch\u012b",
        "Sh\u0101hm\u0101r"
    ],
    "wof:name":"Shahmar-e Baba Morad",
    "wof:placetype":"locality"
},
  "geometry": {"coordinates":[46.4158,34.5095],"type":"Point"}
}