{
  "type": "Feature",
  "properties": {
    "gn:admin1_code":"33",
    "gn:asciiname":"Kalb Kandi",
    "gn:country_code":"IR",
    "gn:dem":1836,
    "gn:feature_class":"P",
    "gn:feature_code":"PPL",
    "gn:name":"Kalb Kand\u012b",
    "gn:population":0,
    "gn:timezone":"Asia/Tehran",
    "iso:country":"IR",
    "name:fas_x_preferred":[
        "\u06a9\u0644\u0628 \u06a9\u0646\u062f\u06cc"
    ],
    "name:fas_x_variant":[
        "Kalb Kand\u012b"
    ],
    "wof:name":"Kalb Kandi",
    "wof:placetype":"locality"
},
  "geometry": {"coordinates":[47.0628,37.2165],"type":"Point"}
}