{
  "type": "Feature",
  "properties": {
    "gn:admin1_code":"0",
    "gn:asciiname":"Mohammadlu",
    "gn:country_code":"IR",
    "gn:dem":1714,
    "gn:feature_class":"P",
    "gn:feature_code":"PPL",
    "gn:name":"Mo\u1e29ammadl\u016b",
    "gn:population":0,
    "gn:timezone":"Asia/Tehran",
    "iso:country":"IR",
    "name:fas_x_preferred":[
        "\u0645\u064f\u062d\u064e\u0645\u064e\u0651\u062f\u0644\u0648"
    ],
    "name:fas_x_variant":[
        "Mo\u1e29ammadl\u016b",
        "\u0645\u062d\u0645\u062f\u0644\u0648"
    ],
    "wof:name":"Mohammadlu",
    "wof:placetype":"locality"
},
  "geometry": {"coordinates":[48.08333,38.75],"type":"Point"}
}