{
  "type": "Feature",
  "properties": {
    "gn:admin1_code":"4.0",
    "gn:asciiname":"Bi Astuk",
    "gn:country_code":"IR",
    "gn:dem":145,
    "gn:feature_class":"P",
    "gn:feature_code":"PPL",
    "gn:name":"B\u012b \u0100st\u016bk",
    "gn:population":0,
    "gn:timezone":"Asia/Tehran",
    "iso:country":"IR",
    "name:fas_x_preferred":[
        "\u0628\u06cc \u0627\u0633\u062a\u0648\u06a9"
    ],
    "name:und_x_variant":[
        "B\u012b \u0100st\u016bk"
    ],
    "wof:name":"Bi Astuk",
    "wof:placetype":"locality"
},
  "geometry": {"coordinates":[60.60612,25.86888],"type":"Point"}
}