{
  "type": "Feature",
  "properties": {
    "gn:admin1_code":"7",
    "gn:asciiname":"Palangi",
    "gn:country_code":"IR",
    "gn:dem":1896,
    "gn:feature_class":"P",
    "gn:feature_code":"PPL",
    "gn:name":"Palang\u012b",
    "gn:population":0,
    "gn:timezone":"Asia/Tehran",
    "iso:country":"IR",
    "name:fas_x_preferred":[
        "\u067e\u0644\u0646\u06af\u06cc"
    ],
    "name:fas_x_variant":[
        "Palang\u012b"
    ],
    "name:msa_x_preferred":[
        "Palangi"
    ],
    "wof:name":"Palangi",
    "wof:placetype":"locality"
},
  "geometry": {"coordinates":[52.1866,30.2561],"type":"Point"}
}