{
  "type": "Feature",
  "properties": {
    "gn:admin1_code":"15",
    "gn:asciiname":"Par Surakh",
    "gn:country_code":"IR",
    "gn:dem":846,
    "gn:feature_class":"P",
    "gn:feature_code":"PPL",
    "gn:name":"Par S\u016br\u0101kh",
    "gn:population":0,
    "gn:timezone":"Asia/Tehran",
    "iso:country":"IR",
    "name:fas_x_preferred":[
        "Par S\u016br\u0101kh"
    ],
    "name:fas_x_variant":[
        "\u067e\u0631\u0633\u0648\u0631\u0627\u062e"
    ],
    "wof:name":"Par Surakh",
    "wof:placetype":"locality"
},
  "geometry": {"coordinates":[49.81667,31.68333],"type":"Point"}
}