{
  "type": "Feature",
  "properties": {
    "gn:admin1_code":"33",
    "gn:asciiname":"Quyjuq",
    "gn:country_code":"IR",
    "gn:dem":1647,
    "gn:feature_class":"P",
    "gn:feature_code":"PPL",
    "gn:name":"Q\u016byj\u016bq",
    "gn:population":0,
    "gn:timezone":"Asia/Tehran",
    "iso:country":"IR",
    "name:fas_x_preferred":[
        "\u0642\u0648\u06cc\u062c\u0648\u0642"
    ],
    "name:fas_x_variant":[
        "Q\u016by\u016bj\u016bq",
        "Q\u016byj\u016bq",
        "\u0642\u0648\u06cc\u0648\u062c\u06cc\u0642"
    ],
    "name:und_x_variant":[
        "Q\u016by\u016bj\u012bq"
    ],
    "wof:name":"Quyjuq",
    "wof:placetype":"locality"
},
  "geometry": {"coordinates":[46.8618,37.3005],"type":"Point"}
}