{
  "type": "Feature",
  "properties": {
    "gn:admin1_code":"23",
    "gn:asciiname":"Shiravand",
    "gn:country_code":"IR",
    "gn:dem":1221,
    "gn:feature_class":"P",
    "gn:feature_code":"PPL",
    "gn:name":"Sh\u012br\u0101vand",
    "gn:population":0,
    "gn:timezone":"Asia/Tehran",
    "iso:country":"IR",
    "name:fas_x_preferred":[
        "\u0634\u064a\u0631\u0627\u0648\u064e\u0646\u062f"
    ],
    "name:fas_x_variant":[
        "Sh\u012br\u0101vand"
    ],
    "wof:name":"Shiravand",
    "wof:placetype":"locality"
},
  "geometry": {"coordinates":[47.51667,33.48333],"type":"Point"}
}