{
  "type": "Feature",
  "properties": {
    "gn:admin1_code":"42.0",
    "gn:asciiname":"Khowshab",
    "gn:country_code":"IR",
    "gn:dem":1187,
    "gn:feature_class":"P",
    "gn:feature_code":"PPL",
    "gn:name":"Khowsh\u0101b",
    "gn:population":0,
    "gn:timezone":"Asia/Tehran",
    "iso:country":"IR",
    "name:fas_x_preferred":[
        "Khowsh\u0101b"
    ],
    "name:fas_x_variant":[
        "Kh\u016bsh\u0101b",
        "\u062e\u0648\u0634\u0627\u0628"
    ],
    "wof:name":"Khowshab",
    "wof:placetype":"locality"
},
  "geometry": {"coordinates":[57.99064,36.42512],"type":"Point"}
}