{
  "type": "Feature",
  "properties": {
    "gn:admin1_code":"11.0",
    "gn:asciiname":"Mazra`eh-ye Torbekestan",
    "gn:country_code":"IR",
    "gn:dem":400,
    "gn:feature_class":"P",
    "gn:feature_code":"PPLF",
    "gn:name":"Mazra\u2018eh-ye Torbekest\u0101n",
    "gn:population":0,
    "gn:timezone":"Asia/Tehran",
    "iso:country":"IR",
    "name:fas_x_preferred":[
        "\u0645\u0632\u0631\u0639\u0647 \u062a\u0631\u0628\u06a9\u0633\u062a\u0627\u0646"
    ],
    "name:und_x_variant":[
        "Mazra\u2018eh-ye Torbekest\u0101n"
    ],
    "wof:name":"Mazra`eh-ye Torbekestan",
    "wof:placetype":"locality"
},
  "geometry": {"coordinates":[55.80599,27.72379],"type":"Point"}
}