{
  "type": "Feature",
  "properties": {
    "gn:admin1_code":"23",
    "gn:asciiname":"Harshir-e Imani",
    "gn:country_code":"IR",
    "gn:dem":900,
    "gn:feature_class":"P",
    "gn:feature_code":"PPL",
    "gn:name":"Harsh\u012br-e \u012am\u0101n\u012b",
    "gn:population":0,
    "gn:timezone":"Asia/Tehran",
    "iso:country":"IR",
    "name:fas_x_preferred":[
        "\u0647\u064e\u0631\u0634\u064a\u0631\u0650 \u064a\u0645\u0627\u0646\u06cc"
    ],
    "name:fas_x_variant":[
        "Harsh\u012br-e \u012am\u0101n\u012b",
        "\u0647\u0631\u0634\u06cc\u0631\u0627\u06cc\u0645\u0627\u0646\u06cc"
    ],
    "wof:name":"Harshir-e Imani",
    "wof:placetype":"locality"
},
  "geometry": {"coordinates":[47.78333,33.16667],"type":"Point"}
}