{
  "type": "Feature",
  "properties": {
    "gn:admin1_code":"35",
    "gn:asciiname":"Valuja",
    "gn:country_code":"IR",
    "gn:dem":-14,
    "gn:feature_class":"P",
    "gn:feature_code":"PPL",
    "gn:name":"Val\u016bj\u0101",
    "gn:population":0,
    "gn:timezone":"Asia/Tehran",
    "iso:country":"IR",
    "name:fas_x_preferred":[
        "\u0648\u0644\u0648\u062c\u0627"
    ],
    "name:fas_x_variant":[
        "Val\u016bj\u0101"
    ],
    "wof:name":"Valuja",
    "wof:placetype":"locality"
},
  "geometry": {"coordinates":[53.17994,36.78273],"type":"Point"}
}