{
  "type": "Feature",
  "properties": {
    "gn:admin1_code":"4.0",
    "gn:asciiname":"Bahteni",
    "gn:cc2":"IR",
    "gn:country_code":"IR",
    "gn:dem":1025,
    "gn:feature_class":"P",
    "gn:feature_code":"PPL",
    "gn:name":"Bahten\u012b",
    "gn:population":0,
    "gn:timezone":"Asia/Tehran",
    "iso:country":"IR",
    "name:fas_x_preferred":[
        "Bahten\u012b"
    ],
    "name:und_x_variant":[
        "Behtan\u012b"
    ],
    "wof:name":"Bahteni",
    "wof:placetype":"locality"
},
  "geometry": {"coordinates":[62.25111,26.70111],"type":"Point"}
}