{
  "type": "Feature",
  "properties": {
    "gn:admin1_code":"13.0",
    "gn:asciiname":"Falvashan",
    "gn:country_code":"IR",
    "gn:dem":943,
    "gn:feature_class":"P",
    "gn:feature_code":"PPL",
    "gn:name":"F\u0101lv\u0101shan",
    "gn:population":0,
    "gn:timezone":"Asia/Tehran",
    "iso:country":"IR",
    "name:ara_x_preferred":[
        "\u0641\u0627\u0644\u0648\u0634\u0646"
    ],
    "name:fas_x_preferred":[
        "\u0641\u0627\u0644\u0648\u0627\u0634\u0646"
    ],
    "name:fas_x_variant":[
        "F\u0101lv\u0101shan",
        "\u0641\u0627\u0644\u0648\u0634\u0646"
    ],
    "wof:name":"Falvashan",
    "wof:placetype":"locality"
},
  "geometry": {"coordinates":[45.8958,34.09],"type":"Point"}
}