{
  "type": "Feature",
  "properties": {
    "gn:admin1_code":"42",
    "gn:asciiname":"Tappeh Mianak",
    "gn:country_code":"IR",
    "gn:dem":2046,
    "gn:feature_class":"P",
    "gn:feature_code":"PPL",
    "gn:name":"Tappeh M\u012b\u0101nak",
    "gn:population":0,
    "gn:timezone":"Asia/Tehran",
    "iso:country":"IR",
    "name:fas_x_preferred":[
        "Tappeh M\u012b\u0101nak"
    ],
    "wof:name":"Tappeh Mianak",
    "wof:placetype":"locality"
},
  "geometry": {"coordinates":[59.74056,33.29833],"type":"Point"}
}