{
  "type": "Feature",
  "properties": {
    "gn:admin1_code":"29.0",
    "gn:asciiname":"Mohammad Robati",
    "gn:country_code":"IR",
    "gn:dem":2004,
    "gn:feature_class":"P",
    "gn:feature_code":"PPLF",
    "gn:name":"Mo\u1e29ammad Rob\u0101\u0163\u012b",
    "gn:population":0,
    "gn:timezone":"Asia/Tehran",
    "iso:country":"IR",
    "name:fas_x_preferred":[
        "\u0645\u062d\u0645\u062f \u0631\u0628\u0627\u0637\u06cc"
    ],
    "name:und_x_variant":[
        "Mo\u1e29ammad Rob\u0101\u0163\u012b"
    ],
    "wof:name":"Mohammad Robati",
    "wof:placetype":"locality"
},
  "geometry": {"coordinates":[55.01355,30.28695],"type":"Point"}
}