{
  "type": "Feature",
  "properties": {
    "gn:admin1_code":"26",
    "gn:asciiname":"Shahrak-e Danesh",
    "gn:country_code":"IR",
    "gn:dem":1167,
    "gn:feature_class":"P",
    "gn:feature_code":"PPL",
    "gn:name":"Shahrak-e D\u0101nesh",
    "gn:population":0,
    "gn:timezone":"Asia/Tehran",
    "iso:country":"IR",
    "name:fas_x_preferred":[
        "\u0634\u0647\u0631\u06a9 \u062f\u0627\u0646\u0634"
    ],
    "name:fas_x_variant":[
        "\u0634\u0627\u0647 \u0622\u0628\u0627\u062f",
        "\u0634\u0627\u062f \u0622\u0628\u0627\u062f",
        "Shahrak-e D\u0101nesh"
    ],
    "name:und_x_variant":[
        "Sh\u0101h\u0101b\u0101d",
        "Sh\u0101d\u0101b\u0101d"
    ],
    "wof:name":"Shahrak-e Danesh",
    "wof:placetype":"locality"
},
  "geometry": {"coordinates":[51.1815,35.6947],"type":"Point"}
}