{
  "type": "Feature",
  "properties": {
    "gn:admin1_code":"32.0",
    "gn:asciiname":"`Ali Kamar",
    "gn:country_code":"IR",
    "gn:dem":1745,
    "gn:feature_class":"P",
    "gn:feature_code":"PPL",
    "gn:name":"\u2018Al\u012b Kamar",
    "gn:population":0,
    "gn:timezone":"Asia/Tehran",
    "iso:country":"IR",
    "name:fas_x_preferred":[
        "\u0639\u0644\u06cc \u06a9\u0645\u0631"
    ],
    "name:fas_x_variant":[
        "\u2018Al\u012b Kamar"
    ],
    "wof:name":"`Ali Kamar",
    "wof:placetype":"locality"
},
  "geometry": {"coordinates":[48.4808,38.5081],"type":"Point"}
}