{
  "type": "Feature",
  "properties": {
    "gn:admin1_code":"29.0",
    "gn:asciiname":"Dahaneh-ye Kuh Gisha",
    "gn:country_code":"IR",
    "gn:dem":646,
    "gn:feature_class":"P",
    "gn:feature_code":"PPLF",
    "gn:name":"Dahaneh-ye K\u016bh G\u012bsh\u0101",
    "gn:population":0,
    "gn:timezone":"Asia/Tehran",
    "iso:country":"IR",
    "name:fas_x_preferred":[
        "\u062f\u0647\u0646\u0647 \u06a9\u0648\u0647 \u06af\u06cc\u0634\u0627"
    ],
    "name:und_x_variant":[
        "Dahaneh-ye K\u016bh G\u012bsh\u0101"
    ],
    "wof:name":"Dahaneh-ye Kuh Gisha",
    "wof:placetype":"locality"
},
  "geometry": {"coordinates":[57.31311,28.06475],"type":"Point"}
}