{
  "type": "Feature",
  "properties": {
    "gn:admin1_code":"16.0",
    "gn:asciiname":"Kuh-e Samasun Jan",
    "gn:country_code":"IR",
    "gn:dem":2292,
    "gn:feature_class":"P",
    "gn:feature_code":"PPL",
    "gn:name":"K\u016bh-e Sam\u0101s\u016bn J\u0101n",
    "gn:population":0,
    "gn:timezone":"Asia/Tehran",
    "iso:country":"IR",
    "name:fas_x_preferred":[
        "Sam\u016br Sanj\u0101n"
    ],
    "name:fas_x_variant":[
        "\u06a9\u0648\u0647 \u0633\u0645\u0627\u0633\u0648\u0646 \u062c\u0627\u0646",
        "\u06a9\u0648\u0647 \u0633\u0645\u0648\u0631 \u0633\u0646\u062c\u0628\u0627\u0628",
        "\u06a9\u0644\u06a9\u0647"
    ],
    "name:und_x_variant":[
        "K\u016bh-e Sam\u0101s\u016bn J\u0101n",
        "K\u016bh-e Sam\u016br Sanjb\u0101b",
        "Kalkeh"
    ],
    "wof:name":"Kuh-e Samasun Jan",
    "wof:placetype":"locality"
},
  "geometry": {"coordinates":[47.01667,35.65],"type":"Point"}
}