{
  "type": "Feature",
  "properties": {
    "gn:admin1_code":"36",
    "gn:asciiname":"Owlang",
    "gn:country_code":"IR",
    "gn:dem":1864,
    "gn:feature_class":"P",
    "gn:feature_code":"PPL",
    "gn:name":"Owlang",
    "gn:population":0,
    "gn:timezone":"Asia/Tehran",
    "iso:country":"IR",
    "name:ara_x_preferred":[
        "\u0627\u0648\u0644\u0646\u063a"
    ],
    "name:azb_x_preferred":[
        "\u0627\u0648\u0644\u0646\u06af"
    ],
    "name:ceb_x_preferred":[
        "Owlang"
    ],
    "name:fas_x_preferred":[
        "\u0627\u0648\u0644\u0646\u06af"
    ],
    "name:und_x_variant":[
        "Ulan",
        "\u016alang"
    ],
    "wof:name":"Owlang",
    "wof:placetype":"locality"
},
  "geometry": {"coordinates":[48.73276,36.40602],"type":"Point"}
}