{
  "type": "Feature",
  "properties": {
    "gn:admin1_code":"29",
    "gn:asciiname":"Mazra`eh-ye Sharif",
    "gn:country_code":"IR",
    "gn:dem":1703,
    "gn:feature_class":"P",
    "gn:feature_code":"PPLF",
    "gn:name":"Mazra\u2018eh-ye Shar\u012bf",
    "gn:population":0,
    "gn:timezone":"Asia/Tehran",
    "iso:country":"IR",
    "name:fas_x_preferred":[
        "\u0634\u0647\u06cc\u062f \u0634\u0627\u0647\u0645\u0631\u0627\u062f\u06cc"
    ],
    "name:fas_x_variant":[
        "Shah\u012bd Sh\u0101hmor\u0101d\u012b",
        "\u0645\u0632\u0631\u0639\u0647 \u0634\u0631\u064a\u0641"
    ],
    "name:und_x_variant":[
        "Mazra\u2018eh-ye Shar\u012bf"
    ],
    "wof:name":"Mazra`eh-ye Sharif",
    "wof:placetype":"locality"
},
  "geometry": {"coordinates":[55.2882,29.4119],"type":"Point"}
}