{
  "type": "Feature",
  "properties": {
    "gn:admin1_code":"36",
    "gn:asciiname":"Uch Bolagh",
    "gn:country_code":"IR",
    "gn:dem":1794,
    "gn:feature_class":"P",
    "gn:feature_code":"PPL",
    "gn:name":"\u016ach Bol\u0101gh",
    "gn:population":0,
    "gn:timezone":"Asia/Tehran",
    "iso:country":"IR",
    "name:fas_x_preferred":[
        "\u0627\u0648\u0686 \u0628\u0644\u0627\u063a"
    ],
    "name:fas_x_variant":[
        "\u016ach Bol\u0101gh",
        "Owch Bol\u0101gh"
    ],
    "name:und_x_variant":[
        "Uch-Bulag",
        "\u016achb\u016bl\u0101gh",
        "Uchbul\u0101q"
    ],
    "wof:name":"Uch Bolagh",
    "wof:placetype":"locality"
},
  "geometry": {"coordinates":[48.24472,37.01178],"type":"Point"}
}