{
  "type": "Feature",
  "properties": {
    "gn:admin1_code":"15",
    "gn:asciiname":"Rashideh",
    "gn:country_code":"IR",
    "gn:dem":24,
    "gn:feature_class":"P",
    "gn:feature_code":"PPL",
    "gn:name":"Rash\u012bdeh",
    "gn:population":0,
    "gn:timezone":"Asia/Tehran",
    "iso:country":"IR",
    "name:fas_x_preferred":[
        "\u0631\u0634\u06cc\u062f\u0647"
    ],
    "name:fas_x_variant":[
        "Rash\u012bdeh"
    ],
    "name:und_x_variant":[
        "Rosheydeh",
        "Resh\u012bdeh"
    ],
    "wof:name":"Rashideh",
    "wof:placetype":"locality"
},
  "geometry": {"coordinates":[49.32773,30.92334],"type":"Point"}
}