{
  "type": "Feature",
  "properties": {
    "gn:admin1_code":"42",
    "gn:asciiname":"Qal`eh-ye Now-e Seyyeda",
    "gn:country_code":"IR",
    "gn:dem":1158,
    "gn:feature_class":"P",
    "gn:feature_code":"PPL",
    "gn:name":"Qal\u2018eh-ye Now-e Seyyed\u0101",
    "gn:population":0,
    "gn:timezone":"Asia/Tehran",
    "iso:country":"IR",
    "name:fas_x_preferred":[
        "\u0642\u0644\u0639\u0647 \u0646\u0648 \u0633\u06cc\u062f\u0647\u0627"
    ],
    "name:fas_x_variant":[
        "Qal\u2018eh Now-e Chambar\u0101n",
        "Qal\u2018eh Now-ye Seyyedh\u0101",
        "\u0642\u0644\u0639\u0647 \u0646\u0648\u0633\u06cc\u062f\u0627",
        "\u0642\u0644\u0639\u0647 \u0646\u0648"
    ],
    "name:und_x_variant":[
        "Q\u012bl\u0101neh",
        "Qal\u2018eh Now",
        "Ghil\u0101na",
        "Qal\u2018ehnow-e Seyyedha",
        "Qal\u2018eh-ye Now-e Seyyed\u0101"
    ],
    "wof:name":"Qal`eh-ye Now-e Seyyeda",
    "wof:placetype":"locality"
},
  "geometry": {"coordinates":[58.82267,36.13848],"type":"Point"}
}