{
  "type": "Feature",
  "properties": {
    "gn:admin1_code":"41.0",
    "gn:asciiname":"Darbelund",
    "gn:country_code":"IR",
    "gn:dem":1474,
    "gn:feature_class":"P",
    "gn:feature_code":"PPL",
    "gn:name":"Darbel\u016bnd",
    "gn:population":0,
    "gn:timezone":"Asia/Tehran",
    "iso:country":"IR",
    "name:fas_x_preferred":[
        "\u062f\u0631\u0628\u0644\u0648\u0646\u062f"
    ],
    "name:fas_x_variant":[
        "Darb-e L\u016bn",
        "Darbel\u016bnd"
    ],
    "wof:name":"Darbelund",
    "wof:placetype":"locality"
},
  "geometry": {"coordinates":[60.5562,32.4644],"type":"Point"}
}