{
  "type": "Feature",
  "properties": {
    "gn:admin1_code":"13",
    "gn:asciiname":"Sarbekuh",
    "gn:country_code":"IR",
    "gn:dem":1409,
    "gn:feature_class":"P",
    "gn:feature_code":"PPL",
    "gn:name":"Sarbek\u016bh",
    "gn:population":0,
    "gn:timezone":"Asia/Tehran",
    "iso:country":"IR",
    "name:ara_x_preferred":[
        "\u0633\u0631\u0628\u0643\u0648\u0629"
    ],
    "name:fas_x_preferred":[
        "\u0633\u0631\u0628\u06a9\u0648\u0647"
    ],
    "name:fas_x_variant":[
        "Sorbak\u016bh",
        "Sarbek\u016bh"
    ],
    "wof:name":"Sarbekuh",
    "wof:placetype":"locality"
},
  "geometry": {"coordinates":[46.708,33.9012],"type":"Point"}
}