{
  "type": "Feature",
  "properties": {
    "gn:admin1_code":"5",
    "gn:asciiname":"Sahrir",
    "gn:country_code":"IR",
    "gn:dem":1692,
    "gn:feature_class":"P",
    "gn:feature_code":"PPL",
    "gn:name":"Sahr\u012br",
    "gn:population":0,
    "gn:timezone":"Asia/Tehran",
    "iso:country":"IR",
    "name:fas_x_preferred":[
        "\u0633\u064e\u0647\u0631\u064a\u0631"
    ],
    "name:fas_x_variant":[
        "Sahr\u012br"
    ],
    "wof:name":"Sahrir",
    "wof:placetype":"locality"
},
  "geometry": {"coordinates":[51.37056,30.84417],"type":"Point"}
}