{
  "type": "Feature",
  "properties": {
    "gn:admin1_code":"1",
    "gn:asciiname":"Javanmard",
    "gn:country_code":"IR",
    "gn:dem":1635,
    "gn:feature_class":"P",
    "gn:feature_code":"PPL",
    "gn:name":"Jav\u0101nmard",
    "gn:population":0,
    "gn:timezone":"Asia/Tehran",
    "iso:country":"IR",
    "name:fas_x_preferred":[
        "\u062c\u0648\u0627\u0646\u0645\u0631\u062f"
    ],
    "name:fas_x_variant":[
        "Jav\u0101nmard"
    ],
    "wof:name":"Javanmard",
    "wof:placetype":"locality"
},
  "geometry": {"coordinates":[46.4167,36.5985],"type":"Point"}
}