{
  "type": "Feature",
  "properties": {
    "gn:admin1_code":"43",
    "gn:asciiname":"Hesari-ye Gazerani",
    "gn:country_code":"IR",
    "gn:dem":1346,
    "gn:feature_class":"P",
    "gn:feature_code":"PPL",
    "gn:name":"\u1e28e\u015f\u0101r\u012b-ye G\u0101zer\u0101n\u012b",
    "gn:population":0,
    "gn:timezone":"Asia/Tehran",
    "iso:country":"IR",
    "name:ara_x_preferred":[
        "\u062d\u0635\u0627\u0631\u064a \u063a\u0627\u0632\u0631\u0627\u0646\u064a"
    ],
    "name:ceb_x_preferred":[
        "\u1e28e\u015f\u0101r\u012b-ye G\u0101zer\u0101n\u012b"
    ],
    "name:fas_x_preferred":[
        "\u1e28e\u015f\u0101r\u012b-ye G\u0101zer\u0101n\u012b"
    ],
    "name:fas_x_variant":[
        "\u062d\u0635\u0627\u0631\u06cc \u06af\u0627\u0632\u0631\u0627\u0646\u06cc"
    ],
    "name:swe_x_preferred":[
        "\u1e28e\u015f\u0101r\u012b-ye G\u0101zer\u0101n\u012b"
    ],
    "name:und_x_variant":[
        "\u1e28e\u015f\u0101r\u012b",
        "\u1e28e\u015f\u0101r",
        "\u062d\u0635\u0627\u0631\u06cc \u06af\u0627\u0632\u0631\u0627\u0646\u06cc"
    ],
    "wof:name":"Hesari-ye Gazerani",
    "wof:placetype":"locality"
},
  "geometry": {"coordinates":[57.6964,36.91699000000001],"type":"Point"}
}