{
  "type": "Feature",
  "properties": {
    "gn:admin1_code":"1",
    "gn:asciiname":"Ashti Bolagh",
    "gn:country_code":"IR",
    "gn:dem":1697,
    "gn:feature_class":"P",
    "gn:feature_code":"PPL",
    "gn:name":"\u0100sht\u012b Bol\u0101gh",
    "gn:population":0,
    "gn:timezone":"Asia/Tehran",
    "iso:country":"IR",
    "name:fas_x_preferred":[
        "\u0622\u0634\u062a\u06cc \u0628\u0644\u0627\u063a"
    ],
    "name:fas_x_variant":[
        "\u0100sht\u012b Bol\u0101gh"
    ],
    "wof:name":"Ashti Bolagh",
    "wof:placetype":"locality"
},
  "geometry": {"coordinates":[46.66084,36.77708],"type":"Point"}
}