{
  "type": "Feature",
  "properties": {
    "gn:admin1_code":"11.0",
    "gn:asciiname":"Aqasin-e Pa'in",
    "gn:country_code":"IR",
    "gn:dem":563,
    "gn:feature_class":"P",
    "gn:feature_code":"PPL",
    "gn:name":"\u0100q\u0101s\u012bn-e P\u0101\u2019\u012bn",
    "gn:population":0,
    "gn:timezone":"Asia/Tehran",
    "iso:country":"IR",
    "name:ara_x_preferred":[
        "\u0623\u063a\u0627\u0633\u064a\u0646 \u0628\u0627\u064a\u064a\u0646"
    ],
    "name:fas_x_preferred":[
        "\u0622\u063a\u0627\u0633\u064a\u0646 \u067e\u0627\u0626\u064a\u0646"
    ],
    "name:fas_x_variant":[
        "\u0622\u0642\u0627\u0633\u064a\u0646 \u067e\u0627\u0626\u064a\u0646",
        "\u0100gh\u0101s\u012bn-e P\u0101\u2019\u012bn",
        "\u0100q\u0101s\u012bn-e P\u0101\u2019\u012bn",
        "\u0627\u063a\u0627\u0633\u06cc\u0646 \u067e\u0627\u06cc\u06cc\u0646"
    ],
    "name:msa_x_preferred":[
        "Aghasin-e Pain"
    ],
    "name:urd_x_preferred":[
        "\u0627\u0642\u0627\u0633\u06cc\u0646 \u067e\u0627\u0626\u06cc\u0646"
    ],
    "wof:name":"Aqasin-e Pa'in",
    "wof:placetype":"locality"
},
  "geometry": {"coordinates":[56.4558,27.696],"type":"Point"}
}