{
  "type": "Feature",
  "properties": {
    "gn:admin1_code":"7.0",
    "gn:asciiname":"Mahalleh-ye Deh-e Bala",
    "gn:country_code":"IR",
    "gn:dem":1268,
    "gn:feature_class":"P",
    "gn:feature_code":"PPL",
    "gn:name":"Ma\u1e29alleh-ye Deh-e B\u0101l\u0101",
    "gn:population":0,
    "gn:timezone":"Asia/Tehran",
    "iso:country":"IR",
    "name:fas_x_preferred":[
        "\u0645\u062d\u0644\u0647 \u062f\u0647 \u0628\u0627\u0644\u0627"
    ],
    "name:und_x_variant":[
        "Ma\u1e29alleh-ye Deh-e B\u0101l\u0101"
    ],
    "wof:name":"Mahalleh-ye Deh-e Bala",
    "wof:placetype":"locality"
},
  "geometry": {"coordinates":[53.93424,28.36888],"type":"Point"}
}