{
  "type": "Feature",
  "properties": {
    "gn:admin1_code":"1",
    "gn:asciiname":"Nivlar",
    "gn:country_code":"IR",
    "gn:dem":1317,
    "gn:feature_class":"P",
    "gn:feature_code":"PPL",
    "gn:name":"N\u012bvlar",
    "gn:population":0,
    "gn:timezone":"Asia/Tehran",
    "iso:country":"IR",
    "name:fas_x_preferred":[
        "\u0646\u064a\u0648\u0644\u0648"
    ],
    "name:fas_x_variant":[
        "\u0646\u06cc\u0648\u0644\u0631",
        "N\u012bvl\u016b",
        "N\u012bvlar"
    ],
    "wof:name":"Nivlar",
    "wof:placetype":"locality"
},
  "geometry": {"coordinates":[45.1203,37.3948],"type":"Point"}
}