{
  "type": "Feature",
  "properties": {
    "gn:admin1_code":"1",
    "gn:asciiname":"Nivlar",
    "gn:country_code":"IR",
    "gn:dem":1317,
    "gn:feature_class":"P",
    "gn:feature_code":"PPL",
    "gn:name":"N\u012bvlar",
    "gn:population":0,
    "gn:timezone":"Asia/Tehran",
    "iso:country":"IR",
    "name:azb_x_preferred":[
        "\u0646\u06cc\u0648\u0644\u0648"
    ],
    "name:aze_x_preferred":[
        "Nivli"
    ],
    "name:ceb_x_preferred":[
        "N\u012bvlar"
    ],
    "name:fas_x_preferred":[
        "\u0646\u064a\u0648\u0644\u0648"
    ],
    "name:fas_x_variant":[
        "\u0646\u06cc\u0648\u0644\u0631",
        "N\u012bvl\u016b",
        "N\u012bvlar",
        "\u0646\u06cc\u0648\u0644\u0648"
    ],
    "name:msa_x_preferred":[
        "Nivlu"
    ],
    "name:pol_x_preferred":[
        "Niwlu"
    ],
    "name:swe_x_preferred":[
        "N\u012bvlar"
    ],
    "name:ukr_x_preferred":[
        "\u041d\u0456\u0432\u043b\u0443"
    ],
    "wof:name":"Nivlar",
    "wof:placetype":"locality"
},
  "geometry": {"coordinates":[45.1203,37.3948],"type":"Point"}
}