{
  "type": "Feature",
  "properties": {
    "gn:admin1_code":"42",
    "gn:asciiname":"Gash",
    "gn:country_code":"IR",
    "gn:dem":1888,
    "gn:feature_class":"P",
    "gn:feature_code":"PPL",
    "gn:name":"G\u0101sh",
    "gn:population":0,
    "gn:timezone":"Asia/Tehran",
    "iso:country":"IR",
    "name:fas_x_preferred":[
        "\u06af\u0627\u0634"
    ],
    "name:fas_x_variant":[
        "G\u0101s",
        "G\u0101sh"
    ],
    "name:und_x_variant":[
        "Q\u0101sh"
    ],
    "wof:name":"Gash",
    "wof:placetype":"locality"
},
  "geometry": {"coordinates":[59.24995,36.89357],"type":"Point"}
}