{
  "type": "Feature",
  "properties": {
    "gn:admin1_code":"29",
    "gn:asciiname":"Bam Bir",
    "gn:country_code":"IR",
    "gn:dem":992,
    "gn:feature_class":"P",
    "gn:feature_code":"PPLL",
    "gn:name":"Bam B\u012br",
    "gn:population":0,
    "gn:timezone":"Asia/Tehran",
    "iso:country":"IR",
    "name:fas_x_preferred":[
        "\u0628\u0646 \u0628\u06cc\u0631"
    ],
    "name:fas_x_variant":[
        "Bon B\u012br",
        "\u0628\u0645 \u0628\u06cc\u0631",
        "\u0628\u0646 \u067e\u06cc\u0631"
    ],
    "name:und_x_variant":[
        "Bam B\u012br",
        "Bon P\u012br"
    ],
    "wof:name":"Bam Bir",
    "wof:placetype":"locality"
},
  "geometry": {"coordinates":[58.09477,26.93074],"type":"Point"}
}