{
  "type": "Feature",
  "properties": {
    "gn:admin1_code":"13",
    "gn:asciiname":"Sheykh Hasan",
    "gn:country_code":"IR",
    "gn:dem":1654,
    "gn:feature_class":"P",
    "gn:feature_code":"PPL",
    "gn:name":"Sheykh \u1e28asan",
    "gn:population":0,
    "gn:timezone":"Asia/Tehran",
    "iso:country":"IR",
    "name:fas_x_preferred":[
        "\u0634\u06cc\u062e \u062d\u0633\u0646"
    ],
    "name:fas_x_variant":[
        "Sheykh \u1e28asan"
    ],
    "name:und_x_variant":[
        "B\u012bvehn\u012bj",
        "Shaikhan"
    ],
    "wof:name":"Sheykh Hasan",
    "wof:placetype":"locality"
},
  "geometry": {"coordinates":[46.1979,34.399],"type":"Point"}
}