{
  "type": "Feature",
  "properties": {
    "gn:admin1_code":"9",
    "gn:asciiname":"Cheshmeh-ye `Ali Mohammad",
    "gn:country_code":"IR",
    "gn:dem":2132,
    "gn:feature_class":"P",
    "gn:feature_code":"PPL",
    "gn:name":"Cheshmeh-ye \u2018Al\u012b Mo\u1e29ammad",
    "gn:population":0,
    "gn:timezone":"Asia/Tehran",
    "iso:country":"IR",
    "name:fas_x_preferred":[
        "\u0686\u0634\u0645\u0647 \u0639\u0644\u06cc \u0645\u062d\u0645\u062f"
    ],
    "name:fas_x_variant":[
        "Cheshmeh-ye \u2018Al\u012b Mo\u1e29ammad"
    ],
    "name:und_x_variant":[
        "Cheshmeh-ye \u2018A\u012b Mo\u1e29ammad",
        "Cheshmeh-ye \u2018Alish\u0101h",
        "Cheshmeh Ali Mohammad",
        "Chasmeh-ye \u2018Al\u012b Mo\u1e29ammad"
    ],
    "wof:name":"Cheshmeh-ye `Ali Mohammad",
    "wof:placetype":"locality"
},
  "geometry": {"coordinates":[49.11701,34.06072],"type":"Point"}
}