{
  "type": "Feature",
  "properties": {
    "gn:admin1_code":"15",
    "gn:asciiname":"Khoshab",
    "gn:country_code":"IR",
    "gn:dem":12,
    "gn:feature_class":"P",
    "gn:feature_code":"PPL",
    "gn:name":"Khosh\u0101b",
    "gn:population":0,
    "gn:timezone":"Asia/Tehran",
    "iso:country":"IR",
    "name:fas_x_preferred":[
        "Khash\u0101b"
    ],
    "name:fas_x_variant":[
        "\u062e\u0634\u0627\u0628"
    ],
    "name:und_x_variant":[
        "Khashsh\u0101b",
        "Khosh\u0101b"
    ],
    "wof:name":"Khoshab",
    "wof:placetype":"locality"
},
  "geometry": {"coordinates":[48.82495,30.77789000000001],"type":"Point"}
}