{
  "type": "Feature",
  "properties": {
    "gn:admin1_code":"33",
    "gn:asciiname":"Sheykh Vali",
    "gn:country_code":"IR",
    "gn:dem":1303,
    "gn:feature_class":"P",
    "gn:feature_code":"PPL",
    "gn:name":"Sheykh Val\u012b",
    "gn:population":0,
    "gn:timezone":"Asia/Tehran",
    "iso:country":"IR",
    "name:ceb_x_preferred":[
        "Sheykh Val\u012b"
    ],
    "name:fas_x_preferred":[
        "\u0634\u06cc\u062e \u0648\u0644\u06cc"
    ],
    "name:fas_x_variant":[
        "\u0634\u0650\u064a\u062e \u0648\u064e\u0644\u06cc",
        "Sheykh Val\u012b",
        "\u0634\u06cc\u062e\u200c\u0648\u0644\u06cc"
    ],
    "name:msa_x_preferred":[
        "Sheykh Vali"
    ],
    "name:swe_x_preferred":[
        "Sheykh Val\u012b"
    ],
    "name:und_x_variant":[
        "Sheikh Vali",
        "Shikhvali",
        "Shaikhwali"
    ],
    "wof:name":"Sheykh Vali",
    "wof:placetype":"locality"
},
  "geometry": {"coordinates":[45.41132,38.22949000000001],"type":"Point"}
}