{
  "type": "Feature",
  "properties": {
    "gn:admin1_code":"5.0",
    "gn:asciiname":"Chali",
    "gn:country_code":"IR",
    "gn:dem":979,
    "gn:feature_class":"P",
    "gn:feature_code":"PPL",
    "gn:name":"Chal\u012b",
    "gn:population":0,
    "gn:timezone":"Asia/Tehran",
    "iso:country":"IR",
    "name:fas_x_preferred":[
        "\u0686\u0644\u06cc"
    ],
    "name:fas_x_variant":[
        "Chal\u012b"
    ],
    "name:ita_x_preferred":[
        "Cali"
    ],
    "name:und_x_variant":[
        "Chel\u012b"
    ],
    "wof:name":"Chali",
    "wof:placetype":"locality"
},
  "geometry": {"coordinates":[50.2218,30.9461],"type":"Point"}
}