{
  "type": "Feature",
  "properties": {
    "gn:admin1_code":"9",
    "gn:asciiname":"Damurchi-ye Bala",
    "gn:country_code":"IR",
    "gn:dem":2207,
    "gn:feature_class":"P",
    "gn:feature_code":"PPL",
    "gn:name":"Dam\u016brch\u012b-ye B\u0101l\u0101",
    "gn:population":0,
    "gn:timezone":"Asia/Tehran",
    "iso:country":"IR",
    "name:fas_x_preferred":[
        "\u062f\u0645\u0648\u0631\u0686\u06cc \u0639\u0644\u064a\u0627"
    ],
    "name:fas_x_variant":[
        "\u062f\u064e\u0645\u064e\u0631\u0686\u0626 \u0639\u064f\u0644\u064a\u0627",
        "\u062a\u0650\u064a\u0645\u0648\u0631\u0686\u06cc",
        "\u062f\u0645\u0648\u0631\u0686\u06cc \u0628\u0627\u0644\u0627",
        "Dam\u016brch\u012b-ye \u2018Oly\u0101",
        "Dam\u016brch\u012b-ye B\u0101l\u0101"
    ],
    "name:und_x_variant":[
        "Taim\u016brchi",
        "Damarch\u012b-ye \u2018Oly\u0101",
        "Teym\u016brch\u012b",
        "Damoorchi Olya"
    ],
    "wof:name":"Damurchi-ye Bala",
    "wof:placetype":"locality"
},
  "geometry": {"coordinates":[49.29275,35.39668],"type":"Point"}
}