{
  "type": "Feature",
  "properties": {
    "gn:admin1_code":"40.0",
    "gn:asciiname":"Mahalleh-ye Bagh-e Shaftalu",
    "gn:country_code":"IR",
    "gn:dem":2239,
    "gn:feature_class":"P",
    "gn:feature_code":"PPL",
    "gn:name":"Ma\u1e29alleh-ye B\u0101gh-e Shaft\u0101l\u016b",
    "gn:population":0,
    "gn:timezone":"Asia/Tehran",
    "iso:country":"IR",
    "name:fas_x_preferred":[
        "\u0645\u062d\u0644\u0647 \u0628\u0627\u063a \u0634\u0641\u062a\u0627\u0644\u0648"
    ],
    "name:und_x_variant":[
        "Ma\u1e29alleh-ye B\u0101gh-e Shaft\u0101l\u016b"
    ],
    "wof:name":"Mahalleh-ye Bagh-e Shaftalu",
    "wof:placetype":"locality"
},
  "geometry": {"coordinates":[54.14362,31.63908],"type":"Point"}
}