{
  "type": "Feature",
  "properties": {
    "gn:admin1_code":"29",
    "gn:asciiname":"Bidan",
    "gn:country_code":"IR",
    "gn:dem":1939,
    "gn:feature_class":"P",
    "gn:feature_code":"PPL",
    "gn:name":"B\u012bd\u0101n",
    "gn:population":0,
    "gn:timezone":"Asia/Tehran",
    "iso:country":"IR",
    "name:fas_x_preferred":[
        "B\u0101bb\u012bd\u0101n"
    ],
    "name:fas_x_variant":[
        "B\u012bd\u0101n",
        "\u0628\u06cc\u062f\u0627\u0646",
        "B\u012bd\u016bn"
    ],
    "name:und_x_variant":[
        "B\u012bd\u0101n",
        "B\u012bd\u016bn",
        "\u0628\u06cc\u062f\u0627\u0646"
    ],
    "wof:name":"Bidan",
    "wof:placetype":"locality"
},
  "geometry": {"coordinates":[56.74816,30.93524],"type":"Point"}
}