{
  "type": "Feature",
  "properties": {
    "gn:admin1_code":"4",
    "gn:asciiname":"Ramk",
    "gn:country_code":"IR",
    "gn:dem":837,
    "gn:feature_class":"P",
    "gn:feature_code":"PPL",
    "gn:name":"R\u0101mk",
    "gn:population":0,
    "gn:timezone":"Asia/Tehran",
    "iso:country":"IR",
    "name:fas_x_preferred":[
        "\u0631\u0627\u0645\u067e"
    ],
    "name:fas_x_variant":[
        "R\u0101nok",
        "R\u0101mp",
        "\u0631\u0627\u0645\u06a9",
        "\u0631\u0627\u0646\u06a9"
    ],
    "name:und_x_variant":[
        "Ramp",
        "Rampak",
        "R\u0101mak",
        "R\u0101mok",
        "R\u0101mk",
        "\u0631\u0627\u0645\u064e\u0643",
        "\u0631\u0627\u0645\u064f\u0643",
        "R\u0101nk"
    ],
    "wof:name":"Ramk",
    "wof:placetype":"locality"
},
  "geometry": {"coordinates":[59.48703,26.60758],"type":"Point"}
}