{
  "type": "Feature",
  "properties": {
    "gn:admin1_code":"4",
    "gn:asciiname":"Damp",
    "gn:country_code":"IR",
    "gn:dem":57,
    "gn:feature_class":"P",
    "gn:feature_code":"PPL",
    "gn:name":"Damp",
    "gn:population":0,
    "gn:timezone":"Asia/Tehran",
    "iso:country":"IR",
    "wof:name":"Damp",
    "wof:placetype":"locality"
},
  "geometry": {"coordinates":[59.13333000000001,25.81667],"type":"Point"}
}