{
  "type": "Feature",
  "properties": {
    "gn:admin1_code":"1",
    "gn:asciiname":"Kuseh Ahmad",
    "gn:country_code":"IR",
    "gn:dem":1565,
    "gn:feature_class":"P",
    "gn:feature_code":"PPL",
    "gn:name":"K\u016bseh A\u1e29mad",
    "gn:population":0,
    "gn:timezone":"Asia/Tehran",
    "iso:country":"IR",
    "name:azb_x_preferred":[
        "\u06a9\u0648\u0633\u0627 \u0627\u062d\u0645\u062f"
    ],
    "name:aze_x_preferred":[
        "Kus\u0259\u0259hm\u0259d"
    ],
    "name:ceb_x_preferred":[
        "K\u016bseh A\u1e29mad"
    ],
    "name:fas_x_preferred":[
        "\u06a9\u0648\u0633\u0647 \u0627\u062d\u0645\u062f"
    ],
    "name:fas_x_variant":[
        "\u0643\u0648\u0633\u0650\u0647 \u0627\u064e\u062d\u0645\u064e\u062f",
        "K\u016bseh A\u1e29mad",
        "\u06a9\u0648\u0633\u0647\u200c\u0627\u062d\u0645\u062f"
    ],
    "name:msa_x_preferred":[
        "Kuseh Ahmad"
    ],
    "name:swe_x_preferred":[
        "K\u016bseh A\u1e29mad"
    ],
    "wof:name":"Kuseh Ahmad",
    "wof:placetype":"locality"
},
  "geometry": {"coordinates":[44.9569,37.7498],"type":"Point"}
}