{
  "type": "Feature",
  "properties": {
    "gn:admin1_code":"11",
    "gn:asciiname":"Qalamun",
    "gn:country_code":"IR",
    "gn:dem":1114,
    "gn:feature_class":"P",
    "gn:feature_code":"PPL",
    "gn:name":"Qalam\u016bn",
    "gn:population":0,
    "gn:timezone":"Asia/Tehran",
    "iso:country":"IR",
    "name:fas_x_preferred":[
        "\u0642\u0644\u0645\u0648\u0646"
    ],
    "name:fas_x_variant":[
        "Qalam\u016bn"
    ],
    "wof:name":"Qalamun",
    "wof:placetype":"locality"
},
  "geometry": {"coordinates":[57.8833,26.6461],"type":"Point"}
}