{
  "type": "Feature",
  "properties": {
    "gn:admin1_code":"42.0",
    "gn:asciiname":"Shahrak-e Shahid Taheriyeh",
    "gn:country_code":"IR",
    "gn:dem":1089,
    "gn:feature_class":"P",
    "gn:feature_code":"PPL",
    "gn:name":"Shahrak-e Shah\u012bd \u0162\u0101her\u012byeh",
    "gn:population":0,
    "gn:timezone":"Asia/Tehran",
    "iso:country":"IR",
    "name:fas_x_preferred":[
        "Shahrak-e Shah\u012bd \u0162\u0101her\u012b"
    ],
    "name:fas_x_variant":[
        "\u0634\u0647\u0631\u06a9 \u0634\u0647\u06cc\u062f \u0637\u0627\u0647\u0631\u06cc",
        "\u0634\u0647\u0631\u06a9 \u0634\u0647\u06cc\u062f \u0637\u0627\u0647\u0631\u06cc\u0647"
    ],
    "name:und_x_variant":[
        "\u0634\u0647\u0631\u06a9 \u0634\u0647\u06cc\u062f \u0637\u0627\u0647\u0631\u06cc",
        "Shahrak-e Shah\u012bd \u0162\u0101her\u012byeh"
    ],
    "wof:name":"Shahrak-e Shahid Taheriyeh",
    "wof:placetype":"locality"
},
  "geometry": {"coordinates":[57.95137,34.11803],"type":"Point"}
}