{
  "type": "Feature",
  "properties": {
    "gn:admin1_code":"33",
    "gn:asciiname":"Gavidaraq",
    "gn:country_code":"IR",
    "gn:dem":1759,
    "gn:feature_class":"P",
    "gn:feature_code":"PPL",
    "gn:name":"Gav\u012bdaraq",
    "gn:population":0,
    "gn:timezone":"Asia/Tehran",
    "iso:country":"IR",
    "name:fas_x_preferred":[
        "\u06af\u0648\u0631\u0647 \u062f\u0631\u0642"
    ],
    "name:fas_x_variant":[
        "G\u016by Daraq-e T\u0101zeh Kand",
        "G\u016breh Daraq",
        "\u06af\u0648\u06cc\u062f\u0631\u0642",
        "\u06af\u0648\u06cc \u062f\u0631\u0642 \u06a9\u0646\u062f\u06cc"
    ],
    "name:und_x_variant":[
        "K\u016bydaraq",
        "T\u0101zeh Kand",
        "Guydaraq",
        "Karadara",
        "Taza-Kend",
        "Taza-kend",
        "Gav\u012bdaraq",
        "Gav\u012b Daraq-e Kand\u012b"
    ],
    "wof:name":"Gavidaraq",
    "wof:placetype":"locality"
},
  "geometry": {"coordinates":[46.85607,38.34437],"type":"Point"}
}