{
  "type": "Feature",
  "properties": {
    "gn:admin1_code":"29.0",
    "gn:asciiname":"Afraz",
    "gn:cc2":"IR",
    "gn:country_code":"IR",
    "gn:dem":2166,
    "gn:feature_class":"P",
    "gn:feature_code":"PPL",
    "gn:name":"Afr\u0101z",
    "gn:population":0,
    "gn:timezone":"Asia/Tehran",
    "iso:country":"IR",
    "name:fas_x_preferred":[
        "Afr\u0101z"
    ],
    "name:und_x_variant":[
        "Afr\u0101r"
    ],
    "wof:name":"Afraz",
    "wof:placetype":"locality"
},
  "geometry": {"coordinates":[57.89778,28.94528],"type":"Point"}
}