{
  "type": "Feature",
  "properties": {
    "gn:admin1_code":"1",
    "gn:asciiname":"Bardeh Mish",
    "gn:country_code":"IR",
    "gn:dem":1819,
    "gn:feature_class":"P",
    "gn:feature_code":"PPL",
    "gn:name":"Bardeh M\u012bsh",
    "gn:population":0,
    "gn:timezone":"Asia/Tehran",
    "iso:country":"IR",
    "name:fas_x_preferred":[
        "\u0628\u0631\u062f\u0647 \u0645\u06cc\u0634"
    ],
    "name:fas_x_variant":[
        "Bardeh M\u012bsh"
    ],
    "wof:name":"Bardeh Mish",
    "wof:placetype":"locality"
},
  "geometry": {"coordinates":[45.0471,37.0951],"type":"Point"}
}