{
  "type": "Feature",
  "properties": {
    "gn:admin1_code":"1",
    "gn:asciiname":"Bardeh Mish",
    "gn:country_code":"IR",
    "gn:dem":1819,
    "gn:feature_class":"P",
    "gn:feature_code":"PPL",
    "gn:name":"Bardeh M\u012bsh",
    "gn:population":0,
    "gn:timezone":"Asia/Tehran",
    "iso:country":"IR",
    "name:azb_x_preferred":[
        "\u0628\u0631\u062f\u0647\u200c\u0645\u06cc\u0634(\u0633\u0648\u06cc\u0648\u0642\u200c\u0628\u0648\u0644\u0627\u0642)"
    ],
    "name:aze_x_preferred":[
        "B\u0259rd\u0259mi\u015f"
    ],
    "name:ceb_x_preferred":[
        "Bardeh M\u012bsh"
    ],
    "name:ckb_x_preferred":[
        "\u0628\u06d5\u0631\u062f\u06d5\u0645\u06ce\u0634"
    ],
    "name:fas_x_preferred":[
        "\u0628\u0631\u062f\u0647 \u0645\u06cc\u0634"
    ],
    "name:fas_x_variant":[
        "Bardeh M\u012bsh",
        "\u0628\u0631\u062f\u0647\u200c\u0645\u06cc\u0634"
    ],
    "name:msa_x_preferred":[
        "Bardeh Mish"
    ],
    "name:swe_x_preferred":[
        "Bardeh M\u012bsh"
    ],
    "wof:name":"Bardeh Mish",
    "wof:placetype":"locality"
},
  "geometry": {"coordinates":[45.0471,37.0951],"type":"Point"}
}