{
  "type": "Feature",
  "properties": {
    "gn:admin1_code":"32",
    "gn:asciiname":"Aminlu",
    "gn:country_code":"IR",
    "gn:dem":1607,
    "gn:feature_class":"P",
    "gn:feature_code":"PPL",
    "gn:name":"Am\u012bnl\u016b",
    "gn:population":0,
    "gn:timezone":"Asia/Tehran",
    "iso:country":"IR",
    "name:fas_x_preferred":[
        "\u0627\u064e\u0645\u064a\u0646\u0644\u0648"
    ],
    "name:fas_x_variant":[
        "\u0627\u0645\u064a\u0646 \u0644\u0648",
        "Am\u012bnl\u016b"
    ],
    "wof:name":"Aminlu",
    "wof:placetype":"locality"
},
  "geometry": {"coordinates":[48.2337,38.0887],"type":"Point"}
}