{
  "type": "Feature",
  "properties": {
    "gn:admin1_code":"33.0",
    "gn:asciiname":"Baba Jan",
    "gn:country_code":"IR",
    "gn:dem":1675,
    "gn:feature_class":"P",
    "gn:feature_code":"PPL",
    "gn:name":"B\u0101b\u0101 J\u0101n",
    "gn:population":0,
    "gn:timezone":"Asia/Tehran",
    "iso:country":"IR",
    "name:fas_x_preferred":[
        "\u0628\u0627\u0628\u0627 \u062c\u0627\u0646"
    ],
    "name:fas_x_variant":[
        "B\u0101b\u0101 J\u0101n"
    ],
    "wof:name":"Baba Jan",
    "wof:placetype":"locality"
},
  "geometry": {"coordinates":[47.25728,38.55785],"type":"Point"}
}