{
  "type": "Feature",
  "properties": {
    "gn:admin1_code":"4.0",
    "gn:asciiname":"Govanich",
    "gn:country_code":"IR",
    "gn:dem":1356,
    "gn:feature_class":"P",
    "gn:feature_code":"PPL",
    "gn:name":"Gov\u0101n\u012bch",
    "gn:population":0,
    "gn:timezone":"Asia/Tehran",
    "iso:country":"IR",
    "name:fas_x_preferred":[
        "\u06af\u0648\u0627\u0646\u064a\u0686"
    ],
    "name:fas_x_variant":[
        "G\u016bn\u012bch",
        "Gov\u0101n\u012bch",
        "G\u016bn\u012bj"
    ],
    "wof:name":"Govanich",
    "wof:placetype":"locality"
},
  "geometry": {"coordinates":[60.69792,27.94591],"type":"Point"}
}