{
  "type": "Feature",
  "properties": {
    "gn:admin1_code":"44",
    "gn:asciiname":"Hojjatabad",
    "gn:country_code":"IR",
    "gn:dem":1225,
    "gn:feature_class":"P",
    "gn:feature_code":"PPL",
    "gn:name":"\u1e28ojjat\u0101b\u0101d",
    "gn:population":0,
    "gn:timezone":"Asia/Tehran",
    "iso:country":"IR",
    "name:fas_x_preferred":[
        "\u062d\u062c\u062a \u0622\u0628\u0627\u062f"
    ],
    "name:fas_x_variant":[
        "\u1e28ojjat\u0101b\u0101d",
        "\u062d\u062c\u062a\u200c\u0622\u0628\u0627\u062f"
    ],
    "wof:name":"Hojjatabad",
    "wof:placetype":"locality"
},
  "geometry": {"coordinates":[50.90617,35.75506],"type":"Point"}
}