{
  "type": "Feature",
  "properties": {
    "gn:admin1_code":"29",
    "gn:asciiname":"Desk",
    "gn:country_code":"IR",
    "gn:dem":1632,
    "gn:feature_class":"P",
    "gn:feature_code":"PPL",
    "gn:name":"Desk",
    "gn:population":0,
    "gn:timezone":"Asia/Tehran",
    "iso:country":"IR",
    "name:ara_x_preferred":[
        "\u062f\u0633\u0643"
    ],
    "name:fas_x_preferred":[
        "Kh\u012b\u0101r\u016b"
    ],
    "name:fas_x_variant":[
        "\u062f\u0633\u06a9"
    ],
    "name:und_x_variant":[
        "Kan G\u012bnow"
    ],
    "wof:name":"Desk",
    "wof:placetype":"locality"
},
  "geometry": {"coordinates":[58.12255,28.98079],"type":"Point"}
}