{
  "type": "Feature",
  "properties": {
    "gn:admin1_code":"42",
    "gn:asciiname":"Dezq",
    "gn:country_code":"IR",
    "gn:dem":1126,
    "gn:feature_class":"P",
    "gn:feature_code":"PPL",
    "gn:name":"Dezq",
    "gn:population":0,
    "gn:timezone":"Asia/Tehran",
    "iso:country":"IR",
    "name:fas_x_preferred":[
        "\u062f\u0632\u0642"
    ],
    "wof:name":"Dezq",
    "wof:placetype":"locality"
},
  "geometry": {"coordinates":[59.49883000000001,36.62508],"type":"Point"}
}