{
  "type": "Feature",
  "properties": {
    "gn:admin1_code":"36",
    "gn:asciiname":"Behestan",
    "gn:country_code":"IR",
    "gn:dem":1307,
    "gn:feature_class":"P",
    "gn:feature_code":"PPL",
    "gn:name":"Behest\u0101n",
    "gn:population":0,
    "gn:timezone":"Asia/Tehran",
    "iso:country":"IR",
    "name:azb_x_preferred":[
        "\u0628\u0647\u0633\u062a\u0627\u0646"
    ],
    "name:fas_x_preferred":[
        "\u0628\u0647\u0633\u062a\u0627\u0646"
    ],
    "name:fas_x_variant":[
        "Behest\u0101n"
    ],
    "wof:name":"Behestan",
    "wof:placetype":"locality"
},
  "geometry": {"coordinates":[47.72709,36.66763],"type":"Point"}
}