{
  "type": "Feature",
  "properties": {
    "gn:admin1_code":"42.0",
    "gn:asciiname":"Dahaneh-ye Teymanak",
    "gn:country_code":"IR",
    "gn:dem":1150,
    "gn:feature_class":"P",
    "gn:feature_code":"PPL",
    "gn:name":"Dahaneh-ye Teymanak",
    "gn:population":0,
    "gn:timezone":"Asia/Tehran",
    "iso:country":"IR",
    "wof:name":"Dahaneh-ye Teymanak",
    "wof:placetype":"locality"
},
  "geometry": {"coordinates":[60.59917,35.47027999999999],"type":"Point"}
}