{
  "type": "Feature",
  "properties": {
    "gn:admin1_code":"1",
    "gn:asciiname":"Salteh",
    "gn:country_code":"IR",
    "gn:dem":1432,
    "gn:feature_class":"P",
    "gn:feature_code":"PPL",
    "gn:name":"S\u0101lteh",
    "gn:population":0,
    "gn:timezone":"Asia/Tehran",
    "iso:country":"IR",
    "name:ara_x_preferred":[
        "\u0633\u0627\u0644\u0637\u0647"
    ],
    "name:aze_x_preferred":[
        "S\u0259lt\u0259"
    ],
    "name:fas_x_preferred":[
        "\u0633\u0627\u0644\u062a\u0647"
    ],
    "name:fas_x_variant":[
        "\u0633\u0627\u0644\u0637\u0650\u0647",
        "S\u0101l\u0163eh",
        "\u0633\u0627\u0644\u062a\u0627",
        "S\u0101lteh",
        "\u0633\u0627\u0644\u0637\u0647"
    ],
    "name:msa_x_preferred":[
        "Salteh"
    ],
    "name:und_x_variant":[
        "S\u0101lt\u0101",
        "Salti Bul\u0101q"
    ],
    "wof:name":"Salteh",
    "wof:placetype":"locality"
},
  "geometry": {"coordinates":[44.89100000000001,38.9339],"type":"Point"}
}