{
  "type": "Feature",
  "properties": {
    "gn:admin1_code":"35.0",
    "gn:asciiname":"Mirudbar",
    "gn:country_code":"IR",
    "gn:dem":743,
    "gn:feature_class":"P",
    "gn:feature_code":"PPL",
    "gn:name":"M\u012br\u016bdb\u0101r",
    "gn:population":0,
    "gn:timezone":"Asia/Tehran",
    "iso:country":"IR",
    "name:fas_x_preferred":[
        "\u0645\u064a\u0627\u0646 \u0631\u0648\u062f\u0628\u0627\u0631"
    ],
    "name:fas_x_variant":[
        "M\u012b\u0101n R\u016bdb\u0101r",
        "\u0645\u06cc\u0631\u0648\u062f\u0628\u0627\u0631",
        "\u0645\u06cc\u0627\u0646\u200c\u0631\u0648\u062f\u0628\u0627\u0631"
    ],
    "name:und_x_variant":[
        "M\u012br\u016bdb\u0101r"
    ],
    "wof:name":"Mirudbar",
    "wof:placetype":"locality"
},
  "geometry": {"coordinates":[51.90394000000001,36.413],"type":"Point"}
}