{
  "type": "Feature",
  "properties": {
    "gn:admin1_code":"23",
    "gn:asciiname":"Darvishabad",
    "gn:country_code":"IR",
    "gn:dem":1644,
    "gn:feature_class":"P",
    "gn:feature_code":"PPL",
    "gn:name":"Darv\u012bsh\u0101b\u0101d",
    "gn:population":0,
    "gn:timezone":"Asia/Tehran",
    "iso:country":"IR",
    "name:fas_x_preferred":[
        "\u062f\u0631\u0648\u06cc\u0634 \u0622\u0628\u0627\u062f"
    ],
    "name:fas_x_variant":[
        "Darv\u012bsh\u0101b\u0101d",
        "\u062f\u0631\u0648\u06cc\u0634\u200c\u0622\u0628\u0627\u062f"
    ],
    "wof:name":"Darvishabad",
    "wof:placetype":"locality"
},
  "geometry": {"coordinates":[48.6118,33.4068],"type":"Point"}
}