{
  "type": "Feature",
  "properties": {
    "gn:admin1_code":"15",
    "gn:asciiname":"Bar Aftab",
    "gn:country_code":"IR",
    "gn:dem":973,
    "gn:feature_class":"P",
    "gn:feature_code":"PPL",
    "gn:name":"Bar \u0100ft\u0101b",
    "gn:population":0,
    "gn:timezone":"Asia/Tehran",
    "iso:country":"IR",
    "name:fas_x_preferred":[
        "Bar \u0100ft\u0101b"
    ],
    "name:fas_x_variant":[
        "\u0628\u0631 \u0622\u0641\u062a\u0627\u0628"
    ],
    "wof:name":"Bar Aftab",
    "wof:placetype":"locality"
},
  "geometry": {"coordinates":[49.9976,31.56072],"type":"Point"}
}