{
  "type": "Feature",
  "properties": {
    "gn:admin1_code":"5.0",
    "gn:asciiname":"Ab Bahareh",
    "gn:country_code":"IR",
    "gn:dem":2059,
    "gn:feature_class":"P",
    "gn:feature_code":"PPL",
    "gn:name":"\u0100b Bah\u0101reh",
    "gn:population":0,
    "gn:timezone":"Asia/Tehran",
    "iso:country":"IR",
    "name:fas_x_preferred":[
        "\u0100b Bah\u0101reh"
    ],
    "name:fas_x_variant":[
        "\u0622\u0628 \u0628\u0647\u0627\u0631\u0647",
        "\u0622\u0628 \u0628\u0647\u0627\u0631\u0647 \u06af\u0644 \u0627\u0633\u067e\u06cc\u062f"
    ],
    "name:und_x_variant":[
        "\u0622\u0628 \u0628\u0647\u0627\u0631\u0647",
        "\u0100b Bah\u0101reh Gol-e Esp\u012bd"
    ],
    "wof:name":"Ab Bahareh",
    "wof:placetype":"locality"
},
  "geometry": {"coordinates":[50.84615,31.11565],"type":"Point"}
}