{
  "type": "Feature",
  "properties": {
    "gn:admin1_code":"4",
    "gn:asciiname":"Padagi",
    "gn:country_code":"IR",
    "gn:dem":1514,
    "gn:feature_class":"P",
    "gn:feature_code":"PPL",
    "gn:name":"Padag\u012b",
    "gn:population":0,
    "gn:timezone":"Asia/Tehran",
    "iso:country":"IR",
    "name:fas_x_preferred":[
        "\u067e\u062f\u06af\u06cc"
    ],
    "name:fas_x_variant":[
        "Padag\u012b"
    ],
    "wof:name":"Padagi",
    "wof:placetype":"locality"
},
  "geometry": {"coordinates":[60.33318000000001,28.4395],"type":"Point"}
}