{
  "type": "Feature",
  "properties": {
    "gn:admin1_code":"28",
    "gn:asciiname":"Tir Kert",
    "gn:country_code":"IR",
    "gn:dem":2298,
    "gn:feature_class":"P",
    "gn:feature_code":"PPL",
    "gn:name":"T\u012br Kert",
    "gn:population":0,
    "gn:timezone":"Asia/Tehran",
    "iso:country":"IR",
    "name:fas_x_preferred":[
        "T\u012br Kert"
    ],
    "name:fas_x_variant":[
        "\u062a\u06cc\u0631 \u06a9\u0631\u062a"
    ],
    "name:und_x_variant":[
        "T\u012br Kart",
        "T\u012b Kert",
        "\u062a\u06cc\u0631 \u06a9\u0631\u062a"
    ],
    "wof:name":"Tir Kert",
    "wof:placetype":"locality"
},
  "geometry": {"coordinates":[50.03007,33.18282],"type":"Point"}
}