{
  "type": "Feature",
  "properties": {
    "gn:admin1_code":"29",
    "gn:asciiname":"Tolombeh-ye Mehravaran",
    "gn:country_code":"IR",
    "gn:dem":1711,
    "gn:feature_class":"P",
    "gn:feature_code":"PPL",
    "gn:name":"Tolombeh-ye Mehr\u0101var\u0101n",
    "gn:population":0,
    "gn:timezone":"Asia/Tehran",
    "iso:country":"IR",
    "name:fas_x_preferred":[
        "Tolombeh-ye Mehr\u0101var\u0101n"
    ],
    "wof:name":"Tolombeh-ye Mehravaran",
    "wof:placetype":"locality"
},
  "geometry": {"coordinates":[55.57666999999999,29.46722],"type":"Point"}
}