{
  "type": "Feature",
  "properties": {
    "gn:admin1_code":"42",
    "gn:asciiname":"Chah-e `Amiq",
    "gn:country_code":"IR",
    "gn:dem":635,
    "gn:feature_class":"P",
    "gn:feature_code":"PPL",
    "gn:name":"Ch\u0101h-e \u2018Am\u012bq",
    "gn:population":0,
    "gn:timezone":"Asia/Tehran",
    "iso:country":"IR",
    "name:fas_x_preferred":[
        "\u0686\u0627\u0647 \u0639\u0645\u06cc\u0642"
    ],
    "name:fas_x_variant":[
        "Ch\u0101h-e \u2018Am\u012bq"
    ],
    "wof:name":"Chah-e `Amiq",
    "wof:placetype":"locality"
},
  "geometry": {"coordinates":[60.5922,33.3486],"type":"Point"}
}