{
  "type": "Feature",
  "properties": {
    "gn:admin1_code":"42.0",
    "gn:asciiname":"Chahar Deh",
    "gn:country_code":"IR",
    "gn:dem":1208,
    "gn:feature_class":"P",
    "gn:feature_code":"PPL",
    "gn:name":"Chah\u0101r Deh",
    "gn:population":0,
    "gn:timezone":"Asia/Tehran",
    "iso:country":"IR",
    "name:fas_x_preferred":[
        "Chah\u0101r Deh"
    ],
    "name:und_x_variant":[
        "Cheh\u0101r Deh"
    ],
    "wof:name":"Chahar Deh",
    "wof:placetype":"locality"
},
  "geometry": {"coordinates":[60.06389,34.765],"type":"Point"}
}