{
  "type": "Feature",
  "properties": {
    "gn:admin1_code":"15",
    "gn:asciiname":"Risman",
    "gn:country_code":"IR",
    "gn:dem":486,
    "gn:feature_class":"P",
    "gn:feature_code":"PPL",
    "gn:name":"R\u012bsm\u0101n",
    "gn:population":0,
    "gn:timezone":"Asia/Tehran",
    "iso:country":"IR",
    "name:fas_x_preferred":[
        "R\u012bsm\u0101n"
    ],
    "name:fas_x_variant":[
        "Darreh R\u012bsm\u0101n",
        "\u0631\u06cc\u0633\u0645\u0627\u0646"
    ],
    "name:und_x_variant":[
        "\u0631\u06cc\u0633\u0645\u0627\u0646"
    ],
    "wof:name":"Risman",
    "wof:placetype":"locality"
},
  "geometry": {"coordinates":[48.48894,32.74148],"type":"Point"}
}