{
  "type": "Feature",
  "properties": {
    "gn:admin1_code":"8.0",
    "gn:asciiname":"Ku Tambaneh",
    "gn:country_code":"IR",
    "gn:dem":-12,
    "gn:feature_class":"P",
    "gn:feature_code":"PPL",
    "gn:name":"K\u016b Tambaneh",
    "gn:population":0,
    "gn:timezone":"Asia/Tehran",
    "iso:country":"IR",
    "name:fas_x_preferred":[
        "K\u016b Tambaneh"
    ],
    "name:fas_x_variant":[
        "\u06a9\u0648 \u062a\u0645\u0628\u0646\u0647"
    ],
    "name:und_x_variant":[
        "\u06a9\u0648 \u062a\u0645\u0628\u0646\u0647"
    ],
    "wof:name":"Ku Tambaneh",
    "wof:placetype":"locality"
},
  "geometry": {"coordinates":[49.93801,37.24508],"type":"Point"}
}