{
  "type": "Feature",
  "properties": {
    "gn:admin1_code":"5",
    "gn:asciiname":"Barzian",
    "gn:country_code":"IR",
    "gn:dem":584,
    "gn:feature_class":"P",
    "gn:feature_code":"PPL",
    "gn:name":"Barz\u012b\u0101n",
    "gn:population":0,
    "gn:timezone":"Asia/Tehran",
    "iso:country":"IR",
    "name:fas_x_preferred":[
        "Barz\u012b\u0101n"
    ],
    "name:und_x_variant":[
        "Barzey\u0101n"
    ],
    "wof:name":"Barzian",
    "wof:placetype":"locality"
},
  "geometry": {"coordinates":[50.37244000000001,30.74777000000001],"type":"Point"}
}