{
  "type": "Feature",
  "properties": {
    "gn:admin1_code":"11",
    "gn:asciiname":"Patak Surgeh",
    "gn:country_code":"IR",
    "gn:dem":1449,
    "gn:feature_class":"P",
    "gn:feature_code":"PPL",
    "gn:name":"P\u0101tak S\u016brgeh",
    "gn:population":0,
    "gn:timezone":"Asia/Tehran",
    "iso:country":"IR",
    "name:fas_x_preferred":[
        "\u067e\u0627\u062a\u06a9 \u0633\u0648\u0631\u06af\u0647"
    ],
    "name:fas_x_variant":[
        "P\u0101tak S\u016brgeh"
    ],
    "wof:name":"Patak Surgeh",
    "wof:placetype":"locality"
},
  "geometry": {"coordinates":[56.5609,27.8807],"type":"Point"}
}