{
  "type": "Feature",
  "properties": {
    "gn:admin1_code":"4.0",
    "gn:asciiname":"Kalinak-e Taj Mohammad Khan",
    "gn:country_code":"IR",
    "gn:dem":552,
    "gn:feature_class":"P",
    "gn:feature_code":"PPL",
    "gn:name":"Kalinak-e T\u0101j Mo\u1e29ammad Kh\u0101n",
    "gn:population":0,
    "gn:timezone":"Asia/Tehran",
    "iso:country":"IR",
    "name:fas_x_preferred":[
        "\u06a9\u0644\u064a\u0646\u06a9 \u062a\u0627\u062c \u0645\u062d\u0645\u0651\u062f \u062e\u0627\u0646"
    ],
    "name:fas_x_variant":[
        "K\u0101lang",
        "Kalinak-e T\u0101j Mo\u1e29ammad Kh\u0101n",
        "K\u0101ling"
    ],
    "name:und_x_variant":[
        "Kolang",
        "Kolnag",
        "Kalinak"
    ],
    "wof:name":"Kalinak-e Taj Mohammad Khan",
    "wof:placetype":"locality"
},
  "geometry": {"coordinates":[60.66282,27.18064],"type":"Point"}
}