{
  "type": "Feature",
  "properties": {
    "gn:admin1_code":"15",
    "gn:asciiname":"Murd-e Ghaffar",
    "gn:country_code":"IR",
    "gn:dem":748,
    "gn:feature_class":"P",
    "gn:feature_code":"PPL",
    "gn:name":"M\u016brd-e Ghaff\u0101r",
    "gn:population":0,
    "gn:timezone":"Asia/Tehran",
    "iso:country":"IR",
    "name:fas_x_preferred":[
        "Boneh-ye Mordeh Ghaff\u0101r"
    ],
    "name:fas_x_variant":[
        "M\u016brd-e Ghaff\u0101r",
        "\u0645\u0648\u0631\u062f \u063a\u0641\u0627\u0631"
    ],
    "name:und_x_variant":[
        "Moord Ghaffar",
        "Boneh-ye M\u016brt Ghaff\u0101r",
        "Bunneh M\u016brdah Ghaff\u0101r"
    ],
    "wof:name":"Murd-e Ghaffar",
    "wof:placetype":"locality"
},
  "geometry": {"coordinates":[49.74903,31.76392],"type":"Point"}
}