{
  "type": "Feature",
  "properties": {
    "gn:admin1_code":"4.0",
    "gn:asciiname":"Hajji Naru'i",
    "gn:country_code":"IR",
    "gn:dem":483,
    "gn:feature_class":"P",
    "gn:feature_code":"PPL",
    "gn:name":"\u1e28\u0101jj\u012b N\u0101r\u016b\u2019\u012b",
    "gn:population":0,
    "gn:timezone":"Asia/Tehran",
    "iso:country":"IR",
    "name:fas_x_preferred":[
        "\u062d\u0627\u062c\u06cc \u0646\u0627\u0631\u0648\u0626\u06cc"
    ],
    "name:und_x_variant":[
        "\u1e28\u0101jj\u012b N\u0101r\u016b\u2019\u012b"
    ],
    "wof:name":"Hajji Naru'i",
    "wof:placetype":"locality"
},
  "geometry": {"coordinates":[61.7517,31.181],"type":"Point"}
}