{
  "type": "Feature",
  "properties": {
    "gn:admin1_code":"15.0",
    "gn:asciiname":"Rabihat",
    "gn:country_code":"IR",
    "gn:dem":6,
    "gn:feature_class":"P",
    "gn:feature_code":"PPL",
    "gn:name":"Rab\u012b\u1e29\u0101t",
    "gn:population":0,
    "gn:timezone":"Asia/Tehran",
    "iso:country":"IR",
    "name:fas_x_preferred":[
        "\u0627\u0631\u0628\u06cc\u062d\u0627\u062a"
    ],
    "name:fas_x_variant":[
        "Arb\u012b\u1e29\u0101t",
        "\u0631\u0628\u06cc\u062d\u0627\u062a"
    ],
    "name:und_x_variant":[
        "Arb\u012b\u1e29\u0101t",
        "\u0627\u0631\u0628\u06cc\u062d\u0627\u062a",
        "Rab\u012b\u1e29\u0101t"
    ],
    "wof:name":"Rabihat",
    "wof:placetype":"locality"
},
  "geometry": {"coordinates":[48.66169,30.67468],"type":"Point"}
}