{
  "type": "Feature",
  "properties": {
    "gn:admin1_code":"15",
    "gn:asciiname":"Shirin Ab",
    "gn:country_code":"IR",
    "gn:dem":487,
    "gn:feature_class":"P",
    "gn:feature_code":"PPL",
    "gn:name":"Sh\u012br\u012bn \u0100b",
    "gn:population":0,
    "gn:timezone":"Asia/Tehran",
    "iso:country":"IR",
    "name:fas_x_preferred":[
        "\u0634\u06cc\u0631\u06cc\u0646 \u0622\u0628"
    ],
    "name:fas_x_variant":[
        "Sh\u012br\u012bn \u0100b",
        "\u0634\u06cc\u0631\u06cc\u0646\u200c\u0622\u0628"
    ],
    "wof:name":"Shirin Ab",
    "wof:placetype":"locality"
},
  "geometry": {"coordinates":[48.29753,32.78379],"type":"Point"}
}