{
  "type": "Feature",
  "properties": {
    "gn:admin1_code":"15.0",
    "gn:asciiname":"Boneh-ye Ghalayem",
    "gn:country_code":"IR",
    "gn:dem":31,
    "gn:feature_class":"P",
    "gn:feature_code":"PPL",
    "gn:name":"Boneh-ye Ghalayem",
    "gn:population":0,
    "gn:timezone":"Asia/Tehran",
    "iso:country":"IR",
    "wof:name":"Boneh-ye Ghalayem",
    "wof:placetype":"locality"
},
  "geometry": {"coordinates":[48.98333,31.85],"type":"Point"}
}