{
  "type": "Feature",
  "properties": {
    "gn:admin1_code":"42",
    "gn:asciiname":"Sowme`eh-ye Bozorg",
    "gn:country_code":"IR",
    "gn:dem":1671,
    "gn:feature_class":"P",
    "gn:feature_code":"PPL",
    "gn:name":"\u015eowme\u2018eh-ye Bozorg",
    "gn:population":0,
    "gn:timezone":"Asia/Tehran",
    "iso:country":"IR",
    "name:fas_x_preferred":[
        "\u0635\u0648\u0645\u0639\u0647 \u0628\u0632\u0631\u06af"
    ],
    "name:fas_x_variant":[
        "\u015eowma\u2018eh-ye B\u0101l\u0101",
        "\u015eowme\u2018eh-ye Bozorg"
    ],
    "wof:name":"Sowme`eh-ye Bozorg",
    "wof:placetype":"locality"
},
  "geometry": {"coordinates":[59.81349,35.55844000000001],"type":"Point"}
}