{
  "type": "Feature",
  "properties": {
    "gn:admin1_code":"38",
    "gn:asciiname":"Sirdan",
    "gn:country_code":"IR",
    "gn:dem":1170,
    "gn:feature_class":"P",
    "gn:feature_code":"PPL",
    "gn:name":"S\u012brd\u0101n",
    "gn:population":0,
    "gn:timezone":"Asia/Tehran",
    "iso:country":"IR",
    "name:ara_x_preferred":[
        "\u0633\u064a\u0631\u062f\u0627\u0646"
    ],
    "name:azb_x_preferred":[
        "\u0633\u06cc\u0631\u062f\u0627\u0646"
    ],
    "name:aze_x_preferred":[
        "Sirdan"
    ],
    "name:ceb_x_preferred":[
        "S\u012brd\u0101n"
    ],
    "name:fas_x_preferred":[
        "\u0633\u064a\u0631\u062f\u0627\u0646"
    ],
    "name:fas_x_variant":[
        "S\u012brd\u0101n",
        "\u0633\u06cc\u0631\u062f\u0627\u0646"
    ],
    "name:mlg_x_preferred":[
        "Sirdan"
    ],
    "name:swe_x_preferred":[
        "S\u012brd\u0101n"
    ],
    "name:tur_x_preferred":[
        "Sirdan"
    ],
    "name:und_x_variant":[
        "Serdan",
        "Sard\u0101n"
    ],
    "wof:name":"Sirdan",
    "wof:placetype":"locality"
},
  "geometry": {"coordinates":[49.19085,36.6476],"type":"Point"}
}