{
  "type": "Feature",
  "properties": {
    "gn:admin1_code":"4.0",
    "gn:asciiname":"Deh-e Rahman",
    "gn:country_code":"IR",
    "gn:dem":483,
    "gn:feature_class":"P",
    "gn:feature_code":"PPL",
    "gn:name":"Deh-e Ra\u1e29m\u0101n",
    "gn:population":0,
    "gn:timezone":"Asia/Tehran",
    "iso:country":"IR",
    "name:fas_x_preferred":[
        "\u062f\u0647 \u0631\u062d\u0645\u0627\u0646"
    ],
    "name:fas_x_variant":[
        "Ra\u1e29m\u0101n",
        "Deh-e Ra\u1e29m\u0101n"
    ],
    "wof:name":"Deh-e Rahman",
    "wof:placetype":"locality"
},
  "geometry": {"coordinates":[61.80022,31.09891],"type":"Point"}
}