{
  "type": "Feature",
  "properties": {
    "gn:admin1_code":"4",
    "gn:asciiname":"Shahumachan",
    "gn:country_code":"IR",
    "gn:dem":1211,
    "gn:feature_class":"P",
    "gn:feature_code":"PPL",
    "gn:name":"Sh\u0101h\u016bmach\u0101n",
    "gn:population":0,
    "gn:timezone":"Asia/Tehran",
    "iso:country":"IR",
    "name:fas_x_preferred":[
        "\u0634\u0627\u0647\u0648\u0645\u0686\u0627\u0646"
    ],
    "name:fas_x_variant":[
        "Sh\u0101h\u016bmach\u0101n"
    ],
    "wof:name":"Shahumachan",
    "wof:placetype":"locality"
},
  "geometry": {"coordinates":[61.5921,26.5345],"type":"Point"}
}