{
  "type": "Feature",
  "properties": {
    "gn:admin1_code":"42",
    "gn:asciiname":"Talebabad",
    "gn:country_code":"IR",
    "gn:dem":1186,
    "gn:feature_class":"P",
    "gn:feature_code":"PPL",
    "gn:name":"\u0162\u0101leb\u0101b\u0101d",
    "gn:population":0,
    "gn:timezone":"Asia/Tehran",
    "iso:country":"IR",
    "name:ara_x_preferred":[
        "\u0637\u0627\u0644\u0628\u200c\u0622\u0628\u0627\u062f"
    ],
    "name:fas_x_preferred":[
        "\u0637\u0627\u0644\u0628 \u0622\u0628\u0627\u062f"
    ],
    "name:fas_x_variant":[
        "\u0162\u0101leb\u0101b\u0101d",
        "\u0637\u0627\u0644\u0628\u200c\u0622\u0628\u0627\u062f"
    ],
    "wof:name":"Talebabad",
    "wof:placetype":"locality"
},
  "geometry": {"coordinates":[59.69403000000001,35.96935999999999],"type":"Point"}
}