{
  "type": "Feature",
  "properties": {
    "gn:admin1_code":"7",
    "gn:asciiname":"Khalu Mohammad",
    "gn:country_code":"IR",
    "gn:dem":411,
    "gn:feature_class":"P",
    "gn:feature_code":"PPL",
    "gn:name":"Kh\u0101l\u016b Mo\u1e29ammad",
    "gn:population":0,
    "gn:timezone":"Asia/Tehran",
    "iso:country":"IR",
    "name:fas_x_preferred":[
        "\u062e\u0627\u0644\u0648 \u0645\u062d\u0645\u0651\u062f"
    ],
    "name:fas_x_variant":[
        "Kh\u0101l\u016b Mo\u1e29ammad \u2018Al\u012b",
        "Kh\u0101l\u016b Mo\u1e29ammad",
        "\u062e\u0627\u0644\u0648 \u0645\u062d\u0645\u062f \u0639\u0644\u06cc"
    ],
    "wof:name":"Khalu Mohammad",
    "wof:placetype":"locality"
},
  "geometry": {"coordinates":[53.2567,27.3138],"type":"Point"}
}