{
  "type": "Feature",
  "properties": {
    "gn:admin1_code":"11",
    "gn:asciiname":"Palur",
    "gn:country_code":"IR",
    "gn:dem":215,
    "gn:feature_class":"P",
    "gn:feature_code":"PPL",
    "gn:name":"P\u0101l\u016br",
    "gn:population":0,
    "gn:timezone":"Asia/Tehran",
    "iso:country":"IR",
    "name:fas_x_preferred":[
        "\u067e\u0627\u0644\u0648\u0631"
    ],
    "name:fas_x_variant":[
        "P\u0101l\u016br"
    ],
    "name:msa_x_preferred":[
        "Palur"
    ],
    "wof:name":"Palur",
    "wof:placetype":"locality"
},
  "geometry": {"coordinates":[57.3477,27.1918],"type":"Point"}
}