{
  "type": "Feature",
  "properties": {
    "gn:admin1_code":"7",
    "gn:asciiname":"Gowd Shaneh",
    "gn:country_code":"IR",
    "gn:dem":1093,
    "gn:feature_class":"P",
    "gn:feature_code":"PPL",
    "gn:name":"Gowd Sh\u0101neh",
    "gn:population":0,
    "gn:timezone":"Asia/Tehran",
    "iso:country":"IR",
    "name:fas_x_preferred":[
        "\u06af\u0648\u062f \u0634\u0627\u0646\u0647"
    ],
    "name:fas_x_variant":[
        "Gowd Sh\u0101neh"
    ],
    "wof:name":"Gowd Shaneh",
    "wof:placetype":"locality"
},
  "geometry": {"coordinates":[54.2762,28.69],"type":"Point"}
}