{
  "type": "Feature",
  "properties": {
    "gn:admin1_code":"35",
    "gn:asciiname":"Bur Khani",
    "gn:country_code":"IR",
    "gn:dem":557,
    "gn:feature_class":"P",
    "gn:feature_code":"PPL",
    "gn:name":"B\u016br Kh\u0101n\u012b",
    "gn:population":0,
    "gn:timezone":"Asia/Tehran",
    "iso:country":"IR",
    "name:fas_x_preferred":[
        "\u0628\u0648\u0631 \u062e\u0627\u0646\u06cc"
    ],
    "name:fas_x_variant":[
        "B\u016br Kh\u0101n\u012b"
    ],
    "wof:name":"Bur Khani",
    "wof:placetype":"locality"
},
  "geometry": {"coordinates":[52.83507,36.23471],"type":"Point"}
}