{
  "type": "Feature",
  "properties": {
    "gn:admin1_code":"8.0",
    "gn:asciiname":"Vishkanank",
    "gn:country_code":"IR",
    "gn:dem":10,
    "gn:feature_class":"P",
    "gn:feature_code":"PPL",
    "gn:name":"V\u012bshk\u0101nank",
    "gn:population":0,
    "gn:timezone":"Asia/Tehran",
    "iso:country":"IR",
    "name:fas_x_preferred":[
        "\u0648\u06cc\u0634\u06a9\u0627\u0646\u0646\u06a9"
    ],
    "name:und_x_variant":[
        "V\u012bshk\u0101nank"
    ],
    "wof:name":"Vishkanank",
    "wof:placetype":"locality"
},
  "geometry": {"coordinates":[49.73953,37.23546],"type":"Point"}
}