{
  "type": "Feature",
  "properties": {
    "gn:admin1_code":"15.0",
    "gn:asciiname":"Sab`eh-ye Seh",
    "gn:country_code":"IR",
    "gn:dem":7,
    "gn:feature_class":"P",
    "gn:feature_code":"PPL",
    "gn:name":"Sab\u2018eh-ye Seh",
    "gn:population":0,
    "gn:timezone":"Asia/Tehran",
    "iso:country":"IR",
    "name:fas_x_preferred":[
        "\u0633\u0628\u0639\u0647 \u0633\u0647"
    ],
    "name:und_x_variant":[
        "Sab\u2018eh-ye Seh"
    ],
    "wof:name":"Sab`eh-ye Seh",
    "wof:placetype":"locality"
},
  "geometry": {"coordinates":[48.34401,30.91887],"type":"Point"}
}