{
  "type": "Feature",
  "properties": {
    "gn:admin1_code":"4.0",
    "gn:asciiname":"Mizeh",
    "gn:cc2":"IR",
    "gn:country_code":"IR",
    "gn:dem":534,
    "gn:feature_class":"P",
    "gn:feature_code":"PPL",
    "gn:name":"M\u012bzeh",
    "gn:population":0,
    "gn:timezone":"Asia/Tehran",
    "iso:country":"IR",
    "name:fas_x_preferred":[
        "M\u012bzeh"
    ],
    "name:und_x_variant":[
        "Minzli"
    ],
    "wof:name":"Mizeh",
    "wof:placetype":"locality"
},
  "geometry": {"coordinates":[60.05,26.25],"type":"Point"}
}