{
  "type": "Feature",
  "properties": {
    "gn:admin1_code":"33",
    "gn:asciiname":"Aghvaran",
    "gn:country_code":"IR",
    "gn:dem":1489,
    "gn:feature_class":"P",
    "gn:feature_code":"PPL",
    "gn:name":"\u0100ghvaran",
    "gn:population":0,
    "gn:timezone":"Asia/Tehran",
    "iso:country":"IR",
    "name:azb_x_preferred":[
        "\u0622\u063a\u200c\u0648\u0631\u0646"
    ],
    "name:fas_x_preferred":[
        "\u0100ghvaran"
    ],
    "name:fas_x_variant":[
        "\u0622\u063a\u200c\u0648\u0631\u0646"
    ],
    "name:msa_x_preferred":[
        "Aghvaran"
    ],
    "wof:name":"Aghvaran",
    "wof:placetype":"locality"
},
  "geometry": {"coordinates":[47.53333,37.41667],"type":"Point"}
}