{
  "type": "Feature",
  "properties": {
    "gn:admin1_code":"33",
    "gn:asciiname":"Mahal-e Ta'sis-e Shahrak Farahiyeh",
    "gn:country_code":"IR",
    "gn:dem":1150,
    "gn:feature_class":"P",
    "gn:feature_code":"PPL",
    "gn:name":"Ma\u1e29al-e Ta\u2019s\u012bs-e Shahrak Far\u0101h\u012byeh",
    "gn:population":0,
    "gn:timezone":"Asia/Tehran",
    "iso:country":"IR",
    "name:fas_x_preferred":[
        "Ma\u1e29al-e Ta\u2019s\u012bs-e Shahrak Far\u0101h\u012byeh"
    ],
    "wof:name":"Mahal-e Ta'sis-e Shahrak Farahiyeh",
    "wof:placetype":"locality"
},
  "geometry": {"coordinates":[47.75,37.45],"type":"Point"}
}