{
  "type": "Feature",
  "properties": {
    "gn:admin1_code":"36",
    "gn:asciiname":"Sharifabad",
    "gn:country_code":"IR",
    "gn:dem":1516,
    "gn:feature_class":"P",
    "gn:feature_code":"PPL",
    "gn:name":"Shar\u012bf\u0101b\u0101d",
    "gn:population":0,
    "gn:timezone":"Asia/Tehran",
    "iso:country":"IR",
    "name:ara_x_preferred":[
        "\u0634\u0631\u064a\u0641 \u0623\u0628\u0627\u062f"
    ],
    "name:azb_x_preferred":[
        "\u0634\u0631\u06cc\u0641 \u0622\u0628\u0627\u062f"
    ],
    "name:fas_x_preferred":[
        "\u0634\u0631\u064a\u0641 \u0622\u0628\u0627\u062f"
    ],
    "name:fas_x_variant":[
        "Shar\u012bf\u0101b\u0101d",
        "\u0634\u0631\u06cc\u0641\u200c\u0622\u0628\u0627\u062f"
    ],
    "name:ita_x_preferred":[
        "Sharifabad"
    ],
    "name:rus_x_preferred":[
        "\u0428\u0435\u0440\u0438\u0444\u0430\u0431\u0430\u0434"
    ],
    "name:zho_x_preferred":[
        "\u8b1d\u91cc\u6cd5\u5df4\u5fb7"
    ],
    "wof:name":"Sharifabad",
    "wof:placetype":"locality"
},
  "geometry": {"coordinates":[49.2681,36.1354],"type":"Point"}
}