{
  "type": "Feature",
  "properties": {
    "gn:admin1_code":"23",
    "gn:asciiname":"Eyvashan",
    "gn:country_code":"IR",
    "gn:dem":1975,
    "gn:feature_class":"P",
    "gn:feature_code":"PPL",
    "gn:name":"Eyvash\u0101n",
    "gn:population":0,
    "gn:timezone":"Asia/Tehran",
    "iso:country":"IR",
    "name:fas_x_preferred":[
        "\u0627\u064a\u0648\u0634\u0627\u0646"
    ],
    "name:fas_x_variant":[
        "\u0627\u06cc\u0648\u0634\u0627\u0646 \u0633\u06cc\u0644",
        "Yeb\u0101s\u016bn",
        "\u2018Eyvash\u0101n Seyl",
        "\u2018Eyvash\u0101n S\u012bl",
        "Eyvash\u0101n",
        "Eyvash\u0101n Seyl"
    ],
    "wof:name":"Eyvashan",
    "wof:placetype":"locality"
},
  "geometry": {"coordinates":[48.87428,33.50291],"type":"Point"}
}