{
  "type": "Feature",
  "properties": {
    "gn:admin1_code":"29.0",
    "gn:asciiname":"Kenarestan",
    "gn:country_code":"IR",
    "gn:dem":639,
    "gn:feature_class":"P",
    "gn:feature_code":"PPLF",
    "gn:name":"Ken\u0101rest\u0101n",
    "gn:population":0,
    "gn:timezone":"Asia/Tehran",
    "iso:country":"IR",
    "name:fas_x_preferred":[
        "\u06a9\u0646\u0627\u0631\u0633\u062a\u0627\u0646"
    ],
    "name:und_x_variant":[
        "Ken\u0101rest\u0101n"
    ],
    "wof:name":"Kenarestan",
    "wof:placetype":"locality"
},
  "geometry": {"coordinates":[58.38356,28.10391],"type":"Point"}
}