{
  "type": "Feature",
  "properties": {
    "gn:admin1_code":"43.0",
    "gn:asciiname":"Nushirvan",
    "gn:country_code":"IR",
    "gn:dem":1439,
    "gn:feature_class":"P",
    "gn:feature_code":"PPL",
    "gn:name":"N\u016bsh\u012brv\u0101n",
    "gn:population":0,
    "gn:timezone":"Asia/Tehran",
    "iso:country":"IR",
    "name:fas_x_preferred":[
        "N\u016bsh\u012brv\u0101n"
    ],
    "name:fas_x_variant":[
        "An\u016bsh\u012brv\u0101n",
        "\u0646\u0648\u0634\u06cc\u0631\u0648\u0627\u0646"
    ],
    "name:und_x_variant":[
        "\u0646\u0648\u0634\u06cc\u0631\u0648\u0627\u0646"
    ],
    "wof:name":"Nushirvan",
    "wof:placetype":"locality"
},
  "geometry": {"coordinates":[57.61086,37.07603],"type":"Point"}
}