{
  "type": "Feature",
  "properties": {
    "gn:admin1_code":"1",
    "gn:asciiname":"Boyuran-e `Olya",
    "gn:country_code":"IR",
    "gn:dem":1665,
    "gn:feature_class":"P",
    "gn:feature_code":"PPL",
    "gn:name":"Boy\u016br\u0101n-e \u2018Oly\u0101",
    "gn:population":0,
    "gn:timezone":"Asia/Tehran",
    "iso:country":"IR",
    "name:fas_x_preferred":[
        "\u0628\u06cc\u0648\u0631\u0627\u0646 \u0639\u0644\u06cc\u0627"
    ],
    "name:fas_x_variant":[
        "Boy\u016br\u0101n",
        "Boy\u016br\u0101n-e \u2018Oly\u0101"
    ],
    "name:und_x_variant":[
        "Boyor\u0101n"
    ],
    "wof:name":"Boyuran-e `Olya",
    "wof:placetype":"locality"
},
  "geometry": {"coordinates":[45.3832,36.1793],"type":"Point"}
}