{
  "type": "Feature",
  "properties": {
    "gn:admin1_code":"29.0",
    "gn:asciiname":"Now Shahr",
    "gn:country_code":"IR",
    "gn:dem":1413,
    "gn:feature_class":"P",
    "gn:feature_code":"PPL",
    "gn:name":"Now Shahr",
    "gn:population":0,
    "gn:timezone":"Asia/Tehran",
    "iso:country":"IR",
    "name:fas_x_preferred":[
        "\u0646\u0648 \u0634\u0647\u0631"
    ],
    "wof:name":"Now Shahr",
    "wof:placetype":"locality"
},
  "geometry": {"coordinates":[55.27568,30.85341],"type":"Point"}
}