{
  "type": "Feature",
  "properties": {
    "gn:admin1_code":"16.0",
    "gn:asciiname":"Best",
    "gn:country_code":"IR",
    "gn:dem":1786,
    "gn:feature_class":"P",
    "gn:feature_code":"PPL",
    "gn:name":"Best",
    "gn:population":0,
    "gn:timezone":"Asia/Tehran",
    "iso:country":"IR",
    "name:aze_x_preferred":[
        "Best"
    ],
    "name:ceb_x_preferred":[
        "Best"
    ],
    "name:ces_x_preferred":[
        "Best"
    ],
    "name:deu_x_preferred":[
        "Best"
    ],
    "name:fas_x_preferred":[
        "\u0628\u0633\u062a"
    ],
    "name:fin_x_preferred":[
        "Best"
    ],
    "name:fra_x_preferred":[
        "Best"
    ],
    "name:heb_x_preferred":[
        "\u05d1\u05e1\u05d8"
    ],
    "name:hye_x_preferred":[
        "\u0532\u0565\u057d\u057f"
    ],
    "name:ita_x_preferred":[
        "Best"
    ],
    "name:jpn_x_preferred":[
        "Best"
    ],
    "name:kor_x_preferred":[
        "\ubca0\uc2a4\ud2b8"
    ],
    "name:nld_x_preferred":[
        "Best"
    ],
    "name:nor_x_preferred":[
        "Best"
    ],
    "name:pol_x_preferred":[
        "Best"
    ],
    "name:por_x_preferred":[
        "Best"
    ],
    "name:slk_x_preferred":[
        "Best"
    ],
    "name:swe_x_preferred":[
        "Best"
    ],
    "wof:name":"Best",
    "wof:placetype":"locality"
},
  "geometry": {"coordinates":[46.5877,35.8849],"type":"Point"}
}