{
  "type": "Feature",
  "properties": {
    "gn:admin1_code":"16.0",
    "gn:asciiname":"Best",
    "gn:country_code":"IR",
    "gn:dem":1786,
    "gn:feature_class":"P",
    "gn:feature_code":"PPL",
    "gn:name":"Best",
    "gn:population":0,
    "gn:timezone":"Asia/Tehran",
    "iso:country":"IR",
    "name:fas_x_preferred":[
        "\u0628\u0633\u062a"
    ],
    "wof:name":"Best",
    "wof:placetype":"locality"
},
  "geometry": {"coordinates":[46.5877,35.8849],"type":"Point"}
}