{
  "type": "Feature",
  "properties": {
    "gn:admin1_code":"8",
    "gn:asciiname":"Ahakalan",
    "gn:country_code":"IR",
    "gn:dem":99,
    "gn:feature_class":"P",
    "gn:feature_code":"PPL",
    "gn:name":"\u0100hakal\u0101n",
    "gn:population":0,
    "gn:timezone":"Asia/Tehran",
    "iso:country":"IR",
    "name:fas_x_preferred":[
        "\u062a\u0646\u06cc\u0627\u0646"
    ],
    "name:fas_x_variant":[
        "Tan\u012b\u0101n",
        "\u0622\u0647\u06a9\u0644\u0627\u0646"
    ],
    "name:und_x_variant":[
        "Nany\u0101n",
        "Tan-Yen",
        "\u0100hakal\u0101n"
    ],
    "wof:name":"Ahakalan",
    "wof:placetype":"locality"
},
  "geometry": {"coordinates":[49.13559,37.31565],"type":"Point"}
}