{
  "type": "Feature",
  "properties": {
    "gn:admin1_code":"38",
    "gn:asciiname":"Fanafin",
    "gn:country_code":"IR",
    "gn:dem":915,
    "gn:feature_class":"P",
    "gn:feature_code":"PPL",
    "gn:name":"F\u0101naf\u012bn",
    "gn:population":0,
    "gn:timezone":"Asia/Tehran",
    "iso:country":"IR",
    "name:fas_x_preferred":[
        "F\u0101naq\u012bn"
    ],
    "name:fas_x_variant":[
        "\u0641\u0627\u0646\u0642\u064a\u0646",
        "\u0641\u0627\u0646\u0641\u064a\u0646"
    ],
    "name:und_x_variant":[
        "\u0641\u0627\u0646\u0642\u064a\u0646",
        "F\u0101naf\u012bn"
    ],
    "wof:name":"Fanafin",
    "wof:placetype":"locality"
},
  "geometry": {"coordinates":[50.2167,36.50819],"type":"Point"}
}