{
  "type": "Feature",
  "properties": {
    "gn:admin1_code":"4",
    "gn:asciiname":"Sahrandowg",
    "gn:country_code":"IR",
    "gn:dem":266,
    "gn:feature_class":"P",
    "gn:feature_code":"PPLF",
    "gn:name":"Sahrandowg",
    "gn:population":0,
    "gn:timezone":"Asia/Tehran",
    "iso:country":"IR",
    "name:fas_x_preferred":[
        "Sar\u012bndowk"
    ],
    "name:fas_x_variant":[
        "Sorkh\u012bn D\u016bk",
        "\u0633\u0631\u06cc\u0646\u062f\u0648\u06a9",
        "\u0633\u0647\u0631\u0646\u062f\u0648\u06af",
        "\u0633\u0647\u0631\u064a\u0646 \u062f\u0648\u06a9"
    ],
    "name:und_x_variant":[
        "Sar\u012bdokht",
        "Sahrandowg",
        "Sahr\u012bn Dowk"
    ],
    "wof:name":"Sahrandowg",
    "wof:placetype":"locality"
},
  "geometry": {"coordinates":[59.57885,26.14434],"type":"Point"}
}