{
  "type": "Feature",
  "properties": {
    "gn:admin1_code":"33",
    "gn:asciiname":"Qal`ehlar",
    "gn:country_code":"IR",
    "gn:dem":1670,
    "gn:feature_class":"P",
    "gn:feature_code":"PPL",
    "gn:name":"Qal\u2018ehlar",
    "gn:population":0,
    "gn:timezone":"Asia/Tehran",
    "iso:country":"IR",
    "name:fas_x_preferred":[
        "\u0642\u0644\u0639\u0647 \u0644\u0631"
    ],
    "name:fas_x_variant":[
        "Qal\u2018ehlar"
    ],
    "name:und_x_variant":[
        "Kalalar",
        "Ghal\u2019eh Lar"
    ],
    "wof:name":"Qal`ehlar",
    "wof:placetype":"locality"
},
  "geometry": {"coordinates":[46.5411,38.2173],"type":"Point"}
}