{
  "type": "Feature",
  "properties": {
    "gn:admin1_code":"29.0",
    "gn:asciiname":"Chaleh",
    "gn:country_code":"IR",
    "gn:dem":2005,
    "gn:feature_class":"P",
    "gn:feature_code":"PPLL",
    "gn:name":"Ch\u0101leh",
    "gn:population":0,
    "gn:timezone":"Asia/Tehran",
    "iso:country":"IR",
    "name:fas_x_preferred":[
        "\u0686\u0627\u0644\u0647"
    ],
    "name:fas_x_variant":[
        "Ch\u0101leh"
    ],
    "wof:name":"Chaleh",
    "wof:placetype":"locality"
},
  "geometry": {"coordinates":[57.0366,28.4492],"type":"Point"}
}