{
  "type": "Feature",
  "properties": {
    "gn:admin1_code":"42",
    "gn:asciiname":"Pishavok",
    "gn:country_code":"IR",
    "gn:dem":1173,
    "gn:feature_class":"P",
    "gn:feature_code":"PPL",
    "gn:name":"P\u012bsh\u0101vok",
    "gn:population":0,
    "gn:timezone":"Asia/Tehran",
    "iso:country":"IR",
    "name:fas_x_preferred":[
        "\u067e\u06cc\u0634\u0627\u0648\u0643"
    ],
    "name:fas_x_variant":[
        "P\u012bsh\u0101vok"
    ],
    "name:und_x_variant":[
        "Pash\u0101vak",
        "P\u012bsh\u0101vak"
    ],
    "wof:name":"Pishavok",
    "wof:placetype":"locality"
},
  "geometry": {"coordinates":[59.37281,36.64098],"type":"Point"}
}