{
  "type": "Feature",
  "properties": {
    "gn:admin1_code":"15",
    "gn:asciiname":"Shanbeh-ye Sa`idi",
    "gn:country_code":"IR",
    "gn:dem":593,
    "gn:feature_class":"P",
    "gn:feature_code":"PPL",
    "gn:name":"Shanbeh-ye Sa\u2018\u012bd\u012b",
    "gn:population":0,
    "gn:timezone":"Asia/Tehran",
    "iso:country":"IR",
    "name:fas_x_preferred":[
        "Shanbeh-ye Sa\u2018\u012bd\u012b"
    ],
    "wof:name":"Shanbeh-ye Sa`idi",
    "wof:placetype":"locality"
},
  "geometry": {"coordinates":[49.91667,31.98333],"type":"Point"}
}