{
  "type": "Feature",
  "properties": {
    "gn:admin1_code":"7.0",
    "gn:asciiname":"Chah Shuli",
    "gn:country_code":"IR",
    "gn:dem":1773,
    "gn:feature_class":"P",
    "gn:feature_code":"PPL",
    "gn:name":"Ch\u0101h Sh\u016bl\u012b",
    "gn:population":0,
    "gn:timezone":"Asia/Tehran",
    "iso:country":"IR",
    "name:fas_x_preferred":[
        "\u0686\u0627\u0647 \u0634\u0648\u0644\u06cc"
    ],
    "name:fas_x_variant":[
        "Ch\u0101h Sh\u016bl\u012b"
    ],
    "wof:name":"Chah Shuli",
    "wof:placetype":"locality"
},
  "geometry": {"coordinates":[52.3567,29.0522],"type":"Point"}
}