{
  "type": "Feature",
  "properties": {
    "gn:admin1_code":"10",
    "gn:asciiname":"Kalgeh",
    "gn:country_code":"IR",
    "gn:dem":1298,
    "gn:feature_class":"P",
    "gn:feature_code":"PPL",
    "gn:name":"Kalgeh",
    "gn:population":0,
    "gn:timezone":"Asia/Tehran",
    "iso:country":"IR",
    "name:fas_x_preferred":[
        "\u0634\u06cc\u0644\u0627\u0628"
    ],
    "name:fas_x_variant":[
        "Sh\u012bl\u0101b",
        "\u06a9\u0644\u06af\u0647"
    ],
    "name:msa_x_preferred":[
        "Shilab"
    ],
    "name:por_x_preferred":[
        "Shilab"
    ],
    "wof:name":"Kalgeh",
    "wof:placetype":"locality"
},
  "geometry": {"coordinates":[47.2911,33.0306],"type":"Point"}
}