{
  "type": "Feature",
  "properties": {
    "gn:admin1_code":"15",
    "gn:asciiname":"Darreh Zang",
    "gn:country_code":"IR",
    "gn:dem":1048,
    "gn:feature_class":"P",
    "gn:feature_code":"PPL",
    "gn:name":"Darreh Zang",
    "gn:population":0,
    "gn:timezone":"Asia/Tehran",
    "iso:country":"IR",
    "name:fas_x_preferred":[
        "\u062f\u0631\u0647 \u0632\u0646\u06af"
    ],
    "name:fas_x_variant":[
        "\u062f\u0631\u0647\u200c\u0632\u0646\u06af"
    ],
    "name:und_x_variant":[
        "Darreh-ye Zang"
    ],
    "wof:name":"Darreh Zang",
    "wof:placetype":"locality"
},
  "geometry": {"coordinates":[50.32009,31.59458],"type":"Point"}
}