{
  "type": "Feature",
  "properties": {
    "gn:admin1_code":"23",
    "gn:asciiname":"Gar Khazineh",
    "gn:country_code":"IR",
    "gn:dem":1188,
    "gn:feature_class":"P",
    "gn:feature_code":"PPL",
    "gn:name":"Gar Khaz\u012bneh",
    "gn:population":0,
    "gn:timezone":"Asia/Tehran",
    "iso:country":"IR",
    "name:fas_x_preferred":[
        "\u06af\u064e\u0631 \u062e\u064e\u0632\u064a\u0646\u0650\u0647"
    ],
    "name:fas_x_variant":[
        "Gar Khaz\u012bneh"
    ],
    "wof:name":"Gar Khazineh",
    "wof:placetype":"locality"
},
  "geometry": {"coordinates":[48.24028,33.48972],"type":"Point"}
}