{
  "type": "Feature",
  "properties": {
    "gn:admin1_code":"22",
    "gn:asciiname":"Mal-e Gap",
    "gn:country_code":"IR",
    "gn:dem":22,
    "gn:feature_class":"P",
    "gn:feature_code":"PPL",
    "gn:name":"Mal-e Gap",
    "gn:population":0,
    "gn:timezone":"Asia/Tehran",
    "iso:country":"IR",
    "name:ceb_x_preferred":[
        "Mal-e Gap"
    ],
    "name:fas_x_preferred":[
        "\u0645\u0644 \u06af\u067e"
    ],
    "name:fas_x_variant":[
        "\u062f\u0644\u0627\u0631\u0633",
        "\u0645\u0644\u200c\u06af\u067e"
    ],
    "name:msa_x_preferred":[
        "Mal-e Gap"
    ],
    "name:pol_x_preferred":[
        "Mal-e Gap"
    ],
    "name:swe_x_preferred":[
        "Mal-e Gap"
    ],
    "name:und_x_variant":[
        "Del\u0101ras"
    ],
    "wof:name":"Mal-e Gap",
    "wof:placetype":"locality"
},
  "geometry": {"coordinates":[51.07705,28.80843],"type":"Point"}
}