{
  "type": "Feature",
  "properties": {
    "gn:admin1_code":"28",
    "gn:asciiname":"Mazra`eh-ye Nowqabad",
    "gn:country_code":"IR",
    "gn:dem":1088,
    "gn:feature_class":"P",
    "gn:feature_code":"PPLF",
    "gn:name":"Mazra\u2018eh-ye Nowq\u0101b\u0101d",
    "gn:population":0,
    "gn:timezone":"Asia/Tehran",
    "iso:country":"IR",
    "name:fas_x_preferred":[
        "Nowq\u0101b\u0101d"
    ],
    "name:fas_x_variant":[
        "\u0646\u0648\u0642 \u0622\u0628\u0627\u062f",
        "\u0645\u0632\u0631\u0639\u0647 \u0646\u0648\u0642\u0627\u0628\u0627\u062f"
    ],
    "name:und_x_variant":[
        "Mazra\u2018eh-ye Nowq\u0101b\u0101d"
    ],
    "wof:name":"Mazra`eh-ye Nowqabad",
    "wof:placetype":"locality"
},
  "geometry": {"coordinates":[54.43178,33.99165],"type":"Point"}
}