{
  "type": "Feature",
  "properties": {
    "gn:admin1_code":"29",
    "gn:asciiname":"Deh-e Siahan",
    "gn:country_code":"IR",
    "gn:dem":2569,
    "gn:feature_class":"P",
    "gn:feature_code":"PPL",
    "gn:name":"Deh-e S\u012b\u0101h\u0101n",
    "gn:population":0,
    "gn:timezone":"Asia/Tehran",
    "iso:country":"IR",
    "name:fas_x_preferred":[
        "\u0633\u06cc\u0627\u0647\u0627\u0646"
    ],
    "name:fas_x_variant":[
        "S\u012b\u0101h\u0101n",
        "\u062f\u0647 \u0633\u06cc\u0627\u0647\u0627\u0646",
        "\u062f\u0647 \u0633\u06cc\u0627\u0647\u0627\u0646 \u0639\u0644\u064a\u0627"
    ],
    "name:und_x_variant":[
        "Deh-e S\u012b\u0101h\u0101n",
        "Deh-e S\u012b\u0101h\u0101n-e \u2018Oly\u0101"
    ],
    "wof:name":"Deh-e Siahan",
    "wof:placetype":"locality"
},
  "geometry": {"coordinates":[55.9949,29.9944],"type":"Point"}
}