{
  "type": "Feature",
  "properties": {
    "gn:admin1_code":"28.0",
    "gn:asciiname":"Fiveh",
    "gn:country_code":"IR",
    "gn:dem":2051,
    "gn:feature_class":"P",
    "gn:feature_code":"PPL",
    "gn:name":"F\u012bveh",
    "gn:population":0,
    "gn:timezone":"Asia/Tehran",
    "iso:country":"IR",
    "name:fas_x_preferred":[
        "\u0641\u06cc\u0648\u0647"
    ],
    "name:fas_x_variant":[
        "Fah\u012byeh",
        "F\u012bveh",
        "\u0641\u0647\u06cc\u0647"
    ],
    "name:und_x_variant":[
        "Fahyeh"
    ],
    "name:urd_x_preferred":[
        "\u0641\u06c1\u06cc\u06c1"
    ],
    "wof:name":"Fiveh",
    "wof:placetype":"locality"
},
  "geometry": {"coordinates":[52.9493,32.6855],"type":"Point"}
}