{
  "type": "Feature",
  "properties": {
    "gn:admin1_code":"1",
    "gn:asciiname":"Karan-e Miani",
    "gn:country_code":"IR",
    "gn:dem":1790,
    "gn:feature_class":"P",
    "gn:feature_code":"PPL",
    "gn:name":"Kar\u0101n-e M\u012b\u0101n\u012b",
    "gn:population":0,
    "gn:timezone":"Asia/Tehran",
    "iso:country":"IR",
    "name:fas_x_preferred":[
        "\u06a9\u0631\u0627\u0646 \u0645\u06cc\u0627\u0646\u06cc"
    ],
    "name:fas_x_variant":[
        "Ker\u0101n-e M\u012b\u0101n\u012b",
        "Kar\u0101n-e M\u012b\u0101n\u012b"
    ],
    "wof:name":"Karan-e Miani",
    "wof:placetype":"locality"
},
  "geometry": {"coordinates":[44.7323,38.9597],"type":"Point"}
}