{
  "type": "Feature",
  "properties": {
    "gn:admin1_code":"16",
    "gn:asciiname":"Gorg Tappeh",
    "gn:country_code":"IR",
    "gn:dem":1569,
    "gn:feature_class":"P",
    "gn:feature_code":"PPL",
    "gn:name":"Gorg Tappeh",
    "gn:population":0,
    "gn:timezone":"Asia/Tehran",
    "iso:country":"IR",
    "name:fas_x_preferred":[
        "\u06af\u0648\u06af \u062a\u067e\u0647"
    ],
    "name:fas_x_variant":[
        "G\u016bgtappeh",
        "G\u016bg Tappeh",
        "\u06af\u0631\u06af \u062a\u067e\u0647"
    ],
    "wof:name":"Gorg Tappeh",
    "wof:placetype":"locality"
},
  "geometry": {"coordinates":[47.76269,36.21784],"type":"Point"}
}