{
  "type": "Feature",
  "properties": {
    "gn:admin1_code":"32",
    "gn:asciiname":"`Eba Beyglu",
    "gn:country_code":"IR",
    "gn:dem":360,
    "gn:feature_class":"P",
    "gn:feature_code":"PPL",
    "gn:name":"\u2018Eb\u0101 Beygl\u016b",
    "gn:population":0,
    "gn:timezone":"Asia/Tehran",
    "iso:country":"IR",
    "name:ara_x_preferred":[
        "\u0639\u0628\u0627\u0628\u064a\u063a\u0644\u0648"
    ],
    "name:azb_x_preferred":[
        "\u0639\u06cc\u0628\u0627 \u0628\u064e\u06cc\u200c\u0644\u06cc"
    ],
    "name:fas_x_preferred":[
        "\u0639\u0628\u0627 \u0628\u064a\u06af\u0644\u0648"
    ],
    "name:fas_x_variant":[
        "\u2018Eb\u0101 Beygl\u016b",
        "\u0639\u0628\u0627\u0628\u06cc\u06af\u200c\u0644\u0648"
    ],
    "name:msa_x_preferred":[
        "Eba Beyglu"
    ],
    "name:mzn_x_preferred":[
        "\u0639\u0628\u0627\u0628\u06cc\u06af\u200c\u0644\u0648"
    ],
    "wof:name":"`Eba Beyglu",
    "wof:placetype":"locality"
},
  "geometry": {"coordinates":[48.2032,39.1646],"type":"Point"}
}