{
  "type": "Feature",
  "properties": {
    "gn:admin1_code":"32",
    "gn:asciiname":"Qarah Qasemlu",
    "gn:country_code":"IR",
    "gn:dem":133,
    "gn:feature_class":"P",
    "gn:feature_code":"PPL",
    "gn:name":"Qarah Q\u0101seml\u016b",
    "gn:population":0,
    "gn:timezone":"Asia/Tehran",
    "iso:country":"IR",
    "name:ara_x_preferred":[
        "\u0642\u0631\u0629 \u0642\u0627\u0633\u0645\u0644\u0648"
    ],
    "name:fas_x_preferred":[
        "\u0642\u0631\u0647 \u0642\u0627\u0633\u0645\u0644\u0648"
    ],
    "name:fas_x_variant":[
        "Qarah Q\u0101seml\u016b",
        "\u0642\u0631\u0647\u200c\u0642\u0627\u0633\u0645\u0644\u0648"
    ],
    "name:msa_x_preferred":[
        "Qarah Qasemlu"
    ],
    "name:mzn_x_preferred":[
        "\u0642\u0631\u0647\u200c\u0642\u0627\u0633\u0645\u0644\u0648"
    ],
    "wof:name":"Qarah Qasemlu",
    "wof:placetype":"locality"
},
  "geometry": {"coordinates":[48.24800000000001,39.3348],"type":"Point"}
}