{
  "type": "Feature",
  "properties": {
    "gn:admin1_code":"40",
    "gn:asciiname":"Mehdiabad-e Mostowfi",
    "gn:country_code":"IR",
    "gn:dem":2143,
    "gn:feature_class":"P",
    "gn:feature_code":"PPL",
    "gn:name":"Mehd\u012b\u0101b\u0101d-e Mostowf\u012b",
    "gn:population":0,
    "gn:timezone":"Asia/Tehran",
    "iso:country":"IR",
    "name:fas_x_preferred":[
        "\u0645\u064e\u0632\u0631\u064e\u0639\u0650\u06c0 \u0645\u0650\u0647\u062f\u064a\u0627\u0628\u0627\u062f\u0650 \u0645\u064f\u0633\u062a\u064f\u0648\u0641\u06cc"
    ],
    "name:fas_x_variant":[
        "Mazra\u2018eh-ye Mehd\u012b\u0101b\u0101d-e Mostowf\u012b",
        "Mehd\u012b\u0101b\u0101d",
        "\u0645\u0647\u062f\u06cc \u0622\u0628\u0627\u062f",
        "\u0645\u0647\u062f\u06cc \u0622\u0628\u0627\u062f \u0645\u0633\u062a\u0648\u0641\u06cc",
        "\u0645\u0632\u0631\u0639\u0647 \u0645\u0633\u062a\u0648\u0641\u06cc"
    ],
    "name:und_x_variant":[
        "Mehd\u012b\u0101b\u0101d-e Mostowf\u012b",
        "Mazra\u2018eh-ye Mastowf\u012b"
    ],
    "wof:name":"Mehdiabad-e Mostowfi",
    "wof:placetype":"locality"
},
  "geometry": {"coordinates":[54.16724,31.63683],"type":"Point"}
}