{
  "type": "Feature",
  "properties": {
    "gn:admin1_code":"35.0",
    "gn:asciiname":"Kharabeh Khvoshrud Pey",
    "gn:country_code":"IR",
    "gn:dem":76,
    "gn:feature_class":"P",
    "gn:feature_code":"PPL",
    "gn:name":"Khar\u0101beh Khvoshr\u016bd Pey",
    "gn:population":0,
    "gn:timezone":"Asia/Tehran",
    "iso:country":"IR",
    "name:ceb_x_preferred":[
        "Khar\u0101beh Khvoshr\u016bd Pey"
    ],
    "name:fas_x_preferred":[
        "\u062e\u064f\u0634\u0643\u0631\u0648\u062f \u067e\u0650\u06cc"
    ],
    "name:fas_x_variant":[
        "Khoshkr\u016bd Pey",
        "Khar\u0101beh Khvoshr\u016bd Pey",
        "\u062e\u0631\u0627\u0628\u0647 \u062e\u0648\u0634\u0631\u0648\u062f \u067e\u06cc",
        "\u062e\u0631\u0627\u0628\u0647 \u062e\u0648\u0634\u200c\u0631\u0648\u062f\u067e\u06cc"
    ],
    "name:mzn_x_preferred":[
        "\u062e\u0631\u0627\u0628\u0647 \u062e\u0648\u0634\u200c\u0631\u0648\u062f\u067e\u06cc"
    ],
    "name:swe_x_preferred":[
        "Khar\u0101beh Khvoshr\u016bd Pey"
    ],
    "wof:name":"Kharabeh Khvoshrud Pey",
    "wof:placetype":"locality"
},
  "geometry": {"coordinates":[52.54648,36.38078],"type":"Point"}
}