{
  "type": "Feature",
  "properties": {
    "gn:admin1_code":"1.0",
    "gn:asciiname":"`Eyshabad",
    "gn:country_code":"IR",
    "gn:dem":1555,
    "gn:feature_class":"P",
    "gn:feature_code":"PPL",
    "gn:name":"\u2018Eysh\u0101b\u0101d",
    "gn:population":0,
    "gn:timezone":"Asia/Tehran",
    "iso:country":"IR",
    "name:fas_x_preferred":[
        "\u0639\u06cc\u0634 \u0622\u0628\u0627\u062f"
    ],
    "name:fas_x_variant":[
        "\u2018Eysh\u0101b\u0101d"
    ],
    "wof:name":"`Eyshabad",
    "wof:placetype":"locality"
},
  "geometry": {"coordinates":[46.0032,36.4671],"type":"Point"}
}