{
  "type": "Feature",
  "properties": {
    "gn:admin1_code":"4.0",
    "gn:asciiname":"Mir Gol-e Kalati",
    "gn:country_code":"IR",
    "gn:dem":478,
    "gn:feature_class":"P",
    "gn:feature_code":"PPL",
    "gn:name":"M\u012br Gol-e Kal\u0101t\u012b",
    "gn:population":0,
    "gn:timezone":"Asia/Tehran",
    "iso:country":"IR",
    "name:fas_x_preferred":[
        "\u0645\u06cc\u0631 \u06af\u0644 \u06a9\u0644\u0627\u062a\u06cc"
    ],
    "name:fas_x_variant":[
        "M\u012br Gol-e Kal\u0101t\u012b"
    ],
    "wof:name":"Mir Gol-e Kalati",
    "wof:placetype":"locality"
},
  "geometry": {"coordinates":[61.5831,31.2352],"type":"Point"}
}