{
  "type": "Feature",
  "properties": {
    "gn:admin1_code":"4.0",
    "gn:asciiname":"Negur",
    "gn:country_code":"IR",
    "gn:dem":29,
    "gn:feature_class":"P",
    "gn:feature_code":"PPL",
    "gn:name":"Neg\u016br",
    "gn:population":0,
    "gn:timezone":"Asia/Tehran",
    "iso:country":"IR",
    "name:fas_x_preferred":[
        "Neg\u016br"
    ],
    "name:fas_x_variant":[
        "\u0646\u06af\u0648\u0631"
    ],
    "name:und_x_variant":[
        "Nigor",
        "N\u012bgv\u0101r",
        "N\u012b Kor",
        "\u0646\u06af\u0648\u0631"
    ],
    "wof:name":"Negur",
    "wof:placetype":"locality"
},
  "geometry": {"coordinates":[61.13834,25.38882000000001],"type":"Point"}
}