{
  "type": "Feature",
  "properties": {
    "gn:admin1_code":"8",
    "gn:asciiname":"Dow Keh",
    "gn:country_code":"IR",
    "gn:dem":77,
    "gn:feature_class":"P",
    "gn:feature_code":"PPL",
    "gn:name":"Dow Keh",
    "gn:population":0,
    "gn:timezone":"Asia/Tehran",
    "iso:country":"IR",
    "name:fas_x_preferred":[
        "\u062f\u0648 \u06a9\u0647"
    ],
    "wof:name":"Dow Keh",
    "wof:placetype":"locality"
},
  "geometry": {"coordinates":[48.8786,37.7946],"type":"Point"}
}