{
  "type": "Feature",
  "properties": {
    "gn:admin1_code":"28.0",
    "gn:asciiname":"Sahra Rowghan",
    "gn:country_code":"IR",
    "gn:dem":1584,
    "gn:feature_class":"P",
    "gn:feature_code":"PPL",
    "gn:name":"\u015ea\u1e29r\u0101 Rowghan",
    "gn:population":0,
    "gn:timezone":"Asia/Tehran",
    "iso:country":"IR",
    "name:fas_x_preferred":[
        "\u015ea\u1e29r\u0101 Rowghan"
    ],
    "wof:name":"Sahra Rowghan",
    "wof:placetype":"locality"
},
  "geometry": {"coordinates":[51.63278,32.63139],"type":"Point"}
}