{
  "type": "Feature",
  "properties": {
    "gn:admin1_code":"28.0",
    "gn:asciiname":"Dastjah",
    "gn:country_code":"IR",
    "gn:dem":1529,
    "gn:feature_class":"P",
    "gn:feature_code":"PPL",
    "gn:name":"Dastj\u0101h",
    "gn:population":0,
    "gn:timezone":"Asia/Tehran",
    "iso:country":"IR",
    "name:fas_x_preferred":[
        "Dastj\u0101"
    ],
    "name:fas_x_variant":[
        "\u062f\u0633\u062a\u062c\u0627",
        "\u062f\u0633\u062a\u062c\u0627\u0647"
    ],
    "name:und_x_variant":[
        "Dastej\u0101",
        "Dastj\u0101\u2019",
        "\u062f\u0633\u062a\u062c\u0627",
        "Dastj\u0101h"
    ],
    "wof:name":"Dastjah",
    "wof:placetype":"locality"
},
  "geometry": {"coordinates":[51.9468,32.53856],"type":"Point"}
}