{
  "type": "Feature",
  "properties": {
    "gn:admin1_code":"29",
    "gn:asciiname":"Sarapardeh",
    "gn:country_code":"IR",
    "gn:dem":2061,
    "gn:feature_class":"P",
    "gn:feature_code":"PPL",
    "gn:name":"Sar\u0101pardeh",
    "gn:population":0,
    "gn:timezone":"Asia/Tehran",
    "iso:country":"IR",
    "name:fas_x_preferred":[
        "Sar\u0101pardeh"
    ],
    "name:fas_x_variant":[
        "\u0633\u0631\u0627\u067e\u0631\u062f\u0647"
    ],
    "wof:name":"Sarapardeh",
    "wof:placetype":"locality"
},
  "geometry": {"coordinates":[56.71038000000001,30.9406],"type":"Point"}
}