{
  "type": "Feature",
  "properties": {
    "gn:admin1_code":"29",
    "gn:asciiname":"Tavahoma",
    "gn:country_code":"IR",
    "gn:dem":1596,
    "gn:feature_class":"P",
    "gn:feature_code":"PPL",
    "gn:name":"Tavahom\u0101",
    "gn:population":0,
    "gn:timezone":"Asia/Tehran",
    "iso:country":"IR",
    "name:fas_x_preferred":[
        "\u062a\u062d\u0645\u0627\u0642"
    ],
    "name:fas_x_variant":[
        "Ta\u1e29m\u0101q",
        "\u062a\u0648\u0647\u0645\u0627"
    ],
    "name:und_x_variant":[
        "Tavahom\u0101"
    ],
    "wof:name":"Tavahoma",
    "wof:placetype":"locality"
},
  "geometry": {"coordinates":[56.79894,28.25588],"type":"Point"}
}