{
  "type": "Feature",
  "properties": {
    "gn:admin1_code":"40",
    "gn:asciiname":"Samku'iyeh",
    "gn:country_code":"IR",
    "gn:dem":1762,
    "gn:feature_class":"P",
    "gn:feature_code":"PPLF",
    "gn:name":"Samk\u016b\u2019\u012byeh",
    "gn:population":0,
    "gn:timezone":"Asia/Tehran",
    "iso:country":"IR",
    "name:fas_x_preferred":[
        "\u0633\u0650\u0645\u0643\u0648\u0626\u064a\u0650\u0651\u0647"
    ],
    "name:fas_x_variant":[
        "\u0632\u064a\u0631\u0643\u0648\u0626\u064a\u0650\u0651\u0647",
        "\u0633\u0650\u0631\u062a\u0650\u0634 \u0686\u064e\u0642\u0648",
        "Samk\u016b\u2019\u012byeh",
        "Z\u012brk\u016b\u2019\u012byeh",
        "Som Ku\u2019iyeh",
        "Sertesh Chaq\u016b",
        "\u0633\u064a\u0645\u06a9\u0648\u0626\u064a\u0647"
    ],
    "name:und_x_variant":[
        "Som Ku\u2019iyeh",
        "Z\u012brk\u016b\u2019\u012byeh",
        "Sertesh Chaq\u016b",
        "Sertschu",
        "S\u012bmk\u016b\u2019\u012byeh"
    ],
    "wof:name":"Samku'iyeh",
    "wof:placetype":"locality"
},
  "geometry": {"coordinates":[56.20199,31.70934],"type":"Point"}
}