{
  "type": "Feature",
  "properties": {
    "gn:admin1_code":"35.0",
    "gn:asciiname":"Danyal Peyghambar",
    "gn:country_code":"IR",
    "gn:dem":31,
    "gn:feature_class":"P",
    "gn:feature_code":"PPL",
    "gn:name":"D\u0101ny\u0101l Peyghambar",
    "gn:population":0,
    "gn:timezone":"Asia/Tehran",
    "iso:country":"IR",
    "name:fas_x_preferred":[
        "\u062f\u0627\u0646\u064a\u0627\u0644"
    ],
    "name:fas_x_variant":[
        "\u062f\u0627\u0646\u064a\u0627",
        "D\u0101n\u012b\u0101l",
        "\u062f\u0627\u0646\u06cc\u0627\u0644 \u067e\u06cc\u063a\u0645\u0628\u0631"
    ],
    "name:und_x_variant":[
        "D\u0101ney\u0101",
        "D\u0101n\u012b\u0101",
        "D\u0101ny\u0101l Peyghambar"
    ],
    "wof:name":"Danyal Peyghambar",
    "wof:placetype":"locality"
},
  "geometry": {"coordinates":[51.18567,36.67974],"type":"Point"}
}