{
  "type": "Feature",
  "properties": {
    "gn:admin1_code":"29",
    "gn:asciiname":"Sagurch-e Haftad Mish",
    "gn:country_code":"IR",
    "gn:dem":1864,
    "gn:feature_class":"P",
    "gn:feature_code":"PPL",
    "gn:name":"S\u0101g\u016brch-e Haft\u0101d M\u012bsh",
    "gn:population":0,
    "gn:timezone":"Asia/Tehran",
    "iso:country":"IR",
    "name:fas_x_preferred":[
        "\u0633\u0627\u06af\u0648\u0631\u0686\u0650 \u0647\u064e\u0641\u062a\u0627\u062f \u0645\u064a\u0634"
    ],
    "name:fas_x_variant":[
        "\u0633\u0627\u06af\u0648\u0631\u0686 \u0647\u064e\u0641\u062a\u0627\u062f\u0645\u064a\u0634",
        "\u0647\u064e\u0641\u062a\u0627\u062f \u0645\u064a\u0634",
        "S\u0101g\u016brch-e Haft\u0101d M\u012bsh"
    ],
    "name:und_x_variant":[
        "Haft\u0101d M\u012bsh",
        "S\u0101g\u016brch Haft\u0101dm\u012bsh"
    ],
    "wof:name":"Sagurch-e Haftad Mish",
    "wof:placetype":"locality"
},
  "geometry": {"coordinates":[57.32889,30.60167],"type":"Point"}
}