{
  "type": "Feature",
  "properties": {
    "gn:admin1_code":"4.0",
    "gn:asciiname":"Vashnam-e Shohdad",
    "gn:country_code":"IR",
    "gn:dem":25,
    "gn:feature_class":"P",
    "gn:feature_code":"PPL",
    "gn:name":"Vashn\u0101m-e Shohd\u0101d",
    "gn:population":0,
    "gn:timezone":"Asia/Tehran",
    "iso:country":"IR",
    "name:fas_x_preferred":[
        "\u0648\u0634\u0646\u0627\u0645"
    ],
    "name:fas_x_variant":[
        "Vashn\u0101m",
        "\u0648\u0634\u0646\u0627\u0645 \u0634\u0647\u062f\u0627\u062f"
    ],
    "name:und_x_variant":[
        "Vashn\u0101m-e \u1e28\u0101j \u2018Abdoll\u0101h",
        "Vashn\u0101m-e Shohd\u0101d"
    ],
    "wof:name":"Vashnam-e Shohdad",
    "wof:placetype":"locality"
},
  "geometry": {"coordinates":[60.8601,25.4386],"type":"Point"}
}