{
  "type": "Feature",
  "properties": {
    "gn:admin1_code":"23",
    "gn:asciiname":"Elyasabad",
    "gn:country_code":"IR",
    "gn:dem":1601,
    "gn:feature_class":"P",
    "gn:feature_code":"PPL",
    "gn:name":"Ely\u0101s\u0101b\u0101d",
    "gn:population":0,
    "gn:timezone":"Asia/Tehran",
    "iso:country":"IR",
    "name:fas_x_preferred":[
        "\u0627\u0650\u0644\u064a\u0627\u0633 \u0622\u0628\u0627\u062f"
    ],
    "name:fas_x_variant":[
        "Ely\u0101s\u0101b\u0101d"
    ],
    "wof:name":"Elyasabad",
    "wof:placetype":"locality"
},
  "geometry": {"coordinates":[48.20611,33.89333],"type":"Point"}
}