{
  "type": "Feature",
  "properties": {
    "gn:admin1_code":"42.0",
    "gn:asciiname":"Ardameh",
    "gn:country_code":"IR",
    "gn:dem":1113,
    "gn:feature_class":"P",
    "gn:feature_code":"PPL",
    "gn:name":"Ard\u0101meh",
    "gn:population":0,
    "gn:timezone":"Asia/Tehran",
    "iso:country":"IR",
    "name:fas_x_preferred":[
        "\u0627\u0631\u062f\u0645\u0647"
    ],
    "name:fas_x_variant":[
        "\u0627\u0631\u062f\u0627\u0645\u0647"
    ],
    "name:und_x_variant":[
        "Ardaheh",
        "Ardameh",
        "Ard\u0101meh"
    ],
    "wof:name":"Ardameh",
    "wof:placetype":"locality"
},
  "geometry": {"coordinates":[58.54334,36.03303],"type":"Point"}
}