{
  "type": "Feature",
  "properties": {
    "gn:admin1_code":"36",
    "gn:asciiname":"Kashkeh Var",
    "gn:country_code":"IR",
    "gn:dem":445,
    "gn:feature_class":"P",
    "gn:feature_code":"PPL",
    "gn:name":"Kashkeh Var",
    "gn:population":0,
    "gn:timezone":"Asia/Tehran",
    "iso:country":"IR",
    "name:fas_x_preferred":[
        "\u0643\u0634\u0643\u0648\u0631"
    ],
    "name:fas_x_variant":[
        "\u06a9\u0634\u06a9\u0647 \u0648\u0631"
    ],
    "name:und_x_variant":[
        "Kashkevar",
        "Kashkeh Var"
    ],
    "wof:name":"Kashkeh Var",
    "wof:placetype":"locality"
},
  "geometry": {"coordinates":[49.1441,36.7614],"type":"Point"}
}