{
  "type": "Feature",
  "properties": {
    "gn:admin1_code":"4",
    "gn:asciiname":"Siahukan",
    "gn:country_code":"IR",
    "gn:dem":895,
    "gn:feature_class":"P",
    "gn:feature_code":"PPL",
    "gn:name":"S\u012b\u0101h\u016bk\u0101n",
    "gn:population":0,
    "gn:timezone":"Asia/Tehran",
    "iso:country":"IR",
    "name:fas_x_preferred":[
        "\u062e\u06cc\u0631 \u0622\u0628\u0627\u062f \u0628\u0627\u0644\u0627"
    ],
    "name:fas_x_variant":[
        "Kheyr\u0101b\u0101d-e B\u0101l\u0101",
        "\u0633\u06cc\u0627\u0647\u0648\u06a9\u0627\u0646",
        "\u0633\u06cc\u0627\u0647\u06a9\u0627\u0646"
    ],
    "name:und_x_variant":[
        "S\u012b\u0101h\u016bk\u0101n",
        "S\u012b\u0101hk\u0101n"
    ],
    "wof:name":"Siahukan",
    "wof:placetype":"locality"
},
  "geometry": {"coordinates":[59.42409,26.65766],"type":"Point"}
}