{
  "type": "Feature",
  "properties": {
    "gn:admin1_code":"29",
    "gn:asciiname":"Darbidu'iyeh",
    "gn:country_code":"IR",
    "gn:dem":2234,
    "gn:feature_class":"P",
    "gn:feature_code":"PPL",
    "gn:name":"Darb\u012bd\u016b\u2019\u012byeh",
    "gn:population":0,
    "gn:timezone":"Asia/Tehran",
    "iso:country":"IR",
    "name:fas_x_preferred":[
        "\u062f\u0631\u0628\u06cc\u062f\u0648\u0626\u06cc\u0647"
    ],
    "name:fas_x_variant":[
        "Darb\u012bd\u016b\u2019\u012byeh"
    ],
    "name:und_x_variant":[
        "B\u012bd\u016b\u2019\u012byeh",
        "B\u012bdu"
    ],
    "wof:name":"Darbidu'iyeh",
    "wof:placetype":"locality"
},
  "geometry": {"coordinates":[55.0923,30.4871],"type":"Point"}
}