{
  "type": "Feature",
  "properties": {
    "gn:admin1_code":"11",
    "gn:asciiname":"Mohebbi",
    "gn:country_code":"IR",
    "gn:dem":912,
    "gn:feature_class":"P",
    "gn:feature_code":"PPL",
    "gn:name":"Mo\u1e29ebb\u012b",
    "gn:population":0,
    "gn:timezone":"Asia/Tehran",
    "iso:country":"IR",
    "name:fas_x_preferred":[
        "\u0645\u062d\u0628\u06cc"
    ],
    "name:fas_x_variant":[
        "Mo\u1e29ebb\u012b"
    ],
    "name:msa_x_preferred":[
        "Mohebbi"
    ],
    "wof:name":"Mohebbi",
    "wof:placetype":"locality"
},
  "geometry": {"coordinates":[56.7194,27.9109],"type":"Point"}
}