{
  "type": "Feature",
  "properties": {
    "gn:admin1_code":"28",
    "gn:asciiname":"Sar Chaqa",
    "gn:country_code":"IR",
    "gn:dem":2324,
    "gn:feature_class":"P",
    "gn:feature_code":"PPL",
    "gn:name":"Sar Chaq\u0101",
    "gn:population":0,
    "gn:timezone":"Asia/Tehran",
    "iso:country":"IR",
    "name:ara_x_preferred":[
        "\u0633\u0631\u062a\u0634\u063a\u0627"
    ],
    "name:fas_x_preferred":[
        "Sar Chaq\u0101"
    ],
    "name:fas_x_variant":[
        "Sarchogh\u0101 P\u0101\u2019\u012bn",
        "\u0633\u0631 \u0686\u0642\u0627",
        "\u0633\u0631\u0686\u063a\u0627"
    ],
    "name:und_x_variant":[
        "Qerekhl\u016b",
        "Sar Cheq\u0101 P\u0101\u2019\u012bn"
    ],
    "wof:name":"Sar Chaqa",
    "wof:placetype":"locality"
},
  "geometry": {"coordinates":[51.53583,31.64116],"type":"Point"}
}