{
  "type": "Feature",
  "properties": {
    "gn:admin1_code":"33",
    "gn:asciiname":"Huri",
    "gn:country_code":"IR",
    "gn:dem":1717,
    "gn:feature_class":"P",
    "gn:feature_code":"PPL",
    "gn:name":"\u1e28\u016br\u012b",
    "gn:population":0,
    "gn:timezone":"Asia/Tehran",
    "iso:country":"IR",
    "name:ara_x_preferred":[
        "\u0647\u0648\u0631\u064a"
    ],
    "name:fas_x_preferred":[
        "\u062d\u0648\u0631\u06cc"
    ],
    "name:fas_x_variant":[
        "\u1e28\u016br\u012b"
    ],
    "name:msa_x_preferred":[
        "Huri"
    ],
    "name:und_x_variant":[
        "D\u012blanch\u012b-ye Arkh\u012b-ye P\u0101\u2019\u012bn"
    ],
    "wof:name":"Huri",
    "wof:placetype":"locality"
},
  "geometry": {"coordinates":[46.05075,37.54362],"type":"Point"}
}