{
  "type": "Feature",
  "properties": {
    "gn:admin1_code":"23",
    "gn:asciiname":"Chenar Modavi-ye Pa'in",
    "gn:country_code":"IR",
    "gn:dem":1355,
    "gn:feature_class":"P",
    "gn:feature_code":"PPL",
    "gn:name":"Chen\u0101r Modav\u012b-ye P\u0101\u2019\u012bn",
    "gn:population":0,
    "gn:timezone":"Asia/Tehran",
    "iso:country":"IR",
    "name:fas_x_preferred":[
        "\u0686\u0646\u0627\u0631 \u0645\u062f\u0648\u06cc"
    ],
    "name:fas_x_variant":[
        "\u0686\u0646\u0627\u0631 \u0645\u062f\u0648\u06cc \u067e\u0627\u0626\u06cc\u0646"
    ],
    "name:und_x_variant":[
        "Chen\u0101r-e Modav\u012b",
        "Chen\u0101r Modav\u012b-ye P\u0101\u2019\u012bn"
    ],
    "wof:name":"Chenar Modavi-ye Pa'in",
    "wof:placetype":"locality"
},
  "geometry": {"coordinates":[47.57262,33.90521],"type":"Point"}
}