{
  "type": "Feature",
  "properties": {
    "gn:admin1_code":"33",
    "gn:asciiname":"Beyg Kandi",
    "gn:country_code":"IR",
    "gn:dem":1680,
    "gn:feature_class":"P",
    "gn:feature_code":"PPL",
    "gn:name":"Beyg Kand\u012b",
    "gn:population":0,
    "gn:timezone":"Asia/Tehran",
    "iso:country":"IR",
    "name:fas_x_preferred":[
        "\u0628\u06cc\u06af \u06a9\u0646\u062f\u06cc"
    ],
    "name:fas_x_variant":[
        "Beyg Kand\u012b R\u016bd",
        "Beyg Kand\u012b",
        "\u0628\u06cc\u06a9 \u06a9\u0646\u062f\u06cc"
    ],
    "name:und_x_variant":[
        "Beyk Kand\u012b"
    ],
    "wof:name":"Beyg Kandi",
    "wof:placetype":"locality"
},
  "geometry": {"coordinates":[46.9215,37.5467],"type":"Point"}
}