{
  "type": "Feature",
  "properties": {
    "gn:admin1_code":"5.0",
    "gn:asciiname":"Karali",
    "gn:country_code":"IR",
    "gn:dem":2122,
    "gn:feature_class":"P",
    "gn:feature_code":"PPL",
    "gn:name":"K\u0101r\u0101l\u012b",
    "gn:population":0,
    "gn:timezone":"Asia/Tehran",
    "iso:country":"IR",
    "name:fas_x_preferred":[
        "K\u0101r\u0101l\u012b"
    ],
    "name:fas_x_variant":[
        "\u06a9\u0627\u0631\u0627\u0644\u06cc"
    ],
    "name:und_x_variant":[
        "\u06a9\u0627\u0631\u0627\u0644\u06cc"
    ],
    "wof:name":"Karali",
    "wof:placetype":"locality"
},
  "geometry": {"coordinates":[51.38327,30.56901],"type":"Point"}
}