{
  "type": "Feature",
  "properties": {
    "gn:admin1_code":"5.0",
    "gn:asciiname":"Karali",
    "gn:country_code":"IR",
    "gn:dem":2122,
    "gn:feature_class":"P",
    "gn:feature_code":"PPL",
    "gn:name":"K\u0101r\u0101l\u012b",
    "gn:population":0,
    "gn:timezone":"Asia/Tehran",
    "iso:country":"IR",
    "name:ara_x_preferred":[
        "\u0643\u0627\u0631\u0627\u0644\u064a"
    ],
    "name:bul_x_preferred":[
        "\u041a\u0430\u0440\u0430\u043b\u0438"
    ],
    "name:fas_x_preferred":[
        "K\u0101r\u0101l\u012b"
    ],
    "name:fas_x_variant":[
        "\u06a9\u0627\u0631\u0627\u0644\u06cc"
    ],
    "name:fra_x_preferred":[
        "Famille Karali"
    ],
    "name:kaz_x_preferred":[
        "\u041a\u0430\u0440\u0430\u043b\u0438"
    ],
    "name:pol_x_preferred":[
        "Karali"
    ],
    "name:ron_x_preferred":[
        "Karali"
    ],
    "name:rus_x_preferred":[
        "\u041a\u0430\u0440\u0430\u043b\u0438"
    ],
    "name:ukr_x_preferred":[
        "\u041a\u0430\u0440\u0430\u043b\u0438"
    ],
    "wof:name":"Karali",
    "wof:placetype":"locality"
},
  "geometry": {"coordinates":[51.38327,30.56901],"type":"Point"}
}