{
  "type": "Feature",
  "properties": {
    "gn:admin1_code":"11",
    "gn:asciiname":"Bidan",
    "gn:country_code":"IR",
    "gn:dem":491,
    "gn:feature_class":"P",
    "gn:feature_code":"PPL",
    "gn:name":"B\u012bd\u0101n",
    "gn:population":0,
    "gn:timezone":"Asia/Tehran",
    "iso:country":"IR",
    "name:deu_x_preferred":[
        "Bidan"
    ],
    "name:fas_x_preferred":[
        "\u0628\u064a\u062f\u0627\u0646"
    ],
    "name:fas_x_variant":[
        "B\u012bd\u0101n"
    ],
    "wof:name":"Bidan",
    "wof:placetype":"locality"
},
  "geometry": {"coordinates":[57.2383,27.7243],"type":"Point"}
}