{
  "type": "Feature",
  "properties": {
    "gn:admin1_code":"35.0",
    "gn:asciiname":"Kamangar Kola",
    "gn:country_code":"IR",
    "gn:dem":60,
    "gn:feature_class":"P",
    "gn:feature_code":"PPL",
    "gn:name":"Kam\u0101ngar Kol\u0101",
    "gn:population":0,
    "gn:timezone":"Asia/Tehran",
    "iso:country":"IR",
    "name:fas_x_preferred":[
        "\u0643\u0645\u0627\u0646\u06af\u0631 \u0643\u0644\u0627"
    ],
    "name:fas_x_variant":[
        "Kam\u0101ngar Kol\u0101"
    ],
    "wof:name":"Kamangar Kola",
    "wof:placetype":"locality"
},
  "geometry": {"coordinates":[52.38169,36.49793],"type":"Point"}
}