{
  "type": "Feature",
  "properties": {
    "gn:admin1_code":"29",
    "gn:asciiname":"Bonava-ye Pa'in",
    "gn:country_code":"IR",
    "gn:dem":2273,
    "gn:feature_class":"P",
    "gn:feature_code":"PPL",
    "gn:name":"Bonav\u0101-ye P\u0101\u2019\u012bn",
    "gn:population":0,
    "gn:timezone":"Asia/Tehran",
    "iso:country":"IR",
    "name:fas_x_preferred":[
        "Behn\u016b\u0101 P\u0101\u2019\u012bn"
    ],
    "name:fas_x_variant":[
        "\u0628\u0646\u0648\u0627 \u067e\u0627\u064a\u064a\u0646",
        "\u0628\u0646\u0648\u0627"
    ],
    "name:und_x_variant":[
        "Bonav\u0101-ye P\u0101\u2019\u012bn",
        "B\u012bnav\u0101",
        "Bonav\u0101"
    ],
    "wof:name":"Bonava-ye Pa'in",
    "wof:placetype":"locality"
},
  "geometry": {"coordinates":[55.06312,30.46936],"type":"Point"}
}