{
  "type": "Feature",
  "properties": {
    "gn:admin1_code":"23",
    "gn:asciiname":"Sar Taq",
    "gn:country_code":"IR",
    "gn:dem":1151,
    "gn:feature_class":"P",
    "gn:feature_code":"PPL",
    "gn:name":"Sar \u0162\u0101q",
    "gn:population":0,
    "gn:timezone":"Asia/Tehran",
    "iso:country":"IR",
    "name:fas_x_preferred":[
        "Sar \u0162\u0101q"
    ],
    "name:fas_x_variant":[
        "\u0633\u0631 \u0637\u0627\u0642"
    ],
    "wof:name":"Sar Taq",
    "wof:placetype":"locality"
},
  "geometry": {"coordinates":[48.2969,33.43776],"type":"Point"}
}