{
  "type": "Feature",
  "properties": {
    "gn:admin1_code":"8",
    "gn:asciiname":"Karsidan",
    "gn:country_code":"IR",
    "gn:dem":-13,
    "gn:feature_class":"P",
    "gn:feature_code":"PPL",
    "gn:name":"K\u0101rs\u012bd\u0101n",
    "gn:population":0,
    "gn:timezone":"Asia/Tehran",
    "iso:country":"IR",
    "name:ara_x_preferred":[
        "\u0643\u0627\u0631\u0633\u064a\u062f\u0627\u0646"
    ],
    "name:ceb_x_preferred":[
        "K\u0101rs\u012bd\u0101n"
    ],
    "name:fas_x_preferred":[
        "K\u0101rs\u012bd\u0101n"
    ],
    "name:fas_x_variant":[
        "\u06a9\u0627\u0631\u0633\u06cc\u062f\u0627\u0646"
    ],
    "name:msa_x_preferred":[
        "Karsidan"
    ],
    "name:por_x_preferred":[
        "Karsidan"
    ],
    "name:swe_x_preferred":[
        "K\u0101rs\u012bd\u0101n"
    ],
    "name:ukr_x_preferred":[
        "\u041a\u0430\u0440\u0441\u0456\u0434\u0430\u043d"
    ],
    "wof:name":"Karsidan",
    "wof:placetype":"locality"
},
  "geometry": {"coordinates":[49.99495,37.30571],"type":"Point"}
}