{
  "type": "Feature",
  "properties": {
    "gn:admin1_code":"15",
    "gn:asciiname":"Darreh Lir",
    "gn:country_code":"IR",
    "gn:dem":506,
    "gn:feature_class":"P",
    "gn:feature_code":"PPL",
    "gn:name":"Darreh L\u012br",
    "gn:population":0,
    "gn:timezone":"Asia/Tehran",
    "iso:country":"IR",
    "name:fas_x_preferred":[
        "\u062f\u0631\u0651\u0647 \u0644\u06cc\u0631"
    ],
    "name:fas_x_variant":[
        "Darreh L\u012br"
    ],
    "wof:name":"Darreh Lir",
    "wof:placetype":"locality"
},
  "geometry": {"coordinates":[50.407,30.6064],"type":"Point"}
}