{
  "type": "Feature",
  "properties": {
    "gn:admin1_code":"39",
    "gn:asciiname":"Giv",
    "gn:country_code":"IR",
    "gn:dem":1668,
    "gn:feature_class":"P",
    "gn:feature_code":"PPL",
    "gn:name":"G\u012bv",
    "gn:population":0,
    "gn:timezone":"Asia/Tehran",
    "iso:country":"IR",
    "name:fas_x_preferred":[
        "\u06af\u064a\u0648"
    ],
    "name:fas_x_variant":[
        "\u06af\u064a\u0631",
        "G\u012bv",
        "\u06af\u06cc\u0648"
    ],
    "name:und_x_variant":[
        "G\u012br"
    ],
    "wof:name":"Giv",
    "wof:placetype":"locality"
},
  "geometry": {"coordinates":[50.27116,34.54741],"type":"Point"}
}