{
  "type": "Feature",
  "properties": {
    "gn:admin1_code":"29.0",
    "gn:asciiname":"Posht-e Bari",
    "gn:country_code":"IR",
    "gn:dem":1047,
    "gn:feature_class":"P",
    "gn:feature_code":"PPL",
    "gn:name":"Posht-e Bar\u012b",
    "gn:population":0,
    "gn:timezone":"Asia/Tehran",
    "iso:country":"IR",
    "name:fas_x_preferred":[
        "\u067e\u0634\u062a \u0628\u0631\u06cc"
    ],
    "name:und_x_variant":[
        "Posht-e Bar\u012b"
    ],
    "wof:name":"Posht-e Bari",
    "wof:placetype":"locality"
},
  "geometry": {"coordinates":[56.39558,28.43042],"type":"Point"}
}