{
  "type": "Feature",
  "properties": {
    "gn:admin1_code":"7",
    "gn:asciiname":"Pehun",
    "gn:country_code":"IR",
    "gn:dem":1236,
    "gn:feature_class":"P",
    "gn:feature_code":"PPL",
    "gn:name":"Peh\u016bn",
    "gn:population":0,
    "gn:timezone":"Asia/Tehran",
    "iso:country":"IR",
    "name:fas_x_preferred":[
        "Peh\u016bn"
    ],
    "name:fas_x_variant":[
        "\u067e\u0647\u0648\u0646"
    ],
    "name:msa_x_preferred":[
        "Pehun"
    ],
    "name:und_x_variant":[
        "\u067e\u0647\u0648\u0646"
    ],
    "wof:name":"Pehun",
    "wof:placetype":"locality"
},
  "geometry": {"coordinates":[51.30295,30.49746],"type":"Point"}
}