{
  "type": "Feature",
  "properties": {
    "gn:admin1_code":"30",
    "gn:asciiname":"Farkhan-e Sofla",
    "gn:country_code":"IR",
    "gn:dem":1417,
    "gn:feature_class":"P",
    "gn:feature_code":"PPL",
    "gn:name":"Farkh\u0101n-e Sofl\u00e1",
    "gn:population":0,
    "gn:timezone":"Asia/Tehran",
    "iso:country":"IR",
    "name:fas_x_preferred":[
        "\u0641\u0631\u062e\u0627\u0646 \u0633\u0641\u0644\u06cc"
    ],
    "wof:name":"Farkhan-e Sofla",
    "wof:placetype":"locality"
},
  "geometry": {"coordinates":[58.61666999999999,37.06667],"type":"Point"}
}