{
  "type": "Feature",
  "properties": {
    "gn:admin1_code":"8.0",
    "gn:asciiname":"Motla Kuh",
    "gn:country_code":"IR",
    "gn:dem":1342,
    "gn:feature_class":"P",
    "gn:feature_code":"PPL",
    "gn:name":"Mo\u0163l\u0101 K\u016bh",
    "gn:population":0,
    "gn:timezone":"Asia/Tehran",
    "iso:country":"IR",
    "name:ara_x_preferred":[
        "\u0645\u0637\u0644\u0627\u06a9\u0648\u0629"
    ],
    "name:fas_x_preferred":[
        "Mo\u0163l\u0101 K\u016bh"
    ],
    "name:fas_x_variant":[
        "\u0645\u0637\u0644\u0627 \u06a9\u0648\u0647",
        "\u0645\u0637\u0644\u0627\u06a9\u0648\u0647"
    ],
    "name:msa_x_preferred":[
        "Motla Kuh"
    ],
    "name:ukr_x_preferred":[
        "\u041c\u0430\u0442\u043b\u0430-\u041a\u0443\u0445"
    ],
    "name:und_x_variant":[
        "\u0645\u0637\u0644\u0627 \u06a9\u0648\u0647"
    ],
    "wof:name":"Motla Kuh",
    "wof:placetype":"locality"
},
  "geometry": {"coordinates":[50.12939,36.8785],"type":"Point"}
}