{
  "type": "Feature",
  "properties": {
    "gn:admin1_code":"4",
    "gn:asciiname":"Chah-e Petali-ye Jabrabad",
    "gn:cc2":"IR",
    "gn:country_code":"IR",
    "gn:dem":403,
    "gn:feature_class":"P",
    "gn:feature_code":"PPL",
    "gn:name":"Ch\u0101h-e Pet\u0101l\u012b-ye Jabr\u0101b\u0101d",
    "gn:population":0,
    "gn:timezone":"Asia/Tehran",
    "iso:country":"IR",
    "name:fas_x_preferred":[
        "Ch\u0101h-e Pet\u0101l\u012b-ye Jabr\u0101b\u0101d"
    ],
    "name:und_x_variant":[
        "Ch\u0101h-e Bet\u0101l"
    ],
    "wof:name":"Chah-e Petali-ye Jabrabad",
    "wof:placetype":"locality"
},
  "geometry": {"coordinates":[59.63333000000001,27.41667],"type":"Point"}
}