{
  "type": "Feature",
  "properties": {
    "gn:admin1_code":"11",
    "gn:asciiname":"Benahbani",
    "gn:country_code":"IR",
    "gn:dem":487,
    "gn:feature_class":"P",
    "gn:feature_code":"PPL",
    "gn:name":"Benahb\u0101n\u012b",
    "gn:population":0,
    "gn:timezone":"Asia/Tehran",
    "iso:country":"IR",
    "name:fas_x_preferred":[
        "\u0628\u0650\u0646\u064e\u0647\u0628\u0627\u0646\u06cc"
    ],
    "name:fas_x_variant":[
        "Benahb\u0101n\u012b"
    ],
    "wof:name":"Benahbani",
    "wof:placetype":"locality"
},
  "geometry": {"coordinates":[57.36556,26.66778],"type":"Point"}
}