{
  "type": "Feature",
  "properties": {
    "gn:admin1_code":"8",
    "gn:asciiname":"Rang Bezhi",
    "gn:country_code":"IR",
    "gn:dem":1645,
    "gn:feature_class":"P",
    "gn:feature_code":"PPLL",
    "gn:name":"Rang Bezh\u012b",
    "gn:population":0,
    "gn:timezone":"Asia/Tehran",
    "iso:country":"IR",
    "name:fas_x_preferred":[
        "\u0631\u0646\u06af \u0628\u0698\u06cc"
    ],
    "name:fas_x_variant":[
        "Rang Bezh\u012b"
    ],
    "wof:name":"Rang Bezhi",
    "wof:placetype":"locality"
},
  "geometry": {"coordinates":[49.10382,37.1165],"type":"Point"}
}