{
  "type": "Feature",
  "properties": {
    "gn:admin1_code":"34",
    "gn:asciiname":"Qal`eh-ye Baleman",
    "gn:country_code":"IR",
    "gn:dem":2029,
    "gn:feature_class":"P",
    "gn:feature_code":"PPL",
    "gn:name":"Qal\u2018eh-ye B\u0101lem\u0101n",
    "gn:population":0,
    "gn:timezone":"Asia/Tehran",
    "iso:country":"IR",
    "name:fas_x_preferred":[
        "\u0628\u0627\u0644\u0645\u0627\u0646"
    ],
    "name:fas_x_variant":[
        "Qal\u2018eh-ye B\u0101lem\u0101n",
        "B\u0101lem\u0101n",
        "\u0642\u0644\u0639\u0647 \u0628\u0627\u0644\u0645\u0627\u0646"
    ],
    "name:und_x_variant":[
        "B\u0101l\u0101man",
        "Qal\u2018eh-ye B\u0101lm\u0101n",
        "Qal\u2018eh B\u0101lm\u0101n"
    ],
    "wof:name":"Qal`eh-ye Baleman",
    "wof:placetype":"locality"
},
  "geometry": {"coordinates":[49.33816,33.8912],"type":"Point"}
}