{
  "type": "Feature",
  "properties": {
    "gn:admin1_code":"35",
    "gn:asciiname":"Pa'in Marznak",
    "gn:country_code":"IR",
    "gn:dem":52,
    "gn:feature_class":"P",
    "gn:feature_code":"PPL",
    "gn:name":"P\u0101\u2019\u012bn Marzn\u0101k",
    "gn:population":0,
    "gn:timezone":"Asia/Tehran",
    "iso:country":"IR",
    "name:fas_x_preferred":[
        "\u067e\u0627\u0626\u064a\u0646 \u0645\u0631\u0632\u0646\u0627\u06a9"
    ],
    "name:fas_x_variant":[
        "P\u0101\u2019\u012bn Marzn\u0101k"
    ],
    "name:und_x_variant":[
        "\u067e\u0627\u0626\u064a\u0646 \u0645\u064e\u0631\u0632\u0646\u0627\u0643"
    ],
    "wof:name":"Pa'in Marznak",
    "wof:placetype":"locality"
},
  "geometry": {"coordinates":[52.68708,36.39493],"type":"Point"}
}