{
  "type": "Feature",
  "properties": {
    "gn:admin1_code":"26.0",
    "gn:asciiname":"Hafeziyeh",
    "gn:country_code":"IR",
    "gn:dem":1234,
    "gn:feature_class":"P",
    "gn:feature_code":"PPL",
    "gn:name":"\u1e28\u0101fez\u0327\u012byeh",
    "gn:population":0,
    "gn:timezone":"Asia/Tehran",
    "iso:country":"IR",
    "name:fas_x_preferred":[
        "\u062d\u0627\u0641\u0650\u0638\u064a\u0650\u0651\u0647"
    ],
    "name:fas_x_variant":[
        "\u1e28\u0101fez\u0327\u012byeh"
    ],
    "wof:name":"Hafeziyeh",
    "wof:placetype":"locality"
},
  "geometry": {"coordinates":[50.98028,35.72972],"type":"Point"}
}