{
  "type": "Feature",
  "properties": {
    "gn:admin1_code":"29.0",
    "gn:asciiname":"Mazra`eh-ye Abad-e Chehel Tan",
    "gn:country_code":"IR",
    "gn:dem":1380,
    "gn:feature_class":"P",
    "gn:feature_code":"PPLF",
    "gn:name":"Mazra\u2018eh-ye \u0100b\u0101d-e Chehel Tan",
    "gn:population":0,
    "gn:timezone":"Asia/Tehran",
    "iso:country":"IR",
    "name:fas_x_preferred":[
        "\u0622\u0628 \u0628\u0627\u062f \u0686\u0647\u0644 \u062a\u0646"
    ],
    "name:fas_x_variant":[
        "\u0100b B\u0101d-e Chehel Tan",
        "\u0645\u0632\u0631\u0639\u0647 \u0622\u0628\u0627\u062f \u0686\u0647\u0644 \u062a\u0646"
    ],
    "name:und_x_variant":[
        "\u0100b\u0101d Chehel Tan",
        "Mazra\u2018eh-ye \u0100b\u0101d-e Chehel Tan"
    ],
    "wof:name":"Mazra`eh-ye Abad-e Chehel Tan",
    "wof:placetype":"locality"
},
  "geometry": {"coordinates":[58.5302,28.5151],"type":"Point"}
}