{
  "type": "Feature",
  "properties": {
    "gn:admin1_code":"15",
    "gn:asciiname":"Sorkheh-ye Felih",
    "gn:country_code":"IR",
    "gn:dem":102,
    "gn:feature_class":"P",
    "gn:feature_code":"PPL",
    "gn:name":"Sorkheh-ye Fel\u012b\u1e29",
    "gn:population":0,
    "gn:timezone":"Asia/Tehran",
    "iso:country":"IR",
    "name:fas_x_preferred":[
        "Sorkheh-ye Fel\u012b\u1e29"
    ],
    "wof:name":"Sorkheh-ye Felih",
    "wof:placetype":"locality"
},
  "geometry": {"coordinates":[48.15,32.36667],"type":"Point"}
}