{
  "type": "Feature",
  "properties": {
    "gn:admin1_code":"37",
    "gn:asciiname":"Bazgir",
    "gn:country_code":"IR",
    "gn:dem":112,
    "gn:feature_class":"P",
    "gn:feature_code":"PPL",
    "gn:name":"B\u0101zg\u012br",
    "gn:population":0,
    "gn:timezone":"Asia/Tehran",
    "iso:country":"IR",
    "name:fas_x_preferred":[
        "\u0628\u0627\u0632 \u06af\u064a\u0631"
    ],
    "name:und_x_variant":[
        "B\u0101zg\u012br"
    ],
    "wof:name":"Bazgir",
    "wof:placetype":"locality"
},
  "geometry": {"coordinates":[55.35309,37.2517],"type":"Point"}
}