{
  "type": "Feature",
  "properties": {
    "gn:admin1_code":"1",
    "gn:asciiname":"Makhmur",
    "gn:country_code":"IR",
    "gn:dem":2416,
    "gn:feature_class":"P",
    "gn:feature_code":"PPL",
    "gn:name":"Makhm\u016br",
    "gn:population":0,
    "gn:timezone":"Asia/Tehran",
    "iso:country":"IR",
    "name:fas_x_preferred":[
        "Makhm\u016br"
    ],
    "name:fas_x_variant":[
        "\u0645\u062e\u0645\u0648\u0631"
    ],
    "wof:name":"Makhmur",
    "wof:placetype":"locality"
},
  "geometry": {"coordinates":[44.2698,38.8635],"type":"Point"}
}