{
  "type": "Feature",
  "properties": {
    "gn:admin1_code":"23",
    "gn:asciiname":"Cheragh`ali Zamani",
    "gn:country_code":"IR",
    "gn:dem":1330,
    "gn:feature_class":"P",
    "gn:feature_code":"PPL",
    "gn:name":"Cher\u0101gh\u2018al\u012b Zam\u0101n\u012b",
    "gn:population":0,
    "gn:timezone":"Asia/Tehran",
    "iso:country":"IR",
    "name:fas_x_preferred":[
        "\u0686\u0650\u0631\u0627\u063a\u0639\u064e\u0644\u06cc \u0632\u064e\u0645\u0627\u0646\u06cc"
    ],
    "name:fas_x_variant":[
        "Cher\u0101gh\u2018al\u012b Zam\u0101n\u012b"
    ],
    "wof:name":"Cheragh`ali Zamani",
    "wof:placetype":"locality"
},
  "geometry": {"coordinates":[47.55,33.71667],"type":"Point"}
}