{
  "type": "Feature",
  "properties": {
    "gn:admin1_code":"29",
    "gn:asciiname":"Murgan",
    "gn:country_code":"IR",
    "gn:dem":2638,
    "gn:feature_class":"P",
    "gn:feature_code":"PPL",
    "gn:name":"M\u016brgan",
    "gn:population":0,
    "gn:timezone":"Asia/Tehran",
    "iso:country":"IR",
    "name:fas_x_preferred":[
        "\u0645\u0648\u0631\u06af\u0646"
    ],
    "name:fas_x_variant":[
        "M\u016brgan"
    ],
    "wof:name":"Murgan",
    "wof:placetype":"locality"
},
  "geometry": {"coordinates":[57.35307,30.24176],"type":"Point"}
}