{
  "type": "Feature",
  "properties": {
    "gn:admin1_code":"38.0",
    "gn:asciiname":"Nosratabad-e Jadid",
    "gn:country_code":"IR",
    "gn:dem":1231,
    "gn:feature_class":"P",
    "gn:feature_code":"PPL",
    "gn:name":"No\u015frat\u0101b\u0101d-e Jad\u012bd",
    "gn:population":0,
    "gn:timezone":"Asia/Tehran",
    "iso:country":"IR",
    "name:fas_x_preferred":[
        "\u0646\u0635\u0631\u062a \u0622\u0628\u0627\u062f"
    ],
    "name:fas_x_variant":[
        "No\u015frat\u0101b\u0101d",
        "\u0646\u0635\u0631\u062a \u0622\u0628\u0627\u062f \u062c\u062f\u06cc\u062f"
    ],
    "name:und_x_variant":[
        "No\u015frat\u0101b\u0101d-e Jad\u012bd"
    ],
    "wof:name":"Nosratabad-e Jadid",
    "wof:placetype":"locality"
},
  "geometry": {"coordinates":[49.8553,36.11929],"type":"Point"}
}