{
  "type": "Feature",
  "properties": {
    "gn:admin1_code":"5.0",
    "gn:asciiname":"Dam-e Tang Asiab",
    "gn:country_code":"IR",
    "gn:dem":1997,
    "gn:feature_class":"P",
    "gn:feature_code":"PPL",
    "gn:name":"Dam-e Tang \u0100s\u012b\u0101b",
    "gn:population":0,
    "gn:timezone":"Asia/Tehran",
    "iso:country":"IR",
    "name:fas_x_preferred":[
        "Dam-e Tang \u0100s\u012b\u0101b"
    ],
    "name:fas_x_variant":[
        "\u062f\u0645 \u062a\u0646\u06af \u0622\u0633\u06cc\u0627\u0628"
    ],
    "name:und_x_variant":[
        "\u062f\u0645 \u062a\u0646\u06af \u0622\u0633\u06cc\u0627\u0628"
    ],
    "wof:name":"Dam-e Tang Asiab",
    "wof:placetype":"locality"
},
  "geometry": {"coordinates":[50.73664,31.19559000000001],"type":"Point"}
}