{
  "type": "Feature",
  "properties": {
    "gn:admin1_code":"5",
    "gn:asciiname":"Bon Zard-e Sofla",
    "gn:country_code":"IR",
    "gn:dem":1729,
    "gn:feature_class":"P",
    "gn:feature_code":"PPL",
    "gn:name":"Bon Zard-e Sofl\u00e1",
    "gn:population":0,
    "gn:timezone":"Asia/Tehran",
    "iso:country":"IR",
    "name:ara_x_preferred":[
        "\u0628\u0646 \u0632\u0631\u062f \u0627\u0644\u0633\u0641\u0644\u064a"
    ],
    "name:ceb_x_preferred":[
        "Bon Zard-e Sofl\u00e1"
    ],
    "name:fas_x_preferred":[
        "\u0628\u064f\u0646 \u0632\u064e\u0631\u062f\u0650 \u067e\u0627\u0626\u064a\u0646"
    ],
    "name:fas_x_variant":[
        "\u0628\u064f\u0646 \u0632\u064e\u0631\u062f \u0633\u064f\u0641\u0644\u064e\u0649",
        "\u0628\u064f\u0646 \u0632\u064e\u0631\u062f",
        "Bon Zard-e P\u0101\u2019\u012bn",
        "Bon Zard-e Sofl\u00e1",
        "\u0628\u0646 \u0632\u0631\u062f \u0633\u0641\u0644\u0649",
        "\u0628\u0646\u200c\u0632\u0631\u062f \u0633\u0641\u0644\u06cc"
    ],
    "name:swe_x_preferred":[
        "Bon Zard-e Sofl\u00e1"
    ],
    "name:und_x_variant":[
        "Bon Zard-e Sofl\u00e1",
        "Bon Zard Sofl\u00e1",
        "Bon Zard",
        "\u0628\u0646 \u0632\u0631\u062f \u0633\u0641\u0644\u0649"
    ],
    "wof:name":"Bon Zard-e Sofla",
    "wof:placetype":"locality"
},
  "geometry": {"coordinates":[51.28304,31.00928],"type":"Point"}
}