{
  "type": "Feature",
  "properties": {
    "gn:admin1_code":"35",
    "gn:asciiname":"Fathiabad",
    "gn:country_code":"IR",
    "gn:dem":-18,
    "gn:feature_class":"P",
    "gn:feature_code":"PPL",
    "gn:name":"Fat\u1e29\u012b\u0101b\u0101d",
    "gn:population":0,
    "gn:timezone":"Asia/Tehran",
    "iso:country":"IR",
    "name:fas_x_preferred":[
        "\u0641\u062a\u062d\u06cc \u0622\u0628\u0627\u062f"
    ],
    "name:fas_x_variant":[
        "Fat\u1e29\u012b\u0101b\u0101d"
    ],
    "wof:name":"Fathiabad",
    "wof:placetype":"locality"
},
  "geometry": {"coordinates":[53.12685,36.75987],"type":"Point"}
}