{
  "type": "Feature",
  "properties": {
    "gn:admin1_code":"5",
    "gn:asciiname":"Darreh Gepi",
    "gn:country_code":"IR",
    "gn:dem":1015,
    "gn:feature_class":"P",
    "gn:feature_code":"PPL",
    "gn:name":"Darreh Gep\u012b",
    "gn:population":0,
    "gn:timezone":"Asia/Tehran",
    "iso:country":"IR",
    "name:ara_x_preferred":[
        "\u062f\u0631\u0629 \u063a\u0628\u064a"
    ],
    "name:ceb_x_preferred":[
        "Darreh Gep\u012b"
    ],
    "name:fas_x_preferred":[
        "Darreh Gep\u012b"
    ],
    "name:fas_x_variant":[
        "\u062f\u0631\u0651\u0647 \u06af\u067e\u06cc",
        "\u062f\u0631\u0647 \u06af\u067e\u06cc"
    ],
    "name:swe_x_preferred":[
        "Darreh Gep\u012b"
    ],
    "wof:name":"Darreh Gepi",
    "wof:placetype":"locality"
},
  "geometry": {"coordinates":[50.00255,31.17814000000001],"type":"Point"}
}