{
  "type": "Feature",
  "properties": {
    "gn:admin1_code":"32.0",
    "gn:asciiname":"Mir Ashraf",
    "gn:country_code":"IR",
    "gn:dem":1346,
    "gn:feature_class":"P",
    "gn:feature_code":"PPL",
    "gn:name":"M\u012br Ashraf",
    "gn:population":0,
    "gn:timezone":"Asia/Tehran",
    "iso:country":"IR",
    "name:fas_x_preferred":[
        "M\u012br Ashraf"
    ],
    "name:fas_x_variant":[
        "\u0645\u06cc\u0631 \u0627\u0634\u0631\u0641"
    ],
    "name:und_x_variant":[
        "\u0645\u06cc\u0631 \u0627\u0634\u0631\u0641"
    ],
    "wof:name":"Mir Ashraf",
    "wof:placetype":"locality"
},
  "geometry": {"coordinates":[48.2636,38.2751],"type":"Point"}
}