{
  "type": "Feature",
  "properties": {
    "gn:admin1_code":"1",
    "gn:asciiname":"Soleyman Aghol",
    "gn:country_code":"IR",
    "gn:dem":2335,
    "gn:feature_class":"P",
    "gn:feature_code":"PPL",
    "gn:name":"Soleym\u0101n \u0100ghol",
    "gn:population":0,
    "gn:timezone":"Asia/Tehran",
    "iso:country":"IR",
    "name:fas_x_preferred":[
        "\u0633\u064f\u0644\u0650\u064a\u0645\u0627\u0646 \u0622\u063a\u064f\u0644"
    ],
    "wof:name":"Soleyman Aghol",
    "wof:placetype":"locality"
},
  "geometry": {"coordinates":[44.05389,39.38083],"type":"Point"}
}