{
  "type": "Feature",
  "properties": {
    "gn:admin1_code":"5",
    "gn:asciiname":"Chel Kareh",
    "gn:country_code":"IR",
    "gn:dem":1354,
    "gn:feature_class":"P",
    "gn:feature_code":"PPL",
    "gn:name":"Chel Kareh",
    "gn:population":0,
    "gn:timezone":"Asia/Tehran",
    "iso:country":"IR",
    "wof:name":"Chel Kareh",
    "wof:placetype":"locality"
},
  "geometry": {"coordinates":[51.29632,30.4147],"type":"Point"}
}