{
  "type": "Feature",
  "properties": {
    "gn:admin1_code":"28.0",
    "gn:asciiname":"Mulenjan",
    "gn:country_code":"IR",
    "gn:dem":1548,
    "gn:feature_class":"P",
    "gn:feature_code":"PPL",
    "gn:name":"M\u016blenj\u0101n",
    "gn:population":0,
    "gn:timezone":"Asia/Tehran",
    "iso:country":"IR",
    "name:fas_x_preferred":[
        "M\u016blenj\u0101n"
    ],
    "name:fas_x_variant":[
        "\u0645\u0648\u0644\u0646\u062c\u0627\u0646"
    ],
    "wof:name":"Mulenjan",
    "wof:placetype":"locality"
},
  "geometry": {"coordinates":[51.79708,32.71861],"type":"Point"}
}