{
  "type": "Feature",
  "properties": {
    "gn:admin1_code":"34",
    "gn:asciiname":"Qeshlaq",
    "gn:country_code":"IR",
    "gn:dem":1994,
    "gn:feature_class":"P",
    "gn:feature_code":"PPL",
    "gn:name":"Qeshl\u0101q",
    "gn:population":0,
    "gn:timezone":"Asia/Tehran",
    "iso:country":"IR",
    "name:ceb_x_preferred":[
        "Qeshlaq"
    ],
    "name:fas_x_preferred":[
        "\u0642\u0634\u0644\u0627\u0642 \u062e\u0633\u0631\u0648 \u0628\u06cc\u06a9"
    ],
    "name:fas_x_variant":[
        "Qeshl\u0101q-e Khosrow Beyk",
        "\u0642\u0634\u0644\u0627\u0642"
    ],
    "name:swe_x_preferred":[
        "Qeshlaq"
    ],
    "name:und_x_variant":[
        "Qeshl\u0101q-e Deh Zam\u0101n",
        "Qeshl\u0101q"
    ],
    "wof:name":"Qeshlaq",
    "wof:placetype":"locality"
},
  "geometry": {"coordinates":[49.27136,33.73525],"type":"Point"}
}