{
  "type": "Feature",
  "properties": {
    "gn:admin1_code":"23",
    "gn:asciiname":"Posht Heleh",
    "gn:country_code":"IR",
    "gn:dem":1450,
    "gn:feature_class":"P",
    "gn:feature_code":"PPL",
    "gn:name":"Posht Heleh",
    "gn:population":0,
    "gn:timezone":"Asia/Tehran",
    "iso:country":"IR",
    "name:fas_x_preferred":[
        "\u067e\u0634\u062a \u0647\u0644\u0647"
    ],
    "wof:name":"Posht Heleh",
    "wof:placetype":"locality"
},
  "geometry": {"coordinates":[47.5274,34.1265],"type":"Point"}
}