{
  "type": "Feature",
  "properties": {
    "gn:admin1_code":"11.0",
    "gn:asciiname":"Mantaqeh-ye Parkuchak",
    "gn:country_code":"IR",
    "gn:dem":294,
    "gn:feature_class":"P",
    "gn:feature_code":"PPL",
    "gn:name":"Man\u0163aqeh-ye Park\u016bchak",
    "gn:population":0,
    "gn:timezone":"Asia/Tehran",
    "iso:country":"IR",
    "name:fas_x_preferred":[
        "Part\u016bpak"
    ],
    "name:fas_x_variant":[
        "\u067e\u0631\u062a\u0648\u067e\u06a9",
        "\u0645\u0646\u0637\u0642\u0647 \u067e\u0631\u06a9\u0648\u0686\u06a9"
    ],
    "name:und_x_variant":[
        "Man\u0163aqeh-ye Park\u016bchak"
    ],
    "wof:name":"Mantaqeh-ye Parkuchak",
    "wof:placetype":"locality"
},
  "geometry": {"coordinates":[55.41136,27.11404000000001],"type":"Point"}
}