{
  "type": "Feature",
  "properties": {
    "gn:admin1_code":"37.0",
    "gn:asciiname":"Mazra`eh-ye Sazeman-e Barani",
    "gn:country_code":"IR",
    "gn:dem":21,
    "gn:feature_class":"P",
    "gn:feature_code":"PPL",
    "gn:name":"Mazra\u2018eh-ye S\u0101zem\u0101n-e B\u0101r\u0101n\u012b",
    "gn:population":0,
    "gn:timezone":"Asia/Tehran",
    "iso:country":"IR",
    "name:fas_x_preferred":[
        "\u0645\u0632\u0631\u0639\u0647 \u0633\u0627\u0632\u0645\u0627\u0646 \u0628\u0627\u0631\u0627\u0646\u06cc"
    ],
    "name:und_x_variant":[
        "Mazra\u2018eh-ye S\u0101zem\u0101n-e B\u0101r\u0101n\u012b"
    ],
    "wof:name":"Mazra`eh-ye Sazeman-e Barani",
    "wof:placetype":"locality"
},
  "geometry": {"coordinates":[54.84515,37.09347],"type":"Point"}
}