{
  "type": "Feature",
  "properties": {
    "gn:admin1_code":"42",
    "gn:asciiname":"Kalateh-ye Ardaj",
    "gn:country_code":"IR",
    "gn:dem":1822,
    "gn:feature_class":"P",
    "gn:feature_code":"PPL",
    "gn:name":"Kal\u0101teh-ye Ardaj",
    "gn:population":0,
    "gn:timezone":"Asia/Tehran",
    "iso:country":"IR",
    "name:fas_x_preferred":[
        "Kal\u0101teh-ye Ardaj"
    ],
    "name:fas_x_variant":[
        "\u06a9\u0644\u0627\u062a\u0647 \u0627\u0631\u062f\u062c"
    ],
    "wof:name":"Kalateh-ye Ardaj",
    "wof:placetype":"locality"
},
  "geometry": {"coordinates":[59.41039,35.42582],"type":"Point"}
}