{
  "type": "Feature",
  "properties": {
    "gn:admin1_code":"43",
    "gn:asciiname":"Daraq",
    "gn:country_code":"IR",
    "gn:dem":1082,
    "gn:feature_class":"P",
    "gn:feature_code":"PPL",
    "gn:name":"Daraq",
    "gn:population":0,
    "gn:timezone":"Asia/Tehran",
    "iso:country":"IR",
    "name:ara_x_preferred":[
        "\u062f\u0631\u0642"
    ],
    "name:aze_x_preferred":[
        "D\u0259r\u0259q"
    ],
    "name:ceb_x_preferred":[
        "Daraq"
    ],
    "name:fas_x_preferred":[
        "\u062f\u0631\u0642"
    ],
    "name:ita_x_preferred":[
        "Daraq"
    ],
    "name:mlg_x_preferred":[
        "Daraq"
    ],
    "name:swe_x_preferred":[
        "Daraq"
    ],
    "name:und_x_variant":[
        "Darreh"
    ],
    "wof:name":"Daraq",
    "wof:placetype":"locality"
},
  "geometry": {"coordinates":[56.21688,36.97103],"type":"Point"}
}