{
  "type": "Feature",
  "properties": {
    "gn:admin1_code":"5.0",
    "gn:asciiname":"Yasuj-e Sadat",
    "gn:country_code":"IR",
    "gn:dem":1934,
    "gn:feature_class":"P",
    "gn:feature_code":"PPL",
    "gn:name":"Y\u0101s\u016bj-e S\u0101d\u0101t",
    "gn:population":0,
    "gn:timezone":"Asia/Tehran",
    "iso:country":"IR",
    "name:fas_x_preferred":[
        "Y\u0101s\u016bj-e S\u0101d\u0101t"
    ],
    "name:fas_x_variant":[
        "\u06cc\u0627\u0633\u0648\u062c \u0633\u0627\u062f\u0627\u062a"
    ],
    "name:und_x_variant":[
        "\u06cc\u0627\u0633\u0648\u062c \u0633\u0627\u062f\u0627\u062a"
    ],
    "wof:name":"Yasuj-e Sadat",
    "wof:placetype":"locality"
},
  "geometry": {"coordinates":[51.60571,30.6745],"type":"Point"}
}