{
  "type": "Feature",
  "properties": {
    "gn:admin1_code":"10.0",
    "gn:asciiname":"Seh Kuran",
    "gn:country_code":"IR",
    "gn:dem":731,
    "gn:feature_class":"P",
    "gn:feature_code":"PPL",
    "gn:name":"Seh K\u016bran",
    "gn:population":0,
    "gn:timezone":"Asia/Tehran",
    "iso:country":"IR",
    "name:fas_x_preferred":[
        "\u0633\u0647 \u06a9\u0648\u0631\u0627\u0646"
    ],
    "name:fas_x_variant":[
        "Seh K\u016bran"
    ],
    "wof:name":"Seh Kuran",
    "wof:placetype":"locality"
},
  "geometry": {"coordinates":[46.1342,33.2812],"type":"Point"}
}