{
  "type": "Feature",
  "properties": {
    "gn:admin1_code":"13",
    "gn:asciiname":"Darvit",
    "gn:country_code":"IR",
    "gn:dem":1562,
    "gn:feature_class":"P",
    "gn:feature_code":"PPL",
    "gn:name":"Darv\u012bt",
    "gn:population":0,
    "gn:timezone":"Asia/Tehran",
    "iso:country":"IR",
    "name:ara_x_preferred":[
        "\u062f\u0631\u0648\u064a\u062a"
    ],
    "name:ceb_x_preferred":[
        "Darv\u012bt"
    ],
    "name:fas_x_preferred":[
        "\u062f\u0631\u0648\u06cc\u062a"
    ],
    "name:fas_x_variant":[
        "Darv\u012bt"
    ],
    "name:swe_x_preferred":[
        "Darv\u012bt"
    ],
    "name:und_x_variant":[
        "Darv\u012bd"
    ],
    "wof:name":"Darvit",
    "wof:placetype":"locality"
},
  "geometry": {"coordinates":[46.2887,34.4279],"type":"Point"}
}