{
  "type": "Feature",
  "properties": {
    "gn:admin1_code":"44",
    "gn:asciiname":"Sorheh",
    "gn:country_code":"IR",
    "gn:dem":1803,
    "gn:feature_class":"P",
    "gn:feature_code":"PPL",
    "gn:name":"Sorheh",
    "gn:population":0,
    "gn:timezone":"Asia/Tehran",
    "iso:country":"IR",
    "name:fas_x_preferred":[
        "\u0633\u0631\u0647\u0647"
    ],
    "wof:name":"Sorheh",
    "wof:placetype":"locality"
},
  "geometry": {"coordinates":[50.94951,35.97669000000001],"type":"Point"}
}