{
  "type": "Feature",
  "properties": {
    "gn:admin1_code":"34",
    "gn:asciiname":"Talkhestan-e `Olya",
    "gn:country_code":"IR",
    "gn:dem":2035,
    "gn:feature_class":"P",
    "gn:feature_code":"PPL",
    "gn:name":"Talkhest\u0101n-e \u2018Oly\u0101",
    "gn:population":0,
    "gn:timezone":"Asia/Tehran",
    "iso:country":"IR",
    "name:fas_x_preferred":[
        "\u062a\u0644\u062e\u0633\u062a\u0627\u0646"
    ],
    "name:fas_x_variant":[
        "Talkhest\u0101n",
        "Talkest\u0101n",
        "\u062a\u0644\u062e\u0633\u062a\u0627\u0646 \u0639\u0644\u064a\u0627"
    ],
    "name:und_x_variant":[
        "Qal\u2018eh-ye Kh\u0101n",
        "Qal\u2018eh Kh\u0101n",
        "Qal\u2018eh-ye Shar\u012bf Kh\u0101n",
        "Talkhest\u0101n-e \u2018Oly\u0101"
    ],
    "wof:name":"Talkhestan-e `Olya",
    "wof:placetype":"locality"
},
  "geometry": {"coordinates":[48.99261,33.78487],"type":"Point"}
}