{
  "type": "Feature",
  "properties": {
    "gn:admin1_code":"42",
    "gn:asciiname":"Piranlu",
    "gn:country_code":"IR",
    "gn:dem":1516,
    "gn:feature_class":"P",
    "gn:feature_code":"PPL",
    "gn:name":"P\u012br\u0101nl\u016b",
    "gn:population":0,
    "gn:timezone":"Asia/Tehran",
    "iso:country":"IR",
    "name:fas_x_preferred":[
        "P\u012br\u0101nl\u016b"
    ],
    "name:fas_x_variant":[
        "\u067e\u06cc\u0631\u0627\u0646\u0644\u0648"
    ],
    "name:und_x_variant":[
        "\u067e\u06cc\u0631\u0627\u0646\u0644\u0648"
    ],
    "wof:name":"Piranlu",
    "wof:placetype":"locality"
},
  "geometry": {"coordinates":[58.70339,37.20923],"type":"Point"}
}