{
  "type": "Feature",
  "properties": {
    "gn:admin1_code":"35.0",
    "gn:asciiname":"Khowsh Kola",
    "gn:country_code":"IR",
    "gn:dem":1807,
    "gn:feature_class":"P",
    "gn:feature_code":"PPL",
    "gn:name":"Khowsh Kol\u0101",
    "gn:population":0,
    "gn:timezone":"Asia/Tehran",
    "iso:country":"IR",
    "name:fas_x_preferred":[
        "\u062e\u0648\u0634 \u0643\u0644\u0627"
    ],
    "name:und_x_variant":[
        "Khowsh Kol\u0101"
    ],
    "wof:name":"Khowsh Kola",
    "wof:placetype":"locality"
},
  "geometry": {"coordinates":[51.2938,36.24184],"type":"Point"}
}