{
  "type": "Feature",
  "properties": {
    "gn:admin1_code":"7",
    "gn:asciiname":"Gol Makan-e Sofla",
    "gn:country_code":"IR",
    "gn:dem":1660,
    "gn:feature_class":"P",
    "gn:feature_code":"PPL",
    "gn:name":"Gol Mak\u0101n-e Sofl\u00e1",
    "gn:population":0,
    "gn:timezone":"Asia/Tehran",
    "iso:country":"IR",
    "name:fas_x_preferred":[
        "Gol Mak\u0101n-e P\u0101\u2019\u012bn"
    ],
    "name:fas_x_variant":[
        "\u06af\u0644 \u0645\u06a9\u0627\u0646 \u0633\u0641\u0644\u06cc",
        "Gol Mak\u0101n-e Sofl\u00e1",
        "\u06af\u0644 \u0645\u06a9\u0627\u0646 \u0628\u0627\u0635\u0631\u06cc"
    ],
    "name:msa_x_preferred":[
        "Gol Makan-e Baseri"
    ],
    "name:und_x_variant":[
        "Gol Mak\u016bn-e B\u0101\u015fer\u012b",
        "Qal\u2018eh-ye P\u0101\u2019\u012bn"
    ],
    "wof:name":"Gol Makan-e Sofla",
    "wof:placetype":"locality"
},
  "geometry": {"coordinates":[52.7307,30.1645],"type":"Point"}
}