{
  "type": "Feature",
  "properties": {
    "gn:admin1_code":"29",
    "gn:asciiname":"Jolgeh",
    "gn:country_code":"IR",
    "gn:dem":1336,
    "gn:feature_class":"P",
    "gn:feature_code":"PPLL",
    "gn:name":"Jolgeh",
    "gn:population":0,
    "gn:timezone":"Asia/Tehran",
    "iso:country":"IR",
    "name:ceb_x_preferred":[
        "Jolgeh"
    ],
    "name:fas_x_preferred":[
        "\u062c\u0644\u06af\u0647"
    ],
    "name:swe_x_preferred":[
        "Jolgeh"
    ],
    "wof:name":"Jolgeh",
    "wof:placetype":"locality"
},
  "geometry": {"coordinates":[58.4482,28.6459],"type":"Point"}
}