{
  "type": "Feature",
  "properties": {
    "gn:admin1_code":"28.0",
    "gn:asciiname":"Savand",
    "gn:country_code":"IR",
    "gn:dem":1591,
    "gn:feature_class":"P",
    "gn:feature_code":"PPL",
    "gn:name":"Savand",
    "gn:population":0,
    "gn:timezone":"Asia/Tehran",
    "iso:country":"IR",
    "name:fas_x_preferred":[
        "\u0633\u0648\u0646\u062f"
    ],
    "name:fas_x_variant":[
        "\u0633\u0627\u0648\u0646\u062f"
    ],
    "wof:name":"Savand",
    "wof:placetype":"locality"
},
  "geometry": {"coordinates":[53.1716,32.6742],"type":"Point"}
}