{
  "type": "Feature",
  "properties": {
    "gn:admin1_code":"8.0",
    "gn:asciiname":"Khorsabin-e Bala",
    "gn:country_code":"IR",
    "gn:dem":154,
    "gn:feature_class":"P",
    "gn:feature_code":"PPL",
    "gn:name":"Khors\u0101b\u012bn-e B\u0101l\u0101",
    "gn:population":0,
    "gn:timezone":"Asia/Tehran",
    "iso:country":"IR",
    "name:fas_x_preferred":[
        "Khors\u0101b\u012bn-e B\u0101l\u0101"
    ],
    "name:fas_x_variant":[
        "\u062e\u0631\u0633\u0627\u0628\u06cc\u0646 \u0628\u0627\u0644\u0627"
    ],
    "wof:name":"Khorsabin-e Bala",
    "wof:placetype":"locality"
},
  "geometry": {"coordinates":[49.62103,36.98275],"type":"Point"}
}