{
  "type": "Feature",
  "properties": {
    "gn:admin1_code":"23",
    "gn:asciiname":"Poshteh-ye `Olya",
    "gn:country_code":"IR",
    "gn:dem":1844,
    "gn:feature_class":"P",
    "gn:feature_code":"PPL",
    "gn:name":"Poshteh-ye \u2018Oly\u0101",
    "gn:population":0,
    "gn:timezone":"Asia/Tehran",
    "iso:country":"IR",
    "name:fas_x_preferred":[
        "\u067e\u0634\u062a\u0647 \u0639\u0644\u064a\u0627"
    ],
    "name:fas_x_variant":[
        "Poshteh-ye B\u0101l\u0101",
        "Poshteh-ye \u2018Oly\u0101"
    ],
    "wof:name":"Poshteh-ye `Olya",
    "wof:placetype":"locality"
},
  "geometry": {"coordinates":[48.8325,33.6418],"type":"Point"}
}