{
  "type": "Feature",
  "properties": {
    "gn:admin1_code":"4.0",
    "gn:asciiname":"Mohirpi",
    "gn:country_code":"IR",
    "gn:dem":1230,
    "gn:feature_class":"P",
    "gn:feature_code":"PPL",
    "gn:name":"Moh\u012brp\u012b",
    "gn:population":0,
    "gn:timezone":"Asia/Tehran",
    "iso:country":"IR",
    "name:fas_x_preferred":[
        "\u0645\u0647\u06cc\u0631\u067e\u06cc"
    ],
    "name:fas_x_variant":[
        "Moh\u012brp\u012b"
    ],
    "wof:name":"Mohirpi",
    "wof:placetype":"locality"
},
  "geometry": {"coordinates":[61.6047,26.5539],"type":"Point"}
}