{
  "type": "Feature",
  "properties": {
    "gn:admin1_code":"26.0",
    "gn:asciiname":"Mojtame`-e Maskuni-ye Namju",
    "gn:country_code":"IR",
    "gn:dem":1072,
    "gn:feature_class":"P",
    "gn:feature_code":"PPL",
    "gn:name":"Mojtame\u2018-e Mask\u016bn\u012b-ye N\u0101mj\u016b",
    "gn:population":0,
    "gn:timezone":"Asia/Tehran",
    "iso:country":"IR",
    "name:fas_x_preferred":[
        "Mojtame\u2018-e Mask\u016bn\u012b-ye N\u0101mj\u016b"
    ],
    "name:fas_x_variant":[
        "\u0645\u062c\u062a\u0645\u0639 \u0645\u0633\u06a9\u0648\u0646\u06cc \u0646\u0627\u0645\u062c\u0648"
    ],
    "wof:name":"Mojtame`-e Maskuni-ye Namju",
    "wof:placetype":"locality"
},
  "geometry": {"coordinates":[51.724,35.4723],"type":"Point"}
}