{
  "type": "Feature",
  "properties": {
    "gn:admin1_code":"35",
    "gn:asciiname":"Vamenan",
    "gn:cc2":"IR",
    "gn:country_code":"IR",
    "gn:dem":1313,
    "gn:feature_class":"P",
    "gn:feature_code":"PPL",
    "gn:name":"V\u0101men\u0101n",
    "gn:population":0,
    "gn:timezone":"Asia/Tehran",
    "iso:country":"IR",
    "name:fas_x_preferred":[
        "\u0648\u0627\u0645\u0650\u0646\u0627\u0646"
    ],
    "name:fas_x_variant":[
        "\u0648\u064e\u0645\u0646\u0627\u0646",
        "\u0648\u0627\u0645\u0646\u0627\u0646"
    ],
    "name:msa_x_preferred":[
        "Vamenan"
    ],
    "name:und_x_variant":[
        "Vamn\u0101n"
    ],
    "wof:name":"Vamenan",
    "wof:placetype":"locality"
},
  "geometry": {"coordinates":[55.52556,36.99167],"type":"Point"}
}