{
  "type": "Feature",
  "properties": {
    "gn:admin1_code":"34",
    "gn:asciiname":"Qal`eh-ye Samur Khan",
    "gn:country_code":"IR",
    "gn:dem":2226,
    "gn:feature_class":"P",
    "gn:feature_code":"PPL",
    "gn:name":"Qal\u2018eh-ye S\u0304am\u016br Kh\u0101n",
    "gn:population":0,
    "gn:timezone":"Asia/Tehran",
    "iso:country":"IR",
    "name:fas_x_preferred":[
        "\u0642\u0644\u0639\u0647 \u062b\u0645\u0648\u0631 \u062e\u0627\u0646"
    ],
    "name:fas_x_variant":[
        "Qam\u0101r Kh\u016bn",
        "Qal\u2018eh Sam\u016br Kh\u0101n",
        "Qal\u2018eh-ye S\u0304am\u016br Kh\u0101n",
        "\u0642\u0644\u0639\u0647 \u062b\u0645\u0631 \u062e\u0627\u0646"
    ],
    "name:ukr_x_preferred":[
        "\u041a\u0430\u043c\u0430\u0440-\u0425\u0443\u043d"
    ],
    "name:und_x_variant":[
        "Qal\u2018eh Samar Kh\u0101n",
        "Qal\u2018eh S\u0304amar Kh\u0101n"
    ],
    "wof:name":"Qal`eh-ye Samur Khan",
    "wof:placetype":"locality"
},
  "geometry": {"coordinates":[48.9899,33.8898],"type":"Point"}
}