{
  "type": "Feature",
  "properties": {
    "gn:admin1_code":"8",
    "gn:asciiname":"Jelveh Khvar",
    "gn:country_code":"IR",
    "gn:dem":1326,
    "gn:feature_class":"P",
    "gn:feature_code":"PPL",
    "gn:name":"Jelveh Khv\u0101r",
    "gn:population":0,
    "gn:timezone":"Asia/Tehran",
    "iso:country":"IR",
    "name:fas_x_preferred":[
        "\u062c\u0644\u0648\u0647 \u062e\u0648\u0627\u0631"
    ],
    "name:fas_x_variant":[
        "Jelveh Khv\u0101r"
    ],
    "wof:name":"Jelveh Khvar",
    "wof:placetype":"locality"
},
  "geometry": {"coordinates":[48.7799,37.522],"type":"Point"}
}