{
  "type": "Feature",
  "properties": {
    "gn:admin1_code":"16",
    "gn:asciiname":"Tekiyeh",
    "gn:country_code":"IR",
    "gn:dem":1794,
    "gn:feature_class":"P",
    "gn:feature_code":"PPL",
    "gn:name":"Tek\u012byeh",
    "gn:population":0,
    "gn:timezone":"Asia/Tehran",
    "iso:country":"IR",
    "name:fas_x_preferred":[
        "\u062a\u06a9\u06cc\u0647"
    ],
    "name:fas_x_variant":[
        "Tek\u012byeh"
    ],
    "wof:name":"Tekiyeh",
    "wof:placetype":"locality"
},
  "geometry": {"coordinates":[47.87536,36.3234],"type":"Point"}
}