{
  "type": "Feature",
  "properties": {
    "gn:admin1_code":"28.0",
    "gn:asciiname":"Fulad Shahr",
    "gn:country_code":"IR",
    "gn:dem":1633,
    "gn:feature_class":"P",
    "gn:feature_code":"PPL",
    "gn:name":"F\u016bl\u0101d Shahr",
    "gn:population":0,
    "gn:timezone":"Asia/Tehran",
    "iso:country":"IR",
    "name:fas_x_preferred":[
        "\u0641\u0648\u0644\u0627\u062f \u0634\u0647\u0631"
    ],
    "name:fas_x_variant":[
        "F\u016bl\u0101d Shahr"
    ],
    "wof:name":"Fulad Shahr",
    "wof:placetype":"locality"
},
  "geometry": {"coordinates":[51.4067,32.5027],"type":"Point"}
}