{
  "type": "Feature",
  "properties": {
    "gn:admin1_code":"7",
    "gn:asciiname":"Bushikan-e Deylami",
    "gn:country_code":"IR",
    "gn:dem":721,
    "gn:feature_class":"P",
    "gn:feature_code":"PPL",
    "gn:name":"B\u016bsh\u012bk\u0101n-e Deylam\u012b",
    "gn:population":0,
    "gn:timezone":"Asia/Tehran",
    "iso:country":"IR",
    "name:fas_x_preferred":[
        "B\u016bsh\u012bk\u0101n-e Deylam\u012b"
    ],
    "name:fas_x_variant":[
        "B\u016bshg\u0101n",
        "\u0628\u0648\u0634\u06cc\u06a9\u0627\u0646 \u062f\u06cc\u0644\u0645\u06cc"
    ],
    "name:und_x_variant":[
        "B\u016bsheg\u0101n-e Deylam\u012b",
        "B\u016bshg\u0101n-e Deylam\u012b"
    ],
    "wof:name":"Bushikan-e Deylami",
    "wof:placetype":"locality"
},
  "geometry": {"coordinates":[51.51171,29.72286],"type":"Point"}
}