{
  "type": "Feature",
  "properties": {
    "gn:admin1_code":"15.0",
    "gn:asciiname":"Sartal Aqa",
    "gn:country_code":"IR",
    "gn:dem":673,
    "gn:feature_class":"P",
    "gn:feature_code":"PPL",
    "gn:name":"Sartal \u0100q\u0101",
    "gn:population":0,
    "gn:timezone":"Asia/Tehran",
    "iso:country":"IR",
    "name:fas_x_preferred":[
        "Sartal \u0100q\u0101"
    ],
    "wof:name":"Sartal Aqa",
    "wof:placetype":"locality"
},
  "geometry": {"coordinates":[49.45,32.13333],"type":"Point"}
}