{
  "type": "Feature",
  "properties": {
    "gn:admin1_code":"35",
    "gn:asciiname":"Kelij Kola",
    "gn:country_code":"IR",
    "gn:dem":868,
    "gn:feature_class":"P",
    "gn:feature_code":"PPL",
    "gn:name":"Kel\u012bj Kol\u0101",
    "gn:population":0,
    "gn:timezone":"Asia/Tehran",
    "iso:country":"IR",
    "name:fas_x_preferred":[
        "\u0643\u0650\u0644\u064a\u0686 \u0643\u064f\u0644\u0627"
    ],
    "name:fas_x_variant":[
        "\u06a9\u0644\u06cc\u062c \u06a9\u0644\u0627",
        "Kel\u012bch Kol\u0101",
        "Kel\u012bj Kol\u0101",
        "\u06a9\u0644\u06cc\u062c\u200c\u06a9\u0644\u0627"
    ],
    "name:glk_x_preferred":[
        "\u0643\u0644\u064a\u0686 \u0643\u0644\u0627"
    ],
    "name:mzn_x_preferred":[
        "\u06a9\u0644\u06cc\u062c\u200c\u06a9\u0644\u0627"
    ],
    "wof:name":"Kelij Kola",
    "wof:placetype":"locality"
},
  "geometry": {"coordinates":[53.21268000000001,36.15139],"type":"Point"}
}