{
  "type": "Feature",
  "properties": {
    "gn:admin1_code":"28",
    "gn:asciiname":"Murak",
    "gn:country_code":"IR",
    "gn:dem":1928,
    "gn:feature_class":"P",
    "gn:feature_code":"PPL",
    "gn:name":"M\u016brak",
    "gn:population":0,
    "gn:timezone":"Asia/Tehran",
    "iso:country":"IR",
    "name:fas_x_preferred":[
        "M\u016brag"
    ],
    "name:fas_x_variant":[
        "M\u016brak",
        "\u0645\u0648\u0631\u06a9"
    ],
    "wof:name":"Murak",
    "wof:placetype":"locality"
},
  "geometry": {"coordinates":[51.51682,31.09893],"type":"Point"}
}