{
  "type": "Feature",
  "properties": {
    "gn:admin1_code":"33.0",
    "gn:asciiname":"`Alalulu",
    "gn:country_code":"IR",
    "gn:dem":840,
    "gn:feature_class":"P",
    "gn:feature_code":"PPL",
    "gn:name":"\u2018Alal\u016bl\u016b",
    "gn:population":0,
    "gn:timezone":"Asia/Tehran",
    "iso:country":"IR",
    "name:fas_x_preferred":[
        "\u0639\u064e\u0644\u0651\u0648\u0644\u0648"
    ],
    "name:fas_x_variant":[
        "\u0639\u0644\u0644\u0648\u0644\u0648",
        "\u2018All\u016bl\u016b",
        "\u2018Alal\u016bl\u016b"
    ],
    "wof:name":"`Alalulu",
    "wof:placetype":"locality"
},
  "geometry": {"coordinates":[47.3577,39.0421],"type":"Point"}
}