{
  "type": "Feature",
  "properties": {
    "gn:admin1_code":"7",
    "gn:asciiname":"Chah Anjir",
    "gn:country_code":"IR",
    "gn:dem":672,
    "gn:feature_class":"P",
    "gn:feature_code":"PPL",
    "gn:name":"Ch\u0101h Anj\u012br",
    "gn:population":0,
    "gn:timezone":"Asia/Tehran",
    "iso:country":"IR",
    "name:fas_x_preferred":[
        "\u0686\u0627\u0647 \u0627\u0646\u062c\u06cc\u0631"
    ],
    "name:fas_x_variant":[
        "Pars\u016br\u012b",
        "Ch\u0101h Anj\u012br"
    ],
    "wof:name":"Chah Anjir",
    "wof:placetype":"locality"
},
  "geometry": {"coordinates":[51.0356,29.942],"type":"Point"}
}