{
  "type": "Feature",
  "properties": {
    "gn:admin1_code":"8.0",
    "gn:asciiname":"Sestelan",
    "gn:country_code":"IR",
    "gn:dem":82,
    "gn:feature_class":"P",
    "gn:feature_code":"PPL",
    "gn:name":"Ses\u0163el\u0101n",
    "gn:population":0,
    "gn:timezone":"Asia/Tehran",
    "iso:country":"IR",
    "name:ara_x_preferred":[
        "\u0633\u0633\u0637\u0644\u0627\u0646"
    ],
    "name:fas_x_preferred":[
        "\u0633\u0633\u0637\u0644\u0627\u0646"
    ],
    "name:fas_x_variant":[
        "Ses\u0163el\u0101n"
    ],
    "name:msa_x_preferred":[
        "Sestelan"
    ],
    "name:ukr_x_preferred":[
        "\u0421\u0435\u0441\u0442\u0435\u043b\u0430\u043d"
    ],
    "name:und_x_variant":[
        "Ses\u0163el\u0101n"
    ],
    "wof:name":"Sestelan",
    "wof:placetype":"locality"
},
  "geometry": {"coordinates":[49.29911,37.15372],"type":"Point"}
}