{
  "type": "Feature",
  "properties": {
    "gn:admin1_code":"8",
    "gn:asciiname":"Sakhbon",
    "gn:country_code":"IR",
    "gn:dem":363,
    "gn:feature_class":"P",
    "gn:feature_code":"PPL",
    "gn:name":"Sakhbon",
    "gn:population":0,
    "gn:timezone":"Asia/Tehran",
    "iso:country":"IR",
    "name:fas_x_preferred":[
        "\u0633\u062e\u0628\u0646"
    ],
    "wof:name":"Sakhbon",
    "wof:placetype":"locality"
},
  "geometry": {"coordinates":[49.0857,37.1666],"type":"Point"}
}