{
  "type": "Feature",
  "properties": {
    "gn:admin1_code":"41",
    "gn:asciiname":"Bozaghan",
    "gn:country_code":"IR",
    "gn:dem":1795,
    "gn:feature_class":"P",
    "gn:feature_code":"PPL",
    "gn:name":"Boz\u0101gh\u0101n",
    "gn:population":0,
    "gn:timezone":"Asia/Tehran",
    "iso:country":"IR",
    "name:fas_x_preferred":[
        "Boz\u0101gh\u0101n"
    ],
    "wof:name":"Bozaghan",
    "wof:placetype":"locality"
},
  "geometry": {"coordinates":[59.65416999999999,32.12611],"type":"Point"}
}