{
  "type": "Feature",
  "properties": {
    "gn:admin1_code":"8.0",
    "gn:asciiname":"Pa'in Mahalleh-ye Kolachah",
    "gn:country_code":"IR",
    "gn:dem":-17,
    "gn:feature_class":"P",
    "gn:feature_code":"PPL",
    "gn:name":"P\u0101\u2019\u012bn Ma\u1e29alleh-ye Kol\u0101ch\u0101h",
    "gn:population":0,
    "gn:timezone":"Asia/Tehran",
    "iso:country":"IR",
    "name:fas_x_preferred":[
        "\u067e\u0627\u0626\u06cc\u0646 \u0645\u062d\u0644\u0647 \u06a9\u0644\u0627\u0686\u0627\u0647"
    ],
    "name:und_x_variant":[
        "P\u0101\u2019\u012bn Ma\u1e29alleh-ye Kol\u0101ch\u0101h"
    ],
    "wof:name":"Pa'in Mahalleh-ye Kolachah",
    "wof:placetype":"locality"
},
  "geometry": {"coordinates":[49.71274,37.38564],"type":"Point"}
}