{
  "type": "Feature",
  "properties": {
    "gn:admin1_code":"41",
    "gn:asciiname":"Mazra`eh-ye Mohebb-e Sofla",
    "gn:country_code":"IR",
    "gn:dem":1647,
    "gn:feature_class":"P",
    "gn:feature_code":"PPL",
    "gn:name":"Mazra\u2018eh-ye Mo\u1e29ebb-e Sofl\u00e1",
    "gn:population":0,
    "gn:timezone":"Asia/Tehran",
    "iso:country":"IR",
    "name:fas_x_preferred":[
        "\u06a9\u0644\u0627\u062a\u0647 \u0645\u062d\u0628 \u067e\u0627\u0626\u06cc\u0646"
    ],
    "name:fas_x_variant":[
        "Mo\u1e29ebb-e P\u0101\u2019\u012bn",
        "Kal\u0101teh-ye Mo\u1e29ebb-e P\u0101\u2019\u012bn",
        "\u0645\u0632\u0631\u0639\u0647 \u0645\u062d\u0628 \u0633\u0641\u0644\u06cc",
        "\u0645\u062d\u0628 \u067e\u0627\u0626\u06cc\u0646"
    ],
    "name:und_x_variant":[
        "Mazra\u2018eh-ye Mo\u1e29ebb-e Sofl\u00e1"
    ],
    "wof:name":"Mazra`eh-ye Mohebb-e Sofla",
    "wof:placetype":"locality"
},
  "geometry": {"coordinates":[59.07311,33.73007],"type":"Point"}
}