{
  "type": "Feature",
  "properties": {
    "gn:admin1_code":"15",
    "gn:asciiname":"Mozaffariyeh-ye Do",
    "gn:country_code":"IR",
    "gn:dem":15,
    "gn:feature_class":"P",
    "gn:feature_code":"PPL",
    "gn:name":"Moz\u0327affar\u012byeh-ye Do",
    "gn:population":0,
    "gn:timezone":"Asia/Tehran",
    "iso:country":"IR",
    "name:fas_x_preferred":[
        "Moz\u0327affar\u012byeh-ye Do"
    ],
    "name:fas_x_variant":[
        "\u0645\u0638\u0641\u0631\u06cc\u0647 \u062f\u0648",
        "Moz\u0327affar\u012b"
    ],
    "name:und_x_variant":[
        "Mudhaffar\u012byeh"
    ],
    "wof:name":"Mozaffariyeh-ye Do",
    "wof:placetype":"locality"
},
  "geometry": {"coordinates":[48.58796,31.23125],"type":"Point"}
}