{
  "type": "Feature",
  "properties": {
    "gn:admin1_code":"1.0",
    "gn:asciiname":"Bezileh",
    "gn:country_code":"IR",
    "gn:dem":1225,
    "gn:feature_class":"P",
    "gn:feature_code":"PPL",
    "gn:name":"Bez\u012bleh",
    "gn:population":0,
    "gn:timezone":"Asia/Tehran",
    "iso:country":"IR",
    "name:azb_x_preferred":[
        "\u0628\u0632\u064a\u0644\u0647"
    ],
    "name:ceb_x_preferred":[
        "Bez\u012bleh"
    ],
    "name:ckb_x_preferred":[
        "\u0628\u06ce\u0632\u06cc\u0644\u06d5"
    ],
    "name:fas_x_preferred":[
        "\u0628\u0632\u06cc\u0644\u0647"
    ],
    "name:fas_x_variant":[
        "Bez\u012bleh"
    ],
    "name:kur_x_preferred":[
        "B\u00eaz\u00eele"
    ],
    "name:msa_x_preferred":[
        "Bezileh"
    ],
    "name:swe_x_preferred":[
        "Bez\u012bleh"
    ],
    "wof:name":"Bezileh",
    "wof:placetype":"locality"
},
  "geometry": {"coordinates":[45.5023,36.1792],"type":"Point"}
}