{
  "type": "Feature",
  "properties": {
    "gn:admin1_code":"28.0",
    "gn:asciiname":"Ghar-e Ra'is",
    "gn:country_code":"IR",
    "gn:dem":1692,
    "gn:feature_class":"P",
    "gn:feature_code":"PPL",
    "gn:name":"Gh\u0101r-e Ra\u2019\u012bs",
    "gn:population":0,
    "gn:timezone":"Asia/Tehran",
    "iso:country":"IR",
    "name:fas_x_preferred":[
        "Gh\u0101r-e Ra\u2019\u012bs"
    ],
    "wof:name":"Ghar-e Ra'is",
    "wof:placetype":"locality"
},
  "geometry": {"coordinates":[51.13333,33.98333],"type":"Point"}
}