{
  "type": "Feature",
  "properties": {
    "gn:admin1_code":"39.0",
    "gn:asciiname":"Ja'far Abad",
    "gn:country_code":"IR",
    "gn:dem":905,
    "gn:feature_class":"P",
    "gn:feature_code":"PPL",
    "gn:name":"Ja\u2019far \u0100b\u0101d",
    "gn:population":0,
    "gn:timezone":"Asia/Tehran",
    "iso:country":"IR",
    "name:fas_x_preferred":[
        "\u062c\u0639\u0641\u0631 \u0622\u0628\u0627\u062f"
    ],
    "name:und_x_variant":[
        "Ja\u2019far \u0100b\u0101d"
    ],
    "wof:name":"Ja'far Abad",
    "wof:placetype":"locality"
},
  "geometry": {"coordinates":[50.63889,34.86778],"type":"Point"}
}