{
  "type": "Feature",
  "properties": {
    "gn:admin1_code":"33",
    "gn:asciiname":"Khoshkenab",
    "gn:country_code":"IR",
    "gn:dem":1819,
    "gn:feature_class":"P",
    "gn:feature_code":"PPL",
    "gn:name":"Khoshken\u0101b",
    "gn:population":0,
    "gn:timezone":"Asia/Tehran",
    "iso:country":"IR",
    "name:fas_x_preferred":[
        "\u062e\u0634\u06a9\u0646\u0627\u0628"
    ],
    "name:fas_x_variant":[
        "Khoshken\u0101b"
    ],
    "wof:name":"Khoshkenab",
    "wof:placetype":"locality"
},
  "geometry": {"coordinates":[47.1226,37.6863],"type":"Point"}
}