{
  "type": "Feature",
  "properties": {
    "gn:admin1_code":"29",
    "gn:asciiname":"Guru",
    "gn:cc2":"IR",
    "gn:country_code":"IR",
    "gn:dem":2661,
    "gn:feature_class":"P",
    "gn:feature_code":"PPL",
    "gn:name":"G\u016br\u016b",
    "gn:population":0,
    "gn:timezone":"Asia/Tehran",
    "iso:country":"IR",
    "name:fas_x_preferred":[
        "\u06af\u0648\u0631\u0648"
    ],
    "name:fas_x_variant":[
        "\u06af\u064f\u0631\u0648",
        "\u06af\u064f\u0631\u064f\u0651\u0647"
    ],
    "name:und_x_variant":[
        "Gorooh",
        "Gor\u016b"
    ],
    "wof:name":"Guru",
    "wof:placetype":"locality"
},
  "geometry": {"coordinates":[57.36056,29.35556],"type":"Point"}
}