{
  "type": "Feature",
  "properties": {
    "gn:admin1_code":"32",
    "gn:asciiname":"Ru'eh Bin",
    "gn:country_code":"IR",
    "gn:dem":2540,
    "gn:feature_class":"P",
    "gn:feature_code":"PPL",
    "gn:name":"R\u016b\u2019eh B\u012bn",
    "gn:population":0,
    "gn:timezone":"Asia/Tehran",
    "iso:country":"IR",
    "name:fas_x_preferred":[
        "\u0631\u0648\u0626\u0650\u0647 \u0628\u064a\u0646"
    ],
    "name:fas_x_variant":[
        "R\u016b\u2019eh B\u012bn"
    ],
    "wof:name":"Ru'eh Bin",
    "wof:placetype":"locality"
},
  "geometry": {"coordinates":[48.86444,37.25611],"type":"Point"}
}