{
  "type": "Feature",
  "properties": {
    "gn:admin1_code":"9",
    "gn:asciiname":"Zaramin-e `Olya",
    "gn:country_code":"IR",
    "gn:dem":1594,
    "gn:feature_class":"P",
    "gn:feature_code":"PPL",
    "gn:name":"Zar\u0101m\u012bn-e \u2018Oly\u0101",
    "gn:population":0,
    "gn:timezone":"Asia/Tehran",
    "iso:country":"IR",
    "name:fas_x_preferred":[
        "\u0632\u0631\u0627\u0645\u06cc\u0646 \u0639\u0644\u06cc\u0627"
    ],
    "name:fas_x_variant":[
        "Zar\u0101m\u012bn-e \u2018Oly\u0101",
        "Zar\u0101m\u012bn-e B\u0101l\u0101",
        "\u0632\u0631\u0627\u0645\u06cc\u0646 \u0628\u0627\u0644\u0627"
    ],
    "name:und_x_variant":[
        "Zar\u0101m\u012bn",
        "Zarr\u0101m\u012bn-e B\u0101l\u0101",
        "Zar\u0101m\u012bn-e B\u0101l\u0101",
        "\u0632\u0631\u0627\u0645\u06cc\u0646 \u0628\u0627\u0644\u0627"
    ],
    "wof:name":"Zaramin-e `Olya",
    "wof:placetype":"locality"
},
  "geometry": {"coordinates":[48.31744000000001,34.18495],"type":"Point"}
}