{
  "type": "Feature",
  "properties": {
    "gn:admin1_code":"5.0",
    "gn:asciiname":"Mombi",
    "gn:country_code":"IR",
    "gn:dem":1221,
    "gn:feature_class":"P",
    "gn:feature_code":"PPL",
    "gn:name":"Momb\u012b",
    "gn:population":0,
    "gn:timezone":"Asia/Tehran",
    "iso:country":"IR",
    "name:fas_x_preferred":[
        "\u0645\u0645\u0628\u06cc"
    ],
    "name:por_x_preferred":[
        "Mombi"
    ],
    "name:und_x_variant":[
        "Momb\u012b"
    ],
    "wof:name":"Mombi",
    "wof:placetype":"locality"
},
  "geometry": {"coordinates":[50.11667,31.10948],"type":"Point"}
}