{
  "type": "Feature",
  "properties": {
    "gn:admin1_code":"29",
    "gn:asciiname":"Sar Meydan",
    "gn:country_code":"IR",
    "gn:dem":691,
    "gn:feature_class":"P",
    "gn:feature_code":"PPL",
    "gn:name":"Sar Meyd\u0101n",
    "gn:population":0,
    "gn:timezone":"Asia/Tehran",
    "iso:country":"IR",
    "name:fas_x_preferred":[
        "\u06af\u064f\u0646\u062c\u0627\u0646"
    ],
    "name:fas_x_variant":[
        "\u06af\u064e\u0646\u062c \u0622\u0628\u0627\u062f",
        "Gonj\u0101n",
        "\u0633\u0631 \u0645\u064a\u062f\u0627\u0646",
        "\u06af\u0648\u0627\u0646\u0686\u0627\u0646 \u067e\u0627\u0626\u06cc\u0646",
        "\u06af\u0648\u0647\u0646\u0686\u0627\u0646"
    ],
    "name:und_x_variant":[
        "Ganj\u0101b\u0101d",
        "Sar Meyd\u0101n",
        "Gav\u0101nch\u0101n-e P\u0101\u2019\u012bn",
        "Gowhanch\u0101n"
    ],
    "wof:name":"Sar Meydan",
    "wof:placetype":"locality"
},
  "geometry": {"coordinates":[58.68917,26.91666],"type":"Point"}
}