{
  "type": "Feature",
  "properties": {
    "gn:admin1_code":"5",
    "gn:asciiname":"Tall Rezaqoli",
    "gn:country_code":"IR",
    "gn:dem":1241,
    "gn:feature_class":"P",
    "gn:feature_code":"PPL",
    "gn:name":"Tall Re\u1e95\u0101qol\u012b",
    "gn:population":0,
    "gn:timezone":"Asia/Tehran",
    "iso:country":"IR",
    "name:fas_x_preferred":[
        "\u0686\u064e\u0645\u062a\u0627\u062c"
    ],
    "name:fas_x_variant":[
        "Chamt\u0101j",
        "\u062a\u0644 \u0631\u0636\u0627\u0642\u0644\u06cc"
    ],
    "name:und_x_variant":[
        "Tall Re\u1e95\u0101qol\u012b"
    ],
    "wof:name":"Tall Rezaqoli",
    "wof:placetype":"locality"
},
  "geometry": {"coordinates":[50.11081,31.11615],"type":"Point"}
}