{
  "type": "Feature",
  "properties": {
    "gn:admin1_code":"35.0",
    "gn:asciiname":"Gol Mazar",
    "gn:country_code":"IR",
    "gn:dem":47,
    "gn:feature_class":"P",
    "gn:feature_code":"PPL",
    "gn:name":"Gol Maz\u0101r",
    "gn:population":0,
    "gn:timezone":"Asia/Tehran",
    "iso:country":"IR",
    "name:ara_x_preferred":[
        "\u063a\u0644\u0645\u0632\u0627\u0631"
    ],
    "name:fas_x_preferred":[
        "\u06af\u0644 \u0645\u0632\u0627\u0631"
    ],
    "name:fas_x_variant":[
        "Gol Maz\u0101r",
        "\u06af\u0644\u0645\u0632\u0627\u0631"
    ],
    "name:mzn_x_preferred":[
        "\u06af\u0644\u0645\u0632\u0627\u0631"
    ],
    "name:ukr_x_preferred":[
        "\u0490\u043e\u043b\u044c-\u041c\u0430\u0437\u0430\u0440"
    ],
    "wof:name":"Gol Mazar",
    "wof:placetype":"locality"
},
  "geometry": {"coordinates":[52.49616,36.41963],"type":"Point"}
}