{
  "type": "Feature",
  "properties": {
    "gn:admin1_code":"26.0",
    "gn:asciiname":"Kordeyan",
    "gn:country_code":"IR",
    "gn:dem":1926,
    "gn:feature_class":"P",
    "gn:feature_code":"PPL",
    "gn:name":"Kordey\u0101n",
    "gn:population":0,
    "gn:timezone":"Asia/Tehran",
    "iso:country":"IR",
    "name:fas_x_preferred":[
        "\u0643\u0631\u062f\u064a\u0627\u0646"
    ],
    "name:fas_x_variant":[
        "Kordey\u0101n",
        "\u06a9\u0631\u062f\u06cc\u0627\u0646"
    ],
    "wof:name":"Kordeyan",
    "wof:placetype":"locality"
},
  "geometry": {"coordinates":[51.6226,35.8592],"type":"Point"}
}