{
  "type": "Feature",
  "properties": {
    "gn:admin1_code":"37.0",
    "gn:asciiname":"Bahlakeh",
    "gn:country_code":"IR",
    "gn:dem":25,
    "gn:feature_class":"P",
    "gn:feature_code":"PPL",
    "gn:name":"Bahlakeh",
    "gn:population":0,
    "gn:timezone":"Asia/Tehran",
    "iso:country":"IR",
    "name:fas_x_preferred":[
        "\u0628\u0647\u0644\u06a9\u0647"
    ],
    "wof:name":"Bahlakeh",
    "wof:placetype":"locality"
},
  "geometry": {"coordinates":[54.94038000000001,37.19246],"type":"Point"}
}