{
  "type": "Feature",
  "properties": {
    "gn:admin1_code":"28.0",
    "gn:asciiname":"Parikan",
    "gn:country_code":"IR",
    "gn:dem":2133,
    "gn:feature_class":"P",
    "gn:feature_code":"PPL",
    "gn:name":"Par\u012bk\u0101n",
    "gn:population":0,
    "gn:timezone":"Asia/Tehran",
    "iso:country":"IR",
    "name:fas_x_preferred":[
        "\u067e\u0631\u06cc\u06a9\u0627\u0646"
    ],
    "name:fas_x_variant":[
        "Par\u012bk\u0101n"
    ],
    "wof:name":"Parikan",
    "wof:placetype":"locality"
},
  "geometry": {"coordinates":[52.8407,32.8162],"type":"Point"}
}