{
  "type": "Feature",
  "properties": {
    "gn:admin1_code":"16.0",
    "gn:asciiname":"Sunj-e `Olya",
    "gn:country_code":"IR",
    "gn:dem":1854,
    "gn:feature_class":"P",
    "gn:feature_code":"PPL",
    "gn:name":"S\u016bnj-e \u2018Oly\u0101",
    "gn:population":0,
    "gn:timezone":"Asia/Tehran",
    "iso:country":"IR",
    "name:fas_x_preferred":[
        "\u0633\u0648\u0646\u062c \u0639\u0644\u06cc\u0627"
    ],
    "name:fas_x_variant":[
        "S\u016bnj-e \u2018Oly\u0101"
    ],
    "wof:name":"Sunj-e `Olya",
    "wof:placetype":"locality"
},
  "geometry": {"coordinates":[45.9913,36.0456],"type":"Point"}
}