{
  "type": "Feature",
  "properties": {
    "gn:admin1_code":"42",
    "gn:asciiname":"Chah-e Moqaddam",
    "gn:country_code":"IR",
    "gn:dem":1220,
    "gn:feature_class":"P",
    "gn:feature_code":"PPL",
    "gn:name":"Ch\u0101h-e Moqaddam",
    "gn:population":0,
    "gn:timezone":"Asia/Tehran",
    "iso:country":"IR",
    "name:fas_x_preferred":[
        "Ch\u0101h-e Moqaddam"
    ],
    "wof:name":"Chah-e Moqaddam",
    "wof:placetype":"locality"
},
  "geometry": {"coordinates":[58.78333000000001,36.86667],"type":"Point"}
}