{
  "type": "Feature",
  "properties": {
    "gn:admin1_code":"13",
    "gn:asciiname":"Qeshlaq",
    "gn:country_code":"IR",
    "gn:dem":1868,
    "gn:feature_class":"P",
    "gn:feature_code":"PPL",
    "gn:name":"Qeshl\u0101q",
    "gn:population":0,
    "gn:timezone":"Asia/Tehran",
    "iso:country":"IR",
    "name:ceb_x_preferred":[
        "Qeshlaq"
    ],
    "name:fas_x_preferred":[
        "\u0642\u0634\u0644\u0627\u0642"
    ],
    "name:fas_x_variant":[
        "Qeshl\u0101q"
    ],
    "name:swe_x_preferred":[
        "Qeshlaq"
    ],
    "wof:name":"Qeshlaq",
    "wof:placetype":"locality"
},
  "geometry": {"coordinates":[47.1839,34.8557],"type":"Point"}
}