{
  "type": "Feature",
  "properties": {
    "gn:admin1_code":"29.0",
    "gn:asciiname":"`Abbasiyeh",
    "gn:country_code":"IR",
    "gn:dem":729,
    "gn:feature_class":"P",
    "gn:feature_code":"PPL",
    "gn:name":"\u2018Abb\u0101s\u012byeh",
    "gn:population":0,
    "gn:timezone":"Asia/Tehran",
    "iso:country":"IR",
    "name:fas_x_preferred":[
        "\u0639\u0628\u0627\u0633\u06cc\u0647"
    ],
    "name:fas_x_variant":[
        "\u2018Abb\u0101s\u012byeh"
    ],
    "wof:name":"`Abbasiyeh",
    "wof:placetype":"locality"
},
  "geometry": {"coordinates":[58.84081,28.86372],"type":"Point"}
}