{
  "type": "Feature",
  "properties": {
    "gn:admin1_code":"41",
    "gn:asciiname":"Sarow",
    "gn:country_code":"IR",
    "gn:dem":1631,
    "gn:feature_class":"P",
    "gn:feature_code":"PPL",
    "gn:name":"Sarow",
    "gn:population":0,
    "gn:timezone":"Asia/Tehran",
    "iso:country":"IR",
    "name:deu_x_preferred":[
        "Sarow"
    ],
    "name:epo_x_preferred":[
        "Sarow"
    ],
    "name:fas_x_preferred":[
        "\u0633\u0648\u0631"
    ],
    "name:fas_x_variant":[
        "S\u016br",
        "\u0633\u0631\u0648",
        "\u0632\u0627\u0631\u0648\u0648"
    ],
    "name:fra_x_preferred":[
        "Sarow"
    ],
    "name:hun_x_preferred":[
        "Sarow"
    ],
    "name:ita_x_preferred":[
        "Sarow"
    ],
    "name:kaz_x_preferred":[
        "\u0417\u0430\u0440\u043e\u0432"
    ],
    "name:kir_x_preferred":[
        "\u0417\u0430\u0440\u043e\u0432"
    ],
    "name:mkd_x_preferred":[
        "\u0417\u0430\u0440\u043e\u0432"
    ],
    "name:msa_x_preferred":[
        "Sarow"
    ],
    "name:nld_x_preferred":[
        "Sarow"
    ],
    "name:pol_x_preferred":[
        "Sarow"
    ],
    "name:ron_x_preferred":[
        "Sarow"
    ],
    "name:rus_x_preferred":[
        "\u0417\u0430\u0440\u043e\u0432"
    ],
    "name:spa_x_preferred":[
        "Sarow"
    ],
    "name:srp_x_preferred":[
        "\u0417\u0430\u0440\u043e\u0432"
    ],
    "name:ukr_x_preferred":[
        "\u0417\u0430\u0440\u043e\u0432"
    ],
    "name:und_x_variant":[
        "Sowr",
        "Savar",
        "Saur",
        "Sarv",
        "Sarow",
        "Gerow",
        "Gero"
    ],
    "name:uzb_x_preferred":[
        "Sarow"
    ],
    "name:vie_x_preferred":[
        "Sarow"
    ],
    "name:vol_x_preferred":[
        "Sarow"
    ],
    "name:war_x_preferred":[
        "Sarow"
    ],
    "wof:name":"Sarow",
    "wof:placetype":"locality"
},
  "geometry": {"coordinates":[59.97677,32.87843],"type":"Point"}
}