{
  "type": "Feature",
  "properties": {
    "gn:admin1_code":"41",
    "gn:asciiname":"Sarow",
    "gn:country_code":"IR",
    "gn:dem":1631,
    "gn:feature_class":"P",
    "gn:feature_code":"PPL",
    "gn:name":"Sarow",
    "gn:population":0,
    "gn:timezone":"Asia/Tehran",
    "iso:country":"IR",
    "name:fas_x_preferred":[
        "\u0633\u0648\u0631"
    ],
    "name:fas_x_variant":[
        "S\u016br",
        "\u0633\u0631\u0648"
    ],
    "name:und_x_variant":[
        "Sowr",
        "Savar",
        "Saur",
        "Sarv",
        "Sarow",
        "Gerow",
        "Gero"
    ],
    "wof:name":"Sarow",
    "wof:placetype":"locality"
},
  "geometry": {"coordinates":[59.97677,32.87843],"type":"Point"}
}