{
  "type": "Feature",
  "properties": {
    "gn:admin1_code":"36",
    "gn:asciiname":"Shahrak-e Allahlu",
    "gn:country_code":"IR",
    "gn:dem":2362,
    "gn:feature_class":"P",
    "gn:feature_code":"PPL",
    "gn:name":"Shahrak-e All\u0101hl\u016b",
    "gn:population":0,
    "gn:timezone":"Asia/Tehran",
    "iso:country":"IR",
    "name:fas_x_preferred":[
        "\u0634\u0647\u0631\u06a9 \u0627\u0644\u0644\u0647 \u0644\u0648"
    ],
    "name:fas_x_variant":[
        "Shahrak-e All\u0101hl\u016b",
        "\u0634\u0647\u0631\u06a9 \u06a9\u0627\u0644\u0633\u0645\u06cc\u0646 \u0645\u0639\u062f\u0646 \u0633\u0631\u0628 \u0627\u0646\u06af\u0648\u0631\u0627\u0646"
    ],
    "name:und_x_variant":[
        "Shahrak-e K\u0101lesm\u012bn-e Ma\u2018dan-e Sorb-e Ang\u016br\u0101n"
    ],
    "wof:name":"Shahrak-e Allahlu",
    "wof:placetype":"locality"
},
  "geometry": {"coordinates":[47.428,36.6195],"type":"Point"}
}