{
  "type": "Feature",
  "properties": {
    "gn:admin1_code":"41",
    "gn:asciiname":"Sukhurg",
    "gn:country_code":"IR",
    "gn:dem":1600,
    "gn:feature_class":"P",
    "gn:feature_code":"PPL",
    "gn:name":"S\u016bkh\u016brg",
    "gn:population":0,
    "gn:timezone":"Asia/Tehran",
    "iso:country":"IR",
    "name:fas_x_preferred":[
        "\u0633\u0648\u062e\u0648\u0631\u06af"
    ],
    "name:fas_x_variant":[
        "S\u016bkh\u016brg"
    ],
    "wof:name":"Sukhurg",
    "wof:placetype":"locality"
},
  "geometry": {"coordinates":[60.0827,33.01051],"type":"Point"}
}