{
  "type": "Feature",
  "properties": {
    "gn:admin1_code":"33",
    "gn:asciiname":"Qarah Kand-e Sedqi",
    "gn:country_code":"IR",
    "gn:dem":1632,
    "gn:feature_class":"P",
    "gn:feature_code":"PPL",
    "gn:name":"Qarah Kand-e \u015eedq\u012b",
    "gn:population":0,
    "gn:timezone":"Asia/Tehran",
    "iso:country":"IR",
    "name:fas_x_preferred":[
        "\u0642\u0631\u0647 \u06a9\u0646\u062f \u0635\u062f\u0642\u06cc"
    ],
    "name:fas_x_variant":[
        "Qareh Kand-e \u015eedq\u012b",
        "Qareh Kand-e \u015eedq\u012bz\u012b",
        "Qarah Kand-e \u015eedq\u012b",
        "\u0642\u0631\u0647 \u06a9\u0646\u062f"
    ],
    "name:und_x_variant":[
        "Qarah Kand"
    ],
    "wof:name":"Qarah Kand-e Sedqi",
    "wof:placetype":"locality"
},
  "geometry": {"coordinates":[46.3842,37.1889],"type":"Point"}
}