{
  "type": "Feature",
  "properties": {
    "gn:admin1_code":"4.0",
    "gn:asciiname":"Ney Padan",
    "gn:country_code":"IR",
    "gn:dem":1215,
    "gn:feature_class":"P",
    "gn:feature_code":"PPL",
    "gn:name":"Ney Pad\u0101n",
    "gn:population":0,
    "gn:timezone":"Asia/Tehran",
    "iso:country":"IR",
    "name:fas_x_preferred":[
        "\u0646\u06cc \u0628\u062f\u0627\u0646"
    ],
    "name:fas_x_variant":[
        "Ney Pad\u0101n",
        "N\u012bfd\u0101n",
        "\u0646\u06cc \u067e\u062f\u0627\u0646"
    ],
    "name:und_x_variant":[
        "N\u012bfd\u0101n"
    ],
    "wof:name":"Ney Padan",
    "wof:placetype":"locality"
},
  "geometry": {"coordinates":[60.76213000000001,27.85538],"type":"Point"}
}