{
  "type": "Feature",
  "properties": {
    "gn:admin1_code":"32",
    "gn:asciiname":"Qeshlaq-e `Ali Aqa",
    "gn:country_code":"IR",
    "gn:dem":118,
    "gn:feature_class":"P",
    "gn:feature_code":"PPL",
    "gn:name":"Qeshl\u0101q-e \u2018Al\u012b \u0100q\u0101",
    "gn:population":0,
    "gn:timezone":"Asia/Tehran",
    "iso:country":"IR",
    "name:fas_x_preferred":[
        "\u0642\u0650\u0634\u0644\u0627\u0642\u0650 \u0622\u063a\u0627\u0644\u0648"
    ],
    "name:fas_x_variant":[
        "Qeshl\u0101q-e \u2018Al\u012b \u0100q\u0101",
        "\u0642\u0650\u0634\u0644\u0627\u0642\u0650 \u0639\u064e\u0644\u06cc \u0622\u0642\u0627",
        "\u0642\u0650\u0634\u0644\u0627\u0642\u0650 \u0622\u063a\u0627\u0628\u0627\u0646\u0648"
    ],
    "name:und_x_variant":[
        "Qeshl\u0101q-e \u0100gh\u0101b\u0101n\u016b",
        "Qeshl\u0101q-e \u0100gh\u0101l\u016b"
    ],
    "wof:name":"Qeshlaq-e `Ali Aqa",
    "wof:placetype":"locality"
},
  "geometry": {"coordinates":[48.21667,39.43333],"type":"Point"}
}