{
  "type": "Feature",
  "properties": {
    "gn:admin1_code":"15.0",
    "gn:asciiname":"Dowr-e Kal",
    "gn:country_code":"IR",
    "gn:dem":199,
    "gn:feature_class":"P",
    "gn:feature_code":"PPL",
    "gn:name":"Dowr-e K\u0101l",
    "gn:population":0,
    "gn:timezone":"Asia/Tehran",
    "iso:country":"IR",
    "wof:name":"Dowr-e Kal",
    "wof:placetype":"locality"
},
  "geometry": {"coordinates":[49.65611,31.27167],"type":"Point"}
}