{
  "type": "Feature",
  "properties": {
    "gn:admin1_code":"0",
    "gn:asciiname":"Geravi",
    "gn:country_code":"IR",
    "gn:dem":1263,
    "gn:feature_class":"P",
    "gn:feature_code":"PPL",
    "gn:name":"Gerav\u012b",
    "gn:population":0,
    "gn:timezone":"Asia/Tehran",
    "iso:country":"IR",
    "name:fas_x_preferred":[
        "\u06af\u0631\u0648\u06cc"
    ],
    "name:fas_x_variant":[
        "Gerav\u012b"
    ],
    "wof:name":"Geravi",
    "wof:placetype":"locality"
},
  "geometry": {"coordinates":[57.8703,26.8202],"type":"Point"}
}