{
  "type": "Feature",
  "properties": {
    "gn:admin1_code":"7",
    "gn:asciiname":"Dehuyeh",
    "gn:country_code":"IR",
    "gn:dem":1568,
    "gn:feature_class":"P",
    "gn:feature_code":"PPL",
    "gn:name":"Deh\u016byeh",
    "gn:population":0,
    "gn:timezone":"Asia/Tehran",
    "iso:country":"IR",
    "name:ara_x_preferred":[
        "\u062f\u0647\u0648\u064a\u0647"
    ],
    "name:fas_x_preferred":[
        "\u062f\u0647\u0648\u0626\u06cc\u0647"
    ],
    "name:fas_x_variant":[
        "Deh\u016byeh",
        "\u062f\u0647\u0648\u06cc\u0647",
        "\u0642\u0644\u0639\u0647 \u062f\u0647\u0648"
    ],
    "name:msa_x_preferred":[
        "Dehuiyeh"
    ],
    "name:und_x_variant":[
        "Qal\u2018eh-ye Doh\u016b",
        "Dehvieh",
        "Deh\u016b",
        "Deh\u016b\u2019\u012byeh",
        "Qal\u2018eh Deh\u016b"
    ],
    "wof:name":"Dehuyeh",
    "wof:placetype":"locality"
},
  "geometry": {"coordinates":[53.9395,29.2639],"type":"Point"}
}