{
  "type": "Feature",
  "properties": {
    "gn:admin1_code":"15",
    "gn:asciiname":"Muzarm",
    "gn:country_code":"IR",
    "gn:dem":1254,
    "gn:feature_class":"P",
    "gn:feature_code":"PPL",
    "gn:name":"M\u016bzarm",
    "gn:population":0,
    "gn:timezone":"Asia/Tehran",
    "iso:country":"IR",
    "name:fas_x_preferred":[
        "M\u016brzom"
    ],
    "name:fas_x_variant":[
        "M\u016bzar\u012b",
        "Deh Kohneh-ye M\u016bzarm",
        "M\u016bzarm",
        "\u0645\u0648\u0632\u0631\u0645",
        "\u062f\u0647\u200c\u06a9\u0647\u0646\u0647 \u0645\u0648\u0632\u0631\u0645"
    ],
    "name:und_x_variant":[
        "M\u016brazm",
        "M\u016bzarm",
        "Mowrzom",
        "\u0645\u0648\u0632\u0631\u0645"
    ],
    "wof:name":"Muzarm",
    "wof:placetype":"locality"
},
  "geometry": {"coordinates":[50.33753,31.64667],"type":"Point"}
}