{
  "type": "Feature",
  "properties": {
    "gn:admin1_code":"42",
    "gn:asciiname":"Izi",
    "gn:country_code":"IR",
    "gn:dem":1009,
    "gn:feature_class":"P",
    "gn:feature_code":"PPL",
    "gn:name":"\u012az\u012b",
    "gn:population":0,
    "gn:timezone":"Asia/Tehran",
    "iso:country":"IR",
    "name:fas_x_preferred":[
        "Qal\u2018eh-ye \u012az\u012b"
    ],
    "name:fas_x_variant":[
        "\u012az\u012b",
        "\u0642\u0644\u0639\u0647 \u0627\u06cc\u0632\u06cc",
        "Deh Ben\u0101m",
        "\u0627\u06cc\u0632\u06cc"
    ],
    "name:und_x_variant":[
        "Deh Ben\u0101m",
        "\u0642\u0644\u0639\u0647 \u0627\u06cc\u0632\u06cc"
    ],
    "wof:name":"Izi",
    "wof:placetype":"locality"
},
  "geometry": {"coordinates":[57.72753,36.22369000000001],"type":"Point"}
}