{
  "type": "Feature",
  "properties": {
    "gn:admin1_code":"3",
    "gn:asciiname":"Shahrak-e Shiasi",
    "gn:country_code":"IR",
    "gn:dem":1476,
    "gn:feature_class":"P",
    "gn:feature_code":"PPL",
    "gn:name":"Shahrak-e Sh\u012b\u0101s\u012b",
    "gn:population":0,
    "gn:timezone":"Asia/Tehran",
    "iso:country":"IR",
    "name:ara_x_preferred":[
        "\u0634\u064a\u0627\u0633\u064a"
    ],
    "name:fas_x_preferred":[
        "\u0634\u064a\u0627\u0633\u06cc"
    ],
    "name:fas_x_variant":[
        "Sh\u012b\u0101s\u012b",
        "\u0634\u0650\u064a\u0627\u0633\u06cc",
        "\u0634\u0647\u0631\u06a9 \u0634\u06cc\u0627\u0633\u06cc"
    ],
    "name:msa_x_preferred":[
        "Shahrak-e Shiasi"
    ],
    "name:und_x_variant":[
        "Shiyasi",
        "Shey\u0101s\u012b",
        "Shias",
        "Shahrak-e Sh\u012b\u0101s\u012b"
    ],
    "wof:name":"Shahrak-e Shiasi",
    "wof:placetype":"locality"
},
  "geometry": {"coordinates":[50.6232,31.68906],"type":"Point"}
}