{
  "type": "Feature",
  "properties": {
    "gn:admin1_code":"7",
    "gn:asciiname":"Bani Asad",
    "gn:country_code":"IR",
    "gn:dem":1607,
    "gn:feature_class":"P",
    "gn:feature_code":"PPL",
    "gn:name":"Ban\u012b Asad",
    "gn:population":0,
    "gn:timezone":"Asia/Tehran",
    "iso:country":"IR",
    "name:fas_x_preferred":[
        "\u0686\u0627\u0647 \u062d\u0627\u062c \u0627\u0633\u0644\u0627\u0646"
    ],
    "name:fas_x_variant":[
        "Ch\u0101h-e \u1e28\u0101jj Asl\u0101n",
        "\u0628\u0646\u06cc \u0627\u0633\u062f"
    ],
    "name:und_x_variant":[
        "Ban\u012b Asad"
    ],
    "wof:name":"Bani Asad",
    "wof:placetype":"locality"
},
  "geometry": {"coordinates":[55.0654,28.8041],"type":"Point"}
}