{
  "type": "Feature",
  "properties": {
    "gn:admin1_code":"3",
    "gn:asciiname":"Sureshjan",
    "gn:country_code":"IR",
    "gn:dem":2098,
    "gn:feature_class":"P",
    "gn:feature_code":"PPL",
    "gn:name":"S\u016breshj\u0101n",
    "gn:population":0,
    "gn:timezone":"Asia/Tehran",
    "iso:country":"IR",
    "name:fas_x_preferred":[
        "S\u016brshj\u0101n"
    ],
    "name:fas_x_variant":[
        "\u0633\u064f\u0651\u0631\u0650\u0634 \u062c\u064e\u0646",
        "S\u016breshj\u0101n",
        "\u0633\u0648\u0631\u0634\u062c\u0627\u0646"
    ],
    "name:und_x_variant":[
        "Sooresh Jan",
        "S\u016breshj\u0101n",
        "\u0633\u0648\u0631\u0634\u062c\u0627\u0646"
    ],
    "wof:name":"Sureshjan",
    "wof:placetype":"locality"
},
  "geometry": {"coordinates":[50.67562,32.31768],"type":"Point"}
}