{
  "type": "Feature",
  "properties": {
    "gn:admin1_code":"5",
    "gn:asciiname":"Kombol",
    "gn:country_code":"IR",
    "gn:dem":677,
    "gn:feature_class":"P",
    "gn:feature_code":"PPL",
    "gn:name":"Kombol",
    "gn:population":0,
    "gn:timezone":"Asia/Tehran",
    "iso:country":"IR",
    "name:ceb_x_preferred":[
        "Kombol"
    ],
    "name:fas_x_preferred":[
        "\u0643\u064f\u0646\u0628\u064f\u0644"
    ],
    "name:fas_x_variant":[
        "\u06a9\u0645\u0628\u0644"
    ],
    "name:swe_x_preferred":[
        "Kombol"
    ],
    "name:und_x_variant":[
        "Konbol"
    ],
    "wof:name":"Kombol",
    "wof:placetype":"locality"
},
  "geometry": {"coordinates":[50.7783,30.3097],"type":"Point"}
}