{
  "type": "Feature",
  "properties": {
    "gn:admin1_code":"5.0",
    "gn:asciiname":"Mazra`eh-ye Darganji",
    "gn:country_code":"IR",
    "gn:dem":1691,
    "gn:feature_class":"P",
    "gn:feature_code":"PPL",
    "gn:name":"Mazra\u2018eh-ye D\u0101rganj\u012b",
    "gn:population":0,
    "gn:timezone":"Asia/Tehran",
    "iso:country":"IR",
    "name:fas_x_preferred":[
        "B\u0101derang"
    ],
    "name:fas_x_variant":[
        "\u0628\u0627\u062f\u0631\u0646\u06af",
        "\u0645\u0632\u0631\u0639\u0647 \u062f\u0627\u0631\u06af\u0646\u062c\u06cc",
        "\u062f\u0627\u0631\u06af\u0646\u062c\u06cc"
    ],
    "name:und_x_variant":[
        "\u0628\u0627\u062f\u0631\u0646\u06af",
        "Mazra\u2018eh-ye D\u0101rganj\u012b",
        "D\u0101rganj\u012b"
    ],
    "wof:name":"Mazra`eh-ye Darganji",
    "wof:placetype":"locality"
},
  "geometry": {"coordinates":[50.50619,31.23871],"type":"Point"}
}