{
  "type": "Feature",
  "properties": {
    "gn:admin1_code":"36",
    "gn:asciiname":"Naderabad",
    "gn:country_code":"IR",
    "gn:dem":1987,
    "gn:feature_class":"P",
    "gn:feature_code":"PPL",
    "gn:name":"N\u0101der\u0101b\u0101d",
    "gn:population":0,
    "gn:timezone":"Asia/Tehran",
    "iso:country":"IR",
    "name:ara_x_preferred":[
        "\u0646\u0630\u064a\u0631 \u0623\u0628\u0627\u062f"
    ],
    "name:azb_x_preferred":[
        "\u0646\u062f\u06cc\u0631\u0622\u0628\u0627\u062f"
    ],
    "name:fas_x_preferred":[
        "\u0646\u0627\u062f\u0631 \u0622\u0628\u0627\u062f"
    ],
    "name:fas_x_variant":[
        "\u0646\u062f\u064a\u0631 \u0622\u0628\u0627\u062f",
        "N\u0101der\u0101b\u0101d",
        "\u0646\u062f\u06cc\u0631\u0622\u0628\u0627\u062f"
    ],
    "name:und_x_variant":[
        "Kadrabad",
        "Nadr\u0101b\u0101d",
        "Nad\u012bs\u0101b\u0101d",
        "Nad\u012br\u0101b\u0101d"
    ],
    "wof:name":"Naderabad",
    "wof:placetype":"locality"
},
  "geometry": {"coordinates":[48.71485,36.36959],"type":"Point"}
}