{
  "type": "Feature",
  "properties": {
    "gn:admin1_code":"15",
    "gn:asciiname":"Namak Talkheneh-ye Rashnow",
    "gn:country_code":"IR",
    "gn:dem":413,
    "gn:feature_class":"P",
    "gn:feature_code":"PPL",
    "gn:name":"Namak Talkheneh-ye Rashnow",
    "gn:population":0,
    "gn:timezone":"Asia/Tehran",
    "iso:country":"IR",
    "name:ara_x_preferred":[
        "\u0646\u0645\u0643 \u062a\u0644\u062e\u0629 \u0631\u0634\u0646\u0648"
    ],
    "name:azb_x_preferred":[
        "\u0646\u0645\u0643 \u062a\u0644\u062e\u0647 \u0631\u0634\u0646\u0648(\u0627\u0646\u062f\u06cc\u0645\u0634\u06a9)"
    ],
    "name:ceb_x_preferred":[
        "Rashn\u016b"
    ],
    "name:fas_x_preferred":[
        "\u0631\u064e\u0634\u0646\u0648\u062f\u06cc"
    ],
    "name:fas_x_variant":[
        "\u0631\u0634\u0646\u0648",
        "Rashn\u016bd\u012b",
        "Rashn\u016b",
        "\u0646\u0645\u06a9 \u062a\u0644\u062e\u0646\u0647 \u0631\u0634\u0646\u0648",
        "\u0646\u0645\u06a9 \u062a\u0644\u062e\u0647 \u0631\u0634\u0646\u0648",
        "\u0646\u0645\u06a9 \u062a\u0644\u062e\u0647",
        "\u0646\u0645\u06a9\u200c\u062a\u0644\u062e\u0647\u200c\u0631\u0634\u0646\u0648"
    ],
    "name:und_x_variant":[
        "Rashnoodi",
        "Namak Talkeh-ye Rashnow",
        "Namak Talkheneh-ye Rashnow",
        "Namak Talkheh-ye Rashnow",
        "Namak Talkheh"
    ],
    "wof:name":"Namak Talkheneh-ye Rashnow",
    "wof:placetype":"locality"
},
  "geometry": {"coordinates":[48.24217,32.74336],"type":"Point"}
}