{
  "type": "Feature",
  "properties": {
    "gn:admin1_code":"26.0",
    "gn:asciiname":"Khanloq",
    "gn:country_code":"IR",
    "gn:dem":920,
    "gn:feature_class":"P",
    "gn:feature_code":"PPL",
    "gn:name":"Kh\u0101nloq",
    "gn:population":0,
    "gn:timezone":"Asia/Tehran",
    "iso:country":"IR",
    "name:fas_x_preferred":[
        "\u062e\u0627\u0646\u0644\u0648\u0642"
    ],
    "name:fas_x_variant":[
        "Kh\u0101nl\u016bq",
        "Kh\u0101nloq",
        "\u062e\u0627\u0646\u0644\u0642"
    ],
    "wof:name":"Khanloq",
    "wof:placetype":"locality"
},
  "geometry": {"coordinates":[51.3345,35.33118],"type":"Point"}
}