{
  "type": "Feature",
  "properties": {
    "gn:admin1_code":"7",
    "gn:asciiname":"Sedeh",
    "gn:country_code":"IR",
    "gn:dem":2170,
    "gn:feature_class":"P",
    "gn:feature_code":"PPL",
    "gn:name":"Sedeh",
    "gn:population":0,
    "gn:timezone":"Asia/Tehran",
    "iso:country":"IR",
    "name:fas_x_preferred":[
        "\u0633\u062f\u0647"
    ],
    "name:und_x_variant":[
        "Sehdeh",
        "Sedeh"
    ],
    "wof:name":"Sedeh",
    "wof:placetype":"locality"
},
  "geometry": {"coordinates":[52.17579,30.71066],"type":"Point"}
}