{
  "type": "Feature",
  "properties": {
    "gn:admin1_code":"42",
    "gn:asciiname":"Barabad",
    "gn:country_code":"IR",
    "gn:dem":858,
    "gn:feature_class":"P",
    "gn:feature_code":"PPL",
    "gn:name":"Bar\u0101b\u0101d",
    "gn:population":0,
    "gn:timezone":"Asia/Tehran",
    "iso:country":"IR",
    "name:fas_x_preferred":[
        "Bor\u0101b\u0101d"
    ],
    "name:fas_x_variant":[
        "\u0628\u0631 \u0622\u0628\u0627\u062f",
        "Bar\u0101b\u0101d",
        "Bor \u0100b\u0101d"
    ],
    "name:und_x_variant":[
        "Bor \u0100b\u0101d"
    ],
    "wof:name":"Barabad",
    "wof:placetype":"locality"
},
  "geometry": {"coordinates":[57.31236,36.06967],"type":"Point"}
}