{
  "type": "Feature",
  "properties": {
    "gn:admin1_code":"36",
    "gn:asciiname":"Nurin",
    "gn:country_code":"IR",
    "gn:dem":1484,
    "gn:feature_class":"P",
    "gn:feature_code":"PPL",
    "gn:name":"N\u016br\u012bn",
    "gn:population":0,
    "gn:timezone":"Asia/Tehran",
    "iso:country":"IR",
    "name:ara_x_preferred":[
        "\u0646\u0648\u0631\u064a\u0646"
    ],
    "name:azb_x_preferred":[
        "\u0646\u0648\u0631\u06cc\u0646"
    ],
    "name:fas_x_preferred":[
        "\u0646\u0648\u0631\u064a\u0646"
    ],
    "name:fas_x_variant":[
        "N\u016br\u012bn",
        "\u0646\u0648\u0631\u06cc\u0646"
    ],
    "name:und_x_variant":[
        "Nar\u016bn",
        "Nurun"
    ],
    "wof:name":"Nurin",
    "wof:placetype":"locality"
},
  "geometry": {"coordinates":[49.28166,36.11054],"type":"Point"}
}