{
  "type": "Feature",
  "properties": {
    "gn:admin1_code":"7",
    "gn:asciiname":"Fadami",
    "gn:country_code":"IR",
    "gn:dem":760,
    "gn:feature_class":"P",
    "gn:feature_code":"PPL",
    "gn:name":"Fad\u0101m\u012b",
    "gn:population":0,
    "gn:timezone":"Asia/Tehran",
    "iso:country":"IR",
    "name:ara_x_preferred":[
        "\u0641\u062f\u0627\u0645\u064a"
    ],
    "name:fas_x_preferred":[
        "\u0641\u062f\u0627\u0645\u06cc"
    ],
    "name:fas_x_variant":[
        "Fad\u0101m\u012b \u0100b-e Sh\u016br",
        "Fad\u0101m\u012b"
    ],
    "name:msa_x_preferred":[
        "Fadami"
    ],
    "name:und_x_variant":[
        "Pad\u016bmi",
        "\u0100b-e Sh\u016br"
    ],
    "name:urd_x_preferred":[
        "\u0641\u062f\u0627\u0645\u06cc"
    ],
    "wof:name":"Fadami",
    "wof:placetype":"locality"
},
  "geometry": {"coordinates":[55.1347,28.2161],"type":"Point"}
}