{
  "type": "Feature",
  "properties": {
    "gn:admin1_code":"28.0",
    "gn:asciiname":"Parvaneh",
    "gn:country_code":"IR",
    "gn:dem":1548,
    "gn:feature_class":"P",
    "gn:feature_code":"PPL",
    "gn:name":"Parv\u0101neh",
    "gn:population":0,
    "gn:timezone":"Asia/Tehran",
    "iso:country":"IR",
    "name:fas_x_preferred":[
        "\u067e\u0631\u0648\u0627\u0646\u0647"
    ],
    "name:fas_x_variant":[
        "Parv\u0101neh"
    ],
    "name:und_x_variant":[
        "Par\u0101vaneh",
        "F\u0101r\u016bna"
    ],
    "wof:name":"Parvaneh",
    "wof:placetype":"locality"
},
  "geometry": {"coordinates":[51.92519,32.83388],"type":"Point"}
}