{
  "type": "Feature",
  "properties": {
    "gn:admin1_code":"42",
    "gn:asciiname":"Fakhrabad",
    "gn:country_code":"IR",
    "gn:dem":1766,
    "gn:feature_class":"P",
    "gn:feature_code":"PPL",
    "gn:name":"Fakhr\u0101b\u0101d",
    "gn:population":0,
    "gn:timezone":"Asia/Tehran",
    "iso:country":"IR",
    "name:fas_x_preferred":[
        "\u0641\u062e\u0631 \u0622\u0628\u0627\u062f"
    ],
    "name:fas_x_variant":[
        "Fakhr\u0101b\u0101d",
        "\u0641\u062e\u0631\u0622\u0628\u0627\u062f"
    ],
    "name:mzn_x_preferred":[
        "\u0641\u062e\u0631\u0622\u0628\u0627\u062f"
    ],
    "wof:name":"Fakhrabad",
    "wof:placetype":"locality"
},
  "geometry": {"coordinates":[59.98195,33.41249000000001],"type":"Point"}
}