{
  "type": "Feature",
  "properties": {
    "gn:admin1_code":"42",
    "gn:asciiname":"Neqab",
    "gn:country_code":"IR",
    "gn:dem":978,
    "gn:feature_class":"P",
    "gn:feature_code":"PPL",
    "gn:name":"Neq\u0101b",
    "gn:population":0,
    "gn:timezone":"Asia/Tehran",
    "iso:country":"IR",
    "name:fas_x_preferred":[
        "Neq\u0101b"
    ],
    "name:fas_x_variant":[
        "\u0646\u0642\u0627\u0628",
        "Nowq\u0101b",
        "Nowgh\u0101b",
        "Noq\u0101b"
    ],
    "name:und_x_variant":[
        "Nowq\u0101b",
        "Naughab",
        "Noq\u0101b",
        "Nowgh\u0101b",
        "\u0646\u0642\u0627\u0628"
    ],
    "wof:name":"Neqab",
    "wof:placetype":"locality"
},
  "geometry": {"coordinates":[58.34159,35.18686],"type":"Point"}
}