{
  "type": "Feature",
  "properties": {
    "gn:admin1_code":"13",
    "gn:asciiname":"Gura Jub-e Baba Karam",
    "gn:country_code":"IR",
    "gn:dem":1538,
    "gn:feature_class":"P",
    "gn:feature_code":"PPL",
    "gn:name":"G\u016br\u0101 J\u016bb-e B\u0101b\u0101 Karam",
    "gn:population":0,
    "gn:timezone":"Asia/Tehran",
    "iso:country":"IR",
    "name:ara_x_preferred":[
        "\u063a\u0648\u0631\u0627\u062c\u0648\u0628 \u0628\u0627\u0628\u0627\u0643\u0631\u0645"
    ],
    "name:ceb_x_preferred":[
        "G\u016br\u0101 J\u016bb-e B\u0101b\u0101 Karam"
    ],
    "name:fas_x_preferred":[
        "\u06af\u0648\u0631\u0627\u062c\u0648\u0628 \u0628\u0627\u0628\u0627 \u06a9\u0631\u0645"
    ],
    "name:fas_x_variant":[
        "G\u016br\u0101 J\u016bb-e B\u0101b\u0101 Karam",
        "\u06af\u0648\u0631\u0627\u062c\u0648\u0628 \u0628\u0627\u0628\u0627\u06a9\u0631\u0645"
    ],
    "name:swe_x_preferred":[
        "G\u016br\u0101 J\u016bb-e B\u0101b\u0101 Karam"
    ],
    "wof:name":"Gura Jub-e Baba Karam",
    "wof:placetype":"locality"
},
  "geometry": {"coordinates":[46.3611,34.3373],"type":"Point"}
}