{
  "type": "Feature",
  "properties": {
    "gn:admin1_code":"5",
    "gn:asciiname":"Zir Chal",
    "gn:country_code":"IR",
    "gn:dem":1782,
    "gn:feature_class":"P",
    "gn:feature_code":"PPL",
    "gn:name":"Z\u012br Ch\u0101l",
    "gn:population":0,
    "gn:timezone":"Asia/Tehran",
    "iso:country":"IR",
    "name:fas_x_preferred":[
        "\u0632\u064a\u0631 \u0686\u0627\u0644"
    ],
    "name:fas_x_variant":[
        "Z\u012br Ch\u0101l"
    ],
    "wof:name":"Zir Chal",
    "wof:placetype":"locality"
},
  "geometry": {"coordinates":[50.69833,31.10111],"type":"Point"}
}