{
  "type": "Feature",
  "properties": {
    "gn:admin1_code":"11",
    "gn:asciiname":"Sokhar",
    "gn:country_code":"IR",
    "gn:dem":328,
    "gn:feature_class":"P",
    "gn:feature_code":"PPL",
    "gn:name":"\u015eokhar",
    "gn:population":0,
    "gn:timezone":"Asia/Tehran",
    "iso:country":"IR",
    "name:fas_x_preferred":[
        "\u0635\u064f\u062e\u064e\u0631"
    ],
    "name:fas_x_variant":[
        "\u015eokhar"
    ],
    "wof:name":"Sokhar",
    "wof:placetype":"locality"
},
  "geometry": {"coordinates":[54.66667,27.01667],"type":"Point"}
}