{
  "type": "Feature",
  "properties": {
    "gn:admin1_code":"35.0",
    "gn:asciiname":"`Alamdar",
    "gn:country_code":"IR",
    "gn:dem":6,
    "gn:feature_class":"P",
    "gn:feature_code":"PPL",
    "gn:name":"\u2018Alamd\u0101r",
    "gn:population":0,
    "gn:timezone":"Asia/Tehran",
    "iso:country":"IR",
    "name:fas_x_preferred":[
        "\u0639\u0644\u0645\u062f\u0627\u0631"
    ],
    "name:fas_x_variant":[
        "\u0627\u064e\u0644\u064e\u0645\u062f\u0627\u0631",
        "\u2018Alamd\u0101r"
    ],
    "name:und_x_variant":[
        "Alamd\u0101r"
    ],
    "wof:name":"`Alamdar",
    "wof:placetype":"locality"
},
  "geometry": {"coordinates":[52.70919,36.51246],"type":"Point"}
}