{
  "type": "Feature",
  "properties": {
    "gn:admin1_code":"23",
    "gn:asciiname":"Qalandar",
    "gn:country_code":"IR",
    "gn:dem":1915,
    "gn:feature_class":"P",
    "gn:feature_code":"PPL",
    "gn:name":"Qalandar",
    "gn:population":0,
    "gn:timezone":"Asia/Tehran",
    "iso:country":"IR",
    "name:fas_x_preferred":[
        "\u0642\u0644\u0646\u062f\u0631"
    ],
    "name:und_x_variant":[
        "Ghalandar",
        "Qalandar",
        "\u0642\u0644\u0646\u062f\u0631"
    ],
    "wof:name":"Qalandar",
    "wof:placetype":"locality"
},
  "geometry": {"coordinates":[48.17188,34.04261],"type":"Point"}
}