{
  "type": "Feature",
  "properties": {
    "gn:admin1_code":"9",
    "gn:asciiname":"Sazian",
    "gn:country_code":"IR",
    "gn:dem":1744,
    "gn:feature_class":"P",
    "gn:feature_code":"PPL",
    "gn:name":"S\u0101z\u012b\u0101n",
    "gn:population":0,
    "gn:timezone":"Asia/Tehran",
    "iso:country":"IR",
    "name:ceb_x_preferred":[
        "S\u0101z\u012b\u0101n"
    ],
    "name:fas_x_preferred":[
        "\u0633\u0627\u0632\u064a\u0651\u0627\u0646"
    ],
    "name:fas_x_variant":[
        "S\u0101z\u012b\u0101n",
        "\u0633\u0627\u0632\u06cc\u0627\u0646"
    ],
    "name:msa_x_preferred":[
        "Saziyan"
    ],
    "name:swe_x_preferred":[
        "S\u0101z\u012b\u0101n"
    ],
    "name:und_x_variant":[
        "S\u0101z\u012by\u0101n"
    ],
    "wof:name":"Sazian",
    "wof:placetype":"locality"
},
  "geometry": {"coordinates":[48.15336,34.57359],"type":"Point"}
}