{
  "type": "Feature",
  "properties": {
    "gn:admin1_code":"35",
    "gn:asciiname":"Khorasan Mahalleh",
    "gn:country_code":"IR",
    "gn:dem":13,
    "gn:feature_class":"P",
    "gn:feature_code":"PPL",
    "gn:name":"Khor\u0101s\u0101n Ma\u1e29alleh",
    "gn:population":0,
    "gn:timezone":"Asia/Tehran",
    "iso:country":"IR",
    "name:fas_x_preferred":[
        "\u062e\u0631\u0627\u0633\u0627\u0646 \u0645\u062d\u0644\u0647"
    ],
    "name:fas_x_variant":[
        "Khor\u0101s\u0101n Ma\u1e29alleh",
        "\u062e\u0631\u0627\u0633\u0627\u0646\u200c\u0645\u062d\u0644\u0647"
    ],
    "name:mzn_x_preferred":[
        "\u062e\u0631\u0627\u0633\u0627\u0646\u200c\u0645\u062d\u0644\u0647"
    ],
    "name:und_x_variant":[
        "\u062e\u064f\u0631\u0627\u0633\u0627\u0646 \u0645\u064e\u062d\u064e\u0644\u0650\u0651\u0647"
    ],
    "wof:name":"Khorasan Mahalleh",
    "wof:placetype":"locality"
},
  "geometry": {"coordinates":[52.60282,36.48207],"type":"Point"}
}