{
  "type": "Feature",
  "properties": {
    "gn:admin1_code":"26.0",
    "gn:asciiname":"Urazan",
    "gn:country_code":"IR",
    "gn:dem":2531,
    "gn:feature_class":"P",
    "gn:feature_code":"PPL",
    "gn:name":"\u016ar\u0101z\u0101n",
    "gn:population":0,
    "gn:timezone":"Asia/Tehran",
    "iso:country":"IR",
    "name:fas_x_preferred":[
        "\u0648\u0631\u0627\u0632\u0627\u0646"
    ],
    "name:fas_x_variant":[
        "\u016ar\u0101z\u0101n"
    ],
    "wof:name":"Urazan",
    "wof:placetype":"locality"
},
  "geometry": {"coordinates":[50.88333,36.15],"type":"Point"}
}