{
  "type": "Feature",
  "properties": {
    "gn:admin1_code":"8.0",
    "gn:asciiname":"Darvaz-e Pa'in",
    "gn:country_code":"IR",
    "gn:dem":28,
    "gn:feature_class":"P",
    "gn:feature_code":"PPL",
    "gn:name":"Darv\u0101z-e P\u0101\u2019\u012bn",
    "gn:population":0,
    "gn:timezone":"Asia/Tehran",
    "iso:country":"IR",
    "name:fas_x_preferred":[
        "\u062f\u0631\u0648\u0627\u0632 \u067e\u0627\u0626\u06cc\u0646"
    ],
    "name:und_x_variant":[
        "Darv\u0101z-e P\u0101\u2019\u012bn"
    ],
    "wof:name":"Darvaz-e Pa'in",
    "wof:placetype":"locality"
},
  "geometry": {"coordinates":[49.14589,37.48118],"type":"Point"}
}