{
  "type": "Feature",
  "properties": {
    "gn:admin1_code":"29",
    "gn:asciiname":"Kuy-e Lay-e `Abdollahabad",
    "gn:country_code":"IR",
    "gn:dem":2823,
    "gn:feature_class":"P",
    "gn:feature_code":"PPL",
    "gn:name":"K\u016by-e L\u0101y-e \u2018Abdoll\u0101h\u0101b\u0101d",
    "gn:population":0,
    "gn:timezone":"Asia/Tehran",
    "iso:country":"IR",
    "name:fas_x_preferred":[
        "K\u016by-e L\u0101y-e \u2018Abdoll\u0101h\u0101b\u0101d"
    ],
    "name:fas_x_variant":[
        "\u06a9\u0648\u06cc \u0644\u0627\u06cc \u0639\u0628\u062f \u0627\u0644\u0644\u0647"
    ],
    "wof:name":"Kuy-e Lay-e `Abdollahabad",
    "wof:placetype":"locality"
},
  "geometry": {"coordinates":[55.25361,30.40333],"type":"Point"}
}