{
  "type": "Feature",
  "properties": {
    "gn:admin1_code":"8",
    "gn:asciiname":"Kuh Boneh",
    "gn:country_code":"IR",
    "gn:dem":10,
    "gn:feature_class":"P",
    "gn:feature_code":"PPL",
    "gn:name":"K\u016bh Boneh",
    "gn:population":0,
    "gn:timezone":"Asia/Tehran",
    "iso:country":"IR",
    "name:fas_x_preferred":[
        "K\u016bh Boneh"
    ],
    "name:fas_x_variant":[
        "\u06a9\u0648\u0647 \u0628\u0646\u0647"
    ],
    "name:msa_x_preferred":[
        "Kuh Boneh"
    ],
    "name:ukr_x_preferred":[
        "\u041a\u0443\u0445-\u0411\u043e\u043d\u0435"
    ],
    "name:und_x_variant":[
        "Kooh Boneh",
        "\u06a9\u0648\u0647 \u0628\u0646\u0647"
    ],
    "wof:name":"Kuh Boneh",
    "wof:placetype":"locality"
},
  "geometry": {"coordinates":[49.99332,37.18603],"type":"Point"}
}