{
  "type": "Feature",
  "properties": {
    "gn:admin1_code":"22",
    "gn:asciiname":"Zardaki-ye Sofla",
    "gn:country_code":"IR",
    "gn:dem":15,
    "gn:feature_class":"P",
    "gn:feature_code":"PPL",
    "gn:name":"Zardak\u012b-ye Sofl\u00e1",
    "gn:population":0,
    "gn:timezone":"Asia/Tehran",
    "iso:country":"IR",
    "name:fas_x_preferred":[
        "\u0632\u064e\u0631\u062f\u064e\u0643\u0626 \u067e\u0627\u0626\u064a\u0646"
    ],
    "name:fas_x_variant":[
        "\u0632\u0631\u062f\u0643\u06cc \u0633\u0641\u0644\u0649",
        "Zardak\u012b-ye P\u0101\u2019\u012bn",
        "Zardak\u012b-ye Sofl\u00e1"
    ],
    "name:und_x_variant":[
        "Zardaki",
        "Zardaki Sofla"
    ],
    "wof:name":"Zardaki-ye Sofla",
    "wof:placetype":"locality"
},
  "geometry": {"coordinates":[50.937,29.2698],"type":"Point"}
}