{
  "type": "Feature",
  "properties": {
    "gn:admin1_code":"28",
    "gn:asciiname":"Mohammadabad",
    "gn:country_code":"IR",
    "gn:dem":949,
    "gn:feature_class":"P",
    "gn:feature_code":"PPL",
    "gn:name":"Mo\u1e29ammad\u0101b\u0101d",
    "gn:population":0,
    "gn:timezone":"Asia/Tehran",
    "iso:country":"IR",
    "name:ara_x_preferred":[
        "\u0645\u062d\u0645\u062f \u0623\u0628\u0627\u062f"
    ],
    "name:fas_x_preferred":[
        "\u0645\u064f\u062d\u064e\u0645\u064e\u0651\u062f\u0627\u0628\u0627\u062f\u0650 \u0645\u064f\u062d\u064e\u0645\u064e\u0651\u062f\u06cc"
    ],
    "name:fas_x_variant":[
        "\u0645\u062d\u0645\u062f \u0622\u0628\u0627\u062f",
        "Mo\u1e29ammad\u0101b\u0101d-e Mo\u1e29ammad\u012b",
        "Mo\u1e29ammad\u0101b\u0101d",
        "\u0645\u062d\u0645\u062f\u0622\u0628\u0627\u062f"
    ],
    "name:und_x_variant":[
        "Muhammad\u0101b\u0101d"
    ],
    "wof:name":"Mohammadabad",
    "wof:placetype":"locality"
},
  "geometry": {"coordinates":[51.7588,33.8818],"type":"Point"}
}