{
  "type": "Feature",
  "properties": {
    "gn:admin1_code":"41",
    "gn:asciiname":"Mazra`eh-ye Andaran",
    "gn:country_code":"IR",
    "gn:dem":2069,
    "gn:feature_class":"P",
    "gn:feature_code":"PPL",
    "gn:name":"Mazra\u2018eh-ye Andar\u0101n",
    "gn:population":0,
    "gn:timezone":"Asia/Tehran",
    "iso:country":"IR",
    "name:fas_x_preferred":[
        "\u06a9\u0644\u0627\u062a\u0647 \u0627\u0646\u062f\u0631\u0648\u0646"
    ],
    "name:fas_x_variant":[
        "Kal\u0101teh-ye Andar\u016b",
        "Kal\u0101teh-ye Andar\u016bn",
        "\u0645\u0632\u0631\u0639\u0647 \u0627\u0646\u062f\u0631\u0627\u0646",
        "\u0627\u0646\u062f\u0631\u0647"
    ],
    "name:und_x_variant":[
        "Mazra\u2018eh-ye Andar\u0101n",
        "Andareh"
    ],
    "wof:name":"Mazra`eh-ye Andaran",
    "wof:placetype":"locality"
},
  "geometry": {"coordinates":[59.51414000000001,33.1264],"type":"Point"}
}