{
  "type": "Feature",
  "properties": {
    "gn:admin1_code":"15",
    "gn:asciiname":"Magran-e Seh",
    "gn:country_code":"IR",
    "gn:dem":34,
    "gn:feature_class":"P",
    "gn:feature_code":"PPL",
    "gn:name":"Magr\u0101n-e Seh",
    "gn:population":0,
    "gn:timezone":"Asia/Tehran",
    "iso:country":"IR",
    "name:fas_x_preferred":[
        "\u0645\u06af\u0631\u0627\u0646 \u0633\u0647"
    ],
    "name:fas_x_variant":[
        "\u0645\u06af\u0631\u06cc\u0627\u0646 \u0633\u0647",
        "\u0639\u0634\u06cc\u0631\u0647 \u062e\u0644\u0641"
    ],
    "name:und_x_variant":[
        "Khasraj Khalaf",
        "Magr\u0101n-e Seh",
        "Magr\u012b\u0101n-e Seh",
        "\u2018Ash\u012breh Khalaf"
    ],
    "wof:name":"Magran-e Seh",
    "wof:placetype":"locality"
},
  "geometry": {"coordinates":[48.47335,31.73562],"type":"Point"}
}