{
  "type": "Feature",
  "properties": {
    "gn:admin1_code":"4.0",
    "gn:asciiname":"Kalateh-ye Sohrab",
    "gn:country_code":"IR",
    "gn:dem":1096,
    "gn:feature_class":"P",
    "gn:feature_code":"PPL",
    "gn:name":"Kal\u0101teh-ye Sohr\u0101b",
    "gn:population":0,
    "gn:timezone":"Asia/Tehran",
    "iso:country":"IR",
    "name:fas_x_preferred":[
        "\u06a9\u0644\u0627\u062a\u0647 \u0633\u0647\u0631\u0627\u0628"
    ],
    "name:fas_x_variant":[
        "Kal\u0101teh-ye Sohr\u0101b"
    ],
    "wof:name":"Kalateh-ye Sohrab",
    "wof:placetype":"locality"
},
  "geometry": {"coordinates":[60.6191,30.7001],"type":"Point"}
}