{
  "type": "Feature",
  "properties": {
    "gn:admin1_code":"41",
    "gn:asciiname":"Kalateh-ye Mazar",
    "gn:country_code":"IR",
    "gn:dem":2000,
    "gn:feature_class":"P",
    "gn:feature_code":"PPL",
    "gn:name":"Kal\u0101teh-ye Maz\u0101r",
    "gn:population":0,
    "gn:timezone":"Asia/Tehran",
    "iso:country":"IR",
    "name:fas_x_preferred":[
        "\u06a9\u0644\u0627\u062a\u0647 \u0645\u0632\u0627\u0631"
    ],
    "name:fas_x_variant":[
        "Kal\u0101teh Maz\u0101r",
        "Kal\u0101teh-ye Maz\u0101r"
    ],
    "wof:name":"Kalateh-ye Mazar",
    "wof:placetype":"locality"
},
  "geometry": {"coordinates":[59.5351,32.178],"type":"Point"}
}