{
  "type": "Feature",
  "properties": {
    "gn:admin1_code":"5",
    "gn:asciiname":"Poshtaveh-ye Sofla",
    "gn:cc2":"IR",
    "gn:country_code":"IR",
    "gn:dem":1557,
    "gn:feature_class":"P",
    "gn:feature_code":"PPL",
    "gn:name":"Posht\u0101veh-ye Sofl\u00e1",
    "gn:population":0,
    "gn:timezone":"Asia/Tehran",
    "iso:country":"IR",
    "name:ara_x_preferred":[
        "\u0628\u0634\u062a \u0637\u0627\u0648\u0629 \u0627\u0644\u0633\u0641\u0644\u064a"
    ],
    "name:fas_x_preferred":[
        "Posht\u0101veh-ye Sofl\u00e1"
    ],
    "name:fas_x_variant":[
        "\u067e\u0634\u062a \u062a\u0627\u0648\u0647 \u0633\u0641\u0644\u06cc",
        "\u067e\u0634\u062a \u0637\u0627\u0648\u0647 \u0633\u0641\u0644\u06cc"
    ],
    "name:und_x_variant":[
        "Posht\u0101veh-ye P\u0101\u2019\u012bn",
        "Posht T\u0101veh-ye Sofl\u00e1"
    ],
    "wof:name":"Poshtaveh-ye Sofla",
    "wof:placetype":"locality"
},
  "geometry": {"coordinates":[50.16528,30.93417],"type":"Point"}
}