{
  "type": "Feature",
  "properties": {
    "gn:admin1_code":"43",
    "gn:asciiname":"Ostad Teymurtash",
    "gn:country_code":"IR",
    "gn:dem":1160,
    "gn:feature_class":"P",
    "gn:feature_code":"PPL",
    "gn:name":"Ost\u0101d Teym\u016brt\u0101sh",
    "gn:population":0,
    "gn:timezone":"Asia/Tehran",
    "iso:country":"IR",
    "name:fas_x_preferred":[
        "Ost\u0101d Teym\u016brt\u0101sh"
    ],
    "name:und_x_variant":[
        "Qal\u2018eh-ye Ost\u0101h\u0101"
    ],
    "wof:name":"Ostad Teymurtash",
    "wof:placetype":"locality"
},
  "geometry": {"coordinates":[57.14333000000001,37.49306],"type":"Point"}
}