{
  "type": "Feature",
  "properties": {
    "gn:admin1_code":"4",
    "gn:asciiname":"Sulkok",
    "gn:country_code":"IR",
    "gn:dem":851,
    "gn:feature_class":"P",
    "gn:feature_code":"PPL",
    "gn:name":"S\u016blkok",
    "gn:population":0,
    "gn:timezone":"Asia/Tehran",
    "iso:country":"IR",
    "name:fas_x_preferred":[
        "\u0633\u0648\u0644\u06a9\u0648\u06a9"
    ],
    "name:fas_x_variant":[
        "Solk\u016bk",
        "S\u016blk\u016bk",
        "\u0633\u0648\u0644\u06a9\u06a9"
    ],
    "name:und_x_variant":[
        "S\u016blkok"
    ],
    "wof:name":"Sulkok",
    "wof:placetype":"locality"
},
  "geometry": {"coordinates":[59.48623000000001,26.70286],"type":"Point"}
}