{
  "type": "Feature",
  "properties": {
    "gn:admin1_code":"25",
    "gn:asciiname":"Sah",
    "gn:country_code":"IR",
    "gn:dem":1508,
    "gn:feature_class":"P",
    "gn:feature_code":"PPL",
    "gn:name":"Sah",
    "gn:population":0,
    "gn:timezone":"Asia/Tehran",
    "iso:country":"IR",
    "name:fas_x_preferred":[
        "\u0635\u062d"
    ],
    "name:fas_x_variant":[
        "\u0635\u064e\u0647",
        "\u0633\u0627\u0631",
        "\u0633\u064e\u0647",
        "\u015ea\u1e29"
    ],
    "name:und_x_variant":[
        "S\u0101r",
        "Sah",
        "\u015eah"
    ],
    "wof:name":"Sah",
    "wof:placetype":"locality"
},
  "geometry": {"coordinates":[53.92756,35.99460999999999],"type":"Point"}
}