{
  "type": "Feature",
  "properties": {
    "gn:admin1_code":"15",
    "gn:asciiname":"Zobeyd va Dabbat",
    "gn:country_code":"IR",
    "gn:dem":32,
    "gn:feature_class":"P",
    "gn:feature_code":"PPL",
    "gn:name":"Zobeyd va Dabb\u0101t",
    "gn:population":0,
    "gn:timezone":"Asia/Tehran",
    "iso:country":"IR",
    "name:ceb_x_preferred":[
        "Zobeydeh D\u016bb\u0101t"
    ],
    "name:fas_x_preferred":[
        "\u0632\u0628\u06cc\u062f\u0647 \u062f\u0648\u0628\u0627\u062a"
    ],
    "name:fas_x_variant":[
        "Zobeydeh D\u016bb\u0101t",
        "\u0632\u0628\u06cc\u062f \u0648 \u062f\u0628\u0627\u062a",
        "\u0632\u0628\u06cc\u062f\u0648\u062f\u0628\u0627\u062a"
    ],
    "name:swe_x_preferred":[
        "Zobeydeh D\u016bb\u0101t"
    ],
    "name:und_x_variant":[
        "Zobeyd va Dabb\u0101t"
    ],
    "wof:name":"Zobeyd va Dabbat",
    "wof:placetype":"locality"
},
  "geometry": {"coordinates":[48.648,31.76613],"type":"Point"}
}