{
  "type": "Feature",
  "properties": {
    "gn:admin1_code":"38.0",
    "gn:asciiname":"Horian",
    "gn:country_code":"IR",
    "gn:dem":979,
    "gn:feature_class":"P",
    "gn:feature_code":"PPL",
    "gn:name":"Hor\u012b\u0101n",
    "gn:population":0,
    "gn:timezone":"Asia/Tehran",
    "iso:country":"IR",
    "name:fas_x_preferred":[
        "\u0647\u0631\u06cc\u0627\u0646"
    ],
    "name:fas_x_variant":[
        "Hor\u012b\u0101n"
    ],
    "wof:name":"Horian",
    "wof:placetype":"locality"
},
  "geometry": {"coordinates":[50.2673,36.4683],"type":"Point"}
}