{
  "type": "Feature",
  "properties": {
    "gn:admin1_code":"11",
    "gn:asciiname":"Konardan-e Shomali",
    "gn:country_code":"IR",
    "gn:dem":188,
    "gn:feature_class":"P",
    "gn:feature_code":"PPL",
    "gn:name":"Kon\u0101rd\u0101n-e Shom\u0101l\u012b",
    "gn:population":0,
    "gn:timezone":"Asia/Tehran",
    "iso:country":"IR",
    "name:fas_x_preferred":[
        "\u062f\u0647\u0646\u0648 \u062f\u0645\u06cc\u062a\u0631"
    ],
    "name:fas_x_variant":[
        "Dehnow Dam\u012btar",
        "\u06a9\u0646\u0627\u0631\u062f\u0627\u0646 \u0634\u0645\u0627\u0644\u06cc"
    ],
    "name:und_x_variant":[
        "Kon\u0101rd\u0101n-e Shom\u0101l\u012b"
    ],
    "wof:name":"Konardan-e Shomali",
    "wof:placetype":"locality"
},
  "geometry": {"coordinates":[53.3189,27.1353],"type":"Point"}
}