{
  "type": "Feature",
  "properties": {
    "gn:admin1_code":"35",
    "gn:asciiname":"Darab Kola",
    "gn:country_code":"IR",
    "gn:dem":120,
    "gn:feature_class":"P",
    "gn:feature_code":"PPL",
    "gn:name":"D\u0101r\u0101b Kol\u0101",
    "gn:population":0,
    "gn:timezone":"Asia/Tehran",
    "iso:country":"IR",
    "name:fas_x_preferred":[
        "\u062f\u0627\u0631\u0627\u0628 \u0643\u064e\u0644\u0627"
    ],
    "name:fas_x_variant":[
        "\u062f\u0627\u0631\u064e\u0628 \u0642\u064e\u0644\u0639\u0650\u0647",
        "D\u0101r\u0101b Kol\u0101",
        "\u062f\u0627\u0631\u0627\u0628 \u0643\u0644\u0627",
        "\u062f\u0627\u0631\u0627\u0628\u06a9\u0644\u0627"
    ],
    "name:mzn_x_preferred":[
        "\u062f\u0627\u0631\u06a9\u0644\u0627"
    ],
    "name:und_x_variant":[
        "D\u0101rab Qal\u2018eh",
        "D\u0101r\u0101b Kal\u0101"
    ],
    "wof:name":"Darab Kola",
    "wof:placetype":"locality"
},
  "geometry": {"coordinates":[53.25214,36.56148],"type":"Point"}
}