{
  "type": "Feature",
  "properties": {
    "gn:admin1_code":"35",
    "gn:asciiname":"Nahar",
    "gn:country_code":"IR",
    "gn:dem":1694,
    "gn:feature_class":"P",
    "gn:feature_code":"PPL",
    "gn:name":"Nahar",
    "gn:population":0,
    "gn:timezone":"Asia/Tehran",
    "iso:country":"IR",
    "name:ara_x_preferred":[
        "\u0646\u0647\u0627\u0631"
    ],
    "name:ceb_x_preferred":[
        "Nahar"
    ],
    "name:deu_x_preferred":[
        "Nahar"
    ],
    "name:fas_x_preferred":[
        "\u0646\u0647\u0631"
    ],
    "name:fra_x_preferred":[
        "Ennahar"
    ],
    "name:ita_x_preferred":[
        "Nahar"
    ],
    "name:pol_x_preferred":[
        "Nahar"
    ],
    "name:swe_x_preferred":[
        "Nahar"
    ],
    "wof:name":"Nahar",
    "wof:placetype":"locality"
},
  "geometry": {"coordinates":[52.3002,35.92069],"type":"Point"}
}