{
  "type": "Feature",
  "properties": {
    "gn:admin1_code":"15.0",
    "gn:asciiname":"Seh Atabak",
    "gn:country_code":"IR",
    "gn:dem":131,
    "gn:feature_class":"P",
    "gn:feature_code":"PPL",
    "gn:name":"Seh At\u0101bak",
    "gn:population":0,
    "gn:timezone":"Asia/Tehran",
    "iso:country":"IR",
    "wof:name":"Seh Atabak",
    "wof:placetype":"locality"
},
  "geometry": {"coordinates":[49.60444,31.18806],"type":"Point"}
}