{
  "type": "Feature",
  "properties": {
    "gn:admin1_code":"15",
    "gn:asciiname":"Boneh-ye Gholam `Aziz Qoli",
    "gn:country_code":"IR",
    "gn:dem":724,
    "gn:feature_class":"P",
    "gn:feature_code":"PPL",
    "gn:name":"Boneh-ye Ghol\u0101m \u2018Az\u012bz Qol\u012b",
    "gn:population":0,
    "gn:timezone":"Asia/Tehran",
    "iso:country":"IR",
    "name:fas_x_preferred":[
        "\u2018Az\u012bz Qol\u012b"
    ],
    "name:fas_x_variant":[
        "Boneh-ye Ghol\u0101m \u2018Az\u012bz Qol\u012b",
        "\u0628\u0646\u0647 \u063a\u0644\u0627\u0645 \u0639\u0632\u06cc\u0632 \u0642\u0644\u06cc",
        "\u063a\u0644\u0627\u0645"
    ],
    "name:und_x_variant":[
        "Ghol\u0101m"
    ],
    "wof:name":"Boneh-ye Gholam `Aziz Qoli",
    "wof:placetype":"locality"
},
  "geometry": {"coordinates":[49.72082,31.76981],"type":"Point"}
}