{
  "type": "Feature",
  "properties": {
    "gn:admin1_code":"23",
    "gn:asciiname":"Sar Qal`eh-ye Sofla",
    "gn:country_code":"IR",
    "gn:dem":1952,
    "gn:feature_class":"P",
    "gn:feature_code":"PPL",
    "gn:name":"Sar Qal\u2018eh-ye Sofl\u00e1",
    "gn:population":0,
    "gn:timezone":"Asia/Tehran",
    "iso:country":"IR",
    "name:fas_x_preferred":[
        "\u0633\u064e\u0631 \u0642\u064e\u0644\u0639\u0650\u0647 \u0639\u064f\u0644\u064a\u0627"
    ],
    "name:fas_x_variant":[
        "\u0633\u064e\u0631 \u063a\u064e\u0644\u0639\u0650\u0647",
        "\u0633\u064e\u0631 \u0642\u064e\u0644\u0639\u0650\u0647 \u0633\u064f\u0641\u0644\u064e\u0649",
        "Sar Qal\u2018eh",
        "\u0633\u0631 \u0642\u0644\u0639\u0647",
        "\u0633\u0631 \u0642\u0644\u0639\u0647 \u0633\u0641\u0644\u06cc"
    ],
    "name:und_x_variant":[
        "Sar Ghal\u2018eh",
        "Sar Qal\u2018eh \u2018Oly\u0101",
        "Sar Qal\u2018eh Sofl\u00e1",
        "Sar Qal\u2018eh-ye Sofl\u00e1"
    ],
    "wof:name":"Sar Qal`eh-ye Sofla",
    "wof:placetype":"locality"
},
  "geometry": {"coordinates":[49.59643,32.90557],"type":"Point"}
}