{
  "type": "Feature",
  "properties": {
    "gn:admin1_code":"11.0",
    "gn:asciiname":"Sokunatgah-e Hasteh Kuh",
    "gn:country_code":"IR",
    "gn:dem":641,
    "gn:feature_class":"P",
    "gn:feature_code":"PPL",
    "gn:name":"Sok\u016bnatg\u0101h-e Hasteh K\u016bh",
    "gn:population":0,
    "gn:timezone":"Asia/Tehran",
    "iso:country":"IR",
    "name:fas_x_preferred":[
        "\u0633\u06a9\u0648\u0646\u062a\u06af\u0627\u0647 \u0647\u0633\u062a\u0647 \u06a9\u0648\u0647"
    ],
    "name:und_x_variant":[
        "Sok\u016bnatg\u0101h-e Hasteh K\u016bh"
    ],
    "wof:name":"Sokunatgah-e Hasteh Kuh",
    "wof:placetype":"locality"
},
  "geometry": {"coordinates":[54.85241,26.90458],"type":"Point"}
}