{
  "type": "Feature",
  "properties": {
    "gn:admin1_code":"13",
    "gn:asciiname":"Kahrar-e Sofla",
    "gn:country_code":"IR",
    "gn:dem":1362,
    "gn:feature_class":"P",
    "gn:feature_code":"PPL",
    "gn:name":"Kahr\u0101r-e Sofl\u00e1",
    "gn:population":0,
    "gn:timezone":"Asia/Tehran",
    "iso:country":"IR",
    "name:ceb_x_preferred":[
        "Kahr\u0101r-e Sofl\u00e1"
    ],
    "name:fas_x_preferred":[
        "\u06a9\u0647\u0631\u0627\u0631 \u0633\u0641\u0644\u06cc"
    ],
    "name:fas_x_variant":[
        "Kahr\u0101r-e Sofl\u00e1"
    ],
    "name:swe_x_preferred":[
        "Kahr\u0101r-e Sofl\u00e1"
    ],
    "name:und_x_variant":[
        "Qahr\u0101r-e P\u0101\u2019\u012bn",
        "Kahr\u0101r"
    ],
    "wof:name":"Kahrar-e Sofla",
    "wof:placetype":"locality"
},
  "geometry": {"coordinates":[47.23,34.2069],"type":"Point"}
}