{
  "type": "Feature",
  "properties": {
    "gn:admin1_code":"7",
    "gn:asciiname":"Chaghan",
    "gn:country_code":"IR",
    "gn:dem":815,
    "gn:feature_class":"P",
    "gn:feature_code":"PPL",
    "gn:name":"Chagh\u0101n",
    "gn:population":0,
    "gn:timezone":"Asia/Tehran",
    "iso:country":"IR",
    "name:fas_x_preferred":[
        "\u0686\u063a\u0627\u0646"
    ],
    "name:fas_x_variant":[
        "Chagh\u0101n"
    ],
    "name:und_x_variant":[
        "Chogh\u0101n"
    ],
    "wof:name":"Chaghan",
    "wof:placetype":"locality"
},
  "geometry": {"coordinates":[53.69752,28.20708],"type":"Point"}
}