{
  "type": "Feature",
  "properties": {
    "gn:admin1_code":"8",
    "gn:asciiname":"Kalah Sara",
    "gn:cc2":"IR",
    "gn:country_code":"IR",
    "gn:dem":267,
    "gn:feature_class":"P",
    "gn:feature_code":"PPL",
    "gn:name":"Kalah Sar\u0101",
    "gn:population":0,
    "gn:timezone":"Asia/Tehran",
    "iso:country":"IR",
    "name:fas_x_preferred":[
        "Kalah Sar\u0101"
    ],
    "name:und_x_variant":[
        "Kaleh Sar\u0101"
    ],
    "wof:name":"Kalah Sara",
    "wof:placetype":"locality"
},
  "geometry": {"coordinates":[48.92083,37.67778],"type":"Point"}
}