{
  "type": "Feature",
  "properties": {
    "gn:admin1_code":"8",
    "gn:asciiname":"Kalah Sara",
    "gn:cc2":"IR",
    "gn:country_code":"IR",
    "gn:dem":267,
    "gn:feature_class":"P",
    "gn:feature_code":"PPL",
    "gn:name":"Kalah Sar\u0101",
    "gn:population":0,
    "gn:timezone":"Asia/Tehran",
    "iso:country":"IR",
    "name:fas_x_preferred":[
        "Kalah Sar\u0101"
    ],
    "name:fas_x_variant":[
        "\u06a9\u0644\u0647\u200c\u0633\u0631\u0627"
    ],
    "name:msa_x_preferred":[
        "Kalah Sara"
    ],
    "name:ukr_x_preferred":[
        "\u041a\u0430\u043b\u0430\u0445-\u0421\u0430\u0440\u0430"
    ],
    "name:und_x_variant":[
        "Kaleh Sar\u0101"
    ],
    "wof:name":"Kalah Sara",
    "wof:placetype":"locality"
},
  "geometry": {"coordinates":[48.92083,37.67778],"type":"Point"}
}