{
  "type": "Feature",
  "properties": {
    "gn:admin1_code":"4.0",
    "gn:asciiname":"Sar Rig",
    "gn:country_code":"IR",
    "gn:dem":483,
    "gn:feature_class":"P",
    "gn:feature_code":"PPL",
    "gn:name":"Sar R\u012bg",
    "gn:population":0,
    "gn:timezone":"Asia/Tehran",
    "iso:country":"IR",
    "name:fas_x_preferred":[
        "\u0633\u0631 \u0631\u06cc\u06af"
    ],
    "name:fas_x_variant":[
        "Sar R\u012bg"
    ],
    "wof:name":"Sar Rig",
    "wof:placetype":"locality"
},
  "geometry": {"coordinates":[61.7385,31.1045],"type":"Point"}
}