{
  "type": "Feature",
  "properties": {
    "gn:admin1_code":"22.0",
    "gn:asciiname":"Ahsham-e Aqa'i",
    "gn:country_code":"IR",
    "gn:dem":12,
    "gn:feature_class":"P",
    "gn:feature_code":"PPL",
    "gn:name":"A\u1e29sham-e \u0100q\u0101\u2019\u012b",
    "gn:population":0,
    "gn:timezone":"Asia/Tehran",
    "iso:country":"IR",
    "name:fas_x_preferred":[
        "\u0627\u064e\u062d\u0634\u064e\u0645\u0650 \u0622\u0642\u0627\u0626\u06cc"
    ],
    "name:fas_x_variant":[
        "A\u1e29sham-e \u0100q\u0101\u2019\u012b"
    ],
    "name:und_x_variant":[
        "A\u1e29sham \u0100q\u0101\u2019\u012b"
    ],
    "wof:name":"Ahsham-e Aqa'i",
    "wof:placetype":"locality"
},
  "geometry": {"coordinates":[51.04083,28.92806],"type":"Point"}
}