{
  "type": "Feature",
  "properties": {
    "gn:admin1_code":"9",
    "gn:asciiname":"Shahrak-e Piruz",
    "gn:country_code":"IR",
    "gn:dem":1998,
    "gn:feature_class":"P",
    "gn:feature_code":"PPL",
    "gn:name":"Shahrak-e P\u012br\u016bz",
    "gn:population":0,
    "gn:timezone":"Asia/Tehran",
    "iso:country":"IR",
    "name:fas_x_preferred":[
        "\u067e\u064a\u0631\u0648\u0632"
    ],
    "name:fas_x_variant":[
        "\u067e\u0631\u06cc",
        "P\u012br\u016bz",
        "Par\u012b",
        "\u0634\u0647\u0631\u06a9 \u067e\u06cc\u0631\u0648\u0632"
    ],
    "name:und_x_variant":[
        "F\u0101r\u012b",
        "Shahrak-e P\u012br\u016bz"
    ],
    "wof:name":"Shahrak-e Piruz",
    "wof:placetype":"locality"
},
  "geometry": {"coordinates":[49.04569,34.135],"type":"Point"}
}