{
  "type": "Feature",
  "properties": {
    "gn:admin1_code":"36",
    "gn:asciiname":"Qizjeh",
    "gn:country_code":"IR",
    "gn:dem":1856,
    "gn:feature_class":"P",
    "gn:feature_code":"PPL",
    "gn:name":"Q\u012bzjeh",
    "gn:population":0,
    "gn:timezone":"Asia/Tehran",
    "iso:country":"IR",
    "name:fas_x_preferred":[
        "\u0642\u064a\u0646\u0631\u062c\u0647"
    ],
    "name:fas_x_variant":[
        "\u0642\u0646\u0628\u0631\u0686\u0647",
        "Q\u012bnarcheh",
        "\u0642\u06cc\u0632\u062c\u0647"
    ],
    "name:und_x_variant":[
        "Gaynardzhe",
        "Qeynarjeh",
        "Ghainarjeh",
        "Q\u012bnarjeh",
        "Qanbarcheh",
        "Q\u012bzjeh"
    ],
    "wof:name":"Qizjeh",
    "wof:placetype":"locality"
},
  "geometry": {"coordinates":[48.6222,36.04849],"type":"Point"}
}