{
  "type": "Feature",
  "properties": {
    "gn:admin1_code":"10",
    "gn:asciiname":"Chambur",
    "gn:country_code":"IR",
    "gn:dem":866,
    "gn:feature_class":"P",
    "gn:feature_code":"PPL",
    "gn:name":"Chamb\u016br",
    "gn:population":0,
    "gn:timezone":"Asia/Tehran",
    "iso:country":"IR",
    "name:fas_x_preferred":[
        "\u0686\u0645\u0628\u0648\u0631"
    ],
    "name:fas_x_variant":[
        "Chamb\u016br"
    ],
    "wof:name":"Chambur",
    "wof:placetype":"locality"
},
  "geometry": {"coordinates":[47.0227,33.6352],"type":"Point"}
}