{
  "type": "Feature",
  "properties": {
    "gn:admin1_code":"15",
    "gn:asciiname":"Mahdiyeh",
    "gn:country_code":"IR",
    "gn:dem":32,
    "gn:feature_class":"P",
    "gn:feature_code":"PPL",
    "gn:name":"Mahd\u012byeh",
    "gn:population":0,
    "gn:timezone":"Asia/Tehran",
    "iso:country":"IR",
    "name:fas_x_preferred":[
        "\u0645\u0647\u062f\u06cc\u0647"
    ],
    "name:fas_x_variant":[
        "Mahd\u012byeh"
    ],
    "wof:name":"Mahdiyeh",
    "wof:placetype":"locality"
},
  "geometry": {"coordinates":[48.9865,31.83909],"type":"Point"}
}