{
  "type": "Feature",
  "properties": {
    "gn:admin1_code":"10.0",
    "gn:asciiname":"Shahrak-e Sartaf",
    "gn:country_code":"IR",
    "gn:dem":1325,
    "gn:feature_class":"P",
    "gn:feature_code":"PPL",
    "gn:name":"Shahrak-e Sar\u0163\u0101f",
    "gn:population":0,
    "gn:timezone":"Asia/Tehran",
    "iso:country":"IR",
    "name:fas_x_preferred":[
        "\u0634\u0647\u0631\u06a9 \u0633\u0631\u0637\u0627\u0641"
    ],
    "name:fas_x_variant":[
        "Shahrak-e Sar\u0163\u0101f"
    ],
    "wof:name":"Shahrak-e Sartaf",
    "wof:placetype":"locality"
},
  "geometry": {"coordinates":[46.3791,33.5888],"type":"Point"}
}