{
  "type": "Feature",
  "properties": {
    "gn:admin1_code":"8",
    "gn:asciiname":"Bala Mahalleh-ye Khereshk",
    "gn:country_code":"IR",
    "gn:dem":183,
    "gn:feature_class":"P",
    "gn:feature_code":"PPL",
    "gn:name":"B\u0101l\u0101 Ma\u1e29alleh-ye Khereshk",
    "gn:population":0,
    "gn:timezone":"Asia/Tehran",
    "iso:country":"IR",
    "name:ceb_x_preferred":[
        "B\u0101l\u0101 Ma\u1e29alleh-ye Khereshk"
    ],
    "name:fas_x_preferred":[
        "\u0628\u0627\u0644\u0627 \u0645\u062d\u0644\u0651\u0647 \u062e\u0631\u0634\u06a9"
    ],
    "name:fas_x_variant":[
        "Kharashk-e P\u0101\u2019\u012bn",
        "B\u0101l\u0101 Ma\u1e29alleh-ye Khereshk",
        "\u062e\u0631\u0634\u06a9"
    ],
    "name:msa_x_preferred":[
        "Kharashk"
    ],
    "name:swe_x_preferred":[
        "B\u0101l\u0101 Ma\u1e29alleh-ye Khereshk"
    ],
    "name:ukr_x_preferred":[
        "\u0425\u0430\u0440\u0430\u0448\u043a"
    ],
    "name:und_x_variant":[
        "Qarehchak",
        "Khareshk",
        "Kharashi",
        "Khereshk"
    ],
    "wof:name":"Bala Mahalleh-ye Khereshk",
    "wof:placetype":"locality"
},
  "geometry": {"coordinates":[49.54129,36.90668],"type":"Point"}
}