{
  "type": "Feature",
  "properties": {
    "gn:admin1_code":"41",
    "gn:asciiname":"Duzangan",
    "gn:country_code":"IR",
    "gn:dem":1791,
    "gn:feature_class":"P",
    "gn:feature_code":"PPL",
    "gn:name":"D\u016bzang\u0101n",
    "gn:population":0,
    "gn:timezone":"Asia/Tehran",
    "iso:country":"IR",
    "name:fas_x_preferred":[
        "\u062f\u0648\u0632\u0646\u06af\u0627\u0646"
    ],
    "name:fas_x_variant":[
        "D\u016bzang\u0101n"
    ],
    "name:und_x_variant":[
        "Kal\u0101teh D\u016bzangun",
        "Doz\u0101ngh\u0101n",
        "Doozangan",
        "D\u016bz\u012bg\u0101n"
    ],
    "wof:name":"Duzangan",
    "wof:placetype":"locality"
},
  "geometry": {"coordinates":[59.6552,32.12536],"type":"Point"}
}