{
  "type": "Feature",
  "properties": {
    "gn:admin1_code":"35.0",
    "gn:asciiname":"Palham Dasht",
    "gn:country_code":"IR",
    "gn:dem":-10,
    "gn:feature_class":"P",
    "gn:feature_code":"PPL",
    "gn:name":"Palham Dasht",
    "gn:population":0,
    "gn:timezone":"Asia/Tehran",
    "iso:country":"IR",
    "name:ceb_x_preferred":[
        "Palham Dasht"
    ],
    "name:fas_x_preferred":[
        "\u067e\u0644\u0647\u0645 \u062f\u0634\u062a"
    ],
    "name:fas_x_variant":[
        "\u067e\u0644\u0647\u0645\u200c\u062f\u0634\u062a"
    ],
    "name:swe_x_preferred":[
        "Palham Dasht"
    ],
    "wof:name":"Palham Dasht",
    "wof:placetype":"locality"
},
  "geometry": {"coordinates":[50.89024000000001,36.78922],"type":"Point"}
}