{
  "type": "Feature",
  "properties": {
    "gn:admin1_code":"42.0",
    "gn:asciiname":"Kalateh-ye Qasemabad",
    "gn:country_code":"IR",
    "gn:dem":321,
    "gn:feature_class":"P",
    "gn:feature_code":"PPL",
    "gn:name":"Kal\u0101teh-ye Q\u0101sem\u0101b\u0101d",
    "gn:population":0,
    "gn:timezone":"Asia/Tehran",
    "iso:country":"IR",
    "name:fas_x_preferred":[
        "Kal\u0101teh-ye Q\u0101sem\u0101b\u0101d"
    ],
    "name:fas_x_variant":[
        "Q\u0101sem Kh\u0101n",
        "\u06a9\u0644\u0627\u062a\u0647 \u0642\u0627\u0633\u0645 \u0622\u0628\u0627\u062f"
    ],
    "name:und_x_variant":[
        "Q\u0101semab\u0101d",
        "\u06a9\u0644\u0627\u062a\u0647 \u0642\u0627\u0633\u0645 \u0622\u0628\u0627\u062f",
        "Kasymkhan"
    ],
    "wof:name":"Kalateh-ye Qasemabad",
    "wof:placetype":"locality"
},
  "geometry": {"coordinates":[61.14992,36.30791],"type":"Point"}
}