{
  "type": "Feature",
  "properties": {
    "gn:admin1_code":"15",
    "gn:asciiname":"`Alleh",
    "gn:country_code":"IR",
    "gn:dem":27,
    "gn:feature_class":"P",
    "gn:feature_code":"PPL",
    "gn:name":"\u2018Alleh",
    "gn:population":0,
    "gn:timezone":"Asia/Tehran",
    "iso:country":"IR",
    "name:fas_x_preferred":[
        "\u0639\u0644\u0647"
    ],
    "name:fas_x_variant":[
        "\u2018Elleh-ye Band-e Q\u012br",
        "\u2018Alleh",
        "\u0639\u0644\u0647 \u0628\u0646\u062f \u0642\u06cc\u0631"
    ],
    "name:und_x_variant":[
        "\u2018Elleh"
    ],
    "wof:name":"`Alleh",
    "wof:placetype":"locality"
},
  "geometry": {"coordinates":[48.88745,31.6843],"type":"Point"}
}