{
  "type": "Feature",
  "properties": {
    "gn:admin1_code":"42",
    "gn:asciiname":"Kheyrabad",
    "gn:country_code":"IR",
    "gn:dem":1614,
    "gn:feature_class":"P",
    "gn:feature_code":"PPL",
    "gn:name":"Kheyr\u0101b\u0101d",
    "gn:population":0,
    "gn:timezone":"Asia/Tehran",
    "iso:country":"IR",
    "name:fas_x_preferred":[
        "\u062e\u06cc\u0631 \u0622\u0628\u0627\u062f"
    ],
    "name:fas_x_variant":[
        "Kheyr\u0101b\u0101d",
        "\u062e\u06cc\u0631\u0622\u0628\u0627\u062f"
    ],
    "wof:name":"Kheyrabad",
    "wof:placetype":"locality"
},
  "geometry": {"coordinates":[57.60374,35.79483],"type":"Point"}
}