{
  "type": "Feature",
  "properties": {
    "gn:admin1_code":"10",
    "gn:asciiname":"Meymeh",
    "gn:country_code":"IR",
    "gn:dem":1225,
    "gn:feature_class":"P",
    "gn:feature_code":"PPL",
    "gn:name":"Meymeh",
    "gn:population":0,
    "gn:timezone":"Asia/Tehran",
    "iso:country":"IR",
    "name:fas_x_preferred":[
        "\u0645\u06cc\u0645\u0647"
    ],
    "wof:name":"Meymeh",
    "wof:placetype":"locality"
},
  "geometry": {"coordinates":[46.9196,33.2278],"type":"Point"}
}