{
  "type": "Feature",
  "properties": {
    "gn:admin1_code":"37.0",
    "gn:asciiname":"Makhtum Pir Hajji",
    "gn:country_code":"IR",
    "gn:dem":42,
    "gn:feature_class":"P",
    "gn:feature_code":"PPL",
    "gn:name":"Makht\u016bm P\u012br \u1e28\u0101jj\u012b",
    "gn:population":0,
    "gn:timezone":"Asia/Tehran",
    "iso:country":"IR",
    "name:fas_x_preferred":[
        "\u0645\u062e\u062a\u0648\u0645 \u067e\u06cc\u0631 \u062d\u0627\u062c\u06cc"
    ],
    "name:und_x_variant":[
        "Makht\u016bm P\u012br \u1e28\u0101jj\u012b"
    ],
    "wof:name":"Makhtum Pir Hajji",
    "wof:placetype":"locality"
},
  "geometry": {"coordinates":[55.18737,37.21995],"type":"Point"}
}