{
  "type": "Feature",
  "properties": {
    "gn:admin1_code":"4.0",
    "gn:asciiname":"Shakband",
    "gn:country_code":"IR",
    "gn:dem":1318,
    "gn:feature_class":"P",
    "gn:feature_code":"PPLF",
    "gn:name":"Shakband",
    "gn:population":0,
    "gn:timezone":"Asia/Tehran",
    "iso:country":"IR",
    "name:fas_x_preferred":[
        "\u0634\u06a9\u0628\u0646\u062f"
    ],
    "wof:name":"Shakband",
    "wof:placetype":"locality"
},
  "geometry": {"coordinates":[61.44667,28.33847],"type":"Point"}
}