{
  "type": "Feature",
  "properties": {
    "gn:admin1_code":"42.0",
    "gn:asciiname":"Chah-e Chehel Nakhowd",
    "gn:country_code":"IR",
    "gn:dem":1111,
    "gn:feature_class":"P",
    "gn:feature_code":"PPLL",
    "gn:name":"Ch\u0101h-e Chehel Nakhowd",
    "gn:population":0,
    "gn:timezone":"Asia/Tehran",
    "iso:country":"IR",
    "name:fas_x_preferred":[
        "\u0686\u0627\u0647 \u0686\u0647\u0644 \u0646\u062e\u0648\u062f"
    ],
    "name:und_x_variant":[
        "Ch\u0101h-e Chehel Nakhowd"
    ],
    "wof:name":"Chah-e Chehel Nakhowd",
    "wof:placetype":"locality"
},
  "geometry": {"coordinates":[58.91546999999999,34.28952],"type":"Point"}
}