{
  "type": "Feature",
  "properties": {
    "gn:admin1_code":"42.0",
    "gn:asciiname":"Dahaneh-ye Akhlamad",
    "gn:country_code":"IR",
    "gn:dem":1264,
    "gn:feature_class":"P",
    "gn:feature_code":"PPL",
    "gn:name":"Dahaneh-ye Akhlamad",
    "gn:population":0,
    "gn:timezone":"Asia/Tehran",
    "iso:country":"IR",
    "name:fas_x_preferred":[
        "\u062f\u0647\u0646\u0647 \u0627\u062e\u0644\u0645\u062f"
    ],
    "name:und_x_variant":[
        "Akhlamad",
        "Dahaneh-ye Akhl\u016bmad",
        "Akhtamand",
        "Dahaneh\u00e9 Akhlemad",
        "Dahaneh-ye Akhlamad"
    ],
    "wof:name":"Dahaneh-ye Akhlamad",
    "wof:placetype":"locality"
},
  "geometry": {"coordinates":[58.97083000000001,36.66384],"type":"Point"}
}