{
  "type": "Feature",
  "properties": {
    "gn:admin1_code":"8",
    "gn:asciiname":"Garfam",
    "gn:country_code":"IR",
    "gn:dem":-10,
    "gn:feature_class":"P",
    "gn:feature_code":"PPL",
    "gn:name":"Garfam",
    "gn:population":0,
    "gn:timezone":"Asia/Tehran",
    "iso:country":"IR",
    "name:fas_x_preferred":[
        "\u06af\u0631\u0641\u0645"
    ],
    "name:und_x_variant":[
        "Garfan",
        "Garfam",
        "\u06af\u0631\u0641\u0645"
    ],
    "wof:name":"Garfam",
    "wof:placetype":"locality"
},
  "geometry": {"coordinates":[49.6396,37.33322],"type":"Point"}
}