{
  "type": "Feature",
  "properties": {
    "gn:admin1_code":"13",
    "gn:asciiname":"Bakalani",
    "gn:country_code":"IR",
    "gn:dem":1319,
    "gn:feature_class":"P",
    "gn:feature_code":"PPL",
    "gn:name":"B\u0101kal\u0101n\u012b",
    "gn:population":0,
    "gn:timezone":"Asia/Tehran",
    "iso:country":"IR",
    "name:fas_x_preferred":[
        "\u0628\u0627\u06a9\u0644\u0627\u0646\u06cc"
    ],
    "name:fas_x_variant":[
        "B\u0101nkal\u0101n\u012b",
        "B\u0101kal\u0101n\u012b"
    ],
    "wof:name":"Bakalani",
    "wof:placetype":"locality"
},
  "geometry": {"coordinates":[46.6747,34.5524],"type":"Point"}
}