{
  "type": "Feature",
  "properties": {
    "gn:admin1_code":"5",
    "gn:asciiname":"Tolchegah",
    "gn:country_code":"IR",
    "gn:dem":1109,
    "gn:feature_class":"P",
    "gn:feature_code":"PPL",
    "gn:name":"Tolcheg\u0101h",
    "gn:population":0,
    "gn:timezone":"Asia/Tehran",
    "iso:country":"IR",
    "name:fas_x_preferred":[
        "\u062a\u064e\u0644 \u0686\u0650\u0643\u0627"
    ],
    "name:fas_x_variant":[
        "\u062a\u064e\u0644 \u0686\u0650\u0642\u0627",
        "\u062a\u064e\u0644\u0650 \u0686\u0650\u06af\u0627\u0647",
        "Tolcheg\u0101h",
        "\u062a\u0644\u0686\u06af\u0627\u0647"
    ],
    "name:und_x_variant":[
        "Tal Cheq\u0101",
        "Tal Chek\u0101",
        "Tal-e Cheg\u0101h"
    ],
    "wof:name":"Tolchegah",
    "wof:placetype":"locality"
},
  "geometry": {"coordinates":[50.96264,30.54016],"type":"Point"}
}