{
  "type": "Feature",
  "properties": {
    "gn:admin1_code":"37.0",
    "gn:asciiname":"Chenashk",
    "gn:country_code":"IR",
    "gn:dem":1056,
    "gn:feature_class":"P",
    "gn:feature_code":"PPL",
    "gn:name":"Chen\u0101shk",
    "gn:population":0,
    "gn:timezone":"Asia/Tehran",
    "iso:country":"IR",
    "name:ceb_x_preferred":[
        "Chen\u0101shk"
    ],
    "name:fas_x_preferred":[
        "Deh Chen\u0101shk"
    ],
    "name:fas_x_variant":[
        "\u0686\u0646\u0627\u0634\u06a9",
        "\u062f\u0647 \u0686\u0646\u0627\u0634\u0643",
        "\u062f\u0647 \u0686\u0646\u0627\u0634\u06a9"
    ],
    "name:msa_x_preferred":[
        "Deh Chenashk"
    ],
    "name:swe_x_preferred":[
        "Chen\u0101shk"
    ],
    "wof:name":"Chenashk",
    "wof:placetype":"locality"
},
  "geometry": {"coordinates":[55.52518000000001,37.06963],"type":"Point"}
}