{
  "type": "Feature",
  "properties": {
    "gn:admin1_code":"5",
    "gn:asciiname":"Qabr-e Qeysar",
    "gn:country_code":"IR",
    "gn:dem":656,
    "gn:feature_class":"P",
    "gn:feature_code":"PPL",
    "gn:name":"Qabr-e Qey\u015far",
    "gn:population":0,
    "gn:timezone":"Asia/Tehran",
    "iso:country":"IR",
    "name:fas_x_preferred":[
        "\u0642\u0628\u0631 \u0642\u06cc\u0635\u0631"
    ],
    "name:fas_x_variant":[
        "Qabr-e Qey\u015far"
    ],
    "name:und_x_variant":[
        "Qabr-e Qey\u015far"
    ],
    "wof:name":"Qabr-e Qeysar",
    "wof:placetype":"locality"
},
  "geometry": {"coordinates":[50.1143,30.8663],"type":"Point"}
}