{
  "type": "Feature",
  "properties": {
    "gn:admin1_code":"7.0",
    "gn:asciiname":"Amirabad",
    "gn:country_code":"IR",
    "gn:dem":1598,
    "gn:feature_class":"P",
    "gn:feature_code":"PPL",
    "gn:name":"Am\u012br\u0101b\u0101d",
    "gn:population":0,
    "gn:timezone":"Asia/Tehran",
    "iso:country":"IR",
    "name:fas_x_preferred":[
        "\u2018Amr\u016b\u0101b\u0101d"
    ],
    "name:fas_x_variant":[
        "Am\u012br\u0101b\u0101d",
        "\u0627\u0645\u06cc\u0631 \u0622\u0628\u0627\u062f",
        "\u0639\u0645\u0631\u0622\u0628\u0627\u062f"
    ],
    "name:msa_x_preferred":[
        "Amrabad"
    ],
    "name:und_x_variant":[
        "\u2018Amr\u0101b\u0101d"
    ],
    "wof:name":"Amirabad",
    "wof:placetype":"locality"
},
  "geometry": {"coordinates":[52.7865,29.8762],"type":"Point"}
}