{
  "type": "Feature",
  "properties": {
    "gn:admin1_code":"15",
    "gn:asciiname":"Dohul",
    "gn:country_code":"IR",
    "gn:dem":36,
    "gn:feature_class":"P",
    "gn:feature_code":"PPL",
    "gn:name":"Doh\u016bl",
    "gn:population":0,
    "gn:timezone":"Asia/Tehran",
    "iso:country":"IR",
    "name:fas_x_preferred":[
        "\u062f\u0647\u0648\u0644"
    ],
    "name:fas_x_variant":[
        "Doh\u016bl"
    ],
    "wof:name":"Dohul",
    "wof:placetype":"locality"
},
  "geometry": {"coordinates":[48.60038,31.92533],"type":"Point"}
}