{
  "type": "Feature",
  "properties": {
    "gn:admin1_code":"35.0",
    "gn:asciiname":"`Alamestan",
    "gn:country_code":"IR",
    "gn:dem":1602,
    "gn:feature_class":"P",
    "gn:feature_code":"PPL",
    "gn:name":"\u2018Alamest\u0101n",
    "gn:population":0,
    "gn:timezone":"Asia/Tehran",
    "iso:country":"IR",
    "name:fas_x_preferred":[
        "\u0627\u064e\u0644\u064e\u0645\u0650\u0633\u062a\u0627\u0646"
    ],
    "name:fas_x_variant":[
        "Alamest\u0101n",
        "\u2018Alamest\u0101n",
        "\u0639\u0644\u0645\u0633\u062a\u0627\u0646"
    ],
    "wof:name":"`Alamestan",
    "wof:placetype":"locality"
},
  "geometry": {"coordinates":[52.39522,36.16418],"type":"Point"}
}