{
  "type": "Feature",
  "properties": {
    "gn:admin1_code":"32",
    "gn:asciiname":"Derow",
    "gn:country_code":"IR",
    "gn:dem":1673,
    "gn:feature_class":"P",
    "gn:feature_code":"PPL",
    "gn:name":"Derow",
    "gn:population":0,
    "gn:timezone":"Asia/Tehran",
    "iso:country":"IR",
    "name:fas_x_preferred":[
        "\u062f\u0631\u0648"
    ],
    "name:msa_x_preferred":[
        "Derow"
    ],
    "name:mzn_x_preferred":[
        "\u062f\u0631\u0648"
    ],
    "name:und_x_variant":[
        "Dehru",
        "Derow"
    ],
    "wof:name":"Derow",
    "wof:placetype":"locality"
},
  "geometry": {"coordinates":[48.7019,37.41191],"type":"Point"}
}