{
  "type": "Feature",
  "properties": {
    "gn:admin1_code":"33",
    "gn:asciiname":"Beyglu",
    "gn:country_code":"IR",
    "gn:dem":1354,
    "gn:feature_class":"P",
    "gn:feature_code":"PPL",
    "gn:name":"Beygl\u016b",
    "gn:population":0,
    "gn:timezone":"Asia/Tehran",
    "iso:country":"IR",
    "name:ceb_x_preferred":[
        "Beygl\u016b"
    ],
    "name:fas_x_preferred":[
        "Beygl\u016b"
    ],
    "name:fas_x_variant":[
        "Baygl\u016b",
        "\u0628\u06cc\u06af\u0644\u0648"
    ],
    "name:msa_x_preferred":[
        "Beyglu"
    ],
    "name:swe_x_preferred":[
        "Beygl\u016b"
    ],
    "name:und_x_variant":[
        "Baygehl\u016b",
        "\u0628\u06cc\u06af\u0644\u0648"
    ],
    "wof:name":"Beyglu",
    "wof:placetype":"locality"
},
  "geometry": {"coordinates":[45.9766,37.9158],"type":"Point"}
}