{
  "type": "Feature",
  "properties": {
    "gn:admin1_code":"8",
    "gn:asciiname":"Jir Kulakbar",
    "gn:country_code":"IR",
    "gn:dem":158,
    "gn:feature_class":"P",
    "gn:feature_code":"PPL",
    "gn:name":"J\u012br K\u016bl\u0101kbar",
    "gn:population":0,
    "gn:timezone":"Asia/Tehran",
    "iso:country":"IR",
    "name:fas_x_preferred":[
        "Kal\u0101k\u0101var-e P\u0101\u2019\u012bn"
    ],
    "name:fas_x_variant":[
        "\u062c\u06cc\u0631 \u06a9\u0648\u0644\u0627\u06a9\u0628\u0631",
        "\u067e\u0627\u0626\u064a\u0646 \u06a9\u0644\u0627 \u06af\u0648\u0627\u0628\u0631"
    ],
    "name:und_x_variant":[
        "J\u012br K\u016bl\u0101kbar",
        "P\u0101\u2019\u012bn Kal\u0101 Gav\u0101bar"
    ],
    "wof:name":"Jir Kulakbar",
    "wof:placetype":"locality"
},
  "geometry": {"coordinates":[49.88636,37.10639000000001],"type":"Point"}
}