{
  "type": "Feature",
  "properties": {
    "gn:admin1_code":"16.0",
    "gn:asciiname":"Banavan",
    "gn:country_code":"IR",
    "gn:dem":1363,
    "gn:feature_class":"P",
    "gn:feature_code":"PPL",
    "gn:name":"B\u0101nav\u0101n",
    "gn:population":0,
    "gn:timezone":"Asia/Tehran",
    "iso:country":"IR",
    "name:fas_x_preferred":[
        "\u0628\u0627\u0646\u064e\u0648\u0627\u0646"
    ],
    "name:fas_x_variant":[
        "B\u0101nav\u0101n"
    ],
    "wof:name":"Banavan",
    "wof:placetype":"locality"
},
  "geometry": {"coordinates":[45.76667,35.86667],"type":"Point"}
}