{
  "type": "Feature",
  "properties": {
    "gn:admin1_code":"4.0",
    "gn:asciiname":"Mir Gol",
    "gn:country_code":"IR",
    "gn:dem":488,
    "gn:feature_class":"P",
    "gn:feature_code":"PPL",
    "gn:name":"M\u012br Gol",
    "gn:population":0,
    "gn:timezone":"Asia/Tehran",
    "iso:country":"IR",
    "name:fas_x_preferred":[
        "\u0645\u06cc\u0631 \u06af\u0644"
    ],
    "name:fas_x_variant":[
        "M\u012br Gol"
    ],
    "wof:name":"Mir Gol",
    "wof:placetype":"locality"
},
  "geometry": {"coordinates":[61.63366,30.89815],"type":"Point"}
}