{
  "type": "Feature",
  "properties": {
    "gn:admin1_code":"33",
    "gn:asciiname":"Qezeljeh",
    "gn:country_code":"IR",
    "gn:dem":1391,
    "gn:feature_class":"P",
    "gn:feature_code":"PPL",
    "gn:name":"Qezeljeh",
    "gn:population":0,
    "gn:timezone":"Asia/Tehran",
    "iso:country":"IR",
    "name:fas_x_preferred":[
        "\u0642\u0650\u0632\u0650\u0644\u062c\u0650\u0647"
    ],
    "name:fas_x_variant":[
        "\u0642\u0632\u0644\u062c\u0647",
        "\u0643\u064a\u0632\u064a\u0644\u062f\u0698\u064e"
    ],
    "name:mlg_x_preferred":[
        "Qezeljeh"
    ],
    "name:msa_x_preferred":[
        "Qezeljeh"
    ],
    "name:tur_x_preferred":[
        "K\u0131z\u0131lca"
    ],
    "name:und_x_variant":[
        "Kyzyldzha",
        "Qizilja",
        "Qizilia"
    ],
    "wof:name":"Qezeljeh",
    "wof:placetype":"locality"
},
  "geometry": {"coordinates":[45.1594,38.3211],"type":"Point"}
}