{
  "type": "Feature",
  "properties": {
    "gn:admin1_code":"13",
    "gn:asciiname":"Nowruzabad",
    "gn:country_code":"IR",
    "gn:dem":1303,
    "gn:feature_class":"P",
    "gn:feature_code":"PPL",
    "gn:name":"Nowr\u016bz\u0101b\u0101d",
    "gn:population":0,
    "gn:timezone":"Asia/Tehran",
    "iso:country":"IR",
    "name:fas_x_preferred":[
        "\u0646\u0648\u0631\u0648\u0632 \u0622\u0628\u0627\u062f"
    ],
    "name:fas_x_variant":[
        "Nowr\u016bz\u0101b\u0101d",
        "\u0646\u0648\u0631\u0648\u0632\u0622\u0628\u0627\u062f"
    ],
    "wof:name":"Nowruzabad",
    "wof:placetype":"locality"
},
  "geometry": {"coordinates":[47.0035,34.4533],"type":"Point"}
}