{
  "type": "Feature",
  "properties": {
    "gn:admin1_code":"15",
    "gn:asciiname":"Garm",
    "gn:country_code":"IR",
    "gn:dem":763,
    "gn:feature_class":"P",
    "gn:feature_code":"PPL",
    "gn:name":"Garm",
    "gn:population":0,
    "gn:timezone":"Asia/Tehran",
    "iso:country":"IR",
    "name:ceb_x_preferred":[
        "Garm"
    ],
    "name:fin_x_preferred":[
        "Garm"
    ],
    "name:fra_x_preferred":[
        "Garm"
    ],
    "name:ita_x_preferred":[
        "Garm"
    ],
    "name:lit_x_preferred":[
        "Garmas"
    ],
    "name:pol_x_preferred":[
        "Garm"
    ],
    "name:rus_x_preferred":[
        "\u0413\u0430\u0440\u043c"
    ],
    "name:swe_x_preferred":[
        "Garm"
    ],
    "wof:name":"Garm",
    "wof:placetype":"locality"
},
  "geometry": {"coordinates":[49.04139,32.89611],"type":"Point"}
}