{
  "type": "Feature",
  "properties": {
    "gn:admin1_code":"15",
    "gn:asciiname":"Do Ab",
    "gn:country_code":"IR",
    "gn:dem":302,
    "gn:feature_class":"P",
    "gn:feature_code":"PPL",
    "gn:name":"Do \u0100b",
    "gn:population":0,
    "gn:timezone":"Asia/Tehran",
    "iso:country":"IR",
    "name:ceb_x_preferred":[
        "Do Ab"
    ],
    "name:fas_x_preferred":[
        "Do \u0100b-e P\u0101\u2019\u012bn"
    ],
    "name:fas_x_variant":[
        "\u062f\u0648 \u0622\u0628 \u067e\u0627\u0626\u06cc\u0646",
        "Do \u0100b",
        "\u062f\u0648 \u0622\u0628",
        "\u062f\u0648\u0622\u0628"
    ],
    "name:swe_x_preferred":[
        "Do Ab"
    ],
    "wof:name":"Do Ab",
    "wof:placetype":"locality"
},
  "geometry": {"coordinates":[48.28364000000001,32.67786],"type":"Point"}
}