{
  "type": "Feature",
  "properties": {
    "gn:admin1_code":"4.0",
    "gn:asciiname":"Deh-e Rostam",
    "gn:country_code":"IR",
    "gn:dem":487,
    "gn:feature_class":"P",
    "gn:feature_code":"PPL",
    "gn:name":"Deh-e Rostam",
    "gn:population":0,
    "gn:timezone":"Asia/Tehran",
    "iso:country":"IR",
    "name:fas_x_preferred":[
        "\u062f\u0647 \u0631\u0633\u062a\u0645"
    ],
    "wof:name":"Deh-e Rostam",
    "wof:placetype":"locality"
},
  "geometry": {"coordinates":[61.6159,30.9005],"type":"Point"}
}