{
  "type": "Feature",
  "properties": {
    "gn:admin1_code":"13",
    "gn:asciiname":"Sarab-e Gilan",
    "gn:country_code":"IR",
    "gn:dem":823,
    "gn:feature_class":"P",
    "gn:feature_code":"PPL",
    "gn:name":"Sar\u0101b-e G\u012bl\u0101n",
    "gn:population":0,
    "gn:timezone":"Asia/Tehran",
    "iso:country":"IR",
    "name:fas_x_preferred":[
        "\u0633\u0631\u0627\u0628 \u06af\u06cc\u0644\u0627\u0646"
    ],
    "name:fas_x_variant":[
        "Sar\u0101b-e G\u012bl\u0101n"
    ],
    "wof:name":"Sarab-e Gilan",
    "wof:placetype":"locality"
},
  "geometry": {"coordinates":[45.9379,34.132],"type":"Point"}
}