{
  "type": "Feature",
  "properties": {
    "gn:admin1_code":"1",
    "gn:asciiname":"Bikash",
    "gn:country_code":"IR",
    "gn:dem":1460,
    "gn:feature_class":"P",
    "gn:feature_code":"PPL",
    "gn:name":"B\u012bkash",
    "gn:population":0,
    "gn:timezone":"Asia/Tehran",
    "iso:country":"IR",
    "name:ara_x_preferred":[
        "\u0628\u064a\u06a9\u0634"
    ],
    "name:ceb_x_preferred":[
        "B\u012bkash"
    ],
    "name:ckb_x_preferred":[
        "\u0628\u06ce\u06a9\u06d5\u0634"
    ],
    "name:fas_x_preferred":[
        "\u0628\u064a\u0643\u064e\u0634"
    ],
    "name:fas_x_variant":[
        "\u0628\u06cc\u06a9\u0634",
        "B\u012bkash"
    ],
    "name:swe_x_preferred":[
        "B\u012bkash"
    ],
    "wof:name":"Bikash",
    "wof:placetype":"locality"
},
  "geometry": {"coordinates":[45.6698,36.1528],"type":"Point"}
}