{
  "type": "Feature",
  "properties": {
    "gn:admin1_code":"13.0",
    "gn:asciiname":"Gazin",
    "gn:country_code":"IR",
    "gn:dem":286,
    "gn:feature_class":"P",
    "gn:feature_code":"PPL",
    "gn:name":"Gaz\u012bn",
    "gn:population":0,
    "gn:timezone":"Asia/Tehran",
    "iso:country":"IR",
    "name:fas_x_preferred":[
        "Gaz\u012bn"
    ],
    "wof:name":"Gazin",
    "wof:placetype":"locality"
},
  "geometry": {"coordinates":[45.65,33.85],"type":"Point"}
}