{
  "type": "Feature",
  "properties": {
    "gn:admin1_code":"15",
    "gn:asciiname":"Tampur Ruyeshid",
    "gn:country_code":"IR",
    "gn:dem":9,
    "gn:feature_class":"P",
    "gn:feature_code":"PPL",
    "gn:name":"Tamp\u016br R\u016byesh\u012bd",
    "gn:population":0,
    "gn:timezone":"Asia/Tehran",
    "iso:country":"IR",
    "name:fas_x_preferred":[
        "Dambar R\u016b\u2019sh\u012bd"
    ],
    "name:fas_x_variant":[
        "Tamb\u016bdor\u016bsheyd",
        "\u062f\u0645\u0628\u0631 \u0631\u0648\u0626\u0634\u06cc\u062f",
        "\u062a\u0645\u067e\u0648\u0631 \u0631\u0648\u06cc\u0634\u06cc\u062f",
        "\u062a\u0645\u067e\u0648\u0631\u0647 \u0631\u0648\u06cc\u0634\u06cc\u062f"
    ],
    "name:und_x_variant":[
        "\u062f\u0645\u0628\u0631 \u0631\u0648\u0626\u0634\u06cc\u062f",
        "Tamp\u016br R\u016byesh\u012bd",
        "Tamp\u016breh R\u016byesh\u012bd"
    ],
    "wof:name":"Tampur Ruyeshid",
    "wof:placetype":"locality"
},
  "geometry": {"coordinates":[48.83897,31.14],"type":"Point"}
}