{
  "type": "Feature",
  "properties": {
    "gn:admin1_code":"7",
    "gn:asciiname":"Tall Bargah",
    "gn:country_code":"IR",
    "gn:dem":1545,
    "gn:feature_class":"P",
    "gn:feature_code":"PPL",
    "gn:name":"Tall B\u0101rg\u0101h",
    "gn:population":0,
    "gn:timezone":"Asia/Tehran",
    "iso:country":"IR",
    "name:ara_x_preferred":[
        "\u062a\u0644 \u0628\u0627\u0631\u063a\u0627\u0647"
    ],
    "name:fas_x_preferred":[
        "\u062a\u0644 \u0628\u0627\u0631\u06af\u0627\u0647"
    ],
    "name:fas_x_variant":[
        "Tal B\u0101rg\u0101h",
        "Tall B\u0101rg\u0101h"
    ],
    "name:msa_x_preferred":[
        "Tall Bargah"
    ],
    "name:und_x_variant":[
        "N\u016bl Barg\u0101",
        "Tol B\u0101rg\u0101h",
        "Tulbarg\u0101h",
        "T\u016bl Bargeh"
    ],
    "wof:name":"Tall Bargah",
    "wof:placetype":"locality"
},
  "geometry": {"coordinates":[55.33858000000001,28.56884],"type":"Point"}
}