{
  "type": "Feature",
  "properties": {
    "gn:admin1_code":"7",
    "gn:asciiname":"Ghiasabad",
    "gn:country_code":"IR",
    "gn:dem":1639,
    "gn:feature_class":"P",
    "gn:feature_code":"PPL",
    "gn:name":"Gh\u012b\u0101s\u0304\u0101b\u0101d",
    "gn:population":0,
    "gn:timezone":"Asia/Tehran",
    "iso:country":"IR",
    "name:fas_x_preferred":[
        "\u063a\u06cc\u0627\u062b \u0622\u0628\u0627\u062f"
    ],
    "name:fas_x_variant":[
        "Gh\u012b\u0101s\u0304\u0101b\u0101d"
    ],
    "wof:name":"Ghiasabad",
    "wof:placetype":"locality"
},
  "geometry": {"coordinates":[53.03294,29.93184],"type":"Point"}
}