{
  "type": "Feature",
  "properties": {
    "gn:admin1_code":"8",
    "gn:asciiname":"Jirsar-e Vishka",
    "gn:country_code":"IR",
    "gn:dem":-14,
    "gn:feature_class":"P",
    "gn:feature_code":"PPL",
    "gn:name":"J\u012brsar-e V\u012bshk\u0101",
    "gn:population":0,
    "gn:timezone":"Asia/Tehran",
    "iso:country":"IR",
    "name:fas_x_preferred":[
        "J\u012brsar-e V\u012bshk\u0101h"
    ],
    "name:fas_x_variant":[
        "\u062c\u06cc\u0631 \u0633\u0631\u0648\u06cc\u0634\u06a9\u0627"
    ],
    "name:und_x_variant":[
        "J\u012brsar-e V\u012bshk\u0101"
    ],
    "wof:name":"Jirsar-e Vishka",
    "wof:placetype":"locality"
},
  "geometry": {"coordinates":[49.73769,37.36248],"type":"Point"}
}