{
  "type": "Feature",
  "properties": {
    "gn:admin1_code":"33",
    "gn:asciiname":"Qiz Qajeh",
    "gn:country_code":"IR",
    "gn:dem":421,
    "gn:feature_class":"P",
    "gn:feature_code":"PPL",
    "gn:name":"Q\u012bz Q\u0101jeh",
    "gn:population":0,
    "gn:timezone":"Asia/Tehran",
    "iso:country":"IR",
    "name:fas_x_preferred":[
        "\u0642\u06cc\u0632 \u0642\u0627\u062c\u0647"
    ],
    "name:fas_x_variant":[
        "Q\u012bz Q\u0101jeh"
    ],
    "wof:name":"Qiz Qajeh",
    "wof:placetype":"locality"
},
  "geometry": {"coordinates":[47.5284,38.9962],"type":"Point"}
}