{
  "type": "Feature",
  "properties": {
    "gn:admin1_code":"13",
    "gn:asciiname":"Afsharan",
    "gn:country_code":"IR",
    "gn:dem":1688,
    "gn:feature_class":"P",
    "gn:feature_code":"PPL",
    "gn:name":"Afsh\u0101r\u0101n",
    "gn:population":0,
    "gn:timezone":"Asia/Tehran",
    "iso:country":"IR",
    "name:fas_x_preferred":[
        "Afsh\u0101r\u0101n"
    ],
    "wof:name":"Afsharan",
    "wof:placetype":"locality"
},
  "geometry": {"coordinates":[47.86667,34.53333],"type":"Point"}
}