{
  "type": "Feature",
  "properties": {
    "gn:admin1_code":"34",
    "gn:asciiname":"Vismeh",
    "gn:country_code":"IR",
    "gn:dem":1675,
    "gn:feature_class":"P",
    "gn:feature_code":"PPL",
    "gn:name":"V\u012bsmeh",
    "gn:population":0,
    "gn:timezone":"Asia/Tehran",
    "iso:country":"IR",
    "name:ara_x_preferred":[
        "\u0648\u064a\u0633\u0645\u0629"
    ],
    "name:ceb_x_preferred":[
        "V\u012bsmeh"
    ],
    "name:fas_x_preferred":[
        "\u0648\u06cc\u0633\u0645\u0647"
    ],
    "name:fas_x_variant":[
        "V\u012bsmeh"
    ],
    "name:swe_x_preferred":[
        "V\u012bsmeh"
    ],
    "name:ukr_x_preferred":[
        "\u0412\u0456\u0441\u043c\u0435"
    ],
    "wof:name":"Vismeh",
    "wof:placetype":"locality"
},
  "geometry": {"coordinates":[49.74762,34.31673],"type":"Point"}
}