{
  "type": "Feature",
  "properties": {
    "gn:admin1_code":"44.0",
    "gn:asciiname":"Bagh-e Bonyad-e Mostaz`afan",
    "gn:country_code":"IR",
    "gn:dem":1300,
    "gn:feature_class":"P",
    "gn:feature_code":"PPLL",
    "gn:name":"B\u0101gh-e Bony\u0101d-e Mosta\u1e95\u2018af\u0101n",
    "gn:population":0,
    "gn:timezone":"Asia/Tehran",
    "iso:country":"IR",
    "name:fas_x_preferred":[
        "\u0628\u0627\u063a \u0628\u0646\u06cc\u0627\u062f \u0645\u0633\u062a\u0635\u0639\u0641\u0627\u0646"
    ],
    "name:fas_x_variant":[
        "B\u0101gh-e Bony\u0101d-e Mosta\u1e95\u2018af\u0101n"
    ],
    "wof:name":"Bagh-e Bonyad-e Mostaz`afan",
    "wof:placetype":"locality"
},
  "geometry": {"coordinates":[50.8219,35.8758],"type":"Point"}
}