{
  "type": "Feature",
  "properties": {
    "gn:admin1_code":"38",
    "gn:asciiname":"Marg",
    "gn:country_code":"IR",
    "gn:dem":1834,
    "gn:feature_class":"P",
    "gn:feature_code":"PPL",
    "gn:name":"Marg",
    "gn:population":0,
    "gn:timezone":"Asia/Tehran",
    "iso:country":"IR",
    "name:fas_x_preferred":[
        "\u0645\u0631\u06af"
    ],
    "name:fas_x_variant":[
        "\u0645\u0631\u062f \u0622\u0628\u0627\u062f"
    ],
    "name:und_x_variant":[
        "Mirg",
        "Marg",
        "Mard\u0101b\u0101d"
    ],
    "wof:name":"Marg",
    "wof:placetype":"locality"
},
  "geometry": {"coordinates":[50.2237,36.4113],"type":"Point"}
}