{
  "type": "Feature",
  "properties": {
    "gn:admin1_code":"29",
    "gn:asciiname":"Shahababad",
    "gn:country_code":"IR",
    "gn:dem":610,
    "gn:feature_class":"P",
    "gn:feature_code":"PPL",
    "gn:name":"Shah\u0101b\u0101b\u0101d",
    "gn:population":0,
    "gn:timezone":"Asia/Tehran",
    "iso:country":"IR",
    "name:fas_x_preferred":[
        "\u0634\u0647\u0627\u0628 \u0622\u0628\u0627\u062f"
    ],
    "name:fas_x_variant":[
        "Shah\u0101b\u0101b\u0101d",
        "Sh\u0101h\u0101b\u0101d",
        "Shahb\u0101b\u0101d"
    ],
    "name:und_x_variant":[
        "Shahb\u0101b\u0101d",
        "Sh\u0101h\u0101b\u0101d"
    ],
    "wof:name":"Shahababad",
    "wof:placetype":"locality"
},
  "geometry": {"coordinates":[59.03016,28.74746],"type":"Point"}
}