{
  "type": "Feature",
  "properties": {
    "gn:admin1_code":"22",
    "gn:asciiname":"Kalat",
    "gn:country_code":"IR",
    "gn:dem":37,
    "gn:feature_class":"P",
    "gn:feature_code":"PPL",
    "gn:name":"Kal\u0101t",
    "gn:population":0,
    "gn:timezone":"Asia/Tehran",
    "iso:country":"IR",
    "name:ara_x_preferred":[
        "\u0643\u0644\u0627\u062a"
    ],
    "name:fas_x_preferred":[
        "\u0643\u0644\u0627\u062a"
    ],
    "name:fas_x_variant":[
        "Kal\u0101t",
        "\u06a9\u0644\u0627\u062a"
    ],
    "name:msa_x_preferred":[
        "Kalat"
    ],
    "wof:name":"Kalat",
    "wof:placetype":"locality"
},
  "geometry": {"coordinates":[52.7318,27.4597],"type":"Point"}
}