{
  "type": "Feature",
  "properties": {
    "gn:admin1_code":"33",
    "gn:asciiname":"Qareh Kowshan",
    "gn:country_code":"IR",
    "gn:dem":2044,
    "gn:feature_class":"P",
    "gn:feature_code":"PPL",
    "gn:name":"Qareh Kowshan",
    "gn:population":0,
    "gn:timezone":"Asia/Tehran",
    "iso:country":"IR",
    "name:fas_x_preferred":[
        "\u0642\u0631\u0647 \u06a9\u0648\u0634\u0646"
    ],
    "name:fas_x_variant":[
        "Qarah K\u016bshan"
    ],
    "wof:name":"Qareh Kowshan",
    "wof:placetype":"locality"
},
  "geometry": {"coordinates":[46.7332,37.7156],"type":"Point"}
}