{
  "type": "Feature",
  "properties": {
    "gn:admin1_code":"35",
    "gn:asciiname":"Pa'in Ganj Afruz",
    "gn:country_code":"IR",
    "gn:dem":23,
    "gn:feature_class":"P",
    "gn:feature_code":"PPL",
    "gn:name":"P\u0101\u2019\u012bn Ganj Afr\u016bz",
    "gn:population":0,
    "gn:timezone":"Asia/Tehran",
    "iso:country":"IR",
    "name:fas_x_preferred":[
        "\u067e\u0627\u0626\u064a\u0646 \u06af\u0646\u062c \u0627\u0641\u0631\u0648\u0632"
    ],
    "name:fas_x_variant":[
        "P\u0101\u2019\u012bn Ganj Afr\u016bz"
    ],
    "name:und_x_variant":[
        "\u067e\u0627\u0626\u064a\u0646 \u06af\u064e\u0646\u062c \u0627\u064e\u0641\u0631\u0648\u0632"
    ],
    "wof:name":"Pa'in Ganj Afruz",
    "wof:placetype":"locality"
},
  "geometry": {"coordinates":[52.70502,36.45412],"type":"Point"}
}