{
  "type": "Feature",
  "properties": {
    "gn:admin1_code":"43",
    "gn:asciiname":"Khabushan",
    "gn:country_code":"IR",
    "gn:dem":1279,
    "gn:feature_class":"P",
    "gn:feature_code":"PPL",
    "gn:name":"Khab\u016bsh\u0101n",
    "gn:population":0,
    "gn:timezone":"Asia/Tehran",
    "iso:country":"IR",
    "name:fas_x_preferred":[
        "Khab\u016bsh\u0101n"
    ],
    "name:fas_x_variant":[
        "\u062e\u0628\u0648\u0634\u0627\u0646"
    ],
    "wof:name":"Khabushan",
    "wof:placetype":"locality"
},
  "geometry": {"coordinates":[58.29029,37.31297],"type":"Point"}
}