{
  "type": "Feature",
  "properties": {
    "gn:admin1_code":"42.0",
    "gn:asciiname":"Tajabad",
    "gn:country_code":"IR",
    "gn:dem":873,
    "gn:feature_class":"P",
    "gn:feature_code":"PPL",
    "gn:name":"T\u0101j\u0101b\u0101d",
    "gn:population":0,
    "gn:timezone":"Asia/Tehran",
    "iso:country":"IR",
    "name:fas_x_preferred":[
        "T\u0101j\u0101b\u0101d"
    ],
    "name:fas_x_variant":[
        "\u062a\u0627\u062c \u0622\u0628\u0627\u062f",
        "\u062a\u0627\u062c\u200c\u0622\u0628\u0627\u062f"
    ],
    "name:sco_x_preferred":[
        "Tajabad"
    ],
    "wof:name":"Tajabad",
    "wof:placetype":"locality"
},
  "geometry": {"coordinates":[57.30455,36.17558],"type":"Point"}
}