{
  "type": "Feature",
  "properties": {
    "gn:admin1_code":"43.0",
    "gn:asciiname":"Alast-e Pa'in",
    "gn:country_code":"IR",
    "gn:dem":1199,
    "gn:feature_class":"P",
    "gn:feature_code":"PPL",
    "gn:name":"Alast-e P\u0101\u2019\u012bn",
    "gn:population":0,
    "gn:timezone":"Asia/Tehran",
    "iso:country":"IR",
    "name:fas_x_preferred":[
        "Alast P\u0101\u2019\u012bn"
    ],
    "name:fas_x_variant":[
        "Alast-e P\u0101\u2019\u012bn",
        "\u0627\u0644\u0633\u062a \u067e\u0627\u0626\u064a\u0646",
        "\u0627\u0644\u0633\u062a \u0633\u0641\u0644\u06cc"
    ],
    "name:und_x_variant":[
        "Alast-e Sofl\u00e1"
    ],
    "wof:name":"Alast-e Pa'in",
    "wof:placetype":"locality"
},
  "geometry": {"coordinates":[57.85023,36.74448],"type":"Point"}
}