{
  "type": "Feature",
  "properties": {
    "gn:admin1_code":"37",
    "gn:asciiname":"Ay Tamer",
    "gn:country_code":"IR",
    "gn:dem":187,
    "gn:feature_class":"P",
    "gn:feature_code":"PPL",
    "gn:name":"\u0100y Tamer",
    "gn:population":0,
    "gn:timezone":"Asia/Tehran",
    "iso:country":"IR",
    "name:ara_x_preferred":[
        "\u0622\u064a\u062a\u0645\u0631"
    ],
    "name:fas_x_preferred":[
        "\u0627\u06cc \u062a\u0645\u0631"
    ],
    "name:fas_x_variant":[
        "\u0622\u06cc \u062a\u0645\u0631",
        "\u0622\u06cc\u200c\u062a\u0645\u0631"
    ],
    "name:msa_x_preferred":[
        "Ay Tamer"
    ],
    "name:und_x_variant":[
        "\u0627\u06cc \u062a\u0645\u0631",
        "Ay Tamer",
        "\u0100y Tamer"
    ],
    "wof:name":"Ay Tamer",
    "wof:placetype":"locality"
},
  "geometry": {"coordinates":[55.47111,37.81417],"type":"Point"}
}