{
  "type": "Feature",
  "properties": {
    "gn:admin1_code":"13",
    "gn:asciiname":"Shahrak-e Shahid Bahonar",
    "gn:country_code":"IR",
    "gn:dem":1566,
    "gn:feature_class":"P",
    "gn:feature_code":"PPL",
    "gn:name":"Shahrak-e Shah\u012bd B\u0101honar",
    "gn:population":0,
    "gn:timezone":"Asia/Tehran",
    "iso:country":"IR",
    "name:fas_x_preferred":[
        "\u0634\u0647\u0631\u06a9 \u0634\u0647\u06cc\u062f \u0628\u0627\u0647\u0646\u0631"
    ],
    "name:fas_x_variant":[
        "Shahrak-e Shah\u012bd B\u0101honar"
    ],
    "wof:name":"Shahrak-e Shahid Bahonar",
    "wof:placetype":"locality"
},
  "geometry": {"coordinates":[47.60100000000001,34.2734],"type":"Point"}
}