{
  "type": "Feature",
  "properties": {
    "gn:admin1_code":"40",
    "gn:asciiname":"Bazok",
    "gn:country_code":"IR",
    "gn:dem":2501,
    "gn:feature_class":"P",
    "gn:feature_code":"PPL",
    "gn:name":"B\u0101zok",
    "gn:population":0,
    "gn:timezone":"Asia/Tehran",
    "iso:country":"IR",
    "name:fas_x_preferred":[
        "\u0628\u0627\u0632\u06a9"
    ],
    "name:fas_x_variant":[
        "B\u0101zok"
    ],
    "wof:name":"Bazok",
    "wof:placetype":"locality"
},
  "geometry": {"coordinates":[54.06934,31.50303],"type":"Point"}
}