{
  "type": "Feature",
  "properties": {
    "gn:admin1_code":"29",
    "gn:asciiname":"Kabir",
    "gn:country_code":"IR",
    "gn:dem":2548,
    "gn:feature_class":"P",
    "gn:feature_code":"PPL",
    "gn:name":"Kab\u012br",
    "gn:population":0,
    "gn:timezone":"Asia/Tehran",
    "iso:country":"IR",
    "name:fas_x_preferred":[
        "\u06a9\u0628\u06cc\u0631"
    ],
    "name:fas_x_variant":[
        "Kab\u012br"
    ],
    "name:und_x_variant":[
        "Ka\u2019\u012br"
    ],
    "wof:name":"Kabir",
    "wof:placetype":"locality"
},
  "geometry": {"coordinates":[56.8926,29.3416],"type":"Point"}
}