{
  "type": "Feature",
  "properties": {
    "gn:admin1_code":"15.0",
    "gn:asciiname":"Budan",
    "gn:country_code":"IR",
    "gn:dem":373,
    "gn:feature_class":"P",
    "gn:feature_code":"PPLL",
    "gn:name":"B\u016bd\u0101n",
    "gn:population":0,
    "gn:timezone":"Asia/Tehran",
    "iso:country":"IR",
    "name:fas_x_preferred":[
        "\u0628\u0648\u062f\u0648\u0646"
    ],
    "name:fas_x_variant":[
        "B\u016bd\u016bn",
        "\u0628\u0648\u062f\u0627\u0646"
    ],
    "name:und_x_variant":[
        "B\u016bd\u0101n"
    ],
    "wof:name":"Budan",
    "wof:placetype":"locality"
},
  "geometry": {"coordinates":[48.77283,32.39168],"type":"Point"}
}