{
  "type": "Feature",
  "properties": {
    "gn:admin1_code":"42",
    "gn:asciiname":"Abkuh",
    "gn:country_code":"IR",
    "gn:dem":1769,
    "gn:feature_class":"P",
    "gn:feature_code":"PPL",
    "gn:name":"\u0100bk\u016bh",
    "gn:population":0,
    "gn:timezone":"Asia/Tehran",
    "iso:country":"IR",
    "name:fas_x_preferred":[
        "\u0622\u0628\u06a9\u0648\u0647"
    ],
    "name:fas_x_variant":[
        "\u0100bk\u016bh"
    ],
    "wof:name":"Abkuh",
    "wof:placetype":"locality"
},
  "geometry": {"coordinates":[59.62237,35.7639],"type":"Point"}
}