{
  "type": "Feature",
  "properties": {
    "gn:admin1_code":"1",
    "gn:asciiname":"Seyyed Taj od Din",
    "gn:country_code":"IR",
    "gn:dem":1398,
    "gn:feature_class":"P",
    "gn:feature_code":"PPL",
    "gn:name":"Seyyed T\u0101j od D\u012bn",
    "gn:population":0,
    "gn:timezone":"Asia/Tehran",
    "iso:country":"IR",
    "name:fas_x_preferred":[
        "\u0633\u06cc\u0651\u062f \u062a\u0627\u062c \u0627\u0644\u062f\u0651\u06cc\u0646"
    ],
    "name:fas_x_variant":[
        "Seyyed T\u0101j od D\u012bn"
    ],
    "name:und_x_variant":[
        "Saiyid H\u0101ji",
        "Seyyed \u1e28\u0101j\u012bn",
        "Seyyed \u1e28\u0101j\u012bm",
        "Seid-Khadzhi",
        "Seyyed \u1e28\u0101j\u012b",
        "Seyyed \u1e28\u0101jj\u012bn"
    ],
    "wof:name":"Seyyed Taj od Din",
    "wof:placetype":"locality"
},
  "geometry": {"coordinates":[45.0382,38.3614],"type":"Point"}
}