{
  "type": "Feature",
  "properties": {
    "gn:admin1_code":"1.0",
    "gn:asciiname":"Hurazeh",
    "gn:country_code":"IR",
    "gn:dem":1591,
    "gn:feature_class":"P",
    "gn:feature_code":"PPL",
    "gn:name":"H\u016br\u0101zeh",
    "gn:population":0,
    "gn:timezone":"Asia/Tehran",
    "iso:country":"IR",
    "name:ara_x_preferred":[
        "\u0647\u0648\u0631\u0627\u0632\u0629"
    ],
    "name:ceb_x_preferred":[
        "H\u016br\u0101zeh"
    ],
    "name:ckb_x_preferred":[
        "\u06be\u06d5\u0648\u0631\u0627\u0632\u06d5"
    ],
    "name:fas_x_preferred":[
        "\u0647\u0648\u0631\u0627\u0632\u0647"
    ],
    "name:fas_x_variant":[
        "H\u016br\u0101zeh"
    ],
    "name:swe_x_preferred":[
        "H\u016br\u0101zeh"
    ],
    "wof:name":"Hurazeh",
    "wof:placetype":"locality"
},
  "geometry": {"coordinates":[45.6552,36.1528],"type":"Point"}
}