{
  "type": "Feature",
  "properties": {
    "gn:admin1_code":"5",
    "gn:asciiname":"Silarestan",
    "gn:country_code":"IR",
    "gn:dem":1451,
    "gn:feature_class":"P",
    "gn:feature_code":"PPL",
    "gn:name":"S\u012bl\u0101rest\u0101n",
    "gn:population":0,
    "gn:timezone":"Asia/Tehran",
    "iso:country":"IR",
    "name:ara_x_preferred":[
        "\u0633\u064a\u0644\u0627\u0631\u0633\u062a\u0627\u0646"
    ],
    "name:fas_x_preferred":[
        "\u0633\u064a\u0644\u0627\u0631\u0650\u0633\u062a\u0627\u0646\u0650 \u0639\u064f\u0644\u064a\u0627"
    ],
    "name:fas_x_variant":[
        "\u0633\u064a\u0644\u0627\u0631\u0650\u0633\u062a\u0627\u0646\u0650 \u0628\u0627\u0644\u0627",
        "S\u012bl\u0101rest\u0101n",
        "S\u012bl\u0101rest\u0101n-e \u2018Oly\u0101",
        "\u0633\u06cc\u0644\u0627\u0631\u0633\u062a\u0627\u0646"
    ],
    "name:und_x_variant":[
        "S\u012bl\u0101rest\u0101n-e B\u0101l\u0101",
        "\u0633\u06cc\u0644\u0627\u0631\u0633\u062a\u0627\u0646"
    ],
    "wof:name":"Silarestan",
    "wof:placetype":"locality"
},
  "geometry": {"coordinates":[50.73596,30.94058],"type":"Point"}
}