{
  "type": "Feature",
  "properties": {
    "gn:admin1_code":"4",
    "gn:asciiname":"Gazdaneh",
    "gn:country_code":"IR",
    "gn:dem":1172,
    "gn:feature_class":"P",
    "gn:feature_code":"PPL",
    "gn:name":"Gazd\u0101neh",
    "gn:population":0,
    "gn:timezone":"Asia/Tehran",
    "iso:country":"IR",
    "name:fas_x_preferred":[
        "\u06af\u0632\u062f\u0627\u0646\u0647"
    ],
    "name:fas_x_variant":[
        "Gazd\u0101neh"
    ],
    "wof:name":"Gazdaneh",
    "wof:placetype":"locality"
},
  "geometry": {"coordinates":[61.49376,28.49469],"type":"Point"}
}