{
  "type": "Feature",
  "properties": {
    "gn:admin1_code":"7",
    "gn:asciiname":"Zeyn od Dini",
    "gn:country_code":"IR",
    "gn:dem":378,
    "gn:feature_class":"P",
    "gn:feature_code":"PPL",
    "gn:name":"Zeyn od D\u012bn\u012b",
    "gn:population":0,
    "gn:timezone":"Asia/Tehran",
    "iso:country":"IR",
    "name:fas_x_preferred":[
        "\u0632\u064a\u0646 \u0627\u0644\u062f\u064a\u0646\u06cc"
    ],
    "name:fas_x_variant":[
        "Zeyn ed D\u012bn\u012b",
        "Zeyn od D\u012bn\u012b"
    ],
    "name:und_x_variant":[
        "Zeinoddin",
        "Zainadoni",
        "Zand\u016bn\u012b",
        "Zeyn od D\u012bn",
        "Zeyn Den\u012b",
        "Zen D\u016bn\u012b"
    ],
    "wof:name":"Zeyn od Dini",
    "wof:placetype":"locality"
},
  "geometry": {"coordinates":[53.8694,27.1394],"type":"Point"}
}