{
  "type": "Feature",
  "properties": {
    "gn:admin1_code":"29",
    "gn:asciiname":"Chah-e Mirza",
    "gn:country_code":"IR",
    "gn:dem":403,
    "gn:feature_class":"P",
    "gn:feature_code":"PPL",
    "gn:name":"Ch\u0101h-e M\u012brz\u0101",
    "gn:population":0,
    "gn:timezone":"Asia/Tehran",
    "iso:country":"IR",
    "name:fas_x_preferred":[
        "\u0686\u0627\u0647 \u0645\u06cc\u0631\u0632\u0627"
    ],
    "name:fas_x_variant":[
        "Ch\u0101h-e M\u012brz\u0101"
    ],
    "wof:name":"Chah-e Mirza",
    "wof:placetype":"locality"
},
  "geometry": {"coordinates":[58.06792,27.33294],"type":"Point"}
}