{
  "type": "Feature",
  "properties": {
    "gn:admin1_code":"8",
    "gn:asciiname":"Bialva",
    "gn:country_code":"IR",
    "gn:dem":25,
    "gn:feature_class":"P",
    "gn:feature_code":"PPL",
    "gn:name":"B\u012b\u0101lv\u0101",
    "gn:population":0,
    "gn:timezone":"Asia/Tehran",
    "iso:country":"IR",
    "name:ceb_x_preferred":[
        "B\u012b\u0101lv\u0101'"
    ],
    "name:fas_x_preferred":[
        "\u0628\u06cc\u0627\u0644\u0648\u0627\u0621"
    ],
    "name:fas_x_variant":[
        "B\u012b\u0101lv\u0101",
        "B\u012b\u0101lv\u0101\u2019",
        "\u0628\u06cc\u0627\u0644\u0648\u0627"
    ],
    "name:msa_x_preferred":[
        "Bialva"
    ],
    "name:swe_x_preferred":[
        "B\u012b\u0101lv\u0101'"
    ],
    "name:ukr_x_preferred":[
        "\u0411\u0456\u044f\u043b\u044c\u0432\u0430"
    ],
    "wof:name":"Bialva",
    "wof:placetype":"locality"
},
  "geometry": {"coordinates":[49.48819,37.16682],"type":"Point"}
}