{
  "type": "Feature",
  "properties": {
    "iso:country":"IR",
    "name:fas_x_preferred":[
        "\u0641\u0631\u06cc\u0645\u0627\u0646"
    ],
    "name:fas_x_variant":[
        "Far\u012bm\u0101n"
    ],
    "name:unk_x_variant":[
        "Far\u012bm\u016bn"
    ],
    "qs:gn_country":"IR",
    "qs:gn_fcode":"PPL",
    "qs:gn_pop":0,
    "qs:name":"Fariman",
    "qs:name_adm0":"Iran",
    "qs:name_adm1":"North Khorasan",
    "qs:photos":2,
    "qs:photos_1k":1,
    "qs:photos_9k":1,
    "qs:photos_9r":1,
    "qs:photos_all":2,
    "qs:photos_sr":1,
    "qs:placetype":"Town",
    "qs:pop_sr":"6",
    "qs:woe_adm0":23424851,
    "wof:name":"Fariman",
    "wof:placetype":"locality"
},
  "geometry": {"coordinates":[59.85006,35.70685],"type":"Point"}
}