{
  "type": "Feature",
  "properties": {
    "iso:country":"IR",
    "name:ara_x_preferred":[
        "\u0645\u0642\u0627\u0637\u0639\u0629 \u0641\u0631\u064a\u0645\u0627\u0646"
    ],
    "name:arz_x_preferred":[
        "\u0634\u0647\u0631\u0633\u062a\u0627\u0646 \u0641\u0631\u064a\u0645\u0627\u0646"
    ],
    "name:aze_x_preferred":[
        "F\u0259riman \u015f\u0259hristan\u0131"
    ],
    "name:ceb_x_preferred":[
        "Shahrest\u0101n-e Far\u012bm\u0101n"
    ],
    "name:cym_x_preferred":[
        "Sir Fariman"
    ],
    "name:deu_x_preferred":[
        "Fariman"
    ],
    "name:eng_x_preferred":[
        "Fariman County"
    ],
    "name:fas_x_preferred":[
        "\u0641\u0631\u06cc\u0645\u0627\u0646"
    ],
    "name:fas_x_variant":[
        "Far\u012bm\u0101n",
        "\u0634\u0647\u0631\u0633\u062a\u0627\u0646 \u0641\u0631\u06cc\u0645\u0627\u0646"
    ],
    "name:gle_x_preferred":[
        "Contae Fariman"
    ],
    "name:glk_x_preferred":[
        "\u0634\u0647\u0631\u0633\u062a\u0627\u0646 \u0641\u0631\u06cc\u0645\u0627\u0646"
    ],
    "name:hun_x_preferred":[
        "Farim\u00e1n megye"
    ],
    "name:jpn_x_preferred":[
        "\u30d5\u30a1\u30ea\u30fc\u30de\u30fc\u30f3\u90e1"
    ],
    "name:kur_x_preferred":[
        "Fer\u00eeman"
    ],
    "name:nan_x_preferred":[
        "Fariman K\u016bn"
    ],
    "name:nld_x_preferred":[
        "Fariman County"
    ],
    "name:nno_x_preferred":[
        "Fariman fylke"
    ],
    "name:pnb_x_preferred":[
        "\u0634\u06c1\u0631\u0633\u062a\u0627\u0646 \u0641\u0631\u06cc\u0645\u0627\u0646"
    ],
    "name:pus_x_preferred":[
        "\u0641\u0631\u064a\u0645\u0627\u0646 \u0648\u0644\u0633\u0648\u0627\u0644\u064a"
    ],
    "name:swe_x_preferred":[
        "Shahrest\u0101n-e Far\u012bm\u0101n"
    ],
    "name:tgk_x_preferred":[
        "\u0428\u0430\u04b3\u0440\u0438\u0441\u0442\u043e\u043d\u0438 \u0424\u0430\u0440\u0435\u043c\u043e\u043d"
    ],
    "name:tur_x_preferred":[
        "Feriman \u015fehristan\u0131"
    ],
    "name:und_x_variant":[
        "Far\u012bm\u016bn"
    ],
    "name:urd_x_preferred":[
        "\u0634\u06c1\u0631\u0633\u062a\u0627\u0646 \u0641\u0631\u06cc\u0645\u0627\u0646"
    ],
    "qs:gn_country":"IR",
    "qs:gn_fcode":"PPL",
    "qs:gn_pop":0,
    "qs:name":"Fariman",
    "qs:name_adm0":"Iran",
    "qs:name_adm1":"North Khorasan",
    "qs:photos":2,
    "qs:photos_1k":1,
    "qs:photos_9k":1,
    "qs:photos_9r":1,
    "qs:photos_all":2,
    "qs:photos_sr":1,
    "qs:placetype":"Town",
    "qs:pop_sr":"6",
    "qs:woe_adm0":23424851,
    "wof:name":"Fariman",
    "wof:placetype":"locality"
},
  "geometry": {"coordinates":[59.85006,35.70685],"type":"Point"}
}