{
  "type": "Feature",
  "properties": {
    "gn:admin1_code":"26",
    "gn:asciiname":"Valiabad",
    "gn:country_code":"IR",
    "gn:dem":938,
    "gn:feature_class":"P",
    "gn:feature_code":"PPL",
    "gn:name":"Val\u012b\u0101b\u0101d",
    "gn:population":0,
    "gn:timezone":"Asia/Tehran",
    "iso:country":"IR",
    "name:fas_x_preferred":[
        "Val\u012b\u0101b\u0101d"
    ],
    "name:fas_x_variant":[
        "\u0648\u0644\u06cc \u0622\u0628\u0627\u062f"
    ],
    "name:und_x_variant":[
        "\u0648\u0644\u06cc \u0622\u0628\u0627\u062f"
    ],
    "wof:name":"Valiabad",
    "wof:placetype":"locality"
},
  "geometry": {"coordinates":[51.5566,35.4229],"type":"Point"}
}