{
  "type": "Feature",
  "properties": {
    "gn:admin1_code":"28",
    "gn:asciiname":"Barownaq",
    "gn:country_code":"IR",
    "gn:dem":1245,
    "gn:feature_class":"P",
    "gn:feature_code":"PPL",
    "gn:name":"B\u0101rownaq",
    "gn:population":0,
    "gn:timezone":"Asia/Tehran",
    "iso:country":"IR",
    "name:fas_x_preferred":[
        "\u0628\u0627\u0631\u0648\u0646\u0642"
    ],
    "name:fas_x_variant":[
        "B\u0101rownaq"
    ],
    "wof:name":"Barownaq",
    "wof:placetype":"locality"
},
  "geometry": {"coordinates":[51.2397,33.991],"type":"Point"}
}