{
  "type": "Feature",
  "properties": {
    "gn:admin1_code":"34",
    "gn:asciiname":"Palangabad",
    "gn:country_code":"IR",
    "gn:dem":1665,
    "gn:feature_class":"P",
    "gn:feature_code":"PPL",
    "gn:name":"Palang\u0101b\u0101d",
    "gn:population":0,
    "gn:timezone":"Asia/Tehran",
    "iso:country":"IR",
    "name:fas_x_preferred":[
        "\u067e\u0644\u0646\u06af \u0622\u0628\u0627\u062f"
    ],
    "name:fas_x_variant":[
        "Palang\u0101b\u0101d"
    ],
    "wof:name":"Palangabad",
    "wof:placetype":"locality"
},
  "geometry": {"coordinates":[49.96003,35.00463],"type":"Point"}
}