{
  "type": "Feature",
  "properties": {
    "gn:admin1_code":"29",
    "gn:asciiname":"Kohan Mahalleh",
    "gn:country_code":"IR",
    "gn:dem":863,
    "gn:feature_class":"P",
    "gn:feature_code":"PPL",
    "gn:name":"Kohan Ma\u1e29alleh",
    "gn:population":0,
    "gn:timezone":"Asia/Tehran",
    "iso:country":"IR",
    "name:fas_x_preferred":[
        "Kahn-e Ma\u1e29alleh-ye P\u0101\u2019\u012bn"
    ],
    "name:fas_x_variant":[
        "\u06a9\u0647\u0646 \u0645\u062d\u0644\u0647",
        "\u06a9\u0647\u0646 \u0645\u062d\u0644\u0647 \u0628\u0627\u0644\u0627",
        "\u06a9\u0647\u0646 \u0645\u062d\u0644\u0647 \u067e\u0627\u06cc\u06cc\u0646",
        "\u06a9\u0647\u0646\u200c\u0645\u062d\u0644\u0647 \u0628\u0627\u0644\u0627"
    ],
    "name:und_x_variant":[
        "Kohan Ma\u1e29alleh",
        "Kahn Mahalleh",
        "Kohan Ma\u1e29alleh-ye B\u0101l\u0101",
        "Kohan Ma\u1e29alleh-ye P\u0101\u2019\u012bn",
        "Kahn Ma\u1e29al",
        "Kahn-e Ma\u1e29alleh-ye B\u0101l\u0101",
        "Kahn-e Ma\u1e29alleh"
    ],
    "wof:name":"Kohan Mahalleh",
    "wof:placetype":"locality"
},
  "geometry": {"coordinates":[58.51434,28.87856],"type":"Point"}
}