{
  "type": "Feature",
  "properties": {
    "gn:admin1_code":"8",
    "gn:asciiname":"`Eliyeh Sara",
    "gn:country_code":"IR",
    "gn:dem":-17,
    "gn:feature_class":"P",
    "gn:feature_code":"PPL",
    "gn:name":"\u2018El\u012byeh Sar\u0101",
    "gn:population":0,
    "gn:timezone":"Asia/Tehran",
    "iso:country":"IR",
    "name:fas_x_preferred":[
        "\u2018Al\u012b Sar\u0101"
    ],
    "name:fas_x_variant":[
        "\u0639\u0644\u06cc\u0647 \u0633\u0631\u0627",
        "\u0639\u0644\u06cc \u0633\u0631\u0627"
    ],
    "name:und_x_variant":[
        "\u2018El\u012byeh Sar\u0101"
    ],
    "wof:name":"`Eliyeh Sara",
    "wof:placetype":"locality"
},
  "geometry": {"coordinates":[49.02279,37.69651],"type":"Point"}
}