{
  "type": "Feature",
  "properties": {
    "gn:admin1_code":"4.0",
    "gn:asciiname":"Kahn-e Rasul Bakhsh",
    "gn:country_code":"IR",
    "gn:dem":1262,
    "gn:feature_class":"P",
    "gn:feature_code":"PPL",
    "gn:name":"Kahn-e Ras\u016bl Bakhsh",
    "gn:population":0,
    "gn:timezone":"Asia/Tehran",
    "iso:country":"IR",
    "name:fas_x_preferred":[
        "\u06a9\u0647\u0646 \u0631\u0633\u0648\u0644 \u0628\u062e\u0634"
    ],
    "name:fas_x_variant":[
        "Qan\u0101t-e Ras\u016bl Bakhsh",
        "Kahn-e Ras\u016bl Bakhsh"
    ],
    "wof:name":"Kahn-e Rasul Bakhsh",
    "wof:placetype":"locality"
},
  "geometry": {"coordinates":[61.7049,27.1418],"type":"Point"}
}