{
  "type": "Feature",
  "properties": {
    "gn:admin1_code":"38.0",
    "gn:asciiname":"Mazra`eh-ye Narmeh Lat",
    "gn:country_code":"IR",
    "gn:dem":2079,
    "gn:feature_class":"P",
    "gn:feature_code":"PPL",
    "gn:name":"Mazra\u2018eh-ye Narmeh L\u0101t",
    "gn:population":0,
    "gn:timezone":"Asia/Tehran",
    "iso:country":"IR",
    "name:fas_x_preferred":[
        "Normal\u0101t"
    ],
    "name:fas_x_variant":[
        "\u0646\u0631\u0645\u0644\u0627\u062a",
        "\u0645\u0632\u0631\u0639\u0647 \u0646\u0631\u0645\u0647 \u0644\u0627\u062a",
        "\u0646\u0631\u0645\u06cc\u0644\u0627\u062a"
    ],
    "name:und_x_variant":[
        "\u0646\u0631\u0645\u0644\u0627\u062a",
        "Mazra\u2018eh-ye Narmeh L\u0101t",
        "Narm\u012bl\u0101t"
    ],
    "wof:name":"Mazra`eh-ye Narmeh Lat",
    "wof:placetype":"locality"
},
  "geometry": {"coordinates":[50.7776,36.36258],"type":"Point"}
}