{
  "type": "Feature",
  "properties": {
    "gn:admin1_code":"35.0",
    "gn:asciiname":"Yan Dasht-e `Olya",
    "gn:country_code":"IR",
    "gn:dem":579,
    "gn:feature_class":"P",
    "gn:feature_code":"PPL",
    "gn:name":"Y\u0101n Dasht-e \u2018Oly\u0101",
    "gn:population":0,
    "gn:timezone":"Asia/Tehran",
    "iso:country":"IR",
    "name:fas_x_preferred":[
        "Y\u0101n Dasht"
    ],
    "name:fas_x_variant":[
        "\u06cc\u0627\u0646 \u062f\u0634\u062a",
        "\u06cc\u0627\u0646 \u062f\u0634\u062a \u0639\u0644\u064a\u0627",
        "\u06cc\u0627\u0646 \u062f\u0634\u062a \u0628\u0627\u0644\u0627",
        "\u06cc\u0627\u0646\u062f\u0634\u062a \u0628\u0627\u0644\u0627"
    ],
    "name:und_x_variant":[
        "\u06cc\u0627\u0646 \u062f\u0634\u062a",
        "Y\u0101n Dasht-e \u2018Oly\u0101",
        "Y\u0101n Dasht-e B\u0101l\u0101"
    ],
    "name:urd_x_preferred":[
        "\u06cc\u0646 \u062f\u0634\u062a-\u0628\u0644\u0627"
    ],
    "wof:name":"Yan Dasht-e `Olya",
    "wof:placetype":"locality"
},
  "geometry": {"coordinates":[50.83947,36.63954],"type":"Point"}
}