{
  "type": "Feature",
  "properties": {
    "gn:admin1_code":"4.0",
    "gn:asciiname":"Nur Khoda",
    "gn:country_code":"IR",
    "gn:dem":482,
    "gn:feature_class":"P",
    "gn:feature_code":"PPL",
    "gn:name":"N\u016br Khod\u0101",
    "gn:population":0,
    "gn:timezone":"Asia/Tehran",
    "iso:country":"IR",
    "name:fas_x_preferred":[
        "\u0646\u0648\u0631 \u062e\u062f\u0627"
    ],
    "name:fas_x_variant":[
        "N\u016br Khod\u0101"
    ],
    "wof:name":"Nur Khoda",
    "wof:placetype":"locality"
},
  "geometry": {"coordinates":[61.58394000000001,31.13341],"type":"Point"}
}