{
  "type": "Feature",
  "properties": {
    "gn:admin1_code":"33",
    "gn:asciiname":"Chelanab",
    "gn:country_code":"IR",
    "gn:dem":2009,
    "gn:feature_class":"P",
    "gn:feature_code":"PPL",
    "gn:name":"Chel\u0101n\u0101b",
    "gn:population":0,
    "gn:timezone":"Asia/Tehran",
    "iso:country":"IR",
    "name:ceb_x_preferred":[
        "Chel\u0101n\u0101b"
    ],
    "name:fas_x_preferred":[
        "\u0686\u0644\u0627\u0646\u0627\u0628"
    ],
    "name:fas_x_variant":[
        "Chelleh N\u0101b",
        "Chel\u0101n\u0101b",
        "\u0686\u0644\u0646\u0627\u0628"
    ],
    "name:msa_x_preferred":[
        "Chelanab"
    ],
    "name:swe_x_preferred":[
        "Chel\u0101n\u0101b"
    ],
    "name:und_x_variant":[
        "Chalnab",
        "Chelan\u0101b",
        "Cheln\u0101b",
        "Chinalyakh",
        "Chinaliakh",
        "Chanb\u0101ly\u0101kh"
    ],
    "wof:name":"Chelanab",
    "wof:placetype":"locality"
},
  "geometry": {"coordinates":[46.5845,38.6165],"type":"Point"}
}