{
  "type": "Feature",
  "properties": {
    "gn:admin1_code":"38",
    "gn:asciiname":"Tuteh Chay",
    "gn:country_code":"IR",
    "gn:dem":1295,
    "gn:feature_class":"P",
    "gn:feature_code":"PPL",
    "gn:name":"T\u016bteh Ch\u0101y",
    "gn:population":0,
    "gn:timezone":"Asia/Tehran",
    "iso:country":"IR",
    "name:fas_x_preferred":[
        "\u062a\u0648\u062a\u0650\u0647 \u0686\u0627\u0644"
    ],
    "name:fas_x_variant":[
        "\u062a\u0648\u062a\u0650\u0647\u0686\u0650\u0647",
        "T\u016bteh Ch\u0101l",
        "T\u016btch\u0101l",
        "\u062a\u0648\u062a\u0686\u0627\u0644",
        "\u062a\u0648\u062a\u0647 \u0686\u0627\u06cc"
    ],
    "name:und_x_variant":[
        "Tutakhchay",
        "T\u016btch\u0101l",
        "T\u016btahch\u0101i",
        "T\u016btehcheh",
        "\u062a\u0648\u062a\u0686\u0627\u0644",
        "T\u016bteh Ch\u0101y"
    ],
    "wof:name":"Tuteh Chay",
    "wof:placetype":"locality"
},
  "geometry": {"coordinates":[49.95294000000001,36.5687],"type":"Point"}
}