{
  "type": "Feature",
  "properties": {
    "gn:admin1_code":"3",
    "gn:asciiname":"Dehnow-e Sofla",
    "gn:cc2":"IR",
    "gn:country_code":"IR",
    "gn:dem":2472,
    "gn:feature_class":"P",
    "gn:feature_code":"PPL",
    "gn:name":"Dehnow-e Sofl\u00e1",
    "gn:population":0,
    "gn:timezone":"Asia/Tehran",
    "iso:country":"IR",
    "name:fas_x_preferred":[
        "\u062f\u0650\u0647\u0646\u064f\u0648\u0650 \u0633\u064f\u0641\u0644\u064e\u0649"
    ],
    "name:fas_x_variant":[
        "\u0646\u0648\u0633\u0639\u064e\u0644\u06cc",
        "Dehnow-e Sofl\u00e1"
    ],
    "name:und_x_variant":[
        "N\u016bs\u2018al\u012b"
    ],
    "wof:name":"Dehnow-e Sofla",
    "wof:placetype":"locality"
},
  "geometry": {"coordinates":[50.17528,32.43778],"type":"Point"}
}