{
  "type": "Feature",
  "properties": {
    "gn:admin1_code":"37",
    "gn:asciiname":"Hajji Balkhan",
    "gn:country_code":"IR",
    "gn:dem":74,
    "gn:feature_class":"P",
    "gn:feature_code":"PPL",
    "gn:name":"\u1e28\u0101jj\u012b Balkh\u0101n",
    "gn:population":0,
    "gn:timezone":"Asia/Tehran",
    "iso:country":"IR",
    "name:ara_x_preferred":[
        "\u062d\u0627\u062c\u064a \u0628\u0644\u062e\u0627\u0646"
    ],
    "name:fas_x_preferred":[
        "B\u0101l\u0101 Kh\u0101n \u1e28\u0101jj\u012b"
    ],
    "name:fas_x_variant":[
        "\u1e28\u0101jj\u012b Belkh\u0101n",
        "\u0628\u0627\u0644\u0627 \u062e\u0627\u0646 \u062d\u0627\u062c\u06cc",
        "\u062d\u0627\u062c\u06cc \u0628\u0644\u062e\u0627\u0646"
    ],
    "name:msa_x_preferred":[
        "Hajji Balkhan"
    ],
    "name:und_x_variant":[
        "Haji Balkhan",
        "\u1e28\u0101jj\u012b Balkh\u0101n",
        "\u062d\u0627\u062c\u06cc \u0628\u0644\u062e\u0627\u0646",
        "\u0628\u0627\u0644\u0627 \u062e\u0627\u0646 \u062d\u0627\u062c\u06cc"
    ],
    "wof:name":"Hajji Balkhan",
    "wof:placetype":"locality"
},
  "geometry": {"coordinates":[55.28576,37.20894000000001],"type":"Point"}
}