{
  "type": "Feature",
  "properties": {
    "gn:admin1_code":"42",
    "gn:asciiname":"Karnaveh-ye Shur",
    "gn:country_code":"IR",
    "gn:dem":559,
    "gn:feature_class":"P",
    "gn:feature_code":"PPL",
    "gn:name":"Karn\u0101veh-ye Sh\u016br",
    "gn:population":0,
    "gn:timezone":"Asia/Tehran",
    "iso:country":"IR",
    "name:fas_x_preferred":[
        "Garn\u0101veh Sh\u016br"
    ],
    "name:fas_x_variant":[
        "\u06a9\u0631\u0646\u0627\u0648\u0647 \u0634\u0648\u0631"
    ],
    "name:und_x_variant":[
        "Karn\u0101veh Sh\u016br",
        "Karn\u0101veh-ye Sh\u016br"
    ],
    "wof:name":"Karnaveh-ye Shur",
    "wof:placetype":"locality"
},
  "geometry": {"coordinates":[59.45457,37.2341],"type":"Point"}
}