{
  "type": "Feature",
  "properties": {
    "gn:admin1_code":"23",
    "gn:asciiname":"Deh-e Sefid",
    "gn:country_code":"IR",
    "gn:dem":2189,
    "gn:feature_class":"P",
    "gn:feature_code":"PPL",
    "gn:name":"Deh-e Sef\u012bd",
    "gn:population":0,
    "gn:timezone":"Asia/Tehran",
    "iso:country":"IR",
    "name:fas_x_preferred":[
        "\u062f\u0647 \u0633\u0641\u06cc\u062f"
    ],
    "name:fas_x_variant":[
        "Deh-e Sef\u012bd",
        "\u062f\u0647 \u0633\u0641\u06cc\u062f \u062f\u0631\u0648\u06cc\u0634",
        "\u062f\u0647\u200c\u0633\u0641\u06cc\u062f"
    ],
    "name:und_x_variant":[
        "Deh-e Sef\u012bd",
        "Deh-e Sef\u012bd Darv\u012bsh"
    ],
    "wof:name":"Deh-e Sefid",
    "wof:placetype":"locality"
},
  "geometry": {"coordinates":[49.78271,33.3933],"type":"Point"}
}