{
  "type": "Feature",
  "properties": {
    "gn:admin1_code":"5",
    "gn:asciiname":"Bard-e Pahn",
    "gn:country_code":"IR",
    "gn:dem":2040,
    "gn:feature_class":"P",
    "gn:feature_code":"PPL",
    "gn:name":"Bard-e Pahn",
    "gn:population":0,
    "gn:timezone":"Asia/Tehran",
    "iso:country":"IR",
    "name:fas_x_preferred":[
        "\u0633\u064e\u0646\u06af\u0650 \u067e\u064e\u0647\u0646"
    ],
    "name:fas_x_variant":[
        "\u0628\u064e\u0631\u062f \u067e\u064e\u0647\u0646\u06cc",
        "\u0628\u0631\u062f \u067e\u0647\u0646"
    ],
    "name:und_x_variant":[
        "Bard Pahn\u012b",
        "Bard-e Pahn",
        "\u0628\u0631\u062f \u067e\u0647\u0646",
        "Sang-e Pahn"
    ],
    "wof:name":"Bard-e Pahn",
    "wof:placetype":"locality"
},
  "geometry": {"coordinates":[51.31873,30.63258],"type":"Point"}
}