{
  "type": "Feature",
  "properties": {
    "gn:admin1_code":"33.0",
    "gn:asciiname":"Chaharshanbeh Chay",
    "gn:country_code":"IR",
    "gn:dem":1455,
    "gn:feature_class":"P",
    "gn:feature_code":"PPL",
    "gn:name":"Chah\u0101rshanbeh Ch\u0101y",
    "gn:population":0,
    "gn:timezone":"Asia/Tehran",
    "iso:country":"IR",
    "name:fas_x_preferred":[
        "\u0634\u0647\u0631\u06a9 \u0627\u0631\u0645"
    ],
    "name:fas_x_variant":[
        "Chah\u0101rshanbeh Ch\u0101y"
    ],
    "wof:name":"Chaharshanbeh Chay",
    "wof:placetype":"locality"
},
  "geometry": {"coordinates":[46.3053,38.1071],"type":"Point"}
}