{
  "type": "Feature",
  "properties": {
    "gn:admin1_code":"7",
    "gn:asciiname":"Somad Jan",
    "gn:country_code":"IR",
    "gn:dem":2383,
    "gn:feature_class":"P",
    "gn:feature_code":"PPL",
    "gn:name":"Som\u0101d J\u0101n",
    "gn:population":0,
    "gn:timezone":"Asia/Tehran",
    "iso:country":"IR",
    "name:ara_x_preferred":[
        "\u0633\u0645\u0627\u0631\u062c\u0627\u0646"
    ],
    "name:fas_x_preferred":[
        "\u0633\u0645\u0627\u062f \u062c\u0627\u0646"
    ],
    "name:fas_x_variant":[
        "Som\u0101d J\u0101n",
        "\u0633\u0645\u0627\u0631 \u062c\u0627\u0646",
        "\u0633\u0645\u0627\u0631\u062c\u0627\u0646"
    ],
    "name:msa_x_preferred":[
        "Somar Jan"
    ],
    "name:und_x_variant":[
        "Som\u0101r J\u0101n"
    ],
    "wof:name":"Somad Jan",
    "wof:placetype":"locality"
},
  "geometry": {"coordinates":[53.5019,30.3877],"type":"Point"}
}