{
  "type": "Feature",
  "properties": {
    "gn:admin1_code":"33",
    "gn:asciiname":"Bash Khalij",
    "gn:country_code":"IR",
    "gn:dem":1663,
    "gn:feature_class":"P",
    "gn:feature_code":"PPL",
    "gn:name":"B\u0101sh Khal\u012bj",
    "gn:population":0,
    "gn:timezone":"Asia/Tehran",
    "iso:country":"IR",
    "name:azb_x_preferred":[
        "\u0628\u0627\u0634\u200c\u062e\u0644\u062c"
    ],
    "name:ceb_x_preferred":[
        "B\u0101sh Khal\u012bj"
    ],
    "name:fas_x_preferred":[
        "\u0628\u0627\u0634 \u062e\u0644\u06cc\u062c"
    ],
    "name:fas_x_variant":[
        "B\u0101sh Khalaj",
        "B\u0101sh Khal\u012bj",
        "\u0628\u0627\u0634 \u062e\u0644\u062c",
        "\u0628\u0627\u0634\u200c\u062e\u0644\u062c"
    ],
    "name:msa_x_preferred":[
        "Bash Khalaj"
    ],
    "name:swe_x_preferred":[
        "B\u0101sh Khal\u012bj"
    ],
    "wof:name":"Bash Khalij",
    "wof:placetype":"locality"
},
  "geometry": {"coordinates":[46.7832,37.3988],"type":"Point"}
}