{
  "type": "Feature",
  "properties": {
    "gn:admin1_code":"16",
    "gn:asciiname":"Balvaneh-ye Mo`tamedi",
    "gn:country_code":"IR",
    "gn:dem":2000,
    "gn:feature_class":"P",
    "gn:feature_code":"PPL",
    "gn:name":"B\u0101lv\u0101neh-ye Mo\u2018tamed\u012b",
    "gn:population":0,
    "gn:timezone":"Asia/Tehran",
    "iso:country":"IR",
    "name:fas_x_preferred":[
        "\u0628\u0627\u0644\u0648\u0627\u0646\u0647 \u0645\u0639\u062a\u0645\u062f\u06cc"
    ],
    "name:fas_x_variant":[
        "B\u0101lv\u0101neh-ye Mo\u2018tamed\u012b"
    ],
    "name:und_x_variant":[
        "T\u0101j\u0101b\u0101d"
    ],
    "wof:name":"Balvaneh-ye Mo`tamedi",
    "wof:placetype":"locality"
},
  "geometry": {"coordinates":[47.58113,35.14436],"type":"Point"}
}