{
  "type": "Feature",
  "properties": {
    "gn:admin1_code":"4.0",
    "gn:asciiname":"Karshan-e Bala",
    "gn:country_code":"IR",
    "gn:dem":1178,
    "gn:feature_class":"P",
    "gn:feature_code":"PPL",
    "gn:name":"Karsh\u0101n-e B\u0101l\u0101",
    "gn:population":0,
    "gn:timezone":"Asia/Tehran",
    "iso:country":"IR",
    "name:fas_x_preferred":[
        "\u06a9\u0648\u0634\u0627\u0646 \u0628\u0627\u0644\u0627"
    ],
    "name:fas_x_variant":[
        "K\u016bsh\u0101n-e Qad\u012bm",
        "K\u016bsh\u0101n-e B\u0101l\u0101",
        "\u06a9\u0631\u0634\u0627\u0646 \u0628\u0627\u0644\u0627"
    ],
    "name:und_x_variant":[
        "Kursh\u0101n",
        "Qal\u2018eh J\u0101n\u012b",
        "K\u016bsh\u0101n",
        "Karsh\u0101n-e B\u0101l\u0101"
    ],
    "wof:name":"Karshan-e Bala",
    "wof:placetype":"locality"
},
  "geometry": {"coordinates":[62.22003,27.01956],"type":"Point"}
}