{
  "type": "Feature",
  "properties": {
    "gn:admin1_code":"7",
    "gn:asciiname":"Kul-e Bozorg",
    "gn:country_code":"IR",
    "gn:dem":845,
    "gn:feature_class":"P",
    "gn:feature_code":"PPL",
    "gn:name":"K\u016bl-e Bozorg",
    "gn:population":0,
    "gn:timezone":"Asia/Tehran",
    "iso:country":"IR",
    "name:fas_x_preferred":[
        "K\u016bl-e Bozorg"
    ],
    "name:fas_x_variant":[
        "\u06a9\u0648\u0644 \u0628\u0632\u0631\u06af",
        "\u06a9\u0648\u0644 \u0628\u0627\u06a9\u0648\u0644 \u0628\u0632\u0631\u06af"
    ],
    "name:msa_x_preferred":[
        "Kulbakul-e Bozorg"
    ],
    "name:und_x_variant":[
        "\u06a9\u0648\u0644 \u0628\u0632\u0631\u06af",
        "K\u016blb\u0101k\u016bl-e Bozorg",
        "K\u016blb\u0101k\u016bn P\u0101\u2018\u012bn",
        "K\u016blb\u0101k\u016bn-e P\u0101\u2018\u012bn",
        "K\u016blb\u0101k\u016bn"
    ],
    "wof:name":"Kul-e Bozorg",
    "wof:placetype":"locality"
},
  "geometry": {"coordinates":[51.42075,30.29116],"type":"Point"}
}