{
  "type": "Feature",
  "properties": {
    "gn:admin1_code":"15",
    "gn:asciiname":"Charof Mudu",
    "gn:cc2":"IR",
    "gn:country_code":"IR",
    "gn:dem":1614,
    "gn:feature_class":"P",
    "gn:feature_code":"PPL",
    "gn:name":"Ch\u0101rof M\u016bd\u016b",
    "gn:population":0,
    "gn:timezone":"Asia/Tehran",
    "iso:country":"IR",
    "name:fas_x_preferred":[
        "Ch\u0101rof M\u016bd\u016b"
    ],
    "name:und_x_variant":[
        "M\u016bd\u016b",
        "Ch\u0101roft M\u016bd\u016b"
    ],
    "wof:name":"Charof Mudu",
    "wof:placetype":"locality"
},
  "geometry": {"coordinates":[49.3275,32.75444],"type":"Point"}
}