{
  "type": "Feature",
  "properties": {
    "gn:admin1_code":"29.0",
    "gn:asciiname":"Kantu",
    "gn:country_code":"IR",
    "gn:dem":2510,
    "gn:feature_class":"P",
    "gn:feature_code":"PPL",
    "gn:name":"Kant\u016b",
    "gn:population":0,
    "gn:timezone":"Asia/Tehran",
    "iso:country":"IR",
    "name:fas_x_preferred":[
        "Shahrak-e Kant\u016b\u2019\u012byeh"
    ],
    "name:fas_x_variant":[
        "\u0634\u0647\u0631\u06a9 \u06a9\u0646\u062a\u0648\u0626\u064a\u0647",
        "\u06a9\u0646\u062a\u0648"
    ],
    "name:und_x_variant":[
        "\u0634\u0647\u0631\u06a9 \u06a9\u0646\u062a\u0648\u0626\u064a\u0647",
        "Kant\u016b"
    ],
    "wof:name":"Kantu",
    "wof:placetype":"locality"
},
  "geometry": {"coordinates":[55.7652,30.00046],"type":"Point"}
}