{
  "type": "Feature",
  "properties": {
    "gn:admin1_code":"5",
    "gn:asciiname":"Cheshmeh Juri",
    "gn:country_code":"IR",
    "gn:dem":1992,
    "gn:feature_class":"P",
    "gn:feature_code":"PPL",
    "gn:name":"Cheshmeh J\u016br\u012b",
    "gn:population":0,
    "gn:timezone":"Asia/Tehran",
    "iso:country":"IR",
    "name:fas_x_preferred":[
        "\u0686\u0650\u0634\u0645\u0650\u0647 \u062c\u0650\u0648\u0650\u0631\u0644"
    ],
    "name:fas_x_variant":[
        "Cheshmeh J\u016br\u012b",
        "\u0686\u0634\u0645\u0647 \u062c\u0648\u0631\u06cc"
    ],
    "name:und_x_variant":[
        "Cheshmeh Jeverl"
    ],
    "wof:name":"Cheshmeh Juri",
    "wof:placetype":"locality"
},
  "geometry": {"coordinates":[51.02091,30.89629],"type":"Point"}
}