{
  "type": "Feature",
  "properties": {
    "gn:admin1_code":"35",
    "gn:asciiname":"Gerd Rudbar",
    "gn:country_code":"IR",
    "gn:dem":96,
    "gn:feature_class":"P",
    "gn:feature_code":"PPL",
    "gn:name":"Gerd R\u016bdb\u0101r",
    "gn:population":0,
    "gn:timezone":"Asia/Tehran",
    "iso:country":"IR",
    "name:fas_x_preferred":[
        "\u06af\u0631\u062f \u0631\u0648\u062f\u0628\u0627\u0631"
    ],
    "name:fas_x_variant":[
        "Gerd R\u016bdb\u0101r"
    ],
    "name:und_x_variant":[
        "\u0650\u0631\u062f \u0631\u0648\u062f\u0628\u0627\u0631"
    ],
    "wof:name":"Gerd Rudbar",
    "wof:placetype":"locality"
},
  "geometry": {"coordinates":[52.67614,36.36164],"type":"Point"}
}