{
  "type": "Feature",
  "properties": {
    "gn:admin1_code":"25.0",
    "gn:asciiname":"Sherkat-e Ta`avani",
    "gn:country_code":"IR",
    "gn:dem":1907,
    "gn:feature_class":"P",
    "gn:feature_code":"PPL",
    "gn:name":"Sherkat-e Ta\u2018\u0101van\u012b",
    "gn:population":0,
    "gn:timezone":"Asia/Tehran",
    "iso:country":"IR",
    "name:fas_x_preferred":[
        "Sherkat-e Ta\u2018\u0101van\u012b"
    ],
    "name:fas_x_variant":[
        "\u0634\u0631\u06a9\u062a \u062a\u0639\u0627\u0648\u0646\u064a"
    ],
    "wof:name":"Sherkat-e Ta`avani",
    "wof:placetype":"locality"
},
  "geometry": {"coordinates":[53.6876,36.05781],"type":"Point"}
}