{
  "type": "Feature",
  "properties": {
    "gn:admin1_code":"11",
    "gn:asciiname":"Bohregh",
    "gn:country_code":"IR",
    "gn:dem":160,
    "gn:feature_class":"P",
    "gn:feature_code":"PPL",
    "gn:name":"Bohregh",
    "gn:population":0,
    "gn:timezone":"Asia/Tehran",
    "iso:country":"IR",
    "name:ara_x_preferred":[
        "\u0628\u0647\u0631\u063a"
    ],
    "name:ceb_x_preferred":[
        "Bohregh"
    ],
    "name:fas_x_preferred":[
        "\u0628\u0647\u0631\u063a"
    ],
    "name:fas_x_variant":[
        "\u0628\u0650\u0647\u0631\u064f\u063a\u0650 \u062a\u064e\u062e\u062a",
        "\u0628\u064f\u0647\u0631\u064f\u063a",
        "\u0628\u064f\u0647\u0631\u0650\u063a\u0650 \u062a\u064e\u062e\u062a"
    ],
    "name:msa_x_preferred":[
        "Bohregh"
    ],
    "name:swe_x_preferred":[
        "Bohregh"
    ],
    "name:und_x_variant":[
        "Behrogh-e Takht",
        "Bohrogh",
        "Bohregh-e Takht"
    ],
    "wof:name":"Bohregh",
    "wof:placetype":"locality"
},
  "geometry": {"coordinates":[56.7091,27.5407],"type":"Point"}
}