{
  "type": "Feature",
  "properties": {
    "gn:admin1_code":"33",
    "gn:asciiname":"Aghcheh Mashhad-e Chahar Dowli",
    "gn:country_code":"IR",
    "gn:dem":1753,
    "gn:feature_class":"P",
    "gn:feature_code":"PPL",
    "gn:name":"\u0100ghcheh Mashhad-e Chah\u0101r Dowl\u012b",
    "gn:population":0,
    "gn:timezone":"Asia/Tehran",
    "iso:country":"IR",
    "name:fas_x_preferred":[
        "\u0622\u063a\u0686\u0647 \u0645\u0634\u0647\u062f \u0686\u0647\u0627\u0631 \u062f\u0648\u0644\u06cc"
    ],
    "name:fas_x_variant":[
        "\u0100ghcheh Mashhad-e Chah\u0101r Dowl\u012b",
        "\u0622\u063a\u0686\u0647 \u0645\u0634\u0647\u062f \u0686\u0627\u0631 \u062f\u0648\u0644\u06cc"
    ],
    "name:und_x_variant":[
        "\u0100ghcheh Mashhad",
        "\u0100ghcheh Mashhad-e Ch\u0101r Dowl\u012b"
    ],
    "wof:name":"Aghcheh Mashhad-e Chahar Dowli",
    "wof:placetype":"locality"
},
  "geometry": {"coordinates":[46.3141,37.1833],"type":"Point"}
}