{
  "type": "Feature",
  "properties": {
    "gn:admin1_code":"4.0",
    "gn:asciiname":"Varmal",
    "gn:country_code":"IR",
    "gn:dem":479,
    "gn:feature_class":"P",
    "gn:feature_code":"PPL",
    "gn:name":"Varm\u0101l",
    "gn:population":0,
    "gn:timezone":"Asia/Tehran",
    "iso:country":"IR",
    "name:fas_x_preferred":[
        "\u0648\u0631\u0645\u0627\u0644"
    ],
    "name:fas_x_variant":[
        "Varm\u0101l"
    ],
    "name:und_x_variant":[
        "Barm\u0101l",
        "Varmai"
    ],
    "wof:name":"Varmal",
    "wof:placetype":"locality"
},
  "geometry": {"coordinates":[61.3378,30.7511],"type":"Point"}
}