{
  "type": "Feature",
  "properties": {
    "gn:admin1_code":"15.0",
    "gn:asciiname":"Bard Neshandeh-ye Gholamreza",
    "gn:country_code":"IR",
    "gn:dem":671,
    "gn:feature_class":"P",
    "gn:feature_code":"PPL",
    "gn:name":"Bard Nesh\u0101ndeh-ye Ghol\u0101mre\u1e95\u0101",
    "gn:population":0,
    "gn:timezone":"Asia/Tehran",
    "iso:country":"IR",
    "name:fas_x_preferred":[
        "\u062a\u0646\u0628\u0627\u06a9\u0648 \u06a9\u0627\u0631"
    ],
    "name:fas_x_variant":[
        "\u0628\u0631\u062f \u0646\u0634\u0627\u0646\u062f\u0647 \u063a\u0644\u0627\u0645\u0631\u0636\u0627",
        "\u062a\u0646\u0628\u0627\u06a9\u0648 \u06a9\u0627\u0631 \u0639\u0644\u06cc"
    ],
    "name:und_x_variant":[
        "Tanb\u0101k\u016b K\u0101r",
        "Bard Nesh\u0101ndeh-ye Ghol\u0101mre\u1e95\u0101",
        "Tanb\u0101k\u016b K\u0101r \u2018Al\u012b"
    ],
    "wof:name":"Bard Neshandeh-ye Gholamreza",
    "wof:placetype":"locality"
},
  "geometry": {"coordinates":[49.67182,31.96758],"type":"Point"}
}