{
  "type": "Feature",
  "properties": {
    "gn:admin1_code":"41.0",
    "gn:asciiname":"Hobabi",
    "gn:country_code":"IR",
    "gn:dem":764,
    "gn:feature_class":"P",
    "gn:feature_code":"PPL",
    "gn:name":"\u1e28ob\u0101b\u012b",
    "gn:population":0,
    "gn:timezone":"Asia/Tehran",
    "iso:country":"IR",
    "name:fas_x_preferred":[
        "\u1e28ob\u0101b\u012b"
    ],
    "wof:name":"Hobabi",
    "wof:placetype":"locality"
},
  "geometry": {"coordinates":[60.70333,31.37722],"type":"Point"}
}