{
  "type": "Feature",
  "properties": {
    "gn:admin1_code":"23.0",
    "gn:asciiname":"`Abbasabad-e Poshteh",
    "gn:country_code":"IR",
    "gn:dem":2021,
    "gn:feature_class":"P",
    "gn:feature_code":"PPL",
    "gn:name":"\u2018Abb\u0101s\u0101b\u0101d-e Poshteh",
    "gn:population":0,
    "gn:timezone":"Asia/Tehran",
    "iso:country":"IR",
    "name:fas_x_preferred":[
        "\u0639\u0628\u0651\u0627\u0633 \u0622\u0628\u0627\u062f"
    ],
    "name:fas_x_variant":[
        "\u2018Abb\u0101s\u0101b\u0101d",
        "\u0639\u0628\u0627\u0633 \u0622\u0628\u0627\u062f \u067e\u0634\u062a\u0647"
    ],
    "name:und_x_variant":[
        "\u2018Abb\u0101s\u0101b\u0101d-e Poshteh"
    ],
    "wof:name":"`Abbasabad-e Poshteh",
    "wof:placetype":"locality"
},
  "geometry": {"coordinates":[49.40437,33.53572],"type":"Point"}
}