{
  "type": "Feature",
  "properties": {
    "gn:admin1_code":"29",
    "gn:asciiname":"Shamzan-e Dulab",
    "gn:country_code":"IR",
    "gn:dem":420,
    "gn:feature_class":"P",
    "gn:feature_code":"PPL",
    "gn:name":"Shamz\u0101n-e D\u016bl\u0101b",
    "gn:population":0,
    "gn:timezone":"Asia/Tehran",
    "iso:country":"IR",
    "name:fas_x_preferred":[
        "\u0634\u0645\u0632\u0627\u0646 \u062f\u0648\u0644\u0627\u0628"
    ],
    "name:fas_x_variant":[
        "D\u016bl\u0101b",
        "Shamz\u0101n-e D\u016bl\u0101b"
    ],
    "wof:name":"Shamzan-e Dulab",
    "wof:placetype":"locality"
},
  "geometry": {"coordinates":[57.916,27.6095],"type":"Point"}
}