{
  "type": "Feature",
  "properties": {
    "gn:admin1_code":"8.0",
    "gn:asciiname":"Gisham",
    "gn:country_code":"IR",
    "gn:dem":326,
    "gn:feature_class":"P",
    "gn:feature_code":"PPLL",
    "gn:name":"G\u012bsham",
    "gn:population":0,
    "gn:timezone":"Asia/Tehran",
    "iso:country":"IR",
    "name:fas_x_preferred":[
        "\u06af\u06cc\u0634\u0645"
    ],
    "name:und_x_variant":[
        "G\u012bsham"
    ],
    "wof:name":"Gisham",
    "wof:placetype":"locality"
},
  "geometry": {"coordinates":[49.34882,37.03795],"type":"Point"}
}