{
  "type": "Feature",
  "properties": {
    "gn:admin1_code":"0",
    "gn:asciiname":"Moshka od Din",
    "gn:country_code":"IR",
    "gn:dem":665,
    "gn:feature_class":"P",
    "gn:feature_code":"PPL",
    "gn:name":"Moshk\u0101 od D\u012bn",
    "gn:population":0,
    "gn:timezone":"Asia/Tehran",
    "iso:country":"IR",
    "name:fas_x_preferred":[
        "\u0645\u0634\u06a9\u0627 \u0627\u0644\u062f\u06cc\u0646"
    ],
    "name:fas_x_variant":[
        "Moshk\u0101 od D\u012bn"
    ],
    "wof:name":"Moshka od Din",
    "wof:placetype":"locality"
},
  "geometry": {"coordinates":[57.6171,26.9902],"type":"Point"}
}