{
  "type": "Feature",
  "properties": {
    "gn:admin1_code":"11",
    "gn:asciiname":"Rostami",
    "gn:country_code":"IR",
    "gn:dem":64,
    "gn:feature_class":"P",
    "gn:feature_code":"PPL",
    "gn:name":"Rostam\u012b",
    "gn:population":0,
    "gn:timezone":"Asia/Tehran",
    "iso:country":"IR",
    "name:ara_x_preferred":[
        "\u0631\u0633\u062a\u0645\u064a"
    ],
    "name:fas_x_preferred":[
        "Rostam\u012b"
    ],
    "name:fas_x_variant":[
        "\u0631\u0633\u062a\u0645\u06cc"
    ],
    "name:msa_x_preferred":[
        "Rostami"
    ],
    "wof:name":"Rostami",
    "wof:placetype":"locality"
},
  "geometry": {"coordinates":[54.06222,26.86854000000001],"type":"Point"}
}