{
  "type": "Feature",
  "properties": {
    "gn:admin1_code":"29",
    "gn:asciiname":"Davaran",
    "gn:country_code":"IR",
    "gn:dem":1905,
    "gn:feature_class":"P",
    "gn:feature_code":"PPL",
    "gn:name":"D\u0101var\u0101n",
    "gn:population":0,
    "gn:timezone":"Asia/Tehran",
    "iso:country":"IR",
    "name:fas_x_preferred":[
        "D\u0101var\u0101n"
    ],
    "name:fas_x_variant":[
        "\u062f\u0627\u0648\u0631\u0627\u0646",
        "D\u0101viran"
    ],
    "name:und_x_variant":[
        "D\u0101viran"
    ],
    "wof:name":"Davaran",
    "wof:placetype":"locality"
},
  "geometry": {"coordinates":[56.19185,30.58055],"type":"Point"}
}