{
  "type": "Feature",
  "properties": {
    "gn:admin1_code":"35",
    "gn:asciiname":"Si Sangan",
    "gn:country_code":"IR",
    "gn:dem":11,
    "gn:feature_class":"P",
    "gn:feature_code":"PPL",
    "gn:name":"S\u012b Sang\u0101n",
    "gn:population":0,
    "gn:timezone":"Asia/Tehran",
    "iso:country":"IR",
    "name:und_x_variant":[
        "S\u012b Sang\u0101n"
    ],
    "wof:name":"Si Sangan",
    "wof:placetype":"locality"
},
  "geometry": {"coordinates":[51.75417,36.57],"type":"Point"}
}