{
  "type": "Feature",
  "properties": {
    "gn:admin1_code":"33",
    "gn:asciiname":"Chay Aqdagh",
    "gn:country_code":"IR",
    "gn:dem":1518,
    "gn:feature_class":"P",
    "gn:feature_code":"PPL",
    "gn:name":"Ch\u0101y \u0100qd\u0101gh",
    "gn:population":0,
    "gn:timezone":"Asia/Tehran",
    "iso:country":"IR",
    "name:fas_x_preferred":[
        "\u0686\u0627\u06cc \u0622\u0642\u062f\u0627\u063a"
    ],
    "name:fas_x_variant":[
        "Ch\u0101\u2019\u012b \u0100q D\u0101gh",
        "Ch\u0101y \u0100qd\u0101gh"
    ],
    "wof:name":"Chay Aqdagh",
    "wof:placetype":"locality"
},
  "geometry": {"coordinates":[47.0406,37.38800000000001],"type":"Point"}
}