{
  "type": "Feature",
  "properties": {
    "gn:admin1_code":"5.0",
    "gn:asciiname":"Dasht-e-Rum",
    "gn:country_code":"IR",
    "gn:dem":2117,
    "gn:feature_class":"P",
    "gn:feature_code":"PPL",
    "gn:name":"Dasht-e-R\u016bm",
    "gn:population":0,
    "gn:timezone":"Asia/Tehran",
    "iso:country":"IR",
    "name:fas_x_preferred":[
        "Dasht-e-R\u016bm"
    ],
    "wof:name":"Dasht-e-Rum",
    "wof:placetype":"locality"
},
  "geometry": {"coordinates":[51.55583,30.53056],"type":"Point"}
}