{
  "type": "Feature",
  "properties": {
    "gn:admin1_code":"8.0",
    "gn:asciiname":"Hamleh Chal",
    "gn:country_code":"IR",
    "gn:dem":1782,
    "gn:feature_class":"P",
    "gn:feature_code":"PPL",
    "gn:name":"Hamleh Ch\u0101l",
    "gn:population":0,
    "gn:timezone":"Asia/Tehran",
    "iso:country":"IR",
    "name:fas_x_preferred":[
        "Haleh Ch\u0101l"
    ],
    "name:fas_x_variant":[
        "\u0647\u0644\u0647 \u0686\u0627\u0644",
        "\u0647\u0645\u0644\u0647 \u0686\u0627\u0644"
    ],
    "name:und_x_variant":[
        "\u0647\u0644\u0647 \u0686\u0627\u0644",
        "Hamleh Ch\u0101l"
    ],
    "wof:name":"Hamleh Chal",
    "wof:placetype":"locality"
},
  "geometry": {"coordinates":[49.94467,36.92681],"type":"Point"}
}