{
  "type": "Feature",
  "properties": {
    "gn:admin1_code":"22.0",
    "gn:asciiname":"Chah Mushi-ye Vosta",
    "gn:country_code":"IR",
    "gn:dem":24,
    "gn:feature_class":"P",
    "gn:feature_code":"PPL",
    "gn:name":"Ch\u0101h M\u016bsh\u012b-ye Vost\u00e1",
    "gn:population":0,
    "gn:timezone":"Asia/Tehran",
    "iso:country":"IR",
    "name:fas_x_preferred":[
        "\u0686\u0627\u0647 \u0645\u0648\u0634\u06cc \u0648\u0633\u0637\u06cc"
    ],
    "name:fas_x_variant":[
        "Ch\u0101h M\u016bsh\u012b-ye Vost\u00e1"
    ],
    "wof:name":"Chah Mushi-ye Vosta",
    "wof:placetype":"locality"
},
  "geometry": {"coordinates":[51.0377,29.4028],"type":"Point"}
}