{
  "type": "Feature",
  "properties": {
    "gn:admin1_code":"33",
    "gn:asciiname":"Pir Bolaghi",
    "gn:country_code":"IR",
    "gn:dem":1227,
    "gn:feature_class":"P",
    "gn:feature_code":"PPL",
    "gn:name":"P\u012br Bol\u0101gh\u012b",
    "gn:population":0,
    "gn:timezone":"Asia/Tehran",
    "iso:country":"IR",
    "name:fas_x_preferred":[
        "\u067e\u06cc\u0631 \u0628\u0644\u0627\u063a\u06cc"
    ],
    "name:fas_x_variant":[
        "P\u012br Bol\u0101gh\u012b"
    ],
    "name:und_x_variant":[
        "Fir Bul\u0101q"
    ],
    "wof:name":"Pir Bolaghi",
    "wof:placetype":"locality"
},
  "geometry": {"coordinates":[46.34335,38.8597],"type":"Point"}
}