{
  "type": "Feature",
  "properties": {
    "gn:admin1_code":"8",
    "gn:asciiname":"Narenj Gol",
    "gn:country_code":"IR",
    "gn:dem":56,
    "gn:feature_class":"P",
    "gn:feature_code":"PPL",
    "gn:name":"N\u0101renj Gol",
    "gn:population":0,
    "gn:timezone":"Asia/Tehran",
    "iso:country":"IR",
    "name:fas_x_preferred":[
        "T\u0101r\u012bkh Gal"
    ],
    "name:fas_x_variant":[
        "N\u0101renjkol",
        "\u062a\u0627\u0631\u06cc\u062e \u06af\u0644",
        "\u0646\u0627\u0631\u0646\u062c \u06af\u0644"
    ],
    "name:und_x_variant":[
        "\u062a\u0627\u0631\u06cc\u062e \u06af\u0644",
        "N\u0101renj Gol",
        "\u0646\u0627\u0631\u0646\u062c \u06a9\u0644"
    ],
    "wof:name":"Narenj Gol",
    "wof:placetype":"locality"
},
  "geometry": {"coordinates":[49.53428,37.16964],"type":"Point"}
}