{
  "type": "Feature",
  "properties": {
    "gn:admin1_code":"7",
    "gn:asciiname":"Majdabad",
    "gn:country_code":"IR",
    "gn:dem":1595,
    "gn:feature_class":"P",
    "gn:feature_code":"PPL",
    "gn:name":"Majd\u0101b\u0101d",
    "gn:population":0,
    "gn:timezone":"Asia/Tehran",
    "iso:country":"IR",
    "name:fas_x_preferred":[
        "\u0645\u062c\u062f \u0622\u0628\u0627\u062f"
    ],
    "name:fas_x_variant":[
        "Majd\u0101b\u0101d"
    ],
    "wof:name":"Majdabad",
    "wof:placetype":"locality"
},
  "geometry": {"coordinates":[52.6641,29.9189],"type":"Point"}
}