{
  "type": "Feature",
  "properties": {
    "gn:admin1_code":"42",
    "gn:asciiname":"Kajabad",
    "gn:country_code":"IR",
    "gn:dem":1855,
    "gn:feature_class":"P",
    "gn:feature_code":"PPL",
    "gn:name":"Kaj\u0101b\u0101d",
    "gn:population":0,
    "gn:timezone":"Asia/Tehran",
    "iso:country":"IR",
    "name:fas_x_preferred":[
        "K\u0101j\u0101b\u0101d"
    ],
    "name:fas_x_variant":[
        "Kaj\u0101b\u0101d",
        "\u06a9\u0627\u062c \u0622\u0628\u0627\u062f",
        "\u06a9\u062c \u0622\u0628\u0627\u062f"
    ],
    "name:und_x_variant":[
        "\u06a9\u0627\u062c \u0622\u0628\u0627\u062f"
    ],
    "wof:name":"Kajabad",
    "wof:placetype":"locality"
},
  "geometry": {"coordinates":[58.4998,34.16895],"type":"Point"}
}