{
  "type": "Feature",
  "properties": {
    "gn:admin1_code":"7.0",
    "gn:asciiname":"Jelow Dar",
    "gn:country_code":"IR",
    "gn:dem":1602,
    "gn:feature_class":"P",
    "gn:feature_code":"PPL",
    "gn:name":"Jelow Dar",
    "gn:population":0,
    "gn:timezone":"Asia/Tehran",
    "iso:country":"IR",
    "name:ara_x_preferred":[
        "\u062c\u0644\u0648\u062f\u0631"
    ],
    "name:fas_x_preferred":[
        "Jolow D\u0101r"
    ],
    "name:fas_x_variant":[
        "\u062c\u0644\u0648 \u062f\u0631",
        "\u062c\u0644\u0648 \u062f\u0627\u0631",
        "\u062c\u0644\u0648\u062f\u0631"
    ],
    "name:msa_x_preferred":[
        "Jolow Dar"
    ],
    "name:und_x_variant":[
        "Jelow D\u0101r"
    ],
    "wof:name":"Jelow Dar",
    "wof:placetype":"locality"
},
  "geometry": {"coordinates":[53.15496,29.78764],"type":"Point"}
}