{
  "type": "Feature",
  "properties": {
    "gn:admin1_code":"33",
    "gn:asciiname":"Bishak",
    "gn:country_code":"IR",
    "gn:dem":1706,
    "gn:feature_class":"P",
    "gn:feature_code":"PPL",
    "gn:name":"B\u012bshak",
    "gn:population":0,
    "gn:timezone":"Asia/Tehran",
    "iso:country":"IR",
    "name:azb_x_preferred":[
        "\u0628\u06cc\u0634\u06a9"
    ],
    "name:fas_x_preferred":[
        "\u0628\u0650\u0634\u0627\u0643"
    ],
    "name:fas_x_variant":[
        "\u0628\u06cc\u0634\u06a9",
        "\u0648\u0650\u0634\u064e\u0643",
        "B\u012bshak",
        "\u0628\u0650\u0634 \u0627\u064e\u0634\u0643",
        "\u0628\u064a\u0634\u064e\u0643"
    ],
    "name:msa_x_preferred":[
        "Bishak"
    ],
    "name:und_x_variant":[
        "Besh\u0101k",
        "Bishak Dizmar",
        "Besh Ashk",
        "Veshak"
    ],
    "wof:name":"Bishak",
    "wof:placetype":"locality"
},
  "geometry": {"coordinates":[46.32602,38.59588],"type":"Point"}
}