{
  "type": "Feature",
  "properties": {
    "gn:admin1_code":"4.0",
    "gn:asciiname":"Jadu Zehi",
    "gn:cc2":"IR",
    "gn:country_code":"IR",
    "gn:dem":25,
    "gn:feature_class":"P",
    "gn:feature_code":"PPL",
    "gn:name":"J\u0101d\u016b Zeh\u012b",
    "gn:population":0,
    "gn:timezone":"Asia/Tehran",
    "iso:country":"IR",
    "name:fas_x_preferred":[
        "J\u0101d\u016b Zeh\u012b"
    ],
    "name:und_x_variant":[
        "J\u0101ddeh Z\u0101\u2019\u012b",
        "Jado Z\u012b",
        "J\u0101ddeh Zeh\u012b",
        "Jadz\u012b",
        "Jad Z\u0101\u2019\u012b"
    ],
    "wof:name":"Jadu Zehi",
    "wof:placetype":"locality"
},
  "geometry": {"coordinates":[61.21222,25.58444],"type":"Point"}
}