{
  "type": "Feature",
  "properties": {
    "gn:admin1_code":"23",
    "gn:asciiname":"Khatunabad",
    "gn:country_code":"IR",
    "gn:dem":1695,
    "gn:feature_class":"P",
    "gn:feature_code":"PPL",
    "gn:name":"Kh\u0101t\u016bn\u0101b\u0101d",
    "gn:population":0,
    "gn:timezone":"Asia/Tehran",
    "iso:country":"IR",
    "name:ara_x_preferred":[
        "\u062e\u0627\u062a\u0648\u0646\u200c\u0622\u0628\u0627\u062f"
    ],
    "name:ceb_x_preferred":[
        "Kh\u0101t\u016bn\u0101b\u0101d"
    ],
    "name:fas_x_preferred":[
        "\u062e\u0627\u062a\u0648\u0646 \u0622\u0628\u0627\u062f"
    ],
    "name:fas_x_variant":[
        "Kh\u0101t\u016bnb\u0101n",
        "\u062e\u0627\u062a\u0648\u0646\u0628\u0627\u0646",
        "Kh\u0101t\u016bn\u0101b\u0101d",
        "\u062e\u0627\u062a\u0648\u0646\u200c\u0622\u0628\u0627\u062f"
    ],
    "wof:name":"Khatunabad",
    "wof:placetype":"locality"
},
  "geometry": {"coordinates":[47.8365,34.1139],"type":"Point"}
}