{
  "type": "Feature",
  "properties": {
    "gn:admin1_code":"23",
    "gn:asciiname":"Farsesh",
    "gn:country_code":"IR",
    "gn:dem":2468,
    "gn:feature_class":"P",
    "gn:feature_code":"PPL",
    "gn:name":"Farsesh",
    "gn:population":0,
    "gn:timezone":"Asia/Tehran",
    "iso:country":"IR",
    "name:ara_x_preferred":[
        "\u0641\u0631\u0633\u0634"
    ],
    "name:fas_x_preferred":[
        "\u0641\u0631\u0633\u0634"
    ],
    "name:und_x_variant":[
        "Porsesh",
        "Parsish",
        "Farsesh",
        "\u0641\u0631\u0633\u0634"
    ],
    "wof:name":"Farsesh",
    "wof:placetype":"locality"
},
  "geometry": {"coordinates":[49.86465,33.09044],"type":"Point"}
}