{
  "type": "Feature",
  "properties": {
    "gn:admin1_code":"9.0",
    "gn:asciiname":"Aghcheh Kharabeh",
    "gn:country_code":"IR",
    "gn:dem":1816,
    "gn:feature_class":"P",
    "gn:feature_code":"PPL",
    "gn:name":"\u0100ghcheh Khar\u0101beh",
    "gn:population":0,
    "gn:timezone":"Asia/Tehran",
    "iso:country":"IR",
    "name:fas_x_preferred":[
        "\u0622\u063a\u0686\u0650\u0647 \u062e\u064e\u0631\u0627\u0628\u0650\u0647"
    ],
    "name:fas_x_variant":[
        "\u0622\u0642\u062c\u0650\u0647 \u062e\u064e\u0631\u0627\u0628\u0650\u0647",
        "\u0622\u0642\u0686\u0650\u0647 \u062e\u064e\u0631\u0627\u0628\u0650\u0647",
        "\u0100ghcheh Khar\u0101beh",
        "\u0622\u063a\u0686\u0647 \u062e\u0631\u0627\u0628\u0647",
        "\u0627\u063a\u0686\u0647 \u062e\u0631\u0627\u0628\u0647"
    ],
    "name:msa_x_preferred":[
        "Aghcheh Kharabeh"
    ],
    "name:und_x_variant":[
        "\u0100qcheh Khar\u0101beh",
        "\u0100qjeh Khar\u0101beh",
        "\u0622\u063a\u0686\u0647 \u062e\u0631\u0627\u0628\u0647"
    ],
    "wof:name":"Aghcheh Kharabeh",
    "wof:placetype":"locality"
},
  "geometry": {"coordinates":[48.3323,34.994],"type":"Point"}
}