{
  "type": "Feature",
  "properties": {
    "gn:admin1_code":"37",
    "gn:asciiname":"Vatan",
    "gn:country_code":"IR",
    "gn:dem":993,
    "gn:feature_class":"P",
    "gn:feature_code":"PPL",
    "gn:name":"Va\u0163an",
    "gn:population":0,
    "gn:timezone":"Asia/Tehran",
    "iso:country":"IR",
    "name:fas_x_preferred":[
        "Va\u0163an"
    ],
    "name:fas_x_variant":[
        "\u0648\u0637\u0646"
    ],
    "name:msa_x_preferred":[
        "Vatan"
    ],
    "name:und_x_variant":[
        "\u0648\u0637\u0646"
    ],
    "wof:name":"Vatan",
    "wof:placetype":"locality"
},
  "geometry": {"coordinates":[55.27032,36.97481],"type":"Point"}
}