{
  "type": "Feature",
  "properties": {
    "gn:admin1_code":"35",
    "gn:asciiname":"Miandasteh",
    "gn:country_code":"IR",
    "gn:dem":1,
    "gn:feature_class":"P",
    "gn:feature_code":"PPL",
    "gn:name":"M\u012b\u0101ndasteh",
    "gn:population":0,
    "gn:timezone":"Asia/Tehran",
    "iso:country":"IR",
    "name:fas_x_preferred":[
        "\u0645\u064a\u0627\u0646 \u062f\u064e\u0633\u062a\u0650\u06c0 \u062c\u064e\u0644\u0627\u0644 \u0627\u064e\u0631\u0632\u064e\u0643"
    ],
    "name:fas_x_variant":[
        "M\u012b\u0101n Dasteh-ye Jal\u0101l Arzak",
        "M\u012b\u0101ndasteh",
        "\u0645\u064a\u0627\u0646\u062f\u0633\u062a\u0647"
    ],
    "wof:name":"Miandasteh",
    "wof:placetype":"locality"
},
  "geometry": {"coordinates":[52.5549,36.53338],"type":"Point"}
}