{
  "type": "Feature",
  "properties": {
    "gn:admin1_code":"11",
    "gn:asciiname":"Kimpunu",
    "gn:country_code":"IR",
    "gn:dem":281,
    "gn:feature_class":"P",
    "gn:feature_code":"PPL",
    "gn:name":"K\u012bmp\u016bn\u016b",
    "gn:population":0,
    "gn:timezone":"Asia/Tehran",
    "iso:country":"IR",
    "name:fas_x_preferred":[
        "\u06a9\u06cc\u0645\u067e\u0648\u0646\u0648"
    ],
    "name:fas_x_variant":[
        "K\u012bmp\u016bn\u016b"
    ],
    "wof:name":"Kimpunu",
    "wof:placetype":"locality"
},
  "geometry": {"coordinates":[56.399,27.5495],"type":"Point"}
}