{
  "type": "Feature",
  "properties": {
    "gn:admin1_code":"35",
    "gn:asciiname":"Darzi Kola-ye Bozorg",
    "gn:country_code":"IR",
    "gn:dem":11,
    "gn:feature_class":"P",
    "gn:feature_code":"PPL",
    "gn:name":"Darz\u012b Kol\u0101-ye Bozorg",
    "gn:population":0,
    "gn:timezone":"Asia/Tehran",
    "iso:country":"IR",
    "name:ceb_x_preferred":[
        "Darz\u012b Kol\u0101-ye Bozorg"
    ],
    "name:fas_x_preferred":[
        "\u062f\u0631\u0632\u06cc \u0643\u0644\u0627 \u0628\u0632\u0631\u06af"
    ],
    "name:fas_x_variant":[
        "Darz\u012b Kol\u0101-ye Bozorg",
        "\u062f\u0631\u0632\u06cc\u06a9\u0644\u0627\u0628\u0632\u0631\u06af"
    ],
    "name:mzn_x_preferred":[
        "\u062f\u0631\u0632\u06cc\u200c\u06a9\u0644\u0627 \u0628\u0632\u0631\u06af"
    ],
    "name:swe_x_preferred":[
        "Darz\u012b Kol\u0101-ye Bozorg"
    ],
    "name:und_x_variant":[
        "\u062f\u064e\u0631\u0632\u06cc \u0643\u064f\u0644\u0627\u06cc \u0628\u064f\u0632\u064f\u0631\u06af"
    ],
    "wof:name":"Darzi Kola-ye Bozorg",
    "wof:placetype":"locality"
},
  "geometry": {"coordinates":[52.52255,36.49538],"type":"Point"}
}