{
  "type": "Feature",
  "properties": {
    "gn:admin1_code":"33",
    "gn:asciiname":"Zazen Kesh",
    "gn:country_code":"IR",
    "gn:dem":1792,
    "gn:feature_class":"P",
    "gn:feature_code":"PPL",
    "gn:name":"Zazen Kesh",
    "gn:population":0,
    "gn:timezone":"Asia/Tehran",
    "iso:country":"IR",
    "name:ceb_x_preferred":[
        "Zazen Kesh"
    ],
    "name:fas_x_preferred":[
        "\u0632\u0632\u0646 \u06a9\u0634"
    ],
    "name:fas_x_variant":[
        "\u0632\u0631\u0646\u06a9\u0634"
    ],
    "name:msa_x_preferred":[
        "Zaren Kesh"
    ],
    "name:swe_x_preferred":[
        "Zazen Kesh"
    ],
    "wof:name":"Zazen Kesh",
    "wof:placetype":"locality"
},
  "geometry": {"coordinates":[47.7685,37.6716],"type":"Point"}
}