{
  "type": "Feature",
  "properties": {
    "gn:admin1_code":"8",
    "gn:asciiname":"Mahalleh-ye Kordabad",
    "gn:country_code":"IR",
    "gn:dem":27,
    "gn:feature_class":"P",
    "gn:feature_code":"PPL",
    "gn:name":"Ma\u1e29alleh-ye Kord\u0101b\u0101d",
    "gn:population":0,
    "gn:timezone":"Asia/Tehran",
    "iso:country":"IR",
    "name:fas_x_preferred":[
        "\u06a9\u0631\u062f \u0622\u0628\u0627\u062f"
    ],
    "name:fas_x_variant":[
        "Kord\u0101b\u0101d",
        "\u0645\u062d\u0644\u0647 \u06a9\u0631\u062f \u0622\u0628\u0627\u062f"
    ],
    "name:und_x_variant":[
        "Kardabad",
        "Kord\u0101b\u0101d",
        "Ma\u1e29alleh-ye Kord\u0101b\u0101d"
    ],
    "wof:name":"Mahalleh-ye Kordabad",
    "wof:placetype":"locality"
},
  "geometry": {"coordinates":[49.34,37.21131],"type":"Point"}
}