{
  "type": "Feature",
  "properties": {
    "gn:admin1_code":"7",
    "gn:asciiname":"Cham-e Riz",
    "gn:country_code":"IR",
    "gn:dem":1696,
    "gn:feature_class":"P",
    "gn:feature_code":"PPL",
    "gn:name":"Cham-e R\u012bz",
    "gn:population":0,
    "gn:timezone":"Asia/Tehran",
    "iso:country":"IR",
    "name:fas_x_preferred":[
        "Cham-e R\u012bz"
    ],
    "wof:name":"Cham-e Riz",
    "wof:placetype":"locality"
},
  "geometry": {"coordinates":[52.37028,30.1925],"type":"Point"}
}