{
  "type": "Feature",
  "properties": {
    "gn:admin1_code":"35.0",
    "gn:asciiname":"Harun Kola-ye Bala",
    "gn:country_code":"IR",
    "gn:dem":55,
    "gn:feature_class":"P",
    "gn:feature_code":"PPL",
    "gn:name":"H\u0101r\u016bn Kol\u0101-ye B\u0101l\u0101",
    "gn:population":0,
    "gn:timezone":"Asia/Tehran",
    "iso:country":"IR",
    "name:fas_x_preferred":[
        "\u0647\u0627\u0631\u0648\u0646 \u0643\u064f\u0644\u0627\u06cc \u0639\u064f\u0644\u064a\u0627"
    ],
    "name:fas_x_variant":[
        "H\u0101r\u016bn Kol\u0101-ye \u2018Oly\u0101",
        "H\u0101r\u016bn Kol\u0101-ye B\u0101l\u0101",
        "\u0647\u0627\u0631\u0648\u0646 \u0643\u0644\u0627 \u0628\u0627\u0644\u0627"
    ],
    "wof:name":"Harun Kola-ye Bala",
    "wof:placetype":"locality"
},
  "geometry": {"coordinates":[52.45432,36.45949],"type":"Point"}
}