{
  "type": "Feature",
  "properties": {
    "gn:admin1_code":"42",
    "gn:asciiname":"Mazra`eh-ye Talkhak",
    "gn:country_code":"IR",
    "gn:dem":1181,
    "gn:feature_class":"P",
    "gn:feature_code":"PPL",
    "gn:name":"Mazra\u2018eh-ye Talkhak",
    "gn:population":0,
    "gn:timezone":"Asia/Tehran",
    "iso:country":"IR",
    "name:fas_x_preferred":[
        "\u0645\u0632\u0631\u0639\u0647 \u062a\u0644\u062e\u06a9"
    ],
    "name:fas_x_variant":[
        "\u0645\u06cc\u062e\u06a9"
    ],
    "name:und_x_variant":[
        "Mazra\u2018eh-ye Talkhak",
        "Talkhak",
        "M\u012bkhak"
    ],
    "wof:name":"Mazra`eh-ye Talkhak",
    "wof:placetype":"locality"
},
  "geometry": {"coordinates":[58.83434000000001,36.16321],"type":"Point"}
}