{
  "type": "Feature",
  "properties": {
    "gn:admin1_code":"34",
    "gn:asciiname":"Zangarak",
    "gn:country_code":"IR",
    "gn:dem":1910,
    "gn:feature_class":"P",
    "gn:feature_code":"PPL",
    "gn:name":"Zang\u0101rak",
    "gn:population":0,
    "gn:timezone":"Asia/Tehran",
    "iso:country":"IR",
    "name:ara_x_preferred":[
        "\u0632\u0646\u063a\u0627\u0631\u0643"
    ],
    "name:ceb_x_preferred":[
        "Zang\u0101rak"
    ],
    "name:fas_x_preferred":[
        "\u0632\u0646\u06af\u0627\u0631\u0643"
    ],
    "name:fas_x_variant":[
        "Zang\u0101rak",
        "\u0632\u0646\u06af\u0627\u0631\u06a9"
    ],
    "name:swe_x_preferred":[
        "Zang\u0101rak"
    ],
    "name:ukr_x_preferred":[
        "\u0417\u0430\u043d\u0434\u0430\u0440\u0430\u043a"
    ],
    "name:und_x_variant":[
        "Zainkarak"
    ],
    "wof:name":"Zangarak",
    "wof:placetype":"locality"
},
  "geometry": {"coordinates":[49.4756,34.6128],"type":"Point"}
}