{
  "type": "Feature",
  "properties": {
    "gn:admin1_code":"35.0",
    "gn:asciiname":"Pichlu",
    "gn:country_code":"IR",
    "gn:dem":1502,
    "gn:feature_class":"P",
    "gn:feature_code":"PPL",
    "gn:name":"P\u012bchl\u016b",
    "gn:population":0,
    "gn:timezone":"Asia/Tehran",
    "iso:country":"IR",
    "name:ceb_x_preferred":[
        "P\u012b Chelow"
    ],
    "name:fas_x_preferred":[
        "\u067e\u06cc \u0686\u0644\u0648"
    ],
    "name:fas_x_variant":[
        "P\u012b Chelow",
        "\u067e\u06cc\u0686\u0644\u0648",
        "\u067e\u06cc\u200c\u0686\u0644\u0648"
    ],
    "name:swe_x_preferred":[
        "P\u012b Chelow"
    ],
    "name:und_x_variant":[
        "P\u012bchl\u016b"
    ],
    "wof:name":"Pichlu",
    "wof:placetype":"locality"
},
  "geometry": {"coordinates":[51.72937,36.36545],"type":"Point"}
}