{
  "type": "Feature",
  "properties": {
    "gn:admin1_code":"9.0",
    "gn:asciiname":"Enjil Baghi",
    "gn:country_code":"IR",
    "gn:dem":1787,
    "gn:feature_class":"P",
    "gn:feature_code":"PPL",
    "gn:name":"Enj\u012bl B\u0101gh\u012b",
    "gn:population":0,
    "gn:timezone":"Asia/Tehran",
    "iso:country":"IR",
    "name:fas_x_preferred":[
        "\u0627\u0646\u062c\u064a\u0631 \u0628\u0627\u063a\u06cc"
    ],
    "name:fas_x_variant":[
        "Anj\u012br B\u0101gh\u012b",
        "\u0627\u0646\u062c\u06cc\u0644 \u0628\u0627\u063a\u06cc"
    ],
    "name:und_x_variant":[
        "Injil B\u0101qi",
        "Enj\u012bl B\u0101gh\u012b"
    ],
    "wof:name":"Enjil Baghi",
    "wof:placetype":"locality"
},
  "geometry": {"coordinates":[48.53163,35.19260999999999],"type":"Point"}
}