{
  "type": "Feature",
  "properties": {
    "gn:admin1_code":"8",
    "gn:asciiname":"Bu'in",
    "gn:country_code":"IR",
    "gn:dem":44,
    "gn:feature_class":"P",
    "gn:feature_code":"PPLL",
    "gn:name":"B\u016b\u2019\u012bn",
    "gn:population":0,
    "gn:timezone":"Asia/Tehran",
    "iso:country":"IR",
    "name:fas_x_preferred":[
        "\u0628\u0648\u0626\u06cc\u0646"
    ],
    "name:fas_x_variant":[
        "B\u016b\u2019\u012bn"
    ],
    "name:und_x_variant":[
        "B\u016b\u2019\u012bn"
    ],
    "wof:name":"Bu'in",
    "wof:placetype":"locality"
},
  "geometry": {"coordinates":[49.28777,37.2276],"type":"Point"}
}