{
  "type": "Feature",
  "properties": {
    "gn:admin1_code":"11",
    "gn:asciiname":"Lavaran",
    "gn:country_code":"IR",
    "gn:dem":19,
    "gn:feature_class":"P",
    "gn:feature_code":"PPL",
    "gn:name":"L\u0101var\u0101n",
    "gn:population":0,
    "gn:timezone":"Asia/Tehran",
    "iso:country":"IR",
    "name:fas_x_preferred":[
        "L\u0101var\u0101n"
    ],
    "name:fas_x_variant":[
        "\u0644\u0627\u0648\u0631\u0627\u0646"
    ],
    "name:und_x_variant":[
        "\u0644\u0627\u0648\u0631\u0627\u0646"
    ],
    "wof:name":"Lavaran",
    "wof:placetype":"locality"
},
  "geometry": {"coordinates":[54.39361,26.77507],"type":"Point"}
}