{
  "type": "Feature",
  "properties": {
    "gn:admin1_code":"8.0",
    "gn:asciiname":"Lasheh Rud",
    "gn:country_code":"IR",
    "gn:dem":298,
    "gn:feature_class":"P",
    "gn:feature_code":"PPL",
    "gn:name":"Lasheh R\u016bd",
    "gn:population":0,
    "gn:timezone":"Asia/Tehran",
    "iso:country":"IR",
    "name:fas_x_preferred":[
        "\u0644\u0634\u0647 \u0631\u0648\u062f"
    ],
    "name:und_x_variant":[
        "Lasheh R\u016bd"
    ],
    "wof:name":"Lasheh Rud",
    "wof:placetype":"locality"
},
  "geometry": {"coordinates":[50.11218,37.15072],"type":"Point"}
}