{
  "type": "Feature",
  "properties": {
    "gn:admin1_code":"1",
    "gn:asciiname":"Taqi Kandi",
    "gn:country_code":"IR",
    "gn:dem":2303,
    "gn:feature_class":"P",
    "gn:feature_code":"PPL",
    "gn:name":"Taq\u012b Kand\u012b",
    "gn:population":0,
    "gn:timezone":"Asia/Tehran",
    "iso:country":"IR",
    "name:fas_x_preferred":[
        "\u062a\u064e\u0642\u06cc \u0643\u064e\u0646\u062f\u06cc"
    ],
    "name:fas_x_variant":[
        "\u062a\u0642\u06cc \u06a9\u0646\u062f\u06cc",
        "Taq\u012b Kand\u012b"
    ],
    "wof:name":"Taqi Kandi",
    "wof:placetype":"locality"
},
  "geometry": {"coordinates":[44.2787,39.0763],"type":"Point"}
}