{
  "type": "Feature",
  "properties": {
    "gn:admin1_code":"28.0",
    "gn:asciiname":"Qarteman",
    "gn:country_code":"IR",
    "gn:dem":1594,
    "gn:feature_class":"P",
    "gn:feature_code":"PPL",
    "gn:name":"Qar\u0163em\u0101n",
    "gn:population":0,
    "gn:timezone":"Asia/Tehran",
    "iso:country":"IR",
    "name:fas_x_preferred":[
        "Qar\u0163em\u0101n"
    ],
    "name:fas_x_variant":[
        "\u0642\u0631\u0637\u0645\u0627\u0646"
    ],
    "name:und_x_variant":[
        "Qar\u0163am\u0101n"
    ],
    "wof:name":"Qarteman",
    "wof:placetype":"locality"
},
  "geometry": {"coordinates":[51.55117,32.64711],"type":"Point"}
}