{
  "type": "Feature",
  "properties": {
    "gn:admin1_code":"10",
    "gn:asciiname":"Sar Choqa",
    "gn:country_code":"IR",
    "gn:dem":928,
    "gn:feature_class":"P",
    "gn:feature_code":"PPL",
    "gn:name":"Sar Choq\u0101",
    "gn:population":0,
    "gn:timezone":"Asia/Tehran",
    "iso:country":"IR",
    "name:ara_x_preferred":[
        "\u0633\u0631\u062a\u0634\u0642\u0627"
    ],
    "name:fas_x_preferred":[
        "\u0633\u0631 \u0686\u063a\u0627 \u0686\u0627\u0644\u0627\u0628 \u0632\u0631\u062f"
    ],
    "name:fas_x_variant":[
        "Sar Choq\u0101 Ch\u0101l\u0101b Zard",
        "Sar Chogh\u0101 Ch\u0101l\u0101b Zard",
        "\u0633\u0631 \u0686\u0642\u0627",
        "\u0633\u0631\u0686\u0642\u0627"
    ],
    "name:msa_x_preferred":[
        "Sar Choqa"
    ],
    "name:und_x_variant":[
        "Sar Choq\u0101"
    ],
    "wof:name":"Sar Choqa",
    "wof:placetype":"locality"
},
  "geometry": {"coordinates":[46.8477,33.6367],"type":"Point"}
}