{
  "type": "Feature",
  "properties": {
    "gn:admin1_code":"37",
    "gn:asciiname":"Jahan Bin",
    "gn:country_code":"IR",
    "gn:dem":84,
    "gn:feature_class":"P",
    "gn:feature_code":"PPL",
    "gn:name":"Jah\u0101n B\u012bn",
    "gn:population":0,
    "gn:timezone":"Asia/Tehran",
    "iso:country":"IR",
    "name:fas_x_preferred":[
        "Jah\u0101n B\u012bn"
    ],
    "name:fas_x_variant":[
        "\u062c\u0647\u0627\u0646 \u0628\u06cc\u0646",
        "Jah\u0101n B\u012bn\u012b",
        "\u062c\u0647\u0627\u0646 \u0628\u064a\u0646\u06cc"
    ],
    "name:und_x_variant":[
        "\u062c\u0647\u0627\u0646 \u0628\u064a\u0646\u06cc"
    ],
    "wof:name":"Jahan Bin",
    "wof:placetype":"locality"
},
  "geometry": {"coordinates":[54.7307,36.95938],"type":"Point"}
}