{
  "type": "Feature",
  "properties": {
    "gn:admin1_code":"28",
    "gn:asciiname":"Sorkhabad",
    "gn:country_code":"IR",
    "gn:dem":2078,
    "gn:feature_class":"P",
    "gn:feature_code":"PPL",
    "gn:name":"Sorkh\u0101b\u0101d",
    "gn:population":0,
    "gn:timezone":"Asia/Tehran",
    "iso:country":"IR",
    "name:fas_x_preferred":[
        "\u0633\u0631\u062e \u0622\u0628\u0627\u062f"
    ],
    "name:fas_x_variant":[
        "Sorkh\u0101b\u0101d"
    ],
    "wof:name":"Sorkhabad",
    "wof:placetype":"locality"
},
  "geometry": {"coordinates":[52.6801,32.9381],"type":"Point"}
}