{
  "type": "Feature",
  "properties": {
    "gn:admin1_code":"34",
    "gn:asciiname":"Darreh Shur",
    "gn:country_code":"IR",
    "gn:dem":2041,
    "gn:feature_class":"P",
    "gn:feature_code":"PPL",
    "gn:name":"Darreh Sh\u016br",
    "gn:population":0,
    "gn:timezone":"Asia/Tehran",
    "iso:country":"IR",
    "name:fas_x_preferred":[
        "\u062f\u0631\u0647 \u0634\u0648\u0631"
    ],
    "name:fas_x_variant":[
        "Darreh Sh\u016br"
    ],
    "wof:name":"Darreh Shur",
    "wof:placetype":"locality"
},
  "geometry": {"coordinates":[49.93017,33.76703],"type":"Point"}
}