{
  "type": "Feature",
  "properties": {
    "gn:admin1_code":"11",
    "gn:asciiname":"Durbini",
    "gn:country_code":"IR",
    "gn:dem":18,
    "gn:feature_class":"P",
    "gn:feature_code":"PPL",
    "gn:name":"D\u016brb\u012bn\u012b",
    "gn:population":0,
    "gn:timezone":"Asia/Tehran",
    "iso:country":"IR",
    "name:ceb_x_preferred":[
        "D\u016brb\u012bn\u012b"
    ],
    "name:fas_x_preferred":[
        "\u062f\u0648\u0631\u0628\u0646\u06cc"
    ],
    "name:fas_x_variant":[
        "D\u016brben\u012b",
        "\u062f\u0648\u0631\u0628\u064a\u0646\u06cc"
    ],
    "name:msa_x_preferred":[
        "Durbeni"
    ],
    "name:swe_x_preferred":[
        "D\u016brb\u012bn\u012b"
    ],
    "name:und_x_variant":[
        "D\u016brbon\u012b",
        "D\u016brb\u012bn\u012b"
    ],
    "wof:name":"Durbini",
    "wof:placetype":"locality"
},
  "geometry": {"coordinates":[55.6615,26.7395],"type":"Point"}
}