{
  "type": "Feature",
  "properties": {
    "gn:admin1_code":"32.0",
    "gn:asciiname":"Ibli-ye `Olya",
    "gn:country_code":"IR",
    "gn:dem":1569,
    "gn:feature_class":"P",
    "gn:feature_code":"PPL",
    "gn:name":"\u012abl\u012b-ye \u2018Oly\u0101",
    "gn:population":0,
    "gn:timezone":"Asia/Tehran",
    "iso:country":"IR",
    "name:fas_x_preferred":[
        "\u0627\u0628\u0644\u06cc \u0639\u0644\u06cc\u0627"
    ],
    "name:fas_x_variant":[
        "Ebl\u012b-ye \u2018Oly\u0101",
        "\u0627\u06cc\u0628\u0644\u06cc \u0639\u0644\u06cc\u0627"
    ],
    "name:msa_x_preferred":[
        "Ebli-ye Olya"
    ],
    "name:und_x_variant":[
        "Abl\u012b-ye B\u0101l\u0101",
        "Ibli-Ulya",
        "Ebell\u012b \u2018Oly\u0101",
        "Ibli Ulia",
        "\u012abl\u012b-ye \u2018Oly\u0101"
    ],
    "wof:name":"Ibli-ye `Olya",
    "wof:placetype":"locality"
},
  "geometry": {"coordinates":[48.23693,37.75245],"type":"Point"}
}