{
  "type": "Feature",
  "properties": {
    "gn:admin1_code":"32",
    "gn:asciiname":"Dasht Andar",
    "gn:country_code":"IR",
    "gn:dem":1804,
    "gn:feature_class":"P",
    "gn:feature_code":"PPL",
    "gn:name":"Dasht Andar",
    "gn:population":0,
    "gn:timezone":"Asia/Tehran",
    "iso:country":"IR",
    "name:fas_x_preferred":[
        "\u062f\u0634\u062a \u0627\u0646\u062f\u0631"
    ],
    "name:msa_x_preferred":[
        "Dasht Andar"
    ],
    "wof:name":"Dasht Andar",
    "wof:placetype":"locality"
},
  "geometry": {"coordinates":[48.75601,37.22727],"type":"Point"}
}