{
  "type": "Feature",
  "properties": {
    "gn:admin1_code":"4",
    "gn:asciiname":"Bon Kel",
    "gn:country_code":"IR",
    "gn:dem":777,
    "gn:feature_class":"P",
    "gn:feature_code":"PPL",
    "gn:name":"Bon Kel",
    "gn:population":0,
    "gn:timezone":"Asia/Tehran",
    "iso:country":"IR",
    "name:fas_x_preferred":[
        "\u0628\u0646 \u06a9\u0644"
    ],
    "wof:name":"Bon Kel",
    "wof:placetype":"locality"
},
  "geometry": {"coordinates":[59.51523,27.90493],"type":"Point"}
}