{
  "type": "Feature",
  "properties": {
    "iso:country":"IR",
    "name:ara_x_preferred":[
        "\u0642\u0631\u0648\u0647"
    ],
    "name:azb_x_preferred":[
        "\u0642\u0648\u0631\u0648\u0647"
    ],
    "name:aze_x_preferred":[
        "Q\u00fcrv\u0259"
    ],
    "name:ckb_x_preferred":[
        "\u0642\u0648\u0631\u0648\u06d5"
    ],
    "name:fas_x_preferred":[
        "\u0642\u0631\u0648\u0647"
    ],
    "name:hin_x_preferred":[
        "\u0915\u094b\u0930\u094d\u0935\u0947"
    ],
    "name:ita_x_preferred":[
        "Qorveh"
    ],
    "name:kur_x_preferred":[
        "Qurwe"
    ],
    "name:mlg_x_preferred":[
        "Qorveh"
    ],
    "name:pnb_x_preferred":[
        "\u0642\u0631\u0648\u06c1"
    ],
    "name:pol_x_preferred":[
        "Ghorwe"
    ],
    "name:ron_x_preferred":[
        "Qorveh"
    ],
    "name:rus_x_preferred":[
        "\u041a\u043e\u0440\u0432\u0435"
    ],
    "name:tgk_x_preferred":[
        "\u049a\u0443\u0440\u0432\u0430"
    ],
    "name:tur_x_preferred":[
        "Gurve"
    ],
    "name:unk_x_variant":[
        "Qurve"
    ],
    "name:urd_x_preferred":[
        "\u0642\u0631\u0648\u06c1"
    ],
    "name:zho_x_preferred":[
        "\u6208\u723e\u97cb"
    ],
    "qs:gn_country":"IR",
    "qs:gn_fcode":"PPL",
    "qs:gn_pop":87953,
    "qs:name":"Qorveh",
    "qs:name_adm0":"Iran",
    "qs:name_adm1":"Kordestan",
    "qs:photos":0,
    "qs:photos_1k":0,
    "qs:photos_9k":1,
    "qs:photos_9r":1,
    "qs:photos_all":1,
    "qs:photos_sr":0,
    "qs:placetype":"Town",
    "qs:pop_sr":"8",
    "qs:woe_adm0":23424851,
    "wd:wordcount":312,
    "wof:name":"Qorveh",
    "wof:placetype":"locality",
    "wof:population":87953
},
  "geometry": {"coordinates":[47.8045,35.1664],"type":"Point"}
}