{
  "type": "Feature",
  "properties": {
    "gn:admin1_code":"42",
    "gn:asciiname":"Bidvey",
    "gn:country_code":"IR",
    "gn:dem":1723,
    "gn:feature_class":"P",
    "gn:feature_code":"PPL",
    "gn:name":"B\u012bdvey",
    "gn:population":0,
    "gn:timezone":"Asia/Tehran",
    "iso:country":"IR",
    "name:fas_x_preferred":[
        "\u0628\u06cc\u062f\u0648\u06cc"
    ],
    "name:fas_x_variant":[
        "B\u012bdvey"
    ],
    "wof:name":"Bidvey",
    "wof:placetype":"locality"
},
  "geometry": {"coordinates":[59.97745,35.08023],"type":"Point"}
}