{
  "type": "Feature",
  "properties": {
    "gn:admin1_code":"7",
    "gn:asciiname":"Kheyrabad",
    "gn:country_code":"IR",
    "gn:dem":1338,
    "gn:feature_class":"P",
    "gn:feature_code":"PPL",
    "gn:name":"Kheyr\u0101b\u0101d",
    "gn:population":0,
    "gn:timezone":"Asia/Tehran",
    "iso:country":"IR",
    "name:fas_x_preferred":[
        "\u062e\u06cc\u0631 \u0622\u0628\u0627\u062f"
    ],
    "name:fas_x_variant":[
        "Kheyr\u0101b\u0101d-e \u1e28\u016bmeh",
        "Kheyr\u0101b\u0101d"
    ],
    "wof:name":"Kheyrabad",
    "wof:placetype":"locality"
},
  "geometry": {"coordinates":[53.67426999999999,28.91593],"type":"Point"}
}