{
  "type": "Feature",
  "properties": {
    "gn:admin1_code":"29",
    "gn:asciiname":"Qanat Chamran",
    "gn:country_code":"IR",
    "gn:dem":2686,
    "gn:feature_class":"P",
    "gn:feature_code":"PPL",
    "gn:name":"Qan\u0101t Chamr\u0101n",
    "gn:population":0,
    "gn:timezone":"Asia/Tehran",
    "iso:country":"IR",
    "name:fas_x_preferred":[
        "\u0642\u0646\u0627\u062a \u0686\u0645\u0631\u0627\u0646"
    ],
    "name:fas_x_variant":[
        "Qan\u0101t Chamr\u0101n"
    ],
    "wof:name":"Qanat Chamran",
    "wof:placetype":"locality"
},
  "geometry": {"coordinates":[56.7627,29.3093],"type":"Point"}
}