{
  "type": "Feature",
  "properties": {
    "gn:admin1_code":"7",
    "gn:asciiname":"Shahrak-e Hajji Tahereh",
    "gn:country_code":"IR",
    "gn:dem":1021,
    "gn:feature_class":"P",
    "gn:feature_code":"PPL",
    "gn:name":"Shahrak-e \u1e28\u0101jj\u012b \u0162\u0101hereh",
    "gn:population":0,
    "gn:timezone":"Asia/Tehran",
    "iso:country":"IR",
    "name:fas_x_preferred":[
        "\u0634\u0647\u0631\u0643 \u062d\u0627\u062c\u06cc \u0637\u0627\u0647\u0631\u0647"
    ],
    "name:fas_x_variant":[
        "Shahrak-e \u1e28\u0101jj\u012b \u0162\u0101hereh"
    ],
    "wof:name":"Shahrak-e Hajji Tahereh",
    "wof:placetype":"locality"
},
  "geometry": {"coordinates":[54.5429,28.3514],"type":"Point"}
}