{
  "type": "Feature",
  "properties": {
    "gn:admin1_code":"26.0",
    "gn:asciiname":"Hasanabad-e Khaleseh",
    "gn:country_code":"IR",
    "gn:dem":1102,
    "gn:feature_class":"P",
    "gn:feature_code":"PPL",
    "gn:name":"\u1e28asan\u0101b\u0101d-e Kh\u0101le\u015feh",
    "gn:population":0,
    "gn:timezone":"Asia/Tehran",
    "iso:country":"IR",
    "name:ara_x_preferred":[
        "\u062d\u0633\u0646\u200c\u0622\u0628\u0627\u062f \u062e\u0627\u0644\u0635\u0629"
    ],
    "name:fas_x_preferred":[
        "\u062d\u064e\u0633\u064e\u0646\u0627\u0628\u0627\u062f\u0650 \u062e\u0627\u0644\u0650\u0635\u0650\u0647"
    ],
    "name:fas_x_variant":[
        "\u062d\u064e\u0633\u064e\u0646 \u0622\u0628\u0627\u062f",
        "\u062d\u0633\u0646 \u0622\u0628\u0627\u062f \u062e\u0627\u0644\u0635\u0647",
        "\u1e28asan\u0101b\u0101d-e Kh\u0101le\u015feh",
        "\u062d\u0633\u0646\u200c\u0622\u0628\u0627\u062f \u062e\u0627\u0644\u0635\u0647"
    ],
    "name:und_x_variant":[
        "\u1e28asan\u0101b\u0101d"
    ],
    "wof:name":"Hasanabad-e Khaleseh",
    "wof:placetype":"locality"
},
  "geometry": {"coordinates":[51.20079000000001,35.61349000000001],"type":"Point"}
}