{
  "type": "Feature",
  "properties": {
    "gn:admin1_code":"4.0",
    "gn:asciiname":"Deh-e Nur Mohammad Khan",
    "gn:country_code":"IR",
    "gn:dem":479,
    "gn:feature_class":"P",
    "gn:feature_code":"PPL",
    "gn:name":"Deh-e N\u016br Mo\u1e29ammad Kh\u0101n",
    "gn:population":0,
    "gn:timezone":"Asia/Tehran",
    "iso:country":"IR",
    "name:fas_x_preferred":[
        "Deh-e N\u016br Mo\u1e29ammad"
    ],
    "name:fas_x_variant":[
        "N\u016br Mo\u1e29ammad Kh\u0101n",
        "\u062f\u0647 \u0646\u0648\u0631 \u0645\u062d\u0645\u0651\u062f \u062e\u0627\u0646",
        "Deh-e N\u016br Mo\u1e29ammad Kh\u0101n"
    ],
    "name:und_x_variant":[
        "Deh-e N\u016br Mo\u1e29ammad Kh\u0101n"
    ],
    "wof:name":"Deh-e Nur Mohammad Khan",
    "wof:placetype":"locality"
},
  "geometry": {"coordinates":[61.7618,31.2135],"type":"Point"}
}