{
  "type": "Feature",
  "properties": {
    "gn:admin1_code":"32",
    "gn:asciiname":"Barezil",
    "gn:country_code":"IR",
    "gn:dem":1230,
    "gn:feature_class":"P",
    "gn:feature_code":"PPL",
    "gn:name":"B\u0101rez\u012bl",
    "gn:population":0,
    "gn:timezone":"Asia/Tehran",
    "iso:country":"IR",
    "name:ceb_x_preferred":[
        "B\u0101rez\u012bl"
    ],
    "name:fas_x_preferred":[
        "\u0628\u0627\u0631\u0632\u064a\u0644"
    ],
    "name:fas_x_variant":[
        "B\u0101rez\u012bl",
        "\u0628\u0627\u0631\u0632\u06cc\u0644"
    ],
    "name:msa_x_preferred":[
        "Barezil"
    ],
    "name:mzn_x_preferred":[
        "\u0628\u0627\u0631\u0632\u06cc\u0644"
    ],
    "name:swe_x_preferred":[
        "B\u0101rez\u012bl"
    ],
    "name:und_x_variant":[
        "B\u0101zer\u012bl"
    ],
    "wof:name":"Barezil",
    "wof:placetype":"locality"
},
  "geometry": {"coordinates":[47.6786,38.44346],"type":"Point"}
}