{
  "type": "Feature",
  "properties": {
    "gn:admin1_code":"41",
    "gn:asciiname":"Chah-e Mir Shams",
    "gn:country_code":"IR",
    "gn:dem":2043,
    "gn:feature_class":"P",
    "gn:feature_code":"PPLF",
    "gn:name":"Ch\u0101h-e M\u012br Shams",
    "gn:population":0,
    "gn:timezone":"Asia/Tehran",
    "iso:country":"IR",
    "name:fas_x_preferred":[
        "Ch\u0101h-e M\u012br Sh\u0101in"
    ],
    "name:fas_x_variant":[
        "\u0686\u0627\u0647 \u0645\u064a\u0631 \u0634\u0645\u0633"
    ],
    "name:und_x_variant":[
        "Ch\u0101h-i-M\u012br-Sh\u0101in",
        "Ch\u0101h-e M\u012br Shams"
    ],
    "wof:name":"Chah-e Mir Shams",
    "wof:placetype":"locality"
},
  "geometry": {"coordinates":[59.92256,32.6283],"type":"Point"}
}