{
  "type": "Feature",
  "properties": {
    "gn:admin1_code":"15",
    "gn:asciiname":"Shomus",
    "gn:country_code":"IR",
    "gn:dem":10,
    "gn:feature_class":"P",
    "gn:feature_code":"PPL",
    "gn:name":"Shom\u016bs",
    "gn:population":0,
    "gn:timezone":"Asia/Tehran",
    "iso:country":"IR",
    "name:fas_x_preferred":[
        "\u0634\u0645\u0648\u0633"
    ],
    "name:fas_x_variant":[
        "Neheyr\u0101t Va Shom\u016bs",
        "Shom\u016bs"
    ],
    "wof:name":"Shomus",
    "wof:placetype":"locality"
},
  "geometry": {"coordinates":[48.0135,31.5536],"type":"Point"}
}