{
  "type": "Feature",
  "properties": {
    "gn:admin1_code":"10.0",
    "gn:asciiname":"Kharani",
    "gn:country_code":"IR",
    "gn:dem":1211,
    "gn:feature_class":"P",
    "gn:feature_code":"PPL",
    "gn:name":"Khar\u0101n\u012b",
    "gn:population":0,
    "gn:timezone":"Asia/Tehran",
    "iso:country":"IR",
    "name:fas_x_preferred":[
        "\u062e\u0631\u0627\u0646\u06cc"
    ],
    "name:fas_x_variant":[
        "Khar\u0101n\u012b"
    ],
    "wof:name":"Kharani",
    "wof:placetype":"locality"
},
  "geometry": {"coordinates":[46.2552,33.818],"type":"Point"}
}