{
  "type": "Feature",
  "properties": {
    "gn:admin1_code":"35",
    "gn:asciiname":"Darvar",
    "gn:country_code":"IR",
    "gn:dem":166,
    "gn:feature_class":"P",
    "gn:feature_code":"PPL",
    "gn:name":"Darv\u0101r",
    "gn:population":0,
    "gn:timezone":"Asia/Tehran",
    "iso:country":"IR",
    "name:fas_x_preferred":[
        "\u062f\u0631\u0648\u0627\u0631"
    ],
    "name:fas_x_variant":[
        "Darw\u0101r",
        "Darv\u0101r"
    ],
    "wof:name":"Darvar",
    "wof:placetype":"locality"
},
  "geometry": {"coordinates":[53.08231,36.44994000000001],"type":"Point"}
}