{
  "type": "Feature",
  "properties": {
    "gn:admin1_code":"16",
    "gn:asciiname":"Yangeh Kand",
    "gn:country_code":"IR",
    "gn:dem":1697,
    "gn:feature_class":"P",
    "gn:feature_code":"PPL",
    "gn:name":"Yangeh Kand",
    "gn:population":0,
    "gn:timezone":"Asia/Tehran",
    "iso:country":"IR",
    "name:fas_x_preferred":[
        "\u064a\u0650\u0646\u06af\u064a\u062e\u0650\u0646\u062f"
    ],
    "name:fas_x_variant":[
        "\u0646\u06cc\u06a9\u06cc \u06a9\u0646\u062f",
        "Yeng\u012b Kand\u012b",
        "N\u012bk\u012b Kand",
        "\u064a\u0650\u0646\u06af\u06cc \u0643\u064e\u0646\u062f\u06cc",
        "\u06cc\u0646\u06af\u0647 \u06a9\u0646\u062f",
        "\u06cc\u0646\u06af\u06cc \u06a9\u0646\u062f"
    ],
    "name:und_x_variant":[
        "Yeng\u012bkhend",
        "Yangeh Kand",
        "Yeng\u012b Kand"
    ],
    "wof:name":"Yangeh Kand",
    "wof:placetype":"locality"
},
  "geometry": {"coordinates":[48.07218,35.74213],"type":"Point"}
}