{
  "type": "Feature",
  "properties": {
    "gn:admin1_code":"42.0",
    "gn:asciiname":"Khalili",
    "gn:country_code":"IR",
    "gn:dem":788,
    "gn:feature_class":"P",
    "gn:feature_code":"PPL",
    "gn:name":"Khal\u012bl\u012b",
    "gn:population":0,
    "gn:timezone":"Asia/Tehran",
    "iso:country":"IR",
    "name:fas_x_preferred":[
        "\u062e\u0644\u06cc\u0644\u06cc"
    ],
    "name:fas_x_variant":[
        "Khal\u012bl\u012bh\u0101",
        "Khal\u012bl\u012b"
    ],
    "wof:name":"Khalili",
    "wof:placetype":"locality"
},
  "geometry": {"coordinates":[60.86578000000001,35.11585],"type":"Point"}
}