{
  "type": "Feature",
  "properties": {
    "gn:admin1_code":"7",
    "gn:asciiname":"Koturi",
    "gn:country_code":"IR",
    "gn:dem":1989,
    "gn:feature_class":"P",
    "gn:feature_code":"PPL",
    "gn:name":"Kot\u016br\u012b",
    "gn:population":0,
    "gn:timezone":"Asia/Tehran",
    "iso:country":"IR",
    "name:fas_x_preferred":[
        "\u06a9\u062a\u0648\u0631\u06cc"
    ],
    "name:fas_x_variant":[
        "Kot\u016br\u012b"
    ],
    "wof:name":"Koturi",
    "wof:placetype":"locality"
},
  "geometry": {"coordinates":[53.3586,29.9905],"type":"Point"}
}