{
  "type": "Feature",
  "properties": {
    "gn:admin1_code":"15",
    "gn:asciiname":"Shekar Ab",
    "gn:country_code":"IR",
    "gn:dem":177,
    "gn:feature_class":"P",
    "gn:feature_code":"PPL",
    "gn:name":"Shekar \u0100b",
    "gn:population":0,
    "gn:timezone":"Asia/Tehran",
    "iso:country":"IR",
    "name:fas_x_preferred":[
        "\u0634\u06a9\u0631 \u0622\u0628\u0627\u062f"
    ],
    "name:fas_x_variant":[
        "Shekar \u0100b",
        "Shokr\u0101b\u0101d",
        "\u0634\u06a9\u0631 \u0622\u0628"
    ],
    "wof:name":"Shekar Ab",
    "wof:placetype":"locality"
},
  "geometry": {"coordinates":[49.23595,31.85698],"type":"Point"}
}