{
  "type": "Feature",
  "properties": {
    "gn:admin1_code":"29",
    "gn:asciiname":"Chah-e Dazu",
    "gn:country_code":"IR",
    "gn:dem":377,
    "gn:feature_class":"P",
    "gn:feature_code":"PPL",
    "gn:name":"Ch\u0101h-e D\u0101z\u016b",
    "gn:population":0,
    "gn:timezone":"Asia/Tehran",
    "iso:country":"IR",
    "name:ara_x_preferred":[
        "\u062a\u0634\u0627\u0629 \u062f\u0627\u0632\u0648"
    ],
    "name:fas_x_preferred":[
        "\u0686\u0627\u0647 \u062f\u0627\u0632\u0648"
    ],
    "name:fas_x_variant":[
        "Ch\u0101h-e D\u0101z\u016b"
    ],
    "wof:name":"Chah-e Dazu",
    "wof:placetype":"locality"
},
  "geometry": {"coordinates":[58.90868,27.6861],"type":"Point"}
}