{
  "type": "Feature",
  "properties": {
    "gn:admin1_code":"42.0",
    "gn:asciiname":"Golzar",
    "gn:country_code":"IR",
    "gn:dem":460,
    "gn:feature_class":"P",
    "gn:feature_code":"PPL",
    "gn:name":"Golz\u0101r",
    "gn:population":0,
    "gn:timezone":"Asia/Tehran",
    "iso:country":"IR",
    "name:fas_x_preferred":[
        "Tappeh Soleym\u0101n"
    ],
    "name:fas_x_variant":[
        "Golz\u0101r",
        "\u06af\u0644\u0632\u0627\u0631"
    ],
    "wof:name":"Golzar",
    "wof:placetype":"locality"
},
  "geometry": {"coordinates":[60.91659,36.20882],"type":"Point"}
}