{
  "type": "Feature",
  "properties": {
    "gn:admin1_code":"8.0",
    "gn:asciiname":"Mianeh Sara-ye Pa'in",
    "gn:country_code":"IR",
    "gn:dem":1637,
    "gn:feature_class":"P",
    "gn:feature_code":"PPL",
    "gn:name":"M\u012b\u0101neh Sar\u0101-ye P\u0101\u2019\u012bn",
    "gn:population":0,
    "gn:timezone":"Asia/Tehran",
    "iso:country":"IR",
    "name:fas_x_preferred":[
        "M\u012b\u0101neh Sar\u0101"
    ],
    "name:fas_x_variant":[
        "\u0645\u06cc\u0627\u0646\u0647 \u0633\u0631\u0627",
        "\u0645\u06cc\u0627\u0646\u0647 \u0633\u0631\u0627 \u067e\u0627\u06cc\u06cc\u0646"
    ],
    "name:und_x_variant":[
        "M\u012b\u0101neh Sar\u0101-ye P\u0101\u2019\u012bn"
    ],
    "wof:name":"Mianeh Sara-ye Pa'in",
    "wof:placetype":"locality"
},
  "geometry": {"coordinates":[49.77774,36.89743],"type":"Point"}
}