{
  "type": "Feature",
  "properties": {
    "gn:admin1_code":"8",
    "gn:asciiname":"Ashkal-e Bala",
    "gn:country_code":"IR",
    "gn:dem":472,
    "gn:feature_class":"P",
    "gn:feature_code":"PPL",
    "gn:name":"Ashk\u0101l-e B\u0101l\u0101",
    "gn:population":0,
    "gn:timezone":"Asia/Tehran",
    "iso:country":"IR",
    "name:fas_x_preferred":[
        "Ashk\u0101l"
    ],
    "name:fas_x_variant":[
        "\u0627\u0634\u06a9\u0627\u0644",
        "\u0627\u0634\u06a9\u0627\u0644 \u0628\u0627\u0644\u0627"
    ],
    "name:fra_x_preferred":[
        "Ashkal"
    ],
    "name:msa_x_preferred":[
        "Ashkal"
    ],
    "name:ukr_x_preferred":[
        "\u0410\u0448\u043a\u0430\u043b"
    ],
    "name:und_x_variant":[
        "Ashk\u0101l\u012b",
        "Ashk\u0101l-e B\u0101l\u0101"
    ],
    "wof:name":"Ashkal-e Bala",
    "wof:placetype":"locality"
},
  "geometry": {"coordinates":[49.98186,37.08467],"type":"Point"}
}