{
  "type": "Feature",
  "properties": {
    "gn:admin1_code":"1",
    "gn:asciiname":"Emam Kandi",
    "gn:country_code":"IR",
    "gn:dem":1177,
    "gn:feature_class":"P",
    "gn:feature_code":"PPL",
    "gn:name":"Em\u0101m Kand\u012b",
    "gn:population":0,
    "gn:timezone":"Asia/Tehran",
    "iso:country":"IR",
    "name:fas_x_preferred":[
        "\u0627\u0645\u0627\u0645 \u06a9\u0646\u062f\u06cc"
    ],
    "name:fas_x_variant":[
        "Em\u0101m Kand\u012b"
    ],
    "wof:name":"Emam Kandi",
    "wof:placetype":"locality"
},
  "geometry": {"coordinates":[44.9417,38.4737],"type":"Point"}
}