{
  "type": "Feature",
  "properties": {
    "gn:admin1_code":"22",
    "gn:asciiname":"Geda'i",
    "gn:country_code":"IR",
    "gn:dem":23,
    "gn:feature_class":"P",
    "gn:feature_code":"PPL",
    "gn:name":"Ged\u0101\u2019\u012b",
    "gn:population":0,
    "gn:timezone":"Asia/Tehran",
    "iso:country":"IR",
    "name:fas_x_preferred":[
        "\u0643\u0650\u062f\u0627\u0626\u06cc"
    ],
    "name:fas_x_variant":[
        "\u0643\u064e\u062f\u0627\u0626\u06cc",
        "\u06af\u062f\u0627\u0626\u06cc",
        "Ked\u0101\u2019\u012b",
        "Ged\u0101\u2019\u012b"
    ],
    "name:und_x_variant":[
        "Kad\u0101\u2019\u012b"
    ],
    "wof:name":"Geda'i",
    "wof:placetype":"locality"
},
  "geometry": {"coordinates":[50.7558,29.5689],"type":"Point"}
}