{
  "type": "Feature",
  "properties": {
    "gn:admin1_code":"33",
    "gn:asciiname":"Guzi Dagh",
    "gn:country_code":"IR",
    "gn:dem":1332,
    "gn:feature_class":"P",
    "gn:feature_code":"PPL",
    "gn:name":"G\u016bz\u012b D\u0101gh",
    "gn:population":0,
    "gn:timezone":"Asia/Tehran",
    "iso:country":"IR",
    "name:fas_x_preferred":[
        "G\u016bz\u012b D\u0101gh"
    ],
    "wof:name":"Guzi Dagh",
    "wof:placetype":"locality"
},
  "geometry": {"coordinates":[45.55,37.85],"type":"Point"}
}