{
  "type": "Feature",
  "properties": {
    "gn:admin1_code":"32",
    "gn:asciiname":"Chatmeh",
    "gn:country_code":"IR",
    "gn:dem":437,
    "gn:feature_class":"P",
    "gn:feature_code":"PPL",
    "gn:name":"Ch\u0101tmeh",
    "gn:population":0,
    "gn:timezone":"Asia/Tehran",
    "iso:country":"IR",
    "name:fas_x_preferred":[
        "\u0686\u0627\u062a\u0645\u0650\u0647"
    ],
    "name:fas_x_variant":[
        "Ch\u0101tmeh"
    ],
    "wof:name":"Chatmeh",
    "wof:placetype":"locality"
},
  "geometry": {"coordinates":[47.83333,39.28333],"type":"Point"}
}