{
  "type": "Feature",
  "properties": {
    "gn:admin1_code":"29",
    "gn:asciiname":"Khaleqabad",
    "gn:cc2":"IR",
    "gn:country_code":"IR",
    "gn:dem":2426,
    "gn:feature_class":"P",
    "gn:feature_code":"PPL",
    "gn:name":"Kh\u0101leq\u0101b\u0101d",
    "gn:population":0,
    "gn:timezone":"Asia/Tehran",
    "iso:country":"IR",
    "name:fas_x_preferred":[
        "\u062e\u0627\u0644\u0650\u0642 \u0622\u0628\u0627\u062f"
    ],
    "name:fas_x_variant":[
        "\u062e\u0627\u0644\u064a\u0642 \u0622\u0628\u0627\u062f",
        "Kh\u0101leq\u0101b\u0101d"
    ],
    "name:und_x_variant":[
        "Kh\u0101l\u012bq\u0101b\u0101d"
    ],
    "wof:name":"Khaleqabad",
    "wof:placetype":"locality"
},
  "geometry": {"coordinates":[57.36666999999999,29.58333],"type":"Point"}
}