{
  "type": "Feature",
  "properties": {
    "gn:admin1_code":"41",
    "gn:asciiname":"Now Kaj",
    "gn:country_code":"IR",
    "gn:dem":1968,
    "gn:feature_class":"P",
    "gn:feature_code":"PPL",
    "gn:name":"Now K\u0101j",
    "gn:population":0,
    "gn:timezone":"Asia/Tehran",
    "iso:country":"IR",
    "name:fas_x_preferred":[
        "Now K\u0101j"
    ],
    "name:fas_x_variant":[
        "\u0646\u0648\u06a9\u0627\u062c",
        "N\u016bk\u0101j",
        "\u0646\u0648\u0631\u0634\u06a9"
    ],
    "name:und_x_variant":[
        "N\u016bk\u0101j",
        "\u0646\u0648\u06a9\u0627\u062c",
        "Nowrashk"
    ],
    "wof:name":"Now Kaj",
    "wof:placetype":"locality"
},
  "geometry": {"coordinates":[59.30601,32.66698],"type":"Point"}
}