{
  "type": "Feature",
  "properties": {
    "gn:admin1_code":"23",
    "gn:asciiname":"Luneh Shahi",
    "gn:country_code":"IR",
    "gn:dem":1289,
    "gn:feature_class":"P",
    "gn:feature_code":"PPL",
    "gn:name":"L\u016bneh Sh\u0101h\u012b",
    "gn:population":0,
    "gn:timezone":"Asia/Tehran",
    "iso:country":"IR",
    "name:fas_x_preferred":[
        "\u0644\u0648\u0646\u0647 \u0634\u0627\u0647\u06cc"
    ],
    "name:fas_x_variant":[
        "L\u016bneh Sh\u0101h\u012b"
    ],
    "wof:name":"Luneh Shahi",
    "wof:placetype":"locality"
},
  "geometry": {"coordinates":[48.9457,33.1643],"type":"Point"}
}