{
  "type": "Feature",
  "properties": {
    "gn:admin1_code":"13",
    "gn:asciiname":"Muli",
    "gn:country_code":"IR",
    "gn:dem":1464,
    "gn:feature_class":"P",
    "gn:feature_code":"PPL",
    "gn:name":"M\u016bl\u012b",
    "gn:population":0,
    "gn:timezone":"Asia/Tehran",
    "iso:country":"IR",
    "name:ceb_x_preferred":[
        "Muli"
    ],
    "name:deu_x_preferred":[
        "Muli"
    ],
    "name:div_x_preferred":[
        "\u0789\u07aa\u078d\u07a8"
    ],
    "name:fas_x_preferred":[
        "\u0645\u0648\u0644\u0648"
    ],
    "name:fas_x_variant":[
        "M\u016bl\u012b",
        "M\u016bl\u016b",
        "\u0645\u0648\u0644\u06cc"
    ],
    "name:nld_x_preferred":[
        "Muli"
    ],
    "name:swe_x_preferred":[
        "Muli"
    ],
    "wof:name":"Muli",
    "wof:placetype":"locality"
},
  "geometry": {"coordinates":[47.29837,33.86079],"type":"Point"}
}