{
  "type": "Feature",
  "properties": {
    "gn:admin1_code":"4.0",
    "gn:asciiname":"Kahir-e Hutan",
    "gn:country_code":"IR",
    "gn:dem":21,
    "gn:feature_class":"P",
    "gn:feature_code":"PPL",
    "gn:name":"Kah\u012br-e H\u016bt\u0101n",
    "gn:population":0,
    "gn:timezone":"Asia/Tehran",
    "iso:country":"IR",
    "name:fas_x_preferred":[
        "Kah\u012br-e H\u016bt\u0101n"
    ],
    "wof:name":"Kahir-e Hutan",
    "wof:placetype":"locality"
},
  "geometry": {"coordinates":[60.13333000000001,25.58333],"type":"Point"}
}