{
  "type": "Feature",
  "properties": {
    "gn:admin1_code":"26.0",
    "gn:asciiname":"Cheshmehha",
    "gn:country_code":"IR",
    "gn:dem":1631,
    "gn:feature_class":"P",
    "gn:feature_code":"PPLF",
    "gn:name":"Cheshmehh\u0101",
    "gn:population":0,
    "gn:timezone":"Asia/Tehran",
    "iso:country":"IR",
    "name:ara_x_preferred":[
        "\u062c\u0634\u0645\u0629 \u0647\u0627"
    ],
    "name:fas_x_preferred":[
        "\u0686\u0650\u0634\u0645\u0650\u0647\u0651\u0627"
    ],
    "name:fas_x_variant":[
        "Cheshmehh\u0101",
        "\u0686\u0634\u0645\u0647 \u0647\u0627",
        "\u0686\u0634\u0645\u0647\u200c\u0647\u0627"
    ],
    "wof:name":"Cheshmehha",
    "wof:placetype":"locality"
},
  "geometry": {"coordinates":[51.89919,35.66768],"type":"Point"}
}