{
  "type": "Feature",
  "properties": {
    "gn:admin1_code":"4.0",
    "gn:asciiname":"Gholam Heydar",
    "gn:country_code":"IR",
    "gn:dem":486,
    "gn:feature_class":"P",
    "gn:feature_code":"PPL",
    "gn:name":"Ghol\u0101m \u1e28eydar",
    "gn:population":0,
    "gn:timezone":"Asia/Tehran",
    "iso:country":"IR",
    "name:fas_x_preferred":[
        "\u063a\u0644\u0627\u0645 \u062d\u06cc\u062f\u0631"
    ],
    "name:fas_x_variant":[
        "Ghol\u0101m \u1e28eydar"
    ],
    "wof:name":"Gholam Heydar",
    "wof:placetype":"locality"
},
  "geometry": {"coordinates":[61.6548,30.9517],"type":"Point"}
}