{
  "type": "Feature",
  "properties": {
    "gn:admin1_code":"23",
    "gn:asciiname":"`Araban",
    "gn:country_code":"IR",
    "gn:dem":1160,
    "gn:feature_class":"P",
    "gn:feature_code":"PPL",
    "gn:name":"\u2018Arab\u0101n",
    "gn:population":0,
    "gn:timezone":"Asia/Tehran",
    "iso:country":"IR",
    "name:fas_x_preferred":[
        "\u0639\u0631\u0628\u0627\u0646"
    ],
    "name:fas_x_variant":[
        "\u2018Ory\u0101n",
        "\u2018Arab\u0101n",
        "\u0639\u0631\u06cc\u0627\u0646"
    ],
    "name:und_x_variant":[
        "\u0639\u0631\u06cc\u0627\u0646"
    ],
    "wof:name":"`Araban",
    "wof:placetype":"locality"
},
  "geometry": {"coordinates":[48.3237,33.4581],"type":"Point"}
}