{
  "type": "Feature",
  "properties": {
    "gn:admin1_code":"10",
    "gn:asciiname":"Cheshmeh Chahi-ye `Olya",
    "gn:country_code":"IR",
    "gn:dem":1297,
    "gn:feature_class":"P",
    "gn:feature_code":"PPL",
    "gn:name":"Cheshmeh Ch\u0101h\u012b-ye \u2018Oly\u0101",
    "gn:population":0,
    "gn:timezone":"Asia/Tehran",
    "iso:country":"IR",
    "name:fas_x_preferred":[
        "\u0686\u0634\u0645\u0647 \u0686\u0627\u0647\u06cc \u0639\u0644\u06cc\u0627"
    ],
    "name:und_x_variant":[
        "Cheshmeh Ch\u0101h\u012b-ye \u2018Oly\u0101"
    ],
    "wof:name":"Cheshmeh Chahi-ye `Olya",
    "wof:placetype":"locality"
},
  "geometry": {"coordinates":[46.5578,33.6857],"type":"Point"}
}