{
  "type": "Feature",
  "properties": {
    "gn:admin1_code":"35.0",
    "gn:asciiname":"Shahrak-e Lashak",
    "gn:country_code":"IR",
    "gn:dem":1611,
    "gn:feature_class":"P",
    "gn:feature_code":"PPL",
    "gn:name":"Shahrak-e L\u0101shak",
    "gn:population":0,
    "gn:timezone":"Asia/Tehran",
    "iso:country":"IR",
    "name:fas_x_preferred":[
        "\u0634\u0647\u0631\u0643 \u0644\u0627\u0634\u06a9"
    ],
    "name:fas_x_variant":[
        "\u0634\u0647\u0631\u06a9 \u062c\u062f\u06cc\u062f \u0627\u0644\u062d\u062f\u0627\u062b"
    ],
    "name:und_x_variant":[
        "Shahrak-e L\u0101shak",
        "Shahrak-e Jad\u012bd ol E\u1e29ad\u0101s\u0304"
    ],
    "wof:name":"Shahrak-e Lashak",
    "wof:placetype":"locality"
},
  "geometry": {"coordinates":[51.63866,36.39402000000001],"type":"Point"}
}