{
  "type": "Feature",
  "properties": {
    "gn:admin1_code":"42",
    "gn:asciiname":"Garnig",
    "gn:country_code":"IR",
    "gn:dem":1158,
    "gn:feature_class":"P",
    "gn:feature_code":"PPL",
    "gn:name":"Garn\u012bg",
    "gn:population":0,
    "gn:timezone":"Asia/Tehran",
    "iso:country":"IR",
    "name:fas_x_preferred":[
        "\u06af\u0631\u0646\u064a\u06af"
    ],
    "name:fas_x_variant":[
        "Garn\u012bg"
    ],
    "wof:name":"Garnig",
    "wof:placetype":"locality"
},
  "geometry": {"coordinates":[60.0431,33.49942],"type":"Point"}
}