{
  "type": "Feature",
  "properties": {
    "gn:admin1_code":"15",
    "gn:asciiname":"Nehzat",
    "gn:country_code":"IR",
    "gn:dem":530,
    "gn:feature_class":"P",
    "gn:feature_code":"PPL",
    "gn:name":"Neh\u1e95at",
    "gn:population":0,
    "gn:timezone":"Asia/Tehran",
    "iso:country":"IR",
    "name:fas_x_preferred":[
        "\u0646\u0647\u0636\u062a"
    ],
    "name:fas_x_variant":[
        "Neh\u1e95at"
    ],
    "wof:name":"Nehzat",
    "wof:placetype":"locality"
},
  "geometry": {"coordinates":[48.585,32.6155],"type":"Point"}
}