{
  "type": "Feature",
  "properties": {
    "gn:admin1_code":"29",
    "gn:asciiname":"Lard Kharan",
    "gn:country_code":"IR",
    "gn:dem":642,
    "gn:feature_class":"P",
    "gn:feature_code":"PPL",
    "gn:name":"Lard Khar\u0101n",
    "gn:population":0,
    "gn:timezone":"Asia/Tehran",
    "iso:country":"IR",
    "name:ara_x_preferred":[
        "\u0644\u0631\u062f\u062e\u0631\u0627\u0646"
    ],
    "name:fas_x_preferred":[
        "\u0644\u0631\u062f \u062e\u0631\u0627\u0646"
    ],
    "name:fas_x_variant":[
        "Lard Khar\u0101n",
        "\u0644\u0631\u062f\u062e\u0631\u0627\u0646"
    ],
    "name:urd_x_preferred":[
        "\u0644\u0631\u062f \u062e\u0631\u0627\u0646"
    ],
    "wof:name":"Lard Kharan",
    "wof:placetype":"locality"
},
  "geometry": {"coordinates":[57.9014,28.4492],"type":"Point"}
}