{
  "type": "Feature",
  "properties": {
    "gn:admin1_code":"15",
    "gn:asciiname":"`Eliyeh-ye Yek",
    "gn:country_code":"IR",
    "gn:dem":34,
    "gn:feature_class":"P",
    "gn:feature_code":"PPL",
    "gn:name":"\u2018El\u012byeh-ye Yek",
    "gn:population":0,
    "gn:timezone":"Asia/Tehran",
    "iso:country":"IR",
    "name:fas_x_preferred":[
        "\u0639\u06cc\u0644\u0647 \u06cc\u06a9"
    ],
    "name:fas_x_variant":[
        "\u2018Eyleh-ye Yek",
        "\u0639\u0644\u06cc\u0647 \u06cc\u06a9"
    ],
    "name:und_x_variant":[
        "Sheykh H\u0101d\u012b",
        "\u2018As\u012bleh-e Yek",
        "\u2018El\u012byeh-ye Yek"
    ],
    "wof:name":"`Eliyeh-ye Yek",
    "wof:placetype":"locality"
},
  "geometry": {"coordinates":[48.63087,31.89566],"type":"Point"}
}