{
  "type": "Feature",
  "properties": {
    "gn:admin1_code":"28.0",
    "gn:asciiname":"Asadabad",
    "gn:country_code":"IR",
    "gn:dem":2252,
    "gn:feature_class":"P",
    "gn:feature_code":"PPL",
    "gn:name":"Asad\u0101b\u0101d",
    "gn:population":0,
    "gn:timezone":"Asia/Tehran",
    "iso:country":"IR",
    "name:ara_x_preferred":[
        "\u0623\u0633\u062f \u0622\u0628\u0627\u062f"
    ],
    "name:azb_x_preferred":[
        "\u0627\u0633\u062f\u0622\u0628\u0627\u062f"
    ],
    "name:aze_x_preferred":[
        "\u018fs\u0259dabad"
    ],
    "name:cat_x_preferred":[
        "Asadabad"
    ],
    "name:ceb_x_preferred":[
        "Asadabad"
    ],
    "name:fas_x_preferred":[
        "Asad\u0101b\u0101d"
    ],
    "name:fas_x_variant":[
        "\u0627\u0633\u062f\u0622\u0628\u0627\u062f"
    ],
    "name:heb_x_preferred":[
        "\u05d0\u05e1\u05d3\u05d0\u05d1\u05d0\u05d3"
    ],
    "name:pol_x_preferred":[
        "Asadabad"
    ],
    "name:por_x_preferred":[
        "Asadabad"
    ],
    "name:rus_x_preferred":[
        "\u0410\u0441\u0430\u0434\u0430\u0431\u0430\u0434"
    ],
    "name:sco_x_preferred":[
        "Asadabad"
    ],
    "name:swe_x_preferred":[
        "Asadabad"
    ],
    "name:tur_x_preferred":[
        "Esedabad"
    ],
    "name:ukr_x_preferred":[
        "\u0410\u0441\u0430\u0434\u0430\u0431\u0430\u0434"
    ],
    "name:urd_x_preferred":[
        "\u0627\u0633\u062f\u0622\u0628\u0627\u062f"
    ],
    "wof:name":"Asadabad",
    "wof:placetype":"locality"
},
  "geometry": {"coordinates":[52.33333,33.05],"type":"Point"}
}