{
  "type": "Feature",
  "properties": {
    "gn:admin1_code":"28.0",
    "gn:asciiname":"Asadabad",
    "gn:country_code":"IR",
    "gn:dem":2252,
    "gn:feature_class":"P",
    "gn:feature_code":"PPL",
    "gn:name":"Asad\u0101b\u0101d",
    "gn:population":0,
    "gn:timezone":"Asia/Tehran",
    "iso:country":"IR",
    "name:fas_x_preferred":[
        "Asad\u0101b\u0101d"
    ],
    "wof:name":"Asadabad",
    "wof:placetype":"locality"
},
  "geometry": {"coordinates":[52.33333,33.05],"type":"Point"}
}