{
  "type": "Feature",
  "properties": {
    "gn:admin1_code":"33",
    "gn:asciiname":"Genanlu",
    "gn:country_code":"IR",
    "gn:dem":889,
    "gn:feature_class":"P",
    "gn:feature_code":"PPL",
    "gn:name":"Gen\u0101nl\u016b",
    "gn:population":0,
    "gn:timezone":"Asia/Tehran",
    "iso:country":"IR",
    "name:fas_x_preferred":[
        "\u063a\u0650\u0646\u0627\u0646\u0644\u0648"
    ],
    "name:fas_x_variant":[
        "\u06af\u0646\u0627\u0646\u0644\u0648",
        "Ghen\u0101nl\u016b",
        "Gon\u0101nl\u016b",
        "Gen\u0101nl\u016b"
    ],
    "wof:name":"Genanlu",
    "wof:placetype":"locality"
},
  "geometry": {"coordinates":[47.1411,39.1048],"type":"Point"}
}