{
  "type": "Feature",
  "properties": {
    "gn:admin1_code":"5.0",
    "gn:asciiname":"Gaz Gu",
    "gn:country_code":"IR",
    "gn:dem":1069,
    "gn:feature_class":"P",
    "gn:feature_code":"PPL",
    "gn:name":"Gaz G\u016b",
    "gn:population":0,
    "gn:timezone":"Asia/Tehran",
    "iso:country":"IR",
    "name:fas_x_preferred":[
        "Gaz G\u016b"
    ],
    "name:fas_x_variant":[
        "\u06af\u0632 \u06af\u0648"
    ],
    "name:und_x_variant":[
        "\u06af\u0632 \u06af\u0648"
    ],
    "wof:name":"Gaz Gu",
    "wof:placetype":"locality"
},
  "geometry": {"coordinates":[50.65302,31.41602],"type":"Point"}
}