{
  "type": "Feature",
  "properties": {
    "gn:admin1_code":"42",
    "gn:asciiname":"Khatumeh",
    "gn:country_code":"IR",
    "gn:dem":1695,
    "gn:feature_class":"P",
    "gn:feature_code":"PPL",
    "gn:name":"Kh\u0101t\u016bmeh",
    "gn:population":0,
    "gn:timezone":"Asia/Tehran",
    "iso:country":"IR",
    "name:fas_x_preferred":[
        "Kh\u0101t\u016bmeh"
    ],
    "name:fas_x_variant":[
        "Kal\u0101teh-ye Kh\u0101t\u016bmeh",
        "\u062e\u0627\u062a\u0648\u0645\u0647"
    ],
    "name:und_x_variant":[
        "\u062e\u0627\u062a\u0648\u0645\u0647"
    ],
    "wof:name":"Khatumeh",
    "wof:placetype":"locality"
},
  "geometry": {"coordinates":[58.43162,34.26582],"type":"Point"}
}