{
  "type": "Feature",
  "properties": {
    "gn:admin1_code":"33",
    "gn:asciiname":"Nazar Kandi",
    "gn:country_code":"IR",
    "gn:dem":646,
    "gn:feature_class":"P",
    "gn:feature_code":"PPL",
    "gn:name":"Naz\u0327ar Kand\u012b",
    "gn:population":0,
    "gn:timezone":"Asia/Tehran",
    "iso:country":"IR",
    "name:fas_x_preferred":[
        "\u0646\u0638\u0631 \u06a9\u0646\u062f\u06cc"
    ],
    "name:fas_x_variant":[
        "Naz\u0327ar Kand\u012b"
    ],
    "wof:name":"Nazar Kandi",
    "wof:placetype":"locality"
},
  "geometry": {"coordinates":[46.23596,38.82419],"type":"Point"}
}