{
  "type": "Feature",
  "properties": {
    "gn:admin1_code":"4.0",
    "gn:asciiname":"Zonnar",
    "gn:cc2":"IR",
    "gn:country_code":"IR",
    "gn:dem":234,
    "gn:feature_class":"P",
    "gn:feature_code":"PPL",
    "gn:name":"Zonnar",
    "gn:population":0,
    "gn:timezone":"Asia/Tehran",
    "iso:country":"IR",
    "name:fas_x_preferred":[
        "\u0632\u0646\u0631"
    ],
    "name:und_x_variant":[
        "Zon\u0101r",
        "Zonnar"
    ],
    "wof:name":"Zonnar",
    "wof:placetype":"locality"
},
  "geometry": {"coordinates":[61.03556,26.01056],"type":"Point"}
}