{
  "type": "Feature",
  "properties": {
    "gn:admin1_code":"15",
    "gn:asciiname":"Seyyed Yadim",
    "gn:country_code":"IR",
    "gn:dem":28,
    "gn:feature_class":"P",
    "gn:feature_code":"PPL",
    "gn:name":"Seyyed Yad\u012bm",
    "gn:population":0,
    "gn:timezone":"Asia/Tehran",
    "iso:country":"IR",
    "name:fas_x_preferred":[
        "Seyyed Yadd\u0101m"
    ],
    "name:fas_x_variant":[
        "\u0633\u06cc\u062f \u06cc\u062f\u06cc\u0645"
    ],
    "name:und_x_variant":[
        "Seyyed Yad\u012bm"
    ],
    "wof:name":"Seyyed Yadim",
    "wof:placetype":"locality"
},
  "geometry": {"coordinates":[48.69284,31.69855],"type":"Point"}
}