{
  "type": "Feature",
  "properties": {
    "gn:admin1_code":"23.0",
    "gn:asciiname":"Hasanabad-e Sanjabi",
    "gn:country_code":"IR",
    "gn:dem":1879,
    "gn:feature_class":"P",
    "gn:feature_code":"PPL",
    "gn:name":"\u1e28asan\u0101b\u0101d-e Sanj\u0101b\u012b",
    "gn:population":0,
    "gn:timezone":"Asia/Tehran",
    "iso:country":"IR",
    "name:ara_x_preferred":[
        "\u062d\u0633\u0646\u200c\u0622\u0628\u0627\u062f \u0633\u0646\u062c\u0627\u0628\u064a"
    ],
    "name:ceb_x_preferred":[
        "\u1e28asan\u0101b\u0101d-e Sanj\u0101b\u012b"
    ],
    "name:fas_x_preferred":[
        "\u062d\u064e\u0633\u064e\u0646\u0627\u0628\u0627\u062f\u0650 \u0633\u064e\u0646\u062c\u0627\u0628\u06cc"
    ],
    "name:fas_x_variant":[
        "\u062d\u0633\u0646 \u0622\u0628\u0627\u062f \u0633\u0646\u062c\u0627\u0628\u06cc",
        "\u1e28asan\u0101b\u0101d-e Sanj\u0101b\u012b",
        "\u062d\u0633\u0646\u200c\u0622\u0628\u0627\u062f \u0633\u0646\u062c\u0627\u0628\u06cc"
    ],
    "name:swe_x_preferred":[
        "\u1e28asan\u0101b\u0101d-e Sanj\u0101b\u012b"
    ],
    "wof:name":"Hasanabad-e Sanjabi",
    "wof:placetype":"locality"
},
  "geometry": {"coordinates":[47.9437,34.1356],"type":"Point"}
}