{
  "type": "Feature",
  "properties": {
    "gn:admin1_code":"7",
    "gn:asciiname":"Khargah-e Shomali",
    "gn:country_code":"IR",
    "gn:dem":407,
    "gn:feature_class":"P",
    "gn:feature_code":"PPL",
    "gn:name":"Kharg\u0101h-e Shom\u0101l\u012b",
    "gn:population":0,
    "gn:timezone":"Asia/Tehran",
    "iso:country":"IR",
    "name:fas_x_preferred":[
        "Kharg\u016b"
    ],
    "name:fas_x_variant":[
        "\u062e\u0631\u06af\u0627\u0647 \u0634\u0645\u0627\u0644\u06cc",
        "\u062e\u0631\u06af\u0648\u06cc\u0647"
    ],
    "name:und_x_variant":[
        "Kharg\u0101h-e Shom\u0101l\u012b",
        "Kharg\u016byeh"
    ],
    "wof:name":"Khargah-e Shomali",
    "wof:placetype":"locality"
},
  "geometry": {"coordinates":[53.5315,27.295],"type":"Point"}
}