{
  "type": "Feature",
  "properties": {
    "gn:admin1_code":"43.0",
    "gn:asciiname":"Baba Hajji",
    "gn:country_code":"IR",
    "gn:dem":522,
    "gn:feature_class":"P",
    "gn:feature_code":"PPL",
    "gn:name":"B\u0101b\u0101 \u1e28\u0101jj\u012b",
    "gn:population":0,
    "gn:timezone":"Asia/Tehran",
    "iso:country":"IR",
    "name:fas_x_preferred":[
        "B\u0101b\u0101 \u1e28\u0101jj\u012b"
    ],
    "name:fas_x_variant":[
        "\u0628\u0627\u0628\u0627 \u062d\u0627\u062c\u06cc"
    ],
    "wof:name":"Baba Hajji",
    "wof:placetype":"locality"
},
  "geometry": {"coordinates":[56.50501,37.76065],"type":"Point"}
}