{
  "type": "Feature",
  "properties": {
    "gn:admin1_code":"15",
    "gn:asciiname":"Sheykh Salman",
    "gn:cc2":"IR",
    "gn:country_code":"IR",
    "gn:dem":2,
    "gn:feature_class":"P",
    "gn:feature_code":"PPL",
    "gn:name":"Sheykh Salm\u0101n",
    "gn:population":0,
    "gn:timezone":"Asia/Tehran",
    "iso:country":"IR",
    "name:fas_x_preferred":[
        "Sheykh Salm\u0101n"
    ],
    "name:und_x_variant":[
        "Shaikh Salm\u0101n"
    ],
    "wof:name":"Sheykh Salman",
    "wof:placetype":"locality"
},
  "geometry": {"coordinates":[48.33333,30.28333],"type":"Point"}
}