{
  "type": "Feature",
  "properties": {
    "gn:admin1_code":"7",
    "gn:asciiname":"Cheshmeh Baklu",
    "gn:country_code":"IR",
    "gn:dem":1831,
    "gn:feature_class":"P",
    "gn:feature_code":"PPL",
    "gn:name":"Cheshmeh Bakl\u016b",
    "gn:population":0,
    "gn:timezone":"Asia/Tehran",
    "iso:country":"IR",
    "name:fas_x_preferred":[
        "\u0686\u0634\u0645\u0647 \u0628\u06a9\u0644\u0648"
    ],
    "name:fas_x_variant":[
        "Cheshmeh Bakl\u016b"
    ],
    "name:msa_x_preferred":[
        "Cheshmeh Baklu"
    ],
    "name:und_x_variant":[
        "Cheshmeh Baygl\u016b",
        "Cheshmeh Bagl\u016b"
    ],
    "wof:name":"Cheshmeh Baklu",
    "wof:placetype":"locality"
},
  "geometry": {"coordinates":[52.0015,30.1037],"type":"Point"}
}