{
  "type": "Feature",
  "properties": {
    "gn:admin1_code":"35.0",
    "gn:asciiname":"Mellatabad",
    "gn:country_code":"IR",
    "gn:dem":19,
    "gn:feature_class":"P",
    "gn:feature_code":"PPL",
    "gn:name":"Mellat\u0101b\u0101d",
    "gn:population":0,
    "gn:timezone":"Asia/Tehran",
    "iso:country":"IR",
    "name:fas_x_preferred":[
        "\u0645\u0650\u0644\u064e\u0651\u062a \u0622\u0628\u0627\u062f"
    ],
    "name:fas_x_variant":[
        "Mellat\u0101b\u0101d"
    ],
    "wof:name":"Mellatabad",
    "wof:placetype":"locality"
},
  "geometry": {"coordinates":[52.38333,36.53333],"type":"Point"}
}