{
  "type": "Feature",
  "properties": {
    "gn:admin1_code":"36",
    "gn:asciiname":"Sowme`eh Bar",
    "gn:country_code":"IR",
    "gn:dem":536,
    "gn:feature_class":"P",
    "gn:feature_code":"PPL",
    "gn:name":"\u015eowme\u2018eh Bar",
    "gn:population":0,
    "gn:timezone":"Asia/Tehran",
    "iso:country":"IR",
    "name:azb_x_preferred":[
        "\u0635\u0648\u0645\u0639\u0647 \u0628\u0631"
    ],
    "name:fas_x_preferred":[
        "\u0633\u0645\u0627\u0648\u0631"
    ],
    "name:fas_x_variant":[
        "\u0635\u0648\u0645\u0639\u0647 \u0628\u0631",
        "Sam\u0101var"
    ],
    "name:und_x_variant":[
        "\u015e\u016bme\u2018eh Bar",
        "Samabar",
        "Sowme\u2018eh Bar",
        "Sem\u0101var",
        "\u015eowme\u2018eh Bar",
        "\u015eowma\u2018eh Bar"
    ],
    "wof:name":"Sowme`eh Bar",
    "wof:placetype":"locality"
},
  "geometry": {"coordinates":[49.0998,36.8263],"type":"Point"}
}