{
  "type": "Feature",
  "properties": {
    "gn:admin1_code":"42",
    "gn:asciiname":"Nakhrud",
    "gn:country_code":"IR",
    "gn:dem":1964,
    "gn:feature_class":"P",
    "gn:feature_code":"PPL",
    "gn:name":"Nakhr\u016bd",
    "gn:population":0,
    "gn:timezone":"Asia/Tehran",
    "iso:country":"IR",
    "name:fas_x_preferred":[
        "Nakhr\u016bd"
    ],
    "name:fas_x_variant":[
        "\u0646\u062e\u0631\u0648\u062f",
        "\u0641\u062e\u0631\u0648\u062f"
    ],
    "name:und_x_variant":[
        "Nakr\u016bd",
        "Fakhr\u016bd"
    ],
    "wof:name":"Nakhrud",
    "wof:placetype":"locality"
},
  "geometry": {"coordinates":[59.59012,33.42524],"type":"Point"}
}