{
  "type": "Feature",
  "properties": {
    "gn:admin1_code":"29.0",
    "gn:asciiname":"Dehnow-ye Abshur Rostamabad",
    "gn:country_code":"IR",
    "gn:dem":753,
    "gn:feature_class":"P",
    "gn:feature_code":"PPL",
    "gn:name":"Dehnow-ye \u0100bsh\u016br Rostam\u0101b\u0101d",
    "gn:population":0,
    "gn:timezone":"Asia/Tehran",
    "iso:country":"IR",
    "name:fas_x_preferred":[
        "\u062f\u0647 \u0646\u0648 \u0622\u0628 \u0634\u0648\u0631"
    ],
    "name:fas_x_variant":[
        "Deh-e Sh\u016br",
        "\u062f\u0647\u0646\u0648 \u0622\u0628\u0634\u0648\u0631 \u0631\u0633\u062a\u0645 \u0622\u0628\u0627\u062f"
    ],
    "name:und_x_variant":[
        "Deh Sh\u016br",
        "Deh Now-ye \u0100b Sh\u016br",
        "Dehnow-ye \u0100bsh\u016br Rostam\u0101b\u0101d"
    ],
    "wof:name":"Dehnow-ye Abshur Rostamabad",
    "wof:placetype":"locality"
},
  "geometry": {"coordinates":[58.7039,28.9578],"type":"Point"}
}