{
  "type": "Feature",
  "properties": {
    "gn:admin1_code":"15",
    "gn:asciiname":"Qal`eh Lava",
    "gn:country_code":"IR",
    "gn:dem":1510,
    "gn:feature_class":"P",
    "gn:feature_code":"PPL",
    "gn:name":"Qal\u2018eh Lav\u0101",
    "gn:population":0,
    "gn:timezone":"Asia/Tehran",
    "iso:country":"IR",
    "name:fas_x_preferred":[
        "Qal\u2018eh Lav\u0101"
    ],
    "wof:name":"Qal`eh Lava",
    "wof:placetype":"locality"
},
  "geometry": {"coordinates":[50.11889,31.84972],"type":"Point"}
}