{
  "type": "Feature",
  "properties": {
    "gn:admin1_code":"1",
    "gn:asciiname":"Adaghan",
    "gn:country_code":"IR",
    "gn:dem":1447,
    "gn:feature_class":"P",
    "gn:feature_code":"PPL",
    "gn:name":"\u0100d\u0101gh\u0101n",
    "gn:population":0,
    "gn:timezone":"Asia/Tehran",
    "iso:country":"IR",
    "name:azb_x_preferred":[
        "\u0627\u062f\u0627\u063a\u0627\u0646"
    ],
    "name:aze_x_preferred":[
        "Ada\u011fan"
    ],
    "name:fas_x_preferred":[
        "\u0100d\u0101gh\u0101n"
    ],
    "name:fas_x_variant":[
        "\u0622\u062f\u0627\u063a\u0627\u0646",
        "\u0627\u062f\u0627\u063a\u0627\u0646"
    ],
    "name:msa_x_preferred":[
        "Adaghan"
    ],
    "name:und_x_variant":[
        "\u0622\u062f\u0627\u063a\u0627\u0646"
    ],
    "wof:name":"Adaghan",
    "wof:placetype":"locality"
},
  "geometry": {"coordinates":[44.6033,39.4157],"type":"Point"}
}