{
  "type": "Feature",
  "properties": {
    "gn:admin1_code":"11",
    "gn:asciiname":"Kalatak-e Kuh-e Pa'in",
    "gn:country_code":"IR",
    "gn:dem":565,
    "gn:feature_class":"P",
    "gn:feature_code":"PPL",
    "gn:name":"Kal\u0101tak-e K\u016bh-e P\u0101\u2019\u012bn",
    "gn:population":0,
    "gn:timezone":"Asia/Tehran",
    "iso:country":"IR",
    "name:fas_x_preferred":[
        "\u06a9\u0644\u0627\u062a\u06a9 \u06a9\u0648\u0647 \u067e\u0627\u0626\u06cc\u0646"
    ],
    "name:fas_x_variant":[
        "Kal\u0101tak-e K\u016bh-e P\u0101\u2019\u012bn"
    ],
    "wof:name":"Kalatak-e Kuh-e Pa'in",
    "wof:placetype":"locality"
},
  "geometry": {"coordinates":[56.3286,27.7241],"type":"Point"}
}