{
  "type": "Feature",
  "properties": {
    "gn:admin1_code":"29",
    "gn:asciiname":"Hojjatabad-e Kork",
    "gn:country_code":"IR",
    "gn:dem":927,
    "gn:feature_class":"P",
    "gn:feature_code":"PPL",
    "gn:name":"\u1e28ojjat\u0101b\u0101d-e Kork",
    "gn:population":0,
    "gn:timezone":"Asia/Tehran",
    "iso:country":"IR",
    "name:fas_x_preferred":[
        "\u062d\u062c\u062a \u0622\u0628\u0627\u062f \u06a9\u0631\u06a9"
    ],
    "name:fas_x_variant":[
        "\u1e28ojjat\u0101b\u0101d-e Kork"
    ],
    "wof:name":"Hojjatabad-e Kork",
    "wof:placetype":"locality"
},
  "geometry": {"coordinates":[58.4816,29.1593],"type":"Point"}
}