{
  "type": "Feature",
  "properties": {
    "gn:admin1_code":"41",
    "gn:asciiname":"Ab Anbar",
    "gn:country_code":"IR",
    "gn:dem":1646,
    "gn:feature_class":"P",
    "gn:feature_code":"PPL",
    "gn:name":"\u0100b Anb\u0101r",
    "gn:population":0,
    "gn:timezone":"Asia/Tehran",
    "iso:country":"IR",
    "name:fas_x_preferred":[
        "\u0622\u0628 \u0627\u064e\u0646\u0628\u0627\u0631"
    ],
    "name:fas_x_variant":[
        "\u0622\u0628 \u0627\u064e\u0645\u0628\u0627\u0631",
        "\u0100b Anb\u0101r"
    ],
    "name:und_x_variant":[
        "\u0100b Amb\u0101r"
    ],
    "wof:name":"Ab Anbar",
    "wof:placetype":"locality"
},
  "geometry": {"coordinates":[59.16667,33.41667],"type":"Point"}
}