{
  "type": "Feature",
  "properties": {
    "gn:admin1_code":"41",
    "gn:asciiname":"Cheshmeh Raj",
    "gn:country_code":"IR",
    "gn:dem":1783,
    "gn:feature_class":"P",
    "gn:feature_code":"PPL",
    "gn:name":"Cheshmeh Raj",
    "gn:population":0,
    "gn:timezone":"Asia/Tehran",
    "iso:country":"IR",
    "name:fas_x_preferred":[
        "\u0686\u0634\u0645\u0647 \u0631\u06cc\u062c"
    ],
    "name:fas_x_variant":[
        "Cheshmeh R\u012bch",
        "Cheshmeh R\u012bj",
        "\u0686\u0634\u0645\u0647 \u0631\u062c"
    ],
    "name:und_x_variant":[
        "Cheshmeh Reyj",
        "Cheshmeh Raj"
    ],
    "wof:name":"Cheshmeh Raj",
    "wof:placetype":"locality"
},
  "geometry": {"coordinates":[59.53845,32.8342],"type":"Point"}
}