{
  "type": "Feature",
  "properties": {
    "gn:admin1_code":"36",
    "gn:asciiname":"Shahidabad",
    "gn:country_code":"IR",
    "gn:dem":1756,
    "gn:feature_class":"P",
    "gn:feature_code":"PPL",
    "gn:name":"Shah\u012bd\u0101b\u0101d",
    "gn:population":0,
    "gn:timezone":"Asia/Tehran",
    "iso:country":"IR",
    "name:fas_x_preferred":[
        "\u0642\u0648\u0637\u06cc \u0622\u0628\u0627\u062f"
    ],
    "name:fas_x_variant":[
        "Q\u016b\u0163\u012b\u0101b\u0101d",
        "\u0634\u0647\u06cc\u062f \u0622\u0628\u0627\u062f"
    ],
    "name:und_x_variant":[
        "Ghooti Abad",
        "Quli\u0101b\u0101d",
        "Shah\u012bd\u0101b\u0101d"
    ],
    "wof:name":"Shahidabad",
    "wof:placetype":"locality"
},
  "geometry": {"coordinates":[48.49937,35.78192],"type":"Point"}
}