{
  "type": "Feature",
  "properties": {
    "gn:admin1_code":"29",
    "gn:asciiname":"Qaziabad",
    "gn:country_code":"IR",
    "gn:dem":2292,
    "gn:feature_class":"P",
    "gn:feature_code":"PPL",
    "gn:name":"Q\u0101\u1e95\u012b\u0101b\u0101d",
    "gn:population":0,
    "gn:timezone":"Asia/Tehran",
    "iso:country":"IR",
    "name:fas_x_preferred":[
        "Q\u0101\u1e95\u012b\u0101b\u0101d"
    ],
    "name:fas_x_variant":[
        "\u0642\u0627\u0636\u06cc\u200c\u0622\u0628\u0627\u062f"
    ],
    "wof:name":"Qaziabad",
    "wof:placetype":"locality"
},
  "geometry": {"coordinates":[57.23333,29.05],"type":"Point"}
}