{
  "type": "Feature",
  "properties": {
    "gn:admin1_code":"42",
    "gn:asciiname":"Kalateh-ye `Arab",
    "gn:country_code":"IR",
    "gn:dem":1094,
    "gn:feature_class":"P",
    "gn:feature_code":"PPL",
    "gn:name":"Kal\u0101teh-ye \u2018Arab",
    "gn:population":0,
    "gn:timezone":"Asia/Tehran",
    "iso:country":"IR",
    "name:fas_x_preferred":[
        "Kal\u0101teh-ye \u2018Arab"
    ],
    "name:fas_x_variant":[
        "\u06a9\u0644\u0627\u062a\u0647 \u0639\u0631\u0628"
    ],
    "name:und_x_variant":[
        "Kal\u0101teh Arab",
        "\u06a9\u0644\u0627\u062a\u0647 \u0639\u0631\u0628"
    ],
    "wof:name":"Kalateh-ye `Arab",
    "wof:placetype":"locality"
},
  "geometry": {"coordinates":[57.6199,36.6171],"type":"Point"}
}