{
  "type": "Feature",
  "properties": {
    "gn:admin1_code":"29",
    "gn:asciiname":"Gari-ye `Olya",
    "gn:country_code":"IR",
    "gn:dem":2682,
    "gn:feature_class":"P",
    "gn:feature_code":"PPL",
    "gn:name":"Gar\u012b-ye \u2018Oly\u0101",
    "gn:population":0,
    "gn:timezone":"Asia/Tehran",
    "iso:country":"IR",
    "name:fas_x_preferred":[
        "\u06af\u0631\u06cc \u0639\u0644\u06cc\u0627"
    ],
    "name:fas_x_variant":[
        "Gar\u012b-ye B\u0101l\u0101",
        "Gar\u012b-ye \u2018Oly\u0101",
        "\u06af\u0631\u06cc \u0628\u0627\u0644\u0627"
    ],
    "wof:name":"Gari-ye `Olya",
    "wof:placetype":"locality"
},
  "geometry": {"coordinates":[55.2671,30.4181],"type":"Point"}
}