{
  "type": "Feature",
  "properties": {
    "gn:admin1_code":"41",
    "gn:asciiname":"Gorgu",
    "gn:country_code":"IR",
    "gn:dem":2073,
    "gn:feature_class":"P",
    "gn:feature_code":"PPL",
    "gn:name":"Gorg\u016b",
    "gn:population":0,
    "gn:timezone":"Asia/Tehran",
    "iso:country":"IR",
    "name:fas_x_preferred":[
        "Gurg\u016b"
    ],
    "name:fas_x_variant":[
        "\u06af\u0631\u06af\u0648"
    ],
    "name:und_x_variant":[
        "Gurg\u016bn",
        "Gorg\u016b"
    ],
    "wof:name":"Gorgu",
    "wof:placetype":"locality"
},
  "geometry": {"coordinates":[59.48695,32.65585],"type":"Point"}
}