{
  "type": "Feature",
  "properties": {
    "gn:admin1_code":"38.0",
    "gn:asciiname":"Varbon",
    "gn:country_code":"IR",
    "gn:dem":1885,
    "gn:elevation":"0.0",
    "gn:feature_class":"P",
    "gn:feature_code":"PPL",
    "gn:name":"Varbon",
    "gn:population":0,
    "gn:timezone":"Asia/Tehran",
    "iso:country":"IR",
    "name:fas_x_preferred":[
        "\u0648\u0631\u0628\u0646"
    ],
    "wof:name":"Varbon",
    "wof:placetype":"locality"
},
  "geometry": {"coordinates":[50.4539,36.4864],"type":"Point"}
}