{
  "type": "Feature",
  "properties": {
    "gn:admin1_code":"41",
    "gn:asciiname":"Torsh Ab",
    "gn:country_code":"IR",
    "gn:dem":1505,
    "gn:feature_class":"P",
    "gn:feature_code":"PPL",
    "gn:name":"Torsh \u0100b",
    "gn:population":0,
    "gn:timezone":"Asia/Tehran",
    "iso:country":"IR",
    "name:fas_x_preferred":[
        "\u062a\u0631\u0634 \u0622\u0628"
    ],
    "name:fas_x_variant":[
        "Torsh \u0100b"
    ],
    "wof:name":"Torsh Ab",
    "wof:placetype":"locality"
},
  "geometry": {"coordinates":[60.22816,31.74389],"type":"Point"}
}