{
  "type": "Feature",
  "properties": {
    "gn:admin1_code":"11.0",
    "gn:asciiname":"Seyyed Ahmad",
    "gn:country_code":"IR",
    "gn:dem":398,
    "gn:feature_class":"P",
    "gn:feature_code":"PPL",
    "gn:name":"Seyyed A\u1e29mad",
    "gn:population":0,
    "gn:timezone":"Asia/Tehran",
    "iso:country":"IR",
    "name:fas_x_preferred":[
        "Seyyed A\u1e29mad"
    ],
    "name:fas_x_variant":[
        "\u0633\u06cc\u062f \u0627\u062d\u0645\u062f"
    ],
    "wof:name":"Seyyed Ahmad",
    "wof:placetype":"locality"
},
  "geometry": {"coordinates":[54.83044,27.23658],"type":"Point"}
}