{
  "type": "Feature",
  "properties": {
    "gn:admin1_code":"15",
    "gn:asciiname":"Kelasmadin-e Yek",
    "gn:country_code":"IR",
    "gn:dem":524,
    "gn:feature_class":"P",
    "gn:feature_code":"PPL",
    "gn:name":"Kel\u0101smad\u012bn-e Yek",
    "gn:population":0,
    "gn:timezone":"Asia/Tehran",
    "iso:country":"IR",
    "name:fas_x_preferred":[
        "Kel\u0101smad\u012bn-e Yek"
    ],
    "name:fas_x_variant":[
        "\u06a9\u0644\u0627\u0633\u0645\u062f\u06cc\u0646 \u06cc\u06a9"
    ],
    "wof:name":"Kelasmadin-e Yek",
    "wof:placetype":"locality"
},
  "geometry": {"coordinates":[49.76361,31.49841],"type":"Point"}
}