{
  "type": "Feature",
  "properties": {
    "gn:admin1_code":"7",
    "gn:asciiname":"Ziadabad",
    "gn:country_code":"IR",
    "gn:dem":1673,
    "gn:feature_class":"P",
    "gn:feature_code":"PPL",
    "gn:name":"Z\u012b\u0101d\u0101b\u0101d",
    "gn:population":0,
    "gn:timezone":"Asia/Tehran",
    "iso:country":"IR",
    "name:fas_x_preferred":[
        "\u0632\u06cc\u0627\u062f \u0622\u0628\u0627\u062f"
    ],
    "name:fas_x_variant":[
        "Z\u012b\u0101d\u0101b\u0101d"
    ],
    "wof:name":"Ziadabad",
    "wof:placetype":"locality"
},
  "geometry": {"coordinates":[53.43157,29.14679000000001],"type":"Point"}
}