{
  "type": "Feature",
  "properties": {
    "gn:admin1_code":"32.0",
    "gn:asciiname":"Seyyedlar",
    "gn:country_code":"IR",
    "gn:dem":2038,
    "gn:feature_class":"P",
    "gn:feature_code":"PPL",
    "gn:name":"Seyyedlar",
    "gn:population":0,
    "gn:timezone":"Asia/Tehran",
    "iso:country":"IR",
    "name:fas_x_preferred":[
        "\u0633\u06cc\u062f\u0644\u0631"
    ],
    "wof:name":"Seyyedlar",
    "wof:placetype":"locality"
},
  "geometry": {"coordinates":[48.0144,38.3348],"type":"Point"}
}