{
  "type": "Feature",
  "properties": {
    "gn:admin1_code":"8",
    "gn:asciiname":"`Asgarabad",
    "gn:country_code":"IR",
    "gn:dem":4,
    "gn:feature_class":"P",
    "gn:feature_code":"PPL",
    "gn:name":"\u2018Asgar\u0101b\u0101d",
    "gn:population":0,
    "gn:timezone":"Asia/Tehran",
    "iso:country":"IR",
    "name:fas_x_preferred":[
        "\u2018Asgar\u0101b\u0101d"
    ],
    "name:fas_x_variant":[
        "\u0639\u0633\u06af\u0631 \u0622\u0628\u0627\u062f",
        "\u0639\u0633\u06af\u0631\u0622\u0628\u0627\u062f"
    ],
    "name:msa_x_preferred":[
        "Asgarabad"
    ],
    "name:ukr_x_preferred":[
        "\u0410\u0441\u0491\u0430\u0440\u0430\u0431\u0430\u0434"
    ],
    "wof:name":"`Asgarabad",
    "wof:placetype":"locality"
},
  "geometry": {"coordinates":[50.42715,37.03575],"type":"Point"}
}