{
  "type": "Feature",
  "properties": {
    "gn:admin1_code":"8.0",
    "gn:asciiname":"Mianeh Sara-ye Bala",
    "gn:country_code":"IR",
    "gn:dem":1689,
    "gn:feature_class":"P",
    "gn:feature_code":"PPL",
    "gn:name":"M\u012b\u0101neh Sar\u0101-ye B\u0101l\u0101",
    "gn:population":0,
    "gn:timezone":"Asia/Tehran",
    "iso:country":"IR",
    "name:fas_x_preferred":[
        "\u0645\u06cc\u0627\u0646\u0647 \u0633\u0631\u0627 \u0628\u0627\u0644\u0627"
    ],
    "name:fas_x_variant":[
        "\u0645\u06cc\u0627\u0646\u0647 \u0633\u0631\u0627"
    ],
    "name:und_x_variant":[
        "M\u012b\u0101neh Sar\u0101-ye B\u0101l\u0101",
        "M\u012b\u0101neh Sar\u0101"
    ],
    "wof:name":"Mianeh Sara-ye Bala",
    "wof:placetype":"locality"
},
  "geometry": {"coordinates":[49.78062,36.89117],"type":"Point"}
}