{
  "type": "Feature",
  "properties": {
    "gn:admin1_code":"33",
    "gn:asciiname":"Ajudanabad",
    "gn:country_code":"IR",
    "gn:dem":815,
    "gn:feature_class":"P",
    "gn:feature_code":"PPL",
    "gn:name":"Aj\u016bd\u0101n\u0101b\u0101d",
    "gn:population":0,
    "gn:timezone":"Asia/Tehran",
    "iso:country":"IR",
    "name:ceb_x_preferred":[
        "Aj\u016bd\u0101n\u0101b\u0101d"
    ],
    "name:fas_x_preferred":[
        "\u0622\u062c\u0648\u062f\u0627\u0646 \u0622\u0628\u0627\u062f"
    ],
    "name:fas_x_variant":[
        "\u0627\u062c\u0648\u062f\u0627\u0646 \u0622\u0628\u0627\u062f",
        "\u0100j\u016bd\u0101n\u0101b\u0101d",
        "Aj\u016bd\u0101n\u0101b\u0101d",
        "\u0622\u062c\u0648\u062f\u0627\u0646\u200c\u0622\u0628\u0627\u062f"
    ],
    "name:msa_x_preferred":[
        "Ajudanabad"
    ],
    "name:swe_x_preferred":[
        "Aj\u016bd\u0101n\u0101b\u0101d"
    ],
    "wof:name":"Ajudanabad",
    "wof:placetype":"locality"
},
  "geometry": {"coordinates":[47.3445,39.0471],"type":"Point"}
}