{
  "type": "Feature",
  "properties": {
    "gn:admin1_code":"4",
    "gn:asciiname":"Haridak",
    "gn:country_code":"IR",
    "gn:dem":918,
    "gn:feature_class":"P",
    "gn:feature_code":"PPL",
    "gn:name":"Har\u012bdak",
    "gn:population":0,
    "gn:timezone":"Asia/Tehran",
    "iso:country":"IR",
    "name:fas_x_preferred":[
        "\u0647\u0631\u06cc\u062f\u06a9"
    ],
    "name:fas_x_variant":[
        "Har\u012bdak"
    ],
    "wof:name":"Haridak",
    "wof:placetype":"locality"
},
  "geometry": {"coordinates":[60.15728000000001,26.71871],"type":"Point"}
}