{
  "type": "Feature",
  "properties": {
    "gn:admin1_code":"13",
    "gn:asciiname":"Khoram",
    "gn:country_code":"IR",
    "gn:dem":1338,
    "gn:feature_class":"P",
    "gn:feature_code":"PPL",
    "gn:name":"Khor\u0101m",
    "gn:population":0,
    "gn:timezone":"Asia/Tehran",
    "iso:country":"IR",
    "name:fas_x_preferred":[
        "Khor\u0101m"
    ],
    "wof:name":"Khoram",
    "wof:placetype":"locality"
},
  "geometry": {"coordinates":[46.58333,34.63333],"type":"Point"}
}