{
  "type": "Feature",
  "properties": {
    "gn:admin1_code":"15",
    "gn:asciiname":"Boneh Parlak",
    "gn:country_code":"IR",
    "gn:dem":738,
    "gn:feature_class":"P",
    "gn:feature_code":"PPL",
    "gn:name":"Boneh P\u0101rlak",
    "gn:population":0,
    "gn:timezone":"Asia/Tehran",
    "iso:country":"IR",
    "name:fas_x_preferred":[
        "\u062f\u0644\u06cc"
    ],
    "name:fas_x_variant":[
        "Qal\u2018eh-ye Del\u012b",
        "Del\u012b",
        "\u0628\u0646\u0647 \u067e\u0627\u0631\u0644\u06a9"
    ],
    "name:und_x_variant":[
        "Qal\u2018eh-i-Dilli",
        "Boneh P\u0101rlak"
    ],
    "wof:name":"Boneh Parlak",
    "wof:placetype":"locality"
},
  "geometry": {"coordinates":[49.4328,32.3296],"type":"Point"}
}