{
  "type": "Feature",
  "properties": {
    "gn:admin1_code":"3.0",
    "gn:asciiname":"Deh Gah",
    "gn:country_code":"IR",
    "gn:dem":2295,
    "gn:feature_class":"P",
    "gn:feature_code":"PPL",
    "gn:name":"Deh Gah",
    "gn:population":0,
    "gn:timezone":"Asia/Tehran",
    "iso:country":"IR",
    "name:fas_x_preferred":[
        "\u062f\u0650\u0647\u0650 \u06af\u064e\u0647"
    ],
    "name:fas_x_variant":[
        "\u062f\u0647 \u06af\u0647"
    ],
    "name:und_x_variant":[
        "Deh-e Gah",
        "\u062f\u0647 \u06af\u0647",
        "Deh Gah"
    ],
    "wof:name":"Deh Gah",
    "wof:placetype":"locality"
},
  "geometry": {"coordinates":[50.28886,32.27919],"type":"Point"}
}