{
  "type": "Feature",
  "properties": {
    "gn:admin1_code":"29",
    "gn:asciiname":"Gahu'iyeh",
    "gn:country_code":"IR",
    "gn:dem":2461,
    "gn:feature_class":"P",
    "gn:feature_code":"PPL",
    "gn:name":"Gah\u016b\u2019\u012byeh",
    "gn:population":0,
    "gn:timezone":"Asia/Tehran",
    "iso:country":"IR",
    "name:ara_x_preferred":[
        "\u063a\u0647\u0648\u064a\u064a\u0629"
    ],
    "name:fas_x_preferred":[
        "\u06af\u0647\u0648\u0626\u064a\u0647"
    ],
    "name:fas_x_variant":[
        "Kah\u016b\u2019\u012byeh",
        "Gah\u016b\u2019\u012byeh",
        "\u06a9\u0647\u0648\u0626\u064a\u0647",
        "\u06af\u0647\u0648\u06cc\u06cc\u0647"
    ],
    "name:und_x_variant":[
        "Gahu",
        "\u06a9\u0647\u0648\u0626\u064a\u0647",
        "G\u0101h\u016b",
        "Gahook"
    ],
    "wof:name":"Gahu'iyeh",
    "wof:placetype":"locality"
},
  "geometry": {"coordinates":[57.41309,29.40501],"type":"Point"}
}