{
  "type": "Feature",
  "properties": {
    "gn:admin1_code":"35",
    "gn:asciiname":"Chalu",
    "gn:country_code":"IR",
    "gn:dem":1242,
    "gn:feature_class":"P",
    "gn:feature_code":"PPL",
    "gn:name":"Ch\u0101l\u016b",
    "gn:population":0,
    "gn:timezone":"Asia/Tehran",
    "iso:country":"IR",
    "name:fas_x_preferred":[
        "\u0686\u0627\u0644\u0648"
    ],
    "name:fas_x_variant":[
        "Ch\u0101l\u016b"
    ],
    "wof:name":"Chalu",
    "wof:placetype":"locality"
},
  "geometry": {"coordinates":[53.67095,36.29901],"type":"Point"}
}