{
  "type": "Feature",
  "properties": {
    "gn:admin1_code":"35.0",
    "gn:asciiname":"Shahrak-e Laleh",
    "gn:country_code":"IR",
    "gn:dem":550,
    "gn:feature_class":"P",
    "gn:feature_code":"PPL",
    "gn:name":"Shahrak-e L\u0101leh",
    "gn:population":0,
    "gn:timezone":"Asia/Tehran",
    "iso:country":"IR",
    "name:fas_x_preferred":[
        "Shahrak-e L\u0101leh"
    ],
    "name:fas_x_variant":[
        "\u0634\u0647\u0631\u06a9 \u0644\u0627\u0644\u0647"
    ],
    "name:und_x_variant":[
        "\u0634\u0647\u0631\u06a9 \u0644\u0627\u0644\u0647"
    ],
    "wof:name":"Shahrak-e Laleh",
    "wof:placetype":"locality"
},
  "geometry": {"coordinates":[51.30181,36.45992],"type":"Point"}
}