{
  "type": "Feature",
  "properties": {
    "gn:admin1_code":"42",
    "gn:asciiname":"Sahlabad",
    "gn:country_code":"IR",
    "gn:dem":1185,
    "gn:feature_class":"P",
    "gn:feature_code":"PPL",
    "gn:name":"Sahl\u0101b\u0101d",
    "gn:population":0,
    "gn:timezone":"Asia/Tehran",
    "iso:country":"IR",
    "name:fas_x_preferred":[
        "\u0633\u0647\u0644 \u0622\u0628\u0627\u062f"
    ],
    "name:fas_x_variant":[
        "Sahl\u0101b\u0101d"
    ],
    "name:und_x_variant":[
        "S\u0101lih\u0101b\u0101d",
        "\u015e\u0101le\u1e29\u0101b\u0101d"
    ],
    "name:urd_x_preferred":[
        "\u0633\u06c1\u0644\u0627\u0628\u0627\u062f"
    ],
    "wof:name":"Sahlabad",
    "wof:placetype":"locality"
},
  "geometry": {"coordinates":[58.70279,36.27375],"type":"Point"}
}