{
  "type": "Feature",
  "properties": {
    "gn:admin1_code":"8.0",
    "gn:asciiname":"Dizyen",
    "gn:country_code":"IR",
    "gn:dem":968,
    "gn:feature_class":"P",
    "gn:feature_code":"PPL",
    "gn:name":"D\u012bzyen",
    "gn:population":0,
    "gn:timezone":"Asia/Tehran",
    "iso:country":"IR",
    "name:fas_x_preferred":[
        "D\u012bzyen"
    ],
    "wof:name":"Dizyen",
    "wof:placetype":"locality"
},
  "geometry": {"coordinates":[49.00111,37.16611],"type":"Point"}
}