{
  "type": "Feature",
  "properties": {
    "gn:admin1_code":"1",
    "gn:asciiname":"Shah Galan",
    "gn:country_code":"IR",
    "gn:dem":1769,
    "gn:feature_class":"P",
    "gn:feature_code":"PPL",
    "gn:name":"Sh\u0101h Galan",
    "gn:population":0,
    "gn:timezone":"Asia/Tehran",
    "iso:country":"IR",
    "name:fas_x_preferred":[
        "\u0634\u0627\u0647 \u06af\u064e\u0644\u064e\u0646"
    ],
    "name:fas_x_variant":[
        "Sh\u0101h Galan"
    ],
    "wof:name":"Shah Galan",
    "wof:placetype":"locality"
},
  "geometry": {"coordinates":[44.37722,39.11917],"type":"Point"}
}