{
  "type": "Feature",
  "properties": {
    "gn:admin1_code":"13",
    "gn:asciiname":"Deh-e Kerisheh",
    "gn:country_code":"IR",
    "gn:dem":1527,
    "gn:feature_class":"P",
    "gn:feature_code":"PPL",
    "gn:name":"Deh-e Ker\u012bsheh",
    "gn:population":0,
    "gn:timezone":"Asia/Tehran",
    "iso:country":"IR",
    "name:fas_x_preferred":[
        "Deh-e Ker\u012bsheh"
    ],
    "wof:name":"Deh-e Kerisheh",
    "wof:placetype":"locality"
},
  "geometry": {"coordinates":[46.63806,34.18360999999999],"type":"Point"}
}