{
  "type": "Feature",
  "properties": {
    "gn:admin1_code":"28.0",
    "gn:asciiname":"Shaydabad",
    "gn:country_code":"IR",
    "gn:dem":1776,
    "gn:feature_class":"P",
    "gn:feature_code":"PPL",
    "gn:name":"Shayd\u0101b\u0101d",
    "gn:population":0,
    "gn:timezone":"Asia/Tehran",
    "iso:country":"IR",
    "name:ara_x_preferred":[
        "\u0634\u064a\u062f\u0622\u0628\u0627\u062f"
    ],
    "name:fas_x_preferred":[
        "Shayd\u0101b\u0101d"
    ],
    "name:fas_x_variant":[
        "\u0634\u06cc\u062f \u0622\u0628\u0627\u062f",
        "\u0634\u06cc\u062f\u0622\u0628\u0627\u062f"
    ],
    "wof:name":"Shaydabad",
    "wof:placetype":"locality"
},
  "geometry": {"coordinates":[50.39093,33.50797],"type":"Point"}
}