{
  "type": "Feature",
  "properties": {
    "gn:admin1_code":"16.0",
    "gn:asciiname":"`Isa Dar",
    "gn:country_code":"IR",
    "gn:dem":1639,
    "gn:feature_class":"P",
    "gn:feature_code":"PPL",
    "gn:name":"\u2018\u012as\u00e1 Dar",
    "gn:population":0,
    "gn:timezone":"Asia/Tehran",
    "iso:country":"IR",
    "name:fas_x_preferred":[
        "\u0639\u06cc\u0633\u06cc \u062f\u0631"
    ],
    "name:fas_x_variant":[
        "\u2018\u012as\u00e1 Dar"
    ],
    "wof:name":"`Isa Dar",
    "wof:placetype":"locality"
},
  "geometry": {"coordinates":[47.04057,35.46443],"type":"Point"}
}