{
  "type": "Feature",
  "properties": {
    "gn:admin1_code":"34.0",
    "gn:asciiname":"Dowzpa",
    "gn:country_code":"IR",
    "gn:dem":2152,
    "gn:feature_class":"P",
    "gn:feature_code":"PPL",
    "gn:name":"Dowzp\u0101",
    "gn:population":0,
    "gn:timezone":"Asia/Tehran",
    "iso:country":"IR",
    "name:fas_x_preferred":[
        "\u062f\u0648\u0632\u067e\u0627"
    ],
    "name:fas_x_variant":[
        "Dow Z\u012b\u0101",
        "Dowzp\u0101",
        "\u062f\u064f\u0648 \u0632\u064a\u0627"
    ],
    "name:und_x_variant":[
        "Do Z\u012b\u0101"
    ],
    "wof:name":"Dowzpa",
    "wof:placetype":"locality"
},
  "geometry": {"coordinates":[50.9414,33.946],"type":"Point"}
}