{
  "type": "Feature",
  "properties": {
    "gn:admin1_code":"25",
    "gn:asciiname":"Torud",
    "gn:country_code":"IR",
    "gn:dem":797,
    "gn:feature_class":"P",
    "gn:feature_code":"PPL",
    "gn:name":"Tor\u016bd",
    "gn:population":0,
    "gn:timezone":"Asia/Tehran",
    "iso:country":"IR",
    "name:fas_x_preferred":[
        "\u0637\u0631\u0648\u062f"
    ],
    "name:fas_x_variant":[
        "\u0162or\u016bd",
        "Tor\u016bd",
        "\u062a\u0631\u0648\u062f",
        "Tur\u016bd"
    ],
    "name:und_x_variant":[
        "Turut",
        "Touroud",
        "Tur\u016bd"
    ],
    "wof:name":"Torud",
    "wof:placetype":"locality"
},
  "geometry": {"coordinates":[55.01536,35.42781],"type":"Point"}
}