{
  "type": "Feature",
  "properties": {
    "gn:admin1_code":"29",
    "gn:asciiname":"Zeh-e Kalut",
    "gn:country_code":"IR",
    "gn:dem":386,
    "gn:feature_class":"P",
    "gn:feature_code":"PPL",
    "gn:name":"Zeh-e Kal\u016bt",
    "gn:population":0,
    "gn:timezone":"Asia/Tehran",
    "iso:country":"IR",
    "name:fas_x_preferred":[
        "\u0632\u0647 \u06a9\u0644\u0648\u062a"
    ],
    "name:fas_x_variant":[
        "Zeh-e Kal\u016bt"
    ],
    "wof:name":"Zeh-e Kalut",
    "wof:placetype":"locality"
},
  "geometry": {"coordinates":[58.58682,27.79256],"type":"Point"}
}