{
  "type": "Feature",
  "properties": {
    "gn:admin1_code":"42",
    "gn:asciiname":"Cheshmeh Sefid",
    "gn:country_code":"IR",
    "gn:dem":1200,
    "gn:feature_class":"P",
    "gn:feature_code":"PPL",
    "gn:name":"Cheshmeh Sef\u012bd",
    "gn:population":0,
    "gn:timezone":"Asia/Tehran",
    "iso:country":"IR",
    "name:fas_x_preferred":[
        "Cheshmeh Sef\u012bd"
    ],
    "name:fas_x_variant":[
        "\u0686\u0634\u0645\u0647 \u0633\u0641\u064a\u062f"
    ],
    "name:und_x_variant":[
        "\u0686\u0634\u0645\u0647 \u0633\u0641\u064a\u062f"
    ],
    "wof:name":"Cheshmeh Sefid",
    "wof:placetype":"locality"
},
  "geometry": {"coordinates":[57.4934,35.41705],"type":"Point"}
}