{
  "type": "Feature",
  "properties": {
    "gn:admin1_code":"5.0",
    "gn:asciiname":"Malmula-ye Bala",
    "gn:country_code":"IR",
    "gn:dem":897,
    "gn:feature_class":"P",
    "gn:feature_code":"PPL",
    "gn:name":"M\u0101lm\u016bl\u0101-ye B\u0101l\u0101",
    "gn:population":0,
    "gn:timezone":"Asia/Tehran",
    "iso:country":"IR",
    "name:fas_x_preferred":[
        "\u0645\u0627\u0644\u0645\u0648\u0644\u0627\u06cc \u0628\u0627\u0644\u0627"
    ],
    "name:fas_x_variant":[
        "M\u0101lm\u016bl\u0101-ye B\u0101l\u0101",
        "\u0645\u0627\u0644 \u0645\u0648\u0644\u0627\u06cc \u0639\u0644\u06cc\u0627"
    ],
    "name:und_x_variant":[
        "M\u0101lm\u016bl\u0101-ye \u2018Oly\u0101"
    ],
    "wof:name":"Malmula-ye Bala",
    "wof:placetype":"locality"
},
  "geometry": {"coordinates":[50.39498,30.99911],"type":"Point"}
}