{
  "type": "Feature",
  "properties": {
    "gn:admin1_code":"36",
    "gn:asciiname":"Paband",
    "gn:country_code":"IR",
    "gn:dem":2005,
    "gn:feature_class":"P",
    "gn:feature_code":"PPL",
    "gn:name":"P\u0101band",
    "gn:population":0,
    "gn:timezone":"Asia/Tehran",
    "iso:country":"IR",
    "name:azb_x_preferred":[
        "\u067e\u0627\u0628\u0646\u062f"
    ],
    "name:fas_x_preferred":[
        "\u067e\u0627\u0628\u0646\u062f"
    ],
    "name:fas_x_variant":[
        "P\u0101band"
    ],
    "name:und_x_variant":[
        "Pavand"
    ],
    "wof:name":"Paband",
    "wof:placetype":"locality"
},
  "geometry": {"coordinates":[48.77515,36.26588],"type":"Point"}
}