{
  "type": "Feature",
  "properties": {
    "gn:admin1_code":"8.0",
    "gn:asciiname":"Parm Kuh",
    "gn:country_code":"IR",
    "gn:dem":876,
    "gn:feature_class":"P",
    "gn:feature_code":"PPL",
    "gn:name":"Parm K\u016bh",
    "gn:population":0,
    "gn:timezone":"Asia/Tehran",
    "iso:country":"IR",
    "name:fas_x_preferred":[
        "\u067e\u0631\u0645 \u06a9\u0648\u0647"
    ],
    "name:fas_x_variant":[
        "\u0686\u0645\u062a\u0648 \u06a9\u0634"
    ],
    "name:und_x_variant":[
        "Parm K\u016bh",
        "Chamt\u016b Kesh"
    ],
    "wof:name":"Parm Kuh",
    "wof:placetype":"locality"
},
  "geometry": {"coordinates":[50.16186,36.84152],"type":"Point"}
}