{
  "type": "Feature",
  "properties": {
    "gn:admin1_code":"1",
    "gn:asciiname":"Salah-e Bala",
    "gn:country_code":"IR",
    "gn:dem":2447,
    "gn:feature_class":"P",
    "gn:feature_code":"PPL",
    "gn:name":"\u015eal\u0101\u1e29-e B\u0101l\u0101",
    "gn:population":0,
    "gn:timezone":"Asia/Tehran",
    "iso:country":"IR",
    "name:fas_x_preferred":[
        "\u015eal\u0101\u1e29-e B\u0101l\u0101"
    ],
    "wof:name":"Salah-e Bala",
    "wof:placetype":"locality"
},
  "geometry": {"coordinates":[44.46667,38.96667],"type":"Point"}
}