{
  "type": "Feature",
  "properties": {
    "gn:admin1_code":"23",
    "gn:asciiname":"Naveh Changizi",
    "gn:country_code":"IR",
    "gn:dem":1393,
    "gn:feature_class":"P",
    "gn:feature_code":"PPL",
    "gn:name":"N\u0101veh Chang\u012bz\u012b",
    "gn:population":0,
    "gn:timezone":"Asia/Tehran",
    "iso:country":"IR",
    "name:fas_x_preferred":[
        "\u0646\u0627\u0648\u0647 \u0686\u0646\u06af\u06cc\u0632\u06cc"
    ],
    "name:fas_x_variant":[
        "\u06af\u0644 \u06a9\u0631\u0645"
    ],
    "name:und_x_variant":[
        "N\u0101veh Chang\u012bz\u012b",
        "Gol Karam"
    ],
    "wof:name":"Naveh Changizi",
    "wof:placetype":"locality"
},
  "geometry": {"coordinates":[47.41704,33.54396],"type":"Point"}
}