{
  "type": "Feature",
  "properties": {
    "gn:admin1_code":"23.0",
    "gn:asciiname":"Zahrakar",
    "gn:country_code":"IR",
    "gn:dem":1024,
    "gn:feature_class":"P",
    "gn:feature_code":"PPL",
    "gn:name":"Zahr\u0101k\u0101r",
    "gn:population":0,
    "gn:timezone":"Asia/Tehran",
    "iso:country":"IR",
    "name:fas_x_preferred":[
        "Zahr\u0101k\u0101r"
    ],
    "name:fas_x_variant":[
        "\u0632\u0647\u0631\u0627\u06a9\u0627\u0631"
    ],
    "name:und_x_variant":[
        "\u0632\u0647\u0631\u0627\u06a9\u0627\u0631"
    ],
    "wof:name":"Zahrakar",
    "wof:placetype":"locality"
},
  "geometry": {"coordinates":[48.0492,33.4858],"type":"Point"}
}