{
  "type": "Feature",
  "properties": {
    "gn:admin1_code":"10",
    "gn:asciiname":"Sarkan",
    "gn:country_code":"IR",
    "gn:dem":755,
    "gn:feature_class":"P",
    "gn:feature_code":"PPL",
    "gn:name":"Sark\u0101n",
    "gn:population":0,
    "gn:timezone":"Asia/Tehran",
    "iso:country":"IR",
    "name:fas_x_preferred":[
        "\u0633\u0631\u06a9\u0627\u0646"
    ],
    "name:fas_x_variant":[
        "Sark\u0101n"
    ],
    "name:und_x_variant":[
        "Serk\u0101n"
    ],
    "wof:name":"Sarkan",
    "wof:placetype":"locality"
},
  "geometry": {"coordinates":[46.8369,33.546],"type":"Point"}
}