{
  "type": "Feature",
  "properties": {
    "gn:admin1_code":"42",
    "gn:asciiname":"Ja`fari",
    "gn:country_code":"IR",
    "gn:dem":888,
    "gn:feature_class":"P",
    "gn:feature_code":"PPL",
    "gn:name":"Ja\u2018far\u012b",
    "gn:population":0,
    "gn:timezone":"Asia/Tehran",
    "iso:country":"IR",
    "name:fas_x_preferred":[
        "Ja\u2018far\u012b"
    ],
    "name:und_x_variant":[
        "Ab\u016b Ja\u2018far\u012b",
        "Shafri"
    ],
    "wof:name":"Ja`fari",
    "wof:placetype":"locality"
},
  "geometry": {"coordinates":[57.46666999999999,33.81667],"type":"Point"}
}