{
  "type": "Feature",
  "properties": {
    "gn:admin1_code":"8",
    "gn:asciiname":"Rud Bardeh",
    "gn:country_code":"IR",
    "gn:dem":26,
    "gn:feature_class":"P",
    "gn:feature_code":"PPL",
    "gn:name":"R\u016bd Bardeh",
    "gn:population":0,
    "gn:timezone":"Asia/Tehran",
    "iso:country":"IR",
    "name:fas_x_preferred":[
        "R\u016bdbordeh"
    ],
    "name:fas_x_variant":[
        "R\u016bd Bardeh",
        "\u0631\u0648\u062f \u0628\u0631\u062f\u0647"
    ],
    "name:und_x_variant":[
        "Rood Bardeh",
        "Rudburde",
        "R\u016bd Bardeh",
        "\u0631\u0648\u062f \u0628\u0631\u062f\u0647"
    ],
    "wof:name":"Rud Bardeh",
    "wof:placetype":"locality"
},
  "geometry": {"coordinates":[49.6973,37.18818],"type":"Point"}
}