{
  "type": "Feature",
  "properties": {
    "gn:admin1_code":"16.0",
    "gn:asciiname":"Noshur-e Sofla",
    "gn:country_code":"IR",
    "gn:dem":1420,
    "gn:elevation":"0.0",
    "gn:feature_class":"P",
    "gn:feature_code":"PPL",
    "gn:name":"Nosh\u016br-e Sofl\u00e1",
    "gn:population":0,
    "gn:timezone":"Asia/Tehran",
    "iso:country":"IR",
    "name:ceb_x_preferred":[
        "Nosh\u016br-e Sofl\u00e1"
    ],
    "name:fas_x_preferred":[
        "\u0622\u0633\u064a\u0627\u0628 \u0628\u064e\u0631\u0642"
    ],
    "name:fas_x_variant":[
        "\u0646\u0634\u0648\u0631 \u0633\u0641\u0644\u06cc",
        "Nosh\u016br-e Sofl\u00e1",
        "\u0100s\u012b\u0101b Barq"
    ],
    "name:swe_x_preferred":[
        "Nosh\u016br-e Sofl\u00e1"
    ],
    "wof:name":"Noshur-e Sofla",
    "wof:placetype":"locality"
},
  "geometry": {"coordinates":[46.9482,35.0278],"type":"Point"}
}