{
  "type": "Feature",
  "properties": {
    "gn:admin1_code":"38.0",
    "gn:asciiname":"Abyek-e Pa'in",
    "gn:country_code":"IR",
    "gn:dem":1369,
    "gn:feature_class":"P",
    "gn:feature_code":"PPL",
    "gn:name":"\u0100byek-e P\u0101\u2019\u012bn",
    "gn:population":0,
    "gn:timezone":"Asia/Tehran",
    "iso:country":"IR",
    "name:ara_x_preferred":[
        "\u0627\u0628\u064a\u0643 \u0627\u0644\u0633\u0641\u0644\u064a"
    ],
    "name:ceb_x_preferred":[
        "\u0100byek-e P\u0101'\u012bn"
    ],
    "name:fas_x_preferred":[
        "\u0622\u0628\u064a\u0650\u0643\u0650 \u0633\u064f\u0641\u0644\u0627"
    ],
    "name:fas_x_variant":[
        "\u0100byek-e Sofl\u0101",
        "Abiak P\u0101\u012bn",
        "\u0100byek-e Vasa\u0163\u012b",
        "\u0622\u0628\u064a\u0650\u0643\u0650 \u0648\u064e\u0633\u064e\u0637\u06cc",
        "\u0100byek-e P\u0101\u2019\u012bn",
        "\u0622\u0628\u064a\u06a9 \u067e\u0627\u0626\u064a\u0646",
        "\u0622\u0628\u064a\u06a9 \u0633\u0641\u0644\u06cc",
        "\u0622\u0628\u06cc\u06a9 \u0633\u0641\u0644\u06cc"
    ],
    "name:und_x_variant":[
        "\u0100byek-e Sofl\u00e1"
    ],
    "wof:name":"Abyek-e Pa'in",
    "wof:placetype":"locality"
},
  "geometry": {"coordinates":[50.55346,36.05415],"type":"Point"}
}