{
  "type": "Feature",
  "properties": {
    "gn:admin1_code":"41",
    "gn:asciiname":"Kalateh-ye Kal Bisheh",
    "gn:country_code":"IR",
    "gn:dem":1637,
    "gn:feature_class":"P",
    "gn:feature_code":"PPL",
    "gn:name":"Kal\u0101teh-ye Kal B\u012bsheh",
    "gn:population":0,
    "gn:timezone":"Asia/Tehran",
    "iso:country":"IR",
    "name:fas_x_preferred":[
        "Kal\u0101teh-ye Kal B\u012bsheh"
    ],
    "name:fas_x_variant":[
        "\u06a9\u0644\u0627\u062a\u0647 \u06a9\u0644 \u0628\u064a\u0634\u0647",
        "K\u0101l\u0101teh Kal B\u012bsheh"
    ],
    "name:und_x_variant":[
        "K\u0101l\u0101teh Kal B\u012bsheh",
        "\u06a9\u0644\u0627\u062a\u0647 \u06a9\u0644 \u0628\u064a\u0634\u0647"
    ],
    "wof:name":"Kalateh-ye Kal Bisheh",
    "wof:placetype":"locality"
},
  "geometry": {"coordinates":[59.03536999999999,32.46663],"type":"Point"}
}