{
  "type": "Feature",
  "properties": {
    "gn:admin1_code":"34.0",
    "gn:asciiname":"`Aliabad-e Kuh Qonaq",
    "gn:country_code":"IR",
    "gn:dem":1400,
    "gn:feature_class":"P",
    "gn:feature_code":"PPL",
    "gn:name":"\u2018Al\u012b\u0101b\u0101d-e K\u016bh Qon\u0101q",
    "gn:population":0,
    "gn:timezone":"Asia/Tehran",
    "iso:country":"IR",
    "name:fas_x_preferred":[
        "\u0639\u0644\u06cc \u0622\u0628\u0627\u062f \u06a9\u0648\u0647 \u0642\u0646\u0627\u0642"
    ],
    "name:und_x_variant":[
        "\u2018Al\u012b\u0101b\u0101d-e K\u016bh Qon\u0101q"
    ],
    "wof:name":"`Aliabad-e Kuh Qonaq",
    "wof:placetype":"locality"
},
  "geometry": {"coordinates":[50.64211,35.45725],"type":"Point"}
}