{
  "type": "Feature",
  "properties": {
    "gn:admin1_code":"34.0",
    "gn:asciiname":"Ormakan",
    "gn:country_code":"IR",
    "gn:dem":1133,
    "gn:feature_class":"P",
    "gn:feature_code":"PPL",
    "gn:name":"Ormakan",
    "gn:population":0,
    "gn:timezone":"Asia/Tehran",
    "iso:country":"IR",
    "name:fas_x_preferred":[
        "\u0627\u064f\u0631\u0645\u064e\u0643\u064e\u0646"
    ],
    "wof:name":"Ormakan",
    "wof:placetype":"locality"
},
  "geometry": {"coordinates":[50.49389,34.69861],"type":"Point"}
}