{
  "type": "Feature",
  "properties": {
    "gn:admin1_code":"5.0",
    "gn:asciiname":"Parchin",
    "gn:country_code":"IR",
    "gn:dem":1953,
    "gn:feature_class":"P",
    "gn:feature_code":"PPL",
    "gn:name":"Parch\u012bn",
    "gn:population":0,
    "gn:timezone":"Asia/Tehran",
    "iso:country":"IR",
    "name:fas_x_preferred":[
        "Parch\u012bn"
    ],
    "name:fas_x_variant":[
        "\u067e\u0631\u0686\u06cc\u0646",
        "\u067e\u0627\u0631\u0686\u06cc\u0646"
    ],
    "name:fra_x_preferred":[
        "Partchine"
    ],
    "name:und_x_variant":[
        "\u067e\u0631\u0686\u06cc\u0646"
    ],
    "wof:name":"Parchin",
    "wof:placetype":"locality"
},
  "geometry": {"coordinates":[50.74847000000001,30.51428],"type":"Point"}
}