{
  "type": "Feature",
  "properties": {
    "gn:admin1_code":"4.0",
    "gn:asciiname":"Gazani-ye Miran",
    "gn:country_code":"IR",
    "gn:dem":36,
    "gn:feature_class":"P",
    "gn:feature_code":"PPL",
    "gn:name":"Gaz\u0101n\u012b-ye M\u012br\u0101n",
    "gn:population":0,
    "gn:timezone":"Asia/Tehran",
    "iso:country":"IR",
    "name:ara_x_preferred":[
        "\u063a\u0632\u0627\u0646\u064a \u0628\u0627\u064a\u064a\u0646"
    ],
    "name:fas_x_preferred":[
        "Gaz\u0101n\u012b-ye M\u012br\u0101n"
    ],
    "name:fas_x_variant":[
        "Gaz\u0101n\u012b-ye P\u0101\u2019\u012bn",
        "\u06af\u0632\u0627\u0646\u06cc \u0645\u06cc\u0631\u0627\u0646",
        "\u06af\u0632\u0627\u0646\u06cc \u067e\u0627\u06cc\u06cc\u0646"
    ],
    "wof:name":"Gazani-ye Miran",
    "wof:placetype":"locality"
},
  "geometry": {"coordinates":[61.06419,25.60576],"type":"Point"}
}