{
  "type": "Feature",
  "properties": {
    "gn:admin1_code":"36",
    "gn:asciiname":"Cha-ye Qeshlaq",
    "gn:country_code":"IR",
    "gn:dem":1998,
    "gn:feature_class":"P",
    "gn:feature_code":"PPL",
    "gn:name":"Ch\u0101-ye Qeshl\u0101q",
    "gn:population":0,
    "gn:timezone":"Asia/Tehran",
    "iso:country":"IR",
    "name:fas_x_preferred":[
        "\u0686\u0627\u06cc \u0642\u0634\u0644\u0627\u0642\u06cc"
    ],
    "name:fas_x_variant":[
        "\u0686\u0627\u06cc \u0642\u0634\u0644\u0627\u0642"
    ],
    "name:und_x_variant":[
        "Ch\u0101-ye Qeshl\u0101q",
        "Ch\u0101-ye Qeshl\u0101q\u012b"
    ],
    "wof:name":"Cha-ye Qeshlaq",
    "wof:placetype":"locality"
},
  "geometry": {"coordinates":[47.28166,36.8046],"type":"Point"}
}