{
  "type": "Feature",
  "properties": {
    "gn:admin1_code":"4.0",
    "gn:asciiname":"Sadaf Sanchuli",
    "gn:country_code":"IR",
    "gn:dem":480,
    "gn:feature_class":"P",
    "gn:feature_code":"PPL",
    "gn:name":"\u015eadaf Sanch\u016bl\u012b",
    "gn:population":0,
    "gn:timezone":"Asia/Tehran",
    "iso:country":"IR",
    "name:fas_x_preferred":[
        "\u0635\u062f\u0641 \u0633\u0646\u0686\u0648\u0644\u06cc"
    ],
    "name:fas_x_variant":[
        "\u015eadaf Sanch\u016bl\u012b"
    ],
    "wof:name":"Sadaf Sanchuli",
    "wof:placetype":"locality"
},
  "geometry": {"coordinates":[61.5582,31.2742],"type":"Point"}
}