{
  "type": "Feature",
  "properties": {
    "gn:admin1_code":"38",
    "gn:asciiname":"Shenin",
    "gn:country_code":"IR",
    "gn:dem":1491,
    "gn:feature_class":"P",
    "gn:feature_code":"PPL",
    "gn:name":"Shen\u012bn",
    "gn:population":0,
    "gn:timezone":"Asia/Tehran",
    "iso:country":"IR",
    "name:ceb_x_preferred":[
        "Shan\u012bn"
    ],
    "name:fas_x_preferred":[
        "\u0634\u0646\u064a\u0646"
    ],
    "name:fas_x_variant":[
        "Shen\u012bn",
        "\u0634\u0646\u064a\u0646 \u0642\u0627\u0642\u0627\u0632\u0627\u0646",
        "\u0634\u0646\u06cc\u0646"
    ],
    "name:swe_x_preferred":[
        "Shan\u012bn"
    ],
    "name:und_x_variant":[
        "Shen\u012bn Q\u0101qz\u0101n",
        "Shanin Ghaghzan Sharghi",
        "Shen\u012bn Q\u0101q\u0101z\u0101n"
    ],
    "wof:name":"Shenin",
    "wof:placetype":"locality"
},
  "geometry": {"coordinates":[49.60607,36.08574],"type":"Point"}
}