{
  "type": "Feature",
  "properties": {
    "gn:admin1_code":"34",
    "gn:asciiname":"Sar Chal",
    "gn:country_code":"IR",
    "gn:dem":2260,
    "gn:feature_class":"P",
    "gn:feature_code":"PPL",
    "gn:name":"Sar Ch\u0101l",
    "gn:population":0,
    "gn:timezone":"Asia/Tehran",
    "iso:country":"IR",
    "name:fas_x_preferred":[
        "\u0633\u0631 \u0686\u0627\u0644"
    ],
    "name:fas_x_variant":[
        "Sar Ch\u0101l"
    ],
    "wof:name":"Sar Chal",
    "wof:placetype":"locality"
},
  "geometry": {"coordinates":[49.12317,34.15486],"type":"Point"}
}