{
  "type": "Feature",
  "properties": {
    "gn:admin1_code":"4.0",
    "gn:asciiname":"Darrudok",
    "gn:cc2":"IR",
    "gn:country_code":"IR",
    "gn:dem":737,
    "gn:feature_class":"P",
    "gn:feature_code":"PPL",
    "gn:name":"Darr\u016bdok",
    "gn:population":0,
    "gn:timezone":"Asia/Tehran",
    "iso:country":"IR",
    "name:fas_x_preferred":[
        "Darr\u016bdok"
    ],
    "name:und_x_variant":[
        "Darr\u016bdak",
        "Dar R\u016bdk"
    ],
    "wof:name":"Darrudok",
    "wof:placetype":"locality"
},
  "geometry": {"coordinates":[60.01806,27.65889],"type":"Point"}
}