{
  "type": "Feature",
  "properties": {
    "gn:admin1_code":"7",
    "gn:asciiname":"Vakilabad",
    "gn:country_code":"IR",
    "gn:dem":1386,
    "gn:feature_class":"P",
    "gn:feature_code":"PPL",
    "gn:name":"Vak\u012bl\u0101b\u0101d",
    "gn:population":0,
    "gn:timezone":"Asia/Tehran",
    "iso:country":"IR",
    "name:fas_x_preferred":[
        "\u0648\u06a9\u06cc\u0644 \u0622\u0628\u0627\u062f"
    ],
    "name:fas_x_variant":[
        "Vak\u012bl\u0101b\u0101d"
    ],
    "wof:name":"Vakilabad",
    "wof:placetype":"locality"
},
  "geometry": {"coordinates":[54.05095,28.92804000000001],"type":"Point"}
}