{
  "type": "Feature",
  "properties": {
    "gn:admin1_code":"8.0",
    "gn:asciiname":"Abdarbu Chal",
    "gn:country_code":"IR",
    "gn:dem":1145,
    "gn:feature_class":"P",
    "gn:feature_code":"PPL",
    "gn:name":"\u0100bd\u0101rb\u016b Ch\u0101l",
    "gn:population":0,
    "gn:timezone":"Asia/Tehran",
    "iso:country":"IR",
    "name:fas_x_preferred":[
        "\u0100bd\u0101rb\u016b Ch\u0101l"
    ],
    "name:fas_x_variant":[
        "\u0622\u0628\u062f\u0627\u0631\u0628\u0648 \u0686\u0627\u0644",
        "\u0627\u0628\u062f\u0648 \u0686\u0627\u0644",
        "\u0622\u0628\u062f\u0648\u0686\u0627\u0644"
    ],
    "name:msa_x_preferred":[
        "Abdu Chal"
    ],
    "name:ukr_x_preferred":[
        "\u0410\u0431\u0434\u0443-\u0427\u0430\u043b"
    ],
    "name:und_x_variant":[
        "Abd\u016b Ch\u0101l"
    ],
    "wof:name":"Abdarbu Chal",
    "wof:placetype":"locality"
},
  "geometry": {"coordinates":[50.25401,36.81117],"type":"Point"}
}