{
  "type": "Feature",
  "properties": {
    "gn:admin1_code":"33.0",
    "gn:asciiname":"Moghar",
    "gn:country_code":"IR",
    "gn:dem":966,
    "gn:feature_class":"P",
    "gn:feature_code":"PPL",
    "gn:name":"Mogh\u0101r",
    "gn:population":0,
    "gn:timezone":"Asia/Tehran",
    "iso:country":"IR",
    "name:fas_x_preferred":[
        "\u0642\u0634\u0644\u0627\u0642 \u0645\u063a\u0627\u0631"
    ],
    "name:fas_x_variant":[
        "Qeshl\u0101q Mogh\u0101r",
        "\u0645\u063a\u0627\u0631"
    ],
    "name:und_x_variant":[
        "Mogh\u0101r"
    ],
    "wof:name":"Moghar",
    "wof:placetype":"locality"
},
  "geometry": {"coordinates":[47.44761,38.61163],"type":"Point"}
}