{
  "type": "Feature",
  "properties": {
    "gn:admin1_code":"5",
    "gn:asciiname":"Gargar",
    "gn:country_code":"IR",
    "gn:dem":1095,
    "gn:feature_class":"P",
    "gn:feature_code":"PPL",
    "gn:name":"Gargar",
    "gn:population":0,
    "gn:timezone":"Asia/Tehran",
    "iso:country":"IR",
    "name:fas_x_preferred":[
        "\u06af\u0631\u06af\u0631"
    ],
    "name:und_x_variant":[
        "\u06af\u0631\u06af\u0631"
    ],
    "wof:name":"Gargar",
    "wof:placetype":"locality"
},
  "geometry": {"coordinates":[50.65875,31.41683],"type":"Point"}
}