{
  "type": "Feature",
  "properties": {
    "gn:admin1_code":"16",
    "gn:asciiname":"Sarvaleh",
    "gn:country_code":"IR",
    "gn:dem":2047,
    "gn:feature_class":"P",
    "gn:feature_code":"PPL",
    "gn:name":"Sarv\u0101leh",
    "gn:population":0,
    "gn:timezone":"Asia/Tehran",
    "iso:country":"IR",
    "name:fas_x_preferred":[
        "\u0633\u0631\u0648\u0627\u0644\u0647"
    ],
    "name:fas_x_variant":[
        "Sarv\u0101leh"
    ],
    "name:und_x_variant":[
        "Sarw\u0101leh"
    ],
    "wof:name":"Sarvaleh",
    "wof:placetype":"locality"
},
  "geometry": {"coordinates":[47.23143,35.21597],"type":"Point"}
}