{
  "type": "Feature",
  "properties": {
    "gn:admin1_code":"8",
    "gn:asciiname":"Do Rah",
    "gn:country_code":"IR",
    "gn:dem":245,
    "gn:feature_class":"P",
    "gn:feature_code":"PPL",
    "gn:name":"Do R\u0101h",
    "gn:population":0,
    "gn:timezone":"Asia/Tehran",
    "iso:country":"IR",
    "name:ara_x_preferred":[
        "\u062f\u0648\u0631\u0627\u0647"
    ],
    "name:fas_x_preferred":[
        "\u062f\u0648 \u0631\u0627\u0647"
    ],
    "name:fas_x_variant":[
        "Do R\u0101h",
        "\u062f\u0648\u0631\u0627\u0647"
    ],
    "name:msa_x_preferred":[
        "Do Rah"
    ],
    "wof:name":"Do Rah",
    "wof:placetype":"locality"
},
  "geometry": {"coordinates":[49.0394,37.5207],"type":"Point"}
}