{
  "type": "Feature",
  "properties": {
    "gn:admin1_code":"41",
    "gn:asciiname":"Mazar-e Astarabad",
    "gn:country_code":"IR",
    "gn:dem":1375,
    "gn:feature_class":"P",
    "gn:feature_code":"PPL",
    "gn:name":"Maz\u0101r-e Astar\u0101b\u0101d",
    "gn:population":0,
    "gn:timezone":"Asia/Tehran",
    "iso:country":"IR",
    "name:fas_x_preferred":[
        "\u0645\u0632\u0627\u0631 \u0627\u0633\u062a\u0631 \u0622\u0628\u0627\u062f"
    ],
    "name:fas_x_variant":[
        "Maz\u0101r-e Astar\u0101b\u0101d"
    ],
    "name:und_x_variant":[
        "Maz\u0101r-i-Aster\u0101b\u0101d"
    ],
    "wof:name":"Mazar-e Astarabad",
    "wof:placetype":"locality"
},
  "geometry": {"coordinates":[59.30105,33.78274],"type":"Point"}
}