{
  "type": "Feature",
  "properties": {
    "gn:admin1_code":"35",
    "gn:asciiname":"Kiadeh",
    "gn:country_code":"IR",
    "gn:dem":1097,
    "gn:feature_class":"P",
    "gn:feature_code":"PPL",
    "gn:name":"K\u012b\u0101deh",
    "gn:population":0,
    "gn:timezone":"Asia/Tehran",
    "iso:country":"IR",
    "name:fas_x_preferred":[
        "\u0643\u064a\u0627\u062f\u0647"
    ],
    "name:fas_x_variant":[
        "\u0643\u064a\u0651\u0627 \u062f\u0650\u0647",
        "\u0643\u0650\u064a\u0627 \u062f\u0650\u0647",
        "K\u012b\u0101deh"
    ],
    "name:und_x_variant":[
        "Key\u0101 Deh",
        "K\u012by\u0101 Deh"
    ],
    "wof:name":"Kiadeh",
    "wof:placetype":"locality"
},
  "geometry": {"coordinates":[53.47251,36.22458],"type":"Point"}
}