{
  "type": "Feature",
  "properties": {
    "gn:admin1_code":"5",
    "gn:asciiname":"Gusheh",
    "gn:country_code":"IR",
    "gn:dem":1841,
    "gn:feature_class":"P",
    "gn:feature_code":"PPL",
    "gn:name":"G\u016bsheh",
    "gn:population":0,
    "gn:timezone":"Asia/Tehran",
    "iso:country":"IR",
    "name:fas_x_preferred":[
        "\u06af\u0648\u0634\u0650\u06c0 \u0634\u0627\u0647\u0632\u0627\u062f\u0650\u0647 \u0642\u0627\u0633\u0650\u0645"
    ],
    "name:fas_x_variant":[
        "G\u016bsheh-ye Sh\u0101hz\u0101deh Q\u0101sem",
        "G\u016bsheh Sh\u0101hz\u0101deh Q\u0101sem",
        "G\u016bsheh",
        "\u06af\u0648\u0634\u0647"
    ],
    "name:und_x_variant":[
        "G\u016bsheh",
        "\u06af\u0648\u0634\u0647"
    ],
    "wof:name":"Gusheh",
    "wof:placetype":"locality"
},
  "geometry": {"coordinates":[51.53225,30.73119],"type":"Point"}
}