{
  "type": "Feature",
  "properties": {
    "gn:admin1_code":"16",
    "gn:asciiname":"Qameshlu",
    "gn:country_code":"IR",
    "gn:dem":1751,
    "gn:feature_class":"P",
    "gn:feature_code":"PPL",
    "gn:name":"Qameshl\u016b",
    "gn:population":0,
    "gn:timezone":"Asia/Tehran",
    "iso:country":"IR",
    "name:aze_x_preferred":[
        "Qam\u0131\u015fl\u0131"
    ],
    "name:fas_x_preferred":[
        "\u0642\u0645\u0634 \u0644\u0648"
    ],
    "name:fas_x_variant":[
        "Qameshl\u016b"
    ],
    "wof:name":"Qameshlu",
    "wof:placetype":"locality"
},
  "geometry": {"coordinates":[47.63513,35.94306],"type":"Point"}
}