{
  "type": "Feature",
  "properties": {
    "gn:admin1_code":"42",
    "gn:asciiname":"Davodli",
    "gn:country_code":"IR",
    "gn:dem":1364,
    "gn:feature_class":"P",
    "gn:feature_code":"PPL",
    "gn:name":"D\u0101vodl\u012b",
    "gn:population":0,
    "gn:timezone":"Asia/Tehran",
    "iso:country":"IR",
    "name:fas_x_preferred":[
        "D\u0101vodl\u012b"
    ],
    "name:fas_x_variant":[
        "D\u0101v\u016bdl\u012b",
        "\u062f\u0627\u0648\u062f\u0644\u06cc"
    ],
    "name:und_x_variant":[
        "\u062f\u0627\u0648\u062f\u0644\u06cc"
    ],
    "wof:name":"Davodli",
    "wof:placetype":"locality"
},
  "geometry": {"coordinates":[58.65484,37.01377],"type":"Point"}
}