{
  "type": "Feature",
  "properties": {
    "gn:admin1_code":"29",
    "gn:asciiname":"Keykhosravi",
    "gn:country_code":"IR",
    "gn:dem":2441,
    "gn:feature_class":"P",
    "gn:feature_code":"PPL",
    "gn:name":"Keykhosrav\u012b",
    "gn:population":0,
    "gn:timezone":"Asia/Tehran",
    "iso:country":"IR",
    "name:ara_x_preferred":[
        "\u06a9\u064a\u062e\u0633\u0631\u0648\u064a"
    ],
    "name:ceb_x_preferred":[
        "Keykhosrav\u012b"
    ],
    "name:fas_x_preferred":[
        "\u06a9\u06cc\u062e\u0633\u0631\u0648\u06cc"
    ],
    "name:fas_x_variant":[
        "Keykhosrav\u012b"
    ],
    "name:swe_x_preferred":[
        "Keykhosrav\u012b"
    ],
    "name:und_x_variant":[
        "Keykhosray\u012b"
    ],
    "wof:name":"Keykhosravi",
    "wof:placetype":"locality"
},
  "geometry": {"coordinates":[56.6439,29.6175],"type":"Point"}
}