{
  "type": "Feature",
  "properties": {
    "gn:admin1_code":"7",
    "gn:asciiname":"Kupon-e Sorna",
    "gn:country_code":"IR",
    "gn:dem":786,
    "gn:feature_class":"P",
    "gn:feature_code":"PPL",
    "gn:name":"K\u016bpon-e Sorn\u0101",
    "gn:population":0,
    "gn:timezone":"Asia/Tehran",
    "iso:country":"IR",
    "name:fas_x_preferred":[
        "K\u016bpon-e Sorn\u0101"
    ],
    "name:fas_x_variant":[
        "P\u016bzeh-ye Sorn\u0101",
        "\u06a9\u0648\u067e\u0646 \u0633\u0631\u0646\u0627",
        "\u067e\u0648\u0632\u0647 \u0633\u0631\u0646\u0627"
    ],
    "wof:name":"Kupon-e Sorna",
    "wof:placetype":"locality"
},
  "geometry": {"coordinates":[51.29547,30.34034],"type":"Point"}
}