{
  "type": "Feature",
  "properties": {
    "gn:admin1_code":"41",
    "gn:asciiname":"Estakhrak",
    "gn:country_code":"IR",
    "gn:dem":2045,
    "gn:feature_class":"P",
    "gn:feature_code":"PPL",
    "gn:name":"Estakhrak",
    "gn:population":0,
    "gn:timezone":"Asia/Tehran",
    "iso:country":"IR",
    "name:fas_x_preferred":[
        "\u0627\u0633\u062a\u062e\u0631\u06a9"
    ],
    "wof:name":"Estakhrak",
    "wof:placetype":"locality"
},
  "geometry": {"coordinates":[59.41117,32.24403],"type":"Point"}
}