{
  "type": "Feature",
  "properties": {
    "gn:admin1_code":"33",
    "gn:asciiname":"Kargas",
    "gn:country_code":"IR",
    "gn:dem":1592,
    "gn:feature_class":"P",
    "gn:feature_code":"PPL",
    "gn:name":"Kargas",
    "gn:population":0,
    "gn:timezone":"Asia/Tehran",
    "iso:country":"IR",
    "name:ara_x_preferred":[
        "\u0643\u0631\u063a\u0633"
    ],
    "name:azb_x_preferred":[
        "\u06a9\u0631\u06af\u0633"
    ],
    "name:fas_x_preferred":[
        "\u06a9\u0631\u06af\u0633"
    ],
    "name:msa_x_preferred":[
        "Kargas"
    ],
    "name:und_x_variant":[
        "Kargasar",
        "Karkas",
        "Kargas"
    ],
    "wof:name":"Kargas",
    "wof:placetype":"locality"
},
  "geometry": {"coordinates":[47.39918,38.94446],"type":"Point"}
}