{
  "type": "Feature",
  "properties": {
    "gn:admin1_code":"11",
    "gn:asciiname":"Zarru Kan",
    "gn:country_code":"IR",
    "gn:dem":938,
    "gn:feature_class":"P",
    "gn:feature_code":"PPL",
    "gn:name":"Zarr\u016b K\u0101n",
    "gn:population":0,
    "gn:timezone":"Asia/Tehran",
    "iso:country":"IR",
    "name:fas_x_preferred":[
        "\u0632\u0631\u0651 \u0643\u0627\u0646"
    ],
    "name:fas_x_variant":[
        "\u0632\u064e\u0631\u064e\u0643\u0627\u0646",
        "\u0632\u064e\u0631\u0650\u0651\u0647 \u0643\u0627\u0646",
        "\u0643\u064e\u0631\u0648\u0643\u0627\u0646",
        "\u0632\u0631\u0648 \u06a9\u0627\u0646",
        "Zarr-e K\u0101n",
        "Zarr\u016b K\u0101n"
    ],
    "name:und_x_variant":[
        "Kar\u016bk\u0101n",
        "Zarreh K\u0101n",
        "Kurukun",
        "Zarak\u0101n"
    ],
    "wof:name":"Zarru Kan",
    "wof:placetype":"locality"
},
  "geometry": {"coordinates":[56.5272,27.8309],"type":"Point"}
}