{
  "type": "Feature",
  "properties": {
    "gn:admin1_code":"16",
    "gn:asciiname":"Qal`eh Gah-e Sharif",
    "gn:country_code":"IR",
    "gn:dem":2151,
    "gn:feature_class":"P",
    "gn:feature_code":"PPL",
    "gn:name":"Qal\u2018eh G\u0101h-e Shar\u012bf",
    "gn:population":0,
    "gn:timezone":"Asia/Tehran",
    "iso:country":"IR",
    "name:fas_x_preferred":[
        "\u0642\u0644\u0639\u0647 \u06af\u0627\u0647 \u0634\u0631\u064a\u0641"
    ],
    "name:fas_x_variant":[
        "Qal\u2018ehg\u0101h-e Shar\u012bf",
        "\u0642\u064e\u0644\u0639\u0650\u0647\u06af\u0627\u0647\u0650 \u0634\u064e\u0631\u064a\u0641",
        "Qal\u2018eh G\u0101h-e Shar\u012bf"
    ],
    "wof:name":"Qal`eh Gah-e Sharif",
    "wof:placetype":"locality"
},
  "geometry": {"coordinates":[46.80429,36.19282000000001],"type":"Point"}
}