{
  "type": "Feature",
  "properties": {
    "gn:admin1_code":"4.0",
    "gn:asciiname":"Yusefabad",
    "gn:country_code":"IR",
    "gn:dem":1810,
    "gn:feature_class":"P",
    "gn:feature_code":"PPL",
    "gn:name":"Y\u016bsef\u0101b\u0101d",
    "gn:population":0,
    "gn:timezone":"Asia/Tehran",
    "iso:country":"IR",
    "name:fas_x_preferred":[
        "\u06cc\u0648\u0633\u0641 \u0622\u0628\u0627\u062f"
    ],
    "name:fas_x_variant":[
        "Y\u016bsef\u0101b\u0101d"
    ],
    "wof:name":"Yusefabad",
    "wof:placetype":"locality"
},
  "geometry": {"coordinates":[60.9041,28.5343],"type":"Point"}
}