{
  "type": "Feature",
  "properties": {
    "gn:admin1_code":"35.0",
    "gn:asciiname":"Bar Sabur",
    "gn:country_code":"IR",
    "gn:dem":-4,
    "gn:feature_class":"P",
    "gn:feature_code":"PPL",
    "gn:name":"Bar Sab\u016br",
    "gn:population":0,
    "gn:timezone":"Asia/Tehran",
    "iso:country":"IR",
    "name:fas_x_preferred":[
        "Bar Sab\u016b"
    ],
    "name:fas_x_variant":[
        "\u0628\u0631 \u0633\u0628\u0648",
        "\u0628\u0631 \u0633\u0628\u0648\u0631",
        "\u0628\u0631 \u0633\u064a\u0628\u0648\u0631"
    ],
    "name:und_x_variant":[
        "Bar Sab\u016br",
        "Bar S\u012bb\u016br"
    ],
    "wof:name":"Bar Sabur",
    "wof:placetype":"locality"
},
  "geometry": {"coordinates":[50.89907,36.75711],"type":"Point"}
}