{
  "type": "Feature",
  "properties": {
    "gn:admin1_code":"36",
    "gn:asciiname":"Khalifehlu",
    "gn:country_code":"IR",
    "gn:dem":1826,
    "gn:feature_class":"P",
    "gn:feature_code":"PPL",
    "gn:name":"Khal\u012bfehl\u016b",
    "gn:population":0,
    "gn:timezone":"Asia/Tehran",
    "iso:country":"IR",
    "name:fas_x_preferred":[
        "\u062e\u0644\u064a\u0641\u0647 \u0644\u0648"
    ],
    "name:fas_x_variant":[
        "Khal\u012bfehl\u016b"
    ],
    "name:und_x_variant":[
        "Khalaf \u2018Al\u012b",
        "Khal\u2019falu"
    ],
    "wof:name":"Khalifehlu",
    "wof:placetype":"locality"
},
  "geometry": {"coordinates":[49.2012,36.291],"type":"Point"}
}