{
  "type": "Feature",
  "properties": {
    "gn:admin1_code":"15",
    "gn:asciiname":"Masiniyeh",
    "gn:country_code":"IR",
    "gn:dem":18,
    "gn:feature_class":"P",
    "gn:feature_code":"PPL",
    "gn:name":"Mas\u0304\u012bn\u012byeh",
    "gn:population":0,
    "gn:timezone":"Asia/Tehran",
    "iso:country":"IR",
    "name:ceb_x_preferred":[
        "Mas\u012bn\u012byeh-ye Sofl\u00e1"
    ],
    "name:fas_x_preferred":[
        "\u0645\u0633\u06cc\u0646\u06cc\u0647 \u0633\u0641\u0644\u06cc"
    ],
    "name:fas_x_variant":[
        "Moseyn\u012byeh",
        "Mas\u012bn\u012byeh-ye Sofl\u00e1",
        "Moseyn\u012byeh-ye Sofl\u00e1",
        "\u0645\u062b\u06cc\u0646\u06cc\u0647",
        "\u0645\u062b\u06cc\u0646\u06cc\u0647 \u0633\u0641\u0644\u06cc"
    ],
    "name:pol_x_preferred":[
        "Mosejnije-je Sofla"
    ],
    "name:swe_x_preferred":[
        "Mas\u012bn\u012byeh-ye Sofl\u00e1"
    ],
    "name:und_x_variant":[
        "Mas\u012bn\u012byeh",
        "Mohs\u0304en\u012byeh",
        "Mas\u0304\u012bn\u012byeh",
        "Mas\u0304\u012bn\u012byeh-ye Sofl\u00e1"
    ],
    "wof:name":"Masiniyeh",
    "wof:placetype":"locality"
},
  "geometry": {"coordinates":[49.41188,30.75232],"type":"Point"}
}