{
  "type": "Feature",
  "properties": {
    "gn:admin1_code":"35.0",
    "gn:asciiname":"Tabarsu",
    "gn:country_code":"IR",
    "gn:dem":1141,
    "gn:feature_class":"P",
    "gn:feature_code":"PPL",
    "gn:name":"\u0162abars\u016b",
    "gn:population":0,
    "gn:timezone":"Asia/Tehran",
    "iso:country":"IR",
    "name:fas_x_preferred":[
        "\u0162abars\u016b"
    ],
    "name:fas_x_variant":[
        "\u0637\u0628\u0631\u0633\u0648",
        "\u062a\u0628\u0631\u0633\u0648"
    ],
    "name:und_x_variant":[
        "\u0637\u0628\u0631\u0633\u0648",
        "Tabars\u016b"
    ],
    "wof:name":"Tabarsu",
    "wof:placetype":"locality"
},
  "geometry": {"coordinates":[51.20942,36.49699],"type":"Point"}
}