{
  "type": "Feature",
  "properties": {
    "gn:admin1_code":"8",
    "gn:asciiname":"Chini Jan",
    "gn:country_code":"IR",
    "gn:dem":-3,
    "gn:feature_class":"P",
    "gn:feature_code":"PPL",
    "gn:name":"Ch\u012bn\u012b J\u0101n",
    "gn:population":0,
    "gn:timezone":"Asia/Tehran",
    "iso:country":"IR",
    "name:fas_x_preferred":[
        "Ch\u012bn\u012b J\u0101n"
    ],
    "name:fas_x_variant":[
        "\u0686\u06cc\u0646\u06cc \u062c\u0627\u0646"
    ],
    "name:msa_x_preferred":[
        "Chini Jan"
    ],
    "name:ukr_x_preferred":[
        "\u0427\u0456\u043d\u0456-\u0414\u0436\u0430\u043d"
    ],
    "name:und_x_variant":[
        "Ch\u012bnj\u0101n",
        "\u0686\u06cc\u0646\u06cc \u062c\u0627\u0646"
    ],
    "wof:name":"Chini Jan",
    "wof:placetype":"locality"
},
  "geometry": {"coordinates":[50.25635,37.14982],"type":"Point"}
}