{
  "type": "Feature",
  "properties": {
    "gn:admin1_code":"4",
    "gn:asciiname":"Jamal Pa'in",
    "gn:country_code":"IR",
    "gn:dem":815,
    "gn:feature_class":"P",
    "gn:feature_code":"PPL",
    "gn:name":"Jam\u0101l P\u0101\u2019\u012bn",
    "gn:population":0,
    "gn:timezone":"Asia/Tehran",
    "iso:country":"IR",
    "name:fas_x_preferred":[
        "Jam\u0101l P\u0101\u2019\u012bn"
    ],
    "wof:name":"Jamal Pa'in",
    "wof:placetype":"locality"
},
  "geometry": {"coordinates":[59.4525,27.90361],"type":"Point"}
}