{
  "type": "Feature",
  "properties": {
    "gn:admin1_code":"37.0",
    "gn:asciiname":"Karbala'i Jamal",
    "gn:country_code":"IR",
    "gn:dem":471,
    "gn:feature_class":"P",
    "gn:feature_code":"PPL",
    "gn:name":"Karbal\u0101\u2019\u012b Jam\u0101l",
    "gn:population":0,
    "gn:timezone":"Asia/Tehran",
    "iso:country":"IR",
    "name:fas_x_preferred":[
        "\u06a9\u0631\u0628\u0644\u0627\u06cc\u06cc \u062c\u0645\u0627\u0644"
    ],
    "name:und_x_variant":[
        "Karbal\u0101\u2019\u012b Jam\u0101l"
    ],
    "wof:name":"Karbala'i Jamal",
    "wof:placetype":"locality"
},
  "geometry": {"coordinates":[55.47558000000001,37.14171],"type":"Point"}
}