{
  "type": "Feature",
  "properties": {
    "gn:admin1_code":"29",
    "gn:asciiname":"Qa'emabad",
    "gn:country_code":"IR",
    "gn:dem":786,
    "gn:feature_class":"P",
    "gn:feature_code":"PPL",
    "gn:name":"Q\u0101\u2019em\u0101b\u0101d",
    "gn:population":0,
    "gn:timezone":"Asia/Tehran",
    "iso:country":"IR",
    "name:fas_x_preferred":[
        "\u0642\u0627\u06cc\u0645 \u0622\u0628\u0627\u062f"
    ],
    "name:fas_x_variant":[
        "Q\u0101\u2019em\u0101b\u0101d"
    ],
    "wof:name":"Qa'emabad",
    "wof:placetype":"locality"
},
  "geometry": {"coordinates":[58.6595,28.9448],"type":"Point"}
}