{
  "type": "Feature",
  "properties": {
    "gn:admin1_code":"1.0",
    "gn:asciiname":"Khezerlu-ye `Olya",
    "gn:country_code":"IR",
    "gn:dem":1551,
    "gn:feature_class":"P",
    "gn:feature_code":"PPL",
    "gn:name":"Khe\u1e95erl\u016b-ye \u2018Oly\u0101",
    "gn:population":0,
    "gn:timezone":"Asia/Tehran",
    "iso:country":"IR",
    "name:fas_x_preferred":[
        "\u062e\u0636\u0631\u0644\u0648 \u0639\u0644\u06cc\u0627"
    ],
    "name:fas_x_variant":[
        "Khe\u1e95erl\u016b-ye \u2018Oly\u0101"
    ],
    "wof:name":"Khezerlu-ye `Olya",
    "wof:placetype":"locality"
},
  "geometry": {"coordinates":[44.8599,38.9842],"type":"Point"}
}