{
  "type": "Feature",
  "properties": {
    "gn:admin1_code":"8",
    "gn:asciiname":"Rineh",
    "gn:country_code":"IR",
    "gn:dem":916,
    "gn:feature_class":"P",
    "gn:feature_code":"PPL",
    "gn:name":"R\u012bneh",
    "gn:population":0,
    "gn:timezone":"Asia/Tehran",
    "iso:country":"IR",
    "name:ara_x_preferred":[
        "\u0631\u064a\u0646\u0647"
    ],
    "name:aze_x_preferred":[
        "Rin\u0259"
    ],
    "name:ceb_x_preferred":[
        "R\u012bneh"
    ],
    "name:fas_x_preferred":[
        "\u0100q Masjed"
    ],
    "name:fas_x_variant":[
        "\u0631\u06cc\u0646\u0647",
        "\u0622\u0642 \u0645\u0633\u062c\u062f"
    ],
    "name:glk_x_preferred":[
        "\u0631\u06cc\u0646\u0647"
    ],
    "name:ita_x_preferred":[
        "Rineh"
    ],
    "name:mlg_x_preferred":[
        "Rineh"
    ],
    "name:mzn_x_preferred":[
        "\u0631\u06cc\u0646\u0647"
    ],
    "name:swe_x_preferred":[
        "R\u012bneh"
    ],
    "name:tur_x_preferred":[
        "Rine"
    ],
    "wof:name":"Rineh",
    "wof:placetype":"locality"
},
  "geometry": {"coordinates":[48.79185,37.50204],"type":"Point"}
}