{
  "type": "Feature",
  "properties": {
    "gn:admin1_code":"44",
    "gn:asciiname":"Fashandak",
    "gn:country_code":"IR",
    "gn:dem":1968,
    "gn:feature_class":"P",
    "gn:feature_code":"PPL",
    "gn:name":"Fashandak",
    "gn:population":0,
    "gn:timezone":"Asia/Tehran",
    "iso:country":"IR",
    "name:fas_x_preferred":[
        "\u0641\u0634\u0646\u062f\u06a9"
    ],
    "name:und_x_variant":[
        "\u0641\u0634\u0646\u062f\u06a9",
        "Fashandak"
    ],
    "wof:name":"Fashandak",
    "wof:placetype":"locality"
},
  "geometry": {"coordinates":[50.71203,36.15231],"type":"Point"}
}