{
  "type": "Feature",
  "properties": {
    "gn:admin1_code":"23",
    "gn:asciiname":"Nabiabad",
    "gn:country_code":"IR",
    "gn:dem":1825,
    "gn:feature_class":"P",
    "gn:feature_code":"PPL",
    "gn:name":"Nab\u012b\u0101b\u0101d",
    "gn:population":0,
    "gn:timezone":"Asia/Tehran",
    "iso:country":"IR",
    "name:ara_x_preferred":[
        "\u0646\u0628\u064a \u0623\u0628\u0627\u062f"
    ],
    "name:ceb_x_preferred":[
        "Nab\u012b\u0101b\u0101d"
    ],
    "name:fas_x_preferred":[
        "Nab\u012b\u0101b\u0101d"
    ],
    "name:fas_x_variant":[
        "\u0646\u0628\u06cc \u0622\u0628\u0627\u062f",
        "\u0646\u0628\u06cc\u200c\u0622\u0628\u0627\u062f"
    ],
    "name:swe_x_preferred":[
        "Nab\u012b\u0101b\u0101d"
    ],
    "name:und_x_variant":[
        "Naghi Abad",
        "\u0646\u0628\u06cc \u0622\u0628\u0627\u062f"
    ],
    "wof:name":"Nabiabad",
    "wof:placetype":"locality"
},
  "geometry": {"coordinates":[48.5844,34.02582],"type":"Point"}
}