{
  "type": "Feature",
  "properties": {
    "gn:admin1_code":"3",
    "gn:asciiname":"Kartogol",
    "gn:country_code":"IR",
    "gn:dem":1851,
    "gn:feature_class":"P",
    "gn:feature_code":"PPL",
    "gn:name":"Kartogol",
    "gn:population":0,
    "gn:timezone":"Asia/Tehran",
    "iso:country":"IR",
    "name:ceb_x_preferred":[
        "Kartogol"
    ],
    "name:fas_x_preferred":[
        "Kortogol-e P\u0101\u2019\u012bn"
    ],
    "name:fas_x_variant":[
        "\u0643\u064f\u0631\u062a\u064f\u06af\u064f\u0644\u0650 \u067e\u0627\u0626\u064a\u0646",
        "\u06a9\u0631\u062a\u06af\u0644"
    ],
    "name:msa_x_preferred":[
        "Kartogol"
    ],
    "name:swe_x_preferred":[
        "Kartogol"
    ],
    "wof:name":"Kartogol",
    "wof:placetype":"locality"
},
  "geometry": {"coordinates":[51.04008,31.54031],"type":"Point"}
}