{
  "type": "Feature",
  "properties": {
    "gn:admin1_code":"42",
    "gn:asciiname":"Gol Sheykh",
    "gn:country_code":"IR",
    "gn:dem":1485,
    "gn:feature_class":"P",
    "gn:feature_code":"PPL",
    "gn:name":"Gol Sheykh",
    "gn:population":0,
    "gn:timezone":"Asia/Tehran",
    "iso:country":"IR",
    "name:ara_x_preferred":[
        "\u063a\u0644 \u0634\u064a\u062e"
    ],
    "name:ceb_x_preferred":[
        "Gol Sheykh"
    ],
    "name:fas_x_preferred":[
        "\u06af\u0644 \u0634\u06cc\u062e"
    ],
    "name:swe_x_preferred":[
        "Gol Sheykh"
    ],
    "wof:name":"Gol Sheykh",
    "wof:placetype":"locality"
},
  "geometry": {"coordinates":[59.92276,35.57279000000001],"type":"Point"}
}