{
  "type": "Feature",
  "properties": {
    "gn:admin1_code":"22",
    "gn:asciiname":"Bovirat",
    "gn:country_code":"IR",
    "gn:dem":10,
    "gn:feature_class":"P",
    "gn:feature_code":"PPL",
    "gn:name":"Bov\u012br\u0101t",
    "gn:population":0,
    "gn:timezone":"Asia/Tehran",
    "iso:country":"IR",
    "name:ara_x_preferred":[
        "\u0628\u0648\u064a\u0631\u0627\u062a"
    ],
    "name:fas_x_preferred":[
        "\u0628\u0648\u064a\u0631\u0627\u062a"
    ],
    "name:fas_x_variant":[
        "Boveyr\u0101t",
        "Bov\u012br\u0101t",
        "\u0628\u0648\u06cc\u0631\u0627\u062a"
    ],
    "name:msa_x_preferred":[
        "Bovirat"
    ],
    "wof:name":"Bovirat",
    "wof:placetype":"locality"
},
  "geometry": {"coordinates":[50.2254,29.9775],"type":"Point"}
}