{
  "type": "Feature",
  "properties": {
    "gn:admin1_code":"15.0",
    "gn:asciiname":"`Avafi",
    "gn:country_code":"IR",
    "gn:dem":47,
    "gn:feature_class":"P",
    "gn:feature_code":"PPL",
    "gn:name":"\u2018Av\u0101f\u012b",
    "gn:population":0,
    "gn:timezone":"Asia/Tehran",
    "iso:country":"IR",
    "name:fas_x_preferred":[
        "\u0639\u0648\u0627\u0641\u06cc"
    ],
    "name:fas_x_variant":[
        "\u2018Av\u0101f\u012b"
    ],
    "name:und_x_variant":[
        "\u2018Av\u012bf\u012b",
        "\u2018Aveyf\u012b"
    ],
    "wof:name":"`Avafi",
    "wof:placetype":"locality"
},
  "geometry": {"coordinates":[49.20882,31.21554],"type":"Point"}
}