{
  "type": "Feature",
  "properties": {
    "gn:admin1_code":"23",
    "gn:asciiname":"Karkhaneh-ye Hakimi",
    "gn:country_code":"IR",
    "gn:dem":1493,
    "gn:feature_class":"P",
    "gn:feature_code":"PPL",
    "gn:name":"K\u0101rkh\u0101neh-ye \u1e28ak\u012bm\u012b",
    "gn:population":0,
    "gn:timezone":"Asia/Tehran",
    "iso:country":"IR",
    "name:ara_x_preferred":[
        "\u0643\u0627\u0631\u062e\u0627\u0646\u0629 \u062d\u0643\u064a\u0645\u064a"
    ],
    "name:ceb_x_preferred":[
        "K\u0101rkh\u0101neh-ye \u1e28ak\u012bm\u012b"
    ],
    "name:fas_x_preferred":[
        "\u0643\u0627\u0631\u062e\u0627\u0646\u0647 \u0641\u0644\u0627\u0646\u062f\u0634\u062a"
    ],
    "name:fas_x_variant":[
        "K\u0101rkh\u0101neh",
        "K\u0101rkh\u0101neh-ye F\u016bn Dasht",
        "K\u0101rkh\u0101neh-ye \u1e28ak\u012bm",
        "K\u0101rkuneh",
        "K\u0101rkh\u0101neh Fol\u0101ndasht",
        "\u0643\u0627\u0631\u062e\u0627\u0646\u0647 \u062d\u0643\u06cc\u0645\u06cc",
        "\u0641\u0644\u0627\u0646\u062f\u0634\u062a",
        "\u06a9\u0627\u0631\u062e\u0627\u0646\u0647 \u062d\u06a9\u06cc\u0645\u06cc"
    ],
    "name:swe_x_preferred":[
        "K\u0101rkh\u0101neh-ye \u1e28ak\u012bm\u012b"
    ],
    "name:und_x_variant":[
        "Karkh\u0101neh S\u0101l\u0101r",
        "K\u0101rkh\u0101neh-ye Fol\u0101n Dasht",
        "K\u0101rkh\u0101neh-ye \u1e28ak\u012bm\u012b",
        "Fol\u0101ndasht"
    ],
    "wof:name":"Karkhaneh-ye Hakimi",
    "wof:placetype":"locality"
},
  "geometry": {"coordinates":[48.74677,33.8252],"type":"Point"}
}