{
  "type": "Feature",
  "properties": {
    "gn:admin1_code":"25",
    "gn:asciiname":"Deh Sarab",
    "gn:country_code":"IR",
    "gn:dem":965,
    "gn:feature_class":"P",
    "gn:feature_code":"PPL",
    "gn:name":"Deh Sar\u0101b",
    "gn:population":0,
    "gn:timezone":"Asia/Tehran",
    "iso:country":"IR",
    "name:fas_x_preferred":[
        "\u062f\u0647 \u0633\u0631\u0627\u0628"
    ],
    "name:fas_x_variant":[
        "Deh Sar\u0101b"
    ],
    "wof:name":"Deh Sarab",
    "wof:placetype":"locality"
},
  "geometry": {"coordinates":[52.4304,35.2811],"type":"Point"}
}