{
  "type": "Feature",
  "properties": {
    "gn:admin1_code":"1.0",
    "gn:asciiname":"Kani Ashkut",
    "gn:country_code":"IR",
    "gn:dem":1448,
    "gn:feature_class":"P",
    "gn:feature_code":"PPL",
    "gn:name":"K\u0101n\u012b Ashk\u016bt",
    "gn:population":0,
    "gn:timezone":"Asia/Tehran",
    "iso:country":"IR",
    "name:fas_x_preferred":[
        "\u06a9\u0627\u0646\u06cc \u0627\u0634\u06a9\u0648\u062a"
    ],
    "name:fas_x_variant":[
        "K\u0101n\u012b Ashk\u016bt"
    ],
    "wof:name":"Kani Ashkut",
    "wof:placetype":"locality"
},
  "geometry": {"coordinates":[45.3196,36.7499],"type":"Point"}
}