{
  "type": "Feature",
  "properties": {
    "gn:admin1_code":"28",
    "gn:asciiname":"Hajjilu",
    "gn:country_code":"IR",
    "gn:dem":2280,
    "gn:feature_class":"P",
    "gn:feature_code":"PPL",
    "gn:name":"\u1e28\u0101jj\u012bl\u016b",
    "gn:population":0,
    "gn:timezone":"Asia/Tehran",
    "iso:country":"IR",
    "name:fas_x_preferred":[
        "\u1e28\u0101jj\u012bl\u016b"
    ],
    "name:fas_x_variant":[
        "\u062d\u0627\u062c\u06cc\u0644\u0648"
    ],
    "name:und_x_variant":[
        "\u1e28aj\u012bl\u016b",
        "\u062d\u0627\u062c\u06cc\u0644\u0648"
    ],
    "wof:name":"Hajjilu",
    "wof:placetype":"locality"
},
  "geometry": {"coordinates":[50.1266,33.19541],"type":"Point"}
}