{
  "type": "Feature",
  "properties": {
    "gn:admin1_code":"22",
    "gn:asciiname":"Masileh-ye Kuseh'i",
    "gn:country_code":"IR",
    "gn:dem":11,
    "gn:feature_class":"P",
    "gn:feature_code":"PPL",
    "gn:name":"Mas\u012bleh-ye K\u016bseh\u2019\u012b",
    "gn:population":0,
    "gn:timezone":"Asia/Tehran",
    "iso:country":"IR",
    "name:fas_x_preferred":[
        "\u0645\u064e\u0633\u064a\u0644\u0650\u06c0 \u0643\u0648\u0633\u0650\u0647\u0626\u06cc"
    ],
    "name:fas_x_variant":[
        "Mas\u012bleh-ye K\u016bseh\u2019\u012b"
    ],
    "wof:name":"Masileh-ye Kuseh'i",
    "wof:placetype":"locality"
},
  "geometry": {"coordinates":[51.46667,28.33333],"type":"Point"}
}