{
  "type": "Feature",
  "properties": {
    "gn:admin1_code":"39.0",
    "gn:asciiname":"`Aliabad",
    "gn:country_code":"IR",
    "gn:dem":813,
    "gn:feature_class":"P",
    "gn:feature_code":"PPL",
    "gn:name":"\u2018Al\u012b\u0101b\u0101d",
    "gn:population":0,
    "gn:timezone":"Asia/Tehran",
    "iso:country":"IR",
    "name:fas_x_preferred":[
        "\u0639\u0644\u06cc \u0622\u0628\u0627\u062f"
    ],
    "name:fas_x_variant":[
        "\u0639\u0644\u06cc \u0622\u0628\u0627\u062f \u06a9\u0648\u0631 \u06af\u0644",
        "\u2018Al\u012b\u0101b\u0101d-e K\u016br Gol",
        "Al\u012b \u0100b\u0101d-e-K\u016br Gol",
        "\u2018Al\u012b\u0101b\u0101d-e K\u016br Gal",
        "\u2018Al\u012b\u0101b\u0101d va K\u016br Gal",
        "\u2018Al\u012b\u0101b\u0101d",
        "\u0639\u064e\u0644\u06cc \u0622\u0628\u0627\u062f \u0648\u064e \u0643\u0648\u0631 \u06af\u064e\u0644",
        "\u2018Al\u012b\u0101b\u0101d-e K\u016br Gel"
    ],
    "wof:name":"`Aliabad",
    "wof:placetype":"locality"
},
  "geometry": {"coordinates":[51.23428,34.89574],"type":"Point"}
}