{
  "type": "Feature",
  "properties": {
    "gn:admin1_code":"8.0",
    "gn:asciiname":"Laleh Jar",
    "gn:country_code":"IR",
    "gn:dem":1395,
    "gn:feature_class":"P",
    "gn:feature_code":"PPL",
    "gn:name":"Laleh J\u0101r",
    "gn:population":0,
    "gn:timezone":"Asia/Tehran",
    "iso:country":"IR",
    "name:fas_x_preferred":[
        "Laleh J\u0101r"
    ],
    "name:fas_x_variant":[
        "\u0644\u0644\u0647 \u062c\u0627\u0631"
    ],
    "name:und_x_variant":[
        "\u0644\u0644\u0647 \u062c\u0627\u0631"
    ],
    "wof:name":"Laleh Jar",
    "wof:placetype":"locality"
},
  "geometry": {"coordinates":[50.06791,36.86198],"type":"Point"}
}