{
  "type": "Feature",
  "properties": {
    "gn:admin1_code":"15",
    "gn:asciiname":"Chahar Qash",
    "gn:country_code":"IR",
    "gn:dem":886,
    "gn:feature_class":"P",
    "gn:feature_code":"PPL",
    "gn:name":"Chah\u0101r Q\u0101sh",
    "gn:population":0,
    "gn:timezone":"Asia/Tehran",
    "iso:country":"IR",
    "name:fas_x_preferred":[
        "Chah\u0101r Q\u0101sh-e P\u0101\u2019\u012bn"
    ],
    "name:fas_x_variant":[
        "Chah\u0101r Q\u0101sh",
        "\u0686\u0647\u0627\u0631 \u0642\u0627\u0634"
    ],
    "wof:name":"Chahar Qash",
    "wof:placetype":"locality"
},
  "geometry": {"coordinates":[49.56504,31.91041],"type":"Point"}
}