{
  "type": "Feature",
  "properties": {
    "gn:admin1_code":"41",
    "gn:asciiname":"Morghab",
    "gn:country_code":"IR",
    "gn:dem":1452,
    "gn:feature_class":"P",
    "gn:feature_code":"PPL",
    "gn:name":"Morgh\u0101b",
    "gn:population":0,
    "gn:timezone":"Asia/Tehran",
    "iso:country":"IR",
    "name:fas_x_preferred":[
        "Morgh\u0101b"
    ],
    "name:fas_x_variant":[
        "Kal\u0101teh-ye \u0100q\u0101 B\u0101b\u0101",
        "\u0645\u0631\u063a\u0627\u0628",
        "Kal\u0101teh \u0100gha B\u0101ba",
        "\u06a9\u0644\u0627\u062a \u0627\u0642 \u0622\u0628\u0627\u062f"
    ],
    "name:und_x_variant":[
        "Kal\u0101t-e Aq\u0101b\u0101d"
    ],
    "wof:name":"Morghab",
    "wof:placetype":"locality"
},
  "geometry": {"coordinates":[59.05628000000001,32.5615],"type":"Point"}
}