{
  "type": "Feature",
  "properties": {
    "gn:admin1_code":"28",
    "gn:asciiname":"`Arabshah",
    "gn:country_code":"IR",
    "gn:dem":1976,
    "gn:feature_class":"P",
    "gn:feature_code":"PPL",
    "gn:name":"\u2018Arabsh\u0101h",
    "gn:population":0,
    "gn:timezone":"Asia/Tehran",
    "iso:country":"IR",
    "name:fas_x_preferred":[
        "\u2018Arabsh\u0101h"
    ],
    "name:fas_x_variant":[
        "\u0639\u0631\u0628\u0634\u0627\u0647",
        "\u0639\u0631\u0628\u200c\u0634\u0627\u0647"
    ],
    "name:und_x_variant":[
        "\u2018Arabsh\u0101"
    ],
    "wof:name":"`Arabshah",
    "wof:placetype":"locality"
},
  "geometry": {"coordinates":[51.50514,31.07346],"type":"Point"}
}