{
  "type": "Feature",
  "properties": {
    "gn:admin1_code":"28.0",
    "gn:asciiname":"Mahalleh-ye Dastgerd Qaddadeh",
    "gn:country_code":"IR",
    "gn:dem":1588,
    "gn:feature_class":"P",
    "gn:feature_code":"PPL",
    "gn:name":"Ma\u1e29alleh-ye Dastgerd Qadd\u0101deh",
    "gn:population":0,
    "gn:timezone":"Asia/Tehran",
    "iso:country":"IR",
    "name:fas_x_preferred":[
        "Dastgerd-e Qadd\u0101deh"
    ],
    "name:fas_x_variant":[
        "\u062f\u0633\u062a\u06af\u0631\u062f \u0642\u062f\u0627\u062f",
        "Dastgerd Qadd\u0101d",
        "\u0645\u062d\u0644\u0647 \u062f\u0633\u062a\u06af\u0631\u062f \u0642\u062f\u0627\u062f\u0647"
    ],
    "name:und_x_variant":[
        "Dastgerd",
        "Dastjerd-e Qadd\u0101deh",
        "Dastkird",
        "Dastgerd Qadd\u0101d",
        "\u062f\u0633\u062a\u06af\u0631\u062f \u0642\u062f\u0627\u062f",
        "Ma\u1e29alleh-ye Dastgerd Qadd\u0101deh"
    ],
    "wof:name":"Mahalleh-ye Dastgerd Qaddadeh",
    "wof:placetype":"locality"
},
  "geometry": {"coordinates":[51.55951,32.70104],"type":"Point"}
}