{
  "type": "Feature",
  "properties": {
    "gn:admin1_code":"15",
    "gn:asciiname":"Rakhoda",
    "gn:country_code":"IR",
    "gn:dem":1808,
    "gn:feature_class":"P",
    "gn:feature_code":"PPL",
    "gn:name":"R\u0101khod\u0101",
    "gn:population":0,
    "gn:timezone":"Asia/Tehran",
    "iso:country":"IR",
    "name:fas_x_preferred":[
        "R\u0101khod\u0101"
    ],
    "wof:name":"Rakhoda",
    "wof:placetype":"locality"
},
  "geometry": {"coordinates":[50.42222,31.63194],"type":"Point"}
}