{
  "type": "Feature",
  "properties": {
    "gn:admin1_code":"42.0",
    "gn:asciiname":"Chah-e `Ezzat",
    "gn:country_code":"IR",
    "gn:dem":851,
    "gn:feature_class":"P",
    "gn:feature_code":"PPL",
    "gn:name":"Ch\u0101h-e \u2018Ezzat",
    "gn:population":0,
    "gn:timezone":"Asia/Tehran",
    "iso:country":"IR",
    "name:fas_x_preferred":[
        "\u0686\u0627\u0647 \u0639\u0632\u062a"
    ],
    "name:fas_x_variant":[
        "Ch\u0101h-e \u2018Ezzat"
    ],
    "wof:name":"Chah-e `Ezzat",
    "wof:placetype":"locality"
},
  "geometry": {"coordinates":[60.77656,35.04198],"type":"Point"}
}