{
  "type": "Feature",
  "properties": {
    "gn:admin1_code":"1",
    "gn:asciiname":"Sotunrash",
    "gn:country_code":"IR",
    "gn:dem":2436,
    "gn:feature_class":"P",
    "gn:feature_code":"PPL",
    "gn:name":"Sot\u016bnrash",
    "gn:population":0,
    "gn:timezone":"Asia/Tehran",
    "iso:country":"IR",
    "name:aze_x_preferred":[
        "\u00dcstunr\u0259\u015f"
    ],
    "name:ceb_x_preferred":[
        "Sot\u016bnrash"
    ],
    "name:fas_x_preferred":[
        "Ost\u016bnrash"
    ],
    "name:fas_x_variant":[
        "Sot\u016bnrash",
        "\u0633\u062a\u0648\u0646\u0631\u0634",
        "\u0627\u0633\u062a\u0648\u0646\u200c\u0631\u0634"
    ],
    "name:msa_x_preferred":[
        "Ostunrash"
    ],
    "name:swe_x_preferred":[
        "Sot\u016bnrash"
    ],
    "name:und_x_variant":[
        "\u0633\u062a\u0648\u0646\u0631\u0634"
    ],
    "wof:name":"Sotunrash",
    "wof:placetype":"locality"
},
  "geometry": {"coordinates":[44.4145,38.0104],"type":"Point"}
}