{
  "type": "Feature",
  "properties": {
    "gn:admin1_code":"28",
    "gn:asciiname":"Dowlatabad",
    "gn:country_code":"IR",
    "gn:dem":2253,
    "gn:feature_class":"P",
    "gn:feature_code":"PPL",
    "gn:name":"Dowlat\u0101b\u0101d",
    "gn:population":0,
    "gn:timezone":"Asia/Tehran",
    "iso:country":"IR",
    "name:fas_x_preferred":[
        "Dowlat\u0101b\u0101d"
    ],
    "name:fas_x_variant":[
        "\u062f\u0648\u0644\u062a \u0622\u0628\u0627\u062f",
        "\u062f\u0648\u0644\u062a\u200c\u0622\u0628\u0627\u062f"
    ],
    "name:und_x_variant":[
        "Daulat\u0101b\u0101d",
        "Dulat\u0101b\u0101d"
    ],
    "wof:name":"Dowlatabad",
    "wof:placetype":"locality"
},
  "geometry": {"coordinates":[50.75661,32.91425],"type":"Point"}
}