{
  "type": "Feature",
  "properties": {
    "gn:admin1_code":"32",
    "gn:asciiname":"Mehdi Posti",
    "gn:country_code":"IR",
    "gn:dem":1323,
    "gn:feature_class":"P",
    "gn:feature_code":"PPL",
    "gn:name":"Mehd\u012b Post\u012b",
    "gn:population":0,
    "gn:timezone":"Asia/Tehran",
    "iso:country":"IR",
    "name:azb_x_preferred":[
        "\u0645\u0647\u062f\u06cc \u067e\u0633\u062a\u06cc(\u0646\u0645\u06cc\u0646)"
    ],
    "name:ceb_x_preferred":[
        "Mehd\u012b Post\u012b"
    ],
    "name:fas_x_preferred":[
        "\u0645\u0647\u062f\u06cc \u067e\u0633\u062a\u06cc"
    ],
    "name:fas_x_variant":[
        "Mehd\u012b Post\u012b"
    ],
    "name:msa_x_preferred":[
        "Mehdi Posti"
    ],
    "name:swe_x_preferred":[
        "Mehd\u012b Post\u012b"
    ],
    "wof:name":"Mehdi Posti",
    "wof:placetype":"locality"
},
  "geometry": {"coordinates":[48.5655,38.3201],"type":"Point"}
}