{
  "type": "Feature",
  "properties": {
    "gn:admin1_code":"40.0",
    "gn:asciiname":"Eslamabad",
    "gn:country_code":"IR",
    "gn:dem":1765,
    "gn:feature_class":"P",
    "gn:feature_code":"PPL",
    "gn:name":"Esl\u0101m\u0101b\u0101d",
    "gn:population":0,
    "gn:timezone":"Asia/Tehran",
    "iso:country":"IR",
    "name:ara_x_preferred":[
        "\u0625\u0633\u0644\u0627\u0645 \u0622\u0628\u0627\u062f"
    ],
    "name:fas_x_preferred":[
        "Esl\u0101m\u0101b\u0101d"
    ],
    "name:fas_x_variant":[
        "\u0627\u0633\u0644\u0627\u0645 \u0622\u0628\u0627\u062f",
        "\u0627\u0633\u0644\u0627\u0645 \u0622\u0628\u0627\u062f \u0686\u0627\u0647 \u0645\u0646\u062c",
        "\u0627\u0633\u0644\u0627\u0645\u200c\u0622\u0628\u0627\u062f"
    ],
    "name:und_x_variant":[
        "Esl\u0101m\u0101b\u0101d Ch\u0101h Monj"
    ],
    "wof:name":"Eslamabad",
    "wof:placetype":"locality"
},
  "geometry": {"coordinates":[54.26875,29.71823],"type":"Point"}
}