{
  "type": "Feature",
  "properties": {
    "gn:admin1_code":"22.0",
    "gn:asciiname":"Gorgi",
    "gn:country_code":"IR",
    "gn:dem":19,
    "gn:feature_class":"P",
    "gn:feature_code":"PPL",
    "gn:name":"Gorg\u012b",
    "gn:population":0,
    "gn:timezone":"Asia/Tehran",
    "iso:country":"IR",
    "name:fas_x_preferred":[
        "\u06af\u0631\u06af\u06cc"
    ],
    "name:fas_x_variant":[
        "Gorg\u012b"
    ],
    "wof:name":"Gorgi",
    "wof:placetype":"locality"
},
  "geometry": {"coordinates":[50.5882,29.64],"type":"Point"}
}