{
  "type": "Feature",
  "properties": {
    "gn:admin1_code":"7",
    "gn:asciiname":"Sumattu",
    "gn:country_code":"IR",
    "gn:dem":392,
    "gn:feature_class":"P",
    "gn:feature_code":"PPL",
    "gn:name":"S\u016bmatt\u016b",
    "gn:population":0,
    "gn:timezone":"Asia/Tehran",
    "iso:country":"IR",
    "name:fas_x_preferred":[
        "\u0633\u0648\u0645\u062a\u0651\u0648"
    ],
    "name:fas_x_variant":[
        "S\u016bmatt\u016b"
    ],
    "wof:name":"Sumattu",
    "wof:placetype":"locality"
},
  "geometry": {"coordinates":[52.7338,27.8115],"type":"Point"}
}